{
"type": "FeatureCollection",
"crs": { "type": "name", "properties": { "name": "urn:ogc:def:crs:OGC:1.3:CRS84" } },
"features": [
{ "type": "Feature", "properties": { "Name": "Fire Detection Centroid ", "Description": "<b>Latitude: <\/b> 19.40248<br\/>  <b>Longitude: <\/b> -155.27428<br\/>  <b>Detection Time: <\/b> 2023-01-17 23:50 UTC<br\/>  <b>Sensor: <\/b> NOAA-20 VIIRS<br\/> <b>Confidence: <\/b> Nominal<br\/>  <b>Day\/Night: <\/b> Day<br\/> <b>Scan: <\/b> 0.51 km<br\/> <b>Track: <\/b> 0.41 km<br\/> <b>FRP: <\/b> 76.05 MW<br\/> <b>Brightness: <\/b> 346.14 K" }, "geometry": { "type": "Point", "coordinates": [ -155.27428, 19.40248, 0.0 ] } },
{ "type": "Feature", "properties": { "Name": "Fire Detection Centroid ", "Description": "<b>Latitude: <\/b> 19.41067<br\/>  <b>Longitude: <\/b> -155.27045<br\/>  <b>Detection Time: <\/b> 2023-01-17 23:50 UTC<br\/>  <b>Sensor: <\/b> NOAA-20 VIIRS<br\/> <b>Confidence: <\/b> Nominal<br\/>  <b>Day\/Night: <\/b> Day<br\/> <b>Scan: <\/b> 0.51 km<br\/> <b>Track: <\/b> 0.41 km<br\/> <b>FRP: <\/b> 11.52 MW<br\/> <b>Brightness: <\/b> 352.45 K" }, "geometry": { "type": "Point", "coordinates": [ -155.27045, 19.41067, 0.0 ] } },
{ "type": "Feature", "properties": { "Name": "Fire Detection Centroid ", "Description": "<b>Latitude: <\/b> 19.40752<br\/>  <b>Longitude: <\/b> -155.26509<br\/>  <b>Detection Time: <\/b> 2023-01-17 23:50 UTC<br\/>  <b>Sensor: <\/b> NOAA-20 VIIRS<br\/> <b>Confidence: <\/b> Nominal<br\/>  <b>Day\/Night: <\/b> Day<br\/> <b>Scan: <\/b> 0.51 km<br\/> <b>Track: <\/b> 0.41 km<br\/> <b>FRP: <\/b> 5.14 MW<br\/> <b>Brightness: <\/b> 332.23 K" }, "geometry": { "type": "Point", "coordinates": [ -155.26509, 19.40752, 0.0 ] } },
{ "type": "Feature", "properties": { "Name": "Fire Detection Centroid ", "Description": "<b>Latitude: <\/b> 19.40689<br\/>  <b>Longitude: <\/b> -155.26993<br\/>  <b>Detection Time: <\/b> 2023-01-17 23:50 UTC<br\/>  <b>Sensor: <\/b> NOAA-20 VIIRS<br\/> <b>Confidence: <\/b> Nominal<br\/>  <b>Day\/Night: <\/b> Day<br\/> <b>Scan: <\/b> 0.51 km<br\/> <b>Track: <\/b> 0.41 km<br\/> <b>FRP: <\/b> 5.14 MW<br\/> <b>Brightness: <\/b> 333.12 K" }, "geometry": { "type": "Point", "coordinates": [ -155.26993, 19.40689, 0.0 ] } },
{ "type": "Feature", "properties": { "Name": "Fire Detection Centroid ", "Description": "<b>Latitude: <\/b> 19.40626<br\/>  <b>Longitude: <\/b> -155.27478<br\/>  <b>Detection Time: <\/b> 2023-01-17 23:50 UTC<br\/>  <b>Sensor: <\/b> NOAA-20 VIIRS<br\/> <b>Confidence: <\/b> Nominal<br\/>  <b>Day\/Night: <\/b> Day<br\/> <b>Scan: <\/b> 0.51 km<br\/> <b>Track: <\/b> 0.41 km<br\/> <b>FRP: <\/b> 76.05 MW<br\/> <b>Brightness: <\/b> 341.21 K" }, "geometry": { "type": "Point", "coordinates": [ -155.27478, 19.40626, 0.0 ] } },
{ "type": "Feature", "properties": { "Name": "Fire Detection Centroid ", "Description": "<b>Latitude: <\/b> 19.41004<br\/>  <b>Longitude: <\/b> -155.27531<br\/>  <b>Detection Time: <\/b> 2023-01-17 23:50 UTC<br\/>  <b>Sensor: <\/b> NOAA-20 VIIRS<br\/> <b>Confidence: <\/b> High<br\/>  <b>Day\/Night: <\/b> Day<br\/> <b>Scan: <\/b> 0.51 km<br\/> <b>Track: <\/b> 0.41 km<br\/> <b>FRP: <\/b> 20.75 MW<br\/> <b>Brightness: <\/b> 367 K" }, "geometry": { "type": "Point", "coordinates": [ -155.27531, 19.41004, 0.0 ] } },
{ "type": "Feature", "properties": { "Name": "Fire Detection Centroid ", "Description": "<b>Latitude: <\/b> 19.40563<br\/>  <b>Longitude: <\/b> -155.27962<br\/>  <b>Detection Time: <\/b> 2023-01-17 23:50 UTC<br\/>  <b>Sensor: <\/b> NOAA-20 VIIRS<br\/> <b>Confidence: <\/b> High<br\/>  <b>Day\/Night: <\/b> Day<br\/> <b>Scan: <\/b> 0.51 km<br\/> <b>Track: <\/b> 0.41 km<br\/> <b>FRP: <\/b> 76.05 MW<br\/> <b>Brightness: <\/b> 367 K" }, "geometry": { "type": "Point", "coordinates": [ -155.27962, 19.40563, 0.0 ] } },
{ "type": "Feature", "properties": { "Name": "Fire Detection Centroid ", "Description": "<b>Latitude: <\/b> 19.40185<br\/>  <b>Longitude: <\/b> -155.27911<br\/>  <b>Detection Time: <\/b> 2023-01-17 23:50 UTC<br\/>  <b>Sensor: <\/b> NOAA-20 VIIRS<br\/> <b>Confidence: <\/b> Nominal<br\/>  <b>Day\/Night: <\/b> Day<br\/> <b>Scan: <\/b> 0.51 km<br\/> <b>Track: <\/b> 0.41 km<br\/> <b>FRP: <\/b> 76.05 MW<br\/> <b>Brightness: <\/b> 353.21 K" }, "geometry": { "type": "Point", "coordinates": [ -155.27911, 19.40185, 0.0 ] } },
{ "type": "Feature", "properties": { "Name": "Fire Detection Centroid ", "Description": "<b>Latitude: <\/b> 19.39869<br\/>  <b>Longitude: <\/b> -155.2738<br\/>  <b>Detection Time: <\/b> 2023-01-17 23:50 UTC<br\/>  <b>Sensor: <\/b> NOAA-20 VIIRS<br\/> <b>Confidence: <\/b> Nominal<br\/>  <b>Day\/Night: <\/b> Day<br\/> <b>Scan: <\/b> 0.51 km<br\/> <b>Track: <\/b> 0.41 km<br\/> <b>FRP: <\/b> 11.06 MW<br\/> <b>Brightness: <\/b> 341.3 K" }, "geometry": { "type": "Point", "coordinates": [ -155.2738, 19.39869, 0.0 ] } }
]
}
