{
"type": "FeatureCollection",
"crs": { "type": "name", "properties": { "name": "urn:ogc:def:crs:OGC:1.3:CRS84" } },
"features": [
{ "type": "Feature", "properties": { "Name": "Fire Detection Centroid ", "Description": "<b>Latitude: <\/b> 39.93904<br\/>  <b>Longitude: <\/b> -76.81964<br\/>  <b>Detection Time: <\/b> 2023-01-22 05:54 UTC<br\/>  <b>Sensor: <\/b> NOAA-20 VIIRS<br\/> <b>Confidence: <\/b> Nominal<br\/>  <b>Day\/Night: <\/b> Night<br\/> <b>Scan: <\/b> 0.7 km<br\/> <b>Track: <\/b> 0.7 km<br\/> <b>FRP: <\/b> 2.13 MW<br\/> <b>Brightness: <\/b> 302.32 K" }, "geometry": { "type": "Point", "coordinates": [ -76.81964, 39.93904, 0.0 ] } },
{ "type": "Feature", "properties": { "Name": "Fire Detection Centroid ", "Description": "<b>Latitude: <\/b> 39.93944<br\/>  <b>Longitude: <\/b> -76.81664<br\/>  <b>Detection Time: <\/b> 2023-01-22 05:54 UTC<br\/>  <b>Sensor: <\/b> NOAA-20 VIIRS<br\/> <b>Confidence: <\/b> Nominal<br\/>  <b>Day\/Night: <\/b> Night<br\/> <b>Scan: <\/b> 0.7 km<br\/> <b>Track: <\/b> 0.7 km<br\/> <b>FRP: <\/b> 1.68 MW<br\/> <b>Brightness: <\/b> 304.29 K" }, "geometry": { "type": "Point", "coordinates": [ -76.81664, 39.93944, 0.0 ] } },
{ "type": "Feature", "properties": { "Name": "Fire Detection Centroid ", "Description": "<b>Latitude: <\/b> 48.18702<br\/>  <b>Longitude: <\/b> -64.92333<br\/>  <b>Detection Time: <\/b> 2023-01-22 05:52 UTC<br\/>  <b>Sensor: <\/b> NOAA-20 VIIRS<br\/> <b>Confidence: <\/b> Nominal<br\/>  <b>Day\/Night: <\/b> Night<br\/> <b>Scan: <\/b> 0.4 km<br\/> <b>Track: <\/b> 0.4 km<br\/> <b>FRP: <\/b> 0.89 MW<br\/> <b>Brightness: <\/b> 303.77 K" }, "geometry": { "type": "Point", "coordinates": [ -64.92333, 48.18702, 0.0 ] } }
]
}
