{
"type": "FeatureCollection",
"crs": { "type": "name", "properties": { "name": "urn:ogc:def:crs:OGC:1.3:CRS84" } },
"features": [
{ "type": "Feature", "properties": { "Name": "Fire Detection Centroid ", "Description": "<b>Latitude: <\/b> 19.74659<br\/>  <b>Longitude: <\/b> -156.03387<br\/>  <b>Detection Time: <\/b> 2024-05-31 23:51 UTC<br\/>  <b>Sensor: <\/b> NOAA-20 VIIRS<br\/> <b>Confidence: <\/b> Nominal<br\/>  <b>Day\/Night: <\/b> Day<br\/> <b>Scan: <\/b> 0.5 km<br\/> <b>Track: <\/b> 0.4 km<br\/> <b>FRP: <\/b> 7.4 MW<br\/> <b>Brightness: <\/b> 333.63 K" }, "geometry": { "type": "Point", "coordinates": [ -156.03387, 19.74659, 0.0 ] } },
{ "type": "Feature", "properties": { "Name": "Fire Detection Centroid ", "Description": "<b>Latitude: <\/b> 19.7471<br\/>  <b>Longitude: <\/b> -156.03531<br\/>  <b>Detection Time: <\/b> 2024-05-31 23:51 UTC<br\/>  <b>Sensor: <\/b> NOAA-20 VIIRS<br\/> <b>Confidence: <\/b> Nominal<br\/>  <b>Day\/Night: <\/b> Day<br\/> <b>Scan: <\/b> 0.5 km<br\/> <b>Track: <\/b> 0.4 km<br\/> <b>FRP: <\/b> 3.27 MW<br\/> <b>Brightness: <\/b> 332.75 K" }, "geometry": { "type": "Point", "coordinates": [ -156.03531, 19.7471, 0.0 ] } },
{ "type": "Feature", "properties": { "Name": "Fire Detection Centroid ", "Description": "<b>Latitude: <\/b> 19.7471<br\/>  <b>Longitude: <\/b> -156.03532<br\/>  <b>Detection Time: <\/b> 2024-05-31 23:50 UTC<br\/>  <b>Sensor: <\/b> NOAA-20 VIIRS<br\/> <b>Confidence: <\/b> Nominal<br\/>  <b>Day\/Night: <\/b> Day<br\/> <b>Scan: <\/b> 0.48 km<br\/> <b>Track: <\/b> 0.4 km<br\/> <b>FRP: <\/b> 3.95 MW<br\/> <b>Brightness: <\/b> 332.75 K" }, "geometry": { "type": "Point", "coordinates": [ -156.03532, 19.7471, 0.0 ] } },
{ "type": "Feature", "properties": { "Name": "Fire Detection Centroid ", "Description": "<b>Latitude: <\/b> 19.74659<br\/>  <b>Longitude: <\/b> -156.03389<br\/>  <b>Detection Time: <\/b> 2024-05-31 23:50 UTC<br\/>  <b>Sensor: <\/b> NOAA-20 VIIRS<br\/> <b>Confidence: <\/b> Nominal<br\/>  <b>Day\/Night: <\/b> Day<br\/> <b>Scan: <\/b> 0.48 km<br\/> <b>Track: <\/b> 0.4 km<br\/> <b>FRP: <\/b> 8.08 MW<br\/> <b>Brightness: <\/b> 333.63 K" }, "geometry": { "type": "Point", "coordinates": [ -156.03389, 19.74659, 0.0 ] } },
{ "type": "Feature", "properties": { "Name": "Fire Detection Centroid ", "Description": "<b>Latitude: <\/b> 44.49814<br\/>  <b>Longitude: <\/b> -123.36971<br\/>  <b>Detection Time: <\/b> 2024-05-31 22:16 UTC<br\/>  <b>Sensor: <\/b> NOAA-20 VIIRS<br\/> <b>Confidence: <\/b> Nominal<br\/>  <b>Day\/Night: <\/b> Day<br\/> <b>Scan: <\/b> 0.7 km<br\/> <b>Track: <\/b> 0.75 km<br\/> <b>FRP: <\/b> 20.66 MW<br\/> <b>Brightness: <\/b> 335.31 K" }, "geometry": { "type": "Point", "coordinates": [ -123.36971, 44.49814, 0.0 ] } },
{ "type": "Feature", "properties": { "Name": "Fire Detection Centroid ", "Description": "<b>Latitude: <\/b> 44.49723<br\/>  <b>Longitude: <\/b> -123.37596<br\/>  <b>Detection Time: <\/b> 2024-05-31 22:16 UTC<br\/>  <b>Sensor: <\/b> NOAA-20 VIIRS<br\/> <b>Confidence: <\/b> High<br\/>  <b>Day\/Night: <\/b> Day<br\/> <b>Scan: <\/b> 0.7 km<br\/> <b>Track: <\/b> 0.75 km<br\/> <b>FRP: <\/b> 32.18 MW<br\/> <b>Brightness: <\/b> 367 K" }, "geometry": { "type": "Point", "coordinates": [ -123.37596, 44.49723, 0.0 ] } },
{ "type": "Feature", "properties": { "Name": "Fire Detection Centroid ", "Description": "<b>Latitude: <\/b> 45.76054<br\/>  <b>Longitude: <\/b> -123.26422<br\/>  <b>Detection Time: <\/b> 2024-05-31 22:16 UTC<br\/>  <b>Sensor: <\/b> NOAA-20 VIIRS<br\/> <b>Confidence: <\/b> High<br\/>  <b>Day\/Night: <\/b> Day<br\/> <b>Scan: <\/b> 0.71 km<br\/> <b>Track: <\/b> 0.75 km<br\/> <b>FRP: <\/b> 19.15 MW<br\/> <b>Brightness: <\/b> 367 K" }, "geometry": { "type": "Point", "coordinates": [ -123.26422, 45.76054, 0.0 ] } },
{ "type": "Feature", "properties": { "Name": "Fire Detection Centroid ", "Description": "<b>Latitude: <\/b> 44.49816<br\/>  <b>Longitude: <\/b> -123.37894<br\/>  <b>Detection Time: <\/b> 2024-05-31 22:16 UTC<br\/>  <b>Sensor: <\/b> NOAA-20 VIIRS<br\/> <b>Confidence: <\/b> Nominal<br\/>  <b>Day\/Night: <\/b> Day<br\/> <b>Scan: <\/b> 0.7 km<br\/> <b>Track: <\/b> 0.75 km<br\/> <b>FRP: <\/b> 29.11 MW<br\/> <b>Brightness: <\/b> 352.65 K" }, "geometry": { "type": "Point", "coordinates": [ -123.37894, 44.49816, 0.0 ] } }
]
}
