{
"type": "FeatureCollection",
"crs": { "type": "name", "properties": { "name": "urn:ogc:def:crs:OGC:1.3:CRS84" } },
"features": [
{ "type": "Feature", "properties": { "Name": "Fire Detection Centroid ", "Description": "<b>Latitude: <\/b> 46.04317<br\/>  <b>Longitude: <\/b> -73.13862<br\/>  <b>Detection Time: <\/b> 2022-08-05 17:06 UTC<br\/>  <b>Sensor: <\/b> NOAA-20 VIIRS<br\/> <b>Confidence: <\/b> Low<br\/>  <b>Day\/Night: <\/b> Day<br\/> <b>Scan: <\/b> 0.5 km<br\/> <b>Track: <\/b> 0.5 km<br\/> <b>FRP: <\/b> 3.01 MW<br\/> <b>Brightness: <\/b> 329.14 K" }, "geometry": { "type": "Point", "coordinates": [ -73.13862, 46.04317, 0.0 ] } },
{ "type": "Feature", "properties": { "Name": "Fire Detection Centroid ", "Description": "<b>Latitude: <\/b> 45.5067<br\/>  <b>Longitude: <\/b> -73.55146<br\/>  <b>Detection Time: <\/b> 2022-08-05 17:06 UTC<br\/>  <b>Sensor: <\/b> NOAA-20 VIIRS<br\/> <b>Confidence: <\/b> Nominal<br\/>  <b>Day\/Night: <\/b> Day<br\/> <b>Scan: <\/b> 0.5 km<br\/> <b>Track: <\/b> 0.5 km<br\/> <b>FRP: <\/b> 1.87 MW<br\/> <b>Brightness: <\/b> 329.97 K" }, "geometry": { "type": "Point", "coordinates": [ -73.55146, 45.5067, 0.0 ] } },
{ "type": "Feature", "properties": { "Name": "Fire Detection Centroid ", "Description": "<b>Latitude: <\/b> 41.45308<br\/>  <b>Longitude: <\/b> -81.67391<br\/>  <b>Detection Time: <\/b> 2022-08-05 17:05 UTC<br\/>  <b>Sensor: <\/b> NOAA-20 VIIRS<br\/> <b>Confidence: <\/b> Nominal<br\/>  <b>Day\/Night: <\/b> Day<br\/> <b>Scan: <\/b> 0.8 km<br\/> <b>Track: <\/b> 0.8 km<br\/> <b>FRP: <\/b> 3.08 MW<br\/> <b>Brightness: <\/b> 325.5 K" }, "geometry": { "type": "Point", "coordinates": [ -81.67391, 41.45308, 0.0 ] } },
{ "type": "Feature", "properties": { "Name": "Fire Detection Centroid ", "Description": "<b>Latitude: <\/b> 18.39586<br\/>  <b>Longitude: <\/b> -64.66001<br\/>  <b>Detection Time: <\/b> 2022-08-05 16:58 UTC<br\/>  <b>Sensor: <\/b> NOAA-20 VIIRS<br\/> <b>Confidence: <\/b> Nominal<br\/>  <b>Day\/Night: <\/b> Day<br\/> <b>Scan: <\/b> 0.6 km<br\/> <b>Track: <\/b> 0.5 km<br\/> <b>FRP: <\/b> 6.37 MW<br\/> <b>Brightness: <\/b> 332.36 K" }, "geometry": { "type": "Point", "coordinates": [ -64.66001, 18.39586, 0.0 ] } }
]
}
