{
"type": "FeatureCollection",
"crs": { "type": "name", "properties": { "name": "urn:ogc:def:crs:OGC:1.3:CRS84" } },
"features": [
{ "type": "Feature", "properties": { "Name": "Fire Detection Centroid ", "Description": "<b>Latitude: <\/b> 41.70453<br\/>  <b>Longitude: <\/b> -71.48864<br\/>  <b>Detection Time: <\/b> 2024-05-17 16:35 UTC<br\/>  <b>Sensor: <\/b> NOAA-20 VIIRS<br\/> <b>Confidence: <\/b> Nominal<br\/>  <b>Day\/Night: <\/b> Day<br\/> <b>Scan: <\/b> 0.6 km<br\/> <b>Track: <\/b> 0.7 km<br\/> <b>FRP: <\/b> 3.79 MW<br\/> <b>Brightness: <\/b> 325.31 K" }, "geometry": { "type": "Point", "coordinates": [ -71.48864, 41.70453, 0.0 ] } }
]
}
