{
"type": "FeatureCollection",
"crs": { "type": "name", "properties": { "name": "urn:ogc:def:crs:OGC:1.3:CRS84" } },
"features": [
{ "type": "Feature", "properties": { "Name": "Fire Detection Centroid ", "Description": "<b>Latitude: <\/b> 19.41241<br\/>  <b>Longitude: <\/b> -155.28552<br\/>  <b>Detection Time: <\/b> 2022-09-06 00:03 UTC<br\/>  <b>Sensor: <\/b> NOAA-20 VIIRS<br\/> <b>Confidence: <\/b> Low<br\/>  <b>Day\/Night: <\/b> Day<br\/> <b>Scan: <\/b> 0.53 km<br\/> <b>Track: <\/b> 0.5 km<br\/> <b>FRP: <\/b> 10.56 MW<br\/> <b>Brightness: <\/b> 342.5 K" }, "geometry": { "type": "Point", "coordinates": [ -155.28552, 19.41241, 0.0 ] } },
{ "type": "Feature", "properties": { "Name": "Fire Detection Centroid ", "Description": "<b>Latitude: <\/b> 19.40723<br\/>  <b>Longitude: <\/b> -155.29001<br\/>  <b>Detection Time: <\/b> 2022-09-06 00:03 UTC<br\/>  <b>Sensor: <\/b> NOAA-20 VIIRS<br\/> <b>Confidence: <\/b> Nominal<br\/>  <b>Day\/Night: <\/b> Day<br\/> <b>Scan: <\/b> 0.53 km<br\/> <b>Track: <\/b> 0.5 km<br\/> <b>FRP: <\/b> 28.65 MW<br\/> <b>Brightness: <\/b> 352.79 K" }, "geometry": { "type": "Point", "coordinates": [ -155.29001, 19.40723, 0.0 ] } },
{ "type": "Feature", "properties": { "Name": "Fire Detection Centroid ", "Description": "<b>Latitude: <\/b> 19.4078<br\/>  <b>Longitude: <\/b> -155.28476<br\/>  <b>Detection Time: <\/b> 2022-09-06 00:03 UTC<br\/>  <b>Sensor: <\/b> NOAA-20 VIIRS<br\/> <b>Confidence: <\/b> Nominal<br\/>  <b>Day\/Night: <\/b> Day<br\/> <b>Scan: <\/b> 0.53 km<br\/> <b>Track: <\/b> 0.5 km<br\/> <b>FRP: <\/b> 10.56 MW<br\/> <b>Brightness: <\/b> 350.42 K" }, "geometry": { "type": "Point", "coordinates": [ -155.28476, 19.4078, 0.0 ] } },
{ "type": "Feature", "properties": { "Name": "Fire Detection Centroid ", "Description": "<b>Latitude: <\/b> 19.40836<br\/>  <b>Longitude: <\/b> -155.27962<br\/>  <b>Detection Time: <\/b> 2022-09-06 00:03 UTC<br\/>  <b>Sensor: <\/b> NOAA-20 VIIRS<br\/> <b>Confidence: <\/b> Low<br\/>  <b>Day\/Night: <\/b> Day<br\/> <b>Scan: <\/b> 0.53 km<br\/> <b>Track: <\/b> 0.5 km<br\/> <b>FRP: <\/b> 10.56 MW<br\/> <b>Brightness: <\/b> 342.85 K" }, "geometry": { "type": "Point", "coordinates": [ -155.27962, 19.40836, 0.0 ] } },
{ "type": "Feature", "properties": { "Name": "Fire Detection Centroid ", "Description": "<b>Latitude: <\/b> 19.40806<br\/>  <b>Longitude: <\/b> -155.2878<br\/>  <b>Detection Time: <\/b> 2022-09-06 00:03 UTC<br\/>  <b>Sensor: <\/b> NOAA-20 VIIRS<br\/> <b>Confidence: <\/b> Nominal<br\/>  <b>Day\/Night: <\/b> Day<br\/> <b>Scan: <\/b> 0.53 km<br\/> <b>Track: <\/b> 0.5 km<br\/> <b>FRP: <\/b> 65.57 MW<br\/> <b>Brightness: <\/b> 356.2 K" }, "geometry": { "type": "Point", "coordinates": [ -155.2878, 19.40806, 0.0 ] } },
{ "type": "Feature", "properties": { "Name": "Fire Detection Centroid ", "Description": "<b>Latitude: <\/b> 19.40866<br\/>  <b>Longitude: <\/b> -155.28262<br\/>  <b>Detection Time: <\/b> 2022-09-06 00:03 UTC<br\/>  <b>Sensor: <\/b> NOAA-20 VIIRS<br\/> <b>Confidence: <\/b> Nominal<br\/>  <b>Day\/Night: <\/b> Day<br\/> <b>Scan: <\/b> 0.53 km<br\/> <b>Track: <\/b> 0.5 km<br\/> <b>FRP: <\/b> 65.57 MW<br\/> <b>Brightness: <\/b> 348.18 K" }, "geometry": { "type": "Point", "coordinates": [ -155.28262, 19.40866, 0.0 ] } },
{ "type": "Feature", "properties": { "Name": "Fire Detection Centroid ", "Description": "<b>Latitude: <\/b> 19.40405<br\/>  <b>Longitude: <\/b> -155.28198<br\/>  <b>Detection Time: <\/b> 2022-09-06 00:03 UTC<br\/>  <b>Sensor: <\/b> NOAA-20 VIIRS<br\/> <b>Confidence: <\/b> Nominal<br\/>  <b>Day\/Night: <\/b> Day<br\/> <b>Scan: <\/b> 0.53 km<br\/> <b>Track: <\/b> 0.5 km<br\/> <b>FRP: <\/b> 65.57 MW<br\/> <b>Brightness: <\/b> 346.22 K" }, "geometry": { "type": "Point", "coordinates": [ -155.28198, 19.40405, 0.0 ] } },
{ "type": "Feature", "properties": { "Name": "Fire Detection Centroid ", "Description": "<b>Latitude: <\/b> 19.40346<br\/>  <b>Longitude: <\/b> -155.28706<br\/>  <b>Detection Time: <\/b> 2022-09-06 00:03 UTC<br\/>  <b>Sensor: <\/b> NOAA-20 VIIRS<br\/> <b>Confidence: <\/b> High<br\/>  <b>Day\/Night: <\/b> Day<br\/> <b>Scan: <\/b> 0.53 km<br\/> <b>Track: <\/b> 0.5 km<br\/> <b>FRP: <\/b> 65.57 MW<br\/> <b>Brightness: <\/b> 367 K" }, "geometry": { "type": "Point", "coordinates": [ -155.28706, 19.40346, 0.0 ] } }
]
}
