{
"type": "FeatureCollection",
"crs": { "type": "name", "properties": { "name": "urn:ogc:def:crs:OGC:1.3:CRS84" } },
"features": [
{ "type": "Feature", "properties": { "Name": "Fire Detection Centroid ", "Description": "<b>Latitude: <\/b> 19.40321<br\/>  <b>Longitude: <\/b> -155.28725<br\/>  <b>Detection Time: <\/b> 2023-07-09 11:55 UTC<br\/>  <b>Sensor: <\/b> NOAA-20 VIIRS<br\/> <b>Confidence: <\/b> Nominal<br\/>  <b>Day\/Night: <\/b> Night<br\/> <b>Scan: <\/b> 0.39 km<br\/> <b>Track: <\/b> 0.36 km<br\/> <b>FRP: <\/b> 1.26 MW<br\/> <b>Brightness: <\/b> 300.17 K" }, "geometry": { "type": "Point", "coordinates": [ -155.28725, 19.40321, 0.0 ] } },
{ "type": "Feature", "properties": { "Name": "Fire Detection Centroid ", "Description": "<b>Latitude: <\/b> 19.40651<br\/>  <b>Longitude: <\/b> -155.28667<br\/>  <b>Detection Time: <\/b> 2023-07-09 11:55 UTC<br\/>  <b>Sensor: <\/b> NOAA-20 VIIRS<br\/> <b>Confidence: <\/b> Nominal<br\/>  <b>Day\/Night: <\/b> Night<br\/> <b>Scan: <\/b> 0.39 km<br\/> <b>Track: <\/b> 0.36 km<br\/> <b>FRP: <\/b> 1.05 MW<br\/> <b>Brightness: <\/b> 301.27 K" }, "geometry": { "type": "Point", "coordinates": [ -155.28667, 19.40651, 0.0 ] } },
{ "type": "Feature", "properties": { "Name": "Fire Detection Centroid ", "Description": "<b>Latitude: <\/b> 19.40925<br\/>  <b>Longitude: <\/b> -155.28247<br\/>  <b>Detection Time: <\/b> 2023-07-09 11:55 UTC<br\/>  <b>Sensor: <\/b> NOAA-20 VIIRS<br\/> <b>Confidence: <\/b> Nominal<br\/>  <b>Day\/Night: <\/b> Night<br\/> <b>Scan: <\/b> 0.39 km<br\/> <b>Track: <\/b> 0.36 km<br\/> <b>FRP: <\/b> 1.53 MW<br\/> <b>Brightness: <\/b> 295.15 K" }, "geometry": { "type": "Point", "coordinates": [ -155.28247, 19.40925, 0.0 ] } },
{ "type": "Feature", "properties": { "Name": "Fire Detection Centroid ", "Description": "<b>Latitude: <\/b> 19.40981<br\/>  <b>Longitude: <\/b> -155.2861<br\/>  <b>Detection Time: <\/b> 2023-07-09 11:55 UTC<br\/>  <b>Sensor: <\/b> NOAA-20 VIIRS<br\/> <b>Confidence: <\/b> Nominal<br\/>  <b>Day\/Night: <\/b> Night<br\/> <b>Scan: <\/b> 0.39 km<br\/> <b>Track: <\/b> 0.36 km<br\/> <b>FRP: <\/b> 1.05 MW<br\/> <b>Brightness: <\/b> 301.87 K" }, "geometry": { "type": "Point", "coordinates": [ -155.2861, 19.40981, 0.0 ] } },
{ "type": "Feature", "properties": { "Name": "Fire Detection Centroid ", "Description": "<b>Latitude: <\/b> 19.412<br\/>  <b>Longitude: <\/b> -155.27826<br\/>  <b>Detection Time: <\/b> 2023-07-09 11:55 UTC<br\/>  <b>Sensor: <\/b> NOAA-20 VIIRS<br\/> <b>Confidence: <\/b> Nominal<br\/>  <b>Day\/Night: <\/b> Night<br\/> <b>Scan: <\/b> 0.39 km<br\/> <b>Track: <\/b> 0.36 km<br\/> <b>FRP: <\/b> 1.6 MW<br\/> <b>Brightness: <\/b> 301.67 K" }, "geometry": { "type": "Point", "coordinates": [ -155.27826, 19.412, 0.0 ] } },
{ "type": "Feature", "properties": { "Name": "Fire Detection Centroid ", "Description": "<b>Latitude: <\/b> 19.41256<br\/>  <b>Longitude: <\/b> -155.28189<br\/>  <b>Detection Time: <\/b> 2023-07-09 11:55 UTC<br\/>  <b>Sensor: <\/b> NOAA-20 VIIRS<br\/> <b>Confidence: <\/b> Nominal<br\/>  <b>Day\/Night: <\/b> Night<br\/> <b>Scan: <\/b> 0.39 km<br\/> <b>Track: <\/b> 0.36 km<br\/> <b>FRP: <\/b> 1.6 MW<br\/> <b>Brightness: <\/b> 310.13 K" }, "geometry": { "type": "Point", "coordinates": [ -155.28189, 19.41256, 0.0 ] } },
{ "type": "Feature", "properties": { "Name": "Fire Detection Centroid ", "Description": "<b>Latitude: <\/b> 19.41311<br\/>  <b>Longitude: <\/b> -155.28552<br\/>  <b>Detection Time: <\/b> 2023-07-09 11:55 UTC<br\/>  <b>Sensor: <\/b> NOAA-20 VIIRS<br\/> <b>Confidence: <\/b> Nominal<br\/>  <b>Day\/Night: <\/b> Night<br\/> <b>Scan: <\/b> 0.39 km<br\/> <b>Track: <\/b> 0.36 km<br\/> <b>FRP: <\/b> 0.73 MW<br\/> <b>Brightness: <\/b> 295.89 K" }, "geometry": { "type": "Point", "coordinates": [ -155.28552, 19.41311, 0.0 ] } },
{ "type": "Feature", "properties": { "Name": "Fire Detection Centroid ", "Description": "<b>Latitude: <\/b> 20.86242<br\/>  <b>Longitude: <\/b> -156.41992<br\/>  <b>Detection Time: <\/b> 2023-07-09 11:55 UTC<br\/>  <b>Sensor: <\/b> NOAA-20 VIIRS<br\/> <b>Confidence: <\/b> Nominal<br\/>  <b>Day\/Night: <\/b> Night<br\/> <b>Scan: <\/b> 0.42 km<br\/> <b>Track: <\/b> 0.37 km<br\/> <b>FRP: <\/b> 0.72 MW<br\/> <b>Brightness: <\/b> 301.97 K" }, "geometry": { "type": "Point", "coordinates": [ -156.41992, 20.86242, 0.0 ] } }
]
}
