{
"type": "FeatureCollection",
"crs": { "type": "name", "properties": { "name": "urn:ogc:def:crs:OGC:1.3:CRS84" } },
"features": [
{ "type": "Feature", "properties": { "Name": "Fire Detection Centroid ", "Description": "<b>Latitude: <\/b> 19.04879<br\/>  <b>Longitude: <\/b> -72.80995<br\/>  <b>Detection Time: <\/b> 2023-12-14 05:48 UTC<br\/>  <b>Sensor: <\/b> NOAA-20 VIIRS<br\/> <b>Confidence: <\/b> Nominal<br\/>  <b>Day\/Night: <\/b> Night<br\/> <b>Scan: <\/b> 0.4 km<br\/> <b>Track: <\/b> 0.6 km<br\/> <b>FRP: <\/b> 1.92 MW<br\/> <b>Brightness: <\/b> 301.42 K" }, "geometry": { "type": "Point", "coordinates": [ -72.80995, 19.04879, 0.0 ] } },
{ "type": "Feature", "properties": { "Name": "Fire Detection Centroid ", "Description": "<b>Latitude: <\/b> 40.62687<br\/>  <b>Longitude: <\/b> -74.17909<br\/>  <b>Detection Time: <\/b> 2023-12-14 05:42 UTC<br\/>  <b>Sensor: <\/b> NOAA-20 VIIRS<br\/> <b>Confidence: <\/b> Nominal<br\/>  <b>Day\/Night: <\/b> Night<br\/> <b>Scan: <\/b> 0.7 km<br\/> <b>Track: <\/b> 0.8 km<br\/> <b>FRP: <\/b> 0.93 MW<br\/> <b>Brightness: <\/b> 303.98 K" }, "geometry": { "type": "Point", "coordinates": [ -74.17909, 40.62687, 0.0 ] } },
{ "type": "Feature", "properties": { "Name": "Fire Detection Centroid ", "Description": "<b>Latitude: <\/b> 45.27979<br\/>  <b>Longitude: <\/b> -66.0215<br\/>  <b>Detection Time: <\/b> 2023-12-14 05:40 UTC<br\/>  <b>Sensor: <\/b> NOAA-20 VIIRS<br\/> <b>Confidence: <\/b> Nominal<br\/>  <b>Day\/Night: <\/b> Night<br\/> <b>Scan: <\/b> 0.6 km<br\/> <b>Track: <\/b> 0.5 km<br\/> <b>FRP: <\/b> 2.47 MW<br\/> <b>Brightness: <\/b> 306.35 K" }, "geometry": { "type": "Point", "coordinates": [ -66.0215, 45.27979, 0.0 ] } }
]
}
