{
"type": "FeatureCollection",
"crs": { "type": "name", "properties": { "name": "urn:ogc:def:crs:OGC:1.3:CRS84" } },
"features": [
{ "type": "Feature", "properties": { "Name": "Fire Detection Centroid ", "Description": "<b>Latitude: <\/b> 18.39096<br\/>  <b>Longitude: <\/b> -71.28228<br\/>  <b>Detection Time: <\/b> 2024-03-30 05:25 UTC<br\/>  <b>Sensor: <\/b> NOAA-20 VIIRS<br\/> <b>Confidence: <\/b> Nominal<br\/>  <b>Day\/Night: <\/b> Night<br\/> <b>Scan: <\/b> 0.8 km<br\/> <b>Track: <\/b> 0.8 km<br\/> <b>FRP: <\/b> 1.64 MW<br\/> <b>Brightness: <\/b> 307.84 K" }, "geometry": { "type": "Point", "coordinates": [ -71.28228, 18.39096, 0.0 ] } },
{ "type": "Feature", "properties": { "Name": "Fire Detection Centroid ", "Description": "<b>Latitude: <\/b> 18.17883<br\/>  <b>Longitude: <\/b> -71.27451<br\/>  <b>Detection Time: <\/b> 2024-03-30 05:25 UTC<br\/>  <b>Sensor: <\/b> NOAA-20 VIIRS<br\/> <b>Confidence: <\/b> Nominal<br\/>  <b>Day\/Night: <\/b> Night<br\/> <b>Scan: <\/b> 0.8 km<br\/> <b>Track: <\/b> 0.8 km<br\/> <b>FRP: <\/b> 2.61 MW<br\/> <b>Brightness: <\/b> 306.28 K" }, "geometry": { "type": "Point", "coordinates": [ -71.27451, 18.17883, 0.0 ] } }
]
}
