{
"type": "FeatureCollection",
"crs": { "type": "name", "properties": { "name": "urn:ogc:def:crs:OGC:1.3:CRS84" } },
"features": [
{ "type": "Feature", "properties": { "Name": "Fire Detection Centroid ", "Description": "<b>Latitude: <\/b> 19.40141<br\/>  <b>Longitude: <\/b> -155.28943<br\/>  <b>Detection Time: <\/b> 2022-09-13 23:12 UTC<br\/>  <b>Sensor: <\/b> NOAA-20 VIIRS<br\/> <b>Confidence: <\/b> Nominal<br\/>  <b>Day\/Night: <\/b> Day<br\/> <b>Scan: <\/b> 0.39 km<br\/> <b>Track: <\/b> 0.44 km<br\/> <b>FRP: <\/b> 9.62 MW<br\/> <b>Brightness: <\/b> 327.83 K" }, "geometry": { "type": "Point", "coordinates": [ -155.28943, 19.40141, 0.0 ] } },
{ "type": "Feature", "properties": { "Name": "Fire Detection Centroid ", "Description": "<b>Latitude: <\/b> 19.40637<br\/>  <b>Longitude: <\/b> -155.28336<br\/>  <b>Detection Time: <\/b> 2022-09-13 23:12 UTC<br\/>  <b>Sensor: <\/b> NOAA-20 VIIRS<br\/> <b>Confidence: <\/b> Nominal<br\/>  <b>Day\/Night: <\/b> Day<br\/> <b>Scan: <\/b> 0.4 km<br\/> <b>Track: <\/b> 0.4 km<br\/> <b>FRP: <\/b> 18.44 MW<br\/> <b>Brightness: <\/b> 351.61 K" }, "geometry": { "type": "Point", "coordinates": [ -155.28336, 19.40637, 0.0 ] } },
{ "type": "Feature", "properties": { "Name": "Fire Detection Centroid ", "Description": "<b>Latitude: <\/b> 19.4057<br\/>  <b>Longitude: <\/b> -155.28702<br\/>  <b>Detection Time: <\/b> 2022-09-13 23:12 UTC<br\/>  <b>Sensor: <\/b> NOAA-20 VIIRS<br\/> <b>Confidence: <\/b> Nominal<br\/>  <b>Day\/Night: <\/b> Day<br\/> <b>Scan: <\/b> 0.4 km<br\/> <b>Track: <\/b> 0.4 km<br\/> <b>FRP: <\/b> 9.62 MW<br\/> <b>Brightness: <\/b> 343.34 K" }, "geometry": { "type": "Point", "coordinates": [ -155.28702, 19.4057, 0.0 ] } },
{ "type": "Feature", "properties": { "Name": "Fire Detection Centroid ", "Description": "<b>Latitude: <\/b> 19.40239<br\/>  <b>Longitude: <\/b> -155.28256<br\/>  <b>Detection Time: <\/b> 2022-09-13 23:12 UTC<br\/>  <b>Sensor: <\/b> NOAA-20 VIIRS<br\/> <b>Confidence: <\/b> Nominal<br\/>  <b>Day\/Night: <\/b> Day<br\/> <b>Scan: <\/b> 0.4 km<br\/> <b>Track: <\/b> 0.4 km<br\/> <b>FRP: <\/b> 18.44 MW<br\/> <b>Brightness: <\/b> 344.36 K" }, "geometry": { "type": "Point", "coordinates": [ -155.28256, 19.40239, 0.0 ] } },
{ "type": "Feature", "properties": { "Name": "Fire Detection Centroid ", "Description": "<b>Latitude: <\/b> 19.40106<br\/>  <b>Longitude: <\/b> -155.28978<br\/>  <b>Detection Time: <\/b> 2022-09-13 23:12 UTC<br\/>  <b>Sensor: <\/b> NOAA-20 VIIRS<br\/> <b>Confidence: <\/b> Nominal<br\/>  <b>Day\/Night: <\/b> Day<br\/> <b>Scan: <\/b> 0.4 km<br\/> <b>Track: <\/b> 0.4 km<br\/> <b>FRP: <\/b> 9.62 MW<br\/> <b>Brightness: <\/b> 327.83 K" }, "geometry": { "type": "Point", "coordinates": [ -155.28978, 19.40106, 0.0 ] } },
{ "type": "Feature", "properties": { "Name": "Fire Detection Centroid ", "Description": "<b>Latitude: <\/b> 19.40273<br\/>  <b>Longitude: <\/b> -155.28218<br\/>  <b>Detection Time: <\/b> 2022-09-13 23:12 UTC<br\/>  <b>Sensor: <\/b> NOAA-20 VIIRS<br\/> <b>Confidence: <\/b> Nominal<br\/>  <b>Day\/Night: <\/b> Day<br\/> <b>Scan: <\/b> 0.39 km<br\/> <b>Track: <\/b> 0.44 km<br\/> <b>FRP: <\/b> 18.45 MW<br\/> <b>Brightness: <\/b> 344.36 K" }, "geometry": { "type": "Point", "coordinates": [ -155.28218, 19.40273, 0.0 ] } },
{ "type": "Feature", "properties": { "Name": "Fire Detection Centroid ", "Description": "<b>Latitude: <\/b> 19.40604<br\/>  <b>Longitude: <\/b> -155.28664<br\/>  <b>Detection Time: <\/b> 2022-09-13 23:12 UTC<br\/>  <b>Sensor: <\/b> NOAA-20 VIIRS<br\/> <b>Confidence: <\/b> Nominal<br\/>  <b>Day\/Night: <\/b> Day<br\/> <b>Scan: <\/b> 0.39 km<br\/> <b>Track: <\/b> 0.44 km<br\/> <b>FRP: <\/b> 9.62 MW<br\/> <b>Brightness: <\/b> 343.34 K" }, "geometry": { "type": "Point", "coordinates": [ -155.28664, 19.40604, 0.0 ] } },
{ "type": "Feature", "properties": { "Name": "Fire Detection Centroid ", "Description": "<b>Latitude: <\/b> 19.40671<br\/>  <b>Longitude: <\/b> -155.28299<br\/>  <b>Detection Time: <\/b> 2022-09-13 23:12 UTC<br\/>  <b>Sensor: <\/b> NOAA-20 VIIRS<br\/> <b>Confidence: <\/b> Nominal<br\/>  <b>Day\/Night: <\/b> Day<br\/> <b>Scan: <\/b> 0.39 km<br\/> <b>Track: <\/b> 0.44 km<br\/> <b>FRP: <\/b> 18.45 MW<br\/> <b>Brightness: <\/b> 351.61 K" }, "geometry": { "type": "Point", "coordinates": [ -155.28299, 19.40671, 0.0 ] } }
]
}
