{
"type": "FeatureCollection",
"crs": { "type": "name", "properties": { "name": "urn:ogc:def:crs:OGC:1.3:CRS84" } },
"features": [
{ "type": "Feature", "properties": { "Name": "Fire Detection Centroid ", "Description": "<b>Latitude: <\/b> 19.40563<br\/>  <b>Longitude: <\/b> -155.28949<br\/>  <b>Detection Time: <\/b> 2022-12-21 00:15 UTC<br\/>  <b>Sensor: <\/b> NOAA-20 VIIRS<br\/> <b>Confidence: <\/b> Nominal<br\/>  <b>Day\/Night: <\/b> Day<br\/> <b>Scan: <\/b> 0.4 km<br\/> <b>Track: <\/b> 0.6 km<br\/> <b>FRP: <\/b> 7.65 MW<br\/> <b>Brightness: <\/b> 337.61 K" }, "geometry": { "type": "Point", "coordinates": [ -155.28949, 19.40563, 0.0 ] } }
]
}
