{
"type": "FeatureCollection",
"crs": { "type": "name", "properties": { "name": "urn:ogc:def:crs:OGC:1.3:CRS84" } },
"features": [
{ "type": "Feature", "properties": { "Name": "Fire Detection Centroid ", "Description": "<b>Latitude: <\/b> 21.95141<br\/>  <b>Longitude: <\/b> -159.66376<br\/>  <b>Detection Time: <\/b> 2023-08-06 00:41 UTC<br\/>  <b>Sensor: <\/b> NOAA-20 VIIRS<br\/> <b>Confidence: <\/b> Nominal<br\/>  <b>Day\/Night: <\/b> Day<br\/> <b>Scan: <\/b> 0.63 km<br\/> <b>Track: <\/b> 0.72 km<br\/> <b>FRP: <\/b> 5.89 MW<br\/> <b>Brightness: <\/b> 329.55 K" }, "geometry": { "type": "Point", "coordinates": [ -159.66376, 21.95141, 0.0 ] } },
{ "type": "Feature", "properties": { "Name": "Fire Detection Centroid ", "Description": "<b>Latitude: <\/b> 21.94687<br\/>  <b>Longitude: <\/b> -159.66252<br\/>  <b>Detection Time: <\/b> 2023-08-06 00:41 UTC<br\/>  <b>Sensor: <\/b> NOAA-20 VIIRS<br\/> <b>Confidence: <\/b> Nominal<br\/>  <b>Day\/Night: <\/b> Day<br\/> <b>Scan: <\/b> 0.63 km<br\/> <b>Track: <\/b> 0.72 km<br\/> <b>FRP: <\/b> 11.31 MW<br\/> <b>Brightness: <\/b> 352.51 K" }, "geometry": { "type": "Point", "coordinates": [ -159.66252, 21.94687, 0.0 ] } }
]
}
