{
"type": "FeatureCollection",
"crs": { "type": "name", "properties": { "name": "urn:ogc:def:crs:OGC:1.3:CRS84" } },
"features": [
{ "type": "Feature", "properties": { "Name": "Fire Detection Centroid ", "Description": "<b>Latitude: <\/b> 38.07063<br\/>  <b>Longitude: <\/b> -122.1386<br\/>  <b>Detection Time: <\/b> 2023-03-15 09:43 UTC<br\/>  <b>Sensor: <\/b> NOAA-20 VIIRS<br\/> <b>Confidence: <\/b> Nominal<br\/>  <b>Day\/Night: <\/b> Night<br\/> <b>Scan: <\/b> 0.5 km<br\/> <b>Track: <\/b> 0.4 km<br\/> <b>FRP: <\/b> 1.63 MW<br\/> <b>Brightness: <\/b> 301.95 K" }, "geometry": { "type": "Point", "coordinates": [ -122.1386, 38.07063, 0.0 ] } },
{ "type": "Feature", "properties": { "Name": "Fire Detection Centroid ", "Description": "<b>Latitude: <\/b> 39.49332<br\/>  <b>Longitude: <\/b> -119.61828<br\/>  <b>Detection Time: <\/b> 2023-03-15 09:43 UTC<br\/>  <b>Sensor: <\/b> NOAA-20 VIIRS<br\/> <b>Confidence: <\/b> Nominal<br\/>  <b>Day\/Night: <\/b> Night<br\/> <b>Scan: <\/b> 0.4 km<br\/> <b>Track: <\/b> 0.4 km<br\/> <b>FRP: <\/b> 0.7 MW<br\/> <b>Brightness: <\/b> 297.33 K" }, "geometry": { "type": "Point", "coordinates": [ -119.61828, 39.49332, 0.0 ] } },
{ "type": "Feature", "properties": { "Name": "Fire Detection Centroid ", "Description": "<b>Latitude: <\/b> 38.01587<br\/>  <b>Longitude: <\/b> -122.11018<br\/>  <b>Detection Time: <\/b> 2023-03-15 09:43 UTC<br\/>  <b>Sensor: <\/b> NOAA-20 VIIRS<br\/> <b>Confidence: <\/b> Nominal<br\/>  <b>Day\/Night: <\/b> Night<br\/> <b>Scan: <\/b> 0.5 km<br\/> <b>Track: <\/b> 0.4 km<br\/> <b>FRP: <\/b> 0.79 MW<br\/> <b>Brightness: <\/b> 295.39 K" }, "geometry": { "type": "Point", "coordinates": [ -122.11018, 38.01587, 0.0 ] } },
{ "type": "Feature", "properties": { "Name": "Fire Detection Centroid ", "Description": "<b>Latitude: <\/b> 38.01651<br\/>  <b>Longitude: <\/b> -122.1156<br\/>  <b>Detection Time: <\/b> 2023-03-15 09:43 UTC<br\/>  <b>Sensor: <\/b> NOAA-20 VIIRS<br\/> <b>Confidence: <\/b> Nominal<br\/>  <b>Day\/Night: <\/b> Night<br\/> <b>Scan: <\/b> 0.5 km<br\/> <b>Track: <\/b> 0.4 km<br\/> <b>FRP: <\/b> 0.73 MW<br\/> <b>Brightness: <\/b> 296.09 K" }, "geometry": { "type": "Point", "coordinates": [ -122.1156, 38.01651, 0.0 ] } },
{ "type": "Feature", "properties": { "Name": "Fire Detection Centroid ", "Description": "<b>Latitude: <\/b> 38.00586<br\/>  <b>Longitude: <\/b> -121.93433<br\/>  <b>Detection Time: <\/b> 2023-03-15 09:43 UTC<br\/>  <b>Sensor: <\/b> NOAA-20 VIIRS<br\/> <b>Confidence: <\/b> Nominal<br\/>  <b>Day\/Night: <\/b> Night<br\/> <b>Scan: <\/b> 0.5 km<br\/> <b>Track: <\/b> 0.4 km<br\/> <b>FRP: <\/b> 0.72 MW<br\/> <b>Brightness: <\/b> 300.9 K" }, "geometry": { "type": "Point", "coordinates": [ -121.93433, 38.00586, 0.0 ] } },
{ "type": "Feature", "properties": { "Name": "Fire Detection Centroid ", "Description": "<b>Latitude: <\/b> 38.0296<br\/>  <b>Longitude: <\/b> -122.06857<br\/>  <b>Detection Time: <\/b> 2023-03-15 09:43 UTC<br\/>  <b>Sensor: <\/b> NOAA-20 VIIRS<br\/> <b>Confidence: <\/b> Nominal<br\/>  <b>Day\/Night: <\/b> Night<br\/> <b>Scan: <\/b> 0.5 km<br\/> <b>Track: <\/b> 0.4 km<br\/> <b>FRP: <\/b> 0.7 MW<br\/> <b>Brightness: <\/b> 295.19 K" }, "geometry": { "type": "Point", "coordinates": [ -122.06857, 38.0296, 0.0 ] } },
{ "type": "Feature", "properties": { "Name": "Fire Detection Centroid ", "Description": "<b>Latitude: <\/b> 45.64787<br\/>  <b>Longitude: <\/b> -120.21243<br\/>  <b>Detection Time: <\/b> 2023-03-15 09:41 UTC<br\/>  <b>Sensor: <\/b> NOAA-20 VIIRS<br\/> <b>Confidence: <\/b> Nominal<br\/>  <b>Day\/Night: <\/b> Night<br\/> <b>Scan: <\/b> 0.5 km<br\/> <b>Track: <\/b> 0.4 km<br\/> <b>FRP: <\/b> 1.07 MW<br\/> <b>Brightness: <\/b> 303.44 K" }, "geometry": { "type": "Point", "coordinates": [ -120.21243, 45.64787, 0.0 ] } },
{ "type": "Feature", "properties": { "Name": "Fire Detection Centroid ", "Description": "<b>Latitude: <\/b> 44.41117<br\/>  <b>Longitude: <\/b> -104.07784<br\/>  <b>Detection Time: <\/b> 2023-03-15 09:41 UTC<br\/>  <b>Sensor: <\/b> NOAA-20 VIIRS<br\/> <b>Confidence: <\/b> Nominal<br\/>  <b>Day\/Night: <\/b> Night<br\/> <b>Scan: <\/b> 0.6 km<br\/> <b>Track: <\/b> 0.5 km<br\/> <b>FRP: <\/b> 0.69 MW<br\/> <b>Brightness: <\/b> 296.58 K" }, "geometry": { "type": "Point", "coordinates": [ -104.07784, 44.41117, 0.0 ] } }
]
}
