{
"type": "FeatureCollection",
"crs": { "type": "name", "properties": { "name": "urn:ogc:def:crs:OGC:1.3:CRS84" } },
"features": [
{ "type": "Feature", "properties": { "Name": "Fire Detection Centroid ", "Description": "<b>Latitude: <\/b> 18.42103<br\/>  <b>Longitude: <\/b> -69.48178<br\/>  <b>Detection Time: <\/b> 2023-08-19 05:42 UTC<br\/>  <b>Sensor: <\/b> NOAA-20 VIIRS<br\/> <b>Confidence: <\/b> Nominal<br\/>  <b>Day\/Night: <\/b> Night<br\/> <b>Scan: <\/b> 0.6 km<br\/> <b>Track: <\/b> 0.5 km<br\/> <b>FRP: <\/b> 1.76 MW<br\/> <b>Brightness: <\/b> 308.46 K" }, "geometry": { "type": "Point", "coordinates": [ -69.48178, 18.42103, 0.0 ] } },
{ "type": "Feature", "properties": { "Name": "Fire Detection Centroid ", "Description": "<b>Latitude: <\/b> 18.41908<br\/>  <b>Longitude: <\/b> -69.4826<br\/>  <b>Detection Time: <\/b> 2023-08-19 05:42 UTC<br\/>  <b>Sensor: <\/b> NOAA-20 VIIRS<br\/> <b>Confidence: <\/b> Nominal<br\/>  <b>Day\/Night: <\/b> Night<br\/> <b>Scan: <\/b> 0.6 km<br\/> <b>Track: <\/b> 0.5 km<br\/> <b>FRP: <\/b> 1.65 MW<br\/> <b>Brightness: <\/b> 308.12 K" }, "geometry": { "type": "Point", "coordinates": [ -69.4826, 18.41908, 0.0 ] } },
{ "type": "Feature", "properties": { "Name": "Fire Detection Centroid ", "Description": "<b>Latitude: <\/b> 46.7545<br\/>  <b>Longitude: <\/b> -71.20818<br\/>  <b>Detection Time: <\/b> 2023-08-19 05:34 UTC<br\/>  <b>Sensor: <\/b> NOAA-20 VIIRS<br\/> <b>Confidence: <\/b> Nominal<br\/>  <b>Day\/Night: <\/b> Night<br\/> <b>Scan: <\/b> 0.6 km<br\/> <b>Track: <\/b> 0.7 km<br\/> <b>FRP: <\/b> 2.94 MW<br\/> <b>Brightness: <\/b> 304.59 K" }, "geometry": { "type": "Point", "coordinates": [ -71.20818, 46.7545, 0.0 ] } },
{ "type": "Feature", "properties": { "Name": "Fire Detection Centroid ", "Description": "<b>Latitude: <\/b> 46.75662<br\/>  <b>Longitude: <\/b> -71.20916<br\/>  <b>Detection Time: <\/b> 2023-08-19 05:34 UTC<br\/>  <b>Sensor: <\/b> NOAA-20 VIIRS<br\/> <b>Confidence: <\/b> Nominal<br\/>  <b>Day\/Night: <\/b> Night<br\/> <b>Scan: <\/b> 0.6 km<br\/> <b>Track: <\/b> 0.7 km<br\/> <b>FRP: <\/b> 1.56 MW<br\/> <b>Brightness: <\/b> 305.32 K" }, "geometry": { "type": "Point", "coordinates": [ -71.20916, 46.75662, 0.0 ] } }
]
}
