{
"type": "FeatureCollection",
"crs": { "type": "name", "properties": { "name": "urn:ogc:def:crs:OGC:1.3:CRS84" } },
"features": [
{ "type": "Feature", "properties": { "Name": "Fire Detection Centroid ", "Description": "<b>Latitude: <\/b> 46.52225<br\/>  <b>Longitude: <\/b> -118.1757<br\/>  <b>Detection Time: <\/b> 2023-07-11 11:10 UTC<br\/>  <b>Sensor: <\/b> NOAA-20 VIIRS<br\/> <b>Confidence: <\/b> Nominal<br\/>  <b>Day\/Night: <\/b> Night<br\/> <b>Scan: <\/b> 0.61 km<br\/> <b>Track: <\/b> 0.71 km<br\/> <b>FRP: <\/b> 11.31 MW<br\/> <b>Brightness: <\/b> 299.11 K" }, "geometry": { "type": "Point", "coordinates": [ -118.1757, 46.52225, 0.0 ] } },
{ "type": "Feature", "properties": { "Name": "Fire Detection Centroid ", "Description": "<b>Latitude: <\/b> 47.57338<br\/>  <b>Longitude: <\/b> -122.36792<br\/>  <b>Detection Time: <\/b> 2023-07-11 11:10 UTC<br\/>  <b>Sensor: <\/b> NOAA-20 VIIRS<br\/> <b>Confidence: <\/b> Nominal<br\/>  <b>Day\/Night: <\/b> Night<br\/> <b>Scan: <\/b> 0.38 km<br\/> <b>Track: <\/b> 0.58 km<br\/> <b>FRP: <\/b> 0.47 MW<br\/> <b>Brightness: <\/b> 295.22 K" }, "geometry": { "type": "Point", "coordinates": [ -122.36792, 47.57338, 0.0 ] } },
{ "type": "Feature", "properties": { "Name": "Fire Detection Centroid ", "Description": "<b>Latitude: <\/b> 47.56991<br\/>  <b>Longitude: <\/b> -122.36941<br\/>  <b>Detection Time: <\/b> 2023-07-11 11:10 UTC<br\/>  <b>Sensor: <\/b> NOAA-20 VIIRS<br\/> <b>Confidence: <\/b> Nominal<br\/>  <b>Day\/Night: <\/b> Night<br\/> <b>Scan: <\/b> 0.38 km<br\/> <b>Track: <\/b> 0.58 km<br\/> <b>FRP: <\/b> 0.46 MW<br\/> <b>Brightness: <\/b> 299.15 K" }, "geometry": { "type": "Point", "coordinates": [ -122.36941, 47.56991, 0.0 ] } },
{ "type": "Feature", "properties": { "Name": "Fire Detection Centroid ", "Description": "<b>Latitude: <\/b> 46.5197<br\/>  <b>Longitude: <\/b> -118.16838<br\/>  <b>Detection Time: <\/b> 2023-07-11 11:10 UTC<br\/>  <b>Sensor: <\/b> NOAA-20 VIIRS<br\/> <b>Confidence: <\/b> High<br\/>  <b>Day\/Night: <\/b> Night<br\/> <b>Scan: <\/b> 0.62 km<br\/> <b>Track: <\/b> 0.71 km<br\/> <b>FRP: <\/b> 23.27 MW<br\/> <b>Brightness: <\/b> 367 K" }, "geometry": { "type": "Point", "coordinates": [ -118.16838, 46.5197, 0.0 ] } }
]
}
