{
"type": "FeatureCollection",
"crs": { "type": "name", "properties": { "name": "urn:ogc:def:crs:OGC:1.3:CRS84" } },
"features": [
{ "type": "Feature", "properties": { "Name": "Fire Detection Centroid ", "Description": "<b>Latitude: <\/b> 45.28236<br\/>  <b>Longitude: <\/b> -66.01674<br\/>  <b>Detection Time: <\/b> 2022-07-11 05:09 UTC<br\/>  <b>Sensor: <\/b> NOAA-20 VIIRS<br\/> <b>Confidence: <\/b> Nominal<br\/>  <b>Day\/Night: <\/b> Night<br\/> <b>Scan: <\/b> 0.7 km<br\/> <b>Track: <\/b> 0.8 km<br\/> <b>FRP: <\/b> 1.74 MW<br\/> <b>Brightness: <\/b> 296.73 K" }, "geometry": { "type": "Point", "coordinates": [ -66.01674, 45.28236, 0.0 ] } }
]
}
