{
"type": "FeatureCollection",
"crs": { "type": "name", "properties": { "name": "urn:ogc:def:crs:OGC:1.3:CRS84" } },
"features": [
{ "type": "Feature", "properties": { "Name": "Fire Detection Centroid ", "Description": "<b>Latitude: <\/b> 18.92851<br\/>  <b>Longitude: <\/b> -70.35394<br\/>  <b>Detection Time: <\/b> 2023-08-03 05:42 UTC<br\/>  <b>Sensor: <\/b> NOAA-20 VIIRS<br\/> <b>Confidence: <\/b> Nominal<br\/>  <b>Day\/Night: <\/b> Night<br\/> <b>Scan: <\/b> 0.3 km<br\/> <b>Track: <\/b> 0.6 km<br\/> <b>FRP: <\/b> 1.1 MW<br\/> <b>Brightness: <\/b> 319.05 K" }, "geometry": { "type": "Point", "coordinates": [ -70.35394, 18.92851, 0.0 ] } },
{ "type": "Feature", "properties": { "Name": "Fire Detection Centroid ", "Description": "<b>Latitude: <\/b> 45.28227<br\/>  <b>Longitude: <\/b> -66.01833<br\/>  <b>Detection Time: <\/b> 2023-08-03 05:35 UTC<br\/>  <b>Sensor: <\/b> NOAA-20 VIIRS<br\/> <b>Confidence: <\/b> Nominal<br\/>  <b>Day\/Night: <\/b> Night<br\/> <b>Scan: <\/b> 0.3 km<br\/> <b>Track: <\/b> 0.6 km<br\/> <b>FRP: <\/b> 0.68 MW<br\/> <b>Brightness: <\/b> 297.01 K" }, "geometry": { "type": "Point", "coordinates": [ -66.01833, 45.28227, 0.0 ] } },
{ "type": "Feature", "properties": { "Name": "Fire Detection Centroid ", "Description": "<b>Latitude: <\/b> 45.28206<br\/>  <b>Longitude: <\/b> -66.01371<br\/>  <b>Detection Time: <\/b> 2023-08-03 05:35 UTC<br\/>  <b>Sensor: <\/b> NOAA-20 VIIRS<br\/> <b>Confidence: <\/b> Nominal<br\/>  <b>Day\/Night: <\/b> Night<br\/> <b>Scan: <\/b> 0.3 km<br\/> <b>Track: <\/b> 0.6 km<br\/> <b>FRP: <\/b> 0.68 MW<br\/> <b>Brightness: <\/b> 304.87 K" }, "geometry": { "type": "Point", "coordinates": [ -66.01371, 45.28206, 0.0 ] } },
{ "type": "Feature", "properties": { "Name": "Fire Detection Centroid ", "Description": "<b>Latitude: <\/b> 45.27678<br\/>  <b>Longitude: <\/b> -66.01433<br\/>  <b>Detection Time: <\/b> 2023-08-03 05:35 UTC<br\/>  <b>Sensor: <\/b> NOAA-20 VIIRS<br\/> <b>Confidence: <\/b> Nominal<br\/>  <b>Day\/Night: <\/b> Night<br\/> <b>Scan: <\/b> 0.3 km<br\/> <b>Track: <\/b> 0.6 km<br\/> <b>FRP: <\/b> 0.68 MW<br\/> <b>Brightness: <\/b> 301.74 K" }, "geometry": { "type": "Point", "coordinates": [ -66.01433, 45.27678, 0.0 ] } },
{ "type": "Feature", "properties": { "Name": "Fire Detection Centroid ", "Description": "<b>Latitude: <\/b> 46.58709<br\/>  <b>Longitude: <\/b> -64.93349<br\/>  <b>Detection Time: <\/b> 2023-08-03 05:34 UTC<br\/>  <b>Sensor: <\/b> NOAA-20 VIIRS<br\/> <b>Confidence: <\/b> Nominal<br\/>  <b>Day\/Night: <\/b> Night<br\/> <b>Scan: <\/b> 0.3 km<br\/> <b>Track: <\/b> 0.5 km<br\/> <b>FRP: <\/b> 1.02 MW<br\/> <b>Brightness: <\/b> 315.95 K" }, "geometry": { "type": "Point", "coordinates": [ -64.93349, 46.58709, 0.0 ] } },
{ "type": "Feature", "properties": { "Name": "Fire Detection Centroid ", "Description": "<b>Latitude: <\/b> 46.58709<br\/>  <b>Longitude: <\/b> -64.93349<br\/>  <b>Detection Time: <\/b> 2023-08-03 05:34 UTC<br\/>  <b>Sensor: <\/b> NOAA-20 VIIRS<br\/> <b>Confidence: <\/b> Nominal<br\/>  <b>Day\/Night: <\/b> Night<br\/> <b>Scan: <\/b> 0.3 km<br\/> <b>Track: <\/b> 0.5 km<br\/> <b>FRP: <\/b> 1.02 MW<br\/> <b>Brightness: <\/b> 315.95 K" }, "geometry": { "type": "Point", "coordinates": [ -64.93349, 46.58709, 0.0 ] } },
{ "type": "Feature", "properties": { "Name": "Fire Detection Centroid ", "Description": "<b>Latitude: <\/b> 48.18645<br\/>  <b>Longitude: <\/b> -64.92191<br\/>  <b>Detection Time: <\/b> 2023-08-03 05:34 UTC<br\/>  <b>Sensor: <\/b> NOAA-20 VIIRS<br\/> <b>Confidence: <\/b> Nominal<br\/>  <b>Day\/Night: <\/b> Night<br\/> <b>Scan: <\/b> 0.3 km<br\/> <b>Track: <\/b> 0.6 km<br\/> <b>FRP: <\/b> 1.6 MW<br\/> <b>Brightness: <\/b> 314.65 K" }, "geometry": { "type": "Point", "coordinates": [ -64.92191, 48.18645, 0.0 ] } },
{ "type": "Feature", "properties": { "Name": "Fire Detection Centroid ", "Description": "<b>Latitude: <\/b> 47.52705<br\/>  <b>Longitude: <\/b> -66.64749<br\/>  <b>Detection Time: <\/b> 2023-08-03 05:34 UTC<br\/>  <b>Sensor: <\/b> NOAA-20 VIIRS<br\/> <b>Confidence: <\/b> Nominal<br\/>  <b>Day\/Night: <\/b> Night<br\/> <b>Scan: <\/b> 0.4 km<br\/> <b>Track: <\/b> 0.6 km<br\/> <b>FRP: <\/b> 0.81 MW<br\/> <b>Brightness: <\/b> 295.48 K" }, "geometry": { "type": "Point", "coordinates": [ -66.64749, 47.52705, 0.0 ] } }
]
}
