{
"type": "FeatureCollection",
"crs": { "type": "name", "properties": { "name": "urn:ogc:def:crs:OGC:1.3:CRS84" } },
"features": [
{ "type": "Feature", "properties": { "Name": "Fire Detection Centroid ", "Description": "<b>Latitude: <\/b> 18.46648<br\/>  <b>Longitude: <\/b> -69.10348<br\/>  <b>Detection Time: <\/b> 2023-08-18 06:01 UTC<br\/>  <b>Sensor: <\/b> NOAA-20 VIIRS<br\/> <b>Confidence: <\/b> Nominal<br\/>  <b>Day\/Night: <\/b> Night<br\/> <b>Scan: <\/b> 0.4 km<br\/> <b>Track: <\/b> 0.4 km<br\/> <b>FRP: <\/b> 0.92 MW<br\/> <b>Brightness: <\/b> 306.78 K" }, "geometry": { "type": "Point", "coordinates": [ -69.10348, 18.46648, 0.0 ] } },
{ "type": "Feature", "properties": { "Name": "Fire Detection Centroid ", "Description": "<b>Latitude: <\/b> 22.12549<br\/>  <b>Longitude: <\/b> -78.31068<br\/>  <b>Detection Time: <\/b> 2023-08-18 06:00 UTC<br\/>  <b>Sensor: <\/b> NOAA-20 VIIRS<br\/> <b>Confidence: <\/b> Nominal<br\/>  <b>Day\/Night: <\/b> Night<br\/> <b>Scan: <\/b> 0.6 km<br\/> <b>Track: <\/b> 0.7 km<br\/> <b>FRP: <\/b> 1.36 MW<br\/> <b>Brightness: <\/b> 308.56 K" }, "geometry": { "type": "Point", "coordinates": [ -78.31068, 22.12549, 0.0 ] } },
{ "type": "Feature", "properties": { "Name": "Fire Detection Centroid ", "Description": "<b>Latitude: <\/b> 36.99988<br\/>  <b>Longitude: <\/b> -76.95988<br\/>  <b>Detection Time: <\/b> 2023-08-18 05:56 UTC<br\/>  <b>Sensor: <\/b> NOAA-20 VIIRS<br\/> <b>Confidence: <\/b> Nominal<br\/>  <b>Day\/Night: <\/b> Night<br\/> <b>Scan: <\/b> 0.7 km<br\/> <b>Track: <\/b> 0.7 km<br\/> <b>FRP: <\/b> 2.05 MW<br\/> <b>Brightness: <\/b> 315.12 K" }, "geometry": { "type": "Point", "coordinates": [ -76.95988, 36.99988, 0.0 ] } },
{ "type": "Feature", "properties": { "Name": "Fire Detection Centroid ", "Description": "<b>Latitude: <\/b> 36.99862<br\/>  <b>Longitude: <\/b> -76.96169<br\/>  <b>Detection Time: <\/b> 2023-08-18 05:56 UTC<br\/>  <b>Sensor: <\/b> NOAA-20 VIIRS<br\/> <b>Confidence: <\/b> Nominal<br\/>  <b>Day\/Night: <\/b> Night<br\/> <b>Scan: <\/b> 0.7 km<br\/> <b>Track: <\/b> 0.7 km<br\/> <b>FRP: <\/b> 2 MW<br\/> <b>Brightness: <\/b> 308.12 K" }, "geometry": { "type": "Point", "coordinates": [ -76.96169, 36.99862, 0.0 ] } },
{ "type": "Feature", "properties": { "Name": "Fire Detection Centroid ", "Description": "<b>Latitude: <\/b> 40.71715<br\/>  <b>Longitude: <\/b> -75.40197<br\/>  <b>Detection Time: <\/b> 2023-08-18 05:55 UTC<br\/>  <b>Sensor: <\/b> NOAA-20 VIIRS<br\/> <b>Confidence: <\/b> Nominal<br\/>  <b>Day\/Night: <\/b> Night<br\/> <b>Scan: <\/b> 0.6 km<br\/> <b>Track: <\/b> 0.7 km<br\/> <b>FRP: <\/b> 0.92 MW<br\/> <b>Brightness: <\/b> 298.89 K" }, "geometry": { "type": "Point", "coordinates": [ -75.40197, 40.71715, 0.0 ] } },
{ "type": "Feature", "properties": { "Name": "Fire Detection Centroid ", "Description": "<b>Latitude: <\/b> 45.33879<br\/>  <b>Longitude: <\/b> -73.5271<br\/>  <b>Detection Time: <\/b> 2023-08-18 05:54 UTC<br\/>  <b>Sensor: <\/b> NOAA-20 VIIRS<br\/> <b>Confidence: <\/b> Nominal<br\/>  <b>Day\/Night: <\/b> Night<br\/> <b>Scan: <\/b> 0.5 km<br\/> <b>Track: <\/b> 0.6 km<br\/> <b>FRP: <\/b> 0.54 MW<br\/> <b>Brightness: <\/b> 299.09 K" }, "geometry": { "type": "Point", "coordinates": [ -73.5271, 45.33879, 0.0 ] } }
]
}
