{
"type": "FeatureCollection",
"crs": { "type": "name", "properties": { "name": "urn:ogc:def:crs:OGC:1.3:CRS84" } },
"features": [
{ "type": "Feature", "properties": { "Name": "Fire Detection Centroid ", "Description": "<b>Latitude: <\/b> 19.40359<br\/>  <b>Longitude: <\/b> -155.28194<br\/>  <b>Detection Time: <\/b> 2023-09-25 00:05 UTC<br\/>  <b>Sensor: <\/b> NOAA-20 VIIRS<br\/> <b>Confidence: <\/b> Nominal<br\/>  <b>Day\/Night: <\/b> Day<br\/> <b>Scan: <\/b> 0.54 km<br\/> <b>Track: <\/b> 0.51 km<br\/> <b>FRP: <\/b> 9 MW<br\/> <b>Brightness: <\/b> 335.27 K" }, "geometry": { "type": "Point", "coordinates": [ -155.28194, 19.40359, 0.0 ] } },
{ "type": "Feature", "properties": { "Name": "Fire Detection Centroid ", "Description": "<b>Latitude: <\/b> 19.40943<br\/>  <b>Longitude: <\/b> -155.27222<br\/>  <b>Detection Time: <\/b> 2023-09-25 00:05 UTC<br\/>  <b>Sensor: <\/b> NOAA-20 VIIRS<br\/> <b>Confidence: <\/b> Low<br\/>  <b>Day\/Night: <\/b> Day<br\/> <b>Scan: <\/b> 0.54 km<br\/> <b>Track: <\/b> 0.51 km<br\/> <b>FRP: <\/b> 13.77 MW<br\/> <b>Brightness: <\/b> 333.51 K" }, "geometry": { "type": "Point", "coordinates": [ -155.27222, 19.40943, 0.0 ] } },
{ "type": "Feature", "properties": { "Name": "Fire Detection Centroid ", "Description": "<b>Latitude: <\/b> 19.40824<br\/>  <b>Longitude: <\/b> -155.28255<br\/>  <b>Detection Time: <\/b> 2023-09-25 00:05 UTC<br\/>  <b>Sensor: <\/b> NOAA-20 VIIRS<br\/> <b>Confidence: <\/b> Nominal<br\/>  <b>Day\/Night: <\/b> Day<br\/> <b>Scan: <\/b> 0.54 km<br\/> <b>Track: <\/b> 0.51 km<br\/> <b>FRP: <\/b> 9 MW<br\/> <b>Brightness: <\/b> 344.52 K" }, "geometry": { "type": "Point", "coordinates": [ -155.28255, 19.40824, 0.0 ] } },
{ "type": "Feature", "properties": { "Name": "Fire Detection Centroid ", "Description": "<b>Latitude: <\/b> 19.40884<br\/>  <b>Longitude: <\/b> -155.27736<br\/>  <b>Detection Time: <\/b> 2023-09-25 00:05 UTC<br\/>  <b>Sensor: <\/b> NOAA-20 VIIRS<br\/> <b>Confidence: <\/b> Nominal<br\/>  <b>Day\/Night: <\/b> Day<br\/> <b>Scan: <\/b> 0.54 km<br\/> <b>Track: <\/b> 0.51 km<br\/> <b>FRP: <\/b> 9 MW<br\/> <b>Brightness: <\/b> 344.08 K" }, "geometry": { "type": "Point", "coordinates": [ -155.27736, 19.40884, 0.0 ] } }
]
}
