{
"type": "FeatureCollection",
"crs": { "type": "name", "properties": { "name": "urn:ogc:def:crs:OGC:1.3:CRS84" } },
"features": [
{ "type": "Feature", "properties": { "Name": "Fire Detection Centroid ", "Description": "<b>Latitude: <\/b> 19.41425<br\/>  <b>Longitude: <\/b> -155.28598<br\/>  <b>Detection Time: <\/b> 2022-11-20 12:25 UTC<br\/>  <b>Sensor: <\/b> NOAA-20 VIIRS<br\/> <b>Confidence: <\/b> Nominal<br\/>  <b>Day\/Night: <\/b> Night<br\/> <b>Scan: <\/b> 0.51 km<br\/> <b>Track: <\/b> 0.49 km<br\/> <b>FRP: <\/b> 1.12 MW<br\/> <b>Brightness: <\/b> 304.88 K" }, "geometry": { "type": "Point", "coordinates": [ -155.28598, 19.41425, 0.0 ] } },
{ "type": "Feature", "properties": { "Name": "Fire Detection Centroid ", "Description": "<b>Latitude: <\/b> 19.41878<br\/>  <b>Longitude: <\/b> -155.28526<br\/>  <b>Detection Time: <\/b> 2022-11-20 12:25 UTC<br\/>  <b>Sensor: <\/b> NOAA-20 VIIRS<br\/> <b>Confidence: <\/b> Nominal<br\/>  <b>Day\/Night: <\/b> Night<br\/> <b>Scan: <\/b> 0.51 km<br\/> <b>Track: <\/b> 0.49 km<br\/> <b>FRP: <\/b> 1.12 MW<br\/> <b>Brightness: <\/b> 295.92 K" }, "geometry": { "type": "Point", "coordinates": [ -155.28526, 19.41878, 0.0 ] } },
{ "type": "Feature", "properties": { "Name": "Fire Detection Centroid ", "Description": "<b>Latitude: <\/b> 19.40427<br\/>  <b>Longitude: <\/b> -155.28275<br\/>  <b>Detection Time: <\/b> 2022-11-20 12:25 UTC<br\/>  <b>Sensor: <\/b> NOAA-20 VIIRS<br\/> <b>Confidence: <\/b> Nominal<br\/>  <b>Day\/Night: <\/b> Night<br\/> <b>Scan: <\/b> 0.51 km<br\/> <b>Track: <\/b> 0.5 km<br\/> <b>FRP: <\/b> 26.16 MW<br\/> <b>Brightness: <\/b> 305.23 K" }, "geometry": { "type": "Point", "coordinates": [ -155.28275, 19.40427, 0.0 ] } },
{ "type": "Feature", "properties": { "Name": "Fire Detection Centroid ", "Description": "<b>Latitude: <\/b> 19.40524<br\/>  <b>Longitude: <\/b> -155.28757<br\/>  <b>Detection Time: <\/b> 2022-11-20 12:25 UTC<br\/>  <b>Sensor: <\/b> NOAA-20 VIIRS<br\/> <b>Confidence: <\/b> Nominal<br\/>  <b>Day\/Night: <\/b> Night<br\/> <b>Scan: <\/b> 0.51 km<br\/> <b>Track: <\/b> 0.49 km<br\/> <b>FRP: <\/b> 26.16 MW<br\/> <b>Brightness: <\/b> 322.82 K" }, "geometry": { "type": "Point", "coordinates": [ -155.28757, 19.40524, 0.0 ] } },
{ "type": "Feature", "properties": { "Name": "Fire Detection Centroid ", "Description": "<b>Latitude: <\/b> 19.40626<br\/>  <b>Longitude: <\/b> -155.29269<br\/>  <b>Detection Time: <\/b> 2022-11-20 12:25 UTC<br\/>  <b>Sensor: <\/b> NOAA-20 VIIRS<br\/> <b>Confidence: <\/b> Nominal<br\/>  <b>Day\/Night: <\/b> Night<br\/> <b>Scan: <\/b> 0.51 km<br\/> <b>Track: <\/b> 0.49 km<br\/> <b>FRP: <\/b> 25.45 MW<br\/> <b>Brightness: <\/b> 337.76 K" }, "geometry": { "type": "Point", "coordinates": [ -155.29269, 19.40626, 0.0 ] } },
{ "type": "Feature", "properties": { "Name": "Fire Detection Centroid ", "Description": "<b>Latitude: <\/b> 19.40876<br\/>  <b>Longitude: <\/b> -155.28183<br\/>  <b>Detection Time: <\/b> 2022-11-20 12:25 UTC<br\/>  <b>Sensor: <\/b> NOAA-20 VIIRS<br\/> <b>Confidence: <\/b> Nominal<br\/>  <b>Day\/Night: <\/b> Night<br\/> <b>Scan: <\/b> 0.51 km<br\/> <b>Track: <\/b> 0.5 km<br\/> <b>FRP: <\/b> 26.16 MW<br\/> <b>Brightness: <\/b> 309.48 K" }, "geometry": { "type": "Point", "coordinates": [ -155.28183, 19.40876, 0.0 ] } },
{ "type": "Feature", "properties": { "Name": "Fire Detection Centroid ", "Description": "<b>Latitude: <\/b> 19.41075<br\/>  <b>Longitude: <\/b> -155.29184<br\/>  <b>Detection Time: <\/b> 2022-11-20 12:25 UTC<br\/>  <b>Sensor: <\/b> NOAA-20 VIIRS<br\/> <b>Confidence: <\/b> Nominal<br\/>  <b>Day\/Night: <\/b> Night<br\/> <b>Scan: <\/b> 0.51 km<br\/> <b>Track: <\/b> 0.49 km<br\/> <b>FRP: <\/b> 25.45 MW<br\/> <b>Brightness: <\/b> 316.51 K" }, "geometry": { "type": "Point", "coordinates": [ -155.29184, 19.41075, 0.0 ] } },
{ "type": "Feature", "properties": { "Name": "Fire Detection Centroid ", "Description": "<b>Latitude: <\/b> 19.40974<br\/>  <b>Longitude: <\/b> -155.28676<br\/>  <b>Detection Time: <\/b> 2022-11-20 12:25 UTC<br\/>  <b>Sensor: <\/b> NOAA-20 VIIRS<br\/> <b>Confidence: <\/b> Nominal<br\/>  <b>Day\/Night: <\/b> Night<br\/> <b>Scan: <\/b> 0.51 km<br\/> <b>Track: <\/b> 0.49 km<br\/> <b>FRP: <\/b> 26.16 MW<br\/> <b>Brightness: <\/b> 342.32 K" }, "geometry": { "type": "Point", "coordinates": [ -155.28676, 19.40974, 0.0 ] } },
{ "type": "Feature", "properties": { "Name": "Fire Detection Centroid ", "Description": "<b>Latitude: <\/b> 19.41324<br\/>  <b>Longitude: <\/b> -155.28091<br\/>  <b>Detection Time: <\/b> 2022-11-20 12:25 UTC<br\/>  <b>Sensor: <\/b> NOAA-20 VIIRS<br\/> <b>Confidence: <\/b> Nominal<br\/>  <b>Day\/Night: <\/b> Night<br\/> <b>Scan: <\/b> 0.51 km<br\/> <b>Track: <\/b> 0.5 km<br\/> <b>FRP: <\/b> 1.12 MW<br\/> <b>Brightness: <\/b> 300.6 K" }, "geometry": { "type": "Point", "coordinates": [ -155.28091, 19.41324, 0.0 ] } }
]
}
