{
"type": "FeatureCollection",
"crs": { "type": "name", "properties": { "name": "urn:ogc:def:crs:OGC:1.3:CRS84" } },
"features": [
{ "type": "Feature", "properties": { "Name": "Fire Detection Centroid ", "Description": "<b>Latitude: <\/b> 19.40452<br\/>  <b>Longitude: <\/b> -155.28642<br\/>  <b>Detection Time: <\/b> 2023-02-28 00:22 UTC<br\/>  <b>Sensor: <\/b> NOAA-20 VIIRS<br\/> <b>Confidence: <\/b> High<br\/>  <b>Day\/Night: <\/b> Day<br\/> <b>Scan: <\/b> 0.55 km<br\/> <b>Track: <\/b> 0.68 km<br\/> <b>FRP: <\/b> 23.06 MW<br\/> <b>Brightness: <\/b> 367 K" }, "geometry": { "type": "Point", "coordinates": [ -155.28642, 19.40452, 0.0 ] } },
{ "type": "Feature", "properties": { "Name": "Fire Detection Centroid ", "Description": "<b>Latitude: <\/b> 19.40629<br\/>  <b>Longitude: <\/b> -155.2907<br\/>  <b>Detection Time: <\/b> 2023-02-28 00:22 UTC<br\/>  <b>Sensor: <\/b> NOAA-20 VIIRS<br\/> <b>Confidence: <\/b> Nominal<br\/>  <b>Day\/Night: <\/b> Day<br\/> <b>Scan: <\/b> 0.55 km<br\/> <b>Track: <\/b> 0.68 km<br\/> <b>FRP: <\/b> 15.28 MW<br\/> <b>Brightness: <\/b> 347.64 K" }, "geometry": { "type": "Point", "coordinates": [ -155.2907, 19.40629, 0.0 ] } },
{ "type": "Feature", "properties": { "Name": "Fire Detection Centroid ", "Description": "<b>Latitude: <\/b> 19.40681<br\/>  <b>Longitude: <\/b> -155.28503<br\/>  <b>Detection Time: <\/b> 2023-02-28 00:22 UTC<br\/>  <b>Sensor: <\/b> NOAA-20 VIIRS<br\/> <b>Confidence: <\/b> Nominal<br\/>  <b>Day\/Night: <\/b> Day<br\/> <b>Scan: <\/b> 0.55 km<br\/> <b>Track: <\/b> 0.68 km<br\/> <b>FRP: <\/b> 18.61 MW<br\/> <b>Brightness: <\/b> 342.64 K" }, "geometry": { "type": "Point", "coordinates": [ -155.28503, 19.40681, 0.0 ] } }
]
}
