{
"type": "FeatureCollection",
"crs": { "type": "name", "properties": { "name": "urn:ogc:def:crs:OGC:1.3:CRS84" } },
"features": [
{ "type": "Feature", "properties": { "Name": "Fire Detection Centroid ", "Description": "<b>Latitude: <\/b> 18.50815<br\/>  <b>Longitude: <\/b> -69.3429<br\/>  <b>Detection Time: <\/b> 2023-09-15 05:36 UTC<br\/>  <b>Sensor: <\/b> NOAA-20 VIIRS<br\/> <b>Confidence: <\/b> Nominal<br\/>  <b>Day\/Night: <\/b> Night<br\/> <b>Scan: <\/b> 0.4 km<br\/> <b>Track: <\/b> 0.6 km<br\/> <b>FRP: <\/b> 0.38 MW<br\/> <b>Brightness: <\/b> 301.07 K" }, "geometry": { "type": "Point", "coordinates": [ -69.3429, 18.50815, 0.0 ] } },
{ "type": "Feature", "properties": { "Name": "Fire Detection Centroid ", "Description": "<b>Latitude: <\/b> 48.18793<br\/>  <b>Longitude: <\/b> -64.92131<br\/>  <b>Detection Time: <\/b> 2023-09-15 05:27 UTC<br\/>  <b>Sensor: <\/b> NOAA-20 VIIRS<br\/> <b>Confidence: <\/b> Nominal<br\/>  <b>Day\/Night: <\/b> Night<br\/> <b>Scan: <\/b> 0.4 km<br\/> <b>Track: <\/b> 0.6 km<br\/> <b>FRP: <\/b> 1.02 MW<br\/> <b>Brightness: <\/b> 304.23 K" }, "geometry": { "type": "Point", "coordinates": [ -64.92131, 48.18793, 0.0 ] } }
]
}
