{
"type": "FeatureCollection",
"crs": { "type": "name", "properties": { "name": "urn:ogc:def:crs:OGC:1.3:CRS84" } },
"features": [
{ "type": "Feature", "properties": { "Name": "Fire Detection Centroid ", "Description": "<b>Latitude: <\/b> 18.57508<br\/>  <b>Longitude: <\/b> -72.29492<br\/>  <b>Detection Time: <\/b> 2023-12-25 05:42 UTC<br\/>  <b>Sensor: <\/b> NOAA-20 VIIRS<br\/> <b>Confidence: <\/b> Nominal<br\/>  <b>Day\/Night: <\/b> Night<br\/> <b>Scan: <\/b> 0.5 km<br\/> <b>Track: <\/b> 0.6 km<br\/> <b>FRP: <\/b> 1.77 MW<br\/> <b>Brightness: <\/b> 301.25 K" }, "geometry": { "type": "Point", "coordinates": [ -72.29492, 18.57508, 0.0 ] } },
{ "type": "Feature", "properties": { "Name": "Fire Detection Centroid ", "Description": "<b>Latitude: <\/b> 18.57464<br\/>  <b>Longitude: <\/b> -72.29044<br\/>  <b>Detection Time: <\/b> 2023-12-25 05:42 UTC<br\/>  <b>Sensor: <\/b> NOAA-20 VIIRS<br\/> <b>Confidence: <\/b> Nominal<br\/>  <b>Day\/Night: <\/b> Night<br\/> <b>Scan: <\/b> 0.5 km<br\/> <b>Track: <\/b> 0.6 km<br\/> <b>FRP: <\/b> 1.77 MW<br\/> <b>Brightness: <\/b> 323.47 K" }, "geometry": { "type": "Point", "coordinates": [ -72.29044, 18.57464, 0.0 ] } },
{ "type": "Feature", "properties": { "Name": "Fire Detection Centroid ", "Description": "<b>Latitude: <\/b> 44.88384<br\/>  <b>Longitude: <\/b> -67.09896<br\/>  <b>Detection Time: <\/b> 2023-12-25 05:34 UTC<br\/>  <b>Sensor: <\/b> NOAA-20 VIIRS<br\/> <b>Confidence: <\/b> Nominal<br\/>  <b>Day\/Night: <\/b> Night<br\/> <b>Scan: <\/b> 0.4 km<br\/> <b>Track: <\/b> 0.6 km<br\/> <b>FRP: <\/b> 1.32 MW<br\/> <b>Brightness: <\/b> 309.13 K" }, "geometry": { "type": "Point", "coordinates": [ -67.09896, 44.88384, 0.0 ] } }
]
}
