{
"type": "FeatureCollection",
"crs": { "type": "name", "properties": { "name": "urn:ogc:def:crs:OGC:1.3:CRS84" } },
"features": [
{ "type": "Feature", "properties": { "Name": "Fire Detection Centroid ", "Description": "<b>Latitude: <\/b> 18.92818<br\/>  <b>Longitude: <\/b> -70.36088<br\/>  <b>Detection Time: <\/b> 2022-07-26 05:35 UTC<br\/>  <b>Sensor: <\/b> NOAA-20 VIIRS<br\/> <b>Confidence: <\/b> Nominal<br\/>  <b>Day\/Night: <\/b> Night<br\/> <b>Scan: <\/b> 0.5 km<br\/> <b>Track: <\/b> 0.6 km<br\/> <b>FRP: <\/b> 0.89 MW<br\/> <b>Brightness: <\/b> 299.61 K" }, "geometry": { "type": "Point", "coordinates": [ -70.36088, 18.92818, 0.0 ] } },
{ "type": "Feature", "properties": { "Name": "Fire Detection Centroid ", "Description": "<b>Latitude: <\/b> 18.92865<br\/>  <b>Longitude: <\/b> -70.36273<br\/>  <b>Detection Time: <\/b> 2022-07-26 05:35 UTC<br\/>  <b>Sensor: <\/b> NOAA-20 VIIRS<br\/> <b>Confidence: <\/b> Nominal<br\/>  <b>Day\/Night: <\/b> Night<br\/> <b>Scan: <\/b> 0.5 km<br\/> <b>Track: <\/b> 0.6 km<br\/> <b>FRP: <\/b> 2.39 MW<br\/> <b>Brightness: <\/b> 301.78 K" }, "geometry": { "type": "Point", "coordinates": [ -70.36273, 18.92865, 0.0 ] } },
{ "type": "Feature", "properties": { "Name": "Fire Detection Centroid ", "Description": "<b>Latitude: <\/b> 18.92857<br\/>  <b>Longitude: <\/b> -70.36498<br\/>  <b>Detection Time: <\/b> 2022-07-26 05:35 UTC<br\/>  <b>Sensor: <\/b> NOAA-20 VIIRS<br\/> <b>Confidence: <\/b> Nominal<br\/>  <b>Day\/Night: <\/b> Night<br\/> <b>Scan: <\/b> 0.5 km<br\/> <b>Track: <\/b> 0.6 km<br\/> <b>FRP: <\/b> 0.89 MW<br\/> <b>Brightness: <\/b> 300.03 K" }, "geometry": { "type": "Point", "coordinates": [ -70.36498, 18.92857, 0.0 ] } }
]
}
