{
"type": "FeatureCollection",
"crs": { "type": "name", "properties": { "name": "urn:ogc:def:crs:OGC:1.3:CRS84" } },
"features": [
{ "type": "Feature", "properties": { "Name": "Fire Detection Centroid ", "Description": "<b>Latitude: <\/b> 38.35232<br\/>  <b>Longitude: <\/b> -76.76948<br\/>  <b>Detection Time: <\/b> 2023-02-08 16:58 UTC<br\/>  <b>Sensor: <\/b> NOAA-20 VIIRS<br\/> <b>Confidence: <\/b> Nominal<br\/>  <b>Day\/Night: <\/b> Day<br\/> <b>Scan: <\/b> 0.7 km<br\/> <b>Track: <\/b> 0.7 km<br\/> <b>FRP: <\/b> 3.25 MW<br\/> <b>Brightness: <\/b> 326.92 K" }, "geometry": { "type": "Point", "coordinates": [ -76.76948, 38.35232, 0.0 ] } },
{ "type": "Feature", "properties": { "Name": "Fire Detection Centroid ", "Description": "<b>Latitude: <\/b> 39.27996<br\/>  <b>Longitude: <\/b> -76.18201<br\/>  <b>Detection Time: <\/b> 2023-02-08 16:58 UTC<br\/>  <b>Sensor: <\/b> NOAA-20 VIIRS<br\/> <b>Confidence: <\/b> Nominal<br\/>  <b>Day\/Night: <\/b> Day<br\/> <b>Scan: <\/b> 0.6 km<br\/> <b>Track: <\/b> 0.7 km<br\/> <b>FRP: <\/b> 3.51 MW<br\/> <b>Brightness: <\/b> 329.96 K" }, "geometry": { "type": "Point", "coordinates": [ -76.18201, 39.27996, 0.0 ] } },
{ "type": "Feature", "properties": { "Name": "Fire Detection Centroid ", "Description": "<b>Latitude: <\/b> 39.8886<br\/>  <b>Longitude: <\/b> -76.45811<br\/>  <b>Detection Time: <\/b> 2023-02-08 16:58 UTC<br\/>  <b>Sensor: <\/b> NOAA-20 VIIRS<br\/> <b>Confidence: <\/b> Nominal<br\/>  <b>Day\/Night: <\/b> Day<br\/> <b>Scan: <\/b> 0.6 km<br\/> <b>Track: <\/b> 0.7 km<br\/> <b>FRP: <\/b> 2.83 MW<br\/> <b>Brightness: <\/b> 327.04 K" }, "geometry": { "type": "Point", "coordinates": [ -76.45811, 39.8886, 0.0 ] } }
]
}
