{
"type": "FeatureCollection",
"crs": { "type": "name", "properties": { "name": "urn:ogc:def:crs:OGC:1.3:CRS84" } },
"features": [
{ "type": "Feature", "properties": { "Name": "Fire Detection Centroid ", "Description": "<b>Latitude: <\/b> 18.92672<br\/>  <b>Longitude: <\/b> -70.35519<br\/>  <b>Detection Time: <\/b> 2023-11-01 05:54 UTC<br\/>  <b>Sensor: <\/b> NOAA-20 VIIRS<br\/> <b>Confidence: <\/b> Nominal<br\/>  <b>Day\/Night: <\/b> Night<br\/> <b>Scan: <\/b> 0.4 km<br\/> <b>Track: <\/b> 0.5 km<br\/> <b>FRP: <\/b> 5.42 MW<br\/> <b>Brightness: <\/b> 331.15 K" }, "geometry": { "type": "Point", "coordinates": [ -70.35519, 18.92672, 0.0 ] } },
{ "type": "Feature", "properties": { "Name": "Fire Detection Centroid ", "Description": "<b>Latitude: <\/b> 18.93101<br\/>  <b>Longitude: <\/b> -70.35485<br\/>  <b>Detection Time: <\/b> 2023-11-01 05:54 UTC<br\/>  <b>Sensor: <\/b> NOAA-20 VIIRS<br\/> <b>Confidence: <\/b> Nominal<br\/>  <b>Day\/Night: <\/b> Night<br\/> <b>Scan: <\/b> 0.4 km<br\/> <b>Track: <\/b> 0.5 km<br\/> <b>FRP: <\/b> 2.34 MW<br\/> <b>Brightness: <\/b> 339.82 K" }, "geometry": { "type": "Point", "coordinates": [ -70.35485, 18.93101, 0.0 ] } },
{ "type": "Feature", "properties": { "Name": "Fire Detection Centroid ", "Description": "<b>Latitude: <\/b> 18.93049<br\/>  <b>Longitude: <\/b> -70.35052<br\/>  <b>Detection Time: <\/b> 2023-11-01 05:54 UTC<br\/>  <b>Sensor: <\/b> NOAA-20 VIIRS<br\/> <b>Confidence: <\/b> Nominal<br\/>  <b>Day\/Night: <\/b> Night<br\/> <b>Scan: <\/b> 0.4 km<br\/> <b>Track: <\/b> 0.5 km<br\/> <b>FRP: <\/b> 2.34 MW<br\/> <b>Brightness: <\/b> 299.16 K" }, "geometry": { "type": "Point", "coordinates": [ -70.35052, 18.93049, 0.0 ] } },
{ "type": "Feature", "properties": { "Name": "Fire Detection Centroid ", "Description": "<b>Latitude: <\/b> 18.00838<br\/>  <b>Longitude: <\/b> -66.65572<br\/>  <b>Detection Time: <\/b> 2023-11-01 05:54 UTC<br\/>  <b>Sensor: <\/b> NOAA-20 VIIRS<br\/> <b>Confidence: <\/b> Nominal<br\/>  <b>Day\/Night: <\/b> Night<br\/> <b>Scan: <\/b> 0.4 km<br\/> <b>Track: <\/b> 0.4 km<br\/> <b>FRP: <\/b> 0.48 MW<br\/> <b>Brightness: <\/b> 304.62 K" }, "geometry": { "type": "Point", "coordinates": [ -66.65572, 18.00838, 0.0 ] } },
{ "type": "Feature", "properties": { "Name": "Fire Detection Centroid ", "Description": "<b>Latitude: <\/b> 45.84119<br\/>  <b>Longitude: <\/b> -73.25166<br\/>  <b>Detection Time: <\/b> 2023-11-01 05:46 UTC<br\/>  <b>Sensor: <\/b> NOAA-20 VIIRS<br\/> <b>Confidence: <\/b> Nominal<br\/>  <b>Day\/Night: <\/b> Night<br\/> <b>Scan: <\/b> 0.6 km<br\/> <b>Track: <\/b> 0.7 km<br\/> <b>FRP: <\/b> 1.47 MW<br\/> <b>Brightness: <\/b> 299.63 K" }, "geometry": { "type": "Point", "coordinates": [ -73.25166, 45.84119, 0.0 ] } },
{ "type": "Feature", "properties": { "Name": "Fire Detection Centroid ", "Description": "<b>Latitude: <\/b> 48.18704<br\/>  <b>Longitude: <\/b> -64.91889<br\/>  <b>Detection Time: <\/b> 2023-11-01 05:45 UTC<br\/>  <b>Sensor: <\/b> NOAA-20 VIIRS<br\/> <b>Confidence: <\/b> Nominal<br\/>  <b>Day\/Night: <\/b> Night<br\/> <b>Scan: <\/b> 0.5 km<br\/> <b>Track: <\/b> 0.5 km<br\/> <b>FRP: <\/b> 1.53 MW<br\/> <b>Brightness: <\/b> 296.65 K" }, "geometry": { "type": "Point", "coordinates": [ -64.91889, 48.18704, 0.0 ] } },
{ "type": "Feature", "properties": { "Name": "Fire Detection Centroid ", "Description": "<b>Latitude: <\/b> 48.18873<br\/>  <b>Longitude: <\/b> -64.91899<br\/>  <b>Detection Time: <\/b> 2023-11-01 05:45 UTC<br\/>  <b>Sensor: <\/b> NOAA-20 VIIRS<br\/> <b>Confidence: <\/b> Nominal<br\/>  <b>Day\/Night: <\/b> Night<br\/> <b>Scan: <\/b> 0.5 km<br\/> <b>Track: <\/b> 0.5 km<br\/> <b>FRP: <\/b> 0.76 MW<br\/> <b>Brightness: <\/b> 303.37 K" }, "geometry": { "type": "Point", "coordinates": [ -64.91899, 48.18873, 0.0 ] } }
]
}
