{
"type": "FeatureCollection",
"crs": { "type": "name", "properties": { "name": "urn:ogc:def:crs:OGC:1.3:CRS84" } },
"features": [
{ "type": "Feature", "properties": { "Name": "Fire Detection Centroid ", "Description": "<b>Latitude: <\/b> 19.41248<br\/>  <b>Longitude: <\/b> -155.27374<br\/>  <b>Detection Time: <\/b> 2023-10-09 11:30 UTC<br\/>  <b>Sensor: <\/b> NOAA-20 VIIRS<br\/> <b>Confidence: <\/b> Nominal<br\/>  <b>Day\/Night: <\/b> Night<br\/> <b>Scan: <\/b> 0.51 km<br\/> <b>Track: <\/b> 0.49 km<br\/> <b>FRP: <\/b> 3.74 MW<br\/> <b>Brightness: <\/b> 307.63 K" }, "geometry": { "type": "Point", "coordinates": [ -155.27374, 19.41248, 0.0 ] } },
{ "type": "Feature", "properties": { "Name": "Fire Detection Centroid ", "Description": "<b>Latitude: <\/b> 19.40455<br\/>  <b>Longitude: <\/b> -155.28458<br\/>  <b>Detection Time: <\/b> 2023-10-09 11:30 UTC<br\/>  <b>Sensor: <\/b> NOAA-20 VIIRS<br\/> <b>Confidence: <\/b> Nominal<br\/>  <b>Day\/Night: <\/b> Night<br\/> <b>Scan: <\/b> 0.51 km<br\/> <b>Track: <\/b> 0.49 km<br\/> <b>FRP: <\/b> 2.91 MW<br\/> <b>Brightness: <\/b> 307.45 K" }, "geometry": { "type": "Point", "coordinates": [ -155.28458, 19.40455, 0.0 ] } },
{ "type": "Feature", "properties": { "Name": "Fire Detection Centroid ", "Description": "<b>Latitude: <\/b> 19.40796<br\/>  <b>Longitude: <\/b> -155.27434<br\/>  <b>Detection Time: <\/b> 2023-10-09 11:30 UTC<br\/>  <b>Sensor: <\/b> NOAA-20 VIIRS<br\/> <b>Confidence: <\/b> Nominal<br\/>  <b>Day\/Night: <\/b> Night<br\/> <b>Scan: <\/b> 0.51 km<br\/> <b>Track: <\/b> 0.49 km<br\/> <b>FRP: <\/b> 3.48 MW<br\/> <b>Brightness: <\/b> 307.08 K" }, "geometry": { "type": "Point", "coordinates": [ -155.27434, 19.40796, 0.0 ] } },
{ "type": "Feature", "properties": { "Name": "Fire Detection Centroid ", "Description": "<b>Latitude: <\/b> 19.40852<br\/>  <b>Longitude: <\/b> -155.27916<br\/>  <b>Detection Time: <\/b> 2023-10-09 11:30 UTC<br\/>  <b>Sensor: <\/b> NOAA-20 VIIRS<br\/> <b>Confidence: <\/b> Nominal<br\/>  <b>Day\/Night: <\/b> Night<br\/> <b>Scan: <\/b> 0.51 km<br\/> <b>Track: <\/b> 0.49 km<br\/> <b>FRP: <\/b> 3.48 MW<br\/> <b>Brightness: <\/b> 313.39 K" }, "geometry": { "type": "Point", "coordinates": [ -155.27916, 19.40852, 0.0 ] } },
{ "type": "Feature", "properties": { "Name": "Fire Detection Centroid ", "Description": "<b>Latitude: <\/b> 19.40906<br\/>  <b>Longitude: <\/b> -155.28386<br\/>  <b>Detection Time: <\/b> 2023-10-09 11:30 UTC<br\/>  <b>Sensor: <\/b> NOAA-20 VIIRS<br\/> <b>Confidence: <\/b> Nominal<br\/>  <b>Day\/Night: <\/b> Night<br\/> <b>Scan: <\/b> 0.51 km<br\/> <b>Track: <\/b> 0.49 km<br\/> <b>FRP: <\/b> 2.91 MW<br\/> <b>Brightness: <\/b> 312.66 K" }, "geometry": { "type": "Point", "coordinates": [ -155.28386, 19.40906, 0.0 ] } },
{ "type": "Feature", "properties": { "Name": "Fire Detection Centroid ", "Description": "<b>Latitude: <\/b> 19.4096<br\/>  <b>Longitude: <\/b> -155.2885<br\/>  <b>Detection Time: <\/b> 2023-10-09 11:30 UTC<br\/>  <b>Sensor: <\/b> NOAA-20 VIIRS<br\/> <b>Confidence: <\/b> Nominal<br\/>  <b>Day\/Night: <\/b> Night<br\/> <b>Scan: <\/b> 0.51 km<br\/> <b>Track: <\/b> 0.49 km<br\/> <b>FRP: <\/b> 2.91 MW<br\/> <b>Brightness: <\/b> 310.51 K" }, "geometry": { "type": "Point", "coordinates": [ -155.2885, 19.4096, 0.0 ] } },
{ "type": "Feature", "properties": { "Name": "Fire Detection Centroid ", "Description": "<b>Latitude: <\/b> 19.41357<br\/>  <b>Longitude: <\/b> -155.28313<br\/>  <b>Detection Time: <\/b> 2023-10-09 11:30 UTC<br\/>  <b>Sensor: <\/b> NOAA-20 VIIRS<br\/> <b>Confidence: <\/b> Nominal<br\/>  <b>Day\/Night: <\/b> Night<br\/> <b>Scan: <\/b> 0.51 km<br\/> <b>Track: <\/b> 0.49 km<br\/> <b>FRP: <\/b> 5.39 MW<br\/> <b>Brightness: <\/b> 315.52 K" }, "geometry": { "type": "Point", "coordinates": [ -155.28313, 19.41357, 0.0 ] } },
{ "type": "Feature", "properties": { "Name": "Fire Detection Centroid ", "Description": "<b>Latitude: <\/b> 19.41303<br\/>  <b>Longitude: <\/b> -155.2785<br\/>  <b>Detection Time: <\/b> 2023-10-09 11:30 UTC<br\/>  <b>Sensor: <\/b> NOAA-20 VIIRS<br\/> <b>Confidence: <\/b> Nominal<br\/>  <b>Day\/Night: <\/b> Night<br\/> <b>Scan: <\/b> 0.51 km<br\/> <b>Track: <\/b> 0.49 km<br\/> <b>FRP: <\/b> 3.74 MW<br\/> <b>Brightness: <\/b> 310.5 K" }, "geometry": { "type": "Point", "coordinates": [ -155.2785, 19.41303, 0.0 ] } }
]
}
