{
"type": "FeatureCollection",
"crs": { "type": "name", "properties": { "name": "urn:ogc:def:crs:OGC:1.3:CRS84" } },
"features": [
{ "type": "Feature", "properties": { "Name": "Fire Detection Centroid ", "Description": "<b>Latitude: <\/b> 40.39268<br\/>  <b>Longitude: <\/b> -79.85362<br\/>  <b>Detection Time: <\/b> 2023-12-08 17:18 UTC<br\/>  <b>Sensor: <\/b> NOAA-20 VIIRS<br\/> <b>Confidence: <\/b> Nominal<br\/>  <b>Day\/Night: <\/b> Day<br\/> <b>Scan: <\/b> 0.5 km<br\/> <b>Track: <\/b> 0.6 km<br\/> <b>FRP: <\/b> 4.76 MW<br\/> <b>Brightness: <\/b> 332.55 K" }, "geometry": { "type": "Point", "coordinates": [ -79.85362, 40.39268, 0.0 ] } },
{ "type": "Feature", "properties": { "Name": "Fire Detection Centroid ", "Description": "<b>Latitude: <\/b> 39.46602<br\/>  <b>Longitude: <\/b> -77.74875<br\/>  <b>Detection Time: <\/b> 2023-12-08 17:17 UTC<br\/>  <b>Sensor: <\/b> NOAA-20 VIIRS<br\/> <b>Confidence: <\/b> Nominal<br\/>  <b>Day\/Night: <\/b> Day<br\/> <b>Scan: <\/b> 0.4 km<br\/> <b>Track: <\/b> 0.6 km<br\/> <b>FRP: <\/b> 2.9 MW<br\/> <b>Brightness: <\/b> 328.69 K" }, "geometry": { "type": "Point", "coordinates": [ -77.74875, 39.46602, 0.0 ] } },
{ "type": "Feature", "properties": { "Name": "Fire Detection Centroid ", "Description": "<b>Latitude: <\/b> 39.28955<br\/>  <b>Longitude: <\/b> -78.00034<br\/>  <b>Detection Time: <\/b> 2023-12-08 17:17 UTC<br\/>  <b>Sensor: <\/b> NOAA-20 VIIRS<br\/> <b>Confidence: <\/b> Nominal<br\/>  <b>Day\/Night: <\/b> Day<br\/> <b>Scan: <\/b> 0.4 km<br\/> <b>Track: <\/b> 0.6 km<br\/> <b>FRP: <\/b> 3.97 MW<br\/> <b>Brightness: <\/b> 343.95 K" }, "geometry": { "type": "Point", "coordinates": [ -78.00034, 39.28955, 0.0 ] } },
{ "type": "Feature", "properties": { "Name": "Fire Detection Centroid ", "Description": "<b>Latitude: <\/b> 19.28722<br\/>  <b>Longitude: <\/b> -72.61159<br\/>  <b>Detection Time: <\/b> 2023-12-08 17:12 UTC<br\/>  <b>Sensor: <\/b> NOAA-20 VIIRS<br\/> <b>Confidence: <\/b> Nominal<br\/>  <b>Day\/Night: <\/b> Day<br\/> <b>Scan: <\/b> 0.6 km<br\/> <b>Track: <\/b> 0.7 km<br\/> <b>FRP: <\/b> 4.36 MW<br\/> <b>Brightness: <\/b> 330.31 K" }, "geometry": { "type": "Point", "coordinates": [ -72.61159, 19.28722, 0.0 ] } },
{ "type": "Feature", "properties": { "Name": "Fire Detection Centroid ", "Description": "<b>Latitude: <\/b> 19.28515<br\/>  <b>Longitude: <\/b> -72.61623<br\/>  <b>Detection Time: <\/b> 2023-12-08 17:12 UTC<br\/>  <b>Sensor: <\/b> NOAA-20 VIIRS<br\/> <b>Confidence: <\/b> Nominal<br\/>  <b>Day\/Night: <\/b> Day<br\/> <b>Scan: <\/b> 0.6 km<br\/> <b>Track: <\/b> 0.7 km<br\/> <b>FRP: <\/b> 5.81 MW<br\/> <b>Brightness: <\/b> 333.14 K" }, "geometry": { "type": "Point", "coordinates": [ -72.61623, 19.28515, 0.0 ] } },
{ "type": "Feature", "properties": { "Name": "Fire Detection Centroid ", "Description": "<b>Latitude: <\/b> 19.28588<br\/>  <b>Longitude: <\/b> -72.61723<br\/>  <b>Detection Time: <\/b> 2023-12-08 17:12 UTC<br\/>  <b>Sensor: <\/b> NOAA-20 VIIRS<br\/> <b>Confidence: <\/b> Nominal<br\/>  <b>Day\/Night: <\/b> Day<br\/> <b>Scan: <\/b> 0.6 km<br\/> <b>Track: <\/b> 0.7 km<br\/> <b>FRP: <\/b> 4.36 MW<br\/> <b>Brightness: <\/b> 330.53 K" }, "geometry": { "type": "Point", "coordinates": [ -72.61723, 19.28588, 0.0 ] } },
{ "type": "Feature", "properties": { "Name": "Fire Detection Centroid ", "Description": "<b>Latitude: <\/b> 19.28645<br\/>  <b>Longitude: <\/b> -72.61058<br\/>  <b>Detection Time: <\/b> 2023-12-08 17:12 UTC<br\/>  <b>Sensor: <\/b> NOAA-20 VIIRS<br\/> <b>Confidence: <\/b> Nominal<br\/>  <b>Day\/Night: <\/b> Day<br\/> <b>Scan: <\/b> 0.6 km<br\/> <b>Track: <\/b> 0.7 km<br\/> <b>FRP: <\/b> 5.46 MW<br\/> <b>Brightness: <\/b> 328.07 K" }, "geometry": { "type": "Point", "coordinates": [ -72.61058, 19.28645, 0.0 ] } },
{ "type": "Feature", "properties": { "Name": "Fire Detection Centroid ", "Description": "<b>Latitude: <\/b> 19.26073<br\/>  <b>Longitude: <\/b> -72.25979<br\/>  <b>Detection Time: <\/b> 2023-12-08 17:12 UTC<br\/>  <b>Sensor: <\/b> NOAA-20 VIIRS<br\/> <b>Confidence: <\/b> Nominal<br\/>  <b>Day\/Night: <\/b> Day<br\/> <b>Scan: <\/b> 0.6 km<br\/> <b>Track: <\/b> 0.7 km<br\/> <b>FRP: <\/b> 10.79 MW<br\/> <b>Brightness: <\/b> 343.55 K" }, "geometry": { "type": "Point", "coordinates": [ -72.25979, 19.26073, 0.0 ] } },
{ "type": "Feature", "properties": { "Name": "Fire Detection Centroid ", "Description": "<b>Latitude: <\/b> 19.26489<br\/>  <b>Longitude: <\/b> -72.25825<br\/>  <b>Detection Time: <\/b> 2023-12-08 17:12 UTC<br\/>  <b>Sensor: <\/b> NOAA-20 VIIRS<br\/> <b>Confidence: <\/b> Nominal<br\/>  <b>Day\/Night: <\/b> Day<br\/> <b>Scan: <\/b> 0.6 km<br\/> <b>Track: <\/b> 0.7 km<br\/> <b>FRP: <\/b> 9.17 MW<br\/> <b>Brightness: <\/b> 355.01 K" }, "geometry": { "type": "Point", "coordinates": [ -72.25825, 19.26489, 0.0 ] } }
]
}
