{
"type": "FeatureCollection",
"crs": { "type": "name", "properties": { "name": "urn:ogc:def:crs:OGC:1.3:CRS84" } },
"features": [
{ "type": "Feature", "properties": { "Name": "Fire Detection Centroid ", "Description": "<b>Latitude: <\/b> 20.86153<br\/>  <b>Longitude: <\/b> -156.4221<br\/>  <b>Detection Time: <\/b> 2024-06-13 11:55 UTC<br\/>  <b>Sensor: <\/b> NOAA-20 VIIRS<br\/> <b>Confidence: <\/b> Nominal<br\/>  <b>Day\/Night: <\/b> Night<br\/> <b>Scan: <\/b> 0.42 km<br\/> <b>Track: <\/b> 0.37 km<br\/> <b>FRP: <\/b> 0.34 MW<br\/> <b>Brightness: <\/b> 302.78 K" }, "geometry": { "type": "Point", "coordinates": [ -156.4221, 20.86153, 0.0 ] } }
]
}
