{
"type": "FeatureCollection",
"crs": { "type": "name", "properties": { "name": "urn:ogc:def:crs:OGC:1.3:CRS84" } },
"features": [
{ "type": "Feature", "properties": { "Name": "Fire Detection Centroid ", "Description": "<b>Latitude: <\/b> 45.15918<br\/>  <b>Longitude: <\/b> -66.03259<br\/>  <b>Detection Time: <\/b> 2024-05-05 05:35 UTC<br\/>  <b>Sensor: <\/b> NOAA-20 VIIRS<br\/> <b>Confidence: <\/b> Nominal<br\/>  <b>Day\/Night: <\/b> Night<br\/> <b>Scan: <\/b> 0.3 km<br\/> <b>Track: <\/b> 0.6 km<br\/> <b>FRP: <\/b> 3.12 MW<br\/> <b>Brightness: <\/b> 337.31 K" }, "geometry": { "type": "Point", "coordinates": [ -66.03259, 45.15918, 0.0 ] } },
{ "type": "Feature", "properties": { "Name": "Fire Detection Centroid ", "Description": "<b>Latitude: <\/b> 45.36847<br\/>  <b>Longitude: <\/b> -66.01153<br\/>  <b>Detection Time: <\/b> 2024-05-05 05:35 UTC<br\/>  <b>Sensor: <\/b> NOAA-20 VIIRS<br\/> <b>Confidence: <\/b> Nominal<br\/>  <b>Day\/Night: <\/b> Night<br\/> <b>Scan: <\/b> 0.3 km<br\/> <b>Track: <\/b> 0.6 km<br\/> <b>FRP: <\/b> 3.1 MW<br\/> <b>Brightness: <\/b> 338.65 K" }, "geometry": { "type": "Point", "coordinates": [ -66.01153, 45.36847, 0.0 ] } },
{ "type": "Feature", "properties": { "Name": "Fire Detection Centroid ", "Description": "<b>Latitude: <\/b> 45.24712<br\/>  <b>Longitude: <\/b> -66.9951<br\/>  <b>Detection Time: <\/b> 2024-05-05 05:35 UTC<br\/>  <b>Sensor: <\/b> NOAA-20 VIIRS<br\/> <b>Confidence: <\/b> Nominal<br\/>  <b>Day\/Night: <\/b> Night<br\/> <b>Scan: <\/b> 0.4 km<br\/> <b>Track: <\/b> 0.6 km<br\/> <b>FRP: <\/b> 0.67 MW<br\/> <b>Brightness: <\/b> 299.52 K" }, "geometry": { "type": "Point", "coordinates": [ -66.9951, 45.24712, 0.0 ] } }
]
}
