{
"type": "FeatureCollection",
"crs": { "type": "name", "properties": { "name": "urn:ogc:def:crs:OGC:1.3:CRS84" } },
"features": [
{ "type": "Feature", "properties": { "Name": "Fire Detection Centroid ", "Description": "<b>Latitude: <\/b> 19.40753<br\/>  <b>Longitude: <\/b> -155.289<br\/>  <b>Detection Time: <\/b> 2023-11-17 12:40 UTC<br\/>  <b>Sensor: <\/b> NOAA-20 VIIRS<br\/> <b>Confidence: <\/b> Nominal<br\/>  <b>Day\/Night: <\/b> Night<br\/> <b>Scan: <\/b> 0.41 km<br\/> <b>Track: <\/b> 0.61 km<br\/> <b>FRP: <\/b> 2.69 MW<br\/> <b>Brightness: <\/b> 302.64 K" }, "geometry": { "type": "Point", "coordinates": [ -155.289, 19.40753, 0.0 ] } },
{ "type": "Feature", "properties": { "Name": "Fire Detection Centroid ", "Description": "<b>Latitude: <\/b> 19.40664<br\/>  <b>Longitude: <\/b> -155.28491<br\/>  <b>Detection Time: <\/b> 2023-11-17 12:40 UTC<br\/>  <b>Sensor: <\/b> NOAA-20 VIIRS<br\/> <b>Confidence: <\/b> Nominal<br\/>  <b>Day\/Night: <\/b> Night<br\/> <b>Scan: <\/b> 0.41 km<br\/> <b>Track: <\/b> 0.61 km<br\/> <b>FRP: <\/b> 2.69 MW<br\/> <b>Brightness: <\/b> 304.44 K" }, "geometry": { "type": "Point", "coordinates": [ -155.28491, 19.40664, 0.0 ] } },
{ "type": "Feature", "properties": { "Name": "Fire Detection Centroid ", "Description": "<b>Latitude: <\/b> 19.40811<br\/>  <b>Longitude: <\/b> -155.28697<br\/>  <b>Detection Time: <\/b> 2023-11-17 12:39 UTC<br\/>  <b>Sensor: <\/b> NOAA-20 VIIRS<br\/> <b>Confidence: <\/b> Nominal<br\/>  <b>Day\/Night: <\/b> Night<br\/> <b>Scan: <\/b> 0.4 km<br\/> <b>Track: <\/b> 0.6 km<br\/> <b>FRP: <\/b> 2.68 MW<br\/> <b>Brightness: <\/b> 302.64 K" }, "geometry": { "type": "Point", "coordinates": [ -155.28697, 19.40811, 0.0 ] } },
{ "type": "Feature", "properties": { "Name": "Fire Detection Centroid ", "Description": "<b>Latitude: <\/b> 19.40724<br\/>  <b>Longitude: <\/b> -155.28297<br\/>  <b>Detection Time: <\/b> 2023-11-17 12:39 UTC<br\/>  <b>Sensor: <\/b> NOAA-20 VIIRS<br\/> <b>Confidence: <\/b> Nominal<br\/>  <b>Day\/Night: <\/b> Night<br\/> <b>Scan: <\/b> 0.4 km<br\/> <b>Track: <\/b> 0.6 km<br\/> <b>FRP: <\/b> 2.68 MW<br\/> <b>Brightness: <\/b> 304.44 K" }, "geometry": { "type": "Point", "coordinates": [ -155.28297, 19.40724, 0.0 ] } }
]
}
