{
"type": "FeatureCollection",
"crs": { "type": "name", "properties": { "name": "urn:ogc:def:crs:OGC:1.3:CRS84" } },
"features": [
{ "type": "Feature", "properties": { "Name": "Fire Detection Centroid ", "Description": "<b>Latitude: <\/b> 19.40366<br\/>  <b>Longitude: <\/b> -155.28563<br\/>  <b>Detection Time: <\/b> 2023-03-01 23:43 UTC<br\/>  <b>Sensor: <\/b> NOAA-20 VIIRS<br\/> <b>Confidence: <\/b> Nominal<br\/>  <b>Day\/Night: <\/b> Day<br\/> <b>Scan: <\/b> 0.43 km<br\/> <b>Track: <\/b> 0.38 km<br\/> <b>FRP: <\/b> 6.39 MW<br\/> <b>Brightness: <\/b> 337.42 K" }, "geometry": { "type": "Point", "coordinates": [ -155.28563, 19.40366, 0.0 ] } }
]
}
