{
"type": "FeatureCollection",
"crs": { "type": "name", "properties": { "name": "urn:ogc:def:crs:OGC:1.3:CRS84" } },
"features": [
{ "type": "Feature", "properties": { "Name": "Fire Detection Centroid ", "Description": "<b>Latitude: <\/b> 45.33139<br\/>  <b>Longitude: <\/b> -73.70248<br\/>  <b>Detection Time: <\/b> 2024-05-11 16:48 UTC<br\/>  <b>Sensor: <\/b> NOAA-20 VIIRS<br\/> <b>Confidence: <\/b> Nominal<br\/>  <b>Day\/Night: <\/b> Day<br\/> <b>Scan: <\/b> 0.4 km<br\/> <b>Track: <\/b> 0.6 km<br\/> <b>FRP: <\/b> 3.59 MW<br\/> <b>Brightness: <\/b> 343.29 K" }, "geometry": { "type": "Point", "coordinates": [ -73.70248, 45.33139, 0.0 ] } }
]
}
