{
"type": "FeatureCollection",
"crs": { "type": "name", "properties": { "name": "urn:ogc:def:crs:OGC:1.3:CRS84" } },
"features": [
{ "type": "Feature", "properties": { "Name": "Fire Detection Centroid ", "Description": "<b>Latitude: <\/b> 19.40595<br\/>  <b>Longitude: <\/b> -155.28917<br\/>  <b>Detection Time: <\/b> 2023-04-25 12:02 UTC<br\/>  <b>Sensor: <\/b> NOAA-20 VIIRS<br\/> <b>Confidence: <\/b> Nominal<br\/>  <b>Day\/Night: <\/b> Night<br\/> <b>Scan: <\/b> 0.39 km<br\/> <b>Track: <\/b> 0.36 km<br\/> <b>FRP: <\/b> 1.05 MW<br\/> <b>Brightness: <\/b> 296.6 K" }, "geometry": { "type": "Point", "coordinates": [ -155.28917, 19.40595, 0.0 ] } },
{ "type": "Feature", "properties": { "Name": "Fire Detection Centroid ", "Description": "<b>Latitude: <\/b> 19.40476<br\/>  <b>Longitude: <\/b> -155.28183<br\/>  <b>Detection Time: <\/b> 2023-04-25 12:02 UTC<br\/>  <b>Sensor: <\/b> NOAA-20 VIIRS<br\/> <b>Confidence: <\/b> Nominal<br\/>  <b>Day\/Night: <\/b> Night<br\/> <b>Scan: <\/b> 0.39 km<br\/> <b>Track: <\/b> 0.36 km<br\/> <b>FRP: <\/b> 2.85 MW<br\/> <b>Brightness: <\/b> 300.47 K" }, "geometry": { "type": "Point", "coordinates": [ -155.28183, 19.40476, 0.0 ] } },
{ "type": "Feature", "properties": { "Name": "Fire Detection Centroid ", "Description": "<b>Latitude: <\/b> 19.59775<br\/>  <b>Longitude: <\/b> -155.50528<br\/>  <b>Detection Time: <\/b> 2023-04-25 12:02 UTC<br\/>  <b>Sensor: <\/b> NOAA-20 VIIRS<br\/> <b>Confidence: <\/b> Nominal<br\/>  <b>Day\/Night: <\/b> Night<br\/> <b>Scan: <\/b> 0.39 km<br\/> <b>Track: <\/b> 0.36 km<br\/> <b>FRP: <\/b> 1.31 MW<br\/> <b>Brightness: <\/b> 296.64 K" }, "geometry": { "type": "Point", "coordinates": [ -155.50528, 19.59775, 0.0 ] } },
{ "type": "Feature", "properties": { "Name": "Fire Detection Centroid ", "Description": "<b>Latitude: <\/b> 19.58732<br\/>  <b>Longitude: <\/b> -155.50349<br\/>  <b>Detection Time: <\/b> 2023-04-25 12:02 UTC<br\/>  <b>Sensor: <\/b> NOAA-20 VIIRS<br\/> <b>Confidence: <\/b> Nominal<br\/>  <b>Day\/Night: <\/b> Night<br\/> <b>Scan: <\/b> 0.39 km<br\/> <b>Track: <\/b> 0.36 km<br\/> <b>FRP: <\/b> 1.15 MW<br\/> <b>Brightness: <\/b> 296.96 K" }, "geometry": { "type": "Point", "coordinates": [ -155.50349, 19.58732, 0.0 ] } },
{ "type": "Feature", "properties": { "Name": "Fire Detection Centroid ", "Description": "<b>Latitude: <\/b> 19.57807<br\/>  <b>Longitude: <\/b> -155.509<br\/>  <b>Detection Time: <\/b> 2023-04-25 12:02 UTC<br\/>  <b>Sensor: <\/b> NOAA-20 VIIRS<br\/> <b>Confidence: <\/b> Nominal<br\/>  <b>Day\/Night: <\/b> Night<br\/> <b>Scan: <\/b> 0.39 km<br\/> <b>Track: <\/b> 0.36 km<br\/> <b>FRP: <\/b> 1.21 MW<br\/> <b>Brightness: <\/b> 298.08 K" }, "geometry": { "type": "Point", "coordinates": [ -155.509, 19.57807, 0.0 ] } }
]
}
