{
"type": "FeatureCollection",
"crs": { "type": "name", "properties": { "name": "urn:ogc:def:crs:OGC:1.3:CRS84" } },
"features": [
{ "type": "Feature", "properties": { "Name": "Fire Detection Centroid ", "Description": "<b>Latitude: <\/b> 38.07213<br\/>  <b>Longitude: <\/b> -122.14011<br\/>  <b>Detection Time: <\/b> 2024-04-02 11:02 UTC<br\/>  <b>Sensor: <\/b> NOAA-20 VIIRS<br\/> <b>Confidence: <\/b> Nominal<br\/>  <b>Day\/Night: <\/b> Night<br\/> <b>Scan: <\/b> 0.57 km<br\/> <b>Track: <\/b> 0.69 km<br\/> <b>FRP: <\/b> 1.06 MW<br\/> <b>Brightness: <\/b> 297.2 K" }, "geometry": { "type": "Point", "coordinates": [ -122.14011, 38.07213, 0.0 ] } },
{ "type": "Feature", "properties": { "Name": "Fire Detection Centroid ", "Description": "<b>Latitude: <\/b> 37.94876<br\/>  <b>Longitude: <\/b> -122.40089<br\/>  <b>Detection Time: <\/b> 2024-04-02 11:02 UTC<br\/>  <b>Sensor: <\/b> NOAA-20 VIIRS<br\/> <b>Confidence: <\/b> Nominal<br\/>  <b>Day\/Night: <\/b> Night<br\/> <b>Scan: <\/b> 0.55 km<br\/> <b>Track: <\/b> 0.68 km<br\/> <b>FRP: <\/b> 1.17 MW<br\/> <b>Brightness: <\/b> 297.48 K" }, "geometry": { "type": "Point", "coordinates": [ -122.40089, 37.94876, 0.0 ] } },
{ "type": "Feature", "properties": { "Name": "Fire Detection Centroid ", "Description": "<b>Latitude: <\/b> 38.0127<br\/>  <b>Longitude: <\/b> -122.11458<br\/>  <b>Detection Time: <\/b> 2024-04-02 11:02 UTC<br\/>  <b>Sensor: <\/b> NOAA-20 VIIRS<br\/> <b>Confidence: <\/b> Nominal<br\/>  <b>Day\/Night: <\/b> Night<br\/> <b>Scan: <\/b> 0.57 km<br\/> <b>Track: <\/b> 0.69 km<br\/> <b>FRP: <\/b> 1.13 MW<br\/> <b>Brightness: <\/b> 295.54 K" }, "geometry": { "type": "Point", "coordinates": [ -122.11458, 38.0127, 0.0 ] } },
{ "type": "Feature", "properties": { "Name": "Fire Detection Centroid ", "Description": "<b>Latitude: <\/b> 45.23<br\/>  <b>Longitude: <\/b> -123.16819<br\/>  <b>Detection Time: <\/b> 2024-04-02 11:00 UTC<br\/>  <b>Sensor: <\/b> NOAA-20 VIIRS<br\/> <b>Confidence: <\/b> Nominal<br\/>  <b>Day\/Night: <\/b> Night<br\/> <b>Scan: <\/b> 0.63 km<br\/> <b>Track: <\/b> 0.54 km<br\/> <b>FRP: <\/b> 2.64 MW<br\/> <b>Brightness: <\/b> 323.55 K" }, "geometry": { "type": "Point", "coordinates": [ -123.16819, 45.23, 0.0 ] } },
{ "type": "Feature", "properties": { "Name": "Fire Detection Centroid ", "Description": "<b>Latitude: <\/b> 47.46851<br\/>  <b>Longitude: <\/b> -122.05023<br\/>  <b>Detection Time: <\/b> 2024-04-02 11:00 UTC<br\/>  <b>Sensor: <\/b> NOAA-20 VIIRS<br\/> <b>Confidence: <\/b> Nominal<br\/>  <b>Day\/Night: <\/b> Night<br\/> <b>Scan: <\/b> 0.61 km<br\/> <b>Track: <\/b> 0.53 km<br\/> <b>FRP: <\/b> 1.46 MW<br\/> <b>Brightness: <\/b> 303.27 K" }, "geometry": { "type": "Point", "coordinates": [ -122.05023, 47.46851, 0.0 ] } },
{ "type": "Feature", "properties": { "Name": "Fire Detection Centroid ", "Description": "<b>Latitude: <\/b> 47.5709<br\/>  <b>Longitude: <\/b> -122.36688<br\/>  <b>Detection Time: <\/b> 2024-04-02 11:00 UTC<br\/>  <b>Sensor: <\/b> NOAA-20 VIIRS<br\/> <b>Confidence: <\/b> Nominal<br\/>  <b>Day\/Night: <\/b> Night<br\/> <b>Scan: <\/b> 0.59 km<br\/> <b>Track: <\/b> 0.53 km<br\/> <b>FRP: <\/b> 2.12 MW<br\/> <b>Brightness: <\/b> 310.33 K" }, "geometry": { "type": "Point", "coordinates": [ -122.36688, 47.5709, 0.0 ] } },
{ "type": "Feature", "properties": { "Name": "Fire Detection Centroid ", "Description": "<b>Latitude: <\/b> 45.63108<br\/>  <b>Longitude: <\/b> -122.7841<br\/>  <b>Detection Time: <\/b> 2024-04-02 11:00 UTC<br\/>  <b>Sensor: <\/b> NOAA-20 VIIRS<br\/> <b>Confidence: <\/b> Nominal<br\/>  <b>Day\/Night: <\/b> Night<br\/> <b>Scan: <\/b> 0.32 km<br\/> <b>Track: <\/b> 0.55 km<br\/> <b>FRP: <\/b> 0.75 MW<br\/> <b>Brightness: <\/b> 296.7 K" }, "geometry": { "type": "Point", "coordinates": [ -122.7841, 45.63108, 0.0 ] } },
{ "type": "Feature", "properties": { "Name": "Fire Detection Centroid ", "Description": "<b>Latitude: <\/b> 45.22867<br\/>  <b>Longitude: <\/b> -123.16753<br\/>  <b>Detection Time: <\/b> 2024-04-02 11:00 UTC<br\/>  <b>Sensor: <\/b> NOAA-20 VIIRS<br\/> <b>Confidence: <\/b> Nominal<br\/>  <b>Day\/Night: <\/b> Night<br\/> <b>Scan: <\/b> 0.63 km<br\/> <b>Track: <\/b> 0.54 km<br\/> <b>FRP: <\/b> 4.27 MW<br\/> <b>Brightness: <\/b> 324.13 K" }, "geometry": { "type": "Point", "coordinates": [ -123.16753, 45.22867, 0.0 ] } },
{ "type": "Feature", "properties": { "Name": "Fire Detection Centroid ", "Description": "<b>Latitude: <\/b> 48.08117<br\/>  <b>Longitude: <\/b> -117.70006<br\/>  <b>Detection Time: <\/b> 2024-04-02 10:58 UTC<br\/>  <b>Sensor: <\/b> NOAA-20 VIIRS<br\/> <b>Confidence: <\/b> Nominal<br\/>  <b>Day\/Night: <\/b> Night<br\/> <b>Scan: <\/b> 0.45 km<br\/> <b>Track: <\/b> 0.63 km<br\/> <b>FRP: <\/b> 0.71 MW<br\/> <b>Brightness: <\/b> 297.28 K" }, "geometry": { "type": "Point", "coordinates": [ -117.70006, 48.08117, 0.0 ] } }
]
}
