{
"type": "FeatureCollection",
"crs": { "type": "name", "properties": { "name": "urn:ogc:def:crs:OGC:1.3:CRS84" } },
"features": [
{ "type": "Feature", "properties": { "Name": "Fire Detection Centroid ", "Description": "<b>Latitude: <\/b> 19.40205<br\/>  <b>Longitude: <\/b> -155.28131<br\/>  <b>Detection Time: <\/b> 2022-11-23 22:41 UTC<br\/>  <b>Sensor: <\/b> NOAA-20 VIIRS<br\/> <b>Confidence: <\/b> Nominal<br\/>  <b>Day\/Night: <\/b> Day<br\/> <b>Scan: <\/b> 0.6 km<br\/> <b>Track: <\/b> 0.7 km<br\/> <b>FRP: <\/b> 57.84 MW<br\/> <b>Brightness: <\/b> 354.94 K" }, "geometry": { "type": "Point", "coordinates": [ -155.28131, 19.40205, 0.0 ] } },
{ "type": "Feature", "properties": { "Name": "Fire Detection Centroid ", "Description": "<b>Latitude: <\/b> 19.40194<br\/>  <b>Longitude: <\/b> -155.28558<br\/>  <b>Detection Time: <\/b> 2022-11-23 22:41 UTC<br\/>  <b>Sensor: <\/b> NOAA-20 VIIRS<br\/> <b>Confidence: <\/b> Nominal<br\/>  <b>Day\/Night: <\/b> Day<br\/> <b>Scan: <\/b> 0.6 km<br\/> <b>Track: <\/b> 0.7 km<br\/> <b>FRP: <\/b> 28.74 MW<br\/> <b>Brightness: <\/b> 328.28 K" }, "geometry": { "type": "Point", "coordinates": [ -155.28558, 19.40194, 0.0 ] } },
{ "type": "Feature", "properties": { "Name": "Fire Detection Centroid ", "Description": "<b>Latitude: <\/b> 19.40325<br\/>  <b>Longitude: <\/b> -155.27983<br\/>  <b>Detection Time: <\/b> 2022-11-23 22:41 UTC<br\/>  <b>Sensor: <\/b> NOAA-20 VIIRS<br\/> <b>Confidence: <\/b> High<br\/>  <b>Day\/Night: <\/b> Day<br\/> <b>Scan: <\/b> 0.6 km<br\/> <b>Track: <\/b> 0.7 km<br\/> <b>FRP: <\/b> 28.74 MW<br\/> <b>Brightness: <\/b> 367 K" }, "geometry": { "type": "Point", "coordinates": [ -155.27983, 19.40325, 0.0 ] } },
{ "type": "Feature", "properties": { "Name": "Fire Detection Centroid ", "Description": "<b>Latitude: <\/b> 19.40303<br\/>  <b>Longitude: <\/b> -155.27922<br\/>  <b>Detection Time: <\/b> 2022-11-23 22:39 UTC<br\/>  <b>Sensor: <\/b> NOAA-20 VIIRS<br\/> <b>Confidence: <\/b> Nominal<br\/>  <b>Day\/Night: <\/b> Day<br\/> <b>Scan: <\/b> 0.63 km<br\/> <b>Track: <\/b> 0.72 km<br\/> <b>FRP: <\/b> 57.85 MW<br\/> <b>Brightness: <\/b> 354.94 K" }, "geometry": { "type": "Point", "coordinates": [ -155.27922, 19.40303, 0.0 ] } },
{ "type": "Feature", "properties": { "Name": "Fire Detection Centroid ", "Description": "<b>Latitude: <\/b> 19.40289<br\/>  <b>Longitude: <\/b> -155.28355<br\/>  <b>Detection Time: <\/b> 2022-11-23 22:39 UTC<br\/>  <b>Sensor: <\/b> NOAA-20 VIIRS<br\/> <b>Confidence: <\/b> Nominal<br\/>  <b>Day\/Night: <\/b> Day<br\/> <b>Scan: <\/b> 0.64 km<br\/> <b>Track: <\/b> 0.72 km<br\/> <b>FRP: <\/b> 28.75 MW<br\/> <b>Brightness: <\/b> 328.28 K" }, "geometry": { "type": "Point", "coordinates": [ -155.28355, 19.40289, 0.0 ] } },
{ "type": "Feature", "properties": { "Name": "Fire Detection Centroid ", "Description": "<b>Latitude: <\/b> 19.40421<br\/>  <b>Longitude: <\/b> -155.27779<br\/>  <b>Detection Time: <\/b> 2022-11-23 22:39 UTC<br\/>  <b>Sensor: <\/b> NOAA-20 VIIRS<br\/> <b>Confidence: <\/b> High<br\/>  <b>Day\/Night: <\/b> Day<br\/> <b>Scan: <\/b> 0.63 km<br\/> <b>Track: <\/b> 0.72 km<br\/> <b>FRP: <\/b> 28.75 MW<br\/> <b>Brightness: <\/b> 367 K" }, "geometry": { "type": "Point", "coordinates": [ -155.27779, 19.40421, 0.0 ] } }
]
}
