{
"type": "FeatureCollection",
"crs": { "type": "name", "properties": { "name": "urn:ogc:def:crs:OGC:1.3:CRS84" } },
"features": [
{ "type": "Feature", "properties": { "Name": "Fire Detection Centroid ", "Description": "<b>Latitude: <\/b> 44.73833<br\/>  <b>Longitude: <\/b> -73.50949<br\/>  <b>Detection Time: <\/b> 2023-04-15 16:23 UTC<br\/>  <b>Sensor: <\/b> NOAA-20 VIIRS<br\/> <b>Confidence: <\/b> Nominal<br\/>  <b>Day\/Night: <\/b> Day<br\/> <b>Scan: <\/b> 0.8 km<br\/> <b>Track: <\/b> 0.8 km<br\/> <b>FRP: <\/b> 13.57 MW<br\/> <b>Brightness: <\/b> 334.86 K" }, "geometry": { "type": "Point", "coordinates": [ -73.50949, 44.73833, 0.0 ] } },
{ "type": "Feature", "properties": { "Name": "Fire Detection Centroid ", "Description": "<b>Latitude: <\/b> 44.74238<br\/>  <b>Longitude: <\/b> -73.50941<br\/>  <b>Detection Time: <\/b> 2023-04-15 16:23 UTC<br\/>  <b>Sensor: <\/b> NOAA-20 VIIRS<br\/> <b>Confidence: <\/b> High<br\/>  <b>Day\/Night: <\/b> Day<br\/> <b>Scan: <\/b> 0.8 km<br\/> <b>Track: <\/b> 0.8 km<br\/> <b>FRP: <\/b> 20.82 MW<br\/> <b>Brightness: <\/b> 367 K" }, "geometry": { "type": "Point", "coordinates": [ -73.50941, 44.74238, 0.0 ] } },
{ "type": "Feature", "properties": { "Name": "Fire Detection Centroid ", "Description": "<b>Latitude: <\/b> 46.5692<br\/>  <b>Longitude: <\/b> -64.01424<br\/>  <b>Detection Time: <\/b> 2023-04-15 16:23 UTC<br\/>  <b>Sensor: <\/b> NOAA-20 VIIRS<br\/> <b>Confidence: <\/b> Nominal<br\/>  <b>Day\/Night: <\/b> Day<br\/> <b>Scan: <\/b> 0.5 km<br\/> <b>Track: <\/b> 0.5 km<br\/> <b>FRP: <\/b> 2.43 MW<br\/> <b>Brightness: <\/b> 325.2 K" }, "geometry": { "type": "Point", "coordinates": [ -64.01424, 46.5692, 0.0 ] } },
{ "type": "Feature", "properties": { "Name": "Fire Detection Centroid ", "Description": "<b>Latitude: <\/b> 44.74153<br\/>  <b>Longitude: <\/b> -73.50069<br\/>  <b>Detection Time: <\/b> 2023-04-15 16:23 UTC<br\/>  <b>Sensor: <\/b> NOAA-20 VIIRS<br\/> <b>Confidence: <\/b> Nominal<br\/>  <b>Day\/Night: <\/b> Day<br\/> <b>Scan: <\/b> 0.8 km<br\/> <b>Track: <\/b> 0.8 km<br\/> <b>FRP: <\/b> 15.97 MW<br\/> <b>Brightness: <\/b> 351.2 K" }, "geometry": { "type": "Point", "coordinates": [ -73.50069, 44.74153, 0.0 ] } },
{ "type": "Feature", "properties": { "Name": "Fire Detection Centroid ", "Description": "<b>Latitude: <\/b> 45.25313<br\/>  <b>Longitude: <\/b> -66.87723<br\/>  <b>Detection Time: <\/b> 2023-04-15 16:22 UTC<br\/>  <b>Sensor: <\/b> NOAA-20 VIIRS<br\/> <b>Confidence: <\/b> High<br\/>  <b>Day\/Night: <\/b> Day<br\/> <b>Scan: <\/b> 0.4 km<br\/> <b>Track: <\/b> 0.6 km<br\/> <b>FRP: <\/b> 9.78 MW<br\/> <b>Brightness: <\/b> 367 K" }, "geometry": { "type": "Point", "coordinates": [ -66.87723, 45.25313, 0.0 ] } },
{ "type": "Feature", "properties": { "Name": "Fire Detection Centroid ", "Description": "<b>Latitude: <\/b> 45.29622<br\/>  <b>Longitude: <\/b> -66.81078<br\/>  <b>Detection Time: <\/b> 2023-04-15 16:22 UTC<br\/>  <b>Sensor: <\/b> NOAA-20 VIIRS<br\/> <b>Confidence: <\/b> High<br\/>  <b>Day\/Night: <\/b> Day<br\/> <b>Scan: <\/b> 0.4 km<br\/> <b>Track: <\/b> 0.6 km<br\/> <b>FRP: <\/b> 13.74 MW<br\/> <b>Brightness: <\/b> 367 K" }, "geometry": { "type": "Point", "coordinates": [ -66.81078, 45.29622, 0.0 ] } },
{ "type": "Feature", "properties": { "Name": "Fire Detection Centroid ", "Description": "<b>Latitude: <\/b> 45.29484<br\/>  <b>Longitude: <\/b> -66.8155<br\/>  <b>Detection Time: <\/b> 2023-04-15 16:22 UTC<br\/>  <b>Sensor: <\/b> NOAA-20 VIIRS<br\/> <b>Confidence: <\/b> Nominal<br\/>  <b>Day\/Night: <\/b> Day<br\/> <b>Scan: <\/b> 0.4 km<br\/> <b>Track: <\/b> 0.6 km<br\/> <b>FRP: <\/b> 8.1 MW<br\/> <b>Brightness: <\/b> 336.25 K" }, "geometry": { "type": "Point", "coordinates": [ -66.8155, 45.29484, 0.0 ] } },
{ "type": "Feature", "properties": { "Name": "Fire Detection Centroid ", "Description": "<b>Latitude: <\/b> 45.25705<br\/>  <b>Longitude: <\/b> -66.8764<br\/>  <b>Detection Time: <\/b> 2023-04-15 16:22 UTC<br\/>  <b>Sensor: <\/b> NOAA-20 VIIRS<br\/> <b>Confidence: <\/b> Nominal<br\/>  <b>Day\/Night: <\/b> Day<br\/> <b>Scan: <\/b> 0.4 km<br\/> <b>Track: <\/b> 0.6 km<br\/> <b>FRP: <\/b> 7.27 MW<br\/> <b>Brightness: <\/b> 348.48 K" }, "geometry": { "type": "Point", "coordinates": [ -66.8764, 45.25705, 0.0 ] } },
{ "type": "Feature", "properties": { "Name": "Fire Detection Centroid ", "Description": "<b>Latitude: <\/b> 45.25575<br\/>  <b>Longitude: <\/b> -66.8809<br\/>  <b>Detection Time: <\/b> 2023-04-15 16:22 UTC<br\/>  <b>Sensor: <\/b> NOAA-20 VIIRS<br\/> <b>Confidence: <\/b> Nominal<br\/>  <b>Day\/Night: <\/b> Day<br\/> <b>Scan: <\/b> 0.4 km<br\/> <b>Track: <\/b> 0.6 km<br\/> <b>FRP: <\/b> 7.54 MW<br\/> <b>Brightness: <\/b> 339.21 K" }, "geometry": { "type": "Point", "coordinates": [ -66.8809, 45.25575, 0.0 ] } }
]
}
