{
"type": "FeatureCollection",
"crs": { "type": "name", "properties": { "name": "urn:ogc:def:crs:OGC:1.3:CRS84" } },
"features": [
{ "type": "Feature", "properties": { "Name": "Fire Detection Centroid ", "Description": "<b>Latitude: <\/b> 45.47092<br\/>  <b>Longitude: <\/b> -73.57075<br\/>  <b>Detection Time: <\/b> 2024-03-29 17:03 UTC<br\/>  <b>Sensor: <\/b> NOAA-20 VIIRS<br\/> <b>Confidence: <\/b> Nominal<br\/>  <b>Day\/Night: <\/b> Day<br\/> <b>Scan: <\/b> 0.5 km<br\/> <b>Track: <\/b> 0.5 km<br\/> <b>FRP: <\/b> 3.49 MW<br\/> <b>Brightness: <\/b> 333.27 K" }, "geometry": { "type": "Point", "coordinates": [ -73.57075, 45.47092, 0.0 ] } },
{ "type": "Feature", "properties": { "Name": "Fire Detection Centroid ", "Description": "<b>Latitude: <\/b> 19.00156<br\/>  <b>Longitude: <\/b> -69.95041<br\/>  <b>Detection Time: <\/b> 2024-03-29 16:56 UTC<br\/>  <b>Sensor: <\/b> NOAA-20 VIIRS<br\/> <b>Confidence: <\/b> Nominal<br\/>  <b>Day\/Night: <\/b> Day<br\/> <b>Scan: <\/b> 0.8 km<br\/> <b>Track: <\/b> 0.8 km<br\/> <b>FRP: <\/b> 4.94 MW<br\/> <b>Brightness: <\/b> 336.73 K" }, "geometry": { "type": "Point", "coordinates": [ -69.95041, 19.00156, 0.0 ] } },
{ "type": "Feature", "properties": { "Name": "Fire Detection Centroid ", "Description": "<b>Latitude: <\/b> 18.79564<br\/>  <b>Longitude: <\/b> -69.89896<br\/>  <b>Detection Time: <\/b> 2024-03-29 16:56 UTC<br\/>  <b>Sensor: <\/b> NOAA-20 VIIRS<br\/> <b>Confidence: <\/b> Nominal<br\/>  <b>Day\/Night: <\/b> Day<br\/> <b>Scan: <\/b> 0.8 km<br\/> <b>Track: <\/b> 0.8 km<br\/> <b>FRP: <\/b> 3.76 MW<br\/> <b>Brightness: <\/b> 336.94 K" }, "geometry": { "type": "Point", "coordinates": [ -69.89896, 18.79564, 0.0 ] } }
]
}
