{
"type": "FeatureCollection",
"crs": { "type": "name", "properties": { "name": "urn:ogc:def:crs:OGC:1.3:CRS84" } },
"features": [
{ "type": "Feature", "properties": { "Name": "Fire Detection Centroid ", "Description": "<b>Latitude: <\/b> 19.57854<br\/>  <b>Longitude: <\/b> -155.50783<br\/>  <b>Detection Time: <\/b> 2023-05-01 11:49 UTC<br\/>  <b>Sensor: <\/b> NOAA-20 VIIRS<br\/> <b>Confidence: <\/b> Nominal<br\/>  <b>Day\/Night: <\/b> Night<br\/> <b>Scan: <\/b> 0.43 km<br\/> <b>Track: <\/b> 0.38 km<br\/> <b>FRP: <\/b> 1.72 MW<br\/> <b>Brightness: <\/b> 295.01 K" }, "geometry": { "type": "Point", "coordinates": [ -155.50783, 19.57854, 0.0 ] } }
]
}
