{
"type": "FeatureCollection",
"crs": { "type": "name", "properties": { "name": "urn:ogc:def:crs:OGC:1.3:CRS84" } },
"features": [
{ "type": "Feature", "properties": { "Name": "Fire Detection Centroid ", "Description": "<b>Latitude: <\/b> 19.40619<br\/>  <b>Longitude: <\/b> -155.28044<br\/>  <b>Detection Time: <\/b> 2023-09-01 11:45 UTC<br\/>  <b>Sensor: <\/b> NOAA-20 VIIRS<br\/> <b>Confidence: <\/b> Nominal<br\/>  <b>Day\/Night: <\/b> Night<br\/> <b>Scan: <\/b> 0.49 km<br\/> <b>Track: <\/b> 0.4 km<br\/> <b>FRP: <\/b> 5.24 MW<br\/> <b>Brightness: <\/b> 308.3 K" }, "geometry": { "type": "Point", "coordinates": [ -155.28044, 19.40619, 0.0 ] } }
]
}
