{
"type": "FeatureCollection",
"crs": { "type": "name", "properties": { "name": "urn:ogc:def:crs:OGC:1.3:CRS84" } },
"features": [
{ "type": "Feature", "properties": { "Name": "Fire Detection Centroid ", "Description": "<b>Latitude: </b> 19.39519<br/>  <b>Longitude: </b> -70.54386<br/>  <b>Detection Time: </b> 2022-06-19 05:29 UTC<br/>  <b>Sensor: </b> NOAA-20 VIIRS<br/> <b>Confidence: </b> Nominal<br/>  <b>Day/Night: </b> Night<br/> <b>Scan: </b> 0.6 km<br/> <b>Track: </b> 0.7 km<br/> <b>FRP: </b> 2.4 MW<br/> <b>Brightness: </b> 304.95 K" }, "geometry": { "type": "Point", "coordinates": [ -70.54386, 19.39519, 0.0 ] } },
{ "type": "Feature", "properties": { "Name": "Fire Detection Centroid ", "Description": "<b>Latitude: </b> 18.93155<br/>  <b>Longitude: </b> -70.3556<br/>  <b>Detection Time: </b> 2022-06-19 05:29 UTC<br/>  <b>Sensor: </b> NOAA-20 VIIRS<br/> <b>Confidence: </b> High<br/>  <b>Day/Night: </b> Night<br/> <b>Scan: </b> 0.6 km<br/> <b>Track: </b> 0.7 km<br/> <b>FRP: </b> 12.93 MW<br/> <b>Brightness: </b> 367 K" }, "geometry": { "type": "Point", "coordinates": [ -70.3556, 18.93155, 0.0 ] } },
{ "type": "Feature", "properties": { "Name": "Fire Detection Centroid ", "Description": "<b>Latitude: </b> 19.39456<br/>  <b>Longitude: </b> -70.54021<br/>  <b>Detection Time: </b> 2022-06-19 05:29 UTC<br/>  <b>Sensor: </b> NOAA-20 VIIRS<br/> <b>Confidence: </b> Nominal<br/>  <b>Day/Night: </b> Night<br/> <b>Scan: </b> 0.6 km<br/> <b>Track: </b> 0.7 km<br/> <b>FRP: </b> 3.03 MW<br/> <b>Brightness: </b> 321.35 K" }, "geometry": { "type": "Point", "coordinates": [ -70.54021, 19.39456, 0.0 ] } },
{ "type": "Feature", "properties": { "Name": "Fire Detection Centroid ", "Description": "<b>Latitude: </b> 19.39471<br/>  <b>Longitude: </b> -70.53813<br/>  <b>Detection Time: </b> 2022-06-19 05:29 UTC<br/>  <b>Sensor: </b> NOAA-20 VIIRS<br/> <b>Confidence: </b> Nominal<br/>  <b>Day/Night: </b> Night<br/> <b>Scan: </b> 0.6 km<br/> <b>Track: </b> 0.7 km<br/> <b>FRP: </b> 2.45 MW<br/> <b>Brightness: </b> 308.52 K" }, "geometry": { "type": "Point", "coordinates": [ -70.53813, 19.39471, 0.0 ] } },
{ "type": "Feature", "properties": { "Name": "Fire Detection Centroid ", "Description": "<b>Latitude: </b> 44.01928<br/>  <b>Longitude: </b> -66.0634<br/>  <b>Detection Time: </b> 2022-06-19 05:22 UTC<br/>  <b>Sensor: </b> NOAA-20 VIIRS<br/> <b>Confidence: </b> Nominal<br/>  <b>Day/Night: </b> Night<br/> <b>Scan: </b> 0.5 km<br/> <b>Track: </b> 0.7 km<br/> <b>FRP: </b> 0.88 MW<br/> <b>Brightness: </b> 302.59 K" }, "geometry": { "type": "Point", "coordinates": [ -66.0634, 44.01928, 0.0 ] } },
{ "type": "Feature", "properties": { "Name": "Fire Detection Centroid ", "Description": "<b>Latitude: </b> 45.63594<br/>  <b>Longitude: </b> -63.80529<br/>  <b>Detection Time: </b> 2022-06-19 05:21 UTC<br/>  <b>Sensor: </b> NOAA-20 VIIRS<br/> <b>Confidence: </b> Nominal<br/>  <b>Day/Night: </b> Night<br/> <b>Scan: </b> 0.4 km<br/> <b>Track: </b> 0.6 km<br/> <b>FRP: </b> 0.21 MW<br/> <b>Brightness: </b> 311.26 K" }, "geometry": { "type": "Point", "coordinates": [ -63.80529, 45.63594, 0.0 ] } },
{ "type": "Feature", "properties": { "Name": "Fire Detection Centroid ", "Description": "<b>Latitude: </b> 45.27938<br/>  <b>Longitude: </b> -66.01938<br/>  <b>Detection Time: </b> 2022-06-19 05:21 UTC<br/>  <b>Sensor: </b> NOAA-20 VIIRS<br/> <b>Confidence: </b> Nominal<br/>  <b>Day/Night: </b> Night<br/> <b>Scan: </b> 0.5 km<br/> <b>Track: </b> 0.7 km<br/> <b>FRP: </b> 2.16 MW<br/> <b>Brightness: </b> 306.04 K" }, "geometry": { "type": "Point", "coordinates": [ -66.01938, 45.27938, 0.0 ] } },
{ "type": "Feature", "properties": { "Name": "Fire Detection Centroid ", "Description": "<b>Latitude: </b> 45.27835<br/>  <b>Longitude: </b> -66.01867<br/>  <b>Detection Time: </b> 2022-06-19 05:21 UTC<br/>  <b>Sensor: </b> NOAA-20 VIIRS<br/> <b>Confidence: </b> Nominal<br/>  <b>Day/Night: </b> Night<br/> <b>Scan: </b> 0.5 km<br/> <b>Track: </b> 0.7 km<br/> <b>FRP: </b> 1.26 MW<br/> <b>Brightness: </b> 295.55 K" }, "geometry": { "type": "Point", "coordinates": [ -66.01867, 45.27835, 0.0 ] } },
{ "type": "Feature", "properties": { "Name": "Fire Detection Centroid ", "Description": "<b>Latitude: </b> 45.28453<br/>  <b>Longitude: </b> -66.01815<br/>  <b>Detection Time: </b> 2022-06-19 05:21 UTC<br/>  <b>Sensor: </b> NOAA-20 VIIRS<br/> <b>Confidence: </b> Nominal<br/>  <b>Day/Night: </b> Night<br/> <b>Scan: </b> 0.5 km<br/> <b>Track: </b> 0.7 km<br/> <b>FRP: </b> 1.26 MW<br/> <b>Brightness: </b> 299.02 K" }, "geometry": { "type": "Point", "coordinates": [ -66.01815, 45.28453, 0.0 ] } }
]
}
