{
"type": "FeatureCollection",
"crs": { "type": "name", "properties": { "name": "urn:ogc:def:crs:OGC:1.3:CRS84" } },
"features": [
{ "type": "Feature", "properties": { "Name": "Fire Detection Centroid ", "Description": "<b>Latitude: <\/b> 19.40538<br\/>  <b>Longitude: <\/b> -155.2769<br\/>  <b>Detection Time: <\/b> 2022-09-03 22:59 UTC<br\/>  <b>Sensor: <\/b> NOAA-20 VIIRS<br\/> <b>Confidence: <\/b> Nominal<br\/>  <b>Day\/Night: <\/b> Day<br\/> <b>Scan: <\/b> 0.62 km<br\/> <b>Track: <\/b> 0.54 km<br\/> <b>FRP: <\/b> 53.07 MW<br\/> <b>Brightness: <\/b> 338.83 K" }, "geometry": { "type": "Point", "coordinates": [ -155.2769, 19.40538, 0.0 ] } },
{ "type": "Feature", "properties": { "Name": "Fire Detection Centroid ", "Description": "<b>Latitude: <\/b> 19.40419<br\/>  <b>Longitude: <\/b> -155.28267<br\/>  <b>Detection Time: <\/b> 2022-09-03 22:59 UTC<br\/>  <b>Sensor: <\/b> NOAA-20 VIIRS<br\/> <b>Confidence: <\/b> Low<br\/>  <b>Day\/Night: <\/b> Day<br\/> <b>Scan: <\/b> 0.62 km<br\/> <b>Track: <\/b> 0.54 km<br\/> <b>FRP: <\/b> 53.07 MW<br\/> <b>Brightness: <\/b> 367 K" }, "geometry": { "type": "Point", "coordinates": [ -155.28267, 19.40419, 0.0 ] } },
{ "type": "Feature", "properties": { "Name": "Fire Detection Centroid ", "Description": "<b>Latitude: <\/b> 19.40909<br\/>  <b>Longitude: <\/b> -155.28365<br\/>  <b>Detection Time: <\/b> 2022-09-03 22:59 UTC<br\/>  <b>Sensor: <\/b> NOAA-20 VIIRS<br\/> <b>Confidence: <\/b> High<br\/>  <b>Day\/Night: <\/b> Day<br\/> <b>Scan: <\/b> 0.62 km<br\/> <b>Track: <\/b> 0.54 km<br\/> <b>FRP: <\/b> 53.07 MW<br\/> <b>Brightness: <\/b> 367 K" }, "geometry": { "type": "Point", "coordinates": [ -155.28365, 19.40909, 0.0 ] } },
{ "type": "Feature", "properties": { "Name": "Fire Detection Centroid ", "Description": "<b>Latitude: <\/b> 19.41026<br\/>  <b>Longitude: <\/b> -155.27794<br\/>  <b>Detection Time: <\/b> 2022-09-03 22:59 UTC<br\/>  <b>Sensor: <\/b> NOAA-20 VIIRS<br\/> <b>Confidence: <\/b> Nominal<br\/>  <b>Day\/Night: <\/b> Day<br\/> <b>Scan: <\/b> 0.62 km<br\/> <b>Track: <\/b> 0.54 km<br\/> <b>FRP: <\/b> 53.07 MW<br\/> <b>Brightness: <\/b> 348.01 K" }, "geometry": { "type": "Point", "coordinates": [ -155.27794, 19.41026, 0.0 ] } },
{ "type": "Feature", "properties": { "Name": "Fire Detection Centroid ", "Description": "<b>Latitude: <\/b> 19.40261<br\/>  <b>Longitude: <\/b> -155.28046<br\/>  <b>Detection Time: <\/b> 2022-09-03 22:59 UTC<br\/>  <b>Sensor: <\/b> NOAA-20 VIIRS<br\/> <b>Confidence: <\/b> Nominal<br\/>  <b>Day\/Night: <\/b> Day<br\/> <b>Scan: <\/b> 0.62 km<br\/> <b>Track: <\/b> 0.54 km<br\/> <b>FRP: <\/b> 18.18 MW<br\/> <b>Brightness: <\/b> 351.63 K" }, "geometry": { "type": "Point", "coordinates": [ -155.28046, 19.40261, 0.0 ] } },
{ "type": "Feature", "properties": { "Name": "Fire Detection Centroid ", "Description": "<b>Latitude: <\/b> 19.40635<br\/>  <b>Longitude: <\/b> -155.28725<br\/>  <b>Detection Time: <\/b> 2022-09-03 22:59 UTC<br\/>  <b>Sensor: <\/b> NOAA-20 VIIRS<br\/> <b>Confidence: <\/b> Nominal<br\/>  <b>Day\/Night: <\/b> Day<br\/> <b>Scan: <\/b> 0.63 km<br\/> <b>Track: <\/b> 0.54 km<br\/> <b>FRP: <\/b> 66.58 MW<br\/> <b>Brightness: <\/b> 346.76 K" }, "geometry": { "type": "Point", "coordinates": [ -155.28725, 19.40635, 0.0 ] } },
{ "type": "Feature", "properties": { "Name": "Fire Detection Centroid ", "Description": "<b>Latitude: <\/b> 19.40748<br\/>  <b>Longitude: <\/b> -155.28154<br\/>  <b>Detection Time: <\/b> 2022-09-03 22:59 UTC<br\/>  <b>Sensor: <\/b> NOAA-20 VIIRS<br\/> <b>Confidence: <\/b> Low<br\/>  <b>Day\/Night: <\/b> Day<br\/> <b>Scan: <\/b> 0.62 km<br\/> <b>Track: <\/b> 0.54 km<br\/> <b>FRP: <\/b> 66.58 MW<br\/> <b>Brightness: <\/b> 367 K" }, "geometry": { "type": "Point", "coordinates": [ -155.28154, 19.40748, 0.0 ] } },
{ "type": "Feature", "properties": { "Name": "Fire Detection Centroid ", "Description": "<b>Latitude: <\/b> 19.4135<br\/>  <b>Longitude: <\/b> -155.27682<br\/>  <b>Detection Time: <\/b> 2022-09-03 22:59 UTC<br\/>  <b>Sensor: <\/b> NOAA-20 VIIRS<br\/> <b>Confidence: <\/b> Nominal<br\/>  <b>Day\/Night: <\/b> Day<br\/> <b>Scan: <\/b> 0.62 km<br\/> <b>Track: <\/b> 0.54 km<br\/> <b>FRP: <\/b> 22.04 MW<br\/> <b>Brightness: <\/b> 342.2 K" }, "geometry": { "type": "Point", "coordinates": [ -155.27682, 19.4135, 0.0 ] } },
{ "type": "Feature", "properties": { "Name": "Fire Detection Centroid ", "Description": "<b>Latitude: <\/b> 19.41238<br\/>  <b>Longitude: <\/b> -155.28249<br\/>  <b>Detection Time: <\/b> 2022-09-03 22:59 UTC<br\/>  <b>Sensor: <\/b> NOAA-20 VIIRS<br\/> <b>Confidence: <\/b> Nominal<br\/>  <b>Day\/Night: <\/b> Day<br\/> <b>Scan: <\/b> 0.62 km<br\/> <b>Track: <\/b> 0.54 km<br\/> <b>FRP: <\/b> 66.58 MW<br\/> <b>Brightness: <\/b> 344.02 K" }, "geometry": { "type": "Point", "coordinates": [ -155.28249, 19.41238, 0.0 ] } }
]
}
