{
"type": "FeatureCollection",
"crs": { "type": "name", "properties": { "name": "urn:ogc:def:crs:OGC:1.3:CRS84" } },
"features": [
{ "type": "Feature", "properties": { "Name": "Fire Detection Centroid ", "Description": "<b>Latitude: <\/b> 19.16517<br\/>  <b>Longitude: <\/b> -69.69841<br\/>  <b>Detection Time: <\/b> 2023-09-24 06:07 UTC<br\/>  <b>Sensor: <\/b> NOAA-20 VIIRS<br\/> <b>Confidence: <\/b> Nominal<br\/>  <b>Day\/Night: <\/b> Night<br\/> <b>Scan: <\/b> 0.4 km<br\/> <b>Track: <\/b> 0.4 km<br\/> <b>FRP: <\/b> 0.97 MW<br\/> <b>Brightness: <\/b> 307.96 K" }, "geometry": { "type": "Point", "coordinates": [ -69.69841, 19.16517, 0.0 ] } },
{ "type": "Feature", "properties": { "Name": "Fire Detection Centroid ", "Description": "<b>Latitude: <\/b> 18.92629<br\/>  <b>Longitude: <\/b> -70.35513<br\/>  <b>Detection Time: <\/b> 2023-09-24 06:07 UTC<br\/>  <b>Sensor: <\/b> NOAA-20 VIIRS<br\/> <b>Confidence: <\/b> Nominal<br\/>  <b>Day\/Night: <\/b> Night<br\/> <b>Scan: <\/b> 0.4 km<br\/> <b>Track: <\/b> 0.4 km<br\/> <b>FRP: <\/b> 9.24 MW<br\/> <b>Brightness: <\/b> 330.61 K" }, "geometry": { "type": "Point", "coordinates": [ -70.35513, 18.92629, 0.0 ] } },
{ "type": "Feature", "properties": { "Name": "Fire Detection Centroid ", "Description": "<b>Latitude: <\/b> 18.92983<br\/>  <b>Longitude: <\/b> -70.35468<br\/>  <b>Detection Time: <\/b> 2023-09-24 06:07 UTC<br\/>  <b>Sensor: <\/b> NOAA-20 VIIRS<br\/> <b>Confidence: <\/b> Nominal<br\/>  <b>Day\/Night: <\/b> Night<br\/> <b>Scan: <\/b> 0.4 km<br\/> <b>Track: <\/b> 0.4 km<br\/> <b>FRP: <\/b> 9.24 MW<br\/> <b>Brightness: <\/b> 330.98 K" }, "geometry": { "type": "Point", "coordinates": [ -70.35468, 18.92983, 0.0 ] } },
{ "type": "Feature", "properties": { "Name": "Fire Detection Centroid ", "Description": "<b>Latitude: <\/b> 18.31534<br\/>  <b>Longitude: <\/b> -64.88495<br\/>  <b>Detection Time: <\/b> 2023-09-24 06:07 UTC<br\/>  <b>Sensor: <\/b> NOAA-20 VIIRS<br\/> <b>Confidence: <\/b> Nominal<br\/>  <b>Day\/Night: <\/b> Night<br\/> <b>Scan: <\/b> 0.4 km<br\/> <b>Track: <\/b> 0.4 km<br\/> <b>FRP: <\/b> 0.73 MW<br\/> <b>Brightness: <\/b> 316.51 K" }, "geometry": { "type": "Point", "coordinates": [ -64.88495, 18.31534, 0.0 ] } },
{ "type": "Feature", "properties": { "Name": "Fire Detection Centroid ", "Description": "<b>Latitude: <\/b> 48.18669<br\/>  <b>Longitude: <\/b> -64.92339<br\/>  <b>Detection Time: <\/b> 2023-09-24 05:59 UTC<br\/>  <b>Sensor: <\/b> NOAA-20 VIIRS<br\/> <b>Confidence: <\/b> Nominal<br\/>  <b>Day\/Night: <\/b> Night<br\/> <b>Scan: <\/b> 0.5 km<br\/> <b>Track: <\/b> 0.4 km<br\/> <b>FRP: <\/b> 1.9 MW<br\/> <b>Brightness: <\/b> 307.29 K" }, "geometry": { "type": "Point", "coordinates": [ -64.92339, 48.18669, 0.0 ] } }
]
}
