{
"type": "FeatureCollection",
"crs": { "type": "name", "properties": { "name": "urn:ogc:def:crs:OGC:1.3:CRS84" } },
"features": [
{ "type": "Feature", "properties": { "Name": "Fire Detection Centroid ", "Description": "<b>Latitude: <\/b> 45.06969<br\/>  <b>Longitude: <\/b> -75.19139<br\/>  <b>Detection Time: <\/b> 2023-05-27 16:36 UTC<br\/>  <b>Sensor: <\/b> NOAA-20 VIIRS<br\/> <b>Confidence: <\/b> Nominal<br\/>  <b>Day\/Night: <\/b> Day<br\/> <b>Scan: <\/b> 0.7 km<br\/> <b>Track: <\/b> 0.7 km<br\/> <b>FRP: <\/b> 2.18 MW<br\/> <b>Brightness: <\/b> 325.85 K" }, "geometry": { "type": "Point", "coordinates": [ -75.19139, 45.06969, 0.0 ] } },
{ "type": "Feature", "properties": { "Name": "Fire Detection Centroid ", "Description": "<b>Latitude: <\/b> 45.06653<br\/>  <b>Longitude: <\/b> -75.19038<br\/>  <b>Detection Time: <\/b> 2023-05-27 16:36 UTC<br\/>  <b>Sensor: <\/b> NOAA-20 VIIRS<br\/> <b>Confidence: <\/b> Nominal<br\/>  <b>Day\/Night: <\/b> Day<br\/> <b>Scan: <\/b> 0.7 km<br\/> <b>Track: <\/b> 0.7 km<br\/> <b>FRP: <\/b> 2.92 MW<br\/> <b>Brightness: <\/b> 328.29 K" }, "geometry": { "type": "Point", "coordinates": [ -75.19038, 45.06653, 0.0 ] } },
{ "type": "Feature", "properties": { "Name": "Fire Detection Centroid ", "Description": "<b>Latitude: <\/b> 45.83622<br\/>  <b>Longitude: <\/b> -73.24899<br\/>  <b>Detection Time: <\/b> 2023-05-27 16:36 UTC<br\/>  <b>Sensor: <\/b> NOAA-20 VIIRS<br\/> <b>Confidence: <\/b> Nominal<br\/>  <b>Day\/Night: <\/b> Day<br\/> <b>Scan: <\/b> 0.5 km<br\/> <b>Track: <\/b> 0.7 km<br\/> <b>FRP: <\/b> 5.33 MW<br\/> <b>Brightness: <\/b> 331.41 K" }, "geometry": { "type": "Point", "coordinates": [ -73.24899, 45.83622, 0.0 ] } },
{ "type": "Feature", "properties": { "Name": "Fire Detection Centroid ", "Description": "<b>Latitude: <\/b> 45.83496<br\/>  <b>Longitude: <\/b> -73.24902<br\/>  <b>Detection Time: <\/b> 2023-05-27 16:36 UTC<br\/>  <b>Sensor: <\/b> NOAA-20 VIIRS<br\/> <b>Confidence: <\/b> Nominal<br\/>  <b>Day\/Night: <\/b> Day<br\/> <b>Scan: <\/b> 0.5 km<br\/> <b>Track: <\/b> 0.7 km<br\/> <b>FRP: <\/b> 1.74 MW<br\/> <b>Brightness: <\/b> 329.32 K" }, "geometry": { "type": "Point", "coordinates": [ -73.24902, 45.83496, 0.0 ] } },
{ "type": "Feature", "properties": { "Name": "Fire Detection Centroid ", "Description": "<b>Latitude: <\/b> 44.88874<br\/>  <b>Longitude: <\/b> -73.08049<br\/>  <b>Detection Time: <\/b> 2023-05-27 16:35 UTC<br\/>  <b>Sensor: <\/b> NOAA-20 VIIRS<br\/> <b>Confidence: <\/b> Nominal<br\/>  <b>Day\/Night: <\/b> Day<br\/> <b>Scan: <\/b> 0.5 km<br\/> <b>Track: <\/b> 0.7 km<br\/> <b>FRP: <\/b> 3.55 MW<br\/> <b>Brightness: <\/b> 336.5 K" }, "geometry": { "type": "Point", "coordinates": [ -73.08049, 44.88874, 0.0 ] } },
{ "type": "Feature", "properties": { "Name": "Fire Detection Centroid ", "Description": "<b>Latitude: <\/b> 45.08422<br\/>  <b>Longitude: <\/b> -64.31194<br\/>  <b>Detection Time: <\/b> 2023-05-27 16:35 UTC<br\/>  <b>Sensor: <\/b> NOAA-20 VIIRS<br\/> <b>Confidence: <\/b> Nominal<br\/>  <b>Day\/Night: <\/b> Day<br\/> <b>Scan: <\/b> 0.4 km<br\/> <b>Track: <\/b> 0.5 km<br\/> <b>FRP: <\/b> 2.51 MW<br\/> <b>Brightness: <\/b> 335.67 K" }, "geometry": { "type": "Point", "coordinates": [ -64.31194, 45.08422, 0.0 ] } },
{ "type": "Feature", "properties": { "Name": "Fire Detection Centroid ", "Description": "<b>Latitude: <\/b> 19.59615<br\/>  <b>Longitude: <\/b> -155.50485<br\/>  <b>Detection Time: <\/b> 2023-05-27 12:02 UTC<br\/>  <b>Sensor: <\/b> NOAA-20 VIIRS<br\/> <b>Confidence: <\/b> Nominal<br\/>  <b>Day\/Night: <\/b> Night<br\/> <b>Scan: <\/b> 0.39 km<br\/> <b>Track: <\/b> 0.36 km<br\/> <b>FRP: <\/b> 1.36 MW<br\/> <b>Brightness: <\/b> 295.66 K" }, "geometry": { "type": "Point", "coordinates": [ -155.50485, 19.59615, 0.0 ] } }
]
}
