{
"type": "FeatureCollection",
"crs": { "type": "name", "properties": { "name": "urn:ogc:def:crs:OGC:1.3:CRS84" } },
"features": [
{ "type": "Feature", "properties": { "Name": "Fire Detection Centroid ", "Description": "<b>Latitude: <\/b> 19.40927<br\/>  <b>Longitude: <\/b> -155.28674<br\/>  <b>Detection Time: <\/b> 2023-04-17 12:51 UTC<br\/>  <b>Sensor: <\/b> NOAA-20 VIIRS<br\/> <b>Confidence: <\/b> Nominal<br\/>  <b>Day\/Night: <\/b> Night<br\/> <b>Scan: <\/b> 0.66 km<br\/> <b>Track: <\/b> 0.73 km<br\/> <b>FRP: <\/b> 2.94 MW<br\/> <b>Brightness: <\/b> 298.96 K" }, "geometry": { "type": "Point", "coordinates": [ -155.28674, 19.40927, 0.0 ] } }
]
}
