{
"type": "FeatureCollection",
"crs": { "type": "name", "properties": { "name": "urn:ogc:def:crs:OGC:1.3:CRS84" } },
"features": [
{ "type": "Feature", "properties": { "Name": "Fire Detection Centroid ", "Description": "<b>Latitude: <\/b> 18.31269<br\/>  <b>Longitude: <\/b> -72.41318<br\/>  <b>Detection Time: <\/b> 2024-01-08 06:19 UTC<br\/>  <b>Sensor: <\/b> NOAA-20 VIIRS<br\/> <b>Confidence: <\/b> Nominal<br\/>  <b>Day\/Night: <\/b> Night<br\/> <b>Scan: <\/b> 0.4 km<br\/> <b>Track: <\/b> 0.4 km<br\/> <b>FRP: <\/b> 0.42 MW<br\/> <b>Brightness: <\/b> 301.76 K" }, "geometry": { "type": "Point", "coordinates": [ -72.41318, 18.31269, 0.0 ] } },
{ "type": "Feature", "properties": { "Name": "Fire Detection Centroid ", "Description": "<b>Latitude: <\/b> 18.82087<br\/>  <b>Longitude: <\/b> -68.65633<br\/>  <b>Detection Time: <\/b> 2024-01-08 06:19 UTC<br\/>  <b>Sensor: <\/b> NOAA-20 VIIRS<br\/> <b>Confidence: <\/b> Nominal<br\/>  <b>Day\/Night: <\/b> Night<br\/> <b>Scan: <\/b> 0.4 km<br\/> <b>Track: <\/b> 0.4 km<br\/> <b>FRP: <\/b> 0.67 MW<br\/> <b>Brightness: <\/b> 313.59 K" }, "geometry": { "type": "Point", "coordinates": [ -68.65633, 18.82087, 0.0 ] } },
{ "type": "Feature", "properties": { "Name": "Fire Detection Centroid ", "Description": "<b>Latitude: <\/b> 18.3589<br\/>  <b>Longitude: <\/b> -71.21893<br\/>  <b>Detection Time: <\/b> 2024-01-08 06:19 UTC<br\/>  <b>Sensor: <\/b> NOAA-20 VIIRS<br\/> <b>Confidence: <\/b> Nominal<br\/>  <b>Day\/Night: <\/b> Night<br\/> <b>Scan: <\/b> 0.4 km<br\/> <b>Track: <\/b> 0.4 km<br\/> <b>FRP: <\/b> 9.18 MW<br\/> <b>Brightness: <\/b> 344.73 K" }, "geometry": { "type": "Point", "coordinates": [ -71.21893, 18.3589, 0.0 ] } },
{ "type": "Feature", "properties": { "Name": "Fire Detection Centroid ", "Description": "<b>Latitude: <\/b> 18.3556<br\/>  <b>Longitude: <\/b> -71.2195<br\/>  <b>Detection Time: <\/b> 2024-01-08 06:19 UTC<br\/>  <b>Sensor: <\/b> NOAA-20 VIIRS<br\/> <b>Confidence: <\/b> Nominal<br\/>  <b>Day\/Night: <\/b> Night<br\/> <b>Scan: <\/b> 0.4 km<br\/> <b>Track: <\/b> 0.4 km<br\/> <b>FRP: <\/b> 1.33 MW<br\/> <b>Brightness: <\/b> 308.42 K" }, "geometry": { "type": "Point", "coordinates": [ -71.2195, 18.3556, 0.0 ] } },
{ "type": "Feature", "properties": { "Name": "Fire Detection Centroid ", "Description": "<b>Latitude: <\/b> 36.35833<br\/>  <b>Longitude: <\/b> -76.80725<br\/>  <b>Detection Time: <\/b> 2024-01-08 06:14 UTC<br\/>  <b>Sensor: <\/b> NOAA-20 VIIRS<br\/> <b>Confidence: <\/b> Nominal<br\/>  <b>Day\/Night: <\/b> Night<br\/> <b>Scan: <\/b> 0.3 km<br\/> <b>Track: <\/b> 0.6 km<br\/> <b>FRP: <\/b> 1.76 MW<br\/> <b>Brightness: <\/b> 327.14 K" }, "geometry": { "type": "Point", "coordinates": [ -76.80725, 36.35833, 0.0 ] } },
{ "type": "Feature", "properties": { "Name": "Fire Detection Centroid ", "Description": "<b>Latitude: <\/b> 39.59279<br\/>  <b>Longitude: <\/b> -75.63634<br\/>  <b>Detection Time: <\/b> 2024-01-08 06:14 UTC<br\/>  <b>Sensor: <\/b> NOAA-20 VIIRS<br\/> <b>Confidence: <\/b> Nominal<br\/>  <b>Day\/Night: <\/b> Night<br\/> <b>Scan: <\/b> 0.3 km<br\/> <b>Track: <\/b> 0.6 km<br\/> <b>FRP: <\/b> 0.7 MW<br\/> <b>Brightness: <\/b> 295.21 K" }, "geometry": { "type": "Point", "coordinates": [ -75.63634, 39.59279, 0.0 ] } },
{ "type": "Feature", "properties": { "Name": "Fire Detection Centroid ", "Description": "<b>Latitude: <\/b> 39.58769<br\/>  <b>Longitude: <\/b> -75.63686<br\/>  <b>Detection Time: <\/b> 2024-01-08 06:14 UTC<br\/>  <b>Sensor: <\/b> NOAA-20 VIIRS<br\/> <b>Confidence: <\/b> Nominal<br\/>  <b>Day\/Night: <\/b> Night<br\/> <b>Scan: <\/b> 0.3 km<br\/> <b>Track: <\/b> 0.6 km<br\/> <b>FRP: <\/b> 0.7 MW<br\/> <b>Brightness: <\/b> 296.46 K" }, "geometry": { "type": "Point", "coordinates": [ -75.63686, 39.58769, 0.0 ] } },
{ "type": "Feature", "properties": { "Name": "Fire Detection Centroid ", "Description": "<b>Latitude: <\/b> 40.15445<br\/>  <b>Longitude: <\/b> -74.7723<br\/>  <b>Detection Time: <\/b> 2024-01-08 06:13 UTC<br\/>  <b>Sensor: <\/b> NOAA-20 VIIRS<br\/> <b>Confidence: <\/b> Nominal<br\/>  <b>Day\/Night: <\/b> Night<br\/> <b>Scan: <\/b> 0.6 km<br\/> <b>Track: <\/b> 0.5 km<br\/> <b>FRP: <\/b> 1.72 MW<br\/> <b>Brightness: <\/b> 306.38 K" }, "geometry": { "type": "Point", "coordinates": [ -74.7723, 40.15445, 0.0 ] } },
{ "type": "Feature", "properties": { "Name": "Fire Detection Centroid ", "Description": "<b>Latitude: <\/b> 48.18836<br\/>  <b>Longitude: <\/b> -64.92062<br\/>  <b>Detection Time: <\/b> 2024-01-08 06:11 UTC<br\/>  <b>Sensor: <\/b> NOAA-20 VIIRS<br\/> <b>Confidence: <\/b> Nominal<br\/>  <b>Day\/Night: <\/b> Night<br\/> <b>Scan: <\/b> 0.4 km<br\/> <b>Track: <\/b> 0.4 km<br\/> <b>FRP: <\/b> 0.75 MW<br\/> <b>Brightness: <\/b> 299.53 K" }, "geometry": { "type": "Point", "coordinates": [ -64.92062, 48.18836, 0.0 ] } }
]
}
