{
"type": "FeatureCollection",
"crs": { "type": "name", "properties": { "name": "urn:ogc:def:crs:OGC:1.3:CRS84" } },
"features": [
{ "type": "Feature", "properties": { "Name": "Fire Detection Centroid ", "Description": "<b>Latitude: <\/b> 45.83586<br\/>  <b>Longitude: <\/b> -73.24869<br\/>  <b>Detection Time: <\/b> 2022-08-21 17:06 UTC<br\/>  <b>Sensor: <\/b> NOAA-20 VIIRS<br\/> <b>Confidence: <\/b> Nominal<br\/>  <b>Day\/Night: <\/b> Day<br\/> <b>Scan: <\/b> 0.5 km<br\/> <b>Track: <\/b> 0.5 km<br\/> <b>FRP: <\/b> 6.31 MW<br\/> <b>Brightness: <\/b> 333.29 K" }, "geometry": { "type": "Point", "coordinates": [ -73.24869, 45.83586, 0.0 ] } }
]
}
