{
"type": "FeatureCollection",
"crs": { "type": "name", "properties": { "name": "urn:ogc:def:crs:OGC:1.3:CRS84" } },
"features": [
{ "type": "Feature", "properties": { "Name": "Fire Detection Centroid ", "Description": "<b>Latitude: <\/b> 18.68852<br\/>  <b>Longitude: <\/b> -71.40469<br\/>  <b>Detection Time: <\/b> 2024-01-09 17:11 UTC<br\/>  <b>Sensor: <\/b> NOAA-20 VIIRS<br\/> <b>Confidence: <\/b> High<br\/>  <b>Day\/Night: <\/b> Day<br\/> <b>Scan: <\/b> 0.5 km<br\/> <b>Track: <\/b> 0.7 km<br\/> <b>FRP: <\/b> 13.8 MW<br\/> <b>Brightness: <\/b> 367 K" }, "geometry": { "type": "Point", "coordinates": [ -71.40469, 18.68852, 0.0 ] } },
{ "type": "Feature", "properties": { "Name": "Fire Detection Centroid ", "Description": "<b>Latitude: <\/b> 18.62796<br\/>  <b>Longitude: <\/b> -71.41874<br\/>  <b>Detection Time: <\/b> 2024-01-09 17:11 UTC<br\/>  <b>Sensor: <\/b> NOAA-20 VIIRS<br\/> <b>Confidence: <\/b> Nominal<br\/>  <b>Day\/Night: <\/b> Day<br\/> <b>Scan: <\/b> 0.5 km<br\/> <b>Track: <\/b> 0.7 km<br\/> <b>FRP: <\/b> 3.55 MW<br\/> <b>Brightness: <\/b> 326.36 K" }, "geometry": { "type": "Point", "coordinates": [ -71.41874, 18.62796, 0.0 ] } },
{ "type": "Feature", "properties": { "Name": "Fire Detection Centroid ", "Description": "<b>Latitude: <\/b> 18.00546<br\/>  <b>Longitude: <\/b> -66.98577<br\/>  <b>Detection Time: <\/b> 2024-01-09 17:11 UTC<br\/>  <b>Sensor: <\/b> NOAA-20 VIIRS<br\/> <b>Confidence: <\/b> Nominal<br\/>  <b>Day\/Night: <\/b> Day<br\/> <b>Scan: <\/b> 0.6 km<br\/> <b>Track: <\/b> 0.5 km<br\/> <b>FRP: <\/b> 7.28 MW<br\/> <b>Brightness: <\/b> 350.31 K" }, "geometry": { "type": "Point", "coordinates": [ -66.98577, 18.00546, 0.0 ] } },
{ "type": "Feature", "properties": { "Name": "Fire Detection Centroid ", "Description": "<b>Latitude: <\/b> 18.00079<br\/>  <b>Longitude: <\/b> -66.98474<br\/>  <b>Detection Time: <\/b> 2024-01-09 17:11 UTC<br\/>  <b>Sensor: <\/b> NOAA-20 VIIRS<br\/> <b>Confidence: <\/b> Nominal<br\/>  <b>Day\/Night: <\/b> Day<br\/> <b>Scan: <\/b> 0.6 km<br\/> <b>Track: <\/b> 0.5 km<br\/> <b>FRP: <\/b> 22.09 MW<br\/> <b>Brightness: <\/b> 354.03 K" }, "geometry": { "type": "Point", "coordinates": [ -66.98474, 18.00079, 0.0 ] } },
{ "type": "Feature", "properties": { "Name": "Fire Detection Centroid ", "Description": "<b>Latitude: <\/b> 18.00647<br\/>  <b>Longitude: <\/b> -66.98056<br\/>  <b>Detection Time: <\/b> 2024-01-09 17:11 UTC<br\/>  <b>Sensor: <\/b> NOAA-20 VIIRS<br\/> <b>Confidence: <\/b> Low<br\/>  <b>Day\/Night: <\/b> Day<br\/> <b>Scan: <\/b> 0.6 km<br\/> <b>Track: <\/b> 0.5 km<br\/> <b>FRP: <\/b> 7.28 MW<br\/> <b>Brightness: <\/b> 328.14 K" }, "geometry": { "type": "Point", "coordinates": [ -66.98056, 18.00647, 0.0 ] } },
{ "type": "Feature", "properties": { "Name": "Fire Detection Centroid ", "Description": "<b>Latitude: <\/b> 17.88524<br\/>  <b>Longitude: <\/b> -71.28028<br\/>  <b>Detection Time: <\/b> 2024-01-09 17:11 UTC<br\/>  <b>Sensor: <\/b> NOAA-20 VIIRS<br\/> <b>Confidence: <\/b> Nominal<br\/>  <b>Day\/Night: <\/b> Day<br\/> <b>Scan: <\/b> 0.5 km<br\/> <b>Track: <\/b> 0.7 km<br\/> <b>FRP: <\/b> 2.77 MW<br\/> <b>Brightness: <\/b> 327.92 K" }, "geometry": { "type": "Point", "coordinates": [ -71.28028, 17.88524, 0.0 ] } },
{ "type": "Feature", "properties": { "Name": "Fire Detection Centroid ", "Description": "<b>Latitude: <\/b> 18.6828<br\/>  <b>Longitude: <\/b> -71.40176<br\/>  <b>Detection Time: <\/b> 2024-01-09 17:11 UTC<br\/>  <b>Sensor: <\/b> NOAA-20 VIIRS<br\/> <b>Confidence: <\/b> Nominal<br\/>  <b>Day\/Night: <\/b> Day<br\/> <b>Scan: <\/b> 0.5 km<br\/> <b>Track: <\/b> 0.7 km<br\/> <b>FRP: <\/b> 13.8 MW<br\/> <b>Brightness: <\/b> 351.59 K" }, "geometry": { "type": "Point", "coordinates": [ -71.40176, 18.6828, 0.0 ] } }
]
}
