{
"type": "FeatureCollection",
"crs": { "type": "name", "properties": { "name": "urn:ogc:def:crs:OGC:1.3:CRS84" } },
"features": [
{ "type": "Feature", "properties": { "Name": "Fire Detection Centroid ", "Description": "<b>Latitude: <\/b> 49.58563<br\/>  <b>Longitude: <\/b> -126.2795<br\/>  <b>Detection Time: <\/b> 2023-08-18 22:25 UTC<br\/>  <b>Sensor: <\/b> NOAA-20 VIIRS<br\/> <b>Confidence: <\/b> Nominal<br\/>  <b>Day\/Night: <\/b> Day<br\/> <b>Scan: <\/b> 0.62 km<br\/> <b>Track: <\/b> 0.71 km<br\/> <b>FRP: <\/b> 4.46 MW<br\/> <b>Brightness: <\/b> 325.74 K" }, "geometry": { "type": "Point", "coordinates": [ -126.2795, 49.58563, 0.0 ] } },
{ "type": "Feature", "properties": { "Name": "Fire Detection Centroid ", "Description": "<b>Latitude: <\/b> 49.59229<br\/>  <b>Longitude: <\/b> -126.28009<br\/>  <b>Detection Time: <\/b> 2023-08-18 22:25 UTC<br\/>  <b>Sensor: <\/b> NOAA-20 VIIRS<br\/> <b>Confidence: <\/b> Nominal<br\/>  <b>Day\/Night: <\/b> Day<br\/> <b>Scan: <\/b> 0.62 km<br\/> <b>Track: <\/b> 0.71 km<br\/> <b>FRP: <\/b> 47.54 MW<br\/> <b>Brightness: <\/b> 347.99 K" }, "geometry": { "type": "Point", "coordinates": [ -126.28009, 49.59229, 0.0 ] } },
{ "type": "Feature", "properties": { "Name": "Fire Detection Centroid ", "Description": "<b>Latitude: <\/b> 49.59222<br\/>  <b>Longitude: <\/b> -126.27431<br\/>  <b>Detection Time: <\/b> 2023-08-18 22:25 UTC<br\/>  <b>Sensor: <\/b> NOAA-20 VIIRS<br\/> <b>Confidence: <\/b> High<br\/>  <b>Day\/Night: <\/b> Day<br\/> <b>Scan: <\/b> 0.62 km<br\/> <b>Track: <\/b> 0.72 km<br\/> <b>FRP: <\/b> 47.54 MW<br\/> <b>Brightness: <\/b> 367 K" }, "geometry": { "type": "Point", "coordinates": [ -126.27431, 49.59222, 0.0 ] } },
{ "type": "Feature", "properties": { "Name": "Fire Detection Centroid ", "Description": "<b>Latitude: <\/b> 49.58852<br\/>  <b>Longitude: <\/b> -126.26972<br\/>  <b>Detection Time: <\/b> 2023-08-18 22:25 UTC<br\/>  <b>Sensor: <\/b> NOAA-20 VIIRS<br\/> <b>Confidence: <\/b> Nominal<br\/>  <b>Day\/Night: <\/b> Day<br\/> <b>Scan: <\/b> 0.62 km<br\/> <b>Track: <\/b> 0.72 km<br\/> <b>FRP: <\/b> 42.14 MW<br\/> <b>Brightness: <\/b> 337.71 K" }, "geometry": { "type": "Point", "coordinates": [ -126.26972, 49.58852, 0.0 ] } },
{ "type": "Feature", "properties": { "Name": "Fire Detection Centroid ", "Description": "<b>Latitude: <\/b> 49.58856<br\/>  <b>Longitude: <\/b> -126.27493<br\/>  <b>Detection Time: <\/b> 2023-08-18 22:25 UTC<br\/>  <b>Sensor: <\/b> NOAA-20 VIIRS<br\/> <b>Confidence: <\/b> Nominal<br\/>  <b>Day\/Night: <\/b> Day<br\/> <b>Scan: <\/b> 0.62 km<br\/> <b>Track: <\/b> 0.71 km<br\/> <b>FRP: <\/b> 42.14 MW<br\/> <b>Brightness: <\/b> 356.59 K" }, "geometry": { "type": "Point", "coordinates": [ -126.27493, 49.58856, 0.0 ] } },
{ "type": "Feature", "properties": { "Name": "Fire Detection Centroid ", "Description": "<b>Latitude: <\/b> 49.58861<br\/>  <b>Longitude: <\/b> -126.28083<br\/>  <b>Detection Time: <\/b> 2023-08-18 22:25 UTC<br\/>  <b>Sensor: <\/b> NOAA-20 VIIRS<br\/> <b>Confidence: <\/b> Nominal<br\/>  <b>Day\/Night: <\/b> Day<br\/> <b>Scan: <\/b> 0.62 km<br\/> <b>Track: <\/b> 0.71 km<br\/> <b>FRP: <\/b> 67.05 MW<br\/> <b>Brightness: <\/b> 335.81 K" }, "geometry": { "type": "Point", "coordinates": [ -126.28083, 49.58861, 0.0 ] } },
{ "type": "Feature", "properties": { "Name": "Fire Detection Centroid ", "Description": "<b>Latitude: <\/b> 49.58556<br\/>  <b>Longitude: <\/b> -126.27337<br\/>  <b>Detection Time: <\/b> 2023-08-18 22:25 UTC<br\/>  <b>Sensor: <\/b> NOAA-20 VIIRS<br\/> <b>Confidence: <\/b> Nominal<br\/>  <b>Day\/Night: <\/b> Day<br\/> <b>Scan: <\/b> 0.62 km<br\/> <b>Track: <\/b> 0.72 km<br\/> <b>FRP: <\/b> 4.46 MW<br\/> <b>Brightness: <\/b> 331.84 K" }, "geometry": { "type": "Point", "coordinates": [ -126.27337, 49.58556, 0.0 ] } }
]
}
