{
"type": "FeatureCollection",
"crs": { "type": "name", "properties": { "name": "urn:ogc:def:crs:OGC:1.3:CRS84" } },
"features": [
{ "type": "Feature", "properties": { "Name": "Fire Detection Centroid ", "Description": "<b>Latitude: <\/b> 19.40422<br\/>  <b>Longitude: <\/b> -155.27917<br\/>  <b>Detection Time: <\/b> 2022-11-25 23:43 UTC<br\/>  <b>Sensor: <\/b> NOAA-20 VIIRS<br\/> <b>Confidence: <\/b> Nominal<br\/>  <b>Day\/Night: <\/b> Day<br\/> <b>Scan: <\/b> 0.4 km<br\/> <b>Track: <\/b> 0.4 km<br\/> <b>FRP: <\/b> 19.26 MW<br\/> <b>Brightness: <\/b> 332.98 K" }, "geometry": { "type": "Point", "coordinates": [ -155.27917, 19.40422, 0.0 ] } },
{ "type": "Feature", "properties": { "Name": "Fire Detection Centroid ", "Description": "<b>Latitude: <\/b> 19.40656<br\/>  <b>Longitude: <\/b> -155.28793<br\/>  <b>Detection Time: <\/b> 2022-11-25 23:43 UTC<br\/>  <b>Sensor: <\/b> NOAA-20 VIIRS<br\/> <b>Confidence: <\/b> Nominal<br\/>  <b>Day\/Night: <\/b> Day<br\/> <b>Scan: <\/b> 0.4 km<br\/> <b>Track: <\/b> 0.4 km<br\/> <b>FRP: <\/b> 17.35 MW<br\/> <b>Brightness: <\/b> 351.68 K" }, "geometry": { "type": "Point", "coordinates": [ -155.28793, 19.40656, 0.0 ] } },
{ "type": "Feature", "properties": { "Name": "Fire Detection Centroid ", "Description": "<b>Latitude: <\/b> 19.40598<br\/>  <b>Longitude: <\/b> -155.2921<br\/>  <b>Detection Time: <\/b> 2022-11-25 23:43 UTC<br\/>  <b>Sensor: <\/b> NOAA-20 VIIRS<br\/> <b>Confidence: <\/b> Nominal<br\/>  <b>Day\/Night: <\/b> Day<br\/> <b>Scan: <\/b> 0.4 km<br\/> <b>Track: <\/b> 0.4 km<br\/> <b>FRP: <\/b> 17.35 MW<br\/> <b>Brightness: <\/b> 332.76 K" }, "geometry": { "type": "Point", "coordinates": [ -155.2921, 19.40598, 0.0 ] } },
{ "type": "Feature", "properties": { "Name": "Fire Detection Centroid ", "Description": "<b>Latitude: <\/b> 19.39959<br\/>  <b>Longitude: <\/b> -155.28688<br\/>  <b>Detection Time: <\/b> 2022-11-25 23:43 UTC<br\/>  <b>Sensor: <\/b> NOAA-20 VIIRS<br\/> <b>Confidence: <\/b> Nominal<br\/>  <b>Day\/Night: <\/b> Day<br\/> <b>Scan: <\/b> 0.4 km<br\/> <b>Track: <\/b> 0.4 km<br\/> <b>FRP: <\/b> 33.81 MW<br\/> <b>Brightness: <\/b> 334.57 K" }, "geometry": { "type": "Point", "coordinates": [ -155.28688, 19.39959, 0.0 ] } },
{ "type": "Feature", "properties": { "Name": "Fire Detection Centroid ", "Description": "<b>Latitude: <\/b> 19.40713<br\/>  <b>Longitude: <\/b> -155.28381<br\/>  <b>Detection Time: <\/b> 2022-11-25 23:43 UTC<br\/>  <b>Sensor: <\/b> NOAA-20 VIIRS<br\/> <b>Confidence: <\/b> Nominal<br\/>  <b>Day\/Night: <\/b> Day<br\/> <b>Scan: <\/b> 0.4 km<br\/> <b>Track: <\/b> 0.4 km<br\/> <b>FRP: <\/b> 14.33 MW<br\/> <b>Brightness: <\/b> 339.44 K" }, "geometry": { "type": "Point", "coordinates": [ -155.28381, 19.40713, 0.0 ] } },
{ "type": "Feature", "properties": { "Name": "Fire Detection Centroid ", "Description": "<b>Latitude: <\/b> 19.40308<br\/>  <b>Longitude: <\/b> -155.28738<br\/>  <b>Detection Time: <\/b> 2022-11-25 23:43 UTC<br\/>  <b>Sensor: <\/b> NOAA-20 VIIRS<br\/> <b>Confidence: <\/b> High<br\/>  <b>Day\/Night: <\/b> Day<br\/> <b>Scan: <\/b> 0.4 km<br\/> <b>Track: <\/b> 0.4 km<br\/> <b>FRP: <\/b> 33.81 MW<br\/> <b>Brightness: <\/b> 367 K" }, "geometry": { "type": "Point", "coordinates": [ -155.28738, 19.40308, 0.0 ] } },
{ "type": "Feature", "properties": { "Name": "Fire Detection Centroid ", "Description": "<b>Latitude: <\/b> 19.40365<br\/>  <b>Longitude: <\/b> -155.28326<br\/>  <b>Detection Time: <\/b> 2022-11-25 23:43 UTC<br\/>  <b>Sensor: <\/b> NOAA-20 VIIRS<br\/> <b>Confidence: <\/b> Nominal<br\/>  <b>Day\/Night: <\/b> Day<br\/> <b>Scan: <\/b> 0.4 km<br\/> <b>Track: <\/b> 0.4 km<br\/> <b>FRP: <\/b> 19.26 MW<br\/> <b>Brightness: <\/b> 345.2 K" }, "geometry": { "type": "Point", "coordinates": [ -155.28326, 19.40365, 0.0 ] } },
{ "type": "Feature", "properties": { "Name": "Fire Detection Centroid ", "Description": "<b>Latitude: <\/b> 19.4025<br\/>  <b>Longitude: <\/b> -155.29153<br\/>  <b>Detection Time: <\/b> 2022-11-25 23:43 UTC<br\/>  <b>Sensor: <\/b> NOAA-20 VIIRS<br\/> <b>Confidence: <\/b> Nominal<br\/>  <b>Day\/Night: <\/b> Day<br\/> <b>Scan: <\/b> 0.4 km<br\/> <b>Track: <\/b> 0.4 km<br\/> <b>FRP: <\/b> 33.81 MW<br\/> <b>Brightness: <\/b> 330.99 K" }, "geometry": { "type": "Point", "coordinates": [ -155.29153, 19.4025, 0.0 ] } }
]
}
