{
"type": "FeatureCollection",
"crs": { "type": "name", "properties": { "name": "urn:ogc:def:crs:OGC:1.3:CRS84" } },
"features": [
{ "type": "Feature", "properties": { "Name": "Fire Detection Centroid ", "Description": "<b>Latitude: <\/b> 19.40469<br\/>  <b>Longitude: <\/b> -155.284<br\/>  <b>Detection Time: <\/b> 2023-12-12 11:29 UTC<br\/>  <b>Sensor: <\/b> NOAA-20 VIIRS<br\/> <b>Confidence: <\/b> Nominal<br\/>  <b>Day\/Night: <\/b> Night<br\/> <b>Scan: <\/b> 0.5 km<br\/> <b>Track: <\/b> 0.49 km<br\/> <b>FRP: <\/b> 2.26 MW<br\/> <b>Brightness: <\/b> 302.35 K" }, "geometry": { "type": "Point", "coordinates": [ -155.284, 19.40469, 0.0 ] } },
{ "type": "Feature", "properties": { "Name": "Fire Detection Centroid ", "Description": "<b>Latitude: <\/b> 45.22915<br\/>  <b>Longitude: <\/b> -123.16872<br\/>  <b>Detection Time: <\/b> 2023-12-12 11:21 UTC<br\/>  <b>Sensor: <\/b> NOAA-20 VIIRS<br\/> <b>Confidence: <\/b> Nominal<br\/>  <b>Day\/Night: <\/b> Night<br\/> <b>Scan: <\/b> 0.56 km<br\/> <b>Track: <\/b> 0.69 km<br\/> <b>FRP: <\/b> 1.98 MW<br\/> <b>Brightness: <\/b> 317.32 K" }, "geometry": { "type": "Point", "coordinates": [ -123.16872, 45.22915, 0.0 ] } },
{ "type": "Feature", "properties": { "Name": "Fire Detection Centroid ", "Description": "<b>Latitude: <\/b> 45.22932<br\/>  <b>Longitude: <\/b> -123.16539<br\/>  <b>Detection Time: <\/b> 2023-12-12 11:21 UTC<br\/>  <b>Sensor: <\/b> NOAA-20 VIIRS<br\/> <b>Confidence: <\/b> Nominal<br\/>  <b>Day\/Night: <\/b> Night<br\/> <b>Scan: <\/b> 0.6 km<br\/> <b>Track: <\/b> 0.7 km<br\/> <b>FRP: <\/b> 1.98 MW<br\/> <b>Brightness: <\/b> 317.32 K" }, "geometry": { "type": "Point", "coordinates": [ -123.16539, 45.22932, 0.0 ] } }
]
}
