{
"type": "FeatureCollection",
"crs": { "type": "name", "properties": { "name": "urn:ogc:def:crs:OGC:1.3:CRS84" } },
"features": [
{ "type": "Feature", "properties": { "Name": "Fire Detection Centroid ", "Description": "<b>Latitude: <\/b> 34.34708<br\/>  <b>Longitude: <\/b> -119.25338<br\/>  <b>Detection Time: <\/b> 2024-03-08 10:53 UTC<br\/>  <b>Sensor: <\/b> NOAA-20 VIIRS<br\/> <b>Confidence: <\/b> Nominal<br\/>  <b>Day\/Night: <\/b> Night<br\/> <b>Scan: <\/b> 0.8 km<br\/> <b>Track: <\/b> 0.8 km<br\/> <b>FRP: <\/b> 0.87 MW<br\/> <b>Brightness: <\/b> 300.12 K" }, "geometry": { "type": "Point", "coordinates": [ -119.25338, 34.34708, 0.0 ] } },
{ "type": "Feature", "properties": { "Name": "Fire Detection Centroid ", "Description": "<b>Latitude: <\/b> 34.31291<br\/>  <b>Longitude: <\/b> -119.27021<br\/>  <b>Detection Time: <\/b> 2024-03-08 10:53 UTC<br\/>  <b>Sensor: <\/b> NOAA-20 VIIRS<br\/> <b>Confidence: <\/b> Nominal<br\/>  <b>Day\/Night: <\/b> Night<br\/> <b>Scan: <\/b> 0.77 km<br\/> <b>Track: <\/b> 0.77 km<br\/> <b>FRP: <\/b> 0.88 MW<br\/> <b>Brightness: <\/b> 300.12 K" }, "geometry": { "type": "Point", "coordinates": [ -119.27021, 34.31291, 0.0 ] } },
{ "type": "Feature", "properties": { "Name": "Fire Detection Centroid ", "Description": "<b>Latitude: <\/b> 39.16124<br\/>  <b>Longitude: <\/b> -121.88138<br\/>  <b>Detection Time: <\/b> 2024-03-08 10:52 UTC<br\/>  <b>Sensor: <\/b> NOAA-20 VIIRS<br\/> <b>Confidence: <\/b> Nominal<br\/>  <b>Day\/Night: <\/b> Night<br\/> <b>Scan: <\/b> 0.4 km<br\/> <b>Track: <\/b> 0.6 km<br\/> <b>FRP: <\/b> 0.69 MW<br\/> <b>Brightness: <\/b> 299.9 K" }, "geometry": { "type": "Point", "coordinates": [ -121.88138, 39.16124, 0.0 ] } },
{ "type": "Feature", "properties": { "Name": "Fire Detection Centroid ", "Description": "<b>Latitude: <\/b> 37.96598<br\/>  <b>Longitude: <\/b> -122.13442<br\/>  <b>Detection Time: <\/b> 2024-03-08 10:52 UTC<br\/>  <b>Sensor: <\/b> NOAA-20 VIIRS<br\/> <b>Confidence: <\/b> Nominal<br\/>  <b>Day\/Night: <\/b> Night<br\/> <b>Scan: <\/b> 0.4 km<br\/> <b>Track: <\/b> 0.6 km<br\/> <b>FRP: <\/b> 1.26 MW<br\/> <b>Brightness: <\/b> 295.06 K" }, "geometry": { "type": "Point", "coordinates": [ -122.13442, 37.96598, 0.0 ] } },
{ "type": "Feature", "properties": { "Name": "Fire Detection Centroid ", "Description": "<b>Latitude: <\/b> 39.16587<br\/>  <b>Longitude: <\/b> -121.88011<br\/>  <b>Detection Time: <\/b> 2024-03-08 10:51 UTC<br\/>  <b>Sensor: <\/b> NOAA-20 VIIRS<br\/> <b>Confidence: <\/b> Nominal<br\/>  <b>Day\/Night: <\/b> Night<br\/> <b>Scan: <\/b> 0.41 km<br\/> <b>Track: <\/b> 0.61 km<br\/> <b>FRP: <\/b> 0.69 MW<br\/> <b>Brightness: <\/b> 299.9 K" }, "geometry": { "type": "Point", "coordinates": [ -121.88011, 39.16587, 0.0 ] } },
{ "type": "Feature", "properties": { "Name": "Fire Detection Centroid ", "Description": "<b>Latitude: <\/b> 38.01316<br\/>  <b>Longitude: <\/b> -122.11189<br\/>  <b>Detection Time: <\/b> 2024-03-08 10:51 UTC<br\/>  <b>Sensor: <\/b> NOAA-20 VIIRS<br\/> <b>Confidence: <\/b> Nominal<br\/>  <b>Day\/Night: <\/b> Night<br\/> <b>Scan: <\/b> 0.43 km<br\/> <b>Track: <\/b> 0.62 km<br\/> <b>FRP: <\/b> 1.27 MW<br\/> <b>Brightness: <\/b> 295.06 K" }, "geometry": { "type": "Point", "coordinates": [ -122.11189, 38.01316, 0.0 ] } }
]
}
