{
"type": "FeatureCollection",
"crs": { "type": "name", "properties": { "name": "urn:ogc:def:crs:OGC:1.3:CRS84" } },
"features": [
{ "type": "Feature", "properties": { "Name": "Fire Detection Centroid ", "Description": "<b>Latitude: <\/b> 20.81781<br\/>  <b>Longitude: <\/b> -156.62044<br\/>  <b>Detection Time: <\/b> 2023-06-28 12:02 UTC<br\/>  <b>Sensor: <\/b> NOAA-20 VIIRS<br\/> <b>Confidence: <\/b> Nominal<br\/>  <b>Day\/Night: <\/b> Night<br\/> <b>Scan: <\/b> 0.39 km<br\/> <b>Track: <\/b> 0.36 km<br\/> <b>FRP: <\/b> 1.1 MW<br\/> <b>Brightness: <\/b> 308.2 K" }, "geometry": { "type": "Point", "coordinates": [ -156.62044, 20.81781, 0.0 ] } },
{ "type": "Feature", "properties": { "Name": "Fire Detection Centroid ", "Description": "<b>Latitude: <\/b> 19.59957<br\/>  <b>Longitude: <\/b> -155.504<br\/>  <b>Detection Time: <\/b> 2023-06-28 12:02 UTC<br\/>  <b>Sensor: <\/b> NOAA-20 VIIRS<br\/> <b>Confidence: <\/b> Nominal<br\/>  <b>Day\/Night: <\/b> Night<br\/> <b>Scan: <\/b> 0.39 km<br\/> <b>Track: <\/b> 0.36 km<br\/> <b>FRP: <\/b> 0.98 MW<br\/> <b>Brightness: <\/b> 297.39 K" }, "geometry": { "type": "Point", "coordinates": [ -155.504, 19.59957, 0.0 ] } },
{ "type": "Feature", "properties": { "Name": "Fire Detection Centroid ", "Description": "<b>Latitude: <\/b> 19.59629<br\/>  <b>Longitude: <\/b> -155.50461<br\/>  <b>Detection Time: <\/b> 2023-06-28 12:02 UTC<br\/>  <b>Sensor: <\/b> NOAA-20 VIIRS<br\/> <b>Confidence: <\/b> Nominal<br\/>  <b>Day\/Night: <\/b> Night<br\/> <b>Scan: <\/b> 0.39 km<br\/> <b>Track: <\/b> 0.36 km<br\/> <b>FRP: <\/b> 0.98 MW<br\/> <b>Brightness: <\/b> 299.85 K" }, "geometry": { "type": "Point", "coordinates": [ -155.50461, 19.59629, 0.0 ] } },
{ "type": "Feature", "properties": { "Name": "Fire Detection Centroid ", "Description": "<b>Latitude: <\/b> 19.40784<br\/>  <b>Longitude: <\/b> -155.28783<br\/>  <b>Detection Time: <\/b> 2023-06-28 12:02 UTC<br\/>  <b>Sensor: <\/b> NOAA-20 VIIRS<br\/> <b>Confidence: <\/b> Nominal<br\/>  <b>Day\/Night: <\/b> Night<br\/> <b>Scan: <\/b> 0.39 km<br\/> <b>Track: <\/b> 0.36 km<br\/> <b>FRP: <\/b> 0.55 MW<br\/> <b>Brightness: <\/b> 298.15 K" }, "geometry": { "type": "Point", "coordinates": [ -155.28783, 19.40784, 0.0 ] } },
{ "type": "Feature", "properties": { "Name": "Fire Detection Centroid ", "Description": "<b>Latitude: <\/b> 19.40725<br\/>  <b>Longitude: <\/b> -155.28413<br\/>  <b>Detection Time: <\/b> 2023-06-28 12:02 UTC<br\/>  <b>Sensor: <\/b> NOAA-20 VIIRS<br\/> <b>Confidence: <\/b> Nominal<br\/>  <b>Day\/Night: <\/b> Night<br\/> <b>Scan: <\/b> 0.39 km<br\/> <b>Track: <\/b> 0.36 km<br\/> <b>FRP: <\/b> 0.55 MW<br\/> <b>Brightness: <\/b> 297.15 K" }, "geometry": { "type": "Point", "coordinates": [ -155.28413, 19.40725, 0.0 ] } },
{ "type": "Feature", "properties": { "Name": "Fire Detection Centroid ", "Description": "<b>Latitude: <\/b> 19.40454<br\/>  <b>Longitude: <\/b> -155.28841<br\/>  <b>Detection Time: <\/b> 2023-06-28 12:02 UTC<br\/>  <b>Sensor: <\/b> NOAA-20 VIIRS<br\/> <b>Confidence: <\/b> Nominal<br\/>  <b>Day\/Night: <\/b> Night<br\/> <b>Scan: <\/b> 0.39 km<br\/> <b>Track: <\/b> 0.36 km<br\/> <b>FRP: <\/b> 0.55 MW<br\/> <b>Brightness: <\/b> 300.4 K" }, "geometry": { "type": "Point", "coordinates": [ -155.28841, 19.40454, 0.0 ] } },
{ "type": "Feature", "properties": { "Name": "Fire Detection Centroid ", "Description": "<b>Latitude: <\/b> 19.40394<br\/>  <b>Longitude: <\/b> -155.28473<br\/>  <b>Detection Time: <\/b> 2023-06-28 12:02 UTC<br\/>  <b>Sensor: <\/b> NOAA-20 VIIRS<br\/> <b>Confidence: <\/b> Nominal<br\/>  <b>Day\/Night: <\/b> Night<br\/> <b>Scan: <\/b> 0.39 km<br\/> <b>Track: <\/b> 0.36 km<br\/> <b>FRP: <\/b> 0.55 MW<br\/> <b>Brightness: <\/b> 298.27 K" }, "geometry": { "type": "Point", "coordinates": [ -155.28473, 19.40394, 0.0 ] } }
]
}
