{
"type": "FeatureCollection",
"crs": { "type": "name", "properties": { "name": "urn:ogc:def:crs:OGC:1.3:CRS84" } },
"features": [
{ "type": "Feature", "properties": { "Name": "Fire Detection Centroid ", "Description": "<b>Latitude: <\/b> 19.40578<br\/>  <b>Longitude: <\/b> -155.28476<br\/>  <b>Detection Time: <\/b> 2022-12-16 23:50 UTC<br\/>  <b>Sensor: <\/b> NOAA-20 VIIRS<br\/> <b>Confidence: <\/b> Nominal<br\/>  <b>Day\/Night: <\/b> Day<br\/> <b>Scan: <\/b> 0.5 km<br\/> <b>Track: <\/b> 0.4 km<br\/> <b>FRP: <\/b> 9.52 MW<br\/> <b>Brightness: <\/b> 335.9 K" }, "geometry": { "type": "Point", "coordinates": [ -155.28476, 19.40578, 0.0 ] } },
{ "type": "Feature", "properties": { "Name": "Fire Detection Centroid ", "Description": "<b>Latitude: <\/b> 19.40623<br\/>  <b>Longitude: <\/b> -155.28426<br\/>  <b>Detection Time: <\/b> 2022-12-16 23:50 UTC<br\/>  <b>Sensor: <\/b> NOAA-20 VIIRS<br\/> <b>Confidence: <\/b> Nominal<br\/>  <b>Day\/Night: <\/b> Day<br\/> <b>Scan: <\/b> 0.51 km<br\/> <b>Track: <\/b> 0.41 km<br\/> <b>FRP: <\/b> 9.53 MW<br\/> <b>Brightness: <\/b> 335.9 K" }, "geometry": { "type": "Point", "coordinates": [ -155.28426, 19.40623, 0.0 ] } }
]
}
