{
"type": "FeatureCollection",
"crs": { "type": "name", "properties": { "name": "urn:ogc:def:crs:OGC:1.3:CRS84" } },
"features": [
{ "type": "Feature", "properties": { "Name": "Fire Detection Centroid ", "Description": "<b>Latitude: <\/b> 46.35648<br\/>  <b>Longitude: <\/b> -118.95056<br\/>  <b>Detection Time: <\/b> 2023-05-24 11:10 UTC<br\/>  <b>Sensor: <\/b> NOAA-20 VIIRS<br\/> <b>Confidence: <\/b> Nominal<br\/>  <b>Day\/Night: <\/b> Night<br\/> <b>Scan: <\/b> 0.57 km<br\/> <b>Track: <\/b> 0.69 km<br\/> <b>FRP: <\/b> 3.99 MW<br\/> <b>Brightness: <\/b> 330.39 K" }, "geometry": { "type": "Point", "coordinates": [ -118.95056, 46.35648, 0.0 ] } },
{ "type": "Feature", "properties": { "Name": "Fire Detection Centroid ", "Description": "<b>Latitude: <\/b> 45.63101<br\/>  <b>Longitude: <\/b> -122.78136<br\/>  <b>Detection Time: <\/b> 2023-05-24 11:10 UTC<br\/>  <b>Sensor: <\/b> NOAA-20 VIIRS<br\/> <b>Confidence: <\/b> Nominal<br\/>  <b>Day\/Night: <\/b> Night<br\/> <b>Scan: <\/b> 0.41 km<br\/> <b>Track: <\/b> 0.6 km<br\/> <b>FRP: <\/b> 0.67 MW<br\/> <b>Brightness: <\/b> 295.43 K" }, "geometry": { "type": "Point", "coordinates": [ -122.78136, 45.63101, 0.0 ] } },
{ "type": "Feature", "properties": { "Name": "Fire Detection Centroid ", "Description": "<b>Latitude: <\/b> 45.6315<br\/>  <b>Longitude: <\/b> -122.78278<br\/>  <b>Detection Time: <\/b> 2023-05-24 11:10 UTC<br\/>  <b>Sensor: <\/b> NOAA-20 VIIRS<br\/> <b>Confidence: <\/b> Nominal<br\/>  <b>Day\/Night: <\/b> Night<br\/> <b>Scan: <\/b> 0.41 km<br\/> <b>Track: <\/b> 0.6 km<br\/> <b>FRP: <\/b> 1.2 MW<br\/> <b>Brightness: <\/b> 300.28 K" }, "geometry": { "type": "Point", "coordinates": [ -122.78278, 45.6315, 0.0 ] } }
]
}
