{
"type": "FeatureCollection",
"crs": { "type": "name", "properties": { "name": "urn:ogc:def:crs:OGC:1.3:CRS84" } },
"features": [
{ "type": "Feature", "properties": { "Name": "Fire Detection Centroid ", "Description": "<b>Latitude: <\/b> 37.95049<br\/>  <b>Longitude: <\/b> -122.40134<br\/>  <b>Detection Time: <\/b> 2023-04-28 11:00 UTC<br\/>  <b>Sensor: <\/b> NOAA-20 VIIRS<br\/> <b>Confidence: <\/b> Nominal<br\/>  <b>Day\/Night: <\/b> Night<br\/> <b>Scan: <\/b> 0.51 km<br\/> <b>Track: <\/b> 0.66 km<br\/> <b>FRP: <\/b> 1.2 MW<br\/> <b>Brightness: <\/b> 299.5 K" }, "geometry": { "type": "Point", "coordinates": [ -122.40134, 37.95049, 0.0 ] } },
{ "type": "Feature", "properties": { "Name": "Fire Detection Centroid ", "Description": "<b>Latitude: <\/b> 38.07364<br\/>  <b>Longitude: <\/b> -122.13885<br\/>  <b>Detection Time: <\/b> 2023-04-28 11:00 UTC<br\/>  <b>Sensor: <\/b> NOAA-20 VIIRS<br\/> <b>Confidence: <\/b> Nominal<br\/>  <b>Day\/Night: <\/b> Night<br\/> <b>Scan: <\/b> 0.52 km<br\/> <b>Track: <\/b> 0.67 km<br\/> <b>FRP: <\/b> 1.22 MW<br\/> <b>Brightness: <\/b> 301.72 K" }, "geometry": { "type": "Point", "coordinates": [ -122.13885, 38.07364, 0.0 ] } },
{ "type": "Feature", "properties": { "Name": "Fire Detection Centroid ", "Description": "<b>Latitude: <\/b> 45.23147<br\/>  <b>Longitude: <\/b> -123.16342<br\/>  <b>Detection Time: <\/b> 2023-04-28 10:58 UTC<br\/>  <b>Sensor: <\/b> NOAA-20 VIIRS<br\/> <b>Confidence: <\/b> Nominal<br\/>  <b>Day\/Night: <\/b> Night<br\/> <b>Scan: <\/b> 0.58 km<br\/> <b>Track: <\/b> 0.52 km<br\/> <b>FRP: <\/b> 4.77 MW<br\/> <b>Brightness: <\/b> 328.87 K" }, "geometry": { "type": "Point", "coordinates": [ -123.16342, 45.23147, 0.0 ] } },
{ "type": "Feature", "properties": { "Name": "Fire Detection Centroid ", "Description": "<b>Latitude: <\/b> 45.64849<br\/>  <b>Longitude: <\/b> -120.21375<br\/>  <b>Detection Time: <\/b> 2023-04-28 10:58 UTC<br\/>  <b>Sensor: <\/b> NOAA-20 VIIRS<br\/> <b>Confidence: <\/b> Nominal<br\/>  <b>Day\/Night: <\/b> Night<br\/> <b>Scan: <\/b> 0.39 km<br\/> <b>Track: <\/b> 0.59 km<br\/> <b>FRP: <\/b> 0.77 MW<br\/> <b>Brightness: <\/b> 301.53 K" }, "geometry": { "type": "Point", "coordinates": [ -120.21375, 45.64849, 0.0 ] } },
{ "type": "Feature", "properties": { "Name": "Fire Detection Centroid ", "Description": "<b>Latitude: <\/b> 45.23124<br\/>  <b>Longitude: <\/b> -123.16384<br\/>  <b>Detection Time: <\/b> 2023-04-28 10:58 UTC<br\/>  <b>Sensor: <\/b> NOAA-20 VIIRS<br\/> <b>Confidence: <\/b> Nominal<br\/>  <b>Day\/Night: <\/b> Night<br\/> <b>Scan: <\/b> 0.58 km<br\/> <b>Track: <\/b> 0.52 km<br\/> <b>FRP: <\/b> 4.08 MW<br\/> <b>Brightness: <\/b> 325.62 K" }, "geometry": { "type": "Point", "coordinates": [ -123.16384, 45.23124, 0.0 ] } },
{ "type": "Feature", "properties": { "Name": "Fire Detection Centroid ", "Description": "<b>Latitude: <\/b> 44.06293<br\/>  <b>Longitude: <\/b> -122.9826<br\/>  <b>Detection Time: <\/b> 2023-04-28 10:58 UTC<br\/>  <b>Sensor: <\/b> NOAA-20 VIIRS<br\/> <b>Confidence: <\/b> Nominal<br\/>  <b>Day\/Night: <\/b> Night<br\/> <b>Scan: <\/b> 0.32 km<br\/> <b>Track: <\/b> 0.55 km<br\/> <b>FRP: <\/b> 0.43 MW<br\/> <b>Brightness: <\/b> 299.02 K" }, "geometry": { "type": "Point", "coordinates": [ -122.9826, 44.06293, 0.0 ] } },
{ "type": "Feature", "properties": { "Name": "Fire Detection Centroid ", "Description": "<b>Latitude: <\/b> 47.57027<br\/>  <b>Longitude: <\/b> -122.34056<br\/>  <b>Detection Time: <\/b> 2023-04-28 10:56 UTC<br\/>  <b>Sensor: <\/b> NOAA-20 VIIRS<br\/> <b>Confidence: <\/b> Nominal<br\/>  <b>Day\/Night: <\/b> Night<br\/> <b>Scan: <\/b> 0.54 km<br\/> <b>Track: <\/b> 0.51 km<br\/> <b>FRP: <\/b> 1.27 MW<br\/> <b>Brightness: <\/b> 300.49 K" }, "geometry": { "type": "Point", "coordinates": [ -122.34056, 47.57027, 0.0 ] } },
{ "type": "Feature", "properties": { "Name": "Fire Detection Centroid ", "Description": "<b>Latitude: <\/b> 47.37001<br\/>  <b>Longitude: <\/b> -114.73215<br\/>  <b>Detection Time: <\/b> 2023-04-28 10:56 UTC<br\/>  <b>Sensor: <\/b> NOAA-20 VIIRS<br\/> <b>Confidence: <\/b> Nominal<br\/>  <b>Day\/Night: <\/b> Night<br\/> <b>Scan: <\/b> 0.59 km<br\/> <b>Track: <\/b> 0.7 km<br\/> <b>FRP: <\/b> 0.32 MW<br\/> <b>Brightness: <\/b> 300.24 K" }, "geometry": { "type": "Point", "coordinates": [ -114.73215, 47.37001, 0.0 ] } },
{ "type": "Feature", "properties": { "Name": "Fire Detection Centroid ", "Description": "<b>Latitude: <\/b> 49.09925<br\/>  <b>Longitude: <\/b> -123.01376<br\/>  <b>Detection Time: <\/b> 2023-04-28 10:56 UTC<br\/>  <b>Sensor: <\/b> NOAA-20 VIIRS<br\/> <b>Confidence: <\/b> Nominal<br\/>  <b>Day\/Night: <\/b> Night<br\/> <b>Scan: <\/b> 0.46 km<br\/> <b>Track: <\/b> 0.47 km<br\/> <b>FRP: <\/b> 1.17 MW<br\/> <b>Brightness: <\/b> 305.69 K" }, "geometry": { "type": "Point", "coordinates": [ -123.01376, 49.09925, 0.0 ] } }
]
}
