{
"type": "FeatureCollection",
"crs": { "type": "name", "properties": { "name": "urn:ogc:def:crs:OGC:1.3:CRS84" } },
"features": [
{ "type": "Feature", "properties": { "Name": "Fire Detection Centroid ", "Description": "<b>Latitude: <\/b> 39.71929<br\/>  <b>Longitude: <\/b> -123.73483<br\/>  <b>Detection Time: <\/b> 2023-12-14 22:08 UTC<br\/>  <b>Sensor: <\/b> NOAA-20 VIIRS<br\/> <b>Confidence: <\/b> Nominal<br\/>  <b>Day\/Night: <\/b> Day<br\/> <b>Scan: <\/b> 0.5 km<br\/> <b>Track: <\/b> 0.7 km<br\/> <b>FRP: <\/b> 3.4 MW<br\/> <b>Brightness: <\/b> 331.7 K" }, "geometry": { "type": "Point", "coordinates": [ -123.73483, 39.71929, 0.0 ] } },
{ "type": "Feature", "properties": { "Name": "Fire Detection Centroid ", "Description": "<b>Latitude: <\/b> 39.71918<br\/>  <b>Longitude: <\/b> -123.73288<br\/>  <b>Detection Time: <\/b> 2023-12-14 22:07 UTC<br\/>  <b>Sensor: <\/b> NOAA-20 VIIRS<br\/> <b>Confidence: <\/b> Nominal<br\/>  <b>Day\/Night: <\/b> Day<br\/> <b>Scan: <\/b> 0.52 km<br\/> <b>Track: <\/b> 0.67 km<br\/> <b>FRP: <\/b> 3.4 MW<br\/> <b>Brightness: <\/b> 331.7 K" }, "geometry": { "type": "Point", "coordinates": [ -123.73288, 39.71918, 0.0 ] } }
]
}
