{
"type": "FeatureCollection",
"crs": { "type": "name", "properties": { "name": "urn:ogc:def:crs:OGC:1.3:CRS84" } },
"features": [
{ "type": "Feature", "properties": { "Name": "Fire Detection Centroid ", "Description": "<b>Latitude: <\/b> 17.99349<br\/>  <b>Longitude: <\/b> -67.06904<br\/>  <b>Detection Time: <\/b> 2024-01-03 17:23 UTC<br\/>  <b>Sensor: <\/b> NOAA-20 VIIRS<br\/> <b>Confidence: <\/b> Nominal<br\/>  <b>Day\/Night: <\/b> Day<br\/> <b>Scan: <\/b> 0.5 km<br\/> <b>Track: <\/b> 0.4 km<br\/> <b>FRP: <\/b> 18.99 MW<br\/> <b>Brightness: <\/b> 335.19 K" }, "geometry": { "type": "Point", "coordinates": [ -67.06904, 17.99349, 0.0 ] } }
]
}
