{
"type": "FeatureCollection",
"crs": { "type": "name", "properties": { "name": "urn:ogc:def:crs:OGC:1.3:CRS84" } },
"features": [
{ "type": "Feature", "properties": { "Name": "Fire Detection Centroid ", "Description": "<b>Latitude: <\/b> 19.40852<br\/>  <b>Longitude: <\/b> -155.28549<br\/>  <b>Detection Time: <\/b> 2023-10-18 23:12 UTC<br\/>  <b>Sensor: <\/b> NOAA-20 VIIRS<br\/> <b>Confidence: <\/b> Low<br\/>  <b>Day\/Night: <\/b> Day<br\/> <b>Scan: <\/b> 0.4 km<br\/> <b>Track: <\/b> 0.4 km<br\/> <b>FRP: <\/b> 12.62 MW<br\/> <b>Brightness: <\/b> 344.24 K" }, "geometry": { "type": "Point", "coordinates": [ -155.28549, 19.40852, 0.0 ] } },
{ "type": "Feature", "properties": { "Name": "Fire Detection Centroid ", "Description": "<b>Latitude: <\/b> 19.40934<br\/>  <b>Longitude: <\/b> -155.28487<br\/>  <b>Detection Time: <\/b> 2023-10-18 23:12 UTC<br\/>  <b>Sensor: <\/b> NOAA-20 VIIRS<br\/> <b>Confidence: <\/b> Low<br\/>  <b>Day\/Night: <\/b> Day<br\/> <b>Scan: <\/b> 0.39 km<br\/> <b>Track: <\/b> 0.44 km<br\/> <b>FRP: <\/b> 12.67 MW<br\/> <b>Brightness: <\/b> 344.24 K" }, "geometry": { "type": "Point", "coordinates": [ -155.28487, 19.40934, 0.0 ] } }
]
}
