{
"type": "FeatureCollection",
"crs": { "type": "name", "properties": { "name": "urn:ogc:def:crs:OGC:1.3:CRS84" } },
"features": [
{ "type": "Feature", "properties": { "Name": "Fire Detection Centroid ", "Description": "<b>Latitude: <\/b> 18.92602<br\/>  <b>Longitude: <\/b> -70.35097<br\/>  <b>Detection Time: <\/b> 2023-04-19 05:29 UTC<br\/>  <b>Sensor: <\/b> NOAA-20 VIIRS<br\/> <b>Confidence: <\/b> Nominal<br\/>  <b>Day\/Night: <\/b> Night<br\/> <b>Scan: <\/b> 0.6 km<br\/> <b>Track: <\/b> 0.7 km<br\/> <b>FRP: <\/b> 4.03 MW<br\/> <b>Brightness: <\/b> 306.42 K" }, "geometry": { "type": "Point", "coordinates": [ -70.35097, 18.92602, 0.0 ] } },
{ "type": "Feature", "properties": { "Name": "Fire Detection Centroid ", "Description": "<b>Latitude: <\/b> 18.93115<br\/>  <b>Longitude: <\/b> -70.35758<br\/>  <b>Detection Time: <\/b> 2023-04-19 05:29 UTC<br\/>  <b>Sensor: <\/b> NOAA-20 VIIRS<br\/> <b>Confidence: <\/b> Nominal<br\/>  <b>Day\/Night: <\/b> Night<br\/> <b>Scan: <\/b> 0.6 km<br\/> <b>Track: <\/b> 0.7 km<br\/> <b>FRP: <\/b> 3.18 MW<br\/> <b>Brightness: <\/b> 313.3 K" }, "geometry": { "type": "Point", "coordinates": [ -70.35758, 18.93115, 0.0 ] } },
{ "type": "Feature", "properties": { "Name": "Fire Detection Centroid ", "Description": "<b>Latitude: <\/b> 18.5092<br\/>  <b>Longitude: <\/b> -69.34296<br\/>  <b>Detection Time: <\/b> 2023-04-19 05:29 UTC<br\/>  <b>Sensor: <\/b> NOAA-20 VIIRS<br\/> <b>Confidence: <\/b> Nominal<br\/>  <b>Day\/Night: <\/b> Night<br\/> <b>Scan: <\/b> 0.5 km<br\/> <b>Track: <\/b> 0.6 km<br\/> <b>FRP: <\/b> 0.72 MW<br\/> <b>Brightness: <\/b> 301.39 K" }, "geometry": { "type": "Point", "coordinates": [ -69.34296, 18.5092, 0.0 ] } },
{ "type": "Feature", "properties": { "Name": "Fire Detection Centroid ", "Description": "<b>Latitude: <\/b> 18.93062<br\/>  <b>Longitude: <\/b> -70.35194<br\/>  <b>Detection Time: <\/b> 2023-04-19 05:29 UTC<br\/>  <b>Sensor: <\/b> NOAA-20 VIIRS<br\/> <b>Confidence: <\/b> Nominal<br\/>  <b>Day\/Night: <\/b> Night<br\/> <b>Scan: <\/b> 0.6 km<br\/> <b>Track: <\/b> 0.7 km<br\/> <b>FRP: <\/b> 3.18 MW<br\/> <b>Brightness: <\/b> 320.76 K" }, "geometry": { "type": "Point", "coordinates": [ -70.35194, 18.93062, 0.0 ] } },
{ "type": "Feature", "properties": { "Name": "Fire Detection Centroid ", "Description": "<b>Latitude: <\/b> 18.92653<br\/>  <b>Longitude: <\/b> -70.35677<br\/>  <b>Detection Time: <\/b> 2023-04-19 05:29 UTC<br\/>  <b>Sensor: <\/b> NOAA-20 VIIRS<br\/> <b>Confidence: <\/b> Nominal<br\/>  <b>Day\/Night: <\/b> Night<br\/> <b>Scan: <\/b> 0.6 km<br\/> <b>Track: <\/b> 0.7 km<br\/> <b>FRP: <\/b> 5.28 MW<br\/> <b>Brightness: <\/b> 328.74 K" }, "geometry": { "type": "Point", "coordinates": [ -70.35677, 18.92653, 0.0 ] } }
]
}
