{
"type": "FeatureCollection",
"crs": { "type": "name", "properties": { "name": "urn:ogc:def:crs:OGC:1.3:CRS84" } },
"features": [
{ "type": "Feature", "properties": { "Name": "Fire Detection Centroid ", "Description": "<b>Latitude: <\/b> 17.99157<br\/>  <b>Longitude: <\/b> -77.04194<br\/>  <b>Detection Time: <\/b> 2023-09-09 05:49 UTC<br\/>  <b>Sensor: <\/b> NOAA-20 VIIRS<br\/> <b>Confidence: <\/b> Nominal<br\/>  <b>Day\/Night: <\/b> Night<br\/> <b>Scan: <\/b> 0.7 km<br\/> <b>Track: <\/b> 0.8 km<br\/> <b>FRP: <\/b> 1.16 MW<br\/> <b>Brightness: <\/b> 303.49 K" }, "geometry": { "type": "Point", "coordinates": [ -77.04194, 17.99157, 0.0 ] } },
{ "type": "Feature", "properties": { "Name": "Fire Detection Centroid ", "Description": "<b>Latitude: <\/b> 18.93028<br\/>  <b>Longitude: <\/b> -70.35316<br\/>  <b>Detection Time: <\/b> 2023-09-09 05:48 UTC<br\/>  <b>Sensor: <\/b> NOAA-20 VIIRS<br\/> <b>Confidence: <\/b> Nominal<br\/>  <b>Day\/Night: <\/b> Night<br\/> <b>Scan: <\/b> 0.5 km<br\/> <b>Track: <\/b> 0.5 km<br\/> <b>FRP: <\/b> 5.06 MW<br\/> <b>Brightness: <\/b> 341.75 K" }, "geometry": { "type": "Point", "coordinates": [ -70.35316, 18.93028, 0.0 ] } },
{ "type": "Feature", "properties": { "Name": "Fire Detection Centroid ", "Description": "<b>Latitude: <\/b> 19.82186<br\/>  <b>Longitude: <\/b> -71.60394<br\/>  <b>Detection Time: <\/b> 2023-09-09 05:48 UTC<br\/>  <b>Sensor: <\/b> NOAA-20 VIIRS<br\/> <b>Confidence: <\/b> Nominal<br\/>  <b>Day\/Night: <\/b> Night<br\/> <b>Scan: <\/b> 0.3 km<br\/> <b>Track: <\/b> 0.6 km<br\/> <b>FRP: <\/b> 0.46 MW<br\/> <b>Brightness: <\/b> 304 K" }, "geometry": { "type": "Point", "coordinates": [ -71.60394, 19.82186, 0.0 ] } },
{ "type": "Feature", "properties": { "Name": "Fire Detection Centroid ", "Description": "<b>Latitude: <\/b> 18.92553<br\/>  <b>Longitude: <\/b> -70.35319<br\/>  <b>Detection Time: <\/b> 2023-09-09 05:48 UTC<br\/>  <b>Sensor: <\/b> NOAA-20 VIIRS<br\/> <b>Confidence: <\/b> Nominal<br\/>  <b>Day\/Night: <\/b> Night<br\/> <b>Scan: <\/b> 0.5 km<br\/> <b>Track: <\/b> 0.5 km<br\/> <b>FRP: <\/b> 5.06 MW<br\/> <b>Brightness: <\/b> 310.26 K" }, "geometry": { "type": "Point", "coordinates": [ -70.35319, 18.92553, 0.0 ] } },
{ "type": "Feature", "properties": { "Name": "Fire Detection Centroid ", "Description": "<b>Latitude: <\/b> 40.63813<br\/>  <b>Longitude: <\/b> -74.22422<br\/>  <b>Detection Time: <\/b> 2023-09-09 05:42 UTC<br\/>  <b>Sensor: <\/b> NOAA-20 VIIRS<br\/> <b>Confidence: <\/b> Nominal<br\/>  <b>Day\/Night: <\/b> Night<br\/> <b>Scan: <\/b> 0.7 km<br\/> <b>Track: <\/b> 0.8 km<br\/> <b>FRP: <\/b> 0.96 MW<br\/> <b>Brightness: <\/b> 300.22 K" }, "geometry": { "type": "Point", "coordinates": [ -74.22422, 40.63813, 0.0 ] } }
]
}
