{
"type": "FeatureCollection",
"crs": { "type": "name", "properties": { "name": "urn:ogc:def:crs:OGC:1.3:CRS84" } },
"features": [
{ "type": "Feature", "properties": { "Name": "Fire Detection Centroid ", "Description": "<b>Latitude: <\/b> 41.32206<br\/>  <b>Longitude: <\/b> -118.24665<br\/>  <b>Detection Time: <\/b> 2023-04-09 21:38 UTC<br\/>  <b>Sensor: <\/b> NOAA-20 VIIRS<br\/> <b>Confidence: <\/b> Nominal<br\/>  <b>Day\/Night: <\/b> Day<br\/> <b>Scan: <\/b> 0.4 km<br\/> <b>Track: <\/b> 0.6 km<br\/> <b>FRP: <\/b> 5.52 MW<br\/> <b>Brightness: <\/b> 331.36 K" }, "geometry": { "type": "Point", "coordinates": [ -118.24665, 41.32206, 0.0 ] } },
{ "type": "Feature", "properties": { "Name": "Fire Detection Centroid ", "Description": "<b>Latitude: <\/b> 41.31675<br\/>  <b>Longitude: <\/b> -118.24145<br\/>  <b>Detection Time: <\/b> 2023-04-09 21:38 UTC<br\/>  <b>Sensor: <\/b> NOAA-20 VIIRS<br\/> <b>Confidence: <\/b> High<br\/>  <b>Day\/Night: <\/b> Day<br\/> <b>Scan: <\/b> 0.4 km<br\/> <b>Track: <\/b> 0.6 km<br\/> <b>FRP: <\/b> 7.82 MW<br\/> <b>Brightness: <\/b> 367 K" }, "geometry": { "type": "Point", "coordinates": [ -118.24145, 41.31675, 0.0 ] } },
{ "type": "Feature", "properties": { "Name": "Fire Detection Centroid ", "Description": "<b>Latitude: <\/b> 41.31652<br\/>  <b>Longitude: <\/b> -118.24627<br\/>  <b>Detection Time: <\/b> 2023-04-09 21:38 UTC<br\/>  <b>Sensor: <\/b> NOAA-20 VIIRS<br\/> <b>Confidence: <\/b> Nominal<br\/>  <b>Day\/Night: <\/b> Day<br\/> <b>Scan: <\/b> 0.4 km<br\/> <b>Track: <\/b> 0.6 km<br\/> <b>FRP: <\/b> 5.52 MW<br\/> <b>Brightness: <\/b> 335.4 K" }, "geometry": { "type": "Point", "coordinates": [ -118.24627, 41.31652, 0.0 ] } },
{ "type": "Feature", "properties": { "Name": "Fire Detection Centroid ", "Description": "<b>Latitude: <\/b> 41.32174<br\/>  <b>Longitude: <\/b> -118.24399<br\/>  <b>Detection Time: <\/b> 2023-04-09 21:38 UTC<br\/>  <b>Sensor: <\/b> NOAA-20 VIIRS<br\/> <b>Confidence: <\/b> High<br\/>  <b>Day\/Night: <\/b> Day<br\/> <b>Scan: <\/b> 0.4 km<br\/> <b>Track: <\/b> 0.6 km<br\/> <b>FRP: <\/b> 10.77 MW<br\/> <b>Brightness: <\/b> 367 K" }, "geometry": { "type": "Point", "coordinates": [ -118.24399, 41.32174, 0.0 ] } },
{ "type": "Feature", "properties": { "Name": "Fire Detection Centroid ", "Description": "<b>Latitude: <\/b> 41.32228<br\/>  <b>Longitude: <\/b> -118.24183<br\/>  <b>Detection Time: <\/b> 2023-04-09 21:38 UTC<br\/>  <b>Sensor: <\/b> NOAA-20 VIIRS<br\/> <b>Confidence: <\/b> Nominal<br\/>  <b>Day\/Night: <\/b> Day<br\/> <b>Scan: <\/b> 0.4 km<br\/> <b>Track: <\/b> 0.6 km<br\/> <b>FRP: <\/b> 7.82 MW<br\/> <b>Brightness: <\/b> 343.24 K" }, "geometry": { "type": "Point", "coordinates": [ -118.24183, 41.32228, 0.0 ] } },
{ "type": "Feature", "properties": { "Name": "Fire Detection Centroid ", "Description": "<b>Latitude: <\/b> 38.67294<br\/>  <b>Longitude: <\/b> -121.98367<br\/>  <b>Detection Time: <\/b> 2023-04-09 21:36 UTC<br\/>  <b>Sensor: <\/b> NOAA-20 VIIRS<br\/> <b>Confidence: <\/b> Nominal<br\/>  <b>Day\/Night: <\/b> Day<br\/> <b>Scan: <\/b> 0.47 km<br\/> <b>Track: <\/b> 0.48 km<br\/> <b>FRP: <\/b> 6.05 MW<br\/> <b>Brightness: <\/b> 347.15 K" }, "geometry": { "type": "Point", "coordinates": [ -121.98367, 38.67294, 0.0 ] } },
{ "type": "Feature", "properties": { "Name": "Fire Detection Centroid ", "Description": "<b>Latitude: <\/b> 32.5223<br\/>  <b>Longitude: <\/b> -115.21186<br\/>  <b>Detection Time: <\/b> 2023-04-09 21:33 UTC<br\/>  <b>Sensor: <\/b> NOAA-20 VIIRS<br\/> <b>Confidence: <\/b> Nominal<br\/>  <b>Day\/Night: <\/b> Day<br\/> <b>Scan: <\/b> 0.5 km<br\/> <b>Track: <\/b> 0.66 km<br\/> <b>FRP: <\/b> 4.77 MW<br\/> <b>Brightness: <\/b> 338.96 K" }, "geometry": { "type": "Point", "coordinates": [ -115.21186, 32.5223, 0.0 ] } }
]
}
