{
"type": "FeatureCollection",
"crs": { "type": "name", "properties": { "name": "urn:ogc:def:crs:OGC:1.3:CRS84" } },
"features": [
{ "type": "Feature", "properties": { "Name": "Fire Detection Centroid ", "Description": "<b>Latitude: <\/b> 19.41444<br\/>  <b>Longitude: <\/b> -155.28406<br\/>  <b>Detection Time: <\/b> 2023-10-15 11:17 UTC<br\/>  <b>Sensor: <\/b> NOAA-20 VIIRS<br\/> <b>Confidence: <\/b> Nominal<br\/>  <b>Day\/Night: <\/b> Night<br\/> <b>Scan: <\/b> 0.41 km<br\/> <b>Track: <\/b> 0.61 km<br\/> <b>FRP: <\/b> 3.83 MW<br\/> <b>Brightness: <\/b> 310.16 K" }, "geometry": { "type": "Point", "coordinates": [ -155.28406, 19.41444, 0.0 ] } },
{ "type": "Feature", "properties": { "Name": "Fire Detection Centroid ", "Description": "<b>Latitude: <\/b> 19.40926<br\/>  <b>Longitude: <\/b> -155.2887<br\/>  <b>Detection Time: <\/b> 2023-10-15 11:17 UTC<br\/>  <b>Sensor: <\/b> NOAA-20 VIIRS<br\/> <b>Confidence: <\/b> Nominal<br\/>  <b>Day\/Night: <\/b> Night<br\/> <b>Scan: <\/b> 0.41 km<br\/> <b>Track: <\/b> 0.61 km<br\/> <b>FRP: <\/b> 2.75 MW<br\/> <b>Brightness: <\/b> 306.59 K" }, "geometry": { "type": "Point", "coordinates": [ -155.2887, 19.40926, 0.0 ] } },
{ "type": "Feature", "properties": { "Name": "Fire Detection Centroid ", "Description": "<b>Latitude: <\/b> 19.40889<br\/>  <b>Longitude: <\/b> -155.28502<br\/>  <b>Detection Time: <\/b> 2023-10-15 11:17 UTC<br\/>  <b>Sensor: <\/b> NOAA-20 VIIRS<br\/> <b>Confidence: <\/b> Nominal<br\/>  <b>Day\/Night: <\/b> Night<br\/> <b>Scan: <\/b> 0.41 km<br\/> <b>Track: <\/b> 0.61 km<br\/> <b>FRP: <\/b> 2.06 MW<br\/> <b>Brightness: <\/b> 308.83 K" }, "geometry": { "type": "Point", "coordinates": [ -155.28502, 19.40889, 0.0 ] } },
{ "type": "Feature", "properties": { "Name": "Fire Detection Centroid ", "Description": "<b>Latitude: <\/b> 19.40851<br\/>  <b>Longitude: <\/b> -155.2812<br\/>  <b>Detection Time: <\/b> 2023-10-15 11:17 UTC<br\/>  <b>Sensor: <\/b> NOAA-20 VIIRS<br\/> <b>Confidence: <\/b> Nominal<br\/>  <b>Day\/Night: <\/b> Night<br\/> <b>Scan: <\/b> 0.41 km<br\/> <b>Track: <\/b> 0.61 km<br\/> <b>FRP: <\/b> 2.06 MW<br\/> <b>Brightness: <\/b> 304.84 K" }, "geometry": { "type": "Point", "coordinates": [ -155.2812, 19.40851, 0.0 ] } }
]
}
