{
"type": "FeatureCollection",
"crs": { "type": "name", "properties": { "name": "urn:ogc:def:crs:OGC:1.3:CRS84" } },
"features": [
{ "type": "Feature", "properties": { "Name": "Fire Detection Centroid ", "Description": "<b>Latitude: <\/b> 19.58915<br\/>  <b>Longitude: <\/b> -155.50375<br\/>  <b>Detection Time: <\/b> 2023-02-20 12:01 UTC<br\/>  <b>Sensor: <\/b> NOAA-20 VIIRS<br\/> <b>Confidence: <\/b> Nominal<br\/>  <b>Day\/Night: <\/b> Night<br\/> <b>Scan: <\/b> 0.39 km<br\/> <b>Track: <\/b> 0.36 km<br\/> <b>FRP: <\/b> 1.05 MW<br\/> <b>Brightness: <\/b> 296.69 K" }, "geometry": { "type": "Point", "coordinates": [ -155.50375, 19.58915, 0.0 ] } },
{ "type": "Feature", "properties": { "Name": "Fire Detection Centroid ", "Description": "<b>Latitude: <\/b> 19.59629<br\/>  <b>Longitude: <\/b> -155.50618<br\/>  <b>Detection Time: <\/b> 2023-02-20 12:01 UTC<br\/>  <b>Sensor: <\/b> NOAA-20 VIIRS<br\/> <b>Confidence: <\/b> Nominal<br\/>  <b>Day\/Night: <\/b> Night<br\/> <b>Scan: <\/b> 0.39 km<br\/> <b>Track: <\/b> 0.36 km<br\/> <b>FRP: <\/b> 0.64 MW<br\/> <b>Brightness: <\/b> 296.96 K" }, "geometry": { "type": "Point", "coordinates": [ -155.50618, 19.59629, 0.0 ] } },
{ "type": "Feature", "properties": { "Name": "Fire Detection Centroid ", "Description": "<b>Latitude: <\/b> 19.59958<br\/>  <b>Longitude: <\/b> -155.50557<br\/>  <b>Detection Time: <\/b> 2023-02-20 12:01 UTC<br\/>  <b>Sensor: <\/b> NOAA-20 VIIRS<br\/> <b>Confidence: <\/b> Nominal<br\/>  <b>Day\/Night: <\/b> Night<br\/> <b>Scan: <\/b> 0.39 km<br\/> <b>Track: <\/b> 0.36 km<br\/> <b>FRP: <\/b> 0.64 MW<br\/> <b>Brightness: <\/b> 295.81 K" }, "geometry": { "type": "Point", "coordinates": [ -155.50557, 19.59958, 0.0 ] } },
{ "type": "Feature", "properties": { "Name": "Fire Detection Centroid ", "Description": "<b>Latitude: <\/b> 19.60942<br\/>  <b>Longitude: <\/b> -155.50374<br\/>  <b>Detection Time: <\/b> 2023-02-20 12:01 UTC<br\/>  <b>Sensor: <\/b> NOAA-20 VIIRS<br\/> <b>Confidence: <\/b> Nominal<br\/>  <b>Day\/Night: <\/b> Night<br\/> <b>Scan: <\/b> 0.39 km<br\/> <b>Track: <\/b> 0.36 km<br\/> <b>FRP: <\/b> 1.25 MW<br\/> <b>Brightness: <\/b> 295.2 K" }, "geometry": { "type": "Point", "coordinates": [ -155.50374, 19.60942, 0.0 ] } },
{ "type": "Feature", "properties": { "Name": "Fire Detection Centroid ", "Description": "<b>Latitude: <\/b> 19.40399<br\/>  <b>Longitude: <\/b> -155.28438<br\/>  <b>Detection Time: <\/b> 2023-02-20 12:01 UTC<br\/>  <b>Sensor: <\/b> NOAA-20 VIIRS<br\/> <b>Confidence: <\/b> Nominal<br\/>  <b>Day\/Night: <\/b> Night<br\/> <b>Scan: <\/b> 0.39 km<br\/> <b>Track: <\/b> 0.36 km<br\/> <b>FRP: <\/b> 0.63 MW<br\/> <b>Brightness: <\/b> 299.79 K" }, "geometry": { "type": "Point", "coordinates": [ -155.28438, 19.40399, 0.0 ] } },
{ "type": "Feature", "properties": { "Name": "Fire Detection Centroid ", "Description": "<b>Latitude: <\/b> 19.40669<br\/>  <b>Longitude: <\/b> -155.28012<br\/>  <b>Detection Time: <\/b> 2023-02-20 12:01 UTC<br\/>  <b>Sensor: <\/b> NOAA-20 VIIRS<br\/> <b>Confidence: <\/b> Nominal<br\/>  <b>Day\/Night: <\/b> Night<br\/> <b>Scan: <\/b> 0.39 km<br\/> <b>Track: <\/b> 0.36 km<br\/> <b>FRP: <\/b> 0.85 MW<br\/> <b>Brightness: <\/b> 300.82 K" }, "geometry": { "type": "Point", "coordinates": [ -155.28012, 19.40669, 0.0 ] } },
{ "type": "Feature", "properties": { "Name": "Fire Detection Centroid ", "Description": "<b>Latitude: <\/b> 19.40729<br\/>  <b>Longitude: <\/b> -155.2838<br\/>  <b>Detection Time: <\/b> 2023-02-20 12:01 UTC<br\/>  <b>Sensor: <\/b> NOAA-20 VIIRS<br\/> <b>Confidence: <\/b> Nominal<br\/>  <b>Day\/Night: <\/b> Night<br\/> <b>Scan: <\/b> 0.39 km<br\/> <b>Track: <\/b> 0.36 km<br\/> <b>FRP: <\/b> 0.63 MW<br\/> <b>Brightness: <\/b> 299.16 K" }, "geometry": { "type": "Point", "coordinates": [ -155.2838, 19.40729, 0.0 ] } },
{ "type": "Feature", "properties": { "Name": "Fire Detection Centroid ", "Description": "<b>Latitude: <\/b> 19.40788<br\/>  <b>Longitude: <\/b> -155.28746<br\/>  <b>Detection Time: <\/b> 2023-02-20 12:01 UTC<br\/>  <b>Sensor: <\/b> NOAA-20 VIIRS<br\/> <b>Confidence: <\/b> Nominal<br\/>  <b>Day\/Night: <\/b> Night<br\/> <b>Scan: <\/b> 0.39 km<br\/> <b>Track: <\/b> 0.36 km<br\/> <b>FRP: <\/b> 0.63 MW<br\/> <b>Brightness: <\/b> 300.14 K" }, "geometry": { "type": "Point", "coordinates": [ -155.28746, 19.40788, 0.0 ] } },
{ "type": "Feature", "properties": { "Name": "Fire Detection Centroid ", "Description": "<b>Latitude: <\/b> 19.58587<br\/>  <b>Longitude: <\/b> -155.50436<br\/>  <b>Detection Time: <\/b> 2023-02-20 12:01 UTC<br\/>  <b>Sensor: <\/b> NOAA-20 VIIRS<br\/> <b>Confidence: <\/b> Nominal<br\/>  <b>Day\/Night: <\/b> Night<br\/> <b>Scan: <\/b> 0.39 km<br\/> <b>Track: <\/b> 0.36 km<br\/> <b>FRP: <\/b> 1.07 MW<br\/> <b>Brightness: <\/b> 296.59 K" }, "geometry": { "type": "Point", "coordinates": [ -155.50436, 19.58587, 0.0 ] } }
]
}
