{
"type": "FeatureCollection",
"crs": { "type": "name", "properties": { "name": "urn:ogc:def:crs:OGC:1.3:CRS84" } },
"features": [
{ "type": "Feature", "properties": { "Name": "Fire Detection Centroid ", "Description": "<b>Latitude: <\/b> 43.65542<br\/>  <b>Longitude: <\/b> -122.10848<br\/>  <b>Detection Time: <\/b> 2022-09-15 11:17 UTC<br\/>  <b>Sensor: <\/b> NOAA-20 VIIRS<br\/> <b>Confidence: <\/b> Nominal<br\/>  <b>Day\/Night: <\/b> Night<br\/> <b>Scan: <\/b> 0.6 km<br\/> <b>Track: <\/b> 0.71 km<br\/> <b>FRP: <\/b> 2.71 MW<br\/> <b>Brightness: <\/b> 311.39 K" }, "geometry": { "type": "Point", "coordinates": [ -122.10848, 43.65542, 0.0 ] } },
{ "type": "Feature", "properties": { "Name": "Fire Detection Centroid ", "Description": "<b>Latitude: <\/b> 43.65041<br\/>  <b>Longitude: <\/b> -122.10929<br\/>  <b>Detection Time: <\/b> 2022-09-15 11:17 UTC<br\/>  <b>Sensor: <\/b> NOAA-20 VIIRS<br\/> <b>Confidence: <\/b> Nominal<br\/>  <b>Day\/Night: <\/b> Night<br\/> <b>Scan: <\/b> 0.6 km<br\/> <b>Track: <\/b> 0.71 km<br\/> <b>FRP: <\/b> 3.03 MW<br\/> <b>Brightness: <\/b> 298.41 K" }, "geometry": { "type": "Point", "coordinates": [ -122.10929, 43.65041, 0.0 ] } },
{ "type": "Feature", "properties": { "Name": "Fire Detection Centroid ", "Description": "<b>Latitude: <\/b> 49.87025<br\/>  <b>Longitude: <\/b> -125.9948<br\/>  <b>Detection Time: <\/b> 2022-09-15 11:15 UTC<br\/>  <b>Sensor: <\/b> NOAA-20 VIIRS<br\/> <b>Confidence: <\/b> Nominal<br\/>  <b>Day\/Night: <\/b> Night<br\/> <b>Scan: <\/b> 0.52 km<br\/> <b>Track: <\/b> 0.5 km<br\/> <b>FRP: <\/b> 1.24 MW<br\/> <b>Brightness: <\/b> 304.93 K" }, "geometry": { "type": "Point", "coordinates": [ -125.9948, 49.87025, 0.0 ] } },
{ "type": "Feature", "properties": { "Name": "Fire Detection Centroid ", "Description": "<b>Latitude: <\/b> 43.65528<br\/>  <b>Longitude: <\/b> -122.10698<br\/>  <b>Detection Time: <\/b> 2022-09-15 11:15 UTC<br\/>  <b>Sensor: <\/b> NOAA-20 VIIRS<br\/> <b>Confidence: <\/b> Nominal<br\/>  <b>Day\/Night: <\/b> Night<br\/> <b>Scan: <\/b> 0.6 km<br\/> <b>Track: <\/b> 0.7 km<br\/> <b>FRP: <\/b> 2.7 MW<br\/> <b>Brightness: <\/b> 311.39 K" }, "geometry": { "type": "Point", "coordinates": [ -122.10698, 43.65528, 0.0 ] } },
{ "type": "Feature", "properties": { "Name": "Fire Detection Centroid ", "Description": "<b>Latitude: <\/b> 43.65017<br\/>  <b>Longitude: <\/b> -122.10751<br\/>  <b>Detection Time: <\/b> 2022-09-15 11:15 UTC<br\/>  <b>Sensor: <\/b> NOAA-20 VIIRS<br\/> <b>Confidence: <\/b> Nominal<br\/>  <b>Day\/Night: <\/b> Night<br\/> <b>Scan: <\/b> 0.6 km<br\/> <b>Track: <\/b> 0.7 km<br\/> <b>FRP: <\/b> 3.02 MW<br\/> <b>Brightness: <\/b> 298.41 K" }, "geometry": { "type": "Point", "coordinates": [ -122.10751, 43.65017, 0.0 ] } }
]
}
