{
"type": "FeatureCollection",
"crs": { "type": "name", "properties": { "name": "urn:ogc:def:crs:OGC:1.3:CRS84" } },
"features": [
{ "type": "Feature", "properties": { "Name": "Fire Detection Centroid ", "Description": "<b>Latitude: <\/b> 18.00821<br\/>  <b>Longitude: <\/b> -66.65439<br\/>  <b>Detection Time: <\/b> 2022-11-24 06:06 UTC<br\/>  <b>Sensor: <\/b> NOAA-20 VIIRS<br\/> <b>Confidence: <\/b> Nominal<br\/>  <b>Day\/Night: <\/b> Night<br\/> <b>Scan: <\/b> 0.4 km<br\/> <b>Track: <\/b> 0.4 km<br\/> <b>FRP: <\/b> 0.31 MW<br\/> <b>Brightness: <\/b> 304.24 K" }, "geometry": { "type": "Point", "coordinates": [ -66.65439, 18.00821, 0.0 ] } },
{ "type": "Feature", "properties": { "Name": "Fire Detection Centroid ", "Description": "<b>Latitude: <\/b> 18.92862<br\/>  <b>Longitude: <\/b> -70.35635<br\/>  <b>Detection Time: <\/b> 2022-11-24 06:06 UTC<br\/>  <b>Sensor: <\/b> NOAA-20 VIIRS<br\/> <b>Confidence: <\/b> Nominal<br\/>  <b>Day\/Night: <\/b> Night<br\/> <b>Scan: <\/b> 0.4 km<br\/> <b>Track: <\/b> 0.4 km<br\/> <b>FRP: <\/b> 4.89 MW<br\/> <b>Brightness: <\/b> 329 K" }, "geometry": { "type": "Point", "coordinates": [ -70.35635, 18.92862, 0.0 ] } },
{ "type": "Feature", "properties": { "Name": "Fire Detection Centroid ", "Description": "<b>Latitude: <\/b> 18.92801<br\/>  <b>Longitude: <\/b> -70.35207<br\/>  <b>Detection Time: <\/b> 2022-11-24 06:06 UTC<br\/>  <b>Sensor: <\/b> NOAA-20 VIIRS<br\/> <b>Confidence: <\/b> Nominal<br\/>  <b>Day\/Night: <\/b> Night<br\/> <b>Scan: <\/b> 0.4 km<br\/> <b>Track: <\/b> 0.4 km<br\/> <b>FRP: <\/b> 5.88 MW<br\/> <b>Brightness: <\/b> 328.78 K" }, "geometry": { "type": "Point", "coordinates": [ -70.35207, 18.92801, 0.0 ] } },
{ "type": "Feature", "properties": { "Name": "Fire Detection Centroid ", "Description": "<b>Latitude: <\/b> 40.68527<br\/>  <b>Longitude: <\/b> -75.25656<br\/>  <b>Detection Time: <\/b> 2022-11-24 06:00 UTC<br\/>  <b>Sensor: <\/b> NOAA-20 VIIRS<br\/> <b>Confidence: <\/b> Nominal<br\/>  <b>Day\/Night: <\/b> Night<br\/> <b>Scan: <\/b> 0.5 km<br\/> <b>Track: <\/b> 0.6 km<br\/> <b>FRP: <\/b> 0.81 MW<br\/> <b>Brightness: <\/b> 298 K" }, "geometry": { "type": "Point", "coordinates": [ -75.25656, 40.68527, 0.0 ] } },
{ "type": "Feature", "properties": { "Name": "Fire Detection Centroid ", "Description": "<b>Latitude: <\/b> 40.15768<br\/>  <b>Longitude: <\/b> -74.77216<br\/>  <b>Detection Time: <\/b> 2022-11-24 06:00 UTC<br\/>  <b>Sensor: <\/b> NOAA-20 VIIRS<br\/> <b>Confidence: <\/b> Nominal<br\/>  <b>Day\/Night: <\/b> Night<br\/> <b>Scan: <\/b> 0.4 km<br\/> <b>Track: <\/b> 0.6 km<br\/> <b>FRP: <\/b> 0.44 MW<br\/> <b>Brightness: <\/b> 298.48 K" }, "geometry": { "type": "Point", "coordinates": [ -74.77216, 40.15768, 0.0 ] } },
{ "type": "Feature", "properties": { "Name": "Fire Detection Centroid ", "Description": "<b>Latitude: <\/b> 39.94359<br\/>  <b>Longitude: <\/b> -76.81532<br\/>  <b>Detection Time: <\/b> 2022-11-24 06:00 UTC<br\/>  <b>Sensor: <\/b> NOAA-20 VIIRS<br\/> <b>Confidence: <\/b> Nominal<br\/>  <b>Day\/Night: <\/b> Night<br\/> <b>Scan: <\/b> 0.6 km<br\/> <b>Track: <\/b> 0.7 km<br\/> <b>FRP: <\/b> 1.16 MW<br\/> <b>Brightness: <\/b> 300.81 K" }, "geometry": { "type": "Point", "coordinates": [ -76.81532, 39.94359, 0.0 ] } },
{ "type": "Feature", "properties": { "Name": "Fire Detection Centroid ", "Description": "<b>Latitude: <\/b> 39.59124<br\/>  <b>Longitude: <\/b> -75.6355<br\/>  <b>Detection Time: <\/b> 2022-11-24 06:00 UTC<br\/>  <b>Sensor: <\/b> NOAA-20 VIIRS<br\/> <b>Confidence: <\/b> Nominal<br\/>  <b>Day\/Night: <\/b> Night<br\/> <b>Scan: <\/b> 0.5 km<br\/> <b>Track: <\/b> 0.6 km<br\/> <b>FRP: <\/b> 2.25 MW<br\/> <b>Brightness: <\/b> 299.27 K" }, "geometry": { "type": "Point", "coordinates": [ -75.6355, 39.59124, 0.0 ] } },
{ "type": "Feature", "properties": { "Name": "Fire Detection Centroid ", "Description": "<b>Latitude: <\/b> 40.89278<br\/>  <b>Longitude: <\/b> -77.71307<br\/>  <b>Detection Time: <\/b> 2022-11-24 06:00 UTC<br\/>  <b>Sensor: <\/b> NOAA-20 VIIRS<br\/> <b>Confidence: <\/b> Nominal<br\/>  <b>Day\/Night: <\/b> Night<br\/> <b>Scan: <\/b> 0.6 km<br\/> <b>Track: <\/b> 0.7 km<br\/> <b>FRP: <\/b> 2.71 MW<br\/> <b>Brightness: <\/b> 316.37 K" }, "geometry": { "type": "Point", "coordinates": [ -77.71307, 40.89278, 0.0 ] } },
{ "type": "Feature", "properties": { "Name": "Fire Detection Centroid ", "Description": "<b>Latitude: <\/b> 44.44658<br\/>  <b>Longitude: <\/b> -68.56013<br\/>  <b>Detection Time: <\/b> 2022-11-24 05:59 UTC<br\/>  <b>Sensor: <\/b> NOAA-20 VIIRS<br\/> <b>Confidence: <\/b> Nominal<br\/>  <b>Day\/Night: <\/b> Night<br\/> <b>Scan: <\/b> 0.5 km<br\/> <b>Track: <\/b> 0.5 km<br\/> <b>FRP: <\/b> 2.94 MW<br\/> <b>Brightness: <\/b> 336.05 K" }, "geometry": { "type": "Point", "coordinates": [ -68.56013, 44.44658, 0.0 ] } }
]
}
