{
"type": "FeatureCollection",
"crs": { "type": "name", "properties": { "name": "urn:ogc:def:crs:OGC:1.3:CRS84" } },
"features": [
{ "type": "Feature", "properties": { "Name": "Fire Detection Centroid ", "Description": "<b>Latitude: <\/b> 21.4174<br\/>  <b>Longitude: <\/b> -157.97145<br\/>  <b>Detection Time: <\/b> 2023-08-13 23:52 UTC<br\/>  <b>Sensor: <\/b> NOAA-20 VIIRS<br\/> <b>Confidence: <\/b> Nominal<br\/>  <b>Day\/Night: <\/b> Day<br\/> <b>Scan: <\/b> 0.42 km<br\/> <b>Track: <\/b> 0.37 km<br\/> <b>FRP: <\/b> 2.91 MW<br\/> <b>Brightness: <\/b> 347.27 K" }, "geometry": { "type": "Point", "coordinates": [ -157.97145, 21.4174, 0.0 ] } }
]
}
