{
"type": "FeatureCollection",
"crs": { "type": "name", "properties": { "name": "urn:ogc:def:crs:OGC:1.3:CRS84" } },
"features": [
{ "type": "Feature", "properties": { "Name": "Fire Detection Centroid ", "Description": "<b>Latitude: <\/b> 19.59592<br\/>  <b>Longitude: <\/b> -155.50548<br\/>  <b>Detection Time: <\/b> 2023-04-26 11:45 UTC<br\/>  <b>Sensor: <\/b> NOAA-20 VIIRS<br\/> <b>Confidence: <\/b> Nominal<br\/>  <b>Day\/Night: <\/b> Night<br\/> <b>Scan: <\/b> 0.51 km<br\/> <b>Track: <\/b> 0.41 km<br\/> <b>FRP: <\/b> 2.15 MW<br\/> <b>Brightness: <\/b> 295.76 K" }, "geometry": { "type": "Point", "coordinates": [ -155.50548, 19.59592, 0.0 ] } }
]
}
