{
"type": "FeatureCollection",
"crs": { "type": "name", "properties": { "name": "urn:ogc:def:crs:OGC:1.3:CRS84" } },
"features": [
{ "type": "Feature", "properties": { "Name": "Fire Detection Centroid ", "Description": "<b>Latitude: <\/b> 40.70494<br\/>  <b>Longitude: <\/b> -123.84256<br\/>  <b>Detection Time: <\/b> 2023-02-03 21:57 UTC<br\/>  <b>Sensor: <\/b> NOAA-20 VIIRS<br\/> <b>Confidence: <\/b> Nominal<br\/>  <b>Day\/Night: <\/b> Day<br\/> <b>Scan: <\/b> 0.35 km<br\/> <b>Track: <\/b> 0.57 km<br\/> <b>FRP: <\/b> 4.86 MW<br\/> <b>Brightness: <\/b> 328.75 K" }, "geometry": { "type": "Point", "coordinates": [ -123.84256, 40.70494, 0.0 ] } }
]
}
