{
"type": "FeatureCollection",
"crs": { "type": "name", "properties": { "name": "urn:ogc:def:crs:OGC:1.3:CRS84" } },
"features": [
{ "type": "Feature", "properties": { "Name": "Fire Detection Centroid ", "Description": "<b>Latitude: <\/b> 45.27263<br\/>  <b>Longitude: <\/b> -74.99959<br\/>  <b>Detection Time: <\/b> 2024-04-11 06:25 UTC<br\/>  <b>Sensor: <\/b> NOAA-20 VIIRS<br\/> <b>Confidence: <\/b> Nominal<br\/>  <b>Day\/Night: <\/b> Night<br\/> <b>Scan: <\/b> 0.5 km<br\/> <b>Track: <\/b> 0.5 km<br\/> <b>FRP: <\/b> 0.88 MW<br\/> <b>Brightness: <\/b> 295.69 K" }, "geometry": { "type": "Point", "coordinates": [ -74.99959, 45.27263, 0.0 ] } },
{ "type": "Feature", "properties": { "Name": "Fire Detection Centroid ", "Description": "<b>Latitude: <\/b> 44.85075<br\/>  <b>Longitude: <\/b> -74.98964<br\/>  <b>Detection Time: <\/b> 2024-04-11 06:25 UTC<br\/>  <b>Sensor: <\/b> NOAA-20 VIIRS<br\/> <b>Confidence: <\/b> Nominal<br\/>  <b>Day\/Night: <\/b> Night<br\/> <b>Scan: <\/b> 0.5 km<br\/> <b>Track: <\/b> 0.5 km<br\/> <b>FRP: <\/b> 1.48 MW<br\/> <b>Brightness: <\/b> 305.77 K" }, "geometry": { "type": "Point", "coordinates": [ -74.98964, 44.85075, 0.0 ] } },
{ "type": "Feature", "properties": { "Name": "Fire Detection Centroid ", "Description": "<b>Latitude: <\/b> 45.72691<br\/>  <b>Longitude: <\/b> -73.27259<br\/>  <b>Detection Time: <\/b> 2024-04-11 06:25 UTC<br\/>  <b>Sensor: <\/b> NOAA-20 VIIRS<br\/> <b>Confidence: <\/b> Nominal<br\/>  <b>Day\/Night: <\/b> Night<br\/> <b>Scan: <\/b> 0.4 km<br\/> <b>Track: <\/b> 0.4 km<br\/> <b>FRP: <\/b> 1.08 MW<br\/> <b>Brightness: <\/b> 301.67 K" }, "geometry": { "type": "Point", "coordinates": [ -73.27259, 45.72691, 0.0 ] } },
{ "type": "Feature", "properties": { "Name": "Fire Detection Centroid ", "Description": "<b>Latitude: <\/b> 48.2495<br\/>  <b>Longitude: <\/b> -79.02381<br\/>  <b>Detection Time: <\/b> 2024-04-11 06:24 UTC<br\/>  <b>Sensor: <\/b> NOAA-20 VIIRS<br\/> <b>Confidence: <\/b> Nominal<br\/>  <b>Day\/Night: <\/b> Night<br\/> <b>Scan: <\/b> 0.4 km<br\/> <b>Track: <\/b> 0.6 km<br\/> <b>FRP: <\/b> 0.7 MW<br\/> <b>Brightness: <\/b> 296.55 K" }, "geometry": { "type": "Point", "coordinates": [ -79.02381, 48.2495, 0.0 ] } }
]
}
