{
"type": "FeatureCollection",
"crs": { "type": "name", "properties": { "name": "urn:ogc:def:crs:OGC:1.3:CRS84" } },
"features": [
{ "type": "Feature", "properties": { "Name": "Fire Detection Centroid ", "Description": "<b>Latitude: <\/b> 19.4832<br\/>  <b>Longitude: <\/b> -155.5838<br\/>  <b>Detection Time: <\/b> 2022-12-16 00:09 UTC<br\/>  <b>Sensor: <\/b> NOAA-20 VIIRS<br\/> <b>Confidence: <\/b> Low<br\/>  <b>Day\/Night: <\/b> Day<br\/> <b>Scan: <\/b> 0.3 km<br\/> <b>Track: <\/b> 0.5 km<br\/> <b>FRP: <\/b> 13.96 MW<br\/> <b>Brightness: <\/b> 367 K" }, "geometry": { "type": "Point", "coordinates": [ -155.5838, 19.4832, 0.0 ] } },
{ "type": "Feature", "properties": { "Name": "Fire Detection Centroid ", "Description": "<b>Latitude: <\/b> 19.47848<br\/>  <b>Longitude: <\/b> -155.58022<br\/>  <b>Detection Time: <\/b> 2022-12-16 00:09 UTC<br\/>  <b>Sensor: <\/b> NOAA-20 VIIRS<br\/> <b>Confidence: <\/b> High<br\/>  <b>Day\/Night: <\/b> Day<br\/> <b>Scan: <\/b> 0.3 km<br\/> <b>Track: <\/b> 0.5 km<br\/> <b>FRP: <\/b> 16.31 MW<br\/> <b>Brightness: <\/b> 367 K" }, "geometry": { "type": "Point", "coordinates": [ -155.58022, 19.47848, 0.0 ] } },
{ "type": "Feature", "properties": { "Name": "Fire Detection Centroid ", "Description": "<b>Latitude: <\/b> 19.48352<br\/>  <b>Longitude: <\/b> -155.58069<br\/>  <b>Detection Time: <\/b> 2022-12-16 00:09 UTC<br\/>  <b>Sensor: <\/b> NOAA-20 VIIRS<br\/> <b>Confidence: <\/b> Low<br\/>  <b>Day\/Night: <\/b> Day<br\/> <b>Scan: <\/b> 0.3 km<br\/> <b>Track: <\/b> 0.5 km<br\/> <b>FRP: <\/b> 16.31 MW<br\/> <b>Brightness: <\/b> 354.27 K" }, "geometry": { "type": "Point", "coordinates": [ -155.58069, 19.48352, 0.0 ] } },
{ "type": "Feature", "properties": { "Name": "Fire Detection Centroid ", "Description": "<b>Latitude: <\/b> 19.47817<br\/>  <b>Longitude: <\/b> -155.58325<br\/>  <b>Detection Time: <\/b> 2022-12-16 00:09 UTC<br\/>  <b>Sensor: <\/b> NOAA-20 VIIRS<br\/> <b>Confidence: <\/b> Low<br\/>  <b>Day\/Night: <\/b> Day<br\/> <b>Scan: <\/b> 0.3 km<br\/> <b>Track: <\/b> 0.5 km<br\/> <b>FRP: <\/b> 13.96 MW<br\/> <b>Brightness: <\/b> 367 K" }, "geometry": { "type": "Point", "coordinates": [ -155.58325, 19.47817, 0.0 ] } }
]
}
