{
"type": "FeatureCollection",
"crs": { "type": "name", "properties": { "name": "urn:ogc:def:crs:OGC:1.3:CRS84" } },
"features": [
{ "type": "Feature", "properties": { "Name": "Fire Detection Centroid ", "Description": "<b>Latitude: <\/b> 19.40705<br\/>  <b>Longitude: <\/b> -155.27882<br\/>  <b>Detection Time: <\/b> 2023-10-05 23:58 UTC<br\/>  <b>Sensor: <\/b> NOAA-20 VIIRS<br\/> <b>Confidence: <\/b> Low<br\/>  <b>Day\/Night: <\/b> Day<br\/> <b>Scan: <\/b> 0.42 km<br\/> <b>Track: <\/b> 0.46 km<br\/> <b>FRP: <\/b> 14.15 MW<br\/> <b>Brightness: <\/b> 344.22 K" }, "geometry": { "type": "Point", "coordinates": [ -155.27882, 19.40705, 0.0 ] } },
{ "type": "Feature", "properties": { "Name": "Fire Detection Centroid ", "Description": "<b>Latitude: <\/b> 19.40552<br\/>  <b>Longitude: <\/b> -155.27934<br\/>  <b>Detection Time: <\/b> 2023-10-05 23:58 UTC<br\/>  <b>Sensor: <\/b> NOAA-20 VIIRS<br\/> <b>Confidence: <\/b> Low<br\/>  <b>Day\/Night: <\/b> Day<br\/> <b>Scan: <\/b> 0.42 km<br\/> <b>Track: <\/b> 0.46 km<br\/> <b>FRP: <\/b> 11.93 MW<br\/> <b>Brightness: <\/b> 344.31 K" }, "geometry": { "type": "Point", "coordinates": [ -155.27934, 19.40552, 0.0 ] } },
{ "type": "Feature", "properties": { "Name": "Fire Detection Centroid ", "Description": "<b>Latitude: <\/b> 19.40752<br\/>  <b>Longitude: <\/b> -155.2748<br\/>  <b>Detection Time: <\/b> 2023-10-05 23:58 UTC<br\/>  <b>Sensor: <\/b> NOAA-20 VIIRS<br\/> <b>Confidence: <\/b> Low<br\/>  <b>Day\/Night: <\/b> Day<br\/> <b>Scan: <\/b> 0.42 km<br\/> <b>Track: <\/b> 0.46 km<br\/> <b>FRP: <\/b> 17.22 MW<br\/> <b>Brightness: <\/b> 346.51 K" }, "geometry": { "type": "Point", "coordinates": [ -155.2748, 19.40752, 0.0 ] } },
{ "type": "Feature", "properties": { "Name": "Fire Detection Centroid ", "Description": "<b>Latitude: <\/b> 19.4069<br\/>  <b>Longitude: <\/b> -155.27957<br\/>  <b>Detection Time: <\/b> 2023-10-05 23:57 UTC<br\/>  <b>Sensor: <\/b> NOAA-20 VIIRS<br\/> <b>Confidence: <\/b> Low<br\/>  <b>Day\/Night: <\/b> Day<br\/> <b>Scan: <\/b> 0.4 km<br\/> <b>Track: <\/b> 0.5 km<br\/> <b>FRP: <\/b> 14.14 MW<br\/> <b>Brightness: <\/b> 344.22 K" }, "geometry": { "type": "Point", "coordinates": [ -155.27957, 19.4069, 0.0 ] } },
{ "type": "Feature", "properties": { "Name": "Fire Detection Centroid ", "Description": "<b>Latitude: <\/b> 19.40737<br\/>  <b>Longitude: <\/b> -155.27553<br\/>  <b>Detection Time: <\/b> 2023-10-05 23:57 UTC<br\/>  <b>Sensor: <\/b> NOAA-20 VIIRS<br\/> <b>Confidence: <\/b> Low<br\/>  <b>Day\/Night: <\/b> Day<br\/> <b>Scan: <\/b> 0.4 km<br\/> <b>Track: <\/b> 0.5 km<br\/> <b>FRP: <\/b> 17.21 MW<br\/> <b>Brightness: <\/b> 346.51 K" }, "geometry": { "type": "Point", "coordinates": [ -155.27553, 19.40737, 0.0 ] } }
]
}
