{
"type": "FeatureCollection",
"crs": { "type": "name", "properties": { "name": "urn:ogc:def:crs:OGC:1.3:CRS84" } },
"features": [
{ "type": "Feature", "properties": { "Name": "Fire Detection Centroid ", "Description": "<b>Latitude: <\/b> 19.40434<br\/>  <b>Longitude: <\/b> -155.27953<br\/>  <b>Detection Time: <\/b> 2023-07-11 00:30 UTC<br\/>  <b>Sensor: <\/b> NOAA-20 VIIRS<br\/> <b>Confidence: <\/b> Low<br\/>  <b>Day\/Night: <\/b> Day<br\/> <b>Scan: <\/b> 0.7 km<br\/> <b>Track: <\/b> 0.75 km<br\/> <b>FRP: <\/b> 18.1 MW<br\/> <b>Brightness: <\/b> 331.07 K" }, "geometry": { "type": "Point", "coordinates": [ -155.27953, 19.40434, 0.0 ] } },
{ "type": "Feature", "properties": { "Name": "Fire Detection Centroid ", "Description": "<b>Latitude: <\/b> 19.05256<br\/>  <b>Longitude: <\/b> -155.61501<br\/>  <b>Detection Time: <\/b> 2023-07-10 22:48 UTC<br\/>  <b>Sensor: <\/b> NOAA-20 VIIRS<br\/> <b>Confidence: <\/b> Nominal<br\/>  <b>Day\/Night: <\/b> Day<br\/> <b>Scan: <\/b> 0.53 km<br\/> <b>Track: <\/b> 0.67 km<br\/> <b>FRP: <\/b> 9.61 MW<br\/> <b>Brightness: <\/b> 345.58 K" }, "geometry": { "type": "Point", "coordinates": [ -155.61501, 19.05256, 0.0 ] } },
{ "type": "Feature", "properties": { "Name": "Fire Detection Centroid ", "Description": "<b>Latitude: <\/b> 19.0516<br\/>  <b>Longitude: <\/b> -155.61937<br\/>  <b>Detection Time: <\/b> 2023-07-10 22:48 UTC<br\/>  <b>Sensor: <\/b> NOAA-20 VIIRS<br\/> <b>Confidence: <\/b> Nominal<br\/>  <b>Day\/Night: <\/b> Day<br\/> <b>Scan: <\/b> 0.53 km<br\/> <b>Track: <\/b> 0.67 km<br\/> <b>FRP: <\/b> 7.34 MW<br\/> <b>Brightness: <\/b> 330.41 K" }, "geometry": { "type": "Point", "coordinates": [ -155.61937, 19.0516, 0.0 ] } },
{ "type": "Feature", "properties": { "Name": "Fire Detection Centroid ", "Description": "<b>Latitude: <\/b> 19.40979<br\/>  <b>Longitude: <\/b> -155.27609<br\/>  <b>Detection Time: <\/b> 2023-07-10 22:48 UTC<br\/>  <b>Sensor: <\/b> NOAA-20 VIIRS<br\/> <b>Confidence: <\/b> Low<br\/>  <b>Day\/Night: <\/b> Day<br\/> <b>Scan: <\/b> 0.49 km<br\/> <b>Track: <\/b> 0.65 km<br\/> <b>FRP: <\/b> 6.39 MW<br\/> <b>Brightness: <\/b> 330.47 K" }, "geometry": { "type": "Point", "coordinates": [ -155.27609, 19.40979, 0.0 ] } },
{ "type": "Feature", "properties": { "Name": "Fire Detection Centroid ", "Description": "<b>Latitude: <\/b> 19.05313<br\/>  <b>Longitude: <\/b> -155.61642<br\/>  <b>Detection Time: <\/b> 2023-07-10 22:48 UTC<br\/>  <b>Sensor: <\/b> NOAA-20 VIIRS<br\/> <b>Confidence: <\/b> Nominal<br\/>  <b>Day\/Night: <\/b> Day<br\/> <b>Scan: <\/b> 0.53 km<br\/> <b>Track: <\/b> 0.67 km<br\/> <b>FRP: <\/b> 9.13 MW<br\/> <b>Brightness: <\/b> 349.4 K" }, "geometry": { "type": "Point", "coordinates": [ -155.61642, 19.05313, 0.0 ] } }
]
}
