{
"type": "FeatureCollection",
"crs": { "type": "name", "properties": { "name": "urn:ogc:def:crs:OGC:1.3:CRS84" } },
"features": [
{ "type": "Feature", "properties": { "Name": "Fire Detection Centroid ", "Description": "<b>Latitude: <\/b> 20.86131<br\/>  <b>Longitude: <\/b> -156.42012<br\/>  <b>Detection Time: <\/b> 2024-03-05 11:55 UTC<br\/>  <b>Sensor: <\/b> NOAA-20 VIIRS<br\/> <b>Confidence: <\/b> Nominal<br\/>  <b>Day\/Night: <\/b> Night<br\/> <b>Scan: <\/b> 0.42 km<br\/> <b>Track: <\/b> 0.38 km<br\/> <b>FRP: <\/b> 0.3 MW<br\/> <b>Brightness: <\/b> 300.07 K" }, "geometry": { "type": "Point", "coordinates": [ -156.42012, 20.86131, 0.0 ] } }
]
}
