{
"type": "FeatureCollection",
"crs": { "type": "name", "properties": { "name": "urn:ogc:def:crs:OGC:1.3:CRS84" } },
"features": [
{ "type": "Feature", "properties": { "Name": "Fire Detection Centroid ", "Description": "<b>Latitude: <\/b> 19.40223<br\/>  <b>Longitude: <\/b> -155.2831<br\/>  <b>Detection Time: <\/b> 2022-07-19 00:22 UTC<br\/>  <b>Sensor: <\/b> NOAA-20 VIIRS<br\/> <b>Confidence: <\/b> High<br\/>  <b>Day\/Night: <\/b> Day<br\/> <b>Scan: <\/b> 0.55 km<br\/> <b>Track: <\/b> 0.68 km<br\/> <b>FRP: <\/b> 59.84 MW<br\/> <b>Brightness: <\/b> 367 K" }, "geometry": { "type": "Point", "coordinates": [ -155.2831, 19.40223, 0.0 ] } },
{ "type": "Feature", "properties": { "Name": "Fire Detection Centroid ", "Description": "<b>Latitude: <\/b> 19.4085<br\/>  <b>Longitude: <\/b> -155.28375<br\/>  <b>Detection Time: <\/b> 2022-07-19 00:22 UTC<br\/>  <b>Sensor: <\/b> NOAA-20 VIIRS<br\/> <b>Confidence: <\/b> Nominal<br\/>  <b>Day\/Night: <\/b> Day<br\/> <b>Scan: <\/b> 0.55 km<br\/> <b>Track: <\/b> 0.68 km<br\/> <b>FRP: <\/b> 12.22 MW<br\/> <b>Brightness: <\/b> 335.27 K" }, "geometry": { "type": "Point", "coordinates": [ -155.28375, 19.4085, 0.0 ] } },
{ "type": "Feature", "properties": { "Name": "Fire Detection Centroid ", "Description": "<b>Latitude: <\/b> 19.40576<br\/>  <b>Longitude: <\/b> -155.28717<br\/>  <b>Detection Time: <\/b> 2022-07-19 00:22 UTC<br\/>  <b>Sensor: <\/b> NOAA-20 VIIRS<br\/> <b>Confidence: <\/b> High<br\/>  <b>Day\/Night: <\/b> Day<br\/> <b>Scan: <\/b> 0.55 km<br\/> <b>Track: <\/b> 0.68 km<br\/> <b>FRP: <\/b> 68.76 MW<br\/> <b>Brightness: <\/b> 367 K" }, "geometry": { "type": "Point", "coordinates": [ -155.28717, 19.40576, 0.0 ] } },
{ "type": "Feature", "properties": { "Name": "Fire Detection Centroid ", "Description": "<b>Latitude: <\/b> 19.40622<br\/>  <b>Longitude: <\/b> -155.28172<br\/>  <b>Detection Time: <\/b> 2022-07-19 00:22 UTC<br\/>  <b>Sensor: <\/b> NOAA-20 VIIRS<br\/> <b>Confidence: <\/b> Nominal<br\/>  <b>Day\/Night: <\/b> Day<br\/> <b>Scan: <\/b> 0.55 km<br\/> <b>Track: <\/b> 0.68 km<br\/> <b>FRP: <\/b> 39.71 MW<br\/> <b>Brightness: <\/b> 339.12 K" }, "geometry": { "type": "Point", "coordinates": [ -155.28172, 19.40622, 0.0 ] } },
{ "type": "Feature", "properties": { "Name": "Fire Detection Centroid ", "Description": "<b>Latitude: <\/b> 19.40526<br\/>  <b>Longitude: <\/b> -155.29297<br\/>  <b>Detection Time: <\/b> 2022-07-19 00:22 UTC<br\/>  <b>Sensor: <\/b> NOAA-20 VIIRS<br\/> <b>Confidence: <\/b> Nominal<br\/>  <b>Day\/Night: <\/b> Day<br\/> <b>Scan: <\/b> 0.55 km<br\/> <b>Track: <\/b> 0.68 km<br\/> <b>FRP: <\/b> 68.76 MW<br\/> <b>Brightness: <\/b> 349.2 K" }, "geometry": { "type": "Point", "coordinates": [ -155.29297, 19.40526, 0.0 ] } }
]
}
