{
"type": "FeatureCollection",
"crs": { "type": "name", "properties": { "name": "urn:ogc:def:crs:OGC:1.3:CRS84" } },
"features": [
{ "type": "Feature", "properties": { "Name": "Fire Detection Centroid ", "Description": "<b>Latitude: <\/b> 18.00376<br\/>  <b>Longitude: <\/b> -66.8667<br\/>  <b>Detection Time: <\/b> 2023-07-30 05:17 UTC<br\/>  <b>Sensor: <\/b> NOAA-20 VIIRS<br\/> <b>Confidence: <\/b> Nominal<br\/>  <b>Day\/Night: <\/b> Night<br\/> <b>Scan: <\/b> 0.5 km<br\/> <b>Track: <\/b> 0.7 km<br\/> <b>FRP: <\/b> 3.55 MW<br\/> <b>Brightness: <\/b> 324.42 K" }, "geometry": { "type": "Point", "coordinates": [ -66.8667, 18.00376, 0.0 ] } },
{ "type": "Feature", "properties": { "Name": "Fire Detection Centroid ", "Description": "<b>Latitude: <\/b> 18.00326<br\/>  <b>Longitude: <\/b> -66.8615<br\/>  <b>Detection Time: <\/b> 2023-07-30 05:17 UTC<br\/>  <b>Sensor: <\/b> NOAA-20 VIIRS<br\/> <b>Confidence: <\/b> Nominal<br\/>  <b>Day\/Night: <\/b> Night<br\/> <b>Scan: <\/b> 0.5 km<br\/> <b>Track: <\/b> 0.7 km<br\/> <b>FRP: <\/b> 3.04 MW<br\/> <b>Brightness: <\/b> 310.05 K" }, "geometry": { "type": "Point", "coordinates": [ -66.8615, 18.00326, 0.0 ] } }
]
}
