{
"type": "FeatureCollection",
"crs": { "type": "name", "properties": { "name": "urn:ogc:def:crs:OGC:1.3:CRS84" } },
"features": [
{ "type": "Feature", "properties": { "Name": "Fire Detection Centroid ", "Description": "<b>Latitude: <\/b> 18.98267<br\/>  <b>Longitude: <\/b> -155.62767<br\/>  <b>Detection Time: <\/b> 2022-07-25 00:09 UTC<br\/>  <b>Sensor: <\/b> NOAA-20 VIIRS<br\/> <b>Confidence: <\/b> Nominal<br\/>  <b>Day\/Night: <\/b> Day<br\/> <b>Scan: <\/b> 0.63 km<br\/> <b>Track: <\/b> 0.54 km<br\/> <b>FRP: <\/b> 72.87 MW<br\/> <b>Brightness: <\/b> 341.95 K" }, "geometry": { "type": "Point", "coordinates": [ -155.62767, 18.98267, 0.0 ] } },
{ "type": "Feature", "properties": { "Name": "Fire Detection Centroid ", "Description": "<b>Latitude: <\/b> 19.72193<br\/>  <b>Longitude: <\/b> -155.64775<br\/>  <b>Detection Time: <\/b> 2022-07-25 00:09 UTC<br\/>  <b>Sensor: <\/b> NOAA-20 VIIRS<br\/> <b>Confidence: <\/b> Nominal<br\/>  <b>Day\/Night: <\/b> Day<br\/> <b>Scan: <\/b> 0.32 km<br\/> <b>Track: <\/b> 0.55 km<br\/> <b>FRP: <\/b> 6.79 MW<br\/> <b>Brightness: <\/b> 353.52 K" }, "geometry": { "type": "Point", "coordinates": [ -155.64775, 19.72193, 0.0 ] } },
{ "type": "Feature", "properties": { "Name": "Fire Detection Centroid ", "Description": "<b>Latitude: <\/b> 18.98198<br\/>  <b>Longitude: <\/b> -155.63396<br\/>  <b>Detection Time: <\/b> 2022-07-25 00:09 UTC<br\/>  <b>Sensor: <\/b> NOAA-20 VIIRS<br\/> <b>Confidence: <\/b> Nominal<br\/>  <b>Day\/Night: <\/b> Day<br\/> <b>Scan: <\/b> 0.63 km<br\/> <b>Track: <\/b> 0.54 km<br\/> <b>FRP: <\/b> 19.49 MW<br\/> <b>Brightness: <\/b> 335.16 K" }, "geometry": { "type": "Point", "coordinates": [ -155.63396, 18.98198, 0.0 ] } },
{ "type": "Feature", "properties": { "Name": "Fire Detection Centroid ", "Description": "<b>Latitude: <\/b> 18.97841<br\/>  <b>Longitude: <\/b> -155.62035<br\/>  <b>Detection Time: <\/b> 2022-07-25 00:09 UTC<br\/>  <b>Sensor: <\/b> NOAA-20 VIIRS<br\/> <b>Confidence: <\/b> Nominal<br\/>  <b>Day\/Night: <\/b> Day<br\/> <b>Scan: <\/b> 0.63 km<br\/> <b>Track: <\/b> 0.54 km<br\/> <b>FRP: <\/b> 72.87 MW<br\/> <b>Brightness: <\/b> 355.79 K" }, "geometry": { "type": "Point", "coordinates": [ -155.62035, 18.97841, 0.0 ] } },
{ "type": "Feature", "properties": { "Name": "Fire Detection Centroid ", "Description": "<b>Latitude: <\/b> 18.98337<br\/>  <b>Longitude: <\/b> -155.62126<br\/>  <b>Detection Time: <\/b> 2022-07-25 00:09 UTC<br\/>  <b>Sensor: <\/b> NOAA-20 VIIRS<br\/> <b>Confidence: <\/b> Nominal<br\/>  <b>Day\/Night: <\/b> Day<br\/> <b>Scan: <\/b> 0.63 km<br\/> <b>Track: <\/b> 0.54 km<br\/> <b>FRP: <\/b> 72.87 MW<br\/> <b>Brightness: <\/b> 349.84 K" }, "geometry": { "type": "Point", "coordinates": [ -155.62126, 18.98337, 0.0 ] } },
{ "type": "Feature", "properties": { "Name": "Fire Detection Centroid ", "Description": "<b>Latitude: <\/b> 18.98407<br\/>  <b>Longitude: <\/b> -155.61488<br\/>  <b>Detection Time: <\/b> 2022-07-25 00:09 UTC<br\/>  <b>Sensor: <\/b> NOAA-20 VIIRS<br\/> <b>Confidence: <\/b> Nominal<br\/>  <b>Day\/Night: <\/b> Day<br\/> <b>Scan: <\/b> 0.63 km<br\/> <b>Track: <\/b> 0.54 km<br\/> <b>FRP: <\/b> 42.02 MW<br\/> <b>Brightness: <\/b> 346.85 K" }, "geometry": { "type": "Point", "coordinates": [ -155.61488, 18.98407, 0.0 ] } }
]
}
