{
"type": "FeatureCollection",
"crs": { "type": "name", "properties": { "name": "urn:ogc:def:crs:OGC:1.3:CRS84" } },
"features": [
{ "type": "Feature", "properties": { "Name": "Fire Detection Centroid ", "Description": "<b>Latitude: <\/b> 45.83549<br\/>  <b>Longitude: <\/b> -73.24933<br\/>  <b>Detection Time: <\/b> 2023-07-19 16:42 UTC<br\/>  <b>Sensor: <\/b> NOAA-20 VIIRS<br\/> <b>Confidence: <\/b> Nominal<br\/>  <b>Day\/Night: <\/b> Day<br\/> <b>Scan: <\/b> 0.4 km<br\/> <b>Track: <\/b> 0.6 km<br\/> <b>FRP: <\/b> 4.92 MW<br\/> <b>Brightness: <\/b> 329.18 K" }, "geometry": { "type": "Point", "coordinates": [ -73.24933, 45.83549, 0.0 ] } },
{ "type": "Feature", "properties": { "Name": "Fire Detection Centroid ", "Description": "<b>Latitude: <\/b> 44.84035<br\/>  <b>Longitude: <\/b> -75.41073<br\/>  <b>Detection Time: <\/b> 2023-07-19 16:42 UTC<br\/>  <b>Sensor: <\/b> NOAA-20 VIIRS<br\/> <b>Confidence: <\/b> Nominal<br\/>  <b>Day\/Night: <\/b> Day<br\/> <b>Scan: <\/b> 0.6 km<br\/> <b>Track: <\/b> 0.7 km<br\/> <b>FRP: <\/b> 3.78 MW<br\/> <b>Brightness: <\/b> 331.63 K" }, "geometry": { "type": "Point", "coordinates": [ -75.41073, 44.84035, 0.0 ] } },
{ "type": "Feature", "properties": { "Name": "Fire Detection Centroid ", "Description": "<b>Latitude: <\/b> 44.84184<br\/>  <b>Longitude: <\/b> -75.41212<br\/>  <b>Detection Time: <\/b> 2023-07-19 16:42 UTC<br\/>  <b>Sensor: <\/b> NOAA-20 VIIRS<br\/> <b>Confidence: <\/b> Nominal<br\/>  <b>Day\/Night: <\/b> Day<br\/> <b>Scan: <\/b> 0.6 km<br\/> <b>Track: <\/b> 0.7 km<br\/> <b>FRP: <\/b> 3.2 MW<br\/> <b>Brightness: <\/b> 331.79 K" }, "geometry": { "type": "Point", "coordinates": [ -75.41212, 44.84184, 0.0 ] } },
{ "type": "Feature", "properties": { "Name": "Fire Detection Centroid ", "Description": "<b>Latitude: <\/b> 45.83757<br\/>  <b>Longitude: <\/b> -73.25142<br\/>  <b>Detection Time: <\/b> 2023-07-19 16:42 UTC<br\/>  <b>Sensor: <\/b> NOAA-20 VIIRS<br\/> <b>Confidence: <\/b> Nominal<br\/>  <b>Day\/Night: <\/b> Day<br\/> <b>Scan: <\/b> 0.4 km<br\/> <b>Track: <\/b> 0.6 km<br\/> <b>FRP: <\/b> 3.84 MW<br\/> <b>Brightness: <\/b> 326.91 K" }, "geometry": { "type": "Point", "coordinates": [ -73.25142, 45.83757, 0.0 ] } }
]
}
