{
"type": "FeatureCollection",
"crs": { "type": "name", "properties": { "name": "urn:ogc:def:crs:OGC:1.3:CRS84" } },
"features": [
{ "type": "Feature", "properties": { "Name": "Fire Detection Centroid ", "Description": "<b>Latitude: <\/b> 33.84861<br\/>  <b>Longitude: <\/b> -116.40802<br\/>  <b>Detection Time: <\/b> 2024-03-04 21:48 UTC<br\/>  <b>Sensor: <\/b> NOAA-20 VIIRS<br\/> <b>Confidence: <\/b> Nominal<br\/>  <b>Day\/Night: <\/b> Day<br\/> <b>Scan: <\/b> 0.66 km<br\/> <b>Track: <\/b> 0.73 km<br\/> <b>FRP: <\/b> 6.59 MW<br\/> <b>Brightness: <\/b> 343.77 K" }, "geometry": { "type": "Point", "coordinates": [ -116.40802, 33.84861, 0.0 ] } },
{ "type": "Feature", "properties": { "Name": "Fire Detection Centroid ", "Description": "<b>Latitude: <\/b> 32.23992<br\/>  <b>Longitude: <\/b> -115.2656<br\/>  <b>Detection Time: <\/b> 2024-03-04 21:48 UTC<br\/>  <b>Sensor: <\/b> NOAA-20 VIIRS<br\/> <b>Confidence: <\/b> Nominal<br\/>  <b>Day\/Night: <\/b> Day<br\/> <b>Scan: <\/b> 0.75 km<br\/> <b>Track: <\/b> 0.77 km<br\/> <b>FRP: <\/b> 4.42 MW<br\/> <b>Brightness: <\/b> 335.22 K" }, "geometry": { "type": "Point", "coordinates": [ -115.2656, 32.23992, 0.0 ] } },
{ "type": "Feature", "properties": { "Name": "Fire Detection Centroid ", "Description": "<b>Latitude: <\/b> 37.16161<br\/>  <b>Longitude: <\/b> -120.21391<br\/>  <b>Detection Time: <\/b> 2024-03-04 21:48 UTC<br\/>  <b>Sensor: <\/b> NOAA-20 VIIRS<br\/> <b>Confidence: <\/b> Nominal<br\/>  <b>Day\/Night: <\/b> Day<br\/> <b>Scan: <\/b> 0.42 km<br\/> <b>Track: <\/b> 0.61 km<br\/> <b>FRP: <\/b> 3.12 MW<br\/> <b>Brightness: <\/b> 338.14 K" }, "geometry": { "type": "Point", "coordinates": [ -120.21391, 37.16161, 0.0 ] } },
{ "type": "Feature", "properties": { "Name": "Fire Detection Centroid ", "Description": "<b>Latitude: <\/b> 37.11067<br\/>  <b>Longitude: <\/b> -120.21117<br\/>  <b>Detection Time: <\/b> 2024-03-04 21:48 UTC<br\/>  <b>Sensor: <\/b> NOAA-20 VIIRS<br\/> <b>Confidence: <\/b> Nominal<br\/>  <b>Day\/Night: <\/b> Day<br\/> <b>Scan: <\/b> 0.4 km<br\/> <b>Track: <\/b> 0.6 km<br\/> <b>FRP: <\/b> 3.12 MW<br\/> <b>Brightness: <\/b> 338.14 K" }, "geometry": { "type": "Point", "coordinates": [ -120.21117, 37.11067, 0.0 ] } },
{ "type": "Feature", "properties": { "Name": "Fire Detection Centroid ", "Description": "<b>Latitude: <\/b> 33.84224<br\/>  <b>Longitude: <\/b> -116.40812<br\/>  <b>Detection Time: <\/b> 2024-03-04 21:47 UTC<br\/>  <b>Sensor: <\/b> NOAA-20 VIIRS<br\/> <b>Confidence: <\/b> Nominal<br\/>  <b>Day\/Night: <\/b> Day<br\/> <b>Scan: <\/b> 0.7 km<br\/> <b>Track: <\/b> 0.7 km<br\/> <b>FRP: <\/b> 6.59 MW<br\/> <b>Brightness: <\/b> 343.77 K" }, "geometry": { "type": "Point", "coordinates": [ -116.40812, 33.84224, 0.0 ] } },
{ "type": "Feature", "properties": { "Name": "Fire Detection Centroid ", "Description": "<b>Latitude: <\/b> 33.84224<br\/>  <b>Longitude: <\/b> -116.40812<br\/>  <b>Detection Time: <\/b> 2024-03-04 21:47 UTC<br\/>  <b>Sensor: <\/b> NOAA-20 VIIRS<br\/> <b>Confidence: <\/b> Nominal<br\/>  <b>Day\/Night: <\/b> Day<br\/> <b>Scan: <\/b> 0.7 km<br\/> <b>Track: <\/b> 0.7 km<br\/> <b>FRP: <\/b> 6.59 MW<br\/> <b>Brightness: <\/b> 343.77 K" }, "geometry": { "type": "Point", "coordinates": [ -116.40812, 33.84224, 0.0 ] } },
{ "type": "Feature", "properties": { "Name": "Fire Detection Centroid ", "Description": "<b>Latitude: <\/b> 32.20477<br\/>  <b>Longitude: <\/b> -115.26596<br\/>  <b>Detection Time: <\/b> 2024-03-04 21:47 UTC<br\/>  <b>Sensor: <\/b> NOAA-20 VIIRS<br\/> <b>Confidence: <\/b> Nominal<br\/>  <b>Day\/Night: <\/b> Day<br\/> <b>Scan: <\/b> 0.7 km<br\/> <b>Track: <\/b> 0.8 km<br\/> <b>FRP: <\/b> 4.41 MW<br\/> <b>Brightness: <\/b> 335.22 K" }, "geometry": { "type": "Point", "coordinates": [ -115.26596, 32.20477, 0.0 ] } }
]
}
