{
"type": "FeatureCollection",
"crs": { "type": "name", "properties": { "name": "urn:ogc:def:crs:OGC:1.3:CRS84" } },
"features": [
{ "type": "Feature", "properties": { "Name": "Fire Detection Centroid ", "Description": "<b>Latitude: <\/b> 42.80397<br\/>  <b>Longitude: <\/b> -80.09736<br\/>  <b>Detection Time: <\/b> 2024-01-04 17:12 UTC<br\/>  <b>Sensor: <\/b> NOAA-20 VIIRS<br\/> <b>Confidence: <\/b> Nominal<br\/>  <b>Day\/Night: <\/b> Day<br\/> <b>Scan: <\/b> 0.5 km<br\/> <b>Track: <\/b> 0.7 km<br\/> <b>FRP: <\/b> 5.73 MW<br\/> <b>Brightness: <\/b> 325.7 K" }, "geometry": { "type": "Point", "coordinates": [ -80.09736, 42.80397, 0.0 ] } },
{ "type": "Feature", "properties": { "Name": "Fire Detection Centroid ", "Description": "<b>Latitude: <\/b> 42.80622<br\/>  <b>Longitude: <\/b> -80.09823<br\/>  <b>Detection Time: <\/b> 2024-01-04 17:12 UTC<br\/>  <b>Sensor: <\/b> NOAA-20 VIIRS<br\/> <b>Confidence: <\/b> Nominal<br\/>  <b>Day\/Night: <\/b> Day<br\/> <b>Scan: <\/b> 0.5 km<br\/> <b>Track: <\/b> 0.7 km<br\/> <b>FRP: <\/b> 4.37 MW<br\/> <b>Brightness: <\/b> 337.49 K" }, "geometry": { "type": "Point", "coordinates": [ -80.09823, 42.80622, 0.0 ] } },
{ "type": "Feature", "properties": { "Name": "Fire Detection Centroid ", "Description": "<b>Latitude: <\/b> 35.29256<br\/>  <b>Longitude: <\/b> -78.64573<br\/>  <b>Detection Time: <\/b> 2024-01-04 17:10 UTC<br\/>  <b>Sensor: <\/b> NOAA-20 VIIRS<br\/> <b>Confidence: <\/b> Nominal<br\/>  <b>Day\/Night: <\/b> Day<br\/> <b>Scan: <\/b> 0.7 km<br\/> <b>Track: <\/b> 0.7 km<br\/> <b>FRP: <\/b> 6.83 MW<br\/> <b>Brightness: <\/b> 329.15 K" }, "geometry": { "type": "Point", "coordinates": [ -78.64573, 35.29256, 0.0 ] } },
{ "type": "Feature", "properties": { "Name": "Fire Detection Centroid ", "Description": "<b>Latitude: <\/b> 35.2954<br\/>  <b>Longitude: <\/b> -78.64539<br\/>  <b>Detection Time: <\/b> 2024-01-04 17:10 UTC<br\/>  <b>Sensor: <\/b> NOAA-20 VIIRS<br\/> <b>Confidence: <\/b> Nominal<br\/>  <b>Day\/Night: <\/b> Day<br\/> <b>Scan: <\/b> 0.7 km<br\/> <b>Track: <\/b> 0.7 km<br\/> <b>FRP: <\/b> 5.44 MW<br\/> <b>Brightness: <\/b> 341.68 K" }, "geometry": { "type": "Point", "coordinates": [ -78.64539, 35.2954, 0.0 ] } },
{ "type": "Feature", "properties": { "Name": "Fire Detection Centroid ", "Description": "<b>Latitude: <\/b> 35.50714<br\/>  <b>Longitude: <\/b> -79.8539<br\/>  <b>Detection Time: <\/b> 2024-01-04 17:10 UTC<br\/>  <b>Sensor: <\/b> NOAA-20 VIIRS<br\/> <b>Confidence: <\/b> Nominal<br\/>  <b>Day\/Night: <\/b> Day<br\/> <b>Scan: <\/b> 0.8 km<br\/> <b>Track: <\/b> 0.8 km<br\/> <b>FRP: <\/b> 5.29 MW<br\/> <b>Brightness: <\/b> 329.96 K" }, "geometry": { "type": "Point", "coordinates": [ -79.8539, 35.50714, 0.0 ] } },
{ "type": "Feature", "properties": { "Name": "Fire Detection Centroid ", "Description": "<b>Latitude: <\/b> 18.37535<br\/>  <b>Longitude: <\/b> -68.66776<br\/>  <b>Detection Time: <\/b> 2024-01-04 17:05 UTC<br\/>  <b>Sensor: <\/b> NOAA-20 VIIRS<br\/> <b>Confidence: <\/b> Nominal<br\/>  <b>Day\/Night: <\/b> Day<br\/> <b>Scan: <\/b> 0.5 km<br\/> <b>Track: <\/b> 0.6 km<br\/> <b>FRP: <\/b> 2.83 MW<br\/> <b>Brightness: <\/b> 328.3 K" }, "geometry": { "type": "Point", "coordinates": [ -68.66776, 18.37535, 0.0 ] } },
{ "type": "Feature", "properties": { "Name": "Fire Detection Centroid ", "Description": "<b>Latitude: <\/b> 18.87255<br\/>  <b>Longitude: <\/b> -70.81596<br\/>  <b>Detection Time: <\/b> 2024-01-04 17:05 UTC<br\/>  <b>Sensor: <\/b> NOAA-20 VIIRS<br\/> <b>Confidence: <\/b> Nominal<br\/>  <b>Day\/Night: <\/b> Day<br\/> <b>Scan: <\/b> 0.6 km<br\/> <b>Track: <\/b> 0.7 km<br\/> <b>FRP: <\/b> 8 MW<br\/> <b>Brightness: <\/b> 341.36 K" }, "geometry": { "type": "Point", "coordinates": [ -70.81596, 18.87255, 0.0 ] } },
{ "type": "Feature", "properties": { "Name": "Fire Detection Centroid ", "Description": "<b>Latitude: <\/b> 18.87151<br\/>  <b>Longitude: <\/b> -70.81504<br\/>  <b>Detection Time: <\/b> 2024-01-04 17:05 UTC<br\/>  <b>Sensor: <\/b> NOAA-20 VIIRS<br\/> <b>Confidence: <\/b> Nominal<br\/>  <b>Day\/Night: <\/b> Day<br\/> <b>Scan: <\/b> 0.6 km<br\/> <b>Track: <\/b> 0.7 km<br\/> <b>FRP: <\/b> 12.22 MW<br\/> <b>Brightness: <\/b> 343.79 K" }, "geometry": { "type": "Point", "coordinates": [ -70.81504, 18.87151, 0.0 ] } }
]
}
