{
"type": "FeatureCollection",
"crs": { "type": "name", "properties": { "name": "urn:ogc:def:crs:OGC:1.3:CRS84" } },
"features": [
{ "type": "Feature", "properties": { "Name": "Fire Detection Centroid ", "Description": "<b>Latitude: <\/b> 45.27998<br\/>  <b>Longitude: <\/b> -66.01687<br\/>  <b>Detection Time: <\/b> 2023-07-13 05:28 UTC<br\/>  <b>Sensor: <\/b> NOAA-20 VIIRS<br\/> <b>Confidence: <\/b> Nominal<br\/>  <b>Day\/Night: <\/b> Night<br\/> <b>Scan: <\/b> 0.4 km<br\/> <b>Track: <\/b> 0.6 km<br\/> <b>FRP: <\/b> 1.4 MW<br\/> <b>Brightness: <\/b> 301.08 K" }, "geometry": { "type": "Point", "coordinates": [ -66.01687, 45.27998, 0.0 ] } }
]
}
