{
"type": "FeatureCollection",
"crs": { "type": "name", "properties": { "name": "urn:ogc:def:crs:OGC:1.3:CRS84" } },
"features": [
{ "type": "Feature", "properties": { "Name": "Fire Detection Centroid ", "Description": "<b>Latitude: <\/b> 46.58667<br\/>  <b>Longitude: <\/b> -84.42242<br\/>  <b>Detection Time: <\/b> 2024-04-24 17:09 UTC<br\/>  <b>Sensor: <\/b> NOAA-20 VIIRS<br\/> <b>Confidence: <\/b> Nominal<br\/>  <b>Day\/Night: <\/b> Day<br\/> <b>Scan: <\/b> 0.7 km<br\/> <b>Track: <\/b> 0.7 km<br\/> <b>FRP: <\/b> 5.07 MW<br\/> <b>Brightness: <\/b> 326.09 K" }, "geometry": { "type": "Point", "coordinates": [ -84.42242, 46.58667, 0.0 ] } },
{ "type": "Feature", "properties": { "Name": "Fire Detection Centroid ", "Description": "<b>Latitude: <\/b> 40.79332<br\/>  <b>Longitude: <\/b> -77.65718<br\/>  <b>Detection Time: <\/b> 2024-04-24 17:07 UTC<br\/>  <b>Sensor: <\/b> NOAA-20 VIIRS<br\/> <b>Confidence: <\/b> Nominal<br\/>  <b>Day\/Night: <\/b> Day<br\/> <b>Scan: <\/b> 0.5 km<br\/> <b>Track: <\/b> 0.7 km<br\/> <b>FRP: <\/b> 4.28 MW<br\/> <b>Brightness: <\/b> 329.9 K" }, "geometry": { "type": "Point", "coordinates": [ -77.65718, 40.79332, 0.0 ] } },
{ "type": "Feature", "properties": { "Name": "Fire Detection Centroid ", "Description": "<b>Latitude: <\/b> 34.37077<br\/>  <b>Longitude: <\/b> -77.68015<br\/>  <b>Detection Time: <\/b> 2024-04-24 17:05 UTC<br\/>  <b>Sensor: <\/b> NOAA-20 VIIRS<br\/> <b>Confidence: <\/b> Nominal<br\/>  <b>Day\/Night: <\/b> Day<br\/> <b>Scan: <\/b> 0.8 km<br\/> <b>Track: <\/b> 0.8 km<br\/> <b>FRP: <\/b> 9.41 MW<br\/> <b>Brightness: <\/b> 347.29 K" }, "geometry": { "type": "Point", "coordinates": [ -77.68015, 34.37077, 0.0 ] } },
{ "type": "Feature", "properties": { "Name": "Fire Detection Centroid ", "Description": "<b>Latitude: <\/b> 35.18518<br\/>  <b>Longitude: <\/b> -76.7563<br\/>  <b>Detection Time: <\/b> 2024-04-24 17:05 UTC<br\/>  <b>Sensor: <\/b> NOAA-20 VIIRS<br\/> <b>Confidence: <\/b> Nominal<br\/>  <b>Day\/Night: <\/b> Day<br\/> <b>Scan: <\/b> 0.6 km<br\/> <b>Track: <\/b> 0.7 km<br\/> <b>FRP: <\/b> 6.55 MW<br\/> <b>Brightness: <\/b> 333.49 K" }, "geometry": { "type": "Point", "coordinates": [ -76.7563, 35.18518, 0.0 ] } }
]
}
