{
"type": "FeatureCollection",
"crs": { "type": "name", "properties": { "name": "urn:ogc:def:crs:OGC:1.3:CRS84" } },
"features": [
{ "type": "Feature", "properties": { "Name": "Fire Detection Centroid ", "Description": "<b>Latitude: <\/b> 17.9136<br\/>  <b>Longitude: <\/b> -71.35236<br\/>  <b>Detection Time: <\/b> 2023-05-04 05:49 UTC<br\/>  <b>Sensor: <\/b> NOAA-20 VIIRS<br\/> <b>Confidence: <\/b> Nominal<br\/>  <b>Day\/Night: <\/b> Night<br\/> <b>Scan: <\/b> 0.6 km<br\/> <b>Track: <\/b> 0.5 km<br\/> <b>FRP: <\/b> 0.75 MW<br\/> <b>Brightness: <\/b> 295.18 K" }, "geometry": { "type": "Point", "coordinates": [ -71.35236, 17.9136, 0.0 ] } },
{ "type": "Feature", "properties": { "Name": "Fire Detection Centroid ", "Description": "<b>Latitude: <\/b> 18.86176<br\/>  <b>Longitude: <\/b> -69.64285<br\/>  <b>Detection Time: <\/b> 2023-05-04 05:48 UTC<br\/>  <b>Sensor: <\/b> NOAA-20 VIIRS<br\/> <b>Confidence: <\/b> Nominal<br\/>  <b>Day\/Night: <\/b> Night<br\/> <b>Scan: <\/b> 0.5 km<br\/> <b>Track: <\/b> 0.5 km<br\/> <b>FRP: <\/b> 0.94 MW<br\/> <b>Brightness: <\/b> 304.82 K" }, "geometry": { "type": "Point", "coordinates": [ -69.64285, 18.86176, 0.0 ] } },
{ "type": "Feature", "properties": { "Name": "Fire Detection Centroid ", "Description": "<b>Latitude: <\/b> 18.92595<br\/>  <b>Longitude: <\/b> -70.35263<br\/>  <b>Detection Time: <\/b> 2023-05-04 05:48 UTC<br\/>  <b>Sensor: <\/b> NOAA-20 VIIRS<br\/> <b>Confidence: <\/b> Nominal<br\/>  <b>Day\/Night: <\/b> Night<br\/> <b>Scan: <\/b> 0.6 km<br\/> <b>Track: <\/b> 0.5 km<br\/> <b>FRP: <\/b> 7.64 MW<br\/> <b>Brightness: <\/b> 336.56 K" }, "geometry": { "type": "Point", "coordinates": [ -70.35263, 18.92595, 0.0 ] } }
]
}
