{
"type": "FeatureCollection",
"crs": { "type": "name", "properties": { "name": "urn:ogc:def:crs:OGC:1.3:CRS84" } },
"features": [
{ "type": "Feature", "properties": { "Name": "Fire Detection Centroid ", "Description": "<b>Latitude: <\/b> 45.22548<br\/>  <b>Longitude: <\/b> -123.16552<br\/>  <b>Detection Time: <\/b> 2023-07-07 22:10 UTC<br\/>  <b>Sensor: <\/b> NOAA-20 VIIRS<br\/> <b>Confidence: <\/b> Low<br\/>  <b>Day\/Night: <\/b> Day<br\/> <b>Scan: <\/b> 0.59 km<br\/> <b>Track: <\/b> 0.7 km<br\/> <b>FRP: <\/b> 5.88 MW<br\/> <b>Brightness: <\/b> 328.01 K" }, "geometry": { "type": "Point", "coordinates": [ -123.16552, 45.22548, 0.0 ] } },
{ "type": "Feature", "properties": { "Name": "Fire Detection Centroid ", "Description": "<b>Latitude: <\/b> 45.22655<br\/>  <b>Longitude: <\/b> -123.16448<br\/>  <b>Detection Time: <\/b> 2023-07-07 22:10 UTC<br\/>  <b>Sensor: <\/b> NOAA-20 VIIRS<br\/> <b>Confidence: <\/b> Low<br\/>  <b>Day\/Night: <\/b> Day<br\/> <b>Scan: <\/b> 0.59 km<br\/> <b>Track: <\/b> 0.7 km<br\/> <b>FRP: <\/b> 5.53 MW<br\/> <b>Brightness: <\/b> 329.16 K" }, "geometry": { "type": "Point", "coordinates": [ -123.16448, 45.22655, 0.0 ] } },
{ "type": "Feature", "properties": { "Name": "Fire Detection Centroid ", "Description": "<b>Latitude: <\/b> 39.00156<br\/>  <b>Longitude: <\/b> -121.43597<br\/>  <b>Detection Time: <\/b> 2023-07-07 22:08 UTC<br\/>  <b>Sensor: <\/b> NOAA-20 VIIRS<br\/> <b>Confidence: <\/b> Nominal<br\/>  <b>Day\/Night: <\/b> Day<br\/> <b>Scan: <\/b> 0.69 km<br\/> <b>Track: <\/b> 0.74 km<br\/> <b>FRP: <\/b> 7.96 MW<br\/> <b>Brightness: <\/b> 339.78 K" }, "geometry": { "type": "Point", "coordinates": [ -121.43597, 39.00156, 0.0 ] } },
{ "type": "Feature", "properties": { "Name": "Fire Detection Centroid ", "Description": "<b>Latitude: <\/b> 39.13951<br\/>  <b>Longitude: <\/b> -121.95106<br\/>  <b>Detection Time: <\/b> 2023-07-07 22:08 UTC<br\/>  <b>Sensor: <\/b> NOAA-20 VIIRS<br\/> <b>Confidence: <\/b> Nominal<br\/>  <b>Day\/Night: <\/b> Day<br\/> <b>Scan: <\/b> 0.64 km<br\/> <b>Track: <\/b> 0.72 km<br\/> <b>FRP: <\/b> 6.56 MW<br\/> <b>Brightness: <\/b> 334.71 K" }, "geometry": { "type": "Point", "coordinates": [ -121.95106, 39.13951, 0.0 ] } },
{ "type": "Feature", "properties": { "Name": "Fire Detection Centroid ", "Description": "<b>Latitude: <\/b> 39.00143<br\/>  <b>Longitude: <\/b> -121.43269<br\/>  <b>Detection Time: <\/b> 2023-07-07 22:08 UTC<br\/>  <b>Sensor: <\/b> NOAA-20 VIIRS<br\/> <b>Confidence: <\/b> Nominal<br\/>  <b>Day\/Night: <\/b> Day<br\/> <b>Scan: <\/b> 0.69 km<br\/> <b>Track: <\/b> 0.74 km<br\/> <b>FRP: <\/b> 7.52 MW<br\/> <b>Brightness: <\/b> 337.23 K" }, "geometry": { "type": "Point", "coordinates": [ -121.43269, 39.00143, 0.0 ] } }
]
}
