{
"type": "FeatureCollection",
"crs": { "type": "name", "properties": { "name": "urn:ogc:def:crs:OGC:1.3:CRS84" } },
"features": [
{ "type": "Feature", "properties": { "Name": "Fire Detection Centroid ", "Description": "<b>Latitude: <\/b> 18.39138<br\/>  <b>Longitude: <\/b> -71.24647<br\/>  <b>Detection Time: <\/b> 2024-01-16 05:29 UTC<br\/>  <b>Sensor: <\/b> NOAA-20 VIIRS<br\/> <b>Confidence: <\/b> Nominal<br\/>  <b>Day\/Night: <\/b> Night<br\/> <b>Scan: <\/b> 0.65 km<br\/> <b>Track: <\/b> 0.73 km<br\/> <b>FRP: <\/b> 4.68 MW<br\/> <b>Brightness: <\/b> 335.94 K" }, "geometry": { "type": "Point", "coordinates": [ -71.24647, 18.39138, 0.0 ] } },
{ "type": "Feature", "properties": { "Name": "Fire Detection Centroid ", "Description": "<b>Latitude: <\/b> 18.39193<br\/>  <b>Longitude: <\/b> -71.25275<br\/>  <b>Detection Time: <\/b> 2024-01-16 05:29 UTC<br\/>  <b>Sensor: <\/b> NOAA-20 VIIRS<br\/> <b>Confidence: <\/b> Nominal<br\/>  <b>Day\/Night: <\/b> Night<br\/> <b>Scan: <\/b> 0.65 km<br\/> <b>Track: <\/b> 0.73 km<br\/> <b>FRP: <\/b> 4.68 MW<br\/> <b>Brightness: <\/b> 314.85 K" }, "geometry": { "type": "Point", "coordinates": [ -71.25275, 18.39193, 0.0 ] } },
{ "type": "Feature", "properties": { "Name": "Fire Detection Centroid ", "Description": "<b>Latitude: <\/b> 18.91439<br\/>  <b>Longitude: <\/b> -71.23417<br\/>  <b>Detection Time: <\/b> 2024-01-16 05:27 UTC<br\/>  <b>Sensor: <\/b> NOAA-20 VIIRS<br\/> <b>Confidence: <\/b> Nominal<br\/>  <b>Day\/Night: <\/b> Night<br\/> <b>Scan: <\/b> 0.66 km<br\/> <b>Track: <\/b> 0.73 km<br\/> <b>FRP: <\/b> 2.19 MW<br\/> <b>Brightness: <\/b> 302.21 K" }, "geometry": { "type": "Point", "coordinates": [ -71.23417, 18.91439, 0.0 ] } },
{ "type": "Feature", "properties": { "Name": "Fire Detection Centroid ", "Description": "<b>Latitude: <\/b> 18.92087<br\/>  <b>Longitude: <\/b> -71.23026<br\/>  <b>Detection Time: <\/b> 2024-01-16 05:27 UTC<br\/>  <b>Sensor: <\/b> NOAA-20 VIIRS<br\/> <b>Confidence: <\/b> Nominal<br\/>  <b>Day\/Night: <\/b> Night<br\/> <b>Scan: <\/b> 0.66 km<br\/> <b>Track: <\/b> 0.73 km<br\/> <b>FRP: <\/b> 2.59 MW<br\/> <b>Brightness: <\/b> 316.29 K" }, "geometry": { "type": "Point", "coordinates": [ -71.23026, 18.92087, 0.0 ] } }
]
}
