{
"type": "FeatureCollection",
"crs": { "type": "name", "properties": { "name": "urn:ogc:def:crs:OGC:1.3:CRS84" } },
"features": [
{ "type": "Feature", "properties": { "Name": "Fire Detection Centroid ", "Description": "<b>Latitude: <\/b> 44.62838<br\/>  <b>Longitude: <\/b> -123.81061<br\/>  <b>Detection Time: <\/b> 2023-12-08 22:22 UTC<br\/>  <b>Sensor: <\/b> NOAA-20 VIIRS<br\/> <b>Confidence: <\/b> Nominal<br\/>  <b>Day\/Night: <\/b> Day<br\/> <b>Scan: <\/b> 0.79 km<br\/> <b>Track: <\/b> 0.78 km<br\/> <b>FRP: <\/b> 10.12 MW<br\/> <b>Brightness: <\/b> 335.38 K" }, "geometry": { "type": "Point", "coordinates": [ -123.81061, 44.62838, 0.0 ] } },
{ "type": "Feature", "properties": { "Name": "Fire Detection Centroid ", "Description": "<b>Latitude: <\/b> 44.62712<br\/>  <b>Longitude: <\/b> -123.80479<br\/>  <b>Detection Time: <\/b> 2023-12-08 22:22 UTC<br\/>  <b>Sensor: <\/b> NOAA-20 VIIRS<br\/> <b>Confidence: <\/b> Nominal<br\/>  <b>Day\/Night: <\/b> Day<br\/> <b>Scan: <\/b> 0.79 km<br\/> <b>Track: <\/b> 0.78 km<br\/> <b>FRP: <\/b> 6.9 MW<br\/> <b>Brightness: <\/b> 337.1 K" }, "geometry": { "type": "Point", "coordinates": [ -123.80479, 44.62712, 0.0 ] } }
]
}
