{
"type": "FeatureCollection",
"crs": { "type": "name", "properties": { "name": "urn:ogc:def:crs:OGC:1.3:CRS84" } },
"features": [
{ "type": "Feature", "properties": { "Name": "Fire Detection Centroid ", "Description": "<b>Latitude: <\/b> 19.17027<br\/>  <b>Longitude: <\/b> -70.32757<br\/>  <b>Detection Time: <\/b> 2022-09-01 05:41 UTC<br\/>  <b>Sensor: <\/b> NOAA-20 VIIRS<br\/> <b>Confidence: <\/b> Nominal<br\/>  <b>Day\/Night: <\/b> Night<br\/> <b>Scan: <\/b> 0.3 km<br\/> <b>Track: <\/b> 0.6 km<br\/> <b>FRP: <\/b> 0.42 MW<br\/> <b>Brightness: <\/b> 298.76 K" }, "geometry": { "type": "Point", "coordinates": [ -70.32757, 19.17027, 0.0 ] } },
{ "type": "Feature", "properties": { "Name": "Fire Detection Centroid ", "Description": "<b>Latitude: <\/b> 19.16991<br\/>  <b>Longitude: <\/b> -70.32417<br\/>  <b>Detection Time: <\/b> 2022-09-01 05:41 UTC<br\/>  <b>Sensor: <\/b> NOAA-20 VIIRS<br\/> <b>Confidence: <\/b> Nominal<br\/>  <b>Day\/Night: <\/b> Night<br\/> <b>Scan: <\/b> 0.3 km<br\/> <b>Track: <\/b> 0.6 km<br\/> <b>FRP: <\/b> 0.42 MW<br\/> <b>Brightness: <\/b> 298.62 K" }, "geometry": { "type": "Point", "coordinates": [ -70.32417, 19.16991, 0.0 ] } },
{ "type": "Feature", "properties": { "Name": "Fire Detection Centroid ", "Description": "<b>Latitude: <\/b> 19.16991<br\/>  <b>Longitude: <\/b> -70.32417<br\/>  <b>Detection Time: <\/b> 2022-09-01 05:41 UTC<br\/>  <b>Sensor: <\/b> NOAA-20 VIIRS<br\/> <b>Confidence: <\/b> Nominal<br\/>  <b>Day\/Night: <\/b> Night<br\/> <b>Scan: <\/b> 0.3 km<br\/> <b>Track: <\/b> 0.6 km<br\/> <b>FRP: <\/b> 0.42 MW<br\/> <b>Brightness: <\/b> 298.62 K" }, "geometry": { "type": "Point", "coordinates": [ -70.32417, 19.16991, 0.0 ] } },
{ "type": "Feature", "properties": { "Name": "Fire Detection Centroid ", "Description": "<b>Latitude: <\/b> 19.17027<br\/>  <b>Longitude: <\/b> -70.32757<br\/>  <b>Detection Time: <\/b> 2022-09-01 05:41 UTC<br\/>  <b>Sensor: <\/b> NOAA-20 VIIRS<br\/> <b>Confidence: <\/b> Nominal<br\/>  <b>Day\/Night: <\/b> Night<br\/> <b>Scan: <\/b> 0.3 km<br\/> <b>Track: <\/b> 0.6 km<br\/> <b>FRP: <\/b> 0.42 MW<br\/> <b>Brightness: <\/b> 298.76 K" }, "geometry": { "type": "Point", "coordinates": [ -70.32757, 19.17027, 0.0 ] } },
{ "type": "Feature", "properties": { "Name": "Fire Detection Centroid ", "Description": "<b>Latitude: <\/b> 18.9288<br\/>  <b>Longitude: <\/b> -70.35939<br\/>  <b>Detection Time: <\/b> 2022-09-01 05:41 UTC<br\/>  <b>Sensor: <\/b> NOAA-20 VIIRS<br\/> <b>Confidence: <\/b> Nominal<br\/>  <b>Day\/Night: <\/b> Night<br\/> <b>Scan: <\/b> 0.3 km<br\/> <b>Track: <\/b> 0.6 km<br\/> <b>FRP: <\/b> 1.78 MW<br\/> <b>Brightness: <\/b> 301.71 K" }, "geometry": { "type": "Point", "coordinates": [ -70.35939, 18.9288, 0.0 ] } },
{ "type": "Feature", "properties": { "Name": "Fire Detection Centroid ", "Description": "<b>Latitude: <\/b> 18.92845<br\/>  <b>Longitude: <\/b> -70.35597<br\/>  <b>Detection Time: <\/b> 2022-09-01 05:41 UTC<br\/>  <b>Sensor: <\/b> NOAA-20 VIIRS<br\/> <b>Confidence: <\/b> Nominal<br\/>  <b>Day\/Night: <\/b> Night<br\/> <b>Scan: <\/b> 0.3 km<br\/> <b>Track: <\/b> 0.6 km<br\/> <b>FRP: <\/b> 4.36 MW<br\/> <b>Brightness: <\/b> 339.32 K" }, "geometry": { "type": "Point", "coordinates": [ -70.35597, 18.92845, 0.0 ] } },
{ "type": "Feature", "properties": { "Name": "Fire Detection Centroid ", "Description": "<b>Latitude: <\/b> 18.92808<br\/>  <b>Longitude: <\/b> -70.35241<br\/>  <b>Detection Time: <\/b> 2022-09-01 05:41 UTC<br\/>  <b>Sensor: <\/b> NOAA-20 VIIRS<br\/> <b>Confidence: <\/b> Nominal<br\/>  <b>Day\/Night: <\/b> Night<br\/> <b>Scan: <\/b> 0.3 km<br\/> <b>Track: <\/b> 0.6 km<br\/> <b>FRP: <\/b> 4.36 MW<br\/> <b>Brightness: <\/b> 332.12 K" }, "geometry": { "type": "Point", "coordinates": [ -70.35241, 18.92808, 0.0 ] } }
]
}
