{
"type": "FeatureCollection",
"crs": { "type": "name", "properties": { "name": "urn:ogc:def:crs:OGC:1.3:CRS84" } },
"features": [
{ "type": "Feature", "properties": { "Name": "Fire Detection Centroid ", "Description": "<b>Latitude: <\/b> 35.85593<br\/>  <b>Longitude: <\/b> -80.74776<br\/>  <b>Detection Time: <\/b> 2023-12-18 17:29 UTC<br\/>  <b>Sensor: <\/b> NOAA-20 VIIRS<br\/> <b>Confidence: <\/b> Nominal<br\/>  <b>Day\/Night: <\/b> Day<br\/> <b>Scan: <\/b> 0.5 km<br\/> <b>Track: <\/b> 0.6 km<br\/> <b>FRP: <\/b> 4.61 MW<br\/> <b>Brightness: <\/b> 338.21 K" }, "geometry": { "type": "Point", "coordinates": [ -80.74776, 35.85593, 0.0 ] } },
{ "type": "Feature", "properties": { "Name": "Fire Detection Centroid ", "Description": "<b>Latitude: <\/b> 35.85384<br\/>  <b>Longitude: <\/b> -80.7496<br\/>  <b>Detection Time: <\/b> 2023-12-18 17:29 UTC<br\/>  <b>Sensor: <\/b> NOAA-20 VIIRS<br\/> <b>Confidence: <\/b> Nominal<br\/>  <b>Day\/Night: <\/b> Day<br\/> <b>Scan: <\/b> 0.5 km<br\/> <b>Track: <\/b> 0.6 km<br\/> <b>FRP: <\/b> 5.01 MW<br\/> <b>Brightness: <\/b> 339.4 K" }, "geometry": { "type": "Point", "coordinates": [ -80.7496, 35.85384, 0.0 ] } },
{ "type": "Feature", "properties": { "Name": "Fire Detection Centroid ", "Description": "<b>Latitude: <\/b> 34.30989<br\/>  <b>Longitude: <\/b> -78.11143<br\/>  <b>Detection Time: <\/b> 2023-12-18 17:28 UTC<br\/>  <b>Sensor: <\/b> NOAA-20 VIIRS<br\/> <b>Confidence: <\/b> Nominal<br\/>  <b>Day\/Night: <\/b> Day<br\/> <b>Scan: <\/b> 0.4 km<br\/> <b>Track: <\/b> 0.6 km<br\/> <b>FRP: <\/b> 4.11 MW<br\/> <b>Brightness: <\/b> 326.1 K" }, "geometry": { "type": "Point", "coordinates": [ -78.11143, 34.30989, 0.0 ] } },
{ "type": "Feature", "properties": { "Name": "Fire Detection Centroid ", "Description": "<b>Latitude: <\/b> 27.39827<br\/>  <b>Longitude: <\/b> -80.50893<br\/>  <b>Detection Time: <\/b> 2023-12-18 17:27 UTC<br\/>  <b>Sensor: <\/b> NOAA-20 VIIRS<br\/> <b>Confidence: <\/b> Nominal<br\/>  <b>Day\/Night: <\/b> Day<br\/> <b>Scan: <\/b> 0.8 km<br\/> <b>Track: <\/b> 0.8 km<br\/> <b>FRP: <\/b> 5.82 MW<br\/> <b>Brightness: <\/b> 335.03 K" }, "geometry": { "type": "Point", "coordinates": [ -80.50893, 27.39827, 0.0 ] } }
]
}
