{
"type": "FeatureCollection",
"crs": { "type": "name", "properties": { "name": "urn:ogc:def:crs:OGC:1.3:CRS84" } },
"features": [
{ "type": "Feature", "properties": { "Name": "Fire Detection Centroid ", "Description": "<b>Latitude: <\/b> 19.36624<br\/>  <b>Longitude: <\/b> -155.30775<br\/>  <b>Detection Time: <\/b> 2024-06-05 00:16 UTC<br\/>  <b>Sensor: <\/b> NOAA-20 VIIRS<br\/> <b>Confidence: <\/b> Nominal<br\/>  <b>Day\/Night: <\/b> Day<br\/> <b>Scan: <\/b> 0.44 km<br\/> <b>Track: <\/b> 0.62 km<br\/> <b>FRP: <\/b> 9.28 MW<br\/> <b>Brightness: <\/b> 349.02 K" }, "geometry": { "type": "Point", "coordinates": [ -155.30775, 19.36624, 0.0 ] } },
{ "type": "Feature", "properties": { "Name": "Fire Detection Centroid ", "Description": "<b>Latitude: <\/b> 19.36747<br\/>  <b>Longitude: <\/b> -155.31004<br\/>  <b>Detection Time: <\/b> 2024-06-04 22:35 UTC<br\/>  <b>Sensor: <\/b> NOAA-20 VIIRS<br\/> <b>Confidence: <\/b> Nominal<br\/>  <b>Day\/Night: <\/b> Day<br\/> <b>Scan: <\/b> 0.8 km<br\/> <b>Track: <\/b> 0.8 km<br\/> <b>FRP: <\/b> 17.16 MW<br\/> <b>Brightness: <\/b> 344.9 K" }, "geometry": { "type": "Point", "coordinates": [ -155.31004, 19.36747, 0.0 ] } },
{ "type": "Feature", "properties": { "Name": "Fire Detection Centroid ", "Description": "<b>Latitude: <\/b> 19.36746<br\/>  <b>Longitude: <\/b> -155.31007<br\/>  <b>Detection Time: <\/b> 2024-06-04 22:35 UTC<br\/>  <b>Sensor: <\/b> NOAA-20 VIIRS<br\/> <b>Confidence: <\/b> Nominal<br\/>  <b>Day\/Night: <\/b> Day<br\/> <b>Scan: <\/b> 0.79 km<br\/> <b>Track: <\/b> 0.78 km<br\/> <b>FRP: <\/b> 17.64 MW<br\/> <b>Brightness: <\/b> 344.9 K" }, "geometry": { "type": "Point", "coordinates": [ -155.31007, 19.36746, 0.0 ] } }
]
}
