{
"type": "FeatureCollection",
"crs": { "type": "name", "properties": { "name": "urn:ogc:def:crs:OGC:1.3:CRS84" } },
"features": [
{ "type": "Feature", "properties": { "Name": "Fire Detection Centroid ", "Description": "<b>Latitude: <\/b> 19.40115<br\/>  <b>Longitude: <\/b> -155.27731<br\/>  <b>Detection Time: <\/b> 2023-01-09 23:01 UTC<br\/>  <b>Sensor: <\/b> NOAA-20 VIIRS<br\/> <b>Confidence: <\/b> Nominal<br\/>  <b>Day\/Night: <\/b> Day<br\/> <b>Scan: <\/b> 0.62 km<br\/> <b>Track: <\/b> 0.54 km<br\/> <b>FRP: <\/b> 19.31 MW<br\/> <b>Brightness: <\/b> 352.98 K" }, "geometry": { "type": "Point", "coordinates": [ -155.27731, 19.40115, 0.0 ] } },
{ "type": "Feature", "properties": { "Name": "Fire Detection Centroid ", "Description": "<b>Latitude: <\/b> 19.40483<br\/>  <b>Longitude: <\/b> -155.28427<br\/>  <b>Detection Time: <\/b> 2023-01-09 23:01 UTC<br\/>  <b>Sensor: <\/b> NOAA-20 VIIRS<br\/> <b>Confidence: <\/b> High<br\/>  <b>Day\/Night: <\/b> Day<br\/> <b>Scan: <\/b> 0.62 km<br\/> <b>Track: <\/b> 0.54 km<br\/> <b>FRP: <\/b> 374.42 MW<br\/> <b>Brightness: <\/b> 367 K" }, "geometry": { "type": "Point", "coordinates": [ -155.28427, 19.40483, 0.0 ] } },
{ "type": "Feature", "properties": { "Name": "Fire Detection Centroid ", "Description": "<b>Latitude: <\/b> 19.40717<br\/>  <b>Longitude: <\/b> -155.27271<br\/>  <b>Detection Time: <\/b> 2023-01-09 23:01 UTC<br\/>  <b>Sensor: <\/b> NOAA-20 VIIRS<br\/> <b>Confidence: <\/b> Low<br\/>  <b>Day\/Night: <\/b> Day<br\/> <b>Scan: <\/b> 0.62 km<br\/> <b>Track: <\/b> 0.54 km<br\/> <b>FRP: <\/b> 651.1 MW<br\/> <b>Brightness: <\/b> 352.02 K" }, "geometry": { "type": "Point", "coordinates": [ -155.27271, 19.40717, 0.0 ] } },
{ "type": "Feature", "properties": { "Name": "Fire Detection Centroid ", "Description": "<b>Latitude: <\/b> 19.406<br\/>  <b>Longitude: <\/b> -155.2785<br\/>  <b>Detection Time: <\/b> 2023-01-09 23:01 UTC<br\/>  <b>Sensor: <\/b> NOAA-20 VIIRS<br\/> <b>Confidence: <\/b> Low<br\/>  <b>Day\/Night: <\/b> Day<br\/> <b>Scan: <\/b> 0.62 km<br\/> <b>Track: <\/b> 0.54 km<br\/> <b>FRP: <\/b> 374.42 MW<br\/> <b>Brightness: <\/b> 367 K" }, "geometry": { "type": "Point", "coordinates": [ -155.2785, 19.406, 0.0 ] } },
{ "type": "Feature", "properties": { "Name": "Fire Detection Centroid ", "Description": "<b>Latitude: <\/b> 19.41087<br\/>  <b>Longitude: <\/b> -155.27951<br\/>  <b>Detection Time: <\/b> 2023-01-09 23:01 UTC<br\/>  <b>Sensor: <\/b> NOAA-20 VIIRS<br\/> <b>Confidence: <\/b> High<br\/>  <b>Day\/Night: <\/b> Day<br\/> <b>Scan: <\/b> 0.62 km<br\/> <b>Track: <\/b> 0.54 km<br\/> <b>FRP: <\/b> 374.42 MW<br\/> <b>Brightness: <\/b> 367 K" }, "geometry": { "type": "Point", "coordinates": [ -155.27951, 19.41087, 0.0 ] } },
{ "type": "Feature", "properties": { "Name": "Fire Detection Centroid ", "Description": "<b>Latitude: <\/b> 19.40973<br\/>  <b>Longitude: <\/b> -155.28516<br\/>  <b>Detection Time: <\/b> 2023-01-09 23:01 UTC<br\/>  <b>Sensor: <\/b> NOAA-20 VIIRS<br\/> <b>Confidence: <\/b> Low<br\/>  <b>Day\/Night: <\/b> Day<br\/> <b>Scan: <\/b> 0.62 km<br\/> <b>Track: <\/b> 0.54 km<br\/> <b>FRP: <\/b> 374.42 MW<br\/> <b>Brightness: <\/b> 367 K" }, "geometry": { "type": "Point", "coordinates": [ -155.28516, 19.40973, 0.0 ] } },
{ "type": "Feature", "properties": { "Name": "Fire Detection Centroid ", "Description": "<b>Latitude: <\/b> 19.39145<br\/>  <b>Longitude: <\/b> -155.27505<br\/>  <b>Detection Time: <\/b> 2023-01-09 23:01 UTC<br\/>  <b>Sensor: <\/b> NOAA-20 VIIRS<br\/> <b>Confidence: <\/b> Low<br\/>  <b>Day\/Night: <\/b> Day<br\/> <b>Scan: <\/b> 0.62 km<br\/> <b>Track: <\/b> 0.54 km<br\/> <b>FRP: <\/b> 10.25 MW<br\/> <b>Brightness: <\/b> 340.07 K" }, "geometry": { "type": "Point", "coordinates": [ -155.27505, 19.39145, 0.0 ] } }
]
}
