{
"type": "FeatureCollection",
"crs": { "type": "name", "properties": { "name": "urn:ogc:def:crs:OGC:1.3:CRS84" } },
"features": [
{ "type": "Feature", "properties": { "Name": "Fire Detection Centroid ", "Description": "<b>Latitude: <\/b> 32.28847<br\/>  <b>Longitude: <\/b> -114.80762<br\/>  <b>Detection Time: <\/b> 2024-01-27 21:40 UTC<br\/>  <b>Sensor: <\/b> NOAA-20 VIIRS<br\/> <b>Confidence: <\/b> Nominal<br\/>  <b>Day\/Night: <\/b> Day<br\/> <b>Scan: <\/b> 0.64 km<br\/> <b>Track: <\/b> 0.72 km<br\/> <b>FRP: <\/b> 8.75 MW<br\/> <b>Brightness: <\/b> 356.06 K" }, "geometry": { "type": "Point", "coordinates": [ -114.80762, 32.28847, 0.0 ] } },
{ "type": "Feature", "properties": { "Name": "Fire Detection Centroid ", "Description": "<b>Latitude: <\/b> 31.48724<br\/>  <b>Longitude: <\/b> -113.41164<br\/>  <b>Detection Time: <\/b> 2024-01-27 21:40 UTC<br\/>  <b>Sensor: <\/b> NOAA-20 VIIRS<br\/> <b>Confidence: <\/b> Nominal<br\/>  <b>Day\/Night: <\/b> Day<br\/> <b>Scan: <\/b> 0.8 km<br\/> <b>Track: <\/b> 0.8 km<br\/> <b>FRP: <\/b> 9.3 MW<br\/> <b>Brightness: <\/b> 351.12 K" }, "geometry": { "type": "Point", "coordinates": [ -113.41164, 31.48724, 0.0 ] } },
{ "type": "Feature", "properties": { "Name": "Fire Detection Centroid ", "Description": "<b>Latitude: <\/b> 31.49419<br\/>  <b>Longitude: <\/b> -113.40968<br\/>  <b>Detection Time: <\/b> 2024-01-27 21:40 UTC<br\/>  <b>Sensor: <\/b> NOAA-20 VIIRS<br\/> <b>Confidence: <\/b> Nominal<br\/>  <b>Day\/Night: <\/b> Day<br\/> <b>Scan: <\/b> 0.77 km<br\/> <b>Track: <\/b> 0.77 km<br\/> <b>FRP: <\/b> 9.31 MW<br\/> <b>Brightness: <\/b> 351.12 K" }, "geometry": { "type": "Point", "coordinates": [ -113.40968, 31.49419, 0.0 ] } },
{ "type": "Feature", "properties": { "Name": "Fire Detection Centroid ", "Description": "<b>Latitude: <\/b> 31.48724<br\/>  <b>Longitude: <\/b> -113.41164<br\/>  <b>Detection Time: <\/b> 2024-01-27 21:40 UTC<br\/>  <b>Sensor: <\/b> NOAA-20 VIIRS<br\/> <b>Confidence: <\/b> Nominal<br\/>  <b>Day\/Night: <\/b> Day<br\/> <b>Scan: <\/b> 0.8 km<br\/> <b>Track: <\/b> 0.8 km<br\/> <b>FRP: <\/b> 9.3 MW<br\/> <b>Brightness: <\/b> 351.12 K" }, "geometry": { "type": "Point", "coordinates": [ -113.41164, 31.48724, 0.0 ] } },
{ "type": "Feature", "properties": { "Name": "Fire Detection Centroid ", "Description": "<b>Latitude: <\/b> 32.25503<br\/>  <b>Longitude: <\/b> -114.80801<br\/>  <b>Detection Time: <\/b> 2024-01-27 21:40 UTC<br\/>  <b>Sensor: <\/b> NOAA-20 VIIRS<br\/> <b>Confidence: <\/b> Nominal<br\/>  <b>Day\/Night: <\/b> Day<br\/> <b>Scan: <\/b> 0.6 km<br\/> <b>Track: <\/b> 0.7 km<br\/> <b>FRP: <\/b> 8.75 MW<br\/> <b>Brightness: <\/b> 356.06 K" }, "geometry": { "type": "Point", "coordinates": [ -114.80801, 32.25503, 0.0 ] } },
{ "type": "Feature", "properties": { "Name": "Fire Detection Centroid ", "Description": "<b>Latitude: <\/b> 31.48724<br\/>  <b>Longitude: <\/b> -113.41164<br\/>  <b>Detection Time: <\/b> 2024-01-27 21:40 UTC<br\/>  <b>Sensor: <\/b> NOAA-20 VIIRS<br\/> <b>Confidence: <\/b> Nominal<br\/>  <b>Day\/Night: <\/b> Day<br\/> <b>Scan: <\/b> 0.8 km<br\/> <b>Track: <\/b> 0.8 km<br\/> <b>FRP: <\/b> 9.3 MW<br\/> <b>Brightness: <\/b> 351.12 K" }, "geometry": { "type": "Point", "coordinates": [ -113.41164, 31.48724, 0.0 ] } }
]
}
