{
"type": "FeatureCollection",
"crs": { "type": "name", "properties": { "name": "urn:ogc:def:crs:OGC:1.3:CRS84" } },
"features": [
{ "type": "Feature", "properties": { "Name": "Fire Detection Centroid ", "Description": "<b>Latitude: <\/b> 40.6372<br\/>  <b>Longitude: <\/b> -74.22809<br\/>  <b>Detection Time: <\/b> 2022-09-22 05:41 UTC<br\/>  <b>Sensor: <\/b> NOAA-20 VIIRS<br\/> <b>Confidence: <\/b> Nominal<br\/>  <b>Day\/Night: <\/b> Night<br\/> <b>Scan: <\/b> 0.7 km<br\/> <b>Track: <\/b> 0.8 km<br\/> <b>FRP: <\/b> 2.14 MW<br\/> <b>Brightness: <\/b> 298.13 K" }, "geometry": { "type": "Point", "coordinates": [ -74.22809, 40.6372, 0.0 ] } }
]
}
