{
"type": "FeatureCollection",
"crs": { "type": "name", "properties": { "name": "urn:ogc:def:crs:OGC:1.3:CRS84" } },
"features": [
{ "type": "Feature", "properties": { "Name": "Fire Detection Centroid ", "Description": "<b>Latitude: <\/b> 19.4052<br\/>  <b>Longitude: <\/b> -155.285<br\/>  <b>Detection Time: <\/b> 2023-03-03 11:55 UTC<br\/>  <b>Sensor: <\/b> NOAA-20 VIIRS<br\/> <b>Confidence: <\/b> Nominal<br\/>  <b>Day\/Night: <\/b> Night<br\/> <b>Scan: <\/b> 0.39 km<br\/> <b>Track: <\/b> 0.36 km<br\/> <b>FRP: <\/b> 4.8 MW<br\/> <b>Brightness: <\/b> 343.55 K" }, "geometry": { "type": "Point", "coordinates": [ -155.285, 19.4052, 0.0 ] } },
{ "type": "Feature", "properties": { "Name": "Fire Detection Centroid ", "Description": "<b>Latitude: <\/b> 19.40795<br\/>  <b>Longitude: <\/b> -155.28078<br\/>  <b>Detection Time: <\/b> 2023-03-03 11:55 UTC<br\/>  <b>Sensor: <\/b> NOAA-20 VIIRS<br\/> <b>Confidence: <\/b> Nominal<br\/>  <b>Day\/Night: <\/b> Night<br\/> <b>Scan: <\/b> 0.39 km<br\/> <b>Track: <\/b> 0.36 km<br\/> <b>FRP: <\/b> 0.91 MW<br\/> <b>Brightness: <\/b> 301.77 K" }, "geometry": { "type": "Point", "coordinates": [ -155.28078, 19.40795, 0.0 ] } },
{ "type": "Feature", "properties": { "Name": "Fire Detection Centroid ", "Description": "<b>Latitude: <\/b> 19.4085<br\/>  <b>Longitude: <\/b> -155.28442<br\/>  <b>Detection Time: <\/b> 2023-03-03 11:55 UTC<br\/>  <b>Sensor: <\/b> NOAA-20 VIIRS<br\/> <b>Confidence: <\/b> Nominal<br\/>  <b>Day\/Night: <\/b> Night<br\/> <b>Scan: <\/b> 0.39 km<br\/> <b>Track: <\/b> 0.36 km<br\/> <b>FRP: <\/b> 0.91 MW<br\/> <b>Brightness: <\/b> 296.04 K" }, "geometry": { "type": "Point", "coordinates": [ -155.28442, 19.4085, 0.0 ] } },
{ "type": "Feature", "properties": { "Name": "Fire Detection Centroid ", "Description": "<b>Latitude: <\/b> 19.40464<br\/>  <b>Longitude: <\/b> -155.28133<br\/>  <b>Detection Time: <\/b> 2023-03-03 11:55 UTC<br\/>  <b>Sensor: <\/b> NOAA-20 VIIRS<br\/> <b>Confidence: <\/b> Nominal<br\/>  <b>Day\/Night: <\/b> Night<br\/> <b>Scan: <\/b> 0.39 km<br\/> <b>Track: <\/b> 0.36 km<br\/> <b>FRP: <\/b> 4.8 MW<br\/> <b>Brightness: <\/b> 299.32 K" }, "geometry": { "type": "Point", "coordinates": [ -155.28133, 19.40464, 0.0 ] } },
{ "type": "Feature", "properties": { "Name": "Fire Detection Centroid ", "Description": "<b>Latitude: <\/b> 19.40576<br\/>  <b>Longitude: <\/b> -155.28864<br\/>  <b>Detection Time: <\/b> 2023-03-03 11:55 UTC<br\/>  <b>Sensor: <\/b> NOAA-20 VIIRS<br\/> <b>Confidence: <\/b> Nominal<br\/>  <b>Day\/Night: <\/b> Night<br\/> <b>Scan: <\/b> 0.39 km<br\/> <b>Track: <\/b> 0.36 km<br\/> <b>FRP: <\/b> 1.42 MW<br\/> <b>Brightness: <\/b> 298.99 K" }, "geometry": { "type": "Point", "coordinates": [ -155.28864, 19.40576, 0.0 ] } }
]
}
