{
"type": "FeatureCollection",
"crs": { "type": "name", "properties": { "name": "urn:ogc:def:crs:OGC:1.3:CRS84" } },
"features": [
{ "type": "Feature", "properties": { "Name": "Fire Detection Centroid ", "Description": "<b>Latitude: <\/b> 18.92533<br\/>  <b>Longitude: <\/b> -70.35175<br\/>  <b>Detection Time: <\/b> 2023-05-15 05:42 UTC<br\/>  <b>Sensor: <\/b> NOAA-20 VIIRS<br\/> <b>Confidence: <\/b> Nominal<br\/>  <b>Day\/Night: <\/b> Night<br\/> <b>Scan: <\/b> 0.3 km<br\/> <b>Track: <\/b> 0.6 km<br\/> <b>FRP: <\/b> 6.14 MW<br\/> <b>Brightness: <\/b> 337.77 K" }, "geometry": { "type": "Point", "coordinates": [ -70.35175, 18.92533, 0.0 ] } },
{ "type": "Feature", "properties": { "Name": "Fire Detection Centroid ", "Description": "<b>Latitude: <\/b> 18.9257<br\/>  <b>Longitude: <\/b> -70.35523<br\/>  <b>Detection Time: <\/b> 2023-05-15 05:42 UTC<br\/>  <b>Sensor: <\/b> NOAA-20 VIIRS<br\/> <b>Confidence: <\/b> Nominal<br\/>  <b>Day\/Night: <\/b> Night<br\/> <b>Scan: <\/b> 0.3 km<br\/> <b>Track: <\/b> 0.6 km<br\/> <b>FRP: <\/b> 6.34 MW<br\/> <b>Brightness: <\/b> 338.69 K" }, "geometry": { "type": "Point", "coordinates": [ -70.35523, 18.9257, 0.0 ] } },
{ "type": "Feature", "properties": { "Name": "Fire Detection Centroid ", "Description": "<b>Latitude: <\/b> 45.2809<br\/>  <b>Longitude: <\/b> -66.01518<br\/>  <b>Detection Time: <\/b> 2023-05-15 05:35 UTC<br\/>  <b>Sensor: <\/b> NOAA-20 VIIRS<br\/> <b>Confidence: <\/b> Nominal<br\/>  <b>Day\/Night: <\/b> Night<br\/> <b>Scan: <\/b> 0.4 km<br\/> <b>Track: <\/b> 0.6 km<br\/> <b>FRP: <\/b> 1.99 MW<br\/> <b>Brightness: <\/b> 300.69 K" }, "geometry": { "type": "Point", "coordinates": [ -66.01518, 45.2809, 0.0 ] } }
]
}
