{
"type": "FeatureCollection",
"crs": { "type": "name", "properties": { "name": "urn:ogc:def:crs:OGC:1.3:CRS84" } },
"features": [
{ "type": "Feature", "properties": { "Name": "Fire Detection Centroid ", "Description": "<b>Latitude: <\/b> 41.69114<br\/>  <b>Longitude: <\/b> -70.56068<br\/>  <b>Detection Time: <\/b> 2023-04-20 16:28 UTC<br\/>  <b>Sensor: <\/b> NOAA-20 VIIRS<br\/> <b>Confidence: <\/b> Nominal<br\/>  <b>Day\/Night: <\/b> Day<br\/> <b>Scan: <\/b> 0.6 km<br\/> <b>Track: <\/b> 0.7 km<br\/> <b>FRP: <\/b> 8.3 MW<br\/> <b>Brightness: <\/b> 352.26 K" }, "geometry": { "type": "Point", "coordinates": [ -70.56068, 41.69114, 0.0 ] } },
{ "type": "Feature", "properties": { "Name": "Fire Detection Centroid ", "Description": "<b>Latitude: <\/b> 41.69024<br\/>  <b>Longitude: <\/b> -70.56274<br\/>  <b>Detection Time: <\/b> 2023-04-20 16:28 UTC<br\/>  <b>Sensor: <\/b> NOAA-20 VIIRS<br\/> <b>Confidence: <\/b> Nominal<br\/>  <b>Day\/Night: <\/b> Day<br\/> <b>Scan: <\/b> 0.6 km<br\/> <b>Track: <\/b> 0.7 km<br\/> <b>FRP: <\/b> 10.43 MW<br\/> <b>Brightness: <\/b> 342.44 K" }, "geometry": { "type": "Point", "coordinates": [ -70.56274, 41.69024, 0.0 ] } },
{ "type": "Feature", "properties": { "Name": "Fire Detection Centroid ", "Description": "<b>Latitude: <\/b> 41.63705<br\/>  <b>Longitude: <\/b> -70.57153<br\/>  <b>Detection Time: <\/b> 2023-04-20 16:28 UTC<br\/>  <b>Sensor: <\/b> NOAA-20 VIIRS<br\/> <b>Confidence: <\/b> Nominal<br\/>  <b>Day\/Night: <\/b> Day<br\/> <b>Scan: <\/b> 0.6 km<br\/> <b>Track: <\/b> 0.7 km<br\/> <b>FRP: <\/b> 8.82 MW<br\/> <b>Brightness: <\/b> 337.22 K" }, "geometry": { "type": "Point", "coordinates": [ -70.57153, 41.63705, 0.0 ] } },
{ "type": "Feature", "properties": { "Name": "Fire Detection Centroid ", "Description": "<b>Latitude: <\/b> 19.57662<br\/>  <b>Longitude: <\/b> -155.51016<br\/>  <b>Detection Time: <\/b> 2023-04-20 11:55 UTC<br\/>  <b>Sensor: <\/b> NOAA-20 VIIRS<br\/> <b>Confidence: <\/b> Nominal<br\/>  <b>Day\/Night: <\/b> Night<br\/> <b>Scan: <\/b> 0.39 km<br\/> <b>Track: <\/b> 0.36 km<br\/> <b>FRP: <\/b> 2.11 MW<br\/> <b>Brightness: <\/b> 296.32 K" }, "geometry": { "type": "Point", "coordinates": [ -155.51016, 19.57662, 0.0 ] } },
{ "type": "Feature", "properties": { "Name": "Fire Detection Centroid ", "Description": "<b>Latitude: <\/b> 19.40682<br\/>  <b>Longitude: <\/b> -155.2878<br\/>  <b>Detection Time: <\/b> 2023-04-20 11:55 UTC<br\/>  <b>Sensor: <\/b> NOAA-20 VIIRS<br\/> <b>Confidence: <\/b> Nominal<br\/>  <b>Day\/Night: <\/b> Night<br\/> <b>Scan: <\/b> 0.39 km<br\/> <b>Track: <\/b> 0.36 km<br\/> <b>FRP: <\/b> 1.3 MW<br\/> <b>Brightness: <\/b> 300.64 K" }, "geometry": { "type": "Point", "coordinates": [ -155.2878, 19.40682, 0.0 ] } },
{ "type": "Feature", "properties": { "Name": "Fire Detection Centroid ", "Description": "<b>Latitude: <\/b> 19.59928<br\/>  <b>Longitude: <\/b> -155.50288<br\/>  <b>Detection Time: <\/b> 2023-04-20 11:55 UTC<br\/>  <b>Sensor: <\/b> NOAA-20 VIIRS<br\/> <b>Confidence: <\/b> Nominal<br\/>  <b>Day\/Night: <\/b> Night<br\/> <b>Scan: <\/b> 0.39 km<br\/> <b>Track: <\/b> 0.36 km<br\/> <b>FRP: <\/b> 1.02 MW<br\/> <b>Brightness: <\/b> 296.14 K" }, "geometry": { "type": "Point", "coordinates": [ -155.50288, 19.59928, 0.0 ] } },
{ "type": "Feature", "properties": { "Name": "Fire Detection Centroid ", "Description": "<b>Latitude: <\/b> 19.60275<br\/>  <b>Longitude: <\/b> -155.50249<br\/>  <b>Detection Time: <\/b> 2023-04-20 11:55 UTC<br\/>  <b>Sensor: <\/b> NOAA-20 VIIRS<br\/> <b>Confidence: <\/b> Nominal<br\/>  <b>Day\/Night: <\/b> Night<br\/> <b>Scan: <\/b> 0.39 km<br\/> <b>Track: <\/b> 0.36 km<br\/> <b>FRP: <\/b> 1.57 MW<br\/> <b>Brightness: <\/b> 295.09 K" }, "geometry": { "type": "Point", "coordinates": [ -155.50249, 19.60275, 0.0 ] } },
{ "type": "Feature", "properties": { "Name": "Fire Detection Centroid ", "Description": "<b>Latitude: <\/b> 19.59596<br\/>  <b>Longitude: <\/b> -155.50339<br\/>  <b>Detection Time: <\/b> 2023-04-20 11:55 UTC<br\/>  <b>Sensor: <\/b> NOAA-20 VIIRS<br\/> <b>Confidence: <\/b> Nominal<br\/>  <b>Day\/Night: <\/b> Night<br\/> <b>Scan: <\/b> 0.39 km<br\/> <b>Track: <\/b> 0.36 km<br\/> <b>FRP: <\/b> 1.02 MW<br\/> <b>Brightness: <\/b> 300.72 K" }, "geometry": { "type": "Point", "coordinates": [ -155.50339, 19.59596, 0.0 ] } },
{ "type": "Feature", "properties": { "Name": "Fire Detection Centroid ", "Description": "<b>Latitude: <\/b> 19.58601<br\/>  <b>Longitude: <\/b> -155.50496<br\/>  <b>Detection Time: <\/b> 2023-04-20 11:55 UTC<br\/>  <b>Sensor: <\/b> NOAA-20 VIIRS<br\/> <b>Confidence: <\/b> Nominal<br\/>  <b>Day\/Night: <\/b> Night<br\/> <b>Scan: <\/b> 0.39 km<br\/> <b>Track: <\/b> 0.36 km<br\/> <b>FRP: <\/b> 1.79 MW<br\/> <b>Brightness: <\/b> 296.56 K" }, "geometry": { "type": "Point", "coordinates": [ -155.50496, 19.58601, 0.0 ] } }
]
}
