{
"type": "FeatureCollection",
"crs": { "type": "name", "properties": { "name": "urn:ogc:def:crs:OGC:1.3:CRS84" } },
"features": [
{ "type": "Feature", "properties": { "Name": "Fire Detection Centroid ", "Description": "<b>Latitude: <\/b> 48.15475<br\/>  <b>Longitude: <\/b> -117.3805<br\/>  <b>Detection Time: <\/b> 2024-01-13 11:19 UTC<br\/>  <b>Sensor: <\/b> NOAA-20 VIIRS<br\/> <b>Confidence: <\/b> Nominal<br\/>  <b>Day\/Night: <\/b> Night<br\/> <b>Scan: <\/b> 0.77 km<br\/> <b>Track: <\/b> 0.77 km<br\/> <b>FRP: <\/b> 4.02 MW<br\/> <b>Brightness: <\/b> 320.22 K" }, "geometry": { "type": "Point", "coordinates": [ -117.3805, 48.15475, 0.0 ] } },
{ "type": "Feature", "properties": { "Name": "Fire Detection Centroid ", "Description": "<b>Latitude: <\/b> 47.56902<br\/>  <b>Longitude: <\/b> -122.37445<br\/>  <b>Detection Time: <\/b> 2024-01-13 11:19 UTC<br\/>  <b>Sensor: <\/b> NOAA-20 VIIRS<br\/> <b>Confidence: <\/b> Nominal<br\/>  <b>Day\/Night: <\/b> Night<br\/> <b>Scan: <\/b> 0.51 km<br\/> <b>Track: <\/b> 0.66 km<br\/> <b>FRP: <\/b> 0.69 MW<br\/> <b>Brightness: <\/b> 296.09 K" }, "geometry": { "type": "Point", "coordinates": [ -122.37445, 47.56902, 0.0 ] } }
]
}
