{
"type": "FeatureCollection",
"crs": { "type": "name", "properties": { "name": "urn:ogc:def:crs:OGC:1.3:CRS84" } },
"features": [
{ "type": "Feature", "properties": { "Name": "Fire Detection Centroid ", "Description": "<b>Latitude: <\/b> 49.09889<br\/>  <b>Longitude: <\/b> -123.01537<br\/>  <b>Detection Time: <\/b> 2023-02-24 10:36 UTC<br\/>  <b>Sensor: <\/b> NOAA-20 VIIRS<br\/> <b>Confidence: <\/b> Nominal<br\/>  <b>Day\/Night: <\/b> Night<br\/> <b>Scan: <\/b> 0.46 km<br\/> <b>Track: <\/b> 0.39 km<br\/> <b>FRP: <\/b> 1.15 MW<br\/> <b>Brightness: <\/b> 304.56 K" }, "geometry": { "type": "Point", "coordinates": [ -123.01537, 49.09889, 0.0 ] } },
{ "type": "Feature", "properties": { "Name": "Fire Detection Centroid ", "Description": "<b>Latitude: <\/b> 49.56324<br\/>  <b>Longitude: <\/b> -124.8814<br\/>  <b>Detection Time: <\/b> 2023-02-24 10:36 UTC<br\/>  <b>Sensor: <\/b> NOAA-20 VIIRS<br\/> <b>Confidence: <\/b> Nominal<br\/>  <b>Day\/Night: <\/b> Night<br\/> <b>Scan: <\/b> 0.41 km<br\/> <b>Track: <\/b> 0.37 km<br\/> <b>FRP: <\/b> 1.37 MW<br\/> <b>Brightness: <\/b> 318.28 K" }, "geometry": { "type": "Point", "coordinates": [ -124.8814, 49.56324, 0.0 ] } },
{ "type": "Feature", "properties": { "Name": "Fire Detection Centroid ", "Description": "<b>Latitude: <\/b> 49.43507<br\/>  <b>Longitude: <\/b> -119.1236<br\/>  <b>Detection Time: <\/b> 2023-02-24 10:36 UTC<br\/>  <b>Sensor: <\/b> NOAA-20 VIIRS<br\/> <b>Confidence: <\/b> Nominal<br\/>  <b>Day\/Night: <\/b> Night<br\/> <b>Scan: <\/b> 0.42 km<br\/> <b>Track: <\/b> 0.45 km<br\/> <b>FRP: <\/b> 3.99 MW<br\/> <b>Brightness: <\/b> 329.68 K" }, "geometry": { "type": "Point", "coordinates": [ -119.1236, 49.43507, 0.0 ] } },
{ "type": "Feature", "properties": { "Name": "Fire Detection Centroid ", "Description": "<b>Latitude: <\/b> 49.56946<br\/>  <b>Longitude: <\/b> -123.94263<br\/>  <b>Detection Time: <\/b> 2023-02-24 10:36 UTC<br\/>  <b>Sensor: <\/b> NOAA-20 VIIRS<br\/> <b>Confidence: <\/b> Nominal<br\/>  <b>Day\/Night: <\/b> Night<br\/> <b>Scan: <\/b> 0.43 km<br\/> <b>Track: <\/b> 0.38 km<br\/> <b>FRP: <\/b> 0.84 MW<br\/> <b>Brightness: <\/b> 295.04 K" }, "geometry": { "type": "Point", "coordinates": [ -123.94263, 49.56946, 0.0 ] } }
]
}
