{
"type": "FeatureCollection",
"crs": { "type": "name", "properties": { "name": "urn:ogc:def:crs:OGC:1.3:CRS84" } },
"features": [
{ "type": "Feature", "properties": { "Name": "Fire Detection Centroid ", "Description": "<b>Latitude: <\/b> 19.40583<br\/>  <b>Longitude: <\/b> -155.28365<br\/>  <b>Detection Time: <\/b> 2024-01-21 12:21 UTC<br\/>  <b>Sensor: <\/b> NOAA-20 VIIRS<br\/> <b>Confidence: <\/b> Nominal<br\/>  <b>Day\/Night: <\/b> Night<br\/> <b>Scan: <\/b> 0.41 km<br\/> <b>Track: <\/b> 0.45 km<br\/> <b>FRP: <\/b> 2.8 MW<br\/> <b>Brightness: <\/b> 303.15 K" }, "geometry": { "type": "Point", "coordinates": [ -155.28365, 19.40583, 0.0 ] } },
{ "type": "Feature", "properties": { "Name": "Fire Detection Centroid ", "Description": "<b>Latitude: <\/b> 19.41056<br\/>  <b>Longitude: <\/b> -155.28212<br\/>  <b>Detection Time: <\/b> 2024-01-21 12:20 UTC<br\/>  <b>Sensor: <\/b> NOAA-20 VIIRS<br\/> <b>Confidence: <\/b> Nominal<br\/>  <b>Day\/Night: <\/b> Night<br\/> <b>Scan: <\/b> 0.4 km<br\/> <b>Track: <\/b> 0.4 km<br\/> <b>FRP: <\/b> 2.8 MW<br\/> <b>Brightness: <\/b> 303.15 K" }, "geometry": { "type": "Point", "coordinates": [ -155.28212, 19.41056, 0.0 ] } }
]
}
