{
"type": "FeatureCollection",
"crs": { "type": "name", "properties": { "name": "urn:ogc:def:crs:OGC:1.3:CRS84" } },
"features": [
{ "type": "Feature", "properties": { "Name": "Fire Detection Centroid ", "Description": "<b>Latitude: <\/b> 19.40473<br\/>  <b>Longitude: <\/b> -155.2823<br\/>  <b>Detection Time: <\/b> 2022-10-08 12:32 UTC<br\/>  <b>Sensor: <\/b> NOAA-20 VIIRS<br\/> <b>Confidence: <\/b> Nominal<br\/>  <b>Day\/Night: <\/b> Night<br\/> <b>Scan: <\/b> 0.33 km<br\/> <b>Track: <\/b> 0.55 km<br\/> <b>FRP: <\/b> 0.39 MW<br\/> <b>Brightness: <\/b> 298.97 K" }, "geometry": { "type": "Point", "coordinates": [ -155.2823, 19.40473, 0.0 ] } },
{ "type": "Feature", "properties": { "Name": "Fire Detection Centroid ", "Description": "<b>Latitude: <\/b> 19.40971<br\/>  <b>Longitude: <\/b> -155.28123<br\/>  <b>Detection Time: <\/b> 2022-10-08 12:32 UTC<br\/>  <b>Sensor: <\/b> NOAA-20 VIIRS<br\/> <b>Confidence: <\/b> Nominal<br\/>  <b>Day\/Night: <\/b> Night<br\/> <b>Scan: <\/b> 0.33 km<br\/> <b>Track: <\/b> 0.55 km<br\/> <b>FRP: <\/b> 0.39 MW<br\/> <b>Brightness: <\/b> 295.15 K" }, "geometry": { "type": "Point", "coordinates": [ -155.28123, 19.40971, 0.0 ] } },
{ "type": "Feature", "properties": { "Name": "Fire Detection Centroid ", "Description": "<b>Latitude: <\/b> 19.40537<br\/>  <b>Longitude: <\/b> -155.2854<br\/>  <b>Detection Time: <\/b> 2022-10-08 12:32 UTC<br\/>  <b>Sensor: <\/b> NOAA-20 VIIRS<br\/> <b>Confidence: <\/b> Nominal<br\/>  <b>Day\/Night: <\/b> Night<br\/> <b>Scan: <\/b> 0.33 km<br\/> <b>Track: <\/b> 0.55 km<br\/> <b>FRP: <\/b> 0.39 MW<br\/> <b>Brightness: <\/b> 304.21 K" }, "geometry": { "type": "Point", "coordinates": [ -155.2854, 19.40537, 0.0 ] } }
]
}
