{
"type": "FeatureCollection",
"crs": { "type": "name", "properties": { "name": "urn:ogc:def:crs:OGC:1.3:CRS84" } },
"features": [
{ "type": "Feature", "properties": { "Name": "Fire Detection Centroid ", "Description": "<b>Latitude: <\/b> 45.28447<br\/>  <b>Longitude: <\/b> -66.02275<br\/>  <b>Detection Time: <\/b> 2022-09-02 05:14 UTC<br\/>  <b>Sensor: <\/b> NOAA-20 VIIRS<br\/> <b>Confidence: <\/b> Nominal<br\/>  <b>Day\/Night: <\/b> Night<br\/> <b>Scan: <\/b> 0.6 km<br\/> <b>Track: <\/b> 0.7 km<br\/> <b>FRP: <\/b> 1.06 MW<br\/> <b>Brightness: <\/b> 297.19 K" }, "geometry": { "type": "Point", "coordinates": [ -66.02275, 45.28447, 0.0 ] } },
{ "type": "Feature", "properties": { "Name": "Fire Detection Centroid ", "Description": "<b>Latitude: <\/b> 45.28092<br\/>  <b>Longitude: <\/b> -66.02026<br\/>  <b>Detection Time: <\/b> 2022-09-02 05:14 UTC<br\/>  <b>Sensor: <\/b> NOAA-20 VIIRS<br\/> <b>Confidence: <\/b> Nominal<br\/>  <b>Day\/Night: <\/b> Night<br\/> <b>Scan: <\/b> 0.6 km<br\/> <b>Track: <\/b> 0.7 km<br\/> <b>FRP: <\/b> 1.47 MW<br\/> <b>Brightness: <\/b> 300.7 K" }, "geometry": { "type": "Point", "coordinates": [ -66.02026, 45.28092, 0.0 ] } }
]
}
