{
"type": "FeatureCollection",
"crs": { "type": "name", "properties": { "name": "urn:ogc:def:crs:OGC:1.3:CRS84" } },
"features": [
{ "type": "Feature", "properties": { "Name": "Fire Detection Centroid ", "Description": "<b>Latitude: <\/b> 18.93323<br\/>  <b>Longitude: <\/b> -70.35193<br\/>  <b>Detection Time: <\/b> 2022-10-24 05:47 UTC<br\/>  <b>Sensor: <\/b> NOAA-20 VIIRS<br\/> <b>Confidence: <\/b> Nominal<br\/>  <b>Day\/Night: <\/b> Night<br\/> <b>Scan: <\/b> 0.6 km<br\/> <b>Track: <\/b> 0.5 km<br\/> <b>FRP: <\/b> 1.45 MW<br\/> <b>Brightness: <\/b> 295.91 K" }, "geometry": { "type": "Point", "coordinates": [ -70.35193, 18.93323, 0.0 ] } },
{ "type": "Feature", "properties": { "Name": "Fire Detection Centroid ", "Description": "<b>Latitude: <\/b> 18.92851<br\/>  <b>Longitude: <\/b> -70.35242<br\/>  <b>Detection Time: <\/b> 2022-10-24 05:47 UTC<br\/>  <b>Sensor: <\/b> NOAA-20 VIIRS<br\/> <b>Confidence: <\/b> Nominal<br\/>  <b>Day\/Night: <\/b> Night<br\/> <b>Scan: <\/b> 0.6 km<br\/> <b>Track: <\/b> 0.5 km<br\/> <b>FRP: <\/b> 7.14 MW<br\/> <b>Brightness: <\/b> 339.37 K" }, "geometry": { "type": "Point", "coordinates": [ -70.35242, 18.92851, 0.0 ] } },
{ "type": "Feature", "properties": { "Name": "Fire Detection Centroid ", "Description": "<b>Latitude: <\/b> 18.92968<br\/>  <b>Longitude: <\/b> -70.36286<br\/>  <b>Detection Time: <\/b> 2022-10-24 05:47 UTC<br\/>  <b>Sensor: <\/b> NOAA-20 VIIRS<br\/> <b>Confidence: <\/b> Nominal<br\/>  <b>Day\/Night: <\/b> Night<br\/> <b>Scan: <\/b> 0.6 km<br\/> <b>Track: <\/b> 0.5 km<br\/> <b>FRP: <\/b> 2.56 MW<br\/> <b>Brightness: <\/b> 301.66 K" }, "geometry": { "type": "Point", "coordinates": [ -70.36286, 18.92968, 0.0 ] } },
{ "type": "Feature", "properties": { "Name": "Fire Detection Centroid ", "Description": "<b>Latitude: <\/b> 18.92757<br\/>  <b>Longitude: <\/b> -70.35921<br\/>  <b>Detection Time: <\/b> 2022-10-24 05:47 UTC<br\/>  <b>Sensor: <\/b> NOAA-20 VIIRS<br\/> <b>Confidence: <\/b> Nominal<br\/>  <b>Day\/Night: <\/b> Night<br\/> <b>Scan: <\/b> 0.6 km<br\/> <b>Track: <\/b> 0.5 km<br\/> <b>FRP: <\/b> 3.98 MW<br\/> <b>Brightness: <\/b> 308.64 K" }, "geometry": { "type": "Point", "coordinates": [ -70.35921, 18.92757, 0.0 ] } },
{ "type": "Feature", "properties": { "Name": "Fire Detection Centroid ", "Description": "<b>Latitude: <\/b> 18.92693<br\/>  <b>Longitude: <\/b> -70.35387<br\/>  <b>Detection Time: <\/b> 2022-10-24 05:47 UTC<br\/>  <b>Sensor: <\/b> NOAA-20 VIIRS<br\/> <b>Confidence: <\/b> Nominal<br\/>  <b>Day\/Night: <\/b> Night<br\/> <b>Scan: <\/b> 0.6 km<br\/> <b>Track: <\/b> 0.5 km<br\/> <b>FRP: <\/b> 3.98 MW<br\/> <b>Brightness: <\/b> 334.6 K" }, "geometry": { "type": "Point", "coordinates": [ -70.35387, 18.92693, 0.0 ] } },
{ "type": "Feature", "properties": { "Name": "Fire Detection Centroid ", "Description": "<b>Latitude: <\/b> 18.92434<br\/>  <b>Longitude: <\/b> -70.35786<br\/>  <b>Detection Time: <\/b> 2022-10-24 05:47 UTC<br\/>  <b>Sensor: <\/b> NOAA-20 VIIRS<br\/> <b>Confidence: <\/b> Nominal<br\/>  <b>Day\/Night: <\/b> Night<br\/> <b>Scan: <\/b> 0.6 km<br\/> <b>Track: <\/b> 0.5 km<br\/> <b>FRP: <\/b> 2.56 MW<br\/> <b>Brightness: <\/b> 298.02 K" }, "geometry": { "type": "Point", "coordinates": [ -70.35786, 18.92434, 0.0 ] } },
{ "type": "Feature", "properties": { "Name": "Fire Detection Centroid ", "Description": "<b>Latitude: <\/b> 18.9291<br\/>  <b>Longitude: <\/b> -70.35767<br\/>  <b>Detection Time: <\/b> 2022-10-24 05:47 UTC<br\/>  <b>Sensor: <\/b> NOAA-20 VIIRS<br\/> <b>Confidence: <\/b> Nominal<br\/>  <b>Day\/Night: <\/b> Night<br\/> <b>Scan: <\/b> 0.6 km<br\/> <b>Track: <\/b> 0.5 km<br\/> <b>FRP: <\/b> 2.56 MW<br\/> <b>Brightness: <\/b> 319.89 K" }, "geometry": { "type": "Point", "coordinates": [ -70.35767, 18.9291, 0.0 ] } },
{ "type": "Feature", "properties": { "Name": "Fire Detection Centroid ", "Description": "<b>Latitude: <\/b> 18.93384<br\/>  <b>Longitude: <\/b> -70.35729<br\/>  <b>Detection Time: <\/b> 2022-10-24 05:47 UTC<br\/>  <b>Sensor: <\/b> NOAA-20 VIIRS<br\/> <b>Confidence: <\/b> Nominal<br\/>  <b>Day\/Night: <\/b> Night<br\/> <b>Scan: <\/b> 0.6 km<br\/> <b>Track: <\/b> 0.5 km<br\/> <b>FRP: <\/b> 1.64 MW<br\/> <b>Brightness: <\/b> 296.89 K" }, "geometry": { "type": "Point", "coordinates": [ -70.35729, 18.93384, 0.0 ] } }
]
}
