{
"type": "FeatureCollection",
"crs": { "type": "name", "properties": { "name": "urn:ogc:def:crs:OGC:1.3:CRS84" } },
"features": [
{ "type": "Feature", "properties": { "Name": "Fire Detection Centroid ", "Description": "<b>Latitude: <\/b> 18.82439<br\/>  <b>Longitude: <\/b> -68.61959<br\/>  <b>Detection Time: <\/b> 2023-02-24 16:52 UTC<br\/>  <b>Sensor: <\/b> NOAA-20 VIIRS<br\/> <b>Confidence: <\/b> Nominal<br\/>  <b>Day\/Night: <\/b> Day<br\/> <b>Scan: <\/b> 0.7 km<br\/> <b>Track: <\/b> 0.8 km<br\/> <b>FRP: <\/b> 7.22 MW<br\/> <b>Brightness: <\/b> 336.27 K" }, "geometry": { "type": "Point", "coordinates": [ -68.61959, 18.82439, 0.0 ] } },
{ "type": "Feature", "properties": { "Name": "Fire Detection Centroid ", "Description": "<b>Latitude: <\/b> 18.82439<br\/>  <b>Longitude: <\/b> -68.61959<br\/>  <b>Detection Time: <\/b> 2023-02-24 16:52 UTC<br\/>  <b>Sensor: <\/b> NOAA-20 VIIRS<br\/> <b>Confidence: <\/b> Nominal<br\/>  <b>Day\/Night: <\/b> Day<br\/> <b>Scan: <\/b> 0.7 km<br\/> <b>Track: <\/b> 0.8 km<br\/> <b>FRP: <\/b> 7.22 MW<br\/> <b>Brightness: <\/b> 336.27 K" }, "geometry": { "type": "Point", "coordinates": [ -68.61959, 18.82439, 0.0 ] } },
{ "type": "Feature", "properties": { "Name": "Fire Detection Centroid ", "Description": "<b>Latitude: <\/b> 18.82592<br\/>  <b>Longitude: <\/b> -68.61311<br\/>  <b>Detection Time: <\/b> 2023-02-24 16:52 UTC<br\/>  <b>Sensor: <\/b> NOAA-20 VIIRS<br\/> <b>Confidence: <\/b> Nominal<br\/>  <b>Day\/Night: <\/b> Day<br\/> <b>Scan: <\/b> 0.7 km<br\/> <b>Track: <\/b> 0.8 km<br\/> <b>FRP: <\/b> 6.84 MW<br\/> <b>Brightness: <\/b> 328.17 K" }, "geometry": { "type": "Point", "coordinates": [ -68.61311, 18.82592, 0.0 ] } },
{ "type": "Feature", "properties": { "Name": "Fire Detection Centroid ", "Description": "<b>Latitude: <\/b> 19.03726<br\/>  <b>Longitude: <\/b> -69.48042<br\/>  <b>Detection Time: <\/b> 2023-02-24 16:52 UTC<br\/>  <b>Sensor: <\/b> NOAA-20 VIIRS<br\/> <b>Confidence: <\/b> Nominal<br\/>  <b>Day\/Night: <\/b> Day<br\/> <b>Scan: <\/b> 0.8 km<br\/> <b>Track: <\/b> 0.8 km<br\/> <b>FRP: <\/b> 5.92 MW<br\/> <b>Brightness: <\/b> 336.31 K" }, "geometry": { "type": "Point", "coordinates": [ -69.48042, 19.03726, 0.0 ] } },
{ "type": "Feature", "properties": { "Name": "Fire Detection Centroid ", "Description": "<b>Latitude: <\/b> 18.82592<br\/>  <b>Longitude: <\/b> -68.61311<br\/>  <b>Detection Time: <\/b> 2023-02-24 16:52 UTC<br\/>  <b>Sensor: <\/b> NOAA-20 VIIRS<br\/> <b>Confidence: <\/b> Nominal<br\/>  <b>Day\/Night: <\/b> Day<br\/> <b>Scan: <\/b> 0.7 km<br\/> <b>Track: <\/b> 0.8 km<br\/> <b>FRP: <\/b> 6.84 MW<br\/> <b>Brightness: <\/b> 328.17 K" }, "geometry": { "type": "Point", "coordinates": [ -68.61311, 18.82592, 0.0 ] } }
]
}
