{
"type": "FeatureCollection",
"crs": { "type": "name", "properties": { "name": "urn:ogc:def:crs:OGC:1.3:CRS84" } },
"features": [
{ "type": "Feature", "properties": { "Name": "Fire Detection Centroid ", "Description": "<b>Latitude: <\/b> 22.17716<br\/>  <b>Longitude: <\/b> -98.26572<br\/>  <b>Detection Time: <\/b> 2023-08-21 08:26 UTC<br\/>  <b>Sensor: <\/b> NOAA-20 VIIRS<br\/> <b>Confidence: <\/b> Nominal<br\/>  <b>Day\/Night: <\/b> Night<br\/> <b>Scan: <\/b> 0.5 km<br\/> <b>Track: <\/b> 0.4 km<br\/> <b>FRP: <\/b> 0.58 MW<br\/> <b>Brightness: <\/b> 296.77 K" }, "geometry": { "type": "Point", "coordinates": [ -98.26572, 22.17716, 0.0 ] } }
]
}
