{
"type": "FeatureCollection",
"crs": { "type": "name", "properties": { "name": "urn:ogc:def:crs:OGC:1.3:CRS84" } },
"features": [
{ "type": "Feature", "properties": { "Name": "Fire Detection Centroid ", "Description": "<b>Latitude: <\/b> 22.61868<br\/>  <b>Longitude: <\/b> -79.69736<br\/>  <b>Detection Time: <\/b> 2023-06-27 18:29 UTC<br\/>  <b>Sensor: <\/b> NOAA-20 VIIRS<br\/> <b>Confidence: <\/b> Low<br\/>  <b>Day\/Night: <\/b> Day<br\/> <b>Scan: <\/b> 0.4 km<br\/> <b>Track: <\/b> 0.4 km<br\/> <b>FRP: <\/b> 4.21 MW<br\/> <b>Brightness: <\/b> 331.59 K" }, "geometry": { "type": "Point", "coordinates": [ -79.69736, 22.61868, 0.0 ] } },
{ "type": "Feature", "properties": { "Name": "Fire Detection Centroid ", "Description": "<b>Latitude: <\/b> 22.62197<br\/>  <b>Longitude: <\/b> -79.69794<br\/>  <b>Detection Time: <\/b> 2023-06-27 18:29 UTC<br\/>  <b>Sensor: <\/b> NOAA-20 VIIRS<br\/> <b>Confidence: <\/b> Low<br\/>  <b>Day\/Night: <\/b> Day<br\/> <b>Scan: <\/b> 0.4 km<br\/> <b>Track: <\/b> 0.4 km<br\/> <b>FRP: <\/b> 4.21 MW<br\/> <b>Brightness: <\/b> 333.63 K" }, "geometry": { "type": "Point", "coordinates": [ -79.69794, 22.62197, 0.0 ] } },
{ "type": "Feature", "properties": { "Name": "Fire Detection Centroid ", "Description": "<b>Latitude: <\/b> 21.47389<br\/>  <b>Longitude: <\/b> -87.66991<br\/>  <b>Detection Time: <\/b> 2023-06-27 18:29 UTC<br\/>  <b>Sensor: <\/b> NOAA-20 VIIRS<br\/> <b>Confidence: <\/b> Nominal<br\/>  <b>Day\/Night: <\/b> Day<br\/> <b>Scan: <\/b> 0.6 km<br\/> <b>Track: <\/b> 0.5 km<br\/> <b>FRP: <\/b> 4.72 MW<br\/> <b>Brightness: <\/b> 330.73 K" }, "geometry": { "type": "Point", "coordinates": [ -87.66991, 21.47389, 0.0 ] } }
]
}
