{
"type": "FeatureCollection",
"crs": { "type": "name", "properties": { "name": "urn:ogc:def:crs:OGC:1.3:CRS84" } },
"features": [
{ "type": "Feature", "properties": { "Name": "Fire Detection Centroid ", "Description": "<b>Latitude: <\/b> 42.80271<br\/>  <b>Longitude: <\/b> -80.09058<br\/>  <b>Detection Time: <\/b> 2022-09-17 16:59 UTC<br\/>  <b>Sensor: <\/b> NOAA-20 VIIRS<br\/> <b>Confidence: <\/b> Nominal<br\/>  <b>Day\/Night: <\/b> Day<br\/> <b>Scan: <\/b> 0.7 km<br\/> <b>Track: <\/b> 0.7 km<br\/> <b>FRP: <\/b> 8.27 MW<br\/> <b>Brightness: <\/b> 327.61 K" }, "geometry": { "type": "Point", "coordinates": [ -80.09058, 42.80271, 0.0 ] } },
{ "type": "Feature", "properties": { "Name": "Fire Detection Centroid ", "Description": "<b>Latitude: <\/b> 42.80456<br\/>  <b>Longitude: <\/b> -80.09338<br\/>  <b>Detection Time: <\/b> 2022-09-17 16:59 UTC<br\/>  <b>Sensor: <\/b> NOAA-20 VIIRS<br\/> <b>Confidence: <\/b> Nominal<br\/>  <b>Day\/Night: <\/b> Day<br\/> <b>Scan: <\/b> 0.7 km<br\/> <b>Track: <\/b> 0.7 km<br\/> <b>FRP: <\/b> 7.69 MW<br\/> <b>Brightness: <\/b> 332.45 K" }, "geometry": { "type": "Point", "coordinates": [ -80.09338, 42.80456, 0.0 ] } },
{ "type": "Feature", "properties": { "Name": "Fire Detection Centroid ", "Description": "<b>Latitude: <\/b> 19.41172<br\/>  <b>Longitude: <\/b> -155.28604<br\/>  <b>Detection Time: <\/b> 2022-09-17 12:25 UTC<br\/>  <b>Sensor: <\/b> NOAA-20 VIIRS<br\/> <b>Confidence: <\/b> Nominal<br\/>  <b>Day\/Night: <\/b> Night<br\/> <b>Scan: <\/b> 0.51 km<br\/> <b>Track: <\/b> 0.5 km<br\/> <b>FRP: <\/b> 1.41 MW<br\/> <b>Brightness: <\/b> 307.32 K" }, "geometry": { "type": "Point", "coordinates": [ -155.28604, 19.41172, 0.0 ] } },
{ "type": "Feature", "properties": { "Name": "Fire Detection Centroid ", "Description": "<b>Latitude: <\/b> 19.40822<br\/>  <b>Longitude: <\/b> -155.29199<br\/>  <b>Detection Time: <\/b> 2022-09-17 12:25 UTC<br\/>  <b>Sensor: <\/b> NOAA-20 VIIRS<br\/> <b>Confidence: <\/b> Nominal<br\/>  <b>Day\/Night: <\/b> Night<br\/> <b>Scan: <\/b> 0.51 km<br\/> <b>Track: <\/b> 0.5 km<br\/> <b>FRP: <\/b> 1.41 MW<br\/> <b>Brightness: <\/b> 303.04 K" }, "geometry": { "type": "Point", "coordinates": [ -155.29199, 19.40822, 0.0 ] } },
{ "type": "Feature", "properties": { "Name": "Fire Detection Centroid ", "Description": "<b>Latitude: <\/b> 19.41522<br\/>  <b>Longitude: <\/b> -155.28014<br\/>  <b>Detection Time: <\/b> 2022-09-17 12:25 UTC<br\/>  <b>Sensor: <\/b> NOAA-20 VIIRS<br\/> <b>Confidence: <\/b> Nominal<br\/>  <b>Day\/Night: <\/b> Night<br\/> <b>Scan: <\/b> 0.51 km<br\/> <b>Track: <\/b> 0.5 km<br\/> <b>FRP: <\/b> 0.87 MW<br\/> <b>Brightness: <\/b> 296.82 K" }, "geometry": { "type": "Point", "coordinates": [ -155.28014, 19.41522, 0.0 ] } },
{ "type": "Feature", "properties": { "Name": "Fire Detection Centroid ", "Description": "<b>Latitude: <\/b> 19.41273<br\/>  <b>Longitude: <\/b> -155.29115<br\/>  <b>Detection Time: <\/b> 2022-09-17 12:25 UTC<br\/>  <b>Sensor: <\/b> NOAA-20 VIIRS<br\/> <b>Confidence: <\/b> Nominal<br\/>  <b>Day\/Night: <\/b> Night<br\/> <b>Scan: <\/b> 0.51 km<br\/> <b>Track: <\/b> 0.5 km<br\/> <b>FRP: <\/b> 1.41 MW<br\/> <b>Brightness: <\/b> 303 K" }, "geometry": { "type": "Point", "coordinates": [ -155.29115, 19.41273, 0.0 ] } }
]
}
