{
"type": "FeatureCollection",
"crs": { "type": "name", "properties": { "name": "urn:ogc:def:crs:OGC:1.3:CRS84" } },
"features": [
{ "type": "Feature", "properties": { "Name": "Fire Detection Centroid ", "Description": "<b>Latitude: <\/b> 46.56<br\/>  <b>Longitude: <\/b> -118.97191<br\/>  <b>Detection Time: <\/b> 2023-09-07 11:21 UTC<br\/>  <b>Sensor: <\/b> NOAA-20 VIIRS<br\/> <b>Confidence: <\/b> Nominal<br\/>  <b>Day\/Night: <\/b> Night<br\/> <b>Scan: <\/b> 0.77 km<br\/> <b>Track: <\/b> 0.78 km<br\/> <b>FRP: <\/b> 1.68 MW<br\/> <b>Brightness: <\/b> 296.72 K" }, "geometry": { "type": "Point", "coordinates": [ -118.97191, 46.56, 0.0 ] } },
{ "type": "Feature", "properties": { "Name": "Fire Detection Centroid ", "Description": "<b>Latitude: <\/b> 48.88754<br\/>  <b>Longitude: <\/b> -122.73543<br\/>  <b>Detection Time: <\/b> 2023-09-07 11:21 UTC<br\/>  <b>Sensor: <\/b> NOAA-20 VIIRS<br\/> <b>Confidence: <\/b> Nominal<br\/>  <b>Day\/Night: <\/b> Night<br\/> <b>Scan: <\/b> 0.45 km<br\/> <b>Track: <\/b> 0.63 km<br\/> <b>FRP: <\/b> 1.59 MW<br\/> <b>Brightness: <\/b> 296.67 K" }, "geometry": { "type": "Point", "coordinates": [ -122.73543, 48.88754, 0.0 ] } },
{ "type": "Feature", "properties": { "Name": "Fire Detection Centroid ", "Description": "<b>Latitude: <\/b> 49.62241<br\/>  <b>Longitude: <\/b> -126.31809<br\/>  <b>Detection Time: <\/b> 2023-09-07 11:21 UTC<br\/>  <b>Sensor: <\/b> NOAA-20 VIIRS<br\/> <b>Confidence: <\/b> Nominal<br\/>  <b>Day\/Night: <\/b> Night<br\/> <b>Scan: <\/b> 0.6 km<br\/> <b>Track: <\/b> 0.53 km<br\/> <b>FRP: <\/b> 8.63 MW<br\/> <b>Brightness: <\/b> 337.99 K" }, "geometry": { "type": "Point", "coordinates": [ -126.31809, 49.62241, 0.0 ] } },
{ "type": "Feature", "properties": { "Name": "Fire Detection Centroid ", "Description": "<b>Latitude: <\/b> 46.55895<br\/>  <b>Longitude: <\/b> -118.97676<br\/>  <b>Detection Time: <\/b> 2023-09-07 11:21 UTC<br\/>  <b>Sensor: <\/b> NOAA-20 VIIRS<br\/> <b>Confidence: <\/b> Nominal<br\/>  <b>Day\/Night: <\/b> Night<br\/> <b>Scan: <\/b> 0.77 km<br\/> <b>Track: <\/b> 0.78 km<br\/> <b>FRP: <\/b> 2.51 MW<br\/> <b>Brightness: <\/b> 296.12 K" }, "geometry": { "type": "Point", "coordinates": [ -118.97676, 46.55895, 0.0 ] } },
{ "type": "Feature", "properties": { "Name": "Fire Detection Centroid ", "Description": "<b>Latitude: <\/b> 49.90186<br\/>  <b>Longitude: <\/b> -119.67135<br\/>  <b>Detection Time: <\/b> 2023-09-07 11:19 UTC<br\/>  <b>Sensor: <\/b> NOAA-20 VIIRS<br\/> <b>Confidence: <\/b> Nominal<br\/>  <b>Day\/Night: <\/b> Night<br\/> <b>Scan: <\/b> 0.55 km<br\/> <b>Track: <\/b> 0.68 km<br\/> <b>FRP: <\/b> 2.13 MW<br\/> <b>Brightness: <\/b> 295.82 K" }, "geometry": { "type": "Point", "coordinates": [ -119.67135, 49.90186, 0.0 ] } },
{ "type": "Feature", "properties": { "Name": "Fire Detection Centroid ", "Description": "<b>Latitude: <\/b> 49.90422<br\/>  <b>Longitude: <\/b> -119.67337<br\/>  <b>Detection Time: <\/b> 2023-09-07 11:19 UTC<br\/>  <b>Sensor: <\/b> NOAA-20 VIIRS<br\/> <b>Confidence: <\/b> Nominal<br\/>  <b>Day\/Night: <\/b> Night<br\/> <b>Scan: <\/b> 0.55 km<br\/> <b>Track: <\/b> 0.68 km<br\/> <b>FRP: <\/b> 2.16 MW<br\/> <b>Brightness: <\/b> 296.02 K" }, "geometry": { "type": "Point", "coordinates": [ -119.67337, 49.90422, 0.0 ] } },
{ "type": "Feature", "properties": { "Name": "Fire Detection Centroid ", "Description": "<b>Latitude: <\/b> 49.91646<br\/>  <b>Longitude: <\/b> -119.6879<br\/>  <b>Detection Time: <\/b> 2023-09-07 11:19 UTC<br\/>  <b>Sensor: <\/b> NOAA-20 VIIRS<br\/> <b>Confidence: <\/b> Nominal<br\/>  <b>Day\/Night: <\/b> Night<br\/> <b>Scan: <\/b> 0.55 km<br\/> <b>Track: <\/b> 0.68 km<br\/> <b>FRP: <\/b> 1.57 MW<br\/> <b>Brightness: <\/b> 296.6 K" }, "geometry": { "type": "Point", "coordinates": [ -119.6879, 49.91646, 0.0 ] } },
{ "type": "Feature", "properties": { "Name": "Fire Detection Centroid ", "Description": "<b>Latitude: <\/b> 49.92085<br\/>  <b>Longitude: <\/b> -119.68434<br\/>  <b>Detection Time: <\/b> 2023-09-07 11:19 UTC<br\/>  <b>Sensor: <\/b> NOAA-20 VIIRS<br\/> <b>Confidence: <\/b> Nominal<br\/>  <b>Day\/Night: <\/b> Night<br\/> <b>Scan: <\/b> 0.55 km<br\/> <b>Track: <\/b> 0.68 km<br\/> <b>FRP: <\/b> 1.78 MW<br\/> <b>Brightness: <\/b> 305.71 K" }, "geometry": { "type": "Point", "coordinates": [ -119.68434, 49.92085, 0.0 ] } },
{ "type": "Feature", "properties": { "Name": "Fire Detection Centroid ", "Description": "<b>Latitude: <\/b> 49.92273<br\/>  <b>Longitude: <\/b> -119.68538<br\/>  <b>Detection Time: <\/b> 2023-09-07 11:19 UTC<br\/>  <b>Sensor: <\/b> NOAA-20 VIIRS<br\/> <b>Confidence: <\/b> Nominal<br\/>  <b>Day\/Night: <\/b> Night<br\/> <b>Scan: <\/b> 0.55 km<br\/> <b>Track: <\/b> 0.68 km<br\/> <b>FRP: <\/b> 1.57 MW<br\/> <b>Brightness: <\/b> 302.46 K" }, "geometry": { "type": "Point", "coordinates": [ -119.68538, 49.92273, 0.0 ] } }
]
}
