{
"type": "FeatureCollection",
"crs": { "type": "name", "properties": { "name": "urn:ogc:def:crs:OGC:1.3:CRS84" } },
"features": [
{ "type": "Feature", "properties": { "Name": "Fire Detection Centroid ", "Description": "<b>Latitude: <\/b> 45.62011<br\/>  <b>Longitude: <\/b> -71.60329<br\/>  <b>Detection Time: <\/b> 2023-07-26 06:25 UTC<br\/>  <b>Sensor: <\/b> NOAA-20 VIIRS<br\/> <b>Confidence: <\/b> Nominal<br\/>  <b>Day\/Night: <\/b> Night<br\/> <b>Scan: <\/b> 0.5 km<br\/> <b>Track: <\/b> 0.4 km<br\/> <b>FRP: <\/b> 1.14 MW<br\/> <b>Brightness: <\/b> 298.98 K" }, "geometry": { "type": "Point", "coordinates": [ -71.60329, 45.62011, 0.0 ] } },
{ "type": "Feature", "properties": { "Name": "Fire Detection Centroid ", "Description": "<b>Latitude: <\/b> 46.5177<br\/>  <b>Longitude: <\/b> -84.40243<br\/>  <b>Detection Time: <\/b> 2023-07-26 06:25 UTC<br\/>  <b>Sensor: <\/b> NOAA-20 VIIRS<br\/> <b>Confidence: <\/b> Nominal<br\/>  <b>Day\/Night: <\/b> Night<br\/> <b>Scan: <\/b> 0.7 km<br\/> <b>Track: <\/b> 0.7 km<br\/> <b>FRP: <\/b> 1.94 MW<br\/> <b>Brightness: <\/b> 297.76 K" }, "geometry": { "type": "Point", "coordinates": [ -84.40243, 46.5177, 0.0 ] } },
{ "type": "Feature", "properties": { "Name": "Fire Detection Centroid ", "Description": "<b>Latitude: <\/b> 46.51781<br\/>  <b>Longitude: <\/b> -84.39346<br\/>  <b>Detection Time: <\/b> 2023-07-26 06:25 UTC<br\/>  <b>Sensor: <\/b> NOAA-20 VIIRS<br\/> <b>Confidence: <\/b> Nominal<br\/>  <b>Day\/Night: <\/b> Night<br\/> <b>Scan: <\/b> 0.7 km<br\/> <b>Track: <\/b> 0.7 km<br\/> <b>FRP: <\/b> 1.65 MW<br\/> <b>Brightness: <\/b> 295.64 K" }, "geometry": { "type": "Point", "coordinates": [ -84.39346, 46.51781, 0.0 ] } },
{ "type": "Feature", "properties": { "Name": "Fire Detection Centroid ", "Description": "<b>Latitude: <\/b> 46.04339<br\/>  <b>Longitude: <\/b> -73.14101<br\/>  <b>Detection Time: <\/b> 2023-07-26 06:25 UTC<br\/>  <b>Sensor: <\/b> NOAA-20 VIIRS<br\/> <b>Confidence: <\/b> Nominal<br\/>  <b>Day\/Night: <\/b> Night<br\/> <b>Scan: <\/b> 0.4 km<br\/> <b>Track: <\/b> 0.4 km<br\/> <b>FRP: <\/b> 0.44 MW<br\/> <b>Brightness: <\/b> 303.98 K" }, "geometry": { "type": "Point", "coordinates": [ -73.14101, 46.04339, 0.0 ] } },
{ "type": "Feature", "properties": { "Name": "Fire Detection Centroid ", "Description": "<b>Latitude: <\/b> 46.52499<br\/>  <b>Longitude: <\/b> -84.3828<br\/>  <b>Detection Time: <\/b> 2023-07-26 06:25 UTC<br\/>  <b>Sensor: <\/b> NOAA-20 VIIRS<br\/> <b>Confidence: <\/b> Nominal<br\/>  <b>Day\/Night: <\/b> Night<br\/> <b>Scan: <\/b> 0.7 km<br\/> <b>Track: <\/b> 0.7 km<br\/> <b>FRP: <\/b> 1.83 MW<br\/> <b>Brightness: <\/b> 310.84 K" }, "geometry": { "type": "Point", "coordinates": [ -84.3828, 46.52499, 0.0 ] } },
{ "type": "Feature", "properties": { "Name": "Fire Detection Centroid ", "Description": "<b>Latitude: <\/b> 46.52504<br\/>  <b>Longitude: <\/b> -84.3736<br\/>  <b>Detection Time: <\/b> 2023-07-26 06:25 UTC<br\/>  <b>Sensor: <\/b> NOAA-20 VIIRS<br\/> <b>Confidence: <\/b> Nominal<br\/>  <b>Day\/Night: <\/b> Night<br\/> <b>Scan: <\/b> 0.7 km<br\/> <b>Track: <\/b> 0.7 km<br\/> <b>FRP: <\/b> 1.83 MW<br\/> <b>Brightness: <\/b> 298.64 K" }, "geometry": { "type": "Point", "coordinates": [ -84.3736, 46.52504, 0.0 ] } },
{ "type": "Feature", "properties": { "Name": "Fire Detection Centroid ", "Description": "<b>Latitude: <\/b> 46.51797<br\/>  <b>Longitude: <\/b> -84.40079<br\/>  <b>Detection Time: <\/b> 2023-07-26 06:25 UTC<br\/>  <b>Sensor: <\/b> NOAA-20 VIIRS<br\/> <b>Confidence: <\/b> Nominal<br\/>  <b>Day\/Night: <\/b> Night<br\/> <b>Scan: <\/b> 0.7 km<br\/> <b>Track: <\/b> 0.7 km<br\/> <b>FRP: <\/b> 2.82 MW<br\/> <b>Brightness: <\/b> 300.87 K" }, "geometry": { "type": "Point", "coordinates": [ -84.40079, 46.51797, 0.0 ] } },
{ "type": "Feature", "properties": { "Name": "Fire Detection Centroid ", "Description": "<b>Latitude: <\/b> 48.18769<br\/>  <b>Longitude: <\/b> -64.92009<br\/>  <b>Detection Time: <\/b> 2023-07-26 06:24 UTC<br\/>  <b>Sensor: <\/b> NOAA-20 VIIRS<br\/> <b>Confidence: <\/b> Nominal<br\/>  <b>Day\/Night: <\/b> Night<br\/> <b>Scan: <\/b> 0.4 km<br\/> <b>Track: <\/b> 0.4 km<br\/> <b>FRP: <\/b> 0.79 MW<br\/> <b>Brightness: <\/b> 299.17 K" }, "geometry": { "type": "Point", "coordinates": [ -64.92009, 48.18769, 0.0 ] } }
]
}
