{
"type": "FeatureCollection",
"crs": { "type": "name", "properties": { "name": "urn:ogc:def:crs:OGC:1.3:CRS84" } },
"features": [
{ "type": "Feature", "properties": { "Name": "Fire Detection Centroid ", "Description": "<b>Latitude: <\/b> 19.59634<br\/>  <b>Longitude: <\/b> -155.50307<br\/>  <b>Detection Time: <\/b> 2023-03-09 11:44 UTC<br\/>  <b>Sensor: <\/b> NOAA-20 VIIRS<br\/> <b>Confidence: <\/b> Nominal<br\/>  <b>Day\/Night: <\/b> Night<br\/> <b>Scan: <\/b> 0.51 km<br\/> <b>Track: <\/b> 0.41 km<br\/> <b>FRP: <\/b> 1.91 MW<br\/> <b>Brightness: <\/b> 295.51 K" }, "geometry": { "type": "Point", "coordinates": [ -155.50307, 19.59634, 0.0 ] } },
{ "type": "Feature", "properties": { "Name": "Fire Detection Centroid ", "Description": "<b>Latitude: <\/b> 19.40886<br\/>  <b>Longitude: <\/b> -155.27888<br\/>  <b>Detection Time: <\/b> 2023-03-09 11:44 UTC<br\/>  <b>Sensor: <\/b> NOAA-20 VIIRS<br\/> <b>Confidence: <\/b> Nominal<br\/>  <b>Day\/Night: <\/b> Night<br\/> <b>Scan: <\/b> 0.5 km<br\/> <b>Track: <\/b> 0.41 km<br\/> <b>FRP: <\/b> 2.05 MW<br\/> <b>Brightness: <\/b> 304.11 K" }, "geometry": { "type": "Point", "coordinates": [ -155.27888, 19.40886, 0.0 ] } },
{ "type": "Feature", "properties": { "Name": "Fire Detection Centroid ", "Description": "<b>Latitude: <\/b> 19.40356<br\/>  <b>Longitude: <\/b> -155.28233<br\/>  <b>Detection Time: <\/b> 2023-03-09 11:44 UTC<br\/>  <b>Sensor: <\/b> NOAA-20 VIIRS<br\/> <b>Confidence: <\/b> Nominal<br\/>  <b>Day\/Night: <\/b> Night<br\/> <b>Scan: <\/b> 0.5 km<br\/> <b>Track: <\/b> 0.41 km<br\/> <b>FRP: <\/b> 1.99 MW<br\/> <b>Brightness: <\/b> 301.08 K" }, "geometry": { "type": "Point", "coordinates": [ -155.28233, 19.40356, 0.0 ] } },
{ "type": "Feature", "properties": { "Name": "Fire Detection Centroid ", "Description": "<b>Latitude: <\/b> 19.40576<br\/>  <b>Longitude: <\/b> -155.28415<br\/>  <b>Detection Time: <\/b> 2023-03-09 11:44 UTC<br\/>  <b>Sensor: <\/b> NOAA-20 VIIRS<br\/> <b>Confidence: <\/b> Nominal<br\/>  <b>Day\/Night: <\/b> Night<br\/> <b>Scan: <\/b> 0.5 km<br\/> <b>Track: <\/b> 0.41 km<br\/> <b>FRP: <\/b> 6.23 MW<br\/> <b>Brightness: <\/b> 330.28 K" }, "geometry": { "type": "Point", "coordinates": [ -155.28415, 19.40576, 0.0 ] } }
]
}
