{
"type": "FeatureCollection",
"crs": { "type": "name", "properties": { "name": "urn:ogc:def:crs:OGC:1.3:CRS84" } },
"features": [
{ "type": "Feature", "properties": { "Name": "Fire Detection Centroid ", "Description": "<b>Latitude: <\/b> 38.53454<br\/>  <b>Longitude: <\/b> -122.48723<br\/>  <b>Detection Time: <\/b> 2024-02-27 22:01 UTC<br\/>  <b>Sensor: <\/b> NOAA-20 VIIRS<br\/> <b>Confidence: <\/b> Nominal<br\/>  <b>Day\/Night: <\/b> Day<br\/> <b>Scan: <\/b> 0.49 km<br\/> <b>Track: <\/b> 0.65 km<br\/> <b>FRP: <\/b> 2.7 MW<br\/> <b>Brightness: <\/b> 334.12 K" }, "geometry": { "type": "Point", "coordinates": [ -122.48723, 38.53454, 0.0 ] } },
{ "type": "Feature", "properties": { "Name": "Fire Detection Centroid ", "Description": "<b>Latitude: <\/b> 38.52958<br\/>  <b>Longitude: <\/b> -122.27961<br\/>  <b>Detection Time: <\/b> 2024-02-27 22:01 UTC<br\/>  <b>Sensor: <\/b> NOAA-20 VIIRS<br\/> <b>Confidence: <\/b> Nominal<br\/>  <b>Day\/Night: <\/b> Day<br\/> <b>Scan: <\/b> 0.5 km<br\/> <b>Track: <\/b> 0.66 km<br\/> <b>FRP: <\/b> 3.36 MW<br\/> <b>Brightness: <\/b> 332.77 K" }, "geometry": { "type": "Point", "coordinates": [ -122.27961, 38.52958, 0.0 ] } },
{ "type": "Feature", "properties": { "Name": "Fire Detection Centroid ", "Description": "<b>Latitude: <\/b> 38.58875<br\/>  <b>Longitude: <\/b> -122.49813<br\/>  <b>Detection Time: <\/b> 2024-02-27 22:01 UTC<br\/>  <b>Sensor: <\/b> NOAA-20 VIIRS<br\/> <b>Confidence: <\/b> Nominal<br\/>  <b>Day\/Night: <\/b> Day<br\/> <b>Scan: <\/b> 0.5 km<br\/> <b>Track: <\/b> 0.6 km<br\/> <b>FRP: <\/b> 2.7 MW<br\/> <b>Brightness: <\/b> 334.12 K" }, "geometry": { "type": "Point", "coordinates": [ -122.49813, 38.58875, 0.0 ] } },
{ "type": "Feature", "properties": { "Name": "Fire Detection Centroid ", "Description": "<b>Latitude: <\/b> 38.60918<br\/>  <b>Longitude: <\/b> -122.28046<br\/>  <b>Detection Time: <\/b> 2024-02-27 22:01 UTC<br\/>  <b>Sensor: <\/b> NOAA-20 VIIRS<br\/> <b>Confidence: <\/b> Nominal<br\/>  <b>Day\/Night: <\/b> Day<br\/> <b>Scan: <\/b> 0.5 km<br\/> <b>Track: <\/b> 0.7 km<br\/> <b>FRP: <\/b> 3.84 MW<br\/> <b>Brightness: <\/b> 332.77 K" }, "geometry": { "type": "Point", "coordinates": [ -122.28046, 38.60918, 0.0 ] } }
]
}
