{
"type": "FeatureCollection",
"crs": { "type": "name", "properties": { "name": "urn:ogc:def:crs:OGC:1.3:CRS84" } },
"features": [
{ "type": "Feature", "properties": { "Name": "Fire Detection Centroid ", "Description": "<b>Latitude: <\/b> 34.37422<br\/>  <b>Longitude: <\/b> -79.88725<br\/>  <b>Detection Time: <\/b> 2023-01-27 06:02 UTC<br\/>  <b>Sensor: <\/b> NOAA-20 VIIRS<br\/> <b>Confidence: <\/b> Nominal<br\/>  <b>Day\/Night: <\/b> Night<br\/> <b>Scan: <\/b> 0.8 km<br\/> <b>Track: <\/b> 0.8 km<br\/> <b>FRP: <\/b> 1.96 MW<br\/> <b>Brightness: <\/b> 298.06 K" }, "geometry": { "type": "Point", "coordinates": [ -79.88725, 34.37422, 0.0 ] } },
{ "type": "Feature", "properties": { "Name": "Fire Detection Centroid ", "Description": "<b>Latitude: <\/b> 36.36033<br\/>  <b>Longitude: <\/b> -76.80554<br\/>  <b>Detection Time: <\/b> 2023-01-27 06:02 UTC<br\/>  <b>Sensor: <\/b> NOAA-20 VIIRS<br\/> <b>Confidence: <\/b> Nominal<br\/>  <b>Day\/Night: <\/b> Night<br\/> <b>Scan: <\/b> 0.5 km<br\/> <b>Track: <\/b> 0.7 km<br\/> <b>FRP: <\/b> 1.65 MW<br\/> <b>Brightness: <\/b> 298.66 K" }, "geometry": { "type": "Point", "coordinates": [ -76.80554, 36.36033, 0.0 ] } },
{ "type": "Feature", "properties": { "Name": "Fire Detection Centroid ", "Description": "<b>Latitude: <\/b> 36.35664<br\/>  <b>Longitude: <\/b> -76.81042<br\/>  <b>Detection Time: <\/b> 2023-01-27 06:02 UTC<br\/>  <b>Sensor: <\/b> NOAA-20 VIIRS<br\/> <b>Confidence: <\/b> Nominal<br\/>  <b>Day\/Night: <\/b> Night<br\/> <b>Scan: <\/b> 0.5 km<br\/> <b>Track: <\/b> 0.7 km<br\/> <b>FRP: <\/b> 2.63 MW<br\/> <b>Brightness: <\/b> 311.19 K" }, "geometry": { "type": "Point", "coordinates": [ -76.81042, 36.35664, 0.0 ] } },
{ "type": "Feature", "properties": { "Name": "Fire Detection Centroid ", "Description": "<b>Latitude: <\/b> 34.37641<br\/>  <b>Longitude: <\/b> -79.89236<br\/>  <b>Detection Time: <\/b> 2023-01-27 06:02 UTC<br\/>  <b>Sensor: <\/b> NOAA-20 VIIRS<br\/> <b>Confidence: <\/b> Nominal<br\/>  <b>Day\/Night: <\/b> Night<br\/> <b>Scan: <\/b> 0.8 km<br\/> <b>Track: <\/b> 0.8 km<br\/> <b>FRP: <\/b> 2.99 MW<br\/> <b>Brightness: <\/b> 314.83 K" }, "geometry": { "type": "Point", "coordinates": [ -79.89236, 34.37641, 0.0 ] } },
{ "type": "Feature", "properties": { "Name": "Fire Detection Centroid ", "Description": "<b>Latitude: <\/b> 39.59099<br\/>  <b>Longitude: <\/b> -75.63773<br\/>  <b>Detection Time: <\/b> 2023-01-27 06:01 UTC<br\/>  <b>Sensor: <\/b> NOAA-20 VIIRS<br\/> <b>Confidence: <\/b> Nominal<br\/>  <b>Day\/Night: <\/b> Night<br\/> <b>Scan: <\/b> 0.5 km<br\/> <b>Track: <\/b> 0.7 km<br\/> <b>FRP: <\/b> 0.86 MW<br\/> <b>Brightness: <\/b> 295.6 K" }, "geometry": { "type": "Point", "coordinates": [ -75.63773, 39.59099, 0.0 ] } },
{ "type": "Feature", "properties": { "Name": "Fire Detection Centroid ", "Description": "<b>Latitude: <\/b> 40.63783<br\/>  <b>Longitude: <\/b> -74.22546<br\/>  <b>Detection Time: <\/b> 2023-01-27 06:00 UTC<br\/>  <b>Sensor: <\/b> NOAA-20 VIIRS<br\/> <b>Confidence: <\/b> Nominal<br\/>  <b>Day\/Night: <\/b> Night<br\/> <b>Scan: <\/b> 0.4 km<br\/> <b>Track: <\/b> 0.6 km<br\/> <b>FRP: <\/b> 0.99 MW<br\/> <b>Brightness: <\/b> 296.6 K" }, "geometry": { "type": "Point", "coordinates": [ -74.22546, 40.63783, 0.0 ] } }
]
}
