{
"type": "FeatureCollection",
"crs": { "type": "name", "properties": { "name": "urn:ogc:def:crs:OGC:1.3:CRS84" } },
"features": [
{ "type": "Feature", "properties": { "Name": "Fire Detection Centroid ", "Description": "<b>Latitude: <\/b> 19.40595<br\/>  <b>Longitude: <\/b> -155.28786<br\/>  <b>Detection Time: <\/b> 2022-10-05 23:00 UTC<br\/>  <b>Sensor: <\/b> NOAA-20 VIIRS<br\/> <b>Confidence: <\/b> Nominal<br\/>  <b>Day\/Night: <\/b> Day<br\/> <b>Scan: <\/b> 0.6 km<br\/> <b>Track: <\/b> 0.5 km<br\/> <b>FRP: <\/b> 6.29 MW<br\/> <b>Brightness: <\/b> 334.21 K" }, "geometry": { "type": "Point", "coordinates": [ -155.28786, 19.40595, 0.0 ] } },
{ "type": "Feature", "properties": { "Name": "Fire Detection Centroid ", "Description": "<b>Latitude: <\/b> 19.40487<br\/>  <b>Longitude: <\/b> -155.2933<br\/>  <b>Detection Time: <\/b> 2022-10-05 23:00 UTC<br\/>  <b>Sensor: <\/b> NOAA-20 VIIRS<br\/> <b>Confidence: <\/b> Nominal<br\/>  <b>Day\/Night: <\/b> Day<br\/> <b>Scan: <\/b> 0.6 km<br\/> <b>Track: <\/b> 0.5 km<br\/> <b>FRP: <\/b> 6.29 MW<br\/> <b>Brightness: <\/b> 327.24 K" }, "geometry": { "type": "Point", "coordinates": [ -155.2933, 19.40487, 0.0 ] } },
{ "type": "Feature", "properties": { "Name": "Fire Detection Centroid ", "Description": "<b>Latitude: <\/b> 19.4054<br\/>  <b>Longitude: <\/b> -155.29245<br\/>  <b>Detection Time: <\/b> 2022-10-05 22:59 UTC<br\/>  <b>Sensor: <\/b> NOAA-20 VIIRS<br\/> <b>Confidence: <\/b> Nominal<br\/>  <b>Day\/Night: <\/b> Day<br\/> <b>Scan: <\/b> 0.62 km<br\/> <b>Track: <\/b> 0.54 km<br\/> <b>FRP: <\/b> 6.29 MW<br\/> <b>Brightness: <\/b> 327.24 K" }, "geometry": { "type": "Point", "coordinates": [ -155.29245, 19.4054, 0.0 ] } },
{ "type": "Feature", "properties": { "Name": "Fire Detection Centroid ", "Description": "<b>Latitude: <\/b> 19.40649<br\/>  <b>Longitude: <\/b> -155.28697<br\/>  <b>Detection Time: <\/b> 2022-10-05 22:59 UTC<br\/>  <b>Sensor: <\/b> NOAA-20 VIIRS<br\/> <b>Confidence: <\/b> Nominal<br\/>  <b>Day\/Night: <\/b> Day<br\/> <b>Scan: <\/b> 0.62 km<br\/> <b>Track: <\/b> 0.54 km<br\/> <b>FRP: <\/b> 6.29 MW<br\/> <b>Brightness: <\/b> 334.21 K" }, "geometry": { "type": "Point", "coordinates": [ -155.28697, 19.40649, 0.0 ] } }
]
}
