{
"type": "FeatureCollection",
"crs": { "type": "name", "properties": { "name": "urn:ogc:def:crs:OGC:1.3:CRS84" } },
"features": [
{ "type": "Feature", "properties": { "Name": "Fire Detection Centroid ", "Description": "<b>Latitude: <\/b> 41.84442<br\/>  <b>Longitude: <\/b> -123.38049<br\/>  <b>Detection Time: <\/b> 2024-01-22 21:37 UTC<br\/>  <b>Sensor: <\/b> NOAA-20 VIIRS<br\/> <b>Confidence: <\/b> Nominal<br\/>  <b>Day\/Night: <\/b> Day<br\/> <b>Scan: <\/b> 0.4 km<br\/> <b>Track: <\/b> 0.5 km<br\/> <b>FRP: <\/b> 7.37 MW<br\/> <b>Brightness: <\/b> 337.5 K" }, "geometry": { "type": "Point", "coordinates": [ -123.38049, 41.84442, 0.0 ] } },
{ "type": "Feature", "properties": { "Name": "Fire Detection Centroid ", "Description": "<b>Latitude: <\/b> 41.84041<br\/>  <b>Longitude: <\/b> -123.37886<br\/>  <b>Detection Time: <\/b> 2024-01-22 21:37 UTC<br\/>  <b>Sensor: <\/b> NOAA-20 VIIRS<br\/> <b>Confidence: <\/b> Nominal<br\/>  <b>Day\/Night: <\/b> Day<br\/> <b>Scan: <\/b> 0.43 km<br\/> <b>Track: <\/b> 0.46 km<br\/> <b>FRP: <\/b> 7.38 MW<br\/> <b>Brightness: <\/b> 337.5 K" }, "geometry": { "type": "Point", "coordinates": [ -123.37886, 41.84041, 0.0 ] } }
]
}
