{
"type": "FeatureCollection",
"crs": { "type": "name", "properties": { "name": "urn:ogc:def:crs:OGC:1.3:CRS84" } },
"features": [
{ "type": "Feature", "properties": { "Name": "Fire Detection Centroid ", "Description": "<b>Latitude: <\/b> 20.01931<br\/>  <b>Longitude: <\/b> -155.79413<br\/>  <b>Detection Time: <\/b> 2023-12-10 23:20 UTC<br\/>  <b>Sensor: <\/b> NOAA-20 VIIRS<br\/> <b>Confidence: <\/b> Low<br\/>  <b>Day\/Night: <\/b> Day<br\/> <b>Scan: <\/b> 0.5 km<br\/> <b>Track: <\/b> 0.41 km<br\/> <b>FRP: <\/b> 2.62 MW<br\/> <b>Brightness: <\/b> 328.99 K" }, "geometry": { "type": "Point", "coordinates": [ -155.79413, 20.01931, 0.0 ] } },
{ "type": "Feature", "properties": { "Name": "Fire Detection Centroid ", "Description": "<b>Latitude: <\/b> 20.0156<br\/>  <b>Longitude: <\/b> -155.79341<br\/>  <b>Detection Time: <\/b> 2023-12-10 23:20 UTC<br\/>  <b>Sensor: <\/b> NOAA-20 VIIRS<br\/> <b>Confidence: <\/b> Nominal<br\/>  <b>Day\/Night: <\/b> Day<br\/> <b>Scan: <\/b> 0.5 km<br\/> <b>Track: <\/b> 0.41 km<br\/> <b>FRP: <\/b> 2.62 MW<br\/> <b>Brightness: <\/b> 338.6 K" }, "geometry": { "type": "Point", "coordinates": [ -155.79341, 20.0156, 0.0 ] } },
{ "type": "Feature", "properties": { "Name": "Fire Detection Centroid ", "Description": "<b>Latitude: <\/b> 20.01856<br\/>  <b>Longitude: <\/b> -155.79466<br\/>  <b>Detection Time: <\/b> 2023-12-10 23:19 UTC<br\/>  <b>Sensor: <\/b> NOAA-20 VIIRS<br\/> <b>Confidence: <\/b> Low<br\/>  <b>Day\/Night: <\/b> Day<br\/> <b>Scan: <\/b> 0.5 km<br\/> <b>Track: <\/b> 0.4 km<br\/> <b>FRP: <\/b> 2.62 MW<br\/> <b>Brightness: <\/b> 328.99 K" }, "geometry": { "type": "Point", "coordinates": [ -155.79466, 20.01856, 0.0 ] } },
{ "type": "Feature", "properties": { "Name": "Fire Detection Centroid ", "Description": "<b>Latitude: <\/b> 20.01486<br\/>  <b>Longitude: <\/b> -155.79393<br\/>  <b>Detection Time: <\/b> 2023-12-10 23:19 UTC<br\/>  <b>Sensor: <\/b> NOAA-20 VIIRS<br\/> <b>Confidence: <\/b> Nominal<br\/>  <b>Day\/Night: <\/b> Day<br\/> <b>Scan: <\/b> 0.5 km<br\/> <b>Track: <\/b> 0.4 km<br\/> <b>FRP: <\/b> 2.62 MW<br\/> <b>Brightness: <\/b> 338.6 K" }, "geometry": { "type": "Point", "coordinates": [ -155.79393, 20.01486, 0.0 ] } }
]
}
