{
"type": "FeatureCollection",
"crs": { "type": "name", "properties": { "name": "urn:ogc:def:crs:OGC:1.3:CRS84" } },
"features": [
{ "type": "Feature", "properties": { "Name": "Fire Detection Centroid ", "Description": "<b>Latitude: <\/b> 19.40749<br\/>  <b>Longitude: <\/b> -155.2791<br\/>  <b>Detection Time: <\/b> 2023-07-10 11:38 UTC<br\/>  <b>Sensor: <\/b> NOAA-20 VIIRS<br\/> <b>Confidence: <\/b> Nominal<br\/>  <b>Day\/Night: <\/b> Night<br\/> <b>Scan: <\/b> 0.4 km<br\/> <b>Track: <\/b> 0.44 km<br\/> <b>FRP: <\/b> 1.77 MW<br\/> <b>Brightness: <\/b> 296.67 K" }, "geometry": { "type": "Point", "coordinates": [ -155.2791, 19.40749, 0.0 ] } },
{ "type": "Feature", "properties": { "Name": "Fire Detection Centroid ", "Description": "<b>Latitude: <\/b> 19.40844<br\/>  <b>Longitude: <\/b> -155.28656<br\/>  <b>Detection Time: <\/b> 2023-07-10 11:38 UTC<br\/>  <b>Sensor: <\/b> NOAA-20 VIIRS<br\/> <b>Confidence: <\/b> Nominal<br\/>  <b>Day\/Night: <\/b> Night<br\/> <b>Scan: <\/b> 0.4 km<br\/> <b>Track: <\/b> 0.44 km<br\/> <b>FRP: <\/b> 1.13 MW<br\/> <b>Brightness: <\/b> 295.13 K" }, "geometry": { "type": "Point", "coordinates": [ -155.28656, 19.40844, 0.0 ] } },
{ "type": "Feature", "properties": { "Name": "Fire Detection Centroid ", "Description": "<b>Latitude: <\/b> 19.40439<br\/>  <b>Longitude: <\/b> -155.28722<br\/>  <b>Detection Time: <\/b> 2023-07-10 11:38 UTC<br\/>  <b>Sensor: <\/b> NOAA-20 VIIRS<br\/> <b>Confidence: <\/b> Nominal<br\/>  <b>Day\/Night: <\/b> Night<br\/> <b>Scan: <\/b> 0.4 km<br\/> <b>Track: <\/b> 0.44 km<br\/> <b>FRP: <\/b> 1.13 MW<br\/> <b>Brightness: <\/b> 295.31 K" }, "geometry": { "type": "Point", "coordinates": [ -155.28722, 19.40439, 0.0 ] } },
{ "type": "Feature", "properties": { "Name": "Fire Detection Centroid ", "Description": "<b>Latitude: <\/b> 19.41154<br\/>  <b>Longitude: <\/b> -155.27849<br\/>  <b>Detection Time: <\/b> 2023-07-10 11:38 UTC<br\/>  <b>Sensor: <\/b> NOAA-20 VIIRS<br\/> <b>Confidence: <\/b> Nominal<br\/>  <b>Day\/Night: <\/b> Night<br\/> <b>Scan: <\/b> 0.4 km<br\/> <b>Track: <\/b> 0.44 km<br\/> <b>FRP: <\/b> 1.29 MW<br\/> <b>Brightness: <\/b> 297.59 K" }, "geometry": { "type": "Point", "coordinates": [ -155.27849, 19.41154, 0.0 ] } },
{ "type": "Feature", "properties": { "Name": "Fire Detection Centroid ", "Description": "<b>Latitude: <\/b> 19.41202<br\/>  <b>Longitude: <\/b> -155.2822<br\/>  <b>Detection Time: <\/b> 2023-07-10 11:38 UTC<br\/>  <b>Sensor: <\/b> NOAA-20 VIIRS<br\/> <b>Confidence: <\/b> Nominal<br\/>  <b>Day\/Night: <\/b> Night<br\/> <b>Scan: <\/b> 0.4 km<br\/> <b>Track: <\/b> 0.44 km<br\/> <b>FRP: <\/b> 1.29 MW<br\/> <b>Brightness: <\/b> 295.17 K" }, "geometry": { "type": "Point", "coordinates": [ -155.2822, 19.41202, 0.0 ] } },
{ "type": "Feature", "properties": { "Name": "Fire Detection Centroid ", "Description": "<b>Latitude: <\/b> 19.40391<br\/>  <b>Longitude: <\/b> -155.28346<br\/>  <b>Detection Time: <\/b> 2023-07-10 11:38 UTC<br\/>  <b>Sensor: <\/b> NOAA-20 VIIRS<br\/> <b>Confidence: <\/b> Nominal<br\/>  <b>Day\/Night: <\/b> Night<br\/> <b>Scan: <\/b> 0.4 km<br\/> <b>Track: <\/b> 0.44 km<br\/> <b>FRP: <\/b> 1.77 MW<br\/> <b>Brightness: <\/b> 295.21 K" }, "geometry": { "type": "Point", "coordinates": [ -155.28346, 19.40391, 0.0 ] } }
]
}
