{
"type": "FeatureCollection",
"crs": { "type": "name", "properties": { "name": "urn:ogc:def:crs:OGC:1.3:CRS84" } },
"features": [
{ "type": "Feature", "properties": { "Name": "Fire Detection Centroid ", "Description": "<b>Latitude: <\/b> 34.19983<br\/>  <b>Longitude: <\/b> -78.16349<br\/>  <b>Detection Time: <\/b> 2023-01-27 17:22 UTC<br\/>  <b>Sensor: <\/b> NOAA-20 VIIRS<br\/> <b>Confidence: <\/b> Nominal<br\/>  <b>Day\/Night: <\/b> Day<br\/> <b>Scan: <\/b> 0.5 km<br\/> <b>Track: <\/b> 0.6 km<br\/> <b>FRP: <\/b> 2.77 MW<br\/> <b>Brightness: <\/b> 329.12 K" }, "geometry": { "type": "Point", "coordinates": [ -78.16349, 34.19983, 0.0 ] } },
{ "type": "Feature", "properties": { "Name": "Fire Detection Centroid ", "Description": "<b>Latitude: <\/b> 34.26109<br\/>  <b>Longitude: <\/b> -78.00584<br\/>  <b>Detection Time: <\/b> 2023-01-27 17:22 UTC<br\/>  <b>Sensor: <\/b> NOAA-20 VIIRS<br\/> <b>Confidence: <\/b> Nominal<br\/>  <b>Day\/Night: <\/b> Day<br\/> <b>Scan: <\/b> 0.5 km<br\/> <b>Track: <\/b> 0.6 km<br\/> <b>FRP: <\/b> 4.77 MW<br\/> <b>Brightness: <\/b> 345.65 K" }, "geometry": { "type": "Point", "coordinates": [ -78.00584, 34.26109, 0.0 ] } },
{ "type": "Feature", "properties": { "Name": "Fire Detection Centroid ", "Description": "<b>Latitude: <\/b> 35.11402<br\/>  <b>Longitude: <\/b> -79.23207<br\/>  <b>Detection Time: <\/b> 2023-01-27 17:22 UTC<br\/>  <b>Sensor: <\/b> NOAA-20 VIIRS<br\/> <b>Confidence: <\/b> Nominal<br\/>  <b>Day\/Night: <\/b> Day<br\/> <b>Scan: <\/b> 0.5 km<br\/> <b>Track: <\/b> 0.7 km<br\/> <b>FRP: <\/b> 8.29 MW<br\/> <b>Brightness: <\/b> 336.76 K" }, "geometry": { "type": "Point", "coordinates": [ -79.23207, 35.11402, 0.0 ] } },
{ "type": "Feature", "properties": { "Name": "Fire Detection Centroid ", "Description": "<b>Latitude: <\/b> 35.11515<br\/>  <b>Longitude: <\/b> -79.23496<br\/>  <b>Detection Time: <\/b> 2023-01-27 17:22 UTC<br\/>  <b>Sensor: <\/b> NOAA-20 VIIRS<br\/> <b>Confidence: <\/b> Nominal<br\/>  <b>Day\/Night: <\/b> Day<br\/> <b>Scan: <\/b> 0.5 km<br\/> <b>Track: <\/b> 0.7 km<br\/> <b>FRP: <\/b> 6.37 MW<br\/> <b>Brightness: <\/b> 354.11 K" }, "geometry": { "type": "Point", "coordinates": [ -79.23496, 35.11515, 0.0 ] } },
{ "type": "Feature", "properties": { "Name": "Fire Detection Centroid ", "Description": "<b>Latitude: <\/b> 35.4447<br\/>  <b>Longitude: <\/b> -79.20318<br\/>  <b>Detection Time: <\/b> 2023-01-27 17:22 UTC<br\/>  <b>Sensor: <\/b> NOAA-20 VIIRS<br\/> <b>Confidence: <\/b> Nominal<br\/>  <b>Day\/Night: <\/b> Day<br\/> <b>Scan: <\/b> 0.5 km<br\/> <b>Track: <\/b> 0.7 km<br\/> <b>FRP: <\/b> 2.31 MW<br\/> <b>Brightness: <\/b> 327.14 K" }, "geometry": { "type": "Point", "coordinates": [ -79.20318, 35.4447, 0.0 ] } },
{ "type": "Feature", "properties": { "Name": "Fire Detection Centroid ", "Description": "<b>Latitude: <\/b> 35.44171<br\/>  <b>Longitude: <\/b> -79.20302<br\/>  <b>Detection Time: <\/b> 2023-01-27 17:22 UTC<br\/>  <b>Sensor: <\/b> NOAA-20 VIIRS<br\/> <b>Confidence: <\/b> Nominal<br\/>  <b>Day\/Night: <\/b> Day<br\/> <b>Scan: <\/b> 0.5 km<br\/> <b>Track: <\/b> 0.7 km<br\/> <b>FRP: <\/b> 2.65 MW<br\/> <b>Brightness: <\/b> 330.8 K" }, "geometry": { "type": "Point", "coordinates": [ -79.20302, 35.44171, 0.0 ] } },
{ "type": "Feature", "properties": { "Name": "Fire Detection Centroid ", "Description": "<b>Latitude: <\/b> 34.09518<br\/>  <b>Longitude: <\/b> -78.29875<br\/>  <b>Detection Time: <\/b> 2023-01-27 17:22 UTC<br\/>  <b>Sensor: <\/b> NOAA-20 VIIRS<br\/> <b>Confidence: <\/b> Nominal<br\/>  <b>Day\/Night: <\/b> Day<br\/> <b>Scan: <\/b> 0.5 km<br\/> <b>Track: <\/b> 0.6 km<br\/> <b>FRP: <\/b> 5.71 MW<br\/> <b>Brightness: <\/b> 349.98 K" }, "geometry": { "type": "Point", "coordinates": [ -78.29875, 34.09518, 0.0 ] } },
{ "type": "Feature", "properties": { "Name": "Fire Detection Centroid ", "Description": "<b>Latitude: <\/b> 34.2598<br\/>  <b>Longitude: <\/b> -78.01061<br\/>  <b>Detection Time: <\/b> 2023-01-27 17:22 UTC<br\/>  <b>Sensor: <\/b> NOAA-20 VIIRS<br\/> <b>Confidence: <\/b> Nominal<br\/>  <b>Day\/Night: <\/b> Day<br\/> <b>Scan: <\/b> 0.5 km<br\/> <b>Track: <\/b> 0.6 km<br\/> <b>FRP: <\/b> 4.77 MW<br\/> <b>Brightness: <\/b> 329.45 K" }, "geometry": { "type": "Point", "coordinates": [ -78.01061, 34.2598, 0.0 ] } }
]
}
