{
"type": "FeatureCollection",
"crs": { "type": "name", "properties": { "name": "urn:ogc:def:crs:OGC:1.3:CRS84" } },
"features": [
{ "type": "Feature", "properties": { "Name": "Fire Detection Centroid ", "Description": "<b>Latitude: <\/b> 19.40805<br\/>  <b>Longitude: <\/b> -155.28128<br\/>  <b>Detection Time: <\/b> 2023-07-12 00:09 UTC<br\/>  <b>Sensor: <\/b> NOAA-20 VIIRS<br\/> <b>Confidence: <\/b> Low<br\/>  <b>Day\/Night: <\/b> Day<br\/> <b>Scan: <\/b> 0.34 km<br\/> <b>Track: <\/b> 0.56 km<br\/> <b>FRP: <\/b> 9.3 MW<br\/> <b>Brightness: <\/b> 338.77 K" }, "geometry": { "type": "Point", "coordinates": [ -155.28128, 19.40805, 0.0 ] } }
]
}
