{
"type": "FeatureCollection",
"crs": { "type": "name", "properties": { "name": "urn:ogc:def:crs:OGC:1.3:CRS84" } },
"features": [
{ "type": "Feature", "properties": { "Name": "Fire Detection Centroid ", "Description": "<b>Latitude: <\/b> 18.36011<br\/>  <b>Longitude: <\/b> -71.41723<br\/>  <b>Detection Time: <\/b> 2023-12-08 06:01 UTC<br\/>  <b>Sensor: <\/b> NOAA-20 VIIRS<br\/> <b>Confidence: <\/b> Nominal<br\/>  <b>Day\/Night: <\/b> Night<br\/> <b>Scan: <\/b> 0.4 km<br\/> <b>Track: <\/b> 0.4 km<br\/> <b>FRP: <\/b> 2.48 MW<br\/> <b>Brightness: <\/b> 315.74 K" }, "geometry": { "type": "Point", "coordinates": [ -71.41723, 18.36011, 0.0 ] } },
{ "type": "Feature", "properties": { "Name": "Fire Detection Centroid ", "Description": "<b>Latitude: <\/b> 18.17537<br\/>  <b>Longitude: <\/b> -77.06503<br\/>  <b>Detection Time: <\/b> 2023-12-08 06:01 UTC<br\/>  <b>Sensor: <\/b> NOAA-20 VIIRS<br\/> <b>Confidence: <\/b> Nominal<br\/>  <b>Day\/Night: <\/b> Night<br\/> <b>Scan: <\/b> 0.5 km<br\/> <b>Track: <\/b> 0.6 km<br\/> <b>FRP: <\/b> 1.05 MW<br\/> <b>Brightness: <\/b> 301.67 K" }, "geometry": { "type": "Point", "coordinates": [ -77.06503, 18.17537, 0.0 ] } },
{ "type": "Feature", "properties": { "Name": "Fire Detection Centroid ", "Description": "<b>Latitude: <\/b> 18.00795<br\/>  <b>Longitude: <\/b> -66.65559<br\/>  <b>Detection Time: <\/b> 2023-12-08 06:00 UTC<br\/>  <b>Sensor: <\/b> NOAA-20 VIIRS<br\/> <b>Confidence: <\/b> Nominal<br\/>  <b>Day\/Night: <\/b> Night<br\/> <b>Scan: <\/b> 0.4 km<br\/> <b>Track: <\/b> 0.4 km<br\/> <b>FRP: <\/b> 0.39 MW<br\/> <b>Brightness: <\/b> 305.94 K" }, "geometry": { "type": "Point", "coordinates": [ -66.65559, 18.00795, 0.0 ] } },
{ "type": "Feature", "properties": { "Name": "Fire Detection Centroid ", "Description": "<b>Latitude: <\/b> 36.35945<br\/>  <b>Longitude: <\/b> -76.8092<br\/>  <b>Detection Time: <\/b> 2023-12-08 05:56 UTC<br\/>  <b>Sensor: <\/b> NOAA-20 VIIRS<br\/> <b>Confidence: <\/b> Nominal<br\/>  <b>Day\/Night: <\/b> Night<br\/> <b>Scan: <\/b> 0.7 km<br\/> <b>Track: <\/b> 0.7 km<br\/> <b>FRP: <\/b> 0.77 MW<br\/> <b>Brightness: <\/b> 296.21 K" }, "geometry": { "type": "Point", "coordinates": [ -76.8092, 36.35945, 0.0 ] } },
{ "type": "Feature", "properties": { "Name": "Fire Detection Centroid ", "Description": "<b>Latitude: <\/b> 39.58827<br\/>  <b>Longitude: <\/b> -75.63638<br\/>  <b>Detection Time: <\/b> 2023-12-08 05:55 UTC<br\/>  <b>Sensor: <\/b> NOAA-20 VIIRS<br\/> <b>Confidence: <\/b> Nominal<br\/>  <b>Day\/Night: <\/b> Night<br\/> <b>Scan: <\/b> 0.6 km<br\/> <b>Track: <\/b> 0.7 km<br\/> <b>FRP: <\/b> 1.21 MW<br\/> <b>Brightness: <\/b> 295.45 K" }, "geometry": { "type": "Point", "coordinates": [ -75.63638, 39.58827, 0.0 ] } }
]
}
