{
"type": "FeatureCollection",
"crs": { "type": "name", "properties": { "name": "urn:ogc:def:crs:OGC:1.3:CRS84" } },
"features": [
{ "type": "Feature", "properties": { "Name": "Fire Detection Centroid ", "Description": "<b>Latitude: <\/b> 45.33973<br\/>  <b>Longitude: <\/b> -73.52338<br\/>  <b>Detection Time: <\/b> 2023-10-14 06:25 UTC<br\/>  <b>Sensor: <\/b> NOAA-20 VIIRS<br\/> <b>Confidence: <\/b> Nominal<br\/>  <b>Day\/Night: <\/b> Night<br\/> <b>Scan: <\/b> 0.4 km<br\/> <b>Track: <\/b> 0.4 km<br\/> <b>FRP: <\/b> 0.82 MW<br\/> <b>Brightness: <\/b> 300.05 K" }, "geometry": { "type": "Point", "coordinates": [ -73.52338, 45.33973, 0.0 ] } },
{ "type": "Feature", "properties": { "Name": "Fire Detection Centroid ", "Description": "<b>Latitude: <\/b> 45.11228<br\/>  <b>Longitude: <\/b> -73.01344<br\/>  <b>Detection Time: <\/b> 2023-10-14 06:25 UTC<br\/>  <b>Sensor: <\/b> NOAA-20 VIIRS<br\/> <b>Confidence: <\/b> Nominal<br\/>  <b>Day\/Night: <\/b> Night<br\/> <b>Scan: <\/b> 0.4 km<br\/> <b>Track: <\/b> 0.4 km<br\/> <b>FRP: <\/b> 1.18 MW<br\/> <b>Brightness: <\/b> 295.34 K" }, "geometry": { "type": "Point", "coordinates": [ -73.01344, 45.11228, 0.0 ] } },
{ "type": "Feature", "properties": { "Name": "Fire Detection Centroid ", "Description": "<b>Latitude: <\/b> 46.04594<br\/>  <b>Longitude: <\/b> -73.14532<br\/>  <b>Detection Time: <\/b> 2023-10-14 06:24 UTC<br\/>  <b>Sensor: <\/b> NOAA-20 VIIRS<br\/> <b>Confidence: <\/b> Nominal<br\/>  <b>Day\/Night: <\/b> Night<br\/> <b>Scan: <\/b> 0.4 km<br\/> <b>Track: <\/b> 0.4 km<br\/> <b>FRP: <\/b> 0.98 MW<br\/> <b>Brightness: <\/b> 300.51 K" }, "geometry": { "type": "Point", "coordinates": [ -73.14532, 46.04594, 0.0 ] } },
{ "type": "Feature", "properties": { "Name": "Fire Detection Centroid ", "Description": "<b>Latitude: <\/b> 45.64331<br\/>  <b>Longitude: <\/b> -73.52357<br\/>  <b>Detection Time: <\/b> 2023-10-14 06:24 UTC<br\/>  <b>Sensor: <\/b> NOAA-20 VIIRS<br\/> <b>Confidence: <\/b> Nominal<br\/>  <b>Day\/Night: <\/b> Night<br\/> <b>Scan: <\/b> 0.4 km<br\/> <b>Track: <\/b> 0.4 km<br\/> <b>FRP: <\/b> 0.8 MW<br\/> <b>Brightness: <\/b> 296.62 K" }, "geometry": { "type": "Point", "coordinates": [ -73.52357, 45.64331, 0.0 ] } },
{ "type": "Feature", "properties": { "Name": "Fire Detection Centroid ", "Description": "<b>Latitude: <\/b> 45.83731<br\/>  <b>Longitude: <\/b> -73.24986<br\/>  <b>Detection Time: <\/b> 2023-10-14 06:24 UTC<br\/>  <b>Sensor: <\/b> NOAA-20 VIIRS<br\/> <b>Confidence: <\/b> Nominal<br\/>  <b>Day\/Night: <\/b> Night<br\/> <b>Scan: <\/b> 0.4 km<br\/> <b>Track: <\/b> 0.4 km<br\/> <b>FRP: <\/b> 1.04 MW<br\/> <b>Brightness: <\/b> 304.43 K" }, "geometry": { "type": "Point", "coordinates": [ -73.24986, 45.83731, 0.0 ] } },
{ "type": "Feature", "properties": { "Name": "Fire Detection Centroid ", "Description": "<b>Latitude: <\/b> 46.52005<br\/>  <b>Longitude: <\/b> -84.37602<br\/>  <b>Detection Time: <\/b> 2023-10-14 06:24 UTC<br\/>  <b>Sensor: <\/b> NOAA-20 VIIRS<br\/> <b>Confidence: <\/b> Nominal<br\/>  <b>Day\/Night: <\/b> Night<br\/> <b>Scan: <\/b> 0.7 km<br\/> <b>Track: <\/b> 0.7 km<br\/> <b>FRP: <\/b> 2.6 MW<br\/> <b>Brightness: <\/b> 311.13 K" }, "geometry": { "type": "Point", "coordinates": [ -84.37602, 46.52005, 0.0 ] } },
{ "type": "Feature", "properties": { "Name": "Fire Detection Centroid ", "Description": "<b>Latitude: <\/b> 46.04548<br\/>  <b>Longitude: <\/b> -73.14011<br\/>  <b>Detection Time: <\/b> 2023-10-14 06:24 UTC<br\/>  <b>Sensor: <\/b> NOAA-20 VIIRS<br\/> <b>Confidence: <\/b> Nominal<br\/>  <b>Day\/Night: <\/b> Night<br\/> <b>Scan: <\/b> 0.4 km<br\/> <b>Track: <\/b> 0.4 km<br\/> <b>FRP: <\/b> 0.98 MW<br\/> <b>Brightness: <\/b> 302 K" }, "geometry": { "type": "Point", "coordinates": [ -73.14011, 46.04548, 0.0 ] } },
{ "type": "Feature", "properties": { "Name": "Fire Detection Centroid ", "Description": "<b>Latitude: <\/b> 46.51995<br\/>  <b>Longitude: <\/b> -84.38536<br\/>  <b>Detection Time: <\/b> 2023-10-14 06:24 UTC<br\/>  <b>Sensor: <\/b> NOAA-20 VIIRS<br\/> <b>Confidence: <\/b> Nominal<br\/>  <b>Day\/Night: <\/b> Night<br\/> <b>Scan: <\/b> 0.7 km<br\/> <b>Track: <\/b> 0.7 km<br\/> <b>FRP: <\/b> 2.6 MW<br\/> <b>Brightness: <\/b> 305.01 K" }, "geometry": { "type": "Point", "coordinates": [ -84.38536, 46.51995, 0.0 ] } }
]
}
