{
"type": "FeatureCollection",
"crs": { "type": "name", "properties": { "name": "urn:ogc:def:crs:OGC:1.3:CRS84" } },
"features": [
{ "type": "Feature", "properties": { "Name": "Fire Detection Centroid ", "Description": "<b>Latitude: <\/b> 18.92793<br\/>  <b>Longitude: <\/b> -70.35638<br\/>  <b>Detection Time: <\/b> 2022-08-17 05:22 UTC<br\/>  <b>Sensor: <\/b> NOAA-20 VIIRS<br\/> <b>Confidence: <\/b> Nominal<br\/>  <b>Day\/Night: <\/b> Night<br\/> <b>Scan: <\/b> 0.7 km<br\/> <b>Track: <\/b> 0.8 km<br\/> <b>FRP: <\/b> 0.95 MW<br\/> <b>Brightness: <\/b> 300.37 K" }, "geometry": { "type": "Point", "coordinates": [ -70.35638, 18.92793, 0.0 ] } },
{ "type": "Feature", "properties": { "Name": "Fire Detection Centroid ", "Description": "<b>Latitude: <\/b> 18.92851<br\/>  <b>Longitude: <\/b> -70.36338<br\/>  <b>Detection Time: <\/b> 2022-08-17 05:22 UTC<br\/>  <b>Sensor: <\/b> NOAA-20 VIIRS<br\/> <b>Confidence: <\/b> Nominal<br\/>  <b>Day\/Night: <\/b> Night<br\/> <b>Scan: <\/b> 0.7 km<br\/> <b>Track: <\/b> 0.8 km<br\/> <b>FRP: <\/b> 0.95 MW<br\/> <b>Brightness: <\/b> 295.33 K" }, "geometry": { "type": "Point", "coordinates": [ -70.36338, 18.92851, 0.0 ] } },
{ "type": "Feature", "properties": { "Name": "Fire Detection Centroid ", "Description": "<b>Latitude: <\/b> 18.9334<br\/>  <b>Longitude: <\/b> -70.36241<br\/>  <b>Detection Time: <\/b> 2022-08-17 05:22 UTC<br\/>  <b>Sensor: <\/b> NOAA-20 VIIRS<br\/> <b>Confidence: <\/b> Nominal<br\/>  <b>Day\/Night: <\/b> Night<br\/> <b>Scan: <\/b> 0.7 km<br\/> <b>Track: <\/b> 0.8 km<br\/> <b>FRP: <\/b> 1.35 MW<br\/> <b>Brightness: <\/b> 296.68 K" }, "geometry": { "type": "Point", "coordinates": [ -70.36241, 18.9334, 0.0 ] } },
{ "type": "Feature", "properties": { "Name": "Fire Detection Centroid ", "Description": "<b>Latitude: <\/b> 18.93287<br\/>  <b>Longitude: <\/b> -70.35554<br\/>  <b>Detection Time: <\/b> 2022-08-17 05:22 UTC<br\/>  <b>Sensor: <\/b> NOAA-20 VIIRS<br\/> <b>Confidence: <\/b> Nominal<br\/>  <b>Day\/Night: <\/b> Night<br\/> <b>Scan: <\/b> 0.7 km<br\/> <b>Track: <\/b> 0.8 km<br\/> <b>FRP: <\/b> 1.13 MW<br\/> <b>Brightness: <\/b> 296.18 K" }, "geometry": { "type": "Point", "coordinates": [ -70.35554, 18.93287, 0.0 ] } }
]
}
