{
"type": "FeatureCollection",
"crs": { "type": "name", "properties": { "name": "urn:ogc:def:crs:OGC:1.3:CRS84" } },
"features": [
{ "type": "Feature", "properties": { "Name": "Fire Detection Centroid ", "Description": "<b>Latitude: <\/b> 19.40275<br\/>  <b>Longitude: <\/b> -155.28612<br\/>  <b>Detection Time: <\/b> 2022-10-26 23:06 UTC<br\/>  <b>Sensor: <\/b> NOAA-20 VIIRS<br\/> <b>Confidence: <\/b> Low<br\/>  <b>Day\/Night: <\/b> Day<br\/> <b>Scan: <\/b> 0.5 km<br\/> <b>Track: <\/b> 0.5 km<br\/> <b>FRP: <\/b> 43.68 MW<br\/> <b>Brightness: <\/b> 299.28 K" }, "geometry": { "type": "Point", "coordinates": [ -155.28612, 19.40275, 0.0 ] } },
{ "type": "Feature", "properties": { "Name": "Fire Detection Centroid ", "Description": "<b>Latitude: <\/b> 19.4036<br\/>  <b>Longitude: <\/b> -155.28159<br\/>  <b>Detection Time: <\/b> 2022-10-26 23:06 UTC<br\/>  <b>Sensor: <\/b> NOAA-20 VIIRS<br\/> <b>Confidence: <\/b> Nominal<br\/>  <b>Day\/Night: <\/b> Day<br\/> <b>Scan: <\/b> 0.5 km<br\/> <b>Track: <\/b> 0.5 km<br\/> <b>FRP: <\/b> 43.68 MW<br\/> <b>Brightness: <\/b> 348.45 K" }, "geometry": { "type": "Point", "coordinates": [ -155.28159, 19.4036, 0.0 ] } },
{ "type": "Feature", "properties": { "Name": "Fire Detection Centroid ", "Description": "<b>Latitude: <\/b> 19.40714<br\/>  <b>Longitude: <\/b> -155.28694<br\/>  <b>Detection Time: <\/b> 2022-10-26 23:06 UTC<br\/>  <b>Sensor: <\/b> NOAA-20 VIIRS<br\/> <b>Confidence: <\/b> Nominal<br\/>  <b>Day\/Night: <\/b> Day<br\/> <b>Scan: <\/b> 0.5 km<br\/> <b>Track: <\/b> 0.5 km<br\/> <b>FRP: <\/b> 43.68 MW<br\/> <b>Brightness: <\/b> 341.55 K" }, "geometry": { "type": "Point", "coordinates": [ -155.28694, 19.40714, 0.0 ] } },
{ "type": "Feature", "properties": { "Name": "Fire Detection Centroid ", "Description": "<b>Latitude: <\/b> 19.408<br\/>  <b>Longitude: <\/b> -155.28249<br\/>  <b>Detection Time: <\/b> 2022-10-26 23:06 UTC<br\/>  <b>Sensor: <\/b> NOAA-20 VIIRS<br\/> <b>Confidence: <\/b> Nominal<br\/>  <b>Day\/Night: <\/b> Day<br\/> <b>Scan: <\/b> 0.5 km<br\/> <b>Track: <\/b> 0.5 km<br\/> <b>FRP: <\/b> 43.68 MW<br\/> <b>Brightness: <\/b> 346.71 K" }, "geometry": { "type": "Point", "coordinates": [ -155.28249, 19.408, 0.0 ] } },
{ "type": "Feature", "properties": { "Name": "Fire Detection Centroid ", "Description": "<b>Latitude: <\/b> 19.40415<br\/>  <b>Longitude: <\/b> -155.28082<br\/>  <b>Detection Time: <\/b> 2022-10-26 23:05 UTC<br\/>  <b>Sensor: <\/b> NOAA-20 VIIRS<br\/> <b>Confidence: <\/b> Nominal<br\/>  <b>Day\/Night: <\/b> Day<br\/> <b>Scan: <\/b> 0.49 km<br\/> <b>Track: <\/b> 0.48 km<br\/> <b>FRP: <\/b> 43.69 MW<br\/> <b>Brightness: <\/b> 348.45 K" }, "geometry": { "type": "Point", "coordinates": [ -155.28082, 19.40415, 0.0 ] } },
{ "type": "Feature", "properties": { "Name": "Fire Detection Centroid ", "Description": "<b>Latitude: <\/b> 19.40328<br\/>  <b>Longitude: <\/b> -155.28537<br\/>  <b>Detection Time: <\/b> 2022-10-26 23:05 UTC<br\/>  <b>Sensor: <\/b> NOAA-20 VIIRS<br\/> <b>Confidence: <\/b> Low<br\/>  <b>Day\/Night: <\/b> Day<br\/> <b>Scan: <\/b> 0.49 km<br\/> <b>Track: <\/b> 0.49 km<br\/> <b>FRP: <\/b> 43.69 MW<br\/> <b>Brightness: <\/b> 299.28 K" }, "geometry": { "type": "Point", "coordinates": [ -155.28537, 19.40328, 0.0 ] } },
{ "type": "Feature", "properties": { "Name": "Fire Detection Centroid ", "Description": "<b>Latitude: <\/b> 19.40769<br\/>  <b>Longitude: <\/b> -155.28619<br\/>  <b>Detection Time: <\/b> 2022-10-26 23:05 UTC<br\/>  <b>Sensor: <\/b> NOAA-20 VIIRS<br\/> <b>Confidence: <\/b> Nominal<br\/>  <b>Day\/Night: <\/b> Day<br\/> <b>Scan: <\/b> 0.49 km<br\/> <b>Track: <\/b> 0.49 km<br\/> <b>FRP: <\/b> 43.69 MW<br\/> <b>Brightness: <\/b> 341.55 K" }, "geometry": { "type": "Point", "coordinates": [ -155.28619, 19.40769, 0.0 ] } },
{ "type": "Feature", "properties": { "Name": "Fire Detection Centroid ", "Description": "<b>Latitude: <\/b> 19.40854<br\/>  <b>Longitude: <\/b> -155.28171<br\/>  <b>Detection Time: <\/b> 2022-10-26 23:05 UTC<br\/>  <b>Sensor: <\/b> NOAA-20 VIIRS<br\/> <b>Confidence: <\/b> Nominal<br\/>  <b>Day\/Night: <\/b> Day<br\/> <b>Scan: <\/b> 0.49 km<br\/> <b>Track: <\/b> 0.48 km<br\/> <b>FRP: <\/b> 43.69 MW<br\/> <b>Brightness: <\/b> 346.71 K" }, "geometry": { "type": "Point", "coordinates": [ -155.28171, 19.40854, 0.0 ] } }
]
}
