{
"type": "FeatureCollection",
"crs": { "type": "name", "properties": { "name": "urn:ogc:def:crs:OGC:1.3:CRS84" } },
"features": [
{ "type": "Feature", "properties": { "Name": "Fire Detection Centroid ", "Description": "<b>Latitude: <\/b> 34.15089<br\/>  <b>Longitude: <\/b> -77.85143<br\/>  <b>Detection Time: <\/b> 2022-11-13 17:28 UTC<br\/>  <b>Sensor: <\/b> NOAA-20 VIIRS<br\/> <b>Confidence: <\/b> Nominal<br\/>  <b>Day\/Night: <\/b> Day<br\/> <b>Scan: <\/b> 0.4 km<br\/> <b>Track: <\/b> 0.6 km<br\/> <b>FRP: <\/b> 2.77 MW<br\/> <b>Brightness: <\/b> 339.34 K" }, "geometry": { "type": "Point", "coordinates": [ -77.85143, 34.15089, 0.0 ] } }
]
}
