{
"type": "FeatureCollection",
"crs": { "type": "name", "properties": { "name": "urn:ogc:def:crs:OGC:1.3:CRS84" } },
"features": [
{ "type": "Feature", "properties": { "Name": "Fire Detection Centroid ", "Description": "<b>Latitude: <\/b> 45.60643<br\/>  <b>Longitude: <\/b> -118.66962<br\/>  <b>Detection Time: <\/b> 2024-04-23 11:04 UTC<br\/>  <b>Sensor: <\/b> NOAA-20 VIIRS<br\/> <b>Confidence: <\/b> Nominal<br\/>  <b>Day\/Night: <\/b> Night<br\/> <b>Scan: <\/b> 0.6 km<br\/> <b>Track: <\/b> 0.7 km<br\/> <b>FRP: <\/b> 0.94 MW<br\/> <b>Brightness: <\/b> 295.09 K" }, "geometry": { "type": "Point", "coordinates": [ -118.66962, 45.60643, 0.0 ] } },
{ "type": "Feature", "properties": { "Name": "Fire Detection Centroid ", "Description": "<b>Latitude: <\/b> 49.22724<br\/>  <b>Longitude: <\/b> -123.74142<br\/>  <b>Detection Time: <\/b> 2024-04-23 11:03 UTC<br\/>  <b>Sensor: <\/b> NOAA-20 VIIRS<br\/> <b>Confidence: <\/b> Nominal<br\/>  <b>Day\/Night: <\/b> Night<br\/> <b>Scan: <\/b> 0.5 km<br\/> <b>Track: <\/b> 0.5 km<br\/> <b>FRP: <\/b> 0.47 MW<br\/> <b>Brightness: <\/b> 295.83 K" }, "geometry": { "type": "Point", "coordinates": [ -123.74142, 49.22724, 0.0 ] } },
{ "type": "Feature", "properties": { "Name": "Fire Detection Centroid ", "Description": "<b>Latitude: <\/b> 49.22724<br\/>  <b>Longitude: <\/b> -123.74142<br\/>  <b>Detection Time: <\/b> 2024-04-23 11:03 UTC<br\/>  <b>Sensor: <\/b> NOAA-20 VIIRS<br\/> <b>Confidence: <\/b> Nominal<br\/>  <b>Day\/Night: <\/b> Night<br\/> <b>Scan: <\/b> 0.5 km<br\/> <b>Track: <\/b> 0.5 km<br\/> <b>FRP: <\/b> 0.47 MW<br\/> <b>Brightness: <\/b> 295.83 K" }, "geometry": { "type": "Point", "coordinates": [ -123.74142, 49.22724, 0.0 ] } }
]
}
