{
"type": "FeatureCollection",
"crs": { "type": "name", "properties": { "name": "urn:ogc:def:crs:OGC:1.3:CRS84" } },
"features": [
{ "type": "Feature", "properties": { "Name": "Fire Detection Centroid ", "Description": "<b>Latitude: <\/b> 20.8599<br\/>  <b>Longitude: <\/b> -156.42146<br\/>  <b>Detection Time: <\/b> 2024-05-27 12:14 UTC<br\/>  <b>Sensor: <\/b> NOAA-20 VIIRS<br\/> <b>Confidence: <\/b> Nominal<br\/>  <b>Day\/Night: <\/b> Night<br\/> <b>Scan: <\/b> 0.44 km<br\/> <b>Track: <\/b> 0.38 km<br\/> <b>FRP: <\/b> 0.49 MW<br\/> <b>Brightness: <\/b> 302.69 K" }, "geometry": { "type": "Point", "coordinates": [ -156.42146, 20.8599, 0.0 ] } }
]
}
