{
"type": "FeatureCollection",
"crs": { "type": "name", "properties": { "name": "urn:ogc:def:crs:OGC:1.3:CRS84" } },
"features": [
{ "type": "Feature", "properties": { "Name": "Fire Detection Centroid ", "Description": "<b>Latitude: <\/b> 21.45817<br\/>  <b>Longitude: <\/b> -158.18933<br\/>  <b>Detection Time: <\/b> 2023-05-09 23:52 UTC<br\/>  <b>Sensor: <\/b> NOAA-20 VIIRS<br\/> <b>Confidence: <\/b> Nominal<br\/>  <b>Day\/Night: <\/b> Day<br\/> <b>Scan: <\/b> 0.41 km<br\/> <b>Track: <\/b> 0.37 km<br\/> <b>FRP: <\/b> 2.48 MW<br\/> <b>Brightness: <\/b> 337.67 K" }, "geometry": { "type": "Point", "coordinates": [ -158.18933, 21.45817, 0.0 ] } },
{ "type": "Feature", "properties": { "Name": "Fire Detection Centroid ", "Description": "<b>Latitude: <\/b> 21.44855<br\/>  <b>Longitude: <\/b> -157.98685<br\/>  <b>Detection Time: <\/b> 2023-05-09 23:52 UTC<br\/>  <b>Sensor: <\/b> NOAA-20 VIIRS<br\/> <b>Confidence: <\/b> Nominal<br\/>  <b>Day\/Night: <\/b> Day<br\/> <b>Scan: <\/b> 0.41 km<br\/> <b>Track: <\/b> 0.37 km<br\/> <b>FRP: <\/b> 3.52 MW<br\/> <b>Brightness: <\/b> 337.19 K" }, "geometry": { "type": "Point", "coordinates": [ -157.98685, 21.44855, 0.0 ] } },
{ "type": "Feature", "properties": { "Name": "Fire Detection Centroid ", "Description": "<b>Latitude: <\/b> 21.41288<br\/>  <b>Longitude: <\/b> -158.01735<br\/>  <b>Detection Time: <\/b> 2023-05-09 23:52 UTC<br\/>  <b>Sensor: <\/b> NOAA-20 VIIRS<br\/> <b>Confidence: <\/b> Nominal<br\/>  <b>Day\/Night: <\/b> Day<br\/> <b>Scan: <\/b> 0.41 km<br\/> <b>Track: <\/b> 0.37 km<br\/> <b>FRP: <\/b> 3.45 MW<br\/> <b>Brightness: <\/b> 334.27 K" }, "geometry": { "type": "Point", "coordinates": [ -158.01735, 21.41288, 0.0 ] } },
{ "type": "Feature", "properties": { "Name": "Fire Detection Centroid ", "Description": "<b>Latitude: <\/b> 38.91327<br\/>  <b>Longitude: <\/b> -122.06901<br\/>  <b>Detection Time: <\/b> 2023-05-09 22:16 UTC<br\/>  <b>Sensor: <\/b> NOAA-20 VIIRS<br\/> <b>Confidence: <\/b> Nominal<br\/>  <b>Day\/Night: <\/b> Day<br\/> <b>Scan: <\/b> 0.77 km<br\/> <b>Track: <\/b> 0.77 km<br\/> <b>FRP: <\/b> 25.48 MW<br\/> <b>Brightness: <\/b> 356.12 K" }, "geometry": { "type": "Point", "coordinates": [ -122.06901, 38.91327, 0.0 ] } },
{ "type": "Feature", "properties": { "Name": "Fire Detection Centroid ", "Description": "<b>Latitude: <\/b> 38.90818<br\/>  <b>Longitude: <\/b> -122.06894<br\/>  <b>Detection Time: <\/b> 2023-05-09 22:16 UTC<br\/>  <b>Sensor: <\/b> NOAA-20 VIIRS<br\/> <b>Confidence: <\/b> Nominal<br\/>  <b>Day\/Night: <\/b> Day<br\/> <b>Scan: <\/b> 0.77 km<br\/> <b>Track: <\/b> 0.77 km<br\/> <b>FRP: <\/b> 14.12 MW<br\/> <b>Brightness: <\/b> 341.25 K" }, "geometry": { "type": "Point", "coordinates": [ -122.06894, 38.90818, 0.0 ] } },
{ "type": "Feature", "properties": { "Name": "Fire Detection Centroid ", "Description": "<b>Latitude: <\/b> 38.91537<br\/>  <b>Longitude: <\/b> -122.06894<br\/>  <b>Detection Time: <\/b> 2023-05-09 22:16 UTC<br\/>  <b>Sensor: <\/b> NOAA-20 VIIRS<br\/> <b>Confidence: <\/b> Low<br\/>  <b>Day\/Night: <\/b> Day<br\/> <b>Scan: <\/b> 0.77 km<br\/> <b>Track: <\/b> 0.77 km<br\/> <b>FRP: <\/b> 14.12 MW<br\/> <b>Brightness: <\/b> 356.06 K" }, "geometry": { "type": "Point", "coordinates": [ -122.06894, 38.91537, 0.0 ] } },
{ "type": "Feature", "properties": { "Name": "Fire Detection Centroid ", "Description": "<b>Latitude: <\/b> 39.64191<br\/>  <b>Longitude: <\/b> -122.00031<br\/>  <b>Detection Time: <\/b> 2023-05-09 22:16 UTC<br\/>  <b>Sensor: <\/b> NOAA-20 VIIRS<br\/> <b>Confidence: <\/b> Nominal<br\/>  <b>Day\/Night: <\/b> Day<br\/> <b>Scan: <\/b> 0.78 km<br\/> <b>Track: <\/b> 0.78 km<br\/> <b>FRP: <\/b> 3.7 MW<br\/> <b>Brightness: <\/b> 325.31 K" }, "geometry": { "type": "Point", "coordinates": [ -122.00031, 39.64191, 0.0 ] } },
{ "type": "Feature", "properties": { "Name": "Fire Detection Centroid ", "Description": "<b>Latitude: <\/b> 39.86393<br\/>  <b>Longitude: <\/b> -121.97725<br\/>  <b>Detection Time: <\/b> 2023-05-09 22:16 UTC<br\/>  <b>Sensor: <\/b> NOAA-20 VIIRS<br\/> <b>Confidence: <\/b> Nominal<br\/>  <b>Day\/Night: <\/b> Day<br\/> <b>Scan: <\/b> 0.78 km<br\/> <b>Track: <\/b> 0.78 km<br\/> <b>FRP: <\/b> 10.41 MW<br\/> <b>Brightness: <\/b> 337.65 K" }, "geometry": { "type": "Point", "coordinates": [ -121.97725, 39.86393, 0.0 ] } }
]
}
