{
"type": "FeatureCollection",
"crs": { "type": "name", "properties": { "name": "urn:ogc:def:crs:OGC:1.3:CRS84" } },
"features": [
{ "type": "Feature", "properties": { "Name": "Fire Detection Centroid ", "Description": "<b>Latitude: <\/b> 19.41134<br\/>  <b>Longitude: <\/b> -155.28592<br\/>  <b>Detection Time: <\/b> 2023-11-19 12:01 UTC<br\/>  <b>Sensor: <\/b> NOAA-20 VIIRS<br\/> <b>Confidence: <\/b> Nominal<br\/>  <b>Day\/Night: <\/b> Night<br\/> <b>Scan: <\/b> 0.39 km<br\/> <b>Track: <\/b> 0.36 km<br\/> <b>FRP: <\/b> 1.25 MW<br\/> <b>Brightness: <\/b> 303.75 K" }, "geometry": { "type": "Point", "coordinates": [ -155.28592, 19.41134, 0.0 ] } },
{ "type": "Feature", "properties": { "Name": "Fire Detection Centroid ", "Description": "<b>Latitude: <\/b> 19.40413<br\/>  <b>Longitude: <\/b> -155.2834<br\/>  <b>Detection Time: <\/b> 2023-11-19 12:01 UTC<br\/>  <b>Sensor: <\/b> NOAA-20 VIIRS<br\/> <b>Confidence: <\/b> Nominal<br\/>  <b>Day\/Night: <\/b> Night<br\/> <b>Scan: <\/b> 0.39 km<br\/> <b>Track: <\/b> 0.36 km<br\/> <b>FRP: <\/b> 1.94 MW<br\/> <b>Brightness: <\/b> 308.54 K" }, "geometry": { "type": "Point", "coordinates": [ -155.2834, 19.40413, 0.0 ] } },
{ "type": "Feature", "properties": { "Name": "Fire Detection Centroid ", "Description": "<b>Latitude: <\/b> 19.40744<br\/>  <b>Longitude: <\/b> -155.28282<br\/>  <b>Detection Time: <\/b> 2023-11-19 12:01 UTC<br\/>  <b>Sensor: <\/b> NOAA-20 VIIRS<br\/> <b>Confidence: <\/b> Nominal<br\/>  <b>Day\/Night: <\/b> Night<br\/> <b>Scan: <\/b> 0.39 km<br\/> <b>Track: <\/b> 0.36 km<br\/> <b>FRP: <\/b> 1.25 MW<br\/> <b>Brightness: <\/b> 301.84 K" }, "geometry": { "type": "Point", "coordinates": [ -155.28282, 19.40744, 0.0 ] } },
{ "type": "Feature", "properties": { "Name": "Fire Detection Centroid ", "Description": "<b>Latitude: <\/b> 19.40803<br\/>  <b>Longitude: <\/b> -155.2865<br\/>  <b>Detection Time: <\/b> 2023-11-19 12:01 UTC<br\/>  <b>Sensor: <\/b> NOAA-20 VIIRS<br\/> <b>Confidence: <\/b> Nominal<br\/>  <b>Day\/Night: <\/b> Night<br\/> <b>Scan: <\/b> 0.39 km<br\/> <b>Track: <\/b> 0.36 km<br\/> <b>FRP: <\/b> 1.25 MW<br\/> <b>Brightness: <\/b> 301.66 K" }, "geometry": { "type": "Point", "coordinates": [ -155.2865, 19.40803, 0.0 ] } }
]
}
