{
"type": "FeatureCollection",
"crs": { "type": "name", "properties": { "name": "urn:ogc:def:crs:OGC:1.3:CRS84" } },
"features": [
{ "type": "Feature", "properties": { "Name": "Fire Detection Centroid ", "Description": "<b>Latitude: <\/b> 39.82815<br\/>  <b>Longitude: <\/b> -122.0443<br\/>  <b>Detection Time: <\/b> 2023-06-10 22:16 UTC<br\/>  <b>Sensor: <\/b> NOAA-20 VIIRS<br\/> <b>Confidence: <\/b> Nominal<br\/>  <b>Day\/Night: <\/b> Day<br\/> <b>Scan: <\/b> 0.77 km<br\/> <b>Track: <\/b> 0.77 km<br\/> <b>FRP: <\/b> 4.44 MW<br\/> <b>Brightness: <\/b> 329.33 K" }, "geometry": { "type": "Point", "coordinates": [ -122.0443, 39.82815, 0.0 ] } }
]
}
