{
"type": "FeatureCollection",
"crs": { "type": "name", "properties": { "name": "urn:ogc:def:crs:OGC:1.3:CRS84" } },
"features": [
{ "type": "Feature", "properties": { "Name": "Fire Detection Centroid ", "Description": "<b>Latitude: <\/b> 38.50973<br\/>  <b>Longitude: <\/b> -122.52824<br\/>  <b>Detection Time: <\/b> 2023-03-01 10:47 UTC<br\/>  <b>Sensor: <\/b> NOAA-20 VIIRS<br\/> <b>Confidence: <\/b> Nominal<br\/>  <b>Day\/Night: <\/b> Night<br\/> <b>Scan: <\/b> 0.33 km<br\/> <b>Track: <\/b> 0.55 km<br\/> <b>FRP: <\/b> 0.92 MW<br\/> <b>Brightness: <\/b> 304.15 K" }, "geometry": { "type": "Point", "coordinates": [ -122.52824, 38.50973, 0.0 ] } },
{ "type": "Feature", "properties": { "Name": "Fire Detection Centroid ", "Description": "<b>Latitude: <\/b> 38.07232<br\/>  <b>Longitude: <\/b> -122.13734<br\/>  <b>Detection Time: <\/b> 2023-03-01 10:47 UTC<br\/>  <b>Sensor: <\/b> NOAA-20 VIIRS<br\/> <b>Confidence: <\/b> Nominal<br\/>  <b>Day\/Night: <\/b> Night<br\/> <b>Scan: <\/b> 0.35 km<br\/> <b>Track: <\/b> 0.57 km<br\/> <b>FRP: <\/b> 1.22 MW<br\/> <b>Brightness: <\/b> 296.61 K" }, "geometry": { "type": "Point", "coordinates": [ -122.13734, 38.07232, 0.0 ] } },
{ "type": "Feature", "properties": { "Name": "Fire Detection Centroid ", "Description": "<b>Latitude: <\/b> 38.01625<br\/>  <b>Longitude: <\/b> -122.11382<br\/>  <b>Detection Time: <\/b> 2023-03-01 10:47 UTC<br\/>  <b>Sensor: <\/b> NOAA-20 VIIRS<br\/> <b>Confidence: <\/b> Nominal<br\/>  <b>Day\/Night: <\/b> Night<br\/> <b>Scan: <\/b> 0.35 km<br\/> <b>Track: <\/b> 0.57 km<br\/> <b>FRP: <\/b> 0.54 MW<br\/> <b>Brightness: <\/b> 296.27 K" }, "geometry": { "type": "Point", "coordinates": [ -122.11382, 38.01625, 0.0 ] } },
{ "type": "Feature", "properties": { "Name": "Fire Detection Centroid ", "Description": "<b>Latitude: <\/b> 38.51665<br\/>  <b>Longitude: <\/b> -122.53439<br\/>  <b>Detection Time: <\/b> 2023-03-01 10:47 UTC<br\/>  <b>Sensor: <\/b> NOAA-20 VIIRS<br\/> <b>Confidence: <\/b> Nominal<br\/>  <b>Day\/Night: <\/b> Night<br\/> <b>Scan: <\/b> 0.33 km<br\/> <b>Track: <\/b> 0.55 km<br\/> <b>FRP: <\/b> 1.63 MW<br\/> <b>Brightness: <\/b> 315.99 K" }, "geometry": { "type": "Point", "coordinates": [ -122.53439, 38.51665, 0.0 ] } },
{ "type": "Feature", "properties": { "Name": "Fire Detection Centroid ", "Description": "<b>Latitude: <\/b> 45.22868<br\/>  <b>Longitude: <\/b> -123.16645<br\/>  <b>Detection Time: <\/b> 2023-03-01 10:45 UTC<br\/>  <b>Sensor: <\/b> NOAA-20 VIIRS<br\/> <b>Confidence: <\/b> Nominal<br\/>  <b>Day\/Night: <\/b> Night<br\/> <b>Scan: <\/b> 0.42 km<br\/> <b>Track: <\/b> 0.45 km<br\/> <b>FRP: <\/b> 3.13 MW<br\/> <b>Brightness: <\/b> 324.7 K" }, "geometry": { "type": "Point", "coordinates": [ -123.16645, 45.22868, 0.0 ] } },
{ "type": "Feature", "properties": { "Name": "Fire Detection Centroid ", "Description": "<b>Latitude: <\/b> 45.23082<br\/>  <b>Longitude: <\/b> -123.16312<br\/>  <b>Detection Time: <\/b> 2023-03-01 10:45 UTC<br\/>  <b>Sensor: <\/b> NOAA-20 VIIRS<br\/> <b>Confidence: <\/b> Nominal<br\/>  <b>Day\/Night: <\/b> Night<br\/> <b>Scan: <\/b> 0.42 km<br\/> <b>Track: <\/b> 0.45 km<br\/> <b>FRP: <\/b> 3.3 MW<br\/> <b>Brightness: <\/b> 321.22 K" }, "geometry": { "type": "Point", "coordinates": [ -123.16312, 45.23082, 0.0 ] } }
]
}
