{
"type": "FeatureCollection",
"crs": { "type": "name", "properties": { "name": "urn:ogc:def:crs:OGC:1.3:CRS84" } },
"features": [
{ "type": "Feature", "properties": { "Name": "Fire Detection Centroid ", "Description": "<b>Latitude: <\/b> 36.43773<br\/>  <b>Longitude: <\/b> -120.9469<br\/>  <b>Detection Time: <\/b> 2023-12-27 21:25 UTC<br\/>  <b>Sensor: <\/b> NOAA-20 VIIRS<br\/> <b>Confidence: <\/b> Nominal<br\/>  <b>Day\/Night: <\/b> Day<br\/> <b>Scan: <\/b> 0.52 km<br\/> <b>Track: <\/b> 0.42 km<br\/> <b>FRP: <\/b> 2.29 MW<br\/> <b>Brightness: <\/b> 325.06 K" }, "geometry": { "type": "Point", "coordinates": [ -120.9469, 36.43773, 0.0 ] } },
{ "type": "Feature", "properties": { "Name": "Fire Detection Centroid ", "Description": "<b>Latitude: <\/b> 37.8531<br\/>  <b>Longitude: <\/b> -119.85993<br\/>  <b>Detection Time: <\/b> 2023-12-27 21:25 UTC<br\/>  <b>Sensor: <\/b> NOAA-20 VIIRS<br\/> <b>Confidence: <\/b> Nominal<br\/>  <b>Day\/Night: <\/b> Day<br\/> <b>Scan: <\/b> 0.41 km<br\/> <b>Track: <\/b> 0.45 km<br\/> <b>FRP: <\/b> 4.72 MW<br\/> <b>Brightness: <\/b> 338.34 K" }, "geometry": { "type": "Point", "coordinates": [ -119.85993, 37.8531, 0.0 ] } },
{ "type": "Feature", "properties": { "Name": "Fire Detection Centroid ", "Description": "<b>Latitude: <\/b> 37.849<br\/>  <b>Longitude: <\/b> -119.85934<br\/>  <b>Detection Time: <\/b> 2023-12-27 21:25 UTC<br\/>  <b>Sensor: <\/b> NOAA-20 VIIRS<br\/> <b>Confidence: <\/b> Nominal<br\/>  <b>Day\/Night: <\/b> Day<br\/> <b>Scan: <\/b> 0.41 km<br\/> <b>Track: <\/b> 0.45 km<br\/> <b>FRP: <\/b> 4.72 MW<br\/> <b>Brightness: <\/b> 334.35 K" }, "geometry": { "type": "Point", "coordinates": [ -119.85934, 37.849, 0.0 ] } },
{ "type": "Feature", "properties": { "Name": "Fire Detection Centroid ", "Description": "<b>Latitude: <\/b> 37.52637<br\/>  <b>Longitude: <\/b> -119.83198<br\/>  <b>Detection Time: <\/b> 2023-12-27 21:25 UTC<br\/>  <b>Sensor: <\/b> NOAA-20 VIIRS<br\/> <b>Confidence: <\/b> Nominal<br\/>  <b>Day\/Night: <\/b> Day<br\/> <b>Scan: <\/b> 0.41 km<br\/> <b>Track: <\/b> 0.45 km<br\/> <b>FRP: <\/b> 2.35 MW<br\/> <b>Brightness: <\/b> 328.12 K" }, "geometry": { "type": "Point", "coordinates": [ -119.83198, 37.52637, 0.0 ] } }
]
}
