{
"type": "FeatureCollection",
"crs": { "type": "name", "properties": { "name": "urn:ogc:def:crs:OGC:1.3:CRS84" } },
"features": [
{ "type": "Feature", "properties": { "Name": "Fire Detection Centroid ", "Description": "<b>Latitude: <\/b> 28.70582<br\/>  <b>Longitude: <\/b> -82.03191<br\/>  <b>Detection Time: <\/b> 2023-01-25 06:42 UTC<br\/>  <b>Sensor: <\/b> NOAA-20 VIIRS<br\/> <b>Confidence: <\/b> Nominal<br\/>  <b>Day\/Night: <\/b> Night<br\/> <b>Scan: <\/b> 0.5 km<br\/> <b>Track: <\/b> 0.5 km<br\/> <b>FRP: <\/b> 2.13 MW<br\/> <b>Brightness: <\/b> 313.85 K" }, "geometry": { "type": "Point", "coordinates": [ -82.03191, 28.70582, 0.0 ] } },
{ "type": "Feature", "properties": { "Name": "Fire Detection Centroid ", "Description": "<b>Latitude: <\/b> 28.70129<br\/>  <b>Longitude: <\/b> -82.03252<br\/>  <b>Detection Time: <\/b> 2023-01-25 06:42 UTC<br\/>  <b>Sensor: <\/b> NOAA-20 VIIRS<br\/> <b>Confidence: <\/b> Nominal<br\/>  <b>Day\/Night: <\/b> Night<br\/> <b>Scan: <\/b> 0.5 km<br\/> <b>Track: <\/b> 0.5 km<br\/> <b>FRP: <\/b> 1.38 MW<br\/> <b>Brightness: <\/b> 306.89 K" }, "geometry": { "type": "Point", "coordinates": [ -82.03252, 28.70129, 0.0 ] } },
{ "type": "Feature", "properties": { "Name": "Fire Detection Centroid ", "Description": "<b>Latitude: <\/b> 33.01659<br\/>  <b>Longitude: <\/b> -79.88418<br\/>  <b>Detection Time: <\/b> 2023-01-25 06:40 UTC<br\/>  <b>Sensor: <\/b> NOAA-20 VIIRS<br\/> <b>Confidence: <\/b> Nominal<br\/>  <b>Day\/Night: <\/b> Night<br\/> <b>Scan: <\/b> 0.4 km<br\/> <b>Track: <\/b> 0.5 km<br\/> <b>FRP: <\/b> 0.9 MW<br\/> <b>Brightness: <\/b> 309.11 K" }, "geometry": { "type": "Point", "coordinates": [ -79.88418, 33.01659, 0.0 ] } },
{ "type": "Feature", "properties": { "Name": "Fire Detection Centroid ", "Description": "<b>Latitude: <\/b> 34.25336<br\/>  <b>Longitude: <\/b> -79.40932<br\/>  <b>Detection Time: <\/b> 2023-01-25 06:40 UTC<br\/>  <b>Sensor: <\/b> NOAA-20 VIIRS<br\/> <b>Confidence: <\/b> Nominal<br\/>  <b>Day\/Night: <\/b> Night<br\/> <b>Scan: <\/b> 0.4 km<br\/> <b>Track: <\/b> 0.5 km<br\/> <b>FRP: <\/b> 2.28 MW<br\/> <b>Brightness: <\/b> 320.49 K" }, "geometry": { "type": "Point", "coordinates": [ -79.40932, 34.25336, 0.0 ] } },
{ "type": "Feature", "properties": { "Name": "Fire Detection Centroid ", "Description": "<b>Latitude: <\/b> 36.35663<br\/>  <b>Longitude: <\/b> -76.80511<br\/>  <b>Detection Time: <\/b> 2023-01-25 06:39 UTC<br\/>  <b>Sensor: <\/b> NOAA-20 VIIRS<br\/> <b>Confidence: <\/b> Nominal<br\/>  <b>Day\/Night: <\/b> Night<br\/> <b>Scan: <\/b> 0.5 km<br\/> <b>Track: <\/b> 0.4 km<br\/> <b>FRP: <\/b> 3.92 MW<br\/> <b>Brightness: <\/b> 326.89 K" }, "geometry": { "type": "Point", "coordinates": [ -76.80511, 36.35663, 0.0 ] } },
{ "type": "Feature", "properties": { "Name": "Fire Detection Centroid ", "Description": "<b>Latitude: <\/b> 45.82272<br\/>  <b>Longitude: <\/b> -73.268<br\/>  <b>Detection Time: <\/b> 2023-01-25 06:37 UTC<br\/>  <b>Sensor: <\/b> NOAA-20 VIIRS<br\/> <b>Confidence: <\/b> Nominal<br\/>  <b>Day\/Night: <\/b> Night<br\/> <b>Scan: <\/b> 0.5 km<br\/> <b>Track: <\/b> 0.4 km<br\/> <b>FRP: <\/b> 1.3 MW<br\/> <b>Brightness: <\/b> 310.34 K" }, "geometry": { "type": "Point", "coordinates": [ -73.268, 45.82272, 0.0 ] } },
{ "type": "Feature", "properties": { "Name": "Fire Detection Centroid ", "Description": "<b>Latitude: <\/b> 48.18651<br\/>  <b>Longitude: <\/b> -64.9199<br\/>  <b>Detection Time: <\/b> 2023-01-25 06:36 UTC<br\/>  <b>Sensor: <\/b> NOAA-20 VIIRS<br\/> <b>Confidence: <\/b> Nominal<br\/>  <b>Day\/Night: <\/b> Night<br\/> <b>Scan: <\/b> 0.4 km<br\/> <b>Track: <\/b> 0.4 km<br\/> <b>FRP: <\/b> 0.6 MW<br\/> <b>Brightness: <\/b> 302.79 K" }, "geometry": { "type": "Point", "coordinates": [ -64.9199, 48.18651, 0.0 ] } }
]
}
