{
"type": "FeatureCollection",
"crs": { "type": "name", "properties": { "name": "urn:ogc:def:crs:OGC:1.3:CRS84" } },
"features": [
{ "type": "Feature", "properties": { "Name": "Fire Detection Centroid ", "Description": "<b>Latitude: <\/b> 19.40844<br\/>  <b>Longitude: <\/b> -155.28035<br\/>  <b>Detection Time: <\/b> 2023-03-07 12:21 UTC<br\/>  <b>Sensor: <\/b> NOAA-20 VIIRS<br\/> <b>Confidence: <\/b> Nominal<br\/>  <b>Day\/Night: <\/b> Night<br\/> <b>Scan: <\/b> 0.41 km<br\/> <b>Track: <\/b> 0.45 km<br\/> <b>FRP: <\/b> 2.13 MW<br\/> <b>Brightness: <\/b> 304.09 K" }, "geometry": { "type": "Point", "coordinates": [ -155.28035, 19.40844, 0.0 ] } },
{ "type": "Feature", "properties": { "Name": "Fire Detection Centroid ", "Description": "<b>Latitude: <\/b> 19.40511<br\/>  <b>Longitude: <\/b> -155.28502<br\/>  <b>Detection Time: <\/b> 2023-03-07 12:21 UTC<br\/>  <b>Sensor: <\/b> NOAA-20 VIIRS<br\/> <b>Confidence: <\/b> Nominal<br\/>  <b>Day\/Night: <\/b> Night<br\/> <b>Scan: <\/b> 0.41 km<br\/> <b>Track: <\/b> 0.45 km<br\/> <b>FRP: <\/b> 2.13 MW<br\/> <b>Brightness: <\/b> 305.24 K" }, "geometry": { "type": "Point", "coordinates": [ -155.28502, 19.40511, 0.0 ] } },
{ "type": "Feature", "properties": { "Name": "Fire Detection Centroid ", "Description": "<b>Latitude: <\/b> 19.40585<br\/>  <b>Longitude: <\/b> -155.28893<br\/>  <b>Detection Time: <\/b> 2023-03-07 12:21 UTC<br\/>  <b>Sensor: <\/b> NOAA-20 VIIRS<br\/> <b>Confidence: <\/b> Nominal<br\/>  <b>Day\/Night: <\/b> Night<br\/> <b>Scan: <\/b> 0.41 km<br\/> <b>Track: <\/b> 0.45 km<br\/> <b>FRP: <\/b> 2.41 MW<br\/> <b>Brightness: <\/b> 311.93 K" }, "geometry": { "type": "Point", "coordinates": [ -155.28893, 19.40585, 0.0 ] } },
{ "type": "Feature", "properties": { "Name": "Fire Detection Centroid ", "Description": "<b>Latitude: <\/b> 37.95761<br\/>  <b>Longitude: <\/b> -121.43082<br\/>  <b>Detection Time: <\/b> 2023-03-07 10:34 UTC<br\/>  <b>Sensor: <\/b> NOAA-20 VIIRS<br\/> <b>Confidence: <\/b> Nominal<br\/>  <b>Day\/Night: <\/b> Night<br\/> <b>Scan: <\/b> 0.53 km<br\/> <b>Track: <\/b> 0.5 km<br\/> <b>FRP: <\/b> 6.88 MW<br\/> <b>Brightness: <\/b> 336.52 K" }, "geometry": { "type": "Point", "coordinates": [ -121.43082, 37.95761, 0.0 ] } },
{ "type": "Feature", "properties": { "Name": "Fire Detection Centroid ", "Description": "<b>Latitude: <\/b> 37.94765<br\/>  <b>Longitude: <\/b> -122.3941<br\/>  <b>Detection Time: <\/b> 2023-03-07 10:34 UTC<br\/>  <b>Sensor: <\/b> NOAA-20 VIIRS<br\/> <b>Confidence: <\/b> Nominal<br\/>  <b>Day\/Night: <\/b> Night<br\/> <b>Scan: <\/b> 0.47 km<br\/> <b>Track: <\/b> 0.48 km<br\/> <b>FRP: <\/b> 3.16 MW<br\/> <b>Brightness: <\/b> 314.74 K" }, "geometry": { "type": "Point", "coordinates": [ -122.3941, 37.94765, 0.0 ] } },
{ "type": "Feature", "properties": { "Name": "Fire Detection Centroid ", "Description": "<b>Latitude: <\/b> 38.07081<br\/>  <b>Longitude: <\/b> -122.14066<br\/>  <b>Detection Time: <\/b> 2023-03-07 10:34 UTC<br\/>  <b>Sensor: <\/b> NOAA-20 VIIRS<br\/> <b>Confidence: <\/b> Nominal<br\/>  <b>Day\/Night: <\/b> Night<br\/> <b>Scan: <\/b> 0.48 km<br\/> <b>Track: <\/b> 0.48 km<br\/> <b>FRP: <\/b> 1.78 MW<br\/> <b>Brightness: <\/b> 295.48 K" }, "geometry": { "type": "Point", "coordinates": [ -122.14066, 38.07081, 0.0 ] } },
{ "type": "Feature", "properties": { "Name": "Fire Detection Centroid ", "Description": "<b>Latitude: <\/b> 37.95742<br\/>  <b>Longitude: <\/b> -121.43041<br\/>  <b>Detection Time: <\/b> 2023-03-07 10:34 UTC<br\/>  <b>Sensor: <\/b> NOAA-20 VIIRS<br\/> <b>Confidence: <\/b> Nominal<br\/>  <b>Day\/Night: <\/b> Night<br\/> <b>Scan: <\/b> 0.53 km<br\/> <b>Track: <\/b> 0.5 km<br\/> <b>FRP: <\/b> 4.61 MW<br\/> <b>Brightness: <\/b> 336.14 K" }, "geometry": { "type": "Point", "coordinates": [ -121.43041, 37.95742, 0.0 ] } },
{ "type": "Feature", "properties": { "Name": "Fire Detection Centroid ", "Description": "<b>Latitude: <\/b> 37.45572<br\/>  <b>Longitude: <\/b> -121.93348<br\/>  <b>Detection Time: <\/b> 2023-03-07 10:34 UTC<br\/>  <b>Sensor: <\/b> NOAA-20 VIIRS<br\/> <b>Confidence: <\/b> Nominal<br\/>  <b>Day\/Night: <\/b> Night<br\/> <b>Scan: <\/b> 0.51 km<br\/> <b>Track: <\/b> 0.49 km<br\/> <b>FRP: <\/b> 0.66 MW<br\/> <b>Brightness: <\/b> 295.69 K" }, "geometry": { "type": "Point", "coordinates": [ -121.93348, 37.45572, 0.0 ] } },
{ "type": "Feature", "properties": { "Name": "Fire Detection Centroid ", "Description": "<b>Latitude: <\/b> 48.62285<br\/>  <b>Longitude: <\/b> -123.53515<br\/>  <b>Detection Time: <\/b> 2023-03-07 10:30 UTC<br\/>  <b>Sensor: <\/b> NOAA-20 VIIRS<br\/> <b>Confidence: <\/b> Nominal<br\/>  <b>Day\/Night: <\/b> Night<br\/> <b>Scan: <\/b> 0.41 km<br\/> <b>Track: <\/b> 0.37 km<br\/> <b>FRP: <\/b> 1.11 MW<br\/> <b>Brightness: <\/b> 310.92 K" }, "geometry": { "type": "Point", "coordinates": [ -123.53515, 48.62285, 0.0 ] } }
]
}
