{
"type": "FeatureCollection",
"crs": { "type": "name", "properties": { "name": "urn:ogc:def:crs:OGC:1.3:CRS84" } },
"features": [
{ "type": "Feature", "properties": { "Name": "Fire Detection Centroid ", "Description": "<b>Latitude: <\/b> 19.40829<br\/>  <b>Longitude: <\/b> -155.28317<br\/>  <b>Detection Time: <\/b> 2023-06-25 00:28 UTC<br\/>  <b>Sensor: <\/b> NOAA-20 VIIRS<br\/> <b>Confidence: <\/b> Nominal<br\/>  <b>Day\/Night: <\/b> Day<br\/> <b>Scan: <\/b> 0.7 km<br\/> <b>Track: <\/b> 0.75 km<br\/> <b>FRP: <\/b> 21.45 MW<br\/> <b>Brightness: <\/b> 339.91 K" }, "geometry": { "type": "Point", "coordinates": [ -155.28317, 19.40829, 0.0 ] } }
]
}
