{
"type": "FeatureCollection",
"crs": { "type": "name", "properties": { "name": "urn:ogc:def:crs:OGC:1.3:CRS84" } },
"features": [
{ "type": "Feature", "properties": { "Name": "Fire Detection Centroid ", "Description": "<b>Latitude: <\/b> 19.40726<br\/>  <b>Longitude: <\/b> -155.2813<br\/>  <b>Detection Time: <\/b> 2024-01-02 11:36 UTC<br\/>  <b>Sensor: <\/b> NOAA-20 VIIRS<br\/> <b>Confidence: <\/b> Nominal<br\/>  <b>Day\/Night: <\/b> Night<br\/> <b>Scan: <\/b> 0.4 km<br\/> <b>Track: <\/b> 0.44 km<br\/> <b>FRP: <\/b> 3.31 MW<br\/> <b>Brightness: <\/b> 305.22 K" }, "geometry": { "type": "Point", "coordinates": [ -155.2813, 19.40726, 0.0 ] } }
]
}
