{
"type": "FeatureCollection",
"crs": { "type": "name", "properties": { "name": "urn:ogc:def:crs:OGC:1.3:CRS84" } },
"features": [
{ "type": "Feature", "properties": { "Name": "Fire Detection Centroid ", "Description": "<b>Latitude: <\/b> 47.01023<br\/>  <b>Longitude: <\/b> -64.00056<br\/>  <b>Detection Time: <\/b> 2023-12-25 17:00 UTC<br\/>  <b>Sensor: <\/b> NOAA-20 VIIRS<br\/> <b>Confidence: <\/b> Nominal<br\/>  <b>Day\/Night: <\/b> Day<br\/> <b>Scan: <\/b> 0.4 km<br\/> <b>Track: <\/b> 0.4 km<br\/> <b>FRP: <\/b> 2.05 MW<br\/> <b>Brightness: <\/b> 325.59 K" }, "geometry": { "type": "Point", "coordinates": [ -64.00056, 47.01023, 0.0 ] } },
{ "type": "Feature", "properties": { "Name": "Fire Detection Centroid ", "Description": "<b>Latitude: <\/b> 19.40674<br\/>  <b>Longitude: <\/b> -155.28496<br\/>  <b>Detection Time: <\/b> 2023-12-25 12:25 UTC<br\/>  <b>Sensor: <\/b> NOAA-20 VIIRS<br\/> <b>Confidence: <\/b> Nominal<br\/>  <b>Day\/Night: <\/b> Night<br\/> <b>Scan: <\/b> 0.52 km<br\/> <b>Track: <\/b> 0.5 km<br\/> <b>FRP: <\/b> 5.66 MW<br\/> <b>Brightness: <\/b> 304.59 K" }, "geometry": { "type": "Point", "coordinates": [ -155.28496, 19.40674, 0.0 ] } }
]
}
