{
"type": "FeatureCollection",
"crs": { "type": "name", "properties": { "name": "urn:ogc:def:crs:OGC:1.3:CRS84" } },
"features": [
{ "type": "Feature", "properties": { "Name": "Fire Detection Centroid ", "Description": "<b>Latitude: <\/b> 45.2049<br\/>  <b>Longitude: <\/b> -121.3624<br\/>  <b>Detection Time: <\/b> 2023-06-02 21:25 UTC<br\/>  <b>Sensor: <\/b> NOAA-20 VIIRS<br\/> <b>Confidence: <\/b> Nominal<br\/>  <b>Day\/Night: <\/b> Day<br\/> <b>Scan: <\/b> 0.41 km<br\/> <b>Track: <\/b> 0.45 km<br\/> <b>FRP: <\/b> 3.41 MW<br\/> <b>Brightness: <\/b> 337.64 K" }, "geometry": { "type": "Point", "coordinates": [ -121.3624, 45.2049, 0.0 ] } },
{ "type": "Feature", "properties": { "Name": "Fire Detection Centroid ", "Description": "<b>Latitude: <\/b> 35.3438<br\/>  <b>Longitude: <\/b> -118.98817<br\/>  <b>Detection Time: <\/b> 2023-06-02 21:25 UTC<br\/>  <b>Sensor: <\/b> NOAA-20 VIIRS<br\/> <b>Confidence: <\/b> Low<br\/>  <b>Day\/Night: <\/b> Day<br\/> <b>Scan: <\/b> 0.42 km<br\/> <b>Track: <\/b> 0.45 km<br\/> <b>FRP: <\/b> 3.54 MW<br\/> <b>Brightness: <\/b> 339.25 K" }, "geometry": { "type": "Point", "coordinates": [ -118.98817, 35.3438, 0.0 ] } },
{ "type": "Feature", "properties": { "Name": "Fire Detection Centroid ", "Description": "<b>Latitude: <\/b> 45.22716<br\/>  <b>Longitude: <\/b> -123.16201<br\/>  <b>Detection Time: <\/b> 2023-06-02 21:25 UTC<br\/>  <b>Sensor: <\/b> NOAA-20 VIIRS<br\/> <b>Confidence: <\/b> Nominal<br\/>  <b>Day\/Night: <\/b> Day<br\/> <b>Scan: <\/b> 0.52 km<br\/> <b>Track: <\/b> 0.42 km<br\/> <b>FRP: <\/b> 6.55 MW<br\/> <b>Brightness: <\/b> 341.88 K" }, "geometry": { "type": "Point", "coordinates": [ -123.16201, 45.22716, 0.0 ] } },
{ "type": "Feature", "properties": { "Name": "Fire Detection Centroid ", "Description": "<b>Latitude: <\/b> 45.92615<br\/>  <b>Longitude: <\/b> -118.86093<br\/>  <b>Detection Time: <\/b> 2023-06-02 21:25 UTC<br\/>  <b>Sensor: <\/b> NOAA-20 VIIRS<br\/> <b>Confidence: <\/b> Nominal<br\/>  <b>Day\/Night: <\/b> Day<br\/> <b>Scan: <\/b> 0.55 km<br\/> <b>Track: <\/b> 0.51 km<br\/> <b>FRP: <\/b> 33.75 MW<br\/> <b>Brightness: <\/b> 343.08 K" }, "geometry": { "type": "Point", "coordinates": [ -118.86093, 45.92615, 0.0 ] } },
{ "type": "Feature", "properties": { "Name": "Fire Detection Centroid ", "Description": "<b>Latitude: <\/b> 45.9214<br\/>  <b>Longitude: <\/b> -118.8606<br\/>  <b>Detection Time: <\/b> 2023-06-02 21:25 UTC<br\/>  <b>Sensor: <\/b> NOAA-20 VIIRS<br\/> <b>Confidence: <\/b> Nominal<br\/>  <b>Day\/Night: <\/b> Day<br\/> <b>Scan: <\/b> 0.55 km<br\/> <b>Track: <\/b> 0.51 km<br\/> <b>FRP: <\/b> 15.4 MW<br\/> <b>Brightness: <\/b> 341.76 K" }, "geometry": { "type": "Point", "coordinates": [ -118.8606, 45.9214, 0.0 ] } },
{ "type": "Feature", "properties": { "Name": "Fire Detection Centroid ", "Description": "<b>Latitude: <\/b> 36.13361<br\/>  <b>Longitude: <\/b> -115.05317<br\/>  <b>Detection Time: <\/b> 2023-06-02 21:25 UTC<br\/>  <b>Sensor: <\/b> NOAA-20 VIIRS<br\/> <b>Confidence: <\/b> Low<br\/>  <b>Day\/Night: <\/b> Day<br\/> <b>Scan: <\/b> 0.35 km<br\/> <b>Track: <\/b> 0.57 km<br\/> <b>FRP: <\/b> 2.9 MW<br\/> <b>Brightness: <\/b> 339.52 K" }, "geometry": { "type": "Point", "coordinates": [ -115.05317, 36.13361, 0.0 ] } },
{ "type": "Feature", "properties": { "Name": "Fire Detection Centroid ", "Description": "<b>Latitude: <\/b> 42.01395<br\/>  <b>Longitude: <\/b> -121.44169<br\/>  <b>Detection Time: <\/b> 2023-06-02 21:25 UTC<br\/>  <b>Sensor: <\/b> NOAA-20 VIIRS<br\/> <b>Confidence: <\/b> Nominal<br\/>  <b>Day\/Night: <\/b> Day<br\/> <b>Scan: <\/b> 0.57 km<br\/> <b>Track: <\/b> 0.43 km<br\/> <b>FRP: <\/b> 7.02 MW<br\/> <b>Brightness: <\/b> 342.94 K" }, "geometry": { "type": "Point", "coordinates": [ -121.44169, 42.01395, 0.0 ] } },
{ "type": "Feature", "properties": { "Name": "Fire Detection Centroid ", "Description": "<b>Latitude: <\/b> 42.79012<br\/>  <b>Longitude: <\/b> -114.58873<br\/>  <b>Detection Time: <\/b> 2023-06-02 21:25 UTC<br\/>  <b>Sensor: <\/b> NOAA-20 VIIRS<br\/> <b>Confidence: <\/b> Nominal<br\/>  <b>Day\/Night: <\/b> Day<br\/> <b>Scan: <\/b> 0.43 km<br\/> <b>Track: <\/b> 0.62 km<br\/> <b>FRP: <\/b> 5.02 MW<br\/> <b>Brightness: <\/b> 347.74 K" }, "geometry": { "type": "Point", "coordinates": [ -114.58873, 42.79012, 0.0 ] } },
{ "type": "Feature", "properties": { "Name": "Fire Detection Centroid ", "Description": "<b>Latitude: <\/b> 44.7614<br\/>  <b>Longitude: <\/b> -123.93417<br\/>  <b>Detection Time: <\/b> 2023-06-02 21:25 UTC<br\/>  <b>Sensor: <\/b> NOAA-20 VIIRS<br\/> <b>Confidence: <\/b> Nominal<br\/>  <b>Day\/Night: <\/b> Day<br\/> <b>Scan: <\/b> 0.48 km<br\/> <b>Track: <\/b> 0.4 km<br\/> <b>FRP: <\/b> 3.65 MW<br\/> <b>Brightness: <\/b> 331.71 K" }, "geometry": { "type": "Point", "coordinates": [ -123.93417, 44.7614, 0.0 ] } }
]
}
