{
"type": "FeatureCollection",
"crs": { "type": "name", "properties": { "name": "urn:ogc:def:crs:OGC:1.3:CRS84" } },
"features": [
{ "type": "Feature", "properties": { "Name": "Fire Detection Centroid ", "Description": "<b>Latitude: <\/b> 20.04436<br\/>  <b>Longitude: <\/b> -155.38327<br\/>  <b>Detection Time: <\/b> 2023-05-04 23:46 UTC<br\/>  <b>Sensor: <\/b> NOAA-20 VIIRS<br\/> <b>Confidence: <\/b> Low<br\/>  <b>Day\/Night: <\/b> Day<br\/> <b>Scan: <\/b> 0.44 km<br\/> <b>Track: <\/b> 0.38 km<br\/> <b>FRP: <\/b> 2.87 MW<br\/> <b>Brightness: <\/b> 330.47 K" }, "geometry": { "type": "Point", "coordinates": [ -155.38327, 20.04436, 0.0 ] } },
{ "type": "Feature", "properties": { "Name": "Fire Detection Centroid ", "Description": "<b>Latitude: <\/b> 19.90257<br\/>  <b>Longitude: <\/b> -155.75874<br\/>  <b>Detection Time: <\/b> 2023-05-04 23:46 UTC<br\/>  <b>Sensor: <\/b> NOAA-20 VIIRS<br\/> <b>Confidence: <\/b> Nominal<br\/>  <b>Day\/Night: <\/b> Day<br\/> <b>Scan: <\/b> 0.42 km<br\/> <b>Track: <\/b> 0.38 km<br\/> <b>FRP: <\/b> 1.63 MW<br\/> <b>Brightness: <\/b> 341.66 K" }, "geometry": { "type": "Point", "coordinates": [ -155.75874, 19.90257, 0.0 ] } },
{ "type": "Feature", "properties": { "Name": "Fire Detection Centroid ", "Description": "<b>Latitude: <\/b> 47.39847<br\/>  <b>Longitude: <\/b> -120.9101<br\/>  <b>Detection Time: <\/b> 2023-05-04 22:12 UTC<br\/>  <b>Sensor: <\/b> NOAA-20 VIIRS<br\/> <b>Confidence: <\/b> Nominal<br\/>  <b>Day\/Night: <\/b> Day<br\/> <b>Scan: <\/b> 0.77 km<br\/> <b>Track: <\/b> 0.78 km<br\/> <b>FRP: <\/b> 11.11 MW<br\/> <b>Brightness: <\/b> 325.42 K" }, "geometry": { "type": "Point", "coordinates": [ -120.9101, 47.39847, 0.0 ] } }
]
}
