{
"type": "FeatureCollection",
"crs": { "type": "name", "properties": { "name": "urn:ogc:def:crs:OGC:1.3:CRS84" } },
"features": [
{ "type": "Feature", "properties": { "Name": "Fire Detection Centroid ", "Description": "<b>Latitude: <\/b> 19.71115<br\/>  <b>Longitude: <\/b> -156.03571<br\/>  <b>Detection Time: <\/b> 2023-06-21 00:05 UTC<br\/>  <b>Sensor: <\/b> NOAA-20 VIIRS<br\/> <b>Confidence: <\/b> Nominal<br\/>  <b>Day\/Night: <\/b> Day<br\/> <b>Scan: <\/b> 0.48 km<br\/> <b>Track: <\/b> 0.48 km<br\/> <b>FRP: <\/b> 10.13 MW<br\/> <b>Brightness: <\/b> 343.48 K" }, "geometry": { "type": "Point", "coordinates": [ -156.03571, 19.71115, 0.0 ] } }
]
}
