{
"type": "FeatureCollection",
"crs": { "type": "name", "properties": { "name": "urn:ogc:def:crs:OGC:1.3:CRS84" } },
"features": [
{ "type": "Feature", "properties": { "Name": "Fire Detection Centroid ", "Description": "<b>Latitude: </b> 19.40385<br/>  <b>Longitude: </b> -155.2776<br/>  <b>Detection Time: </b> 2022-06-17 00:22 UTC<br/>  <b>Sensor: </b> NOAA-20 VIIRS<br/> <b>Confidence: </b> Nominal<br/>  <b>Day/Night: </b> Day<br/> <b>Scan: </b> 0.55 km<br/> <b>Track: </b> 0.68 km<br/> <b>FRP: </b> 10.25 MW<br/> <b>Brightness: </b> 333.16 K" }, "geometry": { "type": "Point", "coordinates": [ -155.2776, 19.40385, 0.0 ] } },
{ "type": "Feature", "properties": { "Name": "Fire Detection Centroid ", "Description": "<b>Latitude: </b> 19.40291<br/>  <b>Longitude: </b> -155.28839<br/>  <b>Detection Time: </b> 2022-06-17 00:22 UTC<br/>  <b>Sensor: </b> NOAA-20 VIIRS<br/> <b>Confidence: </b> High<br/>  <b>Day/Night: </b> Day<br/> <b>Scan: </b> 0.55 km<br/> <b>Track: </b> 0.68 km<br/> <b>FRP: </b> 10.95 MW<br/> <b>Brightness: </b> 367 K" }, "geometry": { "type": "Point", "coordinates": [ -155.28839, 19.40291, 0.0 ] } },
{ "type": "Feature", "properties": { "Name": "Fire Detection Centroid ", "Description": "<b>Latitude: </b> 19.40431<br/>  <b>Longitude: </b> -155.27234<br/>  <b>Detection Time: </b> 2022-06-17 00:22 UTC<br/>  <b>Sensor: </b> NOAA-20 VIIRS<br/> <b>Confidence: </b> Low<br/>  <b>Day/Night: </b> Day<br/> <b>Scan: </b> 0.55 km<br/> <b>Track: </b> 0.68 km<br/> <b>FRP: </b> 11.51 MW<br/> <b>Brightness: </b> 325.55 K" }, "geometry": { "type": "Point", "coordinates": [ -155.27234, 19.40431, 0.0 ] } },
{ "type": "Feature", "properties": { "Name": "Fire Detection Centroid ", "Description": "<b>Latitude: </b> 19.40339<br/>  <b>Longitude: </b> -155.2829<br/>  <b>Detection Time: </b> 2022-06-17 00:22 UTC<br/>  <b>Sensor: </b> NOAA-20 VIIRS<br/> <b>Confidence: </b> Nominal<br/>  <b>Day/Night: </b> Day<br/> <b>Scan: </b> 0.55 km<br/> <b>Track: </b> 0.68 km<br/> <b>FRP: </b> 10.25 MW<br/> <b>Brightness: </b> 348.39 K" }, "geometry": { "type": "Point", "coordinates": [ -155.2829, 19.40339, 0.0 ] } },
{ "type": "Feature", "properties": { "Name": "Fire Detection Centroid ", "Description": "<b>Latitude: </b> 19.40967<br/>  <b>Longitude: </b> -155.28369<br/>  <b>Detection Time: </b> 2022-06-17 00:22 UTC<br/>  <b>Sensor: </b> NOAA-20 VIIRS<br/> <b>Confidence: </b> Nominal<br/>  <b>Day/Night: </b> Day<br/> <b>Scan: </b> 0.55 km<br/> <b>Track: </b> 0.68 km<br/> <b>FRP: </b> 10.25 MW<br/> <b>Brightness: </b> 332.65 K" }, "geometry": { "type": "Point", "coordinates": [ -155.28369, 19.40967, 0.0 ] } },
{ "type": "Feature", "properties": { "Name": "Fire Detection Centroid ", "Description": "<b>Latitude: </b> 19.40917<br/>  <b>Longitude: </b> -155.28938<br/>  <b>Detection Time: </b> 2022-06-17 00:22 UTC<br/>  <b>Sensor: </b> NOAA-20 VIIRS<br/> <b>Confidence: </b> Nominal<br/>  <b>Day/Night: </b> Day<br/> <b>Scan: </b> 0.55 km<br/> <b>Track: </b> 0.68 km<br/> <b>FRP: </b> 10.95 MW<br/> <b>Brightness: </b> 326.74 K" }, "geometry": { "type": "Point", "coordinates": [ -155.28938, 19.40917, 0.0 ] } }
]
}
