{
"type": "FeatureCollection",
"crs": { "type": "name", "properties": { "name": "urn:ogc:def:crs:OGC:1.3:CRS84" } },
"features": [
{ "type": "Feature", "properties": { "Name": "Fire Detection Centroid ", "Description": "<b>Latitude: <\/b> 19.90374<br\/>  <b>Longitude: <\/b> -155.76848<br\/>  <b>Detection Time: <\/b> 2023-06-21 23:46 UTC<br\/>  <b>Sensor: <\/b> NOAA-20 VIIRS<br\/> <b>Confidence: <\/b> Nominal<br\/>  <b>Day\/Night: <\/b> Day<br\/> <b>Scan: <\/b> 0.42 km<br\/> <b>Track: <\/b> 0.38 km<br\/> <b>FRP: <\/b> 6.66 MW<br\/> <b>Brightness: <\/b> 346.6 K" }, "geometry": { "type": "Point", "coordinates": [ -155.76848, 19.90374, 0.0 ] } },
{ "type": "Feature", "properties": { "Name": "Fire Detection Centroid ", "Description": "<b>Latitude: <\/b> 19.90029<br\/>  <b>Longitude: <\/b> -155.76799<br\/>  <b>Detection Time: <\/b> 2023-06-21 23:46 UTC<br\/>  <b>Sensor: <\/b> NOAA-20 VIIRS<br\/> <b>Confidence: <\/b> Low<br\/>  <b>Day\/Night: <\/b> Day<br\/> <b>Scan: <\/b> 0.42 km<br\/> <b>Track: <\/b> 0.38 km<br\/> <b>FRP: <\/b> 6.66 MW<br\/> <b>Brightness: <\/b> 356.34 K" }, "geometry": { "type": "Point", "coordinates": [ -155.76799, 19.90029, 0.0 ] } },
{ "type": "Feature", "properties": { "Name": "Fire Detection Centroid ", "Description": "<b>Latitude: <\/b> 19.89684<br\/>  <b>Longitude: <\/b> -155.76749<br\/>  <b>Detection Time: <\/b> 2023-06-21 23:46 UTC<br\/>  <b>Sensor: <\/b> NOAA-20 VIIRS<br\/> <b>Confidence: <\/b> Nominal<br\/>  <b>Day\/Night: <\/b> Day<br\/> <b>Scan: <\/b> 0.42 km<br\/> <b>Track: <\/b> 0.38 km<br\/> <b>FRP: <\/b> 4.49 MW<br\/> <b>Brightness: <\/b> 348.1 K" }, "geometry": { "type": "Point", "coordinates": [ -155.76749, 19.89684, 0.0 ] } },
{ "type": "Feature", "properties": { "Name": "Fire Detection Centroid ", "Description": "<b>Latitude: <\/b> 19.89739<br\/>  <b>Longitude: <\/b> -155.76355<br\/>  <b>Detection Time: <\/b> 2023-06-21 23:46 UTC<br\/>  <b>Sensor: <\/b> NOAA-20 VIIRS<br\/> <b>Confidence: <\/b> Nominal<br\/>  <b>Day\/Night: <\/b> Day<br\/> <b>Scan: <\/b> 0.42 km<br\/> <b>Track: <\/b> 0.38 km<br\/> <b>FRP: <\/b> 4.49 MW<br\/> <b>Brightness: <\/b> 351.18 K" }, "geometry": { "type": "Point", "coordinates": [ -155.76355, 19.89739, 0.0 ] } },
{ "type": "Feature", "properties": { "Name": "Fire Detection Centroid ", "Description": "<b>Latitude: <\/b> 19.89794<br\/>  <b>Longitude: <\/b> -155.75958<br\/>  <b>Detection Time: <\/b> 2023-06-21 23:46 UTC<br\/>  <b>Sensor: <\/b> NOAA-20 VIIRS<br\/> <b>Confidence: <\/b> Nominal<br\/>  <b>Day\/Night: <\/b> Day<br\/> <b>Scan: <\/b> 0.42 km<br\/> <b>Track: <\/b> 0.38 km<br\/> <b>FRP: <\/b> 2.57 MW<br\/> <b>Brightness: <\/b> 342.54 K" }, "geometry": { "type": "Point", "coordinates": [ -155.75958, 19.89794, 0.0 ] } },
{ "type": "Feature", "properties": { "Name": "Fire Detection Centroid ", "Description": "<b>Latitude: <\/b> 19.89449<br\/>  <b>Longitude: <\/b> -155.75912<br\/>  <b>Detection Time: <\/b> 2023-06-21 23:46 UTC<br\/>  <b>Sensor: <\/b> NOAA-20 VIIRS<br\/> <b>Confidence: <\/b> Nominal<br\/>  <b>Day\/Night: <\/b> Day<br\/> <b>Scan: <\/b> 0.42 km<br\/> <b>Track: <\/b> 0.38 km<br\/> <b>FRP: <\/b> 2.57 MW<br\/> <b>Brightness: <\/b> 344.05 K" }, "geometry": { "type": "Point", "coordinates": [ -155.75912, 19.89449, 0.0 ] } }
]
}
