{
"type": "FeatureCollection",
"crs": { "type": "name", "properties": { "name": "urn:ogc:def:crs:OGC:1.3:CRS84" } },
"features": [
{ "type": "Feature", "properties": { "Name": "Fire Detection Centroid ", "Description": "<b>Latitude: <\/b> 42.29177<br\/>  <b>Longitude: <\/b> -83.16302<br\/>  <b>Detection Time: <\/b> 2023-11-11 17:25 UTC<br\/>  <b>Sensor: <\/b> NOAA-20 VIIRS<br\/> <b>Confidence: <\/b> Nominal<br\/>  <b>Day\/Night: <\/b> Day<br\/> <b>Scan: <\/b> 0.5 km<br\/> <b>Track: <\/b> 0.7 km<br\/> <b>FRP: <\/b> 5.98 MW<br\/> <b>Brightness: <\/b> 337.09 K" }, "geometry": { "type": "Point", "coordinates": [ -83.16302, 42.29177, 0.0 ] } },
{ "type": "Feature", "properties": { "Name": "Fire Detection Centroid ", "Description": "<b>Latitude: <\/b> 42.29523<br\/>  <b>Longitude: <\/b> -83.15165<br\/>  <b>Detection Time: <\/b> 2023-11-11 17:25 UTC<br\/>  <b>Sensor: <\/b> NOAA-20 VIIRS<br\/> <b>Confidence: <\/b> Nominal<br\/>  <b>Day\/Night: <\/b> Day<br\/> <b>Scan: <\/b> 0.5 km<br\/> <b>Track: <\/b> 0.7 km<br\/> <b>FRP: <\/b> 7.67 MW<br\/> <b>Brightness: <\/b> 347.16 K" }, "geometry": { "type": "Point", "coordinates": [ -83.15165, 42.29523, 0.0 ] } },
{ "type": "Feature", "properties": { "Name": "Fire Detection Centroid ", "Description": "<b>Latitude: <\/b> 41.45189<br\/>  <b>Longitude: <\/b> -81.67839<br\/>  <b>Detection Time: <\/b> 2023-11-11 17:24 UTC<br\/>  <b>Sensor: <\/b> NOAA-20 VIIRS<br\/> <b>Confidence: <\/b> Nominal<br\/>  <b>Day\/Night: <\/b> Day<br\/> <b>Scan: <\/b> 0.5 km<br\/> <b>Track: <\/b> 0.6 km<br\/> <b>FRP: <\/b> 3.63 MW<br\/> <b>Brightness: <\/b> 328.14 K" }, "geometry": { "type": "Point", "coordinates": [ -81.67839, 41.45189, 0.0 ] } },
{ "type": "Feature", "properties": { "Name": "Fire Detection Centroid ", "Description": "<b>Latitude: <\/b> 43.94217<br\/>  <b>Longitude: <\/b> -69.51692<br\/>  <b>Detection Time: <\/b> 2023-11-11 17:24 UTC<br\/>  <b>Sensor: <\/b> NOAA-20 VIIRS<br\/> <b>Confidence: <\/b> Nominal<br\/>  <b>Day\/Night: <\/b> Day<br\/> <b>Scan: <\/b> 0.4 km<br\/> <b>Track: <\/b> 0.4 km<br\/> <b>FRP: <\/b> 1.38 MW<br\/> <b>Brightness: <\/b> 331.72 K" }, "geometry": { "type": "Point", "coordinates": [ -69.51692, 43.94217, 0.0 ] } },
{ "type": "Feature", "properties": { "Name": "Fire Detection Centroid ", "Description": "<b>Latitude: <\/b> 37.56039<br\/>  <b>Longitude: <\/b> -77.67122<br\/>  <b>Detection Time: <\/b> 2023-11-11 17:23 UTC<br\/>  <b>Sensor: <\/b> NOAA-20 VIIRS<br\/> <b>Confidence: <\/b> Nominal<br\/>  <b>Day\/Night: <\/b> Day<br\/> <b>Scan: <\/b> 0.4 km<br\/> <b>Track: <\/b> 0.6 km<br\/> <b>FRP: <\/b> 2.27 MW<br\/> <b>Brightness: <\/b> 331.7 K" }, "geometry": { "type": "Point", "coordinates": [ -77.67122, 37.56039, 0.0 ] } },
{ "type": "Feature", "properties": { "Name": "Fire Detection Centroid ", "Description": "<b>Latitude: <\/b> 37.41625<br\/>  <b>Longitude: <\/b> -77.42827<br\/>  <b>Detection Time: <\/b> 2023-11-11 17:23 UTC<br\/>  <b>Sensor: <\/b> NOAA-20 VIIRS<br\/> <b>Confidence: <\/b> Nominal<br\/>  <b>Day\/Night: <\/b> Day<br\/> <b>Scan: <\/b> 0.3 km<br\/> <b>Track: <\/b> 0.6 km<br\/> <b>FRP: <\/b> 3.39 MW<br\/> <b>Brightness: <\/b> 342.14 K" }, "geometry": { "type": "Point", "coordinates": [ -77.42827, 37.41625, 0.0 ] } },
{ "type": "Feature", "properties": { "Name": "Fire Detection Centroid ", "Description": "<b>Latitude: <\/b> 38.76064<br\/>  <b>Longitude: <\/b> -75.5655<br\/>  <b>Detection Time: <\/b> 2023-11-11 17:23 UTC<br\/>  <b>Sensor: <\/b> NOAA-20 VIIRS<br\/> <b>Confidence: <\/b> Nominal<br\/>  <b>Day\/Night: <\/b> Day<br\/> <b>Scan: <\/b> 0.5 km<br\/> <b>Track: <\/b> 0.5 km<br\/> <b>FRP: <\/b> 4.3 MW<br\/> <b>Brightness: <\/b> 325.75 K" }, "geometry": { "type": "Point", "coordinates": [ -75.5655, 38.76064, 0.0 ] } },
{ "type": "Feature", "properties": { "Name": "Fire Detection Centroid ", "Description": "<b>Latitude: <\/b> 37.41625<br\/>  <b>Longitude: <\/b> -77.42827<br\/>  <b>Detection Time: <\/b> 2023-11-11 17:23 UTC<br\/>  <b>Sensor: <\/b> NOAA-20 VIIRS<br\/> <b>Confidence: <\/b> Nominal<br\/>  <b>Day\/Night: <\/b> Day<br\/> <b>Scan: <\/b> 0.3 km<br\/> <b>Track: <\/b> 0.6 km<br\/> <b>FRP: <\/b> 3.39 MW<br\/> <b>Brightness: <\/b> 342.14 K" }, "geometry": { "type": "Point", "coordinates": [ -77.42827, 37.41625, 0.0 ] } },
{ "type": "Feature", "properties": { "Name": "Fire Detection Centroid ", "Description": "<b>Latitude: <\/b> 19.59393<br\/>  <b>Longitude: <\/b> -71.02386<br\/>  <b>Detection Time: <\/b> 2023-11-11 17:18 UTC<br\/>  <b>Sensor: <\/b> NOAA-20 VIIRS<br\/> <b>Confidence: <\/b> Nominal<br\/>  <b>Day\/Night: <\/b> Day<br\/> <b>Scan: <\/b> 0.4 km<br\/> <b>Track: <\/b> 0.6 km<br\/> <b>FRP: <\/b> 3.02 MW<br\/> <b>Brightness: <\/b> 328.98 K" }, "geometry": { "type": "Point", "coordinates": [ -71.02386, 19.59393, 0.0 ] } }
]
}
