{
"type": "FeatureCollection",
"crs": { "type": "name", "properties": { "name": "urn:ogc:def:crs:OGC:1.3:CRS84" } },
"features": [
{ "type": "Feature", "properties": { "Name": "Fire Detection Centroid ", "Description": "<b>Latitude: <\/b> 41.65084<br\/>  <b>Longitude: <\/b> -123.07773<br\/>  <b>Detection Time: <\/b> 2023-11-01 22:15 UTC<br\/>  <b>Sensor: <\/b> NOAA-20 VIIRS<br\/> <b>Confidence: <\/b> Nominal<br\/>  <b>Day\/Night: <\/b> Day<br\/> <b>Scan: <\/b> 0.7 km<br\/> <b>Track: <\/b> 0.7 km<br\/> <b>FRP: <\/b> 15.37 MW<br\/> <b>Brightness: <\/b> 355.7 K" }, "geometry": { "type": "Point", "coordinates": [ -123.07773, 41.65084, 0.0 ] } },
{ "type": "Feature", "properties": { "Name": "Fire Detection Centroid ", "Description": "<b>Latitude: <\/b> 39.28022<br\/>  <b>Longitude: <\/b> -121.82312<br\/>  <b>Detection Time: <\/b> 2023-11-01 22:14 UTC<br\/>  <b>Sensor: <\/b> NOAA-20 VIIRS<br\/> <b>Confidence: <\/b> Nominal<br\/>  <b>Day\/Night: <\/b> Day<br\/> <b>Scan: <\/b> 0.8 km<br\/> <b>Track: <\/b> 0.8 km<br\/> <b>FRP: <\/b> 6.56 MW<br\/> <b>Brightness: <\/b> 341.11 K" }, "geometry": { "type": "Point", "coordinates": [ -121.82312, 39.28022, 0.0 ] } },
{ "type": "Feature", "properties": { "Name": "Fire Detection Centroid ", "Description": "<b>Latitude: <\/b> 38.64774<br\/>  <b>Longitude: <\/b> -122.00758<br\/>  <b>Detection Time: <\/b> 2023-11-01 22:14 UTC<br\/>  <b>Sensor: <\/b> NOAA-20 VIIRS<br\/> <b>Confidence: <\/b> Nominal<br\/>  <b>Day\/Night: <\/b> Day<br\/> <b>Scan: <\/b> 0.8 km<br\/> <b>Track: <\/b> 0.8 km<br\/> <b>FRP: <\/b> 6.7 MW<br\/> <b>Brightness: <\/b> 334.08 K" }, "geometry": { "type": "Point", "coordinates": [ -122.00758, 38.64774, 0.0 ] } },
{ "type": "Feature", "properties": { "Name": "Fire Detection Centroid ", "Description": "<b>Latitude: <\/b> 39.27902<br\/>  <b>Longitude: <\/b> -121.82333<br\/>  <b>Detection Time: <\/b> 2023-11-01 22:14 UTC<br\/>  <b>Sensor: <\/b> NOAA-20 VIIRS<br\/> <b>Confidence: <\/b> Nominal<br\/>  <b>Day\/Night: <\/b> Day<br\/> <b>Scan: <\/b> 0.8 km<br\/> <b>Track: <\/b> 0.8 km<br\/> <b>FRP: <\/b> 6.7 MW<br\/> <b>Brightness: <\/b> 340.99 K" }, "geometry": { "type": "Point", "coordinates": [ -121.82333, 39.27902, 0.0 ] } },
{ "type": "Feature", "properties": { "Name": "Fire Detection Centroid ", "Description": "<b>Latitude: <\/b> 38.50668<br\/>  <b>Longitude: <\/b> -121.93829<br\/>  <b>Detection Time: <\/b> 2023-11-01 22:14 UTC<br\/>  <b>Sensor: <\/b> NOAA-20 VIIRS<br\/> <b>Confidence: <\/b> Nominal<br\/>  <b>Day\/Night: <\/b> Day<br\/> <b>Scan: <\/b> 0.8 km<br\/> <b>Track: <\/b> 0.8 km<br\/> <b>FRP: <\/b> 5.88 MW<br\/> <b>Brightness: <\/b> 327.15 K" }, "geometry": { "type": "Point", "coordinates": [ -121.93829, 38.50668, 0.0 ] } }
]
}
