{
"type": "FeatureCollection",
"crs": { "type": "name", "properties": { "name": "urn:ogc:def:crs:OGC:1.3:CRS84" } },
"features": [
{ "type": "Feature", "properties": { "Name": "Fire Detection Centroid ", "Description": "<b>Latitude: <\/b> 43.26074<br\/>  <b>Longitude: <\/b> -79.80667<br\/>  <b>Detection Time: <\/b> 2023-09-20 17:00 UTC<br\/>  <b>Sensor: <\/b> NOAA-20 VIIRS<br\/> <b>Confidence: <\/b> Nominal<br\/>  <b>Day\/Night: <\/b> Day<br\/> <b>Scan: <\/b> 0.6 km<br\/> <b>Track: <\/b> 0.7 km<br\/> <b>FRP: <\/b> 6.96 MW<br\/> <b>Brightness: <\/b> 328.42 K" }, "geometry": { "type": "Point", "coordinates": [ -79.80667, 43.26074, 0.0 ] } },
{ "type": "Feature", "properties": { "Name": "Fire Detection Centroid ", "Description": "<b>Latitude: <\/b> 18.30878<br\/>  <b>Longitude: <\/b> -64.88521<br\/>  <b>Detection Time: <\/b> 2023-09-20 16:52 UTC<br\/>  <b>Sensor: <\/b> NOAA-20 VIIRS<br\/> <b>Confidence: <\/b> Nominal<br\/>  <b>Day\/Night: <\/b> Day<br\/> <b>Scan: <\/b> 0.4 km<br\/> <b>Track: <\/b> 0.6 km<br\/> <b>FRP: <\/b> 8.25 MW<br\/> <b>Brightness: <\/b> 337 K" }, "geometry": { "type": "Point", "coordinates": [ -64.88521, 18.30878, 0.0 ] } }
]
}
