{
"type": "FeatureCollection",
"crs": { "type": "name", "properties": { "name": "urn:ogc:def:crs:OGC:1.3:CRS84" } },
"features": [
{ "type": "Feature", "properties": { "Name": "Fire Detection Centroid ", "Description": "<b>Latitude: <\/b> 48.18914<br\/>  <b>Longitude: <\/b> -64.92301<br\/>  <b>Detection Time: <\/b> 2022-09-11 05:45 UTC<br\/>  <b>Sensor: <\/b> NOAA-20 VIIRS<br\/> <b>Confidence: <\/b> Nominal<br\/>  <b>Day\/Night: <\/b> Night<br\/> <b>Scan: <\/b> 0.5 km<br\/> <b>Track: <\/b> 0.5 km<br\/> <b>FRP: <\/b> 1.76 MW<br\/> <b>Brightness: <\/b> 308.11 K" }, "geometry": { "type": "Point", "coordinates": [ -64.92301, 48.18914, 0.0 ] } }
]
}
