{
"type": "FeatureCollection",
"crs": { "type": "name", "properties": { "name": "urn:ogc:def:crs:OGC:1.3:CRS84" } },
"features": [
{ "type": "Feature", "properties": { "Name": "Fire Detection Centroid ", "Description": "<b>Latitude: <\/b> 45.28234<br\/>  <b>Longitude: <\/b> -66.01639<br\/>  <b>Detection Time: <\/b> 2023-05-20 05:41 UTC<br\/>  <b>Sensor: <\/b> NOAA-20 VIIRS<br\/> <b>Confidence: <\/b> Nominal<br\/>  <b>Day\/Night: <\/b> Night<br\/> <b>Scan: <\/b> 0.6 km<br\/> <b>Track: <\/b> 0.5 km<br\/> <b>FRP: <\/b> 1.93 MW<br\/> <b>Brightness: <\/b> 297.06 K" }, "geometry": { "type": "Point", "coordinates": [ -66.01639, 45.28234, 0.0 ] } },
{ "type": "Feature", "properties": { "Name": "Fire Detection Centroid ", "Description": "<b>Latitude: <\/b> 48.18968<br\/>  <b>Longitude: <\/b> -64.92265<br\/>  <b>Detection Time: <\/b> 2023-05-20 05:40 UTC<br\/>  <b>Sensor: <\/b> NOAA-20 VIIRS<br\/> <b>Confidence: <\/b> Nominal<br\/>  <b>Day\/Night: <\/b> Night<br\/> <b>Scan: <\/b> 0.6 km<br\/> <b>Track: <\/b> 0.5 km<br\/> <b>FRP: <\/b> 0.99 MW<br\/> <b>Brightness: <\/b> 297.12 K" }, "geometry": { "type": "Point", "coordinates": [ -64.92265, 48.18968, 0.0 ] } }
]
}
