{
"type": "FeatureCollection",
"crs": { "type": "name", "properties": { "name": "urn:ogc:def:crs:OGC:1.3:CRS84" } },
"features": [
{ "type": "Feature", "properties": { "Name": "Fire Detection Centroid ", "Description": "<b>Latitude: <\/b> 19.82544<br\/>  <b>Longitude: <\/b> -155.47725<br\/>  <b>Detection Time: <\/b> 2023-05-21 23:26 UTC<br\/>  <b>Sensor: <\/b> NOAA-20 VIIRS<br\/> <b>Confidence: <\/b> Nominal<br\/>  <b>Day\/Night: <\/b> Day<br\/> <b>Scan: <\/b> 0.42 km<br\/> <b>Track: <\/b> 0.38 km<br\/> <b>FRP: <\/b> 9.12 MW<br\/> <b>Brightness: <\/b> 336.14 K" }, "geometry": { "type": "Point", "coordinates": [ -155.47725, 19.82544, 0.0 ] } }
]
}
