{
"type": "FeatureCollection",
"crs": { "type": "name", "properties": { "name": "urn:ogc:def:crs:OGC:1.3:CRS84" } },
"features": [
{ "type": "Feature", "properties": { "Name": "Fire Detection Centroid ", "Description": "<b>Latitude: <\/b> 49.8711<br\/>  <b>Longitude: <\/b> -114.27567<br\/>  <b>Detection Time: <\/b> 2024-02-05 10:48 UTC<br\/>  <b>Sensor: <\/b> NOAA-20 VIIRS<br\/> <b>Confidence: <\/b> Nominal<br\/>  <b>Day\/Night: <\/b> Night<br\/> <b>Scan: <\/b> 0.4 km<br\/> <b>Track: <\/b> 0.6 km<br\/> <b>FRP: <\/b> 3.89 MW<br\/> <b>Brightness: <\/b> 332.04 K" }, "geometry": { "type": "Point", "coordinates": [ -114.27567, 49.8711, 0.0 ] } },
{ "type": "Feature", "properties": { "Name": "Fire Detection Centroid ", "Description": "<b>Latitude: <\/b> 49.68501<br\/>  <b>Longitude: <\/b> -114.42407<br\/>  <b>Detection Time: <\/b> 2024-02-05 10:48 UTC<br\/>  <b>Sensor: <\/b> NOAA-20 VIIRS<br\/> <b>Confidence: <\/b> Nominal<br\/>  <b>Day\/Night: <\/b> Night<br\/> <b>Scan: <\/b> 0.4 km<br\/> <b>Track: <\/b> 0.6 km<br\/> <b>FRP: <\/b> 6.04 MW<br\/> <b>Brightness: <\/b> 337.3 K" }, "geometry": { "type": "Point", "coordinates": [ -114.42407, 49.68501, 0.0 ] } },
{ "type": "Feature", "properties": { "Name": "Fire Detection Centroid ", "Description": "<b>Latitude: <\/b> 49.86915<br\/>  <b>Longitude: <\/b> -114.26952<br\/>  <b>Detection Time: <\/b> 2024-02-05 10:48 UTC<br\/>  <b>Sensor: <\/b> NOAA-20 VIIRS<br\/> <b>Confidence: <\/b> Nominal<br\/>  <b>Day\/Night: <\/b> Night<br\/> <b>Scan: <\/b> 0.4 km<br\/> <b>Track: <\/b> 0.6 km<br\/> <b>FRP: <\/b> 3.89 MW<br\/> <b>Brightness: <\/b> 334.56 K" }, "geometry": { "type": "Point", "coordinates": [ -114.26952, 49.86915, 0.0 ] } },
{ "type": "Feature", "properties": { "Name": "Fire Detection Centroid ", "Description": "<b>Latitude: <\/b> 49.80293<br\/>  <b>Longitude: <\/b> -114.32565<br\/>  <b>Detection Time: <\/b> 2024-02-05 10:47 UTC<br\/>  <b>Sensor: <\/b> NOAA-20 VIIRS<br\/> <b>Confidence: <\/b> Nominal<br\/>  <b>Day\/Night: <\/b> Night<br\/> <b>Scan: <\/b> 0.43 km<br\/> <b>Track: <\/b> 0.62 km<br\/> <b>FRP: <\/b> 3.9 MW<br\/> <b>Brightness: <\/b> 334.56 K" }, "geometry": { "type": "Point", "coordinates": [ -114.32565, 49.80293, 0.0 ] } },
{ "type": "Feature", "properties": { "Name": "Fire Detection Centroid ", "Description": "<b>Latitude: <\/b> 49.80038<br\/>  <b>Longitude: <\/b> -114.32983<br\/>  <b>Detection Time: <\/b> 2024-02-05 10:47 UTC<br\/>  <b>Sensor: <\/b> NOAA-20 VIIRS<br\/> <b>Confidence: <\/b> Nominal<br\/>  <b>Day\/Night: <\/b> Night<br\/> <b>Scan: <\/b> 0.43 km<br\/> <b>Track: <\/b> 0.62 km<br\/> <b>FRP: <\/b> 6.05 MW<br\/> <b>Brightness: <\/b> 337.3 K" }, "geometry": { "type": "Point", "coordinates": [ -114.32983, 49.80038, 0.0 ] } },
{ "type": "Feature", "properties": { "Name": "Fire Detection Centroid ", "Description": "<b>Latitude: <\/b> 49.80485<br\/>  <b>Longitude: <\/b> -114.33159<br\/>  <b>Detection Time: <\/b> 2024-02-05 10:47 UTC<br\/>  <b>Sensor: <\/b> NOAA-20 VIIRS<br\/> <b>Confidence: <\/b> Nominal<br\/>  <b>Day\/Night: <\/b> Night<br\/> <b>Scan: <\/b> 0.43 km<br\/> <b>Track: <\/b> 0.62 km<br\/> <b>FRP: <\/b> 3.9 MW<br\/> <b>Brightness: <\/b> 332.04 K" }, "geometry": { "type": "Point", "coordinates": [ -114.33159, 49.80485, 0.0 ] } }
]
}
