{
"type": "FeatureCollection",
"crs": { "type": "name", "properties": { "name": "urn:ogc:def:crs:OGC:1.3:CRS84" } },
"features": [
{ "type": "Feature", "properties": { "Name": "Fire Detection Centroid ", "Description": "<b>Latitude: <\/b> 37.95731<br\/>  <b>Longitude: <\/b> -122.19808<br\/>  <b>Detection Time: <\/b> 2024-02-15 11:05 UTC<br\/>  <b>Sensor: <\/b> NOAA-20 VIIRS<br\/> <b>Confidence: <\/b> Nominal<br\/>  <b>Day\/Night: <\/b> Night<br\/> <b>Scan: <\/b> 0.6 km<br\/> <b>Track: <\/b> 0.7 km<br\/> <b>FRP: <\/b> 1.24 MW<br\/> <b>Brightness: <\/b> 295.31 K" }, "geometry": { "type": "Point", "coordinates": [ -122.19808, 37.95731, 0.0 ] } },
{ "type": "Feature", "properties": { "Name": "Fire Detection Centroid ", "Description": "<b>Latitude: <\/b> 38.07265<br\/>  <b>Longitude: <\/b> -122.13896<br\/>  <b>Detection Time: <\/b> 2024-02-15 11:04 UTC<br\/>  <b>Sensor: <\/b> NOAA-20 VIIRS<br\/> <b>Confidence: <\/b> Nominal<br\/>  <b>Day\/Night: <\/b> Night<br\/> <b>Scan: <\/b> 0.62 km<br\/> <b>Track: <\/b> 0.72 km<br\/> <b>FRP: <\/b> 1.25 MW<br\/> <b>Brightness: <\/b> 295.31 K" }, "geometry": { "type": "Point", "coordinates": [ -122.13896, 38.07265, 0.0 ] } }
]
}
