{
"type": "FeatureCollection",
"crs": { "type": "name", "properties": { "name": "urn:ogc:def:crs:OGC:1.3:CRS84" } },
"features": [
{ "type": "Feature", "properties": { "Name": "Fire Detection Centroid ", "Description": "<b>Latitude: <\/b> 48.18864<br\/>  <b>Longitude: <\/b> -64.9257<br\/>  <b>Detection Time: <\/b> 2023-07-24 05:21 UTC<br\/>  <b>Sensor: <\/b> NOAA-20 VIIRS<br\/> <b>Confidence: <\/b> Nominal<br\/>  <b>Day\/Night: <\/b> Night<br\/> <b>Scan: <\/b> 0.5 km<br\/> <b>Track: <\/b> 0.6 km<br\/> <b>FRP: <\/b> 0.85 MW<br\/> <b>Brightness: <\/b> 296.97 K" }, "geometry": { "type": "Point", "coordinates": [ -64.9257, 48.18864, 0.0 ] } },
{ "type": "Feature", "properties": { "Name": "Fire Detection Centroid ", "Description": "<b>Latitude: <\/b> 48.18853<br\/>  <b>Longitude: <\/b> -64.91878<br\/>  <b>Detection Time: <\/b> 2023-07-24 05:21 UTC<br\/>  <b>Sensor: <\/b> NOAA-20 VIIRS<br\/> <b>Confidence: <\/b> Nominal<br\/>  <b>Day\/Night: <\/b> Night<br\/> <b>Scan: <\/b> 0.5 km<br\/> <b>Track: <\/b> 0.6 km<br\/> <b>FRP: <\/b> 0.97 MW<br\/> <b>Brightness: <\/b> 298.03 K" }, "geometry": { "type": "Point", "coordinates": [ -64.91878, 48.18853, 0.0 ] } }
]
}
