{
"type": "FeatureCollection",
"crs": { "type": "name", "properties": { "name": "urn:ogc:def:crs:OGC:1.3:CRS84" } },
"features": [
{ "type": "Feature", "properties": { "Name": "Fire Detection Centroid ", "Description": "<b>Latitude: <\/b> 19.40804<br\/>  <b>Longitude: <\/b> -155.28622<br\/>  <b>Detection Time: <\/b> 2022-11-15 23:33 UTC<br\/>  <b>Sensor: <\/b> NOAA-20 VIIRS<br\/> <b>Confidence: <\/b> Nominal<br\/>  <b>Day\/Night: <\/b> Day<br\/> <b>Scan: <\/b> 0.39 km<br\/> <b>Track: <\/b> 0.36 km<br\/> <b>FRP: <\/b> 73.23 MW<br\/> <b>Brightness: <\/b> 340.39 K" }, "geometry": { "type": "Point", "coordinates": [ -155.28622, 19.40804, 0.0 ] } },
{ "type": "Feature", "properties": { "Name": "Fire Detection Centroid ", "Description": "<b>Latitude: <\/b> 19.40531<br\/>  <b>Longitude: <\/b> -155.28201<br\/>  <b>Detection Time: <\/b> 2022-11-15 23:33 UTC<br\/>  <b>Sensor: <\/b> NOAA-20 VIIRS<br\/> <b>Confidence: <\/b> Nominal<br\/>  <b>Day\/Night: <\/b> Day<br\/> <b>Scan: <\/b> 0.39 km<br\/> <b>Track: <\/b> 0.36 km<br\/> <b>FRP: <\/b> 73.23 MW<br\/> <b>Brightness: <\/b> 345.7 K" }, "geometry": { "type": "Point", "coordinates": [ -155.28201, 19.40531, 0.0 ] } },
{ "type": "Feature", "properties": { "Name": "Fire Detection Centroid ", "Description": "<b>Latitude: <\/b> 19.40475<br\/>  <b>Longitude: <\/b> -155.28566<br\/>  <b>Detection Time: <\/b> 2022-11-15 23:33 UTC<br\/>  <b>Sensor: <\/b> NOAA-20 VIIRS<br\/> <b>Confidence: <\/b> High<br\/>  <b>Day\/Night: <\/b> Day<br\/> <b>Scan: <\/b> 0.39 km<br\/> <b>Track: <\/b> 0.36 km<br\/> <b>FRP: <\/b> 73.23 MW<br\/> <b>Brightness: <\/b> 367 K" }, "geometry": { "type": "Point", "coordinates": [ -155.28566, 19.40475, 0.0 ] } },
{ "type": "Feature", "properties": { "Name": "Fire Detection Centroid ", "Description": "<b>Latitude: <\/b> 19.4076<br\/>  <b>Longitude: <\/b> -155.28662<br\/>  <b>Detection Time: <\/b> 2022-11-15 23:31 UTC<br\/>  <b>Sensor: <\/b> NOAA-20 VIIRS<br\/> <b>Confidence: <\/b> Nominal<br\/>  <b>Day\/Night: <\/b> Day<br\/> <b>Scan: <\/b> 0.4 km<br\/> <b>Track: <\/b> 0.4 km<br\/> <b>FRP: <\/b> 73.23 MW<br\/> <b>Brightness: <\/b> 340.39 K" }, "geometry": { "type": "Point", "coordinates": [ -155.28662, 19.4076, 0.0 ] } },
{ "type": "Feature", "properties": { "Name": "Fire Detection Centroid ", "Description": "<b>Latitude: <\/b> 19.40487<br\/>  <b>Longitude: <\/b> -155.28242<br\/>  <b>Detection Time: <\/b> 2022-11-15 23:31 UTC<br\/>  <b>Sensor: <\/b> NOAA-20 VIIRS<br\/> <b>Confidence: <\/b> Nominal<br\/>  <b>Day\/Night: <\/b> Day<br\/> <b>Scan: <\/b> 0.4 km<br\/> <b>Track: <\/b> 0.4 km<br\/> <b>FRP: <\/b> 73.23 MW<br\/> <b>Brightness: <\/b> 345.7 K" }, "geometry": { "type": "Point", "coordinates": [ -155.28242, 19.40487, 0.0 ] } },
{ "type": "Feature", "properties": { "Name": "Fire Detection Centroid ", "Description": "<b>Latitude: <\/b> 19.40431<br\/>  <b>Longitude: <\/b> -155.28607<br\/>  <b>Detection Time: <\/b> 2022-11-15 23:31 UTC<br\/>  <b>Sensor: <\/b> NOAA-20 VIIRS<br\/> <b>Confidence: <\/b> High<br\/>  <b>Day\/Night: <\/b> Day<br\/> <b>Scan: <\/b> 0.4 km<br\/> <b>Track: <\/b> 0.4 km<br\/> <b>FRP: <\/b> 73.23 MW<br\/> <b>Brightness: <\/b> 367 K" }, "geometry": { "type": "Point", "coordinates": [ -155.28607, 19.40431, 0.0 ] } }
]
}
