{
"type": "FeatureCollection",
"crs": { "type": "name", "properties": { "name": "urn:ogc:def:crs:OGC:1.3:CRS84" } },
"features": [
{ "type": "Feature", "properties": { "Name": "Fire Detection Centroid ", "Description": "<b>Latitude: <\/b> 20.00503<br\/>  <b>Longitude: <\/b> -155.30739<br\/>  <b>Detection Time: <\/b> 2023-04-21 22:48 UTC<br\/>  <b>Sensor: <\/b> NOAA-20 VIIRS<br\/> <b>Confidence: <\/b> Nominal<br\/>  <b>Day\/Night: <\/b> Day<br\/> <b>Scan: <\/b> 0.48 km<br\/> <b>Track: <\/b> 0.65 km<br\/> <b>FRP: <\/b> 2.23 MW<br\/> <b>Brightness: <\/b> 328.87 K" }, "geometry": { "type": "Point", "coordinates": [ -155.30739, 20.00503, 0.0 ] } }
]
}
