{
"type": "FeatureCollection",
"crs": { "type": "name", "properties": { "name": "urn:ogc:def:crs:OGC:1.3:CRS84" } },
"features": [
{ "type": "Feature", "properties": { "Name": "Fire Detection Centroid ", "Description": "<b>Latitude: <\/b> 43.5109<br\/>  <b>Longitude: <\/b> -121.67014<br\/>  <b>Detection Time: <\/b> 2024-01-09 10:57 UTC<br\/>  <b>Sensor: <\/b> NOAA-20 VIIRS<br\/> <b>Confidence: <\/b> Nominal<br\/>  <b>Day\/Night: <\/b> Night<br\/> <b>Scan: <\/b> 0.38 km<br\/> <b>Track: <\/b> 0.59 km<br\/> <b>FRP: <\/b> 1.89 MW<br\/> <b>Brightness: <\/b> 311.53 K" }, "geometry": { "type": "Point", "coordinates": [ -121.67014, 43.5109, 0.0 ] } },
{ "type": "Feature", "properties": { "Name": "Fire Detection Centroid ", "Description": "<b>Latitude: <\/b> 43.50964<br\/>  <b>Longitude: <\/b> -121.66566<br\/>  <b>Detection Time: <\/b> 2024-01-09 10:57 UTC<br\/>  <b>Sensor: <\/b> NOAA-20 VIIRS<br\/> <b>Confidence: <\/b> Nominal<br\/>  <b>Day\/Night: <\/b> Night<br\/> <b>Scan: <\/b> 0.38 km<br\/> <b>Track: <\/b> 0.59 km<br\/> <b>FRP: <\/b> 1.6 MW<br\/> <b>Brightness: <\/b> 299.86 K" }, "geometry": { "type": "Point", "coordinates": [ -121.66566, 43.50964, 0.0 ] } },
{ "type": "Feature", "properties": { "Name": "Fire Detection Centroid ", "Description": "<b>Latitude: <\/b> 43.51137<br\/>  <b>Longitude: <\/b> -121.66805<br\/>  <b>Detection Time: <\/b> 2024-01-09 10:57 UTC<br\/>  <b>Sensor: <\/b> NOAA-20 VIIRS<br\/> <b>Confidence: <\/b> Nominal<br\/>  <b>Day\/Night: <\/b> Night<br\/> <b>Scan: <\/b> 0.4 km<br\/> <b>Track: <\/b> 0.6 km<br\/> <b>FRP: <\/b> 1.89 MW<br\/> <b>Brightness: <\/b> 311.53 K" }, "geometry": { "type": "Point", "coordinates": [ -121.66805, 43.51137, 0.0 ] } },
{ "type": "Feature", "properties": { "Name": "Fire Detection Centroid ", "Description": "<b>Latitude: <\/b> 43.51012<br\/>  <b>Longitude: <\/b> -121.66362<br\/>  <b>Detection Time: <\/b> 2024-01-09 10:57 UTC<br\/>  <b>Sensor: <\/b> NOAA-20 VIIRS<br\/> <b>Confidence: <\/b> Nominal<br\/>  <b>Day\/Night: <\/b> Night<br\/> <b>Scan: <\/b> 0.4 km<br\/> <b>Track: <\/b> 0.6 km<br\/> <b>FRP: <\/b> 1.59 MW<br\/> <b>Brightness: <\/b> 299.86 K" }, "geometry": { "type": "Point", "coordinates": [ -121.66362, 43.51012, 0.0 ] } }
]
}
