{
"type": "FeatureCollection",
"crs": { "type": "name", "properties": { "name": "urn:ogc:def:crs:OGC:1.3:CRS84" } },
"features": [
{ "type": "Feature", "properties": { "Name": "Fire Detection Centroid ", "Description": "<b>Latitude: <\/b> 45.37816<br\/>  <b>Longitude: <\/b> -74.67894<br\/>  <b>Detection Time: <\/b> 2023-09-04 17:01 UTC<br\/>  <b>Sensor: <\/b> NOAA-20 VIIRS<br\/> <b>Confidence: <\/b> Nominal<br\/>  <b>Day\/Night: <\/b> Day<br\/> <b>Scan: <\/b> 0.3 km<br\/> <b>Track: <\/b> 0.5 km<br\/> <b>FRP: <\/b> 2.91 MW<br\/> <b>Brightness: <\/b> 331.82 K" }, "geometry": { "type": "Point", "coordinates": [ -74.67894, 45.37816, 0.0 ] } },
{ "type": "Feature", "properties": { "Name": "Fire Detection Centroid ", "Description": "<b>Latitude: <\/b> 45.37712<br\/>  <b>Longitude: <\/b> -74.68276<br\/>  <b>Detection Time: <\/b> 2023-09-04 17:01 UTC<br\/>  <b>Sensor: <\/b> NOAA-20 VIIRS<br\/> <b>Confidence: <\/b> Nominal<br\/>  <b>Day\/Night: <\/b> Day<br\/> <b>Scan: <\/b> 0.3 km<br\/> <b>Track: <\/b> 0.5 km<br\/> <b>FRP: <\/b> 2.91 MW<br\/> <b>Brightness: <\/b> 341.01 K" }, "geometry": { "type": "Point", "coordinates": [ -74.68276, 45.37712, 0.0 ] } },
{ "type": "Feature", "properties": { "Name": "Fire Detection Centroid ", "Description": "<b>Latitude: <\/b> 46.04052<br\/>  <b>Longitude: <\/b> -73.14162<br\/>  <b>Detection Time: <\/b> 2023-09-04 17:01 UTC<br\/>  <b>Sensor: <\/b> NOAA-20 VIIRS<br\/> <b>Confidence: <\/b> Low<br\/>  <b>Day\/Night: <\/b> Day<br\/> <b>Scan: <\/b> 0.5 km<br\/> <b>Track: <\/b> 0.5 km<br\/> <b>FRP: <\/b> 3.85 MW<br\/> <b>Brightness: <\/b> 328.31 K" }, "geometry": { "type": "Point", "coordinates": [ -73.14162, 46.04052, 0.0 ] } },
{ "type": "Feature", "properties": { "Name": "Fire Detection Centroid ", "Description": "<b>Latitude: <\/b> 45.18625<br\/>  <b>Longitude: <\/b> -74.62452<br\/>  <b>Detection Time: <\/b> 2023-09-04 17:01 UTC<br\/>  <b>Sensor: <\/b> NOAA-20 VIIRS<br\/> <b>Confidence: <\/b> High<br\/>  <b>Day\/Night: <\/b> Day<br\/> <b>Scan: <\/b> 0.3 km<br\/> <b>Track: <\/b> 0.5 km<br\/> <b>FRP: <\/b> 5.25 MW<br\/> <b>Brightness: <\/b> 367 K" }, "geometry": { "type": "Point", "coordinates": [ -74.62452, 45.18625, 0.0 ] } },
{ "type": "Feature", "properties": { "Name": "Fire Detection Centroid ", "Description": "<b>Latitude: <\/b> 42.80388<br\/>  <b>Longitude: <\/b> -80.09218<br\/>  <b>Detection Time: <\/b> 2023-09-04 17:00 UTC<br\/>  <b>Sensor: <\/b> NOAA-20 VIIRS<br\/> <b>Confidence: <\/b> Nominal<br\/>  <b>Day\/Night: <\/b> Day<br\/> <b>Scan: <\/b> 0.7 km<br\/> <b>Track: <\/b> 0.7 km<br\/> <b>FRP: <\/b> 11.49 MW<br\/> <b>Brightness: <\/b> 332.04 K" }, "geometry": { "type": "Point", "coordinates": [ -80.09218, 42.80388, 0.0 ] } },
{ "type": "Feature", "properties": { "Name": "Fire Detection Centroid ", "Description": "<b>Latitude: <\/b> 43.27277<br\/>  <b>Longitude: <\/b> -79.79748<br\/>  <b>Detection Time: <\/b> 2023-09-04 17:00 UTC<br\/>  <b>Sensor: <\/b> NOAA-20 VIIRS<br\/> <b>Confidence: <\/b> Nominal<br\/>  <b>Day\/Night: <\/b> Day<br\/> <b>Scan: <\/b> 0.6 km<br\/> <b>Track: <\/b> 0.7 km<br\/> <b>FRP: <\/b> 5.07 MW<br\/> <b>Brightness: <\/b> 328.01 K" }, "geometry": { "type": "Point", "coordinates": [ -79.79748, 43.27277, 0.0 ] } },
{ "type": "Feature", "properties": { "Name": "Fire Detection Centroid ", "Description": "<b>Latitude: <\/b> 43.27042<br\/>  <b>Longitude: <\/b> -79.80457<br\/>  <b>Detection Time: <\/b> 2023-09-04 17:00 UTC<br\/>  <b>Sensor: <\/b> NOAA-20 VIIRS<br\/> <b>Confidence: <\/b> Nominal<br\/>  <b>Day\/Night: <\/b> Day<br\/> <b>Scan: <\/b> 0.6 km<br\/> <b>Track: <\/b> 0.7 km<br\/> <b>FRP: <\/b> 5.07 MW<br\/> <b>Brightness: <\/b> 331.09 K" }, "geometry": { "type": "Point", "coordinates": [ -79.80457, 43.27042, 0.0 ] } },
{ "type": "Feature", "properties": { "Name": "Fire Detection Centroid ", "Description": "<b>Latitude: <\/b> 19.41369<br\/>  <b>Longitude: <\/b> -155.284<br\/>  <b>Detection Time: <\/b> 2023-09-04 12:27 UTC<br\/>  <b>Sensor: <\/b> NOAA-20 VIIRS<br\/> <b>Confidence: <\/b> Nominal<br\/>  <b>Day\/Night: <\/b> Night<br\/> <b>Scan: <\/b> 0.52 km<br\/> <b>Track: <\/b> 0.5 km<br\/> <b>FRP: <\/b> 6.22 MW<br\/> <b>Brightness: <\/b> 306.96 K" }, "geometry": { "type": "Point", "coordinates": [ -155.284, 19.41369, 0.0 ] } }
]
}
