{
"type": "FeatureCollection",
"crs": { "type": "name", "properties": { "name": "urn:ogc:def:crs:OGC:1.3:CRS84" } },
"features": [
{ "type": "Feature", "properties": { "Name": "Fire Detection Centroid ", "Description": "<b>Latitude: <\/b> 19.40649<br\/>  <b>Longitude: <\/b> -155.2813<br\/>  <b>Detection Time: <\/b> 2023-11-20 11:44 UTC<br\/>  <b>Sensor: <\/b> NOAA-20 VIIRS<br\/> <b>Confidence: <\/b> Nominal<br\/>  <b>Day\/Night: <\/b> Night<br\/> <b>Scan: <\/b> 0.49 km<br\/> <b>Track: <\/b> 0.4 km<br\/> <b>FRP: <\/b> 2.83 MW<br\/> <b>Brightness: <\/b> 312.3 K" }, "geometry": { "type": "Point", "coordinates": [ -155.2813, 19.40649, 0.0 ] } },
{ "type": "Feature", "properties": { "Name": "Fire Detection Centroid ", "Description": "<b>Latitude: <\/b> 19.40713<br\/>  <b>Longitude: <\/b> -155.28592<br\/>  <b>Detection Time: <\/b> 2023-11-20 11:44 UTC<br\/>  <b>Sensor: <\/b> NOAA-20 VIIRS<br\/> <b>Confidence: <\/b> Nominal<br\/>  <b>Day\/Night: <\/b> Night<br\/> <b>Scan: <\/b> 0.49 km<br\/> <b>Track: <\/b> 0.41 km<br\/> <b>FRP: <\/b> 2.83 MW<br\/> <b>Brightness: <\/b> 305.69 K" }, "geometry": { "type": "Point", "coordinates": [ -155.28592, 19.40713, 0.0 ] } },
{ "type": "Feature", "properties": { "Name": "Fire Detection Centroid ", "Description": "<b>Latitude: <\/b> 19.40956<br\/>  <b>Longitude: <\/b> -155.27606<br\/>  <b>Detection Time: <\/b> 2023-11-20 11:44 UTC<br\/>  <b>Sensor: <\/b> NOAA-20 VIIRS<br\/> <b>Confidence: <\/b> Nominal<br\/>  <b>Day\/Night: <\/b> Night<br\/> <b>Scan: <\/b> 0.49 km<br\/> <b>Track: <\/b> 0.4 km<br\/> <b>FRP: <\/b> 5.24 MW<br\/> <b>Brightness: <\/b> 306.01 K" }, "geometry": { "type": "Point", "coordinates": [ -155.27606, 19.40956, 0.0 ] } },
{ "type": "Feature", "properties": { "Name": "Fire Detection Centroid ", "Description": "<b>Latitude: <\/b> 19.41083<br\/>  <b>Longitude: <\/b> -155.28529<br\/>  <b>Detection Time: <\/b> 2023-11-20 11:44 UTC<br\/>  <b>Sensor: <\/b> NOAA-20 VIIRS<br\/> <b>Confidence: <\/b> Nominal<br\/>  <b>Day\/Night: <\/b> Night<br\/> <b>Scan: <\/b> 0.49 km<br\/> <b>Track: <\/b> 0.41 km<br\/> <b>FRP: <\/b> 4.01 MW<br\/> <b>Brightness: <\/b> 311.62 K" }, "geometry": { "type": "Point", "coordinates": [ -155.28529, 19.41083, 0.0 ] } },
{ "type": "Feature", "properties": { "Name": "Fire Detection Centroid ", "Description": "<b>Latitude: <\/b> 19.4139<br\/>  <b>Longitude: <\/b> -155.28011<br\/>  <b>Detection Time: <\/b> 2023-11-20 11:44 UTC<br\/>  <b>Sensor: <\/b> NOAA-20 VIIRS<br\/> <b>Confidence: <\/b> Nominal<br\/>  <b>Day\/Night: <\/b> Night<br\/> <b>Scan: <\/b> 0.49 km<br\/> <b>Track: <\/b> 0.4 km<br\/> <b>FRP: <\/b> 4.01 MW<br\/> <b>Brightness: <\/b> 306.66 K" }, "geometry": { "type": "Point", "coordinates": [ -155.28011, 19.4139, 0.0 ] } },
{ "type": "Feature", "properties": { "Name": "Fire Detection Centroid ", "Description": "<b>Latitude: <\/b> 46.74903<br\/>  <b>Longitude: <\/b> -123.8435<br\/>  <b>Detection Time: <\/b> 2023-11-20 11:34 UTC<br\/>  <b>Sensor: <\/b> NOAA-20 VIIRS<br\/> <b>Confidence: <\/b> Nominal<br\/>  <b>Day\/Night: <\/b> Night<br\/> <b>Scan: <\/b> 0.64 km<br\/> <b>Track: <\/b> 0.72 km<br\/> <b>FRP: <\/b> 1.82 MW<br\/> <b>Brightness: <\/b> 301.29 K" }, "geometry": { "type": "Point", "coordinates": [ -123.8435, 46.74903, 0.0 ] } },
{ "type": "Feature", "properties": { "Name": "Fire Detection Centroid ", "Description": "<b>Latitude: <\/b> 46.75129<br\/>  <b>Longitude: <\/b> -123.84992<br\/>  <b>Detection Time: <\/b> 2023-11-20 11:34 UTC<br\/>  <b>Sensor: <\/b> NOAA-20 VIIRS<br\/> <b>Confidence: <\/b> Nominal<br\/>  <b>Day\/Night: <\/b> Night<br\/> <b>Scan: <\/b> 0.64 km<br\/> <b>Track: <\/b> 0.72 km<br\/> <b>FRP: <\/b> 1.82 MW<br\/> <b>Brightness: <\/b> 304 K" }, "geometry": { "type": "Point", "coordinates": [ -123.84992, 46.75129, 0.0 ] } },
{ "type": "Feature", "properties": { "Name": "Fire Detection Centroid ", "Description": "<b>Latitude: <\/b> 46.75029<br\/>  <b>Longitude: <\/b> -123.8506<br\/>  <b>Detection Time: <\/b> 2023-11-20 11:34 UTC<br\/>  <b>Sensor: <\/b> NOAA-20 VIIRS<br\/> <b>Confidence: <\/b> Nominal<br\/>  <b>Day\/Night: <\/b> Night<br\/> <b>Scan: <\/b> 0.64 km<br\/> <b>Track: <\/b> 0.72 km<br\/> <b>FRP: <\/b> 2.33 MW<br\/> <b>Brightness: <\/b> 310.58 K" }, "geometry": { "type": "Point", "coordinates": [ -123.8506, 46.75029, 0.0 ] } }
]
}
