{
"type": "FeatureCollection",
"crs": { "type": "name", "properties": { "name": "urn:ogc:def:crs:OGC:1.3:CRS84" } },
"features": [
{ "type": "Feature", "properties": { "Name": "Fire Detection Centroid ", "Description": "<b>Latitude: <\/b> 19.40433<br\/>  <b>Longitude: <\/b> -155.28471<br\/>  <b>Detection Time: <\/b> 2024-05-06 12:10 UTC<br\/>  <b>Sensor: <\/b> NOAA-20 VIIRS<br\/> <b>Confidence: <\/b> Nominal<br\/>  <b>Day\/Night: <\/b> Night<br\/> <b>Scan: <\/b> 0.44 km<br\/> <b>Track: <\/b> 0.38 km<br\/> <b>FRP: <\/b> 1.82 MW<br\/> <b>Brightness: <\/b> 300.33 K" }, "geometry": { "type": "Point", "coordinates": [ -155.28471, 19.40433, 0.0 ] } },
{ "type": "Feature", "properties": { "Name": "Fire Detection Centroid ", "Description": "<b>Latitude: <\/b> 19.36612<br\/>  <b>Longitude: <\/b> -155.29166<br\/>  <b>Detection Time: <\/b> 2024-05-06 12:09 UTC<br\/>  <b>Sensor: <\/b> NOAA-20 VIIRS<br\/> <b>Confidence: <\/b> Nominal<br\/>  <b>Day\/Night: <\/b> Night<br\/> <b>Scan: <\/b> 0.4 km<br\/> <b>Track: <\/b> 0.4 km<br\/> <b>FRP: <\/b> 1.81 MW<br\/> <b>Brightness: <\/b> 300.33 K" }, "geometry": { "type": "Point", "coordinates": [ -155.29166, 19.36612, 0.0 ] } }
]
}
