{
"type": "FeatureCollection",
"crs": { "type": "name", "properties": { "name": "urn:ogc:def:crs:OGC:1.3:CRS84" } },
"features": [
{ "type": "Feature", "properties": { "Name": "Fire Detection Centroid ", "Description": "<b>Latitude: <\/b> 18.52984<br\/>  <b>Longitude: <\/b> -69.3625<br\/>  <b>Detection Time: <\/b> 2024-04-30 05:36 UTC<br\/>  <b>Sensor: <\/b> NOAA-20 VIIRS<br\/> <b>Confidence: <\/b> Nominal<br\/>  <b>Day\/Night: <\/b> Night<br\/> <b>Scan: <\/b> 0.4 km<br\/> <b>Track: <\/b> 0.6 km<br\/> <b>FRP: <\/b> 1.26 MW<br\/> <b>Brightness: <\/b> 313.71 K" }, "geometry": { "type": "Point", "coordinates": [ -69.3625, 18.52984, 0.0 ] } },
{ "type": "Feature", "properties": { "Name": "Fire Detection Centroid ", "Description": "<b>Latitude: <\/b> 45.35543<br\/>  <b>Longitude: <\/b> -66.01607<br\/>  <b>Detection Time: <\/b> 2024-04-30 05:29 UTC<br\/>  <b>Sensor: <\/b> NOAA-20 VIIRS<br\/> <b>Confidence: <\/b> Nominal<br\/>  <b>Day\/Night: <\/b> Night<br\/> <b>Scan: <\/b> 0.4 km<br\/> <b>Track: <\/b> 0.6 km<br\/> <b>FRP: <\/b> 1.57 MW<br\/> <b>Brightness: <\/b> 324.27 K" }, "geometry": { "type": "Point", "coordinates": [ -66.01607, 45.35543, 0.0 ] } },
{ "type": "Feature", "properties": { "Name": "Fire Detection Centroid ", "Description": "<b>Latitude: <\/b> 45.35523<br\/>  <b>Longitude: <\/b> -66.01036<br\/>  <b>Detection Time: <\/b> 2024-04-30 05:29 UTC<br\/>  <b>Sensor: <\/b> NOAA-20 VIIRS<br\/> <b>Confidence: <\/b> Nominal<br\/>  <b>Day\/Night: <\/b> Night<br\/> <b>Scan: <\/b> 0.4 km<br\/> <b>Track: <\/b> 0.6 km<br\/> <b>FRP: <\/b> 1.57 MW<br\/> <b>Brightness: <\/b> 301.81 K" }, "geometry": { "type": "Point", "coordinates": [ -66.01036, 45.35523, 0.0 ] } },
{ "type": "Feature", "properties": { "Name": "Fire Detection Centroid ", "Description": "<b>Latitude: <\/b> 45.14944<br\/>  <b>Longitude: <\/b> -66.03252<br\/>  <b>Detection Time: <\/b> 2024-04-30 05:29 UTC<br\/>  <b>Sensor: <\/b> NOAA-20 VIIRS<br\/> <b>Confidence: <\/b> Nominal<br\/>  <b>Day\/Night: <\/b> Night<br\/> <b>Scan: <\/b> 0.4 km<br\/> <b>Track: <\/b> 0.6 km<br\/> <b>FRP: <\/b> 1.75 MW<br\/> <b>Brightness: <\/b> 308.15 K" }, "geometry": { "type": "Point", "coordinates": [ -66.03252, 45.14944, 0.0 ] } },
{ "type": "Feature", "properties": { "Name": "Fire Detection Centroid ", "Description": "<b>Latitude: <\/b> 45.14928<br\/>  <b>Longitude: <\/b> -66.02716<br\/>  <b>Detection Time: <\/b> 2024-04-30 05:29 UTC<br\/>  <b>Sensor: <\/b> NOAA-20 VIIRS<br\/> <b>Confidence: <\/b> Nominal<br\/>  <b>Day\/Night: <\/b> Night<br\/> <b>Scan: <\/b> 0.4 km<br\/> <b>Track: <\/b> 0.6 km<br\/> <b>FRP: <\/b> 2.1 MW<br\/> <b>Brightness: <\/b> 311.26 K" }, "geometry": { "type": "Point", "coordinates": [ -66.02716, 45.14928, 0.0 ] } }
]
}
