{
"type": "FeatureCollection",
"crs": { "type": "name", "properties": { "name": "urn:ogc:def:crs:OGC:1.3:CRS84" } },
"features": [
{ "type": "Feature", "properties": { "Name": "Fire Detection Centroid ", "Description": "<b>Latitude: <\/b> 19.60253<br\/>  <b>Longitude: <\/b> -71.01321<br\/>  <b>Detection Time: <\/b> 2023-10-11 05:48 UTC<br\/>  <b>Sensor: <\/b> NOAA-20 VIIRS<br\/> <b>Confidence: <\/b> Nominal<br\/>  <b>Day\/Night: <\/b> Night<br\/> <b>Scan: <\/b> 0.6 km<br\/> <b>Track: <\/b> 0.5 km<br\/> <b>FRP: <\/b> 1.36 MW<br\/> <b>Brightness: <\/b> 308.39 K" }, "geometry": { "type": "Point", "coordinates": [ -71.01321, 19.60253, 0.0 ] } },
{ "type": "Feature", "properties": { "Name": "Fire Detection Centroid ", "Description": "<b>Latitude: <\/b> 18.93037<br\/>  <b>Longitude: <\/b> -70.35208<br\/>  <b>Detection Time: <\/b> 2023-10-11 05:48 UTC<br\/>  <b>Sensor: <\/b> NOAA-20 VIIRS<br\/> <b>Confidence: <\/b> Nominal<br\/>  <b>Day\/Night: <\/b> Night<br\/> <b>Scan: <\/b> 0.6 km<br\/> <b>Track: <\/b> 0.5 km<br\/> <b>FRP: <\/b> 4.68 MW<br\/> <b>Brightness: <\/b> 335.2 K" }, "geometry": { "type": "Point", "coordinates": [ -70.35208, 18.93037, 0.0 ] } },
{ "type": "Feature", "properties": { "Name": "Fire Detection Centroid ", "Description": "<b>Latitude: <\/b> 46.04434<br\/>  <b>Longitude: <\/b> -73.14391<br\/>  <b>Detection Time: <\/b> 2023-10-11 05:40 UTC<br\/>  <b>Sensor: <\/b> NOAA-20 VIIRS<br\/> <b>Confidence: <\/b> Nominal<br\/>  <b>Day\/Night: <\/b> Night<br\/> <b>Scan: <\/b> 0.7 km<br\/> <b>Track: <\/b> 0.7 km<br\/> <b>FRP: <\/b> 1.66 MW<br\/> <b>Brightness: <\/b> 295.01 K" }, "geometry": { "type": "Point", "coordinates": [ -73.14391, 46.04434, 0.0 ] } }
]
}
