{
"type": "FeatureCollection",
"crs": { "type": "name", "properties": { "name": "urn:ogc:def:crs:OGC:1.3:CRS84" } },
"features": [
{ "type": "Feature", "properties": { "Name": "Fire Detection Centroid ", "Description": "<b>Latitude: <\/b> 35.0529<br\/>  <b>Longitude: <\/b> -90.16703<br\/>  <b>Detection Time: <\/b> 2024-01-26 07:18 UTC<br\/>  <b>Sensor: <\/b> NOAA-20 VIIRS<br\/> <b>Confidence: <\/b> Nominal<br\/>  <b>Day\/Night: <\/b> Night<br\/> <b>Scan: <\/b> 0.5 km<br\/> <b>Track: <\/b> 0.5 km<br\/> <b>FRP: <\/b> 0.8 MW<br\/> <b>Brightness: <\/b> 295.71 K" }, "geometry": { "type": "Point", "coordinates": [ -90.16703, 35.0529, 0.0 ] } },
{ "type": "Feature", "properties": { "Name": "Fire Detection Centroid ", "Description": "<b>Latitude: <\/b> 37.15997<br\/>  <b>Longitude: <\/b> -82.05578<br\/>  <b>Detection Time: <\/b> 2024-01-26 07:17 UTC<br\/>  <b>Sensor: <\/b> NOAA-20 VIIRS<br\/> <b>Confidence: <\/b> Nominal<br\/>  <b>Day\/Night: <\/b> Night<br\/> <b>Scan: <\/b> 0.4 km<br\/> <b>Track: <\/b> 0.4 km<br\/> <b>FRP: <\/b> 1.06 MW<br\/> <b>Brightness: <\/b> 303.3 K" }, "geometry": { "type": "Point", "coordinates": [ -82.05578, 37.15997, 0.0 ] } },
{ "type": "Feature", "properties": { "Name": "Fire Detection Centroid ", "Description": "<b>Latitude: <\/b> 37.40074<br\/>  <b>Longitude: <\/b> -81.25969<br\/>  <b>Detection Time: <\/b> 2024-01-26 07:17 UTC<br\/>  <b>Sensor: <\/b> NOAA-20 VIIRS<br\/> <b>Confidence: <\/b> Nominal<br\/>  <b>Day\/Night: <\/b> Night<br\/> <b>Scan: <\/b> 0.4 km<br\/> <b>Track: <\/b> 0.4 km<br\/> <b>FRP: <\/b> 0.71 MW<br\/> <b>Brightness: <\/b> 302.27 K" }, "geometry": { "type": "Point", "coordinates": [ -81.25969, 37.40074, 0.0 ] } },
{ "type": "Feature", "properties": { "Name": "Fire Detection Centroid ", "Description": "<b>Latitude: <\/b> 36.98567<br\/>  <b>Longitude: <\/b> -81.56866<br\/>  <b>Detection Time: <\/b> 2024-01-26 07:17 UTC<br\/>  <b>Sensor: <\/b> NOAA-20 VIIRS<br\/> <b>Confidence: <\/b> Nominal<br\/>  <b>Day\/Night: <\/b> Night<br\/> <b>Scan: <\/b> 0.4 km<br\/> <b>Track: <\/b> 0.4 km<br\/> <b>FRP: <\/b> 0.57 MW<br\/> <b>Brightness: <\/b> 295.43 K" }, "geometry": { "type": "Point", "coordinates": [ -81.56866, 36.98567, 0.0 ] } },
{ "type": "Feature", "properties": { "Name": "Fire Detection Centroid ", "Description": "<b>Latitude: <\/b> 37.16062<br\/>  <b>Longitude: <\/b> -82.06007<br\/>  <b>Detection Time: <\/b> 2024-01-26 07:17 UTC<br\/>  <b>Sensor: <\/b> NOAA-20 VIIRS<br\/> <b>Confidence: <\/b> Nominal<br\/>  <b>Day\/Night: <\/b> Night<br\/> <b>Scan: <\/b> 0.4 km<br\/> <b>Track: <\/b> 0.4 km<br\/> <b>FRP: <\/b> 1.06 MW<br\/> <b>Brightness: <\/b> 302.45 K" }, "geometry": { "type": "Point", "coordinates": [ -82.06007, 37.16062, 0.0 ] } },
{ "type": "Feature", "properties": { "Name": "Fire Detection Centroid ", "Description": "<b>Latitude: <\/b> 18.39457<br\/>  <b>Longitude: <\/b> -71.72672<br\/>  <b>Detection Time: <\/b> 2024-01-26 05:42 UTC<br\/>  <b>Sensor: <\/b> NOAA-20 VIIRS<br\/> <b>Confidence: <\/b> Nominal<br\/>  <b>Day\/Night: <\/b> Night<br\/> <b>Scan: <\/b> 0.4 km<br\/> <b>Track: <\/b> 0.6 km<br\/> <b>FRP: <\/b> 1.37 MW<br\/> <b>Brightness: <\/b> 299.88 K" }, "geometry": { "type": "Point", "coordinates": [ -71.72672, 18.39457, 0.0 ] } },
{ "type": "Feature", "properties": { "Name": "Fire Detection Centroid ", "Description": "<b>Latitude: <\/b> 20.37536<br\/>  <b>Longitude: <\/b> -75.43812<br\/>  <b>Detection Time: <\/b> 2024-01-26 05:41 UTC<br\/>  <b>Sensor: <\/b> NOAA-20 VIIRS<br\/> <b>Confidence: <\/b> Nominal<br\/>  <b>Day\/Night: <\/b> Night<br\/> <b>Scan: <\/b> 0.8 km<br\/> <b>Track: <\/b> 0.8 km<br\/> <b>FRP: <\/b> 2.81 MW<br\/> <b>Brightness: <\/b> 310.31 K" }, "geometry": { "type": "Point", "coordinates": [ -75.43812, 20.37536, 0.0 ] } },
{ "type": "Feature", "properties": { "Name": "Fire Detection Centroid ", "Description": "<b>Latitude: <\/b> 18.76528<br\/>  <b>Longitude: <\/b> -70.98623<br\/>  <b>Detection Time: <\/b> 2024-01-26 05:41 UTC<br\/>  <b>Sensor: <\/b> NOAA-20 VIIRS<br\/> <b>Confidence: <\/b> Nominal<br\/>  <b>Day\/Night: <\/b> Night<br\/> <b>Scan: <\/b> 0.4 km<br\/> <b>Track: <\/b> 0.6 km<br\/> <b>FRP: <\/b> 3.5 MW<br\/> <b>Brightness: <\/b> 337.73 K" }, "geometry": { "type": "Point", "coordinates": [ -70.98623, 18.76528, 0.0 ] } },
{ "type": "Feature", "properties": { "Name": "Fire Detection Centroid ", "Description": "<b>Latitude: <\/b> 20.1742<br\/>  <b>Longitude: <\/b> -75.21255<br\/>  <b>Detection Time: <\/b> 2024-01-26 05:41 UTC<br\/>  <b>Sensor: <\/b> NOAA-20 VIIRS<br\/> <b>Confidence: <\/b> Nominal<br\/>  <b>Day\/Night: <\/b> Night<br\/> <b>Scan: <\/b> 0.8 km<br\/> <b>Track: <\/b> 0.8 km<br\/> <b>FRP: <\/b> 0.82 MW<br\/> <b>Brightness: <\/b> 301.78 K" }, "geometry": { "type": "Point", "coordinates": [ -75.21255, 20.1742, 0.0 ] } }
]
}
