{
"type": "FeatureCollection",
"crs": { "type": "name", "properties": { "name": "urn:ogc:def:crs:OGC:1.3:CRS84" } },
"features": [
{ "type": "Feature", "properties": { "Name": "Fire Detection Centroid ", "Description": "<b>Latitude: <\/b> 18.51553<br\/>  <b>Longitude: <\/b> -68.48252<br\/>  <b>Detection Time: <\/b> 2024-04-19 05:43 UTC<br\/>  <b>Sensor: <\/b> NOAA-20 VIIRS<br\/> <b>Confidence: <\/b> Nominal<br\/>  <b>Day\/Night: <\/b> Night<br\/> <b>Scan: <\/b> 0.5 km<br\/> <b>Track: <\/b> 0.5 km<br\/> <b>FRP: <\/b> 1.15 MW<br\/> <b>Brightness: <\/b> 302.21 K" }, "geometry": { "type": "Point", "coordinates": [ -68.48252, 18.51553, 0.0 ] } },
{ "type": "Feature", "properties": { "Name": "Fire Detection Centroid ", "Description": "<b>Latitude: <\/b> 18.51498<br\/>  <b>Longitude: <\/b> -68.4777<br\/>  <b>Detection Time: <\/b> 2024-04-19 05:43 UTC<br\/>  <b>Sensor: <\/b> NOAA-20 VIIRS<br\/> <b>Confidence: <\/b> Nominal<br\/>  <b>Day\/Night: <\/b> Night<br\/> <b>Scan: <\/b> 0.5 km<br\/> <b>Track: <\/b> 0.5 km<br\/> <b>FRP: <\/b> 1.15 MW<br\/> <b>Brightness: <\/b> 304.41 K" }, "geometry": { "type": "Point", "coordinates": [ -68.4777, 18.51498, 0.0 ] } },
{ "type": "Feature", "properties": { "Name": "Fire Detection Centroid ", "Description": "<b>Latitude: <\/b> 18.72499<br\/>  <b>Longitude: <\/b> -68.45237<br\/>  <b>Detection Time: <\/b> 2024-04-19 05:43 UTC<br\/>  <b>Sensor: <\/b> NOAA-20 VIIRS<br\/> <b>Confidence: <\/b> Nominal<br\/>  <b>Day\/Night: <\/b> Night<br\/> <b>Scan: <\/b> 0.5 km<br\/> <b>Track: <\/b> 0.5 km<br\/> <b>FRP: <\/b> 1.71 MW<br\/> <b>Brightness: <\/b> 310.39 K" }, "geometry": { "type": "Point", "coordinates": [ -68.45237, 18.72499, 0.0 ] } }
]
}
