{
"type": "FeatureCollection",
"crs": { "type": "name", "properties": { "name": "urn:ogc:def:crs:OGC:1.3:CRS84" } },
"features": [
{ "type": "Feature", "properties": { "Name": "Fire Detection Centroid ", "Description": "<b>Latitude: <\/b> 19.88539<br\/>  <b>Longitude: <\/b> -155.8822<br\/>  <b>Detection Time: <\/b> 2023-08-28 12:57 UTC<br\/>  <b>Sensor: <\/b> NOAA-20 VIIRS<br\/> <b>Confidence: <\/b> Nominal<br\/>  <b>Day\/Night: <\/b> Night<br\/> <b>Scan: <\/b> 0.76 km<br\/> <b>Track: <\/b> 0.77 km<br\/> <b>FRP: <\/b> 1.59 MW<br\/> <b>Brightness: <\/b> 302.67 K" }, "geometry": { "type": "Point", "coordinates": [ -155.8822, 19.88539, 0.0 ] } },
{ "type": "Feature", "properties": { "Name": "Fire Detection Centroid ", "Description": "<b>Latitude: <\/b> 19.89153<br\/>  <b>Longitude: <\/b> -155.88403<br\/>  <b>Detection Time: <\/b> 2023-08-28 12:57 UTC<br\/>  <b>Sensor: <\/b> NOAA-20 VIIRS<br\/> <b>Confidence: <\/b> Nominal<br\/>  <b>Day\/Night: <\/b> Night<br\/> <b>Scan: <\/b> 0.76 km<br\/> <b>Track: <\/b> 0.77 km<br\/> <b>FRP: <\/b> 1.77 MW<br\/> <b>Brightness: <\/b> 300.25 K" }, "geometry": { "type": "Point", "coordinates": [ -155.88403, 19.89153, 0.0 ] } }
]
}
