{
"type": "FeatureCollection",
"crs": { "type": "name", "properties": { "name": "urn:ogc:def:crs:OGC:1.3:CRS84" } },
"features": [
{ "type": "Feature", "properties": { "Name": "Fire Detection Centroid ", "Description": "<b>Latitude: <\/b> 19.40403<br\/>  <b>Longitude: <\/b> -155.27986<br\/>  <b>Detection Time: <\/b> 2022-08-21 23:44 UTC<br\/>  <b>Sensor: <\/b> NOAA-20 VIIRS<br\/> <b>Confidence: <\/b> Nominal<br\/>  <b>Day\/Night: <\/b> Day<br\/> <b>Scan: <\/b> 0.43 km<br\/> <b>Track: <\/b> 0.38 km<br\/> <b>FRP: <\/b> 12.14 MW<br\/> <b>Brightness: <\/b> 345.65 K" }, "geometry": { "type": "Point", "coordinates": [ -155.27986, 19.40403, 0.0 ] } },
{ "type": "Feature", "properties": { "Name": "Fire Detection Centroid ", "Description": "<b>Latitude: <\/b> 19.40638<br\/>  <b>Longitude: <\/b> -155.2886<br\/>  <b>Detection Time: <\/b> 2022-08-21 23:44 UTC<br\/>  <b>Sensor: <\/b> NOAA-20 VIIRS<br\/> <b>Confidence: <\/b> High<br\/>  <b>Day\/Night: <\/b> Day<br\/> <b>Scan: <\/b> 0.43 km<br\/> <b>Track: <\/b> 0.38 km<br\/> <b>FRP: <\/b> 90.5 MW<br\/> <b>Brightness: <\/b> 367 K" }, "geometry": { "type": "Point", "coordinates": [ -155.2886, 19.40638, 0.0 ] } },
{ "type": "Feature", "properties": { "Name": "Fire Detection Centroid ", "Description": "<b>Latitude: <\/b> 19.40695<br\/>  <b>Longitude: <\/b> -155.28447<br\/>  <b>Detection Time: <\/b> 2022-08-21 23:44 UTC<br\/>  <b>Sensor: <\/b> NOAA-20 VIIRS<br\/> <b>Confidence: <\/b> Low<br\/>  <b>Day\/Night: <\/b> Day<br\/> <b>Scan: <\/b> 0.43 km<br\/> <b>Track: <\/b> 0.38 km<br\/> <b>FRP: <\/b> 90.5 MW<br\/> <b>Brightness: <\/b> 367 K" }, "geometry": { "type": "Point", "coordinates": [ -155.28447, 19.40695, 0.0 ] } },
{ "type": "Feature", "properties": { "Name": "Fire Detection Centroid ", "Description": "<b>Latitude: <\/b> 19.41042<br\/>  <b>Longitude: <\/b> -155.28505<br\/>  <b>Detection Time: <\/b> 2022-08-21 23:44 UTC<br\/>  <b>Sensor: <\/b> NOAA-20 VIIRS<br\/> <b>Confidence: <\/b> Low<br\/>  <b>Day\/Night: <\/b> Day<br\/> <b>Scan: <\/b> 0.43 km<br\/> <b>Track: <\/b> 0.38 km<br\/> <b>FRP: <\/b> 41.82 MW<br\/> <b>Brightness: <\/b> 352.57 K" }, "geometry": { "type": "Point", "coordinates": [ -155.28505, 19.41042, 0.0 ] } },
{ "type": "Feature", "properties": { "Name": "Fire Detection Centroid ", "Description": "<b>Latitude: <\/b> 19.40347<br\/>  <b>Longitude: <\/b> -155.28394<br\/>  <b>Detection Time: <\/b> 2022-08-21 23:44 UTC<br\/>  <b>Sensor: <\/b> NOAA-20 VIIRS<br\/> <b>Confidence: <\/b> Low<br\/>  <b>Day\/Night: <\/b> Day<br\/> <b>Scan: <\/b> 0.43 km<br\/> <b>Track: <\/b> 0.38 km<br\/> <b>FRP: <\/b> 90.5 MW<br\/> <b>Brightness: <\/b> 367 K" }, "geometry": { "type": "Point", "coordinates": [ -155.28394, 19.40347, 0.0 ] } }
]
}
