{
"type": "FeatureCollection",
"crs": { "type": "name", "properties": { "name": "urn:ogc:def:crs:OGC:1.3:CRS84" } },
"features": [
{ "type": "Feature", "properties": { "Name": "Fire Detection Centroid ", "Description": "<b>Latitude: <\/b> 47.56833<br\/>  <b>Longitude: <\/b> -122.34273<br\/>  <b>Detection Time: <\/b> 2023-06-03 11:21 UTC<br\/>  <b>Sensor: <\/b> NOAA-20 VIIRS<br\/> <b>Confidence: <\/b> Nominal<br\/>  <b>Day\/Night: <\/b> Night<br\/> <b>Scan: <\/b> 0.51 km<br\/> <b>Track: <\/b> 0.66 km<br\/> <b>FRP: <\/b> 0.91 MW<br\/> <b>Brightness: <\/b> 302.96 K" }, "geometry": { "type": "Point", "coordinates": [ -122.34273, 47.56833, 0.0 ] } },
{ "type": "Feature", "properties": { "Name": "Fire Detection Centroid ", "Description": "<b>Latitude: <\/b> 48.88506<br\/>  <b>Longitude: <\/b> -122.73694<br\/>  <b>Detection Time: <\/b> 2023-06-03 11:21 UTC<br\/>  <b>Sensor: <\/b> NOAA-20 VIIRS<br\/> <b>Confidence: <\/b> Nominal<br\/>  <b>Day\/Night: <\/b> Night<br\/> <b>Scan: <\/b> 0.44 km<br\/> <b>Track: <\/b> 0.62 km<br\/> <b>FRP: <\/b> 1.42 MW<br\/> <b>Brightness: <\/b> 296 K" }, "geometry": { "type": "Point", "coordinates": [ -122.73694, 48.88506, 0.0 ] } },
{ "type": "Feature", "properties": { "Name": "Fire Detection Centroid ", "Description": "<b>Latitude: <\/b> 49.15838<br\/>  <b>Longitude: <\/b> -123.00671<br\/>  <b>Detection Time: <\/b> 2023-06-03 11:21 UTC<br\/>  <b>Sensor: <\/b> NOAA-20 VIIRS<br\/> <b>Confidence: <\/b> Nominal<br\/>  <b>Day\/Night: <\/b> Night<br\/> <b>Scan: <\/b> 0.42 km<br\/> <b>Track: <\/b> 0.61 km<br\/> <b>FRP: <\/b> 0.76 MW<br\/> <b>Brightness: <\/b> 298.16 K" }, "geometry": { "type": "Point", "coordinates": [ -123.00671, 49.15838, 0.0 ] } },
{ "type": "Feature", "properties": { "Name": "Fire Detection Centroid ", "Description": "<b>Latitude: <\/b> 49.16199<br\/>  <b>Longitude: <\/b> -123.00299<br\/>  <b>Detection Time: <\/b> 2023-06-03 11:21 UTC<br\/>  <b>Sensor: <\/b> NOAA-20 VIIRS<br\/> <b>Confidence: <\/b> Nominal<br\/>  <b>Day\/Night: <\/b> Night<br\/> <b>Scan: <\/b> 0.42 km<br\/> <b>Track: <\/b> 0.61 km<br\/> <b>FRP: <\/b> 0.95 MW<br\/> <b>Brightness: <\/b> 295.01 K" }, "geometry": { "type": "Point", "coordinates": [ -123.00299, 49.16199, 0.0 ] } },
{ "type": "Feature", "properties": { "Name": "Fire Detection Centroid ", "Description": "<b>Latitude: <\/b> 47.57132<br\/>  <b>Longitude: <\/b> -122.37226<br\/>  <b>Detection Time: <\/b> 2023-06-03 11:21 UTC<br\/>  <b>Sensor: <\/b> NOAA-20 VIIRS<br\/> <b>Confidence: <\/b> Nominal<br\/>  <b>Day\/Night: <\/b> Night<br\/> <b>Scan: <\/b> 0.5 km<br\/> <b>Track: <\/b> 0.66 km<br\/> <b>FRP: <\/b> 0.66 MW<br\/> <b>Brightness: <\/b> 298.88 K" }, "geometry": { "type": "Point", "coordinates": [ -122.37226, 47.57132, 0.0 ] } }
]
}
