{
"type": "FeatureCollection",
"crs": { "type": "name", "properties": { "name": "urn:ogc:def:crs:OGC:1.3:CRS84" } },
"features": [
{ "type": "Feature", "properties": { "Name": "Fire Detection Centroid ", "Description": "<b>Latitude: <\/b> 19.40975<br\/>  <b>Longitude: <\/b> -155.27916<br\/>  <b>Detection Time: <\/b> 2022-08-21 00:03 UTC<br\/>  <b>Sensor: <\/b> NOAA-20 VIIRS<br\/> <b>Confidence: <\/b> Low<br\/>  <b>Day\/Night: <\/b> Day<br\/> <b>Scan: <\/b> 0.53 km<br\/> <b>Track: <\/b> 0.5 km<br\/> <b>FRP: <\/b> 37.2 MW<br\/> <b>Brightness: <\/b> 343.12 K" }, "geometry": { "type": "Point", "coordinates": [ -155.27916, 19.40975, 0.0 ] } },
{ "type": "Feature", "properties": { "Name": "Fire Detection Centroid ", "Description": "<b>Latitude: <\/b> 19.40859<br\/>  <b>Longitude: <\/b> -155.28946<br\/>  <b>Detection Time: <\/b> 2022-08-21 00:03 UTC<br\/>  <b>Sensor: <\/b> NOAA-20 VIIRS<br\/> <b>Confidence: <\/b> Nominal<br\/>  <b>Day\/Night: <\/b> Day<br\/> <b>Scan: <\/b> 0.53 km<br\/> <b>Track: <\/b> 0.5 km<br\/> <b>FRP: <\/b> 91.18 MW<br\/> <b>Brightness: <\/b> 355.24 K" }, "geometry": { "type": "Point", "coordinates": [ -155.28946, 19.40859, 0.0 ] } },
{ "type": "Feature", "properties": { "Name": "Fire Detection Centroid ", "Description": "<b>Latitude: <\/b> 19.40917<br\/>  <b>Longitude: <\/b> -155.28429<br\/>  <b>Detection Time: <\/b> 2022-08-21 00:03 UTC<br\/>  <b>Sensor: <\/b> NOAA-20 VIIRS<br\/> <b>Confidence: <\/b> Low<br\/>  <b>Day\/Night: <\/b> Day<br\/> <b>Scan: <\/b> 0.53 km<br\/> <b>Track: <\/b> 0.5 km<br\/> <b>FRP: <\/b> 91.18 MW<br\/> <b>Brightness: <\/b> 367 K" }, "geometry": { "type": "Point", "coordinates": [ -155.28429, 19.40917, 0.0 ] } },
{ "type": "Feature", "properties": { "Name": "Fire Detection Centroid ", "Description": "<b>Latitude: <\/b> 19.41375<br\/>  <b>Longitude: <\/b> -155.28505<br\/>  <b>Detection Time: <\/b> 2022-08-21 00:03 UTC<br\/>  <b>Sensor: <\/b> NOAA-20 VIIRS<br\/> <b>Confidence: <\/b> Nominal<br\/>  <b>Day\/Night: <\/b> Day<br\/> <b>Scan: <\/b> 0.53 km<br\/> <b>Track: <\/b> 0.5 km<br\/> <b>FRP: <\/b> 42.05 MW<br\/> <b>Brightness: <\/b> 353.63 K" }, "geometry": { "type": "Point", "coordinates": [ -155.28505, 19.41375, 0.0 ] } },
{ "type": "Feature", "properties": { "Name": "Fire Detection Centroid ", "Description": "<b>Latitude: <\/b> 19.39997<br\/>  <b>Longitude: <\/b> -155.28313<br\/>  <b>Detection Time: <\/b> 2022-08-21 00:03 UTC<br\/>  <b>Sensor: <\/b> NOAA-20 VIIRS<br\/> <b>Confidence: <\/b> Nominal<br\/>  <b>Day\/Night: <\/b> Day<br\/> <b>Scan: <\/b> 0.53 km<br\/> <b>Track: <\/b> 0.5 km<br\/> <b>FRP: <\/b> 29.31 MW<br\/> <b>Brightness: <\/b> 355.18 K" }, "geometry": { "type": "Point", "coordinates": [ -155.28313, 19.39997, 0.0 ] } },
{ "type": "Feature", "properties": { "Name": "Fire Detection Centroid ", "Description": "<b>Latitude: <\/b> 19.40401<br\/>  <b>Longitude: <\/b> -155.28868<br\/>  <b>Detection Time: <\/b> 2022-08-21 00:03 UTC<br\/>  <b>Sensor: <\/b> NOAA-20 VIIRS<br\/> <b>Confidence: <\/b> High<br\/>  <b>Day\/Night: <\/b> Day<br\/> <b>Scan: <\/b> 0.53 km<br\/> <b>Track: <\/b> 0.5 km<br\/> <b>FRP: <\/b> 91.18 MW<br\/> <b>Brightness: <\/b> 367 K" }, "geometry": { "type": "Point", "coordinates": [ -155.28868, 19.40401, 0.0 ] } },
{ "type": "Feature", "properties": { "Name": "Fire Detection Centroid ", "Description": "<b>Latitude: <\/b> 19.40458<br\/>  <b>Longitude: <\/b> -155.28358<br\/>  <b>Detection Time: <\/b> 2022-08-21 00:03 UTC<br\/>  <b>Sensor: <\/b> NOAA-20 VIIRS<br\/> <b>Confidence: <\/b> Nominal<br\/>  <b>Day\/Night: <\/b> Day<br\/> <b>Scan: <\/b> 0.53 km<br\/> <b>Track: <\/b> 0.5 km<br\/> <b>FRP: <\/b> 91.18 MW<br\/> <b>Brightness: <\/b> 350.27 K" }, "geometry": { "type": "Point", "coordinates": [ -155.28358, 19.40458, 0.0 ] } }
]
}
