{
"type": "FeatureCollection",
"crs": { "type": "name", "properties": { "name": "urn:ogc:def:crs:OGC:1.3:CRS84" } },
"features": [
{ "type": "Feature", "properties": { "Name": "Fire Detection Centroid ", "Description": "<b>Latitude: <\/b> 19.40555<br\/>  <b>Longitude: <\/b> -155.28699<br\/>  <b>Detection Time: <\/b> 2022-11-19 23:56 UTC<br\/>  <b>Sensor: <\/b> NOAA-20 VIIRS<br\/> <b>Confidence: <\/b> High<br\/>  <b>Day\/Night: <\/b> Day<br\/> <b>Scan: <\/b> 0.42 km<br\/> <b>Track: <\/b> 0.45 km<br\/> <b>FRP: <\/b> 141.65 MW<br\/> <b>Brightness: <\/b> 367 K" }, "geometry": { "type": "Point", "coordinates": [ -155.28699, 19.40555, 0.0 ] } },
{ "type": "Feature", "properties": { "Name": "Fire Detection Centroid ", "Description": "<b>Latitude: <\/b> 19.40139<br\/>  <b>Longitude: <\/b> -155.28645<br\/>  <b>Detection Time: <\/b> 2022-11-19 23:56 UTC<br\/>  <b>Sensor: <\/b> NOAA-20 VIIRS<br\/> <b>Confidence: <\/b> Nominal<br\/>  <b>Day\/Night: <\/b> Day<br\/> <b>Scan: <\/b> 0.42 km<br\/> <b>Track: <\/b> 0.45 km<br\/> <b>FRP: <\/b> 5.05 MW<br\/> <b>Brightness: <\/b> 337.57 K" }, "geometry": { "type": "Point", "coordinates": [ -155.28645, 19.40139, 0.0 ] } },
{ "type": "Feature", "properties": { "Name": "Fire Detection Centroid ", "Description": "<b>Latitude: <\/b> 19.40559<br\/>  <b>Longitude: <\/b> -155.28366<br\/>  <b>Detection Time: <\/b> 2022-11-19 23:56 UTC<br\/>  <b>Sensor: <\/b> NOAA-20 VIIRS<br\/> <b>Confidence: <\/b> Nominal<br\/>  <b>Day\/Night: <\/b> Day<br\/> <b>Scan: <\/b> 0.4 km<br\/> <b>Track: <\/b> 0.5 km<br\/> <b>FRP: <\/b> 31.4 MW<br\/> <b>Brightness: <\/b> 335.13 K" }, "geometry": { "type": "Point", "coordinates": [ -155.28366, 19.40559, 0.0 ] } },
{ "type": "Feature", "properties": { "Name": "Fire Detection Centroid ", "Description": "<b>Latitude: <\/b> 19.4051<br\/>  <b>Longitude: <\/b> -155.28772<br\/>  <b>Detection Time: <\/b> 2022-11-19 23:56 UTC<br\/>  <b>Sensor: <\/b> NOAA-20 VIIRS<br\/> <b>Confidence: <\/b> High<br\/>  <b>Day\/Night: <\/b> Day<br\/> <b>Scan: <\/b> 0.4 km<br\/> <b>Track: <\/b> 0.5 km<br\/> <b>FRP: <\/b> 141.65 MW<br\/> <b>Brightness: <\/b> 367 K" }, "geometry": { "type": "Point", "coordinates": [ -155.28772, 19.4051, 0.0 ] } },
{ "type": "Feature", "properties": { "Name": "Fire Detection Centroid ", "Description": "<b>Latitude: <\/b> 19.40094<br\/>  <b>Longitude: <\/b> -155.28719<br\/>  <b>Detection Time: <\/b> 2022-11-19 23:56 UTC<br\/>  <b>Sensor: <\/b> NOAA-20 VIIRS<br\/> <b>Confidence: <\/b> Nominal<br\/>  <b>Day\/Night: <\/b> Day<br\/> <b>Scan: <\/b> 0.4 km<br\/> <b>Track: <\/b> 0.5 km<br\/> <b>FRP: <\/b> 5.04 MW<br\/> <b>Brightness: <\/b> 337.57 K" }, "geometry": { "type": "Point", "coordinates": [ -155.28719, 19.40094, 0.0 ] } },
{ "type": "Feature", "properties": { "Name": "Fire Detection Centroid ", "Description": "<b>Latitude: <\/b> 19.40604<br\/>  <b>Longitude: <\/b> -155.28294<br\/>  <b>Detection Time: <\/b> 2022-11-19 23:56 UTC<br\/>  <b>Sensor: <\/b> NOAA-20 VIIRS<br\/> <b>Confidence: <\/b> Nominal<br\/>  <b>Day\/Night: <\/b> Day<br\/> <b>Scan: <\/b> 0.42 km<br\/> <b>Track: <\/b> 0.45 km<br\/> <b>FRP: <\/b> 31.41 MW<br\/> <b>Brightness: <\/b> 335.13 K" }, "geometry": { "type": "Point", "coordinates": [ -155.28294, 19.40604, 0.0 ] } }
]
}
