{
"type": "FeatureCollection",
"crs": { "type": "name", "properties": { "name": "urn:ogc:def:crs:OGC:1.3:CRS84" } },
"features": [
{ "type": "Feature", "properties": { "Name": "Fire Detection Centroid ", "Description": "<b>Latitude: <\/b> 47.00909<br\/>  <b>Longitude: <\/b> -68.17899<br\/>  <b>Detection Time: <\/b> 2022-12-11 07:20 UTC<br\/>  <b>Sensor: <\/b> NOAA-20 VIIRS<br\/> <b>Confidence: <\/b> Nominal<br\/>  <b>Day\/Night: <\/b> Night<br\/> <b>Scan: <\/b> 0.6 km<br\/> <b>Track: <\/b> 0.5 km<br\/> <b>FRP: <\/b> 5.27 MW<br\/> <b>Brightness: <\/b> 328.86 K" }, "geometry": { "type": "Point", "coordinates": [ -68.17899, 47.00909, 0.0 ] } },
{ "type": "Feature", "properties": { "Name": "Fire Detection Centroid ", "Description": "<b>Latitude: <\/b> 18.9279<br\/>  <b>Longitude: <\/b> -70.35302<br\/>  <b>Detection Time: <\/b> 2022-12-11 05:47 UTC<br\/>  <b>Sensor: <\/b> NOAA-20 VIIRS<br\/> <b>Confidence: <\/b> Nominal<br\/>  <b>Day\/Night: <\/b> Night<br\/> <b>Scan: <\/b> 0.6 km<br\/> <b>Track: <\/b> 0.5 km<br\/> <b>FRP: <\/b> 15.27 MW<br\/> <b>Brightness: <\/b> 339.16 K" }, "geometry": { "type": "Point", "coordinates": [ -70.35302, 18.9279, 0.0 ] } },
{ "type": "Feature", "properties": { "Name": "Fire Detection Centroid ", "Description": "<b>Latitude: <\/b> 18.49397<br\/>  <b>Longitude: <\/b> -69.60833<br\/>  <b>Detection Time: <\/b> 2022-12-11 05:47 UTC<br\/>  <b>Sensor: <\/b> NOAA-20 VIIRS<br\/> <b>Confidence: <\/b> Nominal<br\/>  <b>Day\/Night: <\/b> Night<br\/> <b>Scan: <\/b> 0.5 km<br\/> <b>Track: <\/b> 0.5 km<br\/> <b>FRP: <\/b> 1.35 MW<br\/> <b>Brightness: <\/b> 307.58 K" }, "geometry": { "type": "Point", "coordinates": [ -69.60833, 18.49397, 0.0 ] } },
{ "type": "Feature", "properties": { "Name": "Fire Detection Centroid ", "Description": "<b>Latitude: <\/b> 18.92868<br\/>  <b>Longitude: <\/b> -70.35178<br\/>  <b>Detection Time: <\/b> 2022-12-11 05:47 UTC<br\/>  <b>Sensor: <\/b> NOAA-20 VIIRS<br\/> <b>Confidence: <\/b> Nominal<br\/>  <b>Day\/Night: <\/b> Night<br\/> <b>Scan: <\/b> 0.6 km<br\/> <b>Track: <\/b> 0.5 km<br\/> <b>FRP: <\/b> 10.2 MW<br\/> <b>Brightness: <\/b> 334.42 K" }, "geometry": { "type": "Point", "coordinates": [ -70.35178, 18.92868, 0.0 ] } },
{ "type": "Feature", "properties": { "Name": "Fire Detection Centroid ", "Description": "<b>Latitude: <\/b> 18.43472<br\/>  <b>Longitude: <\/b> -71.23496<br\/>  <b>Detection Time: <\/b> 2022-12-11 05:47 UTC<br\/>  <b>Sensor: <\/b> NOAA-20 VIIRS<br\/> <b>Confidence: <\/b> Nominal<br\/>  <b>Day\/Night: <\/b> Night<br\/> <b>Scan: <\/b> 0.6 km<br\/> <b>Track: <\/b> 0.5 km<br\/> <b>FRP: <\/b> 7.08 MW<br\/> <b>Brightness: <\/b> 300.79 K" }, "geometry": { "type": "Point", "coordinates": [ -71.23496, 18.43472, 0.0 ] } },
{ "type": "Feature", "properties": { "Name": "Fire Detection Centroid ", "Description": "<b>Latitude: <\/b> 18.43539<br\/>  <b>Longitude: <\/b> -71.241<br\/>  <b>Detection Time: <\/b> 2022-12-11 05:47 UTC<br\/>  <b>Sensor: <\/b> NOAA-20 VIIRS<br\/> <b>Confidence: <\/b> Nominal<br\/>  <b>Day\/Night: <\/b> Night<br\/> <b>Scan: <\/b> 0.6 km<br\/> <b>Track: <\/b> 0.5 km<br\/> <b>FRP: <\/b> 13.7 MW<br\/> <b>Brightness: <\/b> 338.19 K" }, "geometry": { "type": "Point", "coordinates": [ -71.241, 18.43539, 0.0 ] } },
{ "type": "Feature", "properties": { "Name": "Fire Detection Centroid ", "Description": "<b>Latitude: <\/b> 18.92928<br\/>  <b>Longitude: <\/b> -70.35727<br\/>  <b>Detection Time: <\/b> 2022-12-11 05:47 UTC<br\/>  <b>Sensor: <\/b> NOAA-20 VIIRS<br\/> <b>Confidence: <\/b> Nominal<br\/>  <b>Day\/Night: <\/b> Night<br\/> <b>Scan: <\/b> 0.6 km<br\/> <b>Track: <\/b> 0.5 km<br\/> <b>FRP: <\/b> 10.2 MW<br\/> <b>Brightness: <\/b> 338.26 K" }, "geometry": { "type": "Point", "coordinates": [ -70.35727, 18.92928, 0.0 ] } }
]
}
