{
"type": "FeatureCollection",
"crs": { "type": "name", "properties": { "name": "urn:ogc:def:crs:OGC:1.3:CRS84" } },
"features": [
{ "type": "Feature", "properties": { "Name": "Fire Detection Centroid ", "Description": "<b>Latitude: <\/b> 19.46575<br\/>  <b>Longitude: <\/b> -70.75877<br\/>  <b>Detection Time: <\/b> 2023-11-27 06:07 UTC<br\/>  <b>Sensor: <\/b> NOAA-20 VIIRS<br\/> <b>Confidence: <\/b> Nominal<br\/>  <b>Day\/Night: <\/b> Night<br\/> <b>Scan: <\/b> 0.5 km<br\/> <b>Track: <\/b> 0.4 km<br\/> <b>FRP: <\/b> 1.84 MW<br\/> <b>Brightness: <\/b> 310.73 K" }, "geometry": { "type": "Point", "coordinates": [ -70.75877, 19.46575, 0.0 ] } },
{ "type": "Feature", "properties": { "Name": "Fire Detection Centroid ", "Description": "<b>Latitude: <\/b> 20.37447<br\/>  <b>Longitude: <\/b> -75.83105<br\/>  <b>Detection Time: <\/b> 2023-11-27 06:06 UTC<br\/>  <b>Sensor: <\/b> NOAA-20 VIIRS<br\/> <b>Confidence: <\/b> Nominal<br\/>  <b>Day\/Night: <\/b> Night<br\/> <b>Scan: <\/b> 0.3 km<br\/> <b>Track: <\/b> 0.5 km<br\/> <b>FRP: <\/b> 1.43 MW<br\/> <b>Brightness: <\/b> 316.12 K" }, "geometry": { "type": "Point", "coordinates": [ -75.83105, 20.37447, 0.0 ] } },
{ "type": "Feature", "properties": { "Name": "Fire Detection Centroid ", "Description": "<b>Latitude: <\/b> 22.81029<br\/>  <b>Longitude: <\/b> -80.41721<br\/>  <b>Detection Time: <\/b> 2023-11-27 06:06 UTC<br\/>  <b>Sensor: <\/b> NOAA-20 VIIRS<br\/> <b>Confidence: <\/b> Nominal<br\/>  <b>Day\/Night: <\/b> Night<br\/> <b>Scan: <\/b> 0.7 km<br\/> <b>Track: <\/b> 0.7 km<br\/> <b>FRP: <\/b> 3.45 MW<br\/> <b>Brightness: <\/b> 320.32 K" }, "geometry": { "type": "Point", "coordinates": [ -80.41721, 22.81029, 0.0 ] } },
{ "type": "Feature", "properties": { "Name": "Fire Detection Centroid ", "Description": "<b>Latitude: <\/b> 22.80941<br\/>  <b>Longitude: <\/b> -80.42207<br\/>  <b>Detection Time: <\/b> 2023-11-27 06:06 UTC<br\/>  <b>Sensor: <\/b> NOAA-20 VIIRS<br\/> <b>Confidence: <\/b> Nominal<br\/>  <b>Day\/Night: <\/b> Night<br\/> <b>Scan: <\/b> 0.7 km<br\/> <b>Track: <\/b> 0.7 km<br\/> <b>FRP: <\/b> 3.03 MW<br\/> <b>Brightness: <\/b> 307.92 K" }, "geometry": { "type": "Point", "coordinates": [ -80.42207, 22.80941, 0.0 ] } },
{ "type": "Feature", "properties": { "Name": "Fire Detection Centroid ", "Description": "<b>Latitude: <\/b> 22.80892<br\/>  <b>Longitude: <\/b> -80.41537<br\/>  <b>Detection Time: <\/b> 2023-11-27 06:06 UTC<br\/>  <b>Sensor: <\/b> NOAA-20 VIIRS<br\/> <b>Confidence: <\/b> Nominal<br\/>  <b>Day\/Night: <\/b> Night<br\/> <b>Scan: <\/b> 0.7 km<br\/> <b>Track: <\/b> 0.7 km<br\/> <b>FRP: <\/b> 3.2 MW<br\/> <b>Brightness: <\/b> 310.6 K" }, "geometry": { "type": "Point", "coordinates": [ -80.41537, 22.80892, 0.0 ] } },
{ "type": "Feature", "properties": { "Name": "Fire Detection Centroid ", "Description": "<b>Latitude: <\/b> 40.15366<br\/>  <b>Longitude: <\/b> -74.7702<br\/>  <b>Detection Time: <\/b> 2023-11-27 06:01 UTC<br\/>  <b>Sensor: <\/b> NOAA-20 VIIRS<br\/> <b>Confidence: <\/b> Nominal<br\/>  <b>Day\/Night: <\/b> Night<br\/> <b>Scan: <\/b> 0.4 km<br\/> <b>Track: <\/b> 0.6 km<br\/> <b>FRP: <\/b> 0.73 MW<br\/> <b>Brightness: <\/b> 303.59 K" }, "geometry": { "type": "Point", "coordinates": [ -74.7702, 40.15366, 0.0 ] } },
{ "type": "Feature", "properties": { "Name": "Fire Detection Centroid ", "Description": "<b>Latitude: <\/b> 39.58689<br\/>  <b>Longitude: <\/b> -75.63862<br\/>  <b>Detection Time: <\/b> 2023-11-27 06:01 UTC<br\/>  <b>Sensor: <\/b> NOAA-20 VIIRS<br\/> <b>Confidence: <\/b> Nominal<br\/>  <b>Day\/Night: <\/b> Night<br\/> <b>Scan: <\/b> 0.5 km<br\/> <b>Track: <\/b> 0.6 km<br\/> <b>FRP: <\/b> 0.78 MW<br\/> <b>Brightness: <\/b> 295.02 K" }, "geometry": { "type": "Point", "coordinates": [ -75.63862, 39.58689, 0.0 ] } },
{ "type": "Feature", "properties": { "Name": "Fire Detection Centroid ", "Description": "<b>Latitude: <\/b> 39.5909<br\/>  <b>Longitude: <\/b> -75.63553<br\/>  <b>Detection Time: <\/b> 2023-11-27 06:01 UTC<br\/>  <b>Sensor: <\/b> NOAA-20 VIIRS<br\/> <b>Confidence: <\/b> Nominal<br\/>  <b>Day\/Night: <\/b> Night<br\/> <b>Scan: <\/b> 0.5 km<br\/> <b>Track: <\/b> 0.6 km<br\/> <b>FRP: <\/b> 1.39 MW<br\/> <b>Brightness: <\/b> 296.55 K" }, "geometry": { "type": "Point", "coordinates": [ -75.63553, 39.5909, 0.0 ] } },
{ "type": "Feature", "properties": { "Name": "Fire Detection Centroid ", "Description": "<b>Latitude: <\/b> 40.71926<br\/>  <b>Longitude: <\/b> -75.39972<br\/>  <b>Detection Time: <\/b> 2023-11-27 06:01 UTC<br\/>  <b>Sensor: <\/b> NOAA-20 VIIRS<br\/> <b>Confidence: <\/b> Nominal<br\/>  <b>Day\/Night: <\/b> Night<br\/> <b>Scan: <\/b> 0.5 km<br\/> <b>Track: <\/b> 0.6 km<br\/> <b>FRP: <\/b> 1.07 MW<br\/> <b>Brightness: <\/b> 295.59 K" }, "geometry": { "type": "Point", "coordinates": [ -75.39972, 40.71926, 0.0 ] } }
]
}
