{
"type": "FeatureCollection",
"crs": { "type": "name", "properties": { "name": "urn:ogc:def:crs:OGC:1.3:CRS84" } },
"features": [
{ "type": "Feature", "properties": { "Name": "Fire Detection Centroid ", "Description": "<b>Latitude: <\/b> 42.04447<br\/>  <b>Longitude: <\/b> -72.74566<br\/>  <b>Detection Time: <\/b> 2023-02-13 17:05 UTC<br\/>  <b>Sensor: <\/b> NOAA-20 VIIRS<br\/> <b>Confidence: <\/b> Nominal<br\/>  <b>Day\/Night: <\/b> Day<br\/> <b>Scan: <\/b> 0.5 km<br\/> <b>Track: <\/b> 0.5 km<br\/> <b>FRP: <\/b> 5.36 MW<br\/> <b>Brightness: <\/b> 340.1 K" }, "geometry": { "type": "Point", "coordinates": [ -72.74566, 42.04447, 0.0 ] } },
{ "type": "Feature", "properties": { "Name": "Fire Detection Centroid ", "Description": "<b>Latitude: <\/b> 40.43487<br\/>  <b>Longitude: <\/b> -76.65481<br\/>  <b>Detection Time: <\/b> 2023-02-13 17:05 UTC<br\/>  <b>Sensor: <\/b> NOAA-20 VIIRS<br\/> <b>Confidence: <\/b> Nominal<br\/>  <b>Day\/Night: <\/b> Day<br\/> <b>Scan: <\/b> 0.5 km<br\/> <b>Track: <\/b> 0.6 km<br\/> <b>FRP: <\/b> 2.87 MW<br\/> <b>Brightness: <\/b> 326.17 K" }, "geometry": { "type": "Point", "coordinates": [ -76.65481, 40.43487, 0.0 ] } },
{ "type": "Feature", "properties": { "Name": "Fire Detection Centroid ", "Description": "<b>Latitude: <\/b> 40.44048<br\/>  <b>Longitude: <\/b> -76.65739<br\/>  <b>Detection Time: <\/b> 2023-02-13 17:05 UTC<br\/>  <b>Sensor: <\/b> NOAA-20 VIIRS<br\/> <b>Confidence: <\/b> Nominal<br\/>  <b>Day\/Night: <\/b> Day<br\/> <b>Scan: <\/b> 0.5 km<br\/> <b>Track: <\/b> 0.6 km<br\/> <b>FRP: <\/b> 3.84 MW<br\/> <b>Brightness: <\/b> 325.89 K" }, "geometry": { "type": "Point", "coordinates": [ -76.65739, 40.44048, 0.0 ] } },
{ "type": "Feature", "properties": { "Name": "Fire Detection Centroid ", "Description": "<b>Latitude: <\/b> 40.43739<br\/>  <b>Longitude: <\/b> -76.66803<br\/>  <b>Detection Time: <\/b> 2023-02-13 17:05 UTC<br\/>  <b>Sensor: <\/b> NOAA-20 VIIRS<br\/> <b>Confidence: <\/b> Nominal<br\/>  <b>Day\/Night: <\/b> Day<br\/> <b>Scan: <\/b> 0.5 km<br\/> <b>Track: <\/b> 0.6 km<br\/> <b>FRP: <\/b> 8.41 MW<br\/> <b>Brightness: <\/b> 342.24 K" }, "geometry": { "type": "Point", "coordinates": [ -76.66803, 40.43739, 0.0 ] } },
{ "type": "Feature", "properties": { "Name": "Fire Detection Centroid ", "Description": "<b>Latitude: <\/b> 40.00814<br\/>  <b>Longitude: <\/b> -74.54179<br\/>  <b>Detection Time: <\/b> 2023-02-13 17:04 UTC<br\/>  <b>Sensor: <\/b> NOAA-20 VIIRS<br\/> <b>Confidence: <\/b> Nominal<br\/>  <b>Day\/Night: <\/b> Day<br\/> <b>Scan: <\/b> 0.4 km<br\/> <b>Track: <\/b> 0.6 km<br\/> <b>FRP: <\/b> 2.65 MW<br\/> <b>Brightness: <\/b> 330.85 K" }, "geometry": { "type": "Point", "coordinates": [ -74.54179, 40.00814, 0.0 ] } },
{ "type": "Feature", "properties": { "Name": "Fire Detection Centroid ", "Description": "<b>Latitude: <\/b> 40.53832<br\/>  <b>Longitude: <\/b> -74.64737<br\/>  <b>Detection Time: <\/b> 2023-02-13 17:04 UTC<br\/>  <b>Sensor: <\/b> NOAA-20 VIIRS<br\/> <b>Confidence: <\/b> Nominal<br\/>  <b>Day\/Night: <\/b> Day<br\/> <b>Scan: <\/b> 0.4 km<br\/> <b>Track: <\/b> 0.6 km<br\/> <b>FRP: <\/b> 2.95 MW<br\/> <b>Brightness: <\/b> 328.24 K" }, "geometry": { "type": "Point", "coordinates": [ -74.64737, 40.53832, 0.0 ] } },
{ "type": "Feature", "properties": { "Name": "Fire Detection Centroid ", "Description": "<b>Latitude: <\/b> 37.18662<br\/>  <b>Longitude: <\/b> -76.88802<br\/>  <b>Detection Time: <\/b> 2023-02-13 17:04 UTC<br\/>  <b>Sensor: <\/b> NOAA-20 VIIRS<br\/> <b>Confidence: <\/b> Nominal<br\/>  <b>Day\/Night: <\/b> Day<br\/> <b>Scan: <\/b> 0.6 km<br\/> <b>Track: <\/b> 0.7 km<br\/> <b>FRP: <\/b> 10.57 MW<br\/> <b>Brightness: <\/b> 331.32 K" }, "geometry": { "type": "Point", "coordinates": [ -76.88802, 37.18662, 0.0 ] } },
{ "type": "Feature", "properties": { "Name": "Fire Detection Centroid ", "Description": "<b>Latitude: <\/b> 37.18471<br\/>  <b>Longitude: <\/b> -76.89441<br\/>  <b>Detection Time: <\/b> 2023-02-13 17:04 UTC<br\/>  <b>Sensor: <\/b> NOAA-20 VIIRS<br\/> <b>Confidence: <\/b> Nominal<br\/>  <b>Day\/Night: <\/b> Day<br\/> <b>Scan: <\/b> 0.6 km<br\/> <b>Track: <\/b> 0.7 km<br\/> <b>FRP: <\/b> 10.57 MW<br\/> <b>Brightness: <\/b> 355.34 K" }, "geometry": { "type": "Point", "coordinates": [ -76.89441, 37.18471, 0.0 ] } },
{ "type": "Feature", "properties": { "Name": "Fire Detection Centroid ", "Description": "<b>Latitude: <\/b> 40.54339<br\/>  <b>Longitude: <\/b> -74.64974<br\/>  <b>Detection Time: <\/b> 2023-02-13 17:04 UTC<br\/>  <b>Sensor: <\/b> NOAA-20 VIIRS<br\/> <b>Confidence: <\/b> Nominal<br\/>  <b>Day\/Night: <\/b> Day<br\/> <b>Scan: <\/b> 0.4 km<br\/> <b>Track: <\/b> 0.6 km<br\/> <b>FRP: <\/b> 2.95 MW<br\/> <b>Brightness: <\/b> 338.91 K" }, "geometry": { "type": "Point", "coordinates": [ -74.64974, 40.54339, 0.0 ] } }
]
}
