{
"type": "FeatureCollection",
"crs": { "type": "name", "properties": { "name": "urn:ogc:def:crs:OGC:1.3:CRS84" } },
"features": [
{ "type": "Feature", "properties": { "Name": "Fire Detection Centroid ", "Description": "<b>Latitude: <\/b> 48.18892<br\/>  <b>Longitude: <\/b> -124.23293<br\/>  <b>Detection Time: <\/b> 2024-01-04 20:36 UTC<br\/>  <b>Sensor: <\/b> NOAA-20 VIIRS<br\/> <b>Confidence: <\/b> Nominal<br\/>  <b>Day\/Night: <\/b> Day<br\/> <b>Scan: <\/b> 0.54 km<br\/> <b>Track: <\/b> 0.42 km<br\/> <b>FRP: <\/b> 4.85 MW<br\/> <b>Brightness: <\/b> 328.37 K" }, "geometry": { "type": "Point", "coordinates": [ -124.23293, 48.18892, 0.0 ] } }
]
}
