{
"type": "FeatureCollection",
"crs": { "type": "name", "properties": { "name": "urn:ogc:def:crs:OGC:1.3:CRS84" } },
"features": [
{ "type": "Feature", "properties": { "Name": "Fire Detection Centroid ", "Description": "<b>Latitude: <\/b> 19.41171<br\/>  <b>Longitude: <\/b> -155.28093<br\/>  <b>Detection Time: <\/b> 2023-09-21 23:20 UTC<br\/>  <b>Sensor: <\/b> NOAA-20 VIIRS<br\/> <b>Confidence: <\/b> Nominal<br\/>  <b>Day\/Night: <\/b> Day<br\/> <b>Scan: <\/b> 0.48 km<br\/> <b>Track: <\/b> 0.4 km<br\/> <b>FRP: <\/b> 6.78 MW<br\/> <b>Brightness: <\/b> 343.42 K" }, "geometry": { "type": "Point", "coordinates": [ -155.28093, 19.41171, 0.0 ] } },
{ "type": "Feature", "properties": { "Name": "Fire Detection Centroid ", "Description": "<b>Latitude: <\/b> 19.40445<br\/>  <b>Longitude: <\/b> -155.27959<br\/>  <b>Detection Time: <\/b> 2023-09-21 23:20 UTC<br\/>  <b>Sensor: <\/b> NOAA-20 VIIRS<br\/> <b>Confidence: <\/b> Nominal<br\/>  <b>Day\/Night: <\/b> Day<br\/> <b>Scan: <\/b> 0.48 km<br\/> <b>Track: <\/b> 0.4 km<br\/> <b>FRP: <\/b> 8.97 MW<br\/> <b>Brightness: <\/b> 338.85 K" }, "geometry": { "type": "Point", "coordinates": [ -155.27959, 19.40445, 0.0 ] } },
{ "type": "Feature", "properties": { "Name": "Fire Detection Centroid ", "Description": "<b>Latitude: <\/b> 19.40884<br\/>  <b>Longitude: <\/b> -155.27579<br\/>  <b>Detection Time: <\/b> 2023-09-21 23:20 UTC<br\/>  <b>Sensor: <\/b> NOAA-20 VIIRS<br\/> <b>Confidence: <\/b> Nominal<br\/>  <b>Day\/Night: <\/b> Day<br\/> <b>Scan: <\/b> 0.48 km<br\/> <b>Track: <\/b> 0.4 km<br\/> <b>FRP: <\/b> 9.64 MW<br\/> <b>Brightness: <\/b> 340.79 K" }, "geometry": { "type": "Point", "coordinates": [ -155.27579, 19.40884, 0.0 ] } },
{ "type": "Feature", "properties": { "Name": "Fire Detection Centroid ", "Description": "<b>Latitude: <\/b> 19.40808<br\/>  <b>Longitude: <\/b> -155.28026<br\/>  <b>Detection Time: <\/b> 2023-09-21 23:20 UTC<br\/>  <b>Sensor: <\/b> NOAA-20 VIIRS<br\/> <b>Confidence: <\/b> Nominal<br\/>  <b>Day\/Night: <\/b> Day<br\/> <b>Scan: <\/b> 0.48 km<br\/> <b>Track: <\/b> 0.4 km<br\/> <b>FRP: <\/b> 6.78 MW<br\/> <b>Brightness: <\/b> 344.53 K" }, "geometry": { "type": "Point", "coordinates": [ -155.28026, 19.40808, 0.0 ] } },
{ "type": "Feature", "properties": { "Name": "Fire Detection Centroid ", "Description": "<b>Latitude: <\/b> 19.40732<br\/>  <b>Longitude: <\/b> -155.28473<br\/>  <b>Detection Time: <\/b> 2023-09-21 23:20 UTC<br\/>  <b>Sensor: <\/b> NOAA-20 VIIRS<br\/> <b>Confidence: <\/b> Nominal<br\/>  <b>Day\/Night: <\/b> Day<br\/> <b>Scan: <\/b> 0.48 km<br\/> <b>Track: <\/b> 0.4 km<br\/> <b>FRP: <\/b> 6.78 MW<br\/> <b>Brightness: <\/b> 336.56 K" }, "geometry": { "type": "Point", "coordinates": [ -155.28473, 19.40732, 0.0 ] } },
{ "type": "Feature", "properties": { "Name": "Fire Detection Centroid ", "Description": "<b>Latitude: <\/b> 19.41247<br\/>  <b>Longitude: <\/b> -155.27647<br\/>  <b>Detection Time: <\/b> 2023-09-21 23:20 UTC<br\/>  <b>Sensor: <\/b> NOAA-20 VIIRS<br\/> <b>Confidence: <\/b> Nominal<br\/>  <b>Day\/Night: <\/b> Day<br\/> <b>Scan: <\/b> 0.48 km<br\/> <b>Track: <\/b> 0.4 km<br\/> <b>FRP: <\/b> 9.64 MW<br\/> <b>Brightness: <\/b> 336.23 K" }, "geometry": { "type": "Point", "coordinates": [ -155.27647, 19.41247, 0.0 ] } },
{ "type": "Feature", "properties": { "Name": "Fire Detection Centroid ", "Description": "<b>Latitude: <\/b> 19.41096<br\/>  <b>Longitude: <\/b> -155.28535<br\/>  <b>Detection Time: <\/b> 2023-09-21 23:20 UTC<br\/>  <b>Sensor: <\/b> NOAA-20 VIIRS<br\/> <b>Confidence: <\/b> Nominal<br\/>  <b>Day\/Night: <\/b> Day<br\/> <b>Scan: <\/b> 0.48 km<br\/> <b>Track: <\/b> 0.4 km<br\/> <b>FRP: <\/b> 6.78 MW<br\/> <b>Brightness: <\/b> 337.5 K" }, "geometry": { "type": "Point", "coordinates": [ -155.28535, 19.41096, 0.0 ] } }
]
}
