{
"type": "FeatureCollection",
"crs": { "type": "name", "properties": { "name": "urn:ogc:def:crs:OGC:1.3:CRS84" } },
"features": [
{ "type": "Feature", "properties": { "Name": "Fire Detection Centroid ", "Description": "<b>Latitude: <\/b> 36.21102<br\/>  <b>Longitude: <\/b> -76.20661<br\/>  <b>Detection Time: <\/b> 2023-07-02 16:58 UTC<br\/>  <b>Sensor: <\/b> NOAA-20 VIIRS<br\/> <b>Confidence: <\/b> Nominal<br\/>  <b>Day\/Night: <\/b> Day<br\/> <b>Scan: <\/b> 0.7 km<br\/> <b>Track: <\/b> 0.8 km<br\/> <b>FRP: <\/b> 6.09 MW<br\/> <b>Brightness: <\/b> 335.86 K" }, "geometry": { "type": "Point", "coordinates": [ -76.20661, 36.21102, 0.0 ] } },
{ "type": "Feature", "properties": { "Name": "Fire Detection Centroid ", "Description": "<b>Latitude: <\/b> 19.40385<br\/>  <b>Longitude: <\/b> -155.28806<br\/>  <b>Detection Time: <\/b> 2023-07-02 12:27 UTC<br\/>  <b>Sensor: <\/b> NOAA-20 VIIRS<br\/> <b>Confidence: <\/b> Nominal<br\/>  <b>Day\/Night: <\/b> Night<br\/> <b>Scan: <\/b> 0.52 km<br\/> <b>Track: <\/b> 0.5 km<br\/> <b>FRP: <\/b> 3.9 MW<br\/> <b>Brightness: <\/b> 325.81 K" }, "geometry": { "type": "Point", "coordinates": [ -155.28806, 19.40385, 0.0 ] } },
{ "type": "Feature", "properties": { "Name": "Fire Detection Centroid ", "Description": "<b>Latitude: <\/b> 19.41189<br\/>  <b>Longitude: <\/b> -155.28131<br\/>  <b>Detection Time: <\/b> 2023-07-02 12:27 UTC<br\/>  <b>Sensor: <\/b> NOAA-20 VIIRS<br\/> <b>Confidence: <\/b> Nominal<br\/>  <b>Day\/Night: <\/b> Night<br\/> <b>Scan: <\/b> 0.52 km<br\/> <b>Track: <\/b> 0.5 km<br\/> <b>FRP: <\/b> 4.6 MW<br\/> <b>Brightness: <\/b> 323.53 K" }, "geometry": { "type": "Point", "coordinates": [ -155.28131, 19.41189, 0.0 ] } },
{ "type": "Feature", "properties": { "Name": "Fire Detection Centroid ", "Description": "<b>Latitude: <\/b> 19.41289<br\/>  <b>Longitude: <\/b> -155.28636<br\/>  <b>Detection Time: <\/b> 2023-07-02 12:27 UTC<br\/>  <b>Sensor: <\/b> NOAA-20 VIIRS<br\/> <b>Confidence: <\/b> Nominal<br\/>  <b>Day\/Night: <\/b> Night<br\/> <b>Scan: <\/b> 0.52 km<br\/> <b>Track: <\/b> 0.5 km<br\/> <b>FRP: <\/b> 4.6 MW<br\/> <b>Brightness: <\/b> 317.45 K" }, "geometry": { "type": "Point", "coordinates": [ -155.28636, 19.41289, 0.0 ] } },
{ "type": "Feature", "properties": { "Name": "Fire Detection Centroid ", "Description": "<b>Latitude: <\/b> 19.40836<br\/>  <b>Longitude: <\/b> -155.28719<br\/>  <b>Detection Time: <\/b> 2023-07-02 12:27 UTC<br\/>  <b>Sensor: <\/b> NOAA-20 VIIRS<br\/> <b>Confidence: <\/b> Nominal<br\/>  <b>Day\/Night: <\/b> Night<br\/> <b>Scan: <\/b> 0.52 km<br\/> <b>Track: <\/b> 0.5 km<br\/> <b>FRP: <\/b> 4.6 MW<br\/> <b>Brightness: <\/b> 320.07 K" }, "geometry": { "type": "Point", "coordinates": [ -155.28719, 19.40836, 0.0 ] } },
{ "type": "Feature", "properties": { "Name": "Fire Detection Centroid ", "Description": "<b>Latitude: <\/b> 19.40738<br\/>  <b>Longitude: <\/b> -155.28223<br\/>  <b>Detection Time: <\/b> 2023-07-02 12:27 UTC<br\/>  <b>Sensor: <\/b> NOAA-20 VIIRS<br\/> <b>Confidence: <\/b> Nominal<br\/>  <b>Day\/Night: <\/b> Night<br\/> <b>Scan: <\/b> 0.52 km<br\/> <b>Track: <\/b> 0.5 km<br\/> <b>FRP: <\/b> 4.6 MW<br\/> <b>Brightness: <\/b> 324.02 K" }, "geometry": { "type": "Point", "coordinates": [ -155.28223, 19.40738, 0.0 ] } },
{ "type": "Feature", "properties": { "Name": "Fire Detection Centroid ", "Description": "<b>Latitude: <\/b> 19.40938<br\/>  <b>Longitude: <\/b> -155.29234<br\/>  <b>Detection Time: <\/b> 2023-07-02 12:27 UTC<br\/>  <b>Sensor: <\/b> NOAA-20 VIIRS<br\/> <b>Confidence: <\/b> Nominal<br\/>  <b>Day\/Night: <\/b> Night<br\/> <b>Scan: <\/b> 0.52 km<br\/> <b>Track: <\/b> 0.5 km<br\/> <b>FRP: <\/b> 1.87 MW<br\/> <b>Brightness: <\/b> 298.29 K" }, "geometry": { "type": "Point", "coordinates": [ -155.29234, 19.40938, 0.0 ] } },
{ "type": "Feature", "properties": { "Name": "Fire Detection Centroid ", "Description": "<b>Latitude: <\/b> 19.40289<br\/>  <b>Longitude: <\/b> -155.28319<br\/>  <b>Detection Time: <\/b> 2023-07-02 12:27 UTC<br\/>  <b>Sensor: <\/b> NOAA-20 VIIRS<br\/> <b>Confidence: <\/b> Nominal<br\/>  <b>Day\/Night: <\/b> Night<br\/> <b>Scan: <\/b> 0.52 km<br\/> <b>Track: <\/b> 0.5 km<br\/> <b>FRP: <\/b> 3.9 MW<br\/> <b>Brightness: <\/b> 308.55 K" }, "geometry": { "type": "Point", "coordinates": [ -155.28319, 19.40289, 0.0 ] } },
{ "type": "Feature", "properties": { "Name": "Fire Detection Centroid ", "Description": "<b>Latitude: <\/b> 19.40487<br\/>  <b>Longitude: <\/b> -155.29321<br\/>  <b>Detection Time: <\/b> 2023-07-02 12:27 UTC<br\/>  <b>Sensor: <\/b> NOAA-20 VIIRS<br\/> <b>Confidence: <\/b> Nominal<br\/>  <b>Day\/Night: <\/b> Night<br\/> <b>Scan: <\/b> 0.52 km<br\/> <b>Track: <\/b> 0.5 km<br\/> <b>FRP: <\/b> 1.85 MW<br\/> <b>Brightness: <\/b> 302.42 K" }, "geometry": { "type": "Point", "coordinates": [ -155.29321, 19.40487, 0.0 ] } }
]
}
