{
"type": "FeatureCollection",
"crs": { "type": "name", "properties": { "name": "urn:ogc:def:crs:OGC:1.3:CRS84" } },
"features": [
{ "type": "Feature", "properties": { "Name": "Fire Detection Centroid ", "Description": "<b>Latitude: <\/b> 19.40964<br\/>  <b>Longitude: <\/b> -155.28905<br\/>  <b>Detection Time: <\/b> 2023-11-23 12:25 UTC<br\/>  <b>Sensor: <\/b> NOAA-20 VIIRS<br\/> <b>Confidence: <\/b> Nominal<br\/>  <b>Day\/Night: <\/b> Night<br\/> <b>Scan: <\/b> 0.52 km<br\/> <b>Track: <\/b> 0.5 km<br\/> <b>FRP: <\/b> 3.33 MW<br\/> <b>Brightness: <\/b> 304.18 K" }, "geometry": { "type": "Point", "coordinates": [ -155.28905, 19.40964, 0.0 ] } },
{ "type": "Feature", "properties": { "Name": "Fire Detection Centroid ", "Description": "<b>Latitude: <\/b> 19.40414<br\/>  <b>Longitude: <\/b> -155.28491<br\/>  <b>Detection Time: <\/b> 2023-11-23 12:25 UTC<br\/>  <b>Sensor: <\/b> NOAA-20 VIIRS<br\/> <b>Confidence: <\/b> Nominal<br\/>  <b>Day\/Night: <\/b> Night<br\/> <b>Scan: <\/b> 0.52 km<br\/> <b>Track: <\/b> 0.5 km<br\/> <b>FRP: <\/b> 2.1 MW<br\/> <b>Brightness: <\/b> 305.58 K" }, "geometry": { "type": "Point", "coordinates": [ -155.28491, 19.40414, 0.0 ] } },
{ "type": "Feature", "properties": { "Name": "Fire Detection Centroid ", "Description": "<b>Latitude: <\/b> 19.40865<br\/>  <b>Longitude: <\/b> -155.28403<br\/>  <b>Detection Time: <\/b> 2023-11-23 12:25 UTC<br\/>  <b>Sensor: <\/b> NOAA-20 VIIRS<br\/> <b>Confidence: <\/b> Nominal<br\/>  <b>Day\/Night: <\/b> Night<br\/> <b>Scan: <\/b> 0.52 km<br\/> <b>Track: <\/b> 0.5 km<br\/> <b>FRP: <\/b> 3.59 MW<br\/> <b>Brightness: <\/b> 303.99 K" }, "geometry": { "type": "Point", "coordinates": [ -155.28403, 19.40865, 0.0 ] } },
{ "type": "Feature", "properties": { "Name": "Fire Detection Centroid ", "Description": "<b>Latitude: <\/b> 19.41315<br\/>  <b>Longitude: <\/b> -155.28314<br\/>  <b>Detection Time: <\/b> 2023-11-23 12:25 UTC<br\/>  <b>Sensor: <\/b> NOAA-20 VIIRS<br\/> <b>Confidence: <\/b> Nominal<br\/>  <b>Day\/Night: <\/b> Night<br\/> <b>Scan: <\/b> 0.52 km<br\/> <b>Track: <\/b> 0.5 km<br\/> <b>FRP: <\/b> 3.59 MW<br\/> <b>Brightness: <\/b> 303.89 K" }, "geometry": { "type": "Point", "coordinates": [ -155.28314, 19.41315, 0.0 ] } }
]
}
