{
"type": "FeatureCollection",
"crs": { "type": "name", "properties": { "name": "urn:ogc:def:crs:OGC:1.3:CRS84" } },
"features": [
{ "type": "Feature", "properties": { "Name": "Fire Detection Centroid ", "Description": "<b>Latitude: <\/b> 18.64349<br\/>  <b>Longitude: <\/b> -70.72326<br\/>  <b>Detection Time: <\/b> 2023-11-12 16:59 UTC<br\/>  <b>Sensor: <\/b> NOAA-20 VIIRS<br\/> <b>Confidence: <\/b> Nominal<br\/>  <b>Day\/Night: <\/b> Day<br\/> <b>Scan: <\/b> 0.8 km<br\/> <b>Track: <\/b> 0.8 km<br\/> <b>FRP: <\/b> 10.87 MW<br\/> <b>Brightness: <\/b> 338.88 K" }, "geometry": { "type": "Point", "coordinates": [ -70.72326, 18.64349, 0.0 ] } },
{ "type": "Feature", "properties": { "Name": "Fire Detection Centroid ", "Description": "<b>Latitude: <\/b> 18.64572<br\/>  <b>Longitude: <\/b> -70.72082<br\/>  <b>Detection Time: <\/b> 2023-11-12 16:59 UTC<br\/>  <b>Sensor: <\/b> NOAA-20 VIIRS<br\/> <b>Confidence: <\/b> Nominal<br\/>  <b>Day\/Night: <\/b> Day<br\/> <b>Scan: <\/b> 0.8 km<br\/> <b>Track: <\/b> 0.8 km<br\/> <b>FRP: <\/b> 8.65 MW<br\/> <b>Brightness: <\/b> 337.25 K" }, "geometry": { "type": "Point", "coordinates": [ -70.72082, 18.64572, 0.0 ] } },
{ "type": "Feature", "properties": { "Name": "Fire Detection Centroid ", "Description": "<b>Latitude: <\/b> 19.40941<br\/>  <b>Longitude: <\/b> -155.29024<br\/>  <b>Detection Time: <\/b> 2023-11-12 12:33 UTC<br\/>  <b>Sensor: <\/b> NOAA-20 VIIRS<br\/> <b>Confidence: <\/b> Nominal<br\/>  <b>Day\/Night: <\/b> Night<br\/> <b>Scan: <\/b> 0.32 km<br\/> <b>Track: <\/b> 0.55 km<br\/> <b>FRP: <\/b> 2.06 MW<br\/> <b>Brightness: <\/b> 306.59 K" }, "geometry": { "type": "Point", "coordinates": [ -155.29024, 19.40941, 0.0 ] } },
{ "type": "Feature", "properties": { "Name": "Fire Detection Centroid ", "Description": "<b>Latitude: <\/b> 19.41442<br\/>  <b>Longitude: <\/b> -155.28937<br\/>  <b>Detection Time: <\/b> 2023-11-12 12:33 UTC<br\/>  <b>Sensor: <\/b> NOAA-20 VIIRS<br\/> <b>Confidence: <\/b> Nominal<br\/>  <b>Day\/Night: <\/b> Night<br\/> <b>Scan: <\/b> 0.32 km<br\/> <b>Track: <\/b> 0.55 km<br\/> <b>FRP: <\/b> 2.16 MW<br\/> <b>Brightness: <\/b> 301.72 K" }, "geometry": { "type": "Point", "coordinates": [ -155.28937, 19.41442, 0.0 ] } },
{ "type": "Feature", "properties": { "Name": "Fire Detection Centroid ", "Description": "<b>Latitude: <\/b> 19.41502<br\/>  <b>Longitude: <\/b> -155.28784<br\/>  <b>Detection Time: <\/b> 2023-11-12 12:33 UTC<br\/>  <b>Sensor: <\/b> NOAA-20 VIIRS<br\/> <b>Confidence: <\/b> Nominal<br\/>  <b>Day\/Night: <\/b> Night<br\/> <b>Scan: <\/b> 0.3 km<br\/> <b>Track: <\/b> 0.5 km<br\/> <b>FRP: <\/b> 2.15 MW<br\/> <b>Brightness: <\/b> 301.72 K" }, "geometry": { "type": "Point", "coordinates": [ -155.28784, 19.41502, 0.0 ] } },
{ "type": "Feature", "properties": { "Name": "Fire Detection Centroid ", "Description": "<b>Latitude: <\/b> 19.40933<br\/>  <b>Longitude: <\/b> -155.28545<br\/>  <b>Detection Time: <\/b> 2023-11-12 12:33 UTC<br\/>  <b>Sensor: <\/b> NOAA-20 VIIRS<br\/> <b>Confidence: <\/b> Nominal<br\/>  <b>Day\/Night: <\/b> Night<br\/> <b>Scan: <\/b> 0.3 km<br\/> <b>Track: <\/b> 0.5 km<br\/> <b>FRP: <\/b> 2.06 MW<br\/> <b>Brightness: <\/b> 306.93 K" }, "geometry": { "type": "Point", "coordinates": [ -155.28545, 19.40933, 0.0 ] } },
{ "type": "Feature", "properties": { "Name": "Fire Detection Centroid ", "Description": "<b>Latitude: <\/b> 19.40873<br\/>  <b>Longitude: <\/b> -155.28697<br\/>  <b>Detection Time: <\/b> 2023-11-12 12:33 UTC<br\/>  <b>Sensor: <\/b> NOAA-20 VIIRS<br\/> <b>Confidence: <\/b> Nominal<br\/>  <b>Day\/Night: <\/b> Night<br\/> <b>Scan: <\/b> 0.32 km<br\/> <b>Track: <\/b> 0.55 km<br\/> <b>FRP: <\/b> 2.06 MW<br\/> <b>Brightness: <\/b> 306.93 K" }, "geometry": { "type": "Point", "coordinates": [ -155.28697, 19.40873, 0.0 ] } },
{ "type": "Feature", "properties": { "Name": "Fire Detection Centroid ", "Description": "<b>Latitude: <\/b> 19.41<br\/>  <b>Longitude: <\/b> -155.28864<br\/>  <b>Detection Time: <\/b> 2023-11-12 12:33 UTC<br\/>  <b>Sensor: <\/b> NOAA-20 VIIRS<br\/> <b>Confidence: <\/b> Nominal<br\/>  <b>Day\/Night: <\/b> Night<br\/> <b>Scan: <\/b> 0.3 km<br\/> <b>Track: <\/b> 0.5 km<br\/> <b>FRP: <\/b> 2.06 MW<br\/> <b>Brightness: <\/b> 306.59 K" }, "geometry": { "type": "Point", "coordinates": [ -155.28864, 19.41, 0.0 ] } }
]
}
