{
"type": "FeatureCollection",
"crs": { "type": "name", "properties": { "name": "urn:ogc:def:crs:OGC:1.3:CRS84" } },
"features": [
{ "type": "Feature", "properties": { "Name": "Fire Detection Centroid ", "Description": "<b>Latitude: <\/b> 19.59595<br\/>  <b>Longitude: <\/b> -155.50485<br\/>  <b>Detection Time: <\/b> 2023-05-16 12:08 UTC<br\/>  <b>Sensor: <\/b> NOAA-20 VIIRS<br\/> <b>Confidence: <\/b> Nominal<br\/>  <b>Day\/Night: <\/b> Night<br\/> <b>Scan: <\/b> 0.42 km<br\/> <b>Track: <\/b> 0.38 km<br\/> <b>FRP: <\/b> 1.95 MW<br\/> <b>Brightness: <\/b> 298.69 K" }, "geometry": { "type": "Point", "coordinates": [ -155.50485, 19.59595, 0.0 ] } },
{ "type": "Feature", "properties": { "Name": "Fire Detection Centroid ", "Description": "<b>Latitude: <\/b> 19.58851<br\/>  <b>Longitude: <\/b> -155.50244<br\/>  <b>Detection Time: <\/b> 2023-05-16 12:08 UTC<br\/>  <b>Sensor: <\/b> NOAA-20 VIIRS<br\/> <b>Confidence: <\/b> Nominal<br\/>  <b>Day\/Night: <\/b> Night<br\/> <b>Scan: <\/b> 0.42 km<br\/> <b>Track: <\/b> 0.38 km<br\/> <b>FRP: <\/b> 2.27 MW<br\/> <b>Brightness: <\/b> 295.46 K" }, "geometry": { "type": "Point", "coordinates": [ -155.50244, 19.58851, 0.0 ] } },
{ "type": "Feature", "properties": { "Name": "Fire Detection Centroid ", "Description": "<b>Latitude: <\/b> 19.59933<br\/>  <b>Longitude: <\/b> -155.5041<br\/>  <b>Detection Time: <\/b> 2023-05-16 12:08 UTC<br\/>  <b>Sensor: <\/b> NOAA-20 VIIRS<br\/> <b>Confidence: <\/b> Nominal<br\/>  <b>Day\/Night: <\/b> Night<br\/> <b>Scan: <\/b> 0.42 km<br\/> <b>Track: <\/b> 0.38 km<br\/> <b>FRP: <\/b> 1.86 MW<br\/> <b>Brightness: <\/b> 295.95 K" }, "geometry": { "type": "Point", "coordinates": [ -155.5041, 19.59933, 0.0 ] } }
]
}
