{
"type": "FeatureCollection",
"crs": { "type": "name", "properties": { "name": "urn:ogc:def:crs:OGC:1.3:CRS84" } },
"features": [
{ "type": "Feature", "properties": { "Name": "Fire Detection Centroid ", "Description": "<b>Latitude: <\/b> 45.23017<br\/>  <b>Longitude: <\/b> -123.16418<br\/>  <b>Detection Time: <\/b> 2023-12-07 11:17 UTC<br\/>  <b>Sensor: <\/b> NOAA-20 VIIRS<br\/> <b>Confidence: <\/b> Nominal<br\/>  <b>Day\/Night: <\/b> Night<br\/> <b>Scan: <\/b> 0.48 km<br\/> <b>Track: <\/b> 0.65 km<br\/> <b>FRP: <\/b> 1.3 MW<br\/> <b>Brightness: <\/b> 295.91 K" }, "geometry": { "type": "Point", "coordinates": [ -123.16418, 45.23017, 0.0 ] } },
{ "type": "Feature", "properties": { "Name": "Fire Detection Centroid ", "Description": "<b>Latitude: <\/b> 45.23043<br\/>  <b>Longitude: <\/b> -123.16122<br\/>  <b>Detection Time: <\/b> 2023-12-07 11:15 UTC<br\/>  <b>Sensor: <\/b> NOAA-20 VIIRS<br\/> <b>Confidence: <\/b> Nominal<br\/>  <b>Day\/Night: <\/b> Night<br\/> <b>Scan: <\/b> 0.5 km<br\/> <b>Track: <\/b> 0.6 km<br\/> <b>FRP: <\/b> 1.3 MW<br\/> <b>Brightness: <\/b> 295.91 K" }, "geometry": { "type": "Point", "coordinates": [ -123.16122, 45.23043, 0.0 ] } }
]
}
