{
"type": "FeatureCollection",
"crs": { "type": "name", "properties": { "name": "urn:ogc:def:crs:OGC:1.3:CRS84" } },
"features": [
{ "type": "Feature", "properties": { "Name": "Fire Detection Centroid ", "Description": "<b>Latitude: <\/b> 37.2874<br\/>  <b>Longitude: <\/b> -120.42517<br\/>  <b>Detection Time: <\/b> 2024-05-05 22:02 UTC<br\/>  <b>Sensor: <\/b> NOAA-20 VIIRS<br\/> <b>Confidence: <\/b> Nominal<br\/>  <b>Day\/Night: <\/b> Day<br\/> <b>Scan: <\/b> 0.6 km<br\/> <b>Track: <\/b> 0.7 km<br\/> <b>FRP: <\/b> 4.53 MW<br\/> <b>Brightness: <\/b> 340.99 K" }, "geometry": { "type": "Point", "coordinates": [ -120.42517, 37.2874, 0.0 ] } },
{ "type": "Feature", "properties": { "Name": "Fire Detection Centroid ", "Description": "<b>Latitude: <\/b> 37.08297<br\/>  <b>Longitude: <\/b> -120.41898<br\/>  <b>Detection Time: <\/b> 2024-05-05 22:02 UTC<br\/>  <b>Sensor: <\/b> NOAA-20 VIIRS<br\/> <b>Confidence: <\/b> Nominal<br\/>  <b>Day\/Night: <\/b> Day<br\/> <b>Scan: <\/b> 0.6 km<br\/> <b>Track: <\/b> 0.7 km<br\/> <b>FRP: <\/b> 7.29 MW<br\/> <b>Brightness: <\/b> 347.31 K" }, "geometry": { "type": "Point", "coordinates": [ -120.41898, 37.08297, 0.0 ] } },
{ "type": "Feature", "properties": { "Name": "Fire Detection Centroid ", "Description": "<b>Latitude: <\/b> 37.21013<br\/>  <b>Longitude: <\/b> -120.4216<br\/>  <b>Detection Time: <\/b> 2024-05-05 22:01 UTC<br\/>  <b>Sensor: <\/b> NOAA-20 VIIRS<br\/> <b>Confidence: <\/b> Nominal<br\/>  <b>Day\/Night: <\/b> Day<br\/> <b>Scan: <\/b> 0.64 km<br\/> <b>Track: <\/b> 0.72 km<br\/> <b>FRP: <\/b> 7.29 MW<br\/> <b>Brightness: <\/b> 347.31 K" }, "geometry": { "type": "Point", "coordinates": [ -120.4216, 37.21013, 0.0 ] } },
{ "type": "Feature", "properties": { "Name": "Fire Detection Centroid ", "Description": "<b>Latitude: <\/b> 37.21266<br\/>  <b>Longitude: <\/b> -120.42294<br\/>  <b>Detection Time: <\/b> 2024-05-05 22:01 UTC<br\/>  <b>Sensor: <\/b> NOAA-20 VIIRS<br\/> <b>Confidence: <\/b> Nominal<br\/>  <b>Day\/Night: <\/b> Day<br\/> <b>Scan: <\/b> 0.64 km<br\/> <b>Track: <\/b> 0.72 km<br\/> <b>FRP: <\/b> 4.53 MW<br\/> <b>Brightness: <\/b> 340.99 K" }, "geometry": { "type": "Point", "coordinates": [ -120.42294, 37.21266, 0.0 ] } }
]
}
