{
"type": "FeatureCollection",
"crs": { "type": "name", "properties": { "name": "urn:ogc:def:crs:OGC:1.3:CRS84" } },
"features": [
{ "type": "Feature", "properties": { "Name": "Fire Detection Centroid ", "Description": "<b>Latitude: <\/b> 17.89797<br\/>  <b>Longitude: <\/b> -71.32492<br\/>  <b>Detection Time: <\/b> 2023-08-07 17:18 UTC<br\/>  <b>Sensor: <\/b> NOAA-20 VIIRS<br\/> <b>Confidence: <\/b> Nominal<br\/>  <b>Day\/Night: <\/b> Day<br\/> <b>Scan: <\/b> 0.4 km<br\/> <b>Track: <\/b> 0.6 km<br\/> <b>FRP: <\/b> 5.79 MW<br\/> <b>Brightness: <\/b> 343.02 K" }, "geometry": { "type": "Point", "coordinates": [ -71.32492, 17.89797, 0.0 ] } },
{ "type": "Feature", "properties": { "Name": "Fire Detection Centroid ", "Description": "<b>Latitude: <\/b> 18.57986<br\/>  <b>Longitude: <\/b> -71.27053<br\/>  <b>Detection Time: <\/b> 2023-08-07 17:18 UTC<br\/>  <b>Sensor: <\/b> NOAA-20 VIIRS<br\/> <b>Confidence: <\/b> Nominal<br\/>  <b>Day\/Night: <\/b> Day<br\/> <b>Scan: <\/b> 0.4 km<br\/> <b>Track: <\/b> 0.6 km<br\/> <b>FRP: <\/b> 3.45 MW<br\/> <b>Brightness: <\/b> 342.73 K" }, "geometry": { "type": "Point", "coordinates": [ -71.27053, 18.57986, 0.0 ] } },
{ "type": "Feature", "properties": { "Name": "Fire Detection Centroid ", "Description": "<b>Latitude: <\/b> 18.61223<br\/>  <b>Longitude: <\/b> -70.8326<br\/>  <b>Detection Time: <\/b> 2023-08-07 17:18 UTC<br\/>  <b>Sensor: <\/b> NOAA-20 VIIRS<br\/> <b>Confidence: <\/b> Nominal<br\/>  <b>Day\/Night: <\/b> Day<br\/> <b>Scan: <\/b> 0.4 km<br\/> <b>Track: <\/b> 0.6 km<br\/> <b>FRP: <\/b> 2.94 MW<br\/> <b>Brightness: <\/b> 337.17 K" }, "geometry": { "type": "Point", "coordinates": [ -70.8326, 18.61223, 0.0 ] } },
{ "type": "Feature", "properties": { "Name": "Fire Detection Centroid ", "Description": "<b>Latitude: <\/b> 18.3849<br\/>  <b>Longitude: <\/b> -71.3256<br\/>  <b>Detection Time: <\/b> 2023-08-07 17:18 UTC<br\/>  <b>Sensor: <\/b> NOAA-20 VIIRS<br\/> <b>Confidence: <\/b> Nominal<br\/>  <b>Day\/Night: <\/b> Day<br\/> <b>Scan: <\/b> 0.4 km<br\/> <b>Track: <\/b> 0.6 km<br\/> <b>FRP: <\/b> 4.68 MW<br\/> <b>Brightness: <\/b> 350.36 K" }, "geometry": { "type": "Point", "coordinates": [ -71.3256, 18.3849, 0.0 ] } },
{ "type": "Feature", "properties": { "Name": "Fire Detection Centroid ", "Description": "<b>Latitude: <\/b> 18.09816<br\/>  <b>Longitude: <\/b> -71.65617<br\/>  <b>Detection Time: <\/b> 2023-08-07 17:18 UTC<br\/>  <b>Sensor: <\/b> NOAA-20 VIIRS<br\/> <b>Confidence: <\/b> Nominal<br\/>  <b>Day\/Night: <\/b> Day<br\/> <b>Scan: <\/b> 0.4 km<br\/> <b>Track: <\/b> 0.6 km<br\/> <b>FRP: <\/b> 5.09 MW<br\/> <b>Brightness: <\/b> 337.67 K" }, "geometry": { "type": "Point", "coordinates": [ -71.65617, 18.09816, 0.0 ] } },
{ "type": "Feature", "properties": { "Name": "Fire Detection Centroid ", "Description": "<b>Latitude: <\/b> 17.96313<br\/>  <b>Longitude: <\/b> -71.31713<br\/>  <b>Detection Time: <\/b> 2023-08-07 17:18 UTC<br\/>  <b>Sensor: <\/b> NOAA-20 VIIRS<br\/> <b>Confidence: <\/b> Nominal<br\/>  <b>Day\/Night: <\/b> Day<br\/> <b>Scan: <\/b> 0.4 km<br\/> <b>Track: <\/b> 0.6 km<br\/> <b>FRP: <\/b> 2.51 MW<br\/> <b>Brightness: <\/b> 330.28 K" }, "geometry": { "type": "Point", "coordinates": [ -71.31713, 17.96313, 0.0 ] } },
{ "type": "Feature", "properties": { "Name": "Fire Detection Centroid ", "Description": "<b>Latitude: <\/b> 19.41168<br\/>  <b>Longitude: <\/b> -155.28175<br\/>  <b>Detection Time: <\/b> 2023-08-07 12:51 UTC<br\/>  <b>Sensor: <\/b> NOAA-20 VIIRS<br\/> <b>Confidence: <\/b> Nominal<br\/>  <b>Day\/Night: <\/b> Night<br\/> <b>Scan: <\/b> 0.67 km<br\/> <b>Track: <\/b> 0.74 km<br\/> <b>FRP: <\/b> 4.02 MW<br\/> <b>Brightness: <\/b> 298.84 K" }, "geometry": { "type": "Point", "coordinates": [ -155.28175, 19.41168, 0.0 ] } },
{ "type": "Feature", "properties": { "Name": "Fire Detection Centroid ", "Description": "<b>Latitude: <\/b> 19.40863<br\/>  <b>Longitude: <\/b> -155.28337<br\/>  <b>Detection Time: <\/b> 2023-08-07 12:51 UTC<br\/>  <b>Sensor: <\/b> NOAA-20 VIIRS<br\/> <b>Confidence: <\/b> Nominal<br\/>  <b>Day\/Night: <\/b> Night<br\/> <b>Scan: <\/b> 0.67 km<br\/> <b>Track: <\/b> 0.74 km<br\/> <b>FRP: <\/b> 3.44 MW<br\/> <b>Brightness: <\/b> 304.47 K" }, "geometry": { "type": "Point", "coordinates": [ -155.28337, 19.40863, 0.0 ] } }
]
}
