{
"type": "FeatureCollection",
"crs": { "type": "name", "properties": { "name": "urn:ogc:def:crs:OGC:1.3:CRS84" } },
"features": [
{ "type": "Feature", "properties": { "Name": "Fire Detection Centroid ", "Description": "<b>Latitude: </b> 19.40983<br/>  <b>Longitude: </b> -155.2872<br/>  <b>Detection Time: </b> 2022-06-18 23:44 UTC<br/>  <b>Sensor: </b> NOAA-20 VIIRS<br/> <b>Confidence: </b> Nominal<br/>  <b>Day/Night: </b> Day<br/> <b>Scan: </b> 0.43 km<br/> <b>Track: </b> 0.38 km<br/> <b>FRP: </b> 87.68 MW<br/> <b>Brightness: </b> 353.53 K" }, "geometry": { "type": "Point", "coordinates": [ -155.2872, 19.40983, 0.0 ] } },
{ "type": "Feature", "properties": { "Name": "Fire Detection Centroid ", "Description": "<b>Latitude: </b> 19.40342<br/>  <b>Longitude: </b> -155.28195<br/>  <b>Detection Time: </b> 2022-06-18 23:44 UTC<br/>  <b>Sensor: </b> NOAA-20 VIIRS<br/> <b>Confidence: </b> Nominal<br/>  <b>Day/Night: </b> Day<br/> <b>Scan: </b> 0.43 km<br/> <b>Track: </b> 0.38 km<br/> <b>FRP: </b> 23.05 MW<br/> <b>Brightness: </b> 355.3 K" }, "geometry": { "type": "Point", "coordinates": [ -155.28195, 19.40342, 0.0 ] } },
{ "type": "Feature", "properties": { "Name": "Fire Detection Centroid ", "Description": "<b>Latitude: </b> 19.40286<br/>  <b>Longitude: </b> -155.28609<br/>  <b>Detection Time: </b> 2022-06-18 23:44 UTC<br/>  <b>Sensor: </b> NOAA-20 VIIRS<br/> <b>Confidence: </b> Low<br/>  <b>Day/Night: </b> Day<br/> <b>Scan: </b> 0.43 km<br/> <b>Track: </b> 0.38 km<br/> <b>FRP: </b> 23.05 MW<br/> <b>Brightness: </b> 367 K" }, "geometry": { "type": "Point", "coordinates": [ -155.28609, 19.40286, 0.0 ] } },
{ "type": "Feature", "properties": { "Name": "Fire Detection Centroid ", "Description": "<b>Latitude: </b> 19.40635<br/>  <b>Longitude: </b> -155.28664<br/>  <b>Detection Time: </b> 2022-06-18 23:44 UTC<br/>  <b>Sensor: </b> NOAA-20 VIIRS<br/> <b>Confidence: </b> High<br/>  <b>Day/Night: </b> Day<br/> <b>Scan: </b> 0.43 km<br/> <b>Track: </b> 0.38 km<br/> <b>FRP: </b> 87.68 MW<br/> <b>Brightness: </b> 367 K" }, "geometry": { "type": "Point", "coordinates": [ -155.28664, 19.40635, 0.0 ] } },
{ "type": "Feature", "properties": { "Name": "Fire Detection Centroid ", "Description": "<b>Latitude: </b> 19.39992<br/>  <b>Longitude: </b> -155.28146<br/>  <b>Detection Time: </b> 2022-06-18 23:44 UTC<br/>  <b>Sensor: </b> NOAA-20 VIIRS<br/> <b>Confidence: </b> Nominal<br/>  <b>Day/Night: </b> Day<br/> <b>Scan: </b> 0.43 km<br/> <b>Track: </b> 0.38 km<br/> <b>FRP: </b> 23.05 MW<br/> <b>Brightness: </b> 338.31 K" }, "geometry": { "type": "Point", "coordinates": [ -155.28146, 19.39992, 0.0 ] } },
{ "type": "Feature", "properties": { "Name": "Fire Detection Centroid ", "Description": "<b>Latitude: </b> 19.4104<br/>  <b>Longitude: </b> -155.28305<br/>  <b>Detection Time: </b> 2022-06-18 23:44 UTC<br/>  <b>Sensor: </b> NOAA-20 VIIRS<br/> <b>Confidence: </b> Nominal<br/>  <b>Day/Night: </b> Day<br/> <b>Scan: </b> 0.43 km<br/> <b>Track: </b> 0.38 km<br/> <b>FRP: </b> 87.68 MW<br/> <b>Brightness: </b> 355.6 K" }, "geometry": { "type": "Point", "coordinates": [ -155.28305, 19.4104, 0.0 ] } },
{ "type": "Feature", "properties": { "Name": "Fire Detection Centroid ", "Description": "<b>Latitude: </b> 19.39936<br/>  <b>Longitude: </b> -155.28558<br/>  <b>Detection Time: </b> 2022-06-18 23:44 UTC<br/>  <b>Sensor: </b> NOAA-20 VIIRS<br/> <b>Confidence: </b> Nominal<br/>  <b>Day/Night: </b> Day<br/> <b>Scan: </b> 0.43 km<br/> <b>Track: </b> 0.38 km<br/> <b>FRP: </b> 23.05 MW<br/> <b>Brightness: </b> 339.5 K" }, "geometry": { "type": "Point", "coordinates": [ -155.28558, 19.39936, 0.0 ] } }
]
}
