{
"type": "FeatureCollection",
"crs": { "type": "name", "properties": { "name": "urn:ogc:def:crs:OGC:1.3:CRS84" } },
"features": [
{ "type": "Feature", "properties": { "Name": "Fire Detection Centroid ", "Description": "<b>Latitude: <\/b> 47.62084<br\/>  <b>Longitude: <\/b> -122.33987<br\/>  <b>Detection Time: <\/b> 2024-02-26 10:56 UTC<br\/>  <b>Sensor: <\/b> NOAA-20 VIIRS<br\/> <b>Confidence: <\/b> Nominal<br\/>  <b>Day\/Night: <\/b> Night<br\/> <b>Scan: <\/b> 0.5 km<br\/> <b>Track: <\/b> 0.5 km<br\/> <b>FRP: <\/b> 1.56 MW<br\/> <b>Brightness: <\/b> 309.84 K" }, "geometry": { "type": "Point", "coordinates": [ -122.33987, 47.62084, 0.0 ] } },
{ "type": "Feature", "properties": { "Name": "Fire Detection Centroid ", "Description": "<b>Latitude: <\/b> 49.16807<br\/>  <b>Longitude: <\/b> -122.97311<br\/>  <b>Detection Time: <\/b> 2024-02-26 10:56 UTC<br\/>  <b>Sensor: <\/b> NOAA-20 VIIRS<br\/> <b>Confidence: <\/b> Nominal<br\/>  <b>Day\/Night: <\/b> Night<br\/> <b>Scan: <\/b> 0.5 km<br\/> <b>Track: <\/b> 0.5 km<br\/> <b>FRP: <\/b> 0.95 MW<br\/> <b>Brightness: <\/b> 298.2 K" }, "geometry": { "type": "Point", "coordinates": [ -122.97311, 49.16807, 0.0 ] } }
]
}
