{
"type": "FeatureCollection",
"crs": { "type": "name", "properties": { "name": "urn:ogc:def:crs:OGC:1.3:CRS84" } },
"features": [
{ "type": "Feature", "properties": { "Name": "Fire Detection Centroid ", "Description": "<b>Latitude: <\/b> 19.49879<br\/>  <b>Longitude: <\/b> -155.26549<br\/>  <b>Detection Time: <\/b> 2024-01-23 11:43 UTC<br\/>  <b>Sensor: <\/b> NOAA-20 VIIRS<br\/> <b>Confidence: <\/b> Nominal<br\/>  <b>Day\/Night: <\/b> Night<br\/> <b>Scan: <\/b> 0.5 km<br\/> <b>Track: <\/b> 0.4 km<br\/> <b>FRP: <\/b> 2.05 MW<br\/> <b>Brightness: <\/b> 303.48 K" }, "geometry": { "type": "Point", "coordinates": [ -155.26549, 19.49879, 0.0 ] } },
{ "type": "Feature", "properties": { "Name": "Fire Detection Centroid ", "Description": "<b>Latitude: <\/b> 19.28983<br\/>  <b>Longitude: <\/b> -155.30431<br\/>  <b>Detection Time: <\/b> 2024-01-23 11:43 UTC<br\/>  <b>Sensor: <\/b> NOAA-20 VIIRS<br\/> <b>Confidence: <\/b> Nominal<br\/>  <b>Day\/Night: <\/b> Night<br\/> <b>Scan: <\/b> 0.5 km<br\/> <b>Track: <\/b> 0.4 km<br\/> <b>FRP: <\/b> 2.12 MW<br\/> <b>Brightness: <\/b> 301.97 K" }, "geometry": { "type": "Point", "coordinates": [ -155.30431, 19.28983, 0.0 ] } }
]
}
