{
"type": "FeatureCollection",
"crs": { "type": "name", "properties": { "name": "urn:ogc:def:crs:OGC:1.3:CRS84" } },
"features": [
{ "type": "Feature", "properties": { "Name": "Fire Detection Centroid ", "Description": "<b>Latitude: <\/b> 19.40662<br\/>  <b>Longitude: <\/b> -155.27858<br\/>  <b>Detection Time: <\/b> 2023-03-15 11:30 UTC<br\/>  <b>Sensor: <\/b> NOAA-20 VIIRS<br\/> <b>Confidence: <\/b> Nominal<br\/>  <b>Day\/Night: <\/b> Night<br\/> <b>Scan: <\/b> 0.51 km<br\/> <b>Track: <\/b> 0.49 km<br\/> <b>FRP: <\/b> 3.74 MW<br\/> <b>Brightness: <\/b> 309.25 K" }, "geometry": { "type": "Point", "coordinates": [ -155.27858, 19.40662, 0.0 ] } },
{ "type": "Feature", "properties": { "Name": "Fire Detection Centroid ", "Description": "<b>Latitude: <\/b> 19.40718<br\/>  <b>Longitude: <\/b> -155.28336<br\/>  <b>Detection Time: <\/b> 2023-03-15 11:30 UTC<br\/>  <b>Sensor: <\/b> NOAA-20 VIIRS<br\/> <b>Confidence: <\/b> Nominal<br\/>  <b>Day\/Night: <\/b> Night<br\/> <b>Scan: <\/b> 0.51 km<br\/> <b>Track: <\/b> 0.49 km<br\/> <b>FRP: <\/b> 4.35 MW<br\/> <b>Brightness: <\/b> 304.5 K" }, "geometry": { "type": "Point", "coordinates": [ -155.28336, 19.40718, 0.0 ] } }
]
}
