{
"type": "FeatureCollection",
"crs": { "type": "name", "properties": { "name": "urn:ogc:def:crs:OGC:1.3:CRS84" } },
"features": [
{ "type": "Feature", "properties": { "Name": "Fire Detection Centroid ", "Description": "<b>Latitude: <\/b> 19.40231<br\/>  <b>Longitude: <\/b> -155.27432<br\/>  <b>Detection Time: <\/b> 2022-08-13 00:03 UTC<br\/>  <b>Sensor: <\/b> Suomi-NPP VIIRS<br\/> <b>Confidence: <\/b> Nominal<br\/>  <b>Day\/Night: <\/b> Day<br\/> <b>Scan: <\/b> 0.5 km<br\/> <b>Track: <\/b> 0.5 km<br\/> <b>FRP: <\/b> 11.9 MW<br\/> <b>Brightness: <\/b> 332.96 K" }, "geometry": { "type": "Point", "coordinates": [ -155.27432, 19.40231, 0.0 ] } },
{ "type": "Feature", "properties": { "Name": "Fire Detection Centroid ", "Description": "<b>Latitude: <\/b> 19.41109<br\/>  <b>Longitude: <\/b> -155.28065<br\/>  <b>Detection Time: <\/b> 2022-08-13 00:03 UTC<br\/>  <b>Sensor: <\/b> Suomi-NPP VIIRS<br\/> <b>Confidence: <\/b> Nominal<br\/>  <b>Day\/Night: <\/b> Day<br\/> <b>Scan: <\/b> 0.5 km<br\/> <b>Track: <\/b> 0.5 km<br\/> <b>FRP: <\/b> 10.41 MW<br\/> <b>Brightness: <\/b> 335.95 K" }, "geometry": { "type": "Point", "coordinates": [ -155.28065, 19.41109, 0.0 ] } },
{ "type": "Feature", "properties": { "Name": "Fire Detection Centroid ", "Description": "<b>Latitude: <\/b> 19.73011<br\/>  <b>Longitude: <\/b> -155.69939<br\/>  <b>Detection Time: <\/b> 2022-08-13 00:03 UTC<br\/>  <b>Sensor: <\/b> Suomi-NPP VIIRS<br\/> <b>Confidence: <\/b> Low<br\/>  <b>Day\/Night: <\/b> Day<br\/> <b>Scan: <\/b> 0.5 km<br\/> <b>Track: <\/b> 0.5 km<br\/> <b>FRP: <\/b> 8.86 MW<br\/> <b>Brightness: <\/b> 331.79 K" }, "geometry": { "type": "Point", "coordinates": [ -155.69939, 19.73011, 0.0 ] } },
{ "type": "Feature", "properties": { "Name": "Fire Detection Centroid ", "Description": "<b>Latitude: <\/b> 19.7606<br\/>  <b>Longitude: <\/b> -155.75497<br\/>  <b>Detection Time: <\/b> 2022-08-13 00:03 UTC<br\/>  <b>Sensor: <\/b> Suomi-NPP VIIRS<br\/> <b>Confidence: <\/b> Nominal<br\/>  <b>Day\/Night: <\/b> Day<br\/> <b>Scan: <\/b> 0.5 km<br\/> <b>Track: <\/b> 0.5 km<br\/> <b>FRP: <\/b> 6.45 MW<br\/> <b>Brightness: <\/b> 341.98 K" }, "geometry": { "type": "Point", "coordinates": [ -155.75497, 19.7606, 0.0 ] } },
{ "type": "Feature", "properties": { "Name": "Fire Detection Centroid ", "Description": "<b>Latitude: <\/b> 19.76127<br\/>  <b>Longitude: <\/b> -155.75685<br\/>  <b>Detection Time: <\/b> 2022-08-13 00:03 UTC<br\/>  <b>Sensor: <\/b> Suomi-NPP VIIRS<br\/> <b>Confidence: <\/b> Nominal<br\/>  <b>Day\/Night: <\/b> Day<br\/> <b>Scan: <\/b> 0.5 km<br\/> <b>Track: <\/b> 0.5 km<br\/> <b>FRP: <\/b> 5.02 MW<br\/> <b>Brightness: <\/b> 340.7 K" }, "geometry": { "type": "Point", "coordinates": [ -155.75685, 19.76127, 0.0 ] } }
]
}
