{
"type": "FeatureCollection",
"crs": { "type": "name", "properties": { "name": "urn:ogc:def:crs:OGC:1.3:CRS84" } },
"features": [
{ "type": "Feature", "properties": { "Name": "Fire Detection Centroid ", "Description": "<b>Latitude: <\/b> 21.09859<br\/>  <b>Longitude: <\/b> -77.04263<br\/>  <b>Detection Time: <\/b> 2024-05-15 05:54 UTC<br\/>  <b>Sensor: <\/b> NOAA-20 VIIRS<br\/> <b>Confidence: <\/b> Nominal<br\/>  <b>Day\/Night: <\/b> Night<br\/> <b>Scan: <\/b> 0.6 km<br\/> <b>Track: <\/b> 0.7 km<br\/> <b>FRP: <\/b> 1.73 MW<br\/> <b>Brightness: <\/b> 303.94 K" }, "geometry": { "type": "Point", "coordinates": [ -77.04263, 21.09859, 0.0 ] } },
{ "type": "Feature", "properties": { "Name": "Fire Detection Centroid ", "Description": "<b>Latitude: <\/b> 21.09156<br\/>  <b>Longitude: <\/b> -77.03735<br\/>  <b>Detection Time: <\/b> 2024-05-15 05:54 UTC<br\/>  <b>Sensor: <\/b> NOAA-20 VIIRS<br\/> <b>Confidence: <\/b> Nominal<br\/>  <b>Day\/Night: <\/b> Night<br\/> <b>Scan: <\/b> 0.6 km<br\/> <b>Track: <\/b> 0.7 km<br\/> <b>FRP: <\/b> 1.73 MW<br\/> <b>Brightness: <\/b> 312.54 K" }, "geometry": { "type": "Point", "coordinates": [ -77.03735, 21.09156, 0.0 ] } },
{ "type": "Feature", "properties": { "Name": "Fire Detection Centroid ", "Description": "<b>Latitude: <\/b> 21.31618<br\/>  <b>Longitude: <\/b> -78.27483<br\/>  <b>Detection Time: <\/b> 2024-05-15 05:54 UTC<br\/>  <b>Sensor: <\/b> NOAA-20 VIIRS<br\/> <b>Confidence: <\/b> Nominal<br\/>  <b>Day\/Night: <\/b> Night<br\/> <b>Scan: <\/b> 0.7 km<br\/> <b>Track: <\/b> 0.8 km<br\/> <b>FRP: <\/b> 1.9 MW<br\/> <b>Brightness: <\/b> 305.47 K" }, "geometry": { "type": "Point", "coordinates": [ -78.27483, 21.31618, 0.0 ] } },
{ "type": "Feature", "properties": { "Name": "Fire Detection Centroid ", "Description": "<b>Latitude: <\/b> 21.09202<br\/>  <b>Longitude: <\/b> -77.04323<br\/>  <b>Detection Time: <\/b> 2024-05-15 05:54 UTC<br\/>  <b>Sensor: <\/b> NOAA-20 VIIRS<br\/> <b>Confidence: <\/b> Nominal<br\/>  <b>Day\/Night: <\/b> Night<br\/> <b>Scan: <\/b> 0.6 km<br\/> <b>Track: <\/b> 0.7 km<br\/> <b>FRP: <\/b> 1.73 MW<br\/> <b>Brightness: <\/b> 312.3 K" }, "geometry": { "type": "Point", "coordinates": [ -77.04323, 21.09202, 0.0 ] } },
{ "type": "Feature", "properties": { "Name": "Fire Detection Centroid ", "Description": "<b>Latitude: <\/b> 45.4022<br\/>  <b>Longitude: <\/b> -65.99585<br\/>  <b>Detection Time: <\/b> 2024-05-15 05:47 UTC<br\/>  <b>Sensor: <\/b> NOAA-20 VIIRS<br\/> <b>Confidence: <\/b> Nominal<br\/>  <b>Day\/Night: <\/b> Night<br\/> <b>Scan: <\/b> 0.5 km<br\/> <b>Track: <\/b> 0.5 km<br\/> <b>FRP: <\/b> 1.6 MW<br\/> <b>Brightness: <\/b> 296.25 K" }, "geometry": { "type": "Point", "coordinates": [ -65.99585, 45.4022, 0.0 ] } },
{ "type": "Feature", "properties": { "Name": "Fire Detection Centroid ", "Description": "<b>Latitude: <\/b> 46.07569<br\/>  <b>Longitude: <\/b> -73.14094<br\/>  <b>Detection Time: <\/b> 2024-05-15 05:47 UTC<br\/>  <b>Sensor: <\/b> NOAA-20 VIIRS<br\/> <b>Confidence: <\/b> Nominal<br\/>  <b>Day\/Night: <\/b> Night<br\/> <b>Scan: <\/b> 0.6 km<br\/> <b>Track: <\/b> 0.7 km<br\/> <b>FRP: <\/b> 0.92 MW<br\/> <b>Brightness: <\/b> 297.5 K" }, "geometry": { "type": "Point", "coordinates": [ -73.14094, 46.07569, 0.0 ] } },
{ "type": "Feature", "properties": { "Name": "Fire Detection Centroid ", "Description": "<b>Latitude: <\/b> 48.07679<br\/>  <b>Longitude: <\/b> -64.94092<br\/>  <b>Detection Time: <\/b> 2024-05-15 05:47 UTC<br\/>  <b>Sensor: <\/b> NOAA-20 VIIRS<br\/> <b>Confidence: <\/b> Nominal<br\/>  <b>Day\/Night: <\/b> Night<br\/> <b>Scan: <\/b> 0.5 km<br\/> <b>Track: <\/b> 0.5 km<br\/> <b>FRP: <\/b> 1.2 MW<br\/> <b>Brightness: <\/b> 298.1 K" }, "geometry": { "type": "Point", "coordinates": [ -64.94092, 48.07679, 0.0 ] } },
{ "type": "Feature", "properties": { "Name": "Fire Detection Centroid ", "Description": "<b>Latitude: <\/b> 48.28653<br\/>  <b>Longitude: <\/b> -64.90218<br\/>  <b>Detection Time: <\/b> 2024-05-15 05:47 UTC<br\/>  <b>Sensor: <\/b> NOAA-20 VIIRS<br\/> <b>Confidence: <\/b> Nominal<br\/>  <b>Day\/Night: <\/b> Night<br\/> <b>Scan: <\/b> 0.5 km<br\/> <b>Track: <\/b> 0.5 km<br\/> <b>FRP: <\/b> 0.89 MW<br\/> <b>Brightness: <\/b> 296.32 K" }, "geometry": { "type": "Point", "coordinates": [ -64.90218, 48.28653, 0.0 ] } }
]
}
