{
"type": "FeatureCollection",
"crs": { "type": "name", "properties": { "name": "urn:ogc:def:crs:OGC:1.3:CRS84" } },
"features": [
{ "type": "Feature", "properties": { "Name": "Fire Detection Centroid ", "Description": "<b>Latitude: <\/b> 45.28459<br\/>  <b>Longitude: <\/b> -66.02136<br\/>  <b>Detection Time: <\/b> 2023-11-03 05:08 UTC<br\/>  <b>Sensor: <\/b> NOAA-20 VIIRS<br\/> <b>Confidence: <\/b> Nominal<br\/>  <b>Day\/Night: <\/b> Night<br\/> <b>Scan: <\/b> 0.7 km<br\/> <b>Track: <\/b> 0.8 km<br\/> <b>FRP: <\/b> 2.11 MW<br\/> <b>Brightness: <\/b> 302.01 K" }, "geometry": { "type": "Point", "coordinates": [ -66.02136, 45.28459, 0.0 ] } }
]
}
