{
"type": "FeatureCollection",
"crs": { "type": "name", "properties": { "name": "urn:ogc:def:crs:OGC:1.3:CRS84" } },
"features": [
{ "type": "Feature", "properties": { "Name": "Fire Detection Centroid ", "Description": "<b>Latitude: <\/b> 18.54574<br\/>  <b>Longitude: <\/b> -71.79111<br\/>  <b>Detection Time: <\/b> 2023-12-24 06:01 UTC<br\/>  <b>Sensor: <\/b> NOAA-20 VIIRS<br\/> <b>Confidence: <\/b> Nominal<br\/>  <b>Day\/Night: <\/b> Night<br\/> <b>Scan: <\/b> 0.4 km<br\/> <b>Track: <\/b> 0.5 km<br\/> <b>FRP: <\/b> 0.63 MW<br\/> <b>Brightness: <\/b> 305.6 K" }, "geometry": { "type": "Point", "coordinates": [ -71.79111, 18.54574, 0.0 ] } },
{ "type": "Feature", "properties": { "Name": "Fire Detection Centroid ", "Description": "<b>Latitude: <\/b> 20.76102<br\/>  <b>Longitude: <\/b> -76.38524<br\/>  <b>Detection Time: <\/b> 2023-12-24 06:00 UTC<br\/>  <b>Sensor: <\/b> NOAA-20 VIIRS<br\/> <b>Confidence: <\/b> Nominal<br\/>  <b>Day\/Night: <\/b> Night<br\/> <b>Scan: <\/b> 0.4 km<br\/> <b>Track: <\/b> 0.6 km<br\/> <b>FRP: <\/b> 2.69 MW<br\/> <b>Brightness: <\/b> 319.02 K" }, "geometry": { "type": "Point", "coordinates": [ -76.38524, 20.76102, 0.0 ] } },
{ "type": "Feature", "properties": { "Name": "Fire Detection Centroid ", "Description": "<b>Latitude: <\/b> 20.76091<br\/>  <b>Longitude: <\/b> -76.38633<br\/>  <b>Detection Time: <\/b> 2023-12-24 06:00 UTC<br\/>  <b>Sensor: <\/b> NOAA-20 VIIRS<br\/> <b>Confidence: <\/b> Nominal<br\/>  <b>Day\/Night: <\/b> Night<br\/> <b>Scan: <\/b> 0.4 km<br\/> <b>Track: <\/b> 0.6 km<br\/> <b>FRP: <\/b> 1.88 MW<br\/> <b>Brightness: <\/b> 306.07 K" }, "geometry": { "type": "Point", "coordinates": [ -76.38633, 20.76091, 0.0 ] } },
{ "type": "Feature", "properties": { "Name": "Fire Detection Centroid ", "Description": "<b>Latitude: <\/b> 20.76049<br\/>  <b>Longitude: <\/b> -76.38199<br\/>  <b>Detection Time: <\/b> 2023-12-24 06:00 UTC<br\/>  <b>Sensor: <\/b> NOAA-20 VIIRS<br\/> <b>Confidence: <\/b> Nominal<br\/>  <b>Day\/Night: <\/b> Night<br\/> <b>Scan: <\/b> 0.4 km<br\/> <b>Track: <\/b> 0.6 km<br\/> <b>FRP: <\/b> 2.03 MW<br\/> <b>Brightness: <\/b> 308 K" }, "geometry": { "type": "Point", "coordinates": [ -76.38199, 20.76049, 0.0 ] } },
{ "type": "Feature", "properties": { "Name": "Fire Detection Centroid ", "Description": "<b>Latitude: <\/b> 36.36004<br\/>  <b>Longitude: <\/b> -76.8103<br\/>  <b>Detection Time: <\/b> 2023-12-24 05:56 UTC<br\/>  <b>Sensor: <\/b> NOAA-20 VIIRS<br\/> <b>Confidence: <\/b> Nominal<br\/>  <b>Day\/Night: <\/b> Night<br\/> <b>Scan: <\/b> 0.7 km<br\/> <b>Track: <\/b> 0.7 km<br\/> <b>FRP: <\/b> 2.66 MW<br\/> <b>Brightness: <\/b> 306.04 K" }, "geometry": { "type": "Point", "coordinates": [ -76.8103, 36.36004, 0.0 ] } }
]
}
