{
"type": "FeatureCollection",
"crs": { "type": "name", "properties": { "name": "urn:ogc:def:crs:OGC:1.3:CRS84" } },
"features": [
{ "type": "Feature", "properties": { "Name": "Fire Detection Centroid ", "Description": "<b>Latitude: <\/b> 21.48041<br\/>  <b>Longitude: <\/b> -157.94275<br\/>  <b>Detection Time: <\/b> 2023-11-02 12:19 UTC<br\/>  <b>Sensor: <\/b> NOAA-20 VIIRS<br\/> <b>Confidence: <\/b> Nominal<br\/>  <b>Day\/Night: <\/b> Night<br\/> <b>Scan: <\/b> 0.42 km<br\/> <b>Track: <\/b> 0.38 km<br\/> <b>FRP: <\/b> 1.5 MW<br\/> <b>Brightness: <\/b> 319.4 K" }, "geometry": { "type": "Point", "coordinates": [ -157.94275, 21.48041, 0.0 ] } },
{ "type": "Feature", "properties": { "Name": "Fire Detection Centroid ", "Description": "<b>Latitude: <\/b> 19.40973<br\/>  <b>Longitude: <\/b> -155.28809<br\/>  <b>Detection Time: <\/b> 2023-11-02 12:19 UTC<br\/>  <b>Sensor: <\/b> NOAA-20 VIIRS<br\/> <b>Confidence: <\/b> Nominal<br\/>  <b>Day\/Night: <\/b> Night<br\/> <b>Scan: <\/b> 0.41 km<br\/> <b>Track: <\/b> 0.45 km<br\/> <b>FRP: <\/b> 2.36 MW<br\/> <b>Brightness: <\/b> 310.13 K" }, "geometry": { "type": "Point", "coordinates": [ -155.28809, 19.40973, 0.0 ] } },
{ "type": "Feature", "properties": { "Name": "Fire Detection Centroid ", "Description": "<b>Latitude: <\/b> 19.40494<br\/>  <b>Longitude: <\/b> -155.28493<br\/>  <b>Detection Time: <\/b> 2023-11-02 12:19 UTC<br\/>  <b>Sensor: <\/b> NOAA-20 VIIRS<br\/> <b>Confidence: <\/b> Nominal<br\/>  <b>Day\/Night: <\/b> Night<br\/> <b>Scan: <\/b> 0.41 km<br\/> <b>Track: <\/b> 0.45 km<br\/> <b>FRP: <\/b> 4.05 MW<br\/> <b>Brightness: <\/b> 316.67 K" }, "geometry": { "type": "Point", "coordinates": [ -155.28493, 19.40494, 0.0 ] } },
{ "type": "Feature", "properties": { "Name": "Fire Detection Centroid ", "Description": "<b>Latitude: <\/b> 19.409<br\/>  <b>Longitude: <\/b> -155.28416<br\/>  <b>Detection Time: <\/b> 2023-11-02 12:19 UTC<br\/>  <b>Sensor: <\/b> NOAA-20 VIIRS<br\/> <b>Confidence: <\/b> Nominal<br\/>  <b>Day\/Night: <\/b> Night<br\/> <b>Scan: <\/b> 0.41 km<br\/> <b>Track: <\/b> 0.45 km<br\/> <b>FRP: <\/b> 3.86 MW<br\/> <b>Brightness: <\/b> 308.83 K" }, "geometry": { "type": "Point", "coordinates": [ -155.28416, 19.409, 0.0 ] } },
{ "type": "Feature", "properties": { "Name": "Fire Detection Centroid ", "Description": "<b>Latitude: <\/b> 19.40567<br\/>  <b>Longitude: <\/b> -155.28883<br\/>  <b>Detection Time: <\/b> 2023-11-02 12:19 UTC<br\/>  <b>Sensor: <\/b> NOAA-20 VIIRS<br\/> <b>Confidence: <\/b> Nominal<br\/>  <b>Day\/Night: <\/b> Night<br\/> <b>Scan: <\/b> 0.41 km<br\/> <b>Track: <\/b> 0.45 km<br\/> <b>FRP: <\/b> 3.12 MW<br\/> <b>Brightness: <\/b> 307.33 K" }, "geometry": { "type": "Point", "coordinates": [ -155.28883, 19.40567, 0.0 ] } },
{ "type": "Feature", "properties": { "Name": "Fire Detection Centroid ", "Description": "<b>Latitude: <\/b> 21.49073<br\/>  <b>Longitude: <\/b> -157.92027<br\/>  <b>Detection Time: <\/b> 2023-11-02 12:19 UTC<br\/>  <b>Sensor: <\/b> NOAA-20 VIIRS<br\/> <b>Confidence: <\/b> Nominal<br\/>  <b>Day\/Night: <\/b> Night<br\/> <b>Scan: <\/b> 0.42 km<br\/> <b>Track: <\/b> 0.38 km<br\/> <b>FRP: <\/b> 1.61 MW<br\/> <b>Brightness: <\/b> 316.83 K" }, "geometry": { "type": "Point", "coordinates": [ -157.92027, 21.49073, 0.0 ] } },
{ "type": "Feature", "properties": { "Name": "Fire Detection Centroid ", "Description": "<b>Latitude: <\/b> 21.48523<br\/>  <b>Longitude: <\/b> -157.92957<br\/>  <b>Detection Time: <\/b> 2023-11-02 12:19 UTC<br\/>  <b>Sensor: <\/b> NOAA-20 VIIRS<br\/> <b>Confidence: <\/b> Nominal<br\/>  <b>Day\/Night: <\/b> Night<br\/> <b>Scan: <\/b> 0.42 km<br\/> <b>Track: <\/b> 0.38 km<br\/> <b>FRP: <\/b> 6.54 MW<br\/> <b>Brightness: <\/b> 348.16 K" }, "geometry": { "type": "Point", "coordinates": [ -157.92957, 21.48523, 0.0 ] } },
{ "type": "Feature", "properties": { "Name": "Fire Detection Centroid ", "Description": "<b>Latitude: <\/b> 21.48592<br\/>  <b>Longitude: <\/b> -157.93355<br\/>  <b>Detection Time: <\/b> 2023-11-02 12:19 UTC<br\/>  <b>Sensor: <\/b> NOAA-20 VIIRS<br\/> <b>Confidence: <\/b> Nominal<br\/>  <b>Day\/Night: <\/b> Night<br\/> <b>Scan: <\/b> 0.42 km<br\/> <b>Track: <\/b> 0.38 km<br\/> <b>FRP: <\/b> 2.48 MW<br\/> <b>Brightness: <\/b> 311.87 K" }, "geometry": { "type": "Point", "coordinates": [ -157.93355, 21.48592, 0.0 ] } },
{ "type": "Feature", "properties": { "Name": "Fire Detection Centroid ", "Description": "<b>Latitude: <\/b> 21.48178<br\/>  <b>Longitude: <\/b> -157.93011<br\/>  <b>Detection Time: <\/b> 2023-11-02 12:19 UTC<br\/>  <b>Sensor: <\/b> NOAA-20 VIIRS<br\/> <b>Confidence: <\/b> Nominal<br\/>  <b>Day\/Night: <\/b> Night<br\/> <b>Scan: <\/b> 0.42 km<br\/> <b>Track: <\/b> 0.38 km<br\/> <b>FRP: <\/b> 7.92 MW<br\/> <b>Brightness: <\/b> 338.2 K" }, "geometry": { "type": "Point", "coordinates": [ -157.93011, 21.48178, 0.0 ] } }
]
}
