{
"type": "FeatureCollection",
"crs": { "type": "name", "properties": { "name": "urn:ogc:def:crs:OGC:1.3:CRS84" } },
"features": [
{ "type": "Feature", "properties": { "Name": "Fire Detection Centroid ", "Description": "<b>Latitude: <\/b> 18.23894<br\/>  <b>Longitude: <\/b> -70.41726<br\/>  <b>Detection Time: <\/b> 2023-08-30 05:36 UTC<br\/>  <b>Sensor: <\/b> NOAA-20 VIIRS<br\/> <b>Confidence: <\/b> Nominal<br\/>  <b>Day\/Night: <\/b> Night<br\/> <b>Scan: <\/b> 0.4 km<br\/> <b>Track: <\/b> 0.6 km<br\/> <b>FRP: <\/b> 2.43 MW<br\/> <b>Brightness: <\/b> 322.8 K" }, "geometry": { "type": "Point", "coordinates": [ -70.41726, 18.23894, 0.0 ] } },
{ "type": "Feature", "properties": { "Name": "Fire Detection Centroid ", "Description": "<b>Latitude: <\/b> 18.92767<br\/>  <b>Longitude: <\/b> -70.356<br\/>  <b>Detection Time: <\/b> 2023-08-30 05:36 UTC<br\/>  <b>Sensor: <\/b> NOAA-20 VIIRS<br\/> <b>Confidence: <\/b> Nominal<br\/>  <b>Day\/Night: <\/b> Night<br\/> <b>Scan: <\/b> 0.4 km<br\/> <b>Track: <\/b> 0.6 km<br\/> <b>FRP: <\/b> 2.93 MW<br\/> <b>Brightness: <\/b> 328.2 K" }, "geometry": { "type": "Point", "coordinates": [ -70.356, 18.92767, 0.0 ] } },
{ "type": "Feature", "properties": { "Name": "Fire Detection Centroid ", "Description": "<b>Latitude: <\/b> 18.92723<br\/>  <b>Longitude: <\/b> -70.35152<br\/>  <b>Detection Time: <\/b> 2023-08-30 05:36 UTC<br\/>  <b>Sensor: <\/b> NOAA-20 VIIRS<br\/> <b>Confidence: <\/b> Nominal<br\/>  <b>Day\/Night: <\/b> Night<br\/> <b>Scan: <\/b> 0.4 km<br\/> <b>Track: <\/b> 0.6 km<br\/> <b>FRP: <\/b> 2.93 MW<br\/> <b>Brightness: <\/b> 318.57 K" }, "geometry": { "type": "Point", "coordinates": [ -70.35152, 18.92723, 0.0 ] } }
]
}
