{
"type": "FeatureCollection",
"crs": { "type": "name", "properties": { "name": "urn:ogc:def:crs:OGC:1.3:CRS84" } },
"features": [
{ "type": "Feature", "properties": { "Name": "Fire Detection Centroid ", "Description": "<b>Latitude: <\/b> 37.39228<br\/>  <b>Longitude: <\/b> -81.32773<br\/>  <b>Detection Time: <\/b> 2023-11-26 17:42 UTC<br\/>  <b>Sensor: <\/b> NOAA-20 VIIRS<br\/> <b>Confidence: <\/b> Nominal<br\/>  <b>Day\/Night: <\/b> Day<br\/> <b>Scan: <\/b> 0.3 km<br\/> <b>Track: <\/b> 0.5 km<br\/> <b>FRP: <\/b> 3.02 MW<br\/> <b>Brightness: <\/b> 337.07 K" }, "geometry": { "type": "Point", "coordinates": [ -81.32773, 37.39228, 0.0 ] } },
{ "type": "Feature", "properties": { "Name": "Fire Detection Centroid ", "Description": "<b>Latitude: <\/b> 26.58542<br\/>  <b>Longitude: <\/b> -80.76552<br\/>  <b>Detection Time: <\/b> 2023-11-26 17:39 UTC<br\/>  <b>Sensor: <\/b> NOAA-20 VIIRS<br\/> <b>Confidence: <\/b> Low<br\/>  <b>Day\/Night: <\/b> Day<br\/> <b>Scan: <\/b> 0.5 km<br\/> <b>Track: <\/b> 0.7 km<br\/> <b>FRP: <\/b> 14.78 MW<br\/> <b>Brightness: <\/b> 356.31 K" }, "geometry": { "type": "Point", "coordinates": [ -80.76552, 26.58542, 0.0 ] } },
{ "type": "Feature", "properties": { "Name": "Fire Detection Centroid ", "Description": "<b>Latitude: <\/b> 26.59146<br\/>  <b>Longitude: <\/b> -80.76739<br\/>  <b>Detection Time: <\/b> 2023-11-26 17:39 UTC<br\/>  <b>Sensor: <\/b> NOAA-20 VIIRS<br\/> <b>Confidence: <\/b> Nominal<br\/>  <b>Day\/Night: <\/b> Day<br\/> <b>Scan: <\/b> 0.5 km<br\/> <b>Track: <\/b> 0.7 km<br\/> <b>FRP: <\/b> 14.78 MW<br\/> <b>Brightness: <\/b> 338.06 K" }, "geometry": { "type": "Point", "coordinates": [ -80.76739, 26.59146, 0.0 ] } },
{ "type": "Feature", "properties": { "Name": "Fire Detection Centroid ", "Description": "<b>Latitude: <\/b> 19.56952<br\/>  <b>Longitude: <\/b> -71.0883<br\/>  <b>Detection Time: <\/b> 2023-11-26 17:37 UTC<br\/>  <b>Sensor: <\/b> NOAA-20 VIIRS<br\/> <b>Confidence: <\/b> Nominal<br\/>  <b>Day\/Night: <\/b> Day<br\/> <b>Scan: <\/b> 0.6 km<br\/> <b>Track: <\/b> 0.4 km<br\/> <b>FRP: <\/b> 2.38 MW<br\/> <b>Brightness: <\/b> 329.99 K" }, "geometry": { "type": "Point", "coordinates": [ -71.0883, 19.56952, 0.0 ] } },
{ "type": "Feature", "properties": { "Name": "Fire Detection Centroid ", "Description": "<b>Latitude: <\/b> 20.77518<br\/>  <b>Longitude: <\/b> -77.46176<br\/>  <b>Detection Time: <\/b> 2023-11-26 17:37 UTC<br\/>  <b>Sensor: <\/b> NOAA-20 VIIRS<br\/> <b>Confidence: <\/b> Nominal<br\/>  <b>Day\/Night: <\/b> Day<br\/> <b>Scan: <\/b> 0.5 km<br\/> <b>Track: <\/b> 0.6 km<br\/> <b>FRP: <\/b> 3.84 MW<br\/> <b>Brightness: <\/b> 332.7 K" }, "geometry": { "type": "Point", "coordinates": [ -77.46176, 20.77518, 0.0 ] } },
{ "type": "Feature", "properties": { "Name": "Fire Detection Centroid ", "Description": "<b>Latitude: <\/b> 18.68154<br\/>  <b>Longitude: <\/b> -70.70147<br\/>  <b>Detection Time: <\/b> 2023-11-26 17:36 UTC<br\/>  <b>Sensor: <\/b> NOAA-20 VIIRS<br\/> <b>Confidence: <\/b> Nominal<br\/>  <b>Day\/Night: <\/b> Day<br\/> <b>Scan: <\/b> 0.6 km<br\/> <b>Track: <\/b> 0.4 km<br\/> <b>FRP: <\/b> 3.89 MW<br\/> <b>Brightness: <\/b> 327.87 K" }, "geometry": { "type": "Point", "coordinates": [ -70.70147, 18.68154, 0.0 ] } },
{ "type": "Feature", "properties": { "Name": "Fire Detection Centroid ", "Description": "<b>Latitude: <\/b> 19.12712<br\/>  <b>Longitude: <\/b> -72.4558<br\/>  <b>Detection Time: <\/b> 2023-11-26 17:36 UTC<br\/>  <b>Sensor: <\/b> NOAA-20 VIIRS<br\/> <b>Confidence: <\/b> Nominal<br\/>  <b>Day\/Night: <\/b> Day<br\/> <b>Scan: <\/b> 0.5 km<br\/> <b>Track: <\/b> 0.5 km<br\/> <b>FRP: <\/b> 1.79 MW<br\/> <b>Brightness: <\/b> 329.37 K" }, "geometry": { "type": "Point", "coordinates": [ -72.4558, 19.12712, 0.0 ] } },
{ "type": "Feature", "properties": { "Name": "Fire Detection Centroid ", "Description": "<b>Latitude: <\/b> 19.10916<br\/>  <b>Longitude: <\/b> -72.47961<br\/>  <b>Detection Time: <\/b> 2023-11-26 17:36 UTC<br\/>  <b>Sensor: <\/b> NOAA-20 VIIRS<br\/> <b>Confidence: <\/b> Nominal<br\/>  <b>Day\/Night: <\/b> Day<br\/> <b>Scan: <\/b> 0.5 km<br\/> <b>Track: <\/b> 0.5 km<br\/> <b>FRP: <\/b> 2.13 MW<br\/> <b>Brightness: <\/b> 328.67 K" }, "geometry": { "type": "Point", "coordinates": [ -72.47961, 19.10916, 0.0 ] } }
]
}
