{
"type": "FeatureCollection",
"crs": { "type": "name", "properties": { "name": "urn:ogc:def:crs:OGC:1.3:CRS84" } },
"features": [
{ "type": "Feature", "properties": { "Name": "Fire Detection Centroid ", "Description": "<b>Latitude: <\/b> 19.40705<br\/>  <b>Longitude: <\/b> -155.27621<br\/>  <b>Detection Time: <\/b> 2023-09-20 23:38 UTC<br\/>  <b>Sensor: <\/b> NOAA-20 VIIRS<br\/> <b>Confidence: <\/b> Nominal<br\/>  <b>Day\/Night: <\/b> Day<br\/> <b>Scan: <\/b> 0.4 km<br\/> <b>Track: <\/b> 0.4 km<br\/> <b>FRP: <\/b> 4.71 MW<br\/> <b>Brightness: <\/b> 333.64 K" }, "geometry": { "type": "Point", "coordinates": [ -155.27621, 19.40705, 0.0 ] } },
{ "type": "Feature", "properties": { "Name": "Fire Detection Centroid ", "Description": "<b>Latitude: <\/b> 19.40735<br\/>  <b>Longitude: <\/b> -155.27588<br\/>  <b>Detection Time: <\/b> 2023-09-20 23:37 UTC<br\/>  <b>Sensor: <\/b> NOAA-20 VIIRS<br\/> <b>Confidence: <\/b> Nominal<br\/>  <b>Day\/Night: <\/b> Day<br\/> <b>Scan: <\/b> 0.39 km<br\/> <b>Track: <\/b> 0.36 km<br\/> <b>FRP: <\/b> 4.71 MW<br\/> <b>Brightness: <\/b> 333.64 K" }, "geometry": { "type": "Point", "coordinates": [ -155.27588, 19.40735, 0.0 ] } }
]
}
