{
"type": "FeatureCollection",
"crs": { "type": "name", "properties": { "name": "urn:ogc:def:crs:OGC:1.3:CRS84" } },
"features": [
{ "type": "Feature", "properties": { "Name": "Fire Detection Centroid ", "Description": "<b>Latitude: <\/b> 18.92822<br\/>  <b>Longitude: <\/b> -70.35545<br\/>  <b>Detection Time: <\/b> 2023-10-28 05:29 UTC<br\/>  <b>Sensor: <\/b> NOAA-20 VIIRS<br\/> <b>Confidence: <\/b> Nominal<br\/>  <b>Day\/Night: <\/b> Night<br\/> <b>Scan: <\/b> 0.6 km<br\/> <b>Track: <\/b> 0.7 km<br\/> <b>FRP: <\/b> 4.93 MW<br\/> <b>Brightness: <\/b> 333.6 K" }, "geometry": { "type": "Point", "coordinates": [ -70.35545, 18.92822, 0.0 ] } },
{ "type": "Feature", "properties": { "Name": "Fire Detection Centroid ", "Description": "<b>Latitude: <\/b> 18.92959<br\/>  <b>Longitude: <\/b> -70.35802<br\/>  <b>Detection Time: <\/b> 2023-10-28 05:28 UTC<br\/>  <b>Sensor: <\/b> NOAA-20 VIIRS<br\/> <b>Confidence: <\/b> Nominal<br\/>  <b>Day\/Night: <\/b> Night<br\/> <b>Scan: <\/b> 0.6 km<br\/> <b>Track: <\/b> 0.7 km<br\/> <b>FRP: <\/b> 4.37 MW<br\/> <b>Brightness: <\/b> 323.2 K" }, "geometry": { "type": "Point", "coordinates": [ -70.35802, 18.92959, 0.0 ] } },
{ "type": "Feature", "properties": { "Name": "Fire Detection Centroid ", "Description": "<b>Latitude: <\/b> 18.9291<br\/>  <b>Longitude: <\/b> -70.35234<br\/>  <b>Detection Time: <\/b> 2023-10-28 05:28 UTC<br\/>  <b>Sensor: <\/b> NOAA-20 VIIRS<br\/> <b>Confidence: <\/b> Nominal<br\/>  <b>Day\/Night: <\/b> Night<br\/> <b>Scan: <\/b> 0.6 km<br\/> <b>Track: <\/b> 0.7 km<br\/> <b>FRP: <\/b> 3.28 MW<br\/> <b>Brightness: <\/b> 304.24 K" }, "geometry": { "type": "Point", "coordinates": [ -70.35234, 18.9291, 0.0 ] } }
]
}
