{
"type": "FeatureCollection",
"crs": { "type": "name", "properties": { "name": "urn:ogc:def:crs:OGC:1.3:CRS84" } },
"features": [
{ "type": "Feature", "properties": { "Name": "Fire Detection Centroid ", "Description": "<b>Latitude: <\/b> 18.36852<br\/>  <b>Longitude: <\/b> -71.40897<br\/>  <b>Detection Time: <\/b> 2024-05-10 05:49 UTC<br\/>  <b>Sensor: <\/b> NOAA-20 VIIRS<br\/> <b>Confidence: <\/b> Nominal<br\/>  <b>Day\/Night: <\/b> Night<br\/> <b>Scan: <\/b> 0.6 km<br\/> <b>Track: <\/b> 0.5 km<br\/> <b>FRP: <\/b> 1.47 MW<br\/> <b>Brightness: <\/b> 302.59 K" }, "geometry": { "type": "Point", "coordinates": [ -71.40897, 18.36852, 0.0 ] } },
{ "type": "Feature", "properties": { "Name": "Fire Detection Centroid ", "Description": "<b>Latitude: <\/b> 18.10519<br\/>  <b>Longitude: <\/b> -66.63721<br\/>  <b>Detection Time: <\/b> 2024-05-10 05:49 UTC<br\/>  <b>Sensor: <\/b> NOAA-20 VIIRS<br\/> <b>Confidence: <\/b> Nominal<br\/>  <b>Day\/Night: <\/b> Night<br\/> <b>Scan: <\/b> 0.5 km<br\/> <b>Track: <\/b> 0.4 km<br\/> <b>FRP: <\/b> 0.44 MW<br\/> <b>Brightness: <\/b> 303.25 K" }, "geometry": { "type": "Point", "coordinates": [ -66.63721, 18.10519, 0.0 ] } }
]
}
