{
"type": "FeatureCollection",
"crs": { "type": "name", "properties": { "name": "urn:ogc:def:crs:OGC:1.3:CRS84" } },
"features": [
{ "type": "Feature", "properties": { "Name": "Fire Detection Centroid ", "Description": "<b>Latitude: <\/b> 49.60226<br\/>  <b>Longitude: <\/b> -126.28144<br\/>  <b>Detection Time: <\/b> 2023-08-26 11:47 UTC<br\/>  <b>Sensor: <\/b> NOAA-20 VIIRS<br\/> <b>Confidence: <\/b> Nominal<br\/>  <b>Day\/Night: <\/b> Night<br\/> <b>Scan: <\/b> 0.55 km<br\/> <b>Track: <\/b> 0.68 km<br\/> <b>FRP: <\/b> 3.07 MW<br\/> <b>Brightness: <\/b> 299.95 K" }, "geometry": { "type": "Point", "coordinates": [ -126.28144, 49.60226, 0.0 ] } },
{ "type": "Feature", "properties": { "Name": "Fire Detection Centroid ", "Description": "<b>Latitude: <\/b> 49.60591<br\/>  <b>Longitude: <\/b> -126.29191<br\/>  <b>Detection Time: <\/b> 2023-08-26 11:47 UTC<br\/>  <b>Sensor: <\/b> NOAA-20 VIIRS<br\/> <b>Confidence: <\/b> Nominal<br\/>  <b>Day\/Night: <\/b> Night<br\/> <b>Scan: <\/b> 0.55 km<br\/> <b>Track: <\/b> 0.68 km<br\/> <b>FRP: <\/b> 4.37 MW<br\/> <b>Brightness: <\/b> 312.58 K" }, "geometry": { "type": "Point", "coordinates": [ -126.29191, 49.60591, 0.0 ] } },
{ "type": "Feature", "properties": { "Name": "Fire Detection Centroid ", "Description": "<b>Latitude: <\/b> 49.60422<br\/>  <b>Longitude: <\/b> -126.28706<br\/>  <b>Detection Time: <\/b> 2023-08-26 11:47 UTC<br\/>  <b>Sensor: <\/b> NOAA-20 VIIRS<br\/> <b>Confidence: <\/b> Nominal<br\/>  <b>Day\/Night: <\/b> Night<br\/> <b>Scan: <\/b> 0.55 km<br\/> <b>Track: <\/b> 0.68 km<br\/> <b>FRP: <\/b> 3.07 MW<br\/> <b>Brightness: <\/b> 325.55 K" }, "geometry": { "type": "Point", "coordinates": [ -126.28706, 49.60422, 0.0 ] } },
{ "type": "Feature", "properties": { "Name": "Fire Detection Centroid ", "Description": "<b>Latitude: <\/b> 49.59722<br\/>  <b>Longitude: <\/b> -126.28751<br\/>  <b>Detection Time: <\/b> 2023-08-26 11:47 UTC<br\/>  <b>Sensor: <\/b> NOAA-20 VIIRS<br\/> <b>Confidence: <\/b> Nominal<br\/>  <b>Day\/Night: <\/b> Night<br\/> <b>Scan: <\/b> 0.55 km<br\/> <b>Track: <\/b> 0.68 km<br\/> <b>FRP: <\/b> 3.55 MW<br\/> <b>Brightness: <\/b> 314.98 K" }, "geometry": { "type": "Point", "coordinates": [ -126.28751, 49.59722, 0.0 ] } },
{ "type": "Feature", "properties": { "Name": "Fire Detection Centroid ", "Description": "<b>Latitude: <\/b> 49.59919<br\/>  <b>Longitude: <\/b> -126.29316<br\/>  <b>Detection Time: <\/b> 2023-08-26 11:47 UTC<br\/>  <b>Sensor: <\/b> NOAA-20 VIIRS<br\/> <b>Confidence: <\/b> Nominal<br\/>  <b>Day\/Night: <\/b> Night<br\/> <b>Scan: <\/b> 0.55 km<br\/> <b>Track: <\/b> 0.68 km<br\/> <b>FRP: <\/b> 2.31 MW<br\/> <b>Brightness: <\/b> 302.03 K" }, "geometry": { "type": "Point", "coordinates": [ -126.29316, 49.59919, 0.0 ] } }
]
}
