{
"type": "FeatureCollection",
"crs": { "type": "name", "properties": { "name": "urn:ogc:def:crs:OGC:1.3:CRS84" } },
"features": [
{ "type": "Feature", "properties": { "Name": "Fire Detection Centroid ", "Description": "<b>Latitude: <\/b> 19.41173<br\/>  <b>Longitude: <\/b> -155.28073<br\/>  <b>Detection Time: <\/b> 2022-09-12 23:31 UTC<br\/>  <b>Sensor: <\/b> NOAA-20 VIIRS<br\/> <b>Confidence: <\/b> Nominal<br\/>  <b>Day\/Night: <\/b> Day<br\/> <b>Scan: <\/b> 0.4 km<br\/> <b>Track: <\/b> 0.4 km<br\/> <b>FRP: <\/b> 6.74 MW<br\/> <b>Brightness: <\/b> 337.03 K" }, "geometry": { "type": "Point", "coordinates": [ -155.28073, 19.41173, 0.0 ] } },
{ "type": "Feature", "properties": { "Name": "Fire Detection Centroid ", "Description": "<b>Latitude: <\/b> 19.41203<br\/>  <b>Longitude: <\/b> -155.2805<br\/>  <b>Detection Time: <\/b> 2022-09-12 23:31 UTC<br\/>  <b>Sensor: <\/b> NOAA-20 VIIRS<br\/> <b>Confidence: <\/b> Nominal<br\/>  <b>Day\/Night: <\/b> Day<br\/> <b>Scan: <\/b> 0.39 km<br\/> <b>Track: <\/b> 0.36 km<br\/> <b>FRP: <\/b> 6.75 MW<br\/> <b>Brightness: <\/b> 337.03 K" }, "geometry": { "type": "Point", "coordinates": [ -155.2805, 19.41203, 0.0 ] } }
]
}
