{
"type": "FeatureCollection",
"crs": { "type": "name", "properties": { "name": "urn:ogc:def:crs:OGC:1.3:CRS84" } },
"features": [
{ "type": "Feature", "properties": { "Name": "Fire Detection Centroid ", "Description": "<b>Latitude: <\/b> 45.27874<br\/>  <b>Longitude: <\/b> -66.02181<br\/>  <b>Detection Time: <\/b> 2023-09-21 05:15 UTC<br\/>  <b>Sensor: <\/b> NOAA-20 VIIRS<br\/> <b>Confidence: <\/b> Nominal<br\/>  <b>Day\/Night: <\/b> Night<br\/> <b>Scan: <\/b> 0.6 km<br\/> <b>Track: <\/b> 0.7 km<br\/> <b>FRP: <\/b> 1.53 MW<br\/> <b>Brightness: <\/b> 300.06 K" }, "geometry": { "type": "Point", "coordinates": [ -66.02181, 45.27874, 0.0 ] } }
]
}
