{
"type": "FeatureCollection",
"crs": { "type": "name", "properties": { "name": "urn:ogc:def:crs:OGC:1.3:CRS84" } },
"features": [
{ "type": "Feature", "properties": { "Name": "Fire Detection Centroid ", "Description": "<b>Latitude: <\/b> 34.15285<br\/>  <b>Longitude: <\/b> -118.19234<br\/>  <b>Detection Time: <\/b> 2023-04-08 10:34 UTC<br\/>  <b>Sensor: <\/b> NOAA-20 VIIRS<br\/> <b>Confidence: <\/b> Nominal<br\/>  <b>Day\/Night: <\/b> Night<br\/> <b>Scan: <\/b> 0.49 km<br\/> <b>Track: <\/b> 0.65 km<br\/> <b>FRP: <\/b> 0.75 MW<br\/> <b>Brightness: <\/b> 298.52 K" }, "geometry": { "type": "Point", "coordinates": [ -118.19234, 34.15285, 0.0 ] } },
{ "type": "Feature", "properties": { "Name": "Fire Detection Centroid ", "Description": "<b>Latitude: <\/b> 34.33652<br\/>  <b>Longitude: <\/b> -118.51891<br\/>  <b>Detection Time: <\/b> 2023-04-08 10:34 UTC<br\/>  <b>Sensor: <\/b> NOAA-20 VIIRS<br\/> <b>Confidence: <\/b> Nominal<br\/>  <b>Day\/Night: <\/b> Night<br\/> <b>Scan: <\/b> 0.47 km<br\/> <b>Track: <\/b> 0.64 km<br\/> <b>FRP: <\/b> 1.12 MW<br\/> <b>Brightness: <\/b> 304.66 K" }, "geometry": { "type": "Point", "coordinates": [ -118.51891, 34.33652, 0.0 ] } },
{ "type": "Feature", "properties": { "Name": "Fire Detection Centroid ", "Description": "<b>Latitude: <\/b> 34.60947<br\/>  <b>Longitude: <\/b> -117.33614<br\/>  <b>Detection Time: <\/b> 2023-04-08 10:34 UTC<br\/>  <b>Sensor: <\/b> NOAA-20 VIIRS<br\/> <b>Confidence: <\/b> Nominal<br\/>  <b>Day\/Night: <\/b> Night<br\/> <b>Scan: <\/b> 0.54 km<br\/> <b>Track: <\/b> 0.68 km<br\/> <b>FRP: <\/b> 1.99 MW<br\/> <b>Brightness: <\/b> 307.55 K" }, "geometry": { "type": "Point", "coordinates": [ -117.33614, 34.60947, 0.0 ] } },
{ "type": "Feature", "properties": { "Name": "Fire Detection Centroid ", "Description": "<b>Latitude: <\/b> 48.34443<br\/>  <b>Longitude: <\/b> -119.69031<br\/>  <b>Detection Time: <\/b> 2023-04-08 10:32 UTC<br\/>  <b>Sensor: <\/b> NOAA-20 VIIRS<br\/> <b>Confidence: <\/b> Nominal<br\/>  <b>Day\/Night: <\/b> Night<br\/> <b>Scan: <\/b> 0.55 km<br\/> <b>Track: <\/b> 0.43 km<br\/> <b>FRP: <\/b> 0.91 MW<br\/> <b>Brightness: <\/b> 295.62 K" }, "geometry": { "type": "Point", "coordinates": [ -119.69031, 48.34443, 0.0 ] } },
{ "type": "Feature", "properties": { "Name": "Fire Detection Centroid ", "Description": "<b>Latitude: <\/b> 45.64747<br\/>  <b>Longitude: <\/b> -120.21445<br\/>  <b>Detection Time: <\/b> 2023-04-08 10:32 UTC<br\/>  <b>Sensor: <\/b> NOAA-20 VIIRS<br\/> <b>Confidence: <\/b> Nominal<br\/>  <b>Day\/Night: <\/b> Night<br\/> <b>Scan: <\/b> 0.4 km<br\/> <b>Track: <\/b> 0.44 km<br\/> <b>FRP: <\/b> 1.01 MW<br\/> <b>Brightness: <\/b> 301.67 K" }, "geometry": { "type": "Point", "coordinates": [ -120.21445, 45.64747, 0.0 ] } },
{ "type": "Feature", "properties": { "Name": "Fire Detection Centroid ", "Description": "<b>Latitude: <\/b> 45.81824<br\/>  <b>Longitude: <\/b> -108.44099<br\/>  <b>Detection Time: <\/b> 2023-04-08 10:32 UTC<br\/>  <b>Sensor: <\/b> NOAA-20 VIIRS<br\/> <b>Confidence: <\/b> Nominal<br\/>  <b>Day\/Night: <\/b> Night<br\/> <b>Scan: <\/b> 0.66 km<br\/> <b>Track: <\/b> 0.73 km<br\/> <b>FRP: <\/b> 1 MW<br\/> <b>Brightness: <\/b> 309.61 K" }, "geometry": { "type": "Point", "coordinates": [ -108.44099, 45.81824, 0.0 ] } }
]
}
