{
"type": "FeatureCollection",
"crs": { "type": "name", "properties": { "name": "urn:ogc:def:crs:OGC:1.3:CRS84" } },
"features": [
{ "type": "Feature", "properties": { "Name": "Fire Detection Centroid ", "Description": "<b>Latitude: <\/b> 19.43025<br\/>  <b>Longitude: <\/b> -155.27832<br\/>  <b>Detection Time: <\/b> 2024-03-25 12:12 UTC<br\/>  <b>Sensor: <\/b> NOAA-20 VIIRS<br\/> <b>Confidence: <\/b> Nominal<br\/>  <b>Day\/Night: <\/b> Night<br\/> <b>Scan: <\/b> 0.5 km<br\/> <b>Track: <\/b> 0.4 km<br\/> <b>FRP: <\/b> 3.47 MW<br\/> <b>Brightness: <\/b> 303.06 K" }, "geometry": { "type": "Point", "coordinates": [ -155.27832, 19.43025, 0.0 ] } }
]
}
