{
"type": "FeatureCollection",
"crs": { "type": "name", "properties": { "name": "urn:ogc:def:crs:OGC:1.3:CRS84" } },
"features": [
{ "type": "Feature", "properties": { "Name": "Fire Detection Centroid ", "Description": "<b>Latitude: <\/b> 19.41362<br\/>  <b>Longitude: <\/b> -155.28296<br\/>  <b>Detection Time: <\/b> 2023-10-21 12:46 UTC<br\/>  <b>Sensor: <\/b> NOAA-20 VIIRS<br\/> <b>Confidence: <\/b> Nominal<br\/>  <b>Day\/Night: <\/b> Night<br\/> <b>Scan: <\/b> 0.52 km<br\/> <b>Track: <\/b> 0.67 km<br\/> <b>FRP: <\/b> 4.59 MW<br\/> <b>Brightness: <\/b> 307.96 K" }, "geometry": { "type": "Point", "coordinates": [ -155.28296, 19.41362, 0.0 ] } },
{ "type": "Feature", "properties": { "Name": "Fire Detection Centroid ", "Description": "<b>Latitude: <\/b> 19.40758<br\/>  <b>Longitude: <\/b> -155.28418<br\/>  <b>Detection Time: <\/b> 2023-10-21 12:46 UTC<br\/>  <b>Sensor: <\/b> NOAA-20 VIIRS<br\/> <b>Confidence: <\/b> Nominal<br\/>  <b>Day\/Night: <\/b> Night<br\/> <b>Scan: <\/b> 0.52 km<br\/> <b>Track: <\/b> 0.67 km<br\/> <b>FRP: <\/b> 4.59 MW<br\/> <b>Brightness: <\/b> 308.54 K" }, "geometry": { "type": "Point", "coordinates": [ -155.28418, 19.40758, 0.0 ] } },
{ "type": "Feature", "properties": { "Name": "Fire Detection Centroid ", "Description": "<b>Latitude: <\/b> 19.40877<br\/>  <b>Longitude: <\/b> -155.28938<br\/>  <b>Detection Time: <\/b> 2023-10-21 12:46 UTC<br\/>  <b>Sensor: <\/b> NOAA-20 VIIRS<br\/> <b>Confidence: <\/b> Nominal<br\/>  <b>Day\/Night: <\/b> Night<br\/> <b>Scan: <\/b> 0.52 km<br\/> <b>Track: <\/b> 0.67 km<br\/> <b>FRP: <\/b> 3.69 MW<br\/> <b>Brightness: <\/b> 311.22 K" }, "geometry": { "type": "Point", "coordinates": [ -155.28938, 19.40877, 0.0 ] } },
{ "type": "Feature", "properties": { "Name": "Fire Detection Centroid ", "Description": "<b>Latitude: <\/b> 19.41486<br\/>  <b>Longitude: <\/b> -155.28842<br\/>  <b>Detection Time: <\/b> 2023-10-21 12:46 UTC<br\/>  <b>Sensor: <\/b> NOAA-20 VIIRS<br\/> <b>Confidence: <\/b> Nominal<br\/>  <b>Day\/Night: <\/b> Night<br\/> <b>Scan: <\/b> 0.52 km<br\/> <b>Track: <\/b> 0.67 km<br\/> <b>FRP: <\/b> 3.69 MW<br\/> <b>Brightness: <\/b> 307.72 K" }, "geometry": { "type": "Point", "coordinates": [ -155.28842, 19.41486, 0.0 ] } }
]
}
