{
"type": "FeatureCollection",
"crs": { "type": "name", "properties": { "name": "urn:ogc:def:crs:OGC:1.3:CRS84" } },
"features": [
{ "type": "Feature", "properties": { "Name": "Fire Detection Centroid ", "Description": "<b>Latitude: <\/b> 18.63114<br\/>  <b>Longitude: <\/b> -69.06308<br\/>  <b>Detection Time: <\/b> 2024-04-08 05:48 UTC<br\/>  <b>Sensor: <\/b> NOAA-20 VIIRS<br\/> <b>Confidence: <\/b> Nominal<br\/>  <b>Day\/Night: <\/b> Night<br\/> <b>Scan: <\/b> 0.5 km<br\/> <b>Track: <\/b> 0.5 km<br\/> <b>FRP: <\/b> 0.84 MW<br\/> <b>Brightness: <\/b> 305.32 K" }, "geometry": { "type": "Point", "coordinates": [ -69.06308, 18.63114, 0.0 ] } },
{ "type": "Feature", "properties": { "Name": "Fire Detection Centroid ", "Description": "<b>Latitude: <\/b> 20.37423<br\/>  <b>Longitude: <\/b> -77.04295<br\/>  <b>Detection Time: <\/b> 2024-04-08 05:48 UTC<br\/>  <b>Sensor: <\/b> NOAA-20 VIIRS<br\/> <b>Confidence: <\/b> Nominal<br\/>  <b>Day\/Night: <\/b> Night<br\/> <b>Scan: <\/b> 0.8 km<br\/> <b>Track: <\/b> 0.8 km<br\/> <b>FRP: <\/b> 1.71 MW<br\/> <b>Brightness: <\/b> 298.35 K" }, "geometry": { "type": "Point", "coordinates": [ -77.04295, 20.37423, 0.0 ] } },
{ "type": "Feature", "properties": { "Name": "Fire Detection Centroid ", "Description": "<b>Latitude: <\/b> 18.16254<br\/>  <b>Longitude: <\/b> -65.80025<br\/>  <b>Detection Time: <\/b> 2024-04-08 05:48 UTC<br\/>  <b>Sensor: <\/b> NOAA-20 VIIRS<br\/> <b>Confidence: <\/b> Nominal<br\/>  <b>Day\/Night: <\/b> Night<br\/> <b>Scan: <\/b> 0.4 km<br\/> <b>Track: <\/b> 0.4 km<br\/> <b>FRP: <\/b> 1.06 MW<br\/> <b>Brightness: <\/b> 304.85 K" }, "geometry": { "type": "Point", "coordinates": [ -65.80025, 18.16254, 0.0 ] } },
{ "type": "Feature", "properties": { "Name": "Fire Detection Centroid ", "Description": "<b>Latitude: <\/b> 18.41795<br\/>  <b>Longitude: <\/b> -69.09451<br\/>  <b>Detection Time: <\/b> 2024-04-08 05:48 UTC<br\/>  <b>Sensor: <\/b> NOAA-20 VIIRS<br\/> <b>Confidence: <\/b> Nominal<br\/>  <b>Day\/Night: <\/b> Night<br\/> <b>Scan: <\/b> 0.5 km<br\/> <b>Track: <\/b> 0.5 km<br\/> <b>FRP: <\/b> 1.98 MW<br\/> <b>Brightness: <\/b> 315.39 K" }, "geometry": { "type": "Point", "coordinates": [ -69.09451, 18.41795, 0.0 ] } },
{ "type": "Feature", "properties": { "Name": "Fire Detection Centroid ", "Description": "<b>Latitude: <\/b> 18.62682<br\/>  <b>Longitude: <\/b> -69.06367<br\/>  <b>Detection Time: <\/b> 2024-04-08 05:48 UTC<br\/>  <b>Sensor: <\/b> NOAA-20 VIIRS<br\/> <b>Confidence: <\/b> Nominal<br\/>  <b>Day\/Night: <\/b> Night<br\/> <b>Scan: <\/b> 0.5 km<br\/> <b>Track: <\/b> 0.5 km<br\/> <b>FRP: <\/b> 1.84 MW<br\/> <b>Brightness: <\/b> 315.5 K" }, "geometry": { "type": "Point", "coordinates": [ -69.06367, 18.62682, 0.0 ] } },
{ "type": "Feature", "properties": { "Name": "Fire Detection Centroid ", "Description": "<b>Latitude: <\/b> 18.41744<br\/>  <b>Longitude: <\/b> -69.09025<br\/>  <b>Detection Time: <\/b> 2024-04-08 05:48 UTC<br\/>  <b>Sensor: <\/b> NOAA-20 VIIRS<br\/> <b>Confidence: <\/b> Nominal<br\/>  <b>Day\/Night: <\/b> Night<br\/> <b>Scan: <\/b> 0.5 km<br\/> <b>Track: <\/b> 0.5 km<br\/> <b>FRP: <\/b> 1.99 MW<br\/> <b>Brightness: <\/b> 310.18 K" }, "geometry": { "type": "Point", "coordinates": [ -69.09025, 18.41744, 0.0 ] } },
{ "type": "Feature", "properties": { "Name": "Fire Detection Centroid ", "Description": "<b>Latitude: <\/b> 45.86162<br\/>  <b>Longitude: <\/b> -73.25388<br\/>  <b>Detection Time: <\/b> 2024-04-08 05:40 UTC<br\/>  <b>Sensor: <\/b> NOAA-20 VIIRS<br\/> <b>Confidence: <\/b> Nominal<br\/>  <b>Day\/Night: <\/b> Night<br\/> <b>Scan: <\/b> 0.7 km<br\/> <b>Track: <\/b> 0.7 km<br\/> <b>FRP: <\/b> 3.04 MW<br\/> <b>Brightness: <\/b> 313.78 K" }, "geometry": { "type": "Point", "coordinates": [ -73.25388, 45.86162, 0.0 ] } }
]
}
