{
"type": "FeatureCollection",
"crs": { "type": "name", "properties": { "name": "urn:ogc:def:crs:OGC:1.3:CRS84" } },
"features": [
{ "type": "Feature", "properties": { "Name": "Fire Detection Centroid ", "Description": "<b>Latitude: <\/b> 19.3651<br\/>  <b>Longitude: <\/b> -155.30989<br\/>  <b>Detection Time: <\/b> 2024-06-07 12:08 UTC<br\/>  <b>Sensor: <\/b> NOAA-20 VIIRS<br\/> <b>Confidence: <\/b> Nominal<br\/>  <b>Day\/Night: <\/b> Night<br\/> <b>Scan: <\/b> 0.43 km<br\/> <b>Track: <\/b> 0.38 km<br\/> <b>FRP: <\/b> 2.68 MW<br\/> <b>Brightness: <\/b> 312.49 K" }, "geometry": { "type": "Point", "coordinates": [ -155.30989, 19.3651, 0.0 ] } },
{ "type": "Feature", "properties": { "Name": "Fire Detection Centroid ", "Description": "<b>Latitude: <\/b> 19.36856<br\/>  <b>Longitude: <\/b> -155.30927<br\/>  <b>Detection Time: <\/b> 2024-06-07 12:08 UTC<br\/>  <b>Sensor: <\/b> NOAA-20 VIIRS<br\/> <b>Confidence: <\/b> Nominal<br\/>  <b>Day\/Night: <\/b> Night<br\/> <b>Scan: <\/b> 0.43 km<br\/> <b>Track: <\/b> 0.38 km<br\/> <b>FRP: <\/b> 4.32 MW<br\/> <b>Brightness: <\/b> 327.85 K" }, "geometry": { "type": "Point", "coordinates": [ -155.30927, 19.36856, 0.0 ] } }
]
}
