{
"type": "FeatureCollection",
"crs": { "type": "name", "properties": { "name": "urn:ogc:def:crs:OGC:1.3:CRS84" } },
"features": [
{ "type": "Feature", "properties": { "Name": "Fire Detection Centroid ", "Description": "<b>Latitude: <\/b> 46.1289<br\/>  <b>Longitude: <\/b> -122.40144<br\/>  <b>Detection Time: <\/b> 2024-02-14 11:21 UTC<br\/>  <b>Sensor: <\/b> NOAA-20 VIIRS<br\/> <b>Confidence: <\/b> Nominal<br\/>  <b>Day\/Night: <\/b> Night<br\/> <b>Scan: <\/b> 0.57 km<br\/> <b>Track: <\/b> 0.69 km<br\/> <b>FRP: <\/b> 2.79 MW<br\/> <b>Brightness: <\/b> 317.44 K" }, "geometry": { "type": "Point", "coordinates": [ -122.40144, 46.1289, 0.0 ] } },
{ "type": "Feature", "properties": { "Name": "Fire Detection Centroid ", "Description": "<b>Latitude: <\/b> 46.13289<br\/>  <b>Longitude: <\/b> -122.39997<br\/>  <b>Detection Time: <\/b> 2024-02-14 11:21 UTC<br\/>  <b>Sensor: <\/b> NOAA-20 VIIRS<br\/> <b>Confidence: <\/b> Nominal<br\/>  <b>Day\/Night: <\/b> Night<br\/> <b>Scan: <\/b> 0.57 km<br\/> <b>Track: <\/b> 0.69 km<br\/> <b>FRP: <\/b> 1.26 MW<br\/> <b>Brightness: <\/b> 312.6 K" }, "geometry": { "type": "Point", "coordinates": [ -122.39997, 46.13289, 0.0 ] } },
{ "type": "Feature", "properties": { "Name": "Fire Detection Centroid ", "Description": "<b>Latitude: <\/b> 49.46575<br\/>  <b>Longitude: <\/b> -117.45289<br\/>  <b>Detection Time: <\/b> 2024-02-14 11:19 UTC<br\/>  <b>Sensor: <\/b> NOAA-20 VIIRS<br\/> <b>Confidence: <\/b> Nominal<br\/>  <b>Day\/Night: <\/b> Night<br\/> <b>Scan: <\/b> 0.69 km<br\/> <b>Track: <\/b> 0.74 km<br\/> <b>FRP: <\/b> 6.92 MW<br\/> <b>Brightness: <\/b> 326.8 K" }, "geometry": { "type": "Point", "coordinates": [ -117.45289, 49.46575, 0.0 ] } },
{ "type": "Feature", "properties": { "Name": "Fire Detection Centroid ", "Description": "<b>Latitude: <\/b> 49.46352<br\/>  <b>Longitude: <\/b> -117.44699<br\/>  <b>Detection Time: <\/b> 2024-02-14 11:19 UTC<br\/>  <b>Sensor: <\/b> NOAA-20 VIIRS<br\/> <b>Confidence: <\/b> Nominal<br\/>  <b>Day\/Night: <\/b> Night<br\/> <b>Scan: <\/b> 0.69 km<br\/> <b>Track: <\/b> 0.74 km<br\/> <b>FRP: <\/b> 6.92 MW<br\/> <b>Brightness: <\/b> 336.04 K" }, "geometry": { "type": "Point", "coordinates": [ -117.44699, 49.46352, 0.0 ] } }
]
}
