{
"type": "FeatureCollection",
"crs": { "type": "name", "properties": { "name": "urn:ogc:def:crs:OGC:1.3:CRS84" } },
"features": [
{ "type": "Feature", "properties": { "Name": "Fire Detection Centroid ", "Description": "<b>Latitude: <\/b> 31.03543<br\/>  <b>Longitude: <\/b> -114.84425<br\/>  <b>Detection Time: <\/b> 2023-05-21 10:30 UTC<br\/>  <b>Sensor: <\/b> NOAA-20 VIIRS<br\/> <b>Confidence: <\/b> Nominal<br\/>  <b>Day\/Night: <\/b> Night<br\/> <b>Scan: <\/b> 0.74 km<br\/> <b>Track: <\/b> 0.76 km<br\/> <b>FRP: <\/b> 1.88 MW<br\/> <b>Brightness: <\/b> 299.9 K" }, "geometry": { "type": "Point", "coordinates": [ -114.84425, 31.03543, 0.0 ] } },
{ "type": "Feature", "properties": { "Name": "Fire Detection Centroid ", "Description": "<b>Latitude: <\/b> 31.03587<br\/>  <b>Longitude: <\/b> -114.84697<br\/>  <b>Detection Time: <\/b> 2023-05-21 10:30 UTC<br\/>  <b>Sensor: <\/b> NOAA-20 VIIRS<br\/> <b>Confidence: <\/b> Nominal<br\/>  <b>Day\/Night: <\/b> Night<br\/> <b>Scan: <\/b> 0.74 km<br\/> <b>Track: <\/b> 0.76 km<br\/> <b>FRP: <\/b> 1.53 MW<br\/> <b>Brightness: <\/b> 306.93 K" }, "geometry": { "type": "Point", "coordinates": [ -114.84697, 31.03587, 0.0 ] } }
]
}
