{
"type": "FeatureCollection",
"crs": { "type": "name", "properties": { "name": "urn:ogc:def:crs:OGC:1.3:CRS84" } },
"features": [
{ "type": "Feature", "properties": { "Name": "Fire Detection Centroid ", "Description": "<b>Latitude: <\/b> 46.01547<br\/>  <b>Longitude: <\/b> -65.06223<br\/>  <b>Detection Time: <\/b> 2022-06-26 16:16 UTC<br\/>  <b>Sensor: <\/b> NOAA-20 VIIRS<br\/> <b>Confidence: <\/b> Nominal<br\/>  <b>Day\/Night: <\/b> Day<br\/> <b>Scan: <\/b> 0.4 km<br\/> <b>Track: <\/b> 0.6 km<br\/> <b>FRP: <\/b> 4.73 MW<br\/> <b>Brightness: <\/b> 342.19 K" }, "geometry": { "type": "Point", "coordinates": [ -65.06223, 46.01547, 0.0 ] } },
{ "type": "Feature", "properties": { "Name": "Fire Detection Centroid ", "Description": "<b>Latitude: <\/b> 47.57252<br\/>  <b>Longitude: <\/b> -122.36952<br\/>  <b>Detection Time: <\/b> 2022-06-26 11:34 UTC<br\/>  <b>Sensor: <\/b> NOAA-20 VIIRS<br\/> <b>Confidence: <\/b> Nominal<br\/>  <b>Day\/Night: <\/b> Night<br\/> <b>Scan: <\/b> 0.69 km<br\/> <b>Track: <\/b> 0.74 km<br\/> <b>FRP: <\/b> 2.12 MW<br\/> <b>Brightness: <\/b> 311.43 K" }, "geometry": { "type": "Point", "coordinates": [ -122.36952, 47.57252, 0.0 ] } },
{ "type": "Feature", "properties": { "Name": "Fire Detection Centroid ", "Description": "<b>Latitude: <\/b> 47.57052<br\/>  <b>Longitude: <\/b> -122.37198<br\/>  <b>Detection Time: <\/b> 2022-06-26 11:34 UTC<br\/>  <b>Sensor: <\/b> NOAA-20 VIIRS<br\/> <b>Confidence: <\/b> Nominal<br\/>  <b>Day\/Night: <\/b> Night<br\/> <b>Scan: <\/b> 0.69 km<br\/> <b>Track: <\/b> 0.74 km<br\/> <b>FRP: <\/b> 1.47 MW<br\/> <b>Brightness: <\/b> 311.01 K" }, "geometry": { "type": "Point", "coordinates": [ -122.37198, 47.57052, 0.0 ] } },
{ "type": "Feature", "properties": { "Name": "Fire Detection Centroid ", "Description": "<b>Latitude: <\/b> 48.88571<br\/>  <b>Longitude: <\/b> -122.73254<br\/>  <b>Detection Time: <\/b> 2022-06-26 11:34 UTC<br\/>  <b>Sensor: <\/b> NOAA-20 VIIRS<br\/> <b>Confidence: <\/b> Nominal<br\/>  <b>Day\/Night: <\/b> Night<br\/> <b>Scan: <\/b> 0.6 km<br\/> <b>Track: <\/b> 0.7 km<br\/> <b>FRP: <\/b> 1.17 MW<br\/> <b>Brightness: <\/b> 295.99 K" }, "geometry": { "type": "Point", "coordinates": [ -122.73254, 48.88571, 0.0 ] } }
]
}
