{
"type": "FeatureCollection",
"crs": { "type": "name", "properties": { "name": "urn:ogc:def:crs:OGC:1.3:CRS84" } },
"features": [
{ "type": "Feature", "properties": { "Name": "Fire Detection Centroid ", "Description": "<b>Latitude: <\/b> 21.9019<br\/>  <b>Longitude: <\/b> -159.45421<br\/>  <b>Detection Time: <\/b> 2023-12-09 23:39 UTC<br\/>  <b>Sensor: <\/b> NOAA-20 VIIRS<br\/> <b>Confidence: <\/b> Nominal<br\/>  <b>Day\/Night: <\/b> Day<br\/> <b>Scan: <\/b> 0.4 km<br\/> <b>Track: <\/b> 0.4 km<br\/> <b>FRP: <\/b> 3.76 MW<br\/> <b>Brightness: <\/b> 339.38 K" }, "geometry": { "type": "Point", "coordinates": [ -159.45421, 21.9019, 0.0 ] } },
{ "type": "Feature", "properties": { "Name": "Fire Detection Centroid ", "Description": "<b>Latitude: <\/b> 21.90259<br\/>  <b>Longitude: <\/b> -159.45012<br\/>  <b>Detection Time: <\/b> 2023-12-09 23:39 UTC<br\/>  <b>Sensor: <\/b> NOAA-20 VIIRS<br\/> <b>Confidence: <\/b> Nominal<br\/>  <b>Day\/Night: <\/b> Day<br\/> <b>Scan: <\/b> 0.4 km<br\/> <b>Track: <\/b> 0.4 km<br\/> <b>FRP: <\/b> 3.76 MW<br\/> <b>Brightness: <\/b> 345.51 K" }, "geometry": { "type": "Point", "coordinates": [ -159.45012, 21.90259, 0.0 ] } },
{ "type": "Feature", "properties": { "Name": "Fire Detection Centroid ", "Description": "<b>Latitude: <\/b> 21.89914<br\/>  <b>Longitude: <\/b> -159.44951<br\/>  <b>Detection Time: <\/b> 2023-12-09 23:39 UTC<br\/>  <b>Sensor: <\/b> NOAA-20 VIIRS<br\/> <b>Confidence: <\/b> Nominal<br\/>  <b>Day\/Night: <\/b> Day<br\/> <b>Scan: <\/b> 0.4 km<br\/> <b>Track: <\/b> 0.4 km<br\/> <b>FRP: <\/b> 2.76 MW<br\/> <b>Brightness: <\/b> 340.02 K" }, "geometry": { "type": "Point", "coordinates": [ -159.44951, 21.89914, 0.0 ] } },
{ "type": "Feature", "properties": { "Name": "Fire Detection Centroid ", "Description": "<b>Latitude: <\/b> 21.89846<br\/>  <b>Longitude: <\/b> -159.45358<br\/>  <b>Detection Time: <\/b> 2023-12-09 23:39 UTC<br\/>  <b>Sensor: <\/b> NOAA-20 VIIRS<br\/> <b>Confidence: <\/b> Nominal<br\/>  <b>Day\/Night: <\/b> Day<br\/> <b>Scan: <\/b> 0.4 km<br\/> <b>Track: <\/b> 0.4 km<br\/> <b>FRP: <\/b> 2.76 MW<br\/> <b>Brightness: <\/b> 339.9 K" }, "geometry": { "type": "Point", "coordinates": [ -159.45358, 21.89846, 0.0 ] } },
{ "type": "Feature", "properties": { "Name": "Fire Detection Centroid ", "Description": "<b>Latitude: <\/b> 21.90254<br\/>  <b>Longitude: <\/b> -159.45375<br\/>  <b>Detection Time: <\/b> 2023-12-09 23:37 UTC<br\/>  <b>Sensor: <\/b> NOAA-20 VIIRS<br\/> <b>Confidence: <\/b> Nominal<br\/>  <b>Day\/Night: <\/b> Day<br\/> <b>Scan: <\/b> 0.43 km<br\/> <b>Track: <\/b> 0.38 km<br\/> <b>FRP: <\/b> 3.77 MW<br\/> <b>Brightness: <\/b> 339.38 K" }, "geometry": { "type": "Point", "coordinates": [ -159.45375, 21.90254, 0.0 ] } },
{ "type": "Feature", "properties": { "Name": "Fire Detection Centroid ", "Description": "<b>Latitude: <\/b> 21.89978<br\/>  <b>Longitude: <\/b> -159.44904<br\/>  <b>Detection Time: <\/b> 2023-12-09 23:37 UTC<br\/>  <b>Sensor: <\/b> NOAA-20 VIIRS<br\/> <b>Confidence: <\/b> Nominal<br\/>  <b>Day\/Night: <\/b> Day<br\/> <b>Scan: <\/b> 0.43 km<br\/> <b>Track: <\/b> 0.38 km<br\/> <b>FRP: <\/b> 2.76 MW<br\/> <b>Brightness: <\/b> 340.02 K" }, "geometry": { "type": "Point", "coordinates": [ -159.44904, 21.89978, 0.0 ] } },
{ "type": "Feature", "properties": { "Name": "Fire Detection Centroid ", "Description": "<b>Latitude: <\/b> 21.90322<br\/>  <b>Longitude: <\/b> -159.44968<br\/>  <b>Detection Time: <\/b> 2023-12-09 23:37 UTC<br\/>  <b>Sensor: <\/b> NOAA-20 VIIRS<br\/> <b>Confidence: <\/b> Nominal<br\/>  <b>Day\/Night: <\/b> Day<br\/> <b>Scan: <\/b> 0.43 km<br\/> <b>Track: <\/b> 0.38 km<br\/> <b>FRP: <\/b> 3.77 MW<br\/> <b>Brightness: <\/b> 345.51 K" }, "geometry": { "type": "Point", "coordinates": [ -159.44968, 21.90322, 0.0 ] } },
{ "type": "Feature", "properties": { "Name": "Fire Detection Centroid ", "Description": "<b>Latitude: <\/b> 21.89909<br\/>  <b>Longitude: <\/b> -159.45311<br\/>  <b>Detection Time: <\/b> 2023-12-09 23:37 UTC<br\/>  <b>Sensor: <\/b> NOAA-20 VIIRS<br\/> <b>Confidence: <\/b> Nominal<br\/>  <b>Day\/Night: <\/b> Day<br\/> <b>Scan: <\/b> 0.43 km<br\/> <b>Track: <\/b> 0.38 km<br\/> <b>FRP: <\/b> 2.76 MW<br\/> <b>Brightness: <\/b> 339.9 K" }, "geometry": { "type": "Point", "coordinates": [ -159.45311, 21.89909, 0.0 ] } }
]
}
