{
"type": "FeatureCollection",
"crs": { "type": "name", "properties": { "name": "urn:ogc:def:crs:OGC:1.3:CRS84" } },
"features": [
{ "type": "Feature", "properties": { "Name": "Fire Detection Centroid ", "Description": "<b>Latitude: <\/b> 19.40669<br\/>  <b>Longitude: <\/b> -155.28517<br\/>  <b>Detection Time: <\/b> 2022-07-17 23:00 UTC<br\/>  <b>Sensor: <\/b> NOAA-20 VIIRS<br\/> <b>Confidence: <\/b> Low<br\/>  <b>Day\/Night: <\/b> Day<br\/> <b>Scan: <\/b> 0.6 km<br\/> <b>Track: <\/b> 0.5 km<br\/> <b>FRP: <\/b> 51.4 MW<br\/> <b>Brightness: <\/b> 304.24 K" }, "geometry": { "type": "Point", "coordinates": [ -155.28517, 19.40669, 0.0 ] } },
{ "type": "Feature", "properties": { "Name": "Fire Detection Centroid ", "Description": "<b>Latitude: <\/b> 19.40782<br\/>  <b>Longitude: <\/b> -155.27943<br\/>  <b>Detection Time: <\/b> 2022-07-17 23:00 UTC<br\/>  <b>Sensor: <\/b> NOAA-20 VIIRS<br\/> <b>Confidence: <\/b> Nominal<br\/>  <b>Day\/Night: <\/b> Day<br\/> <b>Scan: <\/b> 0.6 km<br\/> <b>Track: <\/b> 0.5 km<br\/> <b>FRP: <\/b> 51.4 MW<br\/> <b>Brightness: <\/b> 347.96 K" }, "geometry": { "type": "Point", "coordinates": [ -155.27943, 19.40782, 0.0 ] } },
{ "type": "Feature", "properties": { "Name": "Fire Detection Centroid ", "Description": "<b>Latitude: <\/b> 19.40296<br\/>  <b>Longitude: <\/b> -155.27834<br\/>  <b>Detection Time: <\/b> 2022-07-17 23:00 UTC<br\/>  <b>Sensor: <\/b> NOAA-20 VIIRS<br\/> <b>Confidence: <\/b> Nominal<br\/>  <b>Day\/Night: <\/b> Day<br\/> <b>Scan: <\/b> 0.6 km<br\/> <b>Track: <\/b> 0.5 km<br\/> <b>FRP: <\/b> 51.4 MW<br\/> <b>Brightness: <\/b> 346.71 K" }, "geometry": { "type": "Point", "coordinates": [ -155.27834, 19.40296, 0.0 ] } },
{ "type": "Feature", "properties": { "Name": "Fire Detection Centroid ", "Description": "<b>Latitude: <\/b> 19.40182<br\/>  <b>Longitude: <\/b> -155.2841<br\/>  <b>Detection Time: <\/b> 2022-07-17 23:00 UTC<br\/>  <b>Sensor: <\/b> NOAA-20 VIIRS<br\/> <b>Confidence: <\/b> Nominal<br\/>  <b>Day\/Night: <\/b> Day<br\/> <b>Scan: <\/b> 0.6 km<br\/> <b>Track: <\/b> 0.5 km<br\/> <b>FRP: <\/b> 51.4 MW<br\/> <b>Brightness: <\/b> 339.38 K" }, "geometry": { "type": "Point", "coordinates": [ -155.2841, 19.40182, 0.0 ] } },
{ "type": "Feature", "properties": { "Name": "Fire Detection Centroid ", "Description": "<b>Latitude: <\/b> 19.40307<br\/>  <b>Longitude: <\/b> -155.27835<br\/>  <b>Detection Time: <\/b> 2022-07-17 22:59 UTC<br\/>  <b>Sensor: <\/b> NOAA-20 VIIRS<br\/> <b>Confidence: <\/b> Nominal<br\/>  <b>Day\/Night: <\/b> Day<br\/> <b>Scan: <\/b> 0.62 km<br\/> <b>Track: <\/b> 0.54 km<br\/> <b>FRP: <\/b> 51.4 MW<br\/> <b>Brightness: <\/b> 346.71 K" }, "geometry": { "type": "Point", "coordinates": [ -155.27835, 19.40307, 0.0 ] } },
{ "type": "Feature", "properties": { "Name": "Fire Detection Centroid ", "Description": "<b>Latitude: <\/b> 19.40793<br\/>  <b>Longitude: <\/b> -155.27945<br\/>  <b>Detection Time: <\/b> 2022-07-17 22:59 UTC<br\/>  <b>Sensor: <\/b> NOAA-20 VIIRS<br\/> <b>Confidence: <\/b> Nominal<br\/>  <b>Day\/Night: <\/b> Day<br\/> <b>Scan: <\/b> 0.62 km<br\/> <b>Track: <\/b> 0.54 km<br\/> <b>FRP: <\/b> 51.4 MW<br\/> <b>Brightness: <\/b> 347.96 K" }, "geometry": { "type": "Point", "coordinates": [ -155.27945, 19.40793, 0.0 ] } },
{ "type": "Feature", "properties": { "Name": "Fire Detection Centroid ", "Description": "<b>Latitude: <\/b> 19.40192<br\/>  <b>Longitude: <\/b> -155.28412<br\/>  <b>Detection Time: <\/b> 2022-07-17 22:59 UTC<br\/>  <b>Sensor: <\/b> NOAA-20 VIIRS<br\/> <b>Confidence: <\/b> Nominal<br\/>  <b>Day\/Night: <\/b> Day<br\/> <b>Scan: <\/b> 0.62 km<br\/> <b>Track: <\/b> 0.54 km<br\/> <b>FRP: <\/b> 51.4 MW<br\/> <b>Brightness: <\/b> 339.38 K" }, "geometry": { "type": "Point", "coordinates": [ -155.28412, 19.40192, 0.0 ] } },
{ "type": "Feature", "properties": { "Name": "Fire Detection Centroid ", "Description": "<b>Latitude: <\/b> 19.40679<br\/>  <b>Longitude: <\/b> -155.28519<br\/>  <b>Detection Time: <\/b> 2022-07-17 22:59 UTC<br\/>  <b>Sensor: <\/b> NOAA-20 VIIRS<br\/> <b>Confidence: <\/b> Low<br\/>  <b>Day\/Night: <\/b> Day<br\/> <b>Scan: <\/b> 0.62 km<br\/> <b>Track: <\/b> 0.54 km<br\/> <b>FRP: <\/b> 51.4 MW<br\/> <b>Brightness: <\/b> 304.24 K" }, "geometry": { "type": "Point", "coordinates": [ -155.28519, 19.40679, 0.0 ] } }
]
}
