{
"type": "FeatureCollection",
"crs": { "type": "name", "properties": { "name": "urn:ogc:def:crs:OGC:1.3:CRS84" } },
"features": [
{ "type": "Feature", "properties": { "Name": "Fire Detection Centroid ", "Description": "<b>Latitude: <\/b> 19.40401<br\/>  <b>Longitude: <\/b> -155.28693<br\/>  <b>Detection Time: <\/b> 2023-06-22 23:26 UTC<br\/>  <b>Sensor: <\/b> NOAA-20 VIIRS<br\/> <b>Confidence: <\/b> Low<br\/>  <b>Day\/Night: <\/b> Day<br\/> <b>Scan: <\/b> 0.42 km<br\/> <b>Track: <\/b> 0.37 km<br\/> <b>FRP: <\/b> 23.87 MW<br\/> <b>Brightness: <\/b> 355.58 K" }, "geometry": { "type": "Point", "coordinates": [ -155.28693, 19.40401, 0.0 ] } },
{ "type": "Feature", "properties": { "Name": "Fire Detection Centroid ", "Description": "<b>Latitude: <\/b> 19.40806<br\/>  <b>Longitude: <\/b> -155.28362<br\/>  <b>Detection Time: <\/b> 2023-06-22 23:26 UTC<br\/>  <b>Sensor: <\/b> NOAA-20 VIIRS<br\/> <b>Confidence: <\/b> Low<br\/>  <b>Day\/Night: <\/b> Day<br\/> <b>Scan: <\/b> 0.42 km<br\/> <b>Track: <\/b> 0.37 km<br\/> <b>FRP: <\/b> 23.87 MW<br\/> <b>Brightness: <\/b> 350.42 K" }, "geometry": { "type": "Point", "coordinates": [ -155.28362, 19.40806, 0.0 ] } },
{ "type": "Feature", "properties": { "Name": "Fire Detection Centroid ", "Description": "<b>Latitude: <\/b> 19.4121<br\/>  <b>Longitude: <\/b> -155.28033<br\/>  <b>Detection Time: <\/b> 2023-06-22 23:26 UTC<br\/>  <b>Sensor: <\/b> NOAA-20 VIIRS<br\/> <b>Confidence: <\/b> High<br\/>  <b>Day\/Night: <\/b> Day<br\/> <b>Scan: <\/b> 0.42 km<br\/> <b>Track: <\/b> 0.37 km<br\/> <b>FRP: <\/b> 18.13 MW<br\/> <b>Brightness: <\/b> 367 K" }, "geometry": { "type": "Point", "coordinates": [ -155.28033, 19.4121, 0.0 ] } },
{ "type": "Feature", "properties": { "Name": "Fire Detection Centroid ", "Description": "<b>Latitude: <\/b> 19.40869<br\/>  <b>Longitude: <\/b> -155.27972<br\/>  <b>Detection Time: <\/b> 2023-06-22 23:26 UTC<br\/>  <b>Sensor: <\/b> NOAA-20 VIIRS<br\/> <b>Confidence: <\/b> High<br\/>  <b>Day\/Night: <\/b> Day<br\/> <b>Scan: <\/b> 0.42 km<br\/> <b>Track: <\/b> 0.37 km<br\/> <b>FRP: <\/b> 17.24 MW<br\/> <b>Brightness: <\/b> 367 K" }, "geometry": { "type": "Point", "coordinates": [ -155.27972, 19.40869, 0.0 ] } },
{ "type": "Feature", "properties": { "Name": "Fire Detection Centroid ", "Description": "<b>Latitude: <\/b> 19.40125<br\/>  <b>Longitude: <\/b> -155.28238<br\/>  <b>Detection Time: <\/b> 2023-06-22 23:26 UTC<br\/>  <b>Sensor: <\/b> NOAA-20 VIIRS<br\/> <b>Confidence: <\/b> High<br\/>  <b>Day\/Night: <\/b> Day<br\/> <b>Scan: <\/b> 0.42 km<br\/> <b>Track: <\/b> 0.37 km<br\/> <b>FRP: <\/b> 9.88 MW<br\/> <b>Brightness: <\/b> 367 K" }, "geometry": { "type": "Point", "coordinates": [ -155.28238, 19.40125, 0.0 ] } },
{ "type": "Feature", "properties": { "Name": "Fire Detection Centroid ", "Description": "<b>Latitude: <\/b> 19.40061<br\/>  <b>Longitude: <\/b> -155.28627<br\/>  <b>Detection Time: <\/b> 2023-06-22 23:26 UTC<br\/>  <b>Sensor: <\/b> NOAA-20 VIIRS<br\/> <b>Confidence: <\/b> Nominal<br\/>  <b>Day\/Night: <\/b> Day<br\/> <b>Scan: <\/b> 0.42 km<br\/> <b>Track: <\/b> 0.37 km<br\/> <b>FRP: <\/b> 9.88 MW<br\/> <b>Brightness: <\/b> 351.19 K" }, "geometry": { "type": "Point", "coordinates": [ -155.28627, 19.40061, 0.0 ] } },
{ "type": "Feature", "properties": { "Name": "Fire Detection Centroid ", "Description": "<b>Latitude: <\/b> 19.40528<br\/>  <b>Longitude: <\/b> -155.27911<br\/>  <b>Detection Time: <\/b> 2023-06-22 23:26 UTC<br\/>  <b>Sensor: <\/b> NOAA-20 VIIRS<br\/> <b>Confidence: <\/b> Low<br\/>  <b>Day\/Night: <\/b> Day<br\/> <b>Scan: <\/b> 0.42 km<br\/> <b>Track: <\/b> 0.37 km<br\/> <b>FRP: <\/b> 17.24 MW<br\/> <b>Brightness: <\/b> 354.49 K" }, "geometry": { "type": "Point", "coordinates": [ -155.27911, 19.40528, 0.0 ] } },
{ "type": "Feature", "properties": { "Name": "Fire Detection Centroid ", "Description": "<b>Latitude: <\/b> 19.40465<br\/>  <b>Longitude: <\/b> -155.28302<br\/>  <b>Detection Time: <\/b> 2023-06-22 23:26 UTC<br\/>  <b>Sensor: <\/b> NOAA-20 VIIRS<br\/> <b>Confidence: <\/b> Low<br\/>  <b>Day\/Night: <\/b> Day<br\/> <b>Scan: <\/b> 0.42 km<br\/> <b>Track: <\/b> 0.37 km<br\/> <b>FRP: <\/b> 23.87 MW<br\/> <b>Brightness: <\/b> 356.23 K" }, "geometry": { "type": "Point", "coordinates": [ -155.28302, 19.40465, 0.0 ] } }
]
}
