{
"type": "FeatureCollection",
"crs": { "type": "name", "properties": { "name": "urn:ogc:def:crs:OGC:1.3:CRS84" } },
"features": [
{ "type": "Feature", "properties": { "Name": "Fire Detection Centroid ", "Description": "<b>Latitude: <\/b> 19.41003<br\/>  <b>Longitude: <\/b> -155.28403<br\/>  <b>Detection Time: <\/b> 2022-09-10 00:28 UTC<br\/>  <b>Sensor: <\/b> NOAA-20 VIIRS<br\/> <b>Confidence: <\/b> Nominal<br\/>  <b>Day\/Night: <\/b> Day<br\/> <b>Scan: <\/b> 0.69 km<br\/> <b>Track: <\/b> 0.74 km<br\/> <b>FRP: <\/b> 39.94 MW<br\/> <b>Brightness: <\/b> 337.11 K" }, "geometry": { "type": "Point", "coordinates": [ -155.28403, 19.41003, 0.0 ] } },
{ "type": "Feature", "properties": { "Name": "Fire Detection Centroid ", "Description": "<b>Latitude: <\/b> 19.40215<br\/>  <b>Longitude: <\/b> -155.29187<br\/>  <b>Detection Time: <\/b> 2022-09-10 00:28 UTC<br\/>  <b>Sensor: <\/b> NOAA-20 VIIRS<br\/> <b>Confidence: <\/b> Nominal<br\/>  <b>Day\/Night: <\/b> Day<br\/> <b>Scan: <\/b> 0.7 km<br\/> <b>Track: <\/b> 0.7 km<br\/> <b>FRP: <\/b> 78.9 MW<br\/> <b>Brightness: <\/b> 335.67 K" }, "geometry": { "type": "Point", "coordinates": [ -155.29187, 19.40215, 0.0 ] } },
{ "type": "Feature", "properties": { "Name": "Fire Detection Centroid ", "Description": "<b>Latitude: <\/b> 19.40259<br\/>  <b>Longitude: <\/b> -155.29031<br\/>  <b>Detection Time: <\/b> 2022-09-10 00:28 UTC<br\/>  <b>Sensor: <\/b> NOAA-20 VIIRS<br\/> <b>Confidence: <\/b> Nominal<br\/>  <b>Day\/Night: <\/b> Day<br\/> <b>Scan: <\/b> 0.69 km<br\/> <b>Track: <\/b> 0.74 km<br\/> <b>FRP: <\/b> 78.91 MW<br\/> <b>Brightness: <\/b> 335.67 K" }, "geometry": { "type": "Point", "coordinates": [ -155.29031, 19.40259, 0.0 ] } },
{ "type": "Feature", "properties": { "Name": "Fire Detection Centroid ", "Description": "<b>Latitude: <\/b> 19.41023<br\/>  <b>Longitude: <\/b> -155.28598<br\/>  <b>Detection Time: <\/b> 2022-09-10 00:28 UTC<br\/>  <b>Sensor: <\/b> NOAA-20 VIIRS<br\/> <b>Confidence: <\/b> Nominal<br\/>  <b>Day\/Night: <\/b> Day<br\/> <b>Scan: <\/b> 0.69 km<br\/> <b>Track: <\/b> 0.75 km<br\/> <b>FRP: <\/b> 16.39 MW<br\/> <b>Brightness: <\/b> 335.14 K" }, "geometry": { "type": "Point", "coordinates": [ -155.28598, 19.41023, 0.0 ] } },
{ "type": "Feature", "properties": { "Name": "Fire Detection Centroid ", "Description": "<b>Latitude: <\/b> 19.40317<br\/>  <b>Longitude: <\/b> -155.28314<br\/>  <b>Detection Time: <\/b> 2022-09-10 00:28 UTC<br\/>  <b>Sensor: <\/b> NOAA-20 VIIRS<br\/> <b>Confidence: <\/b> High<br\/>  <b>Day\/Night: <\/b> Day<br\/> <b>Scan: <\/b> 0.69 km<br\/> <b>Track: <\/b> 0.74 km<br\/> <b>FRP: <\/b> 39.94 MW<br\/> <b>Brightness: <\/b> 367 K" }, "geometry": { "type": "Point", "coordinates": [ -155.28314, 19.40317, 0.0 ] } }
]
}
