{
"type": "FeatureCollection",
"crs": { "type": "name", "properties": { "name": "urn:ogc:def:crs:OGC:1.3:CRS84" } },
"features": [
{ "type": "Feature", "properties": { "Name": "Fire Detection Centroid ", "Description": "<b>Latitude: <\/b> 33.85196<br\/>  <b>Longitude: <\/b> -118.33544<br\/>  <b>Detection Time: <\/b> 2024-01-15 10:47 UTC<br\/>  <b>Sensor: <\/b> NOAA-20 VIIRS<br\/> <b>Confidence: <\/b> Nominal<br\/>  <b>Day\/Night: <\/b> Night<br\/> <b>Scan: <\/b> 0.73 km<br\/> <b>Track: <\/b> 0.76 km<br\/> <b>FRP: <\/b> 1.45 MW<br\/> <b>Brightness: <\/b> 297.66 K" }, "geometry": { "type": "Point", "coordinates": [ -118.33544, 33.85196, 0.0 ] } },
{ "type": "Feature", "properties": { "Name": "Fire Detection Centroid ", "Description": "<b>Latitude: <\/b> 33.8522<br\/>  <b>Longitude: <\/b> -118.33639<br\/>  <b>Detection Time: <\/b> 2024-01-15 10:47 UTC<br\/>  <b>Sensor: <\/b> NOAA-20 VIIRS<br\/> <b>Confidence: <\/b> Nominal<br\/>  <b>Day\/Night: <\/b> Night<br\/> <b>Scan: <\/b> 0.73 km<br\/> <b>Track: <\/b> 0.76 km<br\/> <b>FRP: <\/b> 1.49 MW<br\/> <b>Brightness: <\/b> 296.78 K" }, "geometry": { "type": "Point", "coordinates": [ -118.33639, 33.8522, 0.0 ] } },
{ "type": "Feature", "properties": { "Name": "Fire Detection Centroid ", "Description": "<b>Latitude: <\/b> 49.08028<br\/>  <b>Longitude: <\/b> -119.63818<br\/>  <b>Detection Time: <\/b> 2024-01-15 10:45 UTC<br\/>  <b>Sensor: <\/b> NOAA-20 VIIRS<br\/> <b>Confidence: <\/b> Nominal<br\/>  <b>Day\/Night: <\/b> Night<br\/> <b>Scan: <\/b> 0.47 km<br\/> <b>Track: <\/b> 0.48 km<br\/> <b>FRP: <\/b> 1.66 MW<br\/> <b>Brightness: <\/b> 320.34 K" }, "geometry": { "type": "Point", "coordinates": [ -119.63818, 49.08028, 0.0 ] } },
{ "type": "Feature", "properties": { "Name": "Fire Detection Centroid ", "Description": "<b>Latitude: <\/b> 47.56958<br\/>  <b>Longitude: <\/b> -122.36845<br\/>  <b>Detection Time: <\/b> 2024-01-15 10:45 UTC<br\/>  <b>Sensor: <\/b> NOAA-20 VIIRS<br\/> <b>Confidence: <\/b> Nominal<br\/>  <b>Day\/Night: <\/b> Night<br\/> <b>Scan: <\/b> 0.4 km<br\/> <b>Track: <\/b> 0.44 km<br\/> <b>FRP: <\/b> 1.27 MW<br\/> <b>Brightness: <\/b> 307.71 K" }, "geometry": { "type": "Point", "coordinates": [ -122.36845, 47.56958, 0.0 ] } }
]
}
