{
"type": "FeatureCollection",
"crs": { "type": "name", "properties": { "name": "urn:ogc:def:crs:OGC:1.3:CRS84" } },
"features": [
{ "type": "Feature", "properties": { "Name": "Fire Detection Centroid ", "Description": "<b>Latitude: <\/b> 18.23354<br\/>  <b>Longitude: <\/b> -70.4573<br\/>  <b>Detection Time: <\/b> 2022-07-15 05:42 UTC<br\/>  <b>Sensor: <\/b> NOAA-20 VIIRS<br\/> <b>Confidence: <\/b> Nominal<br\/>  <b>Day\/Night: <\/b> Night<br\/> <b>Scan: <\/b> 0.3 km<br\/> <b>Track: <\/b> 0.6 km<br\/> <b>FRP: <\/b> 3.84 MW<br\/> <b>Brightness: <\/b> 331.71 K" }, "geometry": { "type": "Point", "coordinates": [ -70.4573, 18.23354, 0.0 ] } },
{ "type": "Feature", "properties": { "Name": "Fire Detection Centroid ", "Description": "<b>Latitude: <\/b> 18.02872<br\/>  <b>Longitude: <\/b> -66.94948<br\/>  <b>Detection Time: <\/b> 2022-07-15 05:41 UTC<br\/>  <b>Sensor: <\/b> NOAA-20 VIIRS<br\/> <b>Confidence: <\/b> Nominal<br\/>  <b>Day\/Night: <\/b> Night<br\/> <b>Scan: <\/b> 0.4 km<br\/> <b>Track: <\/b> 0.5 km<br\/> <b>FRP: <\/b> 0.66 MW<br\/> <b>Brightness: <\/b> 304.96 K" }, "geometry": { "type": "Point", "coordinates": [ -66.94948, 18.02872, 0.0 ] } }
]
}
