{
"type": "FeatureCollection",
"crs": { "type": "name", "properties": { "name": "urn:ogc:def:crs:OGC:1.3:CRS84" } },
"features": [
{ "type": "Feature", "properties": { "Name": "Fire Detection Centroid ", "Description": "<b>Latitude: <\/b> 18.36508<br\/>  <b>Longitude: <\/b> -66.75994<br\/>  <b>Detection Time: <\/b> 2023-03-28 16:52 UTC<br\/>  <b>Sensor: <\/b> NOAA-20 VIIRS<br\/> <b>Confidence: <\/b> Nominal<br\/>  <b>Day\/Night: <\/b> Day<br\/> <b>Scan: <\/b> 0.54 km<br\/> <b>Track: <\/b> 0.68 km<br\/> <b>FRP: <\/b> 4.03 MW<br\/> <b>Brightness: <\/b> 331.56 K" }, "geometry": { "type": "Point", "coordinates": [ -66.75994, 18.36508, 0.0 ] } },
{ "type": "Feature", "properties": { "Name": "Fire Detection Centroid ", "Description": "<b>Latitude: <\/b> 18.07443<br\/>  <b>Longitude: <\/b> -66.79909<br\/>  <b>Detection Time: <\/b> 2023-03-28 16:52 UTC<br\/>  <b>Sensor: <\/b> NOAA-20 VIIRS<br\/> <b>Confidence: <\/b> Nominal<br\/>  <b>Day\/Night: <\/b> Day<br\/> <b>Scan: <\/b> 0.55 km<br\/> <b>Track: <\/b> 0.68 km<br\/> <b>FRP: <\/b> 6.37 MW<br\/> <b>Brightness: <\/b> 337.57 K" }, "geometry": { "type": "Point", "coordinates": [ -66.79909, 18.07443, 0.0 ] } },
{ "type": "Feature", "properties": { "Name": "Fire Detection Centroid ", "Description": "<b>Latitude: <\/b> 18.07666<br\/>  <b>Longitude: <\/b> -66.7974<br\/>  <b>Detection Time: <\/b> 2023-03-28 16:52 UTC<br\/>  <b>Sensor: <\/b> NOAA-20 VIIRS<br\/> <b>Confidence: <\/b> Nominal<br\/>  <b>Day\/Night: <\/b> Day<br\/> <b>Scan: <\/b> 0.56 km<br\/> <b>Track: <\/b> 0.68 km<br\/> <b>FRP: <\/b> 5.93 MW<br\/> <b>Brightness: <\/b> 332.69 K" }, "geometry": { "type": "Point", "coordinates": [ -66.7974, 18.07666, 0.0 ] } }
]
}
