{
"type": "FeatureCollection",
"crs": { "type": "name", "properties": { "name": "urn:ogc:def:crs:OGC:1.3:CRS84" } },
"features": [
{ "type": "Feature", "properties": { "Name": "Fire Detection Centroid ", "Description": "<b>Latitude: <\/b> 45.81565<br\/>  <b>Longitude: <\/b> -66.25049<br\/>  <b>Detection Time: <\/b> 2023-04-29 17:00 UTC<br\/>  <b>Sensor: <\/b> NOAA-20 VIIRS<br\/> <b>Confidence: <\/b> Nominal<br\/>  <b>Day\/Night: <\/b> Day<br\/> <b>Scan: <\/b> 0.4 km<br\/> <b>Track: <\/b> 0.4 km<br\/> <b>FRP: <\/b> 18.32 MW<br\/> <b>Brightness: <\/b> 342.99 K" }, "geometry": { "type": "Point", "coordinates": [ -66.25049, 45.81565, 0.0 ] } },
{ "type": "Feature", "properties": { "Name": "Fire Detection Centroid ", "Description": "<b>Latitude: <\/b> 45.81464<br\/>  <b>Longitude: <\/b> -66.25589<br\/>  <b>Detection Time: <\/b> 2023-04-29 17:00 UTC<br\/>  <b>Sensor: <\/b> NOAA-20 VIIRS<br\/> <b>Confidence: <\/b> Nominal<br\/>  <b>Day\/Night: <\/b> Day<br\/> <b>Scan: <\/b> 0.4 km<br\/> <b>Track: <\/b> 0.4 km<br\/> <b>FRP: <\/b> 18.32 MW<br\/> <b>Brightness: <\/b> 341.72 K" }, "geometry": { "type": "Point", "coordinates": [ -66.25589, 45.81464, 0.0 ] } }
]
}
