{
"type": "FeatureCollection",
"crs": { "type": "name", "properties": { "name": "urn:ogc:def:crs:OGC:1.3:CRS84" } },
"features": [
{ "type": "Feature", "properties": { "Name": "Fire Detection Centroid ", "Description": "<b>Latitude: <\/b> 46.04134<br\/>  <b>Longitude: <\/b> -73.13998<br\/>  <b>Detection Time: <\/b> 2023-04-07 17:13 UTC<br\/>  <b>Sensor: <\/b> NOAA-20 VIIRS<br\/> <b>Confidence: <\/b> Nominal<br\/>  <b>Day\/Night: <\/b> Day<br\/> <b>Scan: <\/b> 0.4 km<br\/> <b>Track: <\/b> 0.4 km<br\/> <b>FRP: <\/b> 3.19 MW<br\/> <b>Brightness: <\/b> 332.28 K" }, "geometry": { "type": "Point", "coordinates": [ -73.13998, 46.04134, 0.0 ] } },
{ "type": "Feature", "properties": { "Name": "Fire Detection Centroid ", "Description": "<b>Latitude: <\/b> 43.26345<br\/>  <b>Longitude: <\/b> -79.80856<br\/>  <b>Detection Time: <\/b> 2023-04-07 17:13 UTC<br\/>  <b>Sensor: <\/b> NOAA-20 VIIRS<br\/> <b>Confidence: <\/b> Nominal<br\/>  <b>Day\/Night: <\/b> Day<br\/> <b>Scan: <\/b> 0.5 km<br\/> <b>Track: <\/b> 0.6 km<br\/> <b>FRP: <\/b> 3.6 MW<br\/> <b>Brightness: <\/b> 327.38 K" }, "geometry": { "type": "Point", "coordinates": [ -79.80856, 43.26345, 0.0 ] } },
{ "type": "Feature", "properties": { "Name": "Fire Detection Centroid ", "Description": "<b>Latitude: <\/b> 19.48125<br\/>  <b>Longitude: <\/b> -71.55682<br\/>  <b>Detection Time: <\/b> 2023-04-07 17:06 UTC<br\/>  <b>Sensor: <\/b> NOAA-20 VIIRS<br\/> <b>Confidence: <\/b> Nominal<br\/>  <b>Day\/Night: <\/b> Day<br\/> <b>Scan: <\/b> 0.7 km<br\/> <b>Track: <\/b> 0.7 km<br\/> <b>FRP: <\/b> 6.75 MW<br\/> <b>Brightness: <\/b> 330.51 K" }, "geometry": { "type": "Point", "coordinates": [ -71.55682, 19.48125, 0.0 ] } },
{ "type": "Feature", "properties": { "Name": "Fire Detection Centroid ", "Description": "<b>Latitude: <\/b> 19.37174<br\/>  <b>Longitude: <\/b> -72.35275<br\/>  <b>Detection Time: <\/b> 2023-04-07 17:06 UTC<br\/>  <b>Sensor: <\/b> NOAA-20 VIIRS<br\/> <b>Confidence: <\/b> Nominal<br\/>  <b>Day\/Night: <\/b> Day<br\/> <b>Scan: <\/b> 0.7 km<br\/> <b>Track: <\/b> 0.8 km<br\/> <b>FRP: <\/b> 7.08 MW<br\/> <b>Brightness: <\/b> 338.43 K" }, "geometry": { "type": "Point", "coordinates": [ -72.35275, 19.37174, 0.0 ] } },
{ "type": "Feature", "properties": { "Name": "Fire Detection Centroid ", "Description": "<b>Latitude: <\/b> 18.935<br\/>  <b>Longitude: <\/b> -72.0001<br\/>  <b>Detection Time: <\/b> 2023-04-07 17:05 UTC<br\/>  <b>Sensor: <\/b> NOAA-20 VIIRS<br\/> <b>Confidence: <\/b> Nominal<br\/>  <b>Day\/Night: <\/b> Day<br\/> <b>Scan: <\/b> 0.7 km<br\/> <b>Track: <\/b> 0.8 km<br\/> <b>FRP: <\/b> 5.72 MW<br\/> <b>Brightness: <\/b> 341.72 K" }, "geometry": { "type": "Point", "coordinates": [ -72.0001, 18.935, 0.0 ] } },
{ "type": "Feature", "properties": { "Name": "Fire Detection Centroid ", "Description": "<b>Latitude: <\/b> 18.66807<br\/>  <b>Longitude: <\/b> -72.15097<br\/>  <b>Detection Time: <\/b> 2023-04-07 17:05 UTC<br\/>  <b>Sensor: <\/b> NOAA-20 VIIRS<br\/> <b>Confidence: <\/b> Nominal<br\/>  <b>Day\/Night: <\/b> Day<br\/> <b>Scan: <\/b> 0.7 km<br\/> <b>Track: <\/b> 0.8 km<br\/> <b>FRP: <\/b> 7.35 MW<br\/> <b>Brightness: <\/b> 338.5 K" }, "geometry": { "type": "Point", "coordinates": [ -72.15097, 18.66807, 0.0 ] } },
{ "type": "Feature", "properties": { "Name": "Fire Detection Centroid ", "Description": "<b>Latitude: <\/b> 19.40716<br\/>  <b>Longitude: <\/b> -155.28479<br\/>  <b>Detection Time: <\/b> 2023-04-07 12:40 UTC<br\/>  <b>Sensor: <\/b> NOAA-20 VIIRS<br\/> <b>Confidence: <\/b> Nominal<br\/>  <b>Day\/Night: <\/b> Night<br\/> <b>Scan: <\/b> 0.41 km<br\/> <b>Track: <\/b> 0.61 km<br\/> <b>FRP: <\/b> 2.78 MW<br\/> <b>Brightness: <\/b> 302.02 K" }, "geometry": { "type": "Point", "coordinates": [ -155.28479, 19.40716, 0.0 ] } }
]
}
