{
"type": "FeatureCollection",
"crs": { "type": "name", "properties": { "name": "urn:ogc:def:crs:OGC:1.3:CRS84" } },
"features": [
{ "type": "Feature", "properties": { "Name": "Fire Detection Centroid ", "Description": "<b>Latitude: <\/b> 18.92831<br\/>  <b>Longitude: <\/b> -70.35326<br\/>  <b>Detection Time: <\/b> 2022-07-16 05:22 UTC<br\/>  <b>Sensor: <\/b> NOAA-20 VIIRS<br\/> <b>Confidence: <\/b> Nominal<br\/>  <b>Day\/Night: <\/b> Night<br\/> <b>Scan: <\/b> 0.7 km<br\/> <b>Track: <\/b> 0.8 km<br\/> <b>FRP: <\/b> 2.26 MW<br\/> <b>Brightness: <\/b> 297.97 K" }, "geometry": { "type": "Point", "coordinates": [ -70.35326, 18.92831, 0.0 ] } },
{ "type": "Feature", "properties": { "Name": "Fire Detection Centroid ", "Description": "<b>Latitude: <\/b> 45.28265<br\/>  <b>Longitude: <\/b> -66.01691<br\/>  <b>Detection Time: <\/b> 2022-07-16 05:15 UTC<br\/>  <b>Sensor: <\/b> NOAA-20 VIIRS<br\/> <b>Confidence: <\/b> Nominal<br\/>  <b>Day\/Night: <\/b> Night<br\/> <b>Scan: <\/b> 0.6 km<br\/> <b>Track: <\/b> 0.7 km<br\/> <b>FRP: <\/b> 1.56 MW<br\/> <b>Brightness: <\/b> 302.3 K" }, "geometry": { "type": "Point", "coordinates": [ -66.01691, 45.28265, 0.0 ] } },
{ "type": "Feature", "properties": { "Name": "Fire Detection Centroid ", "Description": "<b>Latitude: <\/b> 45.27875<br\/>  <b>Longitude: <\/b> -66.01678<br\/>  <b>Detection Time: <\/b> 2022-07-16 05:15 UTC<br\/>  <b>Sensor: <\/b> NOAA-20 VIIRS<br\/> <b>Confidence: <\/b> Nominal<br\/>  <b>Day\/Night: <\/b> Night<br\/> <b>Scan: <\/b> 0.6 km<br\/> <b>Track: <\/b> 0.7 km<br\/> <b>FRP: <\/b> 1.94 MW<br\/> <b>Brightness: <\/b> 297.67 K" }, "geometry": { "type": "Point", "coordinates": [ -66.01678, 45.27875, 0.0 ] } }
]
}
