{
"type": "FeatureCollection",
"crs": { "type": "name", "properties": { "name": "urn:ogc:def:crs:OGC:1.3:CRS84" } },
"features": [
{ "type": "Feature", "properties": { "Name": "Fire Detection Centroid ", "Description": "<b>Latitude: <\/b> 19.40947<br\/>  <b>Longitude: <\/b> -155.28587<br\/>  <b>Detection Time: <\/b> 2023-11-06 12:45 UTC<br\/>  <b>Sensor: <\/b> NOAA-20 VIIRS<br\/> <b>Confidence: <\/b> Nominal<br\/>  <b>Day\/Night: <\/b> Night<br\/> <b>Scan: <\/b> 0.5 km<br\/> <b>Track: <\/b> 0.7 km<br\/> <b>FRP: <\/b> 5.81 MW<br\/> <b>Brightness: <\/b> 303.23 K" }, "geometry": { "type": "Point", "coordinates": [ -155.28587, 19.40947, 0.0 ] } },
{ "type": "Feature", "properties": { "Name": "Fire Detection Centroid ", "Description": "<b>Latitude: <\/b> 49.40723<br\/>  <b>Longitude: <\/b> -115.78283<br\/>  <b>Detection Time: <\/b> 2023-11-06 10:55 UTC<br\/>  <b>Sensor: <\/b> NOAA-20 VIIRS<br\/> <b>Confidence: <\/b> Nominal<br\/>  <b>Day\/Night: <\/b> Night<br\/> <b>Scan: <\/b> 0.5 km<br\/> <b>Track: <\/b> 0.6 km<br\/> <b>FRP: <\/b> 1.98 MW<br\/> <b>Brightness: <\/b> 311.23 K" }, "geometry": { "type": "Point", "coordinates": [ -115.78283, 49.40723, 0.0 ] } },
{ "type": "Feature", "properties": { "Name": "Fire Detection Centroid ", "Description": "<b>Latitude: <\/b> 49.40686<br\/>  <b>Longitude: <\/b> -115.78523<br\/>  <b>Detection Time: <\/b> 2023-11-06 10:55 UTC<br\/>  <b>Sensor: <\/b> NOAA-20 VIIRS<br\/> <b>Confidence: <\/b> Nominal<br\/>  <b>Day\/Night: <\/b> Night<br\/> <b>Scan: <\/b> 0.45 km<br\/> <b>Track: <\/b> 0.63 km<br\/> <b>FRP: <\/b> 1.99 MW<br\/> <b>Brightness: <\/b> 311.23 K" }, "geometry": { "type": "Point", "coordinates": [ -115.78523, 49.40686, 0.0 ] } }
]
}
