{
"type": "FeatureCollection",
"crs": { "type": "name", "properties": { "name": "urn:ogc:def:crs:OGC:1.3:CRS84" } },
"features": [
{ "type": "Feature", "properties": { "Name": "Fire Detection Centroid ", "Description": "<b>Latitude: <\/b> 19.40917<br\/>  <b>Longitude: <\/b> -155.28488<br\/>  <b>Detection Time: <\/b> 2022-09-07 23:26 UTC<br\/>  <b>Sensor: <\/b> NOAA-20 VIIRS<br\/> <b>Confidence: <\/b> Low<br\/>  <b>Day\/Night: <\/b> Day<br\/> <b>Scan: <\/b> 0.42 km<br\/> <b>Track: <\/b> 0.37 km<br\/> <b>FRP: <\/b> 116.73 MW<br\/> <b>Brightness: <\/b> 353.69 K" }, "geometry": { "type": "Point", "coordinates": [ -155.28488, 19.40917, 0.0 ] } },
{ "type": "Feature", "properties": { "Name": "Fire Detection Centroid ", "Description": "<b>Latitude: <\/b> 19.40586<br\/>  <b>Longitude: <\/b> -155.28389<br\/>  <b>Detection Time: <\/b> 2022-09-07 23:26 UTC<br\/>  <b>Sensor: <\/b> NOAA-20 VIIRS<br\/> <b>Confidence: <\/b> High<br\/>  <b>Day\/Night: <\/b> Day<br\/> <b>Scan: <\/b> 0.42 km<br\/> <b>Track: <\/b> 0.37 km<br\/> <b>FRP: <\/b> 106.37 MW<br\/> <b>Brightness: <\/b> 367 K" }, "geometry": { "type": "Point", "coordinates": [ -155.28389, 19.40586, 0.0 ] } },
{ "type": "Feature", "properties": { "Name": "Fire Detection Centroid ", "Description": "<b>Latitude: <\/b> 19.40245<br\/>  <b>Longitude: <\/b> -155.28326<br\/>  <b>Detection Time: <\/b> 2022-09-07 23:26 UTC<br\/>  <b>Sensor: <\/b> NOAA-20 VIIRS<br\/> <b>Confidence: <\/b> Nominal<br\/>  <b>Day\/Night: <\/b> Day<br\/> <b>Scan: <\/b> 0.42 km<br\/> <b>Track: <\/b> 0.37 km<br\/> <b>FRP: <\/b> 106.37 MW<br\/> <b>Brightness: <\/b> 343.38 K" }, "geometry": { "type": "Point", "coordinates": [ -155.28326, 19.40245, 0.0 ] } },
{ "type": "Feature", "properties": { "Name": "Fire Detection Centroid ", "Description": "<b>Latitude: <\/b> 19.40576<br\/>  <b>Longitude: <\/b> -155.28429<br\/>  <b>Detection Time: <\/b> 2022-09-07 23:26 UTC<br\/>  <b>Sensor: <\/b> NOAA-20 VIIRS<br\/> <b>Confidence: <\/b> High<br\/>  <b>Day\/Night: <\/b> Day<br\/> <b>Scan: <\/b> 0.42 km<br\/> <b>Track: <\/b> 0.37 km<br\/> <b>FRP: <\/b> 116.73 MW<br\/> <b>Brightness: <\/b> 367 K" }, "geometry": { "type": "Point", "coordinates": [ -155.28429, 19.40576, 0.0 ] } },
{ "type": "Feature", "properties": { "Name": "Fire Detection Centroid ", "Description": "<b>Latitude: <\/b> 19.40523<br\/>  <b>Longitude: <\/b> -155.28781<br\/>  <b>Detection Time: <\/b> 2022-09-07 23:26 UTC<br\/>  <b>Sensor: <\/b> NOAA-20 VIIRS<br\/> <b>Confidence: <\/b> Low<br\/>  <b>Day\/Night: <\/b> Day<br\/> <b>Scan: <\/b> 0.42 km<br\/> <b>Track: <\/b> 0.37 km<br\/> <b>FRP: <\/b> 44.82 MW<br\/> <b>Brightness: <\/b> 367 K" }, "geometry": { "type": "Point", "coordinates": [ -155.28781, 19.40523, 0.0 ] } }
]
}
