{
"type": "FeatureCollection",
"crs": { "type": "name", "properties": { "name": "urn:ogc:def:crs:OGC:1.3:CRS84" } },
"features": [
{ "type": "Feature", "properties": { "Name": "Fire Detection Centroid ", "Description": "<b>Latitude: <\/b> 49.15047<br\/>  <b>Longitude: <\/b> -124.56577<br\/>  <b>Detection Time: <\/b> 2023-10-22 22:03 UTC<br\/>  <b>Sensor: <\/b> NOAA-20 VIIRS<br\/> <b>Confidence: <\/b> Nominal<br\/>  <b>Day\/Night: <\/b> Day<br\/> <b>Scan: <\/b> 0.44 km<br\/> <b>Track: <\/b> 0.62 km<br\/> <b>FRP: <\/b> 8.5 MW<br\/> <b>Brightness: <\/b> 337.68 K" }, "geometry": { "type": "Point", "coordinates": [ -124.56577, 49.15047, 0.0 ] } },
{ "type": "Feature", "properties": { "Name": "Fire Detection Centroid ", "Description": "<b>Latitude: <\/b> 49.95014<br\/>  <b>Longitude: <\/b> -125.41901<br\/>  <b>Detection Time: <\/b> 2023-10-22 22:03 UTC<br\/>  <b>Sensor: <\/b> NOAA-20 VIIRS<br\/> <b>Confidence: <\/b> Nominal<br\/>  <b>Day\/Night: <\/b> Day<br\/> <b>Scan: <\/b> 0.41 km<br\/> <b>Track: <\/b> 0.6 km<br\/> <b>FRP: <\/b> 7.77 MW<br\/> <b>Brightness: <\/b> 334.2 K" }, "geometry": { "type": "Point", "coordinates": [ -125.41901, 49.95014, 0.0 ] } },
{ "type": "Feature", "properties": { "Name": "Fire Detection Centroid ", "Description": "<b>Latitude: <\/b> 49.95028<br\/>  <b>Longitude: <\/b> -125.41289<br\/>  <b>Detection Time: <\/b> 2023-10-22 22:03 UTC<br\/>  <b>Sensor: <\/b> NOAA-20 VIIRS<br\/> <b>Confidence: <\/b> Nominal<br\/>  <b>Day\/Night: <\/b> Day<br\/> <b>Scan: <\/b> 0.41 km<br\/> <b>Track: <\/b> 0.6 km<br\/> <b>FRP: <\/b> 15.15 MW<br\/> <b>Brightness: <\/b> 354.42 K" }, "geometry": { "type": "Point", "coordinates": [ -125.41289, 49.95028, 0.0 ] } },
{ "type": "Feature", "properties": { "Name": "Fire Detection Centroid ", "Description": "<b>Latitude: <\/b> 49.87825<br\/>  <b>Longitude: <\/b> -125.67354<br\/>  <b>Detection Time: <\/b> 2023-10-22 22:03 UTC<br\/>  <b>Sensor: <\/b> NOAA-20 VIIRS<br\/> <b>Confidence: <\/b> Nominal<br\/>  <b>Day\/Night: <\/b> Day<br\/> <b>Scan: <\/b> 0.4 km<br\/> <b>Track: <\/b> 0.6 km<br\/> <b>FRP: <\/b> 2.66 MW<br\/> <b>Brightness: <\/b> 332.35 K" }, "geometry": { "type": "Point", "coordinates": [ -125.67354, 49.87825, 0.0 ] } },
{ "type": "Feature", "properties": { "Name": "Fire Detection Centroid ", "Description": "<b>Latitude: <\/b> 49.95044<br\/>  <b>Longitude: <\/b> -125.40633<br\/>  <b>Detection Time: <\/b> 2023-10-22 22:03 UTC<br\/>  <b>Sensor: <\/b> NOAA-20 VIIRS<br\/> <b>Confidence: <\/b> Low<br\/>  <b>Day\/Night: <\/b> Day<br\/> <b>Scan: <\/b> 0.41 km<br\/> <b>Track: <\/b> 0.6 km<br\/> <b>FRP: <\/b> 15.15 MW<br\/> <b>Brightness: <\/b> 356.58 K" }, "geometry": { "type": "Point", "coordinates": [ -125.40633, 49.95044, 0.0 ] } },
{ "type": "Feature", "properties": { "Name": "Fire Detection Centroid ", "Description": "<b>Latitude: <\/b> 49.86776<br\/>  <b>Longitude: <\/b> -125.65105<br\/>  <b>Detection Time: <\/b> 2023-10-22 22:03 UTC<br\/>  <b>Sensor: <\/b> NOAA-20 VIIRS<br\/> <b>Confidence: <\/b> Nominal<br\/>  <b>Day\/Night: <\/b> Day<br\/> <b>Scan: <\/b> 0.4 km<br\/> <b>Track: <\/b> 0.6 km<br\/> <b>FRP: <\/b> 3.99 MW<br\/> <b>Brightness: <\/b> 338.46 K" }, "geometry": { "type": "Point", "coordinates": [ -125.65105, 49.86776, 0.0 ] } },
{ "type": "Feature", "properties": { "Name": "Fire Detection Centroid ", "Description": "<b>Latitude: <\/b> 49.41902<br\/>  <b>Longitude: <\/b> -125.31625<br\/>  <b>Detection Time: <\/b> 2023-10-22 22:03 UTC<br\/>  <b>Sensor: <\/b> NOAA-20 VIIRS<br\/> <b>Confidence: <\/b> Nominal<br\/>  <b>Day\/Night: <\/b> Day<br\/> <b>Scan: <\/b> 0.41 km<br\/> <b>Track: <\/b> 0.61 km<br\/> <b>FRP: <\/b> 13.89 MW<br\/> <b>Brightness: <\/b> 347.68 K" }, "geometry": { "type": "Point", "coordinates": [ -125.31625, 49.41902, 0.0 ] } },
{ "type": "Feature", "properties": { "Name": "Fire Detection Centroid ", "Description": "<b>Latitude: <\/b> 49.4234<br\/>  <b>Longitude: <\/b> -125.12463<br\/>  <b>Detection Time: <\/b> 2023-10-22 22:03 UTC<br\/>  <b>Sensor: <\/b> NOAA-20 VIIRS<br\/> <b>Confidence: <\/b> Nominal<br\/>  <b>Day\/Night: <\/b> Day<br\/> <b>Scan: <\/b> 0.42 km<br\/> <b>Track: <\/b> 0.61 km<br\/> <b>FRP: <\/b> 3.49 MW<br\/> <b>Brightness: <\/b> 327.69 K" }, "geometry": { "type": "Point", "coordinates": [ -125.12463, 49.4234, 0.0 ] } },
{ "type": "Feature", "properties": { "Name": "Fire Detection Centroid ", "Description": "<b>Latitude: <\/b> 49.15062<br\/>  <b>Longitude: <\/b> -124.55817<br\/>  <b>Detection Time: <\/b> 2023-10-22 22:03 UTC<br\/>  <b>Sensor: <\/b> NOAA-20 VIIRS<br\/> <b>Confidence: <\/b> Low<br\/>  <b>Day\/Night: <\/b> Day<br\/> <b>Scan: <\/b> 0.44 km<br\/> <b>Track: <\/b> 0.62 km<br\/> <b>FRP: <\/b> 11.71 MW<br\/> <b>Brightness: <\/b> 356.32 K" }, "geometry": { "type": "Point", "coordinates": [ -124.55817, 49.15062, 0.0 ] } }
]
}
