{
"type": "FeatureCollection",
"crs": { "type": "name", "properties": { "name": "urn:ogc:def:crs:OGC:1.3:CRS84" } },
"features": [
{ "type": "Feature", "properties": { "Name": "Fire Detection Centroid ", "Description": "<b>Latitude: <\/b> 38.07298<br\/>  <b>Longitude: <\/b> -122.1399<br\/>  <b>Detection Time: <\/b> 2023-03-23 10:34 UTC<br\/>  <b>Sensor: <\/b> NOAA-20 VIIRS<br\/> <b>Confidence: <\/b> Nominal<br\/>  <b>Day\/Night: <\/b> Night<br\/> <b>Scan: <\/b> 0.48 km<br\/> <b>Track: <\/b> 0.48 km<br\/> <b>FRP: <\/b> 1.12 MW<br\/> <b>Brightness: <\/b> 300.03 K" }, "geometry": { "type": "Point", "coordinates": [ -122.1399, 38.07298, 0.0 ] } },
{ "type": "Feature", "properties": { "Name": "Fire Detection Centroid ", "Description": "<b>Latitude: <\/b> 38.07241<br\/>  <b>Longitude: <\/b> -122.13843<br\/>  <b>Detection Time: <\/b> 2023-03-23 10:34 UTC<br\/>  <b>Sensor: <\/b> NOAA-20 VIIRS<br\/> <b>Confidence: <\/b> Nominal<br\/>  <b>Day\/Night: <\/b> Night<br\/> <b>Scan: <\/b> 0.48 km<br\/> <b>Track: <\/b> 0.48 km<br\/> <b>FRP: <\/b> 1.46 MW<br\/> <b>Brightness: <\/b> 302.15 K" }, "geometry": { "type": "Point", "coordinates": [ -122.13843, 38.07241, 0.0 ] } },
{ "type": "Feature", "properties": { "Name": "Fire Detection Centroid ", "Description": "<b>Latitude: <\/b> 34.60635<br\/>  <b>Longitude: <\/b> -117.33809<br\/>  <b>Detection Time: <\/b> 2023-03-23 10:34 UTC<br\/>  <b>Sensor: <\/b> NOAA-20 VIIRS<br\/> <b>Confidence: <\/b> Nominal<br\/>  <b>Day\/Night: <\/b> Night<br\/> <b>Scan: <\/b> 0.53 km<br\/> <b>Track: <\/b> 0.67 km<br\/> <b>FRP: <\/b> 1.18 MW<br\/> <b>Brightness: <\/b> 295.7 K" }, "geometry": { "type": "Point", "coordinates": [ -117.33809, 34.60635, 0.0 ] } },
{ "type": "Feature", "properties": { "Name": "Fire Detection Centroid ", "Description": "<b>Latitude: <\/b> 34.61237<br\/>  <b>Longitude: <\/b> -117.33612<br\/>  <b>Detection Time: <\/b> 2023-03-23 10:34 UTC<br\/>  <b>Sensor: <\/b> NOAA-20 VIIRS<br\/> <b>Confidence: <\/b> Nominal<br\/>  <b>Day\/Night: <\/b> Night<br\/> <b>Scan: <\/b> 0.53 km<br\/> <b>Track: <\/b> 0.67 km<br\/> <b>FRP: <\/b> 1.18 MW<br\/> <b>Brightness: <\/b> 300.28 K" }, "geometry": { "type": "Point", "coordinates": [ -117.33612, 34.61237, 0.0 ] } },
{ "type": "Feature", "properties": { "Name": "Fire Detection Centroid ", "Description": "<b>Latitude: <\/b> 34.60603<br\/>  <b>Longitude: <\/b> -117.33691<br\/>  <b>Detection Time: <\/b> 2023-03-23 10:34 UTC<br\/>  <b>Sensor: <\/b> NOAA-20 VIIRS<br\/> <b>Confidence: <\/b> Nominal<br\/>  <b>Day\/Night: <\/b> Night<br\/> <b>Scan: <\/b> 0.53 km<br\/> <b>Track: <\/b> 0.67 km<br\/> <b>FRP: <\/b> 1.46 MW<br\/> <b>Brightness: <\/b> 303.47 K" }, "geometry": { "type": "Point", "coordinates": [ -117.33691, 34.60603, 0.0 ] } },
{ "type": "Feature", "properties": { "Name": "Fire Detection Centroid ", "Description": "<b>Latitude: <\/b> 48.04427<br\/>  <b>Longitude: <\/b> -116.97742<br\/>  <b>Detection Time: <\/b> 2023-03-23 10:30 UTC<br\/>  <b>Sensor: <\/b> NOAA-20 VIIRS<br\/> <b>Confidence: <\/b> Nominal<br\/>  <b>Day\/Night: <\/b> Night<br\/> <b>Scan: <\/b> 0.48 km<br\/> <b>Track: <\/b> 0.48 km<br\/> <b>FRP: <\/b> 5.17 MW<br\/> <b>Brightness: <\/b> 332.87 K" }, "geometry": { "type": "Point", "coordinates": [ -116.97742, 48.04427, 0.0 ] } }
]
}
