{
"type": "FeatureCollection",
"crs": { "type": "name", "properties": { "name": "urn:ogc:def:crs:OGC:1.3:CRS84" } },
"features": [
{ "type": "Feature", "properties": { "Name": "Fire Detection Centroid ", "Description": "<b>Latitude: <\/b> 21.40954<br\/>  <b>Longitude: <\/b> -158.00502<br\/>  <b>Detection Time: <\/b> 2023-08-03 23:39 UTC<br\/>  <b>Sensor: <\/b> NOAA-20 VIIRS<br\/> <b>Confidence: <\/b> Low<br\/>  <b>Day\/Night: <\/b> Day<br\/> <b>Scan: <\/b> 0.39 km<br\/> <b>Track: <\/b> 0.36 km<br\/> <b>FRP: <\/b> 11.38 MW<br\/> <b>Brightness: <\/b> 342.93 K" }, "geometry": { "type": "Point", "coordinates": [ -158.00502, 21.40954, 0.0 ] } },
{ "type": "Feature", "properties": { "Name": "Fire Detection Centroid ", "Description": "<b>Latitude: <\/b> 21.40835<br\/>  <b>Longitude: <\/b> -158.01251<br\/>  <b>Detection Time: <\/b> 2023-08-03 23:39 UTC<br\/>  <b>Sensor: <\/b> NOAA-20 VIIRS<br\/> <b>Confidence: <\/b> Low<br\/>  <b>Day\/Night: <\/b> Day<br\/> <b>Scan: <\/b> 0.39 km<br\/> <b>Track: <\/b> 0.36 km<br\/> <b>FRP: <\/b> 5.79 MW<br\/> <b>Brightness: <\/b> 338.04 K" }, "geometry": { "type": "Point", "coordinates": [ -158.01251, 21.40835, 0.0 ] } }
]
}
