{
"type": "FeatureCollection",
"crs": { "type": "name", "properties": { "name": "urn:ogc:def:crs:OGC:1.3:CRS84" } },
"features": [
{ "type": "Feature", "properties": { "Name": "Fire Detection Centroid ", "Description": "<b>Latitude: <\/b> 21.98822<br\/>  <b>Longitude: <\/b> -159.7561<br\/>  <b>Detection Time: <\/b> 2023-07-01 23:58 UTC<br\/>  <b>Sensor: <\/b> NOAA-20 VIIRS<br\/> <b>Confidence: <\/b> Nominal<br\/>  <b>Day\/Night: <\/b> Day<br\/> <b>Scan: <\/b> 0.41 km<br\/> <b>Track: <\/b> 0.37 km<br\/> <b>FRP: <\/b> 8.7 MW<br\/> <b>Brightness: <\/b> 352.15 K" }, "geometry": { "type": "Point", "coordinates": [ -159.7561, 21.98822, 0.0 ] } },
{ "type": "Feature", "properties": { "Name": "Fire Detection Centroid ", "Description": "<b>Latitude: <\/b> 21.99789<br\/>  <b>Longitude: <\/b> -159.7617<br\/>  <b>Detection Time: <\/b> 2023-07-01 23:58 UTC<br\/>  <b>Sensor: <\/b> NOAA-20 VIIRS<br\/> <b>Confidence: <\/b> Nominal<br\/>  <b>Day\/Night: <\/b> Day<br\/> <b>Scan: <\/b> 0.41 km<br\/> <b>Track: <\/b> 0.37 km<br\/> <b>FRP: <\/b> 8.58 MW<br\/> <b>Brightness: <\/b> 348.67 K" }, "geometry": { "type": "Point", "coordinates": [ -159.7617, 21.99789, 0.0 ] } },
{ "type": "Feature", "properties": { "Name": "Fire Detection Centroid ", "Description": "<b>Latitude: <\/b> 21.99448<br\/>  <b>Longitude: <\/b> -159.76114<br\/>  <b>Detection Time: <\/b> 2023-07-01 23:58 UTC<br\/>  <b>Sensor: <\/b> NOAA-20 VIIRS<br\/> <b>Confidence: <\/b> Nominal<br\/>  <b>Day\/Night: <\/b> Day<br\/> <b>Scan: <\/b> 0.41 km<br\/> <b>Track: <\/b> 0.37 km<br\/> <b>FRP: <\/b> 4.31 MW<br\/> <b>Brightness: <\/b> 345 K" }, "geometry": { "type": "Point", "coordinates": [ -159.76114, 21.99448, 0.0 ] } },
{ "type": "Feature", "properties": { "Name": "Fire Detection Centroid ", "Description": "<b>Latitude: <\/b> 21.99503<br\/>  <b>Longitude: <\/b> -159.75719<br\/>  <b>Detection Time: <\/b> 2023-07-01 23:58 UTC<br\/>  <b>Sensor: <\/b> NOAA-20 VIIRS<br\/> <b>Confidence: <\/b> Nominal<br\/>  <b>Day\/Night: <\/b> Day<br\/> <b>Scan: <\/b> 0.41 km<br\/> <b>Track: <\/b> 0.37 km<br\/> <b>FRP: <\/b> 4.31 MW<br\/> <b>Brightness: <\/b> 336.16 K" }, "geometry": { "type": "Point", "coordinates": [ -159.75719, 21.99503, 0.0 ] } },
{ "type": "Feature", "properties": { "Name": "Fire Detection Centroid ", "Description": "<b>Latitude: <\/b> 21.99108<br\/>  <b>Longitude: <\/b> -159.7606<br\/>  <b>Detection Time: <\/b> 2023-07-01 23:58 UTC<br\/>  <b>Sensor: <\/b> NOAA-20 VIIRS<br\/> <b>Confidence: <\/b> Nominal<br\/>  <b>Day\/Night: <\/b> Day<br\/> <b>Scan: <\/b> 0.41 km<br\/> <b>Track: <\/b> 0.37 km<br\/> <b>FRP: <\/b> 4.31 MW<br\/> <b>Brightness: <\/b> 343.62 K" }, "geometry": { "type": "Point", "coordinates": [ -159.7606, 21.99108, 0.0 ] } }
]
}
