{
"type": "FeatureCollection",
"crs": { "type": "name", "properties": { "name": "urn:ogc:def:crs:OGC:1.3:CRS84" } },
"features": [
{ "type": "Feature", "properties": { "Name": "Fire Detection Centroid ", "Description": "<b>Latitude: <\/b> 44.43142<br\/>  <b>Longitude: <\/b> -68.98336<br\/>  <b>Detection Time: <\/b> 2023-07-29 05:29 UTC<br\/>  <b>Sensor: <\/b> NOAA-20 VIIRS<br\/> <b>Confidence: <\/b> Nominal<br\/>  <b>Day\/Night: <\/b> Night<br\/> <b>Scan: <\/b> 0.6 km<br\/> <b>Track: <\/b> 0.7 km<br\/> <b>FRP: <\/b> 1.07 MW<br\/> <b>Brightness: <\/b> 302.83 K" }, "geometry": { "type": "Point", "coordinates": [ -68.98336, 44.43142, 0.0 ] } },
{ "type": "Feature", "properties": { "Name": "Fire Detection Centroid ", "Description": "<b>Latitude: <\/b> 48.18885<br\/>  <b>Longitude: <\/b> -64.92139<br\/>  <b>Detection Time: <\/b> 2023-07-29 05:28 UTC<br\/>  <b>Sensor: <\/b> NOAA-20 VIIRS<br\/> <b>Confidence: <\/b> Nominal<br\/>  <b>Day\/Night: <\/b> Night<br\/> <b>Scan: <\/b> 0.4 km<br\/> <b>Track: <\/b> 0.6 km<br\/> <b>FRP: <\/b> 0.85 MW<br\/> <b>Brightness: <\/b> 308.08 K" }, "geometry": { "type": "Point", "coordinates": [ -64.92139, 48.18885, 0.0 ] } },
{ "type": "Feature", "properties": { "Name": "Fire Detection Centroid ", "Description": "<b>Latitude: <\/b> 48.18962<br\/>  <b>Longitude: <\/b> -64.92146<br\/>  <b>Detection Time: <\/b> 2023-07-29 05:28 UTC<br\/>  <b>Sensor: <\/b> NOAA-20 VIIRS<br\/> <b>Confidence: <\/b> Nominal<br\/>  <b>Day\/Night: <\/b> Night<br\/> <b>Scan: <\/b> 0.4 km<br\/> <b>Track: <\/b> 0.6 km<br\/> <b>FRP: <\/b> 1.52 MW<br\/> <b>Brightness: <\/b> 309.9 K" }, "geometry": { "type": "Point", "coordinates": [ -64.92146, 48.18962, 0.0 ] } }
]
}
