{
"type": "FeatureCollection",
"crs": { "type": "name", "properties": { "name": "urn:ogc:def:crs:OGC:1.3:CRS84" } },
"features": [
{ "type": "Feature", "properties": { "Name": "Fire Detection Centroid ", "Description": "<b>Latitude: <\/b> 19.59401<br\/>  <b>Longitude: <\/b> -155.50343<br\/>  <b>Detection Time: <\/b> 2022-12-17 23:33 UTC<br\/>  <b>Sensor: <\/b> NOAA-20 VIIRS<br\/> <b>Confidence: <\/b> Low<br\/>  <b>Day\/Night: <\/b> Day<br\/> <b>Scan: <\/b> 0.39 km<br\/> <b>Track: <\/b> 0.36 km<br\/> <b>FRP: <\/b> 5.42 MW<br\/> <b>Brightness: <\/b> 331.84 K" }, "geometry": { "type": "Point", "coordinates": [ -155.50343, 19.59401, 0.0 ] } },
{ "type": "Feature", "properties": { "Name": "Fire Detection Centroid ", "Description": "<b>Latitude: <\/b> 19.5973<br\/>  <b>Longitude: <\/b> -155.50404<br\/>  <b>Detection Time: <\/b> 2022-12-17 23:33 UTC<br\/>  <b>Sensor: <\/b> NOAA-20 VIIRS<br\/> <b>Confidence: <\/b> Nominal<br\/>  <b>Day\/Night: <\/b> Day<br\/> <b>Scan: <\/b> 0.39 km<br\/> <b>Track: <\/b> 0.36 km<br\/> <b>FRP: <\/b> 5.42 MW<br\/> <b>Brightness: <\/b> 334.7 K" }, "geometry": { "type": "Point", "coordinates": [ -155.50404, 19.5973, 0.0 ] } },
{ "type": "Feature", "properties": { "Name": "Fire Detection Centroid ", "Description": "<b>Latitude: <\/b> 19.59686<br\/>  <b>Longitude: <\/b> -155.50441<br\/>  <b>Detection Time: <\/b> 2022-12-17 23:31 UTC<br\/>  <b>Sensor: <\/b> NOAA-20 VIIRS<br\/> <b>Confidence: <\/b> Nominal<br\/>  <b>Day\/Night: <\/b> Day<br\/> <b>Scan: <\/b> 0.4 km<br\/> <b>Track: <\/b> 0.4 km<br\/> <b>FRP: <\/b> 5.42 MW<br\/> <b>Brightness: <\/b> 334.7 K" }, "geometry": { "type": "Point", "coordinates": [ -155.50441, 19.59686, 0.0 ] } },
{ "type": "Feature", "properties": { "Name": "Fire Detection Centroid ", "Description": "<b>Latitude: <\/b> 19.59356<br\/>  <b>Longitude: <\/b> -155.50378<br\/>  <b>Detection Time: <\/b> 2022-12-17 23:31 UTC<br\/>  <b>Sensor: <\/b> NOAA-20 VIIRS<br\/> <b>Confidence: <\/b> Low<br\/>  <b>Day\/Night: <\/b> Day<br\/> <b>Scan: <\/b> 0.4 km<br\/> <b>Track: <\/b> 0.4 km<br\/> <b>FRP: <\/b> 5.42 MW<br\/> <b>Brightness: <\/b> 331.84 K" }, "geometry": { "type": "Point", "coordinates": [ -155.50378, 19.59356, 0.0 ] } }
]
}
