{
"type": "FeatureCollection",
"crs": { "type": "name", "properties": { "name": "urn:ogc:def:crs:OGC:1.3:CRS84" } },
"features": [
{ "type": "Feature", "properties": { "Name": "Fire Detection Centroid ", "Description": "<b>Latitude: <\/b> 18.75225<br\/>  <b>Longitude: <\/b> -68.42179<br\/>  <b>Detection Time: <\/b> 2024-02-16 05:48 UTC<br\/>  <b>Sensor: <\/b> NOAA-20 VIIRS<br\/> <b>Confidence: <\/b> Nominal<br\/>  <b>Day\/Night: <\/b> Night<br\/> <b>Scan: <\/b> 0.4 km<br\/> <b>Track: <\/b> 0.5 km<br\/> <b>FRP: <\/b> 1.43 MW<br\/> <b>Brightness: <\/b> 314.53 K" }, "geometry": { "type": "Point", "coordinates": [ -68.42179, 18.75225, 0.0 ] } },
{ "type": "Feature", "properties": { "Name": "Fire Detection Centroid ", "Description": "<b>Latitude: <\/b> 18.53866<br\/>  <b>Longitude: <\/b> -68.45143<br\/>  <b>Detection Time: <\/b> 2024-02-16 05:48 UTC<br\/>  <b>Sensor: <\/b> NOAA-20 VIIRS<br\/> <b>Confidence: <\/b> Nominal<br\/>  <b>Day\/Night: <\/b> Night<br\/> <b>Scan: <\/b> 0.4 km<br\/> <b>Track: <\/b> 0.5 km<br\/> <b>FRP: <\/b> 1.85 MW<br\/> <b>Brightness: <\/b> 320.91 K" }, "geometry": { "type": "Point", "coordinates": [ -68.45143, 18.53866, 0.0 ] } },
{ "type": "Feature", "properties": { "Name": "Fire Detection Centroid ", "Description": "<b>Latitude: <\/b> 17.60995<br\/>  <b>Longitude: <\/b> -64.76434<br\/>  <b>Detection Time: <\/b> 2024-02-16 05:48 UTC<br\/>  <b>Sensor: <\/b> NOAA-20 VIIRS<br\/> <b>Confidence: <\/b> Nominal<br\/>  <b>Day\/Night: <\/b> Night<br\/> <b>Scan: <\/b> 0.4 km<br\/> <b>Track: <\/b> 0.4 km<br\/> <b>FRP: <\/b> 1.57 MW<br\/> <b>Brightness: <\/b> 312.55 K" }, "geometry": { "type": "Point", "coordinates": [ -64.76434, 17.60995, 0.0 ] } },
{ "type": "Feature", "properties": { "Name": "Fire Detection Centroid ", "Description": "<b>Latitude: <\/b> 20.63413<br\/>  <b>Longitude: <\/b> -76.84473<br\/>  <b>Detection Time: <\/b> 2024-02-16 05:48 UTC<br\/>  <b>Sensor: <\/b> NOAA-20 VIIRS<br\/> <b>Confidence: <\/b> Nominal<br\/>  <b>Day\/Night: <\/b> Night<br\/> <b>Scan: <\/b> 0.8 km<br\/> <b>Track: <\/b> 0.8 km<br\/> <b>FRP: <\/b> 1.1 MW<br\/> <b>Brightness: <\/b> 299.75 K" }, "geometry": { "type": "Point", "coordinates": [ -76.84473, 20.63413, 0.0 ] } },
{ "type": "Feature", "properties": { "Name": "Fire Detection Centroid ", "Description": "<b>Latitude: <\/b> 20.43015<br\/>  <b>Longitude: <\/b> -76.86436<br\/>  <b>Detection Time: <\/b> 2024-02-16 05:48 UTC<br\/>  <b>Sensor: <\/b> NOAA-20 VIIRS<br\/> <b>Confidence: <\/b> Nominal<br\/>  <b>Day\/Night: <\/b> Night<br\/> <b>Scan: <\/b> 0.8 km<br\/> <b>Track: <\/b> 0.8 km<br\/> <b>FRP: <\/b> 0.57 MW<br\/> <b>Brightness: <\/b> 299.65 K" }, "geometry": { "type": "Point", "coordinates": [ -76.86436, 20.43015, 0.0 ] } },
{ "type": "Feature", "properties": { "Name": "Fire Detection Centroid ", "Description": "<b>Latitude: <\/b> 45.2072<br\/>  <b>Longitude: <\/b> -66.03279<br\/>  <b>Detection Time: <\/b> 2024-02-16 05:40 UTC<br\/>  <b>Sensor: <\/b> NOAA-20 VIIRS<br\/> <b>Confidence: <\/b> Nominal<br\/>  <b>Day\/Night: <\/b> Night<br\/> <b>Scan: <\/b> 0.6 km<br\/> <b>Track: <\/b> 0.5 km<br\/> <b>FRP: <\/b> 1.26 MW<br\/> <b>Brightness: <\/b> 298.53 K" }, "geometry": { "type": "Point", "coordinates": [ -66.03279, 45.2072, 0.0 ] } },
{ "type": "Feature", "properties": { "Name": "Fire Detection Centroid ", "Description": "<b>Latitude: <\/b> 45.20676<br\/>  <b>Longitude: <\/b> -66.02501<br\/>  <b>Detection Time: <\/b> 2024-02-16 05:40 UTC<br\/>  <b>Sensor: <\/b> NOAA-20 VIIRS<br\/> <b>Confidence: <\/b> Nominal<br\/>  <b>Day\/Night: <\/b> Night<br\/> <b>Scan: <\/b> 0.6 km<br\/> <b>Track: <\/b> 0.5 km<br\/> <b>FRP: <\/b> 1.11 MW<br\/> <b>Brightness: <\/b> 305.38 K" }, "geometry": { "type": "Point", "coordinates": [ -66.02501, 45.20676, 0.0 ] } }
]
}
