{
"type": "FeatureCollection",
"crs": { "type": "name", "properties": { "name": "urn:ogc:def:crs:OGC:1.3:CRS84" } },
"features": [
{ "type": "Feature", "properties": { "Name": "Fire Detection Centroid ", "Description": "<b>Latitude: <\/b> 45.2298<br\/>  <b>Longitude: <\/b> -123.16553<br\/>  <b>Detection Time: <\/b> 2024-05-29 11:28 UTC<br\/>  <b>Sensor: <\/b> NOAA-20 VIIRS<br\/> <b>Confidence: <\/b> Nominal<br\/>  <b>Day\/Night: <\/b> Night<br\/> <b>Scan: <\/b> 0.67 km<br\/> <b>Track: <\/b> 0.74 km<br\/> <b>FRP: <\/b> 2.26 MW<br\/> <b>Brightness: <\/b> 308.67 K" }, "geometry": { "type": "Point", "coordinates": [ -123.16553, 45.2298, 0.0 ] } },
{ "type": "Feature", "properties": { "Name": "Fire Detection Centroid ", "Description": "<b>Latitude: <\/b> 45.23185<br\/>  <b>Longitude: <\/b> -123.16144<br\/>  <b>Detection Time: <\/b> 2024-05-29 11:28 UTC<br\/>  <b>Sensor: <\/b> NOAA-20 VIIRS<br\/> <b>Confidence: <\/b> Nominal<br\/>  <b>Day\/Night: <\/b> Night<br\/> <b>Scan: <\/b> 0.67 km<br\/> <b>Track: <\/b> 0.74 km<br\/> <b>FRP: <\/b> 1.83 MW<br\/> <b>Brightness: <\/b> 306.83 K" }, "geometry": { "type": "Point", "coordinates": [ -123.16144, 45.23185, 0.0 ] } }
]
}
