{
"type": "FeatureCollection",
"crs": { "type": "name", "properties": { "name": "urn:ogc:def:crs:OGC:1.3:CRS84" } },
"features": [
{ "type": "Feature", "properties": { "Name": "Fire Detection Centroid ", "Description": "<b>Latitude: <\/b> 45.28127<br\/>  <b>Longitude: <\/b> -66.01371<br\/>  <b>Detection Time: <\/b> 2022-08-22 05:21 UTC<br\/>  <b>Sensor: <\/b> NOAA-20 VIIRS<br\/> <b>Confidence: <\/b> Nominal<br\/>  <b>Day\/Night: <\/b> Night<br\/> <b>Scan: <\/b> 0.5 km<br\/> <b>Track: <\/b> 0.7 km<br\/> <b>FRP: <\/b> 1.38 MW<br\/> <b>Brightness: <\/b> 301.31 K" }, "geometry": { "type": "Point", "coordinates": [ -66.01371, 45.28127, 0.0 ] } },
{ "type": "Feature", "properties": { "Name": "Fire Detection Centroid ", "Description": "<b>Latitude: <\/b> 45.28138<br\/>  <b>Longitude: <\/b> -66.02052<br\/>  <b>Detection Time: <\/b> 2022-08-22 05:21 UTC<br\/>  <b>Sensor: <\/b> NOAA-20 VIIRS<br\/> <b>Confidence: <\/b> Nominal<br\/>  <b>Day\/Night: <\/b> Night<br\/> <b>Scan: <\/b> 0.5 km<br\/> <b>Track: <\/b> 0.7 km<br\/> <b>FRP: <\/b> 1.38 MW<br\/> <b>Brightness: <\/b> 305.7 K" }, "geometry": { "type": "Point", "coordinates": [ -66.02052, 45.28138, 0.0 ] } },
{ "type": "Feature", "properties": { "Name": "Fire Detection Centroid ", "Description": "<b>Latitude: <\/b> 48.18881<br\/>  <b>Longitude: <\/b> -64.92274<br\/>  <b>Detection Time: <\/b> 2022-08-22 05:20 UTC<br\/>  <b>Sensor: <\/b> NOAA-20 VIIRS<br\/> <b>Confidence: <\/b> Nominal<br\/>  <b>Day\/Night: <\/b> Night<br\/> <b>Scan: <\/b> 0.5 km<br\/> <b>Track: <\/b> 0.6 km<br\/> <b>FRP: <\/b> 0.5 MW<br\/> <b>Brightness: <\/b> 299.45 K" }, "geometry": { "type": "Point", "coordinates": [ -64.92274, 48.18881, 0.0 ] } }
]
}
