{
"type": "FeatureCollection",
"crs": { "type": "name", "properties": { "name": "urn:ogc:def:crs:OGC:1.3:CRS84" } },
"features": [
{ "type": "Feature", "properties": { "Name": "Fire Detection Centroid ", "Description": "<b>Latitude: <\/b> 47.56899<br\/>  <b>Longitude: <\/b> -122.36994<br\/>  <b>Detection Time: <\/b> 2022-12-30 21:14 UTC<br\/>  <b>Sensor: <\/b> NOAA-20 VIIRS<br\/> <b>Confidence: <\/b> Nominal<br\/>  <b>Day\/Night: <\/b> Day<br\/> <b>Scan: <\/b> 0.45 km<br\/> <b>Track: <\/b> 0.39 km<br\/> <b>FRP: <\/b> 3.54 MW<br\/> <b>Brightness: <\/b> 332.03 K" }, "geometry": { "type": "Point", "coordinates": [ -122.36994, 47.56899, 0.0 ] } },
{ "type": "Feature", "properties": { "Name": "Fire Detection Centroid ", "Description": "<b>Latitude: <\/b> 35.40084<br\/>  <b>Longitude: <\/b> -118.54237<br\/>  <b>Detection Time: <\/b> 2022-12-30 21:10 UTC<br\/>  <b>Sensor: <\/b> NOAA-20 VIIRS<br\/> <b>Confidence: <\/b> Nominal<br\/>  <b>Day\/Night: <\/b> Day<br\/> <b>Scan: <\/b> 0.47 km<br\/> <b>Track: <\/b> 0.4 km<br\/> <b>FRP: <\/b> 2.83 MW<br\/> <b>Brightness: <\/b> 327.68 K" }, "geometry": { "type": "Point", "coordinates": [ -118.54237, 35.40084, 0.0 ] } },
{ "type": "Feature", "properties": { "Name": "Fire Detection Centroid ", "Description": "<b>Latitude: <\/b> 33.58027<br\/>  <b>Longitude: <\/b> -116.06916<br\/>  <b>Detection Time: <\/b> 2022-12-30 21:10 UTC<br\/>  <b>Sensor: <\/b> NOAA-20 VIIRS<br\/> <b>Confidence: <\/b> Nominal<br\/>  <b>Day\/Night: <\/b> Day<br\/> <b>Scan: <\/b> 0.39 km<br\/> <b>Track: <\/b> 0.44 km<br\/> <b>FRP: <\/b> 2.54 MW<br\/> <b>Brightness: <\/b> 335.84 K" }, "geometry": { "type": "Point", "coordinates": [ -116.06916, 33.58027, 0.0 ] } },
{ "type": "Feature", "properties": { "Name": "Fire Detection Centroid ", "Description": "<b>Latitude: <\/b> 19.78347<br\/>  <b>Longitude: <\/b> -104.34472<br\/>  <b>Detection Time: <\/b> 2022-12-30 21:03 UTC<br\/>  <b>Sensor: <\/b> NOAA-20 VIIRS<br\/> <b>Confidence: <\/b> Nominal<br\/>  <b>Day\/Night: <\/b> Day<br\/> <b>Scan: <\/b> 0.72 km<br\/> <b>Track: <\/b> 0.75 km<br\/> <b>FRP: <\/b> 8.1 MW<br\/> <b>Brightness: <\/b> 339.77 K" }, "geometry": { "type": "Point", "coordinates": [ -104.34472, 19.78347, 0.0 ] } }
]
}
