{
"type": "FeatureCollection",
"crs": { "type": "name", "properties": { "name": "urn:ogc:def:crs:OGC:1.3:CRS84" } },
"features": [
{ "type": "Feature", "properties": { "Name": "Fire Detection Centroid ", "Description": "<b>Latitude: <\/b> 18.92718<br\/>  <b>Longitude: <\/b> -70.35601<br\/>  <b>Detection Time: <\/b> 2022-11-30 05:53 UTC<br\/>  <b>Sensor: <\/b> NOAA-20 VIIRS<br\/> <b>Confidence: <\/b> Nominal<br\/>  <b>Day\/Night: <\/b> Night<br\/> <b>Scan: <\/b> 0.4 km<br\/> <b>Track: <\/b> 0.5 km<br\/> <b>FRP: <\/b> 1.95 MW<br\/> <b>Brightness: <\/b> 307.18 K" }, "geometry": { "type": "Point", "coordinates": [ -70.35601, 18.92718, 0.0 ] } },
{ "type": "Feature", "properties": { "Name": "Fire Detection Centroid ", "Description": "<b>Latitude: <\/b> 20.23499<br\/>  <b>Longitude: <\/b> -77.01215<br\/>  <b>Detection Time: <\/b> 2022-11-30 05:53 UTC<br\/>  <b>Sensor: <\/b> NOAA-20 VIIRS<br\/> <b>Confidence: <\/b> Nominal<br\/>  <b>Day\/Night: <\/b> Night<br\/> <b>Scan: <\/b> 0.6 km<br\/> <b>Track: <\/b> 0.7 km<br\/> <b>FRP: <\/b> 0.59 MW<br\/> <b>Brightness: <\/b> 301.17 K" }, "geometry": { "type": "Point", "coordinates": [ -77.01215, 20.23499, 0.0 ] } },
{ "type": "Feature", "properties": { "Name": "Fire Detection Centroid ", "Description": "<b>Latitude: <\/b> 18.93147<br\/>  <b>Longitude: <\/b> -70.35564<br\/>  <b>Detection Time: <\/b> 2022-11-30 05:53 UTC<br\/>  <b>Sensor: <\/b> NOAA-20 VIIRS<br\/> <b>Confidence: <\/b> Nominal<br\/>  <b>Day\/Night: <\/b> Night<br\/> <b>Scan: <\/b> 0.4 km<br\/> <b>Track: <\/b> 0.5 km<br\/> <b>FRP: <\/b> 1.3 MW<br\/> <b>Brightness: <\/b> 300.78 K" }, "geometry": { "type": "Point", "coordinates": [ -70.35564, 18.93147, 0.0 ] } },
{ "type": "Feature", "properties": { "Name": "Fire Detection Centroid ", "Description": "<b>Latitude: <\/b> 45.28048<br\/>  <b>Longitude: <\/b> -66.0153<br\/>  <b>Detection Time: <\/b> 2022-11-30 05:46 UTC<br\/>  <b>Sensor: <\/b> NOAA-20 VIIRS<br\/> <b>Confidence: <\/b> Nominal<br\/>  <b>Day\/Night: <\/b> Night<br\/> <b>Scan: <\/b> 0.5 km<br\/> <b>Track: <\/b> 0.5 km<br\/> <b>FRP: <\/b> 1.86 MW<br\/> <b>Brightness: <\/b> 295.05 K" }, "geometry": { "type": "Point", "coordinates": [ -66.0153, 45.28048, 0.0 ] } },
{ "type": "Feature", "properties": { "Name": "Fire Detection Centroid ", "Description": "<b>Latitude: <\/b> 48.52385<br\/>  <b>Longitude: <\/b> -64.35537<br\/>  <b>Detection Time: <\/b> 2022-11-30 05:45 UTC<br\/>  <b>Sensor: <\/b> NOAA-20 VIIRS<br\/> <b>Confidence: <\/b> Nominal<br\/>  <b>Day\/Night: <\/b> Night<br\/> <b>Scan: <\/b> 0.5 km<br\/> <b>Track: <\/b> 0.5 km<br\/> <b>FRP: <\/b> 1.25 MW<br\/> <b>Brightness: <\/b> 305.7 K" }, "geometry": { "type": "Point", "coordinates": [ -64.35537, 48.52385, 0.0 ] } }
]
}
