{
"type": "FeatureCollection",
"crs": { "type": "name", "properties": { "name": "urn:ogc:def:crs:OGC:1.3:CRS84" } },
"features": [
{ "type": "Feature", "properties": { "Name": "Fire Detection Centroid ", "Description": "<b>Latitude: <\/b> 26.29672<br\/>  <b>Longitude: <\/b> -80.15368<br\/>  <b>Detection Time: <\/b> 2024-03-27 06:25 UTC<br\/>  <b>Sensor: <\/b> NOAA-20 VIIRS<br\/> <b>Confidence: <\/b> Nominal<br\/>  <b>Day\/Night: <\/b> Night<br\/> <b>Scan: <\/b> 0.3 km<br\/> <b>Track: <\/b> 0.6 km<br\/> <b>FRP: <\/b> 1.25 MW<br\/> <b>Brightness: <\/b> 309.84 K" }, "geometry": { "type": "Point", "coordinates": [ -80.15368, 26.29672, 0.0 ] } },
{ "type": "Feature", "properties": { "Name": "Fire Detection Centroid ", "Description": "<b>Latitude: <\/b> 37.22619<br\/>  <b>Longitude: <\/b> -82.04096<br\/>  <b>Detection Time: <\/b> 2024-03-27 06:22 UTC<br\/>  <b>Sensor: <\/b> NOAA-20 VIIRS<br\/> <b>Confidence: <\/b> Nominal<br\/>  <b>Day\/Night: <\/b> Night<br\/> <b>Scan: <\/b> 0.6 km<br\/> <b>Track: <\/b> 0.7 km<br\/> <b>FRP: <\/b> 1.08 MW<br\/> <b>Brightness: <\/b> 295.74 K" }, "geometry": { "type": "Point", "coordinates": [ -82.04096, 37.22619, 0.0 ] } },
{ "type": "Feature", "properties": { "Name": "Fire Detection Centroid ", "Description": "<b>Latitude: <\/b> 42.37358<br\/>  <b>Longitude: <\/b> -83.11422<br\/>  <b>Detection Time: <\/b> 2024-03-27 06:21 UTC<br\/>  <b>Sensor: <\/b> NOAA-20 VIIRS<br\/> <b>Confidence: <\/b> Nominal<br\/>  <b>Day\/Night: <\/b> Night<br\/> <b>Scan: <\/b> 0.7 km<br\/> <b>Track: <\/b> 0.7 km<br\/> <b>FRP: <\/b> 1.28 MW<br\/> <b>Brightness: <\/b> 305.77 K" }, "geometry": { "type": "Point", "coordinates": [ -83.11422, 42.37358, 0.0 ] } },
{ "type": "Feature", "properties": { "Name": "Fire Detection Centroid ", "Description": "<b>Latitude: <\/b> 40.37775<br\/>  <b>Longitude: <\/b> -79.85787<br\/>  <b>Detection Time: <\/b> 2024-03-27 06:21 UTC<br\/>  <b>Sensor: <\/b> NOAA-20 VIIRS<br\/> <b>Confidence: <\/b> Nominal<br\/>  <b>Day\/Night: <\/b> Night<br\/> <b>Scan: <\/b> 0.4 km<br\/> <b>Track: <\/b> 0.6 km<br\/> <b>FRP: <\/b> 4.58 MW<br\/> <b>Brightness: <\/b> 331.92 K" }, "geometry": { "type": "Point", "coordinates": [ -79.85787, 40.37775, 0.0 ] } },
{ "type": "Feature", "properties": { "Name": "Fire Detection Centroid ", "Description": "<b>Latitude: <\/b> 42.1674<br\/>  <b>Longitude: <\/b> -83.11878<br\/>  <b>Detection Time: <\/b> 2024-03-27 06:21 UTC<br\/>  <b>Sensor: <\/b> NOAA-20 VIIRS<br\/> <b>Confidence: <\/b> Nominal<br\/>  <b>Day\/Night: <\/b> Night<br\/> <b>Scan: <\/b> 0.7 km<br\/> <b>Track: <\/b> 0.7 km<br\/> <b>FRP: <\/b> 2.23 MW<br\/> <b>Brightness: <\/b> 310.49 K" }, "geometry": { "type": "Point", "coordinates": [ -83.11878, 42.1674, 0.0 ] } },
{ "type": "Feature", "properties": { "Name": "Fire Detection Centroid ", "Description": "<b>Latitude: <\/b> 39.16527<br\/>  <b>Longitude: <\/b> -79.68555<br\/>  <b>Detection Time: <\/b> 2024-03-27 06:21 UTC<br\/>  <b>Sensor: <\/b> NOAA-20 VIIRS<br\/> <b>Confidence: <\/b> Nominal<br\/>  <b>Day\/Night: <\/b> Night<br\/> <b>Scan: <\/b> 0.4 km<br\/> <b>Track: <\/b> 0.6 km<br\/> <b>FRP: <\/b> 0.45 MW<br\/> <b>Brightness: <\/b> 297.01 K" }, "geometry": { "type": "Point", "coordinates": [ -79.68555, 39.16527, 0.0 ] } },
{ "type": "Feature", "properties": { "Name": "Fire Detection Centroid ", "Description": "<b>Latitude: <\/b> 39.27071<br\/>  <b>Longitude: <\/b> -81.02544<br\/>  <b>Detection Time: <\/b> 2024-03-27 06:21 UTC<br\/>  <b>Sensor: <\/b> NOAA-20 VIIRS<br\/> <b>Confidence: <\/b> Nominal<br\/>  <b>Day\/Night: <\/b> Night<br\/> <b>Scan: <\/b> 0.5 km<br\/> <b>Track: <\/b> 0.7 km<br\/> <b>FRP: <\/b> 0.72 MW<br\/> <b>Brightness: <\/b> 300.3 K" }, "geometry": { "type": "Point", "coordinates": [ -81.02544, 39.27071, 0.0 ] } },
{ "type": "Feature", "properties": { "Name": "Fire Detection Centroid ", "Description": "<b>Latitude: <\/b> 39.61795<br\/>  <b>Longitude: <\/b> -84.3801<br\/>  <b>Detection Time: <\/b> 2024-03-27 06:21 UTC<br\/>  <b>Sensor: <\/b> NOAA-20 VIIRS<br\/> <b>Confidence: <\/b> Nominal<br\/>  <b>Day\/Night: <\/b> Night<br\/> <b>Scan: <\/b> 0.8 km<br\/> <b>Track: <\/b> 0.8 km<br\/> <b>FRP: <\/b> 2.5 MW<br\/> <b>Brightness: <\/b> 296.58 K" }, "geometry": { "type": "Point", "coordinates": [ -84.3801, 39.61795, 0.0 ] } },
{ "type": "Feature", "properties": { "Name": "Fire Detection Centroid ", "Description": "<b>Latitude: <\/b> 40.37756<br\/>  <b>Longitude: <\/b> -79.85291<br\/>  <b>Detection Time: <\/b> 2024-03-27 06:21 UTC<br\/>  <b>Sensor: <\/b> NOAA-20 VIIRS<br\/> <b>Confidence: <\/b> Nominal<br\/>  <b>Day\/Night: <\/b> Night<br\/> <b>Scan: <\/b> 0.4 km<br\/> <b>Track: <\/b> 0.6 km<br\/> <b>FRP: <\/b> 3.87 MW<br\/> <b>Brightness: <\/b> 316.61 K" }, "geometry": { "type": "Point", "coordinates": [ -79.85291, 40.37756, 0.0 ] } }
]
}
