{
"type": "FeatureCollection",
"crs": { "type": "name", "properties": { "name": "urn:ogc:def:crs:OGC:1.3:CRS84" } },
"features": [
{ "type": "Feature", "properties": { "Name": "Fire Detection Centroid ", "Description": "<b>Latitude: <\/b> 19.40492<br\/>  <b>Longitude: <\/b> -155.28232<br\/>  <b>Detection Time: <\/b> 2022-10-24 12:32 UTC<br\/>  <b>Sensor: <\/b> NOAA-20 VIIRS<br\/> <b>Confidence: <\/b> Nominal<br\/>  <b>Day\/Night: <\/b> Night<br\/> <b>Scan: <\/b> 0.33 km<br\/> <b>Track: <\/b> 0.55 km<br\/> <b>FRP: <\/b> 1.51 MW<br\/> <b>Brightness: <\/b> 303.79 K" }, "geometry": { "type": "Point", "coordinates": [ -155.28232, 19.40492, 0.0 ] } },
{ "type": "Feature", "properties": { "Name": "Fire Detection Centroid ", "Description": "<b>Latitude: <\/b> 19.42133<br\/>  <b>Longitude: <\/b> -155.28613<br\/>  <b>Detection Time: <\/b> 2022-10-24 12:32 UTC<br\/>  <b>Sensor: <\/b> NOAA-20 VIIRS<br\/> <b>Confidence: <\/b> Nominal<br\/>  <b>Day\/Night: <\/b> Night<br\/> <b>Scan: <\/b> 0.33 km<br\/> <b>Track: <\/b> 0.55 km<br\/> <b>FRP: <\/b> 0.37 MW<br\/> <b>Brightness: <\/b> 296.41 K" }, "geometry": { "type": "Point", "coordinates": [ -155.28613, 19.42133, 0.0 ] } },
{ "type": "Feature", "properties": { "Name": "Fire Detection Centroid ", "Description": "<b>Latitude: <\/b> 19.41193<br\/>  <b>Longitude: <\/b> -155.29095<br\/>  <b>Detection Time: <\/b> 2022-10-24 12:32 UTC<br\/>  <b>Sensor: <\/b> NOAA-20 VIIRS<br\/> <b>Confidence: <\/b> Nominal<br\/>  <b>Day\/Night: <\/b> Night<br\/> <b>Scan: <\/b> 0.33 km<br\/> <b>Track: <\/b> 0.55 km<br\/> <b>FRP: <\/b> 2.11 MW<br\/> <b>Brightness: <\/b> 313.34 K" }, "geometry": { "type": "Point", "coordinates": [ -155.29095, 19.41193, 0.0 ] } },
{ "type": "Feature", "properties": { "Name": "Fire Detection Centroid ", "Description": "<b>Latitude: <\/b> 19.41124<br\/>  <b>Longitude: <\/b> -155.28764<br\/>  <b>Detection Time: <\/b> 2022-10-24 12:32 UTC<br\/>  <b>Sensor: <\/b> NOAA-20 VIIRS<br\/> <b>Confidence: <\/b> Nominal<br\/>  <b>Day\/Night: <\/b> Night<br\/> <b>Scan: <\/b> 0.33 km<br\/> <b>Track: <\/b> 0.55 km<br\/> <b>FRP: <\/b> 2.3 MW<br\/> <b>Brightness: <\/b> 311.87 K" }, "geometry": { "type": "Point", "coordinates": [ -155.28764, 19.41124, 0.0 ] } },
{ "type": "Feature", "properties": { "Name": "Fire Detection Centroid ", "Description": "<b>Latitude: <\/b> 19.41056<br\/>  <b>Longitude: <\/b> -155.28444<br\/>  <b>Detection Time: <\/b> 2022-10-24 12:32 UTC<br\/>  <b>Sensor: <\/b> NOAA-20 VIIRS<br\/> <b>Confidence: <\/b> Nominal<br\/>  <b>Day\/Night: <\/b> Night<br\/> <b>Scan: <\/b> 0.33 km<br\/> <b>Track: <\/b> 0.55 km<br\/> <b>FRP: <\/b> 2.3 MW<br\/> <b>Brightness: <\/b> 307.55 K" }, "geometry": { "type": "Point", "coordinates": [ -155.28444, 19.41056, 0.0 ] } },
{ "type": "Feature", "properties": { "Name": "Fire Detection Centroid ", "Description": "<b>Latitude: <\/b> 19.4099<br\/>  <b>Longitude: <\/b> -155.28125<br\/>  <b>Detection Time: <\/b> 2022-10-24 12:32 UTC<br\/>  <b>Sensor: <\/b> NOAA-20 VIIRS<br\/> <b>Confidence: <\/b> Nominal<br\/>  <b>Day\/Night: <\/b> Night<br\/> <b>Scan: <\/b> 0.33 km<br\/> <b>Track: <\/b> 0.55 km<br\/> <b>FRP: <\/b> 2.3 MW<br\/> <b>Brightness: <\/b> 312.73 K" }, "geometry": { "type": "Point", "coordinates": [ -155.28125, 19.4099, 0.0 ] } },
{ "type": "Feature", "properties": { "Name": "Fire Detection Centroid ", "Description": "<b>Latitude: <\/b> 19.40693<br\/>  <b>Longitude: <\/b> -155.2919<br\/>  <b>Detection Time: <\/b> 2022-10-24 12:32 UTC<br\/>  <b>Sensor: <\/b> NOAA-20 VIIRS<br\/> <b>Confidence: <\/b> High<br\/>  <b>Day\/Night: <\/b> Night<br\/> <b>Scan: <\/b> 0.33 km<br\/> <b>Track: <\/b> 0.55 km<br\/> <b>FRP: <\/b> 42.01 MW<br\/> <b>Brightness: <\/b> 367 K" }, "geometry": { "type": "Point", "coordinates": [ -155.2919, 19.40693, 0.0 ] } },
{ "type": "Feature", "properties": { "Name": "Fire Detection Centroid ", "Description": "<b>Latitude: <\/b> 19.40762<br\/>  <b>Longitude: <\/b> -155.29523<br\/>  <b>Detection Time: <\/b> 2022-10-24 12:32 UTC<br\/>  <b>Sensor: <\/b> NOAA-20 VIIRS<br\/> <b>Confidence: <\/b> Nominal<br\/>  <b>Day\/Night: <\/b> Night<br\/> <b>Scan: <\/b> 0.33 km<br\/> <b>Track: <\/b> 0.55 km<br\/> <b>FRP: <\/b> 42.01 MW<br\/> <b>Brightness: <\/b> 299.35 K" }, "geometry": { "type": "Point", "coordinates": [ -155.29523, 19.40762, 0.0 ] } },
{ "type": "Feature", "properties": { "Name": "Fire Detection Centroid ", "Description": "<b>Latitude: <\/b> 19.40557<br\/>  <b>Longitude: <\/b> -155.28542<br\/>  <b>Detection Time: <\/b> 2022-10-24 12:32 UTC<br\/>  <b>Sensor: <\/b> NOAA-20 VIIRS<br\/> <b>Confidence: <\/b> Nominal<br\/>  <b>Day\/Night: <\/b> Night<br\/> <b>Scan: <\/b> 0.33 km<br\/> <b>Track: <\/b> 0.55 km<br\/> <b>FRP: <\/b> 90.24 MW<br\/> <b>Brightness: <\/b> 317.27 K" }, "geometry": { "type": "Point", "coordinates": [ -155.28542, 19.40557, 0.0 ] } }
]
}
