{
"type": "FeatureCollection",
"crs": { "type": "name", "properties": { "name": "urn:ogc:def:crs:OGC:1.3:CRS84" } },
"features": [
{ "type": "Feature", "properties": { "Name": "Fire Detection Centroid ", "Description": "<b>Latitude: <\/b> 20.20624<br\/>  <b>Longitude: <\/b> -75.11045<br\/>  <b>Detection Time: <\/b> 2023-04-13 05:42 UTC<br\/>  <b>Sensor: <\/b> NOAA-20 VIIRS<br\/> <b>Confidence: <\/b> Nominal<br\/>  <b>Day\/Night: <\/b> Night<br\/> <b>Scan: <\/b> 0.7 km<br\/> <b>Track: <\/b> 0.8 km<br\/> <b>FRP: <\/b> 3.06 MW<br\/> <b>Brightness: <\/b> 304.61 K" }, "geometry": { "type": "Point", "coordinates": [ -75.11045, 20.20624, 0.0 ] } },
{ "type": "Feature", "properties": { "Name": "Fire Detection Centroid ", "Description": "<b>Latitude: <\/b> 20.19917<br\/>  <b>Longitude: <\/b> -75.11127<br\/>  <b>Detection Time: <\/b> 2023-04-13 05:42 UTC<br\/>  <b>Sensor: <\/b> NOAA-20 VIIRS<br\/> <b>Confidence: <\/b> Nominal<br\/>  <b>Day\/Night: <\/b> Night<br\/> <b>Scan: <\/b> 0.7 km<br\/> <b>Track: <\/b> 0.8 km<br\/> <b>FRP: <\/b> 3.06 MW<br\/> <b>Brightness: <\/b> 316.72 K" }, "geometry": { "type": "Point", "coordinates": [ -75.11127, 20.19917, 0.0 ] } },
{ "type": "Feature", "properties": { "Name": "Fire Detection Centroid ", "Description": "<b>Latitude: <\/b> 20.20388<br\/>  <b>Longitude: <\/b> -75.11352<br\/>  <b>Detection Time: <\/b> 2023-04-13 05:42 UTC<br\/>  <b>Sensor: <\/b> NOAA-20 VIIRS<br\/> <b>Confidence: <\/b> Nominal<br\/>  <b>Day\/Night: <\/b> Night<br\/> <b>Scan: <\/b> 0.7 km<br\/> <b>Track: <\/b> 0.8 km<br\/> <b>FRP: <\/b> 3.27 MW<br\/> <b>Brightness: <\/b> 303.25 K" }, "geometry": { "type": "Point", "coordinates": [ -75.11352, 20.20388, 0.0 ] } },
{ "type": "Feature", "properties": { "Name": "Fire Detection Centroid ", "Description": "<b>Latitude: <\/b> 20.20331<br\/>  <b>Longitude: <\/b> -75.10582<br\/>  <b>Detection Time: <\/b> 2023-04-13 05:42 UTC<br\/>  <b>Sensor: <\/b> NOAA-20 VIIRS<br\/> <b>Confidence: <\/b> Nominal<br\/>  <b>Day\/Night: <\/b> Night<br\/> <b>Scan: <\/b> 0.7 km<br\/> <b>Track: <\/b> 0.8 km<br\/> <b>FRP: <\/b> 4.53 MW<br\/> <b>Brightness: <\/b> 315.64 K" }, "geometry": { "type": "Point", "coordinates": [ -75.10582, 20.20331, 0.0 ] } },
{ "type": "Feature", "properties": { "Name": "Fire Detection Centroid ", "Description": "<b>Latitude: <\/b> 20.19625<br\/>  <b>Longitude: <\/b> -75.10676<br\/>  <b>Detection Time: <\/b> 2023-04-13 05:42 UTC<br\/>  <b>Sensor: <\/b> NOAA-20 VIIRS<br\/> <b>Confidence: <\/b> Nominal<br\/>  <b>Day\/Night: <\/b> Night<br\/> <b>Scan: <\/b> 0.7 km<br\/> <b>Track: <\/b> 0.8 km<br\/> <b>FRP: <\/b> 0.69 MW<br\/> <b>Brightness: <\/b> 299.5 K" }, "geometry": { "type": "Point", "coordinates": [ -75.10676, 20.19625, 0.0 ] } },
{ "type": "Feature", "properties": { "Name": "Fire Detection Centroid ", "Description": "<b>Latitude: <\/b> 45.27693<br\/>  <b>Longitude: <\/b> -66.01408<br\/>  <b>Detection Time: <\/b> 2023-04-13 05:34 UTC<br\/>  <b>Sensor: <\/b> NOAA-20 VIIRS<br\/> <b>Confidence: <\/b> Nominal<br\/>  <b>Day\/Night: <\/b> Night<br\/> <b>Scan: <\/b> 0.3 km<br\/> <b>Track: <\/b> 0.6 km<br\/> <b>FRP: <\/b> 0.97 MW<br\/> <b>Brightness: <\/b> 298.34 K" }, "geometry": { "type": "Point", "coordinates": [ -66.01408, 45.27693, 0.0 ] } },
{ "type": "Feature", "properties": { "Name": "Fire Detection Centroid ", "Description": "<b>Latitude: <\/b> 45.72716<br\/>  <b>Longitude: <\/b> -72.5108<br\/>  <b>Detection Time: <\/b> 2023-04-13 05:34 UTC<br\/>  <b>Sensor: <\/b> NOAA-20 VIIRS<br\/> <b>Confidence: <\/b> Nominal<br\/>  <b>Day\/Night: <\/b> Night<br\/> <b>Scan: <\/b> 0.8 km<br\/> <b>Track: <\/b> 0.8 km<br\/> <b>FRP: <\/b> 3.13 MW<br\/> <b>Brightness: <\/b> 316.01 K" }, "geometry": { "type": "Point", "coordinates": [ -72.5108, 45.72716, 0.0 ] } },
{ "type": "Feature", "properties": { "Name": "Fire Detection Centroid ", "Description": "<b>Latitude: <\/b> 45.73148<br\/>  <b>Longitude: <\/b> -72.5086<br\/>  <b>Detection Time: <\/b> 2023-04-13 05:34 UTC<br\/>  <b>Sensor: <\/b> NOAA-20 VIIRS<br\/> <b>Confidence: <\/b> Nominal<br\/>  <b>Day\/Night: <\/b> Night<br\/> <b>Scan: <\/b> 0.8 km<br\/> <b>Track: <\/b> 0.8 km<br\/> <b>FRP: <\/b> 2.84 MW<br\/> <b>Brightness: <\/b> 321.25 K" }, "geometry": { "type": "Point", "coordinates": [ -72.5086, 45.73148, 0.0 ] } },
{ "type": "Feature", "properties": { "Name": "Fire Detection Centroid ", "Description": "<b>Latitude: <\/b> 45.28224<br\/>  <b>Longitude: <\/b> -66.01347<br\/>  <b>Detection Time: <\/b> 2023-04-13 05:34 UTC<br\/>  <b>Sensor: <\/b> NOAA-20 VIIRS<br\/> <b>Confidence: <\/b> Nominal<br\/>  <b>Day\/Night: <\/b> Night<br\/> <b>Scan: <\/b> 0.3 km<br\/> <b>Track: <\/b> 0.6 km<br\/> <b>FRP: <\/b> 0.97 MW<br\/> <b>Brightness: <\/b> 297.04 K" }, "geometry": { "type": "Point", "coordinates": [ -66.01347, 45.28224, 0.0 ] } }
]
}
