{
"type": "FeatureCollection",
"crs": { "type": "name", "properties": { "name": "urn:ogc:def:crs:OGC:1.3:CRS84" } },
"features": [
{ "type": "Feature", "properties": { "Name": "Fire Detection Centroid ", "Description": "<b>Latitude: <\/b> 48.19094<br\/>  <b>Longitude: <\/b> -64.92183<br\/>  <b>Detection Time: <\/b> 2022-06-23 07:26 UTC<br\/>  <b>Sensor: <\/b> NOAA-20 VIIRS<br\/> <b>Confidence: <\/b> Nominal<br\/>  <b>Day\/Night: <\/b> Night<br\/> <b>Scan: <\/b> 0.4 km<br\/> <b>Track: <\/b> 0.6 km<br\/> <b>FRP: <\/b> 1.21 MW<br\/> <b>Brightness: <\/b> 296.37 K" }, "geometry": { "type": "Point", "coordinates": [ -64.92183, 48.19094, 0.0 ] } },
{ "type": "Feature", "properties": { "Name": "Fire Detection Centroid ", "Description": "<b>Latitude: <\/b> 18.92976<br\/>  <b>Longitude: <\/b> -70.35332<br\/>  <b>Detection Time: <\/b> 2022-06-23 05:54 UTC<br\/>  <b>Sensor: <\/b> NOAA-20 VIIRS<br\/> <b>Confidence: <\/b> Nominal<br\/>  <b>Day\/Night: <\/b> Night<br\/> <b>Scan: <\/b> 0.4 km<br\/> <b>Track: <\/b> 0.5 km<br\/> <b>FRP: <\/b> 17.3 MW<br\/> <b>Brightness: <\/b> 352.14 K" }, "geometry": { "type": "Point", "coordinates": [ -70.35332, 18.92976, 0.0 ] } },
{ "type": "Feature", "properties": { "Name": "Fire Detection Centroid ", "Description": "<b>Latitude: <\/b> 18.64024<br\/>  <b>Longitude: <\/b> -71.27499<br\/>  <b>Detection Time: <\/b> 2022-06-23 05:54 UTC<br\/>  <b>Sensor: <\/b> NOAA-20 VIIRS<br\/> <b>Confidence: <\/b> Nominal<br\/>  <b>Day\/Night: <\/b> Night<br\/> <b>Scan: <\/b> 0.5 km<br\/> <b>Track: <\/b> 0.5 km<br\/> <b>FRP: <\/b> 1.2 MW<br\/> <b>Brightness: <\/b> 300.72 K" }, "geometry": { "type": "Point", "coordinates": [ -71.27499, 18.64024, 0.0 ] } },
{ "type": "Feature", "properties": { "Name": "Fire Detection Centroid ", "Description": "<b>Latitude: <\/b> 48.18613<br\/>  <b>Longitude: <\/b> -64.92349<br\/>  <b>Detection Time: <\/b> 2022-06-23 05:46 UTC<br\/>  <b>Sensor: <\/b> NOAA-20 VIIRS<br\/> <b>Confidence: <\/b> Nominal<br\/>  <b>Day\/Night: <\/b> Night<br\/> <b>Scan: <\/b> 0.5 km<br\/> <b>Track: <\/b> 0.5 km<br\/> <b>FRP: <\/b> 1.51 MW<br\/> <b>Brightness: <\/b> 302.65 K" }, "geometry": { "type": "Point", "coordinates": [ -64.92349, 48.18613, 0.0 ] } }
]
}
