{
"type": "FeatureCollection",
"crs": { "type": "name", "properties": { "name": "urn:ogc:def:crs:OGC:1.3:CRS84" } },
"features": [
{ "type": "Feature", "properties": { "Name": "Fire Detection Centroid ", "Description": "<b>Latitude: <\/b> 45.28197<br\/>  <b>Longitude: <\/b> -66.01556<br\/>  <b>Detection Time: <\/b> 2024-05-27 05:23 UTC<br\/>  <b>Sensor: <\/b> NOAA-20 VIIRS<br\/> <b>Confidence: <\/b> Nominal<br\/>  <b>Day\/Night: <\/b> Night<br\/> <b>Scan: <\/b> 0.5 km<br\/> <b>Track: <\/b> 0.66 km<br\/> <b>FRP: <\/b> 1.35 MW<br\/> <b>Brightness: <\/b> 297.6 K" }, "geometry": { "type": "Point", "coordinates": [ -66.01556, 45.28197, 0.0 ] } },
{ "type": "Feature", "properties": { "Name": "Fire Detection Centroid ", "Description": "<b>Latitude: <\/b> 45.28154<br\/>  <b>Longitude: <\/b> -66.01327<br\/>  <b>Detection Time: <\/b> 2024-05-27 05:23 UTC<br\/>  <b>Sensor: <\/b> NOAA-20 VIIRS<br\/> <b>Confidence: <\/b> Nominal<br\/>  <b>Day\/Night: <\/b> Night<br\/> <b>Scan: <\/b> 0.5 km<br\/> <b>Track: <\/b> 0.66 km<br\/> <b>FRP: <\/b> 1.49 MW<br\/> <b>Brightness: <\/b> 298.83 K" }, "geometry": { "type": "Point", "coordinates": [ -66.01327, 45.28154, 0.0 ] } }
]
}
