{
"type": "FeatureCollection",
"crs": { "type": "name", "properties": { "name": "urn:ogc:def:crs:OGC:1.3:CRS84" } },
"features": [
{ "type": "Feature", "properties": { "Name": "Fire Detection Centroid ", "Description": "<b>Latitude: <\/b> 46.57636<br\/>  <b>Longitude: <\/b> -80.78532<br\/>  <b>Detection Time: <\/b> 2023-07-29 16:55 UTC<br\/>  <b>Sensor: <\/b> NOAA-20 VIIRS<br\/> <b>Confidence: <\/b> Nominal<br\/>  <b>Day\/Night: <\/b> Day<br\/> <b>Scan: <\/b> 0.6 km<br\/> <b>Track: <\/b> 0.7 km<br\/> <b>FRP: <\/b> 10.05 MW<br\/> <b>Brightness: <\/b> 352.44 K" }, "geometry": { "type": "Point", "coordinates": [ -80.78532, 46.57636, 0.0 ] } },
{ "type": "Feature", "properties": { "Name": "Fire Detection Centroid ", "Description": "<b>Latitude: <\/b> 46.57376<br\/>  <b>Longitude: <\/b> -80.79272<br\/>  <b>Detection Time: <\/b> 2023-07-29 16:55 UTC<br\/>  <b>Sensor: <\/b> NOAA-20 VIIRS<br\/> <b>Confidence: <\/b> Nominal<br\/>  <b>Day\/Night: <\/b> Day<br\/> <b>Scan: <\/b> 0.6 km<br\/> <b>Track: <\/b> 0.7 km<br\/> <b>FRP: <\/b> 10.05 MW<br\/> <b>Brightness: <\/b> 335.96 K" }, "geometry": { "type": "Point", "coordinates": [ -80.79272, 46.57376, 0.0 ] } },
{ "type": "Feature", "properties": { "Name": "Fire Detection Centroid ", "Description": "<b>Latitude: <\/b> 19.597<br\/>  <b>Longitude: <\/b> -155.50435<br\/>  <b>Detection Time: <\/b> 2023-07-29 12:21 UTC<br\/>  <b>Sensor: <\/b> NOAA-20 VIIRS<br\/> <b>Confidence: <\/b> Nominal<br\/>  <b>Day\/Night: <\/b> Night<br\/> <b>Scan: <\/b> 0.4 km<br\/> <b>Track: <\/b> 0.44 km<br\/> <b>FRP: <\/b> 1.55 MW<br\/> <b>Brightness: <\/b> 299.25 K" }, "geometry": { "type": "Point", "coordinates": [ -155.50435, 19.597, 0.0 ] } },
{ "type": "Feature", "properties": { "Name": "Fire Detection Centroid ", "Description": "<b>Latitude: <\/b> 19.40502<br\/>  <b>Longitude: <\/b> -155.29112<br\/>  <b>Detection Time: <\/b> 2023-07-29 12:21 UTC<br\/>  <b>Sensor: <\/b> NOAA-20 VIIRS<br\/> <b>Confidence: <\/b> Nominal<br\/>  <b>Day\/Night: <\/b> Night<br\/> <b>Scan: <\/b> 0.42 km<br\/> <b>Track: <\/b> 0.45 km<br\/> <b>FRP: <\/b> 2.78 MW<br\/> <b>Brightness: <\/b> 304.32 K" }, "geometry": { "type": "Point", "coordinates": [ -155.29112, 19.40502, 0.0 ] } },
{ "type": "Feature", "properties": { "Name": "Fire Detection Centroid ", "Description": "<b>Latitude: <\/b> 19.40423<br\/>  <b>Longitude: <\/b> -155.28708<br\/>  <b>Detection Time: <\/b> 2023-07-29 12:21 UTC<br\/>  <b>Sensor: <\/b> NOAA-20 VIIRS<br\/> <b>Confidence: <\/b> Nominal<br\/>  <b>Day\/Night: <\/b> Night<br\/> <b>Scan: <\/b> 0.42 km<br\/> <b>Track: <\/b> 0.45 km<br\/> <b>FRP: <\/b> 2.78 MW<br\/> <b>Brightness: <\/b> 309.13 K" }, "geometry": { "type": "Point", "coordinates": [ -155.28708, 19.40423, 0.0 ] } }
]
}
