{
"type": "FeatureCollection",
"crs": { "type": "name", "properties": { "name": "urn:ogc:def:crs:OGC:1.3:CRS84" } },
"features": [
{ "type": "Feature", "properties": { "Name": "Fire Detection Centroid ", "Description": "<b>Latitude: <\/b> 40.17869<br\/>  <b>Longitude: <\/b> -123.45286<br\/>  <b>Detection Time: <\/b> 2023-01-17 10:51 UTC<br\/>  <b>Sensor: <\/b> NOAA-20 VIIRS<br\/> <b>Confidence: <\/b> Nominal<br\/>  <b>Day\/Night: <\/b> Night<br\/> <b>Scan: <\/b> 0.32 km<br\/> <b>Track: <\/b> 0.55 km<br\/> <b>FRP: <\/b> 0.83 MW<br\/> <b>Brightness: <\/b> 302.95 K" }, "geometry": { "type": "Point", "coordinates": [ -123.45286, 40.17869, 0.0 ] } },
{ "type": "Feature", "properties": { "Name": "Fire Detection Centroid ", "Description": "<b>Latitude: <\/b> 38.07289<br\/>  <b>Longitude: <\/b> -122.14175<br\/>  <b>Detection Time: <\/b> 2023-01-17 10:51 UTC<br\/>  <b>Sensor: <\/b> NOAA-20 VIIRS<br\/> <b>Confidence: <\/b> Nominal<br\/>  <b>Day\/Night: <\/b> Night<br\/> <b>Scan: <\/b> 0.43 km<br\/> <b>Track: <\/b> 0.62 km<br\/> <b>FRP: <\/b> 0.98 MW<br\/> <b>Brightness: <\/b> 298.43 K" }, "geometry": { "type": "Point", "coordinates": [ -122.14175, 38.07289, 0.0 ] } },
{ "type": "Feature", "properties": { "Name": "Fire Detection Centroid ", "Description": "<b>Latitude: <\/b> 38.07399<br\/>  <b>Longitude: <\/b> -122.13926<br\/>  <b>Detection Time: <\/b> 2023-01-17 10:51 UTC<br\/>  <b>Sensor: <\/b> NOAA-20 VIIRS<br\/> <b>Confidence: <\/b> Nominal<br\/>  <b>Day\/Night: <\/b> Night<br\/> <b>Scan: <\/b> 0.43 km<br\/> <b>Track: <\/b> 0.62 km<br\/> <b>FRP: <\/b> 1.26 MW<br\/> <b>Brightness: <\/b> 297.22 K" }, "geometry": { "type": "Point", "coordinates": [ -122.13926, 38.07399, 0.0 ] } }
]
}
