{
"type": "FeatureCollection",
"crs": { "type": "name", "properties": { "name": "urn:ogc:def:crs:OGC:1.3:CRS84" } },
"features": [
{ "type": "Feature", "properties": { "Name": "Fire Detection Centroid ", "Description": "<b>Latitude: <\/b> 19.40576<br\/>  <b>Longitude: <\/b> -155.28078<br\/>  <b>Detection Time: <\/b> 2023-03-16 11:13 UTC<br\/>  <b>Sensor: <\/b> NOAA-20 VIIRS<br\/> <b>Confidence: <\/b> Nominal<br\/>  <b>Day\/Night: <\/b> Night<br\/> <b>Scan: <\/b> 0.52 km<br\/> <b>Track: <\/b> 0.67 km<br\/> <b>FRP: <\/b> 2.32 MW<br\/> <b>Brightness: <\/b> 300.76 K" }, "geometry": { "type": "Point", "coordinates": [ -155.28078, 19.40576, 0.0 ] } },
{ "type": "Feature", "properties": { "Name": "Fire Detection Centroid ", "Description": "<b>Latitude: <\/b> 19.60008<br\/>  <b>Longitude: <\/b> -155.50536<br\/>  <b>Detection Time: <\/b> 2023-03-16 11:13 UTC<br\/>  <b>Sensor: <\/b> NOAA-20 VIIRS<br\/> <b>Confidence: <\/b> Nominal<br\/>  <b>Day\/Night: <\/b> Night<br\/> <b>Scan: <\/b> 0.55 km<br\/> <b>Track: <\/b> 0.68 km<br\/> <b>FRP: <\/b> 2.11 MW<br\/> <b>Brightness: <\/b> 295.36 K" }, "geometry": { "type": "Point", "coordinates": [ -155.50536, 19.60008, 0.0 ] } },
{ "type": "Feature", "properties": { "Name": "Fire Detection Centroid ", "Description": "<b>Latitude: <\/b> 45.22788<br\/>  <b>Longitude: <\/b> -123.1635<br\/>  <b>Detection Time: <\/b> 2023-03-16 11:04 UTC<br\/>  <b>Sensor: <\/b> NOAA-20 VIIRS<br\/> <b>Confidence: <\/b> Nominal<br\/>  <b>Day\/Night: <\/b> Night<br\/> <b>Scan: <\/b> 0.34 km<br\/> <b>Track: <\/b> 0.56 km<br\/> <b>FRP: <\/b> 1.97 MW<br\/> <b>Brightness: <\/b> 304.24 K" }, "geometry": { "type": "Point", "coordinates": [ -123.1635, 45.22788, 0.0 ] } },
{ "type": "Feature", "properties": { "Name": "Fire Detection Centroid ", "Description": "<b>Latitude: <\/b> 45.22903<br\/>  <b>Longitude: <\/b> -123.16757<br\/>  <b>Detection Time: <\/b> 2023-03-16 11:04 UTC<br\/>  <b>Sensor: <\/b> NOAA-20 VIIRS<br\/> <b>Confidence: <\/b> Nominal<br\/>  <b>Day\/Night: <\/b> Night<br\/> <b>Scan: <\/b> 0.34 km<br\/> <b>Track: <\/b> 0.56 km<br\/> <b>FRP: <\/b> 2.36 MW<br\/> <b>Brightness: <\/b> 327.59 K" }, "geometry": { "type": "Point", "coordinates": [ -123.16757, 45.22903, 0.0 ] } },
{ "type": "Feature", "properties": { "Name": "Fire Detection Centroid ", "Description": "<b>Latitude: <\/b> 47.5679<br\/>  <b>Longitude: <\/b> -122.34507<br\/>  <b>Detection Time: <\/b> 2023-03-16 11:02 UTC<br\/>  <b>Sensor: <\/b> NOAA-20 VIIRS<br\/> <b>Confidence: <\/b> Nominal<br\/>  <b>Day\/Night: <\/b> Night<br\/> <b>Scan: <\/b> 0.63 km<br\/> <b>Track: <\/b> 0.54 km<br\/> <b>FRP: <\/b> 0.97 MW<br\/> <b>Brightness: <\/b> 296.25 K" }, "geometry": { "type": "Point", "coordinates": [ -122.34507, 47.5679, 0.0 ] } }
]
}
