{
"type": "FeatureCollection",
"crs": { "type": "name", "properties": { "name": "urn:ogc:def:crs:OGC:1.3:CRS84" } },
"features": [
{ "type": "Feature", "properties": { "Name": "Fire Detection Centroid ", "Description": "<b>Latitude: <\/b> 19.40643<br\/>  <b>Longitude: <\/b> -155.28288<br\/>  <b>Detection Time: <\/b> 2023-11-21 11:23 UTC<br\/>  <b>Sensor: <\/b> NOAA-20 VIIRS<br\/> <b>Confidence: <\/b> Nominal<br\/>  <b>Day\/Night: <\/b> Night<br\/> <b>Scan: <\/b> 0.32 km<br\/> <b>Track: <\/b> 0.55 km<br\/> <b>FRP: <\/b> 4 MW<br\/> <b>Brightness: <\/b> 302.04 K" }, "geometry": { "type": "Point", "coordinates": [ -155.28288, 19.40643, 0.0 ] } },
{ "type": "Feature", "properties": { "Name": "Fire Detection Centroid ", "Description": "<b>Latitude: <\/b> 19.41126<br\/>  <b>Longitude: <\/b> -155.28484<br\/>  <b>Detection Time: <\/b> 2023-11-21 11:23 UTC<br\/>  <b>Sensor: <\/b> NOAA-20 VIIRS<br\/> <b>Confidence: <\/b> Nominal<br\/>  <b>Day\/Night: <\/b> Night<br\/> <b>Scan: <\/b> 0.32 km<br\/> <b>Track: <\/b> 0.55 km<br\/> <b>FRP: <\/b> 1.9 MW<br\/> <b>Brightness: <\/b> 308.22 K" }, "geometry": { "type": "Point", "coordinates": [ -155.28484, 19.41126, 0.0 ] } },
{ "type": "Feature", "properties": { "Name": "Fire Detection Centroid ", "Description": "<b>Latitude: <\/b> 19.41209<br\/>  <b>Longitude: <\/b> -155.28795<br\/>  <b>Detection Time: <\/b> 2023-11-21 11:23 UTC<br\/>  <b>Sensor: <\/b> NOAA-20 VIIRS<br\/> <b>Confidence: <\/b> Nominal<br\/>  <b>Day\/Night: <\/b> Night<br\/> <b>Scan: <\/b> 0.32 km<br\/> <b>Track: <\/b> 0.55 km<br\/> <b>FRP: <\/b> 1.96 MW<br\/> <b>Brightness: <\/b> 301.04 K" }, "geometry": { "type": "Point", "coordinates": [ -155.28795, 19.41209, 0.0 ] } },
{ "type": "Feature", "properties": { "Name": "Fire Detection Centroid ", "Description": "<b>Latitude: <\/b> 19.41177<br\/>  <b>Longitude: <\/b> -155.28506<br\/>  <b>Detection Time: <\/b> 2023-11-21 11:23 UTC<br\/>  <b>Sensor: <\/b> NOAA-20 VIIRS<br\/> <b>Confidence: <\/b> Nominal<br\/>  <b>Day\/Night: <\/b> Night<br\/> <b>Scan: <\/b> 0.32 km<br\/> <b>Track: <\/b> 0.55 km<br\/> <b>FRP: <\/b> 1.96 MW<br\/> <b>Brightness: <\/b> 310.13 K" }, "geometry": { "type": "Point", "coordinates": [ -155.28506, 19.41177, 0.0 ] } },
{ "type": "Feature", "properties": { "Name": "Fire Detection Centroid ", "Description": "<b>Latitude: <\/b> 19.41157<br\/>  <b>Longitude: <\/b> -155.28772<br\/>  <b>Detection Time: <\/b> 2023-11-21 11:23 UTC<br\/>  <b>Sensor: <\/b> NOAA-20 VIIRS<br\/> <b>Confidence: <\/b> Nominal<br\/>  <b>Day\/Night: <\/b> Night<br\/> <b>Scan: <\/b> 0.32 km<br\/> <b>Track: <\/b> 0.55 km<br\/> <b>FRP: <\/b> 1.9 MW<br\/> <b>Brightness: <\/b> 306.5 K" }, "geometry": { "type": "Point", "coordinates": [ -155.28772, 19.41157, 0.0 ] } }
]
}
