{
"type": "FeatureCollection",
"crs": { "type": "name", "properties": { "name": "urn:ogc:def:crs:OGC:1.3:CRS84" } },
"features": [
{ "type": "Feature", "properties": { "Name": "Fire Detection Centroid ", "Description": "<b>Latitude: <\/b> 45.84026<br\/>  <b>Longitude: <\/b> -73.25162<br\/>  <b>Detection Time: <\/b> 2023-02-12 05:59 UTC<br\/>  <b>Sensor: <\/b> NOAA-20 VIIRS<br\/> <b>Confidence: <\/b> Nominal<br\/>  <b>Day\/Night: <\/b> Night<br\/> <b>Scan: <\/b> 0.4 km<br\/> <b>Track: <\/b> 0.6 km<br\/> <b>FRP: <\/b> 0.88 MW<br\/> <b>Brightness: <\/b> 296.25 K" }, "geometry": { "type": "Point", "coordinates": [ -73.25162, 45.84026, 0.0 ] } }
]
}
