{
"type": "FeatureCollection",
"crs": { "type": "name", "properties": { "name": "urn:ogc:def:crs:OGC:1.3:CRS84" } },
"features": [
{ "type": "Feature", "properties": { "Name": "Fire Detection Centroid ", "Description": "<b>Latitude: <\/b> 46.72116<br\/>  <b>Longitude: <\/b> -64.35077<br\/>  <b>Detection Time: <\/b> 2023-07-24 16:48 UTC<br\/>  <b>Sensor: <\/b> NOAA-20 VIIRS<br\/> <b>Confidence: <\/b> Nominal<br\/>  <b>Day\/Night: <\/b> Day<br\/> <b>Scan: <\/b> 0.5 km<br\/> <b>Track: <\/b> 0.4 km<br\/> <b>FRP: <\/b> 7.02 MW<br\/> <b>Brightness: <\/b> 336.97 K" }, "geometry": { "type": "Point", "coordinates": [ -64.35077, 46.72116, 0.0 ] } },
{ "type": "Feature", "properties": { "Name": "Fire Detection Centroid ", "Description": "<b>Latitude: <\/b> 45.79728<br\/>  <b>Longitude: <\/b> -72.89417<br\/>  <b>Detection Time: <\/b> 2023-07-24 16:48 UTC<br\/>  <b>Sensor: <\/b> NOAA-20 VIIRS<br\/> <b>Confidence: <\/b> Nominal<br\/>  <b>Day\/Night: <\/b> Day<br\/> <b>Scan: <\/b> 0.4 km<br\/> <b>Track: <\/b> 0.6 km<br\/> <b>FRP: <\/b> 2.18 MW<br\/> <b>Brightness: <\/b> 336.21 K" }, "geometry": { "type": "Point", "coordinates": [ -72.89417, 45.79728, 0.0 ] } },
{ "type": "Feature", "properties": { "Name": "Fire Detection Centroid ", "Description": "<b>Latitude: <\/b> 45.83529<br\/>  <b>Longitude: <\/b> -73.2477<br\/>  <b>Detection Time: <\/b> 2023-07-24 16:48 UTC<br\/>  <b>Sensor: <\/b> NOAA-20 VIIRS<br\/> <b>Confidence: <\/b> Nominal<br\/>  <b>Day\/Night: <\/b> Day<br\/> <b>Scan: <\/b> 0.4 km<br\/> <b>Track: <\/b> 0.6 km<br\/> <b>FRP: <\/b> 2.63 MW<br\/> <b>Brightness: <\/b> 327.88 K" }, "geometry": { "type": "Point", "coordinates": [ -73.2477, 45.83529, 0.0 ] } },
{ "type": "Feature", "properties": { "Name": "Fire Detection Centroid ", "Description": "<b>Latitude: <\/b> 40.60973<br\/>  <b>Longitude: <\/b> -75.31915<br\/>  <b>Detection Time: <\/b> 2023-07-24 16:47 UTC<br\/>  <b>Sensor: <\/b> NOAA-20 VIIRS<br\/> <b>Confidence: <\/b> Nominal<br\/>  <b>Day\/Night: <\/b> Day<br\/> <b>Scan: <\/b> 0.7 km<br\/> <b>Track: <\/b> 0.7 km<br\/> <b>FRP: <\/b> 12.41 MW<br\/> <b>Brightness: <\/b> 326.93 K" }, "geometry": { "type": "Point", "coordinates": [ -75.31915, 40.60973, 0.0 ] } }
]
}
