{
"type": "FeatureCollection",
"crs": { "type": "name", "properties": { "name": "urn:ogc:def:crs:OGC:1.3:CRS84" } },
"features": [
{ "type": "Feature", "properties": { "Name": "Fire Detection Centroid ", "Description": "<b>Latitude: <\/b> 19.46284<br\/>  <b>Longitude: <\/b> -154.92677<br\/>  <b>Detection Time: <\/b> 2024-01-11 12:08 UTC<br\/>  <b>Sensor: <\/b> NOAA-20 VIIRS<br\/> <b>Confidence: <\/b> Nominal<br\/>  <b>Day\/Night: <\/b> Night<br\/> <b>Scan: <\/b> 0.44 km<br\/> <b>Track: <\/b> 0.38 km<br\/> <b>FRP: <\/b> 1.54 MW<br\/> <b>Brightness: <\/b> 312.81 K" }, "geometry": { "type": "Point", "coordinates": [ -154.92677, 19.46284, 0.0 ] } }
]
}
