{
"type": "FeatureCollection",
"crs": { "type": "name", "properties": { "name": "urn:ogc:def:crs:OGC:1.3:CRS84" } },
"features": [
{ "type": "Feature", "properties": { "Name": "Fire Detection Centroid ", "Description": "<b>Latitude: <\/b> 38.01681<br\/>  <b>Longitude: <\/b> -122.11304<br\/>  <b>Detection Time: <\/b> 2024-04-12 11:13 UTC<br\/>  <b>Sensor: <\/b> NOAA-20 VIIRS<br\/> <b>Confidence: <\/b> Nominal<br\/>  <b>Day\/Night: <\/b> Night<br\/> <b>Scan: <\/b> 0.76 km<br\/> <b>Track: <\/b> 0.77 km<br\/> <b>FRP: <\/b> 1.58 MW<br\/> <b>Brightness: <\/b> 297.37 K" }, "geometry": { "type": "Point", "coordinates": [ -122.11304, 38.01681, 0.0 ] } },
{ "type": "Feature", "properties": { "Name": "Fire Detection Centroid ", "Description": "<b>Latitude: <\/b> 38.07235<br\/>  <b>Longitude: <\/b> -122.14125<br\/>  <b>Detection Time: <\/b> 2024-04-12 11:13 UTC<br\/>  <b>Sensor: <\/b> NOAA-20 VIIRS<br\/> <b>Confidence: <\/b> Nominal<br\/>  <b>Day\/Night: <\/b> Night<br\/> <b>Scan: <\/b> 0.76 km<br\/> <b>Track: <\/b> 0.77 km<br\/> <b>FRP: <\/b> 1.01 MW<br\/> <b>Brightness: <\/b> 295.13 K" }, "geometry": { "type": "Point", "coordinates": [ -122.14125, 38.07235, 0.0 ] } },
{ "type": "Feature", "properties": { "Name": "Fire Detection Centroid ", "Description": "<b>Latitude: <\/b> 38.02696<br\/>  <b>Longitude: <\/b> -122.16414<br\/>  <b>Detection Time: <\/b> 2024-04-12 11:11 UTC<br\/>  <b>Sensor: <\/b> NOAA-20 VIIRS<br\/> <b>Confidence: <\/b> Nominal<br\/>  <b>Day\/Night: <\/b> Night<br\/> <b>Scan: <\/b> 0.8 km<br\/> <b>Track: <\/b> 0.8 km<br\/> <b>FRP: <\/b> 0.93 MW<br\/> <b>Brightness: <\/b> 295.13 K" }, "geometry": { "type": "Point", "coordinates": [ -122.16414, 38.02696, 0.0 ] } }
]
}
