{
"type": "FeatureCollection",
"crs": { "type": "name", "properties": { "name": "urn:ogc:def:crs:OGC:1.3:CRS84" } },
"features": [
{ "type": "Feature", "properties": { "Name": "Fire Detection Centroid ", "Description": "<b>Latitude: </b> 45.27896<br/>  <b>Longitude: </b> -66.01685<br/>  <b>Detection Time: </b> 2022-06-15 16:22 UTC<br/>  <b>Sensor: </b> NOAA-20 VIIRS<br/> <b>Confidence: </b> Nominal<br/>  <b>Day/Night: </b> Day<br/> <b>Scan: </b> 0.3 km<br/> <b>Track: </b> 0.6 km<br/> <b>FRP: </b> 3.23 MW<br/> <b>Brightness: </b> 339.28 K" }, "geometry": { "type": "Point", "coordinates": [ -66.01685, 45.27896, 0.0 ] } },
{ "type": "Feature", "properties": { "Name": "Fire Detection Centroid ", "Description": "<b>Latitude: </b> 45.27989<br/>  <b>Longitude: </b> -66.01716<br/>  <b>Detection Time: </b> 2022-06-15 16:22 UTC<br/>  <b>Sensor: </b> NOAA-20 VIIRS<br/> <b>Confidence: </b> Nominal<br/>  <b>Day/Night: </b> Day<br/> <b>Scan: </b> 0.3 km<br/> <b>Track: </b> 0.6 km<br/> <b>FRP: </b> 2.96 MW<br/> <b>Brightness: </b> 332.96 K" }, "geometry": { "type": "Point", "coordinates": [ -66.01716, 45.27989, 0.0 ] } }
]
}
