{
"type": "FeatureCollection",
"crs": { "type": "name", "properties": { "name": "urn:ogc:def:crs:OGC:1.3:CRS84" } },
"features": [
{ "type": "Feature", "properties": { "Name": "Fire Detection Centroid ", "Description": "<b>Latitude: <\/b> 19.59605<br\/>  <b>Longitude: <\/b> -155.50409<br\/>  <b>Detection Time: <\/b> 2023-03-25 11:45 UTC<br\/>  <b>Sensor: <\/b> NOAA-20 VIIRS<br\/> <b>Confidence: <\/b> Nominal<br\/>  <b>Day\/Night: <\/b> Night<br\/> <b>Scan: <\/b> 0.51 km<br\/> <b>Track: <\/b> 0.41 km<br\/> <b>FRP: <\/b> 2.35 MW<br\/> <b>Brightness: <\/b> 295.1 K" }, "geometry": { "type": "Point", "coordinates": [ -155.50409, 19.59605, 0.0 ] } },
{ "type": "Feature", "properties": { "Name": "Fire Detection Centroid ", "Description": "<b>Latitude: <\/b> 19.40875<br\/>  <b>Longitude: <\/b> -155.28043<br\/>  <b>Detection Time: <\/b> 2023-03-25 11:45 UTC<br\/>  <b>Sensor: <\/b> NOAA-20 VIIRS<br\/> <b>Confidence: <\/b> Nominal<br\/>  <b>Day\/Night: <\/b> Night<br\/> <b>Scan: <\/b> 0.49 km<br\/> <b>Track: <\/b> 0.41 km<br\/> <b>FRP: <\/b> 2.27 MW<br\/> <b>Brightness: <\/b> 295.73 K" }, "geometry": { "type": "Point", "coordinates": [ -155.28043, 19.40875, 0.0 ] } },
{ "type": "Feature", "properties": { "Name": "Fire Detection Centroid ", "Description": "<b>Latitude: <\/b> 19.40566<br\/>  <b>Longitude: <\/b> -155.28569<br\/>  <b>Detection Time: <\/b> 2023-03-25 11:45 UTC<br\/>  <b>Sensor: <\/b> NOAA-20 VIIRS<br\/> <b>Confidence: <\/b> Nominal<br\/>  <b>Day\/Night: <\/b> Night<br\/> <b>Scan: <\/b> 0.49 km<br\/> <b>Track: <\/b> 0.41 km<br\/> <b>FRP: <\/b> 1.58 MW<br\/> <b>Brightness: <\/b> 299.43 K" }, "geometry": { "type": "Point", "coordinates": [ -155.28569, 19.40566, 0.0 ] } },
{ "type": "Feature", "properties": { "Name": "Fire Detection Centroid ", "Description": "<b>Latitude: <\/b> 19.40504<br\/>  <b>Longitude: <\/b> -155.28104<br\/>  <b>Detection Time: <\/b> 2023-03-25 11:45 UTC<br\/>  <b>Sensor: <\/b> NOAA-20 VIIRS<br\/> <b>Confidence: <\/b> Nominal<br\/>  <b>Day\/Night: <\/b> Night<br\/> <b>Scan: <\/b> 0.49 km<br\/> <b>Track: <\/b> 0.41 km<br\/> <b>FRP: <\/b> 1.45 MW<br\/> <b>Brightness: <\/b> 299.15 K" }, "geometry": { "type": "Point", "coordinates": [ -155.28104, 19.40504, 0.0 ] } },
{ "type": "Feature", "properties": { "Name": "Fire Detection Centroid ", "Description": "<b>Latitude: <\/b> 19.40708<br\/>  <b>Longitude: <\/b> -155.28331<br\/>  <b>Detection Time: <\/b> 2023-03-25 11:45 UTC<br\/>  <b>Sensor: <\/b> NOAA-20 VIIRS<br\/> <b>Confidence: <\/b> Nominal<br\/>  <b>Day\/Night: <\/b> Night<br\/> <b>Scan: <\/b> 0.49 km<br\/> <b>Track: <\/b> 0.41 km<br\/> <b>FRP: <\/b> 2.71 MW<br\/> <b>Brightness: <\/b> 296.41 K" }, "geometry": { "type": "Point", "coordinates": [ -155.28331, 19.40708, 0.0 ] } },
{ "type": "Feature", "properties": { "Name": "Fire Detection Centroid ", "Description": "<b>Latitude: <\/b> 19.40643<br\/>  <b>Longitude: <\/b> -155.27867<br\/>  <b>Detection Time: <\/b> 2023-03-25 11:45 UTC<br\/>  <b>Sensor: <\/b> NOAA-20 VIIRS<br\/> <b>Confidence: <\/b> Nominal<br\/>  <b>Day\/Night: <\/b> Night<br\/> <b>Scan: <\/b> 0.49 km<br\/> <b>Track: <\/b> 0.41 km<br\/> <b>FRP: <\/b> 2.13 MW<br\/> <b>Brightness: <\/b> 300.23 K" }, "geometry": { "type": "Point", "coordinates": [ -155.27867, 19.40643, 0.0 ] } }
]
}
