{
"type": "FeatureCollection",
"crs": { "type": "name", "properties": { "name": "urn:ogc:def:crs:OGC:1.3:CRS84" } },
"features": [
{ "type": "Feature", "properties": { "Name": "Fire Detection Centroid ", "Description": "<b>Latitude: <\/b> 44.46047<br\/>  <b>Longitude: <\/b> -118.72223<br\/>  <b>Detection Time: <\/b> 2023-10-10 11:03 UTC<br\/>  <b>Sensor: <\/b> NOAA-20 VIIRS<br\/> <b>Confidence: <\/b> Nominal<br\/>  <b>Day\/Night: <\/b> Night<br\/> <b>Scan: <\/b> 0.6 km<br\/> <b>Track: <\/b> 0.7 km<br\/> <b>FRP: <\/b> 1.48 MW<br\/> <b>Brightness: <\/b> 299.37 K" }, "geometry": { "type": "Point", "coordinates": [ -118.72223, 44.46047, 0.0 ] } },
{ "type": "Feature", "properties": { "Name": "Fire Detection Centroid ", "Description": "<b>Latitude: <\/b> 44.46029<br\/>  <b>Longitude: <\/b> -118.72543<br\/>  <b>Detection Time: <\/b> 2023-10-10 11:02 UTC<br\/>  <b>Sensor: <\/b> NOAA-20 VIIRS<br\/> <b>Confidence: <\/b> Nominal<br\/>  <b>Day\/Night: <\/b> Night<br\/> <b>Scan: <\/b> 0.58 km<br\/> <b>Track: <\/b> 0.7 km<br\/> <b>FRP: <\/b> 1.49 MW<br\/> <b>Brightness: <\/b> 299.37 K" }, "geometry": { "type": "Point", "coordinates": [ -118.72543, 44.46029, 0.0 ] } }
]
}
