{
"type": "FeatureCollection",
"crs": { "type": "name", "properties": { "name": "urn:ogc:def:crs:OGC:1.3:CRS84" } },
"features": [
{ "type": "Feature", "properties": { "Name": "Fire Detection Centroid ", "Description": "<b>Latitude: <\/b> 20.86126<br\/>  <b>Longitude: <\/b> -156.4196<br\/>  <b>Detection Time: <\/b> 2023-05-05 12:14 UTC<br\/>  <b>Sensor: <\/b> NOAA-20 VIIRS<br\/> <b>Confidence: <\/b> Nominal<br\/>  <b>Day\/Night: <\/b> Night<br\/> <b>Scan: <\/b> 0.43 km<br\/> <b>Track: <\/b> 0.38 km<br\/> <b>FRP: <\/b> 0.4 MW<br\/> <b>Brightness: <\/b> 302.32 K" }, "geometry": { "type": "Point", "coordinates": [ -156.4196, 20.86126, 0.0 ] } },
{ "type": "Feature", "properties": { "Name": "Fire Detection Centroid ", "Description": "<b>Latitude: <\/b> 19.58736<br\/>  <b>Longitude: <\/b> -155.50424<br\/>  <b>Detection Time: <\/b> 2023-05-05 12:14 UTC<br\/>  <b>Sensor: <\/b> NOAA-20 VIIRS<br\/> <b>Confidence: <\/b> Nominal<br\/>  <b>Day\/Night: <\/b> Night<br\/> <b>Scan: <\/b> 0.49 km<br\/> <b>Track: <\/b> 0.4 km<br\/> <b>FRP: <\/b> 1.25 MW<br\/> <b>Brightness: <\/b> 295.52 K" }, "geometry": { "type": "Point", "coordinates": [ -155.50424, 19.58736, 0.0 ] } },
{ "type": "Feature", "properties": { "Name": "Fire Detection Centroid ", "Description": "<b>Latitude: <\/b> 19.59474<br\/>  <b>Longitude: <\/b> -155.50418<br\/>  <b>Detection Time: <\/b> 2023-05-05 12:14 UTC<br\/>  <b>Sensor: <\/b> NOAA-20 VIIRS<br\/> <b>Confidence: <\/b> Nominal<br\/>  <b>Day\/Night: <\/b> Night<br\/> <b>Scan: <\/b> 0.49 km<br\/> <b>Track: <\/b> 0.4 km<br\/> <b>FRP: <\/b> 0.93 MW<br\/> <b>Brightness: <\/b> 296.4 K" }, "geometry": { "type": "Point", "coordinates": [ -155.50418, 19.59474, 0.0 ] } },
{ "type": "Feature", "properties": { "Name": "Fire Detection Centroid ", "Description": "<b>Latitude: <\/b> 19.59834<br\/>  <b>Longitude: <\/b> -155.50327<br\/>  <b>Detection Time: <\/b> 2023-05-05 12:14 UTC<br\/>  <b>Sensor: <\/b> NOAA-20 VIIRS<br\/> <b>Confidence: <\/b> Nominal<br\/>  <b>Day\/Night: <\/b> Night<br\/> <b>Scan: <\/b> 0.49 km<br\/> <b>Track: <\/b> 0.4 km<br\/> <b>FRP: <\/b> 0.93 MW<br\/> <b>Brightness: <\/b> 297.07 K" }, "geometry": { "type": "Point", "coordinates": [ -155.50327, 19.59834, 0.0 ] } },
{ "type": "Feature", "properties": { "Name": "Fire Detection Centroid ", "Description": "<b>Latitude: <\/b> 20.08311<br\/>  <b>Longitude: <\/b> -155.86246<br\/>  <b>Detection Time: <\/b> 2023-05-05 12:14 UTC<br\/>  <b>Sensor: <\/b> NOAA-20 VIIRS<br\/> <b>Confidence: <\/b> Nominal<br\/>  <b>Day\/Night: <\/b> Night<br\/> <b>Scan: <\/b> 0.46 km<br\/> <b>Track: <\/b> 0.39 km<br\/> <b>FRP: <\/b> 13.32 MW<br\/> <b>Brightness: <\/b> 333.25 K" }, "geometry": { "type": "Point", "coordinates": [ -155.86246, 20.08311, 0.0 ] } }
]
}
