{
"type": "FeatureCollection",
"crs": { "type": "name", "properties": { "name": "urn:ogc:def:crs:OGC:1.3:CRS84" } },
"features": [
{ "type": "Feature", "properties": { "Name": "Fire Detection Centroid ", "Description": "<b>Latitude: <\/b> 18.45661<br\/>  <b>Longitude: <\/b> -66.15112<br\/>  <b>Detection Time: <\/b> 2023-11-22 06:00 UTC<br\/>  <b>Sensor: <\/b> NOAA-20 VIIRS<br\/> <b>Confidence: <\/b> Nominal<br\/>  <b>Day\/Night: <\/b> Night<br\/> <b>Scan: <\/b> 0.4 km<br\/> <b>Track: <\/b> 0.4 km<br\/> <b>FRP: <\/b> 1.03 MW<br\/> <b>Brightness: <\/b> 303.27 K" }, "geometry": { "type": "Point", "coordinates": [ -66.15112, 18.45661, 0.0 ] } },
{ "type": "Feature", "properties": { "Name": "Fire Detection Centroid ", "Description": "<b>Latitude: <\/b> 17.70053<br\/>  <b>Longitude: <\/b> -64.74955<br\/>  <b>Detection Time: <\/b> 2023-11-22 06:00 UTC<br\/>  <b>Sensor: <\/b> NOAA-20 VIIRS<br\/> <b>Confidence: <\/b> Nominal<br\/>  <b>Day\/Night: <\/b> Night<br\/> <b>Scan: <\/b> 0.4 km<br\/> <b>Track: <\/b> 0.4 km<br\/> <b>FRP: <\/b> 0.94 MW<br\/> <b>Brightness: <\/b> 307.04 K" }, "geometry": { "type": "Point", "coordinates": [ -64.74955, 17.70053, 0.0 ] } },
{ "type": "Feature", "properties": { "Name": "Fire Detection Centroid ", "Description": "<b>Latitude: <\/b> 18.00857<br\/>  <b>Longitude: <\/b> -66.65614<br\/>  <b>Detection Time: <\/b> 2023-11-22 06:00 UTC<br\/>  <b>Sensor: <\/b> NOAA-20 VIIRS<br\/> <b>Confidence: <\/b> Nominal<br\/>  <b>Day\/Night: <\/b> Night<br\/> <b>Scan: <\/b> 0.4 km<br\/> <b>Track: <\/b> 0.4 km<br\/> <b>FRP: <\/b> 0.49 MW<br\/> <b>Brightness: <\/b> 302.63 K" }, "geometry": { "type": "Point", "coordinates": [ -66.65614, 18.00857, 0.0 ] } }
]
}
