{
"type": "FeatureCollection",
"crs": { "type": "name", "properties": { "name": "urn:ogc:def:crs:OGC:1.3:CRS84" } },
"features": [
{ "type": "Feature", "properties": { "Name": "Fire Detection Centroid ", "Description": "<b>Latitude: <\/b> 18.92895<br\/>  <b>Longitude: <\/b> -70.3527<br\/>  <b>Detection Time: <\/b> 2022-11-25 05:47 UTC<br\/>  <b>Sensor: <\/b> NOAA-20 VIIRS<br\/> <b>Confidence: <\/b> Nominal<br\/>  <b>Day\/Night: <\/b> Night<br\/> <b>Scan: <\/b> 0.6 km<br\/> <b>Track: <\/b> 0.5 km<br\/> <b>FRP: <\/b> 3.81 MW<br\/> <b>Brightness: <\/b> 336.35 K" }, "geometry": { "type": "Point", "coordinates": [ -70.3527, 18.92895, 0.0 ] } },
{ "type": "Feature", "properties": { "Name": "Fire Detection Centroid ", "Description": "<b>Latitude: <\/b> 18.92956<br\/>  <b>Longitude: <\/b> -70.35812<br\/>  <b>Detection Time: <\/b> 2022-11-25 05:47 UTC<br\/>  <b>Sensor: <\/b> NOAA-20 VIIRS<br\/> <b>Confidence: <\/b> Nominal<br\/>  <b>Day\/Night: <\/b> Night<br\/> <b>Scan: <\/b> 0.6 km<br\/> <b>Track: <\/b> 0.5 km<br\/> <b>FRP: <\/b> 3.81 MW<br\/> <b>Brightness: <\/b> 303.85 K" }, "geometry": { "type": "Point", "coordinates": [ -70.35812, 18.92956, 0.0 ] } }
]
}
