{
"type": "FeatureCollection",
"crs": { "type": "name", "properties": { "name": "urn:ogc:def:crs:OGC:1.3:CRS84" } },
"features": [
{ "type": "Feature", "properties": { "Name": "Fire Detection Centroid ", "Description": "<b>Latitude: <\/b> 19.40724<br\/>  <b>Longitude: <\/b> -155.29155<br\/>  <b>Detection Time: <\/b> 2023-02-19 12:21 UTC<br\/>  <b>Sensor: <\/b> NOAA-20 VIIRS<br\/> <b>Confidence: <\/b> Nominal<br\/>  <b>Day\/Night: <\/b> Night<br\/> <b>Scan: <\/b> 0.4 km<br\/> <b>Track: <\/b> 0.45 km<br\/> <b>FRP: <\/b> 1.44 MW<br\/> <b>Brightness: <\/b> 296.33 K" }, "geometry": { "type": "Point", "coordinates": [ -155.29155, 19.40724, 0.0 ] } },
{ "type": "Feature", "properties": { "Name": "Fire Detection Centroid ", "Description": "<b>Latitude: <\/b> 19.40649<br\/>  <b>Longitude: <\/b> -155.28758<br\/>  <b>Detection Time: <\/b> 2023-02-19 12:21 UTC<br\/>  <b>Sensor: <\/b> NOAA-20 VIIRS<br\/> <b>Confidence: <\/b> Nominal<br\/>  <b>Day\/Night: <\/b> Night<br\/> <b>Scan: <\/b> 0.41 km<br\/> <b>Track: <\/b> 0.45 km<br\/> <b>FRP: <\/b> 1.02 MW<br\/> <b>Brightness: <\/b> 298.79 K" }, "geometry": { "type": "Point", "coordinates": [ -155.28758, 19.40649, 0.0 ] } }
]
}
