{
"type": "FeatureCollection",
"crs": { "type": "name", "properties": { "name": "urn:ogc:def:crs:OGC:1.3:CRS84" } },
"features": [
{ "type": "Feature", "properties": { "Name": "Fire Detection Centroid ", "Description": "<b>Latitude: <\/b> 19.2661<br\/>  <b>Longitude: <\/b> -69.89581<br\/>  <b>Detection Time: <\/b> 2023-04-24 05:36 UTC<br\/>  <b>Sensor: <\/b> NOAA-20 VIIRS<br\/> <b>Confidence: <\/b> Nominal<br\/>  <b>Day\/Night: <\/b> Night<br\/> <b>Scan: <\/b> 0.4 km<br\/> <b>Track: <\/b> 0.6 km<br\/> <b>FRP: <\/b> 0.49 MW<br\/> <b>Brightness: <\/b> 301.29 K" }, "geometry": { "type": "Point", "coordinates": [ -69.89581, 19.2661, 0.0 ] } }
]
}
