{
"type": "FeatureCollection",
"crs": { "type": "name", "properties": { "name": "urn:ogc:def:crs:OGC:1.3:CRS84" } },
"features": [
{ "type": "Feature", "properties": { "Name": "Fire Detection Centroid ", "Description": "<b>Latitude: <\/b> 42.55<br\/>  <b>Longitude: <\/b> -123.0125<br\/>  <b>Detection Time: <\/b> 2023-01-29 21:50 UTC<br\/>  <b>Sensor: <\/b> NOAA-20 VIIRS<br\/> <b>Confidence: <\/b> Nominal<br\/>  <b>Day\/Night: <\/b> Day<br\/> <b>Scan: <\/b> 0.33 km<br\/> <b>Track: <\/b> 0.55 km<br\/> <b>FRP: <\/b> 4.15 MW<br\/> <b>Brightness: <\/b> 327.9 K" }, "geometry": { "type": "Point", "coordinates": [ -123.0125, 42.55, 0.0 ] } },
{ "type": "Feature", "properties": { "Name": "Fire Detection Centroid ", "Description": "<b>Latitude: <\/b> 40.43258<br\/>  <b>Longitude: <\/b> -123.82278<br\/>  <b>Detection Time: <\/b> 2023-01-29 21:50 UTC<br\/>  <b>Sensor: <\/b> NOAA-20 VIIRS<br\/> <b>Confidence: <\/b> Nominal<br\/>  <b>Day\/Night: <\/b> Day<br\/> <b>Scan: <\/b> 0.58 km<br\/> <b>Track: <\/b> 0.52 km<br\/> <b>FRP: <\/b> 7.09 MW<br\/> <b>Brightness: <\/b> 336.87 K" }, "geometry": { "type": "Point", "coordinates": [ -123.82278, 40.43258, 0.0 ] } },
{ "type": "Feature", "properties": { "Name": "Fire Detection Centroid ", "Description": "<b>Latitude: <\/b> 42.54958<br\/>  <b>Longitude: <\/b> -123.02039<br\/>  <b>Detection Time: <\/b> 2023-01-29 21:50 UTC<br\/>  <b>Sensor: <\/b> NOAA-20 VIIRS<br\/> <b>Confidence: <\/b> Nominal<br\/>  <b>Day\/Night: <\/b> Day<br\/> <b>Scan: <\/b> 0.33 km<br\/> <b>Track: <\/b> 0.55 km<br\/> <b>FRP: <\/b> 3.52 MW<br\/> <b>Brightness: <\/b> 334.03 K" }, "geometry": { "type": "Point", "coordinates": [ -123.02039, 42.54958, 0.0 ] } },
{ "type": "Feature", "properties": { "Name": "Fire Detection Centroid ", "Description": "<b>Latitude: <\/b> 42.54734<br\/>  <b>Longitude: <\/b> -123.01836<br\/>  <b>Detection Time: <\/b> 2023-01-29 21:50 UTC<br\/>  <b>Sensor: <\/b> NOAA-20 VIIRS<br\/> <b>Confidence: <\/b> Nominal<br\/>  <b>Day\/Night: <\/b> Day<br\/> <b>Scan: <\/b> 0.33 km<br\/> <b>Track: <\/b> 0.55 km<br\/> <b>FRP: <\/b> 3.12 MW<br\/> <b>Brightness: <\/b> 339.15 K" }, "geometry": { "type": "Point", "coordinates": [ -123.01836, 42.54734, 0.0 ] } },
{ "type": "Feature", "properties": { "Name": "Fire Detection Centroid ", "Description": "<b>Latitude: <\/b> 33.33332<br\/>  <b>Longitude: <\/b> -115.56921<br\/>  <b>Detection Time: <\/b> 2023-01-29 21:46 UTC<br\/>  <b>Sensor: <\/b> NOAA-20 VIIRS<br\/> <b>Confidence: <\/b> Low<br\/>  <b>Day\/Night: <\/b> Day<br\/> <b>Scan: <\/b> 0.73 km<br\/> <b>Track: <\/b> 0.76 km<br\/> <b>FRP: <\/b> 21.36 MW<br\/> <b>Brightness: <\/b> 356.27 K" }, "geometry": { "type": "Point", "coordinates": [ -115.56921, 33.33332, 0.0 ] } },
{ "type": "Feature", "properties": { "Name": "Fire Detection Centroid ", "Description": "<b>Latitude: <\/b> 33.32815<br\/>  <b>Longitude: <\/b> -115.57784<br\/>  <b>Detection Time: <\/b> 2023-01-29 21:46 UTC<br\/>  <b>Sensor: <\/b> NOAA-20 VIIRS<br\/> <b>Confidence: <\/b> Nominal<br\/>  <b>Day\/Night: <\/b> Day<br\/> <b>Scan: <\/b> 0.73 km<br\/> <b>Track: <\/b> 0.76 km<br\/> <b>FRP: <\/b> 22.23 MW<br\/> <b>Brightness: <\/b> 344.4 K" }, "geometry": { "type": "Point", "coordinates": [ -115.57784, 33.32815, 0.0 ] } },
{ "type": "Feature", "properties": { "Name": "Fire Detection Centroid ", "Description": "<b>Latitude: <\/b> 33.32838<br\/>  <b>Longitude: <\/b> -115.57018<br\/>  <b>Detection Time: <\/b> 2023-01-29 21:46 UTC<br\/>  <b>Sensor: <\/b> NOAA-20 VIIRS<br\/> <b>Confidence: <\/b> Low<br\/>  <b>Day\/Night: <\/b> Day<br\/> <b>Scan: <\/b> 0.73 km<br\/> <b>Track: <\/b> 0.76 km<br\/> <b>FRP: <\/b> 27.42 MW<br\/> <b>Brightness: <\/b> 356.4 K" }, "geometry": { "type": "Point", "coordinates": [ -115.57018, 33.32838, 0.0 ] } },
{ "type": "Feature", "properties": { "Name": "Fire Detection Centroid ", "Description": "<b>Latitude: <\/b> 33.33313<br\/>  <b>Longitude: <\/b> -115.57684<br\/>  <b>Detection Time: <\/b> 2023-01-29 21:46 UTC<br\/>  <b>Sensor: <\/b> NOAA-20 VIIRS<br\/> <b>Confidence: <\/b> Nominal<br\/>  <b>Day\/Night: <\/b> Day<br\/> <b>Scan: <\/b> 0.73 km<br\/> <b>Track: <\/b> 0.76 km<br\/> <b>FRP: <\/b> 21.36 MW<br\/> <b>Brightness: <\/b> 351.52 K" }, "geometry": { "type": "Point", "coordinates": [ -115.57684, 33.33313, 0.0 ] } }
]
}
