{
"type": "FeatureCollection",
"crs": { "type": "name", "properties": { "name": "urn:ogc:def:crs:OGC:1.3:CRS84" } },
"features": [
{ "type": "Feature", "properties": { "Name": "Fire Detection Centroid ", "Description": "<b>Latitude: <\/b> 34.64071<br\/>  <b>Longitude: <\/b> -117.32534<br\/>  <b>Detection Time: <\/b> 2024-03-24 10:46 UTC<br\/>  <b>Sensor: <\/b> NOAA-20 VIIRS<br\/> <b>Confidence: <\/b> Nominal<br\/>  <b>Day\/Night: <\/b> Night<br\/> <b>Scan: <\/b> 0.8 km<br\/> <b>Track: <\/b> 0.8 km<br\/> <b>FRP: <\/b> 1.43 MW<br\/> <b>Brightness: <\/b> 297.3 K" }, "geometry": { "type": "Point", "coordinates": [ -117.32534, 34.64071, 0.0 ] } },
{ "type": "Feature", "properties": { "Name": "Fire Detection Centroid ", "Description": "<b>Latitude: <\/b> 34.31016<br\/>  <b>Longitude: <\/b> -119.27014<br\/>  <b>Detection Time: <\/b> 2024-03-24 10:46 UTC<br\/>  <b>Sensor: <\/b> NOAA-20 VIIRS<br\/> <b>Confidence: <\/b> Nominal<br\/>  <b>Day\/Night: <\/b> Night<br\/> <b>Scan: <\/b> 0.6 km<br\/> <b>Track: <\/b> 0.7 km<br\/> <b>FRP: <\/b> 0.61 MW<br\/> <b>Brightness: <\/b> 301.07 K" }, "geometry": { "type": "Point", "coordinates": [ -119.27014, 34.31016, 0.0 ] } },
{ "type": "Feature", "properties": { "Name": "Fire Detection Centroid ", "Description": "<b>Latitude: <\/b> 49.93791<br\/>  <b>Longitude: <\/b> -121.6275<br\/>  <b>Detection Time: <\/b> 2024-03-24 10:43 UTC<br\/>  <b>Sensor: <\/b> NOAA-20 VIIRS<br\/> <b>Confidence: <\/b> Nominal<br\/>  <b>Day\/Night: <\/b> Night<br\/> <b>Scan: <\/b> 0.6 km<br\/> <b>Track: <\/b> 0.4 km<br\/> <b>FRP: <\/b> 1.39 MW<br\/> <b>Brightness: <\/b> 312.56 K" }, "geometry": { "type": "Point", "coordinates": [ -121.6275, 49.93791, 0.0 ] } }
]
}
