{
"type": "FeatureCollection",
"crs": { "type": "name", "properties": { "name": "urn:ogc:def:crs:OGC:1.3:CRS84" } },
"features": [
{ "type": "Feature", "properties": { "Name": "Fire Detection Centroid ", "Description": "<b>Latitude: <\/b> 19.41204<br\/>  <b>Longitude: <\/b> -155.29422<br\/>  <b>Detection Time: <\/b> 2023-02-23 12:46 UTC<br\/>  <b>Sensor: <\/b> NOAA-20 VIIRS<br\/> <b>Confidence: <\/b> Nominal<br\/>  <b>Day\/Night: <\/b> Night<br\/> <b>Scan: <\/b> 0.52 km<br\/> <b>Track: <\/b> 0.67 km<br\/> <b>FRP: <\/b> 9.56 MW<br\/> <b>Brightness: <\/b> 297.61 K" }, "geometry": { "type": "Point", "coordinates": [ -155.29422, 19.41204, 0.0 ] } },
{ "type": "Feature", "properties": { "Name": "Fire Detection Centroid ", "Description": "<b>Latitude: <\/b> 19.4108<br\/>  <b>Longitude: <\/b> -155.28882<br\/>  <b>Detection Time: <\/b> 2023-02-23 12:46 UTC<br\/>  <b>Sensor: <\/b> NOAA-20 VIIRS<br\/> <b>Confidence: <\/b> High<br\/>  <b>Day\/Night: <\/b> Night<br\/> <b>Scan: <\/b> 0.52 km<br\/> <b>Track: <\/b> 0.67 km<br\/> <b>FRP: <\/b> 9.56 MW<br\/> <b>Brightness: <\/b> 367 K" }, "geometry": { "type": "Point", "coordinates": [ -155.28882, 19.4108, 0.0 ] } },
{ "type": "Feature", "properties": { "Name": "Fire Detection Centroid ", "Description": "<b>Latitude: <\/b> 19.40962<br\/>  <b>Longitude: <\/b> -155.28362<br\/>  <b>Detection Time: <\/b> 2023-02-23 12:46 UTC<br\/>  <b>Sensor: <\/b> NOAA-20 VIIRS<br\/> <b>Confidence: <\/b> Nominal<br\/>  <b>Day\/Night: <\/b> Night<br\/> <b>Scan: <\/b> 0.52 km<br\/> <b>Track: <\/b> 0.67 km<br\/> <b>FRP: <\/b> 11.91 MW<br\/> <b>Brightness: <\/b> 316.76 K" }, "geometry": { "type": "Point", "coordinates": [ -155.28362, 19.40962, 0.0 ] } },
{ "type": "Feature", "properties": { "Name": "Fire Detection Centroid ", "Description": "<b>Latitude: <\/b> 19.40477<br\/>  <b>Longitude: <\/b> -155.29004<br\/>  <b>Detection Time: <\/b> 2023-02-23 12:46 UTC<br\/>  <b>Sensor: <\/b> NOAA-20 VIIRS<br\/> <b>Confidence: <\/b> Nominal<br\/>  <b>Day\/Night: <\/b> Night<br\/> <b>Scan: <\/b> 0.52 km<br\/> <b>Track: <\/b> 0.67 km<br\/> <b>FRP: <\/b> 9.56 MW<br\/> <b>Brightness: <\/b> 338.92 K" }, "geometry": { "type": "Point", "coordinates": [ -155.29004, 19.40477, 0.0 ] } },
{ "type": "Feature", "properties": { "Name": "Fire Detection Centroid ", "Description": "<b>Latitude: <\/b> 42.63105<br\/>  <b>Longitude: <\/b> -122.89823<br\/>  <b>Detection Time: <\/b> 2023-02-23 10:57 UTC<br\/>  <b>Sensor: <\/b> NOAA-20 VIIRS<br\/> <b>Confidence: <\/b> Nominal<br\/>  <b>Day\/Night: <\/b> Night<br\/> <b>Scan: <\/b> 0.35 km<br\/> <b>Track: <\/b> 0.57 km<br\/> <b>FRP: <\/b> 0.85 MW<br\/> <b>Brightness: <\/b> 298.65 K" }, "geometry": { "type": "Point", "coordinates": [ -122.89823, 42.63105, 0.0 ] } },
{ "type": "Feature", "properties": { "Name": "Fire Detection Centroid ", "Description": "<b>Latitude: <\/b> 42.62977<br\/>  <b>Longitude: <\/b> -122.89357<br\/>  <b>Detection Time: <\/b> 2023-02-23 10:57 UTC<br\/>  <b>Sensor: <\/b> NOAA-20 VIIRS<br\/> <b>Confidence: <\/b> Nominal<br\/>  <b>Day\/Night: <\/b> Night<br\/> <b>Scan: <\/b> 0.35 km<br\/> <b>Track: <\/b> 0.57 km<br\/> <b>FRP: <\/b> 0.85 MW<br\/> <b>Brightness: <\/b> 310.72 K" }, "geometry": { "type": "Point", "coordinates": [ -122.89357, 42.62977, 0.0 ] } },
{ "type": "Feature", "properties": { "Name": "Fire Detection Centroid ", "Description": "<b>Latitude: <\/b> 42.62493<br\/>  <b>Longitude: <\/b> -122.89633<br\/>  <b>Detection Time: <\/b> 2023-02-23 10:57 UTC<br\/>  <b>Sensor: <\/b> NOAA-20 VIIRS<br\/> <b>Confidence: <\/b> Nominal<br\/>  <b>Day\/Night: <\/b> Night<br\/> <b>Scan: <\/b> 0.35 km<br\/> <b>Track: <\/b> 0.57 km<br\/> <b>FRP: <\/b> 2.13 MW<br\/> <b>Brightness: <\/b> 322.12 K" }, "geometry": { "type": "Point", "coordinates": [ -122.89633, 42.62493, 0.0 ] } },
{ "type": "Feature", "properties": { "Name": "Fire Detection Centroid ", "Description": "<b>Latitude: <\/b> 42.62629<br\/>  <b>Longitude: <\/b> -122.90126<br\/>  <b>Detection Time: <\/b> 2023-02-23 10:57 UTC<br\/>  <b>Sensor: <\/b> NOAA-20 VIIRS<br\/> <b>Confidence: <\/b> Nominal<br\/>  <b>Day\/Night: <\/b> Night<br\/> <b>Scan: <\/b> 0.35 km<br\/> <b>Track: <\/b> 0.57 km<br\/> <b>FRP: <\/b> 2.13 MW<br\/> <b>Brightness: <\/b> 325.32 K" }, "geometry": { "type": "Point", "coordinates": [ -122.90126, 42.62629, 0.0 ] } },
{ "type": "Feature", "properties": { "Name": "Fire Detection Centroid ", "Description": "<b>Latitude: <\/b> 38.07125<br\/>  <b>Longitude: <\/b> -122.14066<br\/>  <b>Detection Time: <\/b> 2023-02-23 10:57 UTC<br\/>  <b>Sensor: <\/b> NOAA-20 VIIRS<br\/> <b>Confidence: <\/b> Nominal<br\/>  <b>Day\/Night: <\/b> Night<br\/> <b>Scan: <\/b> 0.51 km<br\/> <b>Track: <\/b> 0.66 km<br\/> <b>FRP: <\/b> 0.85 MW<br\/> <b>Brightness: <\/b> 295.04 K" }, "geometry": { "type": "Point", "coordinates": [ -122.14066, 38.07125, 0.0 ] } }
]
}
