{
"type": "FeatureCollection",
"crs": { "type": "name", "properties": { "name": "urn:ogc:def:crs:OGC:1.3:CRS84" } },
"features": [
{ "type": "Feature", "properties": { "Name": "Fire Detection Centroid ", "Description": "<b>Latitude: <\/b> 18.58505<br\/>  <b>Longitude: <\/b> -69.26186<br\/>  <b>Detection Time: <\/b> 2024-06-01 18:27 UTC<br\/>  <b>Sensor: <\/b> NOAA-20 VIIRS<br\/> <b>Confidence: <\/b> Nominal<br\/>  <b>Day\/Night: <\/b> Day<br\/> <b>Scan: <\/b> 0.3 km<br\/> <b>Track: <\/b> 0.6 km<br\/> <b>FRP: <\/b> 3.8 MW<br\/> <b>Brightness: <\/b> 328.28 K" }, "geometry": { "type": "Point", "coordinates": [ -69.26186, 18.58505, 0.0 ] } },
{ "type": "Feature", "properties": { "Name": "Fire Detection Centroid ", "Description": "<b>Latitude: <\/b> 19.33855<br\/>  <b>Longitude: <\/b> -72.29405<br\/>  <b>Detection Time: <\/b> 2024-06-01 18:27 UTC<br\/>  <b>Sensor: <\/b> NOAA-20 VIIRS<br\/> <b>Confidence: <\/b> Nominal<br\/>  <b>Day\/Night: <\/b> Day<br\/> <b>Scan: <\/b> 0.5 km<br\/> <b>Track: <\/b> 0.5 km<br\/> <b>FRP: <\/b> 4.27 MW<br\/> <b>Brightness: <\/b> 330.41 K" }, "geometry": { "type": "Point", "coordinates": [ -72.29405, 19.33855, 0.0 ] } },
{ "type": "Feature", "properties": { "Name": "Fire Detection Centroid ", "Description": "<b>Latitude: <\/b> 42.54178<br\/>  <b>Longitude: <\/b> -71.59437<br\/>  <b>Detection Time: <\/b> 2024-06-01 16:53 UTC<br\/>  <b>Sensor: <\/b> NOAA-20 VIIRS<br\/> <b>Confidence: <\/b> Nominal<br\/>  <b>Day\/Night: <\/b> Day<br\/> <b>Scan: <\/b> 0.3 km<br\/> <b>Track: <\/b> 0.6 km<br\/> <b>FRP: <\/b> 4.59 MW<br\/> <b>Brightness: <\/b> 327.89 K" }, "geometry": { "type": "Point", "coordinates": [ -71.59437, 42.54178, 0.0 ] } },
{ "type": "Feature", "properties": { "Name": "Fire Detection Centroid ", "Description": "<b>Latitude: <\/b> 44.30935<br\/>  <b>Longitude: <\/b> -70.24493<br\/>  <b>Detection Time: <\/b> 2024-06-01 16:53 UTC<br\/>  <b>Sensor: <\/b> NOAA-20 VIIRS<br\/> <b>Confidence: <\/b> Nominal<br\/>  <b>Day\/Night: <\/b> Day<br\/> <b>Scan: <\/b> 0.5 km<br\/> <b>Track: <\/b> 0.5 km<br\/> <b>FRP: <\/b> 3.55 MW<br\/> <b>Brightness: <\/b> 326.1 K" }, "geometry": { "type": "Point", "coordinates": [ -70.24493, 44.30935, 0.0 ] } }
]
}
