{
"type": "FeatureCollection",
"crs": { "type": "name", "properties": { "name": "urn:ogc:def:crs:OGC:1.3:CRS84" } },
"features": [
{ "type": "Feature", "properties": { "Name": "Fire Detection Centroid ", "Description": "<b>Latitude: <\/b> 20.03992<br\/>  <b>Longitude: <\/b> -155.37898<br\/>  <b>Detection Time: <\/b> 2023-05-04 00:05 UTC<br\/>  <b>Sensor: <\/b> NOAA-20 VIIRS<br\/> <b>Confidence: <\/b> Nominal<br\/>  <b>Day\/Night: <\/b> Day<br\/> <b>Scan: <\/b> 0.54 km<br\/> <b>Track: <\/b> 0.51 km<br\/> <b>FRP: <\/b> 4.67 MW<br\/> <b>Brightness: <\/b> 329.85 K" }, "geometry": { "type": "Point", "coordinates": [ -155.37898, 20.03992, 0.0 ] } }
]
}
