{
"type": "FeatureCollection",
"crs": { "type": "name", "properties": { "name": "urn:ogc:def:crs:OGC:1.3:CRS84" } },
"features": [
{ "type": "Feature", "properties": { "Name": "Fire Detection Centroid ", "Description": "<b>Latitude: <\/b> 19.40411<br\/>  <b>Longitude: <\/b> -155.28119<br\/>  <b>Detection Time: <\/b> 2023-12-17 11:36 UTC<br\/>  <b>Sensor: <\/b> NOAA-20 VIIRS<br\/> <b>Confidence: <\/b> Nominal<br\/>  <b>Day\/Night: <\/b> Night<br\/> <b>Scan: <\/b> 0.4 km<br\/> <b>Track: <\/b> 0.44 km<br\/> <b>FRP: <\/b> 2.72 MW<br\/> <b>Brightness: <\/b> 299.93 K" }, "geometry": { "type": "Point", "coordinates": [ -155.28119, 19.40411, 0.0 ] } }
]
}
