{
"type": "FeatureCollection",
"crs": { "type": "name", "properties": { "name": "urn:ogc:def:crs:OGC:1.3:CRS84" } },
"features": [
{ "type": "Feature", "properties": { "Name": "Fire Detection Centroid ", "Description": "<b>Latitude: <\/b> 18.92792<br\/>  <b>Longitude: <\/b> -70.35558<br\/>  <b>Detection Time: <\/b> 2022-10-13 05:54 UTC<br\/>  <b>Sensor: <\/b> NOAA-20 VIIRS<br\/> <b>Confidence: <\/b> Nominal<br\/>  <b>Day\/Night: <\/b> Night<br\/> <b>Scan: <\/b> 0.4 km<br\/> <b>Track: <\/b> 0.5 km<br\/> <b>FRP: <\/b> 14.8 MW<br\/> <b>Brightness: <\/b> 340.24 K" }, "geometry": { "type": "Point", "coordinates": [ -70.35558, 18.92792, 0.0 ] } },
{ "type": "Feature", "properties": { "Name": "Fire Detection Centroid ", "Description": "<b>Latitude: <\/b> 18.92739<br\/>  <b>Longitude: <\/b> -70.35131<br\/>  <b>Detection Time: <\/b> 2022-10-13 05:54 UTC<br\/>  <b>Sensor: <\/b> NOAA-20 VIIRS<br\/> <b>Confidence: <\/b> Nominal<br\/>  <b>Day\/Night: <\/b> Night<br\/> <b>Scan: <\/b> 0.4 km<br\/> <b>Track: <\/b> 0.5 km<br\/> <b>FRP: <\/b> 10.07 MW<br\/> <b>Brightness: <\/b> 329.51 K" }, "geometry": { "type": "Point", "coordinates": [ -70.35131, 18.92739, 0.0 ] } },
{ "type": "Feature", "properties": { "Name": "Fire Detection Centroid ", "Description": "<b>Latitude: <\/b> 18.93219<br\/>  <b>Longitude: <\/b> -70.35522<br\/>  <b>Detection Time: <\/b> 2022-10-13 05:54 UTC<br\/>  <b>Sensor: <\/b> NOAA-20 VIIRS<br\/> <b>Confidence: <\/b> Nominal<br\/>  <b>Day\/Night: <\/b> Night<br\/> <b>Scan: <\/b> 0.4 km<br\/> <b>Track: <\/b> 0.5 km<br\/> <b>FRP: <\/b> 0.96 MW<br\/> <b>Brightness: <\/b> 303.96 K" }, "geometry": { "type": "Point", "coordinates": [ -70.35522, 18.93219, 0.0 ] } }
]
}
