{
"type": "FeatureCollection",
"crs": { "type": "name", "properties": { "name": "urn:ogc:def:crs:OGC:1.3:CRS84" } },
"features": [
{ "type": "Feature", "properties": { "Name": "Fire Detection Centroid ", "Description": "<b>Latitude: <\/b> 49.16784<br\/>  <b>Longitude: <\/b> -124.07449<br\/>  <b>Detection Time: <\/b> 2023-12-03 22:18 UTC<br\/>  <b>Sensor: <\/b> NOAA-20 VIIRS<br\/> <b>Confidence: <\/b> Nominal<br\/>  <b>Day\/Night: <\/b> Day<br\/> <b>Scan: <\/b> 0.66 km<br\/> <b>Track: <\/b> 0.73 km<br\/> <b>FRP: <\/b> 6.25 MW<br\/> <b>Brightness: <\/b> 326.73 K" }, "geometry": { "type": "Point", "coordinates": [ -124.07449, 49.16784, 0.0 ] } },
{ "type": "Feature", "properties": { "Name": "Fire Detection Centroid ", "Description": "<b>Latitude: <\/b> 49.16098<br\/>  <b>Longitude: <\/b> -124.0692<br\/>  <b>Detection Time: <\/b> 2023-12-03 22:18 UTC<br\/>  <b>Sensor: <\/b> NOAA-20 VIIRS<br\/> <b>Confidence: <\/b> Low<br\/>  <b>Day\/Night: <\/b> Day<br\/> <b>Scan: <\/b> 0.66 km<br\/> <b>Track: <\/b> 0.73 km<br\/> <b>FRP: <\/b> 14.85 MW<br\/> <b>Brightness: <\/b> 356 K" }, "geometry": { "type": "Point", "coordinates": [ -124.0692, 49.16098, 0.0 ] } }
]
}
