{
"type": "FeatureCollection",
"crs": { "type": "name", "properties": { "name": "urn:ogc:def:crs:OGC:1.3:CRS84" } },
"features": [
{ "type": "Feature", "properties": { "Name": "Fire Detection Centroid ", "Description": "<b>Latitude: <\/b> 49.35301<br\/>  <b>Longitude: <\/b> -122.01292<br\/>  <b>Detection Time: <\/b> 2023-06-05 22:12 UTC<br\/>  <b>Sensor: <\/b> NOAA-20 VIIRS<br\/> <b>Confidence: <\/b> High<br\/>  <b>Day\/Night: <\/b> Day<br\/> <b>Scan: <\/b> 0.68 km<br\/> <b>Track: <\/b> 0.74 km<br\/> <b>FRP: <\/b> 23.34 MW<br\/> <b>Brightness: <\/b> 367 K" }, "geometry": { "type": "Point", "coordinates": [ -122.01292, 49.35301, 0.0 ] } },
{ "type": "Feature", "properties": { "Name": "Fire Detection Centroid ", "Description": "<b>Latitude: <\/b> 49.28362<br\/>  <b>Longitude: <\/b> -124.6069<br\/>  <b>Detection Time: <\/b> 2023-06-05 22:12 UTC<br\/>  <b>Sensor: <\/b> NOAA-20 VIIRS<br\/> <b>Confidence: <\/b> Nominal<br\/>  <b>Day\/Night: <\/b> Day<br\/> <b>Scan: <\/b> 0.52 km<br\/> <b>Track: <\/b> 0.67 km<br\/> <b>FRP: <\/b> 133.58 MW<br\/> <b>Brightness: <\/b> 346.12 K" }, "geometry": { "type": "Point", "coordinates": [ -124.6069, 49.28362, 0.0 ] } },
{ "type": "Feature", "properties": { "Name": "Fire Detection Centroid ", "Description": "<b>Latitude: <\/b> 49.48966<br\/>  <b>Longitude: <\/b> -121.9902<br\/>  <b>Detection Time: <\/b> 2023-06-05 22:12 UTC<br\/>  <b>Sensor: <\/b> NOAA-20 VIIRS<br\/> <b>Confidence: <\/b> Nominal<br\/>  <b>Day\/Night: <\/b> Day<br\/> <b>Scan: <\/b> 0.69 km<br\/> <b>Track: <\/b> 0.74 km<br\/> <b>FRP: <\/b> 22.61 MW<br\/> <b>Brightness: <\/b> 353.38 K" }, "geometry": { "type": "Point", "coordinates": [ -121.9902, 49.48966, 0.0 ] } },
{ "type": "Feature", "properties": { "Name": "Fire Detection Centroid ", "Description": "<b>Latitude: <\/b> 49.48258<br\/>  <b>Longitude: <\/b> -121.98031<br\/>  <b>Detection Time: <\/b> 2023-06-05 22:12 UTC<br\/>  <b>Sensor: <\/b> NOAA-20 VIIRS<br\/> <b>Confidence: <\/b> Nominal<br\/>  <b>Day\/Night: <\/b> Day<br\/> <b>Scan: <\/b> 0.69 km<br\/> <b>Track: <\/b> 0.74 km<br\/> <b>FRP: <\/b> 9.23 MW<br\/> <b>Brightness: <\/b> 325.75 K" }, "geometry": { "type": "Point", "coordinates": [ -121.98031, 49.48258, 0.0 ] } },
{ "type": "Feature", "properties": { "Name": "Fire Detection Centroid ", "Description": "<b>Latitude: <\/b> 49.4825<br\/>  <b>Longitude: <\/b> -121.97581<br\/>  <b>Detection Time: <\/b> 2023-06-05 22:12 UTC<br\/>  <b>Sensor: <\/b> NOAA-20 VIIRS<br\/> <b>Confidence: <\/b> Nominal<br\/>  <b>Day\/Night: <\/b> Day<br\/> <b>Scan: <\/b> 0.69 km<br\/> <b>Track: <\/b> 0.74 km<br\/> <b>FRP: <\/b> 9.23 MW<br\/> <b>Brightness: <\/b> 344.1 K" }, "geometry": { "type": "Point", "coordinates": [ -121.97581, 49.4825, 0.0 ] } },
{ "type": "Feature", "properties": { "Name": "Fire Detection Centroid ", "Description": "<b>Latitude: <\/b> 49.3526<br\/>  <b>Longitude: <\/b> -122.0236<br\/>  <b>Detection Time: <\/b> 2023-06-05 22:12 UTC<br\/>  <b>Sensor: <\/b> NOAA-20 VIIRS<br\/> <b>Confidence: <\/b> Nominal<br\/>  <b>Day\/Night: <\/b> Day<br\/> <b>Scan: <\/b> 0.68 km<br\/> <b>Track: <\/b> 0.74 km<br\/> <b>FRP: <\/b> 16.44 MW<br\/> <b>Brightness: <\/b> 355.09 K" }, "geometry": { "type": "Point", "coordinates": [ -122.0236, 49.3526, 0.0 ] } },
{ "type": "Feature", "properties": { "Name": "Fire Detection Centroid ", "Description": "<b>Latitude: <\/b> 49.35241<br\/>  <b>Longitude: <\/b> -122.01238<br\/>  <b>Detection Time: <\/b> 2023-06-05 22:12 UTC<br\/>  <b>Sensor: <\/b> NOAA-20 VIIRS<br\/> <b>Confidence: <\/b> Nominal<br\/>  <b>Day\/Night: <\/b> Day<br\/> <b>Scan: <\/b> 0.68 km<br\/> <b>Track: <\/b> 0.74 km<br\/> <b>FRP: <\/b> 16.44 MW<br\/> <b>Brightness: <\/b> 344.08 K" }, "geometry": { "type": "Point", "coordinates": [ -122.01238, 49.35241, 0.0 ] } },
{ "type": "Feature", "properties": { "Name": "Fire Detection Centroid ", "Description": "<b>Latitude: <\/b> 49.35315<br\/>  <b>Longitude: <\/b> -122.02417<br\/>  <b>Detection Time: <\/b> 2023-06-05 22:12 UTC<br\/>  <b>Sensor: <\/b> NOAA-20 VIIRS<br\/> <b>Confidence: <\/b> Nominal<br\/>  <b>Day\/Night: <\/b> Day<br\/> <b>Scan: <\/b> 0.68 km<br\/> <b>Track: <\/b> 0.74 km<br\/> <b>FRP: <\/b> 23.56 MW<br\/> <b>Brightness: <\/b> 354.92 K" }, "geometry": { "type": "Point", "coordinates": [ -122.02417, 49.35315, 0.0 ] } },
{ "type": "Feature", "properties": { "Name": "Fire Detection Centroid ", "Description": "<b>Latitude: <\/b> 47.05398<br\/>  <b>Longitude: <\/b> -122.5592<br\/>  <b>Detection Time: <\/b> 2023-06-05 22:10 UTC<br\/>  <b>Sensor: <\/b> NOAA-20 VIIRS<br\/> <b>Confidence: <\/b> Nominal<br\/>  <b>Day\/Night: <\/b> Day<br\/> <b>Scan: <\/b> 0.64 km<br\/> <b>Track: <\/b> 0.72 km<br\/> <b>FRP: <\/b> 4.7 MW<br\/> <b>Brightness: <\/b> 330.27 K" }, "geometry": { "type": "Point", "coordinates": [ -122.5592, 47.05398, 0.0 ] } }
]
}
