{
"type": "FeatureCollection",
"crs": { "type": "name", "properties": { "name": "urn:ogc:def:crs:OGC:1.3:CRS84" } },
"features": [
{ "type": "Feature", "properties": { "Name": "Fire Detection Centroid ", "Description": "<b>Latitude: <\/b> 32.25909<br\/>  <b>Longitude: <\/b> -114.92624<br\/>  <b>Detection Time: <\/b> 2024-01-16 21:47 UTC<br\/>  <b>Sensor: <\/b> NOAA-20 VIIRS<br\/> <b>Confidence: <\/b> Nominal<br\/>  <b>Day\/Night: <\/b> Day<br\/> <b>Scan: <\/b> 0.8 km<br\/> <b>Track: <\/b> 0.8 km<br\/> <b>FRP: <\/b> 4.74 MW<br\/> <b>Brightness: <\/b> 335.65 K" }, "geometry": { "type": "Point", "coordinates": [ -114.92624, 32.25909, 0.0 ] } },
{ "type": "Feature", "properties": { "Name": "Fire Detection Centroid ", "Description": "<b>Latitude: <\/b> 32.25931<br\/>  <b>Longitude: <\/b> -114.91776<br\/>  <b>Detection Time: <\/b> 2024-01-16 21:47 UTC<br\/>  <b>Sensor: <\/b> NOAA-20 VIIRS<br\/> <b>Confidence: <\/b> Nominal<br\/>  <b>Day\/Night: <\/b> Day<br\/> <b>Scan: <\/b> 0.8 km<br\/> <b>Track: <\/b> 0.8 km<br\/> <b>FRP: <\/b> 4.74 MW<br\/> <b>Brightness: <\/b> 327.19 K" }, "geometry": { "type": "Point", "coordinates": [ -114.91776, 32.25931, 0.0 ] } },
{ "type": "Feature", "properties": { "Name": "Fire Detection Centroid ", "Description": "<b>Latitude: <\/b> 32.47106<br\/>  <b>Longitude: <\/b> -114.92913<br\/>  <b>Detection Time: <\/b> 2024-01-16 21:47 UTC<br\/>  <b>Sensor: <\/b> NOAA-20 VIIRS<br\/> <b>Confidence: <\/b> Nominal<br\/>  <b>Day\/Night: <\/b> Day<br\/> <b>Scan: <\/b> 0.8 km<br\/> <b>Track: <\/b> 0.8 km<br\/> <b>FRP: <\/b> 9.16 MW<br\/> <b>Brightness: <\/b> 334.55 K" }, "geometry": { "type": "Point", "coordinates": [ -114.92913, 32.47106, 0.0 ] } },
{ "type": "Feature", "properties": { "Name": "Fire Detection Centroid ", "Description": "<b>Latitude: <\/b> 32.30443<br\/>  <b>Longitude: <\/b> -114.92236<br\/>  <b>Detection Time: <\/b> 2024-01-16 21:46 UTC<br\/>  <b>Sensor: <\/b> NOAA-20 VIIRS<br\/> <b>Confidence: <\/b> Nominal<br\/>  <b>Day\/Night: <\/b> Day<br\/> <b>Scan: <\/b> 0.78 km<br\/> <b>Track: <\/b> 0.78 km<br\/> <b>FRP: <\/b> 9.17 MW<br\/> <b>Brightness: <\/b> 334.55 K" }, "geometry": { "type": "Point", "coordinates": [ -114.92236, 32.30443, 0.0 ] } },
{ "type": "Feature", "properties": { "Name": "Fire Detection Centroid ", "Description": "<b>Latitude: <\/b> 32.30975<br\/>  <b>Longitude: <\/b> -114.91643<br\/>  <b>Detection Time: <\/b> 2024-01-16 21:46 UTC<br\/>  <b>Sensor: <\/b> NOAA-20 VIIRS<br\/> <b>Confidence: <\/b> Nominal<br\/>  <b>Day\/Night: <\/b> Day<br\/> <b>Scan: <\/b> 0.78 km<br\/> <b>Track: <\/b> 0.78 km<br\/> <b>FRP: <\/b> 4.75 MW<br\/> <b>Brightness: <\/b> 327.19 K" }, "geometry": { "type": "Point", "coordinates": [ -114.91643, 32.30975, 0.0 ] } },
{ "type": "Feature", "properties": { "Name": "Fire Detection Centroid ", "Description": "<b>Latitude: <\/b> 32.30951<br\/>  <b>Longitude: <\/b> -114.92491<br\/>  <b>Detection Time: <\/b> 2024-01-16 21:46 UTC<br\/>  <b>Sensor: <\/b> NOAA-20 VIIRS<br\/> <b>Confidence: <\/b> Nominal<br\/>  <b>Day\/Night: <\/b> Day<br\/> <b>Scan: <\/b> 0.78 km<br\/> <b>Track: <\/b> 0.78 km<br\/> <b>FRP: <\/b> 4.75 MW<br\/> <b>Brightness: <\/b> 335.65 K" }, "geometry": { "type": "Point", "coordinates": [ -114.92491, 32.30951, 0.0 ] } }
]
}
