{
"type": "FeatureCollection",
"crs": { "type": "name", "properties": { "name": "urn:ogc:def:crs:OGC:1.3:CRS84" } },
"features": [
{ "type": "Feature", "properties": { "Name": "Fire Detection Centroid ", "Description": "<b>Latitude: <\/b> 47.83267<br\/>  <b>Longitude: <\/b> -117.73104<br\/>  <b>Detection Time: <\/b> 2024-01-26 10:38 UTC<br\/>  <b>Sensor: <\/b> NOAA-20 VIIRS<br\/> <b>Confidence: <\/b> Nominal<br\/>  <b>Day\/Night: <\/b> Night<br\/> <b>Scan: <\/b> 0.53 km<br\/> <b>Track: <\/b> 0.5 km<br\/> <b>FRP: <\/b> 2.26 MW<br\/> <b>Brightness: <\/b> 309.13 K" }, "geometry": { "type": "Point", "coordinates": [ -117.73104, 47.83267, 0.0 ] } },
{ "type": "Feature", "properties": { "Name": "Fire Detection Centroid ", "Description": "<b>Latitude: <\/b> 46.65182<br\/>  <b>Longitude: <\/b> -111.18137<br\/>  <b>Detection Time: <\/b> 2024-01-26 10:37 UTC<br\/>  <b>Sensor: <\/b> NOAA-20 VIIRS<br\/> <b>Confidence: <\/b> Nominal<br\/>  <b>Day\/Night: <\/b> Night<br\/> <b>Scan: <\/b> 0.6 km<br\/> <b>Track: <\/b> 0.7 km<br\/> <b>FRP: <\/b> 2.12 MW<br\/> <b>Brightness: <\/b> 296.79 K" }, "geometry": { "type": "Point", "coordinates": [ -111.18137, 46.65182, 0.0 ] } },
{ "type": "Feature", "properties": { "Name": "Fire Detection Centroid ", "Description": "<b>Latitude: <\/b> 46.64923<br\/>  <b>Longitude: <\/b> -111.1525<br\/>  <b>Detection Time: <\/b> 2024-01-26 10:37 UTC<br\/>  <b>Sensor: <\/b> NOAA-20 VIIRS<br\/> <b>Confidence: <\/b> Nominal<br\/>  <b>Day\/Night: <\/b> Night<br\/> <b>Scan: <\/b> 0.6 km<br\/> <b>Track: <\/b> 0.7 km<br\/> <b>FRP: <\/b> 3.27 MW<br\/> <b>Brightness: <\/b> 320.58 K" }, "geometry": { "type": "Point", "coordinates": [ -111.1525, 46.64923, 0.0 ] } },
{ "type": "Feature", "properties": { "Name": "Fire Detection Centroid ", "Description": "<b>Latitude: <\/b> 46.4584<br\/>  <b>Longitude: <\/b> -111.29115<br\/>  <b>Detection Time: <\/b> 2024-01-26 10:37 UTC<br\/>  <b>Sensor: <\/b> NOAA-20 VIIRS<br\/> <b>Confidence: <\/b> Nominal<br\/>  <b>Day\/Night: <\/b> Night<br\/> <b>Scan: <\/b> 0.6 km<br\/> <b>Track: <\/b> 0.7 km<br\/> <b>FRP: <\/b> 2.65 MW<br\/> <b>Brightness: <\/b> 297.36 K" }, "geometry": { "type": "Point", "coordinates": [ -111.29115, 46.4584, 0.0 ] } },
{ "type": "Feature", "properties": { "Name": "Fire Detection Centroid ", "Description": "<b>Latitude: <\/b> 47.86364<br\/>  <b>Longitude: <\/b> -117.71278<br\/>  <b>Detection Time: <\/b> 2024-01-26 10:37 UTC<br\/>  <b>Sensor: <\/b> NOAA-20 VIIRS<br\/> <b>Confidence: <\/b> Nominal<br\/>  <b>Day\/Night: <\/b> Night<br\/> <b>Scan: <\/b> 0.5 km<br\/> <b>Track: <\/b> 0.5 km<br\/> <b>FRP: <\/b> 2.27 MW<br\/> <b>Brightness: <\/b> 309.13 K" }, "geometry": { "type": "Point", "coordinates": [ -117.71278, 47.86364, 0.0 ] } },
{ "type": "Feature", "properties": { "Name": "Fire Detection Centroid ", "Description": "<b>Latitude: <\/b> 46.56569<br\/>  <b>Longitude: <\/b> -111.22133<br\/>  <b>Detection Time: <\/b> 2024-01-26 10:36 UTC<br\/>  <b>Sensor: <\/b> NOAA-20 VIIRS<br\/> <b>Confidence: <\/b> Nominal<br\/>  <b>Day\/Night: <\/b> Night<br\/> <b>Scan: <\/b> 0.55 km<br\/> <b>Track: <\/b> 0.68 km<br\/> <b>FRP: <\/b> 3.28 MW<br\/> <b>Brightness: <\/b> 320.58 K" }, "geometry": { "type": "Point", "coordinates": [ -111.22133, 46.56569, 0.0 ] } },
{ "type": "Feature", "properties": { "Name": "Fire Detection Centroid ", "Description": "<b>Latitude: <\/b> 46.58043<br\/>  <b>Longitude: <\/b> -111.24424<br\/>  <b>Detection Time: <\/b> 2024-01-26 10:36 UTC<br\/>  <b>Sensor: <\/b> NOAA-20 VIIRS<br\/> <b>Confidence: <\/b> Nominal<br\/>  <b>Day\/Night: <\/b> Night<br\/> <b>Scan: <\/b> 0.55 km<br\/> <b>Track: <\/b> 0.68 km<br\/> <b>FRP: <\/b> 2.13 MW<br\/> <b>Brightness: <\/b> 296.79 K" }, "geometry": { "type": "Point", "coordinates": [ -111.24424, 46.58043, 0.0 ] } },
{ "type": "Feature", "properties": { "Name": "Fire Detection Centroid ", "Description": "<b>Latitude: <\/b> 46.56448<br\/>  <b>Longitude: <\/b> -111.21399<br\/>  <b>Detection Time: <\/b> 2024-01-26 10:36 UTC<br\/>  <b>Sensor: <\/b> NOAA-20 VIIRS<br\/> <b>Confidence: <\/b> Nominal<br\/>  <b>Day\/Night: <\/b> Night<br\/> <b>Scan: <\/b> 0.55 km<br\/> <b>Track: <\/b> 0.68 km<br\/> <b>FRP: <\/b> 2.66 MW<br\/> <b>Brightness: <\/b> 297.36 K" }, "geometry": { "type": "Point", "coordinates": [ -111.21399, 46.56448, 0.0 ] } }
]
}
