{
"type": "FeatureCollection",
"crs": { "type": "name", "properties": { "name": "urn:ogc:def:crs:OGC:1.3:CRS84" } },
"features": [
{ "type": "Feature", "properties": { "Name": "Fire Detection Centroid ", "Description": "<b>Latitude: <\/b> 18.44735<br\/>  <b>Longitude: <\/b> -69.11742<br\/>  <b>Detection Time: <\/b> 2024-06-15 17:23 UTC<br\/>  <b>Sensor: <\/b> NOAA-20 VIIRS<br\/> <b>Confidence: <\/b> Nominal<br\/>  <b>Day\/Night: <\/b> Day<br\/> <b>Scan: <\/b> 0.5 km<br\/> <b>Track: <\/b> 0.5 km<br\/> <b>FRP: <\/b> 6.16 MW<br\/> <b>Brightness: <\/b> 336.32 K" }, "geometry": { "type": "Point", "coordinates": [ -69.11742, 18.44735, 0.0 ] } },
{ "type": "Feature", "properties": { "Name": "Fire Detection Centroid ", "Description": "<b>Latitude: <\/b> 18.44423<br\/>  <b>Longitude: <\/b> -69.11559<br\/>  <b>Detection Time: <\/b> 2024-06-15 17:23 UTC<br\/>  <b>Sensor: <\/b> NOAA-20 VIIRS<br\/> <b>Confidence: <\/b> Nominal<br\/>  <b>Day\/Night: <\/b> Day<br\/> <b>Scan: <\/b> 0.5 km<br\/> <b>Track: <\/b> 0.5 km<br\/> <b>FRP: <\/b> 5.38 MW<br\/> <b>Brightness: <\/b> 337.31 K" }, "geometry": { "type": "Point", "coordinates": [ -69.11559, 18.44423, 0.0 ] } },
{ "type": "Feature", "properties": { "Name": "Fire Detection Centroid ", "Description": "<b>Latitude: <\/b> 17.98513<br\/>  <b>Longitude: <\/b> -71.42113<br\/>  <b>Detection Time: <\/b> 2024-06-15 17:23 UTC<br\/>  <b>Sensor: <\/b> NOAA-20 VIIRS<br\/> <b>Confidence: <\/b> Nominal<br\/>  <b>Day\/Night: <\/b> Day<br\/> <b>Scan: <\/b> 0.3 km<br\/> <b>Track: <\/b> 0.6 km<br\/> <b>FRP: <\/b> 2.14 MW<br\/> <b>Brightness: <\/b> 331.22 K" }, "geometry": { "type": "Point", "coordinates": [ -71.42113, 17.98513, 0.0 ] } },
{ "type": "Feature", "properties": { "Name": "Fire Detection Centroid ", "Description": "<b>Latitude: <\/b> 18.95975<br\/>  <b>Longitude: <\/b> -69.60558<br\/>  <b>Detection Time: <\/b> 2024-06-15 17:23 UTC<br\/>  <b>Sensor: <\/b> NOAA-20 VIIRS<br\/> <b>Confidence: <\/b> Nominal<br\/>  <b>Day\/Night: <\/b> Day<br\/> <b>Scan: <\/b> 0.5 km<br\/> <b>Track: <\/b> 0.5 km<br\/> <b>FRP: <\/b> 4.35 MW<br\/> <b>Brightness: <\/b> 335.07 K" }, "geometry": { "type": "Point", "coordinates": [ -69.60558, 18.95975, 0.0 ] } },
{ "type": "Feature", "properties": { "Name": "Fire Detection Centroid ", "Description": "<b>Latitude: <\/b> 17.91637<br\/>  <b>Longitude: <\/b> -71.35411<br\/>  <b>Detection Time: <\/b> 2024-06-15 17:23 UTC<br\/>  <b>Sensor: <\/b> NOAA-20 VIIRS<br\/> <b>Confidence: <\/b> Nominal<br\/>  <b>Day\/Night: <\/b> Day<br\/> <b>Scan: <\/b> 0.3 km<br\/> <b>Track: <\/b> 0.6 km<br\/> <b>FRP: <\/b> 1.74 MW<br\/> <b>Brightness: <\/b> 333.7 K" }, "geometry": { "type": "Point", "coordinates": [ -71.35411, 17.91637, 0.0 ] } },
{ "type": "Feature", "properties": { "Name": "Fire Detection Centroid ", "Description": "<b>Latitude: <\/b> 18.96417<br\/>  <b>Longitude: <\/b> -69.60654<br\/>  <b>Detection Time: <\/b> 2024-06-15 17:23 UTC<br\/>  <b>Sensor: <\/b> NOAA-20 VIIRS<br\/> <b>Confidence: <\/b> Nominal<br\/>  <b>Day\/Night: <\/b> Day<br\/> <b>Scan: <\/b> 0.5 km<br\/> <b>Track: <\/b> 0.5 km<br\/> <b>FRP: <\/b> 4.35 MW<br\/> <b>Brightness: <\/b> 336.89 K" }, "geometry": { "type": "Point", "coordinates": [ -69.60654, 18.96417, 0.0 ] } },
{ "type": "Feature", "properties": { "Name": "Fire Detection Centroid ", "Description": "<b>Latitude: <\/b> 18.95919<br\/>  <b>Longitude: <\/b> -69.95565<br\/>  <b>Detection Time: <\/b> 2024-06-15 17:23 UTC<br\/>  <b>Sensor: <\/b> NOAA-20 VIIRS<br\/> <b>Confidence: <\/b> Nominal<br\/>  <b>Day\/Night: <\/b> Day<br\/> <b>Scan: <\/b> 0.5 km<br\/> <b>Track: <\/b> 0.5 km<br\/> <b>FRP: <\/b> 7.47 MW<br\/> <b>Brightness: <\/b> 340.09 K" }, "geometry": { "type": "Point", "coordinates": [ -69.95565, 18.95919, 0.0 ] } },
{ "type": "Feature", "properties": { "Name": "Fire Detection Centroid ", "Description": "<b>Latitude: <\/b> 19.0423<br\/>  <b>Longitude: <\/b> -69.76783<br\/>  <b>Detection Time: <\/b> 2024-06-15 17:23 UTC<br\/>  <b>Sensor: <\/b> NOAA-20 VIIRS<br\/> <b>Confidence: <\/b> Nominal<br\/>  <b>Day\/Night: <\/b> Day<br\/> <b>Scan: <\/b> 0.5 km<br\/> <b>Track: <\/b> 0.5 km<br\/> <b>FRP: <\/b> 3.7 MW<br\/> <b>Brightness: <\/b> 331.82 K" }, "geometry": { "type": "Point", "coordinates": [ -69.76783, 19.0423, 0.0 ] } },
{ "type": "Feature", "properties": { "Name": "Fire Detection Centroid ", "Description": "<b>Latitude: <\/b> 17.89969<br\/>  <b>Longitude: <\/b> -71.30705<br\/>  <b>Detection Time: <\/b> 2024-06-15 17:23 UTC<br\/>  <b>Sensor: <\/b> NOAA-20 VIIRS<br\/> <b>Confidence: <\/b> High<br\/>  <b>Day\/Night: <\/b> Day<br\/> <b>Scan: <\/b> 0.3 km<br\/> <b>Track: <\/b> 0.6 km<br\/> <b>FRP: <\/b> 7.8 MW<br\/> <b>Brightness: <\/b> 367 K" }, "geometry": { "type": "Point", "coordinates": [ -71.30705, 17.89969, 0.0 ] } }
]
}
