{
"type": "FeatureCollection",
"crs": { "type": "name", "properties": { "name": "urn:ogc:def:crs:OGC:1.3:CRS84" } },
"features": [
{ "type": "Feature", "properties": { "Name": "Fire Detection Centroid ", "Description": "<b>Latitude: </b> 19.41062<br/>  <b>Longitude: </b> -155.2827<br/>  <b>Detection Time: </b> 2022-06-19 23:26 UTC<br/>  <b>Sensor: </b> NOAA-20 VIIRS<br/> <b>Confidence: </b> Nominal<br/>  <b>Day/Night: </b> Day<br/> <b>Scan: </b> 0.42 km<br/> <b>Track: </b> 0.37 km<br/> <b>FRP: </b> 21.28 MW<br/> <b>Brightness: </b> 353.99 K" }, "geometry": { "type": "Point", "coordinates": [ -155.2827, 19.41062, 0.0 ] } },
{ "type": "Feature", "properties": { "Name": "Fire Detection Centroid ", "Description": "<b>Latitude: </b> 19.40381<br/>  <b>Longitude: </b> -155.28149<br/>  <b>Detection Time: </b> 2022-06-19 23:26 UTC<br/>  <b>Sensor: </b> NOAA-20 VIIRS<br/> <b>Confidence: </b> Nominal<br/>  <b>Day/Night: </b> Day<br/> <b>Scan: </b> 0.42 km<br/> <b>Track: </b> 0.37 km<br/> <b>FRP: </b> 33.64 MW<br/> <b>Brightness: </b> 353.04 K" }, "geometry": { "type": "Point", "coordinates": [ -155.28149, 19.40381, 0.0 ] } },
{ "type": "Feature", "properties": { "Name": "Fire Detection Centroid ", "Description": "<b>Latitude: </b> 19.40317<br/>  <b>Longitude: </b> -155.2854<br/>  <b>Detection Time: </b> 2022-06-19 23:26 UTC<br/>  <b>Sensor: </b> NOAA-20 VIIRS<br/> <b>Confidence: </b> Low<br/>  <b>Day/Night: </b> Day<br/> <b>Scan: </b> 0.42 km<br/> <b>Track: </b> 0.37 km<br/> <b>FRP: </b> 47.29 MW<br/> <b>Brightness: </b> 367 K" }, "geometry": { "type": "Point", "coordinates": [ -155.2854, 19.40317, 0.0 ] } },
{ "type": "Feature", "properties": { "Name": "Fire Detection Centroid ", "Description": "<b>Latitude: </b> 19.40998<br/>  <b>Longitude: </b> -155.28658<br/>  <b>Detection Time: </b> 2022-06-19 23:26 UTC<br/>  <b>Sensor: </b> NOAA-20 VIIRS<br/> <b>Confidence: </b> Nominal<br/>  <b>Day/Night: </b> Day<br/> <b>Scan: </b> 0.42 km<br/> <b>Track: </b> 0.37 km<br/> <b>FRP: </b> 57 MW<br/> <b>Brightness: </b> 347.02 K" }, "geometry": { "type": "Point", "coordinates": [ -155.28658, 19.40998, 0.0 ] } },
{ "type": "Feature", "properties": { "Name": "Fire Detection Centroid ", "Description": "<b>Latitude: </b> 19.40658<br/>  <b>Longitude: </b> -155.28601<br/>  <b>Detection Time: </b> 2022-06-19 23:26 UTC<br/>  <b>Sensor: </b> NOAA-20 VIIRS<br/> <b>Confidence: </b> High<br/>  <b>Day/Night: </b> Day<br/> <b>Scan: </b> 0.42 km<br/> <b>Track: </b> 0.37 km<br/> <b>FRP: </b> 57 MW<br/> <b>Brightness: </b> 367 K" }, "geometry": { "type": "Point", "coordinates": [ -155.28601, 19.40658, 0.0 ] } },
{ "type": "Feature", "properties": { "Name": "Fire Detection Centroid ", "Description": "<b>Latitude: </b> 19.40721<br/>  <b>Longitude: </b> -155.28209<br/>  <b>Detection Time: </b> 2022-06-19 23:26 UTC<br/>  <b>Sensor: </b> NOAA-20 VIIRS<br/> <b>Confidence: </b> Nominal<br/>  <b>Day/Night: </b> Day<br/> <b>Scan: </b> 0.42 km<br/> <b>Track: </b> 0.37 km<br/> <b>FRP: </b> 21.28 MW<br/> <b>Brightness: </b> 348.63 K" }, "geometry": { "type": "Point", "coordinates": [ -155.28209, 19.40721, 0.0 ] } },
{ "type": "Feature", "properties": { "Name": "Fire Detection Centroid ", "Description": "<b>Latitude: </b> 19.40595<br/>  <b>Longitude: </b> -155.28987<br/>  <b>Detection Time: </b> 2022-06-19 23:26 UTC<br/>  <b>Sensor: </b> NOAA-20 VIIRS<br/> <b>Confidence: </b> Nominal<br/>  <b>Day/Night: </b> Day<br/> <b>Scan: </b> 0.42 km<br/> <b>Track: </b> 0.37 km<br/> <b>FRP: </b> 57 MW<br/> <b>Brightness: </b> 335.88 K" }, "geometry": { "type": "Point", "coordinates": [ -155.28987, 19.40595, 0.0 ] } },
{ "type": "Feature", "properties": { "Name": "Fire Detection Centroid ", "Description": "<b>Latitude: </b> 19.40784<br/>  <b>Longitude: </b> -155.2782<br/>  <b>Detection Time: </b> 2022-06-19 23:26 UTC<br/>  <b>Sensor: </b> NOAA-20 VIIRS<br/> <b>Confidence: </b> Low<br/>  <b>Day/Night: </b> Day<br/> <b>Scan: </b> 0.42 km<br/> <b>Track: </b> 0.37 km<br/> <b>FRP: </b> 21.28 MW<br/> <b>Brightness: </b> 367 K" }, "geometry": { "type": "Point", "coordinates": [ -155.2782, 19.40784, 0.0 ] } },
{ "type": "Feature", "properties": { "Name": "Fire Detection Centroid ", "Description": "<b>Latitude: </b> 19.41125<br/>  <b>Longitude: </b> -155.27881<br/>  <b>Detection Time: </b> 2022-06-19 23:26 UTC<br/>  <b>Sensor: </b> NOAA-20 VIIRS<br/> <b>Confidence: </b> Nominal<br/>  <b>Day/Night: </b> Day<br/> <b>Scan: </b> 0.42 km<br/> <b>Track: </b> 0.37 km<br/> <b>FRP: </b> 21.28 MW<br/> <b>Brightness: </b> 348.19 K" }, "geometry": { "type": "Point", "coordinates": [ -155.27881, 19.41125, 0.0 ] } }
]
}
