{
"type": "FeatureCollection",
"crs": { "type": "name", "properties": { "name": "urn:ogc:def:crs:OGC:1.3:CRS84" } },
"features": [
{ "type": "Feature", "properties": { "Name": "Fire Detection Centroid ", "Description": "<b>Latitude: <\/b> 49.75504<br\/>  <b>Longitude: <\/b> -123.97813<br\/>  <b>Detection Time: <\/b> 2023-03-13 21:46 UTC<br\/>  <b>Sensor: <\/b> NOAA-20 VIIRS<br\/> <b>Confidence: <\/b> Nominal<br\/>  <b>Day\/Night: <\/b> Day<br\/> <b>Scan: <\/b> 0.58 km<br\/> <b>Track: <\/b> 0.52 km<br\/> <b>FRP: <\/b> 5.11 MW<br\/> <b>Brightness: <\/b> 331.72 K" }, "geometry": { "type": "Point", "coordinates": [ -123.97813, 49.75504, 0.0 ] } },
{ "type": "Feature", "properties": { "Name": "Fire Detection Centroid ", "Description": "<b>Latitude: <\/b> 49.47911<br\/>  <b>Longitude: <\/b> -123.8494<br\/>  <b>Detection Time: <\/b> 2023-03-13 21:46 UTC<br\/>  <b>Sensor: <\/b> NOAA-20 VIIRS<br\/> <b>Confidence: <\/b> Nominal<br\/>  <b>Day\/Night: <\/b> Day<br\/> <b>Scan: <\/b> 0.58 km<br\/> <b>Track: <\/b> 0.52 km<br\/> <b>FRP: <\/b> 6.97 MW<br\/> <b>Brightness: <\/b> 337.36 K" }, "geometry": { "type": "Point", "coordinates": [ -123.8494, 49.47911, 0.0 ] } },
{ "type": "Feature", "properties": { "Name": "Fire Detection Centroid ", "Description": "<b>Latitude: <\/b> 49.75635<br\/>  <b>Longitude: <\/b> -123.97924<br\/>  <b>Detection Time: <\/b> 2023-03-13 21:46 UTC<br\/>  <b>Sensor: <\/b> NOAA-20 VIIRS<br\/> <b>Confidence: <\/b> Nominal<br\/>  <b>Day\/Night: <\/b> Day<br\/> <b>Scan: <\/b> 0.58 km<br\/> <b>Track: <\/b> 0.52 km<br\/> <b>FRP: <\/b> 3.7 MW<br\/> <b>Brightness: <\/b> 328.25 K" }, "geometry": { "type": "Point", "coordinates": [ -123.97924, 49.75635, 0.0 ] } },
{ "type": "Feature", "properties": { "Name": "Fire Detection Centroid ", "Description": "<b>Latitude: <\/b> 33.59305<br\/>  <b>Longitude: <\/b> -117.33697<br\/>  <b>Detection Time: <\/b> 2023-03-13 21:42 UTC<br\/>  <b>Sensor: <\/b> NOAA-20 VIIRS<br\/> <b>Confidence: <\/b> Nominal<br\/>  <b>Day\/Night: <\/b> Day<br\/> <b>Scan: <\/b> 0.47 km<br\/> <b>Track: <\/b> 0.64 km<br\/> <b>FRP: <\/b> 7.53 MW<br\/> <b>Brightness: <\/b> 331.94 K" }, "geometry": { "type": "Point", "coordinates": [ -117.33697, 33.59305, 0.0 ] } },
{ "type": "Feature", "properties": { "Name": "Fire Detection Centroid ", "Description": "<b>Latitude: <\/b> 33.59333<br\/>  <b>Longitude: <\/b> -117.33145<br\/>  <b>Detection Time: <\/b> 2023-03-13 21:42 UTC<br\/>  <b>Sensor: <\/b> NOAA-20 VIIRS<br\/> <b>Confidence: <\/b> Nominal<br\/>  <b>Day\/Night: <\/b> Day<br\/> <b>Scan: <\/b> 0.47 km<br\/> <b>Track: <\/b> 0.64 km<br\/> <b>FRP: <\/b> 7.19 MW<br\/> <b>Brightness: <\/b> 344.52 K" }, "geometry": { "type": "Point", "coordinates": [ -117.33145, 33.59333, 0.0 ] } }
]
}
