{
"type": "FeatureCollection",
"crs": { "type": "name", "properties": { "name": "urn:ogc:def:crs:OGC:1.3:CRS84" } },
"features": [
{ "type": "Feature", "properties": { "Name": "Fire Detection Centroid ", "Description": "<b>Latitude: <\/b> 39.16125<br\/>  <b>Longitude: <\/b> -121.75758<br\/>  <b>Detection Time: <\/b> 2024-02-12 21:44 UTC<br\/>  <b>Sensor: <\/b> NOAA-20 VIIRS<br\/> <b>Confidence: <\/b> Nominal<br\/>  <b>Day\/Night: <\/b> Day<br\/> <b>Scan: <\/b> 0.59 km<br\/> <b>Track: <\/b> 0.53 km<br\/> <b>FRP: <\/b> 7.06 MW<br\/> <b>Brightness: <\/b> 341.4 K" }, "geometry": { "type": "Point", "coordinates": [ -121.75758, 39.16125, 0.0 ] } },
{ "type": "Feature", "properties": { "Name": "Fire Detection Centroid ", "Description": "<b>Latitude: <\/b> 39.15873<br\/>  <b>Longitude: <\/b> -121.7586<br\/>  <b>Detection Time: <\/b> 2024-02-12 21:44 UTC<br\/>  <b>Sensor: <\/b> NOAA-20 VIIRS<br\/> <b>Confidence: <\/b> Nominal<br\/>  <b>Day\/Night: <\/b> Day<br\/> <b>Scan: <\/b> 0.59 km<br\/> <b>Track: <\/b> 0.53 km<br\/> <b>FRP: <\/b> 8.56 MW<br\/> <b>Brightness: <\/b> 345.46 K" }, "geometry": { "type": "Point", "coordinates": [ -121.7586, 39.15873, 0.0 ] } },
{ "type": "Feature", "properties": { "Name": "Fire Detection Centroid ", "Description": "<b>Latitude: <\/b> 39.25147<br\/>  <b>Longitude: <\/b> -121.77016<br\/>  <b>Detection Time: <\/b> 2024-02-12 21:43 UTC<br\/>  <b>Sensor: <\/b> NOAA-20 VIIRS<br\/> <b>Confidence: <\/b> Nominal<br\/>  <b>Day\/Night: <\/b> Day<br\/> <b>Scan: <\/b> 0.6 km<br\/> <b>Track: <\/b> 0.5 km<br\/> <b>FRP: <\/b> 8.56 MW<br\/> <b>Brightness: <\/b> 345.46 K" }, "geometry": { "type": "Point", "coordinates": [ -121.77016, 39.25147, 0.0 ] } },
{ "type": "Feature", "properties": { "Name": "Fire Detection Centroid ", "Description": "<b>Latitude: <\/b> 35.88026<br\/>  <b>Longitude: <\/b> -120.88749<br\/>  <b>Detection Time: <\/b> 2024-02-12 21:42 UTC<br\/>  <b>Sensor: <\/b> NOAA-20 VIIRS<br\/> <b>Confidence: <\/b> Nominal<br\/>  <b>Day\/Night: <\/b> Day<br\/> <b>Scan: <\/b> 0.6 km<br\/> <b>Track: <\/b> 0.5 km<br\/> <b>FRP: <\/b> 7.91 MW<br\/> <b>Brightness: <\/b> 338.6 K" }, "geometry": { "type": "Point", "coordinates": [ -120.88749, 35.88026, 0.0 ] } },
{ "type": "Feature", "properties": { "Name": "Fire Detection Centroid ", "Description": "<b>Latitude: <\/b> 35.8753<br\/>  <b>Longitude: <\/b> -120.88619<br\/>  <b>Detection Time: <\/b> 2024-02-12 21:42 UTC<br\/>  <b>Sensor: <\/b> NOAA-20 VIIRS<br\/> <b>Confidence: <\/b> Nominal<br\/>  <b>Day\/Night: <\/b> Day<br\/> <b>Scan: <\/b> 0.62 km<br\/> <b>Track: <\/b> 0.54 km<br\/> <b>FRP: <\/b> 7.92 MW<br\/> <b>Brightness: <\/b> 338.6 K" }, "geometry": { "type": "Point", "coordinates": [ -120.88619, 35.8753, 0.0 ] } },
{ "type": "Feature", "properties": { "Name": "Fire Detection Centroid ", "Description": "<b>Latitude: <\/b> 32.51707<br\/>  <b>Longitude: <\/b> -115.35294<br\/>  <b>Detection Time: <\/b> 2024-02-12 21:41 UTC<br\/>  <b>Sensor: <\/b> NOAA-20 VIIRS<br\/> <b>Confidence: <\/b> Nominal<br\/>  <b>Day\/Night: <\/b> Day<br\/> <b>Scan: <\/b> 0.6 km<br\/> <b>Track: <\/b> 0.7 km<br\/> <b>FRP: <\/b> 3.76 MW<br\/> <b>Brightness: <\/b> 333.25 K" }, "geometry": { "type": "Point", "coordinates": [ -115.35294, 32.51707, 0.0 ] } },
{ "type": "Feature", "properties": { "Name": "Fire Detection Centroid ", "Description": "<b>Latitude: <\/b> 32.5103<br\/>  <b>Longitude: <\/b> -115.3512<br\/>  <b>Detection Time: <\/b> 2024-02-12 21:40 UTC<br\/>  <b>Sensor: <\/b> NOAA-20 VIIRS<br\/> <b>Confidence: <\/b> Nominal<br\/>  <b>Day\/Night: <\/b> Day<br\/> <b>Scan: <\/b> 0.6 km<br\/> <b>Track: <\/b> 0.71 km<br\/> <b>FRP: <\/b> 3.77 MW<br\/> <b>Brightness: <\/b> 333.25 K" }, "geometry": { "type": "Point", "coordinates": [ -115.3512, 32.5103, 0.0 ] } }
]
}
