{
"type": "FeatureCollection",
"crs": { "type": "name", "properties": { "name": "urn:ogc:def:crs:OGC:1.3:CRS84" } },
"features": [
{ "type": "Feature", "properties": { "Name": "Fire Detection Centroid ", "Description": "<b>Latitude: <\/b> 18.53342<br\/>  <b>Longitude: <\/b> -72.5499<br\/>  <b>Detection Time: <\/b> 2022-12-16 05:54 UTC<br\/>  <b>Sensor: <\/b> NOAA-20 VIIRS<br\/> <b>Confidence: <\/b> Nominal<br\/>  <b>Day\/Night: <\/b> Night<br\/> <b>Scan: <\/b> 0.6 km<br\/> <b>Track: <\/b> 0.5 km<br\/> <b>FRP: <\/b> 0.88 MW<br\/> <b>Brightness: <\/b> 302.07 K" }, "geometry": { "type": "Point", "coordinates": [ -72.5499, 18.53342, 0.0 ] } },
{ "type": "Feature", "properties": { "Name": "Fire Detection Centroid ", "Description": "<b>Latitude: <\/b> 18.92944<br\/>  <b>Longitude: <\/b> -70.35146<br\/>  <b>Detection Time: <\/b> 2022-12-16 05:53 UTC<br\/>  <b>Sensor: <\/b> NOAA-20 VIIRS<br\/> <b>Confidence: <\/b> Nominal<br\/>  <b>Day\/Night: <\/b> Night<br\/> <b>Scan: <\/b> 0.4 km<br\/> <b>Track: <\/b> 0.5 km<br\/> <b>FRP: <\/b> 12.93 MW<br\/> <b>Brightness: <\/b> 327.88 K" }, "geometry": { "type": "Point", "coordinates": [ -70.35146, 18.92944, 0.0 ] } },
{ "type": "Feature", "properties": { "Name": "Fire Detection Centroid ", "Description": "<b>Latitude: <\/b> 19.24002<br\/>  <b>Longitude: <\/b> -70.88125<br\/>  <b>Detection Time: <\/b> 2022-12-16 05:53 UTC<br\/>  <b>Sensor: <\/b> NOAA-20 VIIRS<br\/> <b>Confidence: <\/b> Nominal<br\/>  <b>Day\/Night: <\/b> Night<br\/> <b>Scan: <\/b> 0.5 km<br\/> <b>Track: <\/b> 0.5 km<br\/> <b>FRP: <\/b> 0.74 MW<br\/> <b>Brightness: <\/b> 301 K" }, "geometry": { "type": "Point", "coordinates": [ -70.88125, 19.24002, 0.0 ] } },
{ "type": "Feature", "properties": { "Name": "Fire Detection Centroid ", "Description": "<b>Latitude: <\/b> 18.61847<br\/>  <b>Longitude: <\/b> -69.31659<br\/>  <b>Detection Time: <\/b> 2022-12-16 05:53 UTC<br\/>  <b>Sensor: <\/b> NOAA-20 VIIRS<br\/> <b>Confidence: <\/b> Nominal<br\/>  <b>Day\/Night: <\/b> Night<br\/> <b>Scan: <\/b> 0.6 km<br\/> <b>Track: <\/b> 0.4 km<br\/> <b>FRP: <\/b> 0.52 MW<br\/> <b>Brightness: <\/b> 300.8 K" }, "geometry": { "type": "Point", "coordinates": [ -69.31659, 18.61847, 0.0 ] } },
{ "type": "Feature", "properties": { "Name": "Fire Detection Centroid ", "Description": "<b>Latitude: <\/b> 18.61681<br\/>  <b>Longitude: <\/b> -69.31492<br\/>  <b>Detection Time: <\/b> 2022-12-16 05:53 UTC<br\/>  <b>Sensor: <\/b> NOAA-20 VIIRS<br\/> <b>Confidence: <\/b> Nominal<br\/>  <b>Day\/Night: <\/b> Night<br\/> <b>Scan: <\/b> 0.6 km<br\/> <b>Track: <\/b> 0.4 km<br\/> <b>FRP: <\/b> 1.65 MW<br\/> <b>Brightness: <\/b> 310.15 K" }, "geometry": { "type": "Point", "coordinates": [ -69.31492, 18.61681, 0.0 ] } },
{ "type": "Feature", "properties": { "Name": "Fire Detection Centroid ", "Description": "<b>Latitude: <\/b> 18.6145<br\/>  <b>Longitude: <\/b> -69.31717<br\/>  <b>Detection Time: <\/b> 2022-12-16 05:53 UTC<br\/>  <b>Sensor: <\/b> NOAA-20 VIIRS<br\/> <b>Confidence: <\/b> Nominal<br\/>  <b>Day\/Night: <\/b> Night<br\/> <b>Scan: <\/b> 0.6 km<br\/> <b>Track: <\/b> 0.4 km<br\/> <b>FRP: <\/b> 0.97 MW<br\/> <b>Brightness: <\/b> 304.27 K" }, "geometry": { "type": "Point", "coordinates": [ -69.31717, 18.6145, 0.0 ] } },
{ "type": "Feature", "properties": { "Name": "Fire Detection Centroid ", "Description": "<b>Latitude: <\/b> 18.92998<br\/>  <b>Longitude: <\/b> -70.35578<br\/>  <b>Detection Time: <\/b> 2022-12-16 05:53 UTC<br\/>  <b>Sensor: <\/b> NOAA-20 VIIRS<br\/> <b>Confidence: <\/b> Nominal<br\/>  <b>Day\/Night: <\/b> Night<br\/> <b>Scan: <\/b> 0.4 km<br\/> <b>Track: <\/b> 0.5 km<br\/> <b>FRP: <\/b> 16.21 MW<br\/> <b>Brightness: <\/b> 338.87 K" }, "geometry": { "type": "Point", "coordinates": [ -70.35578, 18.92998, 0.0 ] } }
]
}
