{
"type": "FeatureCollection",
"crs": { "type": "name", "properties": { "name": "urn:ogc:def:crs:OGC:1.3:CRS84" } },
"features": [
{ "type": "Feature", "properties": { "Name": "Fire Detection Centroid ", "Description": "<b>Latitude: <\/b> 36.35881<br\/>  <b>Longitude: <\/b> -76.80996<br\/>  <b>Detection Time: <\/b> 2023-04-12 05:56 UTC<br\/>  <b>Sensor: <\/b> NOAA-20 VIIRS<br\/> <b>Confidence: <\/b> Nominal<br\/>  <b>Day\/Night: <\/b> Night<br\/> <b>Scan: <\/b> 0.7 km<br\/> <b>Track: <\/b> 0.7 km<br\/> <b>FRP: <\/b> 3.32 MW<br\/> <b>Brightness: <\/b> 315.07 K" }, "geometry": { "type": "Point", "coordinates": [ -76.80996, 36.35881, 0.0 ] } },
{ "type": "Feature", "properties": { "Name": "Fire Detection Centroid ", "Description": "<b>Latitude: <\/b> 46.04424<br\/>  <b>Longitude: <\/b> -73.14214<br\/>  <b>Detection Time: <\/b> 2023-04-12 05:53 UTC<br\/>  <b>Sensor: <\/b> NOAA-20 VIIRS<br\/> <b>Confidence: <\/b> Nominal<br\/>  <b>Day\/Night: <\/b> Night<br\/> <b>Scan: <\/b> 0.5 km<br\/> <b>Track: <\/b> 0.6 km<br\/> <b>FRP: <\/b> 1.84 MW<br\/> <b>Brightness: <\/b> 306.86 K" }, "geometry": { "type": "Point", "coordinates": [ -73.14214, 46.04424, 0.0 ] } },
{ "type": "Feature", "properties": { "Name": "Fire Detection Centroid ", "Description": "<b>Latitude: <\/b> 48.18657<br\/>  <b>Longitude: <\/b> -64.92384<br\/>  <b>Detection Time: <\/b> 2023-04-12 05:52 UTC<br\/>  <b>Sensor: <\/b> NOAA-20 VIIRS<br\/> <b>Confidence: <\/b> Nominal<br\/>  <b>Day\/Night: <\/b> Night<br\/> <b>Scan: <\/b> 0.4 km<br\/> <b>Track: <\/b> 0.4 km<br\/> <b>FRP: <\/b> 1.39 MW<br\/> <b>Brightness: <\/b> 299.58 K" }, "geometry": { "type": "Point", "coordinates": [ -64.92384, 48.18657, 0.0 ] } }
]
}
