{
"type": "FeatureCollection",
"crs": { "type": "name", "properties": { "name": "urn:ogc:def:crs:OGC:1.3:CRS84" } },
"features": [
{ "type": "Feature", "properties": { "Name": "Fire Detection Centroid ", "Description": "<b>Latitude: <\/b> 36.35963<br\/>  <b>Longitude: <\/b> -76.8112<br\/>  <b>Detection Time: <\/b> 2023-02-07 05:55 UTC<br\/>  <b>Sensor: <\/b> NOAA-20 VIIRS<br\/> <b>Confidence: <\/b> Nominal<br\/>  <b>Day\/Night: <\/b> Night<br\/> <b>Scan: <\/b> 0.7 km<br\/> <b>Track: <\/b> 0.7 km<br\/> <b>FRP: <\/b> 2.17 MW<br\/> <b>Brightness: <\/b> 297.75 K" }, "geometry": { "type": "Point", "coordinates": [ -76.8112, 36.35963, 0.0 ] } },
{ "type": "Feature", "properties": { "Name": "Fire Detection Centroid ", "Description": "<b>Latitude: <\/b> 36.35451<br\/>  <b>Longitude: <\/b> -76.81087<br\/>  <b>Detection Time: <\/b> 2023-02-07 05:55 UTC<br\/>  <b>Sensor: <\/b> NOAA-20 VIIRS<br\/> <b>Confidence: <\/b> Nominal<br\/>  <b>Day\/Night: <\/b> Night<br\/> <b>Scan: <\/b> 0.7 km<br\/> <b>Track: <\/b> 0.7 km<br\/> <b>FRP: <\/b> 1.08 MW<br\/> <b>Brightness: <\/b> 296.04 K" }, "geometry": { "type": "Point", "coordinates": [ -76.81087, 36.35451, 0.0 ] } },
{ "type": "Feature", "properties": { "Name": "Fire Detection Centroid ", "Description": "<b>Latitude: <\/b> 40.89248<br\/>  <b>Longitude: <\/b> -77.71043<br\/>  <b>Detection Time: <\/b> 2023-02-07 05:54 UTC<br\/>  <b>Sensor: <\/b> NOAA-20 VIIRS<br\/> <b>Confidence: <\/b> Nominal<br\/>  <b>Day\/Night: <\/b> Night<br\/> <b>Scan: <\/b> 0.8 km<br\/> <b>Track: <\/b> 0.8 km<br\/> <b>FRP: <\/b> 2.66 MW<br\/> <b>Brightness: <\/b> 303.5 K" }, "geometry": { "type": "Point", "coordinates": [ -77.71043, 40.89248, 0.0 ] } }
]
}
