{
"type": "FeatureCollection",
"crs": { "type": "name", "properties": { "name": "urn:ogc:def:crs:OGC:1.3:CRS84" } },
"features": [
{ "type": "Feature", "properties": { "Name": "Fire Detection Centroid ", "Description": "<b>Latitude: <\/b> 18.31258<br\/>  <b>Longitude: <\/b> -64.88206<br\/>  <b>Detection Time: <\/b> 2023-07-08 05:30 UTC<br\/>  <b>Sensor: <\/b> NOAA-20 VIIRS<br\/> <b>Confidence: <\/b> Nominal<br\/>  <b>Day\/Night: <\/b> Night<br\/> <b>Scan: <\/b> 0.5 km<br\/> <b>Track: <\/b> 0.5 km<br\/> <b>FRP: <\/b> 2.02 MW<br\/> <b>Brightness: <\/b> 306.54 K" }, "geometry": { "type": "Point", "coordinates": [ -64.88206, 18.31258, 0.0 ] } },
{ "type": "Feature", "properties": { "Name": "Fire Detection Centroid ", "Description": "<b>Latitude: <\/b> 18.55814<br\/>  <b>Longitude: <\/b> -69.97457<br\/>  <b>Detection Time: <\/b> 2023-07-08 05:30 UTC<br\/>  <b>Sensor: <\/b> NOAA-20 VIIRS<br\/> <b>Confidence: <\/b> Nominal<br\/>  <b>Day\/Night: <\/b> Night<br\/> <b>Scan: <\/b> 0.5 km<br\/> <b>Track: <\/b> 0.7 km<br\/> <b>FRP: <\/b> 1.82 MW<br\/> <b>Brightness: <\/b> 318.77 K" }, "geometry": { "type": "Point", "coordinates": [ -69.97457, 18.55814, 0.0 ] } },
{ "type": "Feature", "properties": { "Name": "Fire Detection Centroid ", "Description": "<b>Latitude: <\/b> 18.55195<br\/>  <b>Longitude: <\/b> -69.97541<br\/>  <b>Detection Time: <\/b> 2023-07-08 05:30 UTC<br\/>  <b>Sensor: <\/b> NOAA-20 VIIRS<br\/> <b>Confidence: <\/b> Nominal<br\/>  <b>Day\/Night: <\/b> Night<br\/> <b>Scan: <\/b> 0.5 km<br\/> <b>Track: <\/b> 0.7 km<br\/> <b>FRP: <\/b> 1.06 MW<br\/> <b>Brightness: <\/b> 306.6 K" }, "geometry": { "type": "Point", "coordinates": [ -69.97541, 18.55195, 0.0 ] } },
{ "type": "Feature", "properties": { "Name": "Fire Detection Centroid ", "Description": "<b>Latitude: <\/b> 18.92812<br\/>  <b>Longitude: <\/b> -70.35468<br\/>  <b>Detection Time: <\/b> 2023-07-08 05:30 UTC<br\/>  <b>Sensor: <\/b> NOAA-20 VIIRS<br\/> <b>Confidence: <\/b> Nominal<br\/>  <b>Day\/Night: <\/b> Night<br\/> <b>Scan: <\/b> 0.6 km<br\/> <b>Track: <\/b> 0.7 km<br\/> <b>FRP: <\/b> 6.14 MW<br\/> <b>Brightness: <\/b> 335.03 K" }, "geometry": { "type": "Point", "coordinates": [ -70.35468, 18.92812, 0.0 ] } }
]
}
