{
"type": "FeatureCollection",
"crs": { "type": "name", "properties": { "name": "urn:ogc:def:crs:OGC:1.3:CRS84" } },
"features": [
{ "type": "Feature", "properties": { "Name": "Fire Detection Centroid ", "Description": "<b>Latitude: <\/b> 46.29869<br\/>  <b>Longitude: <\/b> -123.16588<br\/>  <b>Detection Time: <\/b> 2023-07-05 21:08 UTC<br\/>  <b>Sensor: <\/b> NOAA-20 VIIRS<br\/> <b>Confidence: <\/b> Nominal<br\/>  <b>Day\/Night: <\/b> Day<br\/> <b>Scan: <\/b> 0.39 km<br\/> <b>Track: <\/b> 0.36 km<br\/> <b>FRP: <\/b> 8.76 MW<br\/> <b>Brightness: <\/b> 334.75 K" }, "geometry": { "type": "Point", "coordinates": [ -123.16588, 46.29869, 0.0 ] } },
{ "type": "Feature", "properties": { "Name": "Fire Detection Centroid ", "Description": "<b>Latitude: <\/b> 47.46922<br\/>  <b>Longitude: <\/b> -122.05<br\/>  <b>Detection Time: <\/b> 2023-07-05 21:08 UTC<br\/>  <b>Sensor: <\/b> NOAA-20 VIIRS<br\/> <b>Confidence: <\/b> Low<br\/>  <b>Day\/Night: <\/b> Day<br\/> <b>Scan: <\/b> 0.42 km<br\/> <b>Track: <\/b> 0.38 km<br\/> <b>FRP: <\/b> 5.07 MW<br\/> <b>Brightness: <\/b> 334.74 K" }, "geometry": { "type": "Point", "coordinates": [ -122.05, 47.46922, 0.0 ] } },
{ "type": "Feature", "properties": { "Name": "Fire Detection Centroid ", "Description": "<b>Latitude: <\/b> 43.4742<br\/>  <b>Longitude: <\/b> -114.28018<br\/>  <b>Detection Time: <\/b> 2023-07-05 21:08 UTC<br\/>  <b>Sensor: <\/b> NOAA-20 VIIRS<br\/> <b>Confidence: <\/b> Nominal<br\/>  <b>Day\/Night: <\/b> Day<br\/> <b>Scan: <\/b> 0.52 km<br\/> <b>Track: <\/b> 0.5 km<br\/> <b>FRP: <\/b> 26.38 MW<br\/> <b>Brightness: <\/b> 338.79 K" }, "geometry": { "type": "Point", "coordinates": [ -114.28018, 43.4742, 0.0 ] } },
{ "type": "Feature", "properties": { "Name": "Fire Detection Centroid ", "Description": "<b>Latitude: <\/b> 45.72482<br\/>  <b>Longitude: <\/b> -121.59797<br\/>  <b>Detection Time: <\/b> 2023-07-05 21:08 UTC<br\/>  <b>Sensor: <\/b> NOAA-20 VIIRS<br\/> <b>Confidence: <\/b> Low<br\/>  <b>Day\/Night: <\/b> Day<br\/> <b>Scan: <\/b> 0.42 km<br\/> <b>Track: <\/b> 0.37 km<br\/> <b>FRP: <\/b> 7.22 MW<br\/> <b>Brightness: <\/b> 337.94 K" }, "geometry": { "type": "Point", "coordinates": [ -121.59797, 45.72482, 0.0 ] } }
]
}
