{
"type": "FeatureCollection",
"crs": { "type": "name", "properties": { "name": "urn:ogc:def:crs:OGC:1.3:CRS84" } },
"features": [
{ "type": "Feature", "properties": { "Name": "Fire Detection Centroid ", "Description": "<b>Latitude: <\/b> 19.77501<br\/>  <b>Longitude: <\/b> -155.62383<br\/>  <b>Detection Time: <\/b> 2023-11-17 23:50 UTC<br\/>  <b>Sensor: <\/b> NOAA-20 VIIRS<br\/> <b>Confidence: <\/b> Nominal<br\/>  <b>Day\/Night: <\/b> Day<br\/> <b>Scan: <\/b> 0.5 km<br\/> <b>Track: <\/b> 0.41 km<br\/> <b>FRP: <\/b> 40.29 MW<br\/> <b>Brightness: <\/b> 343.57 K" }, "geometry": { "type": "Point", "coordinates": [ -155.62383, 19.77501, 0.0 ] } },
{ "type": "Feature", "properties": { "Name": "Fire Detection Centroid ", "Description": "<b>Latitude: <\/b> 19.77473<br\/>  <b>Longitude: <\/b> -155.6245<br\/>  <b>Detection Time: <\/b> 2023-11-17 23:50 UTC<br\/>  <b>Sensor: <\/b> NOAA-20 VIIRS<br\/> <b>Confidence: <\/b> Nominal<br\/>  <b>Day\/Night: <\/b> Day<br\/> <b>Scan: <\/b> 0.5 km<br\/> <b>Track: <\/b> 0.4 km<br\/> <b>FRP: <\/b> 40.29 MW<br\/> <b>Brightness: <\/b> 343.57 K" }, "geometry": { "type": "Point", "coordinates": [ -155.6245, 19.77473, 0.0 ] } }
]
}
