{
"type": "FeatureCollection",
"crs": { "type": "name", "properties": { "name": "urn:ogc:def:crs:OGC:1.3:CRS84" } },
"features": [
{ "type": "Feature", "properties": { "Name": "Fire Detection Centroid ", "Description": "<b>Latitude: <\/b> 19.40782<br\/>  <b>Longitude: <\/b> -155.28889<br\/>  <b>Detection Time: <\/b> 2023-07-30 12:02 UTC<br\/>  <b>Sensor: <\/b> NOAA-20 VIIRS<br\/> <b>Confidence: <\/b> Nominal<br\/>  <b>Day\/Night: <\/b> Night<br\/> <b>Scan: <\/b> 0.39 km<br\/> <b>Track: <\/b> 0.36 km<br\/> <b>FRP: <\/b> 2.4 MW<br\/> <b>Brightness: <\/b> 304.67 K" }, "geometry": { "type": "Point", "coordinates": [ -155.28889, 19.40782, 0.0 ] } },
{ "type": "Feature", "properties": { "Name": "Fire Detection Centroid ", "Description": "<b>Latitude: <\/b> 19.4039<br\/>  <b>Longitude: <\/b> -155.2858<br\/>  <b>Detection Time: <\/b> 2023-07-30 12:02 UTC<br\/>  <b>Sensor: <\/b> NOAA-20 VIIRS<br\/> <b>Confidence: <\/b> Nominal<br\/>  <b>Day\/Night: <\/b> Night<br\/> <b>Scan: <\/b> 0.39 km<br\/> <b>Track: <\/b> 0.36 km<br\/> <b>FRP: <\/b> 1.78 MW<br\/> <b>Brightness: <\/b> 310.79 K" }, "geometry": { "type": "Point", "coordinates": [ -155.2858, 19.4039, 0.0 ] } },
{ "type": "Feature", "properties": { "Name": "Fire Detection Centroid ", "Description": "<b>Latitude: <\/b> 19.40933<br\/>  <b>Longitude: <\/b> -155.27725<br\/>  <b>Detection Time: <\/b> 2023-07-30 12:02 UTC<br\/>  <b>Sensor: <\/b> NOAA-20 VIIRS<br\/> <b>Confidence: <\/b> Nominal<br\/>  <b>Day\/Night: <\/b> Night<br\/> <b>Scan: <\/b> 0.39 km<br\/> <b>Track: <\/b> 0.36 km<br\/> <b>FRP: <\/b> 1.78 MW<br\/> <b>Brightness: <\/b> 310.72 K" }, "geometry": { "type": "Point", "coordinates": [ -155.27725, 19.40933, 0.0 ] } },
{ "type": "Feature", "properties": { "Name": "Fire Detection Centroid ", "Description": "<b>Latitude: <\/b> 19.40993<br\/>  <b>Longitude: <\/b> -155.28093<br\/>  <b>Detection Time: <\/b> 2023-07-30 12:02 UTC<br\/>  <b>Sensor: <\/b> NOAA-20 VIIRS<br\/> <b>Confidence: <\/b> Nominal<br\/>  <b>Day\/Night: <\/b> Night<br\/> <b>Scan: <\/b> 0.39 km<br\/> <b>Track: <\/b> 0.36 km<br\/> <b>FRP: <\/b> 1.78 MW<br\/> <b>Brightness: <\/b> 315.06 K" }, "geometry": { "type": "Point", "coordinates": [ -155.28093, 19.40993, 0.0 ] } },
{ "type": "Feature", "properties": { "Name": "Fire Detection Centroid ", "Description": "<b>Latitude: <\/b> 19.41324<br\/>  <b>Longitude: <\/b> -155.28033<br\/>  <b>Detection Time: <\/b> 2023-07-30 12:02 UTC<br\/>  <b>Sensor: <\/b> NOAA-20 VIIRS<br\/> <b>Confidence: <\/b> Nominal<br\/>  <b>Day\/Night: <\/b> Night<br\/> <b>Scan: <\/b> 0.39 km<br\/> <b>Track: <\/b> 0.36 km<br\/> <b>FRP: <\/b> 2.64 MW<br\/> <b>Brightness: <\/b> 311.92 K" }, "geometry": { "type": "Point", "coordinates": [ -155.28033, 19.41324, 0.0 ] } },
{ "type": "Feature", "properties": { "Name": "Fire Detection Centroid ", "Description": "<b>Latitude: <\/b> 19.40451<br\/>  <b>Longitude: <\/b> -155.28947<br\/>  <b>Detection Time: <\/b> 2023-07-30 12:02 UTC<br\/>  <b>Sensor: <\/b> NOAA-20 VIIRS<br\/> <b>Confidence: <\/b> Nominal<br\/>  <b>Day\/Night: <\/b> Night<br\/> <b>Scan: <\/b> 0.39 km<br\/> <b>Track: <\/b> 0.36 km<br\/> <b>FRP: <\/b> 1.78 MW<br\/> <b>Brightness: <\/b> 306.58 K" }, "geometry": { "type": "Point", "coordinates": [ -155.28947, 19.40451, 0.0 ] } },
{ "type": "Feature", "properties": { "Name": "Fire Detection Centroid ", "Description": "<b>Latitude: <\/b> 19.40602<br\/>  <b>Longitude: <\/b> -155.27782<br\/>  <b>Detection Time: <\/b> 2023-07-30 12:02 UTC<br\/>  <b>Sensor: <\/b> NOAA-20 VIIRS<br\/> <b>Confidence: <\/b> Nominal<br\/>  <b>Day\/Night: <\/b> Night<br\/> <b>Scan: <\/b> 0.39 km<br\/> <b>Track: <\/b> 0.36 km<br\/> <b>FRP: <\/b> 1.78 MW<br\/> <b>Brightness: <\/b> 309.26 K" }, "geometry": { "type": "Point", "coordinates": [ -155.27782, 19.40602, 0.0 ] } },
{ "type": "Feature", "properties": { "Name": "Fire Detection Centroid ", "Description": "<b>Latitude: <\/b> 19.40661<br\/>  <b>Longitude: <\/b> -155.28151<br\/>  <b>Detection Time: <\/b> 2023-07-30 12:02 UTC<br\/>  <b>Sensor: <\/b> NOAA-20 VIIRS<br\/> <b>Confidence: <\/b> Nominal<br\/>  <b>Day\/Night: <\/b> Night<br\/> <b>Scan: <\/b> 0.39 km<br\/> <b>Track: <\/b> 0.36 km<br\/> <b>FRP: <\/b> 1.78 MW<br\/> <b>Brightness: <\/b> 311.89 K" }, "geometry": { "type": "Point", "coordinates": [ -155.28151, 19.40661, 0.0 ] } },
{ "type": "Feature", "properties": { "Name": "Fire Detection Centroid ", "Description": "<b>Latitude: <\/b> 19.40722<br\/>  <b>Longitude: <\/b> -155.2852<br\/>  <b>Detection Time: <\/b> 2023-07-30 12:02 UTC<br\/>  <b>Sensor: <\/b> NOAA-20 VIIRS<br\/> <b>Confidence: <\/b> Nominal<br\/>  <b>Day\/Night: <\/b> Night<br\/> <b>Scan: <\/b> 0.39 km<br\/> <b>Track: <\/b> 0.36 km<br\/> <b>FRP: <\/b> 2.4 MW<br\/> <b>Brightness: <\/b> 307.45 K" }, "geometry": { "type": "Point", "coordinates": [ -155.2852, 19.40722, 0.0 ] } }
]
}
