{
"type": "FeatureCollection",
"crs": { "type": "name", "properties": { "name": "urn:ogc:def:crs:OGC:1.3:CRS84" } },
"features": [
{ "type": "Feature", "properties": { "Name": "Fire Detection Centroid ", "Description": "<b>Latitude: <\/b> 19.40797<br\/>  <b>Longitude: <\/b> -155.28653<br\/>  <b>Detection Time: <\/b> 2023-09-24 00:22 UTC<br\/>  <b>Sensor: <\/b> NOAA-20 VIIRS<br\/> <b>Confidence: <\/b> Nominal<br\/>  <b>Day\/Night: <\/b> Day<br\/> <b>Scan: <\/b> 0.55 km<br\/> <b>Track: <\/b> 0.68 km<br\/> <b>FRP: <\/b> 20.88 MW<br\/> <b>Brightness: <\/b> 345.6 K" }, "geometry": { "type": "Point", "coordinates": [ -155.28653, 19.40797, 0.0 ] } },
{ "type": "Feature", "properties": { "Name": "Fire Detection Centroid ", "Description": "<b>Latitude: <\/b> 19.40847<br\/>  <b>Longitude: <\/b> -155.28096<br\/>  <b>Detection Time: <\/b> 2023-09-24 00:22 UTC<br\/>  <b>Sensor: <\/b> NOAA-20 VIIRS<br\/> <b>Confidence: <\/b> Nominal<br\/>  <b>Day\/Night: <\/b> Day<br\/> <b>Scan: <\/b> 0.55 km<br\/> <b>Track: <\/b> 0.68 km<br\/> <b>FRP: <\/b> 12.25 MW<br\/> <b>Brightness: <\/b> 348.73 K" }, "geometry": { "type": "Point", "coordinates": [ -155.28096, 19.40847, 0.0 ] } },
{ "type": "Feature", "properties": { "Name": "Fire Detection Centroid ", "Description": "<b>Latitude: <\/b> 19.40895<br\/>  <b>Longitude: <\/b> -155.27557<br\/>  <b>Detection Time: <\/b> 2023-09-24 00:22 UTC<br\/>  <b>Sensor: <\/b> NOAA-20 VIIRS<br\/> <b>Confidence: <\/b> Nominal<br\/>  <b>Day\/Night: <\/b> Day<br\/> <b>Scan: <\/b> 0.55 km<br\/> <b>Track: <\/b> 0.68 km<br\/> <b>FRP: <\/b> 12.25 MW<br\/> <b>Brightness: <\/b> 343.08 K" }, "geometry": { "type": "Point", "coordinates": [ -155.27557, 19.40895, 0.0 ] } },
{ "type": "Feature", "properties": { "Name": "Fire Detection Centroid ", "Description": "<b>Latitude: <\/b> 19.40215<br\/>  <b>Longitude: <\/b> -155.2804<br\/>  <b>Detection Time: <\/b> 2023-09-24 00:22 UTC<br\/>  <b>Sensor: <\/b> NOAA-20 VIIRS<br\/> <b>Confidence: <\/b> Nominal<br\/>  <b>Day\/Night: <\/b> Day<br\/> <b>Scan: <\/b> 0.55 km<br\/> <b>Track: <\/b> 0.68 km<br\/> <b>FRP: <\/b> 12.25 MW<br\/> <b>Brightness: <\/b> 336.42 K" }, "geometry": { "type": "Point", "coordinates": [ -155.2804, 19.40215, 0.0 ] } },
{ "type": "Feature", "properties": { "Name": "Fire Detection Centroid ", "Description": "<b>Latitude: <\/b> 19.4081<br\/>  <b>Longitude: <\/b> -155.28839<br\/>  <b>Detection Time: <\/b> 2023-09-24 00:22 UTC<br\/>  <b>Sensor: <\/b> NOAA-20 VIIRS<br\/> <b>Confidence: <\/b> Nominal<br\/>  <b>Day\/Night: <\/b> Day<br\/> <b>Scan: <\/b> 0.6 km<br\/> <b>Track: <\/b> 0.7 km<br\/> <b>FRP: <\/b> 20.88 MW<br\/> <b>Brightness: <\/b> 345.6 K" }, "geometry": { "type": "Point", "coordinates": [ -155.28839, 19.4081, 0.0 ] } },
{ "type": "Feature", "properties": { "Name": "Fire Detection Centroid ", "Description": "<b>Latitude: <\/b> 19.40909<br\/>  <b>Longitude: <\/b> -155.27727<br\/>  <b>Detection Time: <\/b> 2023-09-24 00:22 UTC<br\/>  <b>Sensor: <\/b> NOAA-20 VIIRS<br\/> <b>Confidence: <\/b> Nominal<br\/>  <b>Day\/Night: <\/b> Day<br\/> <b>Scan: <\/b> 0.6 km<br\/> <b>Track: <\/b> 0.7 km<br\/> <b>FRP: <\/b> 12.24 MW<br\/> <b>Brightness: <\/b> 343.08 K" }, "geometry": { "type": "Point", "coordinates": [ -155.27727, 19.40909, 0.0 ] } },
{ "type": "Feature", "properties": { "Name": "Fire Detection Centroid ", "Description": "<b>Latitude: <\/b> 19.4086<br\/>  <b>Longitude: <\/b> -155.28275<br\/>  <b>Detection Time: <\/b> 2023-09-24 00:22 UTC<br\/>  <b>Sensor: <\/b> NOAA-20 VIIRS<br\/> <b>Confidence: <\/b> Nominal<br\/>  <b>Day\/Night: <\/b> Day<br\/> <b>Scan: <\/b> 0.6 km<br\/> <b>Track: <\/b> 0.7 km<br\/> <b>FRP: <\/b> 12.24 MW<br\/> <b>Brightness: <\/b> 348.73 K" }, "geometry": { "type": "Point", "coordinates": [ -155.28275, 19.4086, 0.0 ] } },
{ "type": "Feature", "properties": { "Name": "Fire Detection Centroid ", "Description": "<b>Latitude: <\/b> 19.40229<br\/>  <b>Longitude: <\/b> -155.28209<br\/>  <b>Detection Time: <\/b> 2023-09-24 00:22 UTC<br\/>  <b>Sensor: <\/b> NOAA-20 VIIRS<br\/> <b>Confidence: <\/b> Nominal<br\/>  <b>Day\/Night: <\/b> Day<br\/> <b>Scan: <\/b> 0.6 km<br\/> <b>Track: <\/b> 0.7 km<br\/> <b>FRP: <\/b> 12.24 MW<br\/> <b>Brightness: <\/b> 336.42 K" }, "geometry": { "type": "Point", "coordinates": [ -155.28209, 19.40229, 0.0 ] } }
]
}
