{
"type": "FeatureCollection",
"crs": { "type": "name", "properties": { "name": "urn:ogc:def:crs:OGC:1.3:CRS84" } },
"features": [
{ "type": "Feature", "properties": { "Name": "Fire Detection Centroid ", "Description": "<b>Latitude: <\/b> 19.41076<br\/>  <b>Longitude: <\/b> -155.2845<br\/>  <b>Detection Time: <\/b> 2023-11-09 11:49 UTC<br\/>  <b>Sensor: <\/b> NOAA-20 VIIRS<br\/> <b>Confidence: <\/b> Nominal<br\/>  <b>Day\/Night: <\/b> Night<br\/> <b>Scan: <\/b> 0.42 km<br\/> <b>Track: <\/b> 0.38 km<br\/> <b>FRP: <\/b> 3.33 MW<br\/> <b>Brightness: <\/b> 310.35 K" }, "geometry": { "type": "Point", "coordinates": [ -155.2845, 19.41076, 0.0 ] } },
{ "type": "Feature", "properties": { "Name": "Fire Detection Centroid ", "Description": "<b>Latitude: <\/b> 19.4096<br\/>  <b>Longitude: <\/b> -155.27657<br\/>  <b>Detection Time: <\/b> 2023-11-09 11:49 UTC<br\/>  <b>Sensor: <\/b> NOAA-20 VIIRS<br\/> <b>Confidence: <\/b> Nominal<br\/>  <b>Day\/Night: <\/b> Night<br\/> <b>Scan: <\/b> 0.42 km<br\/> <b>Track: <\/b> 0.38 km<br\/> <b>FRP: <\/b> 5.1 MW<br\/> <b>Brightness: <\/b> 308.4 K" }, "geometry": { "type": "Point", "coordinates": [ -155.27657, 19.4096, 0.0 ] } },
{ "type": "Feature", "properties": { "Name": "Fire Detection Centroid ", "Description": "<b>Latitude: <\/b> 19.40789<br\/>  <b>Longitude: <\/b> -155.28903<br\/>  <b>Detection Time: <\/b> 2023-11-09 11:49 UTC<br\/>  <b>Sensor: <\/b> NOAA-20 VIIRS<br\/> <b>Confidence: <\/b> Nominal<br\/>  <b>Day\/Night: <\/b> Night<br\/> <b>Scan: <\/b> 0.42 km<br\/> <b>Track: <\/b> 0.38 km<br\/> <b>FRP: <\/b> 2.35 MW<br\/> <b>Brightness: <\/b> 306.67 K" }, "geometry": { "type": "Point", "coordinates": [ -155.28903, 19.40789, 0.0 ] } },
{ "type": "Feature", "properties": { "Name": "Fire Detection Centroid ", "Description": "<b>Latitude: <\/b> 19.40732<br\/>  <b>Longitude: <\/b> -155.2851<br\/>  <b>Detection Time: <\/b> 2023-11-09 11:49 UTC<br\/>  <b>Sensor: <\/b> NOAA-20 VIIRS<br\/> <b>Confidence: <\/b> Nominal<br\/>  <b>Day\/Night: <\/b> Night<br\/> <b>Scan: <\/b> 0.42 km<br\/> <b>Track: <\/b> 0.38 km<br\/> <b>FRP: <\/b> 2.79 MW<br\/> <b>Brightness: <\/b> 309.67 K" }, "geometry": { "type": "Point", "coordinates": [ -155.2851, 19.40732, 0.0 ] } },
{ "type": "Feature", "properties": { "Name": "Fire Detection Centroid ", "Description": "<b>Latitude: <\/b> 19.40674<br\/>  <b>Longitude: <\/b> -155.2811<br\/>  <b>Detection Time: <\/b> 2023-11-09 11:49 UTC<br\/>  <b>Sensor: <\/b> NOAA-20 VIIRS<br\/> <b>Confidence: <\/b> Nominal<br\/>  <b>Day\/Night: <\/b> Night<br\/> <b>Scan: <\/b> 0.42 km<br\/> <b>Track: <\/b> 0.38 km<br\/> <b>FRP: <\/b> 2.79 MW<br\/> <b>Brightness: <\/b> 313.65 K" }, "geometry": { "type": "Point", "coordinates": [ -155.2811, 19.40674, 0.0 ] } },
{ "type": "Feature", "properties": { "Name": "Fire Detection Centroid ", "Description": "<b>Latitude: <\/b> 19.41363<br\/>  <b>Longitude: <\/b> -155.27998<br\/>  <b>Detection Time: <\/b> 2023-11-09 11:49 UTC<br\/>  <b>Sensor: <\/b> NOAA-20 VIIRS<br\/> <b>Confidence: <\/b> Nominal<br\/>  <b>Day\/Night: <\/b> Night<br\/> <b>Scan: <\/b> 0.42 km<br\/> <b>Track: <\/b> 0.38 km<br\/> <b>FRP: <\/b> 3.33 MW<br\/> <b>Brightness: <\/b> 307.46 K" }, "geometry": { "type": "Point", "coordinates": [ -155.27998, 19.41363, 0.0 ] } },
{ "type": "Feature", "properties": { "Name": "Fire Detection Centroid ", "Description": "<b>Latitude: <\/b> 19.41133<br\/>  <b>Longitude: <\/b> -155.28844<br\/>  <b>Detection Time: <\/b> 2023-11-09 11:49 UTC<br\/>  <b>Sensor: <\/b> NOAA-20 VIIRS<br\/> <b>Confidence: <\/b> Nominal<br\/>  <b>Day\/Night: <\/b> Night<br\/> <b>Scan: <\/b> 0.42 km<br\/> <b>Track: <\/b> 0.38 km<br\/> <b>FRP: <\/b> 1.65 MW<br\/> <b>Brightness: <\/b> 304.93 K" }, "geometry": { "type": "Point", "coordinates": [ -155.28844, 19.41133, 0.0 ] } }
]
}
