{
"type": "FeatureCollection",
"crs": { "type": "name", "properties": { "name": "urn:ogc:def:crs:OGC:1.3:CRS84" } },
"features": [
{ "type": "Feature", "properties": { "Name": "Fire Detection Centroid ", "Description": "<b>Latitude: <\/b> 45.94242<br\/>  <b>Longitude: <\/b> -122.09489<br\/>  <b>Detection Time: <\/b> 2022-09-25 11:28 UTC<br\/>  <b>Sensor: <\/b> NOAA-20 VIIRS<br\/> <b>Confidence: <\/b> Nominal<br\/>  <b>Day\/Night: <\/b> Night<br\/> <b>Scan: <\/b> 0.7 km<br\/> <b>Track: <\/b> 0.75 km<br\/> <b>FRP: <\/b> 1.63 MW<br\/> <b>Brightness: <\/b> 302.35 K" }, "geometry": { "type": "Point", "coordinates": [ -122.09489, 45.94242, 0.0 ] } },
{ "type": "Feature", "properties": { "Name": "Fire Detection Centroid ", "Description": "<b>Latitude: <\/b> 48.88567<br\/>  <b>Longitude: <\/b> -122.73563<br\/>  <b>Detection Time: <\/b> 2022-09-25 11:25 UTC<br\/>  <b>Sensor: <\/b> NOAA-20 VIIRS<br\/> <b>Confidence: <\/b> Nominal<br\/>  <b>Day\/Night: <\/b> Night<br\/> <b>Scan: <\/b> 0.52 km<br\/> <b>Track: <\/b> 0.67 km<br\/> <b>FRP: <\/b> 1.47 MW<br\/> <b>Brightness: <\/b> 297.02 K" }, "geometry": { "type": "Point", "coordinates": [ -122.73563, 48.88567, 0.0 ] } },
{ "type": "Feature", "properties": { "Name": "Fire Detection Centroid ", "Description": "<b>Latitude: <\/b> 49.90501<br\/>  <b>Longitude: <\/b> -120.78703<br\/>  <b>Detection Time: <\/b> 2022-09-25 11:25 UTC<br\/>  <b>Sensor: <\/b> NOAA-20 VIIRS<br\/> <b>Confidence: <\/b> Nominal<br\/>  <b>Day\/Night: <\/b> Night<br\/> <b>Scan: <\/b> 0.57 km<br\/> <b>Track: <\/b> 0.69 km<br\/> <b>FRP: <\/b> 1.71 MW<br\/> <b>Brightness: <\/b> 298.07 K" }, "geometry": { "type": "Point", "coordinates": [ -120.78703, 49.90501, 0.0 ] } },
{ "type": "Feature", "properties": { "Name": "Fire Detection Centroid ", "Description": "<b>Latitude: <\/b> 47.94831<br\/>  <b>Longitude: <\/b> -120.70831<br\/>  <b>Detection Time: <\/b> 2022-09-25 11:25 UTC<br\/>  <b>Sensor: <\/b> NOAA-20 VIIRS<br\/> <b>Confidence: <\/b> Nominal<br\/>  <b>Day\/Night: <\/b> Night<br\/> <b>Scan: <\/b> 0.68 km<br\/> <b>Track: <\/b> 0.74 km<br\/> <b>FRP: <\/b> 3.02 MW<br\/> <b>Brightness: <\/b> 314.06 K" }, "geometry": { "type": "Point", "coordinates": [ -120.70831, 47.94831, 0.0 ] } },
{ "type": "Feature", "properties": { "Name": "Fire Detection Centroid ", "Description": "<b>Latitude: <\/b> 47.57219<br\/>  <b>Longitude: <\/b> -122.37844<br\/>  <b>Detection Time: <\/b> 2022-09-25 11:25 UTC<br\/>  <b>Sensor: <\/b> NOAA-20 VIIRS<br\/> <b>Confidence: <\/b> Nominal<br\/>  <b>Day\/Night: <\/b> Night<br\/> <b>Scan: <\/b> 0.59 km<br\/> <b>Track: <\/b> 0.7 km<br\/> <b>FRP: <\/b> 0.82 MW<br\/> <b>Brightness: <\/b> 296.64 K" }, "geometry": { "type": "Point", "coordinates": [ -122.37844, 47.57219, 0.0 ] } },
{ "type": "Feature", "properties": { "Name": "Fire Detection Centroid ", "Description": "<b>Latitude: <\/b> 47.56728<br\/>  <b>Longitude: <\/b> -122.34333<br\/>  <b>Detection Time: <\/b> 2022-09-25 11:25 UTC<br\/>  <b>Sensor: <\/b> NOAA-20 VIIRS<br\/> <b>Confidence: <\/b> Nominal<br\/>  <b>Day\/Night: <\/b> Night<br\/> <b>Scan: <\/b> 0.6 km<br\/> <b>Track: <\/b> 0.7 km<br\/> <b>FRP: <\/b> 0.56 MW<br\/> <b>Brightness: <\/b> 296.71 K" }, "geometry": { "type": "Point", "coordinates": [ -122.34333, 47.56728, 0.0 ] } },
{ "type": "Feature", "properties": { "Name": "Fire Detection Centroid ", "Description": "<b>Latitude: <\/b> 47.94605<br\/>  <b>Longitude: <\/b> -120.70212<br\/>  <b>Detection Time: <\/b> 2022-09-25 11:25 UTC<br\/>  <b>Sensor: <\/b> NOAA-20 VIIRS<br\/> <b>Confidence: <\/b> Nominal<br\/>  <b>Day\/Night: <\/b> Night<br\/> <b>Scan: <\/b> 0.68 km<br\/> <b>Track: <\/b> 0.74 km<br\/> <b>FRP: <\/b> 3.02 MW<br\/> <b>Brightness: <\/b> 298.67 K" }, "geometry": { "type": "Point", "coordinates": [ -120.70212, 47.94605, 0.0 ] } },
{ "type": "Feature", "properties": { "Name": "Fire Detection Centroid ", "Description": "<b>Latitude: <\/b> 47.56919<br\/>  <b>Longitude: <\/b> -122.36983<br\/>  <b>Detection Time: <\/b> 2022-09-25 11:25 UTC<br\/>  <b>Sensor: <\/b> NOAA-20 VIIRS<br\/> <b>Confidence: <\/b> Nominal<br\/>  <b>Day\/Night: <\/b> Night<br\/> <b>Scan: <\/b> 0.59 km<br\/> <b>Track: <\/b> 0.7 km<br\/> <b>FRP: <\/b> 0.82 MW<br\/> <b>Brightness: <\/b> 297.3 K" }, "geometry": { "type": "Point", "coordinates": [ -122.36983, 47.56919, 0.0 ] } }
]
}
