{
"type": "FeatureCollection",
"crs": { "type": "name", "properties": { "name": "urn:ogc:def:crs:OGC:1.3:CRS84" } },
"features": [
{ "type": "Feature", "properties": { "Name": "Fire Detection Centroid ", "Description": "<b>Latitude: <\/b> 19.40671<br\/>  <b>Longitude: <\/b> -155.27449<br\/>  <b>Detection Time: <\/b> 2023-02-07 00:15 UTC<br\/>  <b>Sensor: <\/b> NOAA-20 VIIRS<br\/> <b>Confidence: <\/b> Nominal<br\/>  <b>Day\/Night: <\/b> Day<br\/> <b>Scan: <\/b> 0.43 km<br\/> <b>Track: <\/b> 0.62 km<br\/> <b>FRP: <\/b> 15.51 MW<br\/> <b>Brightness: <\/b> 341.42 K" }, "geometry": { "type": "Point", "coordinates": [ -155.27449, 19.40671, 0.0 ] } },
{ "type": "Feature", "properties": { "Name": "Fire Detection Centroid ", "Description": "<b>Latitude: <\/b> 19.40631<br\/>  <b>Longitude: <\/b> -155.27858<br\/>  <b>Detection Time: <\/b> 2023-02-07 00:15 UTC<br\/>  <b>Sensor: <\/b> NOAA-20 VIIRS<br\/> <b>Confidence: <\/b> High<br\/>  <b>Day\/Night: <\/b> Day<br\/> <b>Scan: <\/b> 0.43 km<br\/> <b>Track: <\/b> 0.62 km<br\/> <b>FRP: <\/b> 56.28 MW<br\/> <b>Brightness: <\/b> 367 K" }, "geometry": { "type": "Point", "coordinates": [ -155.27858, 19.40631, 0.0 ] } },
{ "type": "Feature", "properties": { "Name": "Fire Detection Centroid ", "Description": "<b>Latitude: <\/b> 19.41113<br\/>  <b>Longitude: <\/b> -155.28793<br\/>  <b>Detection Time: <\/b> 2023-02-07 00:15 UTC<br\/>  <b>Sensor: <\/b> NOAA-20 VIIRS<br\/> <b>Confidence: <\/b> Low<br\/>  <b>Day\/Night: <\/b> Day<br\/> <b>Scan: <\/b> 0.43 km<br\/> <b>Track: <\/b> 0.62 km<br\/> <b>FRP: <\/b> 12.06 MW<br\/> <b>Brightness: <\/b> 332.03 K" }, "geometry": { "type": "Point", "coordinates": [ -155.28793, 19.41113, 0.0 ] } },
{ "type": "Feature", "properties": { "Name": "Fire Detection Centroid ", "Description": "<b>Latitude: <\/b> 19.41156<br\/>  <b>Longitude: <\/b> -155.28357<br\/>  <b>Detection Time: <\/b> 2023-02-07 00:15 UTC<br\/>  <b>Sensor: <\/b> NOAA-20 VIIRS<br\/> <b>Confidence: <\/b> Nominal<br\/>  <b>Day\/Night: <\/b> Day<br\/> <b>Scan: <\/b> 0.43 km<br\/> <b>Track: <\/b> 0.62 km<br\/> <b>FRP: <\/b> 25.16 MW<br\/> <b>Brightness: <\/b> 350.39 K" }, "geometry": { "type": "Point", "coordinates": [ -155.28357, 19.41156, 0.0 ] } },
{ "type": "Feature", "properties": { "Name": "Fire Detection Centroid ", "Description": "<b>Latitude: <\/b> 19.40061<br\/>  <b>Longitude: <\/b> -155.27817<br\/>  <b>Detection Time: <\/b> 2023-02-07 00:15 UTC<br\/>  <b>Sensor: <\/b> NOAA-20 VIIRS<br\/> <b>Confidence: <\/b> Nominal<br\/>  <b>Day\/Night: <\/b> Day<br\/> <b>Scan: <\/b> 0.43 km<br\/> <b>Track: <\/b> 0.62 km<br\/> <b>FRP: <\/b> 56.28 MW<br\/> <b>Brightness: <\/b> 351.45 K" }, "geometry": { "type": "Point", "coordinates": [ -155.27817, 19.40061, 0.0 ] } },
{ "type": "Feature", "properties": { "Name": "Fire Detection Centroid ", "Description": "<b>Latitude: <\/b> 19.40021<br\/>  <b>Longitude: <\/b> -155.28229<br\/>  <b>Detection Time: <\/b> 2023-02-07 00:15 UTC<br\/>  <b>Sensor: <\/b> NOAA-20 VIIRS<br\/> <b>Confidence: <\/b> Nominal<br\/>  <b>Day\/Night: <\/b> Day<br\/> <b>Scan: <\/b> 0.43 km<br\/> <b>Track: <\/b> 0.62 km<br\/> <b>FRP: <\/b> 56.28 MW<br\/> <b>Brightness: <\/b> 354.12 K" }, "geometry": { "type": "Point", "coordinates": [ -155.28229, 19.40021, 0.0 ] } },
{ "type": "Feature", "properties": { "Name": "Fire Detection Centroid ", "Description": "<b>Latitude: <\/b> 19.41199<br\/>  <b>Longitude: <\/b> -155.27924<br\/>  <b>Detection Time: <\/b> 2023-02-07 00:15 UTC<br\/>  <b>Sensor: <\/b> NOAA-20 VIIRS<br\/> <b>Confidence: <\/b> High<br\/>  <b>Day\/Night: <\/b> Day<br\/> <b>Scan: <\/b> 0.43 km<br\/> <b>Track: <\/b> 0.62 km<br\/> <b>FRP: <\/b> 25.16 MW<br\/> <b>Brightness: <\/b> 367 K" }, "geometry": { "type": "Point", "coordinates": [ -155.27924, 19.41199, 0.0 ] } },
{ "type": "Feature", "properties": { "Name": "Fire Detection Centroid ", "Description": "<b>Latitude: <\/b> 19.40505<br\/>  <b>Longitude: <\/b> -155.29135<br\/>  <b>Detection Time: <\/b> 2023-02-07 00:15 UTC<br\/>  <b>Sensor: <\/b> NOAA-20 VIIRS<br\/> <b>Confidence: <\/b> Nominal<br\/>  <b>Day\/Night: <\/b> Day<br\/> <b>Scan: <\/b> 0.43 km<br\/> <b>Track: <\/b> 0.62 km<br\/> <b>FRP: <\/b> 69.55 MW<br\/> <b>Brightness: <\/b> 337.77 K" }, "geometry": { "type": "Point", "coordinates": [ -155.29135, 19.40505, 0.0 ] } },
{ "type": "Feature", "properties": { "Name": "Fire Detection Centroid ", "Description": "<b>Latitude: <\/b> 19.40549<br\/>  <b>Longitude: <\/b> -155.28691<br\/>  <b>Detection Time: <\/b> 2023-02-07 00:15 UTC<br\/>  <b>Sensor: <\/b> NOAA-20 VIIRS<br\/> <b>Confidence: <\/b> Low<br\/>  <b>Day\/Night: <\/b> Day<br\/> <b>Scan: <\/b> 0.43 km<br\/> <b>Track: <\/b> 0.62 km<br\/> <b>FRP: <\/b> 69.55 MW<br\/> <b>Brightness: <\/b> 346.72 K" }, "geometry": { "type": "Point", "coordinates": [ -155.28691, 19.40549, 0.0 ] } }
]
}
