{
"type": "FeatureCollection",
"crs": { "type": "name", "properties": { "name": "urn:ogc:def:crs:OGC:1.3:CRS84" } },
"features": [
{ "type": "Feature", "properties": { "Name": "Fire Detection Centroid ", "Description": "<b>Latitude: <\/b> 43.26089<br\/>  <b>Longitude: <\/b> -79.80633<br\/>  <b>Detection Time: <\/b> 2023-02-12 17:24 UTC<br\/>  <b>Sensor: <\/b> NOAA-20 VIIRS<br\/> <b>Confidence: <\/b> Nominal<br\/>  <b>Day\/Night: <\/b> Day<br\/> <b>Scan: <\/b> 0.3 km<br\/> <b>Track: <\/b> 0.6 km<br\/> <b>FRP: <\/b> 3.43 MW<br\/> <b>Brightness: <\/b> 336.56 K" }, "geometry": { "type": "Point", "coordinates": [ -79.80633, 43.26089, 0.0 ] } },
{ "type": "Feature", "properties": { "Name": "Fire Detection Centroid ", "Description": "<b>Latitude: <\/b> 41.46662<br\/>  <b>Longitude: <\/b> -83.36464<br\/>  <b>Detection Time: <\/b> 2023-02-12 17:24 UTC<br\/>  <b>Sensor: <\/b> NOAA-20 VIIRS<br\/> <b>Confidence: <\/b> Nominal<br\/>  <b>Day\/Night: <\/b> Day<br\/> <b>Scan: <\/b> 0.5 km<br\/> <b>Track: <\/b> 0.7 km<br\/> <b>FRP: <\/b> 2.55 MW<br\/> <b>Brightness: <\/b> 327.2 K" }, "geometry": { "type": "Point", "coordinates": [ -83.36464, 41.46662, 0.0 ] } },
{ "type": "Feature", "properties": { "Name": "Fire Detection Centroid ", "Description": "<b>Latitude: <\/b> 41.45955<br\/>  <b>Longitude: <\/b> -81.67297<br\/>  <b>Detection Time: <\/b> 2023-02-12 17:24 UTC<br\/>  <b>Sensor: <\/b> NOAA-20 VIIRS<br\/> <b>Confidence: <\/b> Nominal<br\/>  <b>Day\/Night: <\/b> Day<br\/> <b>Scan: <\/b> 0.5 km<br\/> <b>Track: <\/b> 0.6 km<br\/> <b>FRP: <\/b> 7.18 MW<br\/> <b>Brightness: <\/b> 336.14 K" }, "geometry": { "type": "Point", "coordinates": [ -81.67297, 41.45955, 0.0 ] } },
{ "type": "Feature", "properties": { "Name": "Fire Detection Centroid ", "Description": "<b>Latitude: <\/b> 41.4526<br\/>  <b>Longitude: <\/b> -81.67526<br\/>  <b>Detection Time: <\/b> 2023-02-12 17:24 UTC<br\/>  <b>Sensor: <\/b> NOAA-20 VIIRS<br\/> <b>Confidence: <\/b> Nominal<br\/>  <b>Day\/Night: <\/b> Day<br\/> <b>Scan: <\/b> 0.5 km<br\/> <b>Track: <\/b> 0.6 km<br\/> <b>FRP: <\/b> 6.03 MW<br\/> <b>Brightness: <\/b> 345.13 K" }, "geometry": { "type": "Point", "coordinates": [ -81.67526, 41.4526, 0.0 ] } }
]
}
