{
"type": "FeatureCollection",
"crs": { "type": "name", "properties": { "name": "urn:ogc:def:crs:OGC:1.3:CRS84" } },
"features": [
{ "type": "Feature", "properties": { "Name": "Fire Detection Centroid ", "Description": "<b>Latitude: <\/b> 45.08915<br\/>  <b>Longitude: <\/b> -75.58709<br\/>  <b>Detection Time: <\/b> 2024-03-20 16:47 UTC<br\/>  <b>Sensor: <\/b> NOAA-20 VIIRS<br\/> <b>Confidence: <\/b> Nominal<br\/>  <b>Day\/Night: <\/b> Day<br\/> <b>Scan: <\/b> 0.5 km<br\/> <b>Track: <\/b> 0.7 km<br\/> <b>FRP: <\/b> 3.46 MW<br\/> <b>Brightness: <\/b> 328.79 K" }, "geometry": { "type": "Point", "coordinates": [ -75.58709, 45.08915, 0.0 ] } },
{ "type": "Feature", "properties": { "Name": "Fire Detection Centroid ", "Description": "<b>Latitude: <\/b> 20.83073<br\/>  <b>Longitude: <\/b> -156.42537<br\/>  <b>Detection Time: <\/b> 2024-03-20 12:14 UTC<br\/>  <b>Sensor: <\/b> NOAA-20 VIIRS<br\/> <b>Confidence: <\/b> Nominal<br\/>  <b>Day\/Night: <\/b> Night<br\/> <b>Scan: <\/b> 0.4 km<br\/> <b>Track: <\/b> 0.4 km<br\/> <b>FRP: <\/b> 0.4 MW<br\/> <b>Brightness: <\/b> 296.34 K" }, "geometry": { "type": "Point", "coordinates": [ -156.42537, 20.83073, 0.0 ] } }
]
}
