{
"type": "FeatureCollection",
"crs": { "type": "name", "properties": { "name": "urn:ogc:def:crs:OGC:1.3:CRS84" } },
"features": [
{ "type": "Feature", "properties": { "Name": "Fire Detection Centroid ", "Description": "<b>Latitude: <\/b> 36.69542<br\/>  <b>Longitude: <\/b> -120.58265<br\/>  <b>Detection Time: <\/b> 2023-03-27 10:58 UTC<br\/>  <b>Sensor: <\/b> NOAA-20 VIIRS<br\/> <b>Confidence: <\/b> Nominal<br\/>  <b>Day\/Night: <\/b> Night<br\/> <b>Scan: <\/b> 0.68 km<br\/> <b>Track: <\/b> 0.74 km<br\/> <b>FRP: <\/b> 0.89 MW<br\/> <b>Brightness: <\/b> 296.86 K" }, "geometry": { "type": "Point", "coordinates": [ -120.58265, 36.69542, 0.0 ] } },
{ "type": "Feature", "properties": { "Name": "Fire Detection Centroid ", "Description": "<b>Latitude: <\/b> 38.60541<br\/>  <b>Longitude: <\/b> -120.52257<br\/>  <b>Detection Time: <\/b> 2023-03-27 10:58 UTC<br\/>  <b>Sensor: <\/b> NOAA-20 VIIRS<br\/> <b>Confidence: <\/b> Nominal<br\/>  <b>Day\/Night: <\/b> Night<br\/> <b>Scan: <\/b> 0.6 km<br\/> <b>Track: <\/b> 0.71 km<br\/> <b>FRP: <\/b> 1.24 MW<br\/> <b>Brightness: <\/b> 302.78 K" }, "geometry": { "type": "Point", "coordinates": [ -120.52257, 38.60541, 0.0 ] } },
{ "type": "Feature", "properties": { "Name": "Fire Detection Centroid ", "Description": "<b>Latitude: <\/b> 38.07172<br\/>  <b>Longitude: <\/b> -122.1408<br\/>  <b>Detection Time: <\/b> 2023-03-27 10:58 UTC<br\/>  <b>Sensor: <\/b> NOAA-20 VIIRS<br\/> <b>Confidence: <\/b> Nominal<br\/>  <b>Day\/Night: <\/b> Night<br\/> <b>Scan: <\/b> 0.52 km<br\/> <b>Track: <\/b> 0.67 km<br\/> <b>FRP: <\/b> 1.29 MW<br\/> <b>Brightness: <\/b> 297.46 K" }, "geometry": { "type": "Point", "coordinates": [ -122.1408, 38.07172, 0.0 ] } },
{ "type": "Feature", "properties": { "Name": "Fire Detection Centroid ", "Description": "<b>Latitude: <\/b> 38.01805<br\/>  <b>Longitude: <\/b> -122.11486<br\/>  <b>Detection Time: <\/b> 2023-03-27 10:58 UTC<br\/>  <b>Sensor: <\/b> NOAA-20 VIIRS<br\/> <b>Confidence: <\/b> Nominal<br\/>  <b>Day\/Night: <\/b> Night<br\/> <b>Scan: <\/b> 0.52 km<br\/> <b>Track: <\/b> 0.67 km<br\/> <b>FRP: <\/b> 2.06 MW<br\/> <b>Brightness: <\/b> 296.71 K" }, "geometry": { "type": "Point", "coordinates": [ -122.11486, 38.01805, 0.0 ] } },
{ "type": "Feature", "properties": { "Name": "Fire Detection Centroid ", "Description": "<b>Latitude: <\/b> 38.0158<br\/>  <b>Longitude: <\/b> -122.11057<br\/>  <b>Detection Time: <\/b> 2023-03-27 10:58 UTC<br\/>  <b>Sensor: <\/b> NOAA-20 VIIRS<br\/> <b>Confidence: <\/b> Nominal<br\/>  <b>Day\/Night: <\/b> Night<br\/> <b>Scan: <\/b> 0.52 km<br\/> <b>Track: <\/b> 0.67 km<br\/> <b>FRP: <\/b> 1.3 MW<br\/> <b>Brightness: <\/b> 295.4 K" }, "geometry": { "type": "Point", "coordinates": [ -122.11057, 38.0158, 0.0 ] } },
{ "type": "Feature", "properties": { "Name": "Fire Detection Centroid ", "Description": "<b>Latitude: <\/b> 46.38013<br\/>  <b>Longitude: <\/b> -120.19435<br\/>  <b>Detection Time: <\/b> 2023-03-27 10:56 UTC<br\/>  <b>Sensor: <\/b> NOAA-20 VIIRS<br\/> <b>Confidence: <\/b> Nominal<br\/>  <b>Day\/Night: <\/b> Night<br\/> <b>Scan: <\/b> 0.37 km<br\/> <b>Track: <\/b> 0.58 km<br\/> <b>FRP: <\/b> 1.16 MW<br\/> <b>Brightness: <\/b> 310.72 K" }, "geometry": { "type": "Point", "coordinates": [ -120.19435, 46.38013, 0.0 ] } }
]
}
