{
"type": "FeatureCollection",
"crs": { "type": "name", "properties": { "name": "urn:ogc:def:crs:OGC:1.3:CRS84" } },
"features": [
{ "type": "Feature", "properties": { "Name": "Fire Detection Centroid ", "Description": "<b>Latitude: <\/b> 19.40754<br\/>  <b>Longitude: <\/b> -155.28697<br\/>  <b>Detection Time: <\/b> 2023-08-06 11:32 UTC<br\/>  <b>Sensor: <\/b> NOAA-20 VIIRS<br\/> <b>Confidence: <\/b> Nominal<br\/>  <b>Day\/Night: <\/b> Night<br\/> <b>Scan: <\/b> 0.5 km<br\/> <b>Track: <\/b> 0.49 km<br\/> <b>FRP: <\/b> 7.22 MW<br\/> <b>Brightness: <\/b> 304.08 K" }, "geometry": { "type": "Point", "coordinates": [ -155.28697, 19.40754, 0.0 ] } },
{ "type": "Feature", "properties": { "Name": "Fire Detection Centroid ", "Description": "<b>Latitude: <\/b> 19.40503<br\/>  <b>Longitude: <\/b> -155.28458<br\/>  <b>Detection Time: <\/b> 2023-08-06 11:32 UTC<br\/>  <b>Sensor: <\/b> NOAA-20 VIIRS<br\/> <b>Confidence: <\/b> Nominal<br\/>  <b>Day\/Night: <\/b> Night<br\/> <b>Scan: <\/b> 0.5 km<br\/> <b>Track: <\/b> 0.49 km<br\/> <b>FRP: <\/b> 3.35 MW<br\/> <b>Brightness: <\/b> 306.2 K" }, "geometry": { "type": "Point", "coordinates": [ -155.28458, 19.40503, 0.0 ] } },
{ "type": "Feature", "properties": { "Name": "Fire Detection Centroid ", "Description": "<b>Latitude: <\/b> 42.41761<br\/>  <b>Longitude: <\/b> -124.12884<br\/>  <b>Detection Time: <\/b> 2023-08-06 11:23 UTC<br\/>  <b>Sensor: <\/b> NOAA-20 VIIRS<br\/> <b>Confidence: <\/b> Nominal<br\/>  <b>Day\/Night: <\/b> Night<br\/> <b>Scan: <\/b> 0.64 km<br\/> <b>Track: <\/b> 0.72 km<br\/> <b>FRP: <\/b> 0.36 MW<br\/> <b>Brightness: <\/b> 295.15 K" }, "geometry": { "type": "Point", "coordinates": [ -124.12884, 42.41761, 0.0 ] } },
{ "type": "Feature", "properties": { "Name": "Fire Detection Centroid ", "Description": "<b>Latitude: <\/b> 42.4597<br\/>  <b>Longitude: <\/b> -124.08218<br\/>  <b>Detection Time: <\/b> 2023-08-06 11:23 UTC<br\/>  <b>Sensor: <\/b> NOAA-20 VIIRS<br\/> <b>Confidence: <\/b> Nominal<br\/>  <b>Day\/Night: <\/b> Night<br\/> <b>Scan: <\/b> 0.64 km<br\/> <b>Track: <\/b> 0.72 km<br\/> <b>FRP: <\/b> 0.56 MW<br\/> <b>Brightness: <\/b> 296.03 K" }, "geometry": { "type": "Point", "coordinates": [ -124.08218, 42.4597, 0.0 ] } }
]
}
