{
"type": "FeatureCollection",
"crs": { "type": "name", "properties": { "name": "urn:ogc:def:crs:OGC:1.3:CRS84" } },
"features": [
{ "type": "Feature", "properties": { "Name": "Fire Detection Centroid ", "Description": "<b>Latitude: <\/b> 43.26614<br\/>  <b>Longitude: <\/b> -79.81407<br\/>  <b>Detection Time: <\/b> 2023-02-01 06:06 UTC<br\/>  <b>Sensor: <\/b> NOAA-20 VIIRS<br\/> <b>Confidence: <\/b> Nominal<br\/>  <b>Day\/Night: <\/b> Night<br\/> <b>Scan: <\/b> 0.7 km<br\/> <b>Track: <\/b> 0.7 km<br\/> <b>FRP: <\/b> 3.11 MW<br\/> <b>Brightness: <\/b> 300.56 K" }, "geometry": { "type": "Point", "coordinates": [ -79.81407, 43.26614, 0.0 ] } },
{ "type": "Feature", "properties": { "Name": "Fire Detection Centroid ", "Description": "<b>Latitude: <\/b> 42.80594<br\/>  <b>Longitude: <\/b> -80.10275<br\/>  <b>Detection Time: <\/b> 2023-02-01 06:06 UTC<br\/>  <b>Sensor: <\/b> NOAA-20 VIIRS<br\/> <b>Confidence: <\/b> Nominal<br\/>  <b>Day\/Night: <\/b> Night<br\/> <b>Scan: <\/b> 0.7 km<br\/> <b>Track: <\/b> 0.8 km<br\/> <b>FRP: <\/b> 3.69 MW<br\/> <b>Brightness: <\/b> 318.46 K" }, "geometry": { "type": "Point", "coordinates": [ -80.10275, 42.80594, 0.0 ] } },
{ "type": "Feature", "properties": { "Name": "Fire Detection Centroid ", "Description": "<b>Latitude: <\/b> 45.27994<br\/>  <b>Longitude: <\/b> -66.01615<br\/>  <b>Detection Time: <\/b> 2023-02-01 06:05 UTC<br\/>  <b>Sensor: <\/b> NOAA-20 VIIRS<br\/> <b>Confidence: <\/b> Nominal<br\/>  <b>Day\/Night: <\/b> Night<br\/> <b>Scan: <\/b> 0.5 km<br\/> <b>Track: <\/b> 0.4 km<br\/> <b>FRP: <\/b> 1.33 MW<br\/> <b>Brightness: <\/b> 295.2 K" }, "geometry": { "type": "Point", "coordinates": [ -66.01615, 45.27994, 0.0 ] } }
]
}
