{
"type": "FeatureCollection",
"crs": { "type": "name", "properties": { "name": "urn:ogc:def:crs:OGC:1.3:CRS84" } },
"features": [
{ "type": "Feature", "properties": { "Name": "Fire Detection Centroid ", "Description": "<b>Latitude: <\/b> 17.97832<br\/>  <b>Longitude: <\/b> -67.0382<br\/>  <b>Detection Time: <\/b> 2024-01-10 05:42 UTC<br\/>  <b>Sensor: <\/b> NOAA-20 VIIRS<br\/> <b>Confidence: <\/b> Nominal<br\/>  <b>Day\/Night: <\/b> Night<br\/> <b>Scan: <\/b> 0.4 km<br\/> <b>Track: <\/b> 0.5 km<br\/> <b>FRP: <\/b> 0.9 MW<br\/> <b>Brightness: <\/b> 305.16 K" }, "geometry": { "type": "Point", "coordinates": [ -67.0382, 17.97832, 0.0 ] } },
{ "type": "Feature", "properties": { "Name": "Fire Detection Centroid ", "Description": "<b>Latitude: <\/b> 18.44583<br\/>  <b>Longitude: <\/b> -71.23009<br\/>  <b>Detection Time: <\/b> 2024-01-10 05:42 UTC<br\/>  <b>Sensor: <\/b> NOAA-20 VIIRS<br\/> <b>Confidence: <\/b> Nominal<br\/>  <b>Day\/Night: <\/b> Night<br\/> <b>Scan: <\/b> 0.4 km<br\/> <b>Track: <\/b> 0.6 km<br\/> <b>FRP: <\/b> 0.76 MW<br\/> <b>Brightness: <\/b> 302.91 K" }, "geometry": { "type": "Point", "coordinates": [ -71.23009, 18.44583, 0.0 ] } }
]
}
