{
"type": "FeatureCollection",
"crs": { "type": "name", "properties": { "name": "urn:ogc:def:crs:OGC:1.3:CRS84" } },
"features": [
{ "type": "Feature", "properties": { "Name": "Fire Detection Centroid ", "Description": "<b>Latitude: <\/b> 19.41245<br\/>  <b>Longitude: <\/b> -155.28108<br\/>  <b>Detection Time: <\/b> 2023-01-22 23:56 UTC<br\/>  <b>Sensor: <\/b> NOAA-20 VIIRS<br\/> <b>Confidence: <\/b> Nominal<br\/>  <b>Day\/Night: <\/b> Day<br\/> <b>Scan: <\/b> 0.42 km<br\/> <b>Track: <\/b> 0.45 km<br\/> <b>FRP: <\/b> 51.43 MW<br\/> <b>Brightness: <\/b> 336.05 K" }, "geometry": { "type": "Point", "coordinates": [ -155.28108, 19.41245, 0.0 ] } },
{ "type": "Feature", "properties": { "Name": "Fire Detection Centroid ", "Description": "<b>Latitude: <\/b> 19.39675<br\/>  <b>Longitude: <\/b> -155.271<br\/>  <b>Detection Time: <\/b> 2023-01-22 23:56 UTC<br\/>  <b>Sensor: <\/b> NOAA-20 VIIRS<br\/> <b>Confidence: <\/b> Nominal<br\/>  <b>Day\/Night: <\/b> Day<br\/> <b>Scan: <\/b> 0.42 km<br\/> <b>Track: <\/b> 0.45 km<br\/> <b>FRP: <\/b> 4.77 MW<br\/> <b>Brightness: <\/b> 328.77 K" }, "geometry": { "type": "Point", "coordinates": [ -155.271, 19.39675, 0.0 ] } },
{ "type": "Feature", "properties": { "Name": "Fire Detection Centroid ", "Description": "<b>Latitude: <\/b> 19.40093<br\/>  <b>Longitude: <\/b> -155.27142<br\/>  <b>Detection Time: <\/b> 2023-01-22 23:56 UTC<br\/>  <b>Sensor: <\/b> NOAA-20 VIIRS<br\/> <b>Confidence: <\/b> Nominal<br\/>  <b>Day\/Night: <\/b> Day<br\/> <b>Scan: <\/b> 0.42 km<br\/> <b>Track: <\/b> 0.45 km<br\/> <b>FRP: <\/b> 5.1 MW<br\/> <b>Brightness: <\/b> 332.98 K" }, "geometry": { "type": "Point", "coordinates": [ -155.27142, 19.40093, 0.0 ] } },
{ "type": "Feature", "properties": { "Name": "Fire Detection Centroid ", "Description": "<b>Latitude: <\/b> 19.40462<br\/>  <b>Longitude: <\/b> -155.27588<br\/>  <b>Detection Time: <\/b> 2023-01-22 23:56 UTC<br\/>  <b>Sensor: <\/b> NOAA-20 VIIRS<br\/> <b>Confidence: <\/b> Nominal<br\/>  <b>Day\/Night: <\/b> Day<br\/> <b>Scan: <\/b> 0.42 km<br\/> <b>Track: <\/b> 0.45 km<br\/> <b>FRP: <\/b> 34.93 MW<br\/> <b>Brightness: <\/b> 343.56 K" }, "geometry": { "type": "Point", "coordinates": [ -155.27588, 19.40462, 0.0 ] } },
{ "type": "Feature", "properties": { "Name": "Fire Detection Centroid ", "Description": "<b>Latitude: <\/b> 19.40413<br\/>  <b>Longitude: <\/b> -155.27989<br\/>  <b>Detection Time: <\/b> 2023-01-22 23:56 UTC<br\/>  <b>Sensor: <\/b> NOAA-20 VIIRS<br\/> <b>Confidence: <\/b> Nominal<br\/>  <b>Day\/Night: <\/b> Day<br\/> <b>Scan: <\/b> 0.42 km<br\/> <b>Track: <\/b> 0.45 km<br\/> <b>FRP: <\/b> 34.93 MW<br\/> <b>Brightness: <\/b> 344.08 K" }, "geometry": { "type": "Point", "coordinates": [ -155.27989, 19.40413, 0.0 ] } },
{ "type": "Feature", "properties": { "Name": "Fire Detection Centroid ", "Description": "<b>Latitude: <\/b> 19.40878<br\/>  <b>Longitude: <\/b> -155.27643<br\/>  <b>Detection Time: <\/b> 2023-01-22 23:56 UTC<br\/>  <b>Sensor: <\/b> NOAA-20 VIIRS<br\/> <b>Confidence: <\/b> Low<br\/>  <b>Day\/Night: <\/b> Day<br\/> <b>Scan: <\/b> 0.42 km<br\/> <b>Track: <\/b> 0.45 km<br\/> <b>FRP: <\/b> 51.43 MW<br\/> <b>Brightness: <\/b> 329.14 K" }, "geometry": { "type": "Point", "coordinates": [ -155.27643, 19.40878, 0.0 ] } }
]
}
