{
"type": "FeatureCollection",
"crs": { "type": "name", "properties": { "name": "urn:ogc:def:crs:OGC:1.3:CRS84" } },
"features": [
{ "type": "Feature", "properties": { "Name": "Fire Detection Centroid ", "Description": "<b>Latitude: <\/b> 37.12061<br\/>  <b>Longitude: <\/b> -119.61762<br\/>  <b>Detection Time: <\/b> 2024-03-10 21:36 UTC<br\/>  <b>Sensor: <\/b> NOAA-20 VIIRS<br\/> <b>Confidence: <\/b> Nominal<br\/>  <b>Day\/Night: <\/b> Day<br\/> <b>Scan: <\/b> 0.6 km<br\/> <b>Track: <\/b> 0.5 km<br\/> <b>FRP: <\/b> 3.21 MW<br\/> <b>Brightness: <\/b> 328.13 K" }, "geometry": { "type": "Point", "coordinates": [ -119.61762, 37.12061, 0.0 ] } },
{ "type": "Feature", "properties": { "Name": "Fire Detection Centroid ", "Description": "<b>Latitude: <\/b> 37.10575<br\/>  <b>Longitude: <\/b> -119.61493<br\/>  <b>Detection Time: <\/b> 2024-03-10 21:36 UTC<br\/>  <b>Sensor: <\/b> NOAA-20 VIIRS<br\/> <b>Confidence: <\/b> Nominal<br\/>  <b>Day\/Night: <\/b> Day<br\/> <b>Scan: <\/b> 0.61 km<br\/> <b>Track: <\/b> 0.53 km<br\/> <b>FRP: <\/b> 3.22 MW<br\/> <b>Brightness: <\/b> 328.13 K" }, "geometry": { "type": "Point", "coordinates": [ -119.61493, 37.10575, 0.0 ] } },
{ "type": "Feature", "properties": { "Name": "Fire Detection Centroid ", "Description": "<b>Latitude: <\/b> 28.18031<br\/>  <b>Longitude: <\/b> -111.28164<br\/>  <b>Detection Time: <\/b> 2024-03-10 21:33 UTC<br\/>  <b>Sensor: <\/b> NOAA-20 VIIRS<br\/> <b>Confidence: <\/b> Nominal<br\/>  <b>Day\/Night: <\/b> Day<br\/> <b>Scan: <\/b> 0.8 km<br\/> <b>Track: <\/b> 0.8 km<br\/> <b>FRP: <\/b> 6.64 MW<br\/> <b>Brightness: <\/b> 343.49 K" }, "geometry": { "type": "Point", "coordinates": [ -111.28164, 28.18031, 0.0 ] } },
{ "type": "Feature", "properties": { "Name": "Fire Detection Centroid ", "Description": "<b>Latitude: <\/b> 28.38484<br\/>  <b>Longitude: <\/b> -111.28841<br\/>  <b>Detection Time: <\/b> 2024-03-10 21:33 UTC<br\/>  <b>Sensor: <\/b> NOAA-20 VIIRS<br\/> <b>Confidence: <\/b> Nominal<br\/>  <b>Day\/Night: <\/b> Day<br\/> <b>Scan: <\/b> 0.8 km<br\/> <b>Track: <\/b> 0.8 km<br\/> <b>FRP: <\/b> 4.51 MW<br\/> <b>Brightness: <\/b> 335.98 K" }, "geometry": { "type": "Point", "coordinates": [ -111.28841, 28.38484, 0.0 ] } },
{ "type": "Feature", "properties": { "Name": "Fire Detection Centroid ", "Description": "<b>Latitude: <\/b> 28.30283<br\/>  <b>Longitude: <\/b> -111.28317<br\/>  <b>Detection Time: <\/b> 2024-03-10 21:33 UTC<br\/>  <b>Sensor: <\/b> NOAA-20 VIIRS<br\/> <b>Confidence: <\/b> Nominal<br\/>  <b>Day\/Night: <\/b> Day<br\/> <b>Scan: <\/b> 0.78 km<br\/> <b>Track: <\/b> 0.78 km<br\/> <b>FRP: <\/b> 6.65 MW<br\/> <b>Brightness: <\/b> 343.49 K" }, "geometry": { "type": "Point", "coordinates": [ -111.28317, 28.30283, 0.0 ] } },
{ "type": "Feature", "properties": { "Name": "Fire Detection Centroid ", "Description": "<b>Latitude: <\/b> 28.30483<br\/>  <b>Longitude: <\/b> -111.28405<br\/>  <b>Detection Time: <\/b> 2024-03-10 21:33 UTC<br\/>  <b>Sensor: <\/b> NOAA-20 VIIRS<br\/> <b>Confidence: <\/b> Nominal<br\/>  <b>Day\/Night: <\/b> Day<br\/> <b>Scan: <\/b> 0.78 km<br\/> <b>Track: <\/b> 0.78 km<br\/> <b>FRP: <\/b> 4.52 MW<br\/> <b>Brightness: <\/b> 335.98 K" }, "geometry": { "type": "Point", "coordinates": [ -111.28405, 28.30483, 0.0 ] } }
]
}
