{
"type": "FeatureCollection",
"crs": { "type": "name", "properties": { "name": "urn:ogc:def:crs:OGC:1.3:CRS84" } },
"features": [
{ "type": "Feature", "properties": { "Name": "Fire Detection Centroid ", "Description": "<b>Latitude: <\/b> 19.59902<br\/>  <b>Longitude: <\/b> -155.50317<br\/>  <b>Detection Time: <\/b> 2023-03-20 11:36 UTC<br\/>  <b>Sensor: <\/b> NOAA-20 VIIRS<br\/> <b>Confidence: <\/b> Nominal<br\/>  <b>Day\/Night: <\/b> Night<br\/> <b>Scan: <\/b> 0.42 km<br\/> <b>Track: <\/b> 0.45 km<br\/> <b>FRP: <\/b> 1.84 MW<br\/> <b>Brightness: <\/b> 299.65 K" }, "geometry": { "type": "Point", "coordinates": [ -155.50317, 19.59902, 0.0 ] } },
{ "type": "Feature", "properties": { "Name": "Fire Detection Centroid ", "Description": "<b>Latitude: <\/b> 19.57855<br\/>  <b>Longitude: <\/b> -155.50824<br\/>  <b>Detection Time: <\/b> 2023-03-20 11:36 UTC<br\/>  <b>Sensor: <\/b> NOAA-20 VIIRS<br\/> <b>Confidence: <\/b> Nominal<br\/>  <b>Day\/Night: <\/b> Night<br\/> <b>Scan: <\/b> 0.42 km<br\/> <b>Track: <\/b> 0.45 km<br\/> <b>FRP: <\/b> 2.16 MW<br\/> <b>Brightness: <\/b> 295.34 K" }, "geometry": { "type": "Point", "coordinates": [ -155.50824, 19.57855, 0.0 ] } },
{ "type": "Feature", "properties": { "Name": "Fire Detection Centroid ", "Description": "<b>Latitude: <\/b> 19.58645<br\/>  <b>Longitude: <\/b> -155.50388<br\/>  <b>Detection Time: <\/b> 2023-03-20 11:36 UTC<br\/>  <b>Sensor: <\/b> NOAA-20 VIIRS<br\/> <b>Confidence: <\/b> Nominal<br\/>  <b>Day\/Night: <\/b> Night<br\/> <b>Scan: <\/b> 0.42 km<br\/> <b>Track: <\/b> 0.45 km<br\/> <b>FRP: <\/b> 1.65 MW<br\/> <b>Brightness: <\/b> 296.36 K" }, "geometry": { "type": "Point", "coordinates": [ -155.50388, 19.58645, 0.0 ] } }
]
}
