{
"type": "FeatureCollection",
"crs": { "type": "name", "properties": { "name": "urn:ogc:def:crs:OGC:1.3:CRS84" } },
"features": [
{ "type": "Feature", "properties": { "Name": "Fire Detection Centroid ", "Description": "<b>Latitude: <\/b> 36.35796<br\/>  <b>Longitude: <\/b> -76.81563<br\/>  <b>Detection Time: <\/b> 2023-01-06 05:57 UTC<br\/>  <b>Sensor: <\/b> NOAA-20 VIIRS<br\/> <b>Confidence: <\/b> Nominal<br\/>  <b>Day\/Night: <\/b> Night<br\/> <b>Scan: <\/b> 0.66 km<br\/> <b>Track: <\/b> 0.73 km<br\/> <b>FRP: <\/b> 1.95 MW<br\/> <b>Brightness: <\/b> 308.28 K" }, "geometry": { "type": "Point", "coordinates": [ -76.81563, 36.35796, 0.0 ] } },
{ "type": "Feature", "properties": { "Name": "Fire Detection Centroid ", "Description": "<b>Latitude: <\/b> 36.3596<br\/>  <b>Longitude: <\/b> -76.8078<br\/>  <b>Detection Time: <\/b> 2023-01-06 05:57 UTC<br\/>  <b>Sensor: <\/b> NOAA-20 VIIRS<br\/> <b>Confidence: <\/b> Nominal<br\/>  <b>Day\/Night: <\/b> Night<br\/> <b>Scan: <\/b> 0.66 km<br\/> <b>Track: <\/b> 0.73 km<br\/> <b>FRP: <\/b> 1.95 MW<br\/> <b>Brightness: <\/b> 301.7 K" }, "geometry": { "type": "Point", "coordinates": [ -76.8078, 36.3596, 0.0 ] } },
{ "type": "Feature", "properties": { "Name": "Fire Detection Centroid ", "Description": "<b>Latitude: <\/b> 36.35976<br\/>  <b>Longitude: <\/b> -76.81528<br\/>  <b>Detection Time: <\/b> 2023-01-06 05:57 UTC<br\/>  <b>Sensor: <\/b> NOAA-20 VIIRS<br\/> <b>Confidence: <\/b> Nominal<br\/>  <b>Day\/Night: <\/b> Night<br\/> <b>Scan: <\/b> 0.66 km<br\/> <b>Track: <\/b> 0.73 km<br\/> <b>FRP: <\/b> 2.53 MW<br\/> <b>Brightness: <\/b> 311.65 K" }, "geometry": { "type": "Point", "coordinates": [ -76.81528, 36.35976, 0.0 ] } },
{ "type": "Feature", "properties": { "Name": "Fire Detection Centroid ", "Description": "<b>Latitude: <\/b> 36.35776<br\/>  <b>Longitude: <\/b> -76.80815<br\/>  <b>Detection Time: <\/b> 2023-01-06 05:57 UTC<br\/>  <b>Sensor: <\/b> NOAA-20 VIIRS<br\/> <b>Confidence: <\/b> Nominal<br\/>  <b>Day\/Night: <\/b> Night<br\/> <b>Scan: <\/b> 0.66 km<br\/> <b>Track: <\/b> 0.73 km<br\/> <b>FRP: <\/b> 1.95 MW<br\/> <b>Brightness: <\/b> 306.74 K" }, "geometry": { "type": "Point", "coordinates": [ -76.80815, 36.35776, 0.0 ] } },
{ "type": "Feature", "properties": { "Name": "Fire Detection Centroid ", "Description": "<b>Latitude: <\/b> 39.94008<br\/>  <b>Longitude: <\/b> -76.8216<br\/>  <b>Detection Time: <\/b> 2023-01-06 05:54 UTC<br\/>  <b>Sensor: <\/b> NOAA-20 VIIRS<br\/> <b>Confidence: <\/b> Nominal<br\/>  <b>Day\/Night: <\/b> Night<br\/> <b>Scan: <\/b> 0.69 km<br\/> <b>Track: <\/b> 0.74 km<br\/> <b>FRP: <\/b> 1.17 MW<br\/> <b>Brightness: <\/b> 297.1 K" }, "geometry": { "type": "Point", "coordinates": [ -76.8216, 39.94008, 0.0 ] } }
]
}
