{
"type": "FeatureCollection",
"crs": { "type": "name", "properties": { "name": "urn:ogc:def:crs:OGC:1.3:CRS84" } },
"features": [
{ "type": "Feature", "properties": { "Name": "Fire Detection Centroid ", "Description": "<b>Latitude: <\/b> 18.6574<br\/>  <b>Longitude: <\/b> -72.29593<br\/>  <b>Detection Time: <\/b> 2022-12-27 05:47 UTC<br\/>  <b>Sensor: <\/b> NOAA-20 VIIRS<br\/> <b>Confidence: <\/b> Nominal<br\/>  <b>Day\/Night: <\/b> Night<br\/> <b>Scan: <\/b> 0.4 km<br\/> <b>Track: <\/b> 0.6 km<br\/> <b>FRP: <\/b> 1.16 MW<br\/> <b>Brightness: <\/b> 312.09 K" }, "geometry": { "type": "Point", "coordinates": [ -72.29593, 18.6574, 0.0 ] } }
]
}
