{
"type": "FeatureCollection",
"crs": { "type": "name", "properties": { "name": "urn:ogc:def:crs:OGC:1.3:CRS84" } },
"features": [
{ "type": "Feature", "properties": { "Name": "Fire Detection Centroid ", "Description": "<b>Latitude: </b> 19.4069<br/>  <b>Longitude: </b> -155.2912<br/>  <b>Detection Time: </b> 2022-06-18 00:05 UTC<br/>  <b>Sensor: </b> NOAA-20 VIIRS<br/> <b>Confidence: </b> Nominal<br/>  <b>Day/Night: </b> Day<br/> <b>Scan: </b> 0.53 km<br/> <b>Track: </b> 0.5 km<br/> <b>FRP: </b> 16.83 MW<br/> <b>Brightness: </b> 346.21 K" }, "geometry": { "type": "Point", "coordinates": [ -155.2912, 19.4069, 0.0 ] } },
{ "type": "Feature", "properties": { "Name": "Fire Detection Centroid ", "Description": "<b>Latitude: </b> 19.40289<br/>  <b>Longitude: </b> -155.28523<br/>  <b>Detection Time: </b> 2022-06-18 00:05 UTC<br/>  <b>Sensor: </b> NOAA-20 VIIRS<br/> <b>Confidence: </b> Nominal<br/>  <b>Day/Night: </b> Day<br/> <b>Scan: </b> 0.53 km<br/> <b>Track: </b> 0.5 km<br/> <b>FRP: </b> 17.36 MW<br/> <b>Brightness: </b> 349.4 K" }, "geometry": { "type": "Point", "coordinates": [ -155.28523, 19.40289, 0.0 ] } },
{ "type": "Feature", "properties": { "Name": "Fire Detection Centroid ", "Description": "<b>Latitude: </b> 19.40347<br/>  <b>Longitude: </b> -155.28011<br/>  <b>Detection Time: </b> 2022-06-18 00:05 UTC<br/>  <b>Sensor: </b> NOAA-20 VIIRS<br/> <b>Confidence: </b> Nominal<br/>  <b>Day/Night: </b> Day<br/> <b>Scan: </b> 0.53 km<br/> <b>Track: </b> 0.5 km<br/> <b>FRP: </b> 17.36 MW<br/> <b>Brightness: </b> 341.9 K" }, "geometry": { "type": "Point", "coordinates": [ -155.28011, 19.40347, 0.0 ] } },
{ "type": "Feature", "properties": { "Name": "Fire Detection Centroid ", "Description": "<b>Latitude: </b> 19.39823<br/>  <b>Longitude: </b> -155.28482<br/>  <b>Detection Time: </b> 2022-06-18 00:05 UTC<br/>  <b>Sensor: </b> NOAA-20 VIIRS<br/> <b>Confidence: </b> Nominal<br/>  <b>Day/Night: </b> Day<br/> <b>Scan: </b> 0.53 km<br/> <b>Track: </b> 0.5 km<br/> <b>FRP: </b> 17.36 MW<br/> <b>Brightness: </b> 325.47 K" }, "geometry": { "type": "Point", "coordinates": [ -155.28482, 19.39823, 0.0 ] } },
{ "type": "Feature", "properties": { "Name": "Fire Detection Centroid ", "Description": "<b>Latitude: </b> 19.39882<br/>  <b>Longitude: </b> -155.27969<br/>  <b>Detection Time: </b> 2022-06-18 00:05 UTC<br/>  <b>Sensor: </b> NOAA-20 VIIRS<br/> <b>Confidence: </b> Nominal<br/>  <b>Day/Night: </b> Day<br/> <b>Scan: </b> 0.53 km<br/> <b>Track: </b> 0.5 km<br/> <b>FRP: </b> 17.36 MW<br/> <b>Brightness: </b> 325.78 K" }, "geometry": { "type": "Point", "coordinates": [ -155.27969, 19.39882, 0.0 ] } },
{ "type": "Feature", "properties": { "Name": "Fire Detection Centroid ", "Description": "<b>Latitude: </b> 19.40811<br/>  <b>Longitude: </b> -155.28069<br/>  <b>Detection Time: </b> 2022-06-18 00:05 UTC<br/>  <b>Sensor: </b> NOAA-20 VIIRS<br/> <b>Confidence: </b> Nominal<br/>  <b>Day/Night: </b> Day<br/> <b>Scan: </b> 0.53 km<br/> <b>Track: </b> 0.5 km<br/> <b>FRP: </b> 16.49 MW<br/> <b>Brightness: </b> 350.71 K" }, "geometry": { "type": "Point", "coordinates": [ -155.28069, 19.40811, 0.0 ] } },
{ "type": "Feature", "properties": { "Name": "Fire Detection Centroid ", "Description": "<b>Latitude: </b> 19.40751<br/>  <b>Longitude: </b> -155.28587<br/>  <b>Detection Time: </b> 2022-06-18 00:05 UTC<br/>  <b>Sensor: </b> NOAA-20 VIIRS<br/> <b>Confidence: </b> High<br/>  <b>Day/Night: </b> Day<br/> <b>Scan: </b> 0.53 km<br/> <b>Track: </b> 0.5 km<br/> <b>FRP: </b> 16.49 MW<br/> <b>Brightness: </b> 367 K" }, "geometry": { "type": "Point", "coordinates": [ -155.28587, 19.40751, 0.0 ] } },
{ "type": "Feature", "properties": { "Name": "Fire Detection Centroid ", "Description": "<b>Latitude: </b> 19.40228<br/>  <b>Longitude: </b> -155.2905<br/>  <b>Detection Time: </b> 2022-06-18 00:05 UTC<br/>  <b>Sensor: </b> NOAA-20 VIIRS<br/> <b>Confidence: </b> Nominal<br/>  <b>Day/Night: </b> Day<br/> <b>Scan: </b> 0.53 km<br/> <b>Track: </b> 0.5 km<br/> <b>FRP: </b> 21.95 MW<br/> <b>Brightness: </b> 344.13 K" }, "geometry": { "type": "Point", "coordinates": [ -155.2905, 19.40228, 0.0 ] } }
]
}
