{
"type": "FeatureCollection",
"crs": { "type": "name", "properties": { "name": "urn:ogc:def:crs:OGC:1.3:CRS84" } },
"features": [
{ "type": "Feature", "properties": { "Name": "Fire Detection Centroid ", "Description": "<b>Latitude: <\/b> 20.86133<br\/>  <b>Longitude: <\/b> -156.4202<br\/>  <b>Detection Time: <\/b> 2024-04-09 12:14 UTC<br\/>  <b>Sensor: <\/b> NOAA-20 VIIRS<br\/> <b>Confidence: <\/b> Nominal<br\/>  <b>Day\/Night: <\/b> Night<br\/> <b>Scan: <\/b> 0.43 km<br\/> <b>Track: <\/b> 0.38 km<br\/> <b>FRP: <\/b> 0.52 MW<br\/> <b>Brightness: <\/b> 298.85 K" }, "geometry": { "type": "Point", "coordinates": [ -156.4202, 20.86133, 0.0 ] } }
]
}
