{
"type": "FeatureCollection",
"crs": { "type": "name", "properties": { "name": "urn:ogc:def:crs:OGC:1.3:CRS84" } },
"features": [
{ "type": "Feature", "properties": { "Name": "Fire Detection Centroid ", "Description": "<b>Latitude: <\/b> 19.51493<br\/>  <b>Longitude: <\/b> -155.52687<br\/>  <b>Detection Time: <\/b> 2022-12-12 23:25 UTC<br\/>  <b>Sensor: <\/b> NOAA-20 VIIRS<br\/> <b>Confidence: <\/b> Nominal<br\/>  <b>Day\/Night: <\/b> Day<br\/> <b>Scan: <\/b> 0.4 km<br\/> <b>Track: <\/b> 0.4 km<br\/> <b>FRP: <\/b> 9.6 MW<br\/> <b>Brightness: <\/b> 326.18 K" }, "geometry": { "type": "Point", "coordinates": [ -155.52687, 19.51493, 0.0 ] } },
{ "type": "Feature", "properties": { "Name": "Fire Detection Centroid ", "Description": "<b>Latitude: <\/b> 19.52649<br\/>  <b>Longitude: <\/b> -155.52112<br\/>  <b>Detection Time: <\/b> 2022-12-12 23:25 UTC<br\/>  <b>Sensor: <\/b> NOAA-20 VIIRS<br\/> <b>Confidence: <\/b> Nominal<br\/>  <b>Day\/Night: <\/b> Day<br\/> <b>Scan: <\/b> 0.4 km<br\/> <b>Track: <\/b> 0.4 km<br\/> <b>FRP: <\/b> 6.76 MW<br\/> <b>Brightness: <\/b> 330.25 K" }, "geometry": { "type": "Point", "coordinates": [ -155.52112, 19.52649, 0.0 ] } },
{ "type": "Feature", "properties": { "Name": "Fire Detection Centroid ", "Description": "<b>Latitude: <\/b> 19.52694<br\/>  <b>Longitude: <\/b> -155.52074<br\/>  <b>Detection Time: <\/b> 2022-12-12 23:24 UTC<br\/>  <b>Sensor: <\/b> NOAA-20 VIIRS<br\/> <b>Confidence: <\/b> Nominal<br\/>  <b>Day\/Night: <\/b> Day<br\/> <b>Scan: <\/b> 0.43 km<br\/> <b>Track: <\/b> 0.38 km<br\/> <b>FRP: <\/b> 6.83 MW<br\/> <b>Brightness: <\/b> 330.25 K" }, "geometry": { "type": "Point", "coordinates": [ -155.52074, 19.52694, 0.0 ] } },
{ "type": "Feature", "properties": { "Name": "Fire Detection Centroid ", "Description": "<b>Latitude: <\/b> 19.51539<br\/>  <b>Longitude: <\/b> -155.52647<br\/>  <b>Detection Time: <\/b> 2022-12-12 23:24 UTC<br\/>  <b>Sensor: <\/b> NOAA-20 VIIRS<br\/> <b>Confidence: <\/b> Nominal<br\/>  <b>Day\/Night: <\/b> Day<br\/> <b>Scan: <\/b> 0.43 km<br\/> <b>Track: <\/b> 0.38 km<br\/> <b>FRP: <\/b> 9.6 MW<br\/> <b>Brightness: <\/b> 326.18 K" }, "geometry": { "type": "Point", "coordinates": [ -155.52647, 19.51539, 0.0 ] } }
]
}
