{
"type": "FeatureCollection",
"crs": { "type": "name", "properties": { "name": "urn:ogc:def:crs:OGC:1.3:CRS84" } },
"features": [
{ "type": "Feature", "properties": { "Name": "Fire Detection Centroid ", "Description": "<b>Latitude: <\/b> 19.40978<br\/>  <b>Longitude: <\/b> -155.27858<br\/>  <b>Detection Time: <\/b> 2022-07-01 22:59 UTC<br\/>  <b>Sensor: <\/b> NOAA-20 VIIRS<br\/> <b>Confidence: <\/b> Nominal<br\/>  <b>Day\/Night: <\/b> Day<br\/> <b>Scan: <\/b> 0.62 km<br\/> <b>Track: <\/b> 0.54 km<br\/> <b>FRP: <\/b> 16.4 MW<br\/> <b>Brightness: <\/b> 340.44 K" }, "geometry": { "type": "Point", "coordinates": [ -155.27858, 19.40978, 0.0 ] } },
{ "type": "Feature", "properties": { "Name": "Fire Detection Centroid ", "Description": "<b>Latitude: <\/b> 19.40864<br\/>  <b>Longitude: <\/b> -155.28424<br\/>  <b>Detection Time: <\/b> 2022-07-01 22:59 UTC<br\/>  <b>Sensor: <\/b> NOAA-20 VIIRS<br\/> <b>Confidence: <\/b> Nominal<br\/>  <b>Day\/Night: <\/b> Day<br\/> <b>Scan: <\/b> 0.62 km<br\/> <b>Track: <\/b> 0.54 km<br\/> <b>FRP: <\/b> 7.18 MW<br\/> <b>Brightness: <\/b> 333.08 K" }, "geometry": { "type": "Point", "coordinates": [ -155.28424, 19.40864, 0.0 ] } },
{ "type": "Feature", "properties": { "Name": "Fire Detection Centroid ", "Description": "<b>Latitude: <\/b> 19.40492<br\/>  <b>Longitude: <\/b> -155.27753<br\/>  <b>Detection Time: <\/b> 2022-07-01 22:59 UTC<br\/>  <b>Sensor: <\/b> NOAA-20 VIIRS<br\/> <b>Confidence: <\/b> Nominal<br\/>  <b>Day\/Night: <\/b> Day<br\/> <b>Scan: <\/b> 0.62 km<br\/> <b>Track: <\/b> 0.54 km<br\/> <b>FRP: <\/b> 47.97 MW<br\/> <b>Brightness: <\/b> 343.55 K" }, "geometry": { "type": "Point", "coordinates": [ -155.27753, 19.40492, 0.0 ] } },
{ "type": "Feature", "properties": { "Name": "Fire Detection Centroid ", "Description": "<b>Latitude: <\/b> 19.40376<br\/>  <b>Longitude: <\/b> -155.28326<br\/>  <b>Detection Time: <\/b> 2022-07-01 22:59 UTC<br\/>  <b>Sensor: <\/b> NOAA-20 VIIRS<br\/> <b>Confidence: <\/b> Low<br\/>  <b>Day\/Night: <\/b> Day<br\/> <b>Scan: <\/b> 0.62 km<br\/> <b>Track: <\/b> 0.54 km<br\/> <b>FRP: <\/b> 111.83 MW<br\/> <b>Brightness: <\/b> 367 K" }, "geometry": { "type": "Point", "coordinates": [ -155.28326, 19.40376, 0.0 ] } }
]
}
