{
"type": "FeatureCollection",
"crs": { "type": "name", "properties": { "name": "urn:ogc:def:crs:OGC:1.3:CRS84" } },
"features": [
{ "type": "Feature", "properties": { "Name": "Fire Detection Centroid ", "Description": "<b>Latitude: <\/b> 19.66017<br\/>  <b>Longitude: <\/b> -71.08194<br\/>  <b>Detection Time: <\/b> 2023-02-19 05:35 UTC<br\/>  <b>Sensor: <\/b> NOAA-20 VIIRS<br\/> <b>Confidence: <\/b> Nominal<br\/>  <b>Day\/Night: <\/b> Night<br\/> <b>Scan: <\/b> 0.5 km<br\/> <b>Track: <\/b> 0.7 km<br\/> <b>FRP: <\/b> 0.89 MW<br\/> <b>Brightness: <\/b> 301.01 K" }, "geometry": { "type": "Point", "coordinates": [ -71.08194, 19.66017, 0.0 ] } },
{ "type": "Feature", "properties": { "Name": "Fire Detection Centroid ", "Description": "<b>Latitude: <\/b> 19.36532<br\/>  <b>Longitude: <\/b> -71.73611<br\/>  <b>Detection Time: <\/b> 2023-02-19 05:35 UTC<br\/>  <b>Sensor: <\/b> NOAA-20 VIIRS<br\/> <b>Confidence: <\/b> Nominal<br\/>  <b>Day\/Night: <\/b> Night<br\/> <b>Scan: <\/b> 0.6 km<br\/> <b>Track: <\/b> 0.7 km<br\/> <b>FRP: <\/b> 1.73 MW<br\/> <b>Brightness: <\/b> 316.16 K" }, "geometry": { "type": "Point", "coordinates": [ -71.73611, 19.36532, 0.0 ] } },
{ "type": "Feature", "properties": { "Name": "Fire Detection Centroid ", "Description": "<b>Latitude: <\/b> 19.23427<br\/>  <b>Longitude: <\/b> -72.34261<br\/>  <b>Detection Time: <\/b> 2023-02-19 05:35 UTC<br\/>  <b>Sensor: <\/b> NOAA-20 VIIRS<br\/> <b>Confidence: <\/b> Nominal<br\/>  <b>Day\/Night: <\/b> Night<br\/> <b>Scan: <\/b> 0.6 km<br\/> <b>Track: <\/b> 0.7 km<br\/> <b>FRP: <\/b> 0.81 MW<br\/> <b>Brightness: <\/b> 303.11 K" }, "geometry": { "type": "Point", "coordinates": [ -72.34261, 19.23427, 0.0 ] } },
{ "type": "Feature", "properties": { "Name": "Fire Detection Centroid ", "Description": "<b>Latitude: <\/b> 18.92764<br\/>  <b>Longitude: <\/b> -70.35749<br\/>  <b>Detection Time: <\/b> 2023-02-19 05:35 UTC<br\/>  <b>Sensor: <\/b> NOAA-20 VIIRS<br\/> <b>Confidence: <\/b> Nominal<br\/>  <b>Day\/Night: <\/b> Night<br\/> <b>Scan: <\/b> 0.5 km<br\/> <b>Track: <\/b> 0.6 km<br\/> <b>FRP: <\/b> 8.43 MW<br\/> <b>Brightness: <\/b> 333.24 K" }, "geometry": { "type": "Point", "coordinates": [ -70.35749, 18.92764, 0.0 ] } },
{ "type": "Feature", "properties": { "Name": "Fire Detection Centroid ", "Description": "<b>Latitude: <\/b> 18.9272<br\/>  <b>Longitude: <\/b> -70.35297<br\/>  <b>Detection Time: <\/b> 2023-02-19 05:35 UTC<br\/>  <b>Sensor: <\/b> NOAA-20 VIIRS<br\/> <b>Confidence: <\/b> Nominal<br\/>  <b>Day\/Night: <\/b> Night<br\/> <b>Scan: <\/b> 0.5 km<br\/> <b>Track: <\/b> 0.6 km<br\/> <b>FRP: <\/b> 8.43 MW<br\/> <b>Brightness: <\/b> 355.67 K" }, "geometry": { "type": "Point", "coordinates": [ -70.35297, 18.9272, 0.0 ] } },
{ "type": "Feature", "properties": { "Name": "Fire Detection Centroid ", "Description": "<b>Latitude: <\/b> 19.66017<br\/>  <b>Longitude: <\/b> -71.08194<br\/>  <b>Detection Time: <\/b> 2023-02-19 05:35 UTC<br\/>  <b>Sensor: <\/b> NOAA-20 VIIRS<br\/> <b>Confidence: <\/b> Nominal<br\/>  <b>Day\/Night: <\/b> Night<br\/> <b>Scan: <\/b> 0.5 km<br\/> <b>Track: <\/b> 0.7 km<br\/> <b>FRP: <\/b> 0.89 MW<br\/> <b>Brightness: <\/b> 301.01 K" }, "geometry": { "type": "Point", "coordinates": [ -71.08194, 19.66017, 0.0 ] } },
{ "type": "Feature", "properties": { "Name": "Fire Detection Centroid ", "Description": "<b>Latitude: <\/b> 18.07438<br\/>  <b>Longitude: <\/b> -66.58972<br\/>  <b>Detection Time: <\/b> 2023-02-19 05:35 UTC<br\/>  <b>Sensor: <\/b> NOAA-20 VIIRS<br\/> <b>Confidence: <\/b> Nominal<br\/>  <b>Day\/Night: <\/b> Night<br\/> <b>Scan: <\/b> 0.5 km<br\/> <b>Track: <\/b> 0.5 km<br\/> <b>FRP: <\/b> 2.2 MW<br\/> <b>Brightness: <\/b> 317.77 K" }, "geometry": { "type": "Point", "coordinates": [ -66.58972, 18.07438, 0.0 ] } },
{ "type": "Feature", "properties": { "Name": "Fire Detection Centroid ", "Description": "<b>Latitude: <\/b> 18.07723<br\/>  <b>Longitude: <\/b> -66.73121<br\/>  <b>Detection Time: <\/b> 2023-02-19 05:35 UTC<br\/>  <b>Sensor: <\/b> NOAA-20 VIIRS<br\/> <b>Confidence: <\/b> Nominal<br\/>  <b>Day\/Night: <\/b> Night<br\/> <b>Scan: <\/b> 0.5 km<br\/> <b>Track: <\/b> 0.5 km<br\/> <b>FRP: <\/b> 0.82 MW<br\/> <b>Brightness: <\/b> 301.7 K" }, "geometry": { "type": "Point", "coordinates": [ -66.73121, 18.07723, 0.0 ] } },
{ "type": "Feature", "properties": { "Name": "Fire Detection Centroid ", "Description": "<b>Latitude: <\/b> 48.18838<br\/>  <b>Longitude: <\/b> -64.92271<br\/>  <b>Detection Time: <\/b> 2023-02-19 05:26 UTC<br\/>  <b>Sensor: <\/b> NOAA-20 VIIRS<br\/> <b>Confidence: <\/b> Nominal<br\/>  <b>Day\/Night: <\/b> Night<br\/> <b>Scan: <\/b> 0.4 km<br\/> <b>Track: <\/b> 0.6 km<br\/> <b>FRP: <\/b> 0.73 MW<br\/> <b>Brightness: <\/b> 296.59 K" }, "geometry": { "type": "Point", "coordinates": [ -64.92271, 48.18838, 0.0 ] } }
]
}
