{
"type": "FeatureCollection",
"crs": { "type": "name", "properties": { "name": "urn:ogc:def:crs:OGC:1.3:CRS84" } },
"features": [
{ "type": "Feature", "properties": { "Name": "Fire Detection Centroid ", "Description": "<b>Latitude: <\/b> 18.93009<br\/>  <b>Longitude: <\/b> -70.35301<br\/>  <b>Detection Time: <\/b> 2023-05-10 05:36 UTC<br\/>  <b>Sensor: <\/b> NOAA-20 VIIRS<br\/> <b>Confidence: <\/b> Nominal<br\/>  <b>Day\/Night: <\/b> Night<br\/> <b>Scan: <\/b> 0.4 km<br\/> <b>Track: <\/b> 0.6 km<br\/> <b>FRP: <\/b> 7.8 MW<br\/> <b>Brightness: <\/b> 349.44 K" }, "geometry": { "type": "Point", "coordinates": [ -70.35301, 18.93009, 0.0 ] } },
{ "type": "Feature", "properties": { "Name": "Fire Detection Centroid ", "Description": "<b>Latitude: <\/b> 19.27935<br\/>  <b>Longitude: <\/b> -71.73415<br\/>  <b>Detection Time: <\/b> 2023-05-10 05:36 UTC<br\/>  <b>Sensor: <\/b> NOAA-20 VIIRS<br\/> <b>Confidence: <\/b> Nominal<br\/>  <b>Day\/Night: <\/b> Night<br\/> <b>Scan: <\/b> 0.6 km<br\/> <b>Track: <\/b> 0.7 km<br\/> <b>FRP: <\/b> 0.76 MW<br\/> <b>Brightness: <\/b> 297.15 K" }, "geometry": { "type": "Point", "coordinates": [ -71.73415, 19.27935, 0.0 ] } },
{ "type": "Feature", "properties": { "Name": "Fire Detection Centroid ", "Description": "<b>Latitude: <\/b> 19.28562<br\/>  <b>Longitude: <\/b> -71.73279<br\/>  <b>Detection Time: <\/b> 2023-05-10 05:36 UTC<br\/>  <b>Sensor: <\/b> NOAA-20 VIIRS<br\/> <b>Confidence: <\/b> Nominal<br\/>  <b>Day\/Night: <\/b> Night<br\/> <b>Scan: <\/b> 0.6 km<br\/> <b>Track: <\/b> 0.7 km<br\/> <b>FRP: <\/b> 0.63 MW<br\/> <b>Brightness: <\/b> 297.74 K" }, "geometry": { "type": "Point", "coordinates": [ -71.73279, 19.28562, 0.0 ] } },
{ "type": "Feature", "properties": { "Name": "Fire Detection Centroid ", "Description": "<b>Latitude: <\/b> 18.25186<br\/>  <b>Longitude: <\/b> -70.39231<br\/>  <b>Detection Time: <\/b> 2023-05-10 05:36 UTC<br\/>  <b>Sensor: <\/b> NOAA-20 VIIRS<br\/> <b>Confidence: <\/b> Nominal<br\/>  <b>Day\/Night: <\/b> Night<br\/> <b>Scan: <\/b> 0.4 km<br\/> <b>Track: <\/b> 0.6 km<br\/> <b>FRP: <\/b> 1.26 MW<br\/> <b>Brightness: <\/b> 305.68 K" }, "geometry": { "type": "Point", "coordinates": [ -70.39231, 18.25186, 0.0 ] } },
{ "type": "Feature", "properties": { "Name": "Fire Detection Centroid ", "Description": "<b>Latitude: <\/b> 18.29073<br\/>  <b>Longitude: <\/b> -70.54738<br\/>  <b>Detection Time: <\/b> 2023-05-10 05:36 UTC<br\/>  <b>Sensor: <\/b> NOAA-20 VIIRS<br\/> <b>Confidence: <\/b> Nominal<br\/>  <b>Day\/Night: <\/b> Night<br\/> <b>Scan: <\/b> 0.5 km<br\/> <b>Track: <\/b> 0.6 km<br\/> <b>FRP: <\/b> 0.75 MW<br\/> <b>Brightness: <\/b> 307.26 K" }, "geometry": { "type": "Point", "coordinates": [ -70.54738, 18.29073, 0.0 ] } },
{ "type": "Feature", "properties": { "Name": "Fire Detection Centroid ", "Description": "<b>Latitude: <\/b> 18.41117<br\/>  <b>Longitude: <\/b> -71.21291<br\/>  <b>Detection Time: <\/b> 2023-05-10 05:36 UTC<br\/>  <b>Sensor: <\/b> NOAA-20 VIIRS<br\/> <b>Confidence: <\/b> Nominal<br\/>  <b>Day\/Night: <\/b> Night<br\/> <b>Scan: <\/b> 0.5 km<br\/> <b>Track: <\/b> 0.7 km<br\/> <b>FRP: <\/b> 0.99 MW<br\/> <b>Brightness: <\/b> 306.36 K" }, "geometry": { "type": "Point", "coordinates": [ -71.21291, 18.41117, 0.0 ] } },
{ "type": "Feature", "properties": { "Name": "Fire Detection Centroid ", "Description": "<b>Latitude: <\/b> 18.40583<br\/>  <b>Longitude: <\/b> -71.21208<br\/>  <b>Detection Time: <\/b> 2023-05-10 05:36 UTC<br\/>  <b>Sensor: <\/b> NOAA-20 VIIRS<br\/> <b>Confidence: <\/b> Nominal<br\/>  <b>Day\/Night: <\/b> Night<br\/> <b>Scan: <\/b> 0.5 km<br\/> <b>Track: <\/b> 0.7 km<br\/> <b>FRP: <\/b> 0.83 MW<br\/> <b>Brightness: <\/b> 303.01 K" }, "geometry": { "type": "Point", "coordinates": [ -71.21208, 18.40583, 0.0 ] } },
{ "type": "Feature", "properties": { "Name": "Fire Detection Centroid ", "Description": "<b>Latitude: <\/b> 45.28097<br\/>  <b>Longitude: <\/b> -66.01582<br\/>  <b>Detection Time: <\/b> 2023-05-10 05:28 UTC<br\/>  <b>Sensor: <\/b> NOAA-20 VIIRS<br\/> <b>Confidence: <\/b> Nominal<br\/>  <b>Day\/Night: <\/b> Night<br\/> <b>Scan: <\/b> 0.4 km<br\/> <b>Track: <\/b> 0.6 km<br\/> <b>FRP: <\/b> 1.91 MW<br\/> <b>Brightness: <\/b> 297.72 K" }, "geometry": { "type": "Point", "coordinates": [ -66.01582, 45.28097, 0.0 ] } }
]
}
