{
"type": "FeatureCollection",
"crs": { "type": "name", "properties": { "name": "urn:ogc:def:crs:OGC:1.3:CRS84" } },
"features": [
{ "type": "Feature", "properties": { "Name": "Fire Detection Centroid ", "Description": "<b>Latitude: <\/b> 18.35542<br\/>  <b>Longitude: <\/b> -71.22521<br\/>  <b>Detection Time: <\/b> 2024-01-05 05:35 UTC<br\/>  <b>Sensor: <\/b> NOAA-20 VIIRS<br\/> <b>Confidence: <\/b> Nominal<br\/>  <b>Day\/Night: <\/b> Night<br\/> <b>Scan: <\/b> 0.5 km<br\/> <b>Track: <\/b> 0.7 km<br\/> <b>FRP: <\/b> 1.46 MW<br\/> <b>Brightness: <\/b> 307.41 K" }, "geometry": { "type": "Point", "coordinates": [ -71.22521, 18.35542, 0.0 ] } },
{ "type": "Feature", "properties": { "Name": "Fire Detection Centroid ", "Description": "<b>Latitude: <\/b> 18.35436<br\/>  <b>Longitude: <\/b> -71.22194<br\/>  <b>Detection Time: <\/b> 2024-01-05 05:35 UTC<br\/>  <b>Sensor: <\/b> NOAA-20 VIIRS<br\/> <b>Confidence: <\/b> Nominal<br\/>  <b>Day\/Night: <\/b> Night<br\/> <b>Scan: <\/b> 0.5 km<br\/> <b>Track: <\/b> 0.7 km<br\/> <b>FRP: <\/b> 1.07 MW<br\/> <b>Brightness: <\/b> 310.79 K" }, "geometry": { "type": "Point", "coordinates": [ -71.22194, 18.35436, 0.0 ] } }
]
}
