{
"type": "FeatureCollection",
"crs": { "type": "name", "properties": { "name": "urn:ogc:def:crs:OGC:1.3:CRS84" } },
"features": [
{ "type": "Feature", "properties": { "Name": "Fire Detection Centroid ", "Description": "<b>Latitude: <\/b> 21.49938<br\/>  <b>Longitude: <\/b> -158.04002<br\/>  <b>Detection Time: <\/b> 2023-08-17 13:04 UTC<br\/>  <b>Sensor: <\/b> NOAA-20 VIIRS<br\/> <b>Confidence: <\/b> Nominal<br\/>  <b>Day\/Night: <\/b> Night<br\/> <b>Scan: <\/b> 0.64 km<br\/> <b>Track: <\/b> 0.72 km<br\/> <b>FRP: <\/b> 1.53 MW<br\/> <b>Brightness: <\/b> 299.33 K" }, "geometry": { "type": "Point", "coordinates": [ -158.04002, 21.49938, 0.0 ] } },
{ "type": "Feature", "properties": { "Name": "Fire Detection Centroid ", "Description": "<b>Latitude: <\/b> 21.50115<br\/>  <b>Longitude: <\/b> -158.04068<br\/>  <b>Detection Time: <\/b> 2023-08-17 13:04 UTC<br\/>  <b>Sensor: <\/b> NOAA-20 VIIRS<br\/> <b>Confidence: <\/b> Nominal<br\/>  <b>Day\/Night: <\/b> Night<br\/> <b>Scan: <\/b> 0.64 km<br\/> <b>Track: <\/b> 0.72 km<br\/> <b>FRP: <\/b> 0.92 MW<br\/> <b>Brightness: <\/b> 298.8 K" }, "geometry": { "type": "Point", "coordinates": [ -158.04068, 21.50115, 0.0 ] } }
]
}
