{
"type": "FeatureCollection",
"crs": { "type": "name", "properties": { "name": "urn:ogc:def:crs:OGC:1.3:CRS84" } },
"features": [
{ "type": "Feature", "properties": { "Name": "Fire Detection Centroid ", "Description": "<b>Latitude: <\/b> 45.20583<br\/>  <b>Longitude: <\/b> -75.7706<br\/>  <b>Detection Time: <\/b> 2024-04-25 16:49 UTC<br\/>  <b>Sensor: <\/b> NOAA-20 VIIRS<br\/> <b>Confidence: <\/b> Nominal<br\/>  <b>Day\/Night: <\/b> Day<br\/> <b>Scan: <\/b> 0.5 km<br\/> <b>Track: <\/b> 0.7 km<br\/> <b>FRP: <\/b> 3.02 MW<br\/> <b>Brightness: <\/b> 330.28 K" }, "geometry": { "type": "Point", "coordinates": [ -75.7706, 45.20583, 0.0 ] } },
{ "type": "Feature", "properties": { "Name": "Fire Detection Centroid ", "Description": "<b>Latitude: <\/b> 43.93622<br\/>  <b>Longitude: <\/b> -71.32308<br\/>  <b>Detection Time: <\/b> 2024-04-25 16:48 UTC<br\/>  <b>Sensor: <\/b> NOAA-20 VIIRS<br\/> <b>Confidence: <\/b> Low<br\/>  <b>Day\/Night: <\/b> Day<br\/> <b>Scan: <\/b> 0.3 km<br\/> <b>Track: <\/b> 0.6 km<br\/> <b>FRP: <\/b> 7.62 MW<br\/> <b>Brightness: <\/b> 356.4 K" }, "geometry": { "type": "Point", "coordinates": [ -71.32308, 43.93622, 0.0 ] } },
{ "type": "Feature", "properties": { "Name": "Fire Detection Centroid ", "Description": "<b>Latitude: <\/b> 42.11953<br\/>  <b>Longitude: <\/b> -72.78528<br\/>  <b>Detection Time: <\/b> 2024-04-25 16:48 UTC<br\/>  <b>Sensor: <\/b> NOAA-20 VIIRS<br\/> <b>Confidence: <\/b> Nominal<br\/>  <b>Day\/Night: <\/b> Day<br\/> <b>Scan: <\/b> 0.4 km<br\/> <b>Track: <\/b> 0.6 km<br\/> <b>FRP: <\/b> 4.69 MW<br\/> <b>Brightness: <\/b> 340.03 K" }, "geometry": { "type": "Point", "coordinates": [ -72.78528, 42.11953, 0.0 ] } },
{ "type": "Feature", "properties": { "Name": "Fire Detection Centroid ", "Description": "<b>Latitude: <\/b> 43.94245<br\/>  <b>Longitude: <\/b> -71.3205<br\/>  <b>Detection Time: <\/b> 2024-04-25 16:48 UTC<br\/>  <b>Sensor: <\/b> NOAA-20 VIIRS<br\/> <b>Confidence: <\/b> Nominal<br\/>  <b>Day\/Night: <\/b> Day<br\/> <b>Scan: <\/b> 0.3 km<br\/> <b>Track: <\/b> 0.6 km<br\/> <b>FRP: <\/b> 7.62 MW<br\/> <b>Brightness: <\/b> 333.17 K" }, "geometry": { "type": "Point", "coordinates": [ -71.3205, 43.94245, 0.0 ] } },
{ "type": "Feature", "properties": { "Name": "Fire Detection Centroid ", "Description": "<b>Latitude: <\/b> 43.93506<br\/>  <b>Longitude: <\/b> -71.32736<br\/>  <b>Detection Time: <\/b> 2024-04-25 16:48 UTC<br\/>  <b>Sensor: <\/b> NOAA-20 VIIRS<br\/> <b>Confidence: <\/b> Nominal<br\/>  <b>Day\/Night: <\/b> Day<br\/> <b>Scan: <\/b> 0.3 km<br\/> <b>Track: <\/b> 0.6 km<br\/> <b>FRP: <\/b> 8.69 MW<br\/> <b>Brightness: <\/b> 344.75 K" }, "geometry": { "type": "Point", "coordinates": [ -71.32736, 43.93506, 0.0 ] } }
]
}
