{
"type": "FeatureCollection",
"crs": { "type": "name", "properties": { "name": "urn:ogc:def:crs:OGC:1.3:CRS84" } },
"features": [
{ "type": "Feature", "properties": { "Name": "Fire Detection Centroid ", "Description": "<b>Latitude: <\/b> 18.92504<br\/>  <b>Longitude: <\/b> -70.35205<br\/>  <b>Detection Time: <\/b> 2023-05-25 05:55 UTC<br\/>  <b>Sensor: <\/b> NOAA-20 VIIRS<br\/> <b>Confidence: <\/b> Nominal<br\/>  <b>Day\/Night: <\/b> Night<br\/> <b>Scan: <\/b> 0.4 km<br\/> <b>Track: <\/b> 0.5 km<br\/> <b>FRP: <\/b> 3.44 MW<br\/> <b>Brightness: <\/b> 307.23 K" }, "geometry": { "type": "Point", "coordinates": [ -70.35205, 18.92504, 0.0 ] } },
{ "type": "Feature", "properties": { "Name": "Fire Detection Centroid ", "Description": "<b>Latitude: <\/b> 18.92934<br\/>  <b>Longitude: <\/b> -70.3519<br\/>  <b>Detection Time: <\/b> 2023-05-25 05:55 UTC<br\/>  <b>Sensor: <\/b> NOAA-20 VIIRS<br\/> <b>Confidence: <\/b> Nominal<br\/>  <b>Day\/Night: <\/b> Night<br\/> <b>Scan: <\/b> 0.4 km<br\/> <b>Track: <\/b> 0.5 km<br\/> <b>FRP: <\/b> 3.44 MW<br\/> <b>Brightness: <\/b> 339.04 K" }, "geometry": { "type": "Point", "coordinates": [ -70.3519, 18.92934, 0.0 ] } },
{ "type": "Feature", "properties": { "Name": "Fire Detection Centroid ", "Description": "<b>Latitude: <\/b> 18.92989<br\/>  <b>Longitude: <\/b> -70.35619<br\/>  <b>Detection Time: <\/b> 2023-05-25 05:55 UTC<br\/>  <b>Sensor: <\/b> NOAA-20 VIIRS<br\/> <b>Confidence: <\/b> Nominal<br\/>  <b>Day\/Night: <\/b> Night<br\/> <b>Scan: <\/b> 0.4 km<br\/> <b>Track: <\/b> 0.5 km<br\/> <b>FRP: <\/b> 3.61 MW<br\/> <b>Brightness: <\/b> 308.67 K" }, "geometry": { "type": "Point", "coordinates": [ -70.35619, 18.92989, 0.0 ] } },
{ "type": "Feature", "properties": { "Name": "Fire Detection Centroid ", "Description": "<b>Latitude: <\/b> 18.25342<br\/>  <b>Longitude: <\/b> -71.17823<br\/>  <b>Detection Time: <\/b> 2023-05-25 05:55 UTC<br\/>  <b>Sensor: <\/b> NOAA-20 VIIRS<br\/> <b>Confidence: <\/b> Nominal<br\/>  <b>Day\/Night: <\/b> Night<br\/> <b>Scan: <\/b> 0.5 km<br\/> <b>Track: <\/b> 0.5 km<br\/> <b>FRP: <\/b> 2.11 MW<br\/> <b>Brightness: <\/b> 317.04 K" }, "geometry": { "type": "Point", "coordinates": [ -71.17823, 18.25342, 0.0 ] } },
{ "type": "Feature", "properties": { "Name": "Fire Detection Centroid ", "Description": "<b>Latitude: <\/b> 45.83975<br\/>  <b>Longitude: <\/b> -73.25369<br\/>  <b>Detection Time: <\/b> 2023-05-25 05:47 UTC<br\/>  <b>Sensor: <\/b> NOAA-20 VIIRS<br\/> <b>Confidence: <\/b> Nominal<br\/>  <b>Day\/Night: <\/b> Night<br\/> <b>Scan: <\/b> 0.6 km<br\/> <b>Track: <\/b> 0.7 km<br\/> <b>FRP: <\/b> 2.24 MW<br\/> <b>Brightness: <\/b> 297.76 K" }, "geometry": { "type": "Point", "coordinates": [ -73.25369, 45.83975, 0.0 ] } },
{ "type": "Feature", "properties": { "Name": "Fire Detection Centroid ", "Description": "<b>Latitude: <\/b> 46.04597<br\/>  <b>Longitude: <\/b> -73.14074<br\/>  <b>Detection Time: <\/b> 2023-05-25 05:47 UTC<br\/>  <b>Sensor: <\/b> NOAA-20 VIIRS<br\/> <b>Confidence: <\/b> Nominal<br\/>  <b>Day\/Night: <\/b> Night<br\/> <b>Scan: <\/b> 0.6 km<br\/> <b>Track: <\/b> 0.7 km<br\/> <b>FRP: <\/b> 2.14 MW<br\/> <b>Brightness: <\/b> 309.63 K" }, "geometry": { "type": "Point", "coordinates": [ -73.14074, 46.04597, 0.0 ] } },
{ "type": "Feature", "properties": { "Name": "Fire Detection Centroid ", "Description": "<b>Latitude: <\/b> 45.84003<br\/>  <b>Longitude: <\/b> -73.25374<br\/>  <b>Detection Time: <\/b> 2023-05-25 05:47 UTC<br\/>  <b>Sensor: <\/b> NOAA-20 VIIRS<br\/> <b>Confidence: <\/b> Nominal<br\/>  <b>Day\/Night: <\/b> Night<br\/> <b>Scan: <\/b> 0.6 km<br\/> <b>Track: <\/b> 0.7 km<br\/> <b>FRP: <\/b> 1.48 MW<br\/> <b>Brightness: <\/b> 298.76 K" }, "geometry": { "type": "Point", "coordinates": [ -73.25374, 45.84003, 0.0 ] } },
{ "type": "Feature", "properties": { "Name": "Fire Detection Centroid ", "Description": "<b>Latitude: <\/b> 46.0467<br\/>  <b>Longitude: <\/b> -73.14084<br\/>  <b>Detection Time: <\/b> 2023-05-25 05:47 UTC<br\/>  <b>Sensor: <\/b> NOAA-20 VIIRS<br\/> <b>Confidence: <\/b> Nominal<br\/>  <b>Day\/Night: <\/b> Night<br\/> <b>Scan: <\/b> 0.6 km<br\/> <b>Track: <\/b> 0.7 km<br\/> <b>FRP: <\/b> 1.64 MW<br\/> <b>Brightness: <\/b> 307.11 K" }, "geometry": { "type": "Point", "coordinates": [ -73.14084, 46.0467, 0.0 ] } }
]
}
