{
"type": "FeatureCollection",
"crs": { "type": "name", "properties": { "name": "urn:ogc:def:crs:OGC:1.3:CRS84" } },
"features": [
{ "type": "Feature", "properties": { "Name": "Fire Detection Centroid ", "Description": "<b>Latitude: <\/b> 40.39339<br\/>  <b>Longitude: <\/b> -79.85234<br\/>  <b>Detection Time: <\/b> 2023-12-14 17:05 UTC<br\/>  <b>Sensor: <\/b> NOAA-20 VIIRS<br\/> <b>Confidence: <\/b> Nominal<br\/>  <b>Day\/Night: <\/b> Day<br\/> <b>Scan: <\/b> 0.7 km<br\/> <b>Track: <\/b> 0.7 km<br\/> <b>FRP: <\/b> 5.72 MW<br\/> <b>Brightness: <\/b> 332.99 K" }, "geometry": { "type": "Point", "coordinates": [ -79.85234, 40.39339, 0.0 ] } },
{ "type": "Feature", "properties": { "Name": "Fire Detection Centroid ", "Description": "<b>Latitude: <\/b> 40.88995<br\/>  <b>Longitude: <\/b> -77.7094<br\/>  <b>Detection Time: <\/b> 2023-12-14 17:05 UTC<br\/>  <b>Sensor: <\/b> NOAA-20 VIIRS<br\/> <b>Confidence: <\/b> Nominal<br\/>  <b>Day\/Night: <\/b> Day<br\/> <b>Scan: <\/b> 0.5 km<br\/> <b>Track: <\/b> 0.7 km<br\/> <b>FRP: <\/b> 3.63 MW<br\/> <b>Brightness: <\/b> 329.14 K" }, "geometry": { "type": "Point", "coordinates": [ -77.7094, 40.88995, 0.0 ] } },
{ "type": "Feature", "properties": { "Name": "Fire Detection Centroid ", "Description": "<b>Latitude: <\/b> 36.2788<br\/>  <b>Longitude: <\/b> -77.15249<br\/>  <b>Detection Time: <\/b> 2023-12-14 17:04 UTC<br\/>  <b>Sensor: <\/b> NOAA-20 VIIRS<br\/> <b>Confidence: <\/b> Nominal<br\/>  <b>Day\/Night: <\/b> Day<br\/> <b>Scan: <\/b> 0.7 km<br\/> <b>Track: <\/b> 0.7 km<br\/> <b>FRP: <\/b> 6.85 MW<br\/> <b>Brightness: <\/b> 339.19 K" }, "geometry": { "type": "Point", "coordinates": [ -77.15249, 36.2788, 0.0 ] } },
{ "type": "Feature", "properties": { "Name": "Fire Detection Centroid ", "Description": "<b>Latitude: <\/b> 34.56156<br\/>  <b>Longitude: <\/b> -77.50845<br\/>  <b>Detection Time: <\/b> 2023-12-14 17:04 UTC<br\/>  <b>Sensor: <\/b> NOAA-20 VIIRS<br\/> <b>Confidence: <\/b> Nominal<br\/>  <b>Day\/Night: <\/b> Day<br\/> <b>Scan: <\/b> 0.8 km<br\/> <b>Track: <\/b> 0.8 km<br\/> <b>FRP: <\/b> 3.16 MW<br\/> <b>Brightness: <\/b> 325.14 K" }, "geometry": { "type": "Point", "coordinates": [ -77.50845, 34.56156, 0.0 ] } },
{ "type": "Feature", "properties": { "Name": "Fire Detection Centroid ", "Description": "<b>Latitude: <\/b> 36.72914<br\/>  <b>Longitude: <\/b> -78.96282<br\/>  <b>Detection Time: <\/b> 2023-12-14 17:04 UTC<br\/>  <b>Sensor: <\/b> NOAA-20 VIIRS<br\/> <b>Confidence: <\/b> Nominal<br\/>  <b>Day\/Night: <\/b> Day<br\/> <b>Scan: <\/b> 0.8 km<br\/> <b>Track: <\/b> 0.8 km<br\/> <b>FRP: <\/b> 4.25 MW<br\/> <b>Brightness: <\/b> 330.92 K" }, "geometry": { "type": "Point", "coordinates": [ -78.96282, 36.72914, 0.0 ] } },
{ "type": "Feature", "properties": { "Name": "Fire Detection Centroid ", "Description": "<b>Latitude: <\/b> 19.40763<br\/>  <b>Longitude: <\/b> -155.28586<br\/>  <b>Detection Time: <\/b> 2023-12-14 12:33 UTC<br\/>  <b>Sensor: <\/b> NOAA-20 VIIRS<br\/> <b>Confidence: <\/b> Nominal<br\/>  <b>Day\/Night: <\/b> Night<br\/> <b>Scan: <\/b> 0.33 km<br\/> <b>Track: <\/b> 0.55 km<br\/> <b>FRP: <\/b> 2.38 MW<br\/> <b>Brightness: <\/b> 304.6 K" }, "geometry": { "type": "Point", "coordinates": [ -155.28586, 19.40763, 0.0 ] } }
]
}
