{
"type": "FeatureCollection",
"crs": { "type": "name", "properties": { "name": "urn:ogc:def:crs:OGC:1.3:CRS84" } },
"features": [
{ "type": "Feature", "properties": { "Name": "Fire Detection Centroid ", "Description": "<b>Latitude: <\/b> 46.52033<br\/>  <b>Longitude: <\/b> -84.39239<br\/>  <b>Detection Time: <\/b> 2024-06-06 17:01 UTC<br\/>  <b>Sensor: <\/b> NOAA-20 VIIRS<br\/> <b>Confidence: <\/b> Nominal<br\/>  <b>Day\/Night: <\/b> Day<br\/> <b>Scan: <\/b> 0.8 km<br\/> <b>Track: <\/b> 0.8 km<br\/> <b>FRP: <\/b> 13.25 MW<br\/> <b>Brightness: <\/b> 330.69 K" }, "geometry": { "type": "Point", "coordinates": [ -84.39239, 46.52033, 0.0 ] } },
{ "type": "Feature", "properties": { "Name": "Fire Detection Centroid ", "Description": "<b>Latitude: <\/b> 42.8005<br\/>  <b>Longitude: <\/b> -80.0997<br\/>  <b>Detection Time: <\/b> 2024-06-06 17:00 UTC<br\/>  <b>Sensor: <\/b> NOAA-20 VIIRS<br\/> <b>Confidence: <\/b> Nominal<br\/>  <b>Day\/Night: <\/b> Day<br\/> <b>Scan: <\/b> 0.7 km<br\/> <b>Track: <\/b> 0.7 km<br\/> <b>FRP: <\/b> 7.13 MW<br\/> <b>Brightness: <\/b> 325.34 K" }, "geometry": { "type": "Point", "coordinates": [ -80.0997, 42.8005, 0.0 ] } },
{ "type": "Feature", "properties": { "Name": "Fire Detection Centroid ", "Description": "<b>Latitude: <\/b> 42.80311<br\/>  <b>Longitude: <\/b> -80.09198<br\/>  <b>Detection Time: <\/b> 2024-06-06 17:00 UTC<br\/>  <b>Sensor: <\/b> NOAA-20 VIIRS<br\/> <b>Confidence: <\/b> Nominal<br\/>  <b>Day\/Night: <\/b> Day<br\/> <b>Scan: <\/b> 0.7 km<br\/> <b>Track: <\/b> 0.7 km<br\/> <b>FRP: <\/b> 7.45 MW<br\/> <b>Brightness: <\/b> 330.46 K" }, "geometry": { "type": "Point", "coordinates": [ -80.09198, 42.80311, 0.0 ] } }
]
}
