{
"type": "FeatureCollection",
"crs": { "type": "name", "properties": { "name": "urn:ogc:def:crs:OGC:1.3:CRS84" } },
"features": [
{ "type": "Feature", "properties": { "Name": "Fire Detection Centroid ", "Description": "<b>Latitude: <\/b> 37.17411<br\/>  <b>Longitude: <\/b> -120.9797<br\/>  <b>Detection Time: <\/b> 2024-05-25 11:06 UTC<br\/>  <b>Sensor: <\/b> NOAA-20 VIIRS<br\/> <b>Confidence: <\/b> Nominal<br\/>  <b>Day\/Night: <\/b> Night<br\/> <b>Scan: <\/b> 0.78 km<br\/> <b>Track: <\/b> 0.78 km<br\/> <b>FRP: <\/b> 1.11 MW<br\/> <b>Brightness: <\/b> 295.97 K" }, "geometry": { "type": "Point", "coordinates": [ -120.9797, 37.17411, 0.0 ] } }
]
}
