{
"type": "FeatureCollection",
"crs": { "type": "name", "properties": { "name": "urn:ogc:def:crs:OGC:1.3:CRS84" } },
"features": [
{ "type": "Feature", "properties": { "Name": "Fire Detection Centroid ", "Description": "<b>Latitude: <\/b> 18.9274<br\/>  <b>Longitude: <\/b> -70.35721<br\/>  <b>Detection Time: <\/b> 2022-08-26 05:54 UTC<br\/>  <b>Sensor: <\/b> NOAA-20 VIIRS<br\/> <b>Confidence: <\/b> Nominal<br\/>  <b>Day\/Night: <\/b> Night<br\/> <b>Scan: <\/b> 0.4 km<br\/> <b>Track: <\/b> 0.5 km<br\/> <b>FRP: <\/b> 4.96 MW<br\/> <b>Brightness: <\/b> 314.45 K" }, "geometry": { "type": "Point", "coordinates": [ -70.35721, 18.9274, 0.0 ] } },
{ "type": "Feature", "properties": { "Name": "Fire Detection Centroid ", "Description": "<b>Latitude: <\/b> 18.92687<br\/>  <b>Longitude: <\/b> -70.35289<br\/>  <b>Detection Time: <\/b> 2022-08-26 05:54 UTC<br\/>  <b>Sensor: <\/b> NOAA-20 VIIRS<br\/> <b>Confidence: <\/b> Nominal<br\/>  <b>Day\/Night: <\/b> Night<br\/> <b>Scan: <\/b> 0.4 km<br\/> <b>Track: <\/b> 0.5 km<br\/> <b>FRP: <\/b> 11.98 MW<br\/> <b>Brightness: <\/b> 340.51 K" }, "geometry": { "type": "Point", "coordinates": [ -70.35289, 18.92687, 0.0 ] } },
{ "type": "Feature", "properties": { "Name": "Fire Detection Centroid ", "Description": "<b>Latitude: <\/b> 18.93169<br\/>  <b>Longitude: <\/b> -70.3568<br\/>  <b>Detection Time: <\/b> 2022-08-26 05:54 UTC<br\/>  <b>Sensor: <\/b> NOAA-20 VIIRS<br\/> <b>Confidence: <\/b> Nominal<br\/>  <b>Day\/Night: <\/b> Night<br\/> <b>Scan: <\/b> 0.4 km<br\/> <b>Track: <\/b> 0.5 km<br\/> <b>FRP: <\/b> 4.96 MW<br\/> <b>Brightness: <\/b> 312.43 K" }, "geometry": { "type": "Point", "coordinates": [ -70.3568, 18.93169, 0.0 ] } },
{ "type": "Feature", "properties": { "Name": "Fire Detection Centroid ", "Description": "<b>Latitude: <\/b> 18.93116<br\/>  <b>Longitude: <\/b> -70.35253<br\/>  <b>Detection Time: <\/b> 2022-08-26 05:54 UTC<br\/>  <b>Sensor: <\/b> NOAA-20 VIIRS<br\/> <b>Confidence: <\/b> Nominal<br\/>  <b>Day\/Night: <\/b> Night<br\/> <b>Scan: <\/b> 0.4 km<br\/> <b>Track: <\/b> 0.5 km<br\/> <b>FRP: <\/b> 11.98 MW<br\/> <b>Brightness: <\/b> 329.86 K" }, "geometry": { "type": "Point", "coordinates": [ -70.35253, 18.93116, 0.0 ] } },
{ "type": "Feature", "properties": { "Name": "Fire Detection Centroid ", "Description": "<b>Latitude: <\/b> 18.39742<br\/>  <b>Longitude: <\/b> -71.03578<br\/>  <b>Detection Time: <\/b> 2022-08-26 05:54 UTC<br\/>  <b>Sensor: <\/b> NOAA-20 VIIRS<br\/> <b>Confidence: <\/b> Nominal<br\/>  <b>Day\/Night: <\/b> Night<br\/> <b>Scan: <\/b> 0.5 km<br\/> <b>Track: <\/b> 0.5 km<br\/> <b>FRP: <\/b> 0.78 MW<br\/> <b>Brightness: <\/b> 304.2 K" }, "geometry": { "type": "Point", "coordinates": [ -71.03578, 18.39742, 0.0 ] } },
{ "type": "Feature", "properties": { "Name": "Fire Detection Centroid ", "Description": "<b>Latitude: <\/b> 45.5752<br\/>  <b>Longitude: <\/b> -63.94379<br\/>  <b>Detection Time: <\/b> 2022-08-26 05:46 UTC<br\/>  <b>Sensor: <\/b> NOAA-20 VIIRS<br\/> <b>Confidence: <\/b> Nominal<br\/>  <b>Day\/Night: <\/b> Night<br\/> <b>Scan: <\/b> 0.4 km<br\/> <b>Track: <\/b> 0.4 km<br\/> <b>FRP: <\/b> 0.57 MW<br\/> <b>Brightness: <\/b> 301.59 K" }, "geometry": { "type": "Point", "coordinates": [ -63.94379, 45.5752, 0.0 ] } }
]
}
