{
"type": "FeatureCollection",
"crs": { "type": "name", "properties": { "name": "urn:ogc:def:crs:OGC:1.3:CRS84" } },
"features": [
{ "type": "Feature", "properties": { "Name": "Fire Detection Centroid ", "Description": "<b>Latitude: <\/b> 19.59716<br\/>  <b>Longitude: <\/b> -155.505<br\/>  <b>Detection Time: <\/b> 2023-04-27 11:23 UTC<br\/>  <b>Sensor: <\/b> NOAA-20 VIIRS<br\/> <b>Confidence: <\/b> Nominal<br\/>  <b>Day\/Night: <\/b> Night<br\/> <b>Scan: <\/b> 0.33 km<br\/> <b>Track: <\/b> 0.56 km<br\/> <b>FRP: <\/b> 1.36 MW<br\/> <b>Brightness: <\/b> 297.24 K" }, "geometry": { "type": "Point", "coordinates": [ -155.505, 19.59716, 0.0 ] } },
{ "type": "Feature", "properties": { "Name": "Fire Detection Centroid ", "Description": "<b>Latitude: <\/b> 19.58681<br\/>  <b>Longitude: <\/b> -155.50485<br\/>  <b>Detection Time: <\/b> 2023-04-27 11:23 UTC<br\/>  <b>Sensor: <\/b> NOAA-20 VIIRS<br\/> <b>Confidence: <\/b> Nominal<br\/>  <b>Day\/Night: <\/b> Night<br\/> <b>Scan: <\/b> 0.33 km<br\/> <b>Track: <\/b> 0.56 km<br\/> <b>FRP: <\/b> 1.67 MW<br\/> <b>Brightness: <\/b> 295.36 K" }, "geometry": { "type": "Point", "coordinates": [ -155.50485, 19.58681, 0.0 ] } },
{ "type": "Feature", "properties": { "Name": "Fire Detection Centroid ", "Description": "<b>Latitude: <\/b> 45.22918<br\/>  <b>Longitude: <\/b> -123.16653<br\/>  <b>Detection Time: <\/b> 2023-04-27 11:17 UTC<br\/>  <b>Sensor: <\/b> NOAA-20 VIIRS<br\/> <b>Confidence: <\/b> Nominal<br\/>  <b>Day\/Night: <\/b> Night<br\/> <b>Scan: <\/b> 0.48 km<br\/> <b>Track: <\/b> 0.65 km<br\/> <b>FRP: <\/b> 1.93 MW<br\/> <b>Brightness: <\/b> 315.47 K" }, "geometry": { "type": "Point", "coordinates": [ -123.16653, 45.22918, 0.0 ] } }
]
}
