{
"type": "FeatureCollection",
"crs": { "type": "name", "properties": { "name": "urn:ogc:def:crs:OGC:1.3:CRS84" } },
"features": [
{ "type": "Feature", "properties": { "Name": "Fire Detection Centroid ", "Description": "<b>Latitude: <\/b> 43.21615<br\/>  <b>Longitude: <\/b> -123.22244<br\/>  <b>Detection Time: <\/b> 2023-03-22 10:51 UTC<br\/>  <b>Sensor: <\/b> NOAA-20 VIIRS<br\/> <b>Confidence: <\/b> Nominal<br\/>  <b>Day\/Night: <\/b> Night<br\/> <b>Scan: <\/b> 0.55 km<br\/> <b>Track: <\/b> 0.51 km<br\/> <b>FRP: <\/b> 1.49 MW<br\/> <b>Brightness: <\/b> 305.16 K" }, "geometry": { "type": "Point", "coordinates": [ -123.22244, 43.21615, 0.0 ] } },
{ "type": "Feature", "properties": { "Name": "Fire Detection Centroid ", "Description": "<b>Latitude: <\/b> 45.64688<br\/>  <b>Longitude: <\/b> -120.21473<br\/>  <b>Detection Time: <\/b> 2023-03-22 10:49 UTC<br\/>  <b>Sensor: <\/b> NOAA-20 VIIRS<br\/> <b>Confidence: <\/b> Nominal<br\/>  <b>Day\/Night: <\/b> Night<br\/> <b>Scan: <\/b> 0.32 km<br\/> <b>Track: <\/b> 0.55 km<br\/> <b>FRP: <\/b> 0.69 MW<br\/> <b>Brightness: <\/b> 302.77 K" }, "geometry": { "type": "Point", "coordinates": [ -120.21473, 45.64688, 0.0 ] } },
{ "type": "Feature", "properties": { "Name": "Fire Detection Centroid ", "Description": "<b>Latitude: <\/b> 47.56763<br\/>  <b>Longitude: <\/b> -122.3427<br\/>  <b>Detection Time: <\/b> 2023-03-22 10:49 UTC<br\/>  <b>Sensor: <\/b> NOAA-20 VIIRS<br\/> <b>Confidence: <\/b> Nominal<br\/>  <b>Day\/Night: <\/b> Night<br\/> <b>Scan: <\/b> 0.46 km<br\/> <b>Track: <\/b> 0.47 km<br\/> <b>FRP: <\/b> 1.1 MW<br\/> <b>Brightness: <\/b> 298.22 K" }, "geometry": { "type": "Point", "coordinates": [ -122.3427, 47.56763, 0.0 ] } },
{ "type": "Feature", "properties": { "Name": "Fire Detection Centroid ", "Description": "<b>Latitude: <\/b> 45.23202<br\/>  <b>Longitude: <\/b> -123.16771<br\/>  <b>Detection Time: <\/b> 2023-03-22 10:49 UTC<br\/>  <b>Sensor: <\/b> NOAA-20 VIIRS<br\/> <b>Confidence: <\/b> Nominal<br\/>  <b>Day\/Night: <\/b> Night<br\/> <b>Scan: <\/b> 0.49 km<br\/> <b>Track: <\/b> 0.49 km<br\/> <b>FRP: <\/b> 1.99 MW<br\/> <b>Brightness: <\/b> 305.83 K" }, "geometry": { "type": "Point", "coordinates": [ -123.16771, 45.23202, 0.0 ] } },
{ "type": "Feature", "properties": { "Name": "Fire Detection Centroid ", "Description": "<b>Latitude: <\/b> 45.23056<br\/>  <b>Longitude: <\/b> -123.16177<br\/>  <b>Detection Time: <\/b> 2023-03-22 10:49 UTC<br\/>  <b>Sensor: <\/b> NOAA-20 VIIRS<br\/> <b>Confidence: <\/b> Nominal<br\/>  <b>Day\/Night: <\/b> Night<br\/> <b>Scan: <\/b> 0.49 km<br\/> <b>Track: <\/b> 0.49 km<br\/> <b>FRP: <\/b> 1.99 MW<br\/> <b>Brightness: <\/b> 313.14 K" }, "geometry": { "type": "Point", "coordinates": [ -123.16177, 45.23056, 0.0 ] } },
{ "type": "Feature", "properties": { "Name": "Fire Detection Centroid ", "Description": "<b>Latitude: <\/b> 48.8856<br\/>  <b>Longitude: <\/b> -122.73567<br\/>  <b>Detection Time: <\/b> 2023-03-22 10:49 UTC<br\/>  <b>Sensor: <\/b> NOAA-20 VIIRS<br\/> <b>Confidence: <\/b> Nominal<br\/>  <b>Day\/Night: <\/b> Night<br\/> <b>Scan: <\/b> 0.41 km<br\/> <b>Track: <\/b> 0.45 km<br\/> <b>FRP: <\/b> 1.41 MW<br\/> <b>Brightness: <\/b> 298.21 K" }, "geometry": { "type": "Point", "coordinates": [ -122.73567, 48.8856, 0.0 ] } },
{ "type": "Feature", "properties": { "Name": "Fire Detection Centroid ", "Description": "<b>Latitude: <\/b> 49.09945<br\/>  <b>Longitude: <\/b> -123.01523<br\/>  <b>Detection Time: <\/b> 2023-03-22 10:49 UTC<br\/>  <b>Sensor: <\/b> NOAA-20 VIIRS<br\/> <b>Confidence: <\/b> Nominal<br\/>  <b>Day\/Night: <\/b> Night<br\/> <b>Scan: <\/b> 0.4 km<br\/> <b>Track: <\/b> 0.44 km<br\/> <b>FRP: <\/b> 0.88 MW<br\/> <b>Brightness: <\/b> 302.86 K" }, "geometry": { "type": "Point", "coordinates": [ -123.01523, 49.09945, 0.0 ] } }
]
}
