{
"type": "FeatureCollection",
"crs": { "type": "name", "properties": { "name": "urn:ogc:def:crs:OGC:1.3:CRS84" } },
"features": [
{ "type": "Feature", "properties": { "Name": "Fire Detection Centroid ", "Description": "<b>Latitude: <\/b> 46.30356<br\/>  <b>Longitude: <\/b> -67.74135<br\/>  <b>Detection Time: <\/b> 2023-09-06 16:23 UTC<br\/>  <b>Sensor: <\/b> NOAA-20 VIIRS<br\/> <b>Confidence: <\/b> Nominal<br\/>  <b>Day\/Night: <\/b> Day<br\/> <b>Scan: <\/b> 0.4 km<br\/> <b>Track: <\/b> 0.6 km<br\/> <b>FRP: <\/b> 4.02 MW<br\/> <b>Brightness: <\/b> 325.29 K" }, "geometry": { "type": "Point", "coordinates": [ -67.74135, 46.30356, 0.0 ] } },
{ "type": "Feature", "properties": { "Name": "Fire Detection Centroid ", "Description": "<b>Latitude: <\/b> 19.40668<br\/>  <b>Longitude: <\/b> -155.27701<br\/>  <b>Detection Time: <\/b> 2023-09-06 11:49 UTC<br\/>  <b>Sensor: <\/b> NOAA-20 VIIRS<br\/> <b>Confidence: <\/b> Nominal<br\/>  <b>Day\/Night: <\/b> Night<br\/> <b>Scan: <\/b> 0.42 km<br\/> <b>Track: <\/b> 0.38 km<br\/> <b>FRP: <\/b> 1.32 MW<br\/> <b>Brightness: <\/b> 297.3 K" }, "geometry": { "type": "Point", "coordinates": [ -155.27701, 19.40668, 0.0 ] } },
{ "type": "Feature", "properties": { "Name": "Fire Detection Centroid ", "Description": "<b>Latitude: <\/b> 19.40724<br\/>  <b>Longitude: <\/b> -155.28096<br\/>  <b>Detection Time: <\/b> 2023-09-06 11:49 UTC<br\/>  <b>Sensor: <\/b> NOAA-20 VIIRS<br\/> <b>Confidence: <\/b> Nominal<br\/>  <b>Day\/Night: <\/b> Night<br\/> <b>Scan: <\/b> 0.42 km<br\/> <b>Track: <\/b> 0.38 km<br\/> <b>FRP: <\/b> 1.46 MW<br\/> <b>Brightness: <\/b> 298.44 K" }, "geometry": { "type": "Point", "coordinates": [ -155.28096, 19.40724, 0.0 ] } },
{ "type": "Feature", "properties": { "Name": "Fire Detection Centroid ", "Description": "<b>Latitude: <\/b> 19.41067<br\/>  <b>Longitude: <\/b> -155.2804<br\/>  <b>Detection Time: <\/b> 2023-09-06 11:49 UTC<br\/>  <b>Sensor: <\/b> NOAA-20 VIIRS<br\/> <b>Confidence: <\/b> Nominal<br\/>  <b>Day\/Night: <\/b> Night<br\/> <b>Scan: <\/b> 0.42 km<br\/> <b>Track: <\/b> 0.38 km<br\/> <b>FRP: <\/b> 1.46 MW<br\/> <b>Brightness: <\/b> 300.19 K" }, "geometry": { "type": "Point", "coordinates": [ -155.2804, 19.41067, 0.0 ] } }
]
}
