{
"type": "FeatureCollection",
"crs": { "type": "name", "properties": { "name": "urn:ogc:def:crs:OGC:1.3:CRS84" } },
"features": [
{ "type": "Feature", "properties": { "Name": "Fire Detection Centroid ", "Description": "<b>Latitude: <\/b> 31.22675<br\/>  <b>Longitude: <\/b> -82.26694<br\/>  <b>Detection Time: <\/b> 2022-08-30 17:34 UTC<br\/>  <b>Sensor: <\/b> NOAA-20 VIIRS<br\/> <b>Confidence: <\/b> Nominal<br\/>  <b>Day\/Night: <\/b> Day<br\/> <b>Scan: <\/b> 0.6 km<br\/> <b>Track: <\/b> 0.7 km<br\/> <b>FRP: <\/b> 8.74 MW<br\/> <b>Brightness: <\/b> 335.38 K" }, "geometry": { "type": "Point", "coordinates": [ -82.26694, 31.22675, 0.0 ] } },
{ "type": "Feature", "properties": { "Name": "Fire Detection Centroid ", "Description": "<b>Latitude: <\/b> 31.34904<br\/>  <b>Longitude: <\/b> -82.64544<br\/>  <b>Detection Time: <\/b> 2022-08-30 17:34 UTC<br\/>  <b>Sensor: <\/b> NOAA-20 VIIRS<br\/> <b>Confidence: <\/b> Nominal<br\/>  <b>Day\/Night: <\/b> Day<br\/> <b>Scan: <\/b> 0.7 km<br\/> <b>Track: <\/b> 0.7 km<br\/> <b>FRP: <\/b> 7.79 MW<br\/> <b>Brightness: <\/b> 339.31 K" }, "geometry": { "type": "Point", "coordinates": [ -82.64544, 31.34904, 0.0 ] } },
{ "type": "Feature", "properties": { "Name": "Fire Detection Centroid ", "Description": "<b>Latitude: <\/b> 19.19149<br\/>  <b>Longitude: <\/b> -71.45336<br\/>  <b>Detection Time: <\/b> 2022-08-30 17:30 UTC<br\/>  <b>Sensor: <\/b> NOAA-20 VIIRS<br\/> <b>Confidence: <\/b> Nominal<br\/>  <b>Day\/Night: <\/b> Day<br\/> <b>Scan: <\/b> 0.5 km<br\/> <b>Track: <\/b> 0.5 km<br\/> <b>FRP: <\/b> 5.15 MW<br\/> <b>Brightness: <\/b> 338.65 K" }, "geometry": { "type": "Point", "coordinates": [ -71.45336, 19.19149, 0.0 ] } }
]
}
