{
"type": "FeatureCollection",
"crs": { "type": "name", "properties": { "name": "urn:ogc:def:crs:OGC:1.3:CRS84" } },
"features": [
{ "type": "Feature", "properties": { "Name": "Fire Detection Centroid ", "Description": "<b>Latitude: <\/b> 36.98492<br\/>  <b>Longitude: <\/b> -120.39931<br\/>  <b>Detection Time: <\/b> 2023-03-23 21:55 UTC<br\/>  <b>Sensor: <\/b> NOAA-20 VIIRS<br\/> <b>Confidence: <\/b> Nominal<br\/>  <b>Day\/Night: <\/b> Day<br\/> <b>Scan: <\/b> 0.51 km<br\/> <b>Track: <\/b> 0.66 km<br\/> <b>FRP: <\/b> 2.66 MW<br\/> <b>Brightness: <\/b> 327.63 K" }, "geometry": { "type": "Point", "coordinates": [ -120.39931, 36.98492, 0.0 ] } }
]
}
