{
"type": "FeatureCollection",
"crs": { "type": "name", "properties": { "name": "urn:ogc:def:crs:OGC:1.3:CRS84" } },
"features": [
{ "type": "Feature", "properties": { "Name": "Fire Detection Centroid ", "Description": "<b>Latitude: <\/b> 19.10736<br\/>  <b>Longitude: <\/b> -72.36268<br\/>  <b>Detection Time: <\/b> 2023-12-28 06:26 UTC<br\/>  <b>Sensor: <\/b> NOAA-20 VIIRS<br\/> <b>Confidence: <\/b> Nominal<br\/>  <b>Day\/Night: <\/b> Night<br\/> <b>Scan: <\/b> 0.4 km<br\/> <b>Track: <\/b> 0.4 km<br\/> <b>FRP: <\/b> 0.46 MW<br\/> <b>Brightness: <\/b> 304.05 K" }, "geometry": { "type": "Point", "coordinates": [ -72.36268, 19.10736, 0.0 ] } },
{ "type": "Feature", "properties": { "Name": "Fire Detection Centroid ", "Description": "<b>Latitude: <\/b> 20.64479<br\/>  <b>Longitude: <\/b> -76.26362<br\/>  <b>Detection Time: <\/b> 2023-12-28 06:25 UTC<br\/>  <b>Sensor: <\/b> NOAA-20 VIIRS<br\/> <b>Confidence: <\/b> Nominal<br\/>  <b>Day\/Night: <\/b> Night<br\/> <b>Scan: <\/b> 0.5 km<br\/> <b>Track: <\/b> 0.4 km<br\/> <b>FRP: <\/b> 2.37 MW<br\/> <b>Brightness: <\/b> 300.08 K" }, "geometry": { "type": "Point", "coordinates": [ -76.26362, 20.64479, 0.0 ] } },
{ "type": "Feature", "properties": { "Name": "Fire Detection Centroid ", "Description": "<b>Latitude: <\/b> 20.64929<br\/>  <b>Longitude: <\/b> -76.26808<br\/>  <b>Detection Time: <\/b> 2023-12-28 06:25 UTC<br\/>  <b>Sensor: <\/b> NOAA-20 VIIRS<br\/> <b>Confidence: <\/b> Nominal<br\/>  <b>Day\/Night: <\/b> Night<br\/> <b>Scan: <\/b> 0.5 km<br\/> <b>Track: <\/b> 0.4 km<br\/> <b>FRP: <\/b> 2.37 MW<br\/> <b>Brightness: <\/b> 322.1 K" }, "geometry": { "type": "Point", "coordinates": [ -76.26808, 20.64929, 0.0 ] } },
{ "type": "Feature", "properties": { "Name": "Fire Detection Centroid ", "Description": "<b>Latitude: <\/b> 20.64996<br\/>  <b>Longitude: <\/b> -76.27312<br\/>  <b>Detection Time: <\/b> 2023-12-28 06:25 UTC<br\/>  <b>Sensor: <\/b> NOAA-20 VIIRS<br\/> <b>Confidence: <\/b> Nominal<br\/>  <b>Day\/Night: <\/b> Night<br\/> <b>Scan: <\/b> 0.5 km<br\/> <b>Track: <\/b> 0.4 km<br\/> <b>FRP: <\/b> 2.06 MW<br\/> <b>Brightness: <\/b> 317.68 K" }, "geometry": { "type": "Point", "coordinates": [ -76.27312, 20.64996, 0.0 ] } },
{ "type": "Feature", "properties": { "Name": "Fire Detection Centroid ", "Description": "<b>Latitude: <\/b> 20.64546<br\/>  <b>Longitude: <\/b> -76.26865<br\/>  <b>Detection Time: <\/b> 2023-12-28 06:25 UTC<br\/>  <b>Sensor: <\/b> NOAA-20 VIIRS<br\/> <b>Confidence: <\/b> Nominal<br\/>  <b>Day\/Night: <\/b> Night<br\/> <b>Scan: <\/b> 0.5 km<br\/> <b>Track: <\/b> 0.4 km<br\/> <b>FRP: <\/b> 2.37 MW<br\/> <b>Brightness: <\/b> 329.47 K" }, "geometry": { "type": "Point", "coordinates": [ -76.26865, 20.64546, 0.0 ] } },
{ "type": "Feature", "properties": { "Name": "Fire Detection Centroid ", "Description": "<b>Latitude: <\/b> 20.64613<br\/>  <b>Longitude: <\/b> -76.2737<br\/>  <b>Detection Time: <\/b> 2023-12-28 06:25 UTC<br\/>  <b>Sensor: <\/b> NOAA-20 VIIRS<br\/> <b>Confidence: <\/b> Nominal<br\/>  <b>Day\/Night: <\/b> Night<br\/> <b>Scan: <\/b> 0.5 km<br\/> <b>Track: <\/b> 0.4 km<br\/> <b>FRP: <\/b> 2.06 MW<br\/> <b>Brightness: <\/b> 306.73 K" }, "geometry": { "type": "Point", "coordinates": [ -76.2737, 20.64613, 0.0 ] } },
{ "type": "Feature", "properties": { "Name": "Fire Detection Centroid ", "Description": "<b>Latitude: <\/b> 36.41224<br\/>  <b>Longitude: <\/b> -80.98737<br\/>  <b>Detection Time: <\/b> 2023-12-28 06:21 UTC<br\/>  <b>Sensor: <\/b> NOAA-20 VIIRS<br\/> <b>Confidence: <\/b> Nominal<br\/>  <b>Day\/Night: <\/b> Night<br\/> <b>Scan: <\/b> 0.5 km<br\/> <b>Track: <\/b> 0.7 km<br\/> <b>FRP: <\/b> 0.95 MW<br\/> <b>Brightness: <\/b> 295.47 K" }, "geometry": { "type": "Point", "coordinates": [ -80.98737, 36.41224, 0.0 ] } },
{ "type": "Feature", "properties": { "Name": "Fire Detection Centroid ", "Description": "<b>Latitude: <\/b> 37.3832<br\/>  <b>Longitude: <\/b> -80.66367<br\/>  <b>Detection Time: <\/b> 2023-12-28 06:21 UTC<br\/>  <b>Sensor: <\/b> NOAA-20 VIIRS<br\/> <b>Confidence: <\/b> Nominal<br\/>  <b>Day\/Night: <\/b> Night<br\/> <b>Scan: <\/b> 0.5 km<br\/> <b>Track: <\/b> 0.6 km<br\/> <b>FRP: <\/b> 0.71 MW<br\/> <b>Brightness: <\/b> 295.88 K" }, "geometry": { "type": "Point", "coordinates": [ -80.66367, 37.3832, 0.0 ] } },
{ "type": "Feature", "properties": { "Name": "Fire Detection Centroid ", "Description": "<b>Latitude: <\/b> 38.60199<br\/>  <b>Longitude: <\/b> -82.82899<br\/>  <b>Detection Time: <\/b> 2023-12-28 06:20 UTC<br\/>  <b>Sensor: <\/b> NOAA-20 VIIRS<br\/> <b>Confidence: <\/b> Nominal<br\/>  <b>Day\/Night: <\/b> Night<br\/> <b>Scan: <\/b> 0.6 km<br\/> <b>Track: <\/b> 0.7 km<br\/> <b>FRP: <\/b> 1.31 MW<br\/> <b>Brightness: <\/b> 297.22 K" }, "geometry": { "type": "Point", "coordinates": [ -82.82899, 38.60199, 0.0 ] } }
]
}
