{
"type": "FeatureCollection",
"crs": { "type": "name", "properties": { "name": "urn:ogc:def:crs:OGC:1.3:CRS84" } },
"features": [
{ "type": "Feature", "properties": { "Name": "Fire Detection Centroid ", "Description": "<b>Latitude: <\/b> 32.60176<br\/>  <b>Longitude: <\/b> -117.01119<br\/>  <b>Detection Time: <\/b> 2023-12-26 10:22 UTC<br\/>  <b>Sensor: <\/b> NOAA-20 VIIRS<br\/> <b>Confidence: <\/b> Nominal<br\/>  <b>Day\/Night: <\/b> Night<br\/> <b>Scan: <\/b> 0.4 km<br\/> <b>Track: <\/b> 0.6 km<br\/> <b>FRP: <\/b> 0.45 MW<br\/> <b>Brightness: <\/b> 296.68 K" }, "geometry": { "type": "Point", "coordinates": [ -117.01119, 32.60176, 0.0 ] } },
{ "type": "Feature", "properties": { "Name": "Fire Detection Centroid ", "Description": "<b>Latitude: <\/b> 32.60114<br\/>  <b>Longitude: <\/b> -117.013<br\/>  <b>Detection Time: <\/b> 2023-12-26 10:21 UTC<br\/>  <b>Sensor: <\/b> NOAA-20 VIIRS<br\/> <b>Confidence: <\/b> Nominal<br\/>  <b>Day\/Night: <\/b> Night<br\/> <b>Scan: <\/b> 0.42 km<br\/> <b>Track: <\/b> 0.61 km<br\/> <b>FRP: <\/b> 0.45 MW<br\/> <b>Brightness: <\/b> 296.68 K" }, "geometry": { "type": "Point", "coordinates": [ -117.013, 32.60114, 0.0 ] } },
{ "type": "Feature", "properties": { "Name": "Fire Detection Centroid ", "Description": "<b>Latitude: <\/b> 36.35765<br\/>  <b>Longitude: <\/b> -114.91452<br\/>  <b>Detection Time: <\/b> 2023-12-26 10:21 UTC<br\/>  <b>Sensor: <\/b> NOAA-20 VIIRS<br\/> <b>Confidence: <\/b> Nominal<br\/>  <b>Day\/Night: <\/b> Night<br\/> <b>Scan: <\/b> 0.44 km<br\/> <b>Track: <\/b> 0.62 km<br\/> <b>FRP: <\/b> 1.14 MW<br\/> <b>Brightness: <\/b> 296.95 K" }, "geometry": { "type": "Point", "coordinates": [ -114.91452, 36.35765, 0.0 ] } },
{ "type": "Feature", "properties": { "Name": "Fire Detection Centroid ", "Description": "<b>Latitude: <\/b> 32.60053<br\/>  <b>Longitude: <\/b> -117.01408<br\/>  <b>Detection Time: <\/b> 2023-12-26 10:21 UTC<br\/>  <b>Sensor: <\/b> NOAA-20 VIIRS<br\/> <b>Confidence: <\/b> Nominal<br\/>  <b>Day\/Night: <\/b> Night<br\/> <b>Scan: <\/b> 0.42 km<br\/> <b>Track: <\/b> 0.61 km<br\/> <b>FRP: <\/b> 0.65 MW<br\/> <b>Brightness: <\/b> 296.2 K" }, "geometry": { "type": "Point", "coordinates": [ -117.01408, 32.60053, 0.0 ] } },
{ "type": "Feature", "properties": { "Name": "Fire Detection Centroid ", "Description": "<b>Latitude: <\/b> 36.35813<br\/>  <b>Longitude: <\/b> -114.91222<br\/>  <b>Detection Time: <\/b> 2023-12-26 10:21 UTC<br\/>  <b>Sensor: <\/b> NOAA-20 VIIRS<br\/> <b>Confidence: <\/b> Nominal<br\/>  <b>Day\/Night: <\/b> Night<br\/> <b>Scan: <\/b> 0.4 km<br\/> <b>Track: <\/b> 0.6 km<br\/> <b>FRP: <\/b> 1.14 MW<br\/> <b>Brightness: <\/b> 296.95 K" }, "geometry": { "type": "Point", "coordinates": [ -114.91222, 36.35813, 0.0 ] } },
{ "type": "Feature", "properties": { "Name": "Fire Detection Centroid ", "Description": "<b>Latitude: <\/b> 44.61152<br\/>  <b>Longitude: <\/b> -123.93384<br\/>  <b>Detection Time: <\/b> 2023-12-26 10:19 UTC<br\/>  <b>Sensor: <\/b> NOAA-20 VIIRS<br\/> <b>Confidence: <\/b> Nominal<br\/>  <b>Day\/Night: <\/b> Night<br\/> <b>Scan: <\/b> 0.39 km<br\/> <b>Track: <\/b> 0.36 km<br\/> <b>FRP: <\/b> 0.59 MW<br\/> <b>Brightness: <\/b> 295.33 K" }, "geometry": { "type": "Point", "coordinates": [ -123.93384, 44.61152, 0.0 ] } },
{ "type": "Feature", "properties": { "Name": "Fire Detection Centroid ", "Description": "<b>Latitude: <\/b> 42.68715<br\/>  <b>Longitude: <\/b> -111.59007<br\/>  <b>Detection Time: <\/b> 2023-12-26 10:19 UTC<br\/>  <b>Sensor: <\/b> NOAA-20 VIIRS<br\/> <b>Confidence: <\/b> Nominal<br\/>  <b>Day\/Night: <\/b> Night<br\/> <b>Scan: <\/b> 0.4 km<br\/> <b>Track: <\/b> 0.6 km<br\/> <b>FRP: <\/b> 11 MW<br\/> <b>Brightness: <\/b> 353.32 K" }, "geometry": { "type": "Point", "coordinates": [ -111.59007, 42.68715, 0.0 ] } },
{ "type": "Feature", "properties": { "Name": "Fire Detection Centroid ", "Description": "<b>Latitude: <\/b> 42.6867<br\/>  <b>Longitude: <\/b> -111.59239<br\/>  <b>Detection Time: <\/b> 2023-12-26 10:19 UTC<br\/>  <b>Sensor: <\/b> NOAA-20 VIIRS<br\/> <b>Confidence: <\/b> Nominal<br\/>  <b>Day\/Night: <\/b> Night<br\/> <b>Scan: <\/b> 0.43 km<br\/> <b>Track: <\/b> 0.62 km<br\/> <b>FRP: <\/b> 11.03 MW<br\/> <b>Brightness: <\/b> 353.32 K" }, "geometry": { "type": "Point", "coordinates": [ -111.59239, 42.6867, 0.0 ] } },
{ "type": "Feature", "properties": { "Name": "Fire Detection Centroid ", "Description": "<b>Latitude: <\/b> 49.09861<br\/>  <b>Longitude: <\/b> -123.01888<br\/>  <b>Detection Time: <\/b> 2023-12-26 10:17 UTC<br\/>  <b>Sensor: <\/b> NOAA-20 VIIRS<br\/> <b>Confidence: <\/b> Nominal<br\/>  <b>Day\/Night: <\/b> Night<br\/> <b>Scan: <\/b> 0.38 km<br\/> <b>Track: <\/b> 0.36 km<br\/> <b>FRP: <\/b> 0.67 MW<br\/> <b>Brightness: <\/b> 312.34 K" }, "geometry": { "type": "Point", "coordinates": [ -123.01888, 49.09861, 0.0 ] } }
]
}
