{
"type": "FeatureCollection",
"crs": { "type": "name", "properties": { "name": "urn:ogc:def:crs:OGC:1.3:CRS84" } },
"features": [
{ "type": "Feature", "properties": { "Name": "Fire Detection Centroid ", "Description": "<b>Latitude: <\/b> 44.97084<br\/>  <b>Longitude: <\/b> -75.51367<br\/>  <b>Detection Time: <\/b> 2023-09-05 16:42 UTC<br\/>  <b>Sensor: <\/b> NOAA-20 VIIRS<br\/> <b>Confidence: <\/b> Nominal<br\/>  <b>Day\/Night: <\/b> Day<br\/> <b>Scan: <\/b> 0.6 km<br\/> <b>Track: <\/b> 0.7 km<br\/> <b>FRP: <\/b> 7.06 MW<br\/> <b>Brightness: <\/b> 333.67 K" }, "geometry": { "type": "Point", "coordinates": [ -75.51367, 44.97084, 0.0 ] } },
{ "type": "Feature", "properties": { "Name": "Fire Detection Centroid ", "Description": "<b>Latitude: <\/b> 45.27805<br\/>  <b>Longitude: <\/b> -66.0158<br\/>  <b>Detection Time: <\/b> 2023-09-05 16:41 UTC<br\/>  <b>Sensor: <\/b> NOAA-20 VIIRS<br\/> <b>Confidence: <\/b> Nominal<br\/>  <b>Day\/Night: <\/b> Day<br\/> <b>Scan: <\/b> 0.4 km<br\/> <b>Track: <\/b> 0.5 km<br\/> <b>FRP: <\/b> 3.04 MW<br\/> <b>Brightness: <\/b> 329.01 K" }, "geometry": { "type": "Point", "coordinates": [ -66.0158, 45.27805, 0.0 ] } },
{ "type": "Feature", "properties": { "Name": "Fire Detection Centroid ", "Description": "<b>Latitude: <\/b> 19.41316<br\/>  <b>Longitude: <\/b> -155.28465<br\/>  <b>Detection Time: <\/b> 2023-09-05 12:08 UTC<br\/>  <b>Sensor: <\/b> NOAA-20 VIIRS<br\/> <b>Confidence: <\/b> Nominal<br\/>  <b>Day\/Night: <\/b> Night<br\/> <b>Scan: <\/b> 0.43 km<br\/> <b>Track: <\/b> 0.38 km<br\/> <b>FRP: <\/b> 3.96 MW<br\/> <b>Brightness: <\/b> 306.14 K" }, "geometry": { "type": "Point", "coordinates": [ -155.28465, 19.41316, 0.0 ] } },
{ "type": "Feature", "properties": { "Name": "Fire Detection Centroid ", "Description": "<b>Latitude: <\/b> 19.40554<br\/>  <b>Longitude: <\/b> -155.28181<br\/>  <b>Detection Time: <\/b> 2023-09-05 12:08 UTC<br\/>  <b>Sensor: <\/b> NOAA-20 VIIRS<br\/> <b>Confidence: <\/b> Nominal<br\/>  <b>Day\/Night: <\/b> Night<br\/> <b>Scan: <\/b> 0.43 km<br\/> <b>Track: <\/b> 0.38 km<br\/> <b>FRP: <\/b> 3.13 MW<br\/> <b>Brightness: <\/b> 308.08 K" }, "geometry": { "type": "Point", "coordinates": [ -155.28181, 19.40554, 0.0 ] } },
{ "type": "Feature", "properties": { "Name": "Fire Detection Centroid ", "Description": "<b>Latitude: <\/b> 19.40347<br\/>  <b>Longitude: <\/b> -155.29065<br\/>  <b>Detection Time: <\/b> 2023-09-05 12:08 UTC<br\/>  <b>Sensor: <\/b> NOAA-20 VIIRS<br\/> <b>Confidence: <\/b> Nominal<br\/>  <b>Day\/Night: <\/b> Night<br\/> <b>Scan: <\/b> 0.43 km<br\/> <b>Track: <\/b> 0.38 km<br\/> <b>FRP: <\/b> 4.36 MW<br\/> <b>Brightness: <\/b> 302.08 K" }, "geometry": { "type": "Point", "coordinates": [ -155.29065, 19.40347, 0.0 ] } }
]
}
