{
"type": "FeatureCollection",
"crs": { "type": "name", "properties": { "name": "urn:ogc:def:crs:OGC:1.3:CRS84" } },
"features": [
{ "type": "Feature", "properties": { "Name": "Fire Detection Centroid ", "Description": "<b>Latitude: <\/b> 38.41943<br\/>  <b>Longitude: <\/b> -75.84103<br\/>  <b>Detection Time: <\/b> 2023-04-24 16:53 UTC<br\/>  <b>Sensor: <\/b> NOAA-20 VIIRS<br\/> <b>Confidence: <\/b> Nominal<br\/>  <b>Day\/Night: <\/b> Day<br\/> <b>Scan: <\/b> 0.7 km<br\/> <b>Track: <\/b> 0.7 km<br\/> <b>FRP: <\/b> 3.48 MW<br\/> <b>Brightness: <\/b> 329.42 K" }, "geometry": { "type": "Point", "coordinates": [ -75.84103, 38.41943, 0.0 ] } },
{ "type": "Feature", "properties": { "Name": "Fire Detection Centroid ", "Description": "<b>Latitude: <\/b> 39.60047<br\/>  <b>Longitude: <\/b> -75.19687<br\/>  <b>Detection Time: <\/b> 2023-04-24 16:53 UTC<br\/>  <b>Sensor: <\/b> NOAA-20 VIIRS<br\/> <b>Confidence: <\/b> Nominal<br\/>  <b>Day\/Night: <\/b> Day<br\/> <b>Scan: <\/b> 0.6 km<br\/> <b>Track: <\/b> 0.7 km<br\/> <b>FRP: <\/b> 3.79 MW<br\/> <b>Brightness: <\/b> 325.61 K" }, "geometry": { "type": "Point", "coordinates": [ -75.19687, 39.60047, 0.0 ] } },
{ "type": "Feature", "properties": { "Name": "Fire Detection Centroid ", "Description": "<b>Latitude: <\/b> 38.42435<br\/>  <b>Longitude: <\/b> -75.84374<br\/>  <b>Detection Time: <\/b> 2023-04-24 16:52 UTC<br\/>  <b>Sensor: <\/b> NOAA-20 VIIRS<br\/> <b>Confidence: <\/b> Nominal<br\/>  <b>Day\/Night: <\/b> Day<br\/> <b>Scan: <\/b> 0.7 km<br\/> <b>Track: <\/b> 0.7 km<br\/> <b>FRP: <\/b> 5.57 MW<br\/> <b>Brightness: <\/b> 335.29 K" }, "geometry": { "type": "Point", "coordinates": [ -75.84374, 38.42435, 0.0 ] } }
]
}
