{
"type": "FeatureCollection",
"crs": { "type": "name", "properties": { "name": "urn:ogc:def:crs:OGC:1.3:CRS84" } },
"features": [
{ "type": "Feature", "properties": { "Name": "Fire Detection Centroid ", "Description": "<b>Latitude: </b> 39.98375<br/>  <b>Longitude: </b> -122.17665<br/>  <b>Detection Time: </b> 2022-06-17 11:04 UTC<br/>  <b>Sensor: </b> NOAA-20 VIIRS<br/> <b>Confidence: </b> Nominal<br/>  <b>Day/Night: </b> Night<br/> <b>Scan: </b> 0.55 km<br/> <b>Track: </b> 0.68 km<br/> <b>FRP: </b> 0.67 MW<br/> <b>Brightness: </b> 300.57 K" }, "geometry": { "type": "Point", "coordinates": [ -122.17665, 39.98375, 0.0 ] } }
]
}
