{
"type": "FeatureCollection",
"crs": { "type": "name", "properties": { "name": "urn:ogc:def:crs:OGC:1.3:CRS84" } },
"features": [
{ "type": "Feature", "properties": { "Name": "Fire Detection Centroid ", "Description": "<b>Latitude: <\/b> 19.40962<br\/>  <b>Longitude: <\/b> -155.27689<br\/>  <b>Detection Time: <\/b> 2022-09-22 00:03 UTC<br\/>  <b>Sensor: <\/b> NOAA-20 VIIRS<br\/> <b>Confidence: <\/b> Nominal<br\/>  <b>Day\/Night: <\/b> Day<br\/> <b>Scan: <\/b> 0.5 km<br\/> <b>Track: <\/b> 0.5 km<br\/> <b>FRP: <\/b> 10.12 MW<br\/> <b>Brightness: <\/b> 332.68 K" }, "geometry": { "type": "Point", "coordinates": [ -155.27689, 19.40962, 0.0 ] } }
]
}
