{
"type": "FeatureCollection",
"crs": { "type": "name", "properties": { "name": "urn:ogc:def:crs:OGC:1.3:CRS84" } },
"features": [
{ "type": "Feature", "properties": { "Name": "Fire Detection Centroid ", "Description": "<b>Latitude: <\/b> 19.39974<br\/>  <b>Longitude: <\/b> -155.28227<br\/>  <b>Detection Time: <\/b> 2022-09-18 23:20 UTC<br\/>  <b>Sensor: <\/b> NOAA-20 VIIRS<br\/> <b>Confidence: <\/b> Nominal<br\/>  <b>Day\/Night: <\/b> Day<br\/> <b>Scan: <\/b> 0.48 km<br\/> <b>Track: <\/b> 0.4 km<br\/> <b>FRP: <\/b> 3.89 MW<br\/> <b>Brightness: <\/b> 325.56 K" }, "geometry": { "type": "Point", "coordinates": [ -155.28227, 19.39974, 0.0 ] } },
{ "type": "Feature", "properties": { "Name": "Fire Detection Centroid ", "Description": "<b>Latitude: <\/b> 19.40702<br\/>  <b>Longitude: <\/b> -155.28369<br\/>  <b>Detection Time: <\/b> 2022-09-18 23:20 UTC<br\/>  <b>Sensor: <\/b> NOAA-20 VIIRS<br\/> <b>Confidence: <\/b> Nominal<br\/>  <b>Day\/Night: <\/b> Day<br\/> <b>Scan: <\/b> 0.48 km<br\/> <b>Track: <\/b> 0.4 km<br\/> <b>FRP: <\/b> 14.04 MW<br\/> <b>Brightness: <\/b> 352.86 K" }, "geometry": { "type": "Point", "coordinates": [ -155.28369, 19.40702, 0.0 ] } },
{ "type": "Feature", "properties": { "Name": "Fire Detection Centroid ", "Description": "<b>Latitude: <\/b> 19.41067<br\/>  <b>Longitude: <\/b> -155.28435<br\/>  <b>Detection Time: <\/b> 2022-09-18 23:20 UTC<br\/>  <b>Sensor: <\/b> NOAA-20 VIIRS<br\/> <b>Confidence: <\/b> Nominal<br\/>  <b>Day\/Night: <\/b> Day<br\/> <b>Scan: <\/b> 0.48 km<br\/> <b>Track: <\/b> 0.4 km<br\/> <b>FRP: <\/b> 8.62 MW<br\/> <b>Brightness: <\/b> 337.46 K" }, "geometry": { "type": "Point", "coordinates": [ -155.28435, 19.41067, 0.0 ] } },
{ "type": "Feature", "properties": { "Name": "Fire Detection Centroid ", "Description": "<b>Latitude: <\/b> 19.40625<br\/>  <b>Longitude: <\/b> -155.28819<br\/>  <b>Detection Time: <\/b> 2022-09-18 23:20 UTC<br\/>  <b>Sensor: <\/b> NOAA-20 VIIRS<br\/> <b>Confidence: <\/b> Nominal<br\/>  <b>Day\/Night: <\/b> Day<br\/> <b>Scan: <\/b> 0.48 km<br\/> <b>Track: <\/b> 0.4 km<br\/> <b>FRP: <\/b> 14.04 MW<br\/> <b>Brightness: <\/b> 347.88 K" }, "geometry": { "type": "Point", "coordinates": [ -155.28819, 19.40625, 0.0 ] } },
{ "type": "Feature", "properties": { "Name": "Fire Detection Centroid ", "Description": "<b>Latitude: <\/b> 19.4026<br\/>  <b>Longitude: <\/b> -155.28754<br\/>  <b>Detection Time: <\/b> 2022-09-18 23:20 UTC<br\/>  <b>Sensor: <\/b> NOAA-20 VIIRS<br\/> <b>Confidence: <\/b> Nominal<br\/>  <b>Day\/Night: <\/b> Day<br\/> <b>Scan: <\/b> 0.48 km<br\/> <b>Track: <\/b> 0.4 km<br\/> <b>FRP: <\/b> 14.04 MW<br\/> <b>Brightness: <\/b> 347.92 K" }, "geometry": { "type": "Point", "coordinates": [ -155.28754, 19.4026, 0.0 ] } },
{ "type": "Feature", "properties": { "Name": "Fire Detection Centroid ", "Description": "<b>Latitude: <\/b> 19.40337<br\/>  <b>Longitude: <\/b> -155.28302<br\/>  <b>Detection Time: <\/b> 2022-09-18 23:20 UTC<br\/>  <b>Sensor: <\/b> NOAA-20 VIIRS<br\/> <b>Confidence: <\/b> Nominal<br\/>  <b>Day\/Night: <\/b> Day<br\/> <b>Scan: <\/b> 0.48 km<br\/> <b>Track: <\/b> 0.4 km<br\/> <b>FRP: <\/b> 14.04 MW<br\/> <b>Brightness: <\/b> 356.27 K" }, "geometry": { "type": "Point", "coordinates": [ -155.28302, 19.40337, 0.0 ] } },
{ "type": "Feature", "properties": { "Name": "Fire Detection Centroid ", "Description": "<b>Latitude: <\/b> 19.40415<br\/>  <b>Longitude: <\/b> -155.2785<br\/>  <b>Detection Time: <\/b> 2022-09-18 23:20 UTC<br\/>  <b>Sensor: <\/b> NOAA-20 VIIRS<br\/> <b>Confidence: <\/b> Nominal<br\/>  <b>Day\/Night: <\/b> Day<br\/> <b>Scan: <\/b> 0.48 km<br\/> <b>Track: <\/b> 0.4 km<br\/> <b>FRP: <\/b> 7.39 MW<br\/> <b>Brightness: <\/b> 333.07 K" }, "geometry": { "type": "Point", "coordinates": [ -155.2785, 19.40415, 0.0 ] } }
]
}
