{
"type": "FeatureCollection",
"crs": { "type": "name", "properties": { "name": "urn:ogc:def:crs:OGC:1.3:CRS84" } },
"features": [
{ "type": "Feature", "properties": { "Name": "Fire Detection Centroid ", "Description": "<b>Latitude: <\/b> 19.60015<br\/>  <b>Longitude: <\/b> -155.50345<br\/>  <b>Detection Time: <\/b> 2023-05-11 12:02 UTC<br\/>  <b>Sensor: <\/b> NOAA-20 VIIRS<br\/> <b>Confidence: <\/b> Nominal<br\/>  <b>Day\/Night: <\/b> Night<br\/> <b>Scan: <\/b> 0.39 km<br\/> <b>Track: <\/b> 0.36 km<br\/> <b>FRP: <\/b> 1.22 MW<br\/> <b>Brightness: <\/b> 300.94 K" }, "geometry": { "type": "Point", "coordinates": [ -155.50345, 19.60015, 0.0 ] } },
{ "type": "Feature", "properties": { "Name": "Fire Detection Centroid ", "Description": "<b>Latitude: <\/b> 19.59686<br\/>  <b>Longitude: <\/b> -155.50406<br\/>  <b>Detection Time: <\/b> 2023-05-11 12:02 UTC<br\/>  <b>Sensor: <\/b> NOAA-20 VIIRS<br\/> <b>Confidence: <\/b> Nominal<br\/>  <b>Day\/Night: <\/b> Night<br\/> <b>Scan: <\/b> 0.39 km<br\/> <b>Track: <\/b> 0.36 km<br\/> <b>FRP: <\/b> 1.22 MW<br\/> <b>Brightness: <\/b> 303.62 K" }, "geometry": { "type": "Point", "coordinates": [ -155.50406, 19.59686, 0.0 ] } },
{ "type": "Feature", "properties": { "Name": "Fire Detection Centroid ", "Description": "<b>Latitude: <\/b> 19.41159<br\/>  <b>Longitude: <\/b> -155.28426<br\/>  <b>Detection Time: <\/b> 2023-05-11 12:02 UTC<br\/>  <b>Sensor: <\/b> NOAA-20 VIIRS<br\/> <b>Confidence: <\/b> Nominal<br\/>  <b>Day\/Night: <\/b> Night<br\/> <b>Scan: <\/b> 0.39 km<br\/> <b>Track: <\/b> 0.36 km<br\/> <b>FRP: <\/b> 1.78 MW<br\/> <b>Brightness: <\/b> 303.85 K" }, "geometry": { "type": "Point", "coordinates": [ -155.28426, 19.41159, 0.0 ] } },
{ "type": "Feature", "properties": { "Name": "Fire Detection Centroid ", "Description": "<b>Latitude: <\/b> 19.40558<br\/>  <b>Longitude: <\/b> -155.28911<br\/>  <b>Detection Time: <\/b> 2023-05-11 12:02 UTC<br\/>  <b>Sensor: <\/b> NOAA-20 VIIRS<br\/> <b>Confidence: <\/b> Nominal<br\/>  <b>Day\/Night: <\/b> Night<br\/> <b>Scan: <\/b> 0.39 km<br\/> <b>Track: <\/b> 0.36 km<br\/> <b>FRP: <\/b> 1.7 MW<br\/> <b>Brightness: <\/b> 302.49 K" }, "geometry": { "type": "Point", "coordinates": [ -155.28911, 19.40558, 0.0 ] } },
{ "type": "Feature", "properties": { "Name": "Fire Detection Centroid ", "Description": "<b>Latitude: <\/b> 19.40498<br\/>  <b>Longitude: <\/b> -155.28543<br\/>  <b>Detection Time: <\/b> 2023-05-11 12:02 UTC<br\/>  <b>Sensor: <\/b> NOAA-20 VIIRS<br\/> <b>Confidence: <\/b> Nominal<br\/>  <b>Day\/Night: <\/b> Night<br\/> <b>Scan: <\/b> 0.39 km<br\/> <b>Track: <\/b> 0.36 km<br\/> <b>FRP: <\/b> 1.7 MW<br\/> <b>Brightness: <\/b> 303.22 K" }, "geometry": { "type": "Point", "coordinates": [ -155.28543, 19.40498, 0.0 ] } },
{ "type": "Feature", "properties": { "Name": "Fire Detection Centroid ", "Description": "<b>Latitude: <\/b> 19.60343<br\/>  <b>Longitude: <\/b> -155.50282<br\/>  <b>Detection Time: <\/b> 2023-05-11 12:02 UTC<br\/>  <b>Sensor: <\/b> NOAA-20 VIIRS<br\/> <b>Confidence: <\/b> Nominal<br\/>  <b>Day\/Night: <\/b> Night<br\/> <b>Scan: <\/b> 0.39 km<br\/> <b>Track: <\/b> 0.36 km<br\/> <b>FRP: <\/b> 1.78 MW<br\/> <b>Brightness: <\/b> 299.46 K" }, "geometry": { "type": "Point", "coordinates": [ -155.50282, 19.60343, 0.0 ] } }
]
}
