{
"type": "FeatureCollection",
"crs": { "type": "name", "properties": { "name": "urn:ogc:def:crs:OGC:1.3:CRS84" } },
"features": [
{ "type": "Feature", "properties": { "Name": "Fire Detection Centroid ", "Description": "<b>Latitude: <\/b> 19.4049<br\/>  <b>Longitude: <\/b> -155.27617<br\/>  <b>Detection Time: <\/b> 2022-09-27 00:09 UTC<br\/>  <b>Sensor: <\/b> NOAA-20 VIIRS<br\/> <b>Confidence: <\/b> Nominal<br\/>  <b>Day\/Night: <\/b> Day<br\/> <b>Scan: <\/b> 0.34 km<br\/> <b>Track: <\/b> 0.56 km<br\/> <b>FRP: <\/b> 5.61 MW<br\/> <b>Brightness: <\/b> 332.83 K" }, "geometry": { "type": "Point", "coordinates": [ -155.27617, 19.4049, 0.0 ] } },
{ "type": "Feature", "properties": { "Name": "Fire Detection Centroid ", "Description": "<b>Latitude: <\/b> 19.40456<br\/>  <b>Longitude: <\/b> -155.2794<br\/>  <b>Detection Time: <\/b> 2022-09-27 00:09 UTC<br\/>  <b>Sensor: <\/b> NOAA-20 VIIRS<br\/> <b>Confidence: <\/b> Nominal<br\/>  <b>Day\/Night: <\/b> Day<br\/> <b>Scan: <\/b> 0.34 km<br\/> <b>Track: <\/b> 0.56 km<br\/> <b>FRP: <\/b> 2.39 MW<br\/> <b>Brightness: <\/b> 331.8 K" }, "geometry": { "type": "Point", "coordinates": [ -155.2794, 19.40456, 0.0 ] } }
]
}
