{
"type": "FeatureCollection",
"crs": { "type": "name", "properties": { "name": "urn:ogc:def:crs:OGC:1.3:CRS84" } },
"features": [
{ "type": "Feature", "properties": { "Name": "Fire Detection Centroid ", "Description": "<b>Latitude: <\/b> 19.40699<br\/>  <b>Longitude: <\/b> -155.28848<br\/>  <b>Detection Time: <\/b> 2022-09-27 23:50 UTC<br\/>  <b>Sensor: <\/b> NOAA-20 VIIRS<br\/> <b>Confidence: <\/b> Nominal<br\/>  <b>Day\/Night: <\/b> Day<br\/> <b>Scan: <\/b> 0.51 km<br\/> <b>Track: <\/b> 0.41 km<br\/> <b>FRP: <\/b> 11 MW<br\/> <b>Brightness: <\/b> 352.91 K" }, "geometry": { "type": "Point", "coordinates": [ -155.28848, 19.40699, 0.0 ] } },
{ "type": "Feature", "properties": { "Name": "Fire Detection Centroid ", "Description": "<b>Latitude: <\/b> 19.4114<br\/>  <b>Longitude: <\/b> -155.28412<br\/>  <b>Detection Time: <\/b> 2022-09-27 23:50 UTC<br\/>  <b>Sensor: <\/b> NOAA-20 VIIRS<br\/> <b>Confidence: <\/b> Nominal<br\/>  <b>Day\/Night: <\/b> Day<br\/> <b>Scan: <\/b> 0.51 km<br\/> <b>Track: <\/b> 0.41 km<br\/> <b>FRP: <\/b> 14.82 MW<br\/> <b>Brightness: <\/b> 346.55 K" }, "geometry": { "type": "Point", "coordinates": [ -155.28412, 19.4114, 0.0 ] } },
{ "type": "Feature", "properties": { "Name": "Fire Detection Centroid ", "Description": "<b>Latitude: <\/b> 19.40763<br\/>  <b>Longitude: <\/b> -155.28352<br\/>  <b>Detection Time: <\/b> 2022-09-27 23:50 UTC<br\/>  <b>Sensor: <\/b> NOAA-20 VIIRS<br\/> <b>Confidence: <\/b> Nominal<br\/>  <b>Day\/Night: <\/b> Day<br\/> <b>Scan: <\/b> 0.51 km<br\/> <b>Track: <\/b> 0.41 km<br\/> <b>FRP: <\/b> 14.82 MW<br\/> <b>Brightness: <\/b> 345.76 K" }, "geometry": { "type": "Point", "coordinates": [ -155.28352, 19.40763, 0.0 ] } },
{ "type": "Feature", "properties": { "Name": "Fire Detection Centroid ", "Description": "<b>Latitude: <\/b> 19.40322<br\/>  <b>Longitude: <\/b> -155.28786<br\/>  <b>Detection Time: <\/b> 2022-09-27 23:50 UTC<br\/>  <b>Sensor: <\/b> NOAA-20 VIIRS<br\/> <b>Confidence: <\/b> Low<br\/>  <b>Day\/Night: <\/b> Day<br\/> <b>Scan: <\/b> 0.51 km<br\/> <b>Track: <\/b> 0.41 km<br\/> <b>FRP: <\/b> 121.82 MW<br\/> <b>Brightness: <\/b> 367 K" }, "geometry": { "type": "Point", "coordinates": [ -155.28786, 19.40322, 0.0 ] } },
{ "type": "Feature", "properties": { "Name": "Fire Detection Centroid ", "Description": "<b>Latitude: <\/b> 19.40385<br\/>  <b>Longitude: <\/b> -155.28294<br\/>  <b>Detection Time: <\/b> 2022-09-27 23:50 UTC<br\/>  <b>Sensor: <\/b> NOAA-20 VIIRS<br\/> <b>Confidence: <\/b> Nominal<br\/>  <b>Day\/Night: <\/b> Day<br\/> <b>Scan: <\/b> 0.51 km<br\/> <b>Track: <\/b> 0.41 km<br\/> <b>FRP: <\/b> 83.57 MW<br\/> <b>Brightness: <\/b> 349.32 K" }, "geometry": { "type": "Point", "coordinates": [ -155.28294, 19.40385, 0.0 ] } },
{ "type": "Feature", "properties": { "Name": "Fire Detection Centroid ", "Description": "<b>Latitude: <\/b> 19.41076<br\/>  <b>Longitude: <\/b> -155.28911<br\/>  <b>Detection Time: <\/b> 2022-09-27 23:50 UTC<br\/>  <b>Sensor: <\/b> NOAA-20 VIIRS<br\/> <b>Confidence: <\/b> Low<br\/>  <b>Day\/Night: <\/b> Day<br\/> <b>Scan: <\/b> 0.51 km<br\/> <b>Track: <\/b> 0.41 km<br\/> <b>FRP: <\/b> 11 MW<br\/> <b>Brightness: <\/b> 330.63 K" }, "geometry": { "type": "Point", "coordinates": [ -155.28911, 19.41076, 0.0 ] } }
]
}
