{
"type": "FeatureCollection",
"crs": { "type": "name", "properties": { "name": "urn:ogc:def:crs:OGC:1.3:CRS84" } },
"features": [
{ "type": "Feature", "properties": { "Name": "Fire Detection Centroid ", "Description": "<b>Latitude: <\/b> 19.40429<br\/>  <b>Longitude: <\/b> -155.28458<br\/>  <b>Detection Time: <\/b> 2024-01-01 11:55 UTC<br\/>  <b>Sensor: <\/b> NOAA-20 VIIRS<br\/> <b>Confidence: <\/b> Nominal<br\/>  <b>Day\/Night: <\/b> Night<br\/> <b>Scan: <\/b> 0.39 km<br\/> <b>Track: <\/b> 0.36 km<br\/> <b>FRP: <\/b> 2.45 MW<br\/> <b>Brightness: <\/b> 309.7 K" }, "geometry": { "type": "Point", "coordinates": [ -155.28458, 19.40429, 0.0 ] } }
]
}
