{
"type": "FeatureCollection",
"crs": { "type": "name", "properties": { "name": "urn:ogc:def:crs:OGC:1.3:CRS84" } },
"features": [
{ "type": "Feature", "properties": { "Name": "Fire Detection Centroid ", "Description": "<b>Latitude: <\/b> 19.15252<br\/>  <b>Longitude: <\/b> -71.50555<br\/>  <b>Detection Time: <\/b> 2024-02-06 05:35 UTC<br\/>  <b>Sensor: <\/b> NOAA-20 VIIRS<br\/> <b>Confidence: <\/b> Nominal<br\/>  <b>Day\/Night: <\/b> Night<br\/> <b>Scan: <\/b> 0.5 km<br\/> <b>Track: <\/b> 0.7 km<br\/> <b>FRP: <\/b> 1.71 MW<br\/> <b>Brightness: <\/b> 302.55 K" }, "geometry": { "type": "Point", "coordinates": [ -71.50555, 19.15252, 0.0 ] } },
{ "type": "Feature", "properties": { "Name": "Fire Detection Centroid ", "Description": "<b>Latitude: <\/b> 19.20786<br\/>  <b>Longitude: <\/b> -71.62527<br\/>  <b>Detection Time: <\/b> 2024-02-06 05:35 UTC<br\/>  <b>Sensor: <\/b> NOAA-20 VIIRS<br\/> <b>Confidence: <\/b> Nominal<br\/>  <b>Day\/Night: <\/b> Night<br\/> <b>Scan: <\/b> 0.6 km<br\/> <b>Track: <\/b> 0.7 km<br\/> <b>FRP: <\/b> 1.65 MW<br\/> <b>Brightness: <\/b> 309.25 K" }, "geometry": { "type": "Point", "coordinates": [ -71.62527, 19.20786, 0.0 ] } },
{ "type": "Feature", "properties": { "Name": "Fire Detection Centroid ", "Description": "<b>Latitude: <\/b> 19.23674<br\/>  <b>Longitude: <\/b> -71.8688<br\/>  <b>Detection Time: <\/b> 2024-02-06 05:35 UTC<br\/>  <b>Sensor: <\/b> NOAA-20 VIIRS<br\/> <b>Confidence: <\/b> Nominal<br\/>  <b>Day\/Night: <\/b> Night<br\/> <b>Scan: <\/b> 0.6 km<br\/> <b>Track: <\/b> 0.7 km<br\/> <b>FRP: <\/b> 0.56 MW<br\/> <b>Brightness: <\/b> 302.91 K" }, "geometry": { "type": "Point", "coordinates": [ -71.8688, 19.23674, 0.0 ] } },
{ "type": "Feature", "properties": { "Name": "Fire Detection Centroid ", "Description": "<b>Latitude: <\/b> 18.11082<br\/>  <b>Longitude: <\/b> -71.10708<br\/>  <b>Detection Time: <\/b> 2024-02-06 05:35 UTC<br\/>  <b>Sensor: <\/b> NOAA-20 VIIRS<br\/> <b>Confidence: <\/b> Nominal<br\/>  <b>Day\/Night: <\/b> Night<br\/> <b>Scan: <\/b> 0.5 km<br\/> <b>Track: <\/b> 0.7 km<br\/> <b>FRP: <\/b> 1.49 MW<br\/> <b>Brightness: <\/b> 305.21 K" }, "geometry": { "type": "Point", "coordinates": [ -71.10708, 18.11082, 0.0 ] } },
{ "type": "Feature", "properties": { "Name": "Fire Detection Centroid ", "Description": "<b>Latitude: <\/b> 18.31882<br\/>  <b>Longitude: <\/b> -71.09163<br\/>  <b>Detection Time: <\/b> 2024-02-06 05:35 UTC<br\/>  <b>Sensor: <\/b> NOAA-20 VIIRS<br\/> <b>Confidence: <\/b> Nominal<br\/>  <b>Day\/Night: <\/b> Night<br\/> <b>Scan: <\/b> 0.5 km<br\/> <b>Track: <\/b> 0.7 km<br\/> <b>FRP: <\/b> 0.85 MW<br\/> <b>Brightness: <\/b> 310.33 K" }, "geometry": { "type": "Point", "coordinates": [ -71.09163, 18.31882, 0.0 ] } },
{ "type": "Feature", "properties": { "Name": "Fire Detection Centroid ", "Description": "<b>Latitude: <\/b> 19.0027<br\/>  <b>Longitude: <\/b> -71.64738<br\/>  <b>Detection Time: <\/b> 2024-02-06 05:35 UTC<br\/>  <b>Sensor: <\/b> NOAA-20 VIIRS<br\/> <b>Confidence: <\/b> Nominal<br\/>  <b>Day\/Night: <\/b> Night<br\/> <b>Scan: <\/b> 0.6 km<br\/> <b>Track: <\/b> 0.7 km<br\/> <b>FRP: <\/b> 0.84 MW<br\/> <b>Brightness: <\/b> 308.05 K" }, "geometry": { "type": "Point", "coordinates": [ -71.64738, 19.0027, 0.0 ] } },
{ "type": "Feature", "properties": { "Name": "Fire Detection Centroid ", "Description": "<b>Latitude: <\/b> 19.03081<br\/>  <b>Longitude: <\/b> -71.89856<br\/>  <b>Detection Time: <\/b> 2024-02-06 05:35 UTC<br\/>  <b>Sensor: <\/b> NOAA-20 VIIRS<br\/> <b>Confidence: <\/b> Nominal<br\/>  <b>Day\/Night: <\/b> Night<br\/> <b>Scan: <\/b> 0.6 km<br\/> <b>Track: <\/b> 0.7 km<br\/> <b>FRP: <\/b> 0.7 MW<br\/> <b>Brightness: <\/b> 303.07 K" }, "geometry": { "type": "Point", "coordinates": [ -71.89856, 19.03081, 0.0 ] } }
]
}
