{
"type": "FeatureCollection",
"crs": { "type": "name", "properties": { "name": "urn:ogc:def:crs:OGC:1.3:CRS84" } },
"features": [
{ "type": "Feature", "properties": { "Name": "Fire Detection Centroid ", "Description": "<b>Latitude: <\/b> 18.92797<br\/>  <b>Longitude: <\/b> -70.35226<br\/>  <b>Detection Time: <\/b> 2023-09-04 05:42 UTC<br\/>  <b>Sensor: <\/b> NOAA-20 VIIRS<br\/> <b>Confidence: <\/b> Nominal<br\/>  <b>Day\/Night: <\/b> Night<br\/> <b>Scan: <\/b> 0.3 km<br\/> <b>Track: <\/b> 0.6 km<br\/> <b>FRP: <\/b> 4.58 MW<br\/> <b>Brightness: <\/b> 329.53 K" }, "geometry": { "type": "Point", "coordinates": [ -70.35226, 18.92797, 0.0 ] } },
{ "type": "Feature", "properties": { "Name": "Fire Detection Centroid ", "Description": "<b>Latitude: <\/b> 18.26446<br\/>  <b>Longitude: <\/b> -70.51654<br\/>  <b>Detection Time: <\/b> 2023-09-04 05:42 UTC<br\/>  <b>Sensor: <\/b> NOAA-20 VIIRS<br\/> <b>Confidence: <\/b> Nominal<br\/>  <b>Day\/Night: <\/b> Night<br\/> <b>Scan: <\/b> 0.3 km<br\/> <b>Track: <\/b> 0.6 km<br\/> <b>FRP: <\/b> 0.48 MW<br\/> <b>Brightness: <\/b> 307.59 K" }, "geometry": { "type": "Point", "coordinates": [ -70.51654, 18.26446, 0.0 ] } },
{ "type": "Feature", "properties": { "Name": "Fire Detection Centroid ", "Description": "<b>Latitude: <\/b> 18.92834<br\/>  <b>Longitude: <\/b> -70.35573<br\/>  <b>Detection Time: <\/b> 2023-09-04 05:42 UTC<br\/>  <b>Sensor: <\/b> NOAA-20 VIIRS<br\/> <b>Confidence: <\/b> Nominal<br\/>  <b>Day\/Night: <\/b> Night<br\/> <b>Scan: <\/b> 0.3 km<br\/> <b>Track: <\/b> 0.6 km<br\/> <b>FRP: <\/b> 5.1 MW<br\/> <b>Brightness: <\/b> 337.64 K" }, "geometry": { "type": "Point", "coordinates": [ -70.35573, 18.92834, 0.0 ] } },
{ "type": "Feature", "properties": { "Name": "Fire Detection Centroid ", "Description": "<b>Latitude: <\/b> 48.19009<br\/>  <b>Longitude: <\/b> -64.9213<br\/>  <b>Detection Time: <\/b> 2023-09-04 05:34 UTC<br\/>  <b>Sensor: <\/b> NOAA-20 VIIRS<br\/> <b>Confidence: <\/b> Nominal<br\/>  <b>Day\/Night: <\/b> Night<br\/> <b>Scan: <\/b> 0.3 km<br\/> <b>Track: <\/b> 0.6 km<br\/> <b>FRP: <\/b> 0.69 MW<br\/> <b>Brightness: <\/b> 311.38 K" }, "geometry": { "type": "Point", "coordinates": [ -64.9213, 48.19009, 0.0 ] } }
]
}
