{
"type": "FeatureCollection",
"crs": { "type": "name", "properties": { "name": "urn:ogc:def:crs:OGC:1.3:CRS84" } },
"features": [
{ "type": "Feature", "properties": { "Name": "Fire Detection Centroid ", "Description": "<b>Latitude: <\/b> 18.92844<br\/>  <b>Longitude: <\/b> -70.35249<br\/>  <b>Detection Time: <\/b> 2023-05-21 05:29 UTC<br\/>  <b>Sensor: <\/b> NOAA-20 VIIRS<br\/> <b>Confidence: <\/b> Nominal<br\/>  <b>Day\/Night: <\/b> Night<br\/> <b>Scan: <\/b> 0.6 km<br\/> <b>Track: <\/b> 0.7 km<br\/> <b>FRP: <\/b> 3.97 MW<br\/> <b>Brightness: <\/b> 328.96 K" }, "geometry": { "type": "Point", "coordinates": [ -70.35249, 18.92844, 0.0 ] } },
{ "type": "Feature", "properties": { "Name": "Fire Detection Centroid ", "Description": "<b>Latitude: <\/b> 18.92896<br\/>  <b>Longitude: <\/b> -70.35819<br\/>  <b>Detection Time: <\/b> 2023-05-21 05:29 UTC<br\/>  <b>Sensor: <\/b> NOAA-20 VIIRS<br\/> <b>Confidence: <\/b> Nominal<br\/>  <b>Day\/Night: <\/b> Night<br\/> <b>Scan: <\/b> 0.6 km<br\/> <b>Track: <\/b> 0.7 km<br\/> <b>FRP: <\/b> 3.97 MW<br\/> <b>Brightness: <\/b> 306.87 K" }, "geometry": { "type": "Point", "coordinates": [ -70.35819, 18.92896, 0.0 ] } }
]
}
