{
"type": "FeatureCollection",
"crs": { "type": "name", "properties": { "name": "urn:ogc:def:crs:OGC:1.3:CRS84" } },
"features": [
{ "type": "Feature", "properties": { "Name": "Fire Detection Centroid ", "Description": "<b>Latitude: <\/b> 45.28171<br\/>  <b>Longitude: <\/b> -66.02167<br\/>  <b>Detection Time: <\/b> 2022-10-04 05:15 UTC<br\/>  <b>Sensor: <\/b> NOAA-20 VIIRS<br\/> <b>Confidence: <\/b> Nominal<br\/>  <b>Day\/Night: <\/b> Night<br\/> <b>Scan: <\/b> 0.6 km<br\/> <b>Track: <\/b> 0.7 km<br\/> <b>FRP: <\/b> 1.64 MW<br\/> <b>Brightness: <\/b> 301.13 K" }, "geometry": { "type": "Point", "coordinates": [ -66.02167, 45.28171, 0.0 ] } },
{ "type": "Feature", "properties": { "Name": "Fire Detection Centroid ", "Description": "<b>Latitude: <\/b> 45.28447<br\/>  <b>Longitude: <\/b> -66.0185<br\/>  <b>Detection Time: <\/b> 2022-10-04 05:15 UTC<br\/>  <b>Sensor: <\/b> NOAA-20 VIIRS<br\/> <b>Confidence: <\/b> Nominal<br\/>  <b>Day\/Night: <\/b> Night<br\/> <b>Scan: <\/b> 0.6 km<br\/> <b>Track: <\/b> 0.7 km<br\/> <b>FRP: <\/b> 1.71 MW<br\/> <b>Brightness: <\/b> 296.04 K" }, "geometry": { "type": "Point", "coordinates": [ -66.0185, 45.28447, 0.0 ] } }
]
}
