{
"type": "FeatureCollection",
"crs": { "type": "name", "properties": { "name": "urn:ogc:def:crs:OGC:1.3:CRS84" } },
"features": [
{ "type": "Feature", "properties": { "Name": "Fire Detection Centroid ", "Description": "<b>Latitude: <\/b> 18.0069<br\/>  <b>Longitude: <\/b> -66.65671<br\/>  <b>Detection Time: <\/b> 2022-08-31 06:00 UTC<br\/>  <b>Sensor: <\/b> NOAA-20 VIIRS<br\/> <b>Confidence: <\/b> Nominal<br\/>  <b>Day\/Night: <\/b> Night<br\/> <b>Scan: <\/b> 0.4 km<br\/> <b>Track: <\/b> 0.4 km<br\/> <b>FRP: <\/b> 0.46 MW<br\/> <b>Brightness: <\/b> 303.85 K" }, "geometry": { "type": "Point", "coordinates": [ -66.65671, 18.0069, 0.0 ] } },
{ "type": "Feature", "properties": { "Name": "Fire Detection Centroid ", "Description": "<b>Latitude: <\/b> 18.9291<br\/>  <b>Longitude: <\/b> -70.35876<br\/>  <b>Detection Time: <\/b> 2022-08-31 06:00 UTC<br\/>  <b>Sensor: <\/b> NOAA-20 VIIRS<br\/> <b>Confidence: <\/b> Nominal<br\/>  <b>Day\/Night: <\/b> Night<br\/> <b>Scan: <\/b> 0.5 km<br\/> <b>Track: <\/b> 0.4 km<br\/> <b>FRP: <\/b> 1.01 MW<br\/> <b>Brightness: <\/b> 300.49 K" }, "geometry": { "type": "Point", "coordinates": [ -70.35876, 18.9291, 0.0 ] } },
{ "type": "Feature", "properties": { "Name": "Fire Detection Centroid ", "Description": "<b>Latitude: <\/b> 19.06422<br\/>  <b>Longitude: <\/b> -70.6967<br\/>  <b>Detection Time: <\/b> 2022-08-31 06:00 UTC<br\/>  <b>Sensor: <\/b> NOAA-20 VIIRS<br\/> <b>Confidence: <\/b> Nominal<br\/>  <b>Day\/Night: <\/b> Night<br\/> <b>Scan: <\/b> 0.6 km<br\/> <b>Track: <\/b> 0.4 km<br\/> <b>FRP: <\/b> 0.5 MW<br\/> <b>Brightness: <\/b> 298.86 K" }, "geometry": { "type": "Point", "coordinates": [ -70.6967, 19.06422, 0.0 ] } },
{ "type": "Feature", "properties": { "Name": "Fire Detection Centroid ", "Description": "<b>Latitude: <\/b> 40.89505<br\/>  <b>Longitude: <\/b> -77.71331<br\/>  <b>Detection Time: <\/b> 2022-08-31 05:54 UTC<br\/>  <b>Sensor: <\/b> NOAA-20 VIIRS<br\/> <b>Confidence: <\/b> Nominal<br\/>  <b>Day\/Night: <\/b> Night<br\/> <b>Scan: <\/b> 0.8 km<br\/> <b>Track: <\/b> 0.8 km<br\/> <b>FRP: <\/b> 2.4 MW<br\/> <b>Brightness: <\/b> 312.74 K" }, "geometry": { "type": "Point", "coordinates": [ -77.71331, 40.89505, 0.0 ] } },
{ "type": "Feature", "properties": { "Name": "Fire Detection Centroid ", "Description": "<b>Latitude: <\/b> 39.94192<br\/>  <b>Longitude: <\/b> -76.8196<br\/>  <b>Detection Time: <\/b> 2022-08-31 05:54 UTC<br\/>  <b>Sensor: <\/b> NOAA-20 VIIRS<br\/> <b>Confidence: <\/b> Nominal<br\/>  <b>Day\/Night: <\/b> Night<br\/> <b>Scan: <\/b> 0.7 km<br\/> <b>Track: <\/b> 0.7 km<br\/> <b>FRP: <\/b> 1.89 MW<br\/> <b>Brightness: <\/b> 311.75 K" }, "geometry": { "type": "Point", "coordinates": [ -76.8196, 39.94192, 0.0 ] } },
{ "type": "Feature", "properties": { "Name": "Fire Detection Centroid ", "Description": "<b>Latitude: <\/b> 39.58743<br\/>  <b>Longitude: <\/b> -75.63845<br\/>  <b>Detection Time: <\/b> 2022-08-31 05:54 UTC<br\/>  <b>Sensor: <\/b> NOAA-20 VIIRS<br\/> <b>Confidence: <\/b> Nominal<br\/>  <b>Day\/Night: <\/b> Night<br\/> <b>Scan: <\/b> 0.6 km<br\/> <b>Track: <\/b> 0.7 km<br\/> <b>FRP: <\/b> 1.15 MW<br\/> <b>Brightness: <\/b> 303.23 K" }, "geometry": { "type": "Point", "coordinates": [ -75.63845, 39.58743, 0.0 ] } },
{ "type": "Feature", "properties": { "Name": "Fire Detection Centroid ", "Description": "<b>Latitude: <\/b> 39.58798<br\/>  <b>Longitude: <\/b> -75.63892<br\/>  <b>Detection Time: <\/b> 2022-08-31 05:54 UTC<br\/>  <b>Sensor: <\/b> NOAA-20 VIIRS<br\/> <b>Confidence: <\/b> Nominal<br\/>  <b>Day\/Night: <\/b> Night<br\/> <b>Scan: <\/b> 0.6 km<br\/> <b>Track: <\/b> 0.7 km<br\/> <b>FRP: <\/b> 1.09 MW<br\/> <b>Brightness: <\/b> 303.47 K" }, "geometry": { "type": "Point", "coordinates": [ -75.63892, 39.58798, 0.0 ] } }
]
}
