{
"type": "FeatureCollection",
"crs": { "type": "name", "properties": { "name": "urn:ogc:def:crs:OGC:1.3:CRS84" } },
"features": [
{ "type": "Feature", "properties": { "Name": "Fire Detection Centroid ", "Description": "<b>Latitude: <\/b> 19.40676<br\/>  <b>Longitude: <\/b> -155.27919<br\/>  <b>Detection Time: <\/b> 2022-07-15 12:25 UTC<br\/>  <b>Sensor: <\/b> NOAA-20 VIIRS<br\/> <b>Confidence: <\/b> Nominal<br\/>  <b>Day\/Night: <\/b> Night<br\/> <b>Scan: <\/b> 0.51 km<br\/> <b>Track: <\/b> 0.5 km<br\/> <b>FRP: <\/b> 3.74 MW<br\/> <b>Brightness: <\/b> 314.85 K" }, "geometry": { "type": "Point", "coordinates": [ -155.27919, 19.40676, 0.0 ] } },
{ "type": "Feature", "properties": { "Name": "Fire Detection Centroid ", "Description": "<b>Latitude: <\/b> 19.40872<br\/>  <b>Longitude: <\/b> -155.28905<br\/>  <b>Detection Time: <\/b> 2022-07-15 12:25 UTC<br\/>  <b>Sensor: <\/b> NOAA-20 VIIRS<br\/> <b>Confidence: <\/b> Nominal<br\/>  <b>Day\/Night: <\/b> Night<br\/> <b>Scan: <\/b> 0.51 km<br\/> <b>Track: <\/b> 0.5 km<br\/> <b>FRP: <\/b> 81.17 MW<br\/> <b>Brightness: <\/b> 335.02 K" }, "geometry": { "type": "Point", "coordinates": [ -155.28905, 19.40872, 0.0 ] } },
{ "type": "Feature", "properties": { "Name": "Fire Detection Centroid ", "Description": "<b>Latitude: <\/b> 19.41124<br\/>  <b>Longitude: <\/b> -155.27823<br\/>  <b>Detection Time: <\/b> 2022-07-15 12:25 UTC<br\/>  <b>Sensor: <\/b> NOAA-20 VIIRS<br\/> <b>Confidence: <\/b> Nominal<br\/>  <b>Day\/Night: <\/b> Night<br\/> <b>Scan: <\/b> 0.51 km<br\/> <b>Track: <\/b> 0.5 km<br\/> <b>FRP: <\/b> 2.33 MW<br\/> <b>Brightness: <\/b> 307.32 K" }, "geometry": { "type": "Point", "coordinates": [ -155.27823, 19.41124, 0.0 ] } },
{ "type": "Feature", "properties": { "Name": "Fire Detection Centroid ", "Description": "<b>Latitude: <\/b> 19.41323<br\/>  <b>Longitude: <\/b> -155.28824<br\/>  <b>Detection Time: <\/b> 2022-07-15 12:25 UTC<br\/>  <b>Sensor: <\/b> NOAA-20 VIIRS<br\/> <b>Confidence: <\/b> Nominal<br\/>  <b>Day\/Night: <\/b> Night<br\/> <b>Scan: <\/b> 0.51 km<br\/> <b>Track: <\/b> 0.5 km<br\/> <b>FRP: <\/b> 3.08 MW<br\/> <b>Brightness: <\/b> 306.9 K" }, "geometry": { "type": "Point", "coordinates": [ -155.28824, 19.41323, 0.0 ] } },
{ "type": "Feature", "properties": { "Name": "Fire Detection Centroid ", "Description": "<b>Latitude: <\/b> 19.41222<br\/>  <b>Longitude: <\/b> -155.28317<br\/>  <b>Detection Time: <\/b> 2022-07-15 12:25 UTC<br\/>  <b>Sensor: <\/b> NOAA-20 VIIRS<br\/> <b>Confidence: <\/b> Nominal<br\/>  <b>Day\/Night: <\/b> Night<br\/> <b>Scan: <\/b> 0.51 km<br\/> <b>Track: <\/b> 0.5 km<br\/> <b>FRP: <\/b> 3.08 MW<br\/> <b>Brightness: <\/b> 323.06 K" }, "geometry": { "type": "Point", "coordinates": [ -155.28317, 19.41222, 0.0 ] } },
{ "type": "Feature", "properties": { "Name": "Fire Detection Centroid ", "Description": "<b>Latitude: <\/b> 19.40324<br\/>  <b>Longitude: <\/b> -155.28496<br\/>  <b>Detection Time: <\/b> 2022-07-15 12:25 UTC<br\/>  <b>Sensor: <\/b> NOAA-20 VIIRS<br\/> <b>Confidence: <\/b> Nominal<br\/>  <b>Day\/Night: <\/b> Night<br\/> <b>Scan: <\/b> 0.51 km<br\/> <b>Track: <\/b> 0.5 km<br\/> <b>FRP: <\/b> 81.17 MW<br\/> <b>Brightness: <\/b> 326.42 K" }, "geometry": { "type": "Point", "coordinates": [ -155.28496, 19.40324, 0.0 ] } },
{ "type": "Feature", "properties": { "Name": "Fire Detection Centroid ", "Description": "<b>Latitude: <\/b> 19.40422<br\/>  <b>Longitude: <\/b> -155.28992<br\/>  <b>Detection Time: <\/b> 2022-07-15 12:25 UTC<br\/>  <b>Sensor: <\/b> NOAA-20 VIIRS<br\/> <b>Confidence: <\/b> Nominal<br\/>  <b>Day\/Night: <\/b> Night<br\/> <b>Scan: <\/b> 0.51 km<br\/> <b>Track: <\/b> 0.5 km<br\/> <b>FRP: <\/b> 81.17 MW<br\/> <b>Brightness: <\/b> 341.06 K" }, "geometry": { "type": "Point", "coordinates": [ -155.28992, 19.40422, 0.0 ] } }
]
}
