{
"type": "FeatureCollection",
"crs": { "type": "name", "properties": { "name": "urn:ogc:def:crs:OGC:1.3:CRS84" } },
"features": [
{ "type": "Feature", "properties": { "Name": "Fire Detection Centroid ", "Description": "<b>Latitude: <\/b> 19.40444<br\/>  <b>Longitude: <\/b> -155.28665<br\/>  <b>Detection Time: <\/b> 2022-11-03 00:15 UTC<br\/>  <b>Sensor: <\/b> NOAA-20 VIIRS<br\/> <b>Confidence: <\/b> Nominal<br\/>  <b>Day\/Night: <\/b> Day<br\/> <b>Scan: <\/b> 0.4 km<br\/> <b>Track: <\/b> 0.6 km<br\/> <b>FRP: <\/b> 7.18 MW<br\/> <b>Brightness: <\/b> 350.18 K" }, "geometry": { "type": "Point", "coordinates": [ -155.28665, 19.40444, 0.0 ] } },
{ "type": "Feature", "properties": { "Name": "Fire Detection Centroid ", "Description": "<b>Latitude: <\/b> 19.40484<br\/>  <b>Longitude: <\/b> -155.28247<br\/>  <b>Detection Time: <\/b> 2022-11-03 00:15 UTC<br\/>  <b>Sensor: <\/b> NOAA-20 VIIRS<br\/> <b>Confidence: <\/b> Low<br\/>  <b>Day\/Night: <\/b> Day<br\/> <b>Scan: <\/b> 0.4 km<br\/> <b>Track: <\/b> 0.6 km<br\/> <b>FRP: <\/b> 10.51 MW<br\/> <b>Brightness: <\/b> 326.69 K" }, "geometry": { "type": "Point", "coordinates": [ -155.28247, 19.40484, 0.0 ] } },
{ "type": "Feature", "properties": { "Name": "Fire Detection Centroid ", "Description": "<b>Latitude: <\/b> 19.40401<br\/>  <b>Longitude: <\/b> -155.29114<br\/>  <b>Detection Time: <\/b> 2022-11-03 00:15 UTC<br\/>  <b>Sensor: <\/b> NOAA-20 VIIRS<br\/> <b>Confidence: <\/b> Nominal<br\/>  <b>Day\/Night: <\/b> Day<br\/> <b>Scan: <\/b> 0.4 km<br\/> <b>Track: <\/b> 0.6 km<br\/> <b>FRP: <\/b> 7.18 MW<br\/> <b>Brightness: <\/b> 338.02 K" }, "geometry": { "type": "Point", "coordinates": [ -155.29114, 19.40401, 0.0 ] } }
]
}
