{
"type": "FeatureCollection",
"crs": { "type": "name", "properties": { "name": "urn:ogc:def:crs:OGC:1.3:CRS84" } },
"features": [
{ "type": "Feature", "properties": { "Name": "Fire Detection Centroid ", "Description": "<b>Latitude: <\/b> 19.40631<br\/>  <b>Longitude: <\/b> -155.28162<br\/>  <b>Detection Time: <\/b> 2023-04-05 11:38 UTC<br\/>  <b>Sensor: <\/b> NOAA-20 VIIRS<br\/> <b>Confidence: <\/b> Nominal<br\/>  <b>Day\/Night: <\/b> Night<br\/> <b>Scan: <\/b> 0.4 km<br\/> <b>Track: <\/b> 0.44 km<br\/> <b>FRP: <\/b> 2.62 MW<br\/> <b>Brightness: <\/b> 299.19 K" }, "geometry": { "type": "Point", "coordinates": [ -155.28162, 19.40631, 0.0 ] } },
{ "type": "Feature", "properties": { "Name": "Fire Detection Centroid ", "Description": "<b>Latitude: <\/b> 19.40582<br\/>  <b>Longitude: <\/b> -155.27782<br\/>  <b>Detection Time: <\/b> 2023-04-05 11:38 UTC<br\/>  <b>Sensor: <\/b> NOAA-20 VIIRS<br\/> <b>Confidence: <\/b> Nominal<br\/>  <b>Day\/Night: <\/b> Night<br\/> <b>Scan: <\/b> 0.4 km<br\/> <b>Track: <\/b> 0.44 km<br\/> <b>FRP: <\/b> 1.19 MW<br\/> <b>Brightness: <\/b> 298.86 K" }, "geometry": { "type": "Point", "coordinates": [ -155.27782, 19.40582, 0.0 ] } },
{ "type": "Feature", "properties": { "Name": "Fire Detection Centroid ", "Description": "<b>Latitude: <\/b> 48.21653<br\/>  <b>Longitude: <\/b> -122.51282<br\/>  <b>Detection Time: <\/b> 2023-04-05 11:28 UTC<br\/>  <b>Sensor: <\/b> NOAA-20 VIIRS<br\/> <b>Confidence: <\/b> Nominal<br\/>  <b>Day\/Night: <\/b> Night<br\/> <b>Scan: <\/b> 0.55 km<br\/> <b>Track: <\/b> 0.68 km<br\/> <b>FRP: <\/b> 0.95 MW<br\/> <b>Brightness: <\/b> 297.42 K" }, "geometry": { "type": "Point", "coordinates": [ -122.51282, 48.21653, 0.0 ] } }
]
}
