{
"type": "FeatureCollection",
"crs": { "type": "name", "properties": { "name": "urn:ogc:def:crs:OGC:1.3:CRS84" } },
"features": [
{ "type": "Feature", "properties": { "Name": "Fire Detection Centroid ", "Description": "<b>Latitude: <\/b> 47.57057<br\/>  <b>Longitude: <\/b> -122.37385<br\/>  <b>Detection Time: <\/b> 2024-01-14 11:02 UTC<br\/>  <b>Sensor: <\/b> NOAA-20 VIIRS<br\/> <b>Confidence: <\/b> Nominal<br\/>  <b>Day\/Night: <\/b> Night<br\/> <b>Scan: <\/b> 0.63 km<br\/> <b>Track: <\/b> 0.54 km<br\/> <b>FRP: <\/b> 1.16 MW<br\/> <b>Brightness: <\/b> 303.66 K" }, "geometry": { "type": "Point", "coordinates": [ -122.37385, 47.57057, 0.0 ] } }
]
}
