{
"type": "FeatureCollection",
"crs": { "type": "name", "properties": { "name": "urn:ogc:def:crs:OGC:1.3:CRS84" } },
"features": [
{ "type": "Feature", "properties": { "Name": "Fire Detection Centroid ", "Description": "<b>Latitude: <\/b> 38.01623<br\/>  <b>Longitude: <\/b> -122.1143<br\/>  <b>Detection Time: <\/b> 2023-12-24 10:58 UTC<br\/>  <b>Sensor: <\/b> NOAA-20 VIIRS<br\/> <b>Confidence: <\/b> Nominal<br\/>  <b>Day\/Night: <\/b> Night<br\/> <b>Scan: <\/b> 0.5 km<br\/> <b>Track: <\/b> 0.7 km<br\/> <b>FRP: <\/b> 1.43 MW<br\/> <b>Brightness: <\/b> 296.12 K" }, "geometry": { "type": "Point", "coordinates": [ -122.1143, 38.01623, 0.0 ] } },
{ "type": "Feature", "properties": { "Name": "Fire Detection Centroid ", "Description": "<b>Latitude: <\/b> 38.01585<br\/>  <b>Longitude: <\/b> -122.11705<br\/>  <b>Detection Time: <\/b> 2023-12-24 10:57 UTC<br\/>  <b>Sensor: <\/b> NOAA-20 VIIRS<br\/> <b>Confidence: <\/b> Nominal<br\/>  <b>Day\/Night: <\/b> Night<br\/> <b>Scan: <\/b> 0.52 km<br\/> <b>Track: <\/b> 0.67 km<br\/> <b>FRP: <\/b> 1.56 MW<br\/> <b>Brightness: <\/b> 296.12 K" }, "geometry": { "type": "Point", "coordinates": [ -122.11705, 38.01585, 0.0 ] } },
{ "type": "Feature", "properties": { "Name": "Fire Detection Centroid ", "Description": "<b>Latitude: <\/b> 48.21592<br\/>  <b>Longitude: <\/b> -118.04056<br\/>  <b>Detection Time: <\/b> 2023-12-24 10:55 UTC<br\/>  <b>Sensor: <\/b> NOAA-20 VIIRS<br\/> <b>Confidence: <\/b> Nominal<br\/>  <b>Day\/Night: <\/b> Night<br\/> <b>Scan: <\/b> 0.4 km<br\/> <b>Track: <\/b> 0.6 km<br\/> <b>FRP: <\/b> 1.72 MW<br\/> <b>Brightness: <\/b> 322.04 K" }, "geometry": { "type": "Point", "coordinates": [ -118.04056, 48.21592, 0.0 ] } },
{ "type": "Feature", "properties": { "Name": "Fire Detection Centroid ", "Description": "<b>Latitude: <\/b> 48.21628<br\/>  <b>Longitude: <\/b> -118.0381<br\/>  <b>Detection Time: <\/b> 2023-12-24 10:55 UTC<br\/>  <b>Sensor: <\/b> NOAA-20 VIIRS<br\/> <b>Confidence: <\/b> Nominal<br\/>  <b>Day\/Night: <\/b> Night<br\/> <b>Scan: <\/b> 0.4 km<br\/> <b>Track: <\/b> 0.6 km<br\/> <b>FRP: <\/b> 1.72 MW<br\/> <b>Brightness: <\/b> 322.04 K" }, "geometry": { "type": "Point", "coordinates": [ -118.0381, 48.21628, 0.0 ] } }
]
}
