{
"type": "FeatureCollection",
"crs": { "type": "name", "properties": { "name": "urn:ogc:def:crs:OGC:1.3:CRS84" } },
"features": [
{ "type": "Feature", "properties": { "Name": "Fire Detection Centroid ", "Description": "<b>Latitude: <\/b> 18.93032<br\/>  <b>Longitude: <\/b> -70.35291<br\/>  <b>Detection Time: <\/b> 2023-10-17 05:35 UTC<br\/>  <b>Sensor: <\/b> NOAA-20 VIIRS<br\/> <b>Confidence: <\/b> Nominal<br\/>  <b>Day\/Night: <\/b> Night<br\/> <b>Scan: <\/b> 0.5 km<br\/> <b>Track: <\/b> 0.6 km<br\/> <b>FRP: <\/b> 3.72 MW<br\/> <b>Brightness: <\/b> 335.73 K" }, "geometry": { "type": "Point", "coordinates": [ -70.35291, 18.93032, 0.0 ] } },
{ "type": "Feature", "properties": { "Name": "Fire Detection Centroid ", "Description": "<b>Latitude: <\/b> 20.22348<br\/>  <b>Longitude: <\/b> -71.83594<br\/>  <b>Detection Time: <\/b> 2023-10-17 05:35 UTC<br\/>  <b>Sensor: <\/b> NOAA-20 VIIRS<br\/> <b>Confidence: <\/b> Nominal<br\/>  <b>Day\/Night: <\/b> Night<br\/> <b>Scan: <\/b> 0.6 km<br\/> <b>Track: <\/b> 0.7 km<br\/> <b>FRP: <\/b> 6.28 MW<br\/> <b>Brightness: <\/b> 295.66 K" }, "geometry": { "type": "Point", "coordinates": [ -71.83594, 20.22348, 0.0 ] } },
{ "type": "Feature", "properties": { "Name": "Fire Detection Centroid ", "Description": "<b>Latitude: <\/b> 18.93076<br\/>  <b>Longitude: <\/b> -70.35732<br\/>  <b>Detection Time: <\/b> 2023-10-17 05:35 UTC<br\/>  <b>Sensor: <\/b> NOAA-20 VIIRS<br\/> <b>Confidence: <\/b> Nominal<br\/>  <b>Day\/Night: <\/b> Night<br\/> <b>Scan: <\/b> 0.5 km<br\/> <b>Track: <\/b> 0.6 km<br\/> <b>FRP: <\/b> 3.72 MW<br\/> <b>Brightness: <\/b> 318.02 K" }, "geometry": { "type": "Point", "coordinates": [ -70.35732, 18.93076, 0.0 ] } }
]
}
