{
"type": "FeatureCollection",
"crs": { "type": "name", "properties": { "name": "urn:ogc:def:crs:OGC:1.3:CRS84" } },
"features": [
{ "type": "Feature", "properties": { "Name": "Fire Detection Centroid ", "Description": "<b>Latitude: <\/b> 40.13977<br\/>  <b>Longitude: <\/b> -123.47543<br\/>  <b>Detection Time: <\/b> 2023-05-03 11:04 UTC<br\/>  <b>Sensor: <\/b> NOAA-20 VIIRS<br\/> <b>Confidence: <\/b> Nominal<br\/>  <b>Day\/Night: <\/b> Night<br\/> <b>Scan: <\/b> 0.47 km<br\/> <b>Track: <\/b> 0.64 km<br\/> <b>FRP: <\/b> 1.46 MW<br\/> <b>Brightness: <\/b> 304.38 K" }, "geometry": { "type": "Point", "coordinates": [ -123.47543, 40.13977, 0.0 ] } },
{ "type": "Feature", "properties": { "Name": "Fire Detection Centroid ", "Description": "<b>Latitude: <\/b> 39.87114<br\/>  <b>Longitude: <\/b> -121.97417<br\/>  <b>Detection Time: <\/b> 2023-05-03 11:04 UTC<br\/>  <b>Sensor: <\/b> NOAA-20 VIIRS<br\/> <b>Confidence: <\/b> Nominal<br\/>  <b>Day\/Night: <\/b> Night<br\/> <b>Scan: <\/b> 0.56 km<br\/> <b>Track: <\/b> 0.69 km<br\/> <b>FRP: <\/b> 0.73 MW<br\/> <b>Brightness: <\/b> 300.81 K" }, "geometry": { "type": "Point", "coordinates": [ -121.97417, 39.87114, 0.0 ] } },
{ "type": "Feature", "properties": { "Name": "Fire Detection Centroid ", "Description": "<b>Latitude: <\/b> 45.23217<br\/>  <b>Longitude: <\/b> -123.16555<br\/>  <b>Detection Time: <\/b> 2023-05-03 11:04 UTC<br\/>  <b>Sensor: <\/b> NOAA-20 VIIRS<br\/> <b>Confidence: <\/b> Nominal<br\/>  <b>Day\/Night: <\/b> Night<br\/> <b>Scan: <\/b> 0.34 km<br\/> <b>Track: <\/b> 0.56 km<br\/> <b>FRP: <\/b> 1.49 MW<br\/> <b>Brightness: <\/b> 310.86 K" }, "geometry": { "type": "Point", "coordinates": [ -123.16555, 45.23217, 0.0 ] } },
{ "type": "Feature", "properties": { "Name": "Fire Detection Centroid ", "Description": "<b>Latitude: <\/b> 49.09763<br\/>  <b>Longitude: <\/b> -123.01522<br\/>  <b>Detection Time: <\/b> 2023-05-03 11:02 UTC<br\/>  <b>Sensor: <\/b> NOAA-20 VIIRS<br\/> <b>Confidence: <\/b> Nominal<br\/>  <b>Day\/Night: <\/b> Night<br\/> <b>Scan: <\/b> 0.54 km<br\/> <b>Track: <\/b> 0.51 km<br\/> <b>FRP: <\/b> 0.7 MW<br\/> <b>Brightness: <\/b> 296.44 K" }, "geometry": { "type": "Point", "coordinates": [ -123.01522, 49.09763, 0.0 ] } },
{ "type": "Feature", "properties": { "Name": "Fire Detection Centroid ", "Description": "<b>Latitude: <\/b> 47.57236<br\/>  <b>Longitude: <\/b> -122.36562<br\/>  <b>Detection Time: <\/b> 2023-05-03 11:02 UTC<br\/>  <b>Sensor: <\/b> NOAA-20 VIIRS<br\/> <b>Confidence: <\/b> Nominal<br\/>  <b>Day\/Night: <\/b> Night<br\/> <b>Scan: <\/b> 0.64 km<br\/> <b>Track: <\/b> 0.54 km<br\/> <b>FRP: <\/b> 2.15 MW<br\/> <b>Brightness: <\/b> 306.07 K" }, "geometry": { "type": "Point", "coordinates": [ -122.36562, 47.57236, 0.0 ] } },
{ "type": "Feature", "properties": { "Name": "Fire Detection Centroid ", "Description": "<b>Latitude: <\/b> 47.57087<br\/>  <b>Longitude: <\/b> -122.34077<br\/>  <b>Detection Time: <\/b> 2023-05-03 11:02 UTC<br\/>  <b>Sensor: <\/b> NOAA-20 VIIRS<br\/> <b>Confidence: <\/b> Nominal<br\/>  <b>Day\/Night: <\/b> Night<br\/> <b>Scan: <\/b> 0.32 km<br\/> <b>Track: <\/b> 0.54 km<br\/> <b>FRP: <\/b> 0.44 MW<br\/> <b>Brightness: <\/b> 299.44 K" }, "geometry": { "type": "Point", "coordinates": [ -122.34077, 47.57087, 0.0 ] } }
]
}
