{
"type": "FeatureCollection",
"crs": { "type": "name", "properties": { "name": "urn:ogc:def:crs:OGC:1.3:CRS84" } },
"features": [
{ "type": "Feature", "properties": { "Name": "Fire Detection Centroid ", "Description": "<b>Latitude: <\/b> 17.70327<br\/>  <b>Longitude: <\/b> -64.74877<br\/>  <b>Detection Time: <\/b> 2023-11-17 05:54 UTC<br\/>  <b>Sensor: <\/b> NOAA-20 VIIRS<br\/> <b>Confidence: <\/b> Nominal<br\/>  <b>Day\/Night: <\/b> Night<br\/> <b>Scan: <\/b> 0.4 km<br\/> <b>Track: <\/b> 0.4 km<br\/> <b>FRP: <\/b> 1.8 MW<br\/> <b>Brightness: <\/b> 307 K" }, "geometry": { "type": "Point", "coordinates": [ -64.74877, 17.70327, 0.0 ] } },
{ "type": "Feature", "properties": { "Name": "Fire Detection Centroid ", "Description": "<b>Latitude: <\/b> 39.58781<br\/>  <b>Longitude: <\/b> -75.63837<br\/>  <b>Detection Time: <\/b> 2023-11-17 05:48 UTC<br\/>  <b>Sensor: <\/b> NOAA-20 VIIRS<br\/> <b>Confidence: <\/b> Nominal<br\/>  <b>Day\/Night: <\/b> Night<br\/> <b>Scan: <\/b> 0.7 km<br\/> <b>Track: <\/b> 0.8 km<br\/> <b>FRP: <\/b> 1.04 MW<br\/> <b>Brightness: <\/b> 295.52 K" }, "geometry": { "type": "Point", "coordinates": [ -75.63837, 39.58781, 0.0 ] } }
]
}
