{
"type": "FeatureCollection",
"crs": { "type": "name", "properties": { "name": "urn:ogc:def:crs:OGC:1.3:CRS84" } },
"features": [
{ "type": "Feature", "properties": { "Name": "Fire Detection Centroid ", "Description": "<b>Latitude: <\/b> 37.22662<br\/>  <b>Longitude: <\/b> -120.42942<br\/>  <b>Detection Time: <\/b> 2023-02-18 10:51 UTC<br\/>  <b>Sensor: <\/b> NOAA-20 VIIRS<br\/> <b>Confidence: <\/b> Nominal<br\/>  <b>Day\/Night: <\/b> Night<br\/> <b>Scan: <\/b> 0.55 km<br\/> <b>Track: <\/b> 0.68 km<br\/> <b>FRP: <\/b> 1.56 MW<br\/> <b>Brightness: <\/b> 305.64 K" }, "geometry": { "type": "Point", "coordinates": [ -120.42942, 37.22662, 0.0 ] } },
{ "type": "Feature", "properties": { "Name": "Fire Detection Centroid ", "Description": "<b>Latitude: <\/b> 37.22489<br\/>  <b>Longitude: <\/b> -120.42361<br\/>  <b>Detection Time: <\/b> 2023-02-18 10:51 UTC<br\/>  <b>Sensor: <\/b> NOAA-20 VIIRS<br\/> <b>Confidence: <\/b> Nominal<br\/>  <b>Day\/Night: <\/b> Night<br\/> <b>Scan: <\/b> 0.55 km<br\/> <b>Track: <\/b> 0.68 km<br\/> <b>FRP: <\/b> 1.56 MW<br\/> <b>Brightness: <\/b> 299.58 K" }, "geometry": { "type": "Point", "coordinates": [ -120.42361, 37.22489, 0.0 ] } },
{ "type": "Feature", "properties": { "Name": "Fire Detection Centroid ", "Description": "<b>Latitude: <\/b> 37.66088<br\/>  <b>Longitude: <\/b> -121.11741<br\/>  <b>Detection Time: <\/b> 2023-02-18 10:51 UTC<br\/>  <b>Sensor: <\/b> NOAA-20 VIIRS<br\/> <b>Confidence: <\/b> Nominal<br\/>  <b>Day\/Night: <\/b> Night<br\/> <b>Scan: <\/b> 0.49 km<br\/> <b>Track: <\/b> 0.65 km<br\/> <b>FRP: <\/b> 3.62 MW<br\/> <b>Brightness: <\/b> 337.2 K" }, "geometry": { "type": "Point", "coordinates": [ -121.11741, 37.66088, 0.0 ] } }
]
}
