{
"type": "FeatureCollection",
"crs": { "type": "name", "properties": { "name": "urn:ogc:def:crs:OGC:1.3:CRS84" } },
"features": [
{ "type": "Feature", "properties": { "Name": "Fire Detection Centroid ", "Description": "<b>Latitude: <\/b> 45.28187<br\/>  <b>Longitude: <\/b> -66.01483<br\/>  <b>Detection Time: <\/b> 2022-06-30 05:15 UTC<br\/>  <b>Sensor: <\/b> NOAA-20 VIIRS<br\/> <b>Confidence: <\/b> Nominal<br\/>  <b>Day\/Night: <\/b> Night<br\/> <b>Scan: <\/b> 0.6 km<br\/> <b>Track: <\/b> 0.7 km<br\/> <b>FRP: <\/b> 1.68 MW<br\/> <b>Brightness: <\/b> 300.48 K" }, "geometry": { "type": "Point", "coordinates": [ -66.01483, 45.28187, 0.0 ] } }
]
}
