{
"type": "FeatureCollection",
"crs": { "type": "name", "properties": { "name": "urn:ogc:def:crs:OGC:1.3:CRS84" } },
"features": [
{ "type": "Feature", "properties": { "Name": "Fire Detection Centroid ", "Description": "<b>Latitude: <\/b> 19.41323<br\/>  <b>Longitude: <\/b> -155.27853<br\/>  <b>Detection Time: <\/b> 2022-06-30 23:20 UTC<br\/>  <b>Sensor: <\/b> NOAA-20 VIIRS<br\/> <b>Confidence: <\/b> Low<br\/>  <b>Day\/Night: <\/b> Day<br\/> <b>Scan: <\/b> 0.48 km<br\/> <b>Track: <\/b> 0.4 km<br\/> <b>FRP: <\/b> 9.32 MW<br\/> <b>Brightness: <\/b> 342.24 K" }, "geometry": { "type": "Point", "coordinates": [ -155.27853, 19.41323, 0.0 ] } },
{ "type": "Feature", "properties": { "Name": "Fire Detection Centroid ", "Description": "<b>Latitude: <\/b> 19.40804<br\/>  <b>Longitude: <\/b> -155.28682<br\/>  <b>Detection Time: <\/b> 2022-06-30 23:20 UTC<br\/>  <b>Sensor: <\/b> NOAA-20 VIIRS<br\/> <b>Confidence: <\/b> Nominal<br\/>  <b>Day\/Night: <\/b> Day<br\/> <b>Scan: <\/b> 0.48 km<br\/> <b>Track: <\/b> 0.4 km<br\/> <b>FRP: <\/b> 62.18 MW<br\/> <b>Brightness: <\/b> 345.72 K" }, "geometry": { "type": "Point", "coordinates": [ -155.28682, 19.40804, 0.0 ] } },
{ "type": "Feature", "properties": { "Name": "Fire Detection Centroid ", "Description": "<b>Latitude: <\/b> 19.40882<br\/>  <b>Longitude: <\/b> -155.28233<br\/>  <b>Detection Time: <\/b> 2022-06-30 23:20 UTC<br\/>  <b>Sensor: <\/b> NOAA-20 VIIRS<br\/> <b>Confidence: <\/b> Nominal<br\/>  <b>Day\/Night: <\/b> Day<br\/> <b>Scan: <\/b> 0.48 km<br\/> <b>Track: <\/b> 0.4 km<br\/> <b>FRP: <\/b> 37.89 MW<br\/> <b>Brightness: <\/b> 351.7 K" }, "geometry": { "type": "Point", "coordinates": [ -155.28233, 19.40882, 0.0 ] } },
{ "type": "Feature", "properties": { "Name": "Fire Detection Centroid ", "Description": "<b>Latitude: <\/b> 19.40959<br\/>  <b>Longitude: <\/b> -155.27785<br\/>  <b>Detection Time: <\/b> 2022-06-30 23:20 UTC<br\/>  <b>Sensor: <\/b> NOAA-20 VIIRS<br\/> <b>Confidence: <\/b> Nominal<br\/>  <b>Day\/Night: <\/b> Day<br\/> <b>Scan: <\/b> 0.48 km<br\/> <b>Track: <\/b> 0.4 km<br\/> <b>FRP: <\/b> 37.89 MW<br\/> <b>Brightness: <\/b> 354.91 K" }, "geometry": { "type": "Point", "coordinates": [ -155.27785, 19.40959, 0.0 ] } },
{ "type": "Feature", "properties": { "Name": "Fire Detection Centroid ", "Description": "<b>Latitude: <\/b> 19.40517<br\/>  <b>Longitude: <\/b> -155.28168<br\/>  <b>Detection Time: <\/b> 2022-06-30 23:20 UTC<br\/>  <b>Sensor: <\/b> NOAA-20 VIIRS<br\/> <b>Confidence: <\/b> Low<br\/>  <b>Day\/Night: <\/b> Day<br\/> <b>Scan: <\/b> 0.48 km<br\/> <b>Track: <\/b> 0.4 km<br\/> <b>FRP: <\/b> 37.89 MW<br\/> <b>Brightness: <\/b> 367 K" }, "geometry": { "type": "Point", "coordinates": [ -155.28168, 19.40517, 0.0 ] } },
{ "type": "Feature", "properties": { "Name": "Fire Detection Centroid ", "Description": "<b>Latitude: <\/b> 19.40595<br\/>  <b>Longitude: <\/b> -155.27716<br\/>  <b>Detection Time: <\/b> 2022-06-30 23:20 UTC<br\/>  <b>Sensor: <\/b> NOAA-20 VIIRS<br\/> <b>Confidence: <\/b> Low<br\/>  <b>Day\/Night: <\/b> Day<br\/> <b>Scan: <\/b> 0.48 km<br\/> <b>Track: <\/b> 0.4 km<br\/> <b>FRP: <\/b> 37.89 MW<br\/> <b>Brightness: <\/b> 341.47 K" }, "geometry": { "type": "Point", "coordinates": [ -155.27716, 19.40595, 0.0 ] } },
{ "type": "Feature", "properties": { "Name": "Fire Detection Centroid ", "Description": "<b>Latitude: <\/b> 19.40439<br\/>  <b>Longitude: <\/b> -155.28619<br\/>  <b>Detection Time: <\/b> 2022-06-30 23:20 UTC<br\/>  <b>Sensor: <\/b> NOAA-20 VIIRS<br\/> <b>Confidence: <\/b> High<br\/>  <b>Day\/Night: <\/b> Day<br\/> <b>Scan: <\/b> 0.48 km<br\/> <b>Track: <\/b> 0.4 km<br\/> <b>FRP: <\/b> 62.18 MW<br\/> <b>Brightness: <\/b> 367 K" }, "geometry": { "type": "Point", "coordinates": [ -155.28619, 19.40439, 0.0 ] } }
]
}
