{
"type": "FeatureCollection",
"crs": { "type": "name", "properties": { "name": "urn:ogc:def:crs:OGC:1.3:CRS84" } },
"features": [
{ "type": "Feature", "properties": { "Name": "Fire Detection Centroid ", "Description": "<b>Latitude: <\/b> 19.4104<br\/>  <b>Longitude: <\/b> -155.28088<br\/>  <b>Detection Time: <\/b> 2022-08-05 00:03 UTC<br\/>  <b>Sensor: <\/b> NOAA-20 VIIRS<br\/> <b>Confidence: <\/b> Nominal<br\/>  <b>Day\/Night: <\/b> Day<br\/> <b>Scan: <\/b> 0.53 km<br\/> <b>Track: <\/b> 0.5 km<br\/> <b>FRP: <\/b> 9.41 MW<br\/> <b>Brightness: <\/b> 349.95 K" }, "geometry": { "type": "Point", "coordinates": [ -155.28088, 19.4104, 0.0 ] } },
{ "type": "Feature", "properties": { "Name": "Fire Detection Centroid ", "Description": "<b>Latitude: <\/b> 19.40982<br\/>  <b>Longitude: <\/b> -155.28603<br\/>  <b>Detection Time: <\/b> 2022-08-05 00:03 UTC<br\/>  <b>Sensor: <\/b> NOAA-20 VIIRS<br\/> <b>Confidence: <\/b> Nominal<br\/>  <b>Day\/Night: <\/b> Day<br\/> <b>Scan: <\/b> 0.53 km<br\/> <b>Track: <\/b> 0.5 km<br\/> <b>FRP: <\/b> 9.41 MW<br\/> <b>Brightness: <\/b> 335.2 K" }, "geometry": { "type": "Point", "coordinates": [ -155.28603, 19.40982, 0.0 ] } },
{ "type": "Feature", "properties": { "Name": "Fire Detection Centroid ", "Description": "<b>Latitude: <\/b> 19.40174<br\/>  <b>Longitude: <\/b> -155.27472<br\/>  <b>Detection Time: <\/b> 2022-08-05 00:03 UTC<br\/>  <b>Sensor: <\/b> NOAA-20 VIIRS<br\/> <b>Confidence: <\/b> Nominal<br\/>  <b>Day\/Night: <\/b> Day<br\/> <b>Scan: <\/b> 0.53 km<br\/> <b>Track: <\/b> 0.5 km<br\/> <b>FRP: <\/b> 12.69 MW<br\/> <b>Brightness: <\/b> 338.14 K" }, "geometry": { "type": "Point", "coordinates": [ -155.27472, 19.40174, 0.0 ] } },
{ "type": "Feature", "properties": { "Name": "Fire Detection Centroid ", "Description": "<b>Latitude: <\/b> 19.40118<br\/>  <b>Longitude: <\/b> -155.27975<br\/>  <b>Detection Time: <\/b> 2022-08-05 00:03 UTC<br\/>  <b>Sensor: <\/b> NOAA-20 VIIRS<br\/> <b>Confidence: <\/b> Nominal<br\/>  <b>Day\/Night: <\/b> Day<br\/> <b>Scan: <\/b> 0.53 km<br\/> <b>Track: <\/b> 0.5 km<br\/> <b>FRP: <\/b> 5.61 MW<br\/> <b>Brightness: <\/b> 340.25 K" }, "geometry": { "type": "Point", "coordinates": [ -155.27975, 19.40118, 0.0 ] } },
{ "type": "Feature", "properties": { "Name": "Fire Detection Centroid ", "Description": "<b>Latitude: <\/b> 19.40061<br\/>  <b>Longitude: <\/b> -155.28481<br\/>  <b>Detection Time: <\/b> 2022-08-05 00:03 UTC<br\/>  <b>Sensor: <\/b> NOAA-20 VIIRS<br\/> <b>Confidence: <\/b> Nominal<br\/>  <b>Day\/Night: <\/b> Day<br\/> <b>Scan: <\/b> 0.53 km<br\/> <b>Track: <\/b> 0.5 km<br\/> <b>FRP: <\/b> 5.61 MW<br\/> <b>Brightness: <\/b> 334.31 K" }, "geometry": { "type": "Point", "coordinates": [ -155.28481, 19.40061, 0.0 ] } },
{ "type": "Feature", "properties": { "Name": "Fire Detection Centroid ", "Description": "<b>Latitude: <\/b> 19.4058<br\/>  <b>Longitude: <\/b> -155.28024<br\/>  <b>Detection Time: <\/b> 2022-08-05 00:03 UTC<br\/>  <b>Sensor: <\/b> NOAA-20 VIIRS<br\/> <b>Confidence: <\/b> Nominal<br\/>  <b>Day\/Night: <\/b> Day<br\/> <b>Scan: <\/b> 0.53 km<br\/> <b>Track: <\/b> 0.5 km<br\/> <b>FRP: <\/b> 5.61 MW<br\/> <b>Brightness: <\/b> 343.2 K" }, "geometry": { "type": "Point", "coordinates": [ -155.28024, 19.4058, 0.0 ] } }
]
}
