{
"type": "FeatureCollection",
"crs": { "type": "name", "properties": { "name": "urn:ogc:def:crs:OGC:1.3:CRS84" } },
"features": [
{ "type": "Feature", "properties": { "Name": "Fire Detection Centroid ", "Description": "<b>Latitude: <\/b> 38.01762<br\/>  <b>Longitude: <\/b> -122.11378<br\/>  <b>Detection Time: <\/b> 2024-05-26 10:45 UTC<br\/>  <b>Sensor: <\/b> NOAA-20 VIIRS<br\/> <b>Confidence: <\/b> Nominal<br\/>  <b>Day\/Night: <\/b> Night<br\/> <b>Scan: <\/b> 0.37 km<br\/> <b>Track: <\/b> 0.58 km<br\/> <b>FRP: <\/b> 1.35 MW<br\/> <b>Brightness: <\/b> 297.67 K" }, "geometry": { "type": "Point", "coordinates": [ -122.11378, 38.01762, 0.0 ] } },
{ "type": "Feature", "properties": { "Name": "Fire Detection Centroid ", "Description": "<b>Latitude: <\/b> 37.45741<br\/>  <b>Longitude: <\/b> -121.93154<br\/>  <b>Detection Time: <\/b> 2024-05-26 10:45 UTC<br\/>  <b>Sensor: <\/b> NOAA-20 VIIRS<br\/> <b>Confidence: <\/b> Nominal<br\/>  <b>Day\/Night: <\/b> Night<br\/> <b>Scan: <\/b> 0.39 km<br\/> <b>Track: <\/b> 0.59 km<br\/> <b>FRP: <\/b> 0.53 MW<br\/> <b>Brightness: <\/b> 300.72 K" }, "geometry": { "type": "Point", "coordinates": [ -121.93154, 37.45741, 0.0 ] } },
{ "type": "Feature", "properties": { "Name": "Fire Detection Centroid ", "Description": "<b>Latitude: <\/b> 39.62148<br\/>  <b>Longitude: <\/b> -119.26342<br\/>  <b>Detection Time: <\/b> 2024-05-26 10:45 UTC<br\/>  <b>Sensor: <\/b> NOAA-20 VIIRS<br\/> <b>Confidence: <\/b> Nominal<br\/>  <b>Day\/Night: <\/b> Night<br\/> <b>Scan: <\/b> 0.46 km<br\/> <b>Track: <\/b> 0.64 km<br\/> <b>FRP: <\/b> 1.11 MW<br\/> <b>Brightness: <\/b> 299.64 K" }, "geometry": { "type": "Point", "coordinates": [ -119.26342, 39.62148, 0.0 ] } },
{ "type": "Feature", "properties": { "Name": "Fire Detection Centroid ", "Description": "<b>Latitude: <\/b> 38.07476<br\/>  <b>Longitude: <\/b> -122.13845<br\/>  <b>Detection Time: <\/b> 2024-05-26 10:45 UTC<br\/>  <b>Sensor: <\/b> NOAA-20 VIIRS<br\/> <b>Confidence: <\/b> Nominal<br\/>  <b>Day\/Night: <\/b> Night<br\/> <b>Scan: <\/b> 0.36 km<br\/> <b>Track: <\/b> 0.58 km<br\/> <b>FRP: <\/b> 1.4 MW<br\/> <b>Brightness: <\/b> 297.14 K" }, "geometry": { "type": "Point", "coordinates": [ -122.13845, 38.07476, 0.0 ] } },
{ "type": "Feature", "properties": { "Name": "Fire Detection Centroid ", "Description": "<b>Latitude: <\/b> 48.90182<br\/>  <b>Longitude: <\/b> -119.02914<br\/>  <b>Detection Time: <\/b> 2024-05-26 10:43 UTC<br\/>  <b>Sensor: <\/b> NOAA-20 VIIRS<br\/> <b>Confidence: <\/b> Nominal<br\/>  <b>Day\/Night: <\/b> Night<br\/> <b>Scan: <\/b> 0.52 km<br\/> <b>Track: <\/b> 0.5 km<br\/> <b>FRP: <\/b> 1.19 MW<br\/> <b>Brightness: <\/b> 303 K" }, "geometry": { "type": "Point", "coordinates": [ -119.02914, 48.90182, 0.0 ] } }
]
}
