{
"type": "FeatureCollection",
"crs": { "type": "name", "properties": { "name": "urn:ogc:def:crs:OGC:1.3:CRS84" } },
"features": [
{ "type": "Feature", "properties": { "Name": "Fire Detection Centroid ", "Description": "<b>Latitude: <\/b> 43.17537<br\/>  <b>Longitude: <\/b> -73.73648<br\/>  <b>Detection Time: <\/b> 2024-06-05 17:18 UTC<br\/>  <b>Sensor: <\/b> NOAA-20 VIIRS<br\/> <b>Confidence: <\/b> Nominal<br\/>  <b>Day\/Night: <\/b> Day<br\/> <b>Scan: <\/b> 0.4 km<br\/> <b>Track: <\/b> 0.4 km<br\/> <b>FRP: <\/b> 2.83 MW<br\/> <b>Brightness: <\/b> 328.06 K" }, "geometry": { "type": "Point", "coordinates": [ -73.73648, 43.17537, 0.0 ] } },
{ "type": "Feature", "properties": { "Name": "Fire Detection Centroid ", "Description": "<b>Latitude: <\/b> 45.40295<br\/>  <b>Longitude: <\/b> -69.58078<br\/>  <b>Detection Time: <\/b> 2024-06-05 17:18 UTC<br\/>  <b>Sensor: <\/b> NOAA-20 VIIRS<br\/> <b>Confidence: <\/b> Nominal<br\/>  <b>Day\/Night: <\/b> Day<br\/> <b>Scan: <\/b> 0.4 km<br\/> <b>Track: <\/b> 0.4 km<br\/> <b>FRP: <\/b> 2.38 MW<br\/> <b>Brightness: <\/b> 333.22 K" }, "geometry": { "type": "Point", "coordinates": [ -69.58078, 45.40295, 0.0 ] } },
{ "type": "Feature", "properties": { "Name": "Fire Detection Centroid ", "Description": "<b>Latitude: <\/b> 35.41457<br\/>  <b>Longitude: <\/b> -77.42844<br\/>  <b>Detection Time: <\/b> 2024-06-05 17:16 UTC<br\/>  <b>Sensor: <\/b> NOAA-20 VIIRS<br\/> <b>Confidence: <\/b> Nominal<br\/>  <b>Day\/Night: <\/b> Day<br\/> <b>Scan: <\/b> 0.5 km<br\/> <b>Track: <\/b> 0.6 km<br\/> <b>FRP: <\/b> 3.3 MW<br\/> <b>Brightness: <\/b> 331.95 K" }, "geometry": { "type": "Point", "coordinates": [ -77.42844, 35.41457, 0.0 ] } },
{ "type": "Feature", "properties": { "Name": "Fire Detection Centroid ", "Description": "<b>Latitude: <\/b> 34.28643<br\/>  <b>Longitude: <\/b> -78.01295<br\/>  <b>Detection Time: <\/b> 2024-06-05 17:16 UTC<br\/>  <b>Sensor: <\/b> NOAA-20 VIIRS<br\/> <b>Confidence: <\/b> Nominal<br\/>  <b>Day\/Night: <\/b> Day<br\/> <b>Scan: <\/b> 0.6 km<br\/> <b>Track: <\/b> 0.7 km<br\/> <b>FRP: <\/b> 3.11 MW<br\/> <b>Brightness: <\/b> 327.66 K" }, "geometry": { "type": "Point", "coordinates": [ -78.01295, 34.28643, 0.0 ] } },
{ "type": "Feature", "properties": { "Name": "Fire Detection Centroid ", "Description": "<b>Latitude: <\/b> 34.28419<br\/>  <b>Longitude: <\/b> -78.01559<br\/>  <b>Detection Time: <\/b> 2024-06-05 17:16 UTC<br\/>  <b>Sensor: <\/b> NOAA-20 VIIRS<br\/> <b>Confidence: <\/b> Nominal<br\/>  <b>Day\/Night: <\/b> Day<br\/> <b>Scan: <\/b> 0.6 km<br\/> <b>Track: <\/b> 0.7 km<br\/> <b>FRP: <\/b> 5.94 MW<br\/> <b>Brightness: <\/b> 337.75 K" }, "geometry": { "type": "Point", "coordinates": [ -78.01559, 34.28419, 0.0 ] } },
{ "type": "Feature", "properties": { "Name": "Fire Detection Centroid ", "Description": "<b>Latitude: <\/b> 35.27003<br\/>  <b>Longitude: <\/b> -77.3628<br\/>  <b>Detection Time: <\/b> 2024-06-05 17:16 UTC<br\/>  <b>Sensor: <\/b> NOAA-20 VIIRS<br\/> <b>Confidence: <\/b> Nominal<br\/>  <b>Day\/Night: <\/b> Day<br\/> <b>Scan: <\/b> 0.5 km<br\/> <b>Track: <\/b> 0.6 km<br\/> <b>FRP: <\/b> 5.11 MW<br\/> <b>Brightness: <\/b> 339.25 K" }, "geometry": { "type": "Point", "coordinates": [ -77.3628, 35.27003, 0.0 ] } },
{ "type": "Feature", "properties": { "Name": "Fire Detection Centroid ", "Description": "<b>Latitude: <\/b> 18.61486<br\/>  <b>Longitude: <\/b> -69.0585<br\/>  <b>Detection Time: <\/b> 2024-06-05 17:11 UTC<br\/>  <b>Sensor: <\/b> NOAA-20 VIIRS<br\/> <b>Confidence: <\/b> Nominal<br\/>  <b>Day\/Night: <\/b> Day<br\/> <b>Scan: <\/b> 0.4 km<br\/> <b>Track: <\/b> 0.6 km<br\/> <b>FRP: <\/b> 4.21 MW<br\/> <b>Brightness: <\/b> 331.95 K" }, "geometry": { "type": "Point", "coordinates": [ -69.0585, 18.61486, 0.0 ] } },
{ "type": "Feature", "properties": { "Name": "Fire Detection Centroid ", "Description": "<b>Latitude: <\/b> 19.37002<br\/>  <b>Longitude: <\/b> -155.31354<br\/>  <b>Detection Time: <\/b> 2024-06-05 12:46 UTC<br\/>  <b>Sensor: <\/b> NOAA-20 VIIRS<br\/> <b>Confidence: <\/b> Nominal<br\/>  <b>Day\/Night: <\/b> Night<br\/> <b>Scan: <\/b> 0.53 km<br\/> <b>Track: <\/b> 0.67 km<br\/> <b>FRP: <\/b> 4.05 MW<br\/> <b>Brightness: <\/b> 308.52 K" }, "geometry": { "type": "Point", "coordinates": [ -155.31354, 19.37002, 0.0 ] } },
{ "type": "Feature", "properties": { "Name": "Fire Detection Centroid ", "Description": "<b>Latitude: <\/b> 19.36891<br\/>  <b>Longitude: <\/b> -155.30869<br\/>  <b>Detection Time: <\/b> 2024-06-05 12:46 UTC<br\/>  <b>Sensor: <\/b> NOAA-20 VIIRS<br\/> <b>Confidence: <\/b> Nominal<br\/>  <b>Day\/Night: <\/b> Night<br\/> <b>Scan: <\/b> 0.53 km<br\/> <b>Track: <\/b> 0.67 km<br\/> <b>FRP: <\/b> 4.05 MW<br\/> <b>Brightness: <\/b> 323.31 K" }, "geometry": { "type": "Point", "coordinates": [ -155.30869, 19.36891, 0.0 ] } }
]
}
