{
"type": "FeatureCollection",
"crs": { "type": "name", "properties": { "name": "urn:ogc:def:crs:OGC:1.3:CRS84" } },
"features": [
{ "type": "Feature", "properties": { "Name": "Fire Detection Centroid ", "Description": "<b>Latitude: <\/b> 21.69995<br\/>  <b>Longitude: <\/b> -77.53341<br\/>  <b>Detection Time: <\/b> 2022-11-07 17:37 UTC<br\/>  <b>Sensor: <\/b> NOAA-20 VIIRS<br\/> <b>Confidence: <\/b> Nominal<br\/>  <b>Day\/Night: <\/b> Day<br\/> <b>Scan: <\/b> 0.4 km<br\/> <b>Track: <\/b> 0.6 km<br\/> <b>FRP: <\/b> 5 MW<br\/> <b>Brightness: <\/b> 335.68 K" }, "geometry": { "type": "Point", "coordinates": [ -77.53341, 21.69995, 0.0 ] } },
{ "type": "Feature", "properties": { "Name": "Fire Detection Centroid ", "Description": "<b>Latitude: <\/b> 21.69725<br\/>  <b>Longitude: <\/b> -77.53082<br\/>  <b>Detection Time: <\/b> 2022-11-07 17:37 UTC<br\/>  <b>Sensor: <\/b> NOAA-20 VIIRS<br\/> <b>Confidence: <\/b> Nominal<br\/>  <b>Day\/Night: <\/b> Day<br\/> <b>Scan: <\/b> 0.4 km<br\/> <b>Track: <\/b> 0.6 km<br\/> <b>FRP: <\/b> 3.8 MW<br\/> <b>Brightness: <\/b> 336.38 K" }, "geometry": { "type": "Point", "coordinates": [ -77.53082, 21.69725, 0.0 ] } },
{ "type": "Feature", "properties": { "Name": "Fire Detection Centroid ", "Description": "<b>Latitude: <\/b> 18.63689<br\/>  <b>Longitude: <\/b> -70.39803<br\/>  <b>Detection Time: <\/b> 2022-11-07 17:36 UTC<br\/>  <b>Sensor: <\/b> NOAA-20 VIIRS<br\/> <b>Confidence: <\/b> Nominal<br\/>  <b>Day\/Night: <\/b> Day<br\/> <b>Scan: <\/b> 0.5 km<br\/> <b>Track: <\/b> 0.4 km<br\/> <b>FRP: <\/b> 4.41 MW<br\/> <b>Brightness: <\/b> 329.73 K" }, "geometry": { "type": "Point", "coordinates": [ -70.39803, 18.63689, 0.0 ] } },
{ "type": "Feature", "properties": { "Name": "Fire Detection Centroid ", "Description": "<b>Latitude: <\/b> 18.63423<br\/>  <b>Longitude: <\/b> -70.40107<br\/>  <b>Detection Time: <\/b> 2022-11-07 17:36 UTC<br\/>  <b>Sensor: <\/b> NOAA-20 VIIRS<br\/> <b>Confidence: <\/b> Nominal<br\/>  <b>Day\/Night: <\/b> Day<br\/> <b>Scan: <\/b> 0.5 km<br\/> <b>Track: <\/b> 0.4 km<br\/> <b>FRP: <\/b> 4.37 MW<br\/> <b>Brightness: <\/b> 328.37 K" }, "geometry": { "type": "Point", "coordinates": [ -70.40107, 18.63423, 0.0 ] } },
{ "type": "Feature", "properties": { "Name": "Fire Detection Centroid ", "Description": "<b>Latitude: <\/b> 18.92438<br\/>  <b>Longitude: <\/b> -70.35315<br\/>  <b>Detection Time: <\/b> 2022-11-07 17:36 UTC<br\/>  <b>Sensor: <\/b> NOAA-20 VIIRS<br\/> <b>Confidence: <\/b> Nominal<br\/>  <b>Day\/Night: <\/b> Day<br\/> <b>Scan: <\/b> 0.5 km<br\/> <b>Track: <\/b> 0.4 km<br\/> <b>FRP: <\/b> 29.96 MW<br\/> <b>Brightness: <\/b> 332.77 K" }, "geometry": { "type": "Point", "coordinates": [ -70.35315, 18.92438, 0.0 ] } }
]
}
