{
"type": "FeatureCollection",
"crs": { "type": "name", "properties": { "name": "urn:ogc:def:crs:OGC:1.3:CRS84" } },
"features": [
{ "type": "Feature", "properties": { "Name": "Fire Detection Centroid ", "Description": "<b>Latitude: <\/b> 19.40643<br\/>  <b>Longitude: <\/b> -155.27853<br\/>  <b>Detection Time: <\/b> 2023-04-04 11:55 UTC<br\/>  <b>Sensor: <\/b> NOAA-20 VIIRS<br\/> <b>Confidence: <\/b> Nominal<br\/>  <b>Day\/Night: <\/b> Night<br\/> <b>Scan: <\/b> 0.39 km<br\/> <b>Track: <\/b> 0.36 km<br\/> <b>FRP: <\/b> 1.16 MW<br\/> <b>Brightness: <\/b> 299.5 K" }, "geometry": { "type": "Point", "coordinates": [ -155.27853, 19.40643, 0.0 ] } },
{ "type": "Feature", "properties": { "Name": "Fire Detection Centroid ", "Description": "<b>Latitude: <\/b> 20.86298<br\/>  <b>Longitude: <\/b> -156.42235<br\/>  <b>Detection Time: <\/b> 2023-04-04 11:55 UTC<br\/>  <b>Sensor: <\/b> NOAA-20 VIIRS<br\/> <b>Confidence: <\/b> Nominal<br\/>  <b>Day\/Night: <\/b> Night<br\/> <b>Scan: <\/b> 0.42 km<br\/> <b>Track: <\/b> 0.38 km<br\/> <b>FRP: <\/b> 0.91 MW<br\/> <b>Brightness: <\/b> 301.46 K" }, "geometry": { "type": "Point", "coordinates": [ -156.42235, 20.86298, 0.0 ] } },
{ "type": "Feature", "properties": { "Name": "Fire Detection Centroid ", "Description": "<b>Latitude: <\/b> 19.60395<br\/>  <b>Longitude: <\/b> -155.50377<br\/>  <b>Detection Time: <\/b> 2023-04-04 11:55 UTC<br\/>  <b>Sensor: <\/b> NOAA-20 VIIRS<br\/> <b>Confidence: <\/b> Nominal<br\/>  <b>Day\/Night: <\/b> Night<br\/> <b>Scan: <\/b> 0.39 km<br\/> <b>Track: <\/b> 0.36 km<br\/> <b>FRP: <\/b> 1.28 MW<br\/> <b>Brightness: <\/b> 295.15 K" }, "geometry": { "type": "Point", "coordinates": [ -155.50377, 19.60395, 0.0 ] } },
{ "type": "Feature", "properties": { "Name": "Fire Detection Centroid ", "Description": "<b>Latitude: <\/b> 19.59732<br\/>  <b>Longitude: <\/b> -155.50478<br\/>  <b>Detection Time: <\/b> 2023-04-04 11:55 UTC<br\/>  <b>Sensor: <\/b> NOAA-20 VIIRS<br\/> <b>Confidence: <\/b> Nominal<br\/>  <b>Day\/Night: <\/b> Night<br\/> <b>Scan: <\/b> 0.39 km<br\/> <b>Track: <\/b> 0.36 km<br\/> <b>FRP: <\/b> 1.37 MW<br\/> <b>Brightness: <\/b> 298.58 K" }, "geometry": { "type": "Point", "coordinates": [ -155.50478, 19.59732, 0.0 ] } }
]
}
