{
"type": "FeatureCollection",
"crs": { "type": "name", "properties": { "name": "urn:ogc:def:crs:OGC:1.3:CRS84" } },
"features": [
{ "type": "Feature", "properties": { "Name": "Fire Detection Centroid ", "Description": "<b>Latitude: <\/b> 48.11224<br\/>  <b>Longitude: <\/b> -122.32584<br\/>  <b>Detection Time: <\/b> 2023-03-29 21:46 UTC<br\/>  <b>Sensor: <\/b> NOAA-20 VIIRS<br\/> <b>Confidence: <\/b> Nominal<br\/>  <b>Day\/Night: <\/b> Day<br\/> <b>Scan: <\/b> 0.34 km<br\/> <b>Track: <\/b> 0.56 km<br\/> <b>FRP: <\/b> 4.12 MW<br\/> <b>Brightness: <\/b> 329.81 K" }, "geometry": { "type": "Point", "coordinates": [ -122.32584, 48.11224, 0.0 ] } },
{ "type": "Feature", "properties": { "Name": "Fire Detection Centroid ", "Description": "<b>Latitude: <\/b> 48.11358<br\/>  <b>Longitude: <\/b> -122.32969<br\/>  <b>Detection Time: <\/b> 2023-03-29 21:46 UTC<br\/>  <b>Sensor: <\/b> NOAA-20 VIIRS<br\/> <b>Confidence: <\/b> Nominal<br\/>  <b>Day\/Night: <\/b> Day<br\/> <b>Scan: <\/b> 0.34 km<br\/> <b>Track: <\/b> 0.56 km<br\/> <b>FRP: <\/b> 3.63 MW<br\/> <b>Brightness: <\/b> 339.54 K" }, "geometry": { "type": "Point", "coordinates": [ -122.32969, 48.11358, 0.0 ] } },
{ "type": "Feature", "properties": { "Name": "Fire Detection Centroid ", "Description": "<b>Latitude: <\/b> 45.64052<br\/>  <b>Longitude: <\/b> -121.14041<br\/>  <b>Detection Time: <\/b> 2023-03-29 21:44 UTC<br\/>  <b>Sensor: <\/b> NOAA-20 VIIRS<br\/> <b>Confidence: <\/b> Nominal<br\/>  <b>Day\/Night: <\/b> Day<br\/> <b>Scan: <\/b> 0.37 km<br\/> <b>Track: <\/b> 0.58 km<br\/> <b>FRP: <\/b> 4.62 MW<br\/> <b>Brightness: <\/b> 347.9 K" }, "geometry": { "type": "Point", "coordinates": [ -121.14041, 45.64052, 0.0 ] } },
{ "type": "Feature", "properties": { "Name": "Fire Detection Centroid ", "Description": "<b>Latitude: <\/b> 45.22682<br\/>  <b>Longitude: <\/b> -123.16164<br\/>  <b>Detection Time: <\/b> 2023-03-29 21:44 UTC<br\/>  <b>Sensor: <\/b> NOAA-20 VIIRS<br\/> <b>Confidence: <\/b> Nominal<br\/>  <b>Day\/Night: <\/b> Day<br\/> <b>Scan: <\/b> 0.58 km<br\/> <b>Track: <\/b> 0.52 km<br\/> <b>FRP: <\/b> 3.05 MW<br\/> <b>Brightness: <\/b> 326.84 K" }, "geometry": { "type": "Point", "coordinates": [ -123.16164, 45.22682, 0.0 ] } },
{ "type": "Feature", "properties": { "Name": "Fire Detection Centroid ", "Description": "<b>Latitude: <\/b> 45.22784<br\/>  <b>Longitude: <\/b> -123.16211<br\/>  <b>Detection Time: <\/b> 2023-03-29 21:44 UTC<br\/>  <b>Sensor: <\/b> NOAA-20 VIIRS<br\/> <b>Confidence: <\/b> Nominal<br\/>  <b>Day\/Night: <\/b> Day<br\/> <b>Scan: <\/b> 0.58 km<br\/> <b>Track: <\/b> 0.52 km<br\/> <b>FRP: <\/b> 3.86 MW<br\/> <b>Brightness: <\/b> 325.7 K" }, "geometry": { "type": "Point", "coordinates": [ -123.16211, 45.22784, 0.0 ] } },
{ "type": "Feature", "properties": { "Name": "Fire Detection Centroid ", "Description": "<b>Latitude: <\/b> 34.74325<br\/>  <b>Longitude: <\/b> -117.9566<br\/>  <b>Detection Time: <\/b> 2023-03-29 21:42 UTC<br\/>  <b>Sensor: <\/b> NOAA-20 VIIRS<br\/> <b>Confidence: <\/b> Nominal<br\/>  <b>Day\/Night: <\/b> Day<br\/> <b>Scan: <\/b> 0.44 km<br\/> <b>Track: <\/b> 0.63 km<br\/> <b>FRP: <\/b> 7.58 MW<br\/> <b>Brightness: <\/b> 356.24 K" }, "geometry": { "type": "Point", "coordinates": [ -117.9566, 34.74325, 0.0 ] } },
{ "type": "Feature", "properties": { "Name": "Fire Detection Centroid ", "Description": "<b>Latitude: <\/b> 34.74352<br\/>  <b>Longitude: <\/b> -117.95173<br\/>  <b>Detection Time: <\/b> 2023-03-29 21:42 UTC<br\/>  <b>Sensor: <\/b> NOAA-20 VIIRS<br\/> <b>Confidence: <\/b> Nominal<br\/>  <b>Day\/Night: <\/b> Day<br\/> <b>Scan: <\/b> 0.44 km<br\/> <b>Track: <\/b> 0.63 km<br\/> <b>FRP: <\/b> 7.58 MW<br\/> <b>Brightness: <\/b> 333.72 K" }, "geometry": { "type": "Point", "coordinates": [ -117.95173, 34.74352, 0.0 ] } }
]
}
