{
"type": "FeatureCollection",
"crs": { "type": "name", "properties": { "name": "urn:ogc:def:crs:OGC:1.3:CRS84" } },
"features": [
{ "type": "Feature", "properties": { "Name": "Fire Detection Centroid ", "Description": "<b>Latitude: <\/b> 18.48738<br\/>  <b>Longitude: <\/b> -69.2367<br\/>  <b>Detection Time: <\/b> 2023-02-20 05:16 UTC<br\/>  <b>Sensor: <\/b> NOAA-20 VIIRS<br\/> <b>Confidence: <\/b> Nominal<br\/>  <b>Day\/Night: <\/b> Night<br\/> <b>Scan: <\/b> 0.8 km<br\/> <b>Track: <\/b> 0.8 km<br\/> <b>FRP: <\/b> 1.93 MW<br\/> <b>Brightness: <\/b> 300.46 K" }, "geometry": { "type": "Point", "coordinates": [ -69.2367, 18.48738, 0.0 ] } },
{ "type": "Feature", "properties": { "Name": "Fire Detection Centroid ", "Description": "<b>Latitude: <\/b> 21.37312<br\/>  <b>Longitude: <\/b> -158.06104<br\/>  <b>Detection Time: <\/b> 2023-02-19 23:33 UTC<br\/>  <b>Sensor: <\/b> NOAA-20 VIIRS<br\/> <b>Confidence: <\/b> Nominal<br\/>  <b>Day\/Night: <\/b> Day<br\/> <b>Scan: <\/b> 0.44 km<br\/> <b>Track: <\/b> 0.39 km<br\/> <b>FRP: <\/b> 4.55 MW<br\/> <b>Brightness: <\/b> 338.83 K" }, "geometry": { "type": "Point", "coordinates": [ -158.06104, 21.37312, 0.0 ] } },
{ "type": "Feature", "properties": { "Name": "Fire Detection Centroid ", "Description": "<b>Latitude: <\/b> 21.37399<br\/>  <b>Longitude: <\/b> -158.05994<br\/>  <b>Detection Time: <\/b> 2023-02-19 23:33 UTC<br\/>  <b>Sensor: <\/b> NOAA-20 VIIRS<br\/> <b>Confidence: <\/b> Nominal<br\/>  <b>Day\/Night: <\/b> Day<br\/> <b>Scan: <\/b> 0.44 km<br\/> <b>Track: <\/b> 0.39 km<br\/> <b>FRP: <\/b> 5.11 MW<br\/> <b>Brightness: <\/b> 335.32 K" }, "geometry": { "type": "Point", "coordinates": [ -158.05994, 21.37399, 0.0 ] } },
{ "type": "Feature", "properties": { "Name": "Fire Detection Centroid ", "Description": "<b>Latitude: <\/b> 21.37369<br\/>  <b>Longitude: <\/b> -158.06012<br\/>  <b>Detection Time: <\/b> 2023-02-19 23:32 UTC<br\/>  <b>Sensor: <\/b> NOAA-20 VIIRS<br\/> <b>Confidence: <\/b> Nominal<br\/>  <b>Day\/Night: <\/b> Day<br\/> <b>Scan: <\/b> 0.4 km<br\/> <b>Track: <\/b> 0.4 km<br\/> <b>FRP: <\/b> 5.11 MW<br\/> <b>Brightness: <\/b> 335.32 K" }, "geometry": { "type": "Point", "coordinates": [ -158.06012, 21.37369, 0.0 ] } },
{ "type": "Feature", "properties": { "Name": "Fire Detection Centroid ", "Description": "<b>Latitude: <\/b> 21.37282<br\/>  <b>Longitude: <\/b> -158.0612<br\/>  <b>Detection Time: <\/b> 2023-02-19 23:32 UTC<br\/>  <b>Sensor: <\/b> NOAA-20 VIIRS<br\/> <b>Confidence: <\/b> Nominal<br\/>  <b>Day\/Night: <\/b> Day<br\/> <b>Scan: <\/b> 0.4 km<br\/> <b>Track: <\/b> 0.4 km<br\/> <b>FRP: <\/b> 4.54 MW<br\/> <b>Brightness: <\/b> 338.83 K" }, "geometry": { "type": "Point", "coordinates": [ -158.0612, 21.37282, 0.0 ] } }
]
}
