{
"type": "FeatureCollection",
"crs": { "type": "name", "properties": { "name": "urn:ogc:def:crs:OGC:1.3:CRS84" } },
"features": [
{ "type": "Feature", "properties": { "Name": "Fire Detection Centroid ", "Description": "<b>Latitude: <\/b> 18.78334<br\/>  <b>Longitude: <\/b> -69.91838<br\/>  <b>Detection Time: <\/b> 2023-03-18 05:29 UTC<br\/>  <b>Sensor: <\/b> NOAA-20 VIIRS<br\/> <b>Confidence: <\/b> Nominal<br\/>  <b>Day\/Night: <\/b> Night<br\/> <b>Scan: <\/b> 0.5 km<br\/> <b>Track: <\/b> 0.7 km<br\/> <b>FRP: <\/b> 0.77 MW<br\/> <b>Brightness: <\/b> 299.44 K" }, "geometry": { "type": "Point", "coordinates": [ -69.91838, 18.78334, 0.0 ] } },
{ "type": "Feature", "properties": { "Name": "Fire Detection Centroid ", "Description": "<b>Latitude: <\/b> 18.39393<br\/>  <b>Longitude: <\/b> -71.86839<br\/>  <b>Detection Time: <\/b> 2023-03-18 05:29 UTC<br\/>  <b>Sensor: <\/b> NOAA-20 VIIRS<br\/> <b>Confidence: <\/b> Nominal<br\/>  <b>Day\/Night: <\/b> Night<br\/> <b>Scan: <\/b> 0.7 km<br\/> <b>Track: <\/b> 0.8 km<br\/> <b>FRP: <\/b> 0.87 MW<br\/> <b>Brightness: <\/b> 296.3 K" }, "geometry": { "type": "Point", "coordinates": [ -71.86839, 18.39393, 0.0 ] } },
{ "type": "Feature", "properties": { "Name": "Fire Detection Centroid ", "Description": "<b>Latitude: <\/b> 18.4054<br\/>  <b>Longitude: <\/b> -71.27408<br\/>  <b>Detection Time: <\/b> 2023-03-18 05:29 UTC<br\/>  <b>Sensor: <\/b> NOAA-20 VIIRS<br\/> <b>Confidence: <\/b> Nominal<br\/>  <b>Day\/Night: <\/b> Night<br\/> <b>Scan: <\/b> 0.6 km<br\/> <b>Track: <\/b> 0.7 km<br\/> <b>FRP: <\/b> 1.31 MW<br\/> <b>Brightness: <\/b> 303.62 K" }, "geometry": { "type": "Point", "coordinates": [ -71.27408, 18.4054, 0.0 ] } },
{ "type": "Feature", "properties": { "Name": "Fire Detection Centroid ", "Description": "<b>Latitude: <\/b> 18.76299<br\/>  <b>Longitude: <\/b> -69.00281<br\/>  <b>Detection Time: <\/b> 2023-03-18 05:29 UTC<br\/>  <b>Sensor: <\/b> NOAA-20 VIIRS<br\/> <b>Confidence: <\/b> Nominal<br\/>  <b>Day\/Night: <\/b> Night<br\/> <b>Scan: <\/b> 0.5 km<br\/> <b>Track: <\/b> 0.6 km<br\/> <b>FRP: <\/b> 0.82 MW<br\/> <b>Brightness: <\/b> 299.84 K" }, "geometry": { "type": "Point", "coordinates": [ -69.00281, 18.76299, 0.0 ] } },
{ "type": "Feature", "properties": { "Name": "Fire Detection Centroid ", "Description": "<b>Latitude: <\/b> 18.76134<br\/>  <b>Longitude: <\/b> -68.99986<br\/>  <b>Detection Time: <\/b> 2023-03-18 05:29 UTC<br\/>  <b>Sensor: <\/b> NOAA-20 VIIRS<br\/> <b>Confidence: <\/b> Nominal<br\/>  <b>Day\/Night: <\/b> Night<br\/> <b>Scan: <\/b> 0.5 km<br\/> <b>Track: <\/b> 0.6 km<br\/> <b>FRP: <\/b> 0.91 MW<br\/> <b>Brightness: <\/b> 302.8 K" }, "geometry": { "type": "Point", "coordinates": [ -68.99986, 18.76134, 0.0 ] } }
]
}
