{
"type": "FeatureCollection",
"crs": { "type": "name", "properties": { "name": "urn:ogc:def:crs:OGC:1.3:CRS84" } },
"features": [
{ "type": "Feature", "properties": { "Name": "Fire Detection Centroid ", "Description": "<b>Latitude: <\/b> 19.02627<br\/>  <b>Longitude: <\/b> -72.2951<br\/>  <b>Detection Time: <\/b> 2024-01-15 05:48 UTC<br\/>  <b>Sensor: <\/b> NOAA-20 VIIRS<br\/> <b>Confidence: <\/b> Nominal<br\/>  <b>Day\/Night: <\/b> Night<br\/> <b>Scan: <\/b> 0.38 km<br\/> <b>Track: <\/b> 0.58 km<br\/> <b>FRP: <\/b> 1.62 MW<br\/> <b>Brightness: <\/b> 317.76 K" }, "geometry": { "type": "Point", "coordinates": [ -72.2951, 19.02627, 0.0 ] } },
{ "type": "Feature", "properties": { "Name": "Fire Detection Centroid ", "Description": "<b>Latitude: <\/b> 20.76005<br\/>  <b>Longitude: <\/b> -76.38672<br\/>  <b>Detection Time: <\/b> 2024-01-15 05:48 UTC<br\/>  <b>Sensor: <\/b> NOAA-20 VIIRS<br\/> <b>Confidence: <\/b> Nominal<br\/>  <b>Day\/Night: <\/b> Night<br\/> <b>Scan: <\/b> 0.73 km<br\/> <b>Track: <\/b> 0.76 km<br\/> <b>FRP: <\/b> 1.18 MW<br\/> <b>Brightness: <\/b> 304.68 K" }, "geometry": { "type": "Point", "coordinates": [ -76.38672, 20.76005, 0.0 ] } },
{ "type": "Feature", "properties": { "Name": "Fire Detection Centroid ", "Description": "<b>Latitude: <\/b> 20.00976<br\/>  <b>Longitude: <\/b> -76.6847<br\/>  <b>Detection Time: <\/b> 2024-01-15 05:48 UTC<br\/>  <b>Sensor: <\/b> NOAA-20 VIIRS<br\/> <b>Confidence: <\/b> Nominal<br\/>  <b>Day\/Night: <\/b> Night<br\/> <b>Scan: <\/b> 0.75 km<br\/> <b>Track: <\/b> 0.77 km<br\/> <b>FRP: <\/b> 2.47 MW<br\/> <b>Brightness: <\/b> 311.55 K" }, "geometry": { "type": "Point", "coordinates": [ -76.6847, 20.00976, 0.0 ] } },
{ "type": "Feature", "properties": { "Name": "Fire Detection Centroid ", "Description": "<b>Latitude: <\/b> 20.01255<br\/>  <b>Longitude: <\/b> -76.68278<br\/>  <b>Detection Time: <\/b> 2024-01-15 05:48 UTC<br\/>  <b>Sensor: <\/b> NOAA-20 VIIRS<br\/> <b>Confidence: <\/b> Nominal<br\/>  <b>Day\/Night: <\/b> Night<br\/> <b>Scan: <\/b> 0.75 km<br\/> <b>Track: <\/b> 0.77 km<br\/> <b>FRP: <\/b> 2.5 MW<br\/> <b>Brightness: <\/b> 308.28 K" }, "geometry": { "type": "Point", "coordinates": [ -76.68278, 20.01255, 0.0 ] } }
]
}
