{
"type": "FeatureCollection",
"crs": { "type": "name", "properties": { "name": "urn:ogc:def:crs:OGC:1.3:CRS84" } },
"features": [
{ "type": "Feature", "properties": { "Name": "Fire Detection Centroid ", "Description": "<b>Latitude: <\/b> 45.227<br\/>  <b>Longitude: <\/b> -123.1645<br\/>  <b>Detection Time: <\/b> 2024-03-07 11:10 UTC<br\/>  <b>Sensor: <\/b> NOAA-20 VIIRS<br\/> <b>Confidence: <\/b> Nominal<br\/>  <b>Day\/Night: <\/b> Night<br\/> <b>Scan: <\/b> 0.4 km<br\/> <b>Track: <\/b> 0.6 km<br\/> <b>FRP: <\/b> 2.12 MW<br\/> <b>Brightness: <\/b> 296.25 K" }, "geometry": { "type": "Point", "coordinates": [ -123.1645, 45.227, 0.0 ] } },
{ "type": "Feature", "properties": { "Name": "Fire Detection Centroid ", "Description": "<b>Latitude: <\/b> 45.22842<br\/>  <b>Longitude: <\/b> -123.1693<br\/>  <b>Detection Time: <\/b> 2024-03-07 11:10 UTC<br\/>  <b>Sensor: <\/b> NOAA-20 VIIRS<br\/> <b>Confidence: <\/b> Nominal<br\/>  <b>Day\/Night: <\/b> Night<br\/> <b>Scan: <\/b> 0.4 km<br\/> <b>Track: <\/b> 0.6 km<br\/> <b>FRP: <\/b> 2.57 MW<br\/> <b>Brightness: <\/b> 320.82 K" }, "geometry": { "type": "Point", "coordinates": [ -123.1693, 45.22842, 0.0 ] } },
{ "type": "Feature", "properties": { "Name": "Fire Detection Centroid ", "Description": "<b>Latitude: <\/b> 45.24444<br\/>  <b>Longitude: <\/b> -123.15886<br\/>  <b>Detection Time: <\/b> 2024-03-07 11:09 UTC<br\/>  <b>Sensor: <\/b> NOAA-20 VIIRS<br\/> <b>Confidence: <\/b> Nominal<br\/>  <b>Day\/Night: <\/b> Night<br\/> <b>Scan: <\/b> 0.4 km<br\/> <b>Track: <\/b> 0.6 km<br\/> <b>FRP: <\/b> 2.56 MW<br\/> <b>Brightness: <\/b> 320.82 K" }, "geometry": { "type": "Point", "coordinates": [ -123.15886, 45.24444, 0.0 ] } },
{ "type": "Feature", "properties": { "Name": "Fire Detection Centroid ", "Description": "<b>Latitude: <\/b> 45.24303<br\/>  <b>Longitude: <\/b> -123.15408<br\/>  <b>Detection Time: <\/b> 2024-03-07 11:09 UTC<br\/>  <b>Sensor: <\/b> NOAA-20 VIIRS<br\/> <b>Confidence: <\/b> Nominal<br\/>  <b>Day\/Night: <\/b> Night<br\/> <b>Scan: <\/b> 0.4 km<br\/> <b>Track: <\/b> 0.6 km<br\/> <b>FRP: <\/b> 2.11 MW<br\/> <b>Brightness: <\/b> 296.25 K" }, "geometry": { "type": "Point", "coordinates": [ -123.15408, 45.24303, 0.0 ] } }
]
}
