{
"type": "FeatureCollection",
"crs": { "type": "name", "properties": { "name": "urn:ogc:def:crs:OGC:1.3:CRS84" } },
"features": [
{ "type": "Feature", "properties": { "Name": "Fire Detection Centroid ", "Description": "<b>Latitude: <\/b> 19.40709<br\/>  <b>Longitude: <\/b> -155.28391<br\/>  <b>Detection Time: <\/b> 2023-11-08 12:08 UTC<br\/>  <b>Sensor: <\/b> NOAA-20 VIIRS<br\/> <b>Confidence: <\/b> Nominal<br\/>  <b>Day\/Night: <\/b> Night<br\/> <b>Scan: <\/b> 0.43 km<br\/> <b>Track: <\/b> 0.38 km<br\/> <b>FRP: <\/b> 2.24 MW<br\/> <b>Brightness: <\/b> 312.65 K" }, "geometry": { "type": "Point", "coordinates": [ -155.28391, 19.40709, 0.0 ] } },
{ "type": "Feature", "properties": { "Name": "Fire Detection Centroid ", "Description": "<b>Latitude: <\/b> 19.40364<br\/>  <b>Longitude: <\/b> -155.28453<br\/>  <b>Detection Time: <\/b> 2023-11-08 12:08 UTC<br\/>  <b>Sensor: <\/b> NOAA-20 VIIRS<br\/> <b>Confidence: <\/b> Nominal<br\/>  <b>Day\/Night: <\/b> Night<br\/> <b>Scan: <\/b> 0.43 km<br\/> <b>Track: <\/b> 0.38 km<br\/> <b>FRP: <\/b> 2.24 MW<br\/> <b>Brightness: <\/b> 310.26 K" }, "geometry": { "type": "Point", "coordinates": [ -155.28453, 19.40364, 0.0 ] } },
{ "type": "Feature", "properties": { "Name": "Fire Detection Centroid ", "Description": "<b>Latitude: <\/b> 19.40984<br\/>  <b>Longitude: <\/b> -155.27924<br\/>  <b>Detection Time: <\/b> 2023-11-08 12:08 UTC<br\/>  <b>Sensor: <\/b> NOAA-20 VIIRS<br\/> <b>Confidence: <\/b> Nominal<br\/>  <b>Day\/Night: <\/b> Night<br\/> <b>Scan: <\/b> 0.43 km<br\/> <b>Track: <\/b> 0.38 km<br\/> <b>FRP: <\/b> 1.99 MW<br\/> <b>Brightness: <\/b> 308.61 K" }, "geometry": { "type": "Point", "coordinates": [ -155.27924, 19.40984, 0.0 ] } },
{ "type": "Feature", "properties": { "Name": "Fire Detection Centroid ", "Description": "<b>Latitude: <\/b> 19.41328<br\/>  <b>Longitude: <\/b> -155.27859<br\/>  <b>Detection Time: <\/b> 2023-11-08 12:08 UTC<br\/>  <b>Sensor: <\/b> NOAA-20 VIIRS<br\/> <b>Confidence: <\/b> Nominal<br\/>  <b>Day\/Night: <\/b> Night<br\/> <b>Scan: <\/b> 0.43 km<br\/> <b>Track: <\/b> 0.38 km<br\/> <b>FRP: <\/b> 1.99 MW<br\/> <b>Brightness: <\/b> 307.57 K" }, "geometry": { "type": "Point", "coordinates": [ -155.27859, 19.41328, 0.0 ] } },
{ "type": "Feature", "properties": { "Name": "Fire Detection Centroid ", "Description": "<b>Latitude: <\/b> 19.40915<br\/>  <b>Longitude: <\/b> -155.27522<br\/>  <b>Detection Time: <\/b> 2023-11-08 12:08 UTC<br\/>  <b>Sensor: <\/b> NOAA-20 VIIRS<br\/> <b>Confidence: <\/b> Nominal<br\/>  <b>Day\/Night: <\/b> Night<br\/> <b>Scan: <\/b> 0.43 km<br\/> <b>Track: <\/b> 0.38 km<br\/> <b>FRP: <\/b> 1.99 MW<br\/> <b>Brightness: <\/b> 307.71 K" }, "geometry": { "type": "Point", "coordinates": [ -155.27522, 19.40915, 0.0 ] } },
{ "type": "Feature", "properties": { "Name": "Fire Detection Centroid ", "Description": "<b>Latitude: <\/b> 19.41122<br\/>  <b>Longitude: <\/b> -155.28732<br\/>  <b>Detection Time: <\/b> 2023-11-08 12:08 UTC<br\/>  <b>Sensor: <\/b> NOAA-20 VIIRS<br\/> <b>Confidence: <\/b> Nominal<br\/>  <b>Day\/Night: <\/b> Night<br\/> <b>Scan: <\/b> 0.43 km<br\/> <b>Track: <\/b> 0.38 km<br\/> <b>FRP: <\/b> 6.52 MW<br\/> <b>Brightness: <\/b> 314.74 K" }, "geometry": { "type": "Point", "coordinates": [ -155.28732, 19.41122, 0.0 ] } },
{ "type": "Feature", "properties": { "Name": "Fire Detection Centroid ", "Description": "<b>Latitude: <\/b> 19.40778<br\/>  <b>Longitude: <\/b> -155.28793<br\/>  <b>Detection Time: <\/b> 2023-11-08 12:08 UTC<br\/>  <b>Sensor: <\/b> NOAA-20 VIIRS<br\/> <b>Confidence: <\/b> Nominal<br\/>  <b>Day\/Night: <\/b> Night<br\/> <b>Scan: <\/b> 0.43 km<br\/> <b>Track: <\/b> 0.38 km<br\/> <b>FRP: <\/b> 2.24 MW<br\/> <b>Brightness: <\/b> 310.69 K" }, "geometry": { "type": "Point", "coordinates": [ -155.28793, 19.40778, 0.0 ] } }
]
}
