{
"type": "FeatureCollection",
"crs": { "type": "name", "properties": { "name": "urn:ogc:def:crs:OGC:1.3:CRS84" } },
"features": [
{ "type": "Feature", "properties": { "Name": "Fire Detection Centroid ", "Description": "<b>Latitude: <\/b> 18.86913<br\/>  <b>Longitude: <\/b> -69.46121<br\/>  <b>Detection Time: <\/b> 2024-04-03 16:54 UTC<br\/>  <b>Sensor: <\/b> NOAA-20 VIIRS<br\/> <b>Confidence: <\/b> Nominal<br\/>  <b>Day\/Night: <\/b> Day<br\/> <b>Scan: <\/b> 0.8 km<br\/> <b>Track: <\/b> 0.8 km<br\/> <b>FRP: <\/b> 7.46 MW<br\/> <b>Brightness: <\/b> 333.09 K" }, "geometry": { "type": "Point", "coordinates": [ -69.46121, 18.86913, 0.0 ] } }
]
}
