{
"type": "FeatureCollection",
"crs": { "type": "name", "properties": { "name": "urn:ogc:def:crs:OGC:1.3:CRS84" } },
"features": [
{ "type": "Feature", "properties": { "Name": "Fire Detection Centroid ", "Description": "<b>Latitude: <\/b> 45.02298<br\/>  <b>Longitude: <\/b> -79.68178<br\/>  <b>Detection Time: <\/b> 2023-10-01 16:54 UTC<br\/>  <b>Sensor: <\/b> NOAA-20 VIIRS<br\/> <b>Confidence: <\/b> Nominal<br\/>  <b>Day\/Night: <\/b> Day<br\/> <b>Scan: <\/b> 0.7 km<br\/> <b>Track: <\/b> 0.7 km<br\/> <b>FRP: <\/b> 7.52 MW<br\/> <b>Brightness: <\/b> 328.84 K" }, "geometry": { "type": "Point", "coordinates": [ -79.68178, 45.02298, 0.0 ] } },
{ "type": "Feature", "properties": { "Name": "Fire Detection Centroid ", "Description": "<b>Latitude: <\/b> 45.02705<br\/>  <b>Longitude: <\/b> -79.68384<br\/>  <b>Detection Time: <\/b> 2023-10-01 16:54 UTC<br\/>  <b>Sensor: <\/b> NOAA-20 VIIRS<br\/> <b>Confidence: <\/b> Nominal<br\/>  <b>Day\/Night: <\/b> Day<br\/> <b>Scan: <\/b> 0.7 km<br\/> <b>Track: <\/b> 0.7 km<br\/> <b>FRP: <\/b> 5.59 MW<br\/> <b>Brightness: <\/b> 335.56 K" }, "geometry": { "type": "Point", "coordinates": [ -79.68384, 45.02705, 0.0 ] } }
]
}
