{
"type": "FeatureCollection",
"crs": { "type": "name", "properties": { "name": "urn:ogc:def:crs:OGC:1.3:CRS84" } },
"features": [
{ "type": "Feature", "properties": { "Name": "Fire Detection Centroid ", "Description": "<b>Latitude: <\/b> 18.99796<br\/>  <b>Longitude: <\/b> -72.46579<br\/>  <b>Detection Time: <\/b> 2024-04-09 05:29 UTC<br\/>  <b>Sensor: <\/b> NOAA-20 VIIRS<br\/> <b>Confidence: <\/b> Nominal<br\/>  <b>Day\/Night: <\/b> Night<br\/> <b>Scan: <\/b> 0.8 km<br\/> <b>Track: <\/b> 0.8 km<br\/> <b>FRP: <\/b> 1.15 MW<br\/> <b>Brightness: <\/b> 299.51 K" }, "geometry": { "type": "Point", "coordinates": [ -72.46579, 18.99796, 0.0 ] } }
]
}
