{
"type": "FeatureCollection",
"crs": { "type": "name", "properties": { "name": "urn:ogc:def:crs:OGC:1.3:CRS84" } },
"features": [
{ "type": "Feature", "properties": { "Name": "Fire Detection Centroid ", "Description": "<b>Latitude: <\/b> 19.40711<br\/>  <b>Longitude: <\/b> -155.27768<br\/>  <b>Detection Time: <\/b> 2022-10-02 00:16 UTC<br\/>  <b>Sensor: <\/b> NOAA-20 VIIRS<br\/> <b>Confidence: <\/b> Nominal<br\/>  <b>Day\/Night: <\/b> Day<br\/> <b>Scan: <\/b> 0.43 km<br\/> <b>Track: <\/b> 0.62 km<br\/> <b>FRP: <\/b> 8.21 MW<br\/> <b>Brightness: <\/b> 335.02 K" }, "geometry": { "type": "Point", "coordinates": [ -155.27768, 19.40711, 0.0 ] } },
{ "type": "Feature", "properties": { "Name": "Fire Detection Centroid ", "Description": "<b>Latitude: <\/b> 19.4067<br\/>  <b>Longitude: <\/b> -155.28186<br\/>  <b>Detection Time: <\/b> 2022-10-02 00:16 UTC<br\/>  <b>Sensor: <\/b> NOAA-20 VIIRS<br\/> <b>Confidence: <\/b> Nominal<br\/>  <b>Day\/Night: <\/b> Day<br\/> <b>Scan: <\/b> 0.43 km<br\/> <b>Track: <\/b> 0.62 km<br\/> <b>FRP: <\/b> 57.89 MW<br\/> <b>Brightness: <\/b> 336.29 K" }, "geometry": { "type": "Point", "coordinates": [ -155.28186, 19.4067, 0.0 ] } },
{ "type": "Feature", "properties": { "Name": "Fire Detection Centroid ", "Description": "<b>Latitude: <\/b> 19.40057<br\/>  <b>Longitude: <\/b> -155.28558<br\/>  <b>Detection Time: <\/b> 2022-10-02 00:16 UTC<br\/>  <b>Sensor: <\/b> NOAA-20 VIIRS<br\/> <b>Confidence: <\/b> Nominal<br\/>  <b>Day\/Night: <\/b> Day<br\/> <b>Scan: <\/b> 0.43 km<br\/> <b>Track: <\/b> 0.62 km<br\/> <b>FRP: <\/b> 9.29 MW<br\/> <b>Brightness: <\/b> 343.04 K" }, "geometry": { "type": "Point", "coordinates": [ -155.28558, 19.40057, 0.0 ] } },
{ "type": "Feature", "properties": { "Name": "Fire Detection Centroid ", "Description": "<b>Latitude: <\/b> 19.40015<br\/>  <b>Longitude: <\/b> -155.28992<br\/>  <b>Detection Time: <\/b> 2022-10-02 00:16 UTC<br\/>  <b>Sensor: <\/b> NOAA-20 VIIRS<br\/> <b>Confidence: <\/b> Nominal<br\/>  <b>Day\/Night: <\/b> Day<br\/> <b>Scan: <\/b> 0.43 km<br\/> <b>Track: <\/b> 0.62 km<br\/> <b>FRP: <\/b> 5.51 MW<br\/> <b>Brightness: <\/b> 332.25 K" }, "geometry": { "type": "Point", "coordinates": [ -155.28992, 19.40015, 0.0 ] } },
{ "type": "Feature", "properties": { "Name": "Fire Detection Centroid ", "Description": "<b>Latitude: <\/b> 19.40629<br\/>  <b>Longitude: <\/b> -155.28612<br\/>  <b>Detection Time: <\/b> 2022-10-02 00:16 UTC<br\/>  <b>Sensor: <\/b> NOAA-20 VIIRS<br\/> <b>Confidence: <\/b> High<br\/>  <b>Day\/Night: <\/b> Day<br\/> <b>Scan: <\/b> 0.43 km<br\/> <b>Track: <\/b> 0.62 km<br\/> <b>FRP: <\/b> 57.89 MW<br\/> <b>Brightness: <\/b> 367 K" }, "geometry": { "type": "Point", "coordinates": [ -155.28612, 19.40629, 0.0 ] } }
]
}
