{
"type": "FeatureCollection",
"crs": { "type": "name", "properties": { "name": "urn:ogc:def:crs:OGC:1.3:CRS84" } },
"features": [
{ "type": "Feature", "properties": { "Name": "Fire Detection Centroid ", "Description": "<b>Latitude: <\/b> 19.78177<br\/>  <b>Longitude: <\/b> -72.63956<br\/>  <b>Detection Time: <\/b> 2023-12-17 17:43 UTC<br\/>  <b>Sensor: <\/b> NOAA-20 VIIRS<br\/> <b>Confidence: <\/b> Nominal<br\/>  <b>Day\/Night: <\/b> Day<br\/> <b>Scan: <\/b> 0.6 km<br\/> <b>Track: <\/b> 0.4 km<br\/> <b>FRP: <\/b> 3.69 MW<br\/> <b>Brightness: <\/b> 330.79 K" }, "geometry": { "type": "Point", "coordinates": [ -72.63956, 19.78177, 0.0 ] } }
]
}
