{
"type": "FeatureCollection",
"crs": { "type": "name", "properties": { "name": "urn:ogc:def:crs:OGC:1.3:CRS84" } },
"features": [
{ "type": "Feature", "properties": { "Name": "Fire Detection Centroid ", "Description": "<b>Latitude: <\/b> 44.49504<br\/>  <b>Longitude: <\/b> -122.37115<br\/>  <b>Detection Time: <\/b> 2024-05-13 11:28 UTC<br\/>  <b>Sensor: <\/b> NOAA-20 VIIRS<br\/> <b>Confidence: <\/b> Nominal<br\/>  <b>Day\/Night: <\/b> Night<br\/> <b>Scan: <\/b> 0.78 km<br\/> <b>Track: <\/b> 0.78 km<br\/> <b>FRP: <\/b> 0.25 MW<br\/> <b>Brightness: <\/b> 297.29 K" }, "geometry": { "type": "Point", "coordinates": [ -122.37115, 44.49504, 0.0 ] } }
]
}
