{
"type": "FeatureCollection",
"crs": { "type": "name", "properties": { "name": "urn:ogc:def:crs:OGC:1.3:CRS84" } },
"features": [
{ "type": "Feature", "properties": { "Name": "Fire Detection Centroid ", "Description": "<b>Latitude: <\/b> 38.20065<br\/>  <b>Longitude: <\/b> -122.95036<br\/>  <b>Detection Time: <\/b> 2024-05-05 10:41 UTC<br\/>  <b>Sensor: <\/b> NOAA-20 VIIRS<br\/> <b>Confidence: <\/b> Nominal<br\/>  <b>Day\/Night: <\/b> Night<br\/> <b>Scan: <\/b> 0.5 km<br\/> <b>Track: <\/b> 0.5 km<br\/> <b>FRP: <\/b> 5.76 MW<br\/> <b>Brightness: <\/b> 337.18 K" }, "geometry": { "type": "Point", "coordinates": [ -122.95036, 38.20065, 0.0 ] } },
{ "type": "Feature", "properties": { "Name": "Fire Detection Centroid ", "Description": "<b>Latitude: <\/b> 38.2589<br\/>  <b>Longitude: <\/b> -122.92818<br\/>  <b>Detection Time: <\/b> 2024-05-05 10:41 UTC<br\/>  <b>Sensor: <\/b> NOAA-20 VIIRS<br\/> <b>Confidence: <\/b> Nominal<br\/>  <b>Day\/Night: <\/b> Night<br\/> <b>Scan: <\/b> 0.55 km<br\/> <b>Track: <\/b> 0.51 km<br\/> <b>FRP: <\/b> 5.78 MW<br\/> <b>Brightness: <\/b> 337.18 K" }, "geometry": { "type": "Point", "coordinates": [ -122.92818, 38.2589, 0.0 ] } }
]
}
