{
"type": "FeatureCollection",
"crs": { "type": "name", "properties": { "name": "urn:ogc:def:crs:OGC:1.3:CRS84" } },
"features": [
{ "type": "Feature", "properties": { "Name": "Fire Detection Centroid ", "Description": "<b>Latitude: <\/b> 18.92955<br\/>  <b>Longitude: <\/b> -70.35375<br\/>  <b>Detection Time: <\/b> 2022-09-27 05:54 UTC<br\/>  <b>Sensor: <\/b> NOAA-20 VIIRS<br\/> <b>Confidence: <\/b> Nominal<br\/>  <b>Day\/Night: <\/b> Night<br\/> <b>Scan: <\/b> 0.4 km<br\/> <b>Track: <\/b> 0.5 km<br\/> <b>FRP: <\/b> 22.02 MW<br\/> <b>Brightness: <\/b> 351.45 K" }, "geometry": { "type": "Point", "coordinates": [ -70.35375, 18.92955, 0.0 ] } },
{ "type": "Feature", "properties": { "Name": "Fire Detection Centroid ", "Description": "<b>Latitude: <\/b> 18.92897<br\/>  <b>Longitude: <\/b> -70.35224<br\/>  <b>Detection Time: <\/b> 2022-09-27 05:54 UTC<br\/>  <b>Sensor: <\/b> NOAA-20 VIIRS<br\/> <b>Confidence: <\/b> Nominal<br\/>  <b>Day\/Night: <\/b> Night<br\/> <b>Scan: <\/b> 0.4 km<br\/> <b>Track: <\/b> 0.5 km<br\/> <b>FRP: <\/b> 13.1 MW<br\/> <b>Brightness: <\/b> 327.83 K" }, "geometry": { "type": "Point", "coordinates": [ -70.35224, 18.92897, 0.0 ] } },
{ "type": "Feature", "properties": { "Name": "Fire Detection Centroid ", "Description": "<b>Latitude: <\/b> 18.92948<br\/>  <b>Longitude: <\/b> -70.35647<br\/>  <b>Detection Time: <\/b> 2022-09-27 05:54 UTC<br\/>  <b>Sensor: <\/b> NOAA-20 VIIRS<br\/> <b>Confidence: <\/b> Nominal<br\/>  <b>Day\/Night: <\/b> Night<br\/> <b>Scan: <\/b> 0.4 km<br\/> <b>Track: <\/b> 0.5 km<br\/> <b>FRP: <\/b> 13.1 MW<br\/> <b>Brightness: <\/b> 338.94 K" }, "geometry": { "type": "Point", "coordinates": [ -70.35647, 18.92948, 0.0 ] } },
{ "type": "Feature", "properties": { "Name": "Fire Detection Centroid ", "Description": "<b>Latitude: <\/b> 19.31395<br\/>  <b>Longitude: <\/b> -69.51206<br\/>  <b>Detection Time: <\/b> 2022-09-27 05:54 UTC<br\/>  <b>Sensor: <\/b> NOAA-20 VIIRS<br\/> <b>Confidence: <\/b> Nominal<br\/>  <b>Day\/Night: <\/b> Night<br\/> <b>Scan: <\/b> 0.4 km<br\/> <b>Track: <\/b> 0.4 km<br\/> <b>FRP: <\/b> 1.05 MW<br\/> <b>Brightness: <\/b> 307.54 K" }, "geometry": { "type": "Point", "coordinates": [ -69.51206, 19.31395, 0.0 ] } }
]
}
