{
"type": "FeatureCollection",
"crs": { "type": "name", "properties": { "name": "urn:ogc:def:crs:OGC:1.3:CRS84" } },
"features": [
{ "type": "Feature", "properties": { "Name": "Fire Detection Centroid ", "Description": "<b>Latitude: <\/b> 18.60891<br\/>  <b>Longitude: <\/b> -71.39327<br\/>  <b>Detection Time: <\/b> 2022-08-05 05:47 UTC<br\/>  <b>Sensor: <\/b> NOAA-20 VIIRS<br\/> <b>Confidence: <\/b> Nominal<br\/>  <b>Day\/Night: <\/b> Night<br\/> <b>Scan: <\/b> 0.3 km<br\/> <b>Track: <\/b> 0.6 km<br\/> <b>FRP: <\/b> 0.98 MW<br\/> <b>Brightness: <\/b> 296.06 K" }, "geometry": { "type": "Point", "coordinates": [ -71.39327, 18.60891, 0.0 ] } },
{ "type": "Feature", "properties": { "Name": "Fire Detection Centroid ", "Description": "<b>Latitude: <\/b> 18.93063<br\/>  <b>Longitude: <\/b> -70.35494<br\/>  <b>Detection Time: <\/b> 2022-08-05 05:47 UTC<br\/>  <b>Sensor: <\/b> NOAA-20 VIIRS<br\/> <b>Confidence: <\/b> Nominal<br\/>  <b>Day\/Night: <\/b> Night<br\/> <b>Scan: <\/b> 0.6 km<br\/> <b>Track: <\/b> 0.5 km<br\/> <b>FRP: <\/b> 5.33 MW<br\/> <b>Brightness: <\/b> 342.25 K" }, "geometry": { "type": "Point", "coordinates": [ -70.35494, 18.93063, 0.0 ] } },
{ "type": "Feature", "properties": { "Name": "Fire Detection Centroid ", "Description": "<b>Latitude: <\/b> 18.92999<br\/>  <b>Longitude: <\/b> -70.34926<br\/>  <b>Detection Time: <\/b> 2022-08-05 05:47 UTC<br\/>  <b>Sensor: <\/b> NOAA-20 VIIRS<br\/> <b>Confidence: <\/b> Nominal<br\/>  <b>Day\/Night: <\/b> Night<br\/> <b>Scan: <\/b> 0.6 km<br\/> <b>Track: <\/b> 0.5 km<br\/> <b>FRP: <\/b> 3.96 MW<br\/> <b>Brightness: <\/b> 297.58 K" }, "geometry": { "type": "Point", "coordinates": [ -70.34926, 18.92999, 0.0 ] } },
{ "type": "Feature", "properties": { "Name": "Fire Detection Centroid ", "Description": "<b>Latitude: <\/b> 18.92583<br\/>  <b>Longitude: <\/b> -70.35496<br\/>  <b>Detection Time: <\/b> 2022-08-05 05:47 UTC<br\/>  <b>Sensor: <\/b> NOAA-20 VIIRS<br\/> <b>Confidence: <\/b> Nominal<br\/>  <b>Day\/Night: <\/b> Night<br\/> <b>Scan: <\/b> 0.6 km<br\/> <b>Track: <\/b> 0.5 km<br\/> <b>FRP: <\/b> 5.33 MW<br\/> <b>Brightness: <\/b> 300.19 K" }, "geometry": { "type": "Point", "coordinates": [ -70.35496, 18.92583, 0.0 ] } },
{ "type": "Feature", "properties": { "Name": "Fire Detection Centroid ", "Description": "<b>Latitude: <\/b> 18.61992<br\/>  <b>Longitude: <\/b> -71.40027<br\/>  <b>Detection Time: <\/b> 2022-08-05 05:47 UTC<br\/>  <b>Sensor: <\/b> NOAA-20 VIIRS<br\/> <b>Confidence: <\/b> Nominal<br\/>  <b>Day\/Night: <\/b> Night<br\/> <b>Scan: <\/b> 0.3 km<br\/> <b>Track: <\/b> 0.6 km<br\/> <b>FRP: <\/b> 1.11 MW<br\/> <b>Brightness: <\/b> 318.12 K" }, "geometry": { "type": "Point", "coordinates": [ -71.40027, 18.61992, 0.0 ] } },
{ "type": "Feature", "properties": { "Name": "Fire Detection Centroid ", "Description": "<b>Latitude: <\/b> 18.61963<br\/>  <b>Longitude: <\/b> -71.39766<br\/>  <b>Detection Time: <\/b> 2022-08-05 05:47 UTC<br\/>  <b>Sensor: <\/b> NOAA-20 VIIRS<br\/> <b>Confidence: <\/b> Nominal<br\/>  <b>Day\/Night: <\/b> Night<br\/> <b>Scan: <\/b> 0.3 km<br\/> <b>Track: <\/b> 0.6 km<br\/> <b>FRP: <\/b> 0.98 MW<br\/> <b>Brightness: <\/b> 296.1 K" }, "geometry": { "type": "Point", "coordinates": [ -71.39766, 18.61963, 0.0 ] } },
{ "type": "Feature", "properties": { "Name": "Fire Detection Centroid ", "Description": "<b>Latitude: <\/b> 18.6086<br\/>  <b>Longitude: <\/b> -71.3904<br\/>  <b>Detection Time: <\/b> 2022-08-05 05:47 UTC<br\/>  <b>Sensor: <\/b> NOAA-20 VIIRS<br\/> <b>Confidence: <\/b> Nominal<br\/>  <b>Day\/Night: <\/b> Night<br\/> <b>Scan: <\/b> 0.3 km<br\/> <b>Track: <\/b> 0.5 km<br\/> <b>FRP: <\/b> 1.64 MW<br\/> <b>Brightness: <\/b> 323.19 K" }, "geometry": { "type": "Point", "coordinates": [ -71.3904, 18.6086, 0.0 ] } }
]
}
