{
"type": "FeatureCollection",
"crs": { "type": "name", "properties": { "name": "urn:ogc:def:crs:OGC:1.3:CRS84" } },
"features": [
{ "type": "Feature", "properties": { "Name": "Fire Detection Centroid ", "Description": "<b>Latitude: <\/b> 19.59681<br\/>  <b>Longitude: <\/b> -155.50461<br\/>  <b>Detection Time: <\/b> 2023-06-06 12:14 UTC<br\/>  <b>Sensor: <\/b> NOAA-20 VIIRS<br\/> <b>Confidence: <\/b> Nominal<br\/>  <b>Day\/Night: <\/b> Night<br\/> <b>Scan: <\/b> 0.48 km<br\/> <b>Track: <\/b> 0.4 km<br\/> <b>FRP: <\/b> 2.07 MW<br\/> <b>Brightness: <\/b> 295.52 K" }, "geometry": { "type": "Point", "coordinates": [ -155.50461, 19.59681, 0.0 ] } }
]
}
