{
"type": "FeatureCollection",
"crs": { "type": "name", "properties": { "name": "urn:ogc:def:crs:OGC:1.3:CRS84" } },
"features": [
{ "type": "Feature", "properties": { "Name": "Fire Detection Centroid ", "Description": "<b>Latitude: <\/b> 39.8718<br\/>  <b>Longitude: <\/b> -121.97054<br\/>  <b>Detection Time: <\/b> 2023-05-06 21:31 UTC<br\/>  <b>Sensor: <\/b> NOAA-20 VIIRS<br\/> <b>Confidence: <\/b> Nominal<br\/>  <b>Day\/Night: <\/b> Day<br\/> <b>Scan: <\/b> 0.4 km<br\/> <b>Track: <\/b> 0.45 km<br\/> <b>FRP: <\/b> 7.86 MW<br\/> <b>Brightness: <\/b> 341.46 K" }, "geometry": { "type": "Point", "coordinates": [ -121.97054, 39.8718, 0.0 ] } },
{ "type": "Feature", "properties": { "Name": "Fire Detection Centroid ", "Description": "<b>Latitude: <\/b> 39.86725<br\/>  <b>Longitude: <\/b> -121.97464<br\/>  <b>Detection Time: <\/b> 2023-05-06 21:31 UTC<br\/>  <b>Sensor: <\/b> NOAA-20 VIIRS<br\/> <b>Confidence: <\/b> Nominal<br\/>  <b>Day\/Night: <\/b> Day<br\/> <b>Scan: <\/b> 0.4 km<br\/> <b>Track: <\/b> 0.45 km<br\/> <b>FRP: <\/b> 11.49 MW<br\/> <b>Brightness: <\/b> 332.97 K" }, "geometry": { "type": "Point", "coordinates": [ -121.97464, 39.86725, 0.0 ] } },
{ "type": "Feature", "properties": { "Name": "Fire Detection Centroid ", "Description": "<b>Latitude: <\/b> 39.86771<br\/>  <b>Longitude: <\/b> -121.96989<br\/>  <b>Detection Time: <\/b> 2023-05-06 21:31 UTC<br\/>  <b>Sensor: <\/b> NOAA-20 VIIRS<br\/> <b>Confidence: <\/b> Nominal<br\/>  <b>Day\/Night: <\/b> Day<br\/> <b>Scan: <\/b> 0.4 km<br\/> <b>Track: <\/b> 0.45 km<br\/> <b>FRP: <\/b> 7.86 MW<br\/> <b>Brightness: <\/b> 328.8 K" }, "geometry": { "type": "Point", "coordinates": [ -121.96989, 39.86771, 0.0 ] } },
{ "type": "Feature", "properties": { "Name": "Fire Detection Centroid ", "Description": "<b>Latitude: <\/b> 40.61766<br\/>  <b>Longitude: <\/b> -123.11632<br\/>  <b>Detection Time: <\/b> 2023-05-06 21:31 UTC<br\/>  <b>Sensor: <\/b> NOAA-20 VIIRS<br\/> <b>Confidence: <\/b> Nominal<br\/>  <b>Day\/Night: <\/b> Day<br\/> <b>Scan: <\/b> 0.55 km<br\/> <b>Track: <\/b> 0.42 km<br\/> <b>FRP: <\/b> 6.28 MW<br\/> <b>Brightness: <\/b> 333.55 K" }, "geometry": { "type": "Point", "coordinates": [ -123.11632, 40.61766, 0.0 ] } },
{ "type": "Feature", "properties": { "Name": "Fire Detection Centroid ", "Description": "<b>Latitude: <\/b> 39.87827<br\/>  <b>Longitude: <\/b> -121.97602<br\/>  <b>Detection Time: <\/b> 2023-05-06 21:31 UTC<br\/>  <b>Sensor: <\/b> NOAA-20 VIIRS<br\/> <b>Confidence: <\/b> Nominal<br\/>  <b>Day\/Night: <\/b> Day<br\/> <b>Scan: <\/b> 0.4 km<br\/> <b>Track: <\/b> 0.45 km<br\/> <b>FRP: <\/b> 3.18 MW<br\/> <b>Brightness: <\/b> 329.5 K" }, "geometry": { "type": "Point", "coordinates": [ -121.97602, 39.87827, 0.0 ] } },
{ "type": "Feature", "properties": { "Name": "Fire Detection Centroid ", "Description": "<b>Latitude: <\/b> 39.87954<br\/>  <b>Longitude: <\/b> -121.97658<br\/>  <b>Detection Time: <\/b> 2023-05-06 21:31 UTC<br\/>  <b>Sensor: <\/b> NOAA-20 VIIRS<br\/> <b>Confidence: <\/b> Nominal<br\/>  <b>Day\/Night: <\/b> Day<br\/> <b>Scan: <\/b> 0.4 km<br\/> <b>Track: <\/b> 0.45 km<br\/> <b>FRP: <\/b> 3.11 MW<br\/> <b>Brightness: <\/b> 329.92 K" }, "geometry": { "type": "Point", "coordinates": [ -121.97658, 39.87954, 0.0 ] } },
{ "type": "Feature", "properties": { "Name": "Fire Detection Centroid ", "Description": "<b>Latitude: <\/b> 40.61756<br\/>  <b>Longitude: <\/b> -123.11763<br\/>  <b>Detection Time: <\/b> 2023-05-06 21:31 UTC<br\/>  <b>Sensor: <\/b> NOAA-20 VIIRS<br\/> <b>Confidence: <\/b> Nominal<br\/>  <b>Day\/Night: <\/b> Day<br\/> <b>Scan: <\/b> 0.55 km<br\/> <b>Track: <\/b> 0.43 km<br\/> <b>FRP: <\/b> 4.59 MW<br\/> <b>Brightness: <\/b> 329.02 K" }, "geometry": { "type": "Point", "coordinates": [ -123.11763, 40.61756, 0.0 ] } },
{ "type": "Feature", "properties": { "Name": "Fire Detection Centroid ", "Description": "<b>Latitude: <\/b> 39.87134<br\/>  <b>Longitude: <\/b> -121.9753<br\/>  <b>Detection Time: <\/b> 2023-05-06 21:31 UTC<br\/>  <b>Sensor: <\/b> NOAA-20 VIIRS<br\/> <b>Confidence: <\/b> Nominal<br\/>  <b>Day\/Night: <\/b> Day<br\/> <b>Scan: <\/b> 0.4 km<br\/> <b>Track: <\/b> 0.45 km<br\/> <b>FRP: <\/b> 11.49 MW<br\/> <b>Brightness: <\/b> 335.34 K" }, "geometry": { "type": "Point", "coordinates": [ -121.9753, 39.87134, 0.0 ] } },
{ "type": "Feature", "properties": { "Name": "Fire Detection Centroid ", "Description": "<b>Latitude: <\/b> 28.70239<br\/>  <b>Longitude: <\/b> -111.40871<br\/>  <b>Detection Time: <\/b> 2023-05-06 21:27 UTC<br\/>  <b>Sensor: <\/b> NOAA-20 VIIRS<br\/> <b>Confidence: <\/b> Nominal<br\/>  <b>Day\/Night: <\/b> Day<br\/> <b>Scan: <\/b> 0.63 km<br\/> <b>Track: <\/b> 0.72 km<br\/> <b>FRP: <\/b> 7.82 MW<br\/> <b>Brightness: <\/b> 348.84 K" }, "geometry": { "type": "Point", "coordinates": [ -111.40871, 28.70239, 0.0 ] } }
]
}
