{
"type": "FeatureCollection",
"crs": { "type": "name", "properties": { "name": "urn:ogc:def:crs:OGC:1.3:CRS84" } },
"features": [
{ "type": "Feature", "properties": { "Name": "Fire Detection Centroid ", "Description": "<b>Latitude: <\/b> 44.04749<br\/>  <b>Longitude: <\/b> -123.64736<br\/>  <b>Detection Time: <\/b> 2023-01-04 09:54 UTC<br\/>  <b>Sensor: <\/b> NOAA-20 VIIRS<br\/> <b>Confidence: <\/b> Nominal<br\/>  <b>Day\/Night: <\/b> Night<br\/> <b>Scan: <\/b> 0.5 km<br\/> <b>Track: <\/b> 0.4 km<br\/> <b>FRP: <\/b> 1.06 MW<br\/> <b>Brightness: <\/b> 309.02 K" }, "geometry": { "type": "Point", "coordinates": [ -123.64736, 44.04749, 0.0 ] } },
{ "type": "Feature", "properties": { "Name": "Fire Detection Centroid ", "Description": "<b>Latitude: <\/b> 44.04384<br\/>  <b>Longitude: <\/b> -123.64824<br\/>  <b>Detection Time: <\/b> 2023-01-04 09:54 UTC<br\/>  <b>Sensor: <\/b> NOAA-20 VIIRS<br\/> <b>Confidence: <\/b> Nominal<br\/>  <b>Day\/Night: <\/b> Night<br\/> <b>Scan: <\/b> 0.5 km<br\/> <b>Track: <\/b> 0.4 km<br\/> <b>FRP: <\/b> 5.35 MW<br\/> <b>Brightness: <\/b> 327.27 K" }, "geometry": { "type": "Point", "coordinates": [ -123.64824, 44.04384, 0.0 ] } },
{ "type": "Feature", "properties": { "Name": "Fire Detection Centroid ", "Description": "<b>Latitude: <\/b> 48.53222<br\/>  <b>Longitude: <\/b> -117.83404<br\/>  <b>Detection Time: <\/b> 2023-01-04 09:52 UTC<br\/>  <b>Sensor: <\/b> NOAA-20 VIIRS<br\/> <b>Confidence: <\/b> Nominal<br\/>  <b>Day\/Night: <\/b> Night<br\/> <b>Scan: <\/b> 0.4 km<br\/> <b>Track: <\/b> 0.4 km<br\/> <b>FRP: <\/b> 1.18 MW<br\/> <b>Brightness: <\/b> 305.14 K" }, "geometry": { "type": "Point", "coordinates": [ -117.83404, 48.53222, 0.0 ] } },
{ "type": "Feature", "properties": { "Name": "Fire Detection Centroid ", "Description": "<b>Latitude: <\/b> 48.52726<br\/>  <b>Longitude: <\/b> -117.84657<br\/>  <b>Detection Time: <\/b> 2023-01-04 09:52 UTC<br\/>  <b>Sensor: <\/b> NOAA-20 VIIRS<br\/> <b>Confidence: <\/b> Nominal<br\/>  <b>Day\/Night: <\/b> Night<br\/> <b>Scan: <\/b> 0.4 km<br\/> <b>Track: <\/b> 0.4 km<br\/> <b>FRP: <\/b> 1.04 MW<br\/> <b>Brightness: <\/b> 305.27 K" }, "geometry": { "type": "Point", "coordinates": [ -117.84657, 48.52726, 0.0 ] } }
]
}
