{
"type": "FeatureCollection",
"crs": { "type": "name", "properties": { "name": "urn:ogc:def:crs:OGC:1.3:CRS84" } },
"features": [
{ "type": "Feature", "properties": { "Name": "Fire Detection Centroid ", "Description": "<b>Latitude: <\/b> 34.60652<br\/>  <b>Longitude: <\/b> -117.33941<br\/>  <b>Detection Time: <\/b> 2023-04-18 10:47 UTC<br\/>  <b>Sensor: <\/b> NOAA-20 VIIRS<br\/> <b>Confidence: <\/b> Nominal<br\/>  <b>Day\/Night: <\/b> Night<br\/> <b>Scan: <\/b> 0.79 km<br\/> <b>Track: <\/b> 0.78 km<br\/> <b>FRP: <\/b> 2.24 MW<br\/> <b>Brightness: <\/b> 301.09 K" }, "geometry": { "type": "Point", "coordinates": [ -117.33941, 34.60652, 0.0 ] } },
{ "type": "Feature", "properties": { "Name": "Fire Detection Centroid ", "Description": "<b>Latitude: <\/b> 38.04325<br\/>  <b>Longitude: <\/b> -122.25105<br\/>  <b>Detection Time: <\/b> 2023-04-18 10:45 UTC<br\/>  <b>Sensor: <\/b> NOAA-20 VIIRS<br\/> <b>Confidence: <\/b> Nominal<br\/>  <b>Day\/Night: <\/b> Night<br\/> <b>Scan: <\/b> 0.35 km<br\/> <b>Track: <\/b> 0.57 km<br\/> <b>FRP: <\/b> 0.73 MW<br\/> <b>Brightness: <\/b> 297.51 K" }, "geometry": { "type": "Point", "coordinates": [ -122.25105, 38.04325, 0.0 ] } },
{ "type": "Feature", "properties": { "Name": "Fire Detection Centroid ", "Description": "<b>Latitude: <\/b> 39.64523<br\/>  <b>Longitude: <\/b> -121.99845<br\/>  <b>Detection Time: <\/b> 2023-04-18 10:45 UTC<br\/>  <b>Sensor: <\/b> NOAA-20 VIIRS<br\/> <b>Confidence: <\/b> Nominal<br\/>  <b>Day\/Night: <\/b> Night<br\/> <b>Scan: <\/b> 0.33 km<br\/> <b>Track: <\/b> 0.55 km<br\/> <b>FRP: <\/b> 0.41 MW<br\/> <b>Brightness: <\/b> 296.82 K" }, "geometry": { "type": "Point", "coordinates": [ -121.99845, 39.64523, 0.0 ] } },
{ "type": "Feature", "properties": { "Name": "Fire Detection Centroid ", "Description": "<b>Latitude: <\/b> 38.01416<br\/>  <b>Longitude: <\/b> -122.11439<br\/>  <b>Detection Time: <\/b> 2023-04-18 10:45 UTC<br\/>  <b>Sensor: <\/b> NOAA-20 VIIRS<br\/> <b>Confidence: <\/b> Nominal<br\/>  <b>Day\/Night: <\/b> Night<br\/> <b>Scan: <\/b> 0.36 km<br\/> <b>Track: <\/b> 0.57 km<br\/> <b>FRP: <\/b> 1.2 MW<br\/> <b>Brightness: <\/b> 299.18 K" }, "geometry": { "type": "Point", "coordinates": [ -122.11439, 38.01416, 0.0 ] } },
{ "type": "Feature", "properties": { "Name": "Fire Detection Centroid ", "Description": "<b>Latitude: <\/b> 38.07054<br\/>  <b>Longitude: <\/b> -122.13812<br\/>  <b>Detection Time: <\/b> 2023-04-18 10:45 UTC<br\/>  <b>Sensor: <\/b> NOAA-20 VIIRS<br\/> <b>Confidence: <\/b> Nominal<br\/>  <b>Day\/Night: <\/b> Night<br\/> <b>Scan: <\/b> 0.36 km<br\/> <b>Track: <\/b> 0.57 km<br\/> <b>FRP: <\/b> 0.83 MW<br\/> <b>Brightness: <\/b> 299.58 K" }, "geometry": { "type": "Point", "coordinates": [ -122.13812, 38.07054, 0.0 ] } },
{ "type": "Feature", "properties": { "Name": "Fire Detection Centroid ", "Description": "<b>Latitude: <\/b> 39.73154<br\/>  <b>Longitude: <\/b> -122.02154<br\/>  <b>Detection Time: <\/b> 2023-04-18 10:45 UTC<br\/>  <b>Sensor: <\/b> NOAA-20 VIIRS<br\/> <b>Confidence: <\/b> Nominal<br\/>  <b>Day\/Night: <\/b> Night<br\/> <b>Scan: <\/b> 0.33 km<br\/> <b>Track: <\/b> 0.55 km<br\/> <b>FRP: <\/b> 0.39 MW<br\/> <b>Brightness: <\/b> 295.53 K" }, "geometry": { "type": "Point", "coordinates": [ -122.02154, 39.73154, 0.0 ] } },
{ "type": "Feature", "properties": { "Name": "Fire Detection Centroid ", "Description": "<b>Latitude: <\/b> 38.04483<br\/>  <b>Longitude: <\/b> -122.25127<br\/>  <b>Detection Time: <\/b> 2023-04-18 10:45 UTC<br\/>  <b>Sensor: <\/b> NOAA-20 VIIRS<br\/> <b>Confidence: <\/b> Nominal<br\/>  <b>Day\/Night: <\/b> Night<br\/> <b>Scan: <\/b> 0.35 km<br\/> <b>Track: <\/b> 0.57 km<br\/> <b>FRP: <\/b> 0.79 MW<br\/> <b>Brightness: <\/b> 295.03 K" }, "geometry": { "type": "Point", "coordinates": [ -122.25127, 38.04483, 0.0 ] } }
]
}
