{
"type": "FeatureCollection",
"crs": { "type": "name", "properties": { "name": "urn:ogc:def:crs:OGC:1.3:CRS84" } },
"features": [
{ "type": "Feature", "properties": { "Name": "Fire Detection Centroid ", "Description": "<b>Latitude: <\/b> 35.93931<br\/>  <b>Longitude: <\/b> -119.06364<br\/>  <b>Detection Time: <\/b> 2023-09-04 22:01 UTC<br\/>  <b>Sensor: <\/b> NOAA-20 VIIRS<br\/> <b>Confidence: <\/b> Nominal<br\/>  <b>Day\/Night: <\/b> Day<br\/> <b>Scan: <\/b> 0.74 km<br\/> <b>Track: <\/b> 0.76 km<br\/> <b>FRP: <\/b> 10.54 MW<br\/> <b>Brightness: <\/b> 346.18 K" }, "geometry": { "type": "Point", "coordinates": [ -119.06364, 35.93931, 0.0 ] } },
{ "type": "Feature", "properties": { "Name": "Fire Detection Centroid ", "Description": "<b>Latitude: <\/b> 35.59628<br\/>  <b>Longitude: <\/b> -119.73897<br\/>  <b>Detection Time: <\/b> 2023-09-04 22:01 UTC<br\/>  <b>Sensor: <\/b> NOAA-20 VIIRS<br\/> <b>Confidence: <\/b> Nominal<br\/>  <b>Day\/Night: <\/b> Day<br\/> <b>Scan: <\/b> 0.67 km<br\/> <b>Track: <\/b> 0.74 km<br\/> <b>FRP: <\/b> 5.14 MW<br\/> <b>Brightness: <\/b> 334.94 K" }, "geometry": { "type": "Point", "coordinates": [ -119.73897, 35.59628, 0.0 ] } },
{ "type": "Feature", "properties": { "Name": "Fire Detection Centroid ", "Description": "<b>Latitude: <\/b> 35.5955<br\/>  <b>Longitude: <\/b> -119.73775<br\/>  <b>Detection Time: <\/b> 2023-09-04 22:01 UTC<br\/>  <b>Sensor: <\/b> NOAA-20 VIIRS<br\/> <b>Confidence: <\/b> Low<br\/>  <b>Day\/Night: <\/b> Day<br\/> <b>Scan: <\/b> 0.67 km<br\/> <b>Track: <\/b> 0.74 km<br\/> <b>FRP: <\/b> 4.28 MW<br\/> <b>Brightness: <\/b> 331.22 K" }, "geometry": { "type": "Point", "coordinates": [ -119.73775, 35.5955, 0.0 ] } },
{ "type": "Feature", "properties": { "Name": "Fire Detection Centroid ", "Description": "<b>Latitude: <\/b> 35.94209<br\/>  <b>Longitude: <\/b> -119.06581<br\/>  <b>Detection Time: <\/b> 2023-09-04 22:01 UTC<br\/>  <b>Sensor: <\/b> NOAA-20 VIIRS<br\/> <b>Confidence: <\/b> Nominal<br\/>  <b>Day\/Night: <\/b> Day<br\/> <b>Scan: <\/b> 0.74 km<br\/> <b>Track: <\/b> 0.76 km<br\/> <b>FRP: <\/b> 7.23 MW<br\/> <b>Brightness: <\/b> 330.88 K" }, "geometry": { "type": "Point", "coordinates": [ -119.06581, 35.94209, 0.0 ] } },
{ "type": "Feature", "properties": { "Name": "Fire Detection Centroid ", "Description": "<b>Latitude: <\/b> 35.94225<br\/>  <b>Longitude: <\/b> -119.0576<br\/>  <b>Detection Time: <\/b> 2023-09-04 22:01 UTC<br\/>  <b>Sensor: <\/b> NOAA-20 VIIRS<br\/> <b>Confidence: <\/b> Nominal<br\/>  <b>Day\/Night: <\/b> Day<br\/> <b>Scan: <\/b> 0.74 km<br\/> <b>Track: <\/b> 0.76 km<br\/> <b>FRP: <\/b> 8.27 MW<br\/> <b>Brightness: <\/b> 333.38 K" }, "geometry": { "type": "Point", "coordinates": [ -119.0576, 35.94225, 0.0 ] } },
{ "type": "Feature", "properties": { "Name": "Fire Detection Centroid ", "Description": "<b>Latitude: <\/b> 38.48243<br\/>  <b>Longitude: <\/b> -121.85649<br\/>  <b>Detection Time: <\/b> 2023-09-04 22:01 UTC<br\/>  <b>Sensor: <\/b> NOAA-20 VIIRS<br\/> <b>Confidence: <\/b> Nominal<br\/>  <b>Day\/Night: <\/b> Day<br\/> <b>Scan: <\/b> 0.53 km<br\/> <b>Track: <\/b> 0.67 km<br\/> <b>FRP: <\/b> 9.11 MW<br\/> <b>Brightness: <\/b> 341.61 K" }, "geometry": { "type": "Point", "coordinates": [ -121.85649, 38.48243, 0.0 ] } }
]
}
