{
"type": "FeatureCollection",
"crs": { "type": "name", "properties": { "name": "urn:ogc:def:crs:OGC:1.3:CRS84" } },
"features": [
{ "type": "Feature", "properties": { "Name": "Fire Detection Centroid ", "Description": "<b>Latitude: <\/b> 21.9069<br\/>  <b>Longitude: <\/b> -159.49155<br\/>  <b>Detection Time: <\/b> 2023-05-30 23:58 UTC<br\/>  <b>Sensor: <\/b> NOAA-20 VIIRS<br\/> <b>Confidence: <\/b> Nominal<br\/>  <b>Day\/Night: <\/b> Day<br\/> <b>Scan: <\/b> 0.42 km<br\/> <b>Track: <\/b> 0.37 km<br\/> <b>FRP: <\/b> 4.62 MW<br\/> <b>Brightness: <\/b> 335.1 K" }, "geometry": { "type": "Point", "coordinates": [ -159.49155, 21.9069, 0.0 ] } }
]
}
