{
"type": "FeatureCollection",
"crs": { "type": "name", "properties": { "name": "urn:ogc:def:crs:OGC:1.3:CRS84" } },
"features": [
{ "type": "Feature", "properties": { "Name": "Fire Detection Centroid ", "Description": "<b>Latitude: <\/b> 19.40706<br\/>  <b>Longitude: <\/b> -155.28069<br\/>  <b>Detection Time: <\/b> 2023-07-09 23:07 UTC<br\/>  <b>Sensor: <\/b> NOAA-20 VIIRS<br\/> <b>Confidence: <\/b> Low<br\/>  <b>Day\/Night: <\/b> Day<br\/> <b>Scan: <\/b> 0.49 km<br\/> <b>Track: <\/b> 0.48 km<br\/> <b>FRP: <\/b> 19.45 MW<br\/> <b>Brightness: <\/b> 326.55 K" }, "geometry": { "type": "Point", "coordinates": [ -155.28069, 19.40706, 0.0 ] } }
]
}
