{
"type": "FeatureCollection",
"crs": { "type": "name", "properties": { "name": "urn:ogc:def:crs:OGC:1.3:CRS84" } },
"features": [
{ "type": "Feature", "properties": { "Name": "Fire Detection Centroid ", "Description": "<b>Latitude: <\/b> 19.41052<br\/>  <b>Longitude: <\/b> -155.28384<br\/>  <b>Detection Time: <\/b> 2023-01-29 12:14 UTC<br\/>  <b>Sensor: <\/b> NOAA-20 VIIRS<br\/> <b>Confidence: <\/b> Nominal<br\/>  <b>Day\/Night: <\/b> Night<br\/> <b>Scan: <\/b> 0.5 km<br\/> <b>Track: <\/b> 0.41 km<br\/> <b>FRP: <\/b> 12.61 MW<br\/> <b>Brightness: <\/b> 343.23 K" }, "geometry": { "type": "Point", "coordinates": [ -155.28384, 19.41052, 0.0 ] } },
{ "type": "Feature", "properties": { "Name": "Fire Detection Centroid ", "Description": "<b>Latitude: <\/b> 19.41137<br\/>  <b>Longitude: <\/b> -155.28862<br\/>  <b>Detection Time: <\/b> 2023-01-29 12:14 UTC<br\/>  <b>Sensor: <\/b> NOAA-20 VIIRS<br\/> <b>Confidence: <\/b> Nominal<br\/>  <b>Day\/Night: <\/b> Night<br\/> <b>Scan: <\/b> 0.5 km<br\/> <b>Track: <\/b> 0.41 km<br\/> <b>FRP: <\/b> 5.21 MW<br\/> <b>Brightness: <\/b> 321.28 K" }, "geometry": { "type": "Point", "coordinates": [ -155.28862, 19.41137, 0.0 ] } },
{ "type": "Feature", "properties": { "Name": "Fire Detection Centroid ", "Description": "<b>Latitude: <\/b> 19.40312<br\/>  <b>Longitude: <\/b> -155.28523<br\/>  <b>Detection Time: <\/b> 2023-01-29 12:14 UTC<br\/>  <b>Sensor: <\/b> NOAA-20 VIIRS<br\/> <b>Confidence: <\/b> Nominal<br\/>  <b>Day\/Night: <\/b> Night<br\/> <b>Scan: <\/b> 0.5 km<br\/> <b>Track: <\/b> 0.41 km<br\/> <b>FRP: <\/b> 33.05 MW<br\/> <b>Brightness: <\/b> 339.74 K" }, "geometry": { "type": "Point", "coordinates": [ -155.28523, 19.40312, 0.0 ] } },
{ "type": "Feature", "properties": { "Name": "Fire Detection Centroid ", "Description": "<b>Latitude: <\/b> 19.40598<br\/>  <b>Longitude: <\/b> -155.2798<br\/>  <b>Detection Time: <\/b> 2023-01-29 12:14 UTC<br\/>  <b>Sensor: <\/b> NOAA-20 VIIRS<br\/> <b>Confidence: <\/b> Nominal<br\/>  <b>Day\/Night: <\/b> Night<br\/> <b>Scan: <\/b> 0.5 km<br\/> <b>Track: <\/b> 0.41 km<br\/> <b>FRP: <\/b> 33.05 MW<br\/> <b>Brightness: <\/b> 332.83 K" }, "geometry": { "type": "Point", "coordinates": [ -155.2798, 19.40598, 0.0 ] } },
{ "type": "Feature", "properties": { "Name": "Fire Detection Centroid ", "Description": "<b>Latitude: <\/b> 19.40229<br\/>  <b>Longitude: <\/b> -155.28056<br\/>  <b>Detection Time: <\/b> 2023-01-29 12:14 UTC<br\/>  <b>Sensor: <\/b> NOAA-20 VIIRS<br\/> <b>Confidence: <\/b> Nominal<br\/>  <b>Day\/Night: <\/b> Night<br\/> <b>Scan: <\/b> 0.5 km<br\/> <b>Track: <\/b> 0.41 km<br\/> <b>FRP: <\/b> 33.05 MW<br\/> <b>Brightness: <\/b> 341.79 K" }, "geometry": { "type": "Point", "coordinates": [ -155.28056, 19.40229, 0.0 ] } },
{ "type": "Feature", "properties": { "Name": "Fire Detection Centroid ", "Description": "<b>Latitude: <\/b> 19.40682<br\/>  <b>Longitude: <\/b> -155.28453<br\/>  <b>Detection Time: <\/b> 2023-01-29 12:14 UTC<br\/>  <b>Sensor: <\/b> NOAA-20 VIIRS<br\/> <b>Confidence: <\/b> Nominal<br\/>  <b>Day\/Night: <\/b> Night<br\/> <b>Scan: <\/b> 0.5 km<br\/> <b>Track: <\/b> 0.41 km<br\/> <b>FRP: <\/b> 33.05 MW<br\/> <b>Brightness: <\/b> 353.71 K" }, "geometry": { "type": "Point", "coordinates": [ -155.28453, 19.40682, 0.0 ] } },
{ "type": "Feature", "properties": { "Name": "Fire Detection Centroid ", "Description": "<b>Latitude: <\/b> 19.40767<br\/>  <b>Longitude: <\/b> -155.28929<br\/>  <b>Detection Time: <\/b> 2023-01-29 12:14 UTC<br\/>  <b>Sensor: <\/b> NOAA-20 VIIRS<br\/> <b>Confidence: <\/b> Nominal<br\/>  <b>Day\/Night: <\/b> Night<br\/> <b>Scan: <\/b> 0.5 km<br\/> <b>Track: <\/b> 0.41 km<br\/> <b>FRP: <\/b> 15.52 MW<br\/> <b>Brightness: <\/b> 339.39 K" }, "geometry": { "type": "Point", "coordinates": [ -155.28929, 19.40767, 0.0 ] } },
{ "type": "Feature", "properties": { "Name": "Fire Detection Centroid ", "Description": "<b>Latitude: <\/b> 19.40968<br\/>  <b>Longitude: <\/b> -155.2791<br\/>  <b>Detection Time: <\/b> 2023-01-29 12:14 UTC<br\/>  <b>Sensor: <\/b> NOAA-20 VIIRS<br\/> <b>Confidence: <\/b> Nominal<br\/>  <b>Day\/Night: <\/b> Night<br\/> <b>Scan: <\/b> 0.5 km<br\/> <b>Track: <\/b> 0.41 km<br\/> <b>FRP: <\/b> 12.61 MW<br\/> <b>Brightness: <\/b> 350.7 K" }, "geometry": { "type": "Point", "coordinates": [ -155.2791, 19.40968, 0.0 ] } }
]
}
