{
"type": "FeatureCollection",
"crs": { "type": "name", "properties": { "name": "urn:ogc:def:crs:OGC:1.3:CRS84" } },
"features": [
{ "type": "Feature", "properties": { "Name": "Fire Detection Centroid ", "Description": "<b>Latitude: <\/b> 34.28425<br\/>  <b>Longitude: <\/b> -119.27669<br\/>  <b>Detection Time: <\/b> 2024-03-29 10:44 UTC<br\/>  <b>Sensor: <\/b> NOAA-20 VIIRS<br\/> <b>Confidence: <\/b> Nominal<br\/>  <b>Day\/Night: <\/b> Night<br\/> <b>Scan: <\/b> 0.6 km<br\/> <b>Track: <\/b> 0.7 km<br\/> <b>FRP: <\/b> 1.1 MW<br\/> <b>Brightness: <\/b> 295.73 K" }, "geometry": { "type": "Point", "coordinates": [ -119.27669, 34.28425, 0.0 ] } },
{ "type": "Feature", "properties": { "Name": "Fire Detection Centroid ", "Description": "<b>Latitude: <\/b> 34.62934<br\/>  <b>Longitude: <\/b> -117.32761<br\/>  <b>Detection Time: <\/b> 2024-03-29 10:44 UTC<br\/>  <b>Sensor: <\/b> NOAA-20 VIIRS<br\/> <b>Confidence: <\/b> Nominal<br\/>  <b>Day\/Night: <\/b> Night<br\/> <b>Scan: <\/b> 0.7 km<br\/> <b>Track: <\/b> 0.8 km<br\/> <b>FRP: <\/b> 2.49 MW<br\/> <b>Brightness: <\/b> 300.03 K" }, "geometry": { "type": "Point", "coordinates": [ -117.32761, 34.62934, 0.0 ] } },
{ "type": "Feature", "properties": { "Name": "Fire Detection Centroid ", "Description": "<b>Latitude: <\/b> 33.73708<br\/>  <b>Longitude: <\/b> -118.27943<br\/>  <b>Detection Time: <\/b> 2024-03-29 10:44 UTC<br\/>  <b>Sensor: <\/b> NOAA-20 VIIRS<br\/> <b>Confidence: <\/b> Nominal<br\/>  <b>Day\/Night: <\/b> Night<br\/> <b>Scan: <\/b> 0.7 km<br\/> <b>Track: <\/b> 0.7 km<br\/> <b>FRP: <\/b> 1.21 MW<br\/> <b>Brightness: <\/b> 295.22 K" }, "geometry": { "type": "Point", "coordinates": [ -118.27943, 33.73708, 0.0 ] } },
{ "type": "Feature", "properties": { "Name": "Fire Detection Centroid ", "Description": "<b>Latitude: <\/b> 33.76016<br\/>  <b>Longitude: <\/b> -118.3802<br\/>  <b>Detection Time: <\/b> 2024-03-29 10:44 UTC<br\/>  <b>Sensor: <\/b> NOAA-20 VIIRS<br\/> <b>Confidence: <\/b> Nominal<br\/>  <b>Day\/Night: <\/b> Night<br\/> <b>Scan: <\/b> 0.7 km<br\/> <b>Track: <\/b> 0.7 km<br\/> <b>FRP: <\/b> 1.86 MW<br\/> <b>Brightness: <\/b> 298.58 K" }, "geometry": { "type": "Point", "coordinates": [ -118.3802, 33.76016, 0.0 ] } },
{ "type": "Feature", "properties": { "Name": "Fire Detection Centroid ", "Description": "<b>Latitude: <\/b> 34.31467<br\/>  <b>Longitude: <\/b> -119.26712<br\/>  <b>Detection Time: <\/b> 2024-03-29 10:43 UTC<br\/>  <b>Sensor: <\/b> NOAA-20 VIIRS<br\/> <b>Confidence: <\/b> Nominal<br\/>  <b>Day\/Night: <\/b> Night<br\/> <b>Scan: <\/b> 0.59 km<br\/> <b>Track: <\/b> 0.7 km<br\/> <b>FRP: <\/b> 1.1 MW<br\/> <b>Brightness: <\/b> 295.73 K" }, "geometry": { "type": "Point", "coordinates": [ -119.26712, 34.31467, 0.0 ] } },
{ "type": "Feature", "properties": { "Name": "Fire Detection Centroid ", "Description": "<b>Latitude: <\/b> 34.60831<br\/>  <b>Longitude: <\/b> -117.33578<br\/>  <b>Detection Time: <\/b> 2024-03-29 10:43 UTC<br\/>  <b>Sensor: <\/b> NOAA-20 VIIRS<br\/> <b>Confidence: <\/b> Nominal<br\/>  <b>Day\/Night: <\/b> Night<br\/> <b>Scan: <\/b> 0.73 km<br\/> <b>Track: <\/b> 0.76 km<br\/> <b>FRP: <\/b> 2.49 MW<br\/> <b>Brightness: <\/b> 300.03 K" }, "geometry": { "type": "Point", "coordinates": [ -117.33578, 34.60831, 0.0 ] } },
{ "type": "Feature", "properties": { "Name": "Fire Detection Centroid ", "Description": "<b>Latitude: <\/b> 33.82025<br\/>  <b>Longitude: <\/b> -118.24455<br\/>  <b>Detection Time: <\/b> 2024-03-29 10:43 UTC<br\/>  <b>Sensor: <\/b> NOAA-20 VIIRS<br\/> <b>Confidence: <\/b> Nominal<br\/>  <b>Day\/Night: <\/b> Night<br\/> <b>Scan: <\/b> 0.69 km<br\/> <b>Track: <\/b> 0.74 km<br\/> <b>FRP: <\/b> 1.24 MW<br\/> <b>Brightness: <\/b> 295.22 K" }, "geometry": { "type": "Point", "coordinates": [ -118.24455, 33.82025, 0.0 ] } },
{ "type": "Feature", "properties": { "Name": "Fire Detection Centroid ", "Description": "<b>Latitude: <\/b> 33.85356<br\/>  <b>Longitude: <\/b> -118.33257<br\/>  <b>Detection Time: <\/b> 2024-03-29 10:43 UTC<br\/>  <b>Sensor: <\/b> NOAA-20 VIIRS<br\/> <b>Confidence: <\/b> Nominal<br\/>  <b>Day\/Night: <\/b> Night<br\/> <b>Scan: <\/b> 0.68 km<br\/> <b>Track: <\/b> 0.74 km<br\/> <b>FRP: <\/b> 1.87 MW<br\/> <b>Brightness: <\/b> 298.58 K" }, "geometry": { "type": "Point", "coordinates": [ -118.33257, 33.85356, 0.0 ] } }
]
}
