{
"type": "FeatureCollection",
"crs": { "type": "name", "properties": { "name": "urn:ogc:def:crs:OGC:1.3:CRS84" } },
"features": [
{ "type": "Feature", "properties": { "Name": "Fire Detection Centroid ", "Description": "<b>Latitude: <\/b> 20.86286<br\/>  <b>Longitude: <\/b> -156.42108<br\/>  <b>Detection Time: <\/b> 2024-02-08 11:42 UTC<br\/>  <b>Sensor: <\/b> NOAA-20 VIIRS<br\/> <b>Confidence: <\/b> Nominal<br\/>  <b>Day\/Night: <\/b> Night<br\/> <b>Scan: <\/b> 0.4 km<br\/> <b>Track: <\/b> 0.44 km<br\/> <b>FRP: <\/b> 0.39 MW<br\/> <b>Brightness: <\/b> 299.19 K" }, "geometry": { "type": "Point", "coordinates": [ -156.42108, 20.86286, 0.0 ] } },
{ "type": "Feature", "properties": { "Name": "Fire Detection Centroid ", "Description": "<b>Latitude: <\/b> 20.77793<br\/>  <b>Longitude: <\/b> -156.43266<br\/>  <b>Detection Time: <\/b> 2024-02-08 11:42 UTC<br\/>  <b>Sensor: <\/b> NOAA-20 VIIRS<br\/> <b>Confidence: <\/b> Nominal<br\/>  <b>Day\/Night: <\/b> Night<br\/> <b>Scan: <\/b> 0.4 km<br\/> <b>Track: <\/b> 0.4 km<br\/> <b>FRP: <\/b> 0.39 MW<br\/> <b>Brightness: <\/b> 299.19 K" }, "geometry": { "type": "Point", "coordinates": [ -156.43266, 20.77793, 0.0 ] } }
]
}
