{
"type": "FeatureCollection",
"crs": { "type": "name", "properties": { "name": "urn:ogc:def:crs:OGC:1.3:CRS84" } },
"features": [
{ "type": "Feature", "properties": { "Name": "Fire Detection Centroid ", "Description": "<b>Latitude: <\/b> 39.06318<br\/>  <b>Longitude: <\/b> -122.04031<br\/>  <b>Detection Time: <\/b> 2024-05-15 22:16 UTC<br\/>  <b>Sensor: <\/b> NOAA-20 VIIRS<br\/> <b>Confidence: <\/b> Nominal<br\/>  <b>Day\/Night: <\/b> Day<br\/> <b>Scan: <\/b> 0.79 km<br\/> <b>Track: <\/b> 0.78 km<br\/> <b>FRP: <\/b> 6.69 MW<br\/> <b>Brightness: <\/b> 339.86 K" }, "geometry": { "type": "Point", "coordinates": [ -122.04031, 39.06318, 0.0 ] } },
{ "type": "Feature", "properties": { "Name": "Fire Detection Centroid ", "Description": "<b>Latitude: <\/b> 38.92263<br\/>  <b>Longitude: <\/b> -122.06178<br\/>  <b>Detection Time: <\/b> 2024-05-15 22:16 UTC<br\/>  <b>Sensor: <\/b> NOAA-20 VIIRS<br\/> <b>Confidence: <\/b> Nominal<br\/>  <b>Day\/Night: <\/b> Day<br\/> <b>Scan: <\/b> 0.79 km<br\/> <b>Track: <\/b> 0.78 km<br\/> <b>FRP: <\/b> 6.49 MW<br\/> <b>Brightness: <\/b> 340.56 K" }, "geometry": { "type": "Point", "coordinates": [ -122.06178, 38.92263, 0.0 ] } },
{ "type": "Feature", "properties": { "Name": "Fire Detection Centroid ", "Description": "<b>Latitude: <\/b> 38.92373<br\/>  <b>Longitude: <\/b> -122.06157<br\/>  <b>Detection Time: <\/b> 2024-05-15 22:16 UTC<br\/>  <b>Sensor: <\/b> NOAA-20 VIIRS<br\/> <b>Confidence: <\/b> Nominal<br\/>  <b>Day\/Night: <\/b> Day<br\/> <b>Scan: <\/b> 0.79 km<br\/> <b>Track: <\/b> 0.78 km<br\/> <b>FRP: <\/b> 4.53 MW<br\/> <b>Brightness: <\/b> 335.71 K" }, "geometry": { "type": "Point", "coordinates": [ -122.06157, 38.92373, 0.0 ] } },
{ "type": "Feature", "properties": { "Name": "Fire Detection Centroid ", "Description": "<b>Latitude: <\/b> 38.97525<br\/>  <b>Longitude: <\/b> -122.06049<br\/>  <b>Detection Time: <\/b> 2024-05-15 22:15 UTC<br\/>  <b>Sensor: <\/b> NOAA-20 VIIRS<br\/> <b>Confidence: <\/b> Nominal<br\/>  <b>Day\/Night: <\/b> Day<br\/> <b>Scan: <\/b> 0.8 km<br\/> <b>Track: <\/b> 0.8 km<br\/> <b>FRP: <\/b> 4.52 MW<br\/> <b>Brightness: <\/b> 335.71 K" }, "geometry": { "type": "Point", "coordinates": [ -122.06049, 38.97525, 0.0 ] } },
{ "type": "Feature", "properties": { "Name": "Fire Detection Centroid ", "Description": "<b>Latitude: <\/b> 39.04198<br\/>  <b>Longitude: <\/b> -122.04104<br\/>  <b>Detection Time: <\/b> 2024-05-15 22:15 UTC<br\/>  <b>Sensor: <\/b> NOAA-20 VIIRS<br\/> <b>Confidence: <\/b> Nominal<br\/>  <b>Day\/Night: <\/b> Day<br\/> <b>Scan: <\/b> 0.8 km<br\/> <b>Track: <\/b> 0.8 km<br\/> <b>FRP: <\/b> 6.69 MW<br\/> <b>Brightness: <\/b> 339.86 K" }, "geometry": { "type": "Point", "coordinates": [ -122.04104, 39.04198, 0.0 ] } },
{ "type": "Feature", "properties": { "Name": "Fire Detection Centroid ", "Description": "<b>Latitude: <\/b> 38.77068<br\/>  <b>Longitude: <\/b> -122.06362<br\/>  <b>Detection Time: <\/b> 2024-05-15 22:15 UTC<br\/>  <b>Sensor: <\/b> NOAA-20 VIIRS<br\/> <b>Confidence: <\/b> Nominal<br\/>  <b>Day\/Night: <\/b> Day<br\/> <b>Scan: <\/b> 0.8 km<br\/> <b>Track: <\/b> 0.8 km<br\/> <b>FRP: <\/b> 6.49 MW<br\/> <b>Brightness: <\/b> 340.56 K" }, "geometry": { "type": "Point", "coordinates": [ -122.06362, 38.77068, 0.0 ] } }
]
}
