{
"type": "FeatureCollection",
"crs": { "type": "name", "properties": { "name": "urn:ogc:def:crs:OGC:1.3:CRS84" } },
"features": [
{ "type": "Feature", "properties": { "Name": "Fire Detection Centroid ", "Description": "<b>Latitude: <\/b> 19.72766<br\/>  <b>Longitude: <\/b> -155.64539<br\/>  <b>Detection Time: <\/b> 2022-08-01 23:20 UTC<br\/>  <b>Sensor: <\/b> NOAA-20 VIIRS<br\/> <b>Confidence: <\/b> Low<br\/>  <b>Day\/Night: <\/b> Day<br\/> <b>Scan: <\/b> 0.5 km<br\/> <b>Track: <\/b> 0.41 km<br\/> <b>FRP: <\/b> 17.03 MW<br\/> <b>Brightness: <\/b> 349.66 K" }, "geometry": { "type": "Point", "coordinates": [ -155.64539, 19.72766, 0.0 ] } },
{ "type": "Feature", "properties": { "Name": "Fire Detection Centroid ", "Description": "<b>Latitude: <\/b> 19.41069<br\/>  <b>Longitude: <\/b> -155.28102<br\/>  <b>Detection Time: <\/b> 2022-08-01 23:18 UTC<br\/>  <b>Sensor: <\/b> NOAA-20 VIIRS<br\/> <b>Confidence: <\/b> Low<br\/>  <b>Day\/Night: <\/b> Day<br\/> <b>Scan: <\/b> 0.49 km<br\/> <b>Track: <\/b> 0.4 km<br\/> <b>FRP: <\/b> 29.81 MW<br\/> <b>Brightness: <\/b> 350.24 K" }, "geometry": { "type": "Point", "coordinates": [ -155.28102, 19.41069, 0.0 ] } },
{ "type": "Feature", "properties": { "Name": "Fire Detection Centroid ", "Description": "<b>Latitude: <\/b> 19.4099<br\/>  <b>Longitude: <\/b> -155.28551<br\/>  <b>Detection Time: <\/b> 2022-08-01 23:18 UTC<br\/>  <b>Sensor: <\/b> NOAA-20 VIIRS<br\/> <b>Confidence: <\/b> Nominal<br\/>  <b>Day\/Night: <\/b> Day<br\/> <b>Scan: <\/b> 0.49 km<br\/> <b>Track: <\/b> 0.4 km<br\/> <b>FRP: <\/b> 80.04 MW<br\/> <b>Brightness: <\/b> 343.08 K" }, "geometry": { "type": "Point", "coordinates": [ -155.28551, 19.4099, 0.0 ] } },
{ "type": "Feature", "properties": { "Name": "Fire Detection Centroid ", "Description": "<b>Latitude: <\/b> 19.41148<br\/>  <b>Longitude: <\/b> -155.27649<br\/>  <b>Detection Time: <\/b> 2022-08-01 23:18 UTC<br\/>  <b>Sensor: <\/b> NOAA-20 VIIRS<br\/> <b>Confidence: <\/b> Nominal<br\/>  <b>Day\/Night: <\/b> Day<br\/> <b>Scan: <\/b> 0.49 km<br\/> <b>Track: <\/b> 0.4 km<br\/> <b>FRP: <\/b> 29.81 MW<br\/> <b>Brightness: <\/b> 338.61 K" }, "geometry": { "type": "Point", "coordinates": [ -155.27649, 19.41148, 0.0 ] } },
{ "type": "Feature", "properties": { "Name": "Fire Detection Centroid ", "Description": "<b>Latitude: <\/b> 19.41435<br\/>  <b>Longitude: <\/b> -155.28166<br\/>  <b>Detection Time: <\/b> 2022-08-01 23:18 UTC<br\/>  <b>Sensor: <\/b> NOAA-20 VIIRS<br\/> <b>Confidence: <\/b> Nominal<br\/>  <b>Day\/Night: <\/b> Day<br\/> <b>Scan: <\/b> 0.49 km<br\/> <b>Track: <\/b> 0.4 km<br\/> <b>FRP: <\/b> 11.44 MW<br\/> <b>Brightness: <\/b> 342.93 K" }, "geometry": { "type": "Point", "coordinates": [ -155.28166, 19.41435, 0.0 ] } },
{ "type": "Feature", "properties": { "Name": "Fire Detection Centroid ", "Description": "<b>Latitude: <\/b> 19.40545<br\/>  <b>Longitude: <\/b> -155.28938<br\/>  <b>Detection Time: <\/b> 2022-08-01 23:18 UTC<br\/>  <b>Sensor: <\/b> NOAA-20 VIIRS<br\/> <b>Confidence: <\/b> Nominal<br\/>  <b>Day\/Night: <\/b> Day<br\/> <b>Scan: <\/b> 0.49 km<br\/> <b>Track: <\/b> 0.4 km<br\/> <b>FRP: <\/b> 80.04 MW<br\/> <b>Brightness: <\/b> 346.48 K" }, "geometry": { "type": "Point", "coordinates": [ -155.28938, 19.40545, 0.0 ] } },
{ "type": "Feature", "properties": { "Name": "Fire Detection Centroid ", "Description": "<b>Latitude: <\/b> 19.40624<br\/>  <b>Longitude: <\/b> -155.28488<br\/>  <b>Detection Time: <\/b> 2022-08-01 23:18 UTC<br\/>  <b>Sensor: <\/b> NOAA-20 VIIRS<br\/> <b>Confidence: <\/b> High<br\/>  <b>Day\/Night: <\/b> Day<br\/> <b>Scan: <\/b> 0.49 km<br\/> <b>Track: <\/b> 0.4 km<br\/> <b>FRP: <\/b> 80.04 MW<br\/> <b>Brightness: <\/b> 367 K" }, "geometry": { "type": "Point", "coordinates": [ -155.28488, 19.40624, 0.0 ] } },
{ "type": "Feature", "properties": { "Name": "Fire Detection Centroid ", "Description": "<b>Latitude: <\/b> 19.40338<br\/>  <b>Longitude: <\/b> -155.27963<br\/>  <b>Detection Time: <\/b> 2022-08-01 23:18 UTC<br\/>  <b>Sensor: <\/b> NOAA-20 VIIRS<br\/> <b>Confidence: <\/b> Nominal<br\/>  <b>Day\/Night: <\/b> Day<br\/> <b>Scan: <\/b> 0.49 km<br\/> <b>Track: <\/b> 0.4 km<br\/> <b>FRP: <\/b> 10.67 MW<br\/> <b>Brightness: <\/b> 340.14 K" }, "geometry": { "type": "Point", "coordinates": [ -155.27963, 19.40338, 0.0 ] } },
{ "type": "Feature", "properties": { "Name": "Fire Detection Centroid ", "Description": "<b>Latitude: <\/b> 19.40259<br\/>  <b>Longitude: <\/b> -155.28418<br\/>  <b>Detection Time: <\/b> 2022-08-01 23:18 UTC<br\/>  <b>Sensor: <\/b> NOAA-20 VIIRS<br\/> <b>Confidence: <\/b> Nominal<br\/>  <b>Day\/Night: <\/b> Day<br\/> <b>Scan: <\/b> 0.49 km<br\/> <b>Track: <\/b> 0.4 km<br\/> <b>FRP: <\/b> 24.51 MW<br\/> <b>Brightness: <\/b> 355.18 K" }, "geometry": { "type": "Point", "coordinates": [ -155.28418, 19.40259, 0.0 ] } }
]
}
