{
"type": "FeatureCollection",
"crs": { "type": "name", "properties": { "name": "urn:ogc:def:crs:OGC:1.3:CRS84" } },
"features": [
{ "type": "Feature", "properties": { "Name": "Fire Detection Centroid ", "Description": "<b>Latitude: <\/b> 48.18699<br\/>  <b>Longitude: <\/b> -64.92416<br\/>  <b>Detection Time: <\/b> 2022-08-01 05:14 UTC<br\/>  <b>Sensor: <\/b> NOAA-20 VIIRS<br\/> <b>Confidence: <\/b> Nominal<br\/>  <b>Day\/Night: <\/b> Night<br\/> <b>Scan: <\/b> 0.6 km<br\/> <b>Track: <\/b> 0.7 km<br\/> <b>FRP: <\/b> 0.96 MW<br\/> <b>Brightness: <\/b> 301.1 K" }, "geometry": { "type": "Point", "coordinates": [ -64.92416, 48.18699, 0.0 ] } }
]
}
