{
"type": "FeatureCollection",
"crs": { "type": "name", "properties": { "name": "urn:ogc:def:crs:OGC:1.3:CRS84" } },
"features": [
{ "type": "Feature", "properties": { "Name": "Fire Detection Centroid ", "Description": "<b>Latitude: <\/b> 45.21338<br\/>  <b>Longitude: <\/b> -65.98026<br\/>  <b>Detection Time: <\/b> 2022-10-30 05:27 UTC<br\/>  <b>Sensor: <\/b> NOAA-20 VIIRS<br\/> <b>Confidence: <\/b> Nominal<br\/>  <b>Day\/Night: <\/b> Night<br\/> <b>Scan: <\/b> 0.4 km<br\/> <b>Track: <\/b> 0.6 km<br\/> <b>FRP: <\/b> 1.95 MW<br\/> <b>Brightness: <\/b> 318.46 K" }, "geometry": { "type": "Point", "coordinates": [ -65.98026, 45.21338, 0.0 ] } }
]
}
