{
"type": "FeatureCollection",
"crs": { "type": "name", "properties": { "name": "urn:ogc:def:crs:OGC:1.3:CRS84" } },
"features": [
{ "type": "Feature", "properties": { "Name": "Fire Detection Centroid ", "Description": "<b>Latitude: <\/b> 21.46503<br\/>  <b>Longitude: <\/b> -158.15323<br\/>  <b>Detection Time: <\/b> 2023-11-14 23:07 UTC<br\/>  <b>Sensor: <\/b> NOAA-20 VIIRS<br\/> <b>Confidence: <\/b> Nominal<br\/>  <b>Day\/Night: <\/b> Day<br\/> <b>Scan: <\/b> 0.34 km<br\/> <b>Track: <\/b> 0.56 km<br\/> <b>FRP: <\/b> 2.11 MW<br\/> <b>Brightness: <\/b> 327.29 K" }, "geometry": { "type": "Point", "coordinates": [ -158.15323, 21.46503, 0.0 ] } },
{ "type": "Feature", "properties": { "Name": "Fire Detection Centroid ", "Description": "<b>Latitude: <\/b> 21.46431<br\/>  <b>Longitude: <\/b> -158.15662<br\/>  <b>Detection Time: <\/b> 2023-11-14 23:07 UTC<br\/>  <b>Sensor: <\/b> NOAA-20 VIIRS<br\/> <b>Confidence: <\/b> Nominal<br\/>  <b>Day\/Night: <\/b> Day<br\/> <b>Scan: <\/b> 0.34 km<br\/> <b>Track: <\/b> 0.56 km<br\/> <b>FRP: <\/b> 2.11 MW<br\/> <b>Brightness: <\/b> 334.25 K" }, "geometry": { "type": "Point", "coordinates": [ -158.15662, 21.46431, 0.0 ] } },
{ "type": "Feature", "properties": { "Name": "Fire Detection Centroid ", "Description": "<b>Latitude: <\/b> 21.4631<br\/>  <b>Longitude: <\/b> -158.15788<br\/>  <b>Detection Time: <\/b> 2023-11-14 23:07 UTC<br\/>  <b>Sensor: <\/b> NOAA-20 VIIRS<br\/> <b>Confidence: <\/b> Nominal<br\/>  <b>Day\/Night: <\/b> Day<br\/> <b>Scan: <\/b> 0.3 km<br\/> <b>Track: <\/b> 0.6 km<br\/> <b>FRP: <\/b> 2.11 MW<br\/> <b>Brightness: <\/b> 334.25 K" }, "geometry": { "type": "Point", "coordinates": [ -158.15788, 21.4631, 0.0 ] } },
{ "type": "Feature", "properties": { "Name": "Fire Detection Centroid ", "Description": "<b>Latitude: <\/b> 21.46381<br\/>  <b>Longitude: <\/b> -158.15454<br\/>  <b>Detection Time: <\/b> 2023-11-14 23:07 UTC<br\/>  <b>Sensor: <\/b> NOAA-20 VIIRS<br\/> <b>Confidence: <\/b> Nominal<br\/>  <b>Day\/Night: <\/b> Day<br\/> <b>Scan: <\/b> 0.3 km<br\/> <b>Track: <\/b> 0.6 km<br\/> <b>FRP: <\/b> 2.11 MW<br\/> <b>Brightness: <\/b> 327.29 K" }, "geometry": { "type": "Point", "coordinates": [ -158.15454, 21.46381, 0.0 ] } },
{ "type": "Feature", "properties": { "Name": "Fire Detection Centroid ", "Description": "<b>Latitude: <\/b> 19.77582<br\/>  <b>Longitude: <\/b> -155.61618<br\/>  <b>Detection Time: <\/b> 2023-11-14 23:06 UTC<br\/>  <b>Sensor: <\/b> NOAA-20 VIIRS<br\/> <b>Confidence: <\/b> Nominal<br\/>  <b>Day\/Night: <\/b> Day<br\/> <b>Scan: <\/b> 0.5 km<br\/> <b>Track: <\/b> 0.5 km<br\/> <b>FRP: <\/b> 3.42 MW<br\/> <b>Brightness: <\/b> 325.35 K" }, "geometry": { "type": "Point", "coordinates": [ -155.61618, 19.77582, 0.0 ] } },
{ "type": "Feature", "properties": { "Name": "Fire Detection Centroid ", "Description": "<b>Latitude: <\/b> 19.77681<br\/>  <b>Longitude: <\/b> -155.6153<br\/>  <b>Detection Time: <\/b> 2023-11-14 23:05 UTC<br\/>  <b>Sensor: <\/b> NOAA-20 VIIRS<br\/> <b>Confidence: <\/b> Nominal<br\/>  <b>Day\/Night: <\/b> Day<br\/> <b>Scan: <\/b> 0.51 km<br\/> <b>Track: <\/b> 0.49 km<br\/> <b>FRP: <\/b> 3.43 MW<br\/> <b>Brightness: <\/b> 325.35 K" }, "geometry": { "type": "Point", "coordinates": [ -155.6153, 19.77681, 0.0 ] } }
]
}
