{
"type": "FeatureCollection",
"crs": { "type": "name", "properties": { "name": "urn:ogc:def:crs:OGC:1.3:CRS84" } },
"features": [
{ "type": "Feature", "properties": { "Name": "Fire Detection Centroid ", "Description": "<b>Latitude: <\/b> 19.40844<br\/>  <b>Longitude: <\/b> -155.28035<br\/>  <b>Detection Time: <\/b> 2023-03-07 12:21 UTC<br\/>  <b>Sensor: <\/b> NOAA-20 VIIRS<br\/> <b>Confidence: <\/b> Nominal<br\/>  <b>Day\/Night: <\/b> Night<br\/> <b>Scan: <\/b> 0.41 km<br\/> <b>Track: <\/b> 0.45 km<br\/> <b>FRP: <\/b> 2.13 MW<br\/> <b>Brightness: <\/b> 304.09 K" }, "geometry": { "type": "Point", "coordinates": [ -155.28035, 19.40844, 0.0 ] } },
{ "type": "Feature", "properties": { "Name": "Fire Detection Centroid ", "Description": "<b>Latitude: <\/b> 19.40511<br\/>  <b>Longitude: <\/b> -155.28502<br\/>  <b>Detection Time: <\/b> 2023-03-07 12:21 UTC<br\/>  <b>Sensor: <\/b> NOAA-20 VIIRS<br\/> <b>Confidence: <\/b> Nominal<br\/>  <b>Day\/Night: <\/b> Night<br\/> <b>Scan: <\/b> 0.41 km<br\/> <b>Track: <\/b> 0.45 km<br\/> <b>FRP: <\/b> 2.13 MW<br\/> <b>Brightness: <\/b> 305.24 K" }, "geometry": { "type": "Point", "coordinates": [ -155.28502, 19.40511, 0.0 ] } },
{ "type": "Feature", "properties": { "Name": "Fire Detection Centroid ", "Description": "<b>Latitude: <\/b> 19.40585<br\/>  <b>Longitude: <\/b> -155.28893<br\/>  <b>Detection Time: <\/b> 2023-03-07 12:21 UTC<br\/>  <b>Sensor: <\/b> NOAA-20 VIIRS<br\/> <b>Confidence: <\/b> Nominal<br\/>  <b>Day\/Night: <\/b> Night<br\/> <b>Scan: <\/b> 0.41 km<br\/> <b>Track: <\/b> 0.45 km<br\/> <b>FRP: <\/b> 2.41 MW<br\/> <b>Brightness: <\/b> 311.93 K" }, "geometry": { "type": "Point", "coordinates": [ -155.28893, 19.40585, 0.0 ] } }
]
}
