{
"type": "FeatureCollection",
"crs": { "type": "name", "properties": { "name": "urn:ogc:def:crs:OGC:1.3:CRS84" } },
"features": [
{ "type": "Feature", "properties": { "Name": "Fire Detection Centroid ", "Description": "<b>Latitude: <\/b> 35.25976<br\/>  <b>Longitude: <\/b> -79.01154<br\/>  <b>Detection Time: <\/b> 2024-01-20 17:10 UTC<br\/>  <b>Sensor: <\/b> NOAA-20 VIIRS<br\/> <b>Confidence: <\/b> Nominal<br\/>  <b>Day\/Night: <\/b> Day<br\/> <b>Scan: <\/b> 0.7 km<br\/> <b>Track: <\/b> 0.8 km<br\/> <b>FRP: <\/b> 12.37 MW<br\/> <b>Brightness: <\/b> 355.16 K" }, "geometry": { "type": "Point", "coordinates": [ -79.01154, 35.25976, 0.0 ] } },
{ "type": "Feature", "properties": { "Name": "Fire Detection Centroid ", "Description": "<b>Latitude: <\/b> 35.26197<br\/>  <b>Longitude: <\/b> -79.00434<br\/>  <b>Detection Time: <\/b> 2024-01-20 17:10 UTC<br\/>  <b>Sensor: <\/b> NOAA-20 VIIRS<br\/> <b>Confidence: <\/b> Nominal<br\/>  <b>Day\/Night: <\/b> Day<br\/> <b>Scan: <\/b> 0.7 km<br\/> <b>Track: <\/b> 0.8 km<br\/> <b>FRP: <\/b> 12.37 MW<br\/> <b>Brightness: <\/b> 328.06 K" }, "geometry": { "type": "Point", "coordinates": [ -79.00434, 35.26197, 0.0 ] } },
{ "type": "Feature", "properties": { "Name": "Fire Detection Centroid ", "Description": "<b>Latitude: <\/b> 18.82313<br\/>  <b>Longitude: <\/b> -72.03253<br\/>  <b>Detection Time: <\/b> 2024-01-20 17:05 UTC<br\/>  <b>Sensor: <\/b> NOAA-20 VIIRS<br\/> <b>Confidence: <\/b> Nominal<br\/>  <b>Day\/Night: <\/b> Day<br\/> <b>Scan: <\/b> 0.7 km<br\/> <b>Track: <\/b> 0.8 km<br\/> <b>FRP: <\/b> 4.31 MW<br\/> <b>Brightness: <\/b> 329.58 K" }, "geometry": { "type": "Point", "coordinates": [ -72.03253, 18.82313, 0.0 ] } },
{ "type": "Feature", "properties": { "Name": "Fire Detection Centroid ", "Description": "<b>Latitude: <\/b> 18.90561<br\/>  <b>Longitude: <\/b> -71.43496<br\/>  <b>Detection Time: <\/b> 2024-01-20 17:05 UTC<br\/>  <b>Sensor: <\/b> NOAA-20 VIIRS<br\/> <b>Confidence: <\/b> Nominal<br\/>  <b>Day\/Night: <\/b> Day<br\/> <b>Scan: <\/b> 0.7 km<br\/> <b>Track: <\/b> 0.7 km<br\/> <b>FRP: <\/b> 5.62 MW<br\/> <b>Brightness: <\/b> 337.55 K" }, "geometry": { "type": "Point", "coordinates": [ -71.43496, 18.90561, 0.0 ] } },
{ "type": "Feature", "properties": { "Name": "Fire Detection Centroid ", "Description": "<b>Latitude: <\/b> 19.0288<br\/>  <b>Longitude: <\/b> -72.0783<br\/>  <b>Detection Time: <\/b> 2024-01-20 17:05 UTC<br\/>  <b>Sensor: <\/b> NOAA-20 VIIRS<br\/> <b>Confidence: <\/b> Nominal<br\/>  <b>Day\/Night: <\/b> Day<br\/> <b>Scan: <\/b> 0.7 km<br\/> <b>Track: <\/b> 0.8 km<br\/> <b>FRP: <\/b> 3.69 MW<br\/> <b>Brightness: <\/b> 330.01 K" }, "geometry": { "type": "Point", "coordinates": [ -72.0783, 19.0288, 0.0 ] } },
{ "type": "Feature", "properties": { "Name": "Fire Detection Centroid ", "Description": "<b>Latitude: <\/b> 18.31732<br\/>  <b>Longitude: <\/b> -67.17742<br\/>  <b>Detection Time: <\/b> 2024-01-20 17:04 UTC<br\/>  <b>Sensor: <\/b> NOAA-20 VIIRS<br\/> <b>Confidence: <\/b> Nominal<br\/>  <b>Day\/Night: <\/b> Day<br\/> <b>Scan: <\/b> 0.4 km<br\/> <b>Track: <\/b> 0.6 km<br\/> <b>FRP: <\/b> 3.78 MW<br\/> <b>Brightness: <\/b> 350.94 K" }, "geometry": { "type": "Point", "coordinates": [ -67.17742, 18.31732, 0.0 ] } }
]
}
