{
"type": "FeatureCollection",
"crs": { "type": "name", "properties": { "name": "urn:ogc:def:crs:OGC:1.3:CRS84" } },
"features": [
{ "type": "Feature", "properties": { "Name": "Fire Detection Centroid ", "Description": "<b>Latitude: <\/b> 42.74515<br\/>  <b>Longitude: <\/b> -122.54764<br\/>  <b>Detection Time: <\/b> 2022-12-28 21:50 UTC<br\/>  <b>Sensor: <\/b> NOAA-20 VIIRS<br\/> <b>Confidence: <\/b> Nominal<br\/>  <b>Day\/Night: <\/b> Day<br\/> <b>Scan: <\/b> 0.35 km<br\/> <b>Track: <\/b> 0.57 km<br\/> <b>FRP: <\/b> 13.33 MW<br\/> <b>Brightness: <\/b> 354.2 K" }, "geometry": { "type": "Point", "coordinates": [ -122.54764, 42.74515, 0.0 ] } },
{ "type": "Feature", "properties": { "Name": "Fire Detection Centroid ", "Description": "<b>Latitude: <\/b> 44.96754<br\/>  <b>Longitude: <\/b> -123.98283<br\/>  <b>Detection Time: <\/b> 2022-12-28 21:50 UTC<br\/>  <b>Sensor: <\/b> NOAA-20 VIIRS<br\/> <b>Confidence: <\/b> Nominal<br\/>  <b>Day\/Night: <\/b> Day<br\/> <b>Scan: <\/b> 0.62 km<br\/> <b>Track: <\/b> 0.54 km<br\/> <b>FRP: <\/b> 7.77 MW<br\/> <b>Brightness: <\/b> 337.67 K" }, "geometry": { "type": "Point", "coordinates": [ -123.98283, 44.96754, 0.0 ] } },
{ "type": "Feature", "properties": { "Name": "Fire Detection Centroid ", "Description": "<b>Latitude: <\/b> 39.80375<br\/>  <b>Longitude: <\/b> -121.60696<br\/>  <b>Detection Time: <\/b> 2022-12-28 21:50 UTC<br\/>  <b>Sensor: <\/b> NOAA-20 VIIRS<br\/> <b>Confidence: <\/b> Nominal<br\/>  <b>Day\/Night: <\/b> Day<br\/> <b>Scan: <\/b> 0.37 km<br\/> <b>Track: <\/b> 0.58 km<br\/> <b>FRP: <\/b> 2.13 MW<br\/> <b>Brightness: <\/b> 327.66 K" }, "geometry": { "type": "Point", "coordinates": [ -121.60696, 39.80375, 0.0 ] } },
{ "type": "Feature", "properties": { "Name": "Fire Detection Centroid ", "Description": "<b>Latitude: <\/b> 39.80932<br\/>  <b>Longitude: <\/b> -121.60378<br\/>  <b>Detection Time: <\/b> 2022-12-28 21:50 UTC<br\/>  <b>Sensor: <\/b> NOAA-20 VIIRS<br\/> <b>Confidence: <\/b> Nominal<br\/>  <b>Day\/Night: <\/b> Day<br\/> <b>Scan: <\/b> 0.37 km<br\/> <b>Track: <\/b> 0.58 km<br\/> <b>FRP: <\/b> 4.19 MW<br\/> <b>Brightness: <\/b> 337.56 K" }, "geometry": { "type": "Point", "coordinates": [ -121.60378, 39.80932, 0.0 ] } },
{ "type": "Feature", "properties": { "Name": "Fire Detection Centroid ", "Description": "<b>Latitude: <\/b> 42.49948<br\/>  <b>Longitude: <\/b> -122.61803<br\/>  <b>Detection Time: <\/b> 2022-12-28 21:50 UTC<br\/>  <b>Sensor: <\/b> NOAA-20 VIIRS<br\/> <b>Confidence: <\/b> Nominal<br\/>  <b>Day\/Night: <\/b> Day<br\/> <b>Scan: <\/b> 0.35 km<br\/> <b>Track: <\/b> 0.57 km<br\/> <b>FRP: <\/b> 2.17 MW<br\/> <b>Brightness: <\/b> 331.88 K" }, "geometry": { "type": "Point", "coordinates": [ -122.61803, 42.49948, 0.0 ] } },
{ "type": "Feature", "properties": { "Name": "Fire Detection Centroid ", "Description": "<b>Latitude: <\/b> 42.75054<br\/>  <b>Longitude: <\/b> -122.54539<br\/>  <b>Detection Time: <\/b> 2022-12-28 21:50 UTC<br\/>  <b>Sensor: <\/b> NOAA-20 VIIRS<br\/> <b>Confidence: <\/b> Nominal<br\/>  <b>Day\/Night: <\/b> Day<br\/> <b>Scan: <\/b> 0.35 km<br\/> <b>Track: <\/b> 0.57 km<br\/> <b>FRP: <\/b> 3.78 MW<br\/> <b>Brightness: <\/b> 328.5 K" }, "geometry": { "type": "Point", "coordinates": [ -122.54539, 42.75054, 0.0 ] } },
{ "type": "Feature", "properties": { "Name": "Fire Detection Centroid ", "Description": "<b>Latitude: <\/b> 42.74537<br\/>  <b>Longitude: <\/b> -122.5433<br\/>  <b>Detection Time: <\/b> 2022-12-28 21:50 UTC<br\/>  <b>Sensor: <\/b> NOAA-20 VIIRS<br\/> <b>Confidence: <\/b> Low<br\/>  <b>Day\/Night: <\/b> Day<br\/> <b>Scan: <\/b> 0.35 km<br\/> <b>Track: <\/b> 0.57 km<br\/> <b>FRP: <\/b> 15.66 MW<br\/> <b>Brightness: <\/b> 355.97 K" }, "geometry": { "type": "Point", "coordinates": [ -122.5433, 42.74537, 0.0 ] } }
]
}
