{
"type": "FeatureCollection",
"crs": { "type": "name", "properties": { "name": "urn:ogc:def:crs:OGC:1.3:CRS84" } },
"features": [
{ "type": "Feature", "properties": { "Name": "Fire Detection Centroid ", "Description": "<b>Latitude: <\/b> 36.09528<br\/>  <b>Longitude: <\/b> -120.08453<br\/>  <b>Detection Time: <\/b> 2023-05-09 10:53 UTC<br\/>  <b>Sensor: <\/b> NOAA-20 VIIRS<br\/> <b>Confidence: <\/b> Nominal<br\/>  <b>Day\/Night: <\/b> Night<br\/> <b>Scan: <\/b> 0.62 km<br\/> <b>Track: <\/b> 0.72 km<br\/> <b>FRP: <\/b> 1.06 MW<br\/> <b>Brightness: <\/b> 303.22 K" }, "geometry": { "type": "Point", "coordinates": [ -120.08453, 36.09528, 0.0 ] } },
{ "type": "Feature", "properties": { "Name": "Fire Detection Centroid ", "Description": "<b>Latitude: <\/b> 36.09502<br\/>  <b>Longitude: <\/b> -120.08447<br\/>  <b>Detection Time: <\/b> 2023-05-09 10:53 UTC<br\/>  <b>Sensor: <\/b> NOAA-20 VIIRS<br\/> <b>Confidence: <\/b> Nominal<br\/>  <b>Day\/Night: <\/b> Night<br\/> <b>Scan: <\/b> 0.62 km<br\/> <b>Track: <\/b> 0.72 km<br\/> <b>FRP: <\/b> 0.78 MW<br\/> <b>Brightness: <\/b> 301.64 K" }, "geometry": { "type": "Point", "coordinates": [ -120.08447, 36.09502, 0.0 ] } },
{ "type": "Feature", "properties": { "Name": "Fire Detection Centroid ", "Description": "<b>Latitude: <\/b> 36.08342<br\/>  <b>Longitude: <\/b> -119.44278<br\/>  <b>Detection Time: <\/b> 2023-05-09 10:53 UTC<br\/>  <b>Sensor: <\/b> NOAA-20 VIIRS<br\/> <b>Confidence: <\/b> Nominal<br\/>  <b>Day\/Night: <\/b> Night<br\/> <b>Scan: <\/b> 0.67 km<br\/> <b>Track: <\/b> 0.74 km<br\/> <b>FRP: <\/b> 2.23 MW<br\/> <b>Brightness: <\/b> 305.48 K" }, "geometry": { "type": "Point", "coordinates": [ -119.44278, 36.08342, 0.0 ] } },
{ "type": "Feature", "properties": { "Name": "Fire Detection Centroid ", "Description": "<b>Latitude: <\/b> 49.14383<br\/>  <b>Longitude: <\/b> -123.02097<br\/>  <b>Detection Time: <\/b> 2023-05-09 10:49 UTC<br\/>  <b>Sensor: <\/b> NOAA-20 VIIRS<br\/> <b>Confidence: <\/b> Nominal<br\/>  <b>Day\/Night: <\/b> Night<br\/> <b>Scan: <\/b> 0.4 km<br\/> <b>Track: <\/b> 0.44 km<br\/> <b>FRP: <\/b> 0.65 MW<br\/> <b>Brightness: <\/b> 296.26 K" }, "geometry": { "type": "Point", "coordinates": [ -123.02097, 49.14383, 0.0 ] } }
]
}
