{
"type": "FeatureCollection",
"crs": { "type": "name", "properties": { "name": "urn:ogc:def:crs:OGC:1.3:CRS84" } },
"features": [
{ "type": "Feature", "properties": { "Name": "Fire Detection Centroid ", "Description": "<b>Latitude: <\/b> 40.91465<br\/>  <b>Longitude: <\/b> -73.85654<br\/>  <b>Detection Time: <\/b> 2024-03-03 17:05 UTC<br\/>  <b>Sensor: <\/b> NOAA-20 VIIRS<br\/> <b>Confidence: <\/b> Nominal<br\/>  <b>Day\/Night: <\/b> Day<br\/> <b>Scan: <\/b> 0.3 km<br\/> <b>Track: <\/b> 0.6 km<br\/> <b>FRP: <\/b> 2.06 MW<br\/> <b>Brightness: <\/b> 338.47 K" }, "geometry": { "type": "Point", "coordinates": [ -73.85654, 40.91465, 0.0 ] } }
]
}
