{
"type": "FeatureCollection",
"crs": { "type": "name", "properties": { "name": "urn:ogc:def:crs:OGC:1.3:CRS84" } },
"features": [
{ "type": "Feature", "properties": { "Name": "Fire Detection Centroid ", "Description": "<b>Latitude: <\/b> 46.47493<br\/>  <b>Longitude: <\/b> -84.38334<br\/>  <b>Detection Time: <\/b> 2024-03-06 06:24 UTC<br\/>  <b>Sensor: <\/b> NOAA-20 VIIRS<br\/> <b>Confidence: <\/b> Nominal<br\/>  <b>Day\/Night: <\/b> Night<br\/> <b>Scan: <\/b> 0.7 km<br\/> <b>Track: <\/b> 0.7 km<br\/> <b>FRP: <\/b> 1.83 MW<br\/> <b>Brightness: <\/b> 301.49 K" }, "geometry": { "type": "Point", "coordinates": [ -84.38334, 46.47493, 0.0 ] } },
{ "type": "Feature", "properties": { "Name": "Fire Detection Centroid ", "Description": "<b>Latitude: <\/b> 46.47503<br\/>  <b>Longitude: <\/b> -84.37408<br\/>  <b>Detection Time: <\/b> 2024-03-06 06:24 UTC<br\/>  <b>Sensor: <\/b> NOAA-20 VIIRS<br\/> <b>Confidence: <\/b> Nominal<br\/>  <b>Day\/Night: <\/b> Night<br\/> <b>Scan: <\/b> 0.7 km<br\/> <b>Track: <\/b> 0.7 km<br\/> <b>FRP: <\/b> 1.83 MW<br\/> <b>Brightness: <\/b> 304.55 K" }, "geometry": { "type": "Point", "coordinates": [ -84.37408, 46.47503, 0.0 ] } },
{ "type": "Feature", "properties": { "Name": "Fire Detection Centroid ", "Description": "<b>Latitude: <\/b> 46.42767<br\/>  <b>Longitude: <\/b> -82.61362<br\/>  <b>Detection Time: <\/b> 2024-03-06 06:24 UTC<br\/>  <b>Sensor: <\/b> NOAA-20 VIIRS<br\/> <b>Confidence: <\/b> Nominal<br\/>  <b>Day\/Night: <\/b> Night<br\/> <b>Scan: <\/b> 0.6 km<br\/> <b>Track: <\/b> 0.7 km<br\/> <b>FRP: <\/b> 1.15 MW<br\/> <b>Brightness: <\/b> 303.62 K" }, "geometry": { "type": "Point", "coordinates": [ -82.61362, 46.42767, 0.0 ] } },
{ "type": "Feature", "properties": { "Name": "Fire Detection Centroid ", "Description": "<b>Latitude: <\/b> 46.68217<br\/>  <b>Longitude: <\/b> -84.38321<br\/>  <b>Detection Time: <\/b> 2024-03-06 06:24 UTC<br\/>  <b>Sensor: <\/b> NOAA-20 VIIRS<br\/> <b>Confidence: <\/b> Nominal<br\/>  <b>Day\/Night: <\/b> Night<br\/> <b>Scan: <\/b> 0.7 km<br\/> <b>Track: <\/b> 0.7 km<br\/> <b>FRP: <\/b> 2.12 MW<br\/> <b>Brightness: <\/b> 299.73 K" }, "geometry": { "type": "Point", "coordinates": [ -84.38321, 46.68217, 0.0 ] } },
{ "type": "Feature", "properties": { "Name": "Fire Detection Centroid ", "Description": "<b>Latitude: <\/b> 46.68223<br\/>  <b>Longitude: <\/b> -84.37364<br\/>  <b>Detection Time: <\/b> 2024-03-06 06:24 UTC<br\/>  <b>Sensor: <\/b> NOAA-20 VIIRS<br\/> <b>Confidence: <\/b> Nominal<br\/>  <b>Day\/Night: <\/b> Night<br\/> <b>Scan: <\/b> 0.7 km<br\/> <b>Track: <\/b> 0.7 km<br\/> <b>FRP: <\/b> 3.33 MW<br\/> <b>Brightness: <\/b> 306.42 K" }, "geometry": { "type": "Point", "coordinates": [ -84.37364, 46.68223, 0.0 ] } }
]
}
