{
"type": "FeatureCollection",
"crs": { "type": "name", "properties": { "name": "urn:ogc:def:crs:OGC:1.3:CRS84" } },
"features": [
{ "type": "Feature", "properties": { "Name": "Fire Detection Centroid ", "Description": "<b>Latitude: <\/b> 34.30162<br\/>  <b>Longitude: <\/b> -79.89783<br\/>  <b>Detection Time: <\/b> 2024-01-18 06:28 UTC<br\/>  <b>Sensor: <\/b> NOAA-20 VIIRS<br\/> <b>Confidence: <\/b> Nominal<br\/>  <b>Day\/Night: <\/b> Night<br\/> <b>Scan: <\/b> 0.3 km<br\/> <b>Track: <\/b> 0.6 km<br\/> <b>FRP: <\/b> 0.67 MW<br\/> <b>Brightness: <\/b> 298.82 K" }, "geometry": { "type": "Point", "coordinates": [ -79.89783, 34.30162, 0.0 ] } },
{ "type": "Feature", "properties": { "Name": "Fire Detection Centroid ", "Description": "<b>Latitude: <\/b> 35.92276<br\/>  <b>Longitude: <\/b> -78.01389<br\/>  <b>Detection Time: <\/b> 2024-01-18 06:27 UTC<br\/>  <b>Sensor: <\/b> NOAA-20 VIIRS<br\/> <b>Confidence: <\/b> Nominal<br\/>  <b>Day\/Night: <\/b> Night<br\/> <b>Scan: <\/b> 0.5 km<br\/> <b>Track: <\/b> 0.5 km<br\/> <b>FRP: <\/b> 1 MW<br\/> <b>Brightness: <\/b> 299.96 K" }, "geometry": { "type": "Point", "coordinates": [ -78.01389, 35.92276, 0.0 ] } },
{ "type": "Feature", "properties": { "Name": "Fire Detection Centroid ", "Description": "<b>Latitude: <\/b> 35.36086<br\/>  <b>Longitude: <\/b> -80.82678<br\/>  <b>Detection Time: <\/b> 2024-01-18 06:27 UTC<br\/>  <b>Sensor: <\/b> NOAA-20 VIIRS<br\/> <b>Confidence: <\/b> Nominal<br\/>  <b>Day\/Night: <\/b> Night<br\/> <b>Scan: <\/b> 0.4 km<br\/> <b>Track: <\/b> 0.6 km<br\/> <b>FRP: <\/b> 0.6 MW<br\/> <b>Brightness: <\/b> 295.19 K" }, "geometry": { "type": "Point", "coordinates": [ -80.82678, 35.36086, 0.0 ] } },
{ "type": "Feature", "properties": { "Name": "Fire Detection Centroid ", "Description": "<b>Latitude: <\/b> 36.3076<br\/>  <b>Longitude: <\/b> -76.74526<br\/>  <b>Detection Time: <\/b> 2024-01-18 06:27 UTC<br\/>  <b>Sensor: <\/b> NOAA-20 VIIRS<br\/> <b>Confidence: <\/b> Nominal<br\/>  <b>Day\/Night: <\/b> Night<br\/> <b>Scan: <\/b> 0.5 km<br\/> <b>Track: <\/b> 0.5 km<br\/> <b>FRP: <\/b> 14.75 MW<br\/> <b>Brightness: <\/b> 337.51 K" }, "geometry": { "type": "Point", "coordinates": [ -76.74526, 36.3076, 0.0 ] } },
{ "type": "Feature", "properties": { "Name": "Fire Detection Centroid ", "Description": "<b>Latitude: <\/b> 34.87619<br\/>  <b>Longitude: <\/b> -79.73702<br\/>  <b>Detection Time: <\/b> 2024-01-18 06:27 UTC<br\/>  <b>Sensor: <\/b> NOAA-20 VIIRS<br\/> <b>Confidence: <\/b> Nominal<br\/>  <b>Day\/Night: <\/b> Night<br\/> <b>Scan: <\/b> 0.3 km<br\/> <b>Track: <\/b> 0.6 km<br\/> <b>FRP: <\/b> 0.61 MW<br\/> <b>Brightness: <\/b> 300.63 K" }, "geometry": { "type": "Point", "coordinates": [ -79.73702, 34.87619, 0.0 ] } },
{ "type": "Feature", "properties": { "Name": "Fire Detection Centroid ", "Description": "<b>Latitude: <\/b> 34.84528<br\/>  <b>Longitude: <\/b> -79.66646<br\/>  <b>Detection Time: <\/b> 2024-01-18 06:27 UTC<br\/>  <b>Sensor: <\/b> NOAA-20 VIIRS<br\/> <b>Confidence: <\/b> Nominal<br\/>  <b>Day\/Night: <\/b> Night<br\/> <b>Scan: <\/b> 0.3 km<br\/> <b>Track: <\/b> 0.6 km<br\/> <b>FRP: <\/b> 0.45 MW<br\/> <b>Brightness: <\/b> 298.2 K" }, "geometry": { "type": "Point", "coordinates": [ -79.66646, 34.84528, 0.0 ] } },
{ "type": "Feature", "properties": { "Name": "Fire Detection Centroid ", "Description": "<b>Latitude: <\/b> 40.22366<br\/>  <b>Longitude: <\/b> -74.75983<br\/>  <b>Detection Time: <\/b> 2024-01-18 06:26 UTC<br\/>  <b>Sensor: <\/b> NOAA-20 VIIRS<br\/> <b>Confidence: <\/b> Nominal<br\/>  <b>Day\/Night: <\/b> Night<br\/> <b>Scan: <\/b> 0.4 km<br\/> <b>Track: <\/b> 0.4 km<br\/> <b>FRP: <\/b> 1.49 MW<br\/> <b>Brightness: <\/b> 321.47 K" }, "geometry": { "type": "Point", "coordinates": [ -74.75983, 40.22366, 0.0 ] } }
]
}
