{
"type": "FeatureCollection",
"crs": { "type": "name", "properties": { "name": "urn:ogc:def:crs:OGC:1.3:CRS84" } },
"features": [
{ "type": "Feature", "properties": { "Name": "Fire Detection Centroid ", "Description": "<b>Latitude: <\/b> 33.01729<br\/>  <b>Longitude: <\/b> -79.88455<br\/>  <b>Detection Time: <\/b> 2023-12-29 06:03 UTC<br\/>  <b>Sensor: <\/b> NOAA-20 VIIRS<br\/> <b>Confidence: <\/b> Nominal<br\/>  <b>Day\/Night: <\/b> Night<br\/> <b>Scan: <\/b> 0.8 km<br\/> <b>Track: <\/b> 0.8 km<br\/> <b>FRP: <\/b> 3.07 MW<br\/> <b>Brightness: <\/b> 306.24 K" }, "geometry": { "type": "Point", "coordinates": [ -79.88455, 33.01729, 0.0 ] } },
{ "type": "Feature", "properties": { "Name": "Fire Detection Centroid ", "Description": "<b>Latitude: <\/b> 33.01412<br\/>  <b>Longitude: <\/b> -79.8847<br\/>  <b>Detection Time: <\/b> 2023-12-29 06:03 UTC<br\/>  <b>Sensor: <\/b> NOAA-20 VIIRS<br\/> <b>Confidence: <\/b> Nominal<br\/>  <b>Day\/Night: <\/b> Night<br\/> <b>Scan: <\/b> 0.8 km<br\/> <b>Track: <\/b> 0.8 km<br\/> <b>FRP: <\/b> 4.08 MW<br\/> <b>Brightness: <\/b> 307 K" }, "geometry": { "type": "Point", "coordinates": [ -79.8847, 33.01412, 0.0 ] } },
{ "type": "Feature", "properties": { "Name": "Fire Detection Centroid ", "Description": "<b>Latitude: <\/b> 40.8917<br\/>  <b>Longitude: <\/b> -77.71067<br\/>  <b>Detection Time: <\/b> 2023-12-29 06:01 UTC<br\/>  <b>Sensor: <\/b> NOAA-20 VIIRS<br\/> <b>Confidence: <\/b> Nominal<br\/>  <b>Day\/Night: <\/b> Night<br\/> <b>Scan: <\/b> 0.6 km<br\/> <b>Track: <\/b> 0.7 km<br\/> <b>FRP: <\/b> 2.54 MW<br\/> <b>Brightness: <\/b> 312.31 K" }, "geometry": { "type": "Point", "coordinates": [ -77.71067, 40.8917, 0.0 ] } },
{ "type": "Feature", "properties": { "Name": "Fire Detection Centroid ", "Description": "<b>Latitude: <\/b> 40.89453<br\/>  <b>Longitude: <\/b> -77.70924<br\/>  <b>Detection Time: <\/b> 2023-12-29 06:01 UTC<br\/>  <b>Sensor: <\/b> NOAA-20 VIIRS<br\/> <b>Confidence: <\/b> Nominal<br\/>  <b>Day\/Night: <\/b> Night<br\/> <b>Scan: <\/b> 0.6 km<br\/> <b>Track: <\/b> 0.7 km<br\/> <b>FRP: <\/b> 3.02 MW<br\/> <b>Brightness: <\/b> 299.47 K" }, "geometry": { "type": "Point", "coordinates": [ -77.70924, 40.89453, 0.0 ] } }
]
}
