{
"type": "FeatureCollection",
"crs": { "type": "name", "properties": { "name": "urn:ogc:def:crs:OGC:1.3:CRS84" } },
"features": [
{ "type": "Feature", "properties": { "Name": "Fire Detection Centroid ", "Description": "<b>Latitude: <\/b> 18.5305<br\/>  <b>Longitude: <\/b> -70.53034<br\/>  <b>Detection Time: <\/b> 2023-12-23 06:19 UTC<br\/>  <b>Sensor: <\/b> NOAA-20 VIIRS<br\/> <b>Confidence: <\/b> Nominal<br\/>  <b>Day\/Night: <\/b> Night<br\/> <b>Scan: <\/b> 0.4 km<br\/> <b>Track: <\/b> 0.4 km<br\/> <b>FRP: <\/b> 0.51 MW<br\/> <b>Brightness: <\/b> 300.25 K" }, "geometry": { "type": "Point", "coordinates": [ -70.53034, 18.5305, 0.0 ] } },
{ "type": "Feature", "properties": { "Name": "Fire Detection Centroid ", "Description": "<b>Latitude: <\/b> 23.08478<br\/>  <b>Longitude: <\/b> -81.27249<br\/>  <b>Detection Time: <\/b> 2023-12-23 06:18 UTC<br\/>  <b>Sensor: <\/b> NOAA-20 VIIRS<br\/> <b>Confidence: <\/b> Nominal<br\/>  <b>Day\/Night: <\/b> Night<br\/> <b>Scan: <\/b> 0.5 km<br\/> <b>Track: <\/b> 0.6 km<br\/> <b>FRP: <\/b> 1.63 MW<br\/> <b>Brightness: <\/b> 308.59 K" }, "geometry": { "type": "Point", "coordinates": [ -81.27249, 23.08478, 0.0 ] } },
{ "type": "Feature", "properties": { "Name": "Fire Detection Centroid ", "Description": "<b>Latitude: <\/b> 23.08722<br\/>  <b>Longitude: <\/b> -81.27335<br\/>  <b>Detection Time: <\/b> 2023-12-23 06:18 UTC<br\/>  <b>Sensor: <\/b> NOAA-20 VIIRS<br\/> <b>Confidence: <\/b> Nominal<br\/>  <b>Day\/Night: <\/b> Night<br\/> <b>Scan: <\/b> 0.5 km<br\/> <b>Track: <\/b> 0.6 km<br\/> <b>FRP: <\/b> 1.9 MW<br\/> <b>Brightness: <\/b> 312.72 K" }, "geometry": { "type": "Point", "coordinates": [ -81.27335, 23.08722, 0.0 ] } },
{ "type": "Feature", "properties": { "Name": "Fire Detection Centroid ", "Description": "<b>Latitude: <\/b> 35.72546<br\/>  <b>Longitude: <\/b> -77.18583<br\/>  <b>Detection Time: <\/b> 2023-12-23 06:15 UTC<br\/>  <b>Sensor: <\/b> NOAA-20 VIIRS<br\/> <b>Confidence: <\/b> Nominal<br\/>  <b>Day\/Night: <\/b> Night<br\/> <b>Scan: <\/b> 0.4 km<br\/> <b>Track: <\/b> 0.6 km<br\/> <b>FRP: <\/b> 1.56 MW<br\/> <b>Brightness: <\/b> 321.34 K" }, "geometry": { "type": "Point", "coordinates": [ -77.18583, 35.72546, 0.0 ] } },
{ "type": "Feature", "properties": { "Name": "Fire Detection Centroid ", "Description": "<b>Latitude: <\/b> 35.34463<br\/>  <b>Longitude: <\/b> -80.8281<br\/>  <b>Detection Time: <\/b> 2023-12-23 06:15 UTC<br\/>  <b>Sensor: <\/b> NOAA-20 VIIRS<br\/> <b>Confidence: <\/b> Nominal<br\/>  <b>Day\/Night: <\/b> Night<br\/> <b>Scan: <\/b> 0.6 km<br\/> <b>Track: <\/b> 0.7 km<br\/> <b>FRP: <\/b> 1.01 MW<br\/> <b>Brightness: <\/b> 301.31 K" }, "geometry": { "type": "Point", "coordinates": [ -80.8281, 35.34463, 0.0 ] } },
{ "type": "Feature", "properties": { "Name": "Fire Detection Centroid ", "Description": "<b>Latitude: <\/b> 35.34486<br\/>  <b>Longitude: <\/b> -80.82711<br\/>  <b>Detection Time: <\/b> 2023-12-23 06:15 UTC<br\/>  <b>Sensor: <\/b> NOAA-20 VIIRS<br\/> <b>Confidence: <\/b> Nominal<br\/>  <b>Day\/Night: <\/b> Night<br\/> <b>Scan: <\/b> 0.6 km<br\/> <b>Track: <\/b> 0.7 km<br\/> <b>FRP: <\/b> 1.22 MW<br\/> <b>Brightness: <\/b> 295.24 K" }, "geometry": { "type": "Point", "coordinates": [ -80.82711, 35.34486, 0.0 ] } },
{ "type": "Feature", "properties": { "Name": "Fire Detection Centroid ", "Description": "<b>Latitude: <\/b> 40.15349<br\/>  <b>Longitude: <\/b> -74.77269<br\/>  <b>Detection Time: <\/b> 2023-12-23 06:14 UTC<br\/>  <b>Sensor: <\/b> NOAA-20 VIIRS<br\/> <b>Confidence: <\/b> Nominal<br\/>  <b>Day\/Night: <\/b> Night<br\/> <b>Scan: <\/b> 0.6 km<br\/> <b>Track: <\/b> 0.5 km<br\/> <b>FRP: <\/b> 1.38 MW<br\/> <b>Brightness: <\/b> 304.05 K" }, "geometry": { "type": "Point", "coordinates": [ -74.77269, 40.15349, 0.0 ] } },
{ "type": "Feature", "properties": { "Name": "Fire Detection Centroid ", "Description": "<b>Latitude: <\/b> 40.15604<br\/>  <b>Longitude: <\/b> -74.77331<br\/>  <b>Detection Time: <\/b> 2023-12-23 06:13 UTC<br\/>  <b>Sensor: <\/b> NOAA-20 VIIRS<br\/> <b>Confidence: <\/b> Nominal<br\/>  <b>Day\/Night: <\/b> Night<br\/> <b>Scan: <\/b> 0.6 km<br\/> <b>Track: <\/b> 0.5 km<br\/> <b>FRP: <\/b> 0.92 MW<br\/> <b>Brightness: <\/b> 301.7 K" }, "geometry": { "type": "Point", "coordinates": [ -74.77331, 40.15604, 0.0 ] } },
{ "type": "Feature", "properties": { "Name": "Fire Detection Centroid ", "Description": "<b>Latitude: <\/b> 45.28122<br\/>  <b>Longitude: <\/b> -66.0196<br\/>  <b>Detection Time: <\/b> 2023-12-23 06:12 UTC<br\/>  <b>Sensor: <\/b> NOAA-20 VIIRS<br\/> <b>Confidence: <\/b> Nominal<br\/>  <b>Day\/Night: <\/b> Night<br\/> <b>Scan: <\/b> 0.4 km<br\/> <b>Track: <\/b> 0.4 km<br\/> <b>FRP: <\/b> 1.2 MW<br\/> <b>Brightness: <\/b> 297.55 K" }, "geometry": { "type": "Point", "coordinates": [ -66.0196, 45.28122, 0.0 ] } }
]
}
