{
"type": "FeatureCollection",
"crs": { "type": "name", "properties": { "name": "urn:ogc:def:crs:OGC:1.3:CRS84" } },
"features": [
{ "type": "Feature", "properties": { "Name": "Fire Detection Centroid ", "Description": "<b>Latitude: <\/b> 48.18882<br\/>  <b>Longitude: <\/b> -64.92136<br\/>  <b>Detection Time: <\/b> 2022-09-18 05:14 UTC<br\/>  <b>Sensor: <\/b> NOAA-20 VIIRS<br\/> <b>Confidence: <\/b> Nominal<br\/>  <b>Day\/Night: <\/b> Night<br\/> <b>Scan: <\/b> 0.6 km<br\/> <b>Track: <\/b> 0.7 km<br\/> <b>FRP: <\/b> 1.23 MW<br\/> <b>Brightness: <\/b> 297.03 K" }, "geometry": { "type": "Point", "coordinates": [ -64.92136, 48.18882, 0.0 ] } },
{ "type": "Feature", "properties": { "Name": "Fire Detection Centroid ", "Description": "<b>Latitude: <\/b> 19.40378<br\/>  <b>Longitude: <\/b> -155.28696<br\/>  <b>Detection Time: <\/b> 2022-09-17 23:37 UTC<br\/>  <b>Sensor: <\/b> NOAA-20 VIIRS<br\/> <b>Confidence: <\/b> High<br\/>  <b>Day\/Night: <\/b> Day<br\/> <b>Scan: <\/b> 0.39 km<br\/> <b>Track: <\/b> 0.36 km<br\/> <b>FRP: <\/b> 126.35 MW<br\/> <b>Brightness: <\/b> 367 K" }, "geometry": { "type": "Point", "coordinates": [ -155.28696, 19.40378, 0.0 ] } },
{ "type": "Feature", "properties": { "Name": "Fire Detection Centroid ", "Description": "<b>Latitude: <\/b> 20.8836<br\/>  <b>Longitude: <\/b> -156.65733<br\/>  <b>Detection Time: <\/b> 2022-09-17 23:37 UTC<br\/>  <b>Sensor: <\/b> NOAA-20 VIIRS<br\/> <b>Confidence: <\/b> Low<br\/>  <b>Day\/Night: <\/b> Day<br\/> <b>Scan: <\/b> 0.38 km<br\/> <b>Track: <\/b> 0.36 km<br\/> <b>FRP: <\/b> 4.36 MW<br\/> <b>Brightness: <\/b> 336.97 K" }, "geometry": { "type": "Point", "coordinates": [ -156.65733, 20.8836, 0.0 ] } },
{ "type": "Feature", "properties": { "Name": "Fire Detection Centroid ", "Description": "<b>Latitude: <\/b> 19.4071<br\/>  <b>Longitude: <\/b> -155.28752<br\/>  <b>Detection Time: <\/b> 2022-09-17 23:37 UTC<br\/>  <b>Sensor: <\/b> NOAA-20 VIIRS<br\/> <b>Confidence: <\/b> Nominal<br\/>  <b>Day\/Night: <\/b> Day<br\/> <b>Scan: <\/b> 0.39 km<br\/> <b>Track: <\/b> 0.36 km<br\/> <b>FRP: <\/b> 15.15 MW<br\/> <b>Brightness: <\/b> 353.57 K" }, "geometry": { "type": "Point", "coordinates": [ -155.28752, 19.4071, 0.0 ] } },
{ "type": "Feature", "properties": { "Name": "Fire Detection Centroid ", "Description": "<b>Latitude: <\/b> 19.41096<br\/>  <b>Longitude: <\/b> -155.28435<br\/>  <b>Detection Time: <\/b> 2022-09-17 23:37 UTC<br\/>  <b>Sensor: <\/b> NOAA-20 VIIRS<br\/> <b>Confidence: <\/b> Low<br\/>  <b>Day\/Night: <\/b> Day<br\/> <b>Scan: <\/b> 0.39 km<br\/> <b>Track: <\/b> 0.36 km<br\/> <b>FRP: <\/b> 15.15 MW<br\/> <b>Brightness: <\/b> 351.39 K" }, "geometry": { "type": "Point", "coordinates": [ -155.28435, 19.41096, 0.0 ] } },
{ "type": "Feature", "properties": { "Name": "Fire Detection Centroid ", "Description": "<b>Latitude: <\/b> 19.40432<br\/>  <b>Longitude: <\/b> -155.28326<br\/>  <b>Detection Time: <\/b> 2022-09-17 23:37 UTC<br\/>  <b>Sensor: <\/b> NOAA-20 VIIRS<br\/> <b>Confidence: <\/b> Low<br\/>  <b>Day\/Night: <\/b> Day<br\/> <b>Scan: <\/b> 0.39 km<br\/> <b>Track: <\/b> 0.36 km<br\/> <b>FRP: <\/b> 126.35 MW<br\/> <b>Brightness: <\/b> 351.29 K" }, "geometry": { "type": "Point", "coordinates": [ -155.28326, 19.40432, 0.0 ] } }
]
}
