{
"type": "FeatureCollection",
"crs": { "type": "name", "properties": { "name": "urn:ogc:def:crs:OGC:1.3:CRS84" } },
"features": [
{ "type": "Feature", "properties": { "Name": "Fire Detection Centroid ", "Description": "<b>Latitude: <\/b> 40.80672<br\/>  <b>Longitude: <\/b> -77.6573<br\/>  <b>Detection Time: <\/b> 2024-05-16 16:54 UTC<br\/>  <b>Sensor: <\/b> NOAA-20 VIIRS<br\/> <b>Confidence: <\/b> Nominal<br\/>  <b>Day\/Night: <\/b> Day<br\/> <b>Scan: <\/b> 0.7 km<br\/> <b>Track: <\/b> 0.8 km<br\/> <b>FRP: <\/b> 5.41 MW<br\/> <b>Brightness: <\/b> 326.09 K" }, "geometry": { "type": "Point", "coordinates": [ -77.6573, 40.80672, 0.0 ] } }
]
}
