{
"type": "FeatureCollection",
"crs": { "type": "name", "properties": { "name": "urn:ogc:def:crs:OGC:1.3:CRS84" } },
"features": [
{ "type": "Feature", "properties": { "Name": "Fire Detection Centroid ", "Description": "<b>Latitude: <\/b> 18.50876<br\/>  <b>Longitude: <\/b> -69.07089<br\/>  <b>Detection Time: <\/b> 2022-10-08 05:48 UTC<br\/>  <b>Sensor: <\/b> NOAA-20 VIIRS<br\/> <b>Confidence: <\/b> Nominal<br\/>  <b>Day\/Night: <\/b> Night<br\/> <b>Scan: <\/b> 0.5 km<br\/> <b>Track: <\/b> 0.5 km<br\/> <b>FRP: <\/b> 2.08 MW<br\/> <b>Brightness: <\/b> 317.61 K" }, "geometry": { "type": "Point", "coordinates": [ -69.07089, 18.50876, 0.0 ] } }
]
}
