{
"type": "FeatureCollection",
"crs": { "type": "name", "properties": { "name": "urn:ogc:def:crs:OGC:1.3:CRS84" } },
"features": [
{ "type": "Feature", "properties": { "Name": "Fire Detection Centroid ", "Description": "<b>Latitude: <\/b> 19.41031<br\/>  <b>Longitude: <\/b> -155.27878<br\/>  <b>Detection Time: <\/b> 2023-09-27 23:07 UTC<br\/>  <b>Sensor: <\/b> NOAA-20 VIIRS<br\/> <b>Confidence: <\/b> Low<br\/>  <b>Day\/Night: <\/b> Day<br\/> <b>Scan: <\/b> 0.49 km<br\/> <b>Track: <\/b> 0.48 km<br\/> <b>FRP: <\/b> 11.05 MW<br\/> <b>Brightness: <\/b> 349.49 K" }, "geometry": { "type": "Point", "coordinates": [ -155.27878, 19.41031, 0.0 ] } },
{ "type": "Feature", "properties": { "Name": "Fire Detection Centroid ", "Description": "<b>Latitude: <\/b> 19.40945<br\/>  <b>Longitude: <\/b> -155.28325<br\/>  <b>Detection Time: <\/b> 2023-09-27 23:07 UTC<br\/>  <b>Sensor: <\/b> NOAA-20 VIIRS<br\/> <b>Confidence: <\/b> Nominal<br\/>  <b>Day\/Night: <\/b> Day<br\/> <b>Scan: <\/b> 0.49 km<br\/> <b>Track: <\/b> 0.48 km<br\/> <b>FRP: <\/b> 15.83 MW<br\/> <b>Brightness: <\/b> 346.99 K" }, "geometry": { "type": "Point", "coordinates": [ -155.28325, 19.40945, 0.0 ] } },
{ "type": "Feature", "properties": { "Name": "Fire Detection Centroid ", "Description": "<b>Latitude: <\/b> 19.4147<br\/>  <b>Longitude: <\/b> -155.27963<br\/>  <b>Detection Time: <\/b> 2023-09-27 23:07 UTC<br\/>  <b>Sensor: <\/b> NOAA-20 VIIRS<br\/> <b>Confidence: <\/b> Low<br\/>  <b>Day\/Night: <\/b> Day<br\/> <b>Scan: <\/b> 0.49 km<br\/> <b>Track: <\/b> 0.48 km<br\/> <b>FRP: <\/b> 11.05 MW<br\/> <b>Brightness: <\/b> 342.25 K" }, "geometry": { "type": "Point", "coordinates": [ -155.27963, 19.4147, 0.0 ] } },
{ "type": "Feature", "properties": { "Name": "Fire Detection Centroid ", "Description": "<b>Latitude: <\/b> 19.4068<br\/>  <b>Longitude: <\/b> -155.27336<br\/>  <b>Detection Time: <\/b> 2023-09-27 23:07 UTC<br\/>  <b>Sensor: <\/b> NOAA-20 VIIRS<br\/> <b>Confidence: <\/b> Low<br\/>  <b>Day\/Night: <\/b> Day<br\/> <b>Scan: <\/b> 0.49 km<br\/> <b>Track: <\/b> 0.48 km<br\/> <b>FRP: <\/b> 10.2 MW<br\/> <b>Brightness: <\/b> 345.46 K" }, "geometry": { "type": "Point", "coordinates": [ -155.27336, 19.4068, 0.0 ] } },
{ "type": "Feature", "properties": { "Name": "Fire Detection Centroid ", "Description": "<b>Latitude: <\/b> 19.40593<br\/>  <b>Longitude: <\/b> -155.27789<br\/>  <b>Detection Time: <\/b> 2023-09-27 23:07 UTC<br\/>  <b>Sensor: <\/b> NOAA-20 VIIRS<br\/> <b>Confidence: <\/b> Nominal<br\/>  <b>Day\/Night: <\/b> Day<br\/> <b>Scan: <\/b> 0.49 km<br\/> <b>Track: <\/b> 0.48 km<br\/> <b>FRP: <\/b> 10.2 MW<br\/> <b>Brightness: <\/b> 348.79 K" }, "geometry": { "type": "Point", "coordinates": [ -155.27789, 19.40593, 0.0 ] } },
{ "type": "Feature", "properties": { "Name": "Fire Detection Centroid ", "Description": "<b>Latitude: <\/b> 19.41117<br\/>  <b>Longitude: <\/b> -155.27428<br\/>  <b>Detection Time: <\/b> 2023-09-27 23:07 UTC<br\/>  <b>Sensor: <\/b> NOAA-20 VIIRS<br\/> <b>Confidence: <\/b> Low<br\/>  <b>Day\/Night: <\/b> Day<br\/> <b>Scan: <\/b> 0.49 km<br\/> <b>Track: <\/b> 0.48 km<br\/> <b>FRP: <\/b> 11.05 MW<br\/> <b>Brightness: <\/b> 347.41 K" }, "geometry": { "type": "Point", "coordinates": [ -155.27428, 19.41117, 0.0 ] } }
]
}
