{
"type": "FeatureCollection",
"crs": { "type": "name", "properties": { "name": "urn:ogc:def:crs:OGC:1.3:CRS84" } },
"features": [
{ "type": "Feature", "properties": { "Name": "Fire Detection Centroid ", "Description": "<b>Latitude: <\/b> 49.99263<br\/>  <b>Longitude: <\/b> -121.61114<br\/>  <b>Detection Time: <\/b> 2023-07-20 11:40 UTC<br\/>  <b>Sensor: <\/b> NOAA-20 VIIRS<br\/> <b>Confidence: <\/b> Nominal<br\/>  <b>Day\/Night: <\/b> Night<br\/> <b>Scan: <\/b> 0.7 km<br\/> <b>Track: <\/b> 0.75 km<br\/> <b>FRP: <\/b> 1.28 MW<br\/> <b>Brightness: <\/b> 302.38 K" }, "geometry": { "type": "Point", "coordinates": [ -121.61114, 49.99263, 0.0 ] } },
{ "type": "Feature", "properties": { "Name": "Fire Detection Centroid ", "Description": "<b>Latitude: <\/b> 49.99474<br\/>  <b>Longitude: <\/b> -121.63756<br\/>  <b>Detection Time: <\/b> 2023-07-20 11:40 UTC<br\/>  <b>Sensor: <\/b> NOAA-20 VIIRS<br\/> <b>Confidence: <\/b> Nominal<br\/>  <b>Day\/Night: <\/b> Night<br\/> <b>Scan: <\/b> 0.7 km<br\/> <b>Track: <\/b> 0.75 km<br\/> <b>FRP: <\/b> 1.72 MW<br\/> <b>Brightness: <\/b> 296.51 K" }, "geometry": { "type": "Point", "coordinates": [ -121.63756, 49.99474, 0.0 ] } },
{ "type": "Feature", "properties": { "Name": "Fire Detection Centroid ", "Description": "<b>Latitude: <\/b> 49.99284<br\/>  <b>Longitude: <\/b> -121.63261<br\/>  <b>Detection Time: <\/b> 2023-07-20 11:40 UTC<br\/>  <b>Sensor: <\/b> NOAA-20 VIIRS<br\/> <b>Confidence: <\/b> Nominal<br\/>  <b>Day\/Night: <\/b> Night<br\/> <b>Scan: <\/b> 0.7 km<br\/> <b>Track: <\/b> 0.75 km<br\/> <b>FRP: <\/b> 1.72 MW<br\/> <b>Brightness: <\/b> 309.54 K" }, "geometry": { "type": "Point", "coordinates": [ -121.63261, 49.99284, 0.0 ] } },
{ "type": "Feature", "properties": { "Name": "Fire Detection Centroid ", "Description": "<b>Latitude: <\/b> 49.98969<br\/>  <b>Longitude: <\/b> -121.62443<br\/>  <b>Detection Time: <\/b> 2023-07-20 11:40 UTC<br\/>  <b>Sensor: <\/b> NOAA-20 VIIRS<br\/> <b>Confidence: <\/b> Nominal<br\/>  <b>Day\/Night: <\/b> Night<br\/> <b>Scan: <\/b> 0.7 km<br\/> <b>Track: <\/b> 0.75 km<br\/> <b>FRP: <\/b> 1.85 MW<br\/> <b>Brightness: <\/b> 302.85 K" }, "geometry": { "type": "Point", "coordinates": [ -121.62443, 49.98969, 0.0 ] } },
{ "type": "Feature", "properties": { "Name": "Fire Detection Centroid ", "Description": "<b>Latitude: <\/b> 48.88696<br\/>  <b>Longitude: <\/b> -122.74802<br\/>  <b>Detection Time: <\/b> 2023-07-20 11:40 UTC<br\/>  <b>Sensor: <\/b> NOAA-20 VIIRS<br\/> <b>Confidence: <\/b> Nominal<br\/>  <b>Day\/Night: <\/b> Night<br\/> <b>Scan: <\/b> 0.69 km<br\/> <b>Track: <\/b> 0.74 km<br\/> <b>FRP: <\/b> 0.87 MW<br\/> <b>Brightness: <\/b> 295.87 K" }, "geometry": { "type": "Point", "coordinates": [ -122.74802, 48.88696, 0.0 ] } },
{ "type": "Feature", "properties": { "Name": "Fire Detection Centroid ", "Description": "<b>Latitude: <\/b> 48.88389<br\/>  <b>Longitude: <\/b> -122.73994<br\/>  <b>Detection Time: <\/b> 2023-07-20 11:40 UTC<br\/>  <b>Sensor: <\/b> NOAA-20 VIIRS<br\/> <b>Confidence: <\/b> Nominal<br\/>  <b>Day\/Night: <\/b> Night<br\/> <b>Scan: <\/b> 0.69 km<br\/> <b>Track: <\/b> 0.75 km<br\/> <b>FRP: <\/b> 0.87 MW<br\/> <b>Brightness: <\/b> 297.36 K" }, "geometry": { "type": "Point", "coordinates": [ -122.73994, 48.88389, 0.0 ] } },
{ "type": "Feature", "properties": { "Name": "Fire Detection Centroid ", "Description": "<b>Latitude: <\/b> 48.88929<br\/>  <b>Longitude: <\/b> -122.73985<br\/>  <b>Detection Time: <\/b> 2023-07-20 11:40 UTC<br\/>  <b>Sensor: <\/b> NOAA-20 VIIRS<br\/> <b>Confidence: <\/b> Nominal<br\/>  <b>Day\/Night: <\/b> Night<br\/> <b>Scan: <\/b> 0.69 km<br\/> <b>Track: <\/b> 0.75 km<br\/> <b>FRP: <\/b> 2.7 MW<br\/> <b>Brightness: <\/b> 306.45 K" }, "geometry": { "type": "Point", "coordinates": [ -122.73985, 48.88929, 0.0 ] } },
{ "type": "Feature", "properties": { "Name": "Fire Detection Centroid ", "Description": "<b>Latitude: <\/b> 48.88621<br\/>  <b>Longitude: <\/b> -122.7316<br\/>  <b>Detection Time: <\/b> 2023-07-20 11:40 UTC<br\/>  <b>Sensor: <\/b> NOAA-20 VIIRS<br\/> <b>Confidence: <\/b> Nominal<br\/>  <b>Day\/Night: <\/b> Night<br\/> <b>Scan: <\/b> 0.69 km<br\/> <b>Track: <\/b> 0.75 km<br\/> <b>FRP: <\/b> 2.26 MW<br\/> <b>Brightness: <\/b> 299.76 K" }, "geometry": { "type": "Point", "coordinates": [ -122.7316, 48.88621, 0.0 ] } }
]
}
