{
"type": "FeatureCollection",
"crs": { "type": "name", "properties": { "name": "urn:ogc:def:crs:OGC:1.3:CRS84" } },
"features": [
{ "type": "Feature", "properties": { "Name": "Fire Detection Centroid ", "Description": "<b>Latitude: <\/b> 45.81712<br\/>  <b>Longitude: <\/b> -73.23849<br\/>  <b>Detection Time: <\/b> 2024-03-24 17:06 UTC<br\/>  <b>Sensor: <\/b> NOAA-20 VIIRS<br\/> <b>Confidence: <\/b> Nominal<br\/>  <b>Day\/Night: <\/b> Day<br\/> <b>Scan: <\/b> 0.5 km<br\/> <b>Track: <\/b> 0.5 km<br\/> <b>FRP: <\/b> 4.06 MW<br\/> <b>Brightness: <\/b> 326.1 K" }, "geometry": { "type": "Point", "coordinates": [ -73.23849, 45.81712, 0.0 ] } },
{ "type": "Feature", "properties": { "Name": "Fire Detection Centroid ", "Description": "<b>Latitude: <\/b> 40.82767<br\/>  <b>Longitude: <\/b> -77.67396<br\/>  <b>Detection Time: <\/b> 2024-03-24 17:05 UTC<br\/>  <b>Sensor: <\/b> NOAA-20 VIIRS<br\/> <b>Confidence: <\/b> Nominal<br\/>  <b>Day\/Night: <\/b> Day<br\/> <b>Scan: <\/b> 0.5 km<br\/> <b>Track: <\/b> 0.7 km<br\/> <b>FRP: <\/b> 4.23 MW<br\/> <b>Brightness: <\/b> 329 K" }, "geometry": { "type": "Point", "coordinates": [ -77.67396, 40.82767, 0.0 ] } },
{ "type": "Feature", "properties": { "Name": "Fire Detection Centroid ", "Description": "<b>Latitude: <\/b> 40.24924<br\/>  <b>Longitude: <\/b> -80.57021<br\/>  <b>Detection Time: <\/b> 2024-03-24 17:05 UTC<br\/>  <b>Sensor: <\/b> NOAA-20 VIIRS<br\/> <b>Confidence: <\/b> Nominal<br\/>  <b>Day\/Night: <\/b> Day<br\/> <b>Scan: <\/b> 0.8 km<br\/> <b>Track: <\/b> 0.8 km<br\/> <b>FRP: <\/b> 6.83 MW<br\/> <b>Brightness: <\/b> 329.3 K" }, "geometry": { "type": "Point", "coordinates": [ -80.57021, 40.24924, 0.0 ] } },
{ "type": "Feature", "properties": { "Name": "Fire Detection Centroid ", "Description": "<b>Latitude: <\/b> 40.44436<br\/>  <b>Longitude: <\/b> -80.67949<br\/>  <b>Detection Time: <\/b> 2024-03-24 17:05 UTC<br\/>  <b>Sensor: <\/b> NOAA-20 VIIRS<br\/> <b>Confidence: <\/b> Nominal<br\/>  <b>Day\/Night: <\/b> Day<br\/> <b>Scan: <\/b> 0.8 km<br\/> <b>Track: <\/b> 0.8 km<br\/> <b>FRP: <\/b> 5.8 MW<br\/> <b>Brightness: <\/b> 339.98 K" }, "geometry": { "type": "Point", "coordinates": [ -80.67949, 40.44436, 0.0 ] } }
]
}
