{
"type": "FeatureCollection",
"crs": { "type": "name", "properties": { "name": "urn:ogc:def:crs:OGC:1.3:CRS84" } },
"features": [
{ "type": "Feature", "properties": { "Name": "Fire Detection Centroid ", "Description": "<b>Latitude: <\/b> 19.41145<br\/>  <b>Longitude: <\/b> -155.27887<br\/>  <b>Detection Time: <\/b> 2022-09-28 23:31 UTC<br\/>  <b>Sensor: <\/b> NOAA-20 VIIRS<br\/> <b>Confidence: <\/b> Low<br\/>  <b>Day\/Night: <\/b> Day<br\/> <b>Scan: <\/b> 0.39 km<br\/> <b>Track: <\/b> 0.36 km<br\/> <b>FRP: <\/b> 18.49 MW<br\/> <b>Brightness: <\/b> 345.86 K" }, "geometry": { "type": "Point", "coordinates": [ -155.27887, 19.41145, 0.0 ] } },
{ "type": "Feature", "properties": { "Name": "Fire Detection Centroid ", "Description": "<b>Latitude: <\/b> 19.40367<br\/>  <b>Longitude: <\/b> -155.28128<br\/>  <b>Detection Time: <\/b> 2022-09-28 23:31 UTC<br\/>  <b>Sensor: <\/b> NOAA-20 VIIRS<br\/> <b>Confidence: <\/b> Nominal<br\/>  <b>Day\/Night: <\/b> Day<br\/> <b>Scan: <\/b> 0.39 km<br\/> <b>Track: <\/b> 0.36 km<br\/> <b>FRP: <\/b> 6.37 MW<br\/> <b>Brightness: <\/b> 344.39 K" }, "geometry": { "type": "Point", "coordinates": [ -155.28128, 19.40367, 0.0 ] } },
{ "type": "Feature", "properties": { "Name": "Fire Detection Centroid ", "Description": "<b>Latitude: <\/b> 19.41033<br\/>  <b>Longitude: <\/b> -155.28613<br\/>  <b>Detection Time: <\/b> 2022-09-28 23:31 UTC<br\/>  <b>Sensor: <\/b> NOAA-20 VIIRS<br\/> <b>Confidence: <\/b> Nominal<br\/>  <b>Day\/Night: <\/b> Day<br\/> <b>Scan: <\/b> 0.39 km<br\/> <b>Track: <\/b> 0.36 km<br\/> <b>FRP: <\/b> 52.9 MW<br\/> <b>Brightness: <\/b> 349.46 K" }, "geometry": { "type": "Point", "coordinates": [ -155.28613, 19.41033, 0.0 ] } },
{ "type": "Feature", "properties": { "Name": "Fire Detection Centroid ", "Description": "<b>Latitude: <\/b> 19.40311<br\/>  <b>Longitude: <\/b> -155.28493<br\/>  <b>Detection Time: <\/b> 2022-09-28 23:31 UTC<br\/>  <b>Sensor: <\/b> NOAA-20 VIIRS<br\/> <b>Confidence: <\/b> Nominal<br\/>  <b>Day\/Night: <\/b> Day<br\/> <b>Scan: <\/b> 0.39 km<br\/> <b>Track: <\/b> 0.36 km<br\/> <b>FRP: <\/b> 9.24 MW<br\/> <b>Brightness: <\/b> 354.84 K" }, "geometry": { "type": "Point", "coordinates": [ -155.28493, 19.40311, 0.0 ] } },
{ "type": "Feature", "properties": { "Name": "Fire Detection Centroid ", "Description": "<b>Latitude: <\/b> 19.40703<br\/>  <b>Longitude: <\/b> -155.28558<br\/>  <b>Detection Time: <\/b> 2022-09-28 23:31 UTC<br\/>  <b>Sensor: <\/b> NOAA-20 VIIRS<br\/> <b>Confidence: <\/b> High<br\/>  <b>Day\/Night: <\/b> Day<br\/> <b>Scan: <\/b> 0.39 km<br\/> <b>Track: <\/b> 0.36 km<br\/> <b>FRP: <\/b> 52.9 MW<br\/> <b>Brightness: <\/b> 367 K" }, "geometry": { "type": "Point", "coordinates": [ -155.28558, 19.40703, 0.0 ] } }
]
}
