{
"type": "FeatureCollection",
"crs": { "type": "name", "properties": { "name": "urn:ogc:def:crs:OGC:1.3:CRS84" } },
"features": [
{ "type": "Feature", "properties": { "Name": "Fire Detection Centroid ", "Description": "<b>Latitude: <\/b> 19.41155<br\/>  <b>Longitude: <\/b> -155.28542<br\/>  <b>Detection Time: <\/b> 2022-09-06 23:44 UTC<br\/>  <b>Sensor: <\/b> NOAA-20 VIIRS<br\/> <b>Confidence: <\/b> Low<br\/>  <b>Day\/Night: <\/b> Day<br\/> <b>Scan: <\/b> 0.43 km<br\/> <b>Track: <\/b> 0.38 km<br\/> <b>FRP: <\/b> 9.31 MW<br\/> <b>Brightness: <\/b> 345.41 K" }, "geometry": { "type": "Point", "coordinates": [ -155.28542, 19.41155, 0.0 ] } },
{ "type": "Feature", "properties": { "Name": "Fire Detection Centroid ", "Description": "<b>Latitude: <\/b> 19.41348<br\/>  <b>Longitude: <\/b> -155.28101<br\/>  <b>Detection Time: <\/b> 2022-09-06 23:44 UTC<br\/>  <b>Sensor: <\/b> NOAA-20 VIIRS<br\/> <b>Confidence: <\/b> Low<br\/>  <b>Day\/Night: <\/b> Day<br\/> <b>Scan: <\/b> 0.43 km<br\/> <b>Track: <\/b> 0.38 km<br\/> <b>FRP: <\/b> 5.5 MW<br\/> <b>Brightness: <\/b> 337.94 K" }, "geometry": { "type": "Point", "coordinates": [ -155.28101, 19.41348, 0.0 ] } },
{ "type": "Feature", "properties": { "Name": "Fire Detection Centroid ", "Description": "<b>Latitude: <\/b> 19.40459<br\/>  <b>Longitude: <\/b> -155.28429<br\/>  <b>Detection Time: <\/b> 2022-09-06 23:44 UTC<br\/>  <b>Sensor: <\/b> NOAA-20 VIIRS<br\/> <b>Confidence: <\/b> High<br\/>  <b>Day\/Night: <\/b> Day<br\/> <b>Scan: <\/b> 0.43 km<br\/> <b>Track: <\/b> 0.38 km<br\/> <b>FRP: <\/b> 143.35 MW<br\/> <b>Brightness: <\/b> 367 K" }, "geometry": { "type": "Point", "coordinates": [ -155.28429, 19.40459, 0.0 ] } },
{ "type": "Feature", "properties": { "Name": "Fire Detection Centroid ", "Description": "<b>Latitude: <\/b> 19.40922<br\/>  <b>Longitude: <\/b> -155.27661<br\/>  <b>Detection Time: <\/b> 2022-09-06 23:44 UTC<br\/>  <b>Sensor: <\/b> NOAA-20 VIIRS<br\/> <b>Confidence: <\/b> Low<br\/>  <b>Day\/Night: <\/b> Day<br\/> <b>Scan: <\/b> 0.43 km<br\/> <b>Track: <\/b> 0.38 km<br\/> <b>FRP: <\/b> 14.41 MW<br\/> <b>Brightness: <\/b> 340.93 K" }, "geometry": { "type": "Point", "coordinates": [ -155.27661, 19.40922, 0.0 ] } },
{ "type": "Feature", "properties": { "Name": "Fire Detection Centroid ", "Description": "<b>Latitude: <\/b> 19.40807<br\/>  <b>Longitude: <\/b> -155.28484<br\/>  <b>Detection Time: <\/b> 2022-09-06 23:44 UTC<br\/>  <b>Sensor: <\/b> NOAA-20 VIIRS<br\/> <b>Confidence: <\/b> Nominal<br\/>  <b>Day\/Night: <\/b> Day<br\/> <b>Scan: <\/b> 0.43 km<br\/> <b>Track: <\/b> 0.38 km<br\/> <b>FRP: <\/b> 143.35 MW<br\/> <b>Brightness: <\/b> 348.19 K" }, "geometry": { "type": "Point", "coordinates": [ -155.28484, 19.40807, 0.0 ] } },
{ "type": "Feature", "properties": { "Name": "Fire Detection Centroid ", "Description": "<b>Latitude: <\/b> 19.41213<br\/>  <b>Longitude: <\/b> -155.28128<br\/>  <b>Detection Time: <\/b> 2022-09-06 23:44 UTC<br\/>  <b>Sensor: <\/b> NOAA-20 VIIRS<br\/> <b>Confidence: <\/b> Low<br\/>  <b>Day\/Night: <\/b> Day<br\/> <b>Scan: <\/b> 0.43 km<br\/> <b>Track: <\/b> 0.38 km<br\/> <b>FRP: <\/b> 8.98 MW<br\/> <b>Brightness: <\/b> 350.9 K" }, "geometry": { "type": "Point", "coordinates": [ -155.28128, 19.41213, 0.0 ] } }
]
}
