{
"type": "FeatureCollection",
"crs": { "type": "name", "properties": { "name": "urn:ogc:def:crs:OGC:1.3:CRS84" } },
"features": [
{ "type": "Feature", "properties": { "Name": "Fire Detection Centroid ", "Description": "<b>Latitude: <\/b> 19.40648<br\/>  <b>Longitude: <\/b> -155.28317<br\/>  <b>Detection Time: <\/b> 2024-02-18 11:55 UTC<br\/>  <b>Sensor: <\/b> NOAA-20 VIIRS<br\/> <b>Confidence: <\/b> Nominal<br\/>  <b>Day\/Night: <\/b> Night<br\/> <b>Scan: <\/b> 0.39 km<br\/> <b>Track: <\/b> 0.36 km<br\/> <b>FRP: <\/b> 2.95 MW<br\/> <b>Brightness: <\/b> 304.93 K" }, "geometry": { "type": "Point", "coordinates": [ -155.28317, 19.40648, 0.0 ] } },
{ "type": "Feature", "properties": { "Name": "Fire Detection Centroid ", "Description": "<b>Latitude: <\/b> 19.44308<br\/>  <b>Longitude: <\/b> -155.27654<br\/>  <b>Detection Time: <\/b> 2024-02-18 11:55 UTC<br\/>  <b>Sensor: <\/b> NOAA-20 VIIRS<br\/> <b>Confidence: <\/b> Nominal<br\/>  <b>Day\/Night: <\/b> Night<br\/> <b>Scan: <\/b> 0.4 km<br\/> <b>Track: <\/b> 0.4 km<br\/> <b>FRP: <\/b> 2.95 MW<br\/> <b>Brightness: <\/b> 304.93 K" }, "geometry": { "type": "Point", "coordinates": [ -155.27654, 19.44308, 0.0 ] } }
]
}
