{
"type": "FeatureCollection",
"crs": { "type": "name", "properties": { "name": "urn:ogc:def:crs:OGC:1.3:CRS84" } },
"features": [
{ "type": "Feature", "properties": { "Name": "Fire Detection Centroid ", "Description": "<b>Latitude: <\/b> 18.95626<br\/>  <b>Longitude: <\/b> -72.12625<br\/>  <b>Detection Time: <\/b> 2024-01-31 05:48 UTC<br\/>  <b>Sensor: <\/b> NOAA-20 VIIRS<br\/> <b>Confidence: <\/b> Nominal<br\/>  <b>Day\/Night: <\/b> Night<br\/> <b>Scan: <\/b> 0.4 km<br\/> <b>Track: <\/b> 0.6 km<br\/> <b>FRP: <\/b> 1.59 MW<br\/> <b>Brightness: <\/b> 320.74 K" }, "geometry": { "type": "Point", "coordinates": [ -72.12625, 18.95626, 0.0 ] } },
{ "type": "Feature", "properties": { "Name": "Fire Detection Centroid ", "Description": "<b>Latitude: <\/b> 17.69819<br\/>  <b>Longitude: <\/b> -64.74836<br\/>  <b>Detection Time: <\/b> 2024-01-31 05:48 UTC<br\/>  <b>Sensor: <\/b> NOAA-20 VIIRS<br\/> <b>Confidence: <\/b> Nominal<br\/>  <b>Day\/Night: <\/b> Night<br\/> <b>Scan: <\/b> 0.4 km<br\/> <b>Track: <\/b> 0.4 km<br\/> <b>FRP: <\/b> 1.02 MW<br\/> <b>Brightness: <\/b> 306.54 K" }, "geometry": { "type": "Point", "coordinates": [ -64.74836, 17.69819, 0.0 ] } },
{ "type": "Feature", "properties": { "Name": "Fire Detection Centroid ", "Description": "<b>Latitude: <\/b> 18.3515<br\/>  <b>Longitude: <\/b> -71.14551<br\/>  <b>Detection Time: <\/b> 2024-01-31 05:48 UTC<br\/>  <b>Sensor: <\/b> NOAA-20 VIIRS<br\/> <b>Confidence: <\/b> Nominal<br\/>  <b>Day\/Night: <\/b> Night<br\/> <b>Scan: <\/b> 0.6 km<br\/> <b>Track: <\/b> 0.5 km<br\/> <b>FRP: <\/b> 1.41 MW<br\/> <b>Brightness: <\/b> 301.89 K" }, "geometry": { "type": "Point", "coordinates": [ -71.14551, 18.3515, 0.0 ] } },
{ "type": "Feature", "properties": { "Name": "Fire Detection Centroid ", "Description": "<b>Latitude: <\/b> 17.93493<br\/>  <b>Longitude: <\/b> -77.00168<br\/>  <b>Detection Time: <\/b> 2024-01-31 05:48 UTC<br\/>  <b>Sensor: <\/b> NOAA-20 VIIRS<br\/> <b>Confidence: <\/b> Nominal<br\/>  <b>Day\/Night: <\/b> Night<br\/> <b>Scan: <\/b> 0.7 km<br\/> <b>Track: <\/b> 0.8 km<br\/> <b>FRP: <\/b> 0.88 MW<br\/> <b>Brightness: <\/b> 301.04 K" }, "geometry": { "type": "Point", "coordinates": [ -77.00168, 17.93493, 0.0 ] } }
]
}
