{
"type": "FeatureCollection",
"crs": { "type": "name", "properties": { "name": "urn:ogc:def:crs:OGC:1.3:CRS84" } },
"features": [
{ "type": "Feature", "properties": { "Name": "Fire Detection Centroid ", "Description": "<b>Latitude: <\/b> 42.23629<br\/>  <b>Longitude: <\/b> -122.85065<br\/>  <b>Detection Time: <\/b> 2024-02-06 21:57 UTC<br\/>  <b>Sensor: <\/b> NOAA-20 VIIRS<br\/> <b>Confidence: <\/b> Nominal<br\/>  <b>Day\/Night: <\/b> Day<br\/> <b>Scan: <\/b> 0.41 km<br\/> <b>Track: <\/b> 0.6 km<br\/> <b>FRP: <\/b> 4.18 MW<br\/> <b>Brightness: <\/b> 331.8 K" }, "geometry": { "type": "Point", "coordinates": [ -122.85065, 42.23629, 0.0 ] } },
{ "type": "Feature", "properties": { "Name": "Fire Detection Centroid ", "Description": "<b>Latitude: <\/b> 42.10719<br\/>  <b>Longitude: <\/b> -122.85221<br\/>  <b>Detection Time: <\/b> 2024-02-06 21:56 UTC<br\/>  <b>Sensor: <\/b> NOAA-20 VIIRS<br\/> <b>Confidence: <\/b> Nominal<br\/>  <b>Day\/Night: <\/b> Day<br\/> <b>Scan: <\/b> 0.4 km<br\/> <b>Track: <\/b> 0.6 km<br\/> <b>FRP: <\/b> 4.25 MW<br\/> <b>Brightness: <\/b> 331.8 K" }, "geometry": { "type": "Point", "coordinates": [ -122.85221, 42.10719, 0.0 ] } },
{ "type": "Feature", "properties": { "Name": "Fire Detection Centroid ", "Description": "<b>Latitude: <\/b> 42.10719<br\/>  <b>Longitude: <\/b> -122.85221<br\/>  <b>Detection Time: <\/b> 2024-02-06 21:56 UTC<br\/>  <b>Sensor: <\/b> NOAA-20 VIIRS<br\/> <b>Confidence: <\/b> Nominal<br\/>  <b>Day\/Night: <\/b> Day<br\/> <b>Scan: <\/b> 0.4 km<br\/> <b>Track: <\/b> 0.6 km<br\/> <b>FRP: <\/b> 4.25 MW<br\/> <b>Brightness: <\/b> 331.8 K" }, "geometry": { "type": "Point", "coordinates": [ -122.85221, 42.10719, 0.0 ] } }
]
}
