{
"type": "FeatureCollection",
"crs": { "type": "name", "properties": { "name": "urn:ogc:def:crs:OGC:1.3:CRS84" } },
"features": [
{ "type": "Feature", "properties": { "Name": "Fire Detection Centroid ", "Description": "<b>Latitude: <\/b> 18.04264<br\/>  <b>Longitude: <\/b> -66.25596<br\/>  <b>Detection Time: <\/b> 2024-01-12 05:03 UTC<br\/>  <b>Sensor: <\/b> NOAA-20 VIIRS<br\/> <b>Confidence: <\/b> Nominal<br\/>  <b>Day\/Night: <\/b> Night<br\/> <b>Scan: <\/b> 0.79 km<br\/> <b>Track: <\/b> 0.78 km<br\/> <b>FRP: <\/b> 1.03 MW<br\/> <b>Brightness: <\/b> 299.23 K" }, "geometry": { "type": "Point", "coordinates": [ -66.25596, 18.04264, 0.0 ] } }
]
}
