{
"type": "FeatureCollection",
"crs": { "type": "name", "properties": { "name": "urn:ogc:def:crs:OGC:1.3:CRS84" } },
"features": [
{ "type": "Feature", "properties": { "Name": "Fire Detection Centroid ", "Description": "<b>Latitude: <\/b> 46.81171<br\/>  <b>Longitude: <\/b> -112.07779<br\/>  <b>Detection Time: <\/b> 2022-12-29 19:51 UTC<br\/>  <b>Sensor: <\/b> NOAA-20 VIIRS<br\/> <b>Confidence: <\/b> Nominal<br\/>  <b>Day\/Night: <\/b> Day<br\/> <b>Scan: <\/b> 0.52 km<br\/> <b>Track: <\/b> 0.42 km<br\/> <b>FRP: <\/b> 10.1 MW<br\/> <b>Brightness: <\/b> 342.49 K" }, "geometry": { "type": "Point", "coordinates": [ -112.07779, 46.81171, 0.0 ] } },
{ "type": "Feature", "properties": { "Name": "Fire Detection Centroid ", "Description": "<b>Latitude: <\/b> 46.81543<br\/>  <b>Longitude: <\/b> -112.07924<br\/>  <b>Detection Time: <\/b> 2022-12-29 19:51 UTC<br\/>  <b>Sensor: <\/b> NOAA-20 VIIRS<br\/> <b>Confidence: <\/b> Nominal<br\/>  <b>Day\/Night: <\/b> Day<br\/> <b>Scan: <\/b> 0.52 km<br\/> <b>Track: <\/b> 0.42 km<br\/> <b>FRP: <\/b> 10.1 MW<br\/> <b>Brightness: <\/b> 325.52 K" }, "geometry": { "type": "Point", "coordinates": [ -112.07924, 46.81543, 0.0 ] } }
]
}
