{
"type": "FeatureCollection",
"crs": { "type": "name", "properties": { "name": "urn:ogc:def:crs:OGC:1.3:CRS84" } },
"features": [
{ "type": "Feature", "properties": { "Name": "Fire Detection Centroid ", "Description": "<b>Latitude: <\/b> 19.40732<br\/>  <b>Longitude: <\/b> -155.28036<br\/>  <b>Detection Time: <\/b> 2022-11-15 12:20 UTC<br\/>  <b>Sensor: <\/b> NOAA-20 VIIRS<br\/> <b>Confidence: <\/b> Nominal<br\/>  <b>Day\/Night: <\/b> Night<br\/> <b>Scan: <\/b> 0.4 km<br\/> <b>Track: <\/b> 0.4 km<br\/> <b>FRP: <\/b> 3.08 MW<br\/> <b>Brightness: <\/b> 311.95 K" }, "geometry": { "type": "Point", "coordinates": [ -155.28036, 19.40732, 0.0 ] } },
{ "type": "Feature", "properties": { "Name": "Fire Detection Centroid ", "Description": "<b>Latitude: <\/b> 19.41138<br\/>  <b>Longitude: <\/b> -155.27953<br\/>  <b>Detection Time: <\/b> 2022-11-15 12:20 UTC<br\/>  <b>Sensor: <\/b> NOAA-20 VIIRS<br\/> <b>Confidence: <\/b> Nominal<br\/>  <b>Day\/Night: <\/b> Night<br\/> <b>Scan: <\/b> 0.4 km<br\/> <b>Track: <\/b> 0.4 km<br\/> <b>FRP: <\/b> 3.08 MW<br\/> <b>Brightness: <\/b> 310.74 K" }, "geometry": { "type": "Point", "coordinates": [ -155.27953, 19.41138, 0.0 ] } },
{ "type": "Feature", "properties": { "Name": "Fire Detection Centroid ", "Description": "<b>Latitude: <\/b> 19.4088<br\/>  <b>Longitude: <\/b> -155.28818<br\/>  <b>Detection Time: <\/b> 2022-11-15 12:20 UTC<br\/>  <b>Sensor: <\/b> NOAA-20 VIIRS<br\/> <b>Confidence: <\/b> Nominal<br\/>  <b>Day\/Night: <\/b> Night<br\/> <b>Scan: <\/b> 0.4 km<br\/> <b>Track: <\/b> 0.4 km<br\/> <b>FRP: <\/b> 57.84 MW<br\/> <b>Brightness: <\/b> 336.34 K" }, "geometry": { "type": "Point", "coordinates": [ -155.28818, 19.4088, 0.0 ] } },
{ "type": "Feature", "properties": { "Name": "Fire Detection Centroid ", "Description": "<b>Latitude: <\/b> 19.41212<br\/>  <b>Longitude: <\/b> -155.28348<br\/>  <b>Detection Time: <\/b> 2022-11-15 12:20 UTC<br\/>  <b>Sensor: <\/b> NOAA-20 VIIRS<br\/> <b>Confidence: <\/b> Nominal<br\/>  <b>Day\/Night: <\/b> Night<br\/> <b>Scan: <\/b> 0.4 km<br\/> <b>Track: <\/b> 0.4 km<br\/> <b>FRP: <\/b> 57.84 MW<br\/> <b>Brightness: <\/b> 310.17 K" }, "geometry": { "type": "Point", "coordinates": [ -155.28348, 19.41212, 0.0 ] } },
{ "type": "Feature", "properties": { "Name": "Fire Detection Centroid ", "Description": "<b>Latitude: <\/b> 19.41288<br\/>  <b>Longitude: <\/b> -155.28745<br\/>  <b>Detection Time: <\/b> 2022-11-15 12:20 UTC<br\/>  <b>Sensor: <\/b> NOAA-20 VIIRS<br\/> <b>Confidence: <\/b> Nominal<br\/>  <b>Day\/Night: <\/b> Night<br\/> <b>Scan: <\/b> 0.4 km<br\/> <b>Track: <\/b> 0.4 km<br\/> <b>FRP: <\/b> 57.84 MW<br\/> <b>Brightness: <\/b> 308.6 K" }, "geometry": { "type": "Point", "coordinates": [ -155.28745, 19.41288, 0.0 ] } },
{ "type": "Feature", "properties": { "Name": "Fire Detection Centroid ", "Description": "<b>Latitude: <\/b> 19.40399<br\/>  <b>Longitude: <\/b> -155.28502<br\/>  <b>Detection Time: <\/b> 2022-11-15 12:20 UTC<br\/>  <b>Sensor: <\/b> NOAA-20 VIIRS<br\/> <b>Confidence: <\/b> Nominal<br\/>  <b>Day\/Night: <\/b> Night<br\/> <b>Scan: <\/b> 0.4 km<br\/> <b>Track: <\/b> 0.4 km<br\/> <b>FRP: <\/b> 2.87 MW<br\/> <b>Brightness: <\/b> 314.56 K" }, "geometry": { "type": "Point", "coordinates": [ -155.28502, 19.40399, 0.0 ] } },
{ "type": "Feature", "properties": { "Name": "Fire Detection Centroid ", "Description": "<b>Latitude: <\/b> 19.41619<br\/>  <b>Longitude: <\/b> -155.28275<br\/>  <b>Detection Time: <\/b> 2022-11-15 12:20 UTC<br\/>  <b>Sensor: <\/b> NOAA-20 VIIRS<br\/> <b>Confidence: <\/b> Nominal<br\/>  <b>Day\/Night: <\/b> Night<br\/> <b>Scan: <\/b> 0.4 km<br\/> <b>Track: <\/b> 0.4 km<br\/> <b>FRP: <\/b> 1.2 MW<br\/> <b>Brightness: <\/b> 300.28 K" }, "geometry": { "type": "Point", "coordinates": [ -155.28275, 19.41619, 0.0 ] } },
{ "type": "Feature", "properties": { "Name": "Fire Detection Centroid ", "Description": "<b>Latitude: <\/b> 19.40473<br\/>  <b>Longitude: <\/b> -155.28894<br\/>  <b>Detection Time: <\/b> 2022-11-15 12:20 UTC<br\/>  <b>Sensor: <\/b> NOAA-20 VIIRS<br\/> <b>Confidence: <\/b> Nominal<br\/>  <b>Day\/Night: <\/b> Night<br\/> <b>Scan: <\/b> 0.4 km<br\/> <b>Track: <\/b> 0.4 km<br\/> <b>FRP: <\/b> 2.87 MW<br\/> <b>Brightness: <\/b> 320.89 K" }, "geometry": { "type": "Point", "coordinates": [ -155.28894, 19.40473, 0.0 ] } }
]
}
