{
"type": "FeatureCollection",
"crs": { "type": "name", "properties": { "name": "urn:ogc:def:crs:OGC:1.3:CRS84" } },
"features": [
{ "type": "Feature", "properties": { "Name": "Fire Detection Centroid ", "Description": "<b>Latitude: <\/b> 45.32543<br\/>  <b>Longitude: <\/b> -75.30744<br\/>  <b>Detection Time: <\/b> 2022-09-24 16:29 UTC<br\/>  <b>Sensor: <\/b> NOAA-20 VIIRS<br\/> <b>Confidence: <\/b> Nominal<br\/>  <b>Day\/Night: <\/b> Day<br\/> <b>Scan: <\/b> 0.8 km<br\/> <b>Track: <\/b> 0.8 km<br\/> <b>FRP: <\/b> 13.78 MW<br\/> <b>Brightness: <\/b> 352.09 K" }, "geometry": { "type": "Point", "coordinates": [ -75.30744, 45.32543, 0.0 ] } },
{ "type": "Feature", "properties": { "Name": "Fire Detection Centroid ", "Description": "<b>Latitude: <\/b> 19.40619<br\/>  <b>Longitude: <\/b> -155.28801<br\/>  <b>Detection Time: <\/b> 2022-09-24 11:55 UTC<br\/>  <b>Sensor: <\/b> NOAA-20 VIIRS<br\/> <b>Confidence: <\/b> Nominal<br\/>  <b>Day\/Night: <\/b> Night<br\/> <b>Scan: <\/b> 0.39 km<br\/> <b>Track: <\/b> 0.36 km<br\/> <b>FRP: <\/b> 19.55 MW<br\/> <b>Brightness: <\/b> 351.01 K" }, "geometry": { "type": "Point", "coordinates": [ -155.28801, 19.40619, 0.0 ] } },
{ "type": "Feature", "properties": { "Name": "Fire Detection Centroid ", "Description": "<b>Latitude: <\/b> 19.40893<br\/>  <b>Longitude: <\/b> -155.2838<br\/>  <b>Detection Time: <\/b> 2022-09-24 11:55 UTC<br\/>  <b>Sensor: <\/b> NOAA-20 VIIRS<br\/> <b>Confidence: <\/b> Nominal<br\/>  <b>Day\/Night: <\/b> Night<br\/> <b>Scan: <\/b> 0.39 km<br\/> <b>Track: <\/b> 0.36 km<br\/> <b>FRP: <\/b> 5.95 MW<br\/> <b>Brightness: <\/b> 342.66 K" }, "geometry": { "type": "Point", "coordinates": [ -155.2838, 19.40893, 0.0 ] } },
{ "type": "Feature", "properties": { "Name": "Fire Detection Centroid ", "Description": "<b>Latitude: <\/b> 19.40949<br\/>  <b>Longitude: <\/b> -155.28745<br\/>  <b>Detection Time: <\/b> 2022-09-24 11:55 UTC<br\/>  <b>Sensor: <\/b> NOAA-20 VIIRS<br\/> <b>Confidence: <\/b> Nominal<br\/>  <b>Day\/Night: <\/b> Night<br\/> <b>Scan: <\/b> 0.39 km<br\/> <b>Track: <\/b> 0.36 km<br\/> <b>FRP: <\/b> 5.95 MW<br\/> <b>Brightness: <\/b> 343.11 K" }, "geometry": { "type": "Point", "coordinates": [ -155.28745, 19.40949, 0.0 ] } },
{ "type": "Feature", "properties": { "Name": "Fire Detection Centroid ", "Description": "<b>Latitude: <\/b> 20.86273<br\/>  <b>Longitude: <\/b> -156.42046<br\/>  <b>Detection Time: <\/b> 2022-09-24 11:55 UTC<br\/>  <b>Sensor: <\/b> NOAA-20 VIIRS<br\/> <b>Confidence: <\/b> Nominal<br\/>  <b>Day\/Night: <\/b> Night<br\/> <b>Scan: <\/b> 0.42 km<br\/> <b>Track: <\/b> 0.38 km<br\/> <b>FRP: <\/b> 0.53 MW<br\/> <b>Brightness: <\/b> 303.44 K" }, "geometry": { "type": "Point", "coordinates": [ -156.42046, 20.86273, 0.0 ] } },
{ "type": "Feature", "properties": { "Name": "Fire Detection Centroid ", "Description": "<b>Latitude: <\/b> 19.40563<br\/>  <b>Longitude: <\/b> -155.28436<br\/>  <b>Detection Time: <\/b> 2022-09-24 11:55 UTC<br\/>  <b>Sensor: <\/b> NOAA-20 VIIRS<br\/> <b>Confidence: <\/b> Nominal<br\/>  <b>Day\/Night: <\/b> Night<br\/> <b>Scan: <\/b> 0.39 km<br\/> <b>Track: <\/b> 0.36 km<br\/> <b>FRP: <\/b> 19.55 MW<br\/> <b>Brightness: <\/b> 344.89 K" }, "geometry": { "type": "Point", "coordinates": [ -155.28436, 19.40563, 0.0 ] } }
]
}
