{
"type": "FeatureCollection",
"crs": { "type": "name", "properties": { "name": "urn:ogc:def:crs:OGC:1.3:CRS84" } },
"features": [
{ "type": "Feature", "properties": { "Name": "Fire Detection Centroid ", "Description": "<b>Latitude: <\/b> 46.04233<br\/>  <b>Longitude: <\/b> -73.13921<br\/>  <b>Detection Time: <\/b> 2024-05-26 17:07 UTC<br\/>  <b>Sensor: <\/b> NOAA-20 VIIRS<br\/> <b>Confidence: <\/b> Low<br\/>  <b>Day\/Night: <\/b> Day<br\/> <b>Scan: <\/b> 0.44 km<br\/> <b>Track: <\/b> 0.46 km<br\/> <b>FRP: <\/b> 4.83 MW<br\/> <b>Brightness: <\/b> 330.11 K" }, "geometry": { "type": "Point", "coordinates": [ -73.13921, 46.04233, 0.0 ] } },
{ "type": "Feature", "properties": { "Name": "Fire Detection Centroid ", "Description": "<b>Latitude: <\/b> 46.04132<br\/>  <b>Longitude: <\/b> -73.14101<br\/>  <b>Detection Time: <\/b> 2024-05-26 17:07 UTC<br\/>  <b>Sensor: <\/b> NOAA-20 VIIRS<br\/> <b>Confidence: <\/b> Low<br\/>  <b>Day\/Night: <\/b> Day<br\/> <b>Scan: <\/b> 0.44 km<br\/> <b>Track: <\/b> 0.46 km<br\/> <b>FRP: <\/b> 3.01 MW<br\/> <b>Brightness: <\/b> 328.5 K" }, "geometry": { "type": "Point", "coordinates": [ -73.14101, 46.04132, 0.0 ] } },
{ "type": "Feature", "properties": { "Name": "Fire Detection Centroid ", "Description": "<b>Latitude: <\/b> 42.80674<br\/>  <b>Longitude: <\/b> -80.09812<br\/>  <b>Detection Time: <\/b> 2024-05-26 17:05 UTC<br\/>  <b>Sensor: <\/b> NOAA-20 VIIRS<br\/> <b>Confidence: <\/b> Nominal<br\/>  <b>Day\/Night: <\/b> Day<br\/> <b>Scan: <\/b> 0.57 km<br\/> <b>Track: <\/b> 0.69 km<br\/> <b>FRP: <\/b> 10.77 MW<br\/> <b>Brightness: <\/b> 337.28 K" }, "geometry": { "type": "Point", "coordinates": [ -80.09812, 42.80674, 0.0 ] } }
]
}
