{
"type": "FeatureCollection",
"crs": { "type": "name", "properties": { "name": "urn:ogc:def:crs:OGC:1.3:CRS84" } },
"features": [
{ "type": "Feature", "properties": { "Name": "Fire Detection Centroid ", "Description": "<b>Latitude: <\/b> 19.40871<br\/>  <b>Longitude: <\/b> -155.28535<br\/>  <b>Detection Time: <\/b> 2023-01-22 00:15 UTC<br\/>  <b>Sensor: <\/b> NOAA-20 VIIRS<br\/> <b>Confidence: <\/b> Nominal<br\/>  <b>Day\/Night: <\/b> Day<br\/> <b>Scan: <\/b> 0.43 km<br\/> <b>Track: <\/b> 0.62 km<br\/> <b>FRP: <\/b> 181.81 MW<br\/> <b>Brightness: <\/b> 354.15 K" }, "geometry": { "type": "Point", "coordinates": [ -155.28535, 19.40871, 0.0 ] } },
{ "type": "Feature", "properties": { "Name": "Fire Detection Centroid ", "Description": "<b>Latitude: <\/b> 19.40262<br\/>  <b>Longitude: <\/b> -155.28888<br\/>  <b>Detection Time: <\/b> 2023-01-22 00:15 UTC<br\/>  <b>Sensor: <\/b> NOAA-20 VIIRS<br\/> <b>Confidence: <\/b> Low<br\/>  <b>Day\/Night: <\/b> Day<br\/> <b>Scan: <\/b> 0.43 km<br\/> <b>Track: <\/b> 0.62 km<br\/> <b>FRP: <\/b> 124.87 MW<br\/> <b>Brightness: <\/b> 367 K" }, "geometry": { "type": "Point", "coordinates": [ -155.28888, 19.40262, 0.0 ] } },
{ "type": "Feature", "properties": { "Name": "Fire Detection Centroid ", "Description": "<b>Latitude: <\/b> 19.40344<br\/>  <b>Longitude: <\/b> -155.28046<br\/>  <b>Detection Time: <\/b> 2023-01-22 00:15 UTC<br\/>  <b>Sensor: <\/b> NOAA-20 VIIRS<br\/> <b>Confidence: <\/b> Low<br\/>  <b>Day\/Night: <\/b> Day<br\/> <b>Scan: <\/b> 0.43 km<br\/> <b>Track: <\/b> 0.62 km<br\/> <b>FRP: <\/b> 181.81 MW<br\/> <b>Brightness: <\/b> 367 K" }, "geometry": { "type": "Point", "coordinates": [ -155.28046, 19.40344, 0.0 ] } },
{ "type": "Feature", "properties": { "Name": "Fire Detection Centroid ", "Description": "<b>Latitude: <\/b> 19.40304<br\/>  <b>Longitude: <\/b> -155.28458<br\/>  <b>Detection Time: <\/b> 2023-01-22 00:15 UTC<br\/>  <b>Sensor: <\/b> NOAA-20 VIIRS<br\/> <b>Confidence: <\/b> Low<br\/>  <b>Day\/Night: <\/b> Day<br\/> <b>Scan: <\/b> 0.43 km<br\/> <b>Track: <\/b> 0.62 km<br\/> <b>FRP: <\/b> 181.81 MW<br\/> <b>Brightness: <\/b> 367 K" }, "geometry": { "type": "Point", "coordinates": [ -155.28458, 19.40304, 0.0 ] } },
{ "type": "Feature", "properties": { "Name": "Fire Detection Centroid ", "Description": "<b>Latitude: <\/b> 19.40913<br\/>  <b>Longitude: <\/b> -155.28108<br\/>  <b>Detection Time: <\/b> 2023-01-22 00:15 UTC<br\/>  <b>Sensor: <\/b> NOAA-20 VIIRS<br\/> <b>Confidence: <\/b> High<br\/>  <b>Day\/Night: <\/b> Day<br\/> <b>Scan: <\/b> 0.43 km<br\/> <b>Track: <\/b> 0.62 km<br\/> <b>FRP: <\/b> 181.81 MW<br\/> <b>Brightness: <\/b> 367 K" }, "geometry": { "type": "Point", "coordinates": [ -155.28108, 19.40913, 0.0 ] } },
{ "type": "Feature", "properties": { "Name": "Fire Detection Centroid ", "Description": "<b>Latitude: <\/b> 19.40384<br\/>  <b>Longitude: <\/b> -155.27634<br\/>  <b>Detection Time: <\/b> 2023-01-22 00:15 UTC<br\/>  <b>Sensor: <\/b> NOAA-20 VIIRS<br\/> <b>Confidence: <\/b> High<br\/>  <b>Day\/Night: <\/b> Day<br\/> <b>Scan: <\/b> 0.43 km<br\/> <b>Track: <\/b> 0.62 km<br\/> <b>FRP: <\/b> 211.97 MW<br\/> <b>Brightness: <\/b> 367 K" }, "geometry": { "type": "Point", "coordinates": [ -155.27634, 19.40384, 0.0 ] } }
]
}
