{
"type": "FeatureCollection",
"crs": { "type": "name", "properties": { "name": "urn:ogc:def:crs:OGC:1.3:CRS84" } },
"features": [
{ "type": "Feature", "properties": { "Name": "Fire Detection Centroid ", "Description": "<b>Latitude: <\/b> 20.84037<br\/>  <b>Longitude: <\/b> -156.47812<br\/>  <b>Detection Time: <\/b> 2023-09-01 22:57 UTC<br\/>  <b>Sensor: <\/b> NOAA-20 VIIRS<br\/> <b>Confidence: <\/b> Nominal<br\/>  <b>Day\/Night: <\/b> Day<br\/> <b>Scan: <\/b> 0.43 km<br\/> <b>Track: <\/b> 0.62 km<br\/> <b>FRP: <\/b> 2.35 MW<br\/> <b>Brightness: <\/b> 327.23 K" }, "geometry": { "type": "Point", "coordinates": [ -156.47812, 20.84037, 0.0 ] } },
{ "type": "Feature", "properties": { "Name": "Fire Detection Centroid ", "Description": "<b>Latitude: <\/b> 49.60803<br\/>  <b>Longitude: <\/b> -126.12532<br\/>  <b>Detection Time: <\/b> 2023-09-01 21:23 UTC<br\/>  <b>Sensor: <\/b> NOAA-20 VIIRS<br\/> <b>Confidence: <\/b> Nominal<br\/>  <b>Day\/Night: <\/b> Day<br\/> <b>Scan: <\/b> 0.42 km<br\/> <b>Track: <\/b> 0.38 km<br\/> <b>FRP: <\/b> 6.66 MW<br\/> <b>Brightness: <\/b> 336.49 K" }, "geometry": { "type": "Point", "coordinates": [ -126.12532, 49.60803, 0.0 ] } },
{ "type": "Feature", "properties": { "Name": "Fire Detection Centroid ", "Description": "<b>Latitude: <\/b> 48.9457<br\/>  <b>Longitude: <\/b> -122.56866<br\/>  <b>Detection Time: <\/b> 2023-09-01 21:23 UTC<br\/>  <b>Sensor: <\/b> NOAA-20 VIIRS<br\/> <b>Confidence: <\/b> Nominal<br\/>  <b>Day\/Night: <\/b> Day<br\/> <b>Scan: <\/b> 0.53 km<br\/> <b>Track: <\/b> 0.42 km<br\/> <b>FRP: <\/b> 4.14 MW<br\/> <b>Brightness: <\/b> 331.64 K" }, "geometry": { "type": "Point", "coordinates": [ -122.56866, 48.9457, 0.0 ] } }
]
}
