{
"type": "FeatureCollection",
"crs": { "type": "name", "properties": { "name": "urn:ogc:def:crs:OGC:1.3:CRS84" } },
"features": [
{ "type": "Feature", "properties": { "Name": "Fire Detection Centroid ", "Description": "<b>Latitude: <\/b> 49.99197<br\/>  <b>Longitude: <\/b> -114.00978<br\/>  <b>Detection Time: <\/b> 2024-03-28 11:00 UTC<br\/>  <b>Sensor: <\/b> NOAA-20 VIIRS<br\/> <b>Confidence: <\/b> Nominal<br\/>  <b>Day\/Night: <\/b> Night<br\/> <b>Scan: <\/b> 0.6 km<br\/> <b>Track: <\/b> 0.7 km<br\/> <b>FRP: <\/b> 2.02 MW<br\/> <b>Brightness: <\/b> 308.72 K" }, "geometry": { "type": "Point", "coordinates": [ -114.00978, 49.99197, 0.0 ] } },
{ "type": "Feature", "properties": { "Name": "Fire Detection Centroid ", "Description": "<b>Latitude: <\/b> 49.97518<br\/>  <b>Longitude: <\/b> -114.02731<br\/>  <b>Detection Time: <\/b> 2024-03-28 11:00 UTC<br\/>  <b>Sensor: <\/b> NOAA-20 VIIRS<br\/> <b>Confidence: <\/b> Nominal<br\/>  <b>Day\/Night: <\/b> Night<br\/> <b>Scan: <\/b> 0.57 km<br\/> <b>Track: <\/b> 0.69 km<br\/> <b>FRP: <\/b> 2.02 MW<br\/> <b>Brightness: <\/b> 308.72 K" }, "geometry": { "type": "Point", "coordinates": [ -114.02731, 49.97518, 0.0 ] } }
]
}
