{
"type": "FeatureCollection",
"crs": { "type": "name", "properties": { "name": "urn:ogc:def:crs:OGC:1.3:CRS84" } },
"features": [
{ "type": "Feature", "properties": { "Name": "Fire Detection Centroid ", "Description": "<b>Latitude: <\/b> 46.59741<br\/>  <b>Longitude: <\/b> -84.45403<br\/>  <b>Detection Time: <\/b> 2024-05-21 17:02 UTC<br\/>  <b>Sensor: <\/b> NOAA-20 VIIRS<br\/> <b>Confidence: <\/b> Nominal<br\/>  <b>Day\/Night: <\/b> Day<br\/> <b>Scan: <\/b> 0.8 km<br\/> <b>Track: <\/b> 0.8 km<br\/> <b>FRP: <\/b> 10.57 MW<br\/> <b>Brightness: <\/b> 331.36 K" }, "geometry": { "type": "Point", "coordinates": [ -84.45403, 46.59741, 0.0 ] } },
{ "type": "Feature", "properties": { "Name": "Fire Detection Centroid ", "Description": "<b>Latitude: <\/b> 46.40992<br\/>  <b>Longitude: <\/b> -84.30688<br\/>  <b>Detection Time: <\/b> 2024-05-21 17:02 UTC<br\/>  <b>Sensor: <\/b> NOAA-20 VIIRS<br\/> <b>Confidence: <\/b> Nominal<br\/>  <b>Day\/Night: <\/b> Day<br\/> <b>Scan: <\/b> 0.8 km<br\/> <b>Track: <\/b> 0.8 km<br\/> <b>FRP: <\/b> 10.95 MW<br\/> <b>Brightness: <\/b> 336.67 K" }, "geometry": { "type": "Point", "coordinates": [ -84.30688, 46.40992, 0.0 ] } },
{ "type": "Feature", "properties": { "Name": "Fire Detection Centroid ", "Description": "<b>Latitude: <\/b> 41.65646<br\/>  <b>Longitude: <\/b> -70.5704<br\/>  <b>Detection Time: <\/b> 2024-05-21 16:59 UTC<br\/>  <b>Sensor: <\/b> NOAA-20 VIIRS<br\/> <b>Confidence: <\/b> Nominal<br\/>  <b>Day\/Night: <\/b> Day<br\/> <b>Scan: <\/b> 0.5 km<br\/> <b>Track: <\/b> 0.5 km<br\/> <b>FRP: <\/b> 12.33 MW<br\/> <b>Brightness: <\/b> 346.01 K" }, "geometry": { "type": "Point", "coordinates": [ -70.5704, 41.65646, 0.0 ] } }
]
}
