{
"type": "FeatureCollection",
"crs": { "type": "name", "properties": { "name": "urn:ogc:def:crs:OGC:1.3:CRS84" } },
"features": [
{ "type": "Feature", "properties": { "Name": "Fire Detection Centroid ", "Description": "<b>Latitude: <\/b> 40.15564<br\/>  <b>Longitude: <\/b> -74.77349<br\/>  <b>Detection Time: <\/b> 2023-10-27 05:41 UTC<br\/>  <b>Sensor: <\/b> NOAA-20 VIIRS<br\/> <b>Confidence: <\/b> Nominal<br\/>  <b>Day\/Night: <\/b> Night<br\/> <b>Scan: <\/b> 0.8 km<br\/> <b>Track: <\/b> 0.8 km<br\/> <b>FRP: <\/b> 0.39 MW<br\/> <b>Brightness: <\/b> 296.02 K" }, "geometry": { "type": "Point", "coordinates": [ -74.77349, 40.15564, 0.0 ] } }
]
}
