{
"type": "FeatureCollection",
"crs": { "type": "name", "properties": { "name": "urn:ogc:def:crs:OGC:1.3:CRS84" } },
"features": [
{ "type": "Feature", "properties": { "Name": "Fire Detection Centroid ", "Description": "<b>Latitude: <\/b> 18.80082<br\/>  <b>Longitude: <\/b> -69.39856<br\/>  <b>Detection Time: <\/b> 2024-02-11 05:42 UTC<br\/>  <b>Sensor: <\/b> NOAA-20 VIIRS<br\/> <b>Confidence: <\/b> Nominal<br\/>  <b>Day\/Night: <\/b> Night<br\/> <b>Scan: <\/b> 0.6 km<br\/> <b>Track: <\/b> 0.5 km<br\/> <b>FRP: <\/b> 5.92 MW<br\/> <b>Brightness: <\/b> 328.48 K" }, "geometry": { "type": "Point", "coordinates": [ -69.39856, 18.80082, 0.0 ] } },
{ "type": "Feature", "properties": { "Name": "Fire Detection Centroid ", "Description": "<b>Latitude: <\/b> 18.24334<br\/>  <b>Longitude: <\/b> -70.45708<br\/>  <b>Detection Time: <\/b> 2024-02-11 05:42 UTC<br\/>  <b>Sensor: <\/b> NOAA-20 VIIRS<br\/> <b>Confidence: <\/b> Nominal<br\/>  <b>Day\/Night: <\/b> Night<br\/> <b>Scan: <\/b> 0.3 km<br\/> <b>Track: <\/b> 0.6 km<br\/> <b>FRP: <\/b> 0.58 MW<br\/> <b>Brightness: <\/b> 307.34 K" }, "geometry": { "type": "Point", "coordinates": [ -70.45708, 18.24334, 0.0 ] } },
{ "type": "Feature", "properties": { "Name": "Fire Detection Centroid ", "Description": "<b>Latitude: <\/b> 18.2898<br\/>  <b>Longitude: <\/b> -71.20284<br\/>  <b>Detection Time: <\/b> 2024-02-11 05:42 UTC<br\/>  <b>Sensor: <\/b> NOAA-20 VIIRS<br\/> <b>Confidence: <\/b> Nominal<br\/>  <b>Day\/Night: <\/b> Night<br\/> <b>Scan: <\/b> 0.4 km<br\/> <b>Track: <\/b> 0.6 km<br\/> <b>FRP: <\/b> 0.77 MW<br\/> <b>Brightness: <\/b> 308.4 K" }, "geometry": { "type": "Point", "coordinates": [ -71.20284, 18.2898, 0.0 ] } },
{ "type": "Feature", "properties": { "Name": "Fire Detection Centroid ", "Description": "<b>Latitude: <\/b> 18.29531<br\/>  <b>Longitude: <\/b> -71.20219<br\/>  <b>Detection Time: <\/b> 2024-02-11 05:42 UTC<br\/>  <b>Sensor: <\/b> NOAA-20 VIIRS<br\/> <b>Confidence: <\/b> Nominal<br\/>  <b>Day\/Night: <\/b> Night<br\/> <b>Scan: <\/b> 0.4 km<br\/> <b>Track: <\/b> 0.6 km<br\/> <b>FRP: <\/b> 1.91 MW<br\/> <b>Brightness: <\/b> 322.34 K" }, "geometry": { "type": "Point", "coordinates": [ -71.20219, 18.29531, 0.0 ] } },
{ "type": "Feature", "properties": { "Name": "Fire Detection Centroid ", "Description": "<b>Latitude: <\/b> 17.98824<br\/>  <b>Longitude: <\/b> -66.66<br\/>  <b>Detection Time: <\/b> 2024-02-11 05:42 UTC<br\/>  <b>Sensor: <\/b> NOAA-20 VIIRS<br\/> <b>Confidence: <\/b> Nominal<br\/>  <b>Day\/Night: <\/b> Night<br\/> <b>Scan: <\/b> 0.4 km<br\/> <b>Track: <\/b> 0.4 km<br\/> <b>FRP: <\/b> 0.26 MW<br\/> <b>Brightness: <\/b> 299.96 K" }, "geometry": { "type": "Point", "coordinates": [ -66.66, 17.98824, 0.0 ] } },
{ "type": "Feature", "properties": { "Name": "Fire Detection Centroid ", "Description": "<b>Latitude: <\/b> 18.59274<br\/>  <b>Longitude: <\/b> -69.42822<br\/>  <b>Detection Time: <\/b> 2024-02-11 05:42 UTC<br\/>  <b>Sensor: <\/b> NOAA-20 VIIRS<br\/> <b>Confidence: <\/b> Nominal<br\/>  <b>Day\/Night: <\/b> Night<br\/> <b>Scan: <\/b> 0.6 km<br\/> <b>Track: <\/b> 0.5 km<br\/> <b>FRP: <\/b> 4.64 MW<br\/> <b>Brightness: <\/b> 330.49 K" }, "geometry": { "type": "Point", "coordinates": [ -69.42822, 18.59274, 0.0 ] } }
]
}
