{
"type": "FeatureCollection",
"crs": { "type": "name", "properties": { "name": "urn:ogc:def:crs:OGC:1.3:CRS84" } },
"features": [
{ "type": "Feature", "properties": { "Name": "Fire Detection Centroid ", "Description": "<b>Latitude: <\/b> 41.63657<br\/>  <b>Longitude: <\/b> -87.1291<br\/>  <b>Detection Time: <\/b> 2023-02-01 17:31 UTC<br\/>  <b>Sensor: <\/b> NOAA-20 VIIRS<br\/> <b>Confidence: <\/b> Nominal<br\/>  <b>Day\/Night: <\/b> Day<br\/> <b>Scan: <\/b> 0.7 km<br\/> <b>Track: <\/b> 0.7 km<br\/> <b>FRP: <\/b> 5.35 MW<br\/> <b>Brightness: <\/b> 327.45 K" }, "geometry": { "type": "Point", "coordinates": [ -87.1291, 41.63657, 0.0 ] } },
{ "type": "Feature", "properties": { "Name": "Fire Detection Centroid ", "Description": "<b>Latitude: <\/b> 40.76991<br\/>  <b>Longitude: <\/b> -82.04389<br\/>  <b>Detection Time: <\/b> 2023-02-01 17:30 UTC<br\/>  <b>Sensor: <\/b> NOAA-20 VIIRS<br\/> <b>Confidence: <\/b> Nominal<br\/>  <b>Day\/Night: <\/b> Day<br\/> <b>Scan: <\/b> 0.4 km<br\/> <b>Track: <\/b> 0.6 km<br\/> <b>FRP: <\/b> 2.18 MW<br\/> <b>Brightness: <\/b> 326.35 K" }, "geometry": { "type": "Point", "coordinates": [ -82.04389, 40.76991, 0.0 ] } },
{ "type": "Feature", "properties": { "Name": "Fire Detection Centroid ", "Description": "<b>Latitude: <\/b> 41.45065<br\/>  <b>Longitude: <\/b> -81.6749<br\/>  <b>Detection Time: <\/b> 2023-02-01 17:30 UTC<br\/>  <b>Sensor: <\/b> NOAA-20 VIIRS<br\/> <b>Confidence: <\/b> Nominal<br\/>  <b>Day\/Night: <\/b> Day<br\/> <b>Scan: <\/b> 0.4 km<br\/> <b>Track: <\/b> 0.6 km<br\/> <b>FRP: <\/b> 5.24 MW<br\/> <b>Brightness: <\/b> 343.14 K" }, "geometry": { "type": "Point", "coordinates": [ -81.6749, 41.45065, 0.0 ] } },
{ "type": "Feature", "properties": { "Name": "Fire Detection Centroid ", "Description": "<b>Latitude: <\/b> 41.46318<br\/>  <b>Longitude: <\/b> -81.67133<br\/>  <b>Detection Time: <\/b> 2023-02-01 17:30 UTC<br\/>  <b>Sensor: <\/b> NOAA-20 VIIRS<br\/> <b>Confidence: <\/b> Nominal<br\/>  <b>Day\/Night: <\/b> Day<br\/> <b>Scan: <\/b> 0.4 km<br\/> <b>Track: <\/b> 0.6 km<br\/> <b>FRP: <\/b> 3.9 MW<br\/> <b>Brightness: <\/b> 333.47 K" }, "geometry": { "type": "Point", "coordinates": [ -81.67133, 41.46318, 0.0 ] } },
{ "type": "Feature", "properties": { "Name": "Fire Detection Centroid ", "Description": "<b>Latitude: <\/b> 38.97234<br\/>  <b>Longitude: <\/b> -77.81728<br\/>  <b>Detection Time: <\/b> 2023-02-01 17:29 UTC<br\/>  <b>Sensor: <\/b> NOAA-20 VIIRS<br\/> <b>Confidence: <\/b> Nominal<br\/>  <b>Day\/Night: <\/b> Day<br\/> <b>Scan: <\/b> 0.6 km<br\/> <b>Track: <\/b> 0.5 km<br\/> <b>FRP: <\/b> 10.5 MW<br\/> <b>Brightness: <\/b> 340.63 K" }, "geometry": { "type": "Point", "coordinates": [ -77.81728, 38.97234, 0.0 ] } }
]
}
