{
"type": "FeatureCollection",
"crs": { "type": "name", "properties": { "name": "urn:ogc:def:crs:OGC:1.3:CRS84" } },
"features": [
{ "type": "Feature", "properties": { "Name": "Fire Detection Centroid ", "Description": "<b>Latitude: <\/b> 36.83906<br\/>  <b>Longitude: <\/b> -78.60578<br\/>  <b>Detection Time: <\/b> 2022-09-22 17:04 UTC<br\/>  <b>Sensor: <\/b> NOAA-20 VIIRS<br\/> <b>Confidence: <\/b> Nominal<br\/>  <b>Day\/Night: <\/b> Day<br\/> <b>Scan: <\/b> 0.8 km<br\/> <b>Track: <\/b> 0.8 km<br\/> <b>FRP: <\/b> 12.05 MW<br\/> <b>Brightness: <\/b> 334.13 K" }, "geometry": { "type": "Point", "coordinates": [ -78.60578, 36.83906, 0.0 ] } },
{ "type": "Feature", "properties": { "Name": "Fire Detection Centroid ", "Description": "<b>Latitude: <\/b> 36.83807<br\/>  <b>Longitude: <\/b> -78.605<br\/>  <b>Detection Time: <\/b> 2022-09-22 17:04 UTC<br\/>  <b>Sensor: <\/b> NOAA-20 VIIRS<br\/> <b>Confidence: <\/b> Nominal<br\/>  <b>Day\/Night: <\/b> Day<br\/> <b>Scan: <\/b> 0.7 km<br\/> <b>Track: <\/b> 0.8 km<br\/> <b>FRP: <\/b> 7.42 MW<br\/> <b>Brightness: <\/b> 334.35 K" }, "geometry": { "type": "Point", "coordinates": [ -78.605, 36.83807, 0.0 ] } },
{ "type": "Feature", "properties": { "Name": "Fire Detection Centroid ", "Description": "<b>Latitude: <\/b> 36.84464<br\/>  <b>Longitude: <\/b> -78.60829<br\/>  <b>Detection Time: <\/b> 2022-09-22 17:04 UTC<br\/>  <b>Sensor: <\/b> NOAA-20 VIIRS<br\/> <b>Confidence: <\/b> Nominal<br\/>  <b>Day\/Night: <\/b> Day<br\/> <b>Scan: <\/b> 0.7 km<br\/> <b>Track: <\/b> 0.8 km<br\/> <b>FRP: <\/b> 9.85 MW<br\/> <b>Brightness: <\/b> 338.32 K" }, "geometry": { "type": "Point", "coordinates": [ -78.60829, 36.84464, 0.0 ] } },
{ "type": "Feature", "properties": { "Name": "Fire Detection Centroid ", "Description": "<b>Latitude: <\/b> 36.84159<br\/>  <b>Longitude: <\/b> -78.59773<br\/>  <b>Detection Time: <\/b> 2022-09-22 17:04 UTC<br\/>  <b>Sensor: <\/b> NOAA-20 VIIRS<br\/> <b>Confidence: <\/b> Nominal<br\/>  <b>Day\/Night: <\/b> Day<br\/> <b>Scan: <\/b> 0.7 km<br\/> <b>Track: <\/b> 0.8 km<br\/> <b>FRP: <\/b> 12.05 MW<br\/> <b>Brightness: <\/b> 335 K" }, "geometry": { "type": "Point", "coordinates": [ -78.59773, 36.84159, 0.0 ] } },
{ "type": "Feature", "properties": { "Name": "Fire Detection Centroid ", "Description": "<b>Latitude: <\/b> 36.83582<br\/>  <b>Longitude: <\/b> -78.13546<br\/>  <b>Detection Time: <\/b> 2022-09-22 17:04 UTC<br\/>  <b>Sensor: <\/b> NOAA-20 VIIRS<br\/> <b>Confidence: <\/b> Nominal<br\/>  <b>Day\/Night: <\/b> Day<br\/> <b>Scan: <\/b> 0.7 km<br\/> <b>Track: <\/b> 0.8 km<br\/> <b>FRP: <\/b> 8.12 MW<br\/> <b>Brightness: <\/b> 336.08 K" }, "geometry": { "type": "Point", "coordinates": [ -78.13546, 36.83582, 0.0 ] } }
]
}
