{
"type": "FeatureCollection",
"crs": { "type": "name", "properties": { "name": "urn:ogc:def:crs:OGC:1.3:CRS84" } },
"features": [
{ "type": "Feature", "properties": { "Name": "Fire Detection Centroid ", "Description": "<b>Latitude: <\/b> 21.48514<br\/>  <b>Longitude: <\/b> -157.93924<br\/>  <b>Detection Time: <\/b> 2023-11-01 00:10 UTC<br\/>  <b>Sensor: <\/b> NOAA-20 VIIRS<br\/> <b>Confidence: <\/b> Nominal<br\/>  <b>Day\/Night: <\/b> Day<br\/> <b>Scan: <\/b> 0.5 km<br\/> <b>Track: <\/b> 0.5 km<br\/> <b>FRP: <\/b> 4.97 MW<br\/> <b>Brightness: <\/b> 334.62 K" }, "geometry": { "type": "Point", "coordinates": [ -157.93924, 21.48514, 0.0 ] } },
{ "type": "Feature", "properties": { "Name": "Fire Detection Centroid ", "Description": "<b>Latitude: <\/b> 21.48074<br\/>  <b>Longitude: <\/b> -157.93852<br\/>  <b>Detection Time: <\/b> 2023-11-01 00:10 UTC<br\/>  <b>Sensor: <\/b> NOAA-20 VIIRS<br\/> <b>Confidence: <\/b> Nominal<br\/>  <b>Day\/Night: <\/b> Day<br\/> <b>Scan: <\/b> 0.5 km<br\/> <b>Track: <\/b> 0.5 km<br\/> <b>FRP: <\/b> 3.67 MW<br\/> <b>Brightness: <\/b> 337.01 K" }, "geometry": { "type": "Point", "coordinates": [ -157.93852, 21.48074, 0.0 ] } },
{ "type": "Feature", "properties": { "Name": "Fire Detection Centroid ", "Description": "<b>Latitude: <\/b> 21.48463<br\/>  <b>Longitude: <\/b> -157.94365<br\/>  <b>Detection Time: <\/b> 2023-11-01 00:10 UTC<br\/>  <b>Sensor: <\/b> NOAA-20 VIIRS<br\/> <b>Confidence: <\/b> Nominal<br\/>  <b>Day\/Night: <\/b> Day<br\/> <b>Scan: <\/b> 0.5 km<br\/> <b>Track: <\/b> 0.5 km<br\/> <b>FRP: <\/b> 5.09 MW<br\/> <b>Brightness: <\/b> 335.8 K" }, "geometry": { "type": "Point", "coordinates": [ -157.94365, 21.48463, 0.0 ] } }
]
}
