{
"type": "FeatureCollection",
"crs": { "type": "name", "properties": { "name": "urn:ogc:def:crs:OGC:1.3:CRS84" } },
"features": [
{ "type": "Feature", "properties": { "Name": "Fire Detection Centroid ", "Description": "<b>Latitude: <\/b> 17.73266<br\/>  <b>Longitude: <\/b> -64.74359<br\/>  <b>Detection Time: <\/b> 2024-03-25 05:28 UTC<br\/>  <b>Sensor: <\/b> NOAA-20 VIIRS<br\/> <b>Confidence: <\/b> Nominal<br\/>  <b>Day\/Night: <\/b> Night<br\/> <b>Scan: <\/b> 0.5 km<br\/> <b>Track: <\/b> 0.5 km<br\/> <b>FRP: <\/b> 1.64 MW<br\/> <b>Brightness: <\/b> 307.42 K" }, "geometry": { "type": "Point", "coordinates": [ -64.74359, 17.73266, 0.0 ] } },
{ "type": "Feature", "properties": { "Name": "Fire Detection Centroid ", "Description": "<b>Latitude: <\/b> 18.61964<br\/>  <b>Longitude: <\/b> -71.5896<br\/>  <b>Detection Time: <\/b> 2024-03-25 05:27 UTC<br\/>  <b>Sensor: <\/b> NOAA-20 VIIRS<br\/> <b>Confidence: <\/b> High<br\/>  <b>Day\/Night: <\/b> Night<br\/> <b>Scan: <\/b> 0.7 km<br\/> <b>Track: <\/b> 0.8 km<br\/> <b>FRP: <\/b> 40.98 MW<br\/> <b>Brightness: <\/b> 367 K" }, "geometry": { "type": "Point", "coordinates": [ -71.5896, 18.61964, 0.0 ] } },
{ "type": "Feature", "properties": { "Name": "Fire Detection Centroid ", "Description": "<b>Latitude: <\/b> 18.61917<br\/>  <b>Longitude: <\/b> -71.58395<br\/>  <b>Detection Time: <\/b> 2024-03-25 05:27 UTC<br\/>  <b>Sensor: <\/b> NOAA-20 VIIRS<br\/> <b>Confidence: <\/b> Nominal<br\/>  <b>Day\/Night: <\/b> Night<br\/> <b>Scan: <\/b> 0.7 km<br\/> <b>Track: <\/b> 0.8 km<br\/> <b>FRP: <\/b> 40.98 MW<br\/> <b>Brightness: <\/b> 347.92 K" }, "geometry": { "type": "Point", "coordinates": [ -71.58395, 18.61917, 0.0 ] } },
{ "type": "Feature", "properties": { "Name": "Fire Detection Centroid ", "Description": "<b>Latitude: <\/b> 18.62009<br\/>  <b>Longitude: <\/b> -71.59508<br\/>  <b>Detection Time: <\/b> 2024-03-25 05:27 UTC<br\/>  <b>Sensor: <\/b> NOAA-20 VIIRS<br\/> <b>Confidence: <\/b> Nominal<br\/>  <b>Day\/Night: <\/b> Night<br\/> <b>Scan: <\/b> 0.7 km<br\/> <b>Track: <\/b> 0.8 km<br\/> <b>FRP: <\/b> 7.78 MW<br\/> <b>Brightness: <\/b> 303.42 K" }, "geometry": { "type": "Point", "coordinates": [ -71.59508, 18.62009, 0.0 ] } },
{ "type": "Feature", "properties": { "Name": "Fire Detection Centroid ", "Description": "<b>Latitude: <\/b> 18.61871<br\/>  <b>Longitude: <\/b> -71.57836<br\/>  <b>Detection Time: <\/b> 2024-03-25 05:27 UTC<br\/>  <b>Sensor: <\/b> NOAA-20 VIIRS<br\/> <b>Confidence: <\/b> Nominal<br\/>  <b>Day\/Night: <\/b> Night<br\/> <b>Scan: <\/b> 0.7 km<br\/> <b>Track: <\/b> 0.8 km<br\/> <b>FRP: <\/b> 18.63 MW<br\/> <b>Brightness: <\/b> 298.76 K" }, "geometry": { "type": "Point", "coordinates": [ -71.57836, 18.61871, 0.0 ] } },
{ "type": "Feature", "properties": { "Name": "Fire Detection Centroid ", "Description": "<b>Latitude: <\/b> 18.62663<br\/>  <b>Longitude: <\/b> -71.58849<br\/>  <b>Detection Time: <\/b> 2024-03-25 05:27 UTC<br\/>  <b>Sensor: <\/b> NOAA-20 VIIRS<br\/> <b>Confidence: <\/b> Nominal<br\/>  <b>Day\/Night: <\/b> Night<br\/> <b>Scan: <\/b> 0.7 km<br\/> <b>Track: <\/b> 0.8 km<br\/> <b>FRP: <\/b> 1.73 MW<br\/> <b>Brightness: <\/b> 299.68 K" }, "geometry": { "type": "Point", "coordinates": [ -71.58849, 18.62663, 0.0 ] } }
]
}
