{
"type": "FeatureCollection",
"crs": { "type": "name", "properties": { "name": "urn:ogc:def:crs:OGC:1.3:CRS84" } },
"features": [
{ "type": "Feature", "properties": { "Name": "Fire Detection Centroid ", "Description": "<b>Latitude: <\/b> 19.36854<br\/>  <b>Longitude: <\/b> -155.3094<br\/>  <b>Detection Time: <\/b> 2024-06-08 11:49 UTC<br\/>  <b>Sensor: <\/b> NOAA-20 VIIRS<br\/> <b>Confidence: <\/b> Nominal<br\/>  <b>Day\/Night: <\/b> Night<br\/> <b>Scan: <\/b> 0.42 km<br\/> <b>Track: <\/b> 0.38 km<br\/> <b>FRP: <\/b> 2.09 MW<br\/> <b>Brightness: <\/b> 321.5 K" }, "geometry": { "type": "Point", "coordinates": [ -155.3094, 19.36854, 0.0 ] } },
{ "type": "Feature", "properties": { "Name": "Fire Detection Centroid ", "Description": "<b>Latitude: <\/b> 19.36511<br\/>  <b>Longitude: <\/b> -155.30998<br\/>  <b>Detection Time: <\/b> 2024-06-08 11:49 UTC<br\/>  <b>Sensor: <\/b> NOAA-20 VIIRS<br\/> <b>Confidence: <\/b> Nominal<br\/>  <b>Day\/Night: <\/b> Night<br\/> <b>Scan: <\/b> 0.42 km<br\/> <b>Track: <\/b> 0.38 km<br\/> <b>FRP: <\/b> 2.09 MW<br\/> <b>Brightness: <\/b> 302.13 K" }, "geometry": { "type": "Point", "coordinates": [ -155.30998, 19.36511, 0.0 ] } }
]
}
