{
"type": "FeatureCollection",
"crs": { "type": "name", "properties": { "name": "urn:ogc:def:crs:OGC:1.3:CRS84" } },
"features": [
{ "type": "Feature", "properties": { "Name": "Fire Detection Centroid ", "Description": "<b>Latitude: <\/b> 47.56974<br\/>  <b>Longitude: <\/b> -122.37074<br\/>  <b>Detection Time: <\/b> 2024-05-07 21:27 UTC<br\/>  <b>Sensor: <\/b> NOAA-20 VIIRS<br\/> <b>Confidence: <\/b> Nominal<br\/>  <b>Day\/Night: <\/b> Day<br\/> <b>Scan: <\/b> 0.41 km<br\/> <b>Track: <\/b> 0.45 km<br\/> <b>FRP: <\/b> 4.64 MW<br\/> <b>Brightness: <\/b> 331.06 K" }, "geometry": { "type": "Point", "coordinates": [ -122.37074, 47.56974, 0.0 ] } },
{ "type": "Feature", "properties": { "Name": "Fire Detection Centroid ", "Description": "<b>Latitude: <\/b> 47.49168<br\/>  <b>Longitude: <\/b> -122.35717<br\/>  <b>Detection Time: <\/b> 2024-05-07 21:27 UTC<br\/>  <b>Sensor: <\/b> NOAA-20 VIIRS<br\/> <b>Confidence: <\/b> Nominal<br\/>  <b>Day\/Night: <\/b> Day<br\/> <b>Scan: <\/b> 0.4 km<br\/> <b>Track: <\/b> 0.4 km<br\/> <b>FRP: <\/b> 4.64 MW<br\/> <b>Brightness: <\/b> 331.06 K" }, "geometry": { "type": "Point", "coordinates": [ -122.35717, 47.49168, 0.0 ] } },
{ "type": "Feature", "properties": { "Name": "Fire Detection Centroid ", "Description": "<b>Latitude: <\/b> 45.1941<br\/>  <b>Longitude: <\/b> -123.1553<br\/>  <b>Detection Time: <\/b> 2024-05-07 21:26 UTC<br\/>  <b>Sensor: <\/b> NOAA-20 VIIRS<br\/> <b>Confidence: <\/b> Nominal<br\/>  <b>Day\/Night: <\/b> Day<br\/> <b>Scan: <\/b> 0.5 km<br\/> <b>Track: <\/b> 0.4 km<br\/> <b>FRP: <\/b> 5.86 MW<br\/> <b>Brightness: <\/b> 332.66 K" }, "geometry": { "type": "Point", "coordinates": [ -123.1553, 45.1941, 0.0 ] } },
{ "type": "Feature", "properties": { "Name": "Fire Detection Centroid ", "Description": "<b>Latitude: <\/b> 39.33362<br\/>  <b>Longitude: <\/b> -123.0786<br\/>  <b>Detection Time: <\/b> 2024-05-07 21:25 UTC<br\/>  <b>Sensor: <\/b> NOAA-20 VIIRS<br\/> <b>Confidence: <\/b> Low<br\/>  <b>Day\/Night: <\/b> Day<br\/> <b>Scan: <\/b> 0.5 km<br\/> <b>Track: <\/b> 0.4 km<br\/> <b>FRP: <\/b> 2.36 MW<br\/> <b>Brightness: <\/b> 327.41 K" }, "geometry": { "type": "Point", "coordinates": [ -123.0786, 39.33362, 0.0 ] } },
{ "type": "Feature", "properties": { "Name": "Fire Detection Centroid ", "Description": "<b>Latitude: <\/b> 34.58268<br\/>  <b>Longitude: <\/b> -111.34432<br\/>  <b>Detection Time: <\/b> 2024-05-07 21:25 UTC<br\/>  <b>Sensor: <\/b> NOAA-20 VIIRS<br\/> <b>Confidence: <\/b> Nominal<br\/>  <b>Day\/Night: <\/b> Day<br\/> <b>Scan: <\/b> 0.59 km<br\/> <b>Track: <\/b> 0.7 km<br\/> <b>FRP: <\/b> 24.93 MW<br\/> <b>Brightness: <\/b> 337.35 K" }, "geometry": { "type": "Point", "coordinates": [ -111.34432, 34.58268, 0.0 ] } },
{ "type": "Feature", "properties": { "Name": "Fire Detection Centroid ", "Description": "<b>Latitude: <\/b> 45.22866<br\/>  <b>Longitude: <\/b> -123.16189<br\/>  <b>Detection Time: <\/b> 2024-05-07 21:25 UTC<br\/>  <b>Sensor: <\/b> NOAA-20 VIIRS<br\/> <b>Confidence: <\/b> Nominal<br\/>  <b>Day\/Night: <\/b> Day<br\/> <b>Scan: <\/b> 0.54 km<br\/> <b>Track: <\/b> 0.42 km<br\/> <b>FRP: <\/b> 5.86 MW<br\/> <b>Brightness: <\/b> 332.66 K" }, "geometry": { "type": "Point", "coordinates": [ -123.16189, 45.22866, 0.0 ] } },
{ "type": "Feature", "properties": { "Name": "Fire Detection Centroid ", "Description": "<b>Latitude: <\/b> 34.58291<br\/>  <b>Longitude: <\/b> -111.33801<br\/>  <b>Detection Time: <\/b> 2024-05-07 21:25 UTC<br\/>  <b>Sensor: <\/b> NOAA-20 VIIRS<br\/> <b>Confidence: <\/b> High<br\/>  <b>Day\/Night: <\/b> Day<br\/> <b>Scan: <\/b> 0.59 km<br\/> <b>Track: <\/b> 0.7 km<br\/> <b>FRP: <\/b> 24.93 MW<br\/> <b>Brightness: <\/b> 367 K" }, "geometry": { "type": "Point", "coordinates": [ -111.33801, 34.58291, 0.0 ] } },
{ "type": "Feature", "properties": { "Name": "Fire Detection Centroid ", "Description": "<b>Latitude: <\/b> 33.91217<br\/>  <b>Longitude: <\/b> -116.80163<br\/>  <b>Detection Time: <\/b> 2024-05-07 21:25 UTC<br\/>  <b>Sensor: <\/b> NOAA-20 VIIRS<br\/> <b>Confidence: <\/b> High<br\/>  <b>Day\/Night: <\/b> Day<br\/> <b>Scan: <\/b> 0.56 km<br\/> <b>Track: <\/b> 0.51 km<br\/> <b>FRP: <\/b> 14.38 MW<br\/> <b>Brightness: <\/b> 367 K" }, "geometry": { "type": "Point", "coordinates": [ -116.80163, 33.91217, 0.0 ] } },
{ "type": "Feature", "properties": { "Name": "Fire Detection Centroid ", "Description": "<b>Latitude: <\/b> 34.57643<br\/>  <b>Longitude: <\/b> -111.33784<br\/>  <b>Detection Time: <\/b> 2024-05-07 21:25 UTC<br\/>  <b>Sensor: <\/b> NOAA-20 VIIRS<br\/> <b>Confidence: <\/b> Nominal<br\/>  <b>Day\/Night: <\/b> Day<br\/> <b>Scan: <\/b> 0.59 km<br\/> <b>Track: <\/b> 0.7 km<br\/> <b>FRP: <\/b> 4.62 MW<br\/> <b>Brightness: <\/b> 330.22 K" }, "geometry": { "type": "Point", "coordinates": [ -111.33784, 34.57643, 0.0 ] } }
]
}
