{
"type": "FeatureCollection",
"crs": { "type": "name", "properties": { "name": "urn:ogc:def:crs:OGC:1.3:CRS84" } },
"features": [
{ "type": "Feature", "properties": { "Name": "Fire Detection Centroid ", "Description": "<b>Latitude: <\/b> 19.40283<br\/>  <b>Longitude: <\/b> -155.27995<br\/>  <b>Detection Time: <\/b> 2022-09-02 23:18 UTC<br\/>  <b>Sensor: <\/b> NOAA-20 VIIRS<br\/> <b>Confidence: <\/b> Low<br\/>  <b>Day\/Night: <\/b> Day<br\/> <b>Scan: <\/b> 0.48 km<br\/> <b>Track: <\/b> 0.4 km<br\/> <b>FRP: <\/b> 11.22 MW<br\/> <b>Brightness: <\/b> 331.85 K" }, "geometry": { "type": "Point", "coordinates": [ -155.27995, 19.40283, 0.0 ] } },
{ "type": "Feature", "properties": { "Name": "Fire Detection Centroid ", "Description": "<b>Latitude: <\/b> 19.41092<br\/>  <b>Longitude: <\/b> -155.27682<br\/>  <b>Detection Time: <\/b> 2022-09-02 23:18 UTC<br\/>  <b>Sensor: <\/b> NOAA-20 VIIRS<br\/> <b>Confidence: <\/b> Low<br\/>  <b>Day\/Night: <\/b> Day<br\/> <b>Scan: <\/b> 0.48 km<br\/> <b>Track: <\/b> 0.4 km<br\/> <b>FRP: <\/b> 11.33 MW<br\/> <b>Brightness: <\/b> 335.35 K" }, "geometry": { "type": "Point", "coordinates": [ -155.27682, 19.41092, 0.0 ] } },
{ "type": "Feature", "properties": { "Name": "Fire Detection Centroid ", "Description": "<b>Latitude: <\/b> 19.41014<br\/>  <b>Longitude: <\/b> -155.28133<br\/>  <b>Detection Time: <\/b> 2022-09-02 23:18 UTC<br\/>  <b>Sensor: <\/b> NOAA-20 VIIRS<br\/> <b>Confidence: <\/b> Low<br\/>  <b>Day\/Night: <\/b> Day<br\/> <b>Scan: <\/b> 0.48 km<br\/> <b>Track: <\/b> 0.4 km<br\/> <b>FRP: <\/b> 45.63 MW<br\/> <b>Brightness: <\/b> 349.84 K" }, "geometry": { "type": "Point", "coordinates": [ -155.28133, 19.41014, 0.0 ] } },
{ "type": "Feature", "properties": { "Name": "Fire Detection Centroid ", "Description": "<b>Latitude: <\/b> 19.40255<br\/>  <b>Longitude: <\/b> -155.28018<br\/>  <b>Detection Time: <\/b> 2022-09-02 23:18 UTC<br\/>  <b>Sensor: <\/b> NOAA-20 VIIRS<br\/> <b>Confidence: <\/b> Low<br\/>  <b>Day\/Night: <\/b> Day<br\/> <b>Scan: <\/b> 0.5 km<br\/> <b>Track: <\/b> 0.4 km<br\/> <b>FRP: <\/b> 11.21 MW<br\/> <b>Brightness: <\/b> 331.85 K" }, "geometry": { "type": "Point", "coordinates": [ -155.28018, 19.40255, 0.0 ] } },
{ "type": "Feature", "properties": { "Name": "Fire Detection Centroid ", "Description": "<b>Latitude: <\/b> 19.40935<br\/>  <b>Longitude: <\/b> -155.28584<br\/>  <b>Detection Time: <\/b> 2022-09-02 23:18 UTC<br\/>  <b>Sensor: <\/b> NOAA-20 VIIRS<br\/> <b>Confidence: <\/b> Nominal<br\/>  <b>Day\/Night: <\/b> Day<br\/> <b>Scan: <\/b> 0.49 km<br\/> <b>Track: <\/b> 0.4 km<br\/> <b>FRP: <\/b> 45.63 MW<br\/> <b>Brightness: <\/b> 355.07 K" }, "geometry": { "type": "Point", "coordinates": [ -155.28584, 19.40935, 0.0 ] } },
{ "type": "Feature", "properties": { "Name": "Fire Detection Centroid ", "Description": "<b>Latitude: <\/b> 19.40907<br\/>  <b>Longitude: <\/b> -155.28606<br\/>  <b>Detection Time: <\/b> 2022-09-02 23:18 UTC<br\/>  <b>Sensor: <\/b> NOAA-20 VIIRS<br\/> <b>Confidence: <\/b> Nominal<br\/>  <b>Day\/Night: <\/b> Day<br\/> <b>Scan: <\/b> 0.5 km<br\/> <b>Track: <\/b> 0.4 km<br\/> <b>FRP: <\/b> 45.63 MW<br\/> <b>Brightness: <\/b> 355.07 K" }, "geometry": { "type": "Point", "coordinates": [ -155.28606, 19.40907, 0.0 ] } },
{ "type": "Feature", "properties": { "Name": "Fire Detection Centroid ", "Description": "<b>Latitude: <\/b> 19.40986<br\/>  <b>Longitude: <\/b> -155.28156<br\/>  <b>Detection Time: <\/b> 2022-09-02 23:18 UTC<br\/>  <b>Sensor: <\/b> NOAA-20 VIIRS<br\/> <b>Confidence: <\/b> Low<br\/>  <b>Day\/Night: <\/b> Day<br\/> <b>Scan: <\/b> 0.5 km<br\/> <b>Track: <\/b> 0.4 km<br\/> <b>FRP: <\/b> 45.63 MW<br\/> <b>Brightness: <\/b> 349.84 K" }, "geometry": { "type": "Point", "coordinates": [ -155.28156, 19.40986, 0.0 ] } },
{ "type": "Feature", "properties": { "Name": "Fire Detection Centroid ", "Description": "<b>Latitude: <\/b> 19.41064<br\/>  <b>Longitude: <\/b> -155.27704<br\/>  <b>Detection Time: <\/b> 2022-09-02 23:18 UTC<br\/>  <b>Sensor: <\/b> NOAA-20 VIIRS<br\/> <b>Confidence: <\/b> Low<br\/>  <b>Day\/Night: <\/b> Day<br\/> <b>Scan: <\/b> 0.5 km<br\/> <b>Track: <\/b> 0.4 km<br\/> <b>FRP: <\/b> 11.33 MW<br\/> <b>Brightness: <\/b> 335.35 K" }, "geometry": { "type": "Point", "coordinates": [ -155.27704, 19.41064, 0.0 ] } }
]
}
