{
"type": "FeatureCollection",
"crs": { "type": "name", "properties": { "name": "urn:ogc:def:crs:OGC:1.3:CRS84" } },
"features": [
{ "type": "Feature", "properties": { "Name": "Fire Detection Centroid ", "Description": "<b>Latitude: <\/b> 43.14716<br\/>  <b>Longitude: <\/b> -115.66467<br\/>  <b>Detection Time: <\/b> 2023-04-15 10:01 UTC<br\/>  <b>Sensor: <\/b> NOAA-20 VIIRS<br\/> <b>Confidence: <\/b> Nominal<br\/>  <b>Day\/Night: <\/b> Night<br\/> <b>Scan: <\/b> 0.5 km<br\/> <b>Track: <\/b> 0.4 km<br\/> <b>FRP: <\/b> 0.83 MW<br\/> <b>Brightness: <\/b> 295.24 K" }, "geometry": { "type": "Point", "coordinates": [ -115.66467, 43.14716, 0.0 ] } },
{ "type": "Feature", "properties": { "Name": "Fire Detection Centroid ", "Description": "<b>Latitude: <\/b> 44.06221<br\/>  <b>Longitude: <\/b> -122.98179<br\/>  <b>Detection Time: <\/b> 2023-04-15 10:01 UTC<br\/>  <b>Sensor: <\/b> NOAA-20 VIIRS<br\/> <b>Confidence: <\/b> Nominal<br\/>  <b>Day\/Night: <\/b> Night<br\/> <b>Scan: <\/b> 0.4 km<br\/> <b>Track: <\/b> 0.4 km<br\/> <b>FRP: <\/b> 0.64 MW<br\/> <b>Brightness: <\/b> 300.65 K" }, "geometry": { "type": "Point", "coordinates": [ -122.98179, 44.06221, 0.0 ] } },
{ "type": "Feature", "properties": { "Name": "Fire Detection Centroid ", "Description": "<b>Latitude: <\/b> 42.68858<br\/>  <b>Longitude: <\/b> -111.59149<br\/>  <b>Detection Time: <\/b> 2023-04-15 10:01 UTC<br\/>  <b>Sensor: <\/b> NOAA-20 VIIRS<br\/> <b>Confidence: <\/b> Nominal<br\/>  <b>Day\/Night: <\/b> Night<br\/> <b>Scan: <\/b> 0.5 km<br\/> <b>Track: <\/b> 0.5 km<br\/> <b>FRP: <\/b> 9.81 MW<br\/> <b>Brightness: <\/b> 350.2 K" }, "geometry": { "type": "Point", "coordinates": [ -111.59149, 42.68858, 0.0 ] } },
{ "type": "Feature", "properties": { "Name": "Fire Detection Centroid ", "Description": "<b>Latitude: <\/b> 42.68423<br\/>  <b>Longitude: <\/b> -111.59333<br\/>  <b>Detection Time: <\/b> 2023-04-15 10:01 UTC<br\/>  <b>Sensor: <\/b> NOAA-20 VIIRS<br\/> <b>Confidence: <\/b> Nominal<br\/>  <b>Day\/Night: <\/b> Night<br\/> <b>Scan: <\/b> 0.5 km<br\/> <b>Track: <\/b> 0.5 km<br\/> <b>FRP: <\/b> 9.81 MW<br\/> <b>Brightness: <\/b> 338.13 K" }, "geometry": { "type": "Point", "coordinates": [ -111.59333, 42.68423, 0.0 ] } },
{ "type": "Feature", "properties": { "Name": "Fire Detection Centroid ", "Description": "<b>Latitude: <\/b> 42.68281<br\/>  <b>Longitude: <\/b> -111.58749<br\/>  <b>Detection Time: <\/b> 2023-04-15 10:01 UTC<br\/>  <b>Sensor: <\/b> NOAA-20 VIIRS<br\/> <b>Confidence: <\/b> Nominal<br\/>  <b>Day\/Night: <\/b> Night<br\/> <b>Scan: <\/b> 0.5 km<br\/> <b>Track: <\/b> 0.5 km<br\/> <b>FRP: <\/b> 10.47 MW<br\/> <b>Brightness: <\/b> 332.53 K" }, "geometry": { "type": "Point", "coordinates": [ -111.58749, 42.68281, 0.0 ] } },
{ "type": "Feature", "properties": { "Name": "Fire Detection Centroid ", "Description": "<b>Latitude: <\/b> 45.46461<br\/>  <b>Longitude: <\/b> -122.21148<br\/>  <b>Detection Time: <\/b> 2023-04-15 10:01 UTC<br\/>  <b>Sensor: <\/b> NOAA-20 VIIRS<br\/> <b>Confidence: <\/b> Nominal<br\/>  <b>Day\/Night: <\/b> Night<br\/> <b>Scan: <\/b> 0.4 km<br\/> <b>Track: <\/b> 0.4 km<br\/> <b>FRP: <\/b> 0.78 MW<br\/> <b>Brightness: <\/b> 298.08 K" }, "geometry": { "type": "Point", "coordinates": [ -122.21148, 45.46461, 0.0 ] } },
{ "type": "Feature", "properties": { "Name": "Fire Detection Centroid ", "Description": "<b>Latitude: <\/b> 48.45412<br\/>  <b>Longitude: <\/b> -122.43763<br\/>  <b>Detection Time: <\/b> 2023-04-15 10:00 UTC<br\/>  <b>Sensor: <\/b> NOAA-20 VIIRS<br\/> <b>Confidence: <\/b> Nominal<br\/>  <b>Day\/Night: <\/b> Night<br\/> <b>Scan: <\/b> 0.4 km<br\/> <b>Track: <\/b> 0.4 km<br\/> <b>FRP: <\/b> 0.68 MW<br\/> <b>Brightness: <\/b> 295.53 K" }, "geometry": { "type": "Point", "coordinates": [ -122.43763, 48.45412, 0.0 ] } },
{ "type": "Feature", "properties": { "Name": "Fire Detection Centroid ", "Description": "<b>Latitude: <\/b> 47.57061<br\/>  <b>Longitude: <\/b> -122.36919<br\/>  <b>Detection Time: <\/b> 2023-04-15 10:00 UTC<br\/>  <b>Sensor: <\/b> NOAA-20 VIIRS<br\/> <b>Confidence: <\/b> Nominal<br\/>  <b>Day\/Night: <\/b> Night<br\/> <b>Scan: <\/b> 0.4 km<br\/> <b>Track: <\/b> 0.4 km<br\/> <b>FRP: <\/b> 2.85 MW<br\/> <b>Brightness: <\/b> 328.28 K" }, "geometry": { "type": "Point", "coordinates": [ -122.36919, 47.57061, 0.0 ] } },
{ "type": "Feature", "properties": { "Name": "Fire Detection Centroid ", "Description": "<b>Latitude: <\/b> 45.64721<br\/>  <b>Longitude: <\/b> -120.21315<br\/>  <b>Detection Time: <\/b> 2023-04-15 10:00 UTC<br\/>  <b>Sensor: <\/b> NOAA-20 VIIRS<br\/> <b>Confidence: <\/b> Nominal<br\/>  <b>Day\/Night: <\/b> Night<br\/> <b>Scan: <\/b> 0.4 km<br\/> <b>Track: <\/b> 0.4 km<br\/> <b>FRP: <\/b> 0.87 MW<br\/> <b>Brightness: <\/b> 299.05 K" }, "geometry": { "type": "Point", "coordinates": [ -120.21315, 45.64721, 0.0 ] } }
]
}
