{
"type": "FeatureCollection",
"crs": { "type": "name", "properties": { "name": "urn:ogc:def:crs:OGC:1.3:CRS84" } },
"features": [
{ "type": "Feature", "properties": { "Name": "Fire Detection Centroid ", "Description": "<b>Latitude: <\/b> 19.60021<br\/>  <b>Longitude: <\/b> -155.50293<br\/>  <b>Detection Time: <\/b> 2023-04-30 12:08 UTC<br\/>  <b>Sensor: <\/b> NOAA-20 VIIRS<br\/> <b>Confidence: <\/b> Nominal<br\/>  <b>Day\/Night: <\/b> Night<br\/> <b>Scan: <\/b> 0.42 km<br\/> <b>Track: <\/b> 0.38 km<br\/> <b>FRP: <\/b> 2.5 MW<br\/> <b>Brightness: <\/b> 299.04 K" }, "geometry": { "type": "Point", "coordinates": [ -155.50293, 19.60021, 0.0 ] } },
{ "type": "Feature", "properties": { "Name": "Fire Detection Centroid ", "Description": "<b>Latitude: <\/b> 19.60377<br\/>  <b>Longitude: <\/b> -155.50307<br\/>  <b>Detection Time: <\/b> 2023-04-30 12:08 UTC<br\/>  <b>Sensor: <\/b> NOAA-20 VIIRS<br\/> <b>Confidence: <\/b> Nominal<br\/>  <b>Day\/Night: <\/b> Night<br\/> <b>Scan: <\/b> 0.42 km<br\/> <b>Track: <\/b> 0.38 km<br\/> <b>FRP: <\/b> 2.44 MW<br\/> <b>Brightness: <\/b> 297.27 K" }, "geometry": { "type": "Point", "coordinates": [ -155.50307, 19.60377, 0.0 ] } },
{ "type": "Feature", "properties": { "Name": "Fire Detection Centroid ", "Description": "<b>Latitude: <\/b> 19.40728<br\/>  <b>Longitude: <\/b> -155.28001<br\/>  <b>Detection Time: <\/b> 2023-04-30 12:08 UTC<br\/>  <b>Sensor: <\/b> NOAA-20 VIIRS<br\/> <b>Confidence: <\/b> Nominal<br\/>  <b>Day\/Night: <\/b> Night<br\/> <b>Scan: <\/b> 0.43 km<br\/> <b>Track: <\/b> 0.38 km<br\/> <b>FRP: <\/b> 2.01 MW<br\/> <b>Brightness: <\/b> 305.38 K" }, "geometry": { "type": "Point", "coordinates": [ -155.28001, 19.40728, 0.0 ] } },
{ "type": "Feature", "properties": { "Name": "Fire Detection Centroid ", "Description": "<b>Latitude: <\/b> 19.40867<br\/>  <b>Longitude: <\/b> -155.28813<br\/>  <b>Detection Time: <\/b> 2023-04-30 12:08 UTC<br\/>  <b>Sensor: <\/b> NOAA-20 VIIRS<br\/> <b>Confidence: <\/b> Nominal<br\/>  <b>Day\/Night: <\/b> Night<br\/> <b>Scan: <\/b> 0.43 km<br\/> <b>Track: <\/b> 0.38 km<br\/> <b>FRP: <\/b> 1.88 MW<br\/> <b>Brightness: <\/b> 301.61 K" }, "geometry": { "type": "Point", "coordinates": [ -155.28813, 19.40867, 0.0 ] } },
{ "type": "Feature", "properties": { "Name": "Fire Detection Centroid ", "Description": "<b>Latitude: <\/b> 19.58665<br\/>  <b>Longitude: <\/b> -155.50595<br\/>  <b>Detection Time: <\/b> 2023-04-30 12:08 UTC<br\/>  <b>Sensor: <\/b> NOAA-20 VIIRS<br\/> <b>Confidence: <\/b> Nominal<br\/>  <b>Day\/Night: <\/b> Night<br\/> <b>Scan: <\/b> 0.42 km<br\/> <b>Track: <\/b> 0.38 km<br\/> <b>FRP: <\/b> 1.91 MW<br\/> <b>Brightness: <\/b> 296.95 K" }, "geometry": { "type": "Point", "coordinates": [ -155.50595, 19.58665, 0.0 ] } },
{ "type": "Feature", "properties": { "Name": "Fire Detection Centroid ", "Description": "<b>Latitude: <\/b> 19.40452<br\/>  <b>Longitude: <\/b> -155.2847<br\/>  <b>Detection Time: <\/b> 2023-04-30 12:08 UTC<br\/>  <b>Sensor: <\/b> NOAA-20 VIIRS<br\/> <b>Confidence: <\/b> Nominal<br\/>  <b>Day\/Night: <\/b> Night<br\/> <b>Scan: <\/b> 0.43 km<br\/> <b>Track: <\/b> 0.38 km<br\/> <b>FRP: <\/b> 2.01 MW<br\/> <b>Brightness: <\/b> 306.23 K" }, "geometry": { "type": "Point", "coordinates": [ -155.2847, 19.40452, 0.0 ] } },
{ "type": "Feature", "properties": { "Name": "Fire Detection Centroid ", "Description": "<b>Latitude: <\/b> 19.59343<br\/>  <b>Longitude: <\/b> -155.50446<br\/>  <b>Detection Time: <\/b> 2023-04-30 12:08 UTC<br\/>  <b>Sensor: <\/b> NOAA-20 VIIRS<br\/> <b>Confidence: <\/b> Nominal<br\/>  <b>Day\/Night: <\/b> Night<br\/> <b>Scan: <\/b> 0.42 km<br\/> <b>Track: <\/b> 0.38 km<br\/> <b>FRP: <\/b> 1.19 MW<br\/> <b>Brightness: <\/b> 295.9 K" }, "geometry": { "type": "Point", "coordinates": [ -155.50446, 19.59343, 0.0 ] } },
{ "type": "Feature", "properties": { "Name": "Fire Detection Centroid ", "Description": "<b>Latitude: <\/b> 19.59682<br\/>  <b>Longitude: <\/b> -155.50369<br\/>  <b>Detection Time: <\/b> 2023-04-30 12:08 UTC<br\/>  <b>Sensor: <\/b> NOAA-20 VIIRS<br\/> <b>Confidence: <\/b> Nominal<br\/>  <b>Day\/Night: <\/b> Night<br\/> <b>Scan: <\/b> 0.42 km<br\/> <b>Track: <\/b> 0.38 km<br\/> <b>FRP: <\/b> 1.19 MW<br\/> <b>Brightness: <\/b> 303.56 K" }, "geometry": { "type": "Point", "coordinates": [ -155.50369, 19.59682, 0.0 ] } }
]
}
