{
"type": "FeatureCollection",
"crs": { "type": "name", "properties": { "name": "urn:ogc:def:crs:OGC:1.3:CRS84" } },
"features": [
{ "type": "Feature", "properties": { "Name": "Fire Detection Centroid ", "Description": "<b>Latitude: <\/b> 39.36308<br\/>  <b>Longitude: <\/b> -121.659<br\/>  <b>Detection Time: <\/b> 2024-04-24 10:47 UTC<br\/>  <b>Sensor: <\/b> NOAA-20 VIIRS<br\/> <b>Confidence: <\/b> Nominal<br\/>  <b>Day\/Night: <\/b> Night<br\/> <b>Scan: <\/b> 0.4 km<br\/> <b>Track: <\/b> 0.6 km<br\/> <b>FRP: <\/b> 0.83 MW<br\/> <b>Brightness: <\/b> 297.99 K" }, "geometry": { "type": "Point", "coordinates": [ -121.659, 39.36308, 0.0 ] } },
{ "type": "Feature", "properties": { "Name": "Fire Detection Centroid ", "Description": "<b>Latitude: <\/b> 40.94223<br\/>  <b>Longitude: <\/b> -114.17574<br\/>  <b>Detection Time: <\/b> 2024-04-24 10:46 UTC<br\/>  <b>Sensor: <\/b> NOAA-20 VIIRS<br\/> <b>Confidence: <\/b> Nominal<br\/>  <b>Day\/Night: <\/b> Night<br\/> <b>Scan: <\/b> 0.8 km<br\/> <b>Track: <\/b> 0.8 km<br\/> <b>FRP: <\/b> 2.16 MW<br\/> <b>Brightness: <\/b> 301.02 K" }, "geometry": { "type": "Point", "coordinates": [ -114.17574, 40.94223, 0.0 ] } },
{ "type": "Feature", "properties": { "Name": "Fire Detection Centroid ", "Description": "<b>Latitude: <\/b> 43.0932<br\/>  <b>Longitude: <\/b> -121.4333<br\/>  <b>Detection Time: <\/b> 2024-04-24 10:46 UTC<br\/>  <b>Sensor: <\/b> NOAA-20 VIIRS<br\/> <b>Confidence: <\/b> Nominal<br\/>  <b>Day\/Night: <\/b> Night<br\/> <b>Scan: <\/b> 0.6 km<br\/> <b>Track: <\/b> 0.5 km<br\/> <b>FRP: <\/b> 1.95 MW<br\/> <b>Brightness: <\/b> 296.52 K" }, "geometry": { "type": "Point", "coordinates": [ -121.4333, 43.0932, 0.0 ] } },
{ "type": "Feature", "properties": { "Name": "Fire Detection Centroid ", "Description": "<b>Latitude: <\/b> 47.58455<br\/>  <b>Longitude: <\/b> -114.1558<br\/>  <b>Detection Time: <\/b> 2024-04-24 10:44 UTC<br\/>  <b>Sensor: <\/b> NOAA-20 VIIRS<br\/> <b>Confidence: <\/b> Nominal<br\/>  <b>Day\/Night: <\/b> Night<br\/> <b>Scan: <\/b> 0.5 km<br\/> <b>Track: <\/b> 0.6 km<br\/> <b>FRP: <\/b> 0.9 MW<br\/> <b>Brightness: <\/b> 297.93 K" }, "geometry": { "type": "Point", "coordinates": [ -114.1558, 47.58455, 0.0 ] } },
{ "type": "Feature", "properties": { "Name": "Fire Detection Centroid ", "Description": "<b>Latitude: <\/b> 48.59492<br\/>  <b>Longitude: <\/b> -108.49886<br\/>  <b>Detection Time: <\/b> 2024-04-24 10:43 UTC<br\/>  <b>Sensor: <\/b> NOAA-20 VIIRS<br\/> <b>Confidence: <\/b> Nominal<br\/>  <b>Day\/Night: <\/b> Night<br\/> <b>Scan: <\/b> 0.7 km<br\/> <b>Track: <\/b> 0.8 km<br\/> <b>FRP: <\/b> 0.91 MW<br\/> <b>Brightness: <\/b> 298.45 K" }, "geometry": { "type": "Point", "coordinates": [ -108.49886, 48.59492, 0.0 ] } }
]
}
