{
"type": "FeatureCollection",
"crs": { "type": "name", "properties": { "name": "urn:ogc:def:crs:OGC:1.3:CRS84" } },
"features": [
{ "type": "Feature", "properties": { "Name": "Fire Detection Centroid ", "Description": "<b>Latitude: <\/b> 45.28003<br\/>  <b>Longitude: <\/b> -66.01936<br\/>  <b>Detection Time: <\/b> 2023-10-02 05:09 UTC<br\/>  <b>Sensor: <\/b> NOAA-20 VIIRS<br\/> <b>Confidence: <\/b> Nominal<br\/>  <b>Day\/Night: <\/b> Night<br\/> <b>Scan: <\/b> 0.7 km<br\/> <b>Track: <\/b> 0.8 km<br\/> <b>FRP: <\/b> 1.84 MW<br\/> <b>Brightness: <\/b> 298.98 K" }, "geometry": { "type": "Point", "coordinates": [ -66.01936, 45.28003, 0.0 ] } },
{ "type": "Feature", "properties": { "Name": "Fire Detection Centroid ", "Description": "<b>Latitude: <\/b> 19.40311<br\/>  <b>Longitude: <\/b> -155.28093<br\/>  <b>Detection Time: <\/b> 2023-10-01 23:32 UTC<br\/>  <b>Sensor: <\/b> NOAA-20 VIIRS<br\/> <b>Confidence: <\/b> Low<br\/>  <b>Day\/Night: <\/b> Day<br\/> <b>Scan: <\/b> 0.4 km<br\/> <b>Track: <\/b> 0.4 km<br\/> <b>FRP: <\/b> 15.53 MW<br\/> <b>Brightness: <\/b> 343.76 K" }, "geometry": { "type": "Point", "coordinates": [ -155.28093, 19.40311, 0.0 ] } },
{ "type": "Feature", "properties": { "Name": "Fire Detection Centroid ", "Description": "<b>Latitude: <\/b> 19.40356<br\/>  <b>Longitude: <\/b> -155.28056<br\/>  <b>Detection Time: <\/b> 2023-10-01 23:31 UTC<br\/>  <b>Sensor: <\/b> NOAA-20 VIIRS<br\/> <b>Confidence: <\/b> Low<br\/>  <b>Day\/Night: <\/b> Day<br\/> <b>Scan: <\/b> 0.39 km<br\/> <b>Track: <\/b> 0.36 km<br\/> <b>FRP: <\/b> 15.54 MW<br\/> <b>Brightness: <\/b> 343.76 K" }, "geometry": { "type": "Point", "coordinates": [ -155.28056, 19.40356, 0.0 ] } }
]
}
