{
"type": "FeatureCollection",
"crs": { "type": "name", "properties": { "name": "urn:ogc:def:crs:OGC:1.3:CRS84" } },
"features": [
{ "type": "Feature", "properties": { "Name": "Fire Detection Centroid ", "Description": "<b>Latitude: </b> 18.92694<br/>  <b>Longitude: </b> -70.35011<br/>  <b>Detection Time: </b> 2022-06-18 05:48 UTC<br/>  <b>Sensor: </b> NOAA-20 VIIRS<br/> <b>Confidence: </b> Nominal<br/>  <b>Day/Night: </b> Night<br/> <b>Scan: </b> 0.6 km<br/> <b>Track: </b> 0.5 km<br/> <b>FRP: </b> 5.82 MW<br/> <b>Brightness: </b> 304.2 K" }, "geometry": { "type": "Point", "coordinates": [ -70.35011, 18.92694, 0.0 ] } },
{ "type": "Feature", "properties": { "Name": "Fire Detection Centroid ", "Description": "<b>Latitude: </b> 18.92925<br/>  <b>Longitude: </b> -70.35342<br/>  <b>Detection Time: </b> 2022-06-18 05:48 UTC<br/>  <b>Sensor: </b> NOAA-20 VIIRS<br/> <b>Confidence: </b> Nominal<br/>  <b>Day/Night: </b> Night<br/> <b>Scan: </b> 0.6 km<br/> <b>Track: </b> 0.5 km<br/> <b>FRP: </b> 13.17 MW<br/> <b>Brightness: </b> 345.17 K" }, "geometry": { "type": "Point", "coordinates": [ -70.35342, 18.92925, 0.0 ] } },
{ "type": "Feature", "properties": { "Name": "Fire Detection Centroid ", "Description": "<b>Latitude: </b> 19.71957<br/>  <b>Longitude: </b> -71.65719<br/>  <b>Detection Time: </b> 2022-06-18 05:48 UTC<br/>  <b>Sensor: </b> NOAA-20 VIIRS<br/> <b>Confidence: </b> Nominal<br/>  <b>Day/Night: </b> Night<br/> <b>Scan: </b> 0.3 km<br/> <b>Track: </b> 0.6 km<br/> <b>FRP: </b> 0.7 MW<br/> <b>Brightness: </b> 306.08 K" }, "geometry": { "type": "Point", "coordinates": [ -71.65719, 19.71957, 0.0 ] } },
{ "type": "Feature", "properties": { "Name": "Fire Detection Centroid ", "Description": "<b>Latitude: </b> 18.92759<br/>  <b>Longitude: </b> -70.35554<br/>  <b>Detection Time: </b> 2022-06-18 05:48 UTC<br/>  <b>Sensor: </b> NOAA-20 VIIRS<br/> <b>Confidence: </b> Nominal<br/>  <b>Day/Night: </b> Night<br/> <b>Scan: </b> 0.6 km<br/> <b>Track: </b> 0.5 km<br/> <b>FRP: </b> 10.46 MW<br/> <b>Brightness: </b> 339.46 K" }, "geometry": { "type": "Point", "coordinates": [ -70.35554, 18.92759, 0.0 ] } },
{ "type": "Feature", "properties": { "Name": "Fire Detection Centroid ", "Description": "<b>Latitude: </b> 45.82481<br/>  <b>Longitude: </b> -73.26909<br/>  <b>Detection Time: </b> 2022-06-18 05:40 UTC<br/>  <b>Sensor: </b> NOAA-20 VIIRS<br/> <b>Confidence: </b> Nominal<br/>  <b>Day/Night: </b> Night<br/> <b>Scan: </b> 0.7 km<br/> <b>Track: </b> 0.7 km<br/> <b>FRP: </b> 1.29 MW<br/> <b>Brightness: </b> 299.47 K" }, "geometry": { "type": "Point", "coordinates": [ -73.26909, 45.82481, 0.0 ] } }
]
}
