{
"type": "FeatureCollection",
"crs": { "type": "name", "properties": { "name": "urn:ogc:def:crs:OGC:1.3:CRS84" } },
"features": [
{ "type": "Feature", "properties": { "Name": "Fire Detection Centroid ", "Description": "<b>Latitude: <\/b> 18.92698<br\/>  <b>Longitude: <\/b> -70.35522<br\/>  <b>Detection Time: <\/b> 2023-08-25 05:30 UTC<br\/>  <b>Sensor: <\/b> NOAA-20 VIIRS<br\/> <b>Confidence: <\/b> Nominal<br\/>  <b>Day\/Night: <\/b> Night<br\/> <b>Scan: <\/b> 0.6 km<br\/> <b>Track: <\/b> 0.7 km<br\/> <b>FRP: <\/b> 1.83 MW<br\/> <b>Brightness: <\/b> 309.22 K" }, "geometry": { "type": "Point", "coordinates": [ -70.35522, 18.92698, 0.0 ] } }
]
}
