{
"type": "FeatureCollection",
"crs": { "type": "name", "properties": { "name": "urn:ogc:def:crs:OGC:1.3:CRS84" } },
"features": [
{ "type": "Feature", "properties": { "Name": "Fire Detection Centroid ", "Description": "<b>Latitude: <\/b> 18.48738<br\/>  <b>Longitude: <\/b> -69.2367<br\/>  <b>Detection Time: <\/b> 2023-02-20 05:16 UTC<br\/>  <b>Sensor: <\/b> NOAA-20 VIIRS<br\/> <b>Confidence: <\/b> Nominal<br\/>  <b>Day\/Night: <\/b> Night<br\/> <b>Scan: <\/b> 0.8 km<br\/> <b>Track: <\/b> 0.8 km<br\/> <b>FRP: <\/b> 1.93 MW<br\/> <b>Brightness: <\/b> 300.46 K" }, "geometry": { "type": "Point", "coordinates": [ -69.2367, 18.48738, 0.0 ] } }
]
}
