{
"type": "FeatureCollection",
"crs": { "type": "name", "properties": { "name": "urn:ogc:def:crs:OGC:1.3:CRS84" } },
"features": [
{ "type": "Feature", "properties": { "Name": "Fire Detection Centroid ", "Description": "<b>Latitude: <\/b> 48.70526<br\/>  <b>Longitude: <\/b> -64.27994<br\/>  <b>Detection Time: <\/b> 2023-12-09 17:00 UTC<br\/>  <b>Sensor: <\/b> NOAA-20 VIIRS<br\/> <b>Confidence: <\/b> Nominal<br\/>  <b>Day\/Night: <\/b> Day<br\/> <b>Scan: <\/b> 0.4 km<br\/> <b>Track: <\/b> 0.4 km<br\/> <b>FRP: <\/b> 4.93 MW<br\/> <b>Brightness: <\/b> 333.46 K" }, "geometry": { "type": "Point", "coordinates": [ -64.27994, 48.70526, 0.0 ] } },
{ "type": "Feature", "properties": { "Name": "Fire Detection Centroid ", "Description": "<b>Latitude: <\/b> 48.70851<br\/>  <b>Longitude: <\/b> -64.28111<br\/>  <b>Detection Time: <\/b> 2023-12-09 17:00 UTC<br\/>  <b>Sensor: <\/b> NOAA-20 VIIRS<br\/> <b>Confidence: <\/b> Nominal<br\/>  <b>Day\/Night: <\/b> Day<br\/> <b>Scan: <\/b> 0.4 km<br\/> <b>Track: <\/b> 0.4 km<br\/> <b>FRP: <\/b> 4.93 MW<br\/> <b>Brightness: <\/b> 344.56 K" }, "geometry": { "type": "Point", "coordinates": [ -64.28111, 48.70851, 0.0 ] } }
]
}
