{
"type": "FeatureCollection",
"crs": { "type": "name", "properties": { "name": "urn:ogc:def:crs:OGC:1.3:CRS84" } },
"features": [
{ "type": "Feature", "properties": { "Name": "Fire Detection Centroid ", "Description": "<b>Latitude: <\/b> 18.8273<br\/>  <b>Longitude: <\/b> -71.37788<br\/>  <b>Detection Time: <\/b> 2024-03-20 05:29 UTC<br\/>  <b>Sensor: <\/b> NOAA-20 VIIRS<br\/> <b>Confidence: <\/b> Nominal<br\/>  <b>Day\/Night: <\/b> Night<br\/> <b>Scan: <\/b> 0.7 km<br\/> <b>Track: <\/b> 0.7 km<br\/> <b>FRP: <\/b> 1.67 MW<br\/> <b>Brightness: <\/b> 312.61 K" }, "geometry": { "type": "Point", "coordinates": [ -71.37788, 18.8273, 0.0 ] } },
{ "type": "Feature", "properties": { "Name": "Fire Detection Centroid ", "Description": "<b>Latitude: <\/b> 18.62028<br\/>  <b>Longitude: <\/b> -71.38468<br\/>  <b>Detection Time: <\/b> 2024-03-20 05:29 UTC<br\/>  <b>Sensor: <\/b> NOAA-20 VIIRS<br\/> <b>Confidence: <\/b> Nominal<br\/>  <b>Day\/Night: <\/b> Night<br\/> <b>Scan: <\/b> 0.7 km<br\/> <b>Track: <\/b> 0.7 km<br\/> <b>FRP: <\/b> 2.63 MW<br\/> <b>Brightness: <\/b> 312.84 K" }, "geometry": { "type": "Point", "coordinates": [ -71.38468, 18.62028, 0.0 ] } },
{ "type": "Feature", "properties": { "Name": "Fire Detection Centroid ", "Description": "<b>Latitude: <\/b> 18.9766<br\/>  <b>Longitude: <\/b> -71.23684<br\/>  <b>Detection Time: <\/b> 2024-03-20 05:29 UTC<br\/>  <b>Sensor: <\/b> NOAA-20 VIIRS<br\/> <b>Confidence: <\/b> Nominal<br\/>  <b>Day\/Night: <\/b> Night<br\/> <b>Scan: <\/b> 0.7 km<br\/> <b>Track: <\/b> 0.7 km<br\/> <b>FRP: <\/b> 3.49 MW<br\/> <b>Brightness: <\/b> 308.53 K" }, "geometry": { "type": "Point", "coordinates": [ -71.23684, 18.9766, 0.0 ] } },
{ "type": "Feature", "properties": { "Name": "Fire Detection Centroid ", "Description": "<b>Latitude: <\/b> 18.976<br\/>  <b>Longitude: <\/b> -71.22984<br\/>  <b>Detection Time: <\/b> 2024-03-20 05:29 UTC<br\/>  <b>Sensor: <\/b> NOAA-20 VIIRS<br\/> <b>Confidence: <\/b> Nominal<br\/>  <b>Day\/Night: <\/b> Night<br\/> <b>Scan: <\/b> 0.7 km<br\/> <b>Track: <\/b> 0.7 km<br\/> <b>FRP: <\/b> 3 MW<br\/> <b>Brightness: <\/b> 297.85 K" }, "geometry": { "type": "Point", "coordinates": [ -71.22984, 18.976, 0.0 ] } }
]
}
