{
"type": "FeatureCollection",
"crs": { "type": "name", "properties": { "name": "urn:ogc:def:crs:OGC:1.3:CRS84" } },
"features": [
{ "type": "Feature", "properties": { "Name": "Fire Detection Centroid ", "Description": "<b>Latitude: <\/b> 31.36672<br\/>  <b>Longitude: <\/b> -101.77268<br\/>  <b>Detection Time: <\/b> 2023-01-16 09:31 UTC<br\/>  <b>Sensor: <\/b> NOAA-20 VIIRS<br\/> <b>Confidence: <\/b> Nominal<br\/>  <b>Day\/Night: <\/b> Night<br\/> <b>Scan: <\/b> 0.6 km<br\/> <b>Track: <\/b> 0.7 km<br\/> <b>FRP: <\/b> 2.5 MW<br\/> <b>Brightness: <\/b> 307.77 K" }, "geometry": { "type": "Point", "coordinates": [ -101.77268, 31.36672, 0.0 ] } },
{ "type": "Feature", "properties": { "Name": "Fire Detection Centroid ", "Description": "<b>Latitude: <\/b> 35.95445<br\/>  <b>Longitude: <\/b> -101.88041<br\/>  <b>Detection Time: <\/b> 2023-01-16 09:30 UTC<br\/>  <b>Sensor: <\/b> NOAA-20 VIIRS<br\/> <b>Confidence: <\/b> Nominal<br\/>  <b>Day\/Night: <\/b> Night<br\/> <b>Scan: <\/b> 0.5 km<br\/> <b>Track: <\/b> 0.6 km<br\/> <b>FRP: <\/b> 0.98 MW<br\/> <b>Brightness: <\/b> 295.14 K" }, "geometry": { "type": "Point", "coordinates": [ -101.88041, 35.95445, 0.0 ] } },
{ "type": "Feature", "properties": { "Name": "Fire Detection Centroid ", "Description": "<b>Latitude: <\/b> 42.68817<br\/>  <b>Longitude: <\/b> -111.59161<br\/>  <b>Detection Time: <\/b> 2023-01-16 09:29 UTC<br\/>  <b>Sensor: <\/b> NOAA-20 VIIRS<br\/> <b>Confidence: <\/b> Nominal<br\/>  <b>Day\/Night: <\/b> Night<br\/> <b>Scan: <\/b> 0.4 km<br\/> <b>Track: <\/b> 0.4 km<br\/> <b>FRP: <\/b> 9.51 MW<br\/> <b>Brightness: <\/b> 332.84 K" }, "geometry": { "type": "Point", "coordinates": [ -111.59161, 42.68817, 0.0 ] } },
{ "type": "Feature", "properties": { "Name": "Fire Detection Centroid ", "Description": "<b>Latitude: <\/b> 43.17963<br\/>  <b>Longitude: <\/b> -115.73466<br\/>  <b>Detection Time: <\/b> 2023-01-16 09:29 UTC<br\/>  <b>Sensor: <\/b> NOAA-20 VIIRS<br\/> <b>Confidence: <\/b> Nominal<br\/>  <b>Day\/Night: <\/b> Night<br\/> <b>Scan: <\/b> 0.4 km<br\/> <b>Track: <\/b> 0.4 km<br\/> <b>FRP: <\/b> 0.77 MW<br\/> <b>Brightness: <\/b> 298.32 K" }, "geometry": { "type": "Point", "coordinates": [ -115.73466, 43.17963, 0.0 ] } },
{ "type": "Feature", "properties": { "Name": "Fire Detection Centroid ", "Description": "<b>Latitude: <\/b> 42.68489<br\/>  <b>Longitude: <\/b> -111.59263<br\/>  <b>Detection Time: <\/b> 2023-01-16 09:29 UTC<br\/>  <b>Sensor: <\/b> NOAA-20 VIIRS<br\/> <b>Confidence: <\/b> Nominal<br\/>  <b>Day\/Night: <\/b> Night<br\/> <b>Scan: <\/b> 0.4 km<br\/> <b>Track: <\/b> 0.4 km<br\/> <b>FRP: <\/b> 9.51 MW<br\/> <b>Brightness: <\/b> 332.83 K" }, "geometry": { "type": "Point", "coordinates": [ -111.59263, 42.68489, 0.0 ] } },
{ "type": "Feature", "properties": { "Name": "Fire Detection Centroid ", "Description": "<b>Latitude: <\/b> 38.2413<br\/>  <b>Longitude: <\/b> -104.60835<br\/>  <b>Detection Time: <\/b> 2023-01-16 09:29 UTC<br\/>  <b>Sensor: <\/b> NOAA-20 VIIRS<br\/> <b>Confidence: <\/b> Nominal<br\/>  <b>Day\/Night: <\/b> Night<br\/> <b>Scan: <\/b> 0.6 km<br\/> <b>Track: <\/b> 0.5 km<br\/> <b>FRP: <\/b> 2.32 MW<br\/> <b>Brightness: <\/b> 299.67 K" }, "geometry": { "type": "Point", "coordinates": [ -104.60835, 38.2413, 0.0 ] } },
{ "type": "Feature", "properties": { "Name": "Fire Detection Centroid ", "Description": "<b>Latitude: <\/b> 38.64835<br\/>  <b>Longitude: <\/b> -97.2505<br\/>  <b>Detection Time: <\/b> 2023-01-16 09:29 UTC<br\/>  <b>Sensor: <\/b> NOAA-20 VIIRS<br\/> <b>Confidence: <\/b> Nominal<br\/>  <b>Day\/Night: <\/b> Night<br\/> <b>Scan: <\/b> 0.7 km<br\/> <b>Track: <\/b> 0.7 km<br\/> <b>FRP: <\/b> 1.11 MW<br\/> <b>Brightness: <\/b> 299.66 K" }, "geometry": { "type": "Point", "coordinates": [ -97.2505, 38.64835, 0.0 ] } },
{ "type": "Feature", "properties": { "Name": "Fire Detection Centroid ", "Description": "<b>Latitude: <\/b> 36.51698<br\/>  <b>Longitude: <\/b> -97.83935<br\/>  <b>Detection Time: <\/b> 2023-01-16 09:29 UTC<br\/>  <b>Sensor: <\/b> NOAA-20 VIIRS<br\/> <b>Confidence: <\/b> Nominal<br\/>  <b>Day\/Night: <\/b> Night<br\/> <b>Scan: <\/b> 0.7 km<br\/> <b>Track: <\/b> 0.8 km<br\/> <b>FRP: <\/b> 0.81 MW<br\/> <b>Brightness: <\/b> 297.49 K" }, "geometry": { "type": "Point", "coordinates": [ -97.83935, 36.51698, 0.0 ] } },
{ "type": "Feature", "properties": { "Name": "Fire Detection Centroid ", "Description": "<b>Latitude: <\/b> 38.65462<br\/>  <b>Longitude: <\/b> -97.24704<br\/>  <b>Detection Time: <\/b> 2023-01-16 09:29 UTC<br\/>  <b>Sensor: <\/b> NOAA-20 VIIRS<br\/> <b>Confidence: <\/b> Nominal<br\/>  <b>Day\/Night: <\/b> Night<br\/> <b>Scan: <\/b> 0.7 km<br\/> <b>Track: <\/b> 0.7 km<br\/> <b>FRP: <\/b> 1.11 MW<br\/> <b>Brightness: <\/b> 299.25 K" }, "geometry": { "type": "Point", "coordinates": [ -97.24704, 38.65462, 0.0 ] } }
]
}
