{
"type": "FeatureCollection",
"crs": { "type": "name", "properties": { "name": "urn:ogc:def:crs:OGC:1.3:CRS84" } },
"features": [
{ "type": "Feature", "properties": { "Name": "Fire Detection Centroid ", "Description": "<b>Latitude: <\/b> 19.40361<br\/>  <b>Longitude: <\/b> -155.28157<br\/>  <b>Detection Time: <\/b> 2023-06-28 23:14 UTC<br\/>  <b>Sensor: <\/b> NOAA-20 VIIRS<br\/> <b>Confidence: <\/b> Low<br\/>  <b>Day\/Night: <\/b> Day<br\/> <b>Scan: <\/b> 0.39 km<br\/> <b>Track: <\/b> 0.44 km<br\/> <b>FRP: <\/b> 19.41 MW<br\/> <b>Brightness: <\/b> 351.09 K" }, "geometry": { "type": "Point", "coordinates": [ -155.28157, 19.40361, 0.0 ] } },
{ "type": "Feature", "properties": { "Name": "Fire Detection Centroid ", "Description": "<b>Latitude: <\/b> 19.40294<br\/>  <b>Longitude: <\/b> -155.28523<br\/>  <b>Detection Time: <\/b> 2023-06-28 23:14 UTC<br\/>  <b>Sensor: <\/b> NOAA-20 VIIRS<br\/> <b>Confidence: <\/b> Low<br\/>  <b>Day\/Night: <\/b> Day<br\/> <b>Scan: <\/b> 0.39 km<br\/> <b>Track: <\/b> 0.44 km<br\/> <b>FRP: <\/b> 17.94 MW<br\/> <b>Brightness: <\/b> 353.87 K" }, "geometry": { "type": "Point", "coordinates": [ -155.28523, 19.40294, 0.0 ] } }
]
}
