{
"type": "FeatureCollection",
"crs": { "type": "name", "properties": { "name": "urn:ogc:def:crs:OGC:1.3:CRS84" } },
"features": [
{ "type": "Feature", "properties": { "Name": "Fire Detection Centroid ", "Description": "<b>Latitude: <\/b> 43.15095<br\/>  <b>Longitude: <\/b> -124.15344<br\/>  <b>Detection Time: <\/b> 2023-05-14 22:22 UTC<br\/>  <b>Sensor: <\/b> NOAA-20 VIIRS<br\/> <b>Confidence: <\/b> Nominal<br\/>  <b>Day\/Night: <\/b> Day<br\/> <b>Scan: <\/b> 0.75 km<br\/> <b>Track: <\/b> 0.77 km<br\/> <b>FRP: <\/b> 10.55 MW<br\/> <b>Brightness: <\/b> 346.76 K" }, "geometry": { "type": "Point", "coordinates": [ -124.15344, 43.15095, 0.0 ] } },
{ "type": "Feature", "properties": { "Name": "Fire Detection Centroid ", "Description": "<b>Latitude: <\/b> 43.15389<br\/>  <b>Longitude: <\/b> -124.15324<br\/>  <b>Detection Time: <\/b> 2023-05-14 22:22 UTC<br\/>  <b>Sensor: <\/b> NOAA-20 VIIRS<br\/> <b>Confidence: <\/b> High<br\/>  <b>Day\/Night: <\/b> Day<br\/> <b>Scan: <\/b> 0.75 km<br\/> <b>Track: <\/b> 0.77 km<br\/> <b>FRP: <\/b> 17.27 MW<br\/> <b>Brightness: <\/b> 367 K" }, "geometry": { "type": "Point", "coordinates": [ -124.15324, 43.15389, 0.0 ] } }
]
}
