{
"type": "FeatureCollection",
"crs": { "type": "name", "properties": { "name": "urn:ogc:def:crs:OGC:1.3:CRS84" } },
"features": [
{ "type": "Feature", "properties": { "Name": "Fire Detection Centroid ", "Description": "<b>Latitude: <\/b> 19.79325<br\/>  <b>Longitude: <\/b> -71.51523<br\/>  <b>Detection Time: <\/b> 2022-08-23 06:01 UTC<br\/>  <b>Sensor: <\/b> Suomi-NPP VIIRS<br\/> <b>Confidence: <\/b> Nominal<br\/>  <b>Day\/Night: <\/b> Night<br\/> <b>Scan: <\/b> 0.4 km<br\/> <b>Track: <\/b> 0.5 km<br\/> <b>FRP: <\/b> 1.71 MW<br\/> <b>Brightness: <\/b> 311.89 K" }, "geometry": { "type": "Point", "coordinates": [ -71.51523, 19.79325, 0.0 ] } },
{ "type": "Feature", "properties": { "Name": "Fire Detection Centroid ", "Description": "<b>Latitude: <\/b> 18.92781<br\/>  <b>Longitude: <\/b> -70.35639<br\/>  <b>Detection Time: <\/b> 2022-08-23 06:01 UTC<br\/>  <b>Sensor: <\/b> Suomi-NPP VIIRS<br\/> <b>Confidence: <\/b> Nominal<br\/>  <b>Day\/Night: <\/b> Night<br\/> <b>Scan: <\/b> 0.5 km<br\/> <b>Track: <\/b> 0.4 km<br\/> <b>FRP: <\/b> 4.81 MW<br\/> <b>Brightness: <\/b> 334.84 K" }, "geometry": { "type": "Point", "coordinates": [ -70.35639, 18.92781, 0.0 ] } },
{ "type": "Feature", "properties": { "Name": "Fire Detection Centroid ", "Description": "<b>Latitude: <\/b> 18.92713<br\/>  <b>Longitude: <\/b> -70.35131<br\/>  <b>Detection Time: <\/b> 2022-08-23 06:01 UTC<br\/>  <b>Sensor: <\/b> Suomi-NPP VIIRS<br\/> <b>Confidence: <\/b> Nominal<br\/>  <b>Day\/Night: <\/b> Night<br\/> <b>Scan: <\/b> 0.5 km<br\/> <b>Track: <\/b> 0.4 km<br\/> <b>FRP: <\/b> 4.81 MW<br\/> <b>Brightness: <\/b> 324.42 K" }, "geometry": { "type": "Point", "coordinates": [ -70.35131, 18.92713, 0.0 ] } },
{ "type": "Feature", "properties": { "Name": "Fire Detection Centroid ", "Description": "<b>Latitude: <\/b> 40.71446<br\/>  <b>Longitude: <\/b> -75.39975<br\/>  <b>Detection Time: <\/b> 2022-08-23 05:55 UTC<br\/>  <b>Sensor: <\/b> Suomi-NPP VIIRS<br\/> <b>Confidence: <\/b> Nominal<br\/>  <b>Day\/Night: <\/b> Night<br\/> <b>Scan: <\/b> 0.6 km<br\/> <b>Track: <\/b> 0.7 km<br\/> <b>FRP: <\/b> 0.7 MW<br\/> <b>Brightness: <\/b> 297.67 K" }, "geometry": { "type": "Point", "coordinates": [ -75.39975, 40.71446, 0.0 ] } },
{ "type": "Feature", "properties": { "Name": "Fire Detection Centroid ", "Description": "<b>Latitude: <\/b> 40.8941<br\/>  <b>Longitude: <\/b> -77.71333<br\/>  <b>Detection Time: <\/b> 2022-08-23 05:55 UTC<br\/>  <b>Sensor: <\/b> Suomi-NPP VIIRS<br\/> <b>Confidence: <\/b> Nominal<br\/>  <b>Day\/Night: <\/b> Night<br\/> <b>Scan: <\/b> 0.7 km<br\/> <b>Track: <\/b> 0.8 km<br\/> <b>FRP: <\/b> 1.05 MW<br\/> <b>Brightness: <\/b> 296.04 K" }, "geometry": { "type": "Point", "coordinates": [ -77.71333, 40.8941, 0.0 ] } },
{ "type": "Feature", "properties": { "Name": "Fire Detection Centroid ", "Description": "<b>Latitude: <\/b> 39.58812<br\/>  <b>Longitude: <\/b> -75.63931<br\/>  <b>Detection Time: <\/b> 2022-08-23 05:55 UTC<br\/>  <b>Sensor: <\/b> Suomi-NPP VIIRS<br\/> <b>Confidence: <\/b> Nominal<br\/>  <b>Day\/Night: <\/b> Night<br\/> <b>Scan: <\/b> 0.6 km<br\/> <b>Track: <\/b> 0.7 km<br\/> <b>FRP: <\/b> 1.61 MW<br\/> <b>Brightness: <\/b> 302.91 K" }, "geometry": { "type": "Point", "coordinates": [ -75.63931, 39.58812, 0.0 ] } },
{ "type": "Feature", "properties": { "Name": "Fire Detection Centroid ", "Description": "<b>Latitude: <\/b> 39.58746<br\/>  <b>Longitude: <\/b> -75.64014<br\/>  <b>Detection Time: <\/b> 2022-08-23 05:55 UTC<br\/>  <b>Sensor: <\/b> Suomi-NPP VIIRS<br\/> <b>Confidence: <\/b> Nominal<br\/>  <b>Day\/Night: <\/b> Night<br\/> <b>Scan: <\/b> 0.6 km<br\/> <b>Track: <\/b> 0.7 km<br\/> <b>FRP: <\/b> 1.56 MW<br\/> <b>Brightness: <\/b> 301.86 K" }, "geometry": { "type": "Point", "coordinates": [ -75.64014, 39.58746, 0.0 ] } },
{ "type": "Feature", "properties": { "Name": "Fire Detection Centroid ", "Description": "<b>Latitude: <\/b> 40.71446<br\/>  <b>Longitude: <\/b> -75.39975<br\/>  <b>Detection Time: <\/b> 2022-08-23 05:55 UTC<br\/>  <b>Sensor: <\/b> Suomi-NPP VIIRS<br\/> <b>Confidence: <\/b> Nominal<br\/>  <b>Day\/Night: <\/b> Night<br\/> <b>Scan: <\/b> 0.6 km<br\/> <b>Track: <\/b> 0.7 km<br\/> <b>FRP: <\/b> 0.7 MW<br\/> <b>Brightness: <\/b> 297.67 K" }, "geometry": { "type": "Point", "coordinates": [ -75.39975, 40.71446, 0.0 ] } },
{ "type": "Feature", "properties": { "Name": "Fire Detection Centroid ", "Description": "<b>Latitude: <\/b> 39.94235<br\/>  <b>Longitude: <\/b> -76.81562<br\/>  <b>Detection Time: <\/b> 2022-08-23 05:55 UTC<br\/>  <b>Sensor: <\/b> Suomi-NPP VIIRS<br\/> <b>Confidence: <\/b> Nominal<br\/>  <b>Day\/Night: <\/b> Night<br\/> <b>Scan: <\/b> 0.7 km<br\/> <b>Track: <\/b> 0.7 km<br\/> <b>FRP: <\/b> 1.46 MW<br\/> <b>Brightness: <\/b> 299.5 K" }, "geometry": { "type": "Point", "coordinates": [ -76.81562, 39.94235, 0.0 ] } }
]
}
