{
"type": "FeatureCollection",
"crs": { "type": "name", "properties": { "name": "urn:ogc:def:crs:OGC:1.3:CRS84" } },
"features": [
{ "type": "Feature", "properties": { "Name": "Fire Detection Centroid ", "Description": "<b>Latitude: <\/b> 45.83733<br\/>  <b>Longitude: <\/b> -73.24458<br\/>  <b>Detection Time: <\/b> 2022-09-23 16:47 UTC<br\/>  <b>Sensor: <\/b> NOAA-20 VIIRS<br\/> <b>Confidence: <\/b> Nominal<br\/>  <b>Day\/Night: <\/b> Day<br\/> <b>Scan: <\/b> 0.4 km<br\/> <b>Track: <\/b> 0.6 km<br\/> <b>FRP: <\/b> 3.35 MW<br\/> <b>Brightness: <\/b> 329.52 K" }, "geometry": { "type": "Point", "coordinates": [ -73.24458, 45.83733, 0.0 ] } },
{ "type": "Feature", "properties": { "Name": "Fire Detection Centroid ", "Description": "<b>Latitude: <\/b> 45.32544<br\/>  <b>Longitude: <\/b> -75.31228<br\/>  <b>Detection Time: <\/b> 2022-09-23 16:47 UTC<br\/>  <b>Sensor: <\/b> NOAA-20 VIIRS<br\/> <b>Confidence: <\/b> Nominal<br\/>  <b>Day\/Night: <\/b> Day<br\/> <b>Scan: <\/b> 0.5 km<br\/> <b>Track: <\/b> 0.6 km<br\/> <b>FRP: <\/b> 7.98 MW<br\/> <b>Brightness: <\/b> 343.29 K" }, "geometry": { "type": "Point", "coordinates": [ -75.31228, 45.32544, 0.0 ] } },
{ "type": "Feature", "properties": { "Name": "Fire Detection Centroid ", "Description": "<b>Latitude: <\/b> 45.83602<br\/>  <b>Longitude: <\/b> -73.2491<br\/>  <b>Detection Time: <\/b> 2022-09-23 16:47 UTC<br\/>  <b>Sensor: <\/b> NOAA-20 VIIRS<br\/> <b>Confidence: <\/b> Nominal<br\/>  <b>Day\/Night: <\/b> Day<br\/> <b>Scan: <\/b> 0.4 km<br\/> <b>Track: <\/b> 0.6 km<br\/> <b>FRP: <\/b> 4.74 MW<br\/> <b>Brightness: <\/b> 337.68 K" }, "geometry": { "type": "Point", "coordinates": [ -73.2491, 45.83602, 0.0 ] } },
{ "type": "Feature", "properties": { "Name": "Fire Detection Centroid ", "Description": "<b>Latitude: <\/b> 45.32721<br\/>  <b>Longitude: <\/b> -75.30662<br\/>  <b>Detection Time: <\/b> 2022-09-23 16:47 UTC<br\/>  <b>Sensor: <\/b> NOAA-20 VIIRS<br\/> <b>Confidence: <\/b> Nominal<br\/>  <b>Day\/Night: <\/b> Day<br\/> <b>Scan: <\/b> 0.5 km<br\/> <b>Track: <\/b> 0.6 km<br\/> <b>FRP: <\/b> 7.08 MW<br\/> <b>Brightness: <\/b> 336.57 K" }, "geometry": { "type": "Point", "coordinates": [ -75.30662, 45.32721, 0.0 ] } },
{ "type": "Feature", "properties": { "Name": "Fire Detection Centroid ", "Description": "<b>Latitude: <\/b> 22.12547<br\/>  <b>Longitude: <\/b> -159.30061<br\/>  <b>Detection Time: <\/b> 2022-09-23 12:14 UTC<br\/>  <b>Sensor: <\/b> NOAA-20 VIIRS<br\/> <b>Confidence: <\/b> Nominal<br\/>  <b>Day\/Night: <\/b> Night<br\/> <b>Scan: <\/b> 0.39 km<br\/> <b>Track: <\/b> 0.36 km<br\/> <b>FRP: <\/b> 2.71 MW<br\/> <b>Brightness: <\/b> 328.43 K" }, "geometry": { "type": "Point", "coordinates": [ -159.30061, 22.12547, 0.0 ] } },
{ "type": "Feature", "properties": { "Name": "Fire Detection Centroid ", "Description": "<b>Latitude: <\/b> 22.12604<br\/>  <b>Longitude: <\/b> -159.30431<br\/>  <b>Detection Time: <\/b> 2022-09-23 12:14 UTC<br\/>  <b>Sensor: <\/b> NOAA-20 VIIRS<br\/> <b>Confidence: <\/b> Nominal<br\/>  <b>Day\/Night: <\/b> Night<br\/> <b>Scan: <\/b> 0.39 km<br\/> <b>Track: <\/b> 0.36 km<br\/> <b>FRP: <\/b> 2.48 MW<br\/> <b>Brightness: <\/b> 324.53 K" }, "geometry": { "type": "Point", "coordinates": [ -159.30431, 22.12604, 0.0 ] } }
]
}
