{
"type": "FeatureCollection",
"crs": { "type": "name", "properties": { "name": "urn:ogc:def:crs:OGC:1.3:CRS84" } },
"features": [
{ "type": "Feature", "properties": { "Name": "Fire Detection Centroid ", "Description": "<b>Latitude: <\/b> 45.07052<br\/>  <b>Longitude: <\/b> -75.19628<br\/>  <b>Detection Time: <\/b> 2023-11-18 16:54 UTC<br\/>  <b>Sensor: <\/b> NOAA-20 VIIRS<br\/> <b>Confidence: <\/b> Nominal<br\/>  <b>Day\/Night: <\/b> Day<br\/> <b>Scan: <\/b> 0.4 km<br\/> <b>Track: <\/b> 0.6 km<br\/> <b>FRP: <\/b> 3 MW<br\/> <b>Brightness: <\/b> 326.88 K" }, "geometry": { "type": "Point", "coordinates": [ -75.19628, 45.07052, 0.0 ] } },
{ "type": "Feature", "properties": { "Name": "Fire Detection Centroid ", "Description": "<b>Latitude: <\/b> 44.05725<br\/>  <b>Longitude: <\/b> -77.62972<br\/>  <b>Detection Time: <\/b> 2023-11-18 16:54 UTC<br\/>  <b>Sensor: <\/b> NOAA-20 VIIRS<br\/> <b>Confidence: <\/b> Nominal<br\/>  <b>Day\/Night: <\/b> Day<br\/> <b>Scan: <\/b> 0.6 km<br\/> <b>Track: <\/b> 0.7 km<br\/> <b>FRP: <\/b> 3.72 MW<br\/> <b>Brightness: <\/b> 331.65 K" }, "geometry": { "type": "Point", "coordinates": [ -77.62972, 44.05725, 0.0 ] } }
]
}
