{
"type": "FeatureCollection",
"crs": { "type": "name", "properties": { "name": "urn:ogc:def:crs:OGC:1.3:CRS84" } },
"features": [
{ "type": "Feature", "properties": { "Name": "Fire Detection Centroid ", "Description": "<b>Latitude: <\/b> 46.43249<br\/>  <b>Longitude: <\/b> -120.3757<br\/>  <b>Detection Time: <\/b> 2023-04-01 11:02 UTC<br\/>  <b>Sensor: <\/b> NOAA-20 VIIRS<br\/> <b>Confidence: <\/b> Nominal<br\/>  <b>Day\/Night: <\/b> Night<br\/> <b>Scan: <\/b> 0.42 km<br\/> <b>Track: <\/b> 0.61 km<br\/> <b>FRP: <\/b> 1.35 MW<br\/> <b>Brightness: <\/b> 311.08 K" }, "geometry": { "type": "Point", "coordinates": [ -120.3757, 46.43249, 0.0 ] } },
{ "type": "Feature", "properties": { "Name": "Fire Detection Centroid ", "Description": "<b>Latitude: <\/b> 48.88779<br\/>  <b>Longitude: <\/b> -122.73902<br\/>  <b>Detection Time: <\/b> 2023-04-01 11:02 UTC<br\/>  <b>Sensor: <\/b> NOAA-20 VIIRS<br\/> <b>Confidence: <\/b> Nominal<br\/>  <b>Day\/Night: <\/b> Night<br\/> <b>Scan: <\/b> 0.56 km<br\/> <b>Track: <\/b> 0.51 km<br\/> <b>FRP: <\/b> 1.49 MW<br\/> <b>Brightness: <\/b> 297.97 K" }, "geometry": { "type": "Point", "coordinates": [ -122.73902, 48.88779, 0.0 ] } }
]
}
