{
"type": "FeatureCollection",
"crs": { "type": "name", "properties": { "name": "urn:ogc:def:crs:OGC:1.3:CRS84" } },
"features": [
{ "type": "Feature", "properties": { "Name": "Fire Detection Centroid ", "Description": "<b>Latitude: <\/b> 19.40939<br\/>  <b>Longitude: <\/b> -155.28787<br\/>  <b>Detection Time: <\/b> 2022-07-09 00:09 UTC<br\/>  <b>Sensor: <\/b> NOAA-20 VIIRS<br\/> <b>Confidence: <\/b> Nominal<br\/>  <b>Day\/Night: <\/b> Day<br\/> <b>Scan: <\/b> 0.34 km<br\/> <b>Track: <\/b> 0.56 km<br\/> <b>FRP: <\/b> 6.49 MW<br\/> <b>Brightness: <\/b> 342.47 K" }, "geometry": { "type": "Point", "coordinates": [ -155.28787, 19.40939, 0.0 ] } },
{ "type": "Feature", "properties": { "Name": "Fire Detection Centroid ", "Description": "<b>Latitude: <\/b> 19.3998<br\/>  <b>Longitude: <\/b> -155.28006<br\/>  <b>Detection Time: <\/b> 2022-07-09 00:09 UTC<br\/>  <b>Sensor: <\/b> NOAA-20 VIIRS<br\/> <b>Confidence: <\/b> High<br\/>  <b>Day\/Night: <\/b> Day<br\/> <b>Scan: <\/b> 0.34 km<br\/> <b>Track: <\/b> 0.56 km<br\/> <b>FRP: <\/b> 35.54 MW<br\/> <b>Brightness: <\/b> 367 K" }, "geometry": { "type": "Point", "coordinates": [ -155.28006, 19.3998, 0.0 ] } },
{ "type": "Feature", "properties": { "Name": "Fire Detection Centroid ", "Description": "<b>Latitude: <\/b> 19.39912<br\/>  <b>Longitude: <\/b> -155.28661<br\/>  <b>Detection Time: <\/b> 2022-07-09 00:09 UTC<br\/>  <b>Sensor: <\/b> NOAA-20 VIIRS<br\/> <b>Confidence: <\/b> Nominal<br\/>  <b>Day\/Night: <\/b> Day<br\/> <b>Scan: <\/b> 0.34 km<br\/> <b>Track: <\/b> 0.56 km<br\/> <b>FRP: <\/b> 58.62 MW<br\/> <b>Brightness: <\/b> 348.5 K" }, "geometry": { "type": "Point", "coordinates": [ -155.28661, 19.39912, 0.0 ] } },
{ "type": "Feature", "properties": { "Name": "Fire Detection Centroid ", "Description": "<b>Latitude: <\/b> 19.39946<br\/>  <b>Longitude: <\/b> -155.28331<br\/>  <b>Detection Time: <\/b> 2022-07-09 00:09 UTC<br\/>  <b>Sensor: <\/b> NOAA-20 VIIRS<br\/> <b>Confidence: <\/b> Low<br\/>  <b>Day\/Night: <\/b> Day<br\/> <b>Scan: <\/b> 0.34 km<br\/> <b>Track: <\/b> 0.56 km<br\/> <b>FRP: <\/b> 58.62 MW<br\/> <b>Brightness: <\/b> 367 K" }, "geometry": { "type": "Point", "coordinates": [ -155.28331, 19.39946, 0.0 ] } },
{ "type": "Feature", "properties": { "Name": "Fire Detection Centroid ", "Description": "<b>Latitude: <\/b> 19.40496<br\/>  <b>Longitude: <\/b> -155.2805<br\/>  <b>Detection Time: <\/b> 2022-07-09 00:09 UTC<br\/>  <b>Sensor: <\/b> NOAA-20 VIIRS<br\/> <b>Confidence: <\/b> High<br\/>  <b>Day\/Night: <\/b> Day<br\/> <b>Scan: <\/b> 0.34 km<br\/> <b>Track: <\/b> 0.56 km<br\/> <b>FRP: <\/b> 35.54 MW<br\/> <b>Brightness: <\/b> 367 K" }, "geometry": { "type": "Point", "coordinates": [ -155.2805, 19.40496, 0.0 ] } },
{ "type": "Feature", "properties": { "Name": "Fire Detection Centroid ", "Description": "<b>Latitude: <\/b> 19.40428<br\/>  <b>Longitude: <\/b> -155.28702<br\/>  <b>Detection Time: <\/b> 2022-07-09 00:09 UTC<br\/>  <b>Sensor: <\/b> NOAA-20 VIIRS<br\/> <b>Confidence: <\/b> High<br\/>  <b>Day\/Night: <\/b> Day<br\/> <b>Scan: <\/b> 0.34 km<br\/> <b>Track: <\/b> 0.56 km<br\/> <b>FRP: <\/b> 58.62 MW<br\/> <b>Brightness: <\/b> 367 K" }, "geometry": { "type": "Point", "coordinates": [ -155.28702, 19.40428, 0.0 ] } },
{ "type": "Feature", "properties": { "Name": "Fire Detection Centroid ", "Description": "<b>Latitude: <\/b> 19.40462<br\/>  <b>Longitude: <\/b> -155.28374<br\/>  <b>Detection Time: <\/b> 2022-07-09 00:09 UTC<br\/>  <b>Sensor: <\/b> NOAA-20 VIIRS<br\/> <b>Confidence: <\/b> Nominal<br\/>  <b>Day\/Night: <\/b> Day<br\/> <b>Scan: <\/b> 0.34 km<br\/> <b>Track: <\/b> 0.56 km<br\/> <b>FRP: <\/b> 58.62 MW<br\/> <b>Brightness: <\/b> 353.01 K" }, "geometry": { "type": "Point", "coordinates": [ -155.28374, 19.40462, 0.0 ] } },
{ "type": "Feature", "properties": { "Name": "Fire Detection Centroid ", "Description": "<b>Latitude: <\/b> 19.41009<br\/>  <b>Longitude: <\/b> -155.28117<br\/>  <b>Detection Time: <\/b> 2022-07-09 00:09 UTC<br\/>  <b>Sensor: <\/b> NOAA-20 VIIRS<br\/> <b>Confidence: <\/b> Nominal<br\/>  <b>Day\/Night: <\/b> Day<br\/> <b>Scan: <\/b> 0.34 km<br\/> <b>Track: <\/b> 0.56 km<br\/> <b>FRP: <\/b> 10.15 MW<br\/> <b>Brightness: <\/b> 345.74 K" }, "geometry": { "type": "Point", "coordinates": [ -155.28117, 19.41009, 0.0 ] } },
{ "type": "Feature", "properties": { "Name": "Fire Detection Centroid ", "Description": "<b>Latitude: <\/b> 19.40974<br\/>  <b>Longitude: <\/b> -155.2845<br\/>  <b>Detection Time: <\/b> 2022-07-09 00:09 UTC<br\/>  <b>Sensor: <\/b> NOAA-20 VIIRS<br\/> <b>Confidence: <\/b> Nominal<br\/>  <b>Day\/Night: <\/b> Day<br\/> <b>Scan: <\/b> 0.34 km<br\/> <b>Track: <\/b> 0.56 km<br\/> <b>FRP: <\/b> 6.49 MW<br\/> <b>Brightness: <\/b> 346.81 K" }, "geometry": { "type": "Point", "coordinates": [ -155.2845, 19.40974, 0.0 ] } }
]
}
