{
"type": "FeatureCollection",
"crs": { "type": "name", "properties": { "name": "urn:ogc:def:crs:OGC:1.3:CRS84" } },
"features": [
{ "type": "Feature", "properties": { "Name": "Fire Detection Centroid ", "Description": "<b>Latitude: <\/b> 45.07052<br\/>  <b>Longitude: <\/b> -75.19628<br\/>  <b>Detection Time: <\/b> 2023-11-18 16:54 UTC<br\/>  <b>Sensor: <\/b> NOAA-20 VIIRS<br\/> <b>Confidence: <\/b> Nominal<br\/>  <b>Day\/Night: <\/b> Day<br\/> <b>Scan: <\/b> 0.4 km<br\/> <b>Track: <\/b> 0.6 km<br\/> <b>FRP: <\/b> 3 MW<br\/> <b>Brightness: <\/b> 326.88 K" }, "geometry": { "type": "Point", "coordinates": [ -75.19628, 45.07052, 0.0 ] } },
{ "type": "Feature", "properties": { "Name": "Fire Detection Centroid ", "Description": "<b>Latitude: <\/b> 44.05725<br\/>  <b>Longitude: <\/b> -77.62972<br\/>  <b>Detection Time: <\/b> 2023-11-18 16:54 UTC<br\/>  <b>Sensor: <\/b> NOAA-20 VIIRS<br\/> <b>Confidence: <\/b> Nominal<br\/>  <b>Day\/Night: <\/b> Day<br\/> <b>Scan: <\/b> 0.6 km<br\/> <b>Track: <\/b> 0.7 km<br\/> <b>FRP: <\/b> 3.72 MW<br\/> <b>Brightness: <\/b> 331.65 K" }, "geometry": { "type": "Point", "coordinates": [ -77.62972, 44.05725, 0.0 ] } },
{ "type": "Feature", "properties": { "Name": "Fire Detection Centroid ", "Description": "<b>Latitude: <\/b> 19.40677<br\/>  <b>Longitude: <\/b> -155.28526<br\/>  <b>Detection Time: <\/b> 2023-11-18 12:21 UTC<br\/>  <b>Sensor: <\/b> NOAA-20 VIIRS<br\/> <b>Confidence: <\/b> Nominal<br\/>  <b>Day\/Night: <\/b> Night<br\/> <b>Scan: <\/b> 0.41 km<br\/> <b>Track: <\/b> 0.45 km<br\/> <b>FRP: <\/b> 2.31 MW<br\/> <b>Brightness: <\/b> 313.24 K" }, "geometry": { "type": "Point", "coordinates": [ -155.28526, 19.40677, 0.0 ] } },
{ "type": "Feature", "properties": { "Name": "Fire Detection Centroid ", "Description": "<b>Latitude: <\/b> 19.40754<br\/>  <b>Longitude: <\/b> -155.28923<br\/>  <b>Detection Time: <\/b> 2023-11-18 12:21 UTC<br\/>  <b>Sensor: <\/b> NOAA-20 VIIRS<br\/> <b>Confidence: <\/b> Nominal<br\/>  <b>Day\/Night: <\/b> Night<br\/> <b>Scan: <\/b> 0.41 km<br\/> <b>Track: <\/b> 0.45 km<br\/> <b>FRP: <\/b> 2.31 MW<br\/> <b>Brightness: <\/b> 306.29 K" }, "geometry": { "type": "Point", "coordinates": [ -155.28923, 19.40754, 0.0 ] } },
{ "type": "Feature", "properties": { "Name": "Fire Detection Centroid ", "Description": "<b>Latitude: <\/b> 19.40935<br\/>  <b>Longitude: <\/b> -155.27669<br\/>  <b>Detection Time: <\/b> 2023-11-18 12:21 UTC<br\/>  <b>Sensor: <\/b> NOAA-20 VIIRS<br\/> <b>Confidence: <\/b> Nominal<br\/>  <b>Day\/Night: <\/b> Night<br\/> <b>Scan: <\/b> 0.41 km<br\/> <b>Track: <\/b> 0.45 km<br\/> <b>FRP: <\/b> 2.81 MW<br\/> <b>Brightness: <\/b> 304.81 K" }, "geometry": { "type": "Point", "coordinates": [ -155.27669, 19.40935, 0.0 ] } },
{ "type": "Feature", "properties": { "Name": "Fire Detection Centroid ", "Description": "<b>Latitude: <\/b> 19.41161<br\/>  <b>Longitude: <\/b> -155.28848<br\/>  <b>Detection Time: <\/b> 2023-11-18 12:21 UTC<br\/>  <b>Sensor: <\/b> NOAA-20 VIIRS<br\/> <b>Confidence: <\/b> Nominal<br\/>  <b>Day\/Night: <\/b> Night<br\/> <b>Scan: <\/b> 0.41 km<br\/> <b>Track: <\/b> 0.45 km<br\/> <b>FRP: <\/b> 5.89 MW<br\/> <b>Brightness: <\/b> 311.78 K" }, "geometry": { "type": "Point", "coordinates": [ -155.28848, 19.41161, 0.0 ] } },
{ "type": "Feature", "properties": { "Name": "Fire Detection Centroid ", "Description": "<b>Latitude: <\/b> 19.41416<br\/>  <b>Longitude: <\/b> -155.27975<br\/>  <b>Detection Time: <\/b> 2023-11-18 12:21 UTC<br\/>  <b>Sensor: <\/b> NOAA-20 VIIRS<br\/> <b>Confidence: <\/b> Nominal<br\/>  <b>Day\/Night: <\/b> Night<br\/> <b>Scan: <\/b> 0.41 km<br\/> <b>Track: <\/b> 0.45 km<br\/> <b>FRP: <\/b> 2.81 MW<br\/> <b>Brightness: <\/b> 304.5 K" }, "geometry": { "type": "Point", "coordinates": [ -155.27975, 19.41416, 0.0 ] } }
]
}
