{
"type": "FeatureCollection",
"crs": { "type": "name", "properties": { "name": "urn:ogc:def:crs:OGC:1.3:CRS84" } },
"features": [
{ "type": "Feature", "properties": { "Name": "Fire Detection Centroid ", "Description": "<b>Latitude: <\/b> 41.60468<br\/>  <b>Longitude: <\/b> -71.43324<br\/>  <b>Detection Time: <\/b> 2022-06-25 16:34 UTC<br\/>  <b>Sensor: <\/b> NOAA-20 VIIRS<br\/> <b>Confidence: <\/b> Nominal<br\/>  <b>Day\/Night: <\/b> Day<br\/> <b>Scan: <\/b> 0.6 km<br\/> <b>Track: <\/b> 0.7 km<br\/> <b>FRP: <\/b> 5.28 MW<br\/> <b>Brightness: <\/b> 326.34 K" }, "geometry": { "type": "Point", "coordinates": [ -71.43324, 41.60468, 0.0 ] } },
{ "type": "Feature", "properties": { "Name": "Fire Detection Centroid ", "Description": "<b>Latitude: <\/b> 19.41012<br\/>  <b>Longitude: <\/b> -155.28535<br\/>  <b>Detection Time: <\/b> 2022-06-25 12:02 UTC<br\/>  <b>Sensor: <\/b> NOAA-20 VIIRS<br\/> <b>Confidence: <\/b> Nominal<br\/>  <b>Day\/Night: <\/b> Night<br\/> <b>Scan: <\/b> 0.39 km<br\/> <b>Track: <\/b> 0.36 km<br\/> <b>FRP: <\/b> 0.52 MW<br\/> <b>Brightness: <\/b> 302.49 K" }, "geometry": { "type": "Point", "coordinates": [ -155.28535, 19.41012, 0.0 ] } },
{ "type": "Feature", "properties": { "Name": "Fire Detection Centroid ", "Description": "<b>Latitude: <\/b> 19.41342<br\/>  <b>Longitude: <\/b> -155.28477<br\/>  <b>Detection Time: <\/b> 2022-06-25 12:02 UTC<br\/>  <b>Sensor: <\/b> NOAA-20 VIIRS<br\/> <b>Confidence: <\/b> Nominal<br\/>  <b>Day\/Night: <\/b> Night<br\/> <b>Scan: <\/b> 0.39 km<br\/> <b>Track: <\/b> 0.36 km<br\/> <b>FRP: <\/b> 1.28 MW<br\/> <b>Brightness: <\/b> 312.8 K" }, "geometry": { "type": "Point", "coordinates": [ -155.28477, 19.41342, 0.0 ] } },
{ "type": "Feature", "properties": { "Name": "Fire Detection Centroid ", "Description": "<b>Latitude: <\/b> 19.41283<br\/>  <b>Longitude: <\/b> -155.2811<br\/>  <b>Detection Time: <\/b> 2022-06-25 12:02 UTC<br\/>  <b>Sensor: <\/b> NOAA-20 VIIRS<br\/> <b>Confidence: <\/b> Nominal<br\/>  <b>Day\/Night: <\/b> Night<br\/> <b>Scan: <\/b> 0.39 km<br\/> <b>Track: <\/b> 0.36 km<br\/> <b>FRP: <\/b> 1.28 MW<br\/> <b>Brightness: <\/b> 313.9 K" }, "geometry": { "type": "Point", "coordinates": [ -155.2811, 19.41283, 0.0 ] } },
{ "type": "Feature", "properties": { "Name": "Fire Detection Centroid ", "Description": "<b>Latitude: <\/b> 19.40952<br\/>  <b>Longitude: <\/b> -155.28169<br\/>  <b>Detection Time: <\/b> 2022-06-25 12:02 UTC<br\/>  <b>Sensor: <\/b> NOAA-20 VIIRS<br\/> <b>Confidence: <\/b> Nominal<br\/>  <b>Day\/Night: <\/b> Night<br\/> <b>Scan: <\/b> 0.39 km<br\/> <b>Track: <\/b> 0.36 km<br\/> <b>FRP: <\/b> 0.52 MW<br\/> <b>Brightness: <\/b> 298.21 K" }, "geometry": { "type": "Point", "coordinates": [ -155.28169, 19.40952, 0.0 ] } },
{ "type": "Feature", "properties": { "Name": "Fire Detection Centroid ", "Description": "<b>Latitude: <\/b> 19.41733<br\/>  <b>Longitude: <\/b> -155.28792<br\/>  <b>Detection Time: <\/b> 2022-06-25 12:02 UTC<br\/>  <b>Sensor: <\/b> NOAA-20 VIIRS<br\/> <b>Confidence: <\/b> Nominal<br\/>  <b>Day\/Night: <\/b> Night<br\/> <b>Scan: <\/b> 0.39 km<br\/> <b>Track: <\/b> 0.36 km<br\/> <b>FRP: <\/b> 0.62 MW<br\/> <b>Brightness: <\/b> 295.65 K" }, "geometry": { "type": "Point", "coordinates": [ -155.28792, 19.41733, 0.0 ] } }
]
}
