{
"type": "FeatureCollection",
"crs": { "type": "name", "properties": { "name": "urn:ogc:def:crs:OGC:1.3:CRS84" } },
"features": [
{ "type": "Feature", "properties": { "Name": "Fire Detection Centroid ", "Description": "<b>Latitude: <\/b> 19.40716<br\/>  <b>Longitude: <\/b> -155.28479<br\/>  <b>Detection Time: <\/b> 2023-04-07 12:40 UTC<br\/>  <b>Sensor: <\/b> NOAA-20 VIIRS<br\/> <b>Confidence: <\/b> Nominal<br\/>  <b>Day\/Night: <\/b> Night<br\/> <b>Scan: <\/b> 0.41 km<br\/> <b>Track: <\/b> 0.61 km<br\/> <b>FRP: <\/b> 2.78 MW<br\/> <b>Brightness: <\/b> 302.02 K" }, "geometry": { "type": "Point", "coordinates": [ -155.28479, 19.40716, 0.0 ] } }
]
}
