{
"type": "FeatureCollection",
"crs": { "type": "name", "properties": { "name": "urn:ogc:def:crs:OGC:1.3:CRS84" } },
"features": [
{ "type": "Feature", "properties": { "Name": "Fire Detection Centroid ", "Description": "<b>Latitude: <\/b> 19.36716<br\/>  <b>Longitude: <\/b> -155.30963<br\/>  <b>Detection Time: <\/b> 2024-06-09 11:30 UTC<br\/>  <b>Sensor: <\/b> NOAA-20 VIIRS<br\/> <b>Confidence: <\/b> Nominal<br\/>  <b>Day\/Night: <\/b> Night<br\/> <b>Scan: <\/b> 0.5 km<br\/> <b>Track: <\/b> 0.49 km<br\/> <b>FRP: <\/b> 1.76 MW<br\/> <b>Brightness: <\/b> 302.26 K" }, "geometry": { "type": "Point", "coordinates": [ -155.30963, 19.36716, 0.0 ] } }
]
}
