{
"type": "FeatureCollection",
"crs": { "type": "name", "properties": { "name": "urn:ogc:def:crs:OGC:1.3:CRS84" } },
"features": [
{ "type": "Feature", "properties": { "Name": "Fire Detection Centroid ", "Description": "<b>Latitude: <\/b> 45.64905<br\/>  <b>Longitude: <\/b> -120.21419<br\/>  <b>Detection Time: <\/b> 2023-05-30 10:58 UTC<br\/>  <b>Sensor: <\/b> NOAA-20 VIIRS<br\/> <b>Confidence: <\/b> Nominal<br\/>  <b>Day\/Night: <\/b> Night<br\/> <b>Scan: <\/b> 0.38 km<br\/> <b>Track: <\/b> 0.59 km<br\/> <b>FRP: <\/b> 0.31 MW<br\/> <b>Brightness: <\/b> 298.59 K" }, "geometry": { "type": "Point", "coordinates": [ -120.21419, 45.64905, 0.0 ] } },
{ "type": "Feature", "properties": { "Name": "Fire Detection Centroid ", "Description": "<b>Latitude: <\/b> 43.93401<br\/>  <b>Longitude: <\/b> -123.51448<br\/>  <b>Detection Time: <\/b> 2023-05-30 10:58 UTC<br\/>  <b>Sensor: <\/b> NOAA-20 VIIRS<br\/> <b>Confidence: <\/b> Nominal<br\/>  <b>Day\/Night: <\/b> Night<br\/> <b>Scan: <\/b> 0.6 km<br\/> <b>Track: <\/b> 0.53 km<br\/> <b>FRP: <\/b> 0.85 MW<br\/> <b>Brightness: <\/b> 296.38 K" }, "geometry": { "type": "Point", "coordinates": [ -123.51448, 43.93401, 0.0 ] } },
{ "type": "Feature", "properties": { "Name": "Fire Detection Centroid ", "Description": "<b>Latitude: <\/b> 49.16076<br\/>  <b>Longitude: <\/b> -123.00233<br\/>  <b>Detection Time: <\/b> 2023-05-30 10:56 UTC<br\/>  <b>Sensor: <\/b> NOAA-20 VIIRS<br\/> <b>Confidence: <\/b> Nominal<br\/>  <b>Day\/Night: <\/b> Night<br\/> <b>Scan: <\/b> 0.46 km<br\/> <b>Track: <\/b> 0.47 km<br\/> <b>FRP: <\/b> 0.48 MW<br\/> <b>Brightness: <\/b> 295.5 K" }, "geometry": { "type": "Point", "coordinates": [ -123.00233, 49.16076, 0.0 ] } }
]
}
