{
"type": "FeatureCollection",
"crs": { "type": "name", "properties": { "name": "urn:ogc:def:crs:OGC:1.3:CRS84" } },
"features": [
{ "type": "Feature", "properties": { "Name": "Fire Detection Centroid ", "Description": "<b>Latitude: <\/b> 47.42766<br\/>  <b>Longitude: <\/b> -79.42514<br\/>  <b>Detection Time: <\/b> 2022-11-26 16:47 UTC<br\/>  <b>Sensor: <\/b> NOAA-20 VIIRS<br\/> <b>Confidence: <\/b> Nominal<br\/>  <b>Day\/Night: <\/b> Day<br\/> <b>Scan: <\/b> 0.62 km<br\/> <b>Track: <\/b> 0.71 km<br\/> <b>FRP: <\/b> 3.11 MW<br\/> <b>Brightness: <\/b> 325.88 K" }, "geometry": { "type": "Point", "coordinates": [ -79.42514, 47.42766, 0.0 ] } },
{ "type": "Feature", "properties": { "Name": "Fire Detection Centroid ", "Description": "<b>Latitude: <\/b> 46.04287<br\/>  <b>Longitude: <\/b> -73.14005<br\/>  <b>Detection Time: <\/b> 2022-11-26 16:47 UTC<br\/>  <b>Sensor: <\/b> NOAA-20 VIIRS<br\/> <b>Confidence: <\/b> Nominal<br\/>  <b>Day\/Night: <\/b> Day<br\/> <b>Scan: <\/b> 0.37 km<br\/> <b>Track: <\/b> 0.58 km<br\/> <b>FRP: <\/b> 3.52 MW<br\/> <b>Brightness: <\/b> 332.05 K" }, "geometry": { "type": "Point", "coordinates": [ -73.14005, 46.04287, 0.0 ] } }
]
}
