{
"type": "FeatureCollection",
"crs": { "type": "name", "properties": { "name": "urn:ogc:def:crs:OGC:1.3:CRS84" } },
"features": [
{ "type": "Feature", "properties": { "Name": "Fire Detection Centroid ", "Description": "<b>Latitude: <\/b> 46.86238<br\/>  <b>Longitude: <\/b> -67.90681<br\/>  <b>Detection Time: <\/b> 2023-09-26 16:48 UTC<br\/>  <b>Sensor: <\/b> NOAA-20 VIIRS<br\/> <b>Confidence: <\/b> Nominal<br\/>  <b>Day\/Night: <\/b> Day<br\/> <b>Scan: <\/b> 0.4 km<br\/> <b>Track: <\/b> 0.4 km<br\/> <b>FRP: <\/b> 2.87 MW<br\/> <b>Brightness: <\/b> 327.62 K" }, "geometry": { "type": "Point", "coordinates": [ -67.90681, 46.86238, 0.0 ] } },
{ "type": "Feature", "properties": { "Name": "Fire Detection Centroid ", "Description": "<b>Latitude: <\/b> 19.40497<br\/>  <b>Longitude: <\/b> -155.28065<br\/>  <b>Detection Time: <\/b> 2023-09-26 12:14 UTC<br\/>  <b>Sensor: <\/b> NOAA-20 VIIRS<br\/> <b>Confidence: <\/b> Nominal<br\/>  <b>Day\/Night: <\/b> Night<br\/> <b>Scan: <\/b> 0.51 km<br\/> <b>Track: <\/b> 0.41 km<br\/> <b>FRP: <\/b> 0.95 MW<br\/> <b>Brightness: <\/b> 295.59 K" }, "geometry": { "type": "Point", "coordinates": [ -155.28065, 19.40497, 0.0 ] } },
{ "type": "Feature", "properties": { "Name": "Fire Detection Centroid ", "Description": "<b>Latitude: <\/b> 19.40783<br\/>  <b>Longitude: <\/b> -155.27518<br\/>  <b>Detection Time: <\/b> 2023-09-26 12:14 UTC<br\/>  <b>Sensor: <\/b> NOAA-20 VIIRS<br\/> <b>Confidence: <\/b> Nominal<br\/>  <b>Day\/Night: <\/b> Night<br\/> <b>Scan: <\/b> 0.51 km<br\/> <b>Track: <\/b> 0.41 km<br\/> <b>FRP: <\/b> 1.38 MW<br\/> <b>Brightness: <\/b> 296.48 K" }, "geometry": { "type": "Point", "coordinates": [ -155.27518, 19.40783, 0.0 ] } },
{ "type": "Feature", "properties": { "Name": "Fire Detection Centroid ", "Description": "<b>Latitude: <\/b> 19.40869<br\/>  <b>Longitude: <\/b> -155.27991<br\/>  <b>Detection Time: <\/b> 2023-09-26 12:14 UTC<br\/>  <b>Sensor: <\/b> NOAA-20 VIIRS<br\/> <b>Confidence: <\/b> Nominal<br\/>  <b>Day\/Night: <\/b> Night<br\/> <b>Scan: <\/b> 0.51 km<br\/> <b>Track: <\/b> 0.41 km<br\/> <b>FRP: <\/b> 0.95 MW<br\/> <b>Brightness: <\/b> 295.92 K" }, "geometry": { "type": "Point", "coordinates": [ -155.27991, 19.40869, 0.0 ] } },
{ "type": "Feature", "properties": { "Name": "Fire Detection Centroid ", "Description": "<b>Latitude: <\/b> 19.40956<br\/>  <b>Longitude: <\/b> -155.28471<br\/>  <b>Detection Time: <\/b> 2023-09-26 12:14 UTC<br\/>  <b>Sensor: <\/b> NOAA-20 VIIRS<br\/> <b>Confidence: <\/b> Nominal<br\/>  <b>Day\/Night: <\/b> Night<br\/> <b>Scan: <\/b> 0.51 km<br\/> <b>Track: <\/b> 0.41 km<br\/> <b>FRP: <\/b> 0.95 MW<br\/> <b>Brightness: <\/b> 298.86 K" }, "geometry": { "type": "Point", "coordinates": [ -155.28471, 19.40956, 0.0 ] } },
{ "type": "Feature", "properties": { "Name": "Fire Detection Centroid ", "Description": "<b>Latitude: <\/b> 19.41328<br\/>  <b>Longitude: <\/b> -155.28406<br\/>  <b>Detection Time: <\/b> 2023-09-26 12:14 UTC<br\/>  <b>Sensor: <\/b> NOAA-20 VIIRS<br\/> <b>Confidence: <\/b> Nominal<br\/>  <b>Day\/Night: <\/b> Night<br\/> <b>Scan: <\/b> 0.51 km<br\/> <b>Track: <\/b> 0.41 km<br\/> <b>FRP: <\/b> 2.4 MW<br\/> <b>Brightness: <\/b> 302.17 K" }, "geometry": { "type": "Point", "coordinates": [ -155.28406, 19.41328, 0.0 ] } }
]
}
