{
"type": "FeatureCollection",
"crs": { "type": "name", "properties": { "name": "urn:ogc:def:crs:OGC:1.3:CRS84" } },
"features": [
{ "type": "Feature", "properties": { "Name": "Fire Detection Centroid ", "Description": "<b>Latitude: <\/b> 36.2182<br\/>  <b>Longitude: <\/b> -78.0539<br\/>  <b>Detection Time: <\/b> 2023-04-18 17:04 UTC<br\/>  <b>Sensor: <\/b> NOAA-20 VIIRS<br\/> <b>Confidence: <\/b> Nominal<br\/>  <b>Day\/Night: <\/b> Day<br\/> <b>Scan: <\/b> 0.7 km<br\/> <b>Track: <\/b> 0.8 km<br\/> <b>FRP: <\/b> 8.96 MW<br\/> <b>Brightness: <\/b> 331.58 K" }, "geometry": { "type": "Point", "coordinates": [ -78.0539, 36.2182, 0.0 ] } },
{ "type": "Feature", "properties": { "Name": "Fire Detection Centroid ", "Description": "<b>Latitude: <\/b> 19.20612<br\/>  <b>Longitude: <\/b> -70.15547<br\/>  <b>Detection Time: <\/b> 2023-04-18 16:59 UTC<br\/>  <b>Sensor: <\/b> NOAA-20 VIIRS<br\/> <b>Confidence: <\/b> Nominal<br\/>  <b>Day\/Night: <\/b> Day<br\/> <b>Scan: <\/b> 0.7 km<br\/> <b>Track: <\/b> 0.7 km<br\/> <b>FRP: <\/b> 8.01 MW<br\/> <b>Brightness: <\/b> 337.23 K" }, "geometry": { "type": "Point", "coordinates": [ -70.15547, 19.20612, 0.0 ] } },
{ "type": "Feature", "properties": { "Name": "Fire Detection Centroid ", "Description": "<b>Latitude: <\/b> 19.20612<br\/>  <b>Longitude: <\/b> -70.15547<br\/>  <b>Detection Time: <\/b> 2023-04-18 16:59 UTC<br\/>  <b>Sensor: <\/b> NOAA-20 VIIRS<br\/> <b>Confidence: <\/b> Nominal<br\/>  <b>Day\/Night: <\/b> Day<br\/> <b>Scan: <\/b> 0.7 km<br\/> <b>Track: <\/b> 0.7 km<br\/> <b>FRP: <\/b> 8.01 MW<br\/> <b>Brightness: <\/b> 337.23 K" }, "geometry": { "type": "Point", "coordinates": [ -70.15547, 19.20612, 0.0 ] } },
{ "type": "Feature", "properties": { "Name": "Fire Detection Centroid ", "Description": "<b>Latitude: <\/b> 19.5158<br\/>  <b>Longitude: <\/b> -70.05806<br\/>  <b>Detection Time: <\/b> 2023-04-18 16:59 UTC<br\/>  <b>Sensor: <\/b> NOAA-20 VIIRS<br\/> <b>Confidence: <\/b> Nominal<br\/>  <b>Day\/Night: <\/b> Day<br\/> <b>Scan: <\/b> 0.7 km<br\/> <b>Track: <\/b> 0.7 km<br\/> <b>FRP: <\/b> 4.65 MW<br\/> <b>Brightness: <\/b> 328.54 K" }, "geometry": { "type": "Point", "coordinates": [ -70.05806, 19.5158, 0.0 ] } },
{ "type": "Feature", "properties": { "Name": "Fire Detection Centroid ", "Description": "<b>Latitude: <\/b> 19.52236<br\/>  <b>Longitude: <\/b> -70.05974<br\/>  <b>Detection Time: <\/b> 2023-04-18 16:59 UTC<br\/>  <b>Sensor: <\/b> NOAA-20 VIIRS<br\/> <b>Confidence: <\/b> Nominal<br\/>  <b>Day\/Night: <\/b> Day<br\/> <b>Scan: <\/b> 0.7 km<br\/> <b>Track: <\/b> 0.7 km<br\/> <b>FRP: <\/b> 4.65 MW<br\/> <b>Brightness: <\/b> 333.99 K" }, "geometry": { "type": "Point", "coordinates": [ -70.05974, 19.52236, 0.0 ] } },
{ "type": "Feature", "properties": { "Name": "Fire Detection Centroid ", "Description": "<b>Latitude: <\/b> 19.52006<br\/>  <b>Longitude: <\/b> -70.05928<br\/>  <b>Detection Time: <\/b> 2023-04-18 16:59 UTC<br\/>  <b>Sensor: <\/b> NOAA-20 VIIRS<br\/> <b>Confidence: <\/b> Nominal<br\/>  <b>Day\/Night: <\/b> Day<br\/> <b>Scan: <\/b> 0.7 km<br\/> <b>Track: <\/b> 0.7 km<br\/> <b>FRP: <\/b> 6.51 MW<br\/> <b>Brightness: <\/b> 331.68 K" }, "geometry": { "type": "Point", "coordinates": [ -70.05928, 19.52006, 0.0 ] } }
]
}
