{
"type": "FeatureCollection",
"crs": { "type": "name", "properties": { "name": "urn:ogc:def:crs:OGC:1.3:CRS84" } },
"features": [
{ "type": "Feature", "properties": { "Name": "Fire Detection Centroid ", "Description": "<b>Latitude: <\/b> 21.45518<br\/>  <b>Longitude: <\/b> -158.1512<br\/>  <b>Detection Time: <\/b> 2022-11-04 12:25 UTC<br\/>  <b>Sensor: <\/b> NOAA-20 VIIRS<br\/> <b>Confidence: <\/b> Nominal<br\/>  <b>Day\/Night: <\/b> Night<br\/> <b>Scan: <\/b> 0.49 km<br\/> <b>Track: <\/b> 0.4 km<br\/> <b>FRP: <\/b> 1.69 MW<br\/> <b>Brightness: <\/b> 318.92 K" }, "geometry": { "type": "Point", "coordinates": [ -158.1512, 21.45518, 0.0 ] } }
]
}
