{
"type": "FeatureCollection",
"crs": { "type": "name", "properties": { "name": "urn:ogc:def:crs:OGC:1.3:CRS84" } },
"features": [
{ "type": "Feature", "properties": { "Name": "Fire Detection Centroid ", "Description": "<b>Latitude: <\/b> 19.59734<br\/>  <b>Longitude: <\/b> -155.50551<br\/>  <b>Detection Time: <\/b> 2023-03-26 11:23 UTC<br\/>  <b>Sensor: <\/b> NOAA-20 VIIRS<br\/> <b>Confidence: <\/b> Nominal<br\/>  <b>Day\/Night: <\/b> Night<br\/> <b>Scan: <\/b> 0.34 km<br\/> <b>Track: <\/b> 0.56 km<br\/> <b>FRP: <\/b> 1.12 MW<br\/> <b>Brightness: <\/b> 296.2 K" }, "geometry": { "type": "Point", "coordinates": [ -155.50551, 19.59734, 0.0 ] } },
{ "type": "Feature", "properties": { "Name": "Fire Detection Centroid ", "Description": "<b>Latitude: <\/b> 48.616<br\/>  <b>Longitude: <\/b> -124.54453<br\/>  <b>Detection Time: <\/b> 2023-03-26 11:15 UTC<br\/>  <b>Sensor: <\/b> NOAA-20 VIIRS<br\/> <b>Confidence: <\/b> Nominal<br\/>  <b>Day\/Night: <\/b> Night<br\/> <b>Scan: <\/b> 0.33 km<br\/> <b>Track: <\/b> 0.55 km<br\/> <b>FRP: <\/b> 0.09 MW<br\/> <b>Brightness: <\/b> 295.24 K" }, "geometry": { "type": "Point", "coordinates": [ -124.54453, 48.616, 0.0 ] } }
]
}
