{
"type": "FeatureCollection",
"crs": { "type": "name", "properties": { "name": "urn:ogc:def:crs:OGC:1.3:CRS84" } },
"features": [
{ "type": "Feature", "properties": { "Name": "Fire Detection Centroid ", "Description": "<b>Latitude: <\/b> 19.59615<br\/>  <b>Longitude: <\/b> -155.50485<br\/>  <b>Detection Time: <\/b> 2023-05-27 12:02 UTC<br\/>  <b>Sensor: <\/b> NOAA-20 VIIRS<br\/> <b>Confidence: <\/b> Nominal<br\/>  <b>Day\/Night: <\/b> Night<br\/> <b>Scan: <\/b> 0.39 km<br\/> <b>Track: <\/b> 0.36 km<br\/> <b>FRP: <\/b> 1.36 MW<br\/> <b>Brightness: <\/b> 295.66 K" }, "geometry": { "type": "Point", "coordinates": [ -155.50485, 19.59615, 0.0 ] } }
]
}
