{
"type": "FeatureCollection",
"crs": { "type": "name", "properties": { "name": "urn:ogc:def:crs:OGC:1.3:CRS84" } },
"features": [
{ "type": "Feature", "properties": { "Name": "Fire Detection Centroid ", "Description": "<b>Latitude: <\/b> 19.4103<br\/>  <b>Longitude: <\/b> -155.2771<br\/>  <b>Detection Time: <\/b> 2023-11-24 12:08 UTC<br\/>  <b>Sensor: <\/b> NOAA-20 VIIRS<br\/> <b>Confidence: <\/b> Nominal<br\/>  <b>Day\/Night: <\/b> Night<br\/> <b>Scan: <\/b> 0.43 km<br\/> <b>Track: <\/b> 0.38 km<br\/> <b>FRP: <\/b> 1.79 MW<br\/> <b>Brightness: <\/b> 299.19 K" }, "geometry": { "type": "Point", "coordinates": [ -155.2771, 19.4103, 0.0 ] } }
]
}
