{
"type": "FeatureCollection",
"crs": { "type": "name", "properties": { "name": "urn:ogc:def:crs:OGC:1.3:CRS84" } },
"features": [
{ "type": "Feature", "properties": { "Name": "Fire Detection Centroid ", "Description": "<b>Latitude: <\/b> 47.52565<br\/>  <b>Longitude: <\/b> -66.64238<br\/>  <b>Detection Time: <\/b> 2023-08-03 17:01 UTC<br\/>  <b>Sensor: <\/b> NOAA-20 VIIRS<br\/> <b>Confidence: <\/b> Nominal<br\/>  <b>Day\/Night: <\/b> Day<br\/> <b>Scan: <\/b> 0.4 km<br\/> <b>Track: <\/b> 0.4 km<br\/> <b>FRP: <\/b> 4.98 MW<br\/> <b>Brightness: <\/b> 331.8 K" }, "geometry": { "type": "Point", "coordinates": [ -66.64238, 47.52565, 0.0 ] } },
{ "type": "Feature", "properties": { "Name": "Fire Detection Centroid ", "Description": "<b>Latitude: <\/b> 44.44128<br\/>  <b>Longitude: <\/b> -69.45117<br\/>  <b>Detection Time: <\/b> 2023-08-03 17:00 UTC<br\/>  <b>Sensor: <\/b> NOAA-20 VIIRS<br\/> <b>Confidence: <\/b> Nominal<br\/>  <b>Day\/Night: <\/b> Day<br\/> <b>Scan: <\/b> 0.4 km<br\/> <b>Track: <\/b> 0.4 km<br\/> <b>FRP: <\/b> 1.27 MW<br\/> <b>Brightness: <\/b> 328.93 K" }, "geometry": { "type": "Point", "coordinates": [ -69.45117, 44.44128, 0.0 ] } }
]
}
