{
"type": "FeatureCollection",
"crs": { "type": "name", "properties": { "name": "urn:ogc:def:crs:OGC:1.3:CRS84" } },
"features": [
{ "type": "Feature", "properties": { "Name": "Fire Detection Centroid ", "Description": "<b>Latitude: <\/b> 19.40306<br\/>  <b>Longitude: <\/b> -155.28961<br\/>  <b>Detection Time: <\/b> 2022-11-08 00:22 UTC<br\/>  <b>Sensor: <\/b> NOAA-20 VIIRS<br\/> <b>Confidence: <\/b> Nominal<br\/>  <b>Day\/Night: <\/b> Day<br\/> <b>Scan: <\/b> 0.55 km<br\/> <b>Track: <\/b> 0.68 km<br\/> <b>FRP: <\/b> 34.95 MW<br\/> <b>Brightness: <\/b> 348.36 K" }, "geometry": { "type": "Point", "coordinates": [ -155.28961, 19.40306, 0.0 ] } },
{ "type": "Feature", "properties": { "Name": "Fire Detection Centroid ", "Description": "<b>Latitude: <\/b> 19.40355<br\/>  <b>Longitude: <\/b> -155.28404<br\/>  <b>Detection Time: <\/b> 2022-11-08 00:22 UTC<br\/>  <b>Sensor: <\/b> NOAA-20 VIIRS<br\/> <b>Confidence: <\/b> Low<br\/>  <b>Day\/Night: <\/b> Day<br\/> <b>Scan: <\/b> 0.55 km<br\/> <b>Track: <\/b> 0.68 km<br\/> <b>FRP: <\/b> 35.55 MW<br\/> <b>Brightness: <\/b> 356.17 K" }, "geometry": { "type": "Point", "coordinates": [ -155.28404, 19.40355, 0.0 ] } },
{ "type": "Feature", "properties": { "Name": "Fire Detection Centroid ", "Description": "<b>Latitude: <\/b> 19.40249<br\/>  <b>Longitude: <\/b> -155.29182<br\/>  <b>Detection Time: <\/b> 2022-11-08 00:21 UTC<br\/>  <b>Sensor: <\/b> NOAA-20 VIIRS<br\/> <b>Confidence: <\/b> Nominal<br\/>  <b>Day\/Night: <\/b> Day<br\/> <b>Scan: <\/b> 0.5 km<br\/> <b>Track: <\/b> 0.7 km<br\/> <b>FRP: <\/b> 34.94 MW<br\/> <b>Brightness: <\/b> 348.36 K" }, "geometry": { "type": "Point", "coordinates": [ -155.29182, 19.40249, 0.0 ] } },
{ "type": "Feature", "properties": { "Name": "Fire Detection Centroid ", "Description": "<b>Latitude: <\/b> 19.40299<br\/>  <b>Longitude: <\/b> -155.28609<br\/>  <b>Detection Time: <\/b> 2022-11-08 00:21 UTC<br\/>  <b>Sensor: <\/b> NOAA-20 VIIRS<br\/> <b>Confidence: <\/b> Low<br\/>  <b>Day\/Night: <\/b> Day<br\/> <b>Scan: <\/b> 0.5 km<br\/> <b>Track: <\/b> 0.7 km<br\/> <b>FRP: <\/b> 35.55 MW<br\/> <b>Brightness: <\/b> 356.17 K" }, "geometry": { "type": "Point", "coordinates": [ -155.28609, 19.40299, 0.0 ] } }
]
}
