{
"type": "FeatureCollection",
"crs": { "type": "name", "properties": { "name": "urn:ogc:def:crs:OGC:1.3:CRS84" } },
"features": [
{ "type": "Feature", "properties": { "Name": "Fire Detection Centroid ", "Description": "<b>Latitude: <\/b> 22.01604<br\/>  <b>Longitude: <\/b> -78.31047<br\/>  <b>Detection Time: <\/b> 2023-04-23 05:54 UTC<br\/>  <b>Sensor: <\/b> NOAA-20 VIIRS<br\/> <b>Confidence: <\/b> Nominal<br\/>  <b>Day\/Night: <\/b> Night<br\/> <b>Scan: <\/b> 0.8 km<br\/> <b>Track: <\/b> 0.8 km<br\/> <b>FRP: <\/b> 2.34 MW<br\/> <b>Brightness: <\/b> 307.21 K" }, "geometry": { "type": "Point", "coordinates": [ -78.31047, 22.01604, 0.0 ] } },
{ "type": "Feature", "properties": { "Name": "Fire Detection Centroid ", "Description": "<b>Latitude: <\/b> 20.63905<br\/>  <b>Longitude: <\/b> -76.88525<br\/>  <b>Detection Time: <\/b> 2023-04-23 05:54 UTC<br\/>  <b>Sensor: <\/b> NOAA-20 VIIRS<br\/> <b>Confidence: <\/b> Nominal<br\/>  <b>Day\/Night: <\/b> Night<br\/> <b>Scan: <\/b> 0.6 km<br\/> <b>Track: <\/b> 0.7 km<br\/> <b>FRP: <\/b> 1.05 MW<br\/> <b>Brightness: <\/b> 299.19 K" }, "geometry": { "type": "Point", "coordinates": [ -76.88525, 20.63905, 0.0 ] } },
{ "type": "Feature", "properties": { "Name": "Fire Detection Centroid ", "Description": "<b>Latitude: <\/b> 20.63954<br\/>  <b>Longitude: <\/b> -76.8912<br\/>  <b>Detection Time: <\/b> 2023-04-23 05:54 UTC<br\/>  <b>Sensor: <\/b> NOAA-20 VIIRS<br\/> <b>Confidence: <\/b> Nominal<br\/>  <b>Day\/Night: <\/b> Night<br\/> <b>Scan: <\/b> 0.6 km<br\/> <b>Track: <\/b> 0.7 km<br\/> <b>FRP: <\/b> 1.36 MW<br\/> <b>Brightness: <\/b> 303.55 K" }, "geometry": { "type": "Point", "coordinates": [ -76.8912, 20.63954, 0.0 ] } },
{ "type": "Feature", "properties": { "Name": "Fire Detection Centroid ", "Description": "<b>Latitude: <\/b> 22.02069<br\/>  <b>Longitude: <\/b> -78.30783<br\/>  <b>Detection Time: <\/b> 2023-04-23 05:54 UTC<br\/>  <b>Sensor: <\/b> NOAA-20 VIIRS<br\/> <b>Confidence: <\/b> Nominal<br\/>  <b>Day\/Night: <\/b> Night<br\/> <b>Scan: <\/b> 0.8 km<br\/> <b>Track: <\/b> 0.8 km<br\/> <b>FRP: <\/b> 1.97 MW<br\/> <b>Brightness: <\/b> 302.76 K" }, "geometry": { "type": "Point", "coordinates": [ -78.30783, 22.02069, 0.0 ] } },
{ "type": "Feature", "properties": { "Name": "Fire Detection Centroid ", "Description": "<b>Latitude: <\/b> 45.279<br\/>  <b>Longitude: <\/b> -66.01838<br\/>  <b>Detection Time: <\/b> 2023-04-23 05:47 UTC<br\/>  <b>Sensor: <\/b> NOAA-20 VIIRS<br\/> <b>Confidence: <\/b> Nominal<br\/>  <b>Day\/Night: <\/b> Night<br\/> <b>Scan: <\/b> 0.5 km<br\/> <b>Track: <\/b> 0.5 km<br\/> <b>FRP: <\/b> 1.85 MW<br\/> <b>Brightness: <\/b> 300.38 K" }, "geometry": { "type": "Point", "coordinates": [ -66.01838, 45.279, 0.0 ] } },
{ "type": "Feature", "properties": { "Name": "Fire Detection Centroid ", "Description": "<b>Latitude: <\/b> 48.18689<br\/>  <b>Longitude: <\/b> -64.9222<br\/>  <b>Detection Time: <\/b> 2023-04-23 05:46 UTC<br\/>  <b>Sensor: <\/b> NOAA-20 VIIRS<br\/> <b>Confidence: <\/b> Nominal<br\/>  <b>Day\/Night: <\/b> Night<br\/> <b>Scan: <\/b> 0.5 km<br\/> <b>Track: <\/b> 0.5 km<br\/> <b>FRP: <\/b> 0.87 MW<br\/> <b>Brightness: <\/b> 299.99 K" }, "geometry": { "type": "Point", "coordinates": [ -64.9222, 48.18689, 0.0 ] } }
]
}
