{
"type": "FeatureCollection",
"crs": { "type": "name", "properties": { "name": "urn:ogc:def:crs:OGC:1.3:CRS84" } },
"features": [
{ "type": "Feature", "properties": { "Name": "Fire Detection Centroid ", "Description": "<b>Latitude: <\/b> 49.15874<br\/>  <b>Longitude: <\/b> -123.0053<br\/>  <b>Detection Time: <\/b> 2024-05-19 11:17 UTC<br\/>  <b>Sensor: <\/b> NOAA-20 VIIRS<br\/> <b>Confidence: <\/b> Nominal<br\/>  <b>Day\/Night: <\/b> Night<br\/> <b>Scan: <\/b> 0.37 km<br\/> <b>Track: <\/b> 0.58 km<br\/> <b>FRP: <\/b> 0.68 MW<br\/> <b>Brightness: <\/b> 298.3 K" }, "geometry": { "type": "Point", "coordinates": [ -123.0053, 49.15874, 0.0 ] } },
{ "type": "Feature", "properties": { "Name": "Fire Detection Centroid ", "Description": "<b>Latitude: <\/b> 49.07574<br\/>  <b>Longitude: <\/b> -123.06307<br\/>  <b>Detection Time: <\/b> 2024-05-19 11:15 UTC<br\/>  <b>Sensor: <\/b> NOAA-20 VIIRS<br\/> <b>Confidence: <\/b> Nominal<br\/>  <b>Day\/Night: <\/b> Night<br\/> <b>Scan: <\/b> 0.4 km<br\/> <b>Track: <\/b> 0.6 km<br\/> <b>FRP: <\/b> 0.63 MW<br\/> <b>Brightness: <\/b> 298.3 K" }, "geometry": { "type": "Point", "coordinates": [ -123.06307, 49.07574, 0.0 ] } }
]
}
