{
"type": "FeatureCollection",
"crs": { "type": "name", "properties": { "name": "urn:ogc:def:crs:OGC:1.3:CRS84" } },
"features": [
{ "type": "Feature", "properties": { "Name": "Fire Detection Centroid ", "Description": "<b>Latitude: <\/b> 46.93077<br\/>  <b>Longitude: <\/b> -67.59026<br\/>  <b>Detection Time: <\/b> 2023-04-21 16:10 UTC<br\/>  <b>Sensor: <\/b> NOAA-20 VIIRS<br\/> <b>Confidence: <\/b> Nominal<br\/>  <b>Day\/Night: <\/b> Day<br\/> <b>Scan: <\/b> 0.5 km<br\/> <b>Track: <\/b> 0.7 km<br\/> <b>FRP: <\/b> 4.66 MW<br\/> <b>Brightness: <\/b> 342.26 K" }, "geometry": { "type": "Point", "coordinates": [ -67.59026, 46.93077, 0.0 ] } }
]
}
