{
"type": "FeatureCollection",
"crs": { "type": "name", "properties": { "name": "urn:ogc:def:crs:OGC:1.3:CRS84" } },
"features": [
{ "type": "Feature", "properties": { "Name": "Fire Detection Centroid ", "Description": "<b>Latitude: <\/b> 19.40674<br\/>  <b>Longitude: <\/b> -155.28015<br\/>  <b>Detection Time: <\/b> 2023-09-22 22:59 UTC<br\/>  <b>Sensor: <\/b> NOAA-20 VIIRS<br\/> <b>Confidence: <\/b> Nominal<br\/>  <b>Day\/Night: <\/b> Day<br\/> <b>Scan: <\/b> 0.61 km<br\/> <b>Track: <\/b> 0.54 km<br\/> <b>FRP: <\/b> 28.57 MW<br\/> <b>Brightness: <\/b> 350.8 K" }, "geometry": { "type": "Point", "coordinates": [ -155.28015, 19.40674, 0.0 ] } },
{ "type": "Feature", "properties": { "Name": "Fire Detection Centroid ", "Description": "<b>Latitude: <\/b> 19.41385<br\/>  <b>Longitude: <\/b> -155.26987<br\/>  <b>Detection Time: <\/b> 2023-09-22 22:59 UTC<br\/>  <b>Sensor: <\/b> NOAA-20 VIIRS<br\/> <b>Confidence: <\/b> Nominal<br\/>  <b>Day\/Night: <\/b> Day<br\/> <b>Scan: <\/b> 0.61 km<br\/> <b>Track: <\/b> 0.54 km<br\/> <b>FRP: <\/b> 12.59 MW<br\/> <b>Brightness: <\/b> 334.52 K" }, "geometry": { "type": "Point", "coordinates": [ -155.26987, 19.41385, 0.0 ] } },
{ "type": "Feature", "properties": { "Name": "Fire Detection Centroid ", "Description": "<b>Latitude: <\/b> 19.41272<br\/>  <b>Longitude: <\/b> -155.27553<br\/>  <b>Detection Time: <\/b> 2023-09-22 22:59 UTC<br\/>  <b>Sensor: <\/b> NOAA-20 VIIRS<br\/> <b>Confidence: <\/b> Nominal<br\/>  <b>Day\/Night: <\/b> Day<br\/> <b>Scan: <\/b> 0.61 km<br\/> <b>Track: <\/b> 0.54 km<br\/> <b>FRP: <\/b> 12.59 MW<br\/> <b>Brightness: <\/b> 346.26 K" }, "geometry": { "type": "Point", "coordinates": [ -155.27553, 19.41272, 0.0 ] } },
{ "type": "Feature", "properties": { "Name": "Fire Detection Centroid ", "Description": "<b>Latitude: <\/b> 19.41159<br\/>  <b>Longitude: <\/b> -155.28111<br\/>  <b>Detection Time: <\/b> 2023-09-22 22:59 UTC<br\/>  <b>Sensor: <\/b> NOAA-20 VIIRS<br\/> <b>Confidence: <\/b> Nominal<br\/>  <b>Day\/Night: <\/b> Day<br\/> <b>Scan: <\/b> 0.61 km<br\/> <b>Track: <\/b> 0.54 km<br\/> <b>FRP: <\/b> 25.61 MW<br\/> <b>Brightness: <\/b> 351.7 K" }, "geometry": { "type": "Point", "coordinates": [ -155.28111, 19.41159, 0.0 ] } },
{ "type": "Feature", "properties": { "Name": "Fire Detection Centroid ", "Description": "<b>Latitude: <\/b> 19.40903<br\/>  <b>Longitude: <\/b> -155.26875<br\/>  <b>Detection Time: <\/b> 2023-09-22 22:59 UTC<br\/>  <b>Sensor: <\/b> NOAA-20 VIIRS<br\/> <b>Confidence: <\/b> Low<br\/>  <b>Day\/Night: <\/b> Day<br\/> <b>Scan: <\/b> 0.61 km<br\/> <b>Track: <\/b> 0.54 km<br\/> <b>FRP: <\/b> 16.63 MW<br\/> <b>Brightness: <\/b> 337.26 K" }, "geometry": { "type": "Point", "coordinates": [ -155.26875, 19.40903, 0.0 ] } },
{ "type": "Feature", "properties": { "Name": "Fire Detection Centroid ", "Description": "<b>Latitude: <\/b> 19.40788<br\/>  <b>Longitude: <\/b> -155.27446<br\/>  <b>Detection Time: <\/b> 2023-09-22 22:59 UTC<br\/>  <b>Sensor: <\/b> NOAA-20 VIIRS<br\/> <b>Confidence: <\/b> Nominal<br\/>  <b>Day\/Night: <\/b> Day<br\/> <b>Scan: <\/b> 0.61 km<br\/> <b>Track: <\/b> 0.54 km<br\/> <b>FRP: <\/b> 16.63 MW<br\/> <b>Brightness: <\/b> 351.21 K" }, "geometry": { "type": "Point", "coordinates": [ -155.27446, 19.40788, 0.0 ] } }
]
}
