{
"type": "FeatureCollection",
"crs": { "type": "name", "properties": { "name": "urn:ogc:def:crs:OGC:1.3:CRS84" } },
"features": [
{ "type": "Feature", "properties": { "Name": "Fire Detection Centroid ", "Description": "<b>Latitude: <\/b> 49.92255<br\/>  <b>Longitude: <\/b> -124.22043<br\/>  <b>Detection Time: <\/b> 2023-12-11 21:27 UTC<br\/>  <b>Sensor: <\/b> NOAA-20 VIIRS<br\/> <b>Confidence: <\/b> Nominal<br\/>  <b>Day\/Night: <\/b> Day<br\/> <b>Scan: <\/b> 0.54 km<br\/> <b>Track: <\/b> 0.42 km<br\/> <b>FRP: <\/b> 5.54 MW<br\/> <b>Brightness: <\/b> 343.44 K" }, "geometry": { "type": "Point", "coordinates": [ -124.22043, 49.92255, 0.0 ] } },
{ "type": "Feature", "properties": { "Name": "Fire Detection Centroid ", "Description": "<b>Latitude: <\/b> 47.24491<br\/>  <b>Longitude: <\/b> -120.25285<br\/>  <b>Detection Time: <\/b> 2023-12-11 21:26 UTC<br\/>  <b>Sensor: <\/b> NOAA-20 VIIRS<br\/> <b>Confidence: <\/b> Nominal<br\/>  <b>Day\/Night: <\/b> Day<br\/> <b>Scan: <\/b> 0.5 km<br\/> <b>Track: <\/b> 0.5 km<br\/> <b>FRP: <\/b> 3.03 MW<br\/> <b>Brightness: <\/b> 326.14 K" }, "geometry": { "type": "Point", "coordinates": [ -120.25285, 47.24491, 0.0 ] } },
{ "type": "Feature", "properties": { "Name": "Fire Detection Centroid ", "Description": "<b>Latitude: <\/b> 46.28236<br\/>  <b>Longitude: <\/b> -123.00401<br\/>  <b>Detection Time: <\/b> 2023-12-11 21:25 UTC<br\/>  <b>Sensor: <\/b> NOAA-20 VIIRS<br\/> <b>Confidence: <\/b> Nominal<br\/>  <b>Day\/Night: <\/b> Day<br\/> <b>Scan: <\/b> 0.55 km<br\/> <b>Track: <\/b> 0.42 km<br\/> <b>FRP: <\/b> 4.31 MW<br\/> <b>Brightness: <\/b> 326.33 K" }, "geometry": { "type": "Point", "coordinates": [ -123.00401, 46.28236, 0.0 ] } },
{ "type": "Feature", "properties": { "Name": "Fire Detection Centroid ", "Description": "<b>Latitude: <\/b> 42.29087<br\/>  <b>Longitude: <\/b> -120.46645<br\/>  <b>Detection Time: <\/b> 2023-12-11 21:25 UTC<br\/>  <b>Sensor: <\/b> NOAA-20 VIIRS<br\/> <b>Confidence: <\/b> Nominal<br\/>  <b>Day\/Night: <\/b> Day<br\/> <b>Scan: <\/b> 0.43 km<br\/> <b>Track: <\/b> 0.46 km<br\/> <b>FRP: <\/b> 18.45 MW<br\/> <b>Brightness: <\/b> 327.77 K" }, "geometry": { "type": "Point", "coordinates": [ -120.46645, 42.29087, 0.0 ] } },
{ "type": "Feature", "properties": { "Name": "Fire Detection Centroid ", "Description": "<b>Latitude: <\/b> 42.29134<br\/>  <b>Longitude: <\/b> -120.46124<br\/>  <b>Detection Time: <\/b> 2023-12-11 21:25 UTC<br\/>  <b>Sensor: <\/b> NOAA-20 VIIRS<br\/> <b>Confidence: <\/b> Nominal<br\/>  <b>Day\/Night: <\/b> Day<br\/> <b>Scan: <\/b> 0.43 km<br\/> <b>Track: <\/b> 0.46 km<br\/> <b>FRP: <\/b> 18.45 MW<br\/> <b>Brightness: <\/b> 339.04 K" }, "geometry": { "type": "Point", "coordinates": [ -120.46124, 42.29134, 0.0 ] } },
{ "type": "Feature", "properties": { "Name": "Fire Detection Centroid ", "Description": "<b>Latitude: <\/b> 36.25507<br\/>  <b>Longitude: <\/b> -121.08998<br\/>  <b>Detection Time: <\/b> 2023-12-11 21:25 UTC<br\/>  <b>Sensor: <\/b> NOAA-20 VIIRS<br\/> <b>Confidence: <\/b> Nominal<br\/>  <b>Day\/Night: <\/b> Day<br\/> <b>Scan: <\/b> 0.51 km<br\/> <b>Track: <\/b> 0.41 km<br\/> <b>FRP: <\/b> 1.99 MW<br\/> <b>Brightness: <\/b> 327.88 K" }, "geometry": { "type": "Point", "coordinates": [ -121.08998, 36.25507, 0.0 ] } },
{ "type": "Feature", "properties": { "Name": "Fire Detection Centroid ", "Description": "<b>Latitude: <\/b> 37.88739<br\/>  <b>Longitude: <\/b> -121.67803<br\/>  <b>Detection Time: <\/b> 2023-12-11 21:25 UTC<br\/>  <b>Sensor: <\/b> NOAA-20 VIIRS<br\/> <b>Confidence: <\/b> Nominal<br\/>  <b>Day\/Night: <\/b> Day<br\/> <b>Scan: <\/b> 0.5 km<br\/> <b>Track: <\/b> 0.41 km<br\/> <b>FRP: <\/b> 1.54 MW<br\/> <b>Brightness: <\/b> 327.14 K" }, "geometry": { "type": "Point", "coordinates": [ -121.67803, 37.88739, 0.0 ] } },
{ "type": "Feature", "properties": { "Name": "Fire Detection Centroid ", "Description": "<b>Latitude: <\/b> 38.26305<br\/>  <b>Longitude: <\/b> -115.78396<br\/>  <b>Detection Time: <\/b> 2023-12-11 21:25 UTC<br\/>  <b>Sensor: <\/b> NOAA-20 VIIRS<br\/> <b>Confidence: <\/b> Nominal<br\/>  <b>Day\/Night: <\/b> Day<br\/> <b>Scan: <\/b> 0.34 km<br\/> <b>Track: <\/b> 0.56 km<br\/> <b>FRP: <\/b> 1.78 MW<br\/> <b>Brightness: <\/b> 325.46 K" }, "geometry": { "type": "Point", "coordinates": [ -115.78396, 38.26305, 0.0 ] } },
{ "type": "Feature", "properties": { "Name": "Fire Detection Centroid ", "Description": "<b>Latitude: <\/b> 47.24508<br\/>  <b>Longitude: <\/b> -120.25131<br\/>  <b>Detection Time: <\/b> 2023-12-11 21:25 UTC<br\/>  <b>Sensor: <\/b> NOAA-20 VIIRS<br\/> <b>Confidence: <\/b> Nominal<br\/>  <b>Day\/Night: <\/b> Day<br\/> <b>Scan: <\/b> 0.49 km<br\/> <b>Track: <\/b> 0.49 km<br\/> <b>FRP: <\/b> 3.03 MW<br\/> <b>Brightness: <\/b> 326.14 K" }, "geometry": { "type": "Point", "coordinates": [ -120.25131, 47.24508, 0.0 ] } }
]
}
