{
"type": "FeatureCollection",
"crs": { "type": "name", "properties": { "name": "urn:ogc:def:crs:OGC:1.3:CRS84" } },
"features": [
{ "type": "Feature", "properties": { "Name": "Fire Detection Centroid ", "Description": "<b>Latitude: <\/b> 18.26479<br\/>  <b>Longitude: <\/b> -70.36308<br\/>  <b>Detection Time: <\/b> 2023-11-12 05:48 UTC<br\/>  <b>Sensor: <\/b> NOAA-20 VIIRS<br\/> <b>Confidence: <\/b> Nominal<br\/>  <b>Day\/Night: <\/b> Night<br\/> <b>Scan: <\/b> 0.5 km<br\/> <b>Track: <\/b> 0.5 km<br\/> <b>FRP: <\/b> 1.11 MW<br\/> <b>Brightness: <\/b> 305.95 K" }, "geometry": { "type": "Point", "coordinates": [ -70.36308, 18.26479, 0.0 ] } },
{ "type": "Feature", "properties": { "Name": "Fire Detection Centroid ", "Description": "<b>Latitude: <\/b> 45.28291<br\/>  <b>Longitude: <\/b> -66.01942<br\/>  <b>Detection Time: <\/b> 2023-11-12 05:40 UTC<br\/>  <b>Sensor: <\/b> NOAA-20 VIIRS<br\/> <b>Confidence: <\/b> Nominal<br\/>  <b>Day\/Night: <\/b> Night<br\/> <b>Scan: <\/b> 0.6 km<br\/> <b>Track: <\/b> 0.5 km<br\/> <b>FRP: <\/b> 1.47 MW<br\/> <b>Brightness: <\/b> 295.29 K" }, "geometry": { "type": "Point", "coordinates": [ -66.01942, 45.28291, 0.0 ] } }
]
}
