{
"type": "FeatureCollection",
"crs": { "type": "name", "properties": { "name": "urn:ogc:def:crs:OGC:1.3:CRS84" } },
"features": [
{ "type": "Feature", "properties": { "Name": "Fire Detection Centroid ", "Description": "<b>Latitude: <\/b> 44.45214<br\/>  <b>Longitude: <\/b> -83.52643<br\/>  <b>Detection Time: <\/b> 2024-05-10 17:08 UTC<br\/>  <b>Sensor: <\/b> NOAA-20 VIIRS<br\/> <b>Confidence: <\/b> High<br\/>  <b>Day\/Night: <\/b> Day<br\/> <b>Scan: <\/b> 0.7 km<br\/> <b>Track: <\/b> 0.8 km<br\/> <b>FRP: <\/b> 50.15 MW<br\/> <b>Brightness: <\/b> 367 K" }, "geometry": { "type": "Point", "coordinates": [ -83.52643, 44.45214, 0.0 ] } },
{ "type": "Feature", "properties": { "Name": "Fire Detection Centroid ", "Description": "<b>Latitude: <\/b> 41.46783<br\/>  <b>Longitude: <\/b> -81.68546<br\/>  <b>Detection Time: <\/b> 2024-05-10 17:07 UTC<br\/>  <b>Sensor: <\/b> NOAA-20 VIIRS<br\/> <b>Confidence: <\/b> Nominal<br\/>  <b>Day\/Night: <\/b> Day<br\/> <b>Scan: <\/b> 0.7 km<br\/> <b>Track: <\/b> 0.8 km<br\/> <b>FRP: <\/b> 8.18 MW<br\/> <b>Brightness: <\/b> 330.94 K" }, "geometry": { "type": "Point", "coordinates": [ -81.68546, 41.46783, 0.0 ] } },
{ "type": "Feature", "properties": { "Name": "Fire Detection Centroid ", "Description": "<b>Latitude: <\/b> 43.20809<br\/>  <b>Longitude: <\/b> -79.21481<br\/>  <b>Detection Time: <\/b> 2024-05-10 17:07 UTC<br\/>  <b>Sensor: <\/b> NOAA-20 VIIRS<br\/> <b>Confidence: <\/b> Nominal<br\/>  <b>Day\/Night: <\/b> Day<br\/> <b>Scan: <\/b> 0.5 km<br\/> <b>Track: <\/b> 0.7 km<br\/> <b>FRP: <\/b> 18.34 MW<br\/> <b>Brightness: <\/b> 350.32 K" }, "geometry": { "type": "Point", "coordinates": [ -79.21481, 43.20809, 0.0 ] } },
{ "type": "Feature", "properties": { "Name": "Fire Detection Centroid ", "Description": "<b>Latitude: <\/b> 43.20984<br\/>  <b>Longitude: <\/b> -79.20907<br\/>  <b>Detection Time: <\/b> 2024-05-10 17:07 UTC<br\/>  <b>Sensor: <\/b> NOAA-20 VIIRS<br\/> <b>Confidence: <\/b> Low<br\/>  <b>Day\/Night: <\/b> Day<br\/> <b>Scan: <\/b> 0.5 km<br\/> <b>Track: <\/b> 0.7 km<br\/> <b>FRP: <\/b> 21.83 MW<br\/> <b>Brightness: <\/b> 356 K" }, "geometry": { "type": "Point", "coordinates": [ -79.20907, 43.20984, 0.0 ] } }
]
}
