{
"type": "FeatureCollection",
"crs": { "type": "name", "properties": { "name": "urn:ogc:def:crs:OGC:1.3:CRS84" } },
"features": [
{ "type": "Feature", "properties": { "Name": "Fire Detection Centroid ", "Description": "<b>Latitude: <\/b> 18.49559<br\/>  <b>Longitude: <\/b> -70.61802<br\/>  <b>Detection Time: <\/b> 2023-08-08 05:49 UTC<br\/>  <b>Sensor: <\/b> NOAA-20 VIIRS<br\/> <b>Confidence: <\/b> Nominal<br\/>  <b>Day\/Night: <\/b> Night<br\/> <b>Scan: <\/b> 0.6 km<br\/> <b>Track: <\/b> 0.5 km<br\/> <b>FRP: <\/b> 1.75 MW<br\/> <b>Brightness: <\/b> 310.84 K" }, "geometry": { "type": "Point", "coordinates": [ -70.61802, 18.49559, 0.0 ] } },
{ "type": "Feature", "properties": { "Name": "Fire Detection Centroid ", "Description": "<b>Latitude: <\/b> 17.70213<br\/>  <b>Longitude: <\/b> -64.74886<br\/>  <b>Detection Time: <\/b> 2023-08-08 05:49 UTC<br\/>  <b>Sensor: <\/b> NOAA-20 VIIRS<br\/> <b>Confidence: <\/b> Nominal<br\/>  <b>Day\/Night: <\/b> Night<br\/> <b>Scan: <\/b> 0.4 km<br\/> <b>Track: <\/b> 0.4 km<br\/> <b>FRP: <\/b> 2.59 MW<br\/> <b>Brightness: <\/b> 308.67 K" }, "geometry": { "type": "Point", "coordinates": [ -64.74886, 17.70213, 0.0 ] } }
]
}
