{
"type": "FeatureCollection",
"crs": { "type": "name", "properties": { "name": "urn:ogc:def:crs:OGC:1.3:CRS84" } },
"features": [
{ "type": "Feature", "properties": { "Name": "Fire Detection Centroid ", "Description": "<b>Latitude: <\/b> 37.95975<br\/>  <b>Longitude: <\/b> -82.19886<br\/>  <b>Detection Time: <\/b> 2023-12-24 17:17 UTC<br\/>  <b>Sensor: <\/b> NOAA-20 VIIRS<br\/> <b>Confidence: <\/b> Nominal<br\/>  <b>Day\/Night: <\/b> Day<br\/> <b>Scan: <\/b> 0.7 km<br\/> <b>Track: <\/b> 0.8 km<br\/> <b>FRP: <\/b> 3.35 MW<br\/> <b>Brightness: <\/b> 325.12 K" }, "geometry": { "type": "Point", "coordinates": [ -82.19886, 37.95975, 0.0 ] } },
{ "type": "Feature", "properties": { "Name": "Fire Detection Centroid ", "Description": "<b>Latitude: <\/b> 36.35303<br\/>  <b>Longitude: <\/b> -76.80506<br\/>  <b>Detection Time: <\/b> 2023-12-24 17:16 UTC<br\/>  <b>Sensor: <\/b> NOAA-20 VIIRS<br\/> <b>Confidence: <\/b> Nominal<br\/>  <b>Day\/Night: <\/b> Day<br\/> <b>Scan: <\/b> 0.4 km<br\/> <b>Track: <\/b> 0.6 km<br\/> <b>FRP: <\/b> 4.8 MW<br\/> <b>Brightness: <\/b> 349.52 K" }, "geometry": { "type": "Point", "coordinates": [ -76.80506, 36.35303, 0.0 ] } },
{ "type": "Feature", "properties": { "Name": "Fire Detection Centroid ", "Description": "<b>Latitude: <\/b> 18.95517<br\/>  <b>Longitude: <\/b> -72.13577<br\/>  <b>Detection Time: <\/b> 2023-12-24 17:11 UTC<br\/>  <b>Sensor: <\/b> NOAA-20 VIIRS<br\/> <b>Confidence: <\/b> Nominal<br\/>  <b>Day\/Night: <\/b> Day<br\/> <b>Scan: <\/b> 0.6 km<br\/> <b>Track: <\/b> 0.7 km<br\/> <b>FRP: <\/b> 5.86 MW<br\/> <b>Brightness: <\/b> 339.52 K" }, "geometry": { "type": "Point", "coordinates": [ -72.13577, 18.95517, 0.0 ] } },
{ "type": "Feature", "properties": { "Name": "Fire Detection Centroid ", "Description": "<b>Latitude: <\/b> 18.95805<br\/>  <b>Longitude: <\/b> -72.13722<br\/>  <b>Detection Time: <\/b> 2023-12-24 17:11 UTC<br\/>  <b>Sensor: <\/b> NOAA-20 VIIRS<br\/> <b>Confidence: <\/b> Nominal<br\/>  <b>Day\/Night: <\/b> Day<br\/> <b>Scan: <\/b> 0.6 km<br\/> <b>Track: <\/b> 0.7 km<br\/> <b>FRP: <\/b> 5.4 MW<br\/> <b>Brightness: <\/b> 339.47 K" }, "geometry": { "type": "Point", "coordinates": [ -72.13722, 18.95805, 0.0 ] } }
]
}
