{
"type": "FeatureCollection",
"crs": { "type": "name", "properties": { "name": "urn:ogc:def:crs:OGC:1.3:CRS84" } },
"features": [
{ "type": "Feature", "properties": { "Name": "Fire Detection Centroid ", "Description": "<b>Latitude: <\/b> 33.22042<br\/>  <b>Longitude: <\/b> -86.81617<br\/>  <b>Detection Time: <\/b> 2023-02-05 06:34 UTC<br\/>  <b>Sensor: <\/b> NOAA-20 VIIRS<br\/> <b>Confidence: <\/b> Nominal<br\/>  <b>Day\/Night: <\/b> Night<br\/> <b>Scan: <\/b> 0.7 km<br\/> <b>Track: <\/b> 0.7 km<br\/> <b>FRP: <\/b> 1.08 MW<br\/> <b>Brightness: <\/b> 296.28 K" }, "geometry": { "type": "Point", "coordinates": [ -86.81617, 33.22042, 0.0 ] } },
{ "type": "Feature", "properties": { "Name": "Fire Detection Centroid ", "Description": "<b>Latitude: <\/b> 33.5367<br\/>  <b>Longitude: <\/b> -86.75731<br\/>  <b>Detection Time: <\/b> 2023-02-05 06:34 UTC<br\/>  <b>Sensor: <\/b> NOAA-20 VIIRS<br\/> <b>Confidence: <\/b> Nominal<br\/>  <b>Day\/Night: <\/b> Night<br\/> <b>Scan: <\/b> 0.7 km<br\/> <b>Track: <\/b> 0.7 km<br\/> <b>FRP: <\/b> 0.83 MW<br\/> <b>Brightness: <\/b> 295.37 K" }, "geometry": { "type": "Point", "coordinates": [ -86.75731, 33.5367, 0.0 ] } },
{ "type": "Feature", "properties": { "Name": "Fire Detection Centroid ", "Description": "<b>Latitude: <\/b> 33.53769<br\/>  <b>Longitude: <\/b> -86.75932<br\/>  <b>Detection Time: <\/b> 2023-02-05 06:34 UTC<br\/>  <b>Sensor: <\/b> NOAA-20 VIIRS<br\/> <b>Confidence: <\/b> Nominal<br\/>  <b>Day\/Night: <\/b> Night<br\/> <b>Scan: <\/b> 0.7 km<br\/> <b>Track: <\/b> 0.7 km<br\/> <b>FRP: <\/b> 0.92 MW<br\/> <b>Brightness: <\/b> 297.92 K" }, "geometry": { "type": "Point", "coordinates": [ -86.75932, 33.53769, 0.0 ] } },
{ "type": "Feature", "properties": { "Name": "Fire Detection Centroid ", "Description": "<b>Latitude: <\/b> 33.22945<br\/>  <b>Longitude: <\/b> -87.51515<br\/>  <b>Detection Time: <\/b> 2023-02-05 06:34 UTC<br\/>  <b>Sensor: <\/b> NOAA-20 VIIRS<br\/> <b>Confidence: <\/b> Nominal<br\/>  <b>Day\/Night: <\/b> Night<br\/> <b>Scan: <\/b> 0.7 km<br\/> <b>Track: <\/b> 0.8 km<br\/> <b>FRP: <\/b> 2.72 MW<br\/> <b>Brightness: <\/b> 314.7 K" }, "geometry": { "type": "Point", "coordinates": [ -87.51515, 33.22945, 0.0 ] } },
{ "type": "Feature", "properties": { "Name": "Fire Detection Centroid ", "Description": "<b>Latitude: <\/b> 33.22079<br\/>  <b>Longitude: <\/b> -86.79304<br\/>  <b>Detection Time: <\/b> 2023-02-05 06:34 UTC<br\/>  <b>Sensor: <\/b> NOAA-20 VIIRS<br\/> <b>Confidence: <\/b> Nominal<br\/>  <b>Day\/Night: <\/b> Night<br\/> <b>Scan: <\/b> 0.7 km<br\/> <b>Track: <\/b> 0.7 km<br\/> <b>FRP: <\/b> 0.88 MW<br\/> <b>Brightness: <\/b> 295.56 K" }, "geometry": { "type": "Point", "coordinates": [ -86.79304, 33.22079, 0.0 ] } },
{ "type": "Feature", "properties": { "Name": "Fire Detection Centroid ", "Description": "<b>Latitude: <\/b> 33.22148<br\/>  <b>Longitude: <\/b> -86.81591<br\/>  <b>Detection Time: <\/b> 2023-02-05 06:34 UTC<br\/>  <b>Sensor: <\/b> NOAA-20 VIIRS<br\/> <b>Confidence: <\/b> Nominal<br\/>  <b>Day\/Night: <\/b> Night<br\/> <b>Scan: <\/b> 0.7 km<br\/> <b>Track: <\/b> 0.7 km<br\/> <b>FRP: <\/b> 0.96 MW<br\/> <b>Brightness: <\/b> 295.73 K" }, "geometry": { "type": "Point", "coordinates": [ -86.81591, 33.22148, 0.0 ] } },
{ "type": "Feature", "properties": { "Name": "Fire Detection Centroid ", "Description": "<b>Latitude: <\/b> 33.23369<br\/>  <b>Longitude: <\/b> -87.51537<br\/>  <b>Detection Time: <\/b> 2023-02-05 06:34 UTC<br\/>  <b>Sensor: <\/b> NOAA-20 VIIRS<br\/> <b>Confidence: <\/b> Nominal<br\/>  <b>Day\/Night: <\/b> Night<br\/> <b>Scan: <\/b> 0.7 km<br\/> <b>Track: <\/b> 0.8 km<br\/> <b>FRP: <\/b> 3.38 MW<br\/> <b>Brightness: <\/b> 315.32 K" }, "geometry": { "type": "Point", "coordinates": [ -87.51537, 33.23369, 0.0 ] } },
{ "type": "Feature", "properties": { "Name": "Fire Detection Centroid ", "Description": "<b>Latitude: <\/b> 40.31269<br\/>  <b>Longitude: <\/b> -80.61034<br\/>  <b>Detection Time: <\/b> 2023-02-05 06:32 UTC<br\/>  <b>Sensor: <\/b> NOAA-20 VIIRS<br\/> <b>Confidence: <\/b> Nominal<br\/>  <b>Day\/Night: <\/b> Night<br\/> <b>Scan: <\/b> 0.3 km<br\/> <b>Track: <\/b> 0.6 km<br\/> <b>FRP: <\/b> 2.67 MW<br\/> <b>Brightness: <\/b> 325.63 K" }, "geometry": { "type": "Point", "coordinates": [ -80.61034, 40.31269, 0.0 ] } },
{ "type": "Feature", "properties": { "Name": "Fire Detection Centroid ", "Description": "<b>Latitude: <\/b> 39.38313<br\/>  <b>Longitude: <\/b> -80.68346<br\/>  <b>Detection Time: <\/b> 2023-02-05 06:32 UTC<br\/>  <b>Sensor: <\/b> NOAA-20 VIIRS<br\/> <b>Confidence: <\/b> Nominal<br\/>  <b>Day\/Night: <\/b> Night<br\/> <b>Scan: <\/b> 0.3 km<br\/> <b>Track: <\/b> 0.6 km<br\/> <b>FRP: <\/b> 0.56 MW<br\/> <b>Brightness: <\/b> 298.97 K" }, "geometry": { "type": "Point", "coordinates": [ -80.68346, 39.38313, 0.0 ] } }
]
}
