{
"type": "FeatureCollection",
"crs": { "type": "name", "properties": { "name": "urn:ogc:def:crs:OGC:1.3:CRS84" } },
"features": [
{ "type": "Feature", "properties": { "Name": "Fire Detection Centroid ", "Description": "<b>Latitude: <\/b> 44.41178<br\/>  <b>Longitude: <\/b> -77.67678<br\/>  <b>Detection Time: <\/b> 2023-04-14 16:42 UTC<br\/>  <b>Sensor: <\/b> NOAA-20 VIIRS<br\/> <b>Confidence: <\/b> Nominal<br\/>  <b>Day\/Night: <\/b> Day<br\/> <b>Scan: <\/b> 0.8 km<br\/> <b>Track: <\/b> 0.8 km<br\/> <b>FRP: <\/b> 4.47 MW<br\/> <b>Brightness: <\/b> 326.28 K" }, "geometry": { "type": "Point", "coordinates": [ -77.67678, 44.41178, 0.0 ] } },
{ "type": "Feature", "properties": { "Name": "Fire Detection Centroid ", "Description": "<b>Latitude: <\/b> 45.02917<br\/>  <b>Longitude: <\/b> -67.38703<br\/>  <b>Detection Time: <\/b> 2023-04-14 16:41 UTC<br\/>  <b>Sensor: <\/b> NOAA-20 VIIRS<br\/> <b>Confidence: <\/b> Nominal<br\/>  <b>Day\/Night: <\/b> Day<br\/> <b>Scan: <\/b> 0.5 km<br\/> <b>Track: <\/b> 0.5 km<br\/> <b>FRP: <\/b> 8.64 MW<br\/> <b>Brightness: <\/b> 333.48 K" }, "geometry": { "type": "Point", "coordinates": [ -67.38703, 45.02917, 0.0 ] } },
{ "type": "Feature", "properties": { "Name": "Fire Detection Centroid ", "Description": "<b>Latitude: <\/b> 45.82895<br\/>  <b>Longitude: <\/b> -65.46568<br\/>  <b>Detection Time: <\/b> 2023-04-14 16:41 UTC<br\/>  <b>Sensor: <\/b> NOAA-20 VIIRS<br\/> <b>Confidence: <\/b> Nominal<br\/>  <b>Day\/Night: <\/b> Day<br\/> <b>Scan: <\/b> 0.4 km<br\/> <b>Track: <\/b> 0.4 km<br\/> <b>FRP: <\/b> 1.85 MW<br\/> <b>Brightness: <\/b> 330.91 K" }, "geometry": { "type": "Point", "coordinates": [ -65.46568, 45.82895, 0.0 ] } },
{ "type": "Feature", "properties": { "Name": "Fire Detection Centroid ", "Description": "<b>Latitude: <\/b> 44.10132<br\/>  <b>Longitude: <\/b> -75.57964<br\/>  <b>Detection Time: <\/b> 2023-04-14 16:41 UTC<br\/>  <b>Sensor: <\/b> NOAA-20 VIIRS<br\/> <b>Confidence: <\/b> Low<br\/>  <b>Day\/Night: <\/b> Day<br\/> <b>Scan: <\/b> 0.6 km<br\/> <b>Track: <\/b> 0.7 km<br\/> <b>FRP: <\/b> 2.91 MW<br\/> <b>Brightness: <\/b> 327.91 K" }, "geometry": { "type": "Point", "coordinates": [ -75.57964, 44.10132, 0.0 ] } },
{ "type": "Feature", "properties": { "Name": "Fire Detection Centroid ", "Description": "<b>Latitude: <\/b> 41.54156<br\/>  <b>Longitude: <\/b> -71.56025<br\/>  <b>Detection Time: <\/b> 2023-04-14 16:40 UTC<br\/>  <b>Sensor: <\/b> NOAA-20 VIIRS<br\/> <b>Confidence: <\/b> High<br\/>  <b>Day\/Night: <\/b> Day<br\/> <b>Scan: <\/b> 0.5 km<br\/> <b>Track: <\/b> 0.7 km<br\/> <b>FRP: <\/b> 10.76 MW<br\/> <b>Brightness: <\/b> 367 K" }, "geometry": { "type": "Point", "coordinates": [ -71.56025, 41.54156, 0.0 ] } },
{ "type": "Feature", "properties": { "Name": "Fire Detection Centroid ", "Description": "<b>Latitude: <\/b> 19.40536<br\/>  <b>Longitude: <\/b> -155.28252<br\/>  <b>Detection Time: <\/b> 2023-04-14 12:08 UTC<br\/>  <b>Sensor: <\/b> NOAA-20 VIIRS<br\/> <b>Confidence: <\/b> Nominal<br\/>  <b>Day\/Night: <\/b> Night<br\/> <b>Scan: <\/b> 0.43 km<br\/> <b>Track: <\/b> 0.38 km<br\/> <b>FRP: <\/b> 1.54 MW<br\/> <b>Brightness: <\/b> 301.02 K" }, "geometry": { "type": "Point", "coordinates": [ -155.28252, 19.40536, 0.0 ] } },
{ "type": "Feature", "properties": { "Name": "Fire Detection Centroid ", "Description": "<b>Latitude: <\/b> 20.86167<br\/>  <b>Longitude: <\/b> -156.42094<br\/>  <b>Detection Time: <\/b> 2023-04-14 12:08 UTC<br\/>  <b>Sensor: <\/b> NOAA-20 VIIRS<br\/> <b>Confidence: <\/b> Nominal<br\/>  <b>Day\/Night: <\/b> Night<br\/> <b>Scan: <\/b> 0.39 km<br\/> <b>Track: <\/b> 0.36 km<br\/> <b>FRP: <\/b> 0.43 MW<br\/> <b>Brightness: <\/b> 300.19 K" }, "geometry": { "type": "Point", "coordinates": [ -156.42094, 20.86167, 0.0 ] } },
{ "type": "Feature", "properties": { "Name": "Fire Detection Centroid ", "Description": "<b>Latitude: <\/b> 19.57834<br\/>  <b>Longitude: <\/b> -155.51003<br\/>  <b>Detection Time: <\/b> 2023-04-14 12:08 UTC<br\/>  <b>Sensor: <\/b> NOAA-20 VIIRS<br\/> <b>Confidence: <\/b> Nominal<br\/>  <b>Day\/Night: <\/b> Night<br\/> <b>Scan: <\/b> 0.42 km<br\/> <b>Track: <\/b> 0.38 km<br\/> <b>FRP: <\/b> 1.28 MW<br\/> <b>Brightness: <\/b> 295.04 K" }, "geometry": { "type": "Point", "coordinates": [ -155.51003, 19.57834, 0.0 ] } },
{ "type": "Feature", "properties": { "Name": "Fire Detection Centroid ", "Description": "<b>Latitude: <\/b> 19.40606<br\/>  <b>Longitude: <\/b> -155.28654<br\/>  <b>Detection Time: <\/b> 2023-04-14 12:08 UTC<br\/>  <b>Sensor: <\/b> NOAA-20 VIIRS<br\/> <b>Confidence: <\/b> Nominal<br\/>  <b>Day\/Night: <\/b> Night<br\/> <b>Scan: <\/b> 0.43 km<br\/> <b>Track: <\/b> 0.38 km<br\/> <b>FRP: <\/b> 1.54 MW<br\/> <b>Brightness: <\/b> 299.65 K" }, "geometry": { "type": "Point", "coordinates": [ -155.28654, 19.40606, 0.0 ] } }
]
}
