{
"type": "FeatureCollection",
"crs": { "type": "name", "properties": { "name": "urn:ogc:def:crs:OGC:1.3:CRS84" } },
"features": [
{ "type": "Feature", "properties": { "Name": "Fire Detection Centroid ", "Description": "<b>Latitude: <\/b> 18.92737<br\/>  <b>Longitude: <\/b> -70.35339<br\/>  <b>Detection Time: <\/b> 2023-07-07 05:49 UTC<br\/>  <b>Sensor: <\/b> NOAA-20 VIIRS<br\/> <b>Confidence: <\/b> Nominal<br\/>  <b>Day\/Night: <\/b> Night<br\/> <b>Scan: <\/b> 0.6 km<br\/> <b>Track: <\/b> 0.5 km<br\/> <b>FRP: <\/b> 6.44 MW<br\/> <b>Brightness: <\/b> 331.68 K" }, "geometry": { "type": "Point", "coordinates": [ -70.35339, 18.92737, 0.0 ] } },
{ "type": "Feature", "properties": { "Name": "Fire Detection Centroid ", "Description": "<b>Latitude: <\/b> 17.69938<br\/>  <b>Longitude: <\/b> -64.74857<br\/>  <b>Detection Time: <\/b> 2023-07-07 05:49 UTC<br\/>  <b>Sensor: <\/b> NOAA-20 VIIRS<br\/> <b>Confidence: <\/b> Nominal<br\/>  <b>Day\/Night: <\/b> Night<br\/> <b>Scan: <\/b> 0.4 km<br\/> <b>Track: <\/b> 0.4 km<br\/> <b>FRP: <\/b> 2.52 MW<br\/> <b>Brightness: <\/b> 309.7 K" }, "geometry": { "type": "Point", "coordinates": [ -64.74857, 17.69938, 0.0 ] } },
{ "type": "Feature", "properties": { "Name": "Fire Detection Centroid ", "Description": "<b>Latitude: <\/b> 19.61814<br\/>  <b>Longitude: <\/b> -69.88857<br\/>  <b>Detection Time: <\/b> 2023-07-07 05:48 UTC<br\/>  <b>Sensor: <\/b> NOAA-20 VIIRS<br\/> <b>Confidence: <\/b> Nominal<br\/>  <b>Day\/Night: <\/b> Night<br\/> <b>Scan: <\/b> 0.5 km<br\/> <b>Track: <\/b> 0.5 km<br\/> <b>FRP: <\/b> 2.49 MW<br\/> <b>Brightness: <\/b> 305.71 K" }, "geometry": { "type": "Point", "coordinates": [ -69.88857, 19.61814, 0.0 ] } },
{ "type": "Feature", "properties": { "Name": "Fire Detection Centroid ", "Description": "<b>Latitude: <\/b> 19.99658<br\/>  <b>Longitude: <\/b> -75.77931<br\/>  <b>Detection Time: <\/b> 2023-07-07 05:48 UTC<br\/>  <b>Sensor: <\/b> NOAA-20 VIIRS<br\/> <b>Confidence: <\/b> Nominal<br\/>  <b>Day\/Night: <\/b> Night<br\/> <b>Scan: <\/b> 0.6 km<br\/> <b>Track: <\/b> 0.7 km<br\/> <b>FRP: <\/b> 1.43 MW<br\/> <b>Brightness: <\/b> 308.64 K" }, "geometry": { "type": "Point", "coordinates": [ -75.77931, 19.99658, 0.0 ] } },
{ "type": "Feature", "properties": { "Name": "Fire Detection Centroid ", "Description": "<b>Latitude: <\/b> 45.83703<br\/>  <b>Longitude: <\/b> -73.25079<br\/>  <b>Detection Time: <\/b> 2023-07-07 05:41 UTC<br\/>  <b>Sensor: <\/b> NOAA-20 VIIRS<br\/> <b>Confidence: <\/b> Nominal<br\/>  <b>Day\/Night: <\/b> Night<br\/> <b>Scan: <\/b> 0.7 km<br\/> <b>Track: <\/b> 0.7 km<br\/> <b>FRP: <\/b> 3.7 MW<br\/> <b>Brightness: <\/b> 306.75 K" }, "geometry": { "type": "Point", "coordinates": [ -73.25079, 45.83703, 0.0 ] } }
]
}
