{
"type": "FeatureCollection",
"crs": { "type": "name", "properties": { "name": "urn:ogc:def:crs:OGC:1.3:CRS84" } },
"features": [
{ "type": "Feature", "properties": { "Name": "Fire Detection Centroid ", "Description": "<b>Latitude: <\/b> 45.75368<br\/>  <b>Longitude: <\/b> -66.2683<br\/>  <b>Detection Time: <\/b> 2023-05-07 16:10 UTC<br\/>  <b>Sensor: <\/b> NOAA-20 VIIRS<br\/> <b>Confidence: <\/b> Nominal<br\/>  <b>Day\/Night: <\/b> Day<br\/> <b>Scan: <\/b> 0.5 km<br\/> <b>Track: <\/b> 0.7 km<br\/> <b>FRP: <\/b> 4.17 MW<br\/> <b>Brightness: <\/b> 336.38 K" }, "geometry": { "type": "Point", "coordinates": [ -66.2683, 45.75368, 0.0 ] } },
{ "type": "Feature", "properties": { "Name": "Fire Detection Centroid ", "Description": "<b>Latitude: <\/b> 45.75543<br\/>  <b>Longitude: <\/b> -66.26283<br\/>  <b>Detection Time: <\/b> 2023-05-07 16:10 UTC<br\/>  <b>Sensor: <\/b> NOAA-20 VIIRS<br\/> <b>Confidence: <\/b> Nominal<br\/>  <b>Day\/Night: <\/b> Day<br\/> <b>Scan: <\/b> 0.5 km<br\/> <b>Track: <\/b> 0.7 km<br\/> <b>FRP: <\/b> 4.17 MW<br\/> <b>Brightness: <\/b> 345.08 K" }, "geometry": { "type": "Point", "coordinates": [ -66.26283, 45.75543, 0.0 ] } },
{ "type": "Feature", "properties": { "Name": "Fire Detection Centroid ", "Description": "<b>Latitude: <\/b> 45.75187<br\/>  <b>Longitude: <\/b> -66.26066<br\/>  <b>Detection Time: <\/b> 2023-05-07 16:10 UTC<br\/>  <b>Sensor: <\/b> NOAA-20 VIIRS<br\/> <b>Confidence: <\/b> Nominal<br\/>  <b>Day\/Night: <\/b> Day<br\/> <b>Scan: <\/b> 0.5 km<br\/> <b>Track: <\/b> 0.7 km<br\/> <b>FRP: <\/b> 3.56 MW<br\/> <b>Brightness: <\/b> 339.55 K" }, "geometry": { "type": "Point", "coordinates": [ -66.26066, 45.75187, 0.0 ] } },
{ "type": "Feature", "properties": { "Name": "Fire Detection Centroid ", "Description": "<b>Latitude: <\/b> 45.75361<br\/>  <b>Longitude: <\/b> -66.25507<br\/>  <b>Detection Time: <\/b> 2023-05-07 16:10 UTC<br\/>  <b>Sensor: <\/b> NOAA-20 VIIRS<br\/> <b>Confidence: <\/b> Nominal<br\/>  <b>Day\/Night: <\/b> Day<br\/> <b>Scan: <\/b> 0.5 km<br\/> <b>Track: <\/b> 0.7 km<br\/> <b>FRP: <\/b> 3.56 MW<br\/> <b>Brightness: <\/b> 328.86 K" }, "geometry": { "type": "Point", "coordinates": [ -66.25507, 45.75361, 0.0 ] } }
]
}
