{
"type": "FeatureCollection",
"crs": { "type": "name", "properties": { "name": "urn:ogc:def:crs:OGC:1.3:CRS84" } },
"features": [
{ "type": "Feature", "properties": { "Name": "Fire Detection Centroid ", "Description": "<b>Latitude: <\/b> 19.40472<br\/>  <b>Longitude: <\/b> -155.28282<br\/>  <b>Detection Time: <\/b> 2024-04-20 12:10 UTC<br\/>  <b>Sensor: <\/b> NOAA-20 VIIRS<br\/> <b>Confidence: <\/b> Nominal<br\/>  <b>Day\/Night: <\/b> Night<br\/> <b>Scan: <\/b> 0.44 km<br\/> <b>Track: <\/b> 0.38 km<br\/> <b>FRP: <\/b> 2.51 MW<br\/> <b>Brightness: <\/b> 304.88 K" }, "geometry": { "type": "Point", "coordinates": [ -155.28282, 19.40472, 0.0 ] } },
{ "type": "Feature", "properties": { "Name": "Fire Detection Centroid ", "Description": "<b>Latitude: <\/b> 19.33864<br\/>  <b>Longitude: <\/b> -155.29477<br\/>  <b>Detection Time: <\/b> 2024-04-20 12:09 UTC<br\/>  <b>Sensor: <\/b> NOAA-20 VIIRS<br\/> <b>Confidence: <\/b> Nominal<br\/>  <b>Day\/Night: <\/b> Night<br\/> <b>Scan: <\/b> 0.4 km<br\/> <b>Track: <\/b> 0.4 km<br\/> <b>FRP: <\/b> 2.5 MW<br\/> <b>Brightness: <\/b> 304.88 K" }, "geometry": { "type": "Point", "coordinates": [ -155.29477, 19.33864, 0.0 ] } }
]
}
