{
"type": "FeatureCollection",
"crs": { "type": "name", "properties": { "name": "urn:ogc:def:crs:OGC:1.3:CRS84" } },
"features": [
{ "type": "Feature", "properties": { "Name": "Fire Detection Centroid ", "Description": "<b>Latitude: <\/b> 41.2679<br\/>  <b>Longitude: <\/b> -105.60613<br\/>  <b>Detection Time: <\/b> 2023-02-26 10:00 UTC<br\/>  <b>Sensor: <\/b> NOAA-20 VIIRS<br\/> <b>Confidence: <\/b> Nominal<br\/>  <b>Day\/Night: <\/b> Night<br\/> <b>Scan: <\/b> 0.5 km<br\/> <b>Track: <\/b> 0.7 km<br\/> <b>FRP: <\/b> 0.98 MW<br\/> <b>Brightness: <\/b> 296.63 K" }, "geometry": { "type": "Point", "coordinates": [ -105.60613, 41.2679, 0.0 ] } },
{ "type": "Feature", "properties": { "Name": "Fire Detection Centroid ", "Description": "<b>Latitude: <\/b> 43.0793<br\/>  <b>Longitude: <\/b> -114.15429<br\/>  <b>Detection Time: <\/b> 2023-02-26 10:00 UTC<br\/>  <b>Sensor: <\/b> NOAA-20 VIIRS<br\/> <b>Confidence: <\/b> Nominal<br\/>  <b>Day\/Night: <\/b> Night<br\/> <b>Scan: <\/b> 0.6 km<br\/> <b>Track: <\/b> 0.4 km<br\/> <b>FRP: <\/b> 1.64 MW<br\/> <b>Brightness: <\/b> 316.1 K" }, "geometry": { "type": "Point", "coordinates": [ -114.15429, 43.0793, 0.0 ] } },
{ "type": "Feature", "properties": { "Name": "Fire Detection Centroid ", "Description": "<b>Latitude: <\/b> 45.94556<br\/>  <b>Longitude: <\/b> -111.47803<br\/>  <b>Detection Time: <\/b> 2023-02-26 09:59 UTC<br\/>  <b>Sensor: <\/b> NOAA-20 VIIRS<br\/> <b>Confidence: <\/b> Nominal<br\/>  <b>Day\/Night: <\/b> Night<br\/> <b>Scan: <\/b> 0.4 km<br\/> <b>Track: <\/b> 0.5 km<br\/> <b>FRP: <\/b> 1.33 MW<br\/> <b>Brightness: <\/b> 303.15 K" }, "geometry": { "type": "Point", "coordinates": [ -111.47803, 45.94556, 0.0 ] } },
{ "type": "Feature", "properties": { "Name": "Fire Detection Centroid ", "Description": "<b>Latitude: <\/b> 44.16235<br\/>  <b>Longitude: <\/b> -105.42561<br\/>  <b>Detection Time: <\/b> 2023-02-26 09:59 UTC<br\/>  <b>Sensor: <\/b> NOAA-20 VIIRS<br\/> <b>Confidence: <\/b> Nominal<br\/>  <b>Day\/Night: <\/b> Night<br\/> <b>Scan: <\/b> 0.4 km<br\/> <b>Track: <\/b> 0.6 km<br\/> <b>FRP: <\/b> 0.58 MW<br\/> <b>Brightness: <\/b> 295.81 K" }, "geometry": { "type": "Point", "coordinates": [ -105.42561, 44.16235, 0.0 ] } },
{ "type": "Feature", "properties": { "Name": "Fire Detection Centroid ", "Description": "<b>Latitude: <\/b> 43.69291<br\/>  <b>Longitude: <\/b> -105.35719<br\/>  <b>Detection Time: <\/b> 2023-02-26 09:59 UTC<br\/>  <b>Sensor: <\/b> NOAA-20 VIIRS<br\/> <b>Confidence: <\/b> Nominal<br\/>  <b>Day\/Night: <\/b> Night<br\/> <b>Scan: <\/b> 0.5 km<br\/> <b>Track: <\/b> 0.6 km<br\/> <b>FRP: <\/b> 1.65 MW<br\/> <b>Brightness: <\/b> 312.22 K" }, "geometry": { "type": "Point", "coordinates": [ -105.35719, 43.69291, 0.0 ] } }
]
}
