{
"type": "FeatureCollection",
"crs": { "type": "name", "properties": { "name": "urn:ogc:def:crs:OGC:1.3:CRS84" } },
"features": [
{ "type": "Feature", "properties": { "Name": "Fire Detection Centroid ", "Description": "<b>Latitude: <\/b> 39.14217<br\/>  <b>Longitude: <\/b> -78.05231<br\/>  <b>Detection Time: <\/b> 2023-01-07 16:58 UTC<br\/>  <b>Sensor: <\/b> NOAA-20 VIIRS<br\/> <b>Confidence: <\/b> Nominal<br\/>  <b>Day\/Night: <\/b> Day<br\/> <b>Scan: <\/b> 0.72 km<br\/> <b>Track: <\/b> 0.76 km<br\/> <b>FRP: <\/b> 2.16 MW<br\/> <b>Brightness: <\/b> 325.83 K" }, "geometry": { "type": "Point", "coordinates": [ -78.05231, 39.14217, 0.0 ] } }
]
}
