{
"type": "FeatureCollection",
"crs": { "type": "name", "properties": { "name": "urn:ogc:def:crs:OGC:1.3:CRS84" } },
"features": [
{ "type": "Feature", "properties": { "Name": "Fire Detection Centroid ", "Description": "<b>Latitude: <\/b> 18.92862<br\/>  <b>Longitude: <\/b> -70.35517<br\/>  <b>Detection Time: <\/b> 2022-07-10 05:35 UTC<br\/>  <b>Sensor: <\/b> NOAA-20 VIIRS<br\/> <b>Confidence: <\/b> Nominal<br\/>  <b>Day\/Night: <\/b> Night<br\/> <b>Scan: <\/b> 0.4 km<br\/> <b>Track: <\/b> 0.6 km<br\/> <b>FRP: <\/b> 1.41 MW<br\/> <b>Brightness: <\/b> 313.78 K" }, "geometry": { "type": "Point", "coordinates": [ -70.35517, 18.92862, 0.0 ] } },
{ "type": "Feature", "properties": { "Name": "Fire Detection Centroid ", "Description": "<b>Latitude: <\/b> 18.92905<br\/>  <b>Longitude: <\/b> -70.35953<br\/>  <b>Detection Time: <\/b> 2022-07-10 05:35 UTC<br\/>  <b>Sensor: <\/b> NOAA-20 VIIRS<br\/> <b>Confidence: <\/b> Nominal<br\/>  <b>Day\/Night: <\/b> Night<br\/> <b>Scan: <\/b> 0.5 km<br\/> <b>Track: <\/b> 0.6 km<br\/> <b>FRP: <\/b> 1.41 MW<br\/> <b>Brightness: <\/b> 302.63 K" }, "geometry": { "type": "Point", "coordinates": [ -70.35953, 18.92905, 0.0 ] } },
{ "type": "Feature", "properties": { "Name": "Fire Detection Centroid ", "Description": "<b>Latitude: <\/b> 45.28289<br\/>  <b>Longitude: <\/b> -66.01714<br\/>  <b>Detection Time: <\/b> 2022-07-10 05:28 UTC<br\/>  <b>Sensor: <\/b> NOAA-20 VIIRS<br\/> <b>Confidence: <\/b> Nominal<br\/>  <b>Day\/Night: <\/b> Night<br\/> <b>Scan: <\/b> 0.4 km<br\/> <b>Track: <\/b> 0.6 km<br\/> <b>FRP: <\/b> 1.21 MW<br\/> <b>Brightness: <\/b> 299.33 K" }, "geometry": { "type": "Point", "coordinates": [ -66.01714, 45.28289, 0.0 ] } },
{ "type": "Feature", "properties": { "Name": "Fire Detection Centroid ", "Description": "<b>Latitude: <\/b> 45.28177<br\/>  <b>Longitude: <\/b> -66.01334<br\/>  <b>Detection Time: <\/b> 2022-07-10 05:28 UTC<br\/>  <b>Sensor: <\/b> NOAA-20 VIIRS<br\/> <b>Confidence: <\/b> Nominal<br\/>  <b>Day\/Night: <\/b> Night<br\/> <b>Scan: <\/b> 0.4 km<br\/> <b>Track: <\/b> 0.6 km<br\/> <b>FRP: <\/b> 2.09 MW<br\/> <b>Brightness: <\/b> 304.61 K" }, "geometry": { "type": "Point", "coordinates": [ -66.01334, 45.28177, 0.0 ] } },
{ "type": "Feature", "properties": { "Name": "Fire Detection Centroid ", "Description": "<b>Latitude: <\/b> 48.19056<br\/>  <b>Longitude: <\/b> -64.92081<br\/>  <b>Detection Time: <\/b> 2022-07-10 05:27 UTC<br\/>  <b>Sensor: <\/b> NOAA-20 VIIRS<br\/> <b>Confidence: <\/b> Nominal<br\/>  <b>Day\/Night: <\/b> Night<br\/> <b>Scan: <\/b> 0.4 km<br\/> <b>Track: <\/b> 0.6 km<br\/> <b>FRP: <\/b> 0.68 MW<br\/> <b>Brightness: <\/b> 301.57 K" }, "geometry": { "type": "Point", "coordinates": [ -64.92081, 48.19056, 0.0 ] } }
]
}
