{
"type": "FeatureCollection",
"crs": { "type": "name", "properties": { "name": "urn:ogc:def:crs:OGC:1.3:CRS84" } },
"features": [
{ "type": "Feature", "properties": { "Name": "Fire Detection Centroid ", "Description": "<b>Latitude: <\/b> 18.13612<br\/>  <b>Longitude: <\/b> -71.20596<br\/>  <b>Detection Time: <\/b> 2023-04-29 05:42 UTC<br\/>  <b>Sensor: <\/b> NOAA-20 VIIRS<br\/> <b>Confidence: <\/b> Nominal<br\/>  <b>Day\/Night: <\/b> Night<br\/> <b>Scan: <\/b> 0.4 km<br\/> <b>Track: <\/b> 0.6 km<br\/> <b>FRP: <\/b> 0.74 MW<br\/> <b>Brightness: <\/b> 297.49 K" }, "geometry": { "type": "Point", "coordinates": [ -71.20596, 18.13612, 0.0 ] } }
]
}
