{
"type": "FeatureCollection",
"crs": { "type": "name", "properties": { "name": "urn:ogc:def:crs:OGC:1.3:CRS84" } },
"features": [
{ "type": "Feature", "properties": { "Name": "Fire Detection Centroid ", "Description": "<b>Latitude: <\/b> 18.92804<br\/>  <b>Longitude: <\/b> -70.35206<br\/>  <b>Detection Time: <\/b> 2023-10-06 05:42 UTC<br\/>  <b>Sensor: <\/b> NOAA-20 VIIRS<br\/> <b>Confidence: <\/b> Nominal<br\/>  <b>Day\/Night: <\/b> Night<br\/> <b>Scan: <\/b> 0.3 km<br\/> <b>Track: <\/b> 0.6 km<br\/> <b>FRP: <\/b> 4.43 MW<br\/> <b>Brightness: <\/b> 329.98 K" }, "geometry": { "type": "Point", "coordinates": [ -70.35206, 18.92804, 0.0 ] } },
{ "type": "Feature", "properties": { "Name": "Fire Detection Centroid ", "Description": "<b>Latitude: <\/b> 18.92843<br\/>  <b>Longitude: <\/b> -70.35557<br\/>  <b>Detection Time: <\/b> 2023-10-06 05:42 UTC<br\/>  <b>Sensor: <\/b> NOAA-20 VIIRS<br\/> <b>Confidence: <\/b> Nominal<br\/>  <b>Day\/Night: <\/b> Night<br\/> <b>Scan: <\/b> 0.3 km<br\/> <b>Track: <\/b> 0.6 km<br\/> <b>FRP: <\/b> 5.11 MW<br\/> <b>Brightness: <\/b> 337.42 K" }, "geometry": { "type": "Point", "coordinates": [ -70.35557, 18.92843, 0.0 ] } },
{ "type": "Feature", "properties": { "Name": "Fire Detection Centroid ", "Description": "<b>Latitude: <\/b> 18.92846<br\/>  <b>Longitude: <\/b> -70.3524<br\/>  <b>Detection Time: <\/b> 2023-10-06 05:42 UTC<br\/>  <b>Sensor: <\/b> NOAA-20 VIIRS<br\/> <b>Confidence: <\/b> Nominal<br\/>  <b>Day\/Night: <\/b> Night<br\/> <b>Scan: <\/b> 0.3 km<br\/> <b>Track: <\/b> 0.6 km<br\/> <b>FRP: <\/b> 4.74 MW<br\/> <b>Brightness: <\/b> 326.22 K" }, "geometry": { "type": "Point", "coordinates": [ -70.3524, 18.92846, 0.0 ] } },
{ "type": "Feature", "properties": { "Name": "Fire Detection Centroid ", "Description": "<b>Latitude: <\/b> 18.92883<br\/>  <b>Longitude: <\/b> -70.35591<br\/>  <b>Detection Time: <\/b> 2023-10-06 05:42 UTC<br\/>  <b>Sensor: <\/b> NOAA-20 VIIRS<br\/> <b>Confidence: <\/b> Nominal<br\/>  <b>Day\/Night: <\/b> Night<br\/> <b>Scan: <\/b> 0.3 km<br\/> <b>Track: <\/b> 0.6 km<br\/> <b>FRP: <\/b> 5.68 MW<br\/> <b>Brightness: <\/b> 339.9 K" }, "geometry": { "type": "Point", "coordinates": [ -70.35591, 18.92883, 0.0 ] } },
{ "type": "Feature", "properties": { "Name": "Fire Detection Centroid ", "Description": "<b>Latitude: <\/b> 45.11135<br\/>  <b>Longitude: <\/b> -73.01467<br\/>  <b>Detection Time: <\/b> 2023-10-06 05:34 UTC<br\/>  <b>Sensor: <\/b> NOAA-20 VIIRS<br\/> <b>Confidence: <\/b> Nominal<br\/>  <b>Day\/Night: <\/b> Night<br\/> <b>Scan: <\/b> 0.8 km<br\/> <b>Track: <\/b> 0.8 km<br\/> <b>FRP: <\/b> 0.75 MW<br\/> <b>Brightness: <\/b> 295.12 K" }, "geometry": { "type": "Point", "coordinates": [ -73.01467, 45.11135, 0.0 ] } },
{ "type": "Feature", "properties": { "Name": "Fire Detection Centroid ", "Description": "<b>Latitude: <\/b> 48.5906<br\/>  <b>Longitude: <\/b> -68.18398<br\/>  <b>Detection Time: <\/b> 2023-10-06 05:33 UTC<br\/>  <b>Sensor: <\/b> NOAA-20 VIIRS<br\/> <b>Confidence: <\/b> Nominal<br\/>  <b>Day\/Night: <\/b> Night<br\/> <b>Scan: <\/b> 0.5 km<br\/> <b>Track: <\/b> 0.6 km<br\/> <b>FRP: <\/b> 0.55 MW<br\/> <b>Brightness: <\/b> 299.82 K" }, "geometry": { "type": "Point", "coordinates": [ -68.18398, 48.5906, 0.0 ] } }
]
}
