{
"type": "FeatureCollection",
"crs": { "type": "name", "properties": { "name": "urn:ogc:def:crs:OGC:1.3:CRS84" } },
"features": [
{ "type": "Feature", "properties": { "Name": "Fire Detection Centroid ", "Description": "<b>Latitude: <\/b> 18.73167<br\/>  <b>Longitude: <\/b> -70.05173<br\/>  <b>Detection Time: <\/b> 2023-11-02 18:26 UTC<br\/>  <b>Sensor: <\/b> NOAA-20 VIIRS<br\/> <b>Confidence: <\/b> Nominal<br\/>  <b>Day\/Night: <\/b> Day<br\/> <b>Scan: <\/b> 0.6 km<br\/> <b>Track: <\/b> 0.5 km<br\/> <b>FRP: <\/b> 10.38 MW<br\/> <b>Brightness: <\/b> 334.58 K" }, "geometry": { "type": "Point", "coordinates": [ -70.05173, 18.73167, 0.0 ] } },
{ "type": "Feature", "properties": { "Name": "Fire Detection Centroid ", "Description": "<b>Latitude: <\/b> 19.12027<br\/>  <b>Longitude: <\/b> -69.74209<br\/>  <b>Detection Time: <\/b> 2023-11-02 18:26 UTC<br\/>  <b>Sensor: <\/b> NOAA-20 VIIRS<br\/> <b>Confidence: <\/b> Nominal<br\/>  <b>Day\/Night: <\/b> Day<br\/> <b>Scan: <\/b> 0.3 km<br\/> <b>Track: <\/b> 0.6 km<br\/> <b>FRP: <\/b> 3.8 MW<br\/> <b>Brightness: <\/b> 334.04 K" }, "geometry": { "type": "Point", "coordinates": [ -69.74209, 19.12027, 0.0 ] } },
{ "type": "Feature", "properties": { "Name": "Fire Detection Centroid ", "Description": "<b>Latitude: <\/b> 19.15246<br\/>  <b>Longitude: <\/b> -69.72984<br\/>  <b>Detection Time: <\/b> 2023-11-02 18:26 UTC<br\/>  <b>Sensor: <\/b> NOAA-20 VIIRS<br\/> <b>Confidence: <\/b> Nominal<br\/>  <b>Day\/Night: <\/b> Day<br\/> <b>Scan: <\/b> 0.3 km<br\/> <b>Track: <\/b> 0.6 km<br\/> <b>FRP: <\/b> 2.04 MW<br\/> <b>Brightness: <\/b> 335.71 K" }, "geometry": { "type": "Point", "coordinates": [ -69.72984, 19.15246, 0.0 ] } }
]
}
