{
"type": "FeatureCollection",
"crs": { "type": "name", "properties": { "name": "urn:ogc:def:crs:OGC:1.3:CRS84" } },
"features": [
{ "type": "Feature", "properties": { "Name": "Fire Detection Centroid ", "Description": "<b>Latitude: <\/b> 19.59644<br\/>  <b>Longitude: <\/b> -155.50441<br\/>  <b>Detection Time: <\/b> 2023-03-13 12:08 UTC<br\/>  <b>Sensor: <\/b> NOAA-20 VIIRS<br\/> <b>Confidence: <\/b> Nominal<br\/>  <b>Day\/Night: <\/b> Night<br\/> <b>Scan: <\/b> 0.42 km<br\/> <b>Track: <\/b> 0.37 km<br\/> <b>FRP: <\/b> 1.69 MW<br\/> <b>Brightness: <\/b> 303.51 K" }, "geometry": { "type": "Point", "coordinates": [ -155.50441, 19.59644, 0.0 ] } },
{ "type": "Feature", "properties": { "Name": "Fire Detection Centroid ", "Description": "<b>Latitude: <\/b> 19.59982<br\/>  <b>Longitude: <\/b> -155.50365<br\/>  <b>Detection Time: <\/b> 2023-03-13 12:08 UTC<br\/>  <b>Sensor: <\/b> NOAA-20 VIIRS<br\/> <b>Confidence: <\/b> Nominal<br\/>  <b>Day\/Night: <\/b> Night<br\/> <b>Scan: <\/b> 0.42 km<br\/> <b>Track: <\/b> 0.37 km<br\/> <b>FRP: <\/b> 1.95 MW<br\/> <b>Brightness: <\/b> 298.97 K" }, "geometry": { "type": "Point", "coordinates": [ -155.50365, 19.59982, 0.0 ] } }
]
}
