{
"type": "FeatureCollection",
"crs": { "type": "name", "properties": { "name": "urn:ogc:def:crs:OGC:1.3:CRS84" } },
"features": [
{ "type": "Feature", "properties": { "Name": "Fire Detection Centroid ", "Description": "<b>Latitude: <\/b> 19.77445<br\/>  <b>Longitude: <\/b> -155.61948<br\/>  <b>Detection Time: <\/b> 2023-11-10 11:29 UTC<br\/>  <b>Sensor: <\/b> NOAA-20 VIIRS<br\/> <b>Confidence: <\/b> Nominal<br\/>  <b>Day\/Night: <\/b> Night<br\/> <b>Scan: <\/b> 0.54 km<br\/> <b>Track: <\/b> 0.51 km<br\/> <b>FRP: <\/b> 16.84 MW<br\/> <b>Brightness: <\/b> 352.74 K" }, "geometry": { "type": "Point", "coordinates": [ -155.61948, 19.77445, 0.0 ] } },
{ "type": "Feature", "properties": { "Name": "Fire Detection Centroid ", "Description": "<b>Latitude: <\/b> 19.77505<br\/>  <b>Longitude: <\/b> -155.62477<br\/>  <b>Detection Time: <\/b> 2023-11-10 11:29 UTC<br\/>  <b>Sensor: <\/b> NOAA-20 VIIRS<br\/> <b>Confidence: <\/b> Nominal<br\/>  <b>Day\/Night: <\/b> Night<br\/> <b>Scan: <\/b> 0.54 km<br\/> <b>Track: <\/b> 0.51 km<br\/> <b>FRP: <\/b> 5.14 MW<br\/> <b>Brightness: <\/b> 297.59 K" }, "geometry": { "type": "Point", "coordinates": [ -155.62477, 19.77505, 0.0 ] } },
{ "type": "Feature", "properties": { "Name": "Fire Detection Centroid ", "Description": "<b>Latitude: <\/b> 19.40522<br\/>  <b>Longitude: <\/b> -155.28537<br\/>  <b>Detection Time: <\/b> 2023-11-10 11:29 UTC<br\/>  <b>Sensor: <\/b> NOAA-20 VIIRS<br\/> <b>Confidence: <\/b> Nominal<br\/>  <b>Day\/Night: <\/b> Night<br\/> <b>Scan: <\/b> 0.51 km<br\/> <b>Track: <\/b> 0.49 km<br\/> <b>FRP: <\/b> 3.08 MW<br\/> <b>Brightness: <\/b> 305.45 K" }, "geometry": { "type": "Point", "coordinates": [ -155.28537, 19.40522, 0.0 ] } },
{ "type": "Feature", "properties": { "Name": "Fire Detection Centroid ", "Description": "<b>Latitude: <\/b> 19.7698<br\/>  <b>Longitude: <\/b> -155.6201<br\/>  <b>Detection Time: <\/b> 2023-11-10 11:29 UTC<br\/>  <b>Sensor: <\/b> NOAA-20 VIIRS<br\/> <b>Confidence: <\/b> Nominal<br\/>  <b>Day\/Night: <\/b> Night<br\/> <b>Scan: <\/b> 0.54 km<br\/> <b>Track: <\/b> 0.51 km<br\/> <b>FRP: <\/b> 16.84 MW<br\/> <b>Brightness: <\/b> 327.62 K" }, "geometry": { "type": "Point", "coordinates": [ -155.6201, 19.7698, 0.0 ] } }
]
}
