{
"type": "FeatureCollection",
"crs": { "type": "name", "properties": { "name": "urn:ogc:def:crs:OGC:1.3:CRS84" } },
"features": [
{ "type": "Feature", "properties": { "Name": "Fire Detection Centroid ", "Description": "<b>Latitude: <\/b> 21.50775<br\/>  <b>Longitude: <\/b> -158.1008<br\/>  <b>Detection Time: <\/b> 2023-04-18 00:05 UTC<br\/>  <b>Sensor: <\/b> NOAA-20 VIIRS<br\/> <b>Confidence: <\/b> Nominal<br\/>  <b>Day\/Night: <\/b> Day<br\/> <b>Scan: <\/b> 0.57 km<br\/> <b>Track: <\/b> 0.43 km<br\/> <b>FRP: <\/b> 9.56 MW<br\/> <b>Brightness: <\/b> 344.25 K" }, "geometry": { "type": "Point", "coordinates": [ -158.1008, 21.50775, 0.0 ] } },
{ "type": "Feature", "properties": { "Name": "Fire Detection Centroid ", "Description": "<b>Latitude: <\/b> 21.49693<br\/>  <b>Longitude: <\/b> -158.10303<br\/>  <b>Detection Time: <\/b> 2023-04-18 00:05 UTC<br\/>  <b>Sensor: <\/b> NOAA-20 VIIRS<br\/> <b>Confidence: <\/b> Nominal<br\/>  <b>Day\/Night: <\/b> Day<br\/> <b>Scan: <\/b> 0.57 km<br\/> <b>Track: <\/b> 0.43 km<br\/> <b>FRP: <\/b> 11.71 MW<br\/> <b>Brightness: <\/b> 338.77 K" }, "geometry": { "type": "Point", "coordinates": [ -158.10303, 21.49693, 0.0 ] } },
{ "type": "Feature", "properties": { "Name": "Fire Detection Centroid ", "Description": "<b>Latitude: <\/b> 21.50956<br\/>  <b>Longitude: <\/b> -158.09915<br\/>  <b>Detection Time: <\/b> 2023-04-18 00:05 UTC<br\/>  <b>Sensor: <\/b> NOAA-20 VIIRS<br\/> <b>Confidence: <\/b> Nominal<br\/>  <b>Day\/Night: <\/b> Day<br\/> <b>Scan: <\/b> 0.57 km<br\/> <b>Track: <\/b> 0.43 km<br\/> <b>FRP: <\/b> 6.02 MW<br\/> <b>Brightness: <\/b> 328.87 K" }, "geometry": { "type": "Point", "coordinates": [ -158.09915, 21.50956, 0.0 ] } }
]
}
