{
"type": "FeatureCollection",
"crs": { "type": "name", "properties": { "name": "urn:ogc:def:crs:OGC:1.3:CRS84" } },
"features": [
{ "type": "Feature", "properties": { "Name": "Fire Detection Centroid ", "Description": "<b>Latitude: <\/b> 18.28738<br\/>  <b>Longitude: <\/b> -71.41473<br\/>  <b>Detection Time: <\/b> 2024-06-12 05:29 UTC<br\/>  <b>Sensor: <\/b> NOAA-20 VIIRS<br\/> <b>Confidence: <\/b> Nominal<br\/>  <b>Day\/Night: <\/b> Night<br\/> <b>Scan: <\/b> 0.7 km<br\/> <b>Track: <\/b> 0.7 km<br\/> <b>FRP: <\/b> 2.11 MW<br\/> <b>Brightness: <\/b> 304.52 K" }, "geometry": { "type": "Point", "coordinates": [ -71.41473, 18.28738, 0.0 ] } },
{ "type": "Feature", "properties": { "Name": "Fire Detection Centroid ", "Description": "<b>Latitude: <\/b> 45.28165<br\/>  <b>Longitude: <\/b> -66.01466<br\/>  <b>Detection Time: <\/b> 2024-06-12 05:21 UTC<br\/>  <b>Sensor: <\/b> NOAA-20 VIIRS<br\/> <b>Confidence: <\/b> Nominal<br\/>  <b>Day\/Night: <\/b> Night<br\/> <b>Scan: <\/b> 0.5 km<br\/> <b>Track: <\/b> 0.7 km<br\/> <b>FRP: <\/b> 1.74 MW<br\/> <b>Brightness: <\/b> 300.72 K" }, "geometry": { "type": "Point", "coordinates": [ -66.01466, 45.28165, 0.0 ] } },
{ "type": "Feature", "properties": { "Name": "Fire Detection Centroid ", "Description": "<b>Latitude: <\/b> 48.18842<br\/>  <b>Longitude: <\/b> -64.92412<br\/>  <b>Detection Time: <\/b> 2024-06-12 05:20 UTC<br\/>  <b>Sensor: <\/b> NOAA-20 VIIRS<br\/> <b>Confidence: <\/b> Nominal<br\/>  <b>Day\/Night: <\/b> Night<br\/> <b>Scan: <\/b> 0.5 km<br\/> <b>Track: <\/b> 0.6 km<br\/> <b>FRP: <\/b> 1.3 MW<br\/> <b>Brightness: <\/b> 299.2 K" }, "geometry": { "type": "Point", "coordinates": [ -64.92412, 48.18842, 0.0 ] } }
]
}
