{
"type": "FeatureCollection",
"crs": { "type": "name", "properties": { "name": "urn:ogc:def:crs:OGC:1.3:CRS84" } },
"features": [
{ "type": "Feature", "properties": { "Name": "Fire Detection Centroid ", "Description": "<b>Latitude: <\/b> 43.2506<br\/>  <b>Longitude: <\/b> -70.95975<br\/>  <b>Detection Time: <\/b> 2023-06-16 05:35 UTC<br\/>  <b>Sensor: <\/b> NOAA-20 VIIRS<br\/> <b>Confidence: <\/b> Nominal<br\/>  <b>Day\/Night: <\/b> Night<br\/> <b>Scan: <\/b> 0.6 km<br\/> <b>Track: <\/b> 0.7 km<br\/> <b>FRP: <\/b> 0.56 MW<br\/> <b>Brightness: <\/b> 296.89 K" }, "geometry": { "type": "Point", "coordinates": [ -70.95975, 43.2506, 0.0 ] } },
{ "type": "Feature", "properties": { "Name": "Fire Detection Centroid ", "Description": "<b>Latitude: <\/b> 43.24758<br\/>  <b>Longitude: <\/b> -70.96217<br\/>  <b>Detection Time: <\/b> 2023-06-16 05:35 UTC<br\/>  <b>Sensor: <\/b> NOAA-20 VIIRS<br\/> <b>Confidence: <\/b> Nominal<br\/>  <b>Day\/Night: <\/b> Night<br\/> <b>Scan: <\/b> 0.6 km<br\/> <b>Track: <\/b> 0.7 km<br\/> <b>FRP: <\/b> 0.61 MW<br\/> <b>Brightness: <\/b> 295.3 K" }, "geometry": { "type": "Point", "coordinates": [ -70.96217, 43.24758, 0.0 ] } }
]
}
