{
"type": "FeatureCollection",
"crs": { "type": "name", "properties": { "name": "urn:ogc:def:crs:OGC:1.3:CRS84" } },
"features": [
{ "type": "Feature", "properties": { "Name": "Fire Detection Centroid ", "Description": "<b>Latitude: <\/b> 36.81297<br\/>  <b>Longitude: <\/b> -120.71938<br\/>  <b>Detection Time: <\/b> 2024-04-03 22:01 UTC<br\/>  <b>Sensor: <\/b> NOAA-20 VIIRS<br\/> <b>Confidence: <\/b> Nominal<br\/>  <b>Day\/Night: <\/b> Day<br\/> <b>Scan: <\/b> 0.61 km<br\/> <b>Track: <\/b> 0.71 km<br\/> <b>FRP: <\/b> 4.86 MW<br\/> <b>Brightness: <\/b> 334.33 K" }, "geometry": { "type": "Point", "coordinates": [ -120.71938, 36.81297, 0.0 ] } },
{ "type": "Feature", "properties": { "Name": "Fire Detection Centroid ", "Description": "<b>Latitude: <\/b> 36.80642<br\/>  <b>Longitude: <\/b> -120.71929<br\/>  <b>Detection Time: <\/b> 2024-04-03 22:01 UTC<br\/>  <b>Sensor: <\/b> NOAA-20 VIIRS<br\/> <b>Confidence: <\/b> Nominal<br\/>  <b>Day\/Night: <\/b> Day<br\/> <b>Scan: <\/b> 0.61 km<br\/> <b>Track: <\/b> 0.71 km<br\/> <b>FRP: <\/b> 4.86 MW<br\/> <b>Brightness: <\/b> 335.08 K" }, "geometry": { "type": "Point", "coordinates": [ -120.71929, 36.80642, 0.0 ] } }
]
}
