{
"type": "FeatureCollection",
"crs": { "type": "name", "properties": { "name": "urn:ogc:def:crs:OGC:1.3:CRS84" } },
"features": [
{ "type": "Feature", "properties": { "Name": "Fire Detection Centroid ", "Description": "<b>Latitude: <\/b> 19.40536<br\/>  <b>Longitude: <\/b> -155.28252<br\/>  <b>Detection Time: <\/b> 2023-04-14 12:08 UTC<br\/>  <b>Sensor: <\/b> NOAA-20 VIIRS<br\/> <b>Confidence: <\/b> Nominal<br\/>  <b>Day\/Night: <\/b> Night<br\/> <b>Scan: <\/b> 0.43 km<br\/> <b>Track: <\/b> 0.38 km<br\/> <b>FRP: <\/b> 1.54 MW<br\/> <b>Brightness: <\/b> 301.02 K" }, "geometry": { "type": "Point", "coordinates": [ -155.28252, 19.40536, 0.0 ] } },
{ "type": "Feature", "properties": { "Name": "Fire Detection Centroid ", "Description": "<b>Latitude: <\/b> 20.86167<br\/>  <b>Longitude: <\/b> -156.42094<br\/>  <b>Detection Time: <\/b> 2023-04-14 12:08 UTC<br\/>  <b>Sensor: <\/b> NOAA-20 VIIRS<br\/> <b>Confidence: <\/b> Nominal<br\/>  <b>Day\/Night: <\/b> Night<br\/> <b>Scan: <\/b> 0.39 km<br\/> <b>Track: <\/b> 0.36 km<br\/> <b>FRP: <\/b> 0.43 MW<br\/> <b>Brightness: <\/b> 300.19 K" }, "geometry": { "type": "Point", "coordinates": [ -156.42094, 20.86167, 0.0 ] } },
{ "type": "Feature", "properties": { "Name": "Fire Detection Centroid ", "Description": "<b>Latitude: <\/b> 19.57834<br\/>  <b>Longitude: <\/b> -155.51003<br\/>  <b>Detection Time: <\/b> 2023-04-14 12:08 UTC<br\/>  <b>Sensor: <\/b> NOAA-20 VIIRS<br\/> <b>Confidence: <\/b> Nominal<br\/>  <b>Day\/Night: <\/b> Night<br\/> <b>Scan: <\/b> 0.42 km<br\/> <b>Track: <\/b> 0.38 km<br\/> <b>FRP: <\/b> 1.28 MW<br\/> <b>Brightness: <\/b> 295.04 K" }, "geometry": { "type": "Point", "coordinates": [ -155.51003, 19.57834, 0.0 ] } },
{ "type": "Feature", "properties": { "Name": "Fire Detection Centroid ", "Description": "<b>Latitude: <\/b> 19.40606<br\/>  <b>Longitude: <\/b> -155.28654<br\/>  <b>Detection Time: <\/b> 2023-04-14 12:08 UTC<br\/>  <b>Sensor: <\/b> NOAA-20 VIIRS<br\/> <b>Confidence: <\/b> Nominal<br\/>  <b>Day\/Night: <\/b> Night<br\/> <b>Scan: <\/b> 0.43 km<br\/> <b>Track: <\/b> 0.38 km<br\/> <b>FRP: <\/b> 1.54 MW<br\/> <b>Brightness: <\/b> 299.65 K" }, "geometry": { "type": "Point", "coordinates": [ -155.28654, 19.40606, 0.0 ] } }
]
}
