{
"type": "FeatureCollection",
"crs": { "type": "name", "properties": { "name": "urn:ogc:def:crs:OGC:1.3:CRS84" } },
"features": [
{ "type": "Feature", "properties": { "Name": "Fire Detection Centroid ", "Description": "<b>Latitude: <\/b> 34.60412<br\/>  <b>Longitude: <\/b> -80.73978<br\/>  <b>Detection Time: <\/b> 2022-11-13 06:08 UTC<br\/>  <b>Sensor: <\/b> NOAA-20 VIIRS<br\/> <b>Confidence: <\/b> Nominal<br\/>  <b>Day\/Night: <\/b> Night<br\/> <b>Scan: <\/b> 0.7 km<br\/> <b>Track: <\/b> 0.7 km<br\/> <b>FRP: <\/b> 2.01 MW<br\/> <b>Brightness: <\/b> 300.25 K" }, "geometry": { "type": "Point", "coordinates": [ -80.73978, 34.60412, 0.0 ] } }
]
}
