{
"type": "FeatureCollection",
"crs": { "type": "name", "properties": { "name": "urn:ogc:def:crs:OGC:1.3:CRS84" } },
"features": [
{ "type": "Feature", "properties": { "Name": "Fire Detection Centroid ", "Description": "<b>Latitude: <\/b> 48.86593<br\/>  <b>Longitude: <\/b> -119.64038<br\/>  <b>Detection Time: <\/b> 2023-03-28 22:03 UTC<br\/>  <b>Sensor: <\/b> NOAA-20 VIIRS<br\/> <b>Confidence: <\/b> Nominal<br\/>  <b>Day\/Night: <\/b> Day<br\/> <b>Scan: <\/b> 0.75 km<br\/> <b>Track: <\/b> 0.77 km<br\/> <b>FRP: <\/b> 9.49 MW<br\/> <b>Brightness: <\/b> 343.56 K" }, "geometry": { "type": "Point", "coordinates": [ -119.64038, 48.86593, 0.0 ] } }
]
}
