{
"type": "FeatureCollection",
"crs": { "type": "name", "properties": { "name": "urn:ogc:def:crs:OGC:1.3:CRS84" } },
"features": [
{ "type": "Feature", "properties": { "Name": "Fire Detection Centroid ", "Description": "<b>Latitude: <\/b> 46.57548<br\/>  <b>Longitude: <\/b> -120.46587<br\/>  <b>Detection Time: <\/b> 2024-05-30 11:10 UTC<br\/>  <b>Sensor: <\/b> NOAA-20 VIIRS<br\/> <b>Confidence: <\/b> Nominal<br\/>  <b>Day\/Night: <\/b> Night<br\/> <b>Scan: <\/b> 0.49 km<br\/> <b>Track: <\/b> 0.65 km<br\/> <b>FRP: <\/b> 1.54 MW<br\/> <b>Brightness: <\/b> 303.46 K" }, "geometry": { "type": "Point", "coordinates": [ -120.46587, 46.57548, 0.0 ] } },
{ "type": "Feature", "properties": { "Name": "Fire Detection Centroid ", "Description": "<b>Latitude: <\/b> 45.23049<br\/>  <b>Longitude: <\/b> -123.16656<br\/>  <b>Detection Time: <\/b> 2024-05-30 11:10 UTC<br\/>  <b>Sensor: <\/b> NOAA-20 VIIRS<br\/> <b>Confidence: <\/b> Nominal<br\/>  <b>Day\/Night: <\/b> Night<br\/> <b>Scan: <\/b> 0.41 km<br\/> <b>Track: <\/b> 0.61 km<br\/> <b>FRP: <\/b> 0.83 MW<br\/> <b>Brightness: <\/b> 298.77 K" }, "geometry": { "type": "Point", "coordinates": [ -123.16656, 45.23049, 0.0 ] } },
{ "type": "Feature", "properties": { "Name": "Fire Detection Centroid ", "Description": "<b>Latitude: <\/b> 46.57271<br\/>  <b>Longitude: <\/b> -120.46724<br\/>  <b>Detection Time: <\/b> 2024-05-30 11:08 UTC<br\/>  <b>Sensor: <\/b> NOAA-20 VIIRS<br\/> <b>Confidence: <\/b> Nominal<br\/>  <b>Day\/Night: <\/b> Night<br\/> <b>Scan: <\/b> 0.49 km<br\/> <b>Track: <\/b> 0.65 km<br\/> <b>FRP: <\/b> 1.21 MW<br\/> <b>Brightness: <\/b> 307.32 K" }, "geometry": { "type": "Point", "coordinates": [ -120.46724, 46.57271, 0.0 ] } }
]
}
