{
"type": "FeatureCollection",
"crs": { "type": "name", "properties": { "name": "urn:ogc:def:crs:OGC:1.3:CRS84" } },
"features": [
{ "type": "Feature", "properties": { "Name": "Fire Detection Centroid ", "Description": "<b>Latitude: <\/b> 19.40419<br\/>  <b>Longitude: <\/b> -155.27843<br\/>  <b>Detection Time: <\/b> 2023-09-19 23:58 UTC<br\/>  <b>Sensor: <\/b> NOAA-20 VIIRS<br\/> <b>Confidence: <\/b> Nominal<br\/>  <b>Day\/Night: <\/b> Day<br\/> <b>Scan: <\/b> 0.43 km<br\/> <b>Track: <\/b> 0.46 km<br\/> <b>FRP: <\/b> 7.16 MW<br\/> <b>Brightness: <\/b> 340.37 K" }, "geometry": { "type": "Point", "coordinates": [ -155.27843, 19.40419, 0.0 ] } },
{ "type": "Feature", "properties": { "Name": "Fire Detection Centroid ", "Description": "<b>Latitude: <\/b> 19.4037<br\/>  <b>Longitude: <\/b> -155.28249<br\/>  <b>Detection Time: <\/b> 2023-09-19 23:58 UTC<br\/>  <b>Sensor: <\/b> NOAA-20 VIIRS<br\/> <b>Confidence: <\/b> Nominal<br\/>  <b>Day\/Night: <\/b> Day<br\/> <b>Scan: <\/b> 0.43 km<br\/> <b>Track: <\/b> 0.46 km<br\/> <b>FRP: <\/b> 4.8 MW<br\/> <b>Brightness: <\/b> 333.63 K" }, "geometry": { "type": "Point", "coordinates": [ -155.28249, 19.4037, 0.0 ] } },
{ "type": "Feature", "properties": { "Name": "Fire Detection Centroid ", "Description": "<b>Latitude: <\/b> 19.40888<br\/>  <b>Longitude: <\/b> -155.2749<br\/>  <b>Detection Time: <\/b> 2023-09-19 23:58 UTC<br\/>  <b>Sensor: <\/b> NOAA-20 VIIRS<br\/> <b>Confidence: <\/b> Nominal<br\/>  <b>Day\/Night: <\/b> Day<br\/> <b>Scan: <\/b> 0.43 km<br\/> <b>Track: <\/b> 0.46 km<br\/> <b>FRP: <\/b> 7.16 MW<br\/> <b>Brightness: <\/b> 355.72 K" }, "geometry": { "type": "Point", "coordinates": [ -155.2749, 19.40888, 0.0 ] } },
{ "type": "Feature", "properties": { "Name": "Fire Detection Centroid ", "Description": "<b>Latitude: <\/b> 19.40838<br\/>  <b>Longitude: <\/b> -155.27896<br\/>  <b>Detection Time: <\/b> 2023-09-19 23:58 UTC<br\/>  <b>Sensor: <\/b> NOAA-20 VIIRS<br\/> <b>Confidence: <\/b> Nominal<br\/>  <b>Day\/Night: <\/b> Day<br\/> <b>Scan: <\/b> 0.43 km<br\/> <b>Track: <\/b> 0.46 km<br\/> <b>FRP: <\/b> 7.16 MW<br\/> <b>Brightness: <\/b> 353.79 K" }, "geometry": { "type": "Point", "coordinates": [ -155.27896, 19.40838, 0.0 ] } },
{ "type": "Feature", "properties": { "Name": "Fire Detection Centroid ", "Description": "<b>Latitude: <\/b> 19.40788<br\/>  <b>Longitude: <\/b> -155.28308<br\/>  <b>Detection Time: <\/b> 2023-09-19 23:58 UTC<br\/>  <b>Sensor: <\/b> NOAA-20 VIIRS<br\/> <b>Confidence: <\/b> Nominal<br\/>  <b>Day\/Night: <\/b> Day<br\/> <b>Scan: <\/b> 0.43 km<br\/> <b>Track: <\/b> 0.46 km<br\/> <b>FRP: <\/b> 4.8 MW<br\/> <b>Brightness: <\/b> 333.77 K" }, "geometry": { "type": "Point", "coordinates": [ -155.28308, 19.40788, 0.0 ] } },
{ "type": "Feature", "properties": { "Name": "Fire Detection Centroid ", "Description": "<b>Latitude: <\/b> 19.40468<br\/>  <b>Longitude: <\/b> -155.27435<br\/>  <b>Detection Time: <\/b> 2023-09-19 23:58 UTC<br\/>  <b>Sensor: <\/b> NOAA-20 VIIRS<br\/> <b>Confidence: <\/b> Nominal<br\/>  <b>Day\/Night: <\/b> Day<br\/> <b>Scan: <\/b> 0.43 km<br\/> <b>Track: <\/b> 0.46 km<br\/> <b>FRP: <\/b> 7.16 MW<br\/> <b>Brightness: <\/b> 337.33 K" }, "geometry": { "type": "Point", "coordinates": [ -155.27435, 19.40468, 0.0 ] } },
{ "type": "Feature", "properties": { "Name": "Fire Detection Centroid ", "Description": "<b>Latitude: <\/b> 19.41257<br\/>  <b>Longitude: <\/b> -155.27959<br\/>  <b>Detection Time: <\/b> 2023-09-19 23:58 UTC<br\/>  <b>Sensor: <\/b> NOAA-20 VIIRS<br\/> <b>Confidence: <\/b> Nominal<br\/>  <b>Day\/Night: <\/b> Day<br\/> <b>Scan: <\/b> 0.43 km<br\/> <b>Track: <\/b> 0.46 km<br\/> <b>FRP: <\/b> 11.77 MW<br\/> <b>Brightness: <\/b> 334.15 K" }, "geometry": { "type": "Point", "coordinates": [ -155.27959, 19.41257, 0.0 ] } }
]
}
