{
"type": "FeatureCollection",
"crs": { "type": "name", "properties": { "name": "urn:ogc:def:crs:OGC:1.3:CRS84" } },
"features": [
{ "type": "Feature", "properties": { "Name": "Fire Detection Centroid ", "Description": "<b>Latitude: <\/b> 45.11118<br\/>  <b>Longitude: <\/b> -73.01381<br\/>  <b>Detection Time: <\/b> 2023-09-25 05:41 UTC<br\/>  <b>Sensor: <\/b> NOAA-20 VIIRS<br\/> <b>Confidence: <\/b> Nominal<br\/>  <b>Day\/Night: <\/b> Night<br\/> <b>Scan: <\/b> 0.7 km<br\/> <b>Track: <\/b> 0.7 km<br\/> <b>FRP: <\/b> 1.15 MW<br\/> <b>Brightness: <\/b> 298.08 K" }, "geometry": { "type": "Point", "coordinates": [ -73.01381, 45.11118, 0.0 ] } },
{ "type": "Feature", "properties": { "Name": "Fire Detection Centroid ", "Description": "<b>Latitude: <\/b> 45.83867<br\/>  <b>Longitude: <\/b> -73.25869<br\/>  <b>Detection Time: <\/b> 2023-09-25 05:41 UTC<br\/>  <b>Sensor: <\/b> NOAA-20 VIIRS<br\/> <b>Confidence: <\/b> Nominal<br\/>  <b>Day\/Night: <\/b> Night<br\/> <b>Scan: <\/b> 0.7 km<br\/> <b>Track: <\/b> 0.7 km<br\/> <b>FRP: <\/b> 1.47 MW<br\/> <b>Brightness: <\/b> 296.9 K" }, "geometry": { "type": "Point", "coordinates": [ -73.25869, 45.83867, 0.0 ] } },
{ "type": "Feature", "properties": { "Name": "Fire Detection Centroid ", "Description": "<b>Latitude: <\/b> 45.83875<br\/>  <b>Longitude: <\/b> -73.25077<br\/>  <b>Detection Time: <\/b> 2023-09-25 05:41 UTC<br\/>  <b>Sensor: <\/b> NOAA-20 VIIRS<br\/> <b>Confidence: <\/b> Nominal<br\/>  <b>Day\/Night: <\/b> Night<br\/> <b>Scan: <\/b> 0.7 km<br\/> <b>Track: <\/b> 0.7 km<br\/> <b>FRP: <\/b> 2.08 MW<br\/> <b>Brightness: <\/b> 308.61 K" }, "geometry": { "type": "Point", "coordinates": [ -73.25077, 45.83875, 0.0 ] } },
{ "type": "Feature", "properties": { "Name": "Fire Detection Centroid ", "Description": "<b>Latitude: <\/b> 45.8387<br\/>  <b>Longitude: <\/b> -73.24955<br\/>  <b>Detection Time: <\/b> 2023-09-25 05:41 UTC<br\/>  <b>Sensor: <\/b> NOAA-20 VIIRS<br\/> <b>Confidence: <\/b> Nominal<br\/>  <b>Day\/Night: <\/b> Night<br\/> <b>Scan: <\/b> 0.7 km<br\/> <b>Track: <\/b> 0.7 km<br\/> <b>FRP: <\/b> 1.47 MW<br\/> <b>Brightness: <\/b> 304.06 K" }, "geometry": { "type": "Point", "coordinates": [ -73.24955, 45.8387, 0.0 ] } },
{ "type": "Feature", "properties": { "Name": "Fire Detection Centroid ", "Description": "<b>Latitude: <\/b> 46.04593<br\/>  <b>Longitude: <\/b> -73.14453<br\/>  <b>Detection Time: <\/b> 2023-09-25 05:40 UTC<br\/>  <b>Sensor: <\/b> NOAA-20 VIIRS<br\/> <b>Confidence: <\/b> Nominal<br\/>  <b>Day\/Night: <\/b> Night<br\/> <b>Scan: <\/b> 0.7 km<br\/> <b>Track: <\/b> 0.7 km<br\/> <b>FRP: <\/b> 1.9 MW<br\/> <b>Brightness: <\/b> 300.68 K" }, "geometry": { "type": "Point", "coordinates": [ -73.14453, 46.04593, 0.0 ] } },
{ "type": "Feature", "properties": { "Name": "Fire Detection Centroid ", "Description": "<b>Latitude: <\/b> 48.18791<br\/>  <b>Longitude: <\/b> -64.92384<br\/>  <b>Detection Time: <\/b> 2023-09-25 05:40 UTC<br\/>  <b>Sensor: <\/b> NOAA-20 VIIRS<br\/> <b>Confidence: <\/b> Nominal<br\/>  <b>Day\/Night: <\/b> Night<br\/> <b>Scan: <\/b> 0.6 km<br\/> <b>Track: <\/b> 0.5 km<br\/> <b>FRP: <\/b> 1.03 MW<br\/> <b>Brightness: <\/b> 301.85 K" }, "geometry": { "type": "Point", "coordinates": [ -64.92384, 48.18791, 0.0 ] } }
]
}
