{
"type": "FeatureCollection",
"crs": { "type": "name", "properties": { "name": "urn:ogc:def:crs:OGC:1.3:CRS84" } },
"features": [
{ "type": "Feature", "properties": { "Name": "Fire Detection Centroid ", "Description": "<b>Latitude: <\/b> 45.27665<br\/>  <b>Longitude: <\/b> -66.01467<br\/>  <b>Detection Time: <\/b> 2023-06-22 05:22 UTC<br\/>  <b>Sensor: <\/b> NOAA-20 VIIRS<br\/> <b>Confidence: <\/b> Nominal<br\/>  <b>Day\/Night: <\/b> Night<br\/> <b>Scan: <\/b> 0.5 km<br\/> <b>Track: <\/b> 0.7 km<br\/> <b>FRP: <\/b> 0.73 MW<br\/> <b>Brightness: <\/b> 298.39 K" }, "geometry": { "type": "Point", "coordinates": [ -66.01467, 45.27665, 0.0 ] } },
{ "type": "Feature", "properties": { "Name": "Fire Detection Centroid ", "Description": "<b>Latitude: <\/b> 45.28283<br\/>  <b>Longitude: <\/b> -66.01427<br\/>  <b>Detection Time: <\/b> 2023-06-22 05:22 UTC<br\/>  <b>Sensor: <\/b> NOAA-20 VIIRS<br\/> <b>Confidence: <\/b> Nominal<br\/>  <b>Day\/Night: <\/b> Night<br\/> <b>Scan: <\/b> 0.5 km<br\/> <b>Track: <\/b> 0.7 km<br\/> <b>FRP: <\/b> 1.4 MW<br\/> <b>Brightness: <\/b> 299.88 K" }, "geometry": { "type": "Point", "coordinates": [ -66.01427, 45.28283, 0.0 ] } },
{ "type": "Feature", "properties": { "Name": "Fire Detection Centroid ", "Description": "<b>Latitude: <\/b> 45.28294<br\/>  <b>Longitude: <\/b> -66.02096<br\/>  <b>Detection Time: <\/b> 2023-06-22 05:22 UTC<br\/>  <b>Sensor: <\/b> NOAA-20 VIIRS<br\/> <b>Confidence: <\/b> Nominal<br\/>  <b>Day\/Night: <\/b> Night<br\/> <b>Scan: <\/b> 0.5 km<br\/> <b>Track: <\/b> 0.7 km<br\/> <b>FRP: <\/b> 0.6 MW<br\/> <b>Brightness: <\/b> 297.17 K" }, "geometry": { "type": "Point", "coordinates": [ -66.02096, 45.28294, 0.0 ] } },
{ "type": "Feature", "properties": { "Name": "Fire Detection Centroid ", "Description": "<b>Latitude: <\/b> 48.19012<br\/>  <b>Longitude: <\/b> -64.92247<br\/>  <b>Detection Time: <\/b> 2023-06-22 05:21 UTC<br\/>  <b>Sensor: <\/b> NOAA-20 VIIRS<br\/> <b>Confidence: <\/b> Nominal<br\/>  <b>Day\/Night: <\/b> Night<br\/> <b>Scan: <\/b> 0.5 km<br\/> <b>Track: <\/b> 0.6 km<br\/> <b>FRP: <\/b> 1.29 MW<br\/> <b>Brightness: <\/b> 305.85 K" }, "geometry": { "type": "Point", "coordinates": [ -64.92247, 48.19012, 0.0 ] } }
]
}
