{
"type": "FeatureCollection",
"crs": { "type": "name", "properties": { "name": "urn:ogc:def:crs:OGC:1.3:CRS84" } },
"features": [
{ "type": "Feature", "properties": { "Name": "Fire Detection Centroid ", "Description": "<b>Latitude: <\/b> 18.1869<br\/>  <b>Longitude: <\/b> -72.86523<br\/>  <b>Detection Time: <\/b> 2024-06-11 05:48 UTC<br\/>  <b>Sensor: <\/b> NOAA-20 VIIRS<br\/> <b>Confidence: <\/b> Nominal<br\/>  <b>Day\/Night: <\/b> Night<br\/> <b>Scan: <\/b> 0.4 km<br\/> <b>Track: <\/b> 0.6 km<br\/> <b>FRP: <\/b> 0.93 MW<br\/> <b>Brightness: <\/b> 304.24 K" }, "geometry": { "type": "Point", "coordinates": [ -72.86523, 18.1869, 0.0 ] } },
{ "type": "Feature", "properties": { "Name": "Fire Detection Centroid ", "Description": "<b>Latitude: <\/b> 40.63491<br\/>  <b>Longitude: <\/b> -74.21947<br\/>  <b>Detection Time: <\/b> 2024-06-11 05:41 UTC<br\/>  <b>Sensor: <\/b> NOAA-20 VIIRS<br\/> <b>Confidence: <\/b> Nominal<br\/>  <b>Day\/Night: <\/b> Night<br\/> <b>Scan: <\/b> 0.7 km<br\/> <b>Track: <\/b> 0.8 km<br\/> <b>FRP: <\/b> 1.95 MW<br\/> <b>Brightness: <\/b> 296.85 K" }, "geometry": { "type": "Point", "coordinates": [ -74.21947, 40.63491, 0.0 ] } },
{ "type": "Feature", "properties": { "Name": "Fire Detection Centroid ", "Description": "<b>Latitude: <\/b> 40.63889<br\/>  <b>Longitude: <\/b> -74.22305<br\/>  <b>Detection Time: <\/b> 2024-06-11 05:41 UTC<br\/>  <b>Sensor: <\/b> NOAA-20 VIIRS<br\/> <b>Confidence: <\/b> Nominal<br\/>  <b>Day\/Night: <\/b> Night<br\/> <b>Scan: <\/b> 0.7 km<br\/> <b>Track: <\/b> 0.8 km<br\/> <b>FRP: <\/b> 2.95 MW<br\/> <b>Brightness: <\/b> 299.28 K" }, "geometry": { "type": "Point", "coordinates": [ -74.22305, 40.63889, 0.0 ] } },
{ "type": "Feature", "properties": { "Name": "Fire Detection Centroid ", "Description": "<b>Latitude: <\/b> 45.14445<br\/>  <b>Longitude: <\/b> -66.75526<br\/>  <b>Detection Time: <\/b> 2024-06-11 05:40 UTC<br\/>  <b>Sensor: <\/b> NOAA-20 VIIRS<br\/> <b>Confidence: <\/b> Nominal<br\/>  <b>Day\/Night: <\/b> Night<br\/> <b>Scan: <\/b> 0.3 km<br\/> <b>Track: <\/b> 0.5 km<br\/> <b>FRP: <\/b> 0.4 MW<br\/> <b>Brightness: <\/b> 298.06 K" }, "geometry": { "type": "Point", "coordinates": [ -66.75526, 45.14445, 0.0 ] } },
{ "type": "Feature", "properties": { "Name": "Fire Detection Centroid ", "Description": "<b>Latitude: <\/b> 45.28017<br\/>  <b>Longitude: <\/b> -66.01466<br\/>  <b>Detection Time: <\/b> 2024-06-11 05:40 UTC<br\/>  <b>Sensor: <\/b> NOAA-20 VIIRS<br\/> <b>Confidence: <\/b> Nominal<br\/>  <b>Day\/Night: <\/b> Night<br\/> <b>Scan: <\/b> 0.6 km<br\/> <b>Track: <\/b> 0.5 km<br\/> <b>FRP: <\/b> 2.14 MW<br\/> <b>Brightness: <\/b> 297.71 K" }, "geometry": { "type": "Point", "coordinates": [ -66.01466, 45.28017, 0.0 ] } }
]
}
