{
"type": "FeatureCollection",
"crs": { "type": "name", "properties": { "name": "urn:ogc:def:crs:OGC:1.3:CRS84" } },
"features": [
{ "type": "Feature", "properties": { "Name": "Fire Detection Centroid ", "Description": "<b>Latitude: <\/b> 35.66612<br\/>  <b>Longitude: <\/b> -77.63773<br\/>  <b>Detection Time: <\/b> 2023-10-16 17:10 UTC<br\/>  <b>Sensor: <\/b> NOAA-20 VIIRS<br\/> <b>Confidence: <\/b> Nominal<br\/>  <b>Day\/Night: <\/b> Day<br\/> <b>Scan: <\/b> 0.6 km<br\/> <b>Track: <\/b> 0.7 km<br\/> <b>FRP: <\/b> 3.98 MW<br\/> <b>Brightness: <\/b> 330.51 K" }, "geometry": { "type": "Point", "coordinates": [ -77.63773, 35.66612, 0.0 ] } },
{ "type": "Feature", "properties": { "Name": "Fire Detection Centroid ", "Description": "<b>Latitude: <\/b> 18.92811<br\/>  <b>Longitude: <\/b> -70.35075<br\/>  <b>Detection Time: <\/b> 2023-10-16 17:05 UTC<br\/>  <b>Sensor: <\/b> NOAA-20 VIIRS<br\/> <b>Confidence: <\/b> Nominal<br\/>  <b>Day\/Night: <\/b> Day<br\/> <b>Scan: <\/b> 0.6 km<br\/> <b>Track: <\/b> 0.7 km<br\/> <b>FRP: <\/b> 4.77 MW<br\/> <b>Brightness: <\/b> 329.82 K" }, "geometry": { "type": "Point", "coordinates": [ -70.35075, 18.92811, 0.0 ] } }
]
}
