{
"type": "FeatureCollection",
"crs": { "type": "name", "properties": { "name": "urn:ogc:def:crs:OGC:1.3:CRS84" } },
"features": [
{ "type": "Feature", "properties": { "Name": "Fire Detection Centroid ", "Description": "<b>Latitude: <\/b> 21.48533<br\/>  <b>Longitude: <\/b> -157.95746<br\/>  <b>Detection Time: <\/b> 2023-10-30 22:48 UTC<br\/>  <b>Sensor: <\/b> NOAA-20 VIIRS<br\/> <b>Confidence: <\/b> Nominal<br\/>  <b>Day\/Night: <\/b> Day<br\/> <b>Scan: <\/b> 0.67 km<br\/> <b>Track: <\/b> 0.74 km<br\/> <b>FRP: <\/b> 5.97 MW<br\/> <b>Brightness: <\/b> 329.87 K" }, "geometry": { "type": "Point", "coordinates": [ -157.95746, 21.48533, 0.0 ] } },
{ "type": "Feature", "properties": { "Name": "Fire Detection Centroid ", "Description": "<b>Latitude: <\/b> 21.48348<br\/>  <b>Longitude: <\/b> -157.96004<br\/>  <b>Detection Time: <\/b> 2023-10-30 22:48 UTC<br\/>  <b>Sensor: <\/b> NOAA-20 VIIRS<br\/> <b>Confidence: <\/b> Nominal<br\/>  <b>Day\/Night: <\/b> Day<br\/> <b>Scan: <\/b> 0.7 km<br\/> <b>Track: <\/b> 0.7 km<br\/> <b>FRP: <\/b> 5.97 MW<br\/> <b>Brightness: <\/b> 329.87 K" }, "geometry": { "type": "Point", "coordinates": [ -157.96004, 21.48348, 0.0 ] } }
]
}
