{
"type": "FeatureCollection",
"crs": { "type": "name", "properties": { "name": "urn:ogc:def:crs:OGC:1.3:CRS84" } },
"features": [
{ "type": "Feature", "properties": { "Name": "Fire Detection Centroid ", "Description": "<b>Latitude: <\/b> 41.61866<br\/>  <b>Longitude: <\/b> -71.44051<br\/>  <b>Detection Time: <\/b> 2024-05-22 16:41 UTC<br\/>  <b>Sensor: <\/b> NOAA-20 VIIRS<br\/> <b>Confidence: <\/b> Nominal<br\/>  <b>Day\/Night: <\/b> Day<br\/> <b>Scan: <\/b> 0.5 km<br\/> <b>Track: <\/b> 0.6 km<br\/> <b>FRP: <\/b> 3.83 MW<br\/> <b>Brightness: <\/b> 331.2 K" }, "geometry": { "type": "Point", "coordinates": [ -71.44051, 41.61866, 0.0 ] } }
]
}
