{
"type": "FeatureCollection",
"crs": { "type": "name", "properties": { "name": "urn:ogc:def:crs:OGC:1.3:CRS84" } },
"features": [
{ "type": "Feature", "properties": { "Name": "Fire Detection Centroid ", "Description": "<b>Latitude: <\/b> 38.94908<br\/>  <b>Longitude: <\/b> -122.02003<br\/>  <b>Detection Time: <\/b> 2022-10-28 11:10 UTC<br\/>  <b>Sensor: <\/b> NOAA-20 VIIRS<br\/> <b>Confidence: <\/b> Nominal<br\/>  <b>Day\/Night: <\/b> Night<br\/> <b>Scan: <\/b> 0.7 km<br\/> <b>Track: <\/b> 0.8 km<br\/> <b>FRP: <\/b> 1.45 MW<br\/> <b>Brightness: <\/b> 300.98 K" }, "geometry": { "type": "Point", "coordinates": [ -122.02003, 38.94908, 0.0 ] } },
{ "type": "Feature", "properties": { "Name": "Fire Detection Centroid ", "Description": "<b>Latitude: <\/b> 38.9496<br\/>  <b>Longitude: <\/b> -122.02319<br\/>  <b>Detection Time: <\/b> 2022-10-28 11:10 UTC<br\/>  <b>Sensor: <\/b> NOAA-20 VIIRS<br\/> <b>Confidence: <\/b> Nominal<br\/>  <b>Day\/Night: <\/b> Night<br\/> <b>Scan: <\/b> 0.72 km<br\/> <b>Track: <\/b> 0.75 km<br\/> <b>FRP: <\/b> 1.45 MW<br\/> <b>Brightness: <\/b> 300.98 K" }, "geometry": { "type": "Point", "coordinates": [ -122.02319, 38.9496, 0.0 ] } }
]
}
