{
"type": "FeatureCollection",
"crs": { "type": "name", "properties": { "name": "urn:ogc:def:crs:OGC:1.3:CRS84" } },
"features": [
{ "type": "Feature", "properties": { "Name": "Fire Detection Centroid ", "Description": "<b>Latitude: <\/b> 19.40608<br\/>  <b>Longitude: <\/b> -155.27672<br\/>  <b>Detection Time: <\/b> 2022-11-17 22:54 UTC<br\/>  <b>Sensor: <\/b> NOAA-20 VIIRS<br\/> <b>Confidence: <\/b> Nominal<br\/>  <b>Day\/Night: <\/b> Day<br\/> <b>Scan: <\/b> 0.39 km<br\/> <b>Track: <\/b> 0.6 km<br\/> <b>FRP: <\/b> 13.38 MW<br\/> <b>Brightness: <\/b> 331.91 K" }, "geometry": { "type": "Point", "coordinates": [ -155.27672, 19.40608, 0.0 ] } },
{ "type": "Feature", "properties": { "Name": "Fire Detection Centroid ", "Description": "<b>Latitude: <\/b> 19.40451<br\/>  <b>Longitude: <\/b> -155.28401<br\/>  <b>Detection Time: <\/b> 2022-11-17 22:54 UTC<br\/>  <b>Sensor: <\/b> NOAA-20 VIIRS<br\/> <b>Confidence: <\/b> Nominal<br\/>  <b>Day\/Night: <\/b> Day<br\/> <b>Scan: <\/b> 0.39 km<br\/> <b>Track: <\/b> 0.6 km<br\/> <b>FRP: <\/b> 56.68 MW<br\/> <b>Brightness: <\/b> 335.86 K" }, "geometry": { "type": "Point", "coordinates": [ -155.28401, 19.40451, 0.0 ] } },
{ "type": "Feature", "properties": { "Name": "Fire Detection Centroid ", "Description": "<b>Latitude: <\/b> 19.41069<br\/>  <b>Longitude: <\/b> -155.28148<br\/>  <b>Detection Time: <\/b> 2022-11-17 22:54 UTC<br\/>  <b>Sensor: <\/b> NOAA-20 VIIRS<br\/> <b>Confidence: <\/b> Nominal<br\/>  <b>Day\/Night: <\/b> Day<br\/> <b>Scan: <\/b> 0.39 km<br\/> <b>Track: <\/b> 0.6 km<br\/> <b>FRP: <\/b> 6.87 MW<br\/> <b>Brightness: <\/b> 329.77 K" }, "geometry": { "type": "Point", "coordinates": [ -155.28148, 19.41069, 0.0 ] } },
{ "type": "Feature", "properties": { "Name": "Fire Detection Centroid ", "Description": "<b>Latitude: <\/b> 19.40529<br\/>  <b>Longitude: <\/b> -155.28036<br\/>  <b>Detection Time: <\/b> 2022-11-17 22:54 UTC<br\/>  <b>Sensor: <\/b> NOAA-20 VIIRS<br\/> <b>Confidence: <\/b> High<br\/>  <b>Day\/Night: <\/b> Day<br\/> <b>Scan: <\/b> 0.39 km<br\/> <b>Track: <\/b> 0.6 km<br\/> <b>FRP: <\/b> 56.68 MW<br\/> <b>Brightness: <\/b> 367 K" }, "geometry": { "type": "Point", "coordinates": [ -155.28036, 19.40529, 0.0 ] } },
{ "type": "Feature", "properties": { "Name": "Fire Detection Centroid ", "Description": "<b>Latitude: <\/b> 19.40687<br\/>  <b>Longitude: <\/b> -155.27306<br\/>  <b>Detection Time: <\/b> 2022-11-17 22:54 UTC<br\/>  <b>Sensor: <\/b> NOAA-20 VIIRS<br\/> <b>Confidence: <\/b> Low<br\/>  <b>Day\/Night: <\/b> Day<br\/> <b>Scan: <\/b> 0.39 km<br\/> <b>Track: <\/b> 0.6 km<br\/> <b>FRP: <\/b> 13.38 MW<br\/> <b>Brightness: <\/b> 328.23 K" }, "geometry": { "type": "Point", "coordinates": [ -155.27306, 19.40687, 0.0 ] } }
]
}
