{
"type": "FeatureCollection",
"crs": { "type": "name", "properties": { "name": "urn:ogc:def:crs:OGC:1.3:CRS84" } },
"features": [
{ "type": "Feature", "properties": { "Name": "Fire Detection Centroid ", "Description": "<b>Latitude: <\/b> 19.40642<br\/>  <b>Longitude: <\/b> -155.28484<br\/>  <b>Detection Time: <\/b> 2023-12-31 12:14 UTC<br\/>  <b>Sensor: <\/b> NOAA-20 VIIRS<br\/> <b>Confidence: <\/b> Nominal<br\/>  <b>Day\/Night: <\/b> Night<br\/> <b>Scan: <\/b> 0.5 km<br\/> <b>Track: <\/b> 0.41 km<br\/> <b>FRP: <\/b> 4.32 MW<br\/> <b>Brightness: <\/b> 307.72 K" }, "geometry": { "type": "Point", "coordinates": [ -155.28484, 19.40642, 0.0 ] } }
]
}
