{
"type": "FeatureCollection",
"crs": { "type": "name", "properties": { "name": "urn:ogc:def:crs:OGC:1.3:CRS84" } },
"features": [
{ "type": "Feature", "properties": { "Name": "Fire Detection Centroid ", "Description": "<b>Latitude: <\/b> 19.41113<br\/>  <b>Longitude: <\/b> -155.28036<br\/>  <b>Detection Time: <\/b> 2022-11-15 12:21 UTC<br\/>  <b>Sensor: <\/b> NOAA-20 VIIRS<br\/> <b>Confidence: <\/b> Nominal<br\/>  <b>Day\/Night: <\/b> Night<br\/> <b>Scan: <\/b> 0.41 km<br\/> <b>Track: <\/b> 0.45 km<br\/> <b>FRP: <\/b> 3.09 MW<br\/> <b>Brightness: <\/b> 310.74 K" }, "geometry": { "type": "Point", "coordinates": [ -155.28036, 19.41113, 0.0 ] } },
{ "type": "Feature", "properties": { "Name": "Fire Detection Centroid ", "Description": "<b>Latitude: <\/b> 19.40855<br\/>  <b>Longitude: <\/b> -155.28902<br\/>  <b>Detection Time: <\/b> 2022-11-15 12:21 UTC<br\/>  <b>Sensor: <\/b> NOAA-20 VIIRS<br\/> <b>Confidence: <\/b> Nominal<br\/>  <b>Day\/Night: <\/b> Night<br\/> <b>Scan: <\/b> 0.41 km<br\/> <b>Track: <\/b> 0.45 km<br\/> <b>FRP: <\/b> 57.84 MW<br\/> <b>Brightness: <\/b> 336.34 K" }, "geometry": { "type": "Point", "coordinates": [ -155.28902, 19.40855, 0.0 ] } },
{ "type": "Feature", "properties": { "Name": "Fire Detection Centroid ", "Description": "<b>Latitude: <\/b> 19.40706<br\/>  <b>Longitude: <\/b> -155.28119<br\/>  <b>Detection Time: <\/b> 2022-11-15 12:21 UTC<br\/>  <b>Sensor: <\/b> NOAA-20 VIIRS<br\/> <b>Confidence: <\/b> Nominal<br\/>  <b>Day\/Night: <\/b> Night<br\/> <b>Scan: <\/b> 0.41 km<br\/> <b>Track: <\/b> 0.45 km<br\/> <b>FRP: <\/b> 3.09 MW<br\/> <b>Brightness: <\/b> 311.95 K" }, "geometry": { "type": "Point", "coordinates": [ -155.28119, 19.40706, 0.0 ] } },
{ "type": "Feature", "properties": { "Name": "Fire Detection Centroid ", "Description": "<b>Latitude: <\/b> 19.40449<br\/>  <b>Longitude: <\/b> -155.28979<br\/>  <b>Detection Time: <\/b> 2022-11-15 12:21 UTC<br\/>  <b>Sensor: <\/b> NOAA-20 VIIRS<br\/> <b>Confidence: <\/b> Nominal<br\/>  <b>Day\/Night: <\/b> Night<br\/> <b>Scan: <\/b> 0.41 km<br\/> <b>Track: <\/b> 0.45 km<br\/> <b>FRP: <\/b> 2.87 MW<br\/> <b>Brightness: <\/b> 320.89 K" }, "geometry": { "type": "Point", "coordinates": [ -155.28979, 19.40449, 0.0 ] } },
{ "type": "Feature", "properties": { "Name": "Fire Detection Centroid ", "Description": "<b>Latitude: <\/b> 19.40373<br\/>  <b>Longitude: <\/b> -155.28584<br\/>  <b>Detection Time: <\/b> 2022-11-15 12:21 UTC<br\/>  <b>Sensor: <\/b> NOAA-20 VIIRS<br\/> <b>Confidence: <\/b> Nominal<br\/>  <b>Day\/Night: <\/b> Night<br\/> <b>Scan: <\/b> 0.41 km<br\/> <b>Track: <\/b> 0.45 km<br\/> <b>FRP: <\/b> 2.87 MW<br\/> <b>Brightness: <\/b> 314.56 K" }, "geometry": { "type": "Point", "coordinates": [ -155.28584, 19.40373, 0.0 ] } },
{ "type": "Feature", "properties": { "Name": "Fire Detection Centroid ", "Description": "<b>Latitude: <\/b> 19.41595<br\/>  <b>Longitude: <\/b> -155.28358<br\/>  <b>Detection Time: <\/b> 2022-11-15 12:21 UTC<br\/>  <b>Sensor: <\/b> NOAA-20 VIIRS<br\/> <b>Confidence: <\/b> Nominal<br\/>  <b>Day\/Night: <\/b> Night<br\/> <b>Scan: <\/b> 0.41 km<br\/> <b>Track: <\/b> 0.45 km<br\/> <b>FRP: <\/b> 1.2 MW<br\/> <b>Brightness: <\/b> 300.28 K" }, "geometry": { "type": "Point", "coordinates": [ -155.28358, 19.41595, 0.0 ] } },
{ "type": "Feature", "properties": { "Name": "Fire Detection Centroid ", "Description": "<b>Latitude: <\/b> 19.41263<br\/>  <b>Longitude: <\/b> -155.2883<br\/>  <b>Detection Time: <\/b> 2022-11-15 12:21 UTC<br\/>  <b>Sensor: <\/b> NOAA-20 VIIRS<br\/> <b>Confidence: <\/b> Nominal<br\/>  <b>Day\/Night: <\/b> Night<br\/> <b>Scan: <\/b> 0.41 km<br\/> <b>Track: <\/b> 0.45 km<br\/> <b>FRP: <\/b> 57.84 MW<br\/> <b>Brightness: <\/b> 308.6 K" }, "geometry": { "type": "Point", "coordinates": [ -155.2883, 19.41263, 0.0 ] } },
{ "type": "Feature", "properties": { "Name": "Fire Detection Centroid ", "Description": "<b>Latitude: <\/b> 19.41187<br\/>  <b>Longitude: <\/b> -155.28432<br\/>  <b>Detection Time: <\/b> 2022-11-15 12:21 UTC<br\/>  <b>Sensor: <\/b> NOAA-20 VIIRS<br\/> <b>Confidence: <\/b> Nominal<br\/>  <b>Day\/Night: <\/b> Night<br\/> <b>Scan: <\/b> 0.41 km<br\/> <b>Track: <\/b> 0.45 km<br\/> <b>FRP: <\/b> 57.84 MW<br\/> <b>Brightness: <\/b> 310.17 K" }, "geometry": { "type": "Point", "coordinates": [ -155.28432, 19.41187, 0.0 ] } }
]
}
