{
"type": "FeatureCollection",
"crs": { "type": "name", "properties": { "name": "urn:ogc:def:crs:OGC:1.3:CRS84" } },
"features": [
{ "type": "Feature", "properties": { "Name": "Fire Detection Centroid ", "Description": "<b>Latitude: <\/b> 19.41086<br\/>  <b>Longitude: <\/b> -155.27925<br\/>  <b>Detection Time: <\/b> 2023-10-04 11:23 UTC<br\/>  <b>Sensor: <\/b> NOAA-20 VIIRS<br\/> <b>Confidence: <\/b> Nominal<br\/>  <b>Day\/Night: <\/b> Night<br\/> <b>Scan: <\/b> 0.32 km<br\/> <b>Track: <\/b> 0.55 km<br\/> <b>FRP: <\/b> 2.95 MW<br\/> <b>Brightness: <\/b> 313.21 K" }, "geometry": { "type": "Point", "coordinates": [ -155.27925, 19.41086, 0.0 ] } },
{ "type": "Feature", "properties": { "Name": "Fire Detection Centroid ", "Description": "<b>Latitude: <\/b> 19.41118<br\/>  <b>Longitude: <\/b> -155.28221<br\/>  <b>Detection Time: <\/b> 2023-10-04 11:23 UTC<br\/>  <b>Sensor: <\/b> NOAA-20 VIIRS<br\/> <b>Confidence: <\/b> Nominal<br\/>  <b>Day\/Night: <\/b> Night<br\/> <b>Scan: <\/b> 0.32 km<br\/> <b>Track: <\/b> 0.55 km<br\/> <b>FRP: <\/b> 2.73 MW<br\/> <b>Brightness: <\/b> 301.49 K" }, "geometry": { "type": "Point", "coordinates": [ -155.28221, 19.41118, 0.0 ] } },
{ "type": "Feature", "properties": { "Name": "Fire Detection Centroid ", "Description": "<b>Latitude: <\/b> 19.41054<br\/>  <b>Longitude: <\/b> -155.27625<br\/>  <b>Detection Time: <\/b> 2023-10-04 11:23 UTC<br\/>  <b>Sensor: <\/b> NOAA-20 VIIRS<br\/> <b>Confidence: <\/b> Nominal<br\/>  <b>Day\/Night: <\/b> Night<br\/> <b>Scan: <\/b> 0.32 km<br\/> <b>Track: <\/b> 0.55 km<br\/> <b>FRP: <\/b> 2.95 MW<br\/> <b>Brightness: <\/b> 313.21 K" }, "geometry": { "type": "Point", "coordinates": [ -155.27625, 19.41054, 0.0 ] } },
{ "type": "Feature", "properties": { "Name": "Fire Detection Centroid ", "Description": "<b>Latitude: <\/b> 19.40585<br\/>  <b>Longitude: <\/b> -155.27994<br\/>  <b>Detection Time: <\/b> 2023-10-04 11:23 UTC<br\/>  <b>Sensor: <\/b> NOAA-20 VIIRS<br\/> <b>Confidence: <\/b> Nominal<br\/>  <b>Day\/Night: <\/b> Night<br\/> <b>Scan: <\/b> 0.32 km<br\/> <b>Track: <\/b> 0.55 km<br\/> <b>FRP: <\/b> 2.51 MW<br\/> <b>Brightness: <\/b> 310.07 K" }, "geometry": { "type": "Point", "coordinates": [ -155.27994, 19.40585, 0.0 ] } },
{ "type": "Feature", "properties": { "Name": "Fire Detection Centroid ", "Description": "<b>Latitude: <\/b> 48.1719<br\/>  <b>Longitude: <\/b> -118.75558<br\/>  <b>Detection Time: <\/b> 2023-10-04 11:15 UTC<br\/>  <b>Sensor: <\/b> NOAA-20 VIIRS<br\/> <b>Confidence: <\/b> Nominal<br\/>  <b>Day\/Night: <\/b> Night<br\/> <b>Scan: <\/b> 0.59 km<br\/> <b>Track: <\/b> 0.7 km<br\/> <b>FRP: <\/b> 1.45 MW<br\/> <b>Brightness: <\/b> 299.96 K" }, "geometry": { "type": "Point", "coordinates": [ -118.75558, 48.1719, 0.0 ] } },
{ "type": "Feature", "properties": { "Name": "Fire Detection Centroid ", "Description": "<b>Latitude: <\/b> 48.17204<br\/>  <b>Longitude: <\/b> -118.75236<br\/>  <b>Detection Time: <\/b> 2023-10-04 11:14 UTC<br\/>  <b>Sensor: <\/b> NOAA-20 VIIRS<br\/> <b>Confidence: <\/b> Nominal<br\/>  <b>Day\/Night: <\/b> Night<br\/> <b>Scan: <\/b> 0.6 km<br\/> <b>Track: <\/b> 0.7 km<br\/> <b>FRP: <\/b> 1.45 MW<br\/> <b>Brightness: <\/b> 299.96 K" }, "geometry": { "type": "Point", "coordinates": [ -118.75236, 48.17204, 0.0 ] } },
{ "type": "Feature", "properties": { "Name": "Fire Detection Centroid ", "Description": "<b>Latitude: <\/b> 48.17204<br\/>  <b>Longitude: <\/b> -118.75236<br\/>  <b>Detection Time: <\/b> 2023-10-04 11:14 UTC<br\/>  <b>Sensor: <\/b> NOAA-20 VIIRS<br\/> <b>Confidence: <\/b> Nominal<br\/>  <b>Day\/Night: <\/b> Night<br\/> <b>Scan: <\/b> 0.6 km<br\/> <b>Track: <\/b> 0.7 km<br\/> <b>FRP: <\/b> 1.45 MW<br\/> <b>Brightness: <\/b> 299.96 K" }, "geometry": { "type": "Point", "coordinates": [ -118.75236, 48.17204, 0.0 ] } }
]
}
