{
"type": "FeatureCollection",
"crs": { "type": "name", "properties": { "name": "urn:ogc:def:crs:OGC:1.3:CRS84" } },
"features": [
{ "type": "Feature", "properties": { "Name": "Fire Detection Centroid ", "Description": "<b>Latitude: <\/b> 18.92925<br\/>  <b>Longitude: <\/b> -70.35372<br\/>  <b>Detection Time: <\/b> 2023-06-21 05:48 UTC<br\/>  <b>Sensor: <\/b> NOAA-20 VIIRS<br\/> <b>Confidence: <\/b> Nominal<br\/>  <b>Day\/Night: <\/b> Night<br\/> <b>Scan: <\/b> 0.6 km<br\/> <b>Track: <\/b> 0.5 km<br\/> <b>FRP: <\/b> 11.77 MW<br\/> <b>Brightness: <\/b> 343.21 K" }, "geometry": { "type": "Point", "coordinates": [ -70.35372, 18.92925, 0.0 ] } },
{ "type": "Feature", "properties": { "Name": "Fire Detection Centroid ", "Description": "<b>Latitude: <\/b> 18.82296<br\/>  <b>Longitude: <\/b> -70.40246<br\/>  <b>Detection Time: <\/b> 2023-06-21 05:48 UTC<br\/>  <b>Sensor: <\/b> NOAA-20 VIIRS<br\/> <b>Confidence: <\/b> Nominal<br\/>  <b>Day\/Night: <\/b> Night<br\/> <b>Scan: <\/b> 0.6 km<br\/> <b>Track: <\/b> 0.5 km<br\/> <b>FRP: <\/b> 1.87 MW<br\/> <b>Brightness: <\/b> 311.38 K" }, "geometry": { "type": "Point", "coordinates": [ -70.40246, 18.82296, 0.0 ] } },
{ "type": "Feature", "properties": { "Name": "Fire Detection Centroid ", "Description": "<b>Latitude: <\/b> 46.04281<br\/>  <b>Longitude: <\/b> -73.14514<br\/>  <b>Detection Time: <\/b> 2023-06-21 05:41 UTC<br\/>  <b>Sensor: <\/b> NOAA-20 VIIRS<br\/> <b>Confidence: <\/b> Nominal<br\/>  <b>Day\/Night: <\/b> Night<br\/> <b>Scan: <\/b> 0.7 km<br\/> <b>Track: <\/b> 0.7 km<br\/> <b>FRP: <\/b> 1.9 MW<br\/> <b>Brightness: <\/b> 308.78 K" }, "geometry": { "type": "Point", "coordinates": [ -73.14514, 46.04281, 0.0 ] } },
{ "type": "Feature", "properties": { "Name": "Fire Detection Centroid ", "Description": "<b>Latitude: <\/b> 45.99403<br\/>  <b>Longitude: <\/b> -66.51484<br\/>  <b>Detection Time: <\/b> 2023-06-21 05:41 UTC<br\/>  <b>Sensor: <\/b> NOAA-20 VIIRS<br\/> <b>Confidence: <\/b> Nominal<br\/>  <b>Day\/Night: <\/b> Night<br\/> <b>Scan: <\/b> 0.3 km<br\/> <b>Track: <\/b> 0.5 km<br\/> <b>FRP: <\/b> 0.23 MW<br\/> <b>Brightness: <\/b> 299.05 K" }, "geometry": { "type": "Point", "coordinates": [ -66.51484, 45.99403, 0.0 ] } },
{ "type": "Feature", "properties": { "Name": "Fire Detection Centroid ", "Description": "<b>Latitude: <\/b> 45.27818<br\/>  <b>Longitude: <\/b> -66.01646<br\/>  <b>Detection Time: <\/b> 2023-06-21 05:41 UTC<br\/>  <b>Sensor: <\/b> NOAA-20 VIIRS<br\/> <b>Confidence: <\/b> Nominal<br\/>  <b>Day\/Night: <\/b> Night<br\/> <b>Scan: <\/b> 0.6 km<br\/> <b>Track: <\/b> 0.5 km<br\/> <b>FRP: <\/b> 1.04 MW<br\/> <b>Brightness: <\/b> 295.24 K" }, "geometry": { "type": "Point", "coordinates": [ -66.01646, 45.27818, 0.0 ] } },
{ "type": "Feature", "properties": { "Name": "Fire Detection Centroid ", "Description": "<b>Latitude: <\/b> 45.83573<br\/>  <b>Longitude: <\/b> -73.25694<br\/>  <b>Detection Time: <\/b> 2023-06-21 05:41 UTC<br\/>  <b>Sensor: <\/b> NOAA-20 VIIRS<br\/> <b>Confidence: <\/b> Nominal<br\/>  <b>Day\/Night: <\/b> Night<br\/> <b>Scan: <\/b> 0.7 km<br\/> <b>Track: <\/b> 0.7 km<br\/> <b>FRP: <\/b> 1.18 MW<br\/> <b>Brightness: <\/b> 297.38 K" }, "geometry": { "type": "Point", "coordinates": [ -73.25694, 45.83573, 0.0 ] } },
{ "type": "Feature", "properties": { "Name": "Fire Detection Centroid ", "Description": "<b>Latitude: <\/b> 45.08728<br\/>  <b>Longitude: <\/b> -73.91014<br\/>  <b>Detection Time: <\/b> 2023-06-21 05:41 UTC<br\/>  <b>Sensor: <\/b> NOAA-20 VIIRS<br\/> <b>Confidence: <\/b> Nominal<br\/>  <b>Day\/Night: <\/b> Night<br\/> <b>Scan: <\/b> 0.7 km<br\/> <b>Track: <\/b> 0.8 km<br\/> <b>FRP: <\/b> 0.69 MW<br\/> <b>Brightness: <\/b> 296.43 K" }, "geometry": { "type": "Point", "coordinates": [ -73.91014, 45.08728, 0.0 ] } },
{ "type": "Feature", "properties": { "Name": "Fire Detection Centroid ", "Description": "<b>Latitude: <\/b> 48.18694<br\/>  <b>Longitude: <\/b> -64.92322<br\/>  <b>Detection Time: <\/b> 2023-06-21 05:40 UTC<br\/>  <b>Sensor: <\/b> NOAA-20 VIIRS<br\/> <b>Confidence: <\/b> Nominal<br\/>  <b>Day\/Night: <\/b> Night<br\/> <b>Scan: <\/b> 0.6 km<br\/> <b>Track: <\/b> 0.5 km<br\/> <b>FRP: <\/b> 1.72 MW<br\/> <b>Brightness: <\/b> 305.38 K" }, "geometry": { "type": "Point", "coordinates": [ -64.92322, 48.18694, 0.0 ] } },
{ "type": "Feature", "properties": { "Name": "Fire Detection Centroid ", "Description": "<b>Latitude: <\/b> 48.18633<br\/>  <b>Longitude: <\/b> -64.91792<br\/>  <b>Detection Time: <\/b> 2023-06-21 05:40 UTC<br\/>  <b>Sensor: <\/b> NOAA-20 VIIRS<br\/> <b>Confidence: <\/b> Nominal<br\/>  <b>Day\/Night: <\/b> Night<br\/> <b>Scan: <\/b> 0.6 km<br\/> <b>Track: <\/b> 0.5 km<br\/> <b>FRP: <\/b> 1.13 MW<br\/> <b>Brightness: <\/b> 300.84 K" }, "geometry": { "type": "Point", "coordinates": [ -64.91792, 48.18633, 0.0 ] } }
]
}
