{
"type": "FeatureCollection",
"crs": { "type": "name", "properties": { "name": "urn:ogc:def:crs:OGC:1.3:CRS84" } },
"features": [
{ "type": "Feature", "properties": { "Name": "Fire Detection Centroid ", "Description": "<b>Latitude: <\/b> 40.60865<br\/>  <b>Longitude: <\/b> -75.31812<br\/>  <b>Detection Time: <\/b> 2023-07-13 16:53 UTC<br\/>  <b>Sensor: <\/b> NOAA-20 VIIRS<br\/> <b>Confidence: <\/b> Low<br\/>  <b>Day\/Night: <\/b> Day<br\/> <b>Scan: <\/b> 0.6 km<br\/> <b>Track: <\/b> 0.7 km<br\/> <b>FRP: <\/b> 8.86 MW<br\/> <b>Brightness: <\/b> 326.12 K" }, "geometry": { "type": "Point", "coordinates": [ -75.31812, 40.60865, 0.0 ] } },
{ "type": "Feature", "properties": { "Name": "Fire Detection Centroid ", "Description": "<b>Latitude: <\/b> 19.40318<br\/>  <b>Longitude: <\/b> -155.28542<br\/>  <b>Detection Time: <\/b> 2023-07-13 12:21 UTC<br\/>  <b>Sensor: <\/b> NOAA-20 VIIRS<br\/> <b>Confidence: <\/b> Nominal<br\/>  <b>Day\/Night: <\/b> Night<br\/> <b>Scan: <\/b> 0.41 km<br\/> <b>Track: <\/b> 0.45 km<br\/> <b>FRP: <\/b> 3.14 MW<br\/> <b>Brightness: <\/b> 312.79 K" }, "geometry": { "type": "Point", "coordinates": [ -155.28542, 19.40318, 0.0 ] } },
{ "type": "Feature", "properties": { "Name": "Fire Detection Centroid ", "Description": "<b>Latitude: <\/b> 19.40392<br\/>  <b>Longitude: <\/b> -155.2894<br\/>  <b>Detection Time: <\/b> 2023-07-13 12:21 UTC<br\/>  <b>Sensor: <\/b> NOAA-20 VIIRS<br\/> <b>Confidence: <\/b> Nominal<br\/>  <b>Day\/Night: <\/b> Night<br\/> <b>Scan: <\/b> 0.41 km<br\/> <b>Track: <\/b> 0.45 km<br\/> <b>FRP: <\/b> 2.9 MW<br\/> <b>Brightness: <\/b> 315.45 K" }, "geometry": { "type": "Point", "coordinates": [ -155.2894, 19.40392, 0.0 ] } },
{ "type": "Feature", "properties": { "Name": "Fire Detection Centroid ", "Description": "<b>Latitude: <\/b> 19.40653<br\/>  <b>Longitude: <\/b> -155.28067<br\/>  <b>Detection Time: <\/b> 2023-07-13 12:21 UTC<br\/>  <b>Sensor: <\/b> NOAA-20 VIIRS<br\/> <b>Confidence: <\/b> Nominal<br\/>  <b>Day\/Night: <\/b> Night<br\/> <b>Scan: <\/b> 0.41 km<br\/> <b>Track: <\/b> 0.45 km<br\/> <b>FRP: <\/b> 2.67 MW<br\/> <b>Brightness: <\/b> 318.56 K" }, "geometry": { "type": "Point", "coordinates": [ -155.28067, 19.40653, 0.0 ] } },
{ "type": "Feature", "properties": { "Name": "Fire Detection Centroid ", "Description": "<b>Latitude: <\/b> 19.40726<br\/>  <b>Longitude: <\/b> -155.28459<br\/>  <b>Detection Time: <\/b> 2023-07-13 12:21 UTC<br\/>  <b>Sensor: <\/b> NOAA-20 VIIRS<br\/> <b>Confidence: <\/b> Nominal<br\/>  <b>Day\/Night: <\/b> Night<br\/> <b>Scan: <\/b> 0.41 km<br\/> <b>Track: <\/b> 0.45 km<br\/> <b>FRP: <\/b> 2.67 MW<br\/> <b>Brightness: <\/b> 312.19 K" }, "geometry": { "type": "Point", "coordinates": [ -155.28459, 19.40726, 0.0 ] } },
{ "type": "Feature", "properties": { "Name": "Fire Detection Centroid ", "Description": "<b>Latitude: <\/b> 19.408<br\/>  <b>Longitude: <\/b> -155.28862<br\/>  <b>Detection Time: <\/b> 2023-07-13 12:21 UTC<br\/>  <b>Sensor: <\/b> NOAA-20 VIIRS<br\/> <b>Confidence: <\/b> Nominal<br\/>  <b>Day\/Night: <\/b> Night<br\/> <b>Scan: <\/b> 0.41 km<br\/> <b>Track: <\/b> 0.45 km<br\/> <b>FRP: <\/b> 3.93 MW<br\/> <b>Brightness: <\/b> 314 K" }, "geometry": { "type": "Point", "coordinates": [ -155.28862, 19.408, 0.0 ] } },
{ "type": "Feature", "properties": { "Name": "Fire Detection Centroid ", "Description": "<b>Latitude: <\/b> 19.41061<br\/>  <b>Longitude: <\/b> -155.27985<br\/>  <b>Detection Time: <\/b> 2023-07-13 12:21 UTC<br\/>  <b>Sensor: <\/b> NOAA-20 VIIRS<br\/> <b>Confidence: <\/b> Nominal<br\/>  <b>Day\/Night: <\/b> Night<br\/> <b>Scan: <\/b> 0.41 km<br\/> <b>Track: <\/b> 0.45 km<br\/> <b>FRP: <\/b> 2.67 MW<br\/> <b>Brightness: <\/b> 317.78 K" }, "geometry": { "type": "Point", "coordinates": [ -155.27985, 19.41061, 0.0 ] } },
{ "type": "Feature", "properties": { "Name": "Fire Detection Centroid ", "Description": "<b>Latitude: <\/b> 19.41135<br\/>  <b>Longitude: <\/b> -155.28383<br\/>  <b>Detection Time: <\/b> 2023-07-13 12:21 UTC<br\/>  <b>Sensor: <\/b> NOAA-20 VIIRS<br\/> <b>Confidence: <\/b> Nominal<br\/>  <b>Day\/Night: <\/b> Night<br\/> <b>Scan: <\/b> 0.41 km<br\/> <b>Track: <\/b> 0.45 km<br\/> <b>FRP: <\/b> 2.67 MW<br\/> <b>Brightness: <\/b> 315.71 K" }, "geometry": { "type": "Point", "coordinates": [ -155.28383, 19.41135, 0.0 ] } },
{ "type": "Feature", "properties": { "Name": "Fire Detection Centroid ", "Description": "<b>Latitude: <\/b> 19.41476<br\/>  <b>Longitude: <\/b> -155.28352<br\/>  <b>Detection Time: <\/b> 2023-07-13 12:21 UTC<br\/>  <b>Sensor: <\/b> NOAA-20 VIIRS<br\/> <b>Confidence: <\/b> Nominal<br\/>  <b>Day\/Night: <\/b> Night<br\/> <b>Scan: <\/b> 0.41 km<br\/> <b>Track: <\/b> 0.45 km<br\/> <b>FRP: <\/b> 2.67 MW<br\/> <b>Brightness: <\/b> 308.55 K" }, "geometry": { "type": "Point", "coordinates": [ -155.28352, 19.41476, 0.0 ] } }
]
}
