{
"type": "FeatureCollection",
"crs": { "type": "name", "properties": { "name": "urn:ogc:def:crs:OGC:1.3:CRS84" } },
"features": [
{ "type": "Feature", "properties": { "Name": "Fire Detection Centroid ", "Description": "<b>Latitude: <\/b> 45.77121<br\/>  <b>Longitude: <\/b> -66.32122<br\/>  <b>Detection Time: <\/b> 2024-04-10 16:29 UTC<br\/>  <b>Sensor: <\/b> NOAA-20 VIIRS<br\/> <b>Confidence: <\/b> Nominal<br\/>  <b>Day\/Night: <\/b> Day<br\/> <b>Scan: <\/b> 0.6 km<br\/> <b>Track: <\/b> 0.5 km<br\/> <b>FRP: <\/b> 9.61 MW<br\/> <b>Brightness: <\/b> 341.95 K" }, "geometry": { "type": "Point", "coordinates": [ -66.32122, 45.77121, 0.0 ] } },
{ "type": "Feature", "properties": { "Name": "Fire Detection Centroid ", "Description": "<b>Latitude: <\/b> 45.76662<br\/>  <b>Longitude: <\/b> -66.31866<br\/>  <b>Detection Time: <\/b> 2024-04-10 16:29 UTC<br\/>  <b>Sensor: <\/b> NOAA-20 VIIRS<br\/> <b>Confidence: <\/b> Nominal<br\/>  <b>Day\/Night: <\/b> Day<br\/> <b>Scan: <\/b> 0.6 km<br\/> <b>Track: <\/b> 0.5 km<br\/> <b>FRP: <\/b> 4.95 MW<br\/> <b>Brightness: <\/b> 326.15 K" }, "geometry": { "type": "Point", "coordinates": [ -66.31866, 45.76662, 0.0 ] } },
{ "type": "Feature", "properties": { "Name": "Fire Detection Centroid ", "Description": "<b>Latitude: <\/b> 45.77423<br\/>  <b>Longitude: <\/b> -66.28992<br\/>  <b>Detection Time: <\/b> 2024-04-10 16:29 UTC<br\/>  <b>Sensor: <\/b> NOAA-20 VIIRS<br\/> <b>Confidence: <\/b> Nominal<br\/>  <b>Day\/Night: <\/b> Day<br\/> <b>Scan: <\/b> 0.6 km<br\/> <b>Track: <\/b> 0.5 km<br\/> <b>FRP: <\/b> 6.97 MW<br\/> <b>Brightness: <\/b> 338.08 K" }, "geometry": { "type": "Point", "coordinates": [ -66.28992, 45.77423, 0.0 ] } },
{ "type": "Feature", "properties": { "Name": "Fire Detection Centroid ", "Description": "<b>Latitude: <\/b> 45.77618<br\/>  <b>Longitude: <\/b> -66.28257<br\/>  <b>Detection Time: <\/b> 2024-04-10 16:29 UTC<br\/>  <b>Sensor: <\/b> NOAA-20 VIIRS<br\/> <b>Confidence: <\/b> Nominal<br\/>  <b>Day\/Night: <\/b> Day<br\/> <b>Scan: <\/b> 0.6 km<br\/> <b>Track: <\/b> 0.5 km<br\/> <b>FRP: <\/b> 6.97 MW<br\/> <b>Brightness: <\/b> 345.03 K" }, "geometry": { "type": "Point", "coordinates": [ -66.28257, 45.77618, 0.0 ] } },
{ "type": "Feature", "properties": { "Name": "Fire Detection Centroid ", "Description": "<b>Latitude: <\/b> 41.8533<br\/>  <b>Longitude: <\/b> -70.62222<br\/>  <b>Detection Time: <\/b> 2024-04-10 16:28 UTC<br\/>  <b>Sensor: <\/b> NOAA-20 VIIRS<br\/> <b>Confidence: <\/b> Nominal<br\/>  <b>Day\/Night: <\/b> Day<br\/> <b>Scan: <\/b> 0.6 km<br\/> <b>Track: <\/b> 0.7 km<br\/> <b>FRP: <\/b> 11.12 MW<br\/> <b>Brightness: <\/b> 356 K" }, "geometry": { "type": "Point", "coordinates": [ -70.62222, 41.8533, 0.0 ] } }
]
}
