{
"type": "FeatureCollection",
"crs": { "type": "name", "properties": { "name": "urn:ogc:def:crs:OGC:1.3:CRS84" } },
"features": [
{ "type": "Feature", "properties": { "Name": "Fire Detection Centroid ", "Description": "<b>Latitude: <\/b> 19.40679<br\/>  <b>Longitude: <\/b> -155.28445<br\/>  <b>Detection Time: <\/b> 2024-01-28 11:49 UTC<br\/>  <b>Sensor: <\/b> NOAA-20 VIIRS<br\/> <b>Confidence: <\/b> Nominal<br\/>  <b>Day\/Night: <\/b> Night<br\/> <b>Scan: <\/b> 0.42 km<br\/> <b>Track: <\/b> 0.38 km<br\/> <b>FRP: <\/b> 3.33 MW<br\/> <b>Brightness: <\/b> 304.02 K" }, "geometry": { "type": "Point", "coordinates": [ -155.28445, 19.40679, 0.0 ] } },
{ "type": "Feature", "properties": { "Name": "Fire Detection Centroid ", "Description": "<b>Latitude: <\/b> 19.41049<br\/>  <b>Longitude: <\/b> -155.28346<br\/>  <b>Detection Time: <\/b> 2024-01-28 11:49 UTC<br\/>  <b>Sensor: <\/b> NOAA-20 VIIRS<br\/> <b>Confidence: <\/b> Nominal<br\/>  <b>Day\/Night: <\/b> Night<br\/> <b>Scan: <\/b> 0.4 km<br\/> <b>Track: <\/b> 0.4 km<br\/> <b>FRP: <\/b> 3.32 MW<br\/> <b>Brightness: <\/b> 304.02 K" }, "geometry": { "type": "Point", "coordinates": [ -155.28346, 19.41049, 0.0 ] } }
]
}
