{
"type": "FeatureCollection",
"crs": { "type": "name", "properties": { "name": "urn:ogc:def:crs:OGC:1.3:CRS84" } },
"features": [
{ "type": "Feature", "properties": { "Name": "Fire Detection Centroid ", "Description": "<b>Latitude: <\/b> 20.84824<br\/>  <b>Longitude: <\/b> -156.50583<br\/>  <b>Detection Time: <\/b> 2023-10-16 23:51 UTC<br\/>  <b>Sensor: <\/b> NOAA-20 VIIRS<br\/> <b>Confidence: <\/b> Nominal<br\/>  <b>Day\/Night: <\/b> Day<br\/> <b>Scan: <\/b> 0.5 km<br\/> <b>Track: <\/b> 0.4 km<br\/> <b>FRP: <\/b> 12.84 MW<br\/> <b>Brightness: <\/b> 340.17 K" }, "geometry": { "type": "Point", "coordinates": [ -156.50583, 20.84824, 0.0 ] } },
{ "type": "Feature", "properties": { "Name": "Fire Detection Centroid ", "Description": "<b>Latitude: <\/b> 20.84853<br\/>  <b>Longitude: <\/b> -156.50526<br\/>  <b>Detection Time: <\/b> 2023-10-16 23:50 UTC<br\/>  <b>Sensor: <\/b> NOAA-20 VIIRS<br\/> <b>Confidence: <\/b> Nominal<br\/>  <b>Day\/Night: <\/b> Day<br\/> <b>Scan: <\/b> 0.46 km<br\/> <b>Track: <\/b> 0.39 km<br\/> <b>FRP: <\/b> 12.84 MW<br\/> <b>Brightness: <\/b> 340.17 K" }, "geometry": { "type": "Point", "coordinates": [ -156.50526, 20.84853, 0.0 ] } }
]
}
