{
"type": "FeatureCollection",
"crs": { "type": "name", "properties": { "name": "urn:ogc:def:crs:OGC:1.3:CRS84" } },
"features": [
{ "type": "Feature", "properties": { "Name": "Fire Detection Centroid ", "Description": "<b>Latitude: <\/b> 21.36953<br\/>  <b>Longitude: <\/b> -158.0665<br\/>  <b>Detection Time: <\/b> 2023-10-28 23:26 UTC<br\/>  <b>Sensor: <\/b> NOAA-20 VIIRS<br\/> <b>Confidence: <\/b> Nominal<br\/>  <b>Day\/Night: <\/b> Day<br\/> <b>Scan: <\/b> 0.5 km<br\/> <b>Track: <\/b> 0.4 km<br\/> <b>FRP: <\/b> 9.41 MW<br\/> <b>Brightness: <\/b> 338.1 K" }, "geometry": { "type": "Point", "coordinates": [ -158.0665, 21.36953, 0.0 ] } },
{ "type": "Feature", "properties": { "Name": "Fire Detection Centroid ", "Description": "<b>Latitude: <\/b> 21.37028<br\/>  <b>Longitude: <\/b> -158.06598<br\/>  <b>Detection Time: <\/b> 2023-10-28 23:26 UTC<br\/>  <b>Sensor: <\/b> NOAA-20 VIIRS<br\/> <b>Confidence: <\/b> Nominal<br\/>  <b>Day\/Night: <\/b> Day<br\/> <b>Scan: <\/b> 0.53 km<br\/> <b>Track: <\/b> 0.42 km<br\/> <b>FRP: <\/b> 9.42 MW<br\/> <b>Brightness: <\/b> 338.1 K" }, "geometry": { "type": "Point", "coordinates": [ -158.06598, 21.37028, 0.0 ] } }
]
}
