{
"type": "FeatureCollection",
"crs": { "type": "name", "properties": { "name": "urn:ogc:def:crs:OGC:1.3:CRS84" } },
"features": [
{ "type": "Feature", "properties": { "Name": "Fire Detection Centroid ", "Description": "<b>Latitude: <\/b> 35.47696<br\/>  <b>Longitude: <\/b> -76.30859<br\/>  <b>Detection Time: <\/b> 2023-05-04 17:04 UTC<br\/>  <b>Sensor: <\/b> NOAA-20 VIIRS<br\/> <b>Confidence: <\/b> Nominal<br\/>  <b>Day\/Night: <\/b> Day<br\/> <b>Scan: <\/b> 0.6 km<br\/> <b>Track: <\/b> 0.7 km<br\/> <b>FRP: <\/b> 5.2 MW<br\/> <b>Brightness: <\/b> 328.69 K" }, "geometry": { "type": "Point", "coordinates": [ -76.30859, 35.47696, 0.0 ] } },
{ "type": "Feature", "properties": { "Name": "Fire Detection Centroid ", "Description": "<b>Latitude: <\/b> 18.92417<br\/>  <b>Longitude: <\/b> -70.34634<br\/>  <b>Detection Time: <\/b> 2023-05-04 16:59 UTC<br\/>  <b>Sensor: <\/b> NOAA-20 VIIRS<br\/> <b>Confidence: <\/b> Nominal<br\/>  <b>Day\/Night: <\/b> Day<br\/> <b>Scan: <\/b> 0.7 km<br\/> <b>Track: <\/b> 0.8 km<br\/> <b>FRP: <\/b> 5.64 MW<br\/> <b>Brightness: <\/b> 327.18 K" }, "geometry": { "type": "Point", "coordinates": [ -70.34634, 18.92417, 0.0 ] } },
{ "type": "Feature", "properties": { "Name": "Fire Detection Centroid ", "Description": "<b>Latitude: <\/b> 18.92918<br\/>  <b>Longitude: <\/b> -70.3492<br\/>  <b>Detection Time: <\/b> 2023-05-04 16:59 UTC<br\/>  <b>Sensor: <\/b> NOAA-20 VIIRS<br\/> <b>Confidence: <\/b> Nominal<br\/>  <b>Day\/Night: <\/b> Day<br\/> <b>Scan: <\/b> 0.7 km<br\/> <b>Track: <\/b> 0.8 km<br\/> <b>FRP: <\/b> 6.37 MW<br\/> <b>Brightness: <\/b> 334 K" }, "geometry": { "type": "Point", "coordinates": [ -70.3492, 18.92918, 0.0 ] } },
{ "type": "Feature", "properties": { "Name": "Fire Detection Centroid ", "Description": "<b>Latitude: <\/b> 19.46078<br\/>  <b>Longitude: <\/b> -70.03426<br\/>  <b>Detection Time: <\/b> 2023-05-04 16:59 UTC<br\/>  <b>Sensor: <\/b> NOAA-20 VIIRS<br\/> <b>Confidence: <\/b> Nominal<br\/>  <b>Day\/Night: <\/b> Day<br\/> <b>Scan: <\/b> 0.7 km<br\/> <b>Track: <\/b> 0.7 km<br\/> <b>FRP: <\/b> 5.69 MW<br\/> <b>Brightness: <\/b> 328.2 K" }, "geometry": { "type": "Point", "coordinates": [ -70.03426, 19.46078, 0.0 ] } }
]
}
