{
"type": "FeatureCollection",
"crs": { "type": "name", "properties": { "name": "urn:ogc:def:crs:OGC:1.3:CRS84" } },
"features": [
{ "type": "Feature", "properties": { "Name": "Fire Detection Centroid ", "Description": "<b>Latitude: <\/b> 19.40887<br\/>  <b>Longitude: <\/b> -155.28435<br\/>  <b>Detection Time: <\/b> 2023-08-12 00:30 UTC<br\/>  <b>Sensor: <\/b> NOAA-20 VIIRS<br\/> <b>Confidence: <\/b> Low<br\/>  <b>Day\/Night: <\/b> Day<br\/> <b>Scan: <\/b> 0.71 km<br\/> <b>Track: <\/b> 0.75 km<br\/> <b>FRP: <\/b> 16.23 MW<br\/> <b>Brightness: <\/b> 328.29 K" }, "geometry": { "type": "Point", "coordinates": [ -155.28435, 19.40887, 0.0 ] } }
]
}
