{
"type": "FeatureCollection",
"crs": { "type": "name", "properties": { "name": "urn:ogc:def:crs:OGC:1.3:CRS84" } },
"features": [
{ "type": "Feature", "properties": { "Name": "Fire Detection Centroid ", "Description": "<b>Latitude: <\/b> 19.0897<br\/>  <b>Longitude: <\/b> -69.89081<br\/>  <b>Detection Time: <\/b> 2024-02-16 16:59 UTC<br\/>  <b>Sensor: <\/b> NOAA-20 VIIRS<br\/> <b>Confidence: <\/b> Nominal<br\/>  <b>Day\/Night: <\/b> Day<br\/> <b>Scan: <\/b> 0.7 km<br\/> <b>Track: <\/b> 0.7 km<br\/> <b>FRP: <\/b> 6.63 MW<br\/> <b>Brightness: <\/b> 341.91 K" }, "geometry": { "type": "Point", "coordinates": [ -69.89081, 19.0897, 0.0 ] } },
{ "type": "Feature", "properties": { "Name": "Fire Detection Centroid ", "Description": "<b>Latitude: <\/b> 18.41955<br\/>  <b>Longitude: <\/b> -69.20641<br\/>  <b>Detection Time: <\/b> 2024-02-16 16:59 UTC<br\/>  <b>Sensor: <\/b> NOAA-20 VIIRS<br\/> <b>Confidence: <\/b> High<br\/>  <b>Day\/Night: <\/b> Day<br\/> <b>Scan: <\/b> 0.6 km<br\/> <b>Track: <\/b> 0.7 km<br\/> <b>FRP: <\/b> 25.87 MW<br\/> <b>Brightness: <\/b> 367 K" }, "geometry": { "type": "Point", "coordinates": [ -69.20641, 18.41955, 0.0 ] } },
{ "type": "Feature", "properties": { "Name": "Fire Detection Centroid ", "Description": "<b>Latitude: <\/b> 18.62494<br\/>  <b>Longitude: <\/b> -69.25744<br\/>  <b>Detection Time: <\/b> 2024-02-16 16:59 UTC<br\/>  <b>Sensor: <\/b> NOAA-20 VIIRS<br\/> <b>Confidence: <\/b> High<br\/>  <b>Day\/Night: <\/b> Day<br\/> <b>Scan: <\/b> 0.6 km<br\/> <b>Track: <\/b> 0.7 km<br\/> <b>FRP: <\/b> 32.34 MW<br\/> <b>Brightness: <\/b> 367 K" }, "geometry": { "type": "Point", "coordinates": [ -69.25744, 18.62494, 0.0 ] } },
{ "type": "Feature", "properties": { "Name": "Fire Detection Centroid ", "Description": "<b>Latitude: <\/b> 18.70475<br\/>  <b>Longitude: <\/b> -69.11585<br\/>  <b>Detection Time: <\/b> 2024-02-16 16:59 UTC<br\/>  <b>Sensor: <\/b> NOAA-20 VIIRS<br\/> <b>Confidence: <\/b> Nominal<br\/>  <b>Day\/Night: <\/b> Day<br\/> <b>Scan: <\/b> 0.6 km<br\/> <b>Track: <\/b> 0.7 km<br\/> <b>FRP: <\/b> 10.47 MW<br\/> <b>Brightness: <\/b> 340.21 K" }, "geometry": { "type": "Point", "coordinates": [ -69.11585, 18.70475, 0.0 ] } },
{ "type": "Feature", "properties": { "Name": "Fire Detection Centroid ", "Description": "<b>Latitude: <\/b> 18.86111<br\/>  <b>Longitude: <\/b> -70.49634<br\/>  <b>Detection Time: <\/b> 2024-02-16 16:59 UTC<br\/>  <b>Sensor: <\/b> NOAA-20 VIIRS<br\/> <b>Confidence: <\/b> Nominal<br\/>  <b>Day\/Night: <\/b> Day<br\/> <b>Scan: <\/b> 0.7 km<br\/> <b>Track: <\/b> 0.8 km<br\/> <b>FRP: <\/b> 7.9 MW<br\/> <b>Brightness: <\/b> 328.97 K" }, "geometry": { "type": "Point", "coordinates": [ -70.49634, 18.86111, 0.0 ] } },
{ "type": "Feature", "properties": { "Name": "Fire Detection Centroid ", "Description": "<b>Latitude: <\/b> 19.07054<br\/>  <b>Longitude: <\/b> -70.52626<br\/>  <b>Detection Time: <\/b> 2024-02-16 16:59 UTC<br\/>  <b>Sensor: <\/b> NOAA-20 VIIRS<br\/> <b>Confidence: <\/b> Nominal<br\/>  <b>Day\/Night: <\/b> Day<br\/> <b>Scan: <\/b> 0.7 km<br\/> <b>Track: <\/b> 0.8 km<br\/> <b>FRP: <\/b> 5.61 MW<br\/> <b>Brightness: <\/b> 325.33 K" }, "geometry": { "type": "Point", "coordinates": [ -70.52626, 19.07054, 0.0 ] } },
{ "type": "Feature", "properties": { "Name": "Fire Detection Centroid ", "Description": "<b>Latitude: <\/b> 19.06909<br\/>  <b>Longitude: <\/b> -70.53241<br\/>  <b>Detection Time: <\/b> 2024-02-16 16:59 UTC<br\/>  <b>Sensor: <\/b> NOAA-20 VIIRS<br\/> <b>Confidence: <\/b> Nominal<br\/>  <b>Day\/Night: <\/b> Day<br\/> <b>Scan: <\/b> 0.7 km<br\/> <b>Track: <\/b> 0.8 km<br\/> <b>FRP: <\/b> 5.61 MW<br\/> <b>Brightness: <\/b> 326.37 K" }, "geometry": { "type": "Point", "coordinates": [ -70.53241, 19.06909, 0.0 ] } },
{ "type": "Feature", "properties": { "Name": "Fire Detection Centroid ", "Description": "<b>Latitude: <\/b> 19.19659<br\/>  <b>Longitude: <\/b> -69.63156<br\/>  <b>Detection Time: <\/b> 2024-02-16 16:59 UTC<br\/>  <b>Sensor: <\/b> NOAA-20 VIIRS<br\/> <b>Confidence: <\/b> Nominal<br\/>  <b>Day\/Night: <\/b> Day<br\/> <b>Scan: <\/b> 0.6 km<br\/> <b>Track: <\/b> 0.7 km<br\/> <b>FRP: <\/b> 12.51 MW<br\/> <b>Brightness: <\/b> 350.82 K" }, "geometry": { "type": "Point", "coordinates": [ -69.63156, 19.19659, 0.0 ] } },
{ "type": "Feature", "properties": { "Name": "Fire Detection Centroid ", "Description": "<b>Latitude: <\/b> 19.40247<br\/>  <b>Longitude: <\/b> -69.6851<br\/>  <b>Detection Time: <\/b> 2024-02-16 16:59 UTC<br\/>  <b>Sensor: <\/b> NOAA-20 VIIRS<br\/> <b>Confidence: <\/b> Nominal<br\/>  <b>Day\/Night: <\/b> Day<br\/> <b>Scan: <\/b> 0.6 km<br\/> <b>Track: <\/b> 0.7 km<br\/> <b>FRP: <\/b> 8.28 MW<br\/> <b>Brightness: <\/b> 347.05 K" }, "geometry": { "type": "Point", "coordinates": [ -69.6851, 19.40247, 0.0 ] } }
]
}
