{
"type": "FeatureCollection",
"crs": { "type": "name", "properties": { "name": "urn:ogc:def:crs:OGC:1.3:CRS84" } },
"features": [
{ "type": "Feature", "properties": { "Name": "Fire Detection Centroid ", "Description": "<b>Latitude: <\/b> 39.59079<br\/>  <b>Longitude: <\/b> -75.6357<br\/>  <b>Detection Time: <\/b> 2024-05-31 05:49 UTC<br\/>  <b>Sensor: <\/b> NOAA-20 VIIRS<br\/> <b>Confidence: <\/b> Nominal<br\/>  <b>Day\/Night: <\/b> Night<br\/> <b>Scan: <\/b> 0.7 km<br\/> <b>Track: <\/b> 0.7 km<br\/> <b>FRP: <\/b> 1.27 MW<br\/> <b>Brightness: <\/b> 298.05 K" }, "geometry": { "type": "Point", "coordinates": [ -75.6357, 39.59079, 0.0 ] } },
{ "type": "Feature", "properties": { "Name": "Fire Detection Centroid ", "Description": "<b>Latitude: <\/b> 40.15313<br\/>  <b>Longitude: <\/b> -74.77196<br\/>  <b>Detection Time: <\/b> 2024-05-31 05:48 UTC<br\/>  <b>Sensor: <\/b> NOAA-20 VIIRS<br\/> <b>Confidence: <\/b> Nominal<br\/>  <b>Day\/Night: <\/b> Night<br\/> <b>Scan: <\/b> 0.6 km<br\/> <b>Track: <\/b> 0.7 km<br\/> <b>FRP: <\/b> 0.57 MW<br\/> <b>Brightness: <\/b> 300.09 K" }, "geometry": { "type": "Point", "coordinates": [ -74.77196, 40.15313, 0.0 ] } },
{ "type": "Feature", "properties": { "Name": "Fire Detection Centroid ", "Description": "<b>Latitude: <\/b> 40.63804<br\/>  <b>Longitude: <\/b> -74.2225<br\/>  <b>Detection Time: <\/b> 2024-05-31 05:48 UTC<br\/>  <b>Sensor: <\/b> NOAA-20 VIIRS<br\/> <b>Confidence: <\/b> Nominal<br\/>  <b>Day\/Night: <\/b> Night<br\/> <b>Scan: <\/b> 0.6 km<br\/> <b>Track: <\/b> 0.7 km<br\/> <b>FRP: <\/b> 1.59 MW<br\/> <b>Brightness: <\/b> 296.91 K" }, "geometry": { "type": "Point", "coordinates": [ -74.2225, 40.63804, 0.0 ] } },
{ "type": "Feature", "properties": { "Name": "Fire Detection Centroid ", "Description": "<b>Latitude: <\/b> 41.56829<br\/>  <b>Longitude: <\/b> -72.77083<br\/>  <b>Detection Time: <\/b> 2024-05-31 05:48 UTC<br\/>  <b>Sensor: <\/b> NOAA-20 VIIRS<br\/> <b>Confidence: <\/b> Nominal<br\/>  <b>Day\/Night: <\/b> Night<br\/> <b>Scan: <\/b> 0.5 km<br\/> <b>Track: <\/b> 0.7 km<br\/> <b>FRP: <\/b> 1.39 MW<br\/> <b>Brightness: <\/b> 308.06 K" }, "geometry": { "type": "Point", "coordinates": [ -72.77083, 41.56829, 0.0 ] } },
{ "type": "Feature", "properties": { "Name": "Fire Detection Centroid ", "Description": "<b>Latitude: <\/b> 40.63713<br\/>  <b>Longitude: <\/b> -74.22569<br\/>  <b>Detection Time: <\/b> 2024-05-31 05:48 UTC<br\/>  <b>Sensor: <\/b> NOAA-20 VIIRS<br\/> <b>Confidence: <\/b> Nominal<br\/>  <b>Day\/Night: <\/b> Night<br\/> <b>Scan: <\/b> 0.6 km<br\/> <b>Track: <\/b> 0.7 km<br\/> <b>FRP: <\/b> 1.74 MW<br\/> <b>Brightness: <\/b> 297.61 K" }, "geometry": { "type": "Point", "coordinates": [ -74.22569, 40.63713, 0.0 ] } },
{ "type": "Feature", "properties": { "Name": "Fire Detection Centroid ", "Description": "<b>Latitude: <\/b> 45.83546<br\/>  <b>Longitude: <\/b> -73.25274<br\/>  <b>Detection Time: <\/b> 2024-05-31 05:47 UTC<br\/>  <b>Sensor: <\/b> NOAA-20 VIIRS<br\/> <b>Confidence: <\/b> Nominal<br\/>  <b>Day\/Night: <\/b> Night<br\/> <b>Scan: <\/b> 0.6 km<br\/> <b>Track: <\/b> 0.7 km<br\/> <b>FRP: <\/b> 1.85 MW<br\/> <b>Brightness: <\/b> 305.11 K" }, "geometry": { "type": "Point", "coordinates": [ -73.25274, 45.83546, 0.0 ] } },
{ "type": "Feature", "properties": { "Name": "Fire Detection Centroid ", "Description": "<b>Latitude: <\/b> 44.97792<br\/>  <b>Longitude: <\/b> -73.66227<br\/>  <b>Detection Time: <\/b> 2024-05-31 05:47 UTC<br\/>  <b>Sensor: <\/b> NOAA-20 VIIRS<br\/> <b>Confidence: <\/b> Nominal<br\/>  <b>Day\/Night: <\/b> Night<br\/> <b>Scan: <\/b> 0.6 km<br\/> <b>Track: <\/b> 0.7 km<br\/> <b>FRP: <\/b> 1.95 MW<br\/> <b>Brightness: <\/b> 311.41 K" }, "geometry": { "type": "Point", "coordinates": [ -73.66227, 44.97792, 0.0 ] } },
{ "type": "Feature", "properties": { "Name": "Fire Detection Centroid ", "Description": "<b>Latitude: <\/b> 44.97823<br\/>  <b>Longitude: <\/b> -73.66214<br\/>  <b>Detection Time: <\/b> 2024-05-31 05:47 UTC<br\/>  <b>Sensor: <\/b> NOAA-20 VIIRS<br\/> <b>Confidence: <\/b> Nominal<br\/>  <b>Day\/Night: <\/b> Night<br\/> <b>Scan: <\/b> 0.6 km<br\/> <b>Track: <\/b> 0.7 km<br\/> <b>FRP: <\/b> 1.72 MW<br\/> <b>Brightness: <\/b> 312.14 K" }, "geometry": { "type": "Point", "coordinates": [ -73.66214, 44.97823, 0.0 ] } },
{ "type": "Feature", "properties": { "Name": "Fire Detection Centroid ", "Description": "<b>Latitude: <\/b> 45.83678<br\/>  <b>Longitude: <\/b> -73.25243<br\/>  <b>Detection Time: <\/b> 2024-05-31 05:47 UTC<br\/>  <b>Sensor: <\/b> NOAA-20 VIIRS<br\/> <b>Confidence: <\/b> Nominal<br\/>  <b>Day\/Night: <\/b> Night<br\/> <b>Scan: <\/b> 0.6 km<br\/> <b>Track: <\/b> 0.7 km<br\/> <b>FRP: <\/b> 1.5 MW<br\/> <b>Brightness: <\/b> 310.59 K" }, "geometry": { "type": "Point", "coordinates": [ -73.25243, 45.83678, 0.0 ] } }
]
}
