{
"type": "FeatureCollection",
"crs": { "type": "name", "properties": { "name": "urn:ogc:def:crs:OGC:1.3:CRS84" } },
"features": [
{ "type": "Feature", "properties": { "Name": "Fire Detection Centroid ", "Description": "<b>Latitude: <\/b> 40.89061<br\/>  <b>Longitude: <\/b> -77.70919<br\/>  <b>Detection Time: <\/b> 2023-11-07 16:59 UTC<br\/>  <b>Sensor: <\/b> NOAA-20 VIIRS<br\/> <b>Confidence: <\/b> Nominal<br\/>  <b>Day\/Night: <\/b> Day<br\/> <b>Scan: <\/b> 0.6 km<br\/> <b>Track: <\/b> 0.7 km<br\/> <b>FRP: <\/b> 3.68 MW<br\/> <b>Brightness: <\/b> 326.09 K" }, "geometry": { "type": "Point", "coordinates": [ -77.70919, 40.89061, 0.0 ] } },
{ "type": "Feature", "properties": { "Name": "Fire Detection Centroid ", "Description": "<b>Latitude: <\/b> 38.4904<br\/>  <b>Longitude: <\/b> -78.38258<br\/>  <b>Detection Time: <\/b> 2023-11-07 16:58 UTC<br\/>  <b>Sensor: <\/b> NOAA-20 VIIRS<br\/> <b>Confidence: <\/b> Nominal<br\/>  <b>Day\/Night: <\/b> Day<br\/> <b>Scan: <\/b> 0.8 km<br\/> <b>Track: <\/b> 0.8 km<br\/> <b>FRP: <\/b> 7.73 MW<br\/> <b>Brightness: <\/b> 334.95 K" }, "geometry": { "type": "Point", "coordinates": [ -78.38258, 38.4904, 0.0 ] } },
{ "type": "Feature", "properties": { "Name": "Fire Detection Centroid ", "Description": "<b>Latitude: <\/b> 38.49111<br\/>  <b>Longitude: <\/b> -78.39521<br\/>  <b>Detection Time: <\/b> 2023-11-07 16:58 UTC<br\/>  <b>Sensor: <\/b> NOAA-20 VIIRS<br\/> <b>Confidence: <\/b> Nominal<br\/>  <b>Day\/Night: <\/b> Day<br\/> <b>Scan: <\/b> 0.8 km<br\/> <b>Track: <\/b> 0.8 km<br\/> <b>FRP: <\/b> 18.76 MW<br\/> <b>Brightness: <\/b> 353.21 K" }, "geometry": { "type": "Point", "coordinates": [ -78.39521, 38.49111, 0.0 ] } },
{ "type": "Feature", "properties": { "Name": "Fire Detection Centroid ", "Description": "<b>Latitude: <\/b> 38.49327<br\/>  <b>Longitude: <\/b> -78.38873<br\/>  <b>Detection Time: <\/b> 2023-11-07 16:58 UTC<br\/>  <b>Sensor: <\/b> NOAA-20 VIIRS<br\/> <b>Confidence: <\/b> Nominal<br\/>  <b>Day\/Night: <\/b> Day<br\/> <b>Scan: <\/b> 0.8 km<br\/> <b>Track: <\/b> 0.8 km<br\/> <b>FRP: <\/b> 18.76 MW<br\/> <b>Brightness: <\/b> 353.77 K" }, "geometry": { "type": "Point", "coordinates": [ -78.38873, 38.49327, 0.0 ] } },
{ "type": "Feature", "properties": { "Name": "Fire Detection Centroid ", "Description": "<b>Latitude: <\/b> 38.48846<br\/>  <b>Longitude: <\/b> -78.3885<br\/>  <b>Detection Time: <\/b> 2023-11-07 16:58 UTC<br\/>  <b>Sensor: <\/b> NOAA-20 VIIRS<br\/> <b>Confidence: <\/b> Nominal<br\/>  <b>Day\/Night: <\/b> Day<br\/> <b>Scan: <\/b> 0.8 km<br\/> <b>Track: <\/b> 0.8 km<br\/> <b>FRP: <\/b> 7.73 MW<br\/> <b>Brightness: <\/b> 325.25 K" }, "geometry": { "type": "Point", "coordinates": [ -78.3885, 38.48846, 0.0 ] } }
]
}
