{
"type": "FeatureCollection",
"crs": { "type": "name", "properties": { "name": "urn:ogc:def:crs:OGC:1.3:CRS84" } },
"features": [
{ "type": "Feature", "properties": { "Name": "Fire Detection Centroid ", "Description": "<b>Latitude: <\/b> 19.40032<br\/>  <b>Longitude: <\/b> -155.28514<br\/>  <b>Detection Time: <\/b> 2023-02-09 23:18 UTC<br\/>  <b>Sensor: <\/b> NOAA-20 VIIRS<br\/> <b>Confidence: <\/b> Nominal<br\/>  <b>Day\/Night: <\/b> Day<br\/> <b>Scan: <\/b> 0.49 km<br\/> <b>Track: <\/b> 0.4 km<br\/> <b>FRP: <\/b> 4.85 MW<br\/> <b>Brightness: <\/b> 325.83 K" }, "geometry": { "type": "Point", "coordinates": [ -155.28514, 19.40032, 0.0 ] } }
]
}
