{
"type": "FeatureCollection",
"crs": { "type": "name", "properties": { "name": "urn:ogc:def:crs:OGC:1.3:CRS84" } },
"features": [
{ "type": "Feature", "properties": { "Name": "Fire Detection Centroid ", "Description": "<b>Latitude: <\/b> 18.92794<br\/>  <b>Longitude: <\/b> -70.35464<br\/>  <b>Detection Time: <\/b> 2022-10-18 06:00 UTC<br\/>  <b>Sensor: <\/b> NOAA-20 VIIRS<br\/> <b>Confidence: <\/b> Nominal<br\/>  <b>Day\/Night: <\/b> Night<br\/> <b>Scan: <\/b> 0.5 km<br\/> <b>Track: <\/b> 0.4 km<br\/> <b>FRP: <\/b> 30.86 MW<br\/> <b>Brightness: <\/b> 336.4 K" }, "geometry": { "type": "Point", "coordinates": [ -70.35464, 18.92794, 0.0 ] } },
{ "type": "Feature", "properties": { "Name": "Fire Detection Centroid ", "Description": "<b>Latitude: <\/b> 18.0074<br\/>  <b>Longitude: <\/b> -66.65675<br\/>  <b>Detection Time: <\/b> 2022-10-18 06:00 UTC<br\/>  <b>Sensor: <\/b> NOAA-20 VIIRS<br\/> <b>Confidence: <\/b> Nominal<br\/>  <b>Day\/Night: <\/b> Night<br\/> <b>Scan: <\/b> 0.4 km<br\/> <b>Track: <\/b> 0.4 km<br\/> <b>FRP: <\/b> 0.46 MW<br\/> <b>Brightness: <\/b> 304.62 K" }, "geometry": { "type": "Point", "coordinates": [ -66.65675, 18.0074, 0.0 ] } },
{ "type": "Feature", "properties": { "Name": "Fire Detection Centroid ", "Description": "<b>Latitude: <\/b> 36.36104<br\/>  <b>Longitude: <\/b> -76.80986<br\/>  <b>Detection Time: <\/b> 2022-10-18 05:55 UTC<br\/>  <b>Sensor: <\/b> NOAA-20 VIIRS<br\/> <b>Confidence: <\/b> Nominal<br\/>  <b>Day\/Night: <\/b> Night<br\/> <b>Scan: <\/b> 0.7 km<br\/> <b>Track: <\/b> 0.7 km<br\/> <b>FRP: <\/b> 1.3 MW<br\/> <b>Brightness: <\/b> 303.76 K" }, "geometry": { "type": "Point", "coordinates": [ -76.80986, 36.36104, 0.0 ] } },
{ "type": "Feature", "properties": { "Name": "Fire Detection Centroid ", "Description": "<b>Latitude: <\/b> 36.35427<br\/>  <b>Longitude: <\/b> -76.81009<br\/>  <b>Detection Time: <\/b> 2022-10-18 05:55 UTC<br\/>  <b>Sensor: <\/b> NOAA-20 VIIRS<br\/> <b>Confidence: <\/b> Nominal<br\/>  <b>Day\/Night: <\/b> Night<br\/> <b>Scan: <\/b> 0.7 km<br\/> <b>Track: <\/b> 0.7 km<br\/> <b>FRP: <\/b> 2.48 MW<br\/> <b>Brightness: <\/b> 318.83 K" }, "geometry": { "type": "Point", "coordinates": [ -76.81009, 36.35427, 0.0 ] } }
]
}
