{
"type": "FeatureCollection",
"crs": { "type": "name", "properties": { "name": "urn:ogc:def:crs:OGC:1.3:CRS84" } },
"features": [
{ "type": "Feature", "properties": { "Name": "Fire Detection Centroid ", "Description": "<b>Latitude: <\/b> 19.40415<br\/>  <b>Longitude: <\/b> -155.28522<br\/>  <b>Detection Time: <\/b> 2022-11-10 23:26 UTC<br\/>  <b>Sensor: <\/b> NOAA-20 VIIRS<br\/> <b>Confidence: <\/b> High<br\/>  <b>Day\/Night: <\/b> Day<br\/> <b>Scan: <\/b> 0.42 km<br\/> <b>Track: <\/b> 0.37 km<br\/> <b>FRP: <\/b> 71.92 MW<br\/> <b>Brightness: <\/b> 367 K" }, "geometry": { "type": "Point", "coordinates": [ -155.28522, 19.40415, 0.0 ] } },
{ "type": "Feature", "properties": { "Name": "Fire Detection Centroid ", "Description": "<b>Latitude: <\/b> 19.40756<br\/>  <b>Longitude: <\/b> -155.2858<br\/>  <b>Detection Time: <\/b> 2022-11-10 23:26 UTC<br\/>  <b>Sensor: <\/b> NOAA-20 VIIRS<br\/> <b>Confidence: <\/b> Nominal<br\/>  <b>Day\/Night: <\/b> Day<br\/> <b>Scan: <\/b> 0.42 km<br\/> <b>Track: <\/b> 0.37 km<br\/> <b>FRP: <\/b> 71.92 MW<br\/> <b>Brightness: <\/b> 353.21 K" }, "geometry": { "type": "Point", "coordinates": [ -155.2858, 19.40756, 0.0 ] } },
{ "type": "Feature", "properties": { "Name": "Fire Detection Centroid ", "Description": "<b>Latitude: <\/b> 19.40479<br\/>  <b>Longitude: <\/b> -155.28131<br\/>  <b>Detection Time: <\/b> 2022-11-10 23:26 UTC<br\/>  <b>Sensor: <\/b> NOAA-20 VIIRS<br\/> <b>Confidence: <\/b> Nominal<br\/>  <b>Day\/Night: <\/b> Day<br\/> <b>Scan: <\/b> 0.42 km<br\/> <b>Track: <\/b> 0.37 km<br\/> <b>FRP: <\/b> 71.92 MW<br\/> <b>Brightness: <\/b> 345.71 K" }, "geometry": { "type": "Point", "coordinates": [ -155.28131, 19.40479, 0.0 ] } },
{ "type": "Feature", "properties": { "Name": "Fire Detection Centroid ", "Description": "<b>Latitude: <\/b> 19.40434<br\/>  <b>Longitude: <\/b> -155.28171<br\/>  <b>Detection Time: <\/b> 2022-11-10 23:25 UTC<br\/>  <b>Sensor: <\/b> NOAA-20 VIIRS<br\/> <b>Confidence: <\/b> Nominal<br\/>  <b>Day\/Night: <\/b> Day<br\/> <b>Scan: <\/b> 0.4 km<br\/> <b>Track: <\/b> 0.4 km<br\/> <b>FRP: <\/b> 71.91 MW<br\/> <b>Brightness: <\/b> 345.71 K" }, "geometry": { "type": "Point", "coordinates": [ -155.28171, 19.40434, 0.0 ] } },
{ "type": "Feature", "properties": { "Name": "Fire Detection Centroid ", "Description": "<b>Latitude: <\/b> 19.40711<br\/>  <b>Longitude: <\/b> -155.28624<br\/>  <b>Detection Time: <\/b> 2022-11-10 23:25 UTC<br\/>  <b>Sensor: <\/b> NOAA-20 VIIRS<br\/> <b>Confidence: <\/b> Nominal<br\/>  <b>Day\/Night: <\/b> Day<br\/> <b>Scan: <\/b> 0.4 km<br\/> <b>Track: <\/b> 0.4 km<br\/> <b>FRP: <\/b> 71.91 MW<br\/> <b>Brightness: <\/b> 353.21 K" }, "geometry": { "type": "Point", "coordinates": [ -155.28624, 19.40711, 0.0 ] } },
{ "type": "Feature", "properties": { "Name": "Fire Detection Centroid ", "Description": "<b>Latitude: <\/b> 19.40371<br\/>  <b>Longitude: <\/b> -155.28563<br\/>  <b>Detection Time: <\/b> 2022-11-10 23:25 UTC<br\/>  <b>Sensor: <\/b> NOAA-20 VIIRS<br\/> <b>Confidence: <\/b> High<br\/>  <b>Day\/Night: <\/b> Day<br\/> <b>Scan: <\/b> 0.4 km<br\/> <b>Track: <\/b> 0.4 km<br\/> <b>FRP: <\/b> 71.91 MW<br\/> <b>Brightness: <\/b> 367 K" }, "geometry": { "type": "Point", "coordinates": [ -155.28563, 19.40371, 0.0 ] } }
]
}
