{
"type": "FeatureCollection",
"crs": { "type": "name", "properties": { "name": "urn:ogc:def:crs:OGC:1.3:CRS84" } },
"features": [
{ "type": "Feature", "properties": { "Name": "Fire Detection Centroid ", "Description": "<b>Latitude: <\/b> 19.74659<br\/>  <b>Longitude: <\/b> -156.03387<br\/>  <b>Detection Time: <\/b> 2024-05-31 23:51 UTC<br\/>  <b>Sensor: <\/b> NOAA-20 VIIRS<br\/> <b>Confidence: <\/b> Nominal<br\/>  <b>Day\/Night: <\/b> Day<br\/> <b>Scan: <\/b> 0.5 km<br\/> <b>Track: <\/b> 0.4 km<br\/> <b>FRP: <\/b> 7.4 MW<br\/> <b>Brightness: <\/b> 333.63 K" }, "geometry": { "type": "Point", "coordinates": [ -156.03387, 19.74659, 0.0 ] } },
{ "type": "Feature", "properties": { "Name": "Fire Detection Centroid ", "Description": "<b>Latitude: <\/b> 19.7471<br\/>  <b>Longitude: <\/b> -156.03531<br\/>  <b>Detection Time: <\/b> 2024-05-31 23:51 UTC<br\/>  <b>Sensor: <\/b> NOAA-20 VIIRS<br\/> <b>Confidence: <\/b> Nominal<br\/>  <b>Day\/Night: <\/b> Day<br\/> <b>Scan: <\/b> 0.5 km<br\/> <b>Track: <\/b> 0.4 km<br\/> <b>FRP: <\/b> 3.27 MW<br\/> <b>Brightness: <\/b> 332.75 K" }, "geometry": { "type": "Point", "coordinates": [ -156.03531, 19.7471, 0.0 ] } },
{ "type": "Feature", "properties": { "Name": "Fire Detection Centroid ", "Description": "<b>Latitude: <\/b> 19.7471<br\/>  <b>Longitude: <\/b> -156.03532<br\/>  <b>Detection Time: <\/b> 2024-05-31 23:50 UTC<br\/>  <b>Sensor: <\/b> NOAA-20 VIIRS<br\/> <b>Confidence: <\/b> Nominal<br\/>  <b>Day\/Night: <\/b> Day<br\/> <b>Scan: <\/b> 0.48 km<br\/> <b>Track: <\/b> 0.4 km<br\/> <b>FRP: <\/b> 3.95 MW<br\/> <b>Brightness: <\/b> 332.75 K" }, "geometry": { "type": "Point", "coordinates": [ -156.03532, 19.7471, 0.0 ] } },
{ "type": "Feature", "properties": { "Name": "Fire Detection Centroid ", "Description": "<b>Latitude: <\/b> 19.74659<br\/>  <b>Longitude: <\/b> -156.03389<br\/>  <b>Detection Time: <\/b> 2024-05-31 23:50 UTC<br\/>  <b>Sensor: <\/b> NOAA-20 VIIRS<br\/> <b>Confidence: <\/b> Nominal<br\/>  <b>Day\/Night: <\/b> Day<br\/> <b>Scan: <\/b> 0.48 km<br\/> <b>Track: <\/b> 0.4 km<br\/> <b>FRP: <\/b> 8.08 MW<br\/> <b>Brightness: <\/b> 333.63 K" }, "geometry": { "type": "Point", "coordinates": [ -156.03389, 19.74659, 0.0 ] } }
]
}
