{
"type": "FeatureCollection",
"crs": { "type": "name", "properties": { "name": "urn:ogc:def:crs:OGC:1.3:CRS84" } },
"features": [
{ "type": "Feature", "properties": { "Name": "Fire Detection Centroid ", "Description": "<b>Latitude: <\/b> 48.18882<br\/>  <b>Longitude: <\/b> -64.92136<br\/>  <b>Detection Time: <\/b> 2022-09-18 05:14 UTC<br\/>  <b>Sensor: <\/b> NOAA-20 VIIRS<br\/> <b>Confidence: <\/b> Nominal<br\/>  <b>Day\/Night: <\/b> Night<br\/> <b>Scan: <\/b> 0.6 km<br\/> <b>Track: <\/b> 0.7 km<br\/> <b>FRP: <\/b> 1.23 MW<br\/> <b>Brightness: <\/b> 297.03 K" }, "geometry": { "type": "Point", "coordinates": [ -64.92136, 48.18882, 0.0 ] } }
]
}
