{
"type": "FeatureCollection",
"crs": { "type": "name", "properties": { "name": "urn:ogc:def:crs:OGC:1.3:CRS84" } },
"features": [
{ "type": "Feature", "properties": { "Name": "Fire Detection Centroid ", "Description": "<b>Latitude: <\/b> 19.59535<br\/>  <b>Longitude: <\/b> -155.50319<br\/>  <b>Detection Time: <\/b> 2023-03-14 11:49 UTC<br\/>  <b>Sensor: <\/b> NOAA-20 VIIRS<br\/> <b>Confidence: <\/b> Nominal<br\/>  <b>Day\/Night: <\/b> Night<br\/> <b>Scan: <\/b> 0.43 km<br\/> <b>Track: <\/b> 0.38 km<br\/> <b>FRP: <\/b> 2.73 MW<br\/> <b>Brightness: <\/b> 298.17 K" }, "geometry": { "type": "Point", "coordinates": [ -155.50319, 19.59535, 0.0 ] } },
{ "type": "Feature", "properties": { "Name": "Fire Detection Centroid ", "Description": "<b>Latitude: <\/b> 19.40744<br\/>  <b>Longitude: <\/b> -155.28371<br\/>  <b>Detection Time: <\/b> 2023-03-14 11:49 UTC<br\/>  <b>Sensor: <\/b> NOAA-20 VIIRS<br\/> <b>Confidence: <\/b> Nominal<br\/>  <b>Day\/Night: <\/b> Night<br\/> <b>Scan: <\/b> 0.42 km<br\/> <b>Track: <\/b> 0.38 km<br\/> <b>FRP: <\/b> 1.08 MW<br\/> <b>Brightness: <\/b> 301.14 K" }, "geometry": { "type": "Point", "coordinates": [ -155.28371, 19.40744, 0.0 ] } },
{ "type": "Feature", "properties": { "Name": "Fire Detection Centroid ", "Description": "<b>Latitude: <\/b> 19.40686<br\/>  <b>Longitude: <\/b> -155.27972<br\/>  <b>Detection Time: <\/b> 2023-03-14 11:49 UTC<br\/>  <b>Sensor: <\/b> NOAA-20 VIIRS<br\/> <b>Confidence: <\/b> Nominal<br\/>  <b>Day\/Night: <\/b> Night<br\/> <b>Scan: <\/b> 0.42 km<br\/> <b>Track: <\/b> 0.38 km<br\/> <b>FRP: <\/b> 1.08 MW<br\/> <b>Brightness: <\/b> 301.85 K" }, "geometry": { "type": "Point", "coordinates": [ -155.27972, 19.40686, 0.0 ] } },
{ "type": "Feature", "properties": { "Name": "Fire Detection Centroid ", "Description": "<b>Latitude: <\/b> 19.40399<br\/>  <b>Longitude: <\/b> -155.28429<br\/>  <b>Detection Time: <\/b> 2023-03-14 11:49 UTC<br\/>  <b>Sensor: <\/b> NOAA-20 VIIRS<br\/> <b>Confidence: <\/b> Nominal<br\/>  <b>Day\/Night: <\/b> Night<br\/> <b>Scan: <\/b> 0.42 km<br\/> <b>Track: <\/b> 0.38 km<br\/> <b>FRP: <\/b> 1.08 MW<br\/> <b>Brightness: <\/b> 300.94 K" }, "geometry": { "type": "Point", "coordinates": [ -155.28429, 19.40399, 0.0 ] } }
]
}
