{
"type": "FeatureCollection",
"crs": { "type": "name", "properties": { "name": "urn:ogc:def:crs:OGC:1.3:CRS84" } },
"features": [
{ "type": "Feature", "properties": { "Name": "Fire Detection Centroid ", "Description": "<b>Latitude: <\/b> 45.52485<br\/>  <b>Longitude: <\/b> -122.26852<br\/>  <b>Detection Time: <\/b> 2024-05-26 22:10 UTC<br\/>  <b>Sensor: <\/b> NOAA-20 VIIRS<br\/> <b>Confidence: <\/b> Nominal<br\/>  <b>Day\/Night: <\/b> Day<br\/> <b>Scan: <\/b> 0.67 km<br\/> <b>Track: <\/b> 0.73 km<br\/> <b>FRP: <\/b> 5.19 MW<br\/> <b>Brightness: <\/b> 328.06 K" }, "geometry": { "type": "Point", "coordinates": [ -122.26852, 45.52485, 0.0 ] } }
]
}
