{
"type": "FeatureCollection",
"crs": { "type": "name", "properties": { "name": "urn:ogc:def:crs:OGC:1.3:CRS84" } },
"features": [
{ "type": "Feature", "properties": { "Name": "Fire Detection Centroid ", "Description": "<b>Latitude: <\/b> 45.23058<br\/>  <b>Longitude: <\/b> -123.16932<br\/>  <b>Detection Time: <\/b> 2024-03-06 11:27 UTC<br\/>  <b>Sensor: <\/b> NOAA-20 VIIRS<br\/> <b>Confidence: <\/b> Nominal<br\/>  <b>Day\/Night: <\/b> Night<br\/> <b>Scan: <\/b> 0.66 km<br\/> <b>Track: <\/b> 0.73 km<br\/> <b>FRP: <\/b> 1.23 MW<br\/> <b>Brightness: <\/b> 300.32 K" }, "geometry": { "type": "Point", "coordinates": [ -123.16932, 45.23058, 0.0 ] } },
{ "type": "Feature", "properties": { "Name": "Fire Detection Centroid ", "Description": "<b>Latitude: <\/b> 47.4677<br\/>  <b>Longitude: <\/b> -122.05145<br\/>  <b>Detection Time: <\/b> 2024-03-06 11:27 UTC<br\/>  <b>Sensor: <\/b> NOAA-20 VIIRS<br\/> <b>Confidence: <\/b> Nominal<br\/>  <b>Day\/Night: <\/b> Night<br\/> <b>Scan: <\/b> 0.61 km<br\/> <b>Track: <\/b> 0.71 km<br\/> <b>FRP: <\/b> 0.89 MW<br\/> <b>Brightness: <\/b> 295.39 K" }, "geometry": { "type": "Point", "coordinates": [ -122.05145, 47.4677, 0.0 ] } },
{ "type": "Feature", "properties": { "Name": "Fire Detection Centroid ", "Description": "<b>Latitude: <\/b> 47.46932<br\/>  <b>Longitude: <\/b> -122.05367<br\/>  <b>Detection Time: <\/b> 2024-03-06 11:27 UTC<br\/>  <b>Sensor: <\/b> NOAA-20 VIIRS<br\/> <b>Confidence: <\/b> Nominal<br\/>  <b>Day\/Night: <\/b> Night<br\/> <b>Scan: <\/b> 0.61 km<br\/> <b>Track: <\/b> 0.71 km<br\/> <b>FRP: <\/b> 0.92 MW<br\/> <b>Brightness: <\/b> 298.9 K" }, "geometry": { "type": "Point", "coordinates": [ -122.05367, 47.46932, 0.0 ] } },
{ "type": "Feature", "properties": { "Name": "Fire Detection Centroid ", "Description": "<b>Latitude: <\/b> 48.43571<br\/>  <b>Longitude: <\/b> -119.5144<br\/>  <b>Detection Time: <\/b> 2024-03-06 11:25 UTC<br\/>  <b>Sensor: <\/b> NOAA-20 VIIRS<br\/> <b>Confidence: <\/b> Nominal<br\/>  <b>Day\/Night: <\/b> Night<br\/> <b>Scan: <\/b> 0.72 km<br\/> <b>Track: <\/b> 0.75 km<br\/> <b>FRP: <\/b> 1.11 MW<br\/> <b>Brightness: <\/b> 299.11 K" }, "geometry": { "type": "Point", "coordinates": [ -119.5144, 48.43571, 0.0 ] } }
]
}
