{
"type": "FeatureCollection",
"crs": { "type": "name", "properties": { "name": "urn:ogc:def:crs:OGC:1.3:CRS84" } },
"features": [
{ "type": "Feature", "properties": { "Name": "Fire Detection Centroid ", "Description": "<b>Latitude: <\/b> 45.0946<br\/>  <b>Longitude: <\/b> -73.94027<br\/>  <b>Detection Time: <\/b> 2023-05-21 16:48 UTC<br\/>  <b>Sensor: <\/b> NOAA-20 VIIRS<br\/> <b>Confidence: <\/b> Nominal<br\/>  <b>Day\/Night: <\/b> Day<br\/> <b>Scan: <\/b> 0.4 km<br\/> <b>Track: <\/b> 0.6 km<br\/> <b>FRP: <\/b> 3.26 MW<br\/> <b>Brightness: <\/b> 332.79 K" }, "geometry": { "type": "Point", "coordinates": [ -73.94027, 45.0946, 0.0 ] } },
{ "type": "Feature", "properties": { "Name": "Fire Detection Centroid ", "Description": "<b>Latitude: <\/b> 45.8378<br\/>  <b>Longitude: <\/b> -73.2476<br\/>  <b>Detection Time: <\/b> 2023-05-21 16:48 UTC<br\/>  <b>Sensor: <\/b> NOAA-20 VIIRS<br\/> <b>Confidence: <\/b> Nominal<br\/>  <b>Day\/Night: <\/b> Day<br\/> <b>Scan: <\/b> 0.4 km<br\/> <b>Track: <\/b> 0.6 km<br\/> <b>FRP: <\/b> 4.13 MW<br\/> <b>Brightness: <\/b> 329.36 K" }, "geometry": { "type": "Point", "coordinates": [ -73.2476, 45.8378, 0.0 ] } },
{ "type": "Feature", "properties": { "Name": "Fire Detection Centroid ", "Description": "<b>Latitude: <\/b> 42.54241<br\/>  <b>Longitude: <\/b> -71.59369<br\/>  <b>Detection Time: <\/b> 2023-05-21 16:47 UTC<br\/>  <b>Sensor: <\/b> NOAA-20 VIIRS<br\/> <b>Confidence: <\/b> Nominal<br\/>  <b>Day\/Night: <\/b> Day<br\/> <b>Scan: <\/b> 0.4 km<br\/> <b>Track: <\/b> 0.6 km<br\/> <b>FRP: <\/b> 4.89 MW<br\/> <b>Brightness: <\/b> 325.44 K" }, "geometry": { "type": "Point", "coordinates": [ -71.59369, 42.54241, 0.0 ] } }
]
}
