{
"type": "FeatureCollection",
"crs": { "type": "name", "properties": { "name": "urn:ogc:def:crs:OGC:1.3:CRS84" } },
"features": [
{ "type": "Feature", "properties": { "Name": "Fire Detection Centroid ", "Description": "<b>Latitude: <\/b> 34.61069<br\/>  <b>Longitude: <\/b> -117.33958<br\/>  <b>Detection Time: <\/b> 2023-05-04 10:47 UTC<br\/>  <b>Sensor: <\/b> NOAA-20 VIIRS<br\/> <b>Confidence: <\/b> Nominal<br\/>  <b>Day\/Night: <\/b> Night<br\/> <b>Scan: <\/b> 0.79 km<br\/> <b>Track: <\/b> 0.78 km<br\/> <b>FRP: <\/b> 2.4 MW<br\/> <b>Brightness: <\/b> 296.54 K" }, "geometry": { "type": "Point", "coordinates": [ -117.33958, 34.61069, 0.0 ] } },
{ "type": "Feature", "properties": { "Name": "Fire Detection Centroid ", "Description": "<b>Latitude: <\/b> 38.01854<br\/>  <b>Longitude: <\/b> -122.1132<br\/>  <b>Detection Time: <\/b> 2023-05-04 10:45 UTC<br\/>  <b>Sensor: <\/b> NOAA-20 VIIRS<br\/> <b>Confidence: <\/b> Nominal<br\/>  <b>Day\/Night: <\/b> Night<br\/> <b>Scan: <\/b> 0.36 km<br\/> <b>Track: <\/b> 0.57 km<br\/> <b>FRP: <\/b> 1.16 MW<br\/> <b>Brightness: <\/b> 295.4 K" }, "geometry": { "type": "Point", "coordinates": [ -122.1132, 38.01854, 0.0 ] } },
{ "type": "Feature", "properties": { "Name": "Fire Detection Centroid ", "Description": "<b>Latitude: <\/b> 38.06985<br\/>  <b>Longitude: <\/b> -122.13915<br\/>  <b>Detection Time: <\/b> 2023-05-04 10:45 UTC<br\/>  <b>Sensor: <\/b> NOAA-20 VIIRS<br\/> <b>Confidence: <\/b> Nominal<br\/>  <b>Day\/Night: <\/b> Night<br\/> <b>Scan: <\/b> 0.35 km<br\/> <b>Track: <\/b> 0.57 km<br\/> <b>FRP: <\/b> 0.7 MW<br\/> <b>Brightness: <\/b> 297.86 K" }, "geometry": { "type": "Point", "coordinates": [ -122.13915, 38.06985, 0.0 ] } },
{ "type": "Feature", "properties": { "Name": "Fire Detection Centroid ", "Description": "<b>Latitude: <\/b> 48.38577<br\/>  <b>Longitude: <\/b> -116.27176<br\/>  <b>Detection Time: <\/b> 2023-05-04 10:43 UTC<br\/>  <b>Sensor: <\/b> NOAA-20 VIIRS<br\/> <b>Confidence: <\/b> Nominal<br\/>  <b>Day\/Night: <\/b> Night<br\/> <b>Scan: <\/b> 0.34 km<br\/> <b>Track: <\/b> 0.56 km<br\/> <b>FRP: <\/b> 1.19 MW<br\/> <b>Brightness: <\/b> 309.86 K" }, "geometry": { "type": "Point", "coordinates": [ -116.27176, 48.38577, 0.0 ] } },
{ "type": "Feature", "properties": { "Name": "Fire Detection Centroid ", "Description": "<b>Latitude: <\/b> 45.64389<br\/>  <b>Longitude: <\/b> -116.09017<br\/>  <b>Detection Time: <\/b> 2023-05-04 10:43 UTC<br\/>  <b>Sensor: <\/b> NOAA-20 VIIRS<br\/> <b>Confidence: <\/b> Nominal<br\/>  <b>Day\/Night: <\/b> Night<br\/> <b>Scan: <\/b> 0.43 km<br\/> <b>Track: <\/b> 0.62 km<br\/> <b>FRP: <\/b> 0.71 MW<br\/> <b>Brightness: <\/b> 295.36 K" }, "geometry": { "type": "Point", "coordinates": [ -116.09017, 45.64389, 0.0 ] } },
{ "type": "Feature", "properties": { "Name": "Fire Detection Centroid ", "Description": "<b>Latitude: <\/b> 48.30048<br\/>  <b>Longitude: <\/b> -116.95718<br\/>  <b>Detection Time: <\/b> 2023-05-04 10:43 UTC<br\/>  <b>Sensor: <\/b> NOAA-20 VIIRS<br\/> <b>Confidence: <\/b> Nominal<br\/>  <b>Day\/Night: <\/b> Night<br\/> <b>Scan: <\/b> 0.32 km<br\/> <b>Track: <\/b> 0.55 km<br\/> <b>FRP: <\/b> 0.6 MW<br\/> <b>Brightness: <\/b> 295.75 K" }, "geometry": { "type": "Point", "coordinates": [ -116.95718, 48.30048, 0.0 ] } },
{ "type": "Feature", "properties": { "Name": "Fire Detection Centroid ", "Description": "<b>Latitude: <\/b> 47.56932<br\/>  <b>Longitude: <\/b> -122.34175<br\/>  <b>Detection Time: <\/b> 2023-05-04 10:43 UTC<br\/>  <b>Sensor: <\/b> NOAA-20 VIIRS<br\/> <b>Confidence: <\/b> Nominal<br\/>  <b>Day\/Night: <\/b> Night<br\/> <b>Scan: <\/b> 0.4 km<br\/> <b>Track: <\/b> 0.44 km<br\/> <b>FRP: <\/b> 0.84 MW<br\/> <b>Brightness: <\/b> 300.46 K" }, "geometry": { "type": "Point", "coordinates": [ -122.34175, 47.56932, 0.0 ] } }
]
}
