{
"type": "FeatureCollection",
"crs": { "type": "name", "properties": { "name": "urn:ogc:def:crs:OGC:1.3:CRS84" } },
"features": [
{ "type": "Feature", "properties": { "Name": "Fire Detection Centroid ", "Description": "<b>Latitude: <\/b> 18.84464<br\/>  <b>Longitude: <\/b> -71.36815<br\/>  <b>Detection Time: <\/b> 2024-01-19 17:24 UTC<br\/>  <b>Sensor: <\/b> NOAA-20 VIIRS<br\/> <b>Confidence: <\/b> Nominal<br\/>  <b>Day\/Night: <\/b> Day<br\/> <b>Scan: <\/b> 0.3 km<br\/> <b>Track: <\/b> 0.6 km<br\/> <b>FRP: <\/b> 1.55 MW<br\/> <b>Brightness: <\/b> 329.93 K" }, "geometry": { "type": "Point", "coordinates": [ -71.36815, 18.84464, 0.0 ] } },
{ "type": "Feature", "properties": { "Name": "Fire Detection Centroid ", "Description": "<b>Latitude: <\/b> 18.8072<br\/>  <b>Longitude: <\/b> -72.11208<br\/>  <b>Detection Time: <\/b> 2024-01-19 17:24 UTC<br\/>  <b>Sensor: <\/b> NOAA-20 VIIRS<br\/> <b>Confidence: <\/b> Nominal<br\/>  <b>Day\/Night: <\/b> Day<br\/> <b>Scan: <\/b> 0.4 km<br\/> <b>Track: <\/b> 0.6 km<br\/> <b>FRP: <\/b> 2.09 MW<br\/> <b>Brightness: <\/b> 330.18 K" }, "geometry": { "type": "Point", "coordinates": [ -72.11208, 18.8072, 0.0 ] } },
{ "type": "Feature", "properties": { "Name": "Fire Detection Centroid ", "Description": "<b>Latitude: <\/b> 18.65883<br\/>  <b>Longitude: <\/b> -70.98036<br\/>  <b>Detection Time: <\/b> 2024-01-19 17:24 UTC<br\/>  <b>Sensor: <\/b> NOAA-20 VIIRS<br\/> <b>Confidence: <\/b> Nominal<br\/>  <b>Day\/Night: <\/b> Day<br\/> <b>Scan: <\/b> 0.6 km<br\/> <b>Track: <\/b> 0.5 km<br\/> <b>FRP: <\/b> 4.01 MW<br\/> <b>Brightness: <\/b> 328.81 K" }, "geometry": { "type": "Point", "coordinates": [ -70.98036, 18.65883, 0.0 ] } },
{ "type": "Feature", "properties": { "Name": "Fire Detection Centroid ", "Description": "<b>Latitude: <\/b> 18.38542<br\/>  <b>Longitude: <\/b> -69.1145<br\/>  <b>Detection Time: <\/b> 2024-01-19 17:23 UTC<br\/>  <b>Sensor: <\/b> NOAA-20 VIIRS<br\/> <b>Confidence: <\/b> Nominal<br\/>  <b>Day\/Night: <\/b> Day<br\/> <b>Scan: <\/b> 0.5 km<br\/> <b>Track: <\/b> 0.5 km<br\/> <b>FRP: <\/b> 3.69 MW<br\/> <b>Brightness: <\/b> 331.27 K" }, "geometry": { "type": "Point", "coordinates": [ -69.1145, 18.38542, 0.0 ] } }
]
}
