{
"type": "FeatureCollection",
"crs": { "type": "name", "properties": { "name": "urn:ogc:def:crs:OGC:1.3:CRS84" } },
"features": [
{ "type": "Feature", "properties": { "Name": "Fire Detection Centroid ", "Description": "<b>Latitude: <\/b> 18.92529<br\/>  <b>Longitude: <\/b> -70.35288<br\/>  <b>Detection Time: <\/b> 2023-07-02 05:42 UTC<br\/>  <b>Sensor: <\/b> NOAA-20 VIIRS<br\/> <b>Confidence: <\/b> Nominal<br\/>  <b>Day\/Night: <\/b> Night<br\/> <b>Scan: <\/b> 0.3 km<br\/> <b>Track: <\/b> 0.6 km<br\/> <b>FRP: <\/b> 2.76 MW<br\/> <b>Brightness: <\/b> 328.2 K" }, "geometry": { "type": "Point", "coordinates": [ -70.35288, 18.92529, 0.0 ] } },
{ "type": "Feature", "properties": { "Name": "Fire Detection Centroid ", "Description": "<b>Latitude: <\/b> 18.9306<br\/>  <b>Longitude: <\/b> -70.35297<br\/>  <b>Detection Time: <\/b> 2023-07-02 05:42 UTC<br\/>  <b>Sensor: <\/b> NOAA-20 VIIRS<br\/> <b>Confidence: <\/b> Nominal<br\/>  <b>Day\/Night: <\/b> Night<br\/> <b>Scan: <\/b> 0.3 km<br\/> <b>Track: <\/b> 0.6 km<br\/> <b>FRP: <\/b> 2.76 MW<br\/> <b>Brightness: <\/b> 333.68 K" }, "geometry": { "type": "Point", "coordinates": [ -70.35297, 18.9306, 0.0 ] } },
{ "type": "Feature", "properties": { "Name": "Fire Detection Centroid ", "Description": "<b>Latitude: <\/b> 48.18818<br\/>  <b>Longitude: <\/b> -64.92149<br\/>  <b>Detection Time: <\/b> 2023-07-02 05:34 UTC<br\/>  <b>Sensor: <\/b> NOAA-20 VIIRS<br\/> <b>Confidence: <\/b> Nominal<br\/>  <b>Day\/Night: <\/b> Night<br\/> <b>Scan: <\/b> 0.3 km<br\/> <b>Track: <\/b> 0.6 km<br\/> <b>FRP: <\/b> 0.46 MW<br\/> <b>Brightness: <\/b> 298.83 K" }, "geometry": { "type": "Point", "coordinates": [ -64.92149, 48.18818, 0.0 ] } }
]
}
