{
"type": "FeatureCollection",
"crs": { "type": "name", "properties": { "name": "urn:ogc:def:crs:OGC:1.3:CRS84" } },
"features": [
{ "type": "Feature", "properties": { "Name": "Fire Detection Centroid ", "Description": "<b>Latitude: <\/b> 47.57064<br\/>  <b>Longitude: <\/b> -122.3716<br\/>  <b>Detection Time: <\/b> 2023-04-11 11:17 UTC<br\/>  <b>Sensor: <\/b> NOAA-20 VIIRS<br\/> <b>Confidence: <\/b> Nominal<br\/>  <b>Day\/Night: <\/b> Night<br\/> <b>Scan: <\/b> 0.44 km<br\/> <b>Track: <\/b> 0.62 km<br\/> <b>FRP: <\/b> 1.1 MW<br\/> <b>Brightness: <\/b> 304.74 K" }, "geometry": { "type": "Point", "coordinates": [ -122.3716, 47.57064, 0.0 ] } }
]
}
