{
"type": "FeatureCollection",
"crs": { "type": "name", "properties": { "name": "urn:ogc:def:crs:OGC:1.3:CRS84" } },
"features": [
{ "type": "Feature", "properties": { "Name": "Fire Detection Centroid ", "Description": "<b>Latitude: <\/b> 38.60103<br\/>  <b>Longitude: <\/b> -120.50923<br\/>  <b>Detection Time: <\/b> 2023-04-08 21:55 UTC<br\/>  <b>Sensor: <\/b> NOAA-20 VIIRS<br\/> <b>Confidence: <\/b> Nominal<br\/>  <b>Day\/Night: <\/b> Day<br\/> <b>Scan: <\/b> 0.52 km<br\/> <b>Track: <\/b> 0.67 km<br\/> <b>FRP: <\/b> 10.15 MW<br\/> <b>Brightness: <\/b> 329.59 K" }, "geometry": { "type": "Point", "coordinates": [ -120.50923, 38.60103, 0.0 ] } },
{ "type": "Feature", "properties": { "Name": "Fire Detection Centroid ", "Description": "<b>Latitude: <\/b> 38.67214<br\/>  <b>Longitude: <\/b> -121.9838<br\/>  <b>Detection Time: <\/b> 2023-04-08 21:55 UTC<br\/>  <b>Sensor: <\/b> NOAA-20 VIIRS<br\/> <b>Confidence: <\/b> Nominal<br\/>  <b>Day\/Night: <\/b> Day<br\/> <b>Scan: <\/b> 0.43 km<br\/> <b>Track: <\/b> 0.62 km<br\/> <b>FRP: <\/b> 4.96 MW<br\/> <b>Brightness: <\/b> 345.39 K" }, "geometry": { "type": "Point", "coordinates": [ -121.9838, 38.67214, 0.0 ] } },
{ "type": "Feature", "properties": { "Name": "Fire Detection Centroid ", "Description": "<b>Latitude: <\/b> 38.60138<br\/>  <b>Longitude: <\/b> -120.49843<br\/>  <b>Detection Time: <\/b> 2023-04-08 21:55 UTC<br\/>  <b>Sensor: <\/b> NOAA-20 VIIRS<br\/> <b>Confidence: <\/b> Nominal<br\/>  <b>Day\/Night: <\/b> Day<br\/> <b>Scan: <\/b> 0.52 km<br\/> <b>Track: <\/b> 0.67 km<br\/> <b>FRP: <\/b> 7.08 MW<br\/> <b>Brightness: <\/b> 330.44 K" }, "geometry": { "type": "Point", "coordinates": [ -120.49843, 38.60138, 0.0 ] } }
]
}
