{
"type": "FeatureCollection",
"crs": { "type": "name", "properties": { "name": "urn:ogc:def:crs:OGC:1.3:CRS84" } },
"features": [
{ "type": "Feature", "properties": { "Name": "Fire Detection Centroid ", "Description": "<b>Latitude: <\/b> 19.58574<br\/>  <b>Longitude: <\/b> -155.50626<br\/>  <b>Detection Time: <\/b> 2023-03-10 11:23 UTC<br\/>  <b>Sensor: <\/b> NOAA-20 VIIRS<br\/> <b>Confidence: <\/b> Nominal<br\/>  <b>Day\/Night: <\/b> Night<br\/> <b>Scan: <\/b> 0.34 km<br\/> <b>Track: <\/b> 0.56 km<br\/> <b>FRP: <\/b> 1.51 MW<br\/> <b>Brightness: <\/b> 296.37 K" }, "geometry": { "type": "Point", "coordinates": [ -155.50626, 19.58574, 0.0 ] } },
{ "type": "Feature", "properties": { "Name": "Fire Detection Centroid ", "Description": "<b>Latitude: <\/b> 19.59613<br\/>  <b>Longitude: <\/b> -155.50639<br\/>  <b>Detection Time: <\/b> 2023-03-10 11:23 UTC<br\/>  <b>Sensor: <\/b> NOAA-20 VIIRS<br\/> <b>Confidence: <\/b> Nominal<br\/>  <b>Day\/Night: <\/b> Night<br\/> <b>Scan: <\/b> 0.34 km<br\/> <b>Track: <\/b> 0.56 km<br\/> <b>FRP: <\/b> 1.63 MW<br\/> <b>Brightness: <\/b> 295.57 K" }, "geometry": { "type": "Point", "coordinates": [ -155.50639, 19.59613, 0.0 ] } }
]
}
