{
"type": "FeatureCollection",
"crs": { "type": "name", "properties": { "name": "urn:ogc:def:crs:OGC:1.3:CRS84" } },
"features": [
{ "type": "Feature", "properties": { "Name": "Fire Detection Centroid ", "Description": "<b>Latitude: <\/b> 20.92014<br\/>  <b>Longitude: <\/b> -156.6797<br\/>  <b>Detection Time: <\/b> 2023-08-26 23:07 UTC<br\/>  <b>Sensor: <\/b> NOAA-20 VIIRS<br\/> <b>Confidence: <\/b> Nominal<br\/>  <b>Day\/Night: <\/b> Day<br\/> <b>Scan: <\/b> 0.55 km<br\/> <b>Track: <\/b> 0.51 km<br\/> <b>FRP: <\/b> 12.48 MW<br\/> <b>Brightness: <\/b> 342.06 K" }, "geometry": { "type": "Point", "coordinates": [ -156.6797, 20.92014, 0.0 ] } }
]
}
