{
"type": "FeatureCollection",
"crs": { "type": "name", "properties": { "name": "urn:ogc:def:crs:OGC:1.3:CRS84" } },
"features": [
{ "type": "Feature", "properties": { "Name": "Fire Detection Centroid ", "Description": "<b>Latitude: <\/b> 43.19632<br\/>  <b>Longitude: <\/b> -79.75256<br\/>  <b>Detection Time: <\/b> 2024-02-06 16:54 UTC<br\/>  <b>Sensor: <\/b> NOAA-20 VIIRS<br\/> <b>Confidence: <\/b> Nominal<br\/>  <b>Day\/Night: <\/b> Day<br\/> <b>Scan: <\/b> 0.8 km<br\/> <b>Track: <\/b> 0.8 km<br\/> <b>FRP: <\/b> 8.91 MW<br\/> <b>Brightness: <\/b> 326.72 K" }, "geometry": { "type": "Point", "coordinates": [ -79.75256, 43.19632, 0.0 ] } }
]
}
