{
"type": "FeatureCollection",
"crs": { "type": "name", "properties": { "name": "urn:ogc:def:crs:OGC:1.3:CRS84" } },
"features": [
{ "type": "Feature", "properties": { "Name": "Fire Detection Centroid ", "Description": "<b>Latitude: <\/b> 41.79377<br\/>  <b>Longitude: <\/b> -122.6468<br\/>  <b>Detection Time: <\/b> 2023-01-17 22:14 UTC<br\/>  <b>Sensor: <\/b> NOAA-20 VIIRS<br\/> <b>Confidence: <\/b> Nominal<br\/>  <b>Day\/Night: <\/b> Day<br\/> <b>Scan: <\/b> 0.73 km<br\/> <b>Track: <\/b> 0.76 km<br\/> <b>FRP: <\/b> 13.65 MW<br\/> <b>Brightness: <\/b> 351.61 K" }, "geometry": { "type": "Point", "coordinates": [ -122.6468, 41.79377, 0.0 ] } },
{ "type": "Feature", "properties": { "Name": "Fire Detection Centroid ", "Description": "<b>Latitude: <\/b> 41.79102<br\/>  <b>Longitude: <\/b> -122.65055<br\/>  <b>Detection Time: <\/b> 2023-01-17 22:14 UTC<br\/>  <b>Sensor: <\/b> NOAA-20 VIIRS<br\/> <b>Confidence: <\/b> Nominal<br\/>  <b>Day\/Night: <\/b> Day<br\/> <b>Scan: <\/b> 0.73 km<br\/> <b>Track: <\/b> 0.76 km<br\/> <b>FRP: <\/b> 16.35 MW<br\/> <b>Brightness: <\/b> 335.1 K" }, "geometry": { "type": "Point", "coordinates": [ -122.65055, 41.79102, 0.0 ] } }
]
}
