{
"type": "FeatureCollection",
"crs": { "type": "name", "properties": { "name": "urn:ogc:def:crs:OGC:1.3:CRS84" } },
"features": [
{ "type": "Feature", "properties": { "Name": "Fire Detection Centroid ", "Description": "<b>Latitude: <\/b> 19.63304<br\/>  <b>Longitude: <\/b> -71.6797<br\/>  <b>Detection Time: <\/b> 2022-12-06 05:41 UTC<br\/>  <b>Sensor: <\/b> NOAA-20 VIIRS<br\/> <b>Confidence: <\/b> Nominal<br\/>  <b>Day\/Night: <\/b> Night<br\/> <b>Scan: <\/b> 0.4 km<br\/> <b>Track: <\/b> 0.6 km<br\/> <b>FRP: <\/b> 3.26 MW<br\/> <b>Brightness: <\/b> 329.4 K" }, "geometry": { "type": "Point", "coordinates": [ -71.6797, 19.63304, 0.0 ] } }
]
}
