{
"type": "FeatureCollection",
"crs": { "type": "name", "properties": { "name": "urn:ogc:def:crs:OGC:1.3:CRS84" } },
"features": [
{ "type": "Feature", "properties": { "Name": "Fire Detection Centroid ", "Description": "<b>Latitude: <\/b> 19.40735<br\/>  <b>Longitude: <\/b> -155.28601<br\/>  <b>Detection Time: <\/b> 2023-03-30 11:49 UTC<br\/>  <b>Sensor: <\/b> NOAA-20 VIIRS<br\/> <b>Confidence: <\/b> Nominal<br\/>  <b>Day\/Night: <\/b> Night<br\/> <b>Scan: <\/b> 0.42 km<br\/> <b>Track: <\/b> 0.38 km<br\/> <b>FRP: <\/b> 1.7 MW<br\/> <b>Brightness: <\/b> 302.97 K" }, "geometry": { "type": "Point", "coordinates": [ -155.28601, 19.40735, 0.0 ] } },
{ "type": "Feature", "properties": { "Name": "Fire Detection Centroid ", "Description": "<b>Latitude: <\/b> 19.59644<br\/>  <b>Longitude: <\/b> -155.50458<br\/>  <b>Detection Time: <\/b> 2023-03-30 11:49 UTC<br\/>  <b>Sensor: <\/b> NOAA-20 VIIRS<br\/> <b>Confidence: <\/b> Nominal<br\/>  <b>Day\/Night: <\/b> Night<br\/> <b>Scan: <\/b> 0.43 km<br\/> <b>Track: <\/b> 0.38 km<br\/> <b>FRP: <\/b> 1.18 MW<br\/> <b>Brightness: <\/b> 295.22 K" }, "geometry": { "type": "Point", "coordinates": [ -155.50458, 19.59644, 0.0 ] } },
{ "type": "Feature", "properties": { "Name": "Fire Detection Centroid ", "Description": "<b>Latitude: <\/b> 19.40334<br\/>  <b>Longitude: <\/b> -155.28261<br\/>  <b>Detection Time: <\/b> 2023-03-30 11:49 UTC<br\/>  <b>Sensor: <\/b> NOAA-20 VIIRS<br\/> <b>Confidence: <\/b> Nominal<br\/>  <b>Day\/Night: <\/b> Night<br\/> <b>Scan: <\/b> 0.42 km<br\/> <b>Track: <\/b> 0.38 km<br\/> <b>FRP: <\/b> 1.79 MW<br\/> <b>Brightness: <\/b> 301.94 K" }, "geometry": { "type": "Point", "coordinates": [ -155.28261, 19.40334, 0.0 ] } },
{ "type": "Feature", "properties": { "Name": "Fire Detection Centroid ", "Description": "<b>Latitude: <\/b> 19.40622<br\/>  <b>Longitude: <\/b> -155.27806<br\/>  <b>Detection Time: <\/b> 2023-03-30 11:49 UTC<br\/>  <b>Sensor: <\/b> NOAA-20 VIIRS<br\/> <b>Confidence: <\/b> Nominal<br\/>  <b>Day\/Night: <\/b> Night<br\/> <b>Scan: <\/b> 0.42 km<br\/> <b>Track: <\/b> 0.38 km<br\/> <b>FRP: <\/b> 2.23 MW<br\/> <b>Brightness: <\/b> 305.47 K" }, "geometry": { "type": "Point", "coordinates": [ -155.27806, 19.40622, 0.0 ] } },
{ "type": "Feature", "properties": { "Name": "Fire Detection Centroid ", "Description": "<b>Latitude: <\/b> 19.40679<br\/>  <b>Longitude: <\/b> -155.28204<br\/>  <b>Detection Time: <\/b> 2023-03-30 11:49 UTC<br\/>  <b>Sensor: <\/b> NOAA-20 VIIRS<br\/> <b>Confidence: <\/b> Nominal<br\/>  <b>Day\/Night: <\/b> Night<br\/> <b>Scan: <\/b> 0.42 km<br\/> <b>Track: <\/b> 0.38 km<br\/> <b>FRP: <\/b> 1.7 MW<br\/> <b>Brightness: <\/b> 304.43 K" }, "geometry": { "type": "Point", "coordinates": [ -155.28204, 19.40679, 0.0 ] } }
]
}
