{
"type": "FeatureCollection",
"crs": { "type": "name", "properties": { "name": "urn:ogc:def:crs:OGC:1.3:CRS84" } },
"features": [
{ "type": "Feature", "properties": { "Name": "Fire Detection Centroid ", "Description": "<b>Latitude: <\/b> 20.86231<br\/>  <b>Longitude: <\/b> -156.41988<br\/>  <b>Detection Time: <\/b> 2024-03-30 12:10 UTC<br\/>  <b>Sensor: <\/b> NOAA-20 VIIRS<br\/> <b>Confidence: <\/b> Nominal<br\/>  <b>Day\/Night: <\/b> Night<br\/> <b>Scan: <\/b> 0.4 km<br\/> <b>Track: <\/b> 0.37 km<br\/> <b>FRP: <\/b> 0.35 MW<br\/> <b>Brightness: <\/b> 300.53 K" }, "geometry": { "type": "Point", "coordinates": [ -156.41988, 20.86231, 0.0 ] } },
{ "type": "Feature", "properties": { "Name": "Fire Detection Centroid ", "Description": "<b>Latitude: <\/b> 20.80577<br\/>  <b>Longitude: <\/b> -156.43031<br\/>  <b>Detection Time: <\/b> 2024-03-30 12:10 UTC<br\/>  <b>Sensor: <\/b> NOAA-20 VIIRS<br\/> <b>Confidence: <\/b> Nominal<br\/>  <b>Day\/Night: <\/b> Night<br\/> <b>Scan: <\/b> 0.4 km<br\/> <b>Track: <\/b> 0.4 km<br\/> <b>FRP: <\/b> 0.34 MW<br\/> <b>Brightness: <\/b> 300.53 K" }, "geometry": { "type": "Point", "coordinates": [ -156.43031, 20.80577, 0.0 ] } }
]
}
