{
"type": "FeatureCollection",
"crs": { "type": "name", "properties": { "name": "urn:ogc:def:crs:OGC:1.3:CRS84" } },
"features": [
{ "type": "Feature", "properties": { "Name": "Fire Detection Centroid ", "Description": "<b>Latitude: <\/b> 37.61686<br\/>  <b>Longitude: <\/b> -120.52616<br\/>  <b>Detection Time: <\/b> 2024-04-25 21:50 UTC<br\/>  <b>Sensor: <\/b> NOAA-20 VIIRS<br\/> <b>Confidence: <\/b> Nominal<br\/>  <b>Day\/Night: <\/b> Day<br\/> <b>Scan: <\/b> 0.4 km<br\/> <b>Track: <\/b> 0.6 km<br\/> <b>FRP: <\/b> 4.53 MW<br\/> <b>Brightness: <\/b> 334.24 K" }, "geometry": { "type": "Point", "coordinates": [ -120.52616, 37.61686, 0.0 ] } },
{ "type": "Feature", "properties": { "Name": "Fire Detection Centroid ", "Description": "<b>Latitude: <\/b> 36.29677<br\/>  <b>Longitude: <\/b> -121.30219<br\/>  <b>Detection Time: <\/b> 2024-04-25 21:50 UTC<br\/>  <b>Sensor: <\/b> NOAA-20 VIIRS<br\/> <b>Confidence: <\/b> Nominal<br\/>  <b>Day\/Night: <\/b> Day<br\/> <b>Scan: <\/b> 0.38 km<br\/> <b>Track: <\/b> 0.59 km<br\/> <b>FRP: <\/b> 2.88 MW<br\/> <b>Brightness: <\/b> 331.01 K" }, "geometry": { "type": "Point", "coordinates": [ -121.30219, 36.29677, 0.0 ] } },
{ "type": "Feature", "properties": { "Name": "Fire Detection Centroid ", "Description": "<b>Latitude: <\/b> 37.59921<br\/>  <b>Longitude: <\/b> -120.52486<br\/>  <b>Detection Time: <\/b> 2024-04-25 21:50 UTC<br\/>  <b>Sensor: <\/b> NOAA-20 VIIRS<br\/> <b>Confidence: <\/b> Nominal<br\/>  <b>Day\/Night: <\/b> Day<br\/> <b>Scan: <\/b> 0.43 km<br\/> <b>Track: <\/b> 0.62 km<br\/> <b>FRP: <\/b> 4.53 MW<br\/> <b>Brightness: <\/b> 334.24 K" }, "geometry": { "type": "Point", "coordinates": [ -120.52486, 37.59921, 0.0 ] } },
{ "type": "Feature", "properties": { "Name": "Fire Detection Centroid ", "Description": "<b>Latitude: <\/b> 32.84096<br\/>  <b>Longitude: <\/b> -115.39241<br\/>  <b>Detection Time: <\/b> 2024-04-25 21:48 UTC<br\/>  <b>Sensor: <\/b> NOAA-20 VIIRS<br\/> <b>Confidence: <\/b> Nominal<br\/>  <b>Day\/Night: <\/b> Day<br\/> <b>Scan: <\/b> 0.8 km<br\/> <b>Track: <\/b> 0.8 km<br\/> <b>FRP: <\/b> 6.89 MW<br\/> <b>Brightness: <\/b> 349.04 K" }, "geometry": { "type": "Point", "coordinates": [ -115.39241, 32.84096, 0.0 ] } },
{ "type": "Feature", "properties": { "Name": "Fire Detection Centroid ", "Description": "<b>Latitude: <\/b> 33.04536<br\/>  <b>Longitude: <\/b> -115.39827<br\/>  <b>Detection Time: <\/b> 2024-04-25 21:48 UTC<br\/>  <b>Sensor: <\/b> NOAA-20 VIIRS<br\/> <b>Confidence: <\/b> Nominal<br\/>  <b>Day\/Night: <\/b> Day<br\/> <b>Scan: <\/b> 0.8 km<br\/> <b>Track: <\/b> 0.8 km<br\/> <b>FRP: <\/b> 8.82 MW<br\/> <b>Brightness: <\/b> 344.26 K" }, "geometry": { "type": "Point", "coordinates": [ -115.39827, 33.04536, 0.0 ] } },
{ "type": "Feature", "properties": { "Name": "Fire Detection Centroid ", "Description": "<b>Latitude: <\/b> 32.95078<br\/>  <b>Longitude: <\/b> -115.39574<br\/>  <b>Detection Time: <\/b> 2024-04-25 21:48 UTC<br\/>  <b>Sensor: <\/b> NOAA-20 VIIRS<br\/> <b>Confidence: <\/b> Nominal<br\/>  <b>Day\/Night: <\/b> Day<br\/> <b>Scan: <\/b> 0.78 km<br\/> <b>Track: <\/b> 0.78 km<br\/> <b>FRP: <\/b> 8.83 MW<br\/> <b>Brightness: <\/b> 344.26 K" }, "geometry": { "type": "Point", "coordinates": [ -115.39574, 32.95078, 0.0 ] } },
{ "type": "Feature", "properties": { "Name": "Fire Detection Centroid ", "Description": "<b>Latitude: <\/b> 32.9485<br\/>  <b>Longitude: <\/b> -115.39386<br\/>  <b>Detection Time: <\/b> 2024-04-25 21:48 UTC<br\/>  <b>Sensor: <\/b> NOAA-20 VIIRS<br\/> <b>Confidence: <\/b> Nominal<br\/>  <b>Day\/Night: <\/b> Day<br\/> <b>Scan: <\/b> 0.78 km<br\/> <b>Track: <\/b> 0.78 km<br\/> <b>FRP: <\/b> 6.9 MW<br\/> <b>Brightness: <\/b> 349.04 K" }, "geometry": { "type": "Point", "coordinates": [ -115.39386, 32.9485, 0.0 ] } }
]
}
