{
"type": "FeatureCollection",
"crs": { "type": "name", "properties": { "name": "urn:ogc:def:crs:OGC:1.3:CRS84" } },
"features": [
{ "type": "Feature", "properties": { "Name": "Fire Detection Centroid ", "Description": "<b>Latitude: <\/b> 34.61095<br\/>  <b>Longitude: <\/b> -117.33566<br\/>  <b>Detection Time: <\/b> 2023-03-12 10:41 UTC<br\/>  <b>Sensor: <\/b> NOAA-20 VIIRS<br\/> <b>Confidence: <\/b> Nominal<br\/>  <b>Day\/Night: <\/b> Night<br\/> <b>Scan: <\/b> 0.65 km<br\/> <b>Track: <\/b> 0.73 km<br\/> <b>FRP: <\/b> 1.68 MW<br\/> <b>Brightness: <\/b> 306.2 K" }, "geometry": { "type": "Point", "coordinates": [ -117.33566, 34.61095, 0.0 ] } },
{ "type": "Feature", "properties": { "Name": "Fire Detection Centroid ", "Description": "<b>Latitude: <\/b> 34.6063<br\/>  <b>Longitude: <\/b> -117.33863<br\/>  <b>Detection Time: <\/b> 2023-03-12 10:41 UTC<br\/>  <b>Sensor: <\/b> NOAA-20 VIIRS<br\/> <b>Confidence: <\/b> Nominal<br\/>  <b>Day\/Night: <\/b> Night<br\/> <b>Scan: <\/b> 0.65 km<br\/> <b>Track: <\/b> 0.73 km<br\/> <b>FRP: <\/b> 1.69 MW<br\/> <b>Brightness: <\/b> 308.17 K" }, "geometry": { "type": "Point", "coordinates": [ -117.33863, 34.6063, 0.0 ] } },
{ "type": "Feature", "properties": { "Name": "Fire Detection Centroid ", "Description": "<b>Latitude: <\/b> 34.33505<br\/>  <b>Longitude: <\/b> -118.52045<br\/>  <b>Detection Time: <\/b> 2023-03-12 10:41 UTC<br\/>  <b>Sensor: <\/b> NOAA-20 VIIRS<br\/> <b>Confidence: <\/b> Nominal<br\/>  <b>Day\/Night: <\/b> Night<br\/> <b>Scan: <\/b> 0.57 km<br\/> <b>Track: <\/b> 0.69 km<br\/> <b>FRP: <\/b> 0.68 MW<br\/> <b>Brightness: <\/b> 296.52 K" }, "geometry": { "type": "Point", "coordinates": [ -118.52045, 34.33505, 0.0 ] } },
{ "type": "Feature", "properties": { "Name": "Fire Detection Centroid ", "Description": "<b>Latitude: <\/b> 47.57256<br\/>  <b>Longitude: <\/b> -122.36811<br\/>  <b>Detection Time: <\/b> 2023-03-12 10:38 UTC<br\/>  <b>Sensor: <\/b> NOAA-20 VIIRS<br\/> <b>Confidence: <\/b> Nominal<br\/>  <b>Day\/Night: <\/b> Night<br\/> <b>Scan: <\/b> 0.52 km<br\/> <b>Track: <\/b> 0.41 km<br\/> <b>FRP: <\/b> 2.11 MW<br\/> <b>Brightness: <\/b> 318.28 K" }, "geometry": { "type": "Point", "coordinates": [ -122.36811, 47.57256, 0.0 ] } },
{ "type": "Feature", "properties": { "Name": "Fire Detection Centroid ", "Description": "<b>Latitude: <\/b> 47.56682<br\/>  <b>Longitude: <\/b> -122.34151<br\/>  <b>Detection Time: <\/b> 2023-03-12 10:38 UTC<br\/>  <b>Sensor: <\/b> NOAA-20 VIIRS<br\/> <b>Confidence: <\/b> Nominal<br\/>  <b>Day\/Night: <\/b> Night<br\/> <b>Scan: <\/b> 0.52 km<br\/> <b>Track: <\/b> 0.41 km<br\/> <b>FRP: <\/b> 0.84 MW<br\/> <b>Brightness: <\/b> 298.57 K" }, "geometry": { "type": "Point", "coordinates": [ -122.34151, 47.56682, 0.0 ] } },
{ "type": "Feature", "properties": { "Name": "Fire Detection Centroid ", "Description": "<b>Latitude: <\/b> 47.56892<br\/>  <b>Longitude: <\/b> -122.36992<br\/>  <b>Detection Time: <\/b> 2023-03-12 10:38 UTC<br\/>  <b>Sensor: <\/b> NOAA-20 VIIRS<br\/> <b>Confidence: <\/b> Nominal<br\/>  <b>Day\/Night: <\/b> Night<br\/> <b>Scan: <\/b> 0.52 km<br\/> <b>Track: <\/b> 0.41 km<br\/> <b>FRP: <\/b> 2.54 MW<br\/> <b>Brightness: <\/b> 316.22 K" }, "geometry": { "type": "Point", "coordinates": [ -122.36992, 47.56892, 0.0 ] } }
]
}
