{
"type": "FeatureCollection",
"crs": { "type": "name", "properties": { "name": "urn:ogc:def:crs:OGC:1.3:CRS84" } },
"features": [
{ "type": "Feature", "properties": { "Name": "Fire Detection Centroid ", "Description": "<b>Latitude: <\/b> 19.40425<br\/>  <b>Longitude: <\/b> -155.27901<br\/>  <b>Detection Time: <\/b> 2023-02-27 11:29 UTC<br\/>  <b>Sensor: <\/b> NOAA-20 VIIRS<br\/> <b>Confidence: <\/b> Nominal<br\/>  <b>Day\/Night: <\/b> Night<br\/> <b>Scan: <\/b> 0.51 km<br\/> <b>Track: <\/b> 0.49 km<br\/> <b>FRP: <\/b> 8.34 MW<br\/> <b>Brightness: <\/b> 295.94 K" }, "geometry": { "type": "Point", "coordinates": [ -155.27901, 19.40425, 0.0 ] } },
{ "type": "Feature", "properties": { "Name": "Fire Detection Centroid ", "Description": "<b>Latitude: <\/b> 19.40615<br\/>  <b>Longitude: <\/b> -155.28677<br\/>  <b>Detection Time: <\/b> 2023-02-27 11:29 UTC<br\/>  <b>Sensor: <\/b> NOAA-20 VIIRS<br\/> <b>Confidence: <\/b> Nominal<br\/>  <b>Day\/Night: <\/b> Night<br\/> <b>Scan: <\/b> 0.51 km<br\/> <b>Track: <\/b> 0.49 km<br\/> <b>FRP: <\/b> 18.94 MW<br\/> <b>Brightness: <\/b> 339.06 K" }, "geometry": { "type": "Point", "coordinates": [ -155.28677, 19.40615, 0.0 ] } },
{ "type": "Feature", "properties": { "Name": "Fire Detection Centroid ", "Description": "<b>Latitude: <\/b> 19.40959<br\/>  <b>Longitude: <\/b> -155.27649<br\/>  <b>Detection Time: <\/b> 2023-02-27 11:29 UTC<br\/>  <b>Sensor: <\/b> NOAA-20 VIIRS<br\/> <b>Confidence: <\/b> Nominal<br\/>  <b>Day\/Night: <\/b> Night<br\/> <b>Scan: <\/b> 0.51 km<br\/> <b>Track: <\/b> 0.49 km<br\/> <b>FRP: <\/b> 1.68 MW<br\/> <b>Brightness: <\/b> 299.36 K" }, "geometry": { "type": "Point", "coordinates": [ -155.27649, 19.40959, 0.0 ] } },
{ "type": "Feature", "properties": { "Name": "Fire Detection Centroid ", "Description": "<b>Latitude: <\/b> 19.41013<br\/>  <b>Longitude: <\/b> -155.28128<br\/>  <b>Detection Time: <\/b> 2023-02-27 11:29 UTC<br\/>  <b>Sensor: <\/b> NOAA-20 VIIRS<br\/> <b>Confidence: <\/b> Nominal<br\/>  <b>Day\/Night: <\/b> Night<br\/> <b>Scan: <\/b> 0.51 km<br\/> <b>Track: <\/b> 0.49 km<br\/> <b>FRP: <\/b> 2.79 MW<br\/> <b>Brightness: <\/b> 297.82 K" }, "geometry": { "type": "Point", "coordinates": [ -155.28128, 19.41013, 0.0 ] } },
{ "type": "Feature", "properties": { "Name": "Fire Detection Centroid ", "Description": "<b>Latitude: <\/b> 19.40483<br\/>  <b>Longitude: <\/b> -155.28384<br\/>  <b>Detection Time: <\/b> 2023-02-27 11:29 UTC<br\/>  <b>Sensor: <\/b> NOAA-20 VIIRS<br\/> <b>Confidence: <\/b> Nominal<br\/>  <b>Day\/Night: <\/b> Night<br\/> <b>Scan: <\/b> 0.51 km<br\/> <b>Track: <\/b> 0.49 km<br\/> <b>FRP: <\/b> 8.34 MW<br\/> <b>Brightness: <\/b> 347.12 K" }, "geometry": { "type": "Point", "coordinates": [ -155.28384, 19.40483, 0.0 ] } },
{ "type": "Feature", "properties": { "Name": "Fire Detection Centroid ", "Description": "<b>Latitude: <\/b> 19.40878<br\/>  <b>Longitude: <\/b> -155.27838<br\/>  <b>Detection Time: <\/b> 2023-02-27 11:29 UTC<br\/>  <b>Sensor: <\/b> NOAA-20 VIIRS<br\/> <b>Confidence: <\/b> Nominal<br\/>  <b>Day\/Night: <\/b> Night<br\/> <b>Scan: <\/b> 0.51 km<br\/> <b>Track: <\/b> 0.49 km<br\/> <b>FRP: <\/b> 8.34 MW<br\/> <b>Brightness: <\/b> 309.73 K" }, "geometry": { "type": "Point", "coordinates": [ -155.27838, 19.40878, 0.0 ] } },
{ "type": "Feature", "properties": { "Name": "Fire Detection Centroid ", "Description": "<b>Latitude: <\/b> 19.40936<br\/>  <b>Longitude: <\/b> -155.28314<br\/>  <b>Detection Time: <\/b> 2023-02-27 11:29 UTC<br\/>  <b>Sensor: <\/b> NOAA-20 VIIRS<br\/> <b>Confidence: <\/b> Nominal<br\/>  <b>Day\/Night: <\/b> Night<br\/> <b>Scan: <\/b> 0.51 km<br\/> <b>Track: <\/b> 0.49 km<br\/> <b>FRP: <\/b> 8.34 MW<br\/> <b>Brightness: <\/b> 342.55 K" }, "geometry": { "type": "Point", "coordinates": [ -155.28314, 19.40936, 0.0 ] } },
{ "type": "Feature", "properties": { "Name": "Fire Detection Centroid ", "Description": "<b>Latitude: <\/b> 19.4056<br\/>  <b>Longitude: <\/b> -155.28197<br\/>  <b>Detection Time: <\/b> 2023-02-27 11:29 UTC<br\/>  <b>Sensor: <\/b> NOAA-20 VIIRS<br\/> <b>Confidence: <\/b> Nominal<br\/>  <b>Day\/Night: <\/b> Night<br\/> <b>Scan: <\/b> 0.51 km<br\/> <b>Track: <\/b> 0.49 km<br\/> <b>FRP: <\/b> 18.94 MW<br\/> <b>Brightness: <\/b> 328.63 K" }, "geometry": { "type": "Point", "coordinates": [ -155.28197, 19.4056, 0.0 ] } }
]
}
