{
"type": "FeatureCollection",
"crs": { "type": "name", "properties": { "name": "urn:ogc:def:crs:OGC:1.3:CRS84" } },
"features": [
{ "type": "Feature", "properties": { "Name": "Fire Detection Centroid ", "Description": "<b>Latitude: <\/b> 45.28054<br\/>  <b>Longitude: <\/b> -66.01887<br\/>  <b>Detection Time: <\/b> 2023-09-26 05:22 UTC<br\/>  <b>Sensor: <\/b> NOAA-20 VIIRS<br\/> <b>Confidence: <\/b> Nominal<br\/>  <b>Day\/Night: <\/b> Night<br\/> <b>Scan: <\/b> 0.5 km<br\/> <b>Track: <\/b> 0.7 km<br\/> <b>FRP: <\/b> 1.99 MW<br\/> <b>Brightness: <\/b> 303.17 K" }, "geometry": { "type": "Point", "coordinates": [ -66.01887, 45.28054, 0.0 ] } },
{ "type": "Feature", "properties": { "Name": "Fire Detection Centroid ", "Description": "<b>Latitude: <\/b> 45.28141<br\/>  <b>Longitude: <\/b> -66.01424<br\/>  <b>Detection Time: <\/b> 2023-09-26 05:22 UTC<br\/>  <b>Sensor: <\/b> NOAA-20 VIIRS<br\/> <b>Confidence: <\/b> Nominal<br\/>  <b>Day\/Night: <\/b> Night<br\/> <b>Scan: <\/b> 0.5 km<br\/> <b>Track: <\/b> 0.7 km<br\/> <b>FRP: <\/b> 1.18 MW<br\/> <b>Brightness: <\/b> 298.85 K" }, "geometry": { "type": "Point", "coordinates": [ -66.01424, 45.28141, 0.0 ] } },
{ "type": "Feature", "properties": { "Name": "Fire Detection Centroid ", "Description": "<b>Latitude: <\/b> 45.28154<br\/>  <b>Longitude: <\/b> -66.02091<br\/>  <b>Detection Time: <\/b> 2023-09-26 05:22 UTC<br\/>  <b>Sensor: <\/b> NOAA-20 VIIRS<br\/> <b>Confidence: <\/b> Nominal<br\/>  <b>Day\/Night: <\/b> Night<br\/> <b>Scan: <\/b> 0.5 km<br\/> <b>Track: <\/b> 0.7 km<br\/> <b>FRP: <\/b> 1.18 MW<br\/> <b>Brightness: <\/b> 309.84 K" }, "geometry": { "type": "Point", "coordinates": [ -66.02091, 45.28154, 0.0 ] } }
]
}
