{
"type": "FeatureCollection",
"crs": { "type": "name", "properties": { "name": "urn:ogc:def:crs:OGC:1.3:CRS84" } },
"features": [
{ "type": "Feature", "properties": { "Name": "Fire Detection Centroid ", "Description": "<b>Latitude: <\/b> 42.58131<br\/>  <b>Longitude: <\/b> -122.98209<br\/>  <b>Detection Time: <\/b> 2024-05-03 11:17 UTC<br\/>  <b>Sensor: <\/b> NOAA-20 VIIRS<br\/> <b>Confidence: <\/b> Nominal<br\/>  <b>Day\/Night: <\/b> Night<br\/> <b>Scan: <\/b> 0.6 km<br\/> <b>Track: <\/b> 0.7 km<br\/> <b>FRP: <\/b> 1.53 MW<br\/> <b>Brightness: <\/b> 299.07 K" }, "geometry": { "type": "Point", "coordinates": [ -122.98209, 42.58131, 0.0 ] } },
{ "type": "Feature", "properties": { "Name": "Fire Detection Centroid ", "Description": "<b>Latitude: <\/b> 47.59537<br\/>  <b>Longitude: <\/b> -121.95961<br\/>  <b>Detection Time: <\/b> 2024-05-03 11:16 UTC<br\/>  <b>Sensor: <\/b> NOAA-20 VIIRS<br\/> <b>Confidence: <\/b> Nominal<br\/>  <b>Day\/Night: <\/b> Night<br\/> <b>Scan: <\/b> 0.5 km<br\/> <b>Track: <\/b> 0.6 km<br\/> <b>FRP: <\/b> 0.79 MW<br\/> <b>Brightness: <\/b> 309.77 K" }, "geometry": { "type": "Point", "coordinates": [ -121.95961, 47.59537, 0.0 ] } },
{ "type": "Feature", "properties": { "Name": "Fire Detection Centroid ", "Description": "<b>Latitude: <\/b> 47.40408<br\/>  <b>Longitude: <\/b> -122.09665<br\/>  <b>Detection Time: <\/b> 2024-05-03 11:16 UTC<br\/>  <b>Sensor: <\/b> NOAA-20 VIIRS<br\/> <b>Confidence: <\/b> Nominal<br\/>  <b>Day\/Night: <\/b> Night<br\/> <b>Scan: <\/b> 0.5 km<br\/> <b>Track: <\/b> 0.6 km<br\/> <b>FRP: <\/b> 1.17 MW<br\/> <b>Brightness: <\/b> 305.56 K" }, "geometry": { "type": "Point", "coordinates": [ -122.09665, 47.40408, 0.0 ] } },
{ "type": "Feature", "properties": { "Name": "Fire Detection Centroid ", "Description": "<b>Latitude: <\/b> 48.77319<br\/>  <b>Longitude: <\/b> -122.81354<br\/>  <b>Detection Time: <\/b> 2024-05-03 11:15 UTC<br\/>  <b>Sensor: <\/b> NOAA-20 VIIRS<br\/> <b>Confidence: <\/b> Nominal<br\/>  <b>Day\/Night: <\/b> Night<br\/> <b>Scan: <\/b> 0.4 km<br\/> <b>Track: <\/b> 0.6 km<br\/> <b>FRP: <\/b> 1.34 MW<br\/> <b>Brightness: <\/b> 297.24 K" }, "geometry": { "type": "Point", "coordinates": [ -122.81354, 48.77319, 0.0 ] } },
{ "type": "Feature", "properties": { "Name": "Fire Detection Centroid ", "Description": "<b>Latitude: <\/b> 48.77319<br\/>  <b>Longitude: <\/b> -122.81354<br\/>  <b>Detection Time: <\/b> 2024-05-03 11:15 UTC<br\/>  <b>Sensor: <\/b> NOAA-20 VIIRS<br\/> <b>Confidence: <\/b> Nominal<br\/>  <b>Day\/Night: <\/b> Night<br\/> <b>Scan: <\/b> 0.4 km<br\/> <b>Track: <\/b> 0.6 km<br\/> <b>FRP: <\/b> 1.34 MW<br\/> <b>Brightness: <\/b> 297.24 K" }, "geometry": { "type": "Point", "coordinates": [ -122.81354, 48.77319, 0.0 ] } }
]
}
