{
"type": "FeatureCollection",
"crs": { "type": "name", "properties": { "name": "urn:ogc:def:crs:OGC:1.3:CRS84" } },
"features": [
{ "type": "Feature", "properties": { "Name": "Fire Detection Centroid ", "Description": "<b>Latitude: <\/b> 18.92796<br\/>  <b>Longitude: <\/b> -70.35059<br\/>  <b>Detection Time: <\/b> 2022-09-06 05:47 UTC<br\/>  <b>Sensor: <\/b> NOAA-20 VIIRS<br\/> <b>Confidence: <\/b> Nominal<br\/>  <b>Day\/Night: <\/b> Night<br\/> <b>Scan: <\/b> 0.6 km<br\/> <b>Track: <\/b> 0.5 km<br\/> <b>FRP: <\/b> 9.35 MW<br\/> <b>Brightness: <\/b> 319.77 K" }, "geometry": { "type": "Point", "coordinates": [ -70.35059, 18.92796, 0.0 ] } },
{ "type": "Feature", "properties": { "Name": "Fire Detection Centroid ", "Description": "<b>Latitude: <\/b> 18.9286<br\/>  <b>Longitude: <\/b> -70.35609<br\/>  <b>Detection Time: <\/b> 2022-09-06 05:47 UTC<br\/>  <b>Sensor: <\/b> NOAA-20 VIIRS<br\/> <b>Confidence: <\/b> Nominal<br\/>  <b>Day\/Night: <\/b> Night<br\/> <b>Scan: <\/b> 0.6 km<br\/> <b>Track: <\/b> 0.5 km<br\/> <b>FRP: <\/b> 9.35 MW<br\/> <b>Brightness: <\/b> 338.74 K" }, "geometry": { "type": "Point", "coordinates": [ -70.35609, 18.9286, 0.0 ] } },
{ "type": "Feature", "properties": { "Name": "Fire Detection Centroid ", "Description": "<b>Latitude: <\/b> 19.20312<br\/>  <b>Longitude: <\/b> -70.32883<br\/>  <b>Detection Time: <\/b> 2022-09-06 05:47 UTC<br\/>  <b>Sensor: <\/b> NOAA-20 VIIRS<br\/> <b>Confidence: <\/b> Nominal<br\/>  <b>Day\/Night: <\/b> Night<br\/> <b>Scan: <\/b> 0.6 km<br\/> <b>Track: <\/b> 0.5 km<br\/> <b>FRP: <\/b> 1.24 MW<br\/> <b>Brightness: <\/b> 309.84 K" }, "geometry": { "type": "Point", "coordinates": [ -70.32883, 19.20312, 0.0 ] } },
{ "type": "Feature", "properties": { "Name": "Fire Detection Centroid ", "Description": "<b>Latitude: <\/b> 45.83662<br\/>  <b>Longitude: <\/b> -73.25068<br\/>  <b>Detection Time: <\/b> 2022-09-06 05:40 UTC<br\/>  <b>Sensor: <\/b> NOAA-20 VIIRS<br\/> <b>Confidence: <\/b> Nominal<br\/>  <b>Day\/Night: <\/b> Night<br\/> <b>Scan: <\/b> 0.7 km<br\/> <b>Track: <\/b> 0.7 km<br\/> <b>FRP: <\/b> 1.37 MW<br\/> <b>Brightness: <\/b> 295.62 K" }, "geometry": { "type": "Point", "coordinates": [ -73.25068, 45.83662, 0.0 ] } },
{ "type": "Feature", "properties": { "Name": "Fire Detection Centroid ", "Description": "<b>Latitude: <\/b> 46.04391<br\/>  <b>Longitude: <\/b> -73.14367<br\/>  <b>Detection Time: <\/b> 2022-09-06 05:40 UTC<br\/>  <b>Sensor: <\/b> NOAA-20 VIIRS<br\/> <b>Confidence: <\/b> Nominal<br\/>  <b>Day\/Night: <\/b> Night<br\/> <b>Scan: <\/b> 0.7 km<br\/> <b>Track: <\/b> 0.7 km<br\/> <b>FRP: <\/b> 2.51 MW<br\/> <b>Brightness: <\/b> 296.6 K" }, "geometry": { "type": "Point", "coordinates": [ -73.14367, 46.04391, 0.0 ] } },
{ "type": "Feature", "properties": { "Name": "Fire Detection Centroid ", "Description": "<b>Latitude: <\/b> 45.83706<br\/>  <b>Longitude: <\/b> -73.25867<br\/>  <b>Detection Time: <\/b> 2022-09-06 05:40 UTC<br\/>  <b>Sensor: <\/b> NOAA-20 VIIRS<br\/> <b>Confidence: <\/b> Nominal<br\/>  <b>Day\/Night: <\/b> Night<br\/> <b>Scan: <\/b> 0.7 km<br\/> <b>Track: <\/b> 0.7 km<br\/> <b>FRP: <\/b> 1.63 MW<br\/> <b>Brightness: <\/b> 297.26 K" }, "geometry": { "type": "Point", "coordinates": [ -73.25867, 45.83706, 0.0 ] } }
]
}
