{
"type": "FeatureCollection",
"crs": { "type": "name", "properties": { "name": "urn:ogc:def:crs:OGC:1.3:CRS84" } },
"features": [
{ "type": "Feature", "properties": { "Name": "Fire Detection Centroid ", "Description": "<b>Latitude: <\/b> 48.72097<br\/>  <b>Longitude: <\/b> -118.09914<br\/>  <b>Detection Time: <\/b> 2023-02-11 11:19 UTC<br\/>  <b>Sensor: <\/b> NOAA-20 VIIRS<br\/> <b>Confidence: <\/b> Nominal<br\/>  <b>Day\/Night: <\/b> Night<br\/> <b>Scan: <\/b> 0.69 km<br\/> <b>Track: <\/b> 0.74 km<br\/> <b>FRP: <\/b> 2.09 MW<br\/> <b>Brightness: <\/b> 310.74 K" }, "geometry": { "type": "Point", "coordinates": [ -118.09914, 48.72097, 0.0 ] } },
{ "type": "Feature", "properties": { "Name": "Fire Detection Centroid ", "Description": "<b>Latitude: <\/b> 48.71859<br\/>  <b>Longitude: <\/b> -118.09277<br\/>  <b>Detection Time: <\/b> 2023-02-11 11:19 UTC<br\/>  <b>Sensor: <\/b> NOAA-20 VIIRS<br\/> <b>Confidence: <\/b> Nominal<br\/>  <b>Day\/Night: <\/b> Night<br\/> <b>Scan: <\/b> 0.69 km<br\/> <b>Track: <\/b> 0.74 km<br\/> <b>FRP: <\/b> 2.09 MW<br\/> <b>Brightness: <\/b> 298.07 K" }, "geometry": { "type": "Point", "coordinates": [ -118.09277, 48.71859, 0.0 ] } },
{ "type": "Feature", "properties": { "Name": "Fire Detection Centroid ", "Description": "<b>Latitude: <\/b> 48.72477<br\/>  <b>Longitude: <\/b> -118.0882<br\/>  <b>Detection Time: <\/b> 2023-02-11 11:19 UTC<br\/>  <b>Sensor: <\/b> NOAA-20 VIIRS<br\/> <b>Confidence: <\/b> Nominal<br\/>  <b>Day\/Night: <\/b> Night<br\/> <b>Scan: <\/b> 0.69 km<br\/> <b>Track: <\/b> 0.74 km<br\/> <b>FRP: <\/b> 3 MW<br\/> <b>Brightness: <\/b> 310.84 K" }, "geometry": { "type": "Point", "coordinates": [ -118.0882, 48.72477, 0.0 ] } }
]
}
