{
"type": "FeatureCollection",
"crs": { "type": "name", "properties": { "name": "urn:ogc:def:crs:OGC:1.3:CRS84" } },
"features": [
{ "type": "Feature", "properties": { "Name": "Fire Detection Centroid ", "Description": "<b>Latitude: <\/b> 34.54881<br\/>  <b>Longitude: <\/b> -117.35683<br\/>  <b>Detection Time: <\/b> 2024-01-22 10:15 UTC<br\/>  <b>Sensor: <\/b> NOAA-20 VIIRS<br\/> <b>Confidence: <\/b> Nominal<br\/>  <b>Day\/Night: <\/b> Night<br\/> <b>Scan: <\/b> 0.6 km<br\/> <b>Track: <\/b> 0.5 km<br\/> <b>FRP: <\/b> 1.69 MW<br\/> <b>Brightness: <\/b> 299.05 K" }, "geometry": { "type": "Point", "coordinates": [ -117.35683, 34.54881, 0.0 ] } },
{ "type": "Feature", "properties": { "Name": "Fire Detection Centroid ", "Description": "<b>Latitude: <\/b> 45.55331<br\/>  <b>Longitude: <\/b> -123.95708<br\/>  <b>Detection Time: <\/b> 2024-01-22 10:13 UTC<br\/>  <b>Sensor: <\/b> NOAA-20 VIIRS<br\/> <b>Confidence: <\/b> Nominal<br\/>  <b>Day\/Night: <\/b> Night<br\/> <b>Scan: <\/b> 0.4 km<br\/> <b>Track: <\/b> 0.4 km<br\/> <b>FRP: <\/b> 1.29 MW<br\/> <b>Brightness: <\/b> 307.53 K" }, "geometry": { "type": "Point", "coordinates": [ -123.95708, 45.55331, 0.0 ] } },
{ "type": "Feature", "properties": { "Name": "Fire Detection Centroid ", "Description": "<b>Latitude: <\/b> 42.61223<br\/>  <b>Longitude: <\/b> -111.62719<br\/>  <b>Detection Time: <\/b> 2024-01-22 10:13 UTC<br\/>  <b>Sensor: <\/b> NOAA-20 VIIRS<br\/> <b>Confidence: <\/b> Nominal<br\/>  <b>Day\/Night: <\/b> Night<br\/> <b>Scan: <\/b> 0.3 km<br\/> <b>Track: <\/b> 0.6 km<br\/> <b>FRP: <\/b> 2.66 MW<br\/> <b>Brightness: <\/b> 321.58 K" }, "geometry": { "type": "Point", "coordinates": [ -111.62719, 42.61223, 0.0 ] } },
{ "type": "Feature", "properties": { "Name": "Fire Detection Centroid ", "Description": "<b>Latitude: <\/b> 45.55404<br\/>  <b>Longitude: <\/b> -123.96198<br\/>  <b>Detection Time: <\/b> 2024-01-22 10:13 UTC<br\/>  <b>Sensor: <\/b> NOAA-20 VIIRS<br\/> <b>Confidence: <\/b> Nominal<br\/>  <b>Day\/Night: <\/b> Night<br\/> <b>Scan: <\/b> 0.4 km<br\/> <b>Track: <\/b> 0.4 km<br\/> <b>FRP: <\/b> 1.23 MW<br\/> <b>Brightness: <\/b> 302.74 K" }, "geometry": { "type": "Point", "coordinates": [ -123.96198, 45.55404, 0.0 ] } }
]
}
