{
"type": "FeatureCollection",
"crs": { "type": "name", "properties": { "name": "urn:ogc:def:crs:OGC:1.3:CRS84" } },
"features": [
{ "type": "Feature", "properties": { "Name": "Fire Detection Centroid ", "Description": "<b>Latitude: <\/b> 19.40558<br\/>  <b>Longitude: <\/b> -155.28714<br\/>  <b>Detection Time: <\/b> 2023-08-04 12:08 UTC<br\/>  <b>Sensor: <\/b> NOAA-20 VIIRS<br\/> <b>Confidence: <\/b> Nominal<br\/>  <b>Day\/Night: <\/b> Night<br\/> <b>Scan: <\/b> 0.43 km<br\/> <b>Track: <\/b> 0.38 km<br\/> <b>FRP: <\/b> 4.34 MW<br\/> <b>Brightness: <\/b> 310.33 K" }, "geometry": { "type": "Point", "coordinates": [ -155.28714, 19.40558, 0.0 ] } },
{ "type": "Feature", "properties": { "Name": "Fire Detection Centroid ", "Description": "<b>Latitude: <\/b> 19.40487<br\/>  <b>Longitude: <\/b> -155.28308<br\/>  <b>Detection Time: <\/b> 2023-08-04 12:08 UTC<br\/>  <b>Sensor: <\/b> NOAA-20 VIIRS<br\/> <b>Confidence: <\/b> Nominal<br\/>  <b>Day\/Night: <\/b> Night<br\/> <b>Scan: <\/b> 0.43 km<br\/> <b>Track: <\/b> 0.38 km<br\/> <b>FRP: <\/b> 2.06 MW<br\/> <b>Brightness: <\/b> 308.62 K" }, "geometry": { "type": "Point", "coordinates": [ -155.28308, 19.40487, 0.0 ] } },
{ "type": "Feature", "properties": { "Name": "Fire Detection Centroid ", "Description": "<b>Latitude: <\/b> 19.59811<br\/>  <b>Longitude: <\/b> -155.50444<br\/>  <b>Detection Time: <\/b> 2023-08-04 12:08 UTC<br\/>  <b>Sensor: <\/b> NOAA-20 VIIRS<br\/> <b>Confidence: <\/b> Nominal<br\/>  <b>Day\/Night: <\/b> Night<br\/> <b>Scan: <\/b> 0.42 km<br\/> <b>Track: <\/b> 0.38 km<br\/> <b>FRP: <\/b> 0.92 MW<br\/> <b>Brightness: <\/b> 298.71 K" }, "geometry": { "type": "Point", "coordinates": [ -155.50444, 19.59811, 0.0 ] } },
{ "type": "Feature", "properties": { "Name": "Fire Detection Centroid ", "Description": "<b>Latitude: <\/b> 19.59471<br\/>  <b>Longitude: <\/b> -155.50519<br\/>  <b>Detection Time: <\/b> 2023-08-04 12:08 UTC<br\/>  <b>Sensor: <\/b> NOAA-20 VIIRS<br\/> <b>Confidence: <\/b> Nominal<br\/>  <b>Day\/Night: <\/b> Night<br\/> <b>Scan: <\/b> 0.42 km<br\/> <b>Track: <\/b> 0.38 km<br\/> <b>FRP: <\/b> 0.92 MW<br\/> <b>Brightness: <\/b> 298.62 K" }, "geometry": { "type": "Point", "coordinates": [ -155.50519, 19.59471, 0.0 ] } },
{ "type": "Feature", "properties": { "Name": "Fire Detection Centroid ", "Description": "<b>Latitude: <\/b> 19.4118<br\/>  <b>Longitude: <\/b> -155.2818<br\/>  <b>Detection Time: <\/b> 2023-08-04 12:08 UTC<br\/>  <b>Sensor: <\/b> NOAA-20 VIIRS<br\/> <b>Confidence: <\/b> Nominal<br\/>  <b>Day\/Night: <\/b> Night<br\/> <b>Scan: <\/b> 0.43 km<br\/> <b>Track: <\/b> 0.38 km<br\/> <b>FRP: <\/b> 4.27 MW<br\/> <b>Brightness: <\/b> 312.08 K" }, "geometry": { "type": "Point", "coordinates": [ -155.2818, 19.4118, 0.0 ] } },
{ "type": "Feature", "properties": { "Name": "Fire Detection Centroid ", "Description": "<b>Latitude: <\/b> 19.40834<br\/>  <b>Longitude: <\/b> -155.28242<br\/>  <b>Detection Time: <\/b> 2023-08-04 12:08 UTC<br\/>  <b>Sensor: <\/b> NOAA-20 VIIRS<br\/> <b>Confidence: <\/b> Nominal<br\/>  <b>Day\/Night: <\/b> Night<br\/> <b>Scan: <\/b> 0.43 km<br\/> <b>Track: <\/b> 0.38 km<br\/> <b>FRP: <\/b> 2.06 MW<br\/> <b>Brightness: <\/b> 309.86 K" }, "geometry": { "type": "Point", "coordinates": [ -155.28242, 19.40834, 0.0 ] } },
{ "type": "Feature", "properties": { "Name": "Fire Detection Centroid ", "Description": "<b>Latitude: <\/b> 19.40763<br\/>  <b>Longitude: <\/b> -155.27835<br\/>  <b>Detection Time: <\/b> 2023-08-04 12:08 UTC<br\/>  <b>Sensor: <\/b> NOAA-20 VIIRS<br\/> <b>Confidence: <\/b> Nominal<br\/>  <b>Day\/Night: <\/b> Night<br\/> <b>Scan: <\/b> 0.43 km<br\/> <b>Track: <\/b> 0.38 km<br\/> <b>FRP: <\/b> 2.06 MW<br\/> <b>Brightness: <\/b> 310.31 K" }, "geometry": { "type": "Point", "coordinates": [ -155.27835, 19.40763, 0.0 ] } }
]
}
