{
"type": "FeatureCollection",
"crs": { "type": "name", "properties": { "name": "urn:ogc:def:crs:OGC:1.3:CRS84" } },
"features": [
{ "type": "Feature", "properties": { "Name": "Fire Detection Centroid ", "Description": "<b>Latitude: <\/b> 21.99755<br\/>  <b>Longitude: <\/b> -159.38148<br\/>  <b>Detection Time: <\/b> 2022-10-19 23:38 UTC<br\/>  <b>Sensor: <\/b> NOAA-20 VIIRS<br\/> <b>Confidence: <\/b> Nominal<br\/>  <b>Day\/Night: <\/b> Day<br\/> <b>Scan: <\/b> 0.4 km<br\/> <b>Track: <\/b> 0.4 km<br\/> <b>FRP: <\/b> 5.45 MW<br\/> <b>Brightness: <\/b> 344.46 K" }, "geometry": { "type": "Point", "coordinates": [ -159.38148, 21.99755, 0.0 ] } },
{ "type": "Feature", "properties": { "Name": "Fire Detection Centroid ", "Description": "<b>Latitude: <\/b> 21.99822<br\/>  <b>Longitude: <\/b> -159.37744<br\/>  <b>Detection Time: <\/b> 2022-10-19 23:38 UTC<br\/>  <b>Sensor: <\/b> NOAA-20 VIIRS<br\/> <b>Confidence: <\/b> Nominal<br\/>  <b>Day\/Night: <\/b> Day<br\/> <b>Scan: <\/b> 0.4 km<br\/> <b>Track: <\/b> 0.4 km<br\/> <b>FRP: <\/b> 5.45 MW<br\/> <b>Brightness: <\/b> 333.65 K" }, "geometry": { "type": "Point", "coordinates": [ -159.37744, 21.99822, 0.0 ] } },
{ "type": "Feature", "properties": { "Name": "Fire Detection Centroid ", "Description": "<b>Latitude: <\/b> 21.99799<br\/>  <b>Longitude: <\/b> -159.38106<br\/>  <b>Detection Time: <\/b> 2022-10-19 23:37 UTC<br\/>  <b>Sensor: <\/b> NOAA-20 VIIRS<br\/> <b>Confidence: <\/b> Nominal<br\/>  <b>Day\/Night: <\/b> Day<br\/> <b>Scan: <\/b> 0.42 km<br\/> <b>Track: <\/b> 0.38 km<br\/> <b>FRP: <\/b> 5.5 MW<br\/> <b>Brightness: <\/b> 344.46 K" }, "geometry": { "type": "Point", "coordinates": [ -159.38106, 21.99799, 0.0 ] } },
{ "type": "Feature", "properties": { "Name": "Fire Detection Centroid ", "Description": "<b>Latitude: <\/b> 21.99866<br\/>  <b>Longitude: <\/b> -159.377<br\/>  <b>Detection Time: <\/b> 2022-10-19 23:37 UTC<br\/>  <b>Sensor: <\/b> NOAA-20 VIIRS<br\/> <b>Confidence: <\/b> Nominal<br\/>  <b>Day\/Night: <\/b> Day<br\/> <b>Scan: <\/b> 0.42 km<br\/> <b>Track: <\/b> 0.38 km<br\/> <b>FRP: <\/b> 5.5 MW<br\/> <b>Brightness: <\/b> 333.65 K" }, "geometry": { "type": "Point", "coordinates": [ -159.377, 21.99866, 0.0 ] } }
]
}
