{
"type": "FeatureCollection",
"crs": { "type": "name", "properties": { "name": "urn:ogc:def:crs:OGC:1.3:CRS84" } },
"features": [
{ "type": "Feature", "properties": { "Name": "Fire Detection Centroid ", "Description": "<b>Latitude: <\/b> 19.40892<br\/>  <b>Longitude: <\/b> -155.27859<br\/>  <b>Detection Time: <\/b> 2023-03-11 11:06 UTC<br\/>  <b>Sensor: <\/b> NOAA-20 VIIRS<br\/> <b>Confidence: <\/b> Nominal<br\/>  <b>Day\/Night: <\/b> Night<br\/> <b>Scan: <\/b> 0.66 km<br\/> <b>Track: <\/b> 0.73 km<br\/> <b>FRP: <\/b> 3.23 MW<br\/> <b>Brightness: <\/b> 298.23 K" }, "geometry": { "type": "Point", "coordinates": [ -155.27859, 19.40892, 0.0 ] } }
]
}
