{
"type": "FeatureCollection",
"crs": { "type": "name", "properties": { "name": "urn:ogc:def:crs:OGC:1.3:CRS84" } },
"features": [
{ "type": "Feature", "properties": { "Name": "Fire Detection Centroid ", "Description": "<b>Latitude: <\/b> 18.92868<br\/>  <b>Longitude: <\/b> -70.35564<br\/>  <b>Detection Time: <\/b> 2022-10-01 06:19 UTC<br\/>  <b>Sensor: <\/b> NOAA-20 VIIRS<br\/> <b>Confidence: <\/b> Nominal<br\/>  <b>Day\/Night: <\/b> Night<br\/> <b>Scan: <\/b> 0.4 km<br\/> <b>Track: <\/b> 0.4 km<br\/> <b>FRP: <\/b> 24.66 MW<br\/> <b>Brightness: <\/b> 334.77 K" }, "geometry": { "type": "Point", "coordinates": [ -70.35564, 18.92868, 0.0 ] } },
{ "type": "Feature", "properties": { "Name": "Fire Detection Centroid ", "Description": "<b>Latitude: <\/b> 23.1489<br\/>  <b>Longitude: <\/b> -81.88476<br\/>  <b>Detection Time: <\/b> 2022-10-01 06:18 UTC<br\/>  <b>Sensor: <\/b> NOAA-20 VIIRS<br\/> <b>Confidence: <\/b> Nominal<br\/>  <b>Day\/Night: <\/b> Night<br\/> <b>Scan: <\/b> 0.5 km<br\/> <b>Track: <\/b> 0.7 km<br\/> <b>FRP: <\/b> 1.27 MW<br\/> <b>Brightness: <\/b> 300.96 K" }, "geometry": { "type": "Point", "coordinates": [ -81.88476, 23.1489, 0.0 ] } },
{ "type": "Feature", "properties": { "Name": "Fire Detection Centroid ", "Description": "<b>Latitude: <\/b> 27.86012<br\/>  <b>Longitude: <\/b> -82.60802<br\/>  <b>Detection Time: <\/b> 2022-10-01 06:17 UTC<br\/>  <b>Sensor: <\/b> NOAA-20 VIIRS<br\/> <b>Confidence: <\/b> Nominal<br\/>  <b>Day\/Night: <\/b> Night<br\/> <b>Scan: <\/b> 0.7 km<br\/> <b>Track: <\/b> 0.7 km<br\/> <b>FRP: <\/b> 2.31 MW<br\/> <b>Brightness: <\/b> 300.63 K" }, "geometry": { "type": "Point", "coordinates": [ -82.60802, 27.86012, 0.0 ] } },
{ "type": "Feature", "properties": { "Name": "Fire Detection Centroid ", "Description": "<b>Latitude: <\/b> 47.61528<br\/>  <b>Longitude: <\/b> -64.88182<br\/>  <b>Detection Time: <\/b> 2022-10-01 06:11 UTC<br\/>  <b>Sensor: <\/b> NOAA-20 VIIRS<br\/> <b>Confidence: <\/b> Nominal<br\/>  <b>Day\/Night: <\/b> Night<br\/> <b>Scan: <\/b> 0.4 km<br\/> <b>Track: <\/b> 0.4 km<br\/> <b>FRP: <\/b> 0.44 MW<br\/> <b>Brightness: <\/b> 295.33 K" }, "geometry": { "type": "Point", "coordinates": [ -64.88182, 47.61528, 0.0 ] } },
{ "type": "Feature", "properties": { "Name": "Fire Detection Centroid ", "Description": "<b>Latitude: <\/b> 47.86806<br\/>  <b>Longitude: <\/b> -64.6467<br\/>  <b>Detection Time: <\/b> 2022-10-01 06:11 UTC<br\/>  <b>Sensor: <\/b> NOAA-20 VIIRS<br\/> <b>Confidence: <\/b> Nominal<br\/>  <b>Day\/Night: <\/b> Night<br\/> <b>Scan: <\/b> 0.4 km<br\/> <b>Track: <\/b> 0.4 km<br\/> <b>FRP: <\/b> 1.82 MW<br\/> <b>Brightness: <\/b> 322.62 K" }, "geometry": { "type": "Point", "coordinates": [ -64.6467, 47.86806, 0.0 ] } },
{ "type": "Feature", "properties": { "Name": "Fire Detection Centroid ", "Description": "<b>Latitude: <\/b> 48.1883<br\/>  <b>Longitude: <\/b> -64.9234<br\/>  <b>Detection Time: <\/b> 2022-10-01 06:11 UTC<br\/>  <b>Sensor: <\/b> NOAA-20 VIIRS<br\/> <b>Confidence: <\/b> Nominal<br\/>  <b>Day\/Night: <\/b> Night<br\/> <b>Scan: <\/b> 0.4 km<br\/> <b>Track: <\/b> 0.4 km<br\/> <b>FRP: <\/b> 1.24 MW<br\/> <b>Brightness: <\/b> 304.84 K" }, "geometry": { "type": "Point", "coordinates": [ -64.9234, 48.1883, 0.0 ] } }
]
}
