{
"type": "FeatureCollection",
"crs": { "type": "name", "properties": { "name": "urn:ogc:def:crs:OGC:1.3:CRS84" } },
"features": [
{ "type": "Feature", "properties": { "Name": "Fire Detection Centroid ", "Description": "<b>Latitude: <\/b> 46.04234<br\/>  <b>Longitude: <\/b> -73.14461<br\/>  <b>Detection Time: <\/b> 2022-10-08 17:06 UTC<br\/>  <b>Sensor: <\/b> NOAA-20 VIIRS<br\/> <b>Confidence: <\/b> Nominal<br\/>  <b>Day\/Night: <\/b> Day<br\/> <b>Scan: <\/b> 0.4 km<br\/> <b>Track: <\/b> 0.5 km<br\/> <b>FRP: <\/b> 4.81 MW<br\/> <b>Brightness: <\/b> 339 K" }, "geometry": { "type": "Point", "coordinates": [ -73.14461, 46.04234, 0.0 ] } },
{ "type": "Feature", "properties": { "Name": "Fire Detection Centroid ", "Description": "<b>Latitude: <\/b> 41.58783<br\/>  <b>Longitude: <\/b> -74.182<br\/>  <b>Detection Time: <\/b> 2022-10-08 17:05 UTC<br\/>  <b>Sensor: <\/b> NOAA-20 VIIRS<br\/> <b>Confidence: <\/b> Nominal<br\/>  <b>Day\/Night: <\/b> Day<br\/> <b>Scan: <\/b> 0.3 km<br\/> <b>Track: <\/b> 0.6 km<br\/> <b>FRP: <\/b> 3.26 MW<br\/> <b>Brightness: <\/b> 340.64 K" }, "geometry": { "type": "Point", "coordinates": [ -74.182, 41.58783, 0.0 ] } },
{ "type": "Feature", "properties": { "Name": "Fire Detection Centroid ", "Description": "<b>Latitude: <\/b> 18.92638<br\/>  <b>Longitude: <\/b> -70.35447<br\/>  <b>Detection Time: <\/b> 2022-10-08 16:58 UTC<br\/>  <b>Sensor: <\/b> NOAA-20 VIIRS<br\/> <b>Confidence: <\/b> Nominal<br\/>  <b>Day\/Night: <\/b> Day<br\/> <b>Scan: <\/b> 0.7 km<br\/> <b>Track: <\/b> 0.8 km<br\/> <b>FRP: <\/b> 7.98 MW<br\/> <b>Brightness: <\/b> 328.76 K" }, "geometry": { "type": "Point", "coordinates": [ -70.35447, 18.92638, 0.0 ] } },
{ "type": "Feature", "properties": { "Name": "Fire Detection Centroid ", "Description": "<b>Latitude: <\/b> 19.40473<br\/>  <b>Longitude: <\/b> -155.2823<br\/>  <b>Detection Time: <\/b> 2022-10-08 12:32 UTC<br\/>  <b>Sensor: <\/b> NOAA-20 VIIRS<br\/> <b>Confidence: <\/b> Nominal<br\/>  <b>Day\/Night: <\/b> Night<br\/> <b>Scan: <\/b> 0.33 km<br\/> <b>Track: <\/b> 0.55 km<br\/> <b>FRP: <\/b> 0.39 MW<br\/> <b>Brightness: <\/b> 298.97 K" }, "geometry": { "type": "Point", "coordinates": [ -155.2823, 19.40473, 0.0 ] } },
{ "type": "Feature", "properties": { "Name": "Fire Detection Centroid ", "Description": "<b>Latitude: <\/b> 19.40971<br\/>  <b>Longitude: <\/b> -155.28123<br\/>  <b>Detection Time: <\/b> 2022-10-08 12:32 UTC<br\/>  <b>Sensor: <\/b> NOAA-20 VIIRS<br\/> <b>Confidence: <\/b> Nominal<br\/>  <b>Day\/Night: <\/b> Night<br\/> <b>Scan: <\/b> 0.33 km<br\/> <b>Track: <\/b> 0.55 km<br\/> <b>FRP: <\/b> 0.39 MW<br\/> <b>Brightness: <\/b> 295.15 K" }, "geometry": { "type": "Point", "coordinates": [ -155.28123, 19.40971, 0.0 ] } },
{ "type": "Feature", "properties": { "Name": "Fire Detection Centroid ", "Description": "<b>Latitude: <\/b> 19.40537<br\/>  <b>Longitude: <\/b> -155.2854<br\/>  <b>Detection Time: <\/b> 2022-10-08 12:32 UTC<br\/>  <b>Sensor: <\/b> NOAA-20 VIIRS<br\/> <b>Confidence: <\/b> Nominal<br\/>  <b>Day\/Night: <\/b> Night<br\/> <b>Scan: <\/b> 0.33 km<br\/> <b>Track: <\/b> 0.55 km<br\/> <b>FRP: <\/b> 0.39 MW<br\/> <b>Brightness: <\/b> 304.21 K" }, "geometry": { "type": "Point", "coordinates": [ -155.2854, 19.40537, 0.0 ] } }
]
}
