{
"type": "FeatureCollection",
"crs": { "type": "name", "properties": { "name": "urn:ogc:def:crs:OGC:1.3:CRS84" } },
"features": [
{ "type": "Feature", "properties": { "Name": "Fire Detection Centroid ", "Description": "<b>Latitude: <\/b> 19.09696<br\/>  <b>Longitude: <\/b> -71.09069<br\/>  <b>Detection Time: <\/b> 2024-03-04 05:29 UTC<br\/>  <b>Sensor: <\/b> NOAA-20 VIIRS<br\/> <b>Confidence: <\/b> Nominal<br\/>  <b>Day\/Night: <\/b> Night<br\/> <b>Scan: <\/b> 0.6 km<br\/> <b>Track: <\/b> 0.7 km<br\/> <b>FRP: <\/b> 3.26 MW<br\/> <b>Brightness: <\/b> 311.38 K" }, "geometry": { "type": "Point", "coordinates": [ -71.09069, 19.09696, 0.0 ] } },
{ "type": "Feature", "properties": { "Name": "Fire Detection Centroid ", "Description": "<b>Latitude: <\/b> 18.29382<br\/>  <b>Longitude: <\/b> -70.56462<br\/>  <b>Detection Time: <\/b> 2024-03-04 05:29 UTC<br\/>  <b>Sensor: <\/b> NOAA-20 VIIRS<br\/> <b>Confidence: <\/b> Nominal<br\/>  <b>Day\/Night: <\/b> Night<br\/> <b>Scan: <\/b> 0.6 km<br\/> <b>Track: <\/b> 0.7 km<br\/> <b>FRP: <\/b> 3.38 MW<br\/> <b>Brightness: <\/b> 321.51 K" }, "geometry": { "type": "Point", "coordinates": [ -70.56462, 18.29382, 0.0 ] } },
{ "type": "Feature", "properties": { "Name": "Fire Detection Centroid ", "Description": "<b>Latitude: <\/b> 18.50016<br\/>  <b>Longitude: <\/b> -70.53295<br\/>  <b>Detection Time: <\/b> 2024-03-04 05:29 UTC<br\/>  <b>Sensor: <\/b> NOAA-20 VIIRS<br\/> <b>Confidence: <\/b> Nominal<br\/>  <b>Day\/Night: <\/b> Night<br\/> <b>Scan: <\/b> 0.6 km<br\/> <b>Track: <\/b> 0.7 km<br\/> <b>FRP: <\/b> 3.06 MW<br\/> <b>Brightness: <\/b> 328.81 K" }, "geometry": { "type": "Point", "coordinates": [ -70.53295, 18.50016, 0.0 ] } },
{ "type": "Feature", "properties": { "Name": "Fire Detection Centroid ", "Description": "<b>Latitude: <\/b> 18.82102<br\/>  <b>Longitude: <\/b> -72.00521<br\/>  <b>Detection Time: <\/b> 2024-03-04 05:29 UTC<br\/>  <b>Sensor: <\/b> NOAA-20 VIIRS<br\/> <b>Confidence: <\/b> Nominal<br\/>  <b>Day\/Night: <\/b> Night<br\/> <b>Scan: <\/b> 0.7 km<br\/> <b>Track: <\/b> 0.8 km<br\/> <b>FRP: <\/b> 1.34 MW<br\/> <b>Brightness: <\/b> 299.54 K" }, "geometry": { "type": "Point", "coordinates": [ -72.00521, 18.82102, 0.0 ] } },
{ "type": "Feature", "properties": { "Name": "Fire Detection Centroid ", "Description": "<b>Latitude: <\/b> 18.8876<br\/>  <b>Longitude: <\/b> -71.13457<br\/>  <b>Detection Time: <\/b> 2024-03-04 05:29 UTC<br\/>  <b>Sensor: <\/b> NOAA-20 VIIRS<br\/> <b>Confidence: <\/b> Nominal<br\/>  <b>Day\/Night: <\/b> Night<br\/> <b>Scan: <\/b> 0.6 km<br\/> <b>Track: <\/b> 0.7 km<br\/> <b>FRP: <\/b> 1.83 MW<br\/> <b>Brightness: <\/b> 307.27 K" }, "geometry": { "type": "Point", "coordinates": [ -71.13457, 18.8876, 0.0 ] } }
]
}
