{
"type": "FeatureCollection",
"crs": { "type": "name", "properties": { "name": "urn:ogc:def:crs:OGC:1.3:CRS84" } },
"features": [
{ "type": "Feature", "properties": { "Name": "Fire Detection Centroid ", "Description": "<b>Latitude: <\/b> 19.40441<br\/>  <b>Longitude: <\/b> -155.28085<br\/>  <b>Detection Time: <\/b> 2023-04-16 11:32 UTC<br\/>  <b>Sensor: <\/b> NOAA-20 VIIRS<br\/> <b>Confidence: <\/b> Nominal<br\/>  <b>Day\/Night: <\/b> Night<br\/> <b>Scan: <\/b> 0.5 km<br\/> <b>Track: <\/b> 0.49 km<br\/> <b>FRP: <\/b> 2.81 MW<br\/> <b>Brightness: <\/b> 301.59 K" }, "geometry": { "type": "Point", "coordinates": [ -155.28085, 19.40441, 0.0 ] } }
]
}
