{
"type": "FeatureCollection",
"crs": { "type": "name", "properties": { "name": "urn:ogc:def:crs:OGC:1.3:CRS84" } },
"features": [
{ "type": "Feature", "properties": { "Name": "Fire Detection Centroid ", "Description": "<b>Latitude: <\/b> 36.21102<br\/>  <b>Longitude: <\/b> -76.20661<br\/>  <b>Detection Time: <\/b> 2023-07-02 16:58 UTC<br\/>  <b>Sensor: <\/b> NOAA-20 VIIRS<br\/> <b>Confidence: <\/b> Nominal<br\/>  <b>Day\/Night: <\/b> Day<br\/> <b>Scan: <\/b> 0.7 km<br\/> <b>Track: <\/b> 0.8 km<br\/> <b>FRP: <\/b> 6.09 MW<br\/> <b>Brightness: <\/b> 335.86 K" }, "geometry": { "type": "Point", "coordinates": [ -76.20661, 36.21102, 0.0 ] } }
]
}
