{
"type": "FeatureCollection",
"crs": { "type": "name", "properties": { "name": "urn:ogc:def:crs:OGC:1.3:CRS84" } },
"features": [
{ "type": "Feature", "properties": { "Name": "Fire Detection Centroid ", "Description": "<b>Latitude: <\/b> 32.49687<br\/>  <b>Longitude: <\/b> -116.79816<br\/>  <b>Detection Time: <\/b> 2023-12-04 10:35 UTC<br\/>  <b>Sensor: <\/b> NOAA-20 VIIRS<br\/> <b>Confidence: <\/b> Nominal<br\/>  <b>Day\/Night: <\/b> Night<br\/> <b>Scan: <\/b> 0.7 km<br\/> <b>Track: <\/b> 0.7 km<br\/> <b>FRP: <\/b> 1.01 MW<br\/> <b>Brightness: <\/b> 300.72 K" }, "geometry": { "type": "Point", "coordinates": [ -116.79816, 32.49687, 0.0 ] } },
{ "type": "Feature", "properties": { "Name": "Fire Detection Centroid ", "Description": "<b>Latitude: <\/b> 32.49663<br\/>  <b>Longitude: <\/b> -116.80167<br\/>  <b>Detection Time: <\/b> 2023-12-04 10:34 UTC<br\/>  <b>Sensor: <\/b> NOAA-20 VIIRS<br\/> <b>Confidence: <\/b> Nominal<br\/>  <b>Day\/Night: <\/b> Night<br\/> <b>Scan: <\/b> 0.65 km<br\/> <b>Track: <\/b> 0.73 km<br\/> <b>FRP: <\/b> 1.02 MW<br\/> <b>Brightness: <\/b> 300.72 K" }, "geometry": { "type": "Point", "coordinates": [ -116.80167, 32.49663, 0.0 ] } },
{ "type": "Feature", "properties": { "Name": "Fire Detection Centroid ", "Description": "<b>Latitude: <\/b> 38.01606<br\/>  <b>Longitude: <\/b> -122.1142<br\/>  <b>Detection Time: <\/b> 2023-12-04 10:34 UTC<br\/>  <b>Sensor: <\/b> NOAA-20 VIIRS<br\/> <b>Confidence: <\/b> Nominal<br\/>  <b>Day\/Night: <\/b> Night<br\/> <b>Scan: <\/b> 0.49 km<br\/> <b>Track: <\/b> 0.48 km<br\/> <b>FRP: <\/b> 1.08 MW<br\/> <b>Brightness: <\/b> 296.66 K" }, "geometry": { "type": "Point", "coordinates": [ -122.1142, 38.01606, 0.0 ] } },
{ "type": "Feature", "properties": { "Name": "Fire Detection Centroid ", "Description": "<b>Latitude: <\/b> 40.41055<br\/>  <b>Longitude: <\/b> -110.76653<br\/>  <b>Detection Time: <\/b> 2023-12-04 10:32 UTC<br\/>  <b>Sensor: <\/b> NOAA-20 VIIRS<br\/> <b>Confidence: <\/b> Nominal<br\/>  <b>Day\/Night: <\/b> Night<br\/> <b>Scan: <\/b> 0.8 km<br\/> <b>Track: <\/b> 0.8 km<br\/> <b>FRP: <\/b> 0.81 MW<br\/> <b>Brightness: <\/b> 297.85 K" }, "geometry": { "type": "Point", "coordinates": [ -110.76653, 40.41055, 0.0 ] } },
{ "type": "Feature", "properties": { "Name": "Fire Detection Centroid ", "Description": "<b>Latitude: <\/b> 47.57195<br\/>  <b>Longitude: <\/b> -122.37184<br\/>  <b>Detection Time: <\/b> 2023-12-04 10:32 UTC<br\/>  <b>Sensor: <\/b> NOAA-20 VIIRS<br\/> <b>Confidence: <\/b> Nominal<br\/>  <b>Day\/Night: <\/b> Night<br\/> <b>Scan: <\/b> 0.46 km<br\/> <b>Track: <\/b> 0.39 km<br\/> <b>FRP: <\/b> 1.08 MW<br\/> <b>Brightness: <\/b> 310.74 K" }, "geometry": { "type": "Point", "coordinates": [ -122.37184, 47.57195, 0.0 ] } },
{ "type": "Feature", "properties": { "Name": "Fire Detection Centroid ", "Description": "<b>Latitude: <\/b> 40.4105<br\/>  <b>Longitude: <\/b> -110.77049<br\/>  <b>Detection Time: <\/b> 2023-12-04 10:32 UTC<br\/>  <b>Sensor: <\/b> NOAA-20 VIIRS<br\/> <b>Confidence: <\/b> Nominal<br\/>  <b>Day\/Night: <\/b> Night<br\/> <b>Scan: <\/b> 0.79 km<br\/> <b>Track: <\/b> 0.78 km<br\/> <b>FRP: <\/b> 0.82 MW<br\/> <b>Brightness: <\/b> 297.85 K" }, "geometry": { "type": "Point", "coordinates": [ -110.77049, 40.4105, 0.0 ] } }
]
}
