{
"type": "FeatureCollection",
"crs": { "type": "name", "properties": { "name": "urn:ogc:def:crs:OGC:1.3:CRS84" } },
"features": [
{ "type": "Feature", "properties": { "Name": "Fire Detection Centroid ", "Description": "<b>Latitude: <\/b> 18.50886<br\/>  <b>Longitude: <\/b> -69.34328<br\/>  <b>Detection Time: <\/b> 2023-10-12 05:29 UTC<br\/>  <b>Sensor: <\/b> NOAA-20 VIIRS<br\/> <b>Confidence: <\/b> Nominal<br\/>  <b>Day\/Night: <\/b> Night<br\/> <b>Scan: <\/b> 0.5 km<br\/> <b>Track: <\/b> 0.6 km<br\/> <b>FRP: <\/b> 0.84 MW<br\/> <b>Brightness: <\/b> 302.66 K" }, "geometry": { "type": "Point", "coordinates": [ -69.34328, 18.50886, 0.0 ] } },
{ "type": "Feature", "properties": { "Name": "Fire Detection Centroid ", "Description": "<b>Latitude: <\/b> 18.92964<br\/>  <b>Longitude: <\/b> -70.35124<br\/>  <b>Detection Time: <\/b> 2023-10-12 05:29 UTC<br\/>  <b>Sensor: <\/b> NOAA-20 VIIRS<br\/> <b>Confidence: <\/b> Nominal<br\/>  <b>Day\/Night: <\/b> Night<br\/> <b>Scan: <\/b> 0.6 km<br\/> <b>Track: <\/b> 0.7 km<br\/> <b>FRP: <\/b> 3.28 MW<br\/> <b>Brightness: <\/b> 305.58 K" }, "geometry": { "type": "Point", "coordinates": [ -70.35124, 18.92964, 0.0 ] } },
{ "type": "Feature", "properties": { "Name": "Fire Detection Centroid ", "Description": "<b>Latitude: <\/b> 18.93015<br\/>  <b>Longitude: <\/b> -70.35705<br\/>  <b>Detection Time: <\/b> 2023-10-12 05:29 UTC<br\/>  <b>Sensor: <\/b> NOAA-20 VIIRS<br\/> <b>Confidence: <\/b> Nominal<br\/>  <b>Day\/Night: <\/b> Night<br\/> <b>Scan: <\/b> 0.6 km<br\/> <b>Track: <\/b> 0.7 km<br\/> <b>FRP: <\/b> 4.09 MW<br\/> <b>Brightness: <\/b> 325.23 K" }, "geometry": { "type": "Point", "coordinates": [ -70.35705, 18.93015, 0.0 ] } }
]
}
