{
"type": "FeatureCollection",
"crs": { "type": "name", "properties": { "name": "urn:ogc:def:crs:OGC:1.3:CRS84" } },
"features": [
{ "type": "Feature", "properties": { "Name": "Fire Detection Centroid ", "Description": "<b>Latitude: <\/b> 18.92926<br\/>  <b>Longitude: <\/b> -70.3557<br\/>  <b>Detection Time: <\/b> 2022-08-16 05:41 UTC<br\/>  <b>Sensor: <\/b> NOAA-20 VIIRS<br\/> <b>Confidence: <\/b> Nominal<br\/>  <b>Day\/Night: <\/b> Night<br\/> <b>Scan: <\/b> 0.3 km<br\/> <b>Track: <\/b> 0.6 km<br\/> <b>FRP: <\/b> 4.3 MW<br\/> <b>Brightness: <\/b> 327.03 K" }, "geometry": { "type": "Point", "coordinates": [ -70.3557, 18.92926, 0.0 ] } },
{ "type": "Feature", "properties": { "Name": "Fire Detection Centroid ", "Description": "<b>Latitude: <\/b> 45.28107<br\/>  <b>Longitude: <\/b> -66.01499<br\/>  <b>Detection Time: <\/b> 2022-08-16 05:33 UTC<br\/>  <b>Sensor: <\/b> NOAA-20 VIIRS<br\/> <b>Confidence: <\/b> Nominal<br\/>  <b>Day\/Night: <\/b> Night<br\/> <b>Scan: <\/b> 0.4 km<br\/> <b>Track: <\/b> 0.6 km<br\/> <b>FRP: <\/b> 1.72 MW<br\/> <b>Brightness: <\/b> 308.82 K" }, "geometry": { "type": "Point", "coordinates": [ -66.01499, 45.28107, 0.0 ] } },
{ "type": "Feature", "properties": { "Name": "Fire Detection Centroid ", "Description": "<b>Latitude: <\/b> 45.28126<br\/>  <b>Longitude: <\/b> -66.01971<br\/>  <b>Detection Time: <\/b> 2022-08-16 05:33 UTC<br\/>  <b>Sensor: <\/b> NOAA-20 VIIRS<br\/> <b>Confidence: <\/b> Nominal<br\/>  <b>Day\/Night: <\/b> Night<br\/> <b>Scan: <\/b> 0.4 km<br\/> <b>Track: <\/b> 0.6 km<br\/> <b>FRP: <\/b> 1.32 MW<br\/> <b>Brightness: <\/b> 299.66 K" }, "geometry": { "type": "Point", "coordinates": [ -66.01971, 45.28126, 0.0 ] } },
{ "type": "Feature", "properties": { "Name": "Fire Detection Centroid ", "Description": "<b>Latitude: <\/b> 45.28334<br\/>  <b>Longitude: <\/b> -66.0135<br\/>  <b>Detection Time: <\/b> 2022-08-16 05:33 UTC<br\/>  <b>Sensor: <\/b> NOAA-20 VIIRS<br\/> <b>Confidence: <\/b> Nominal<br\/>  <b>Day\/Night: <\/b> Night<br\/> <b>Scan: <\/b> 0.4 km<br\/> <b>Track: <\/b> 0.6 km<br\/> <b>FRP: <\/b> 1.11 MW<br\/> <b>Brightness: <\/b> 301.2 K" }, "geometry": { "type": "Point", "coordinates": [ -66.0135, 45.28334, 0.0 ] } },
{ "type": "Feature", "properties": { "Name": "Fire Detection Centroid ", "Description": "<b>Latitude: <\/b> 45.27801<br\/>  <b>Longitude: <\/b> -66.01409<br\/>  <b>Detection Time: <\/b> 2022-08-16 05:33 UTC<br\/>  <b>Sensor: <\/b> NOAA-20 VIIRS<br\/> <b>Confidence: <\/b> Nominal<br\/>  <b>Day\/Night: <\/b> Night<br\/> <b>Scan: <\/b> 0.4 km<br\/> <b>Track: <\/b> 0.6 km<br\/> <b>FRP: <\/b> 1.11 MW<br\/> <b>Brightness: <\/b> 301.3 K" }, "geometry": { "type": "Point", "coordinates": [ -66.01409, 45.27801, 0.0 ] } }
]
}
