{
"type": "FeatureCollection",
"crs": { "type": "name", "properties": { "name": "urn:ogc:def:crs:OGC:1.3:CRS84" } },
"features": [
{ "type": "Feature", "properties": { "Name": "Fire Detection Centroid ", "Description": "<b>Latitude: <\/b> 18.25523<br\/>  <b>Longitude: <\/b> -78.24311<br\/>  <b>Detection Time: <\/b> 2022-10-08 18:39 UTC<br\/>  <b>Sensor: <\/b> NOAA-20 VIIRS<br\/> <b>Confidence: <\/b> Nominal<br\/>  <b>Day\/Night: <\/b> Day<br\/> <b>Scan: <\/b> 0.5 km<br\/> <b>Track: <\/b> 0.4 km<br\/> <b>FRP: <\/b> 6.09 MW<br\/> <b>Brightness: <\/b> 333.26 K" }, "geometry": { "type": "Point", "coordinates": [ -78.24311, 18.25523, 0.0 ] } },
{ "type": "Feature", "properties": { "Name": "Fire Detection Centroid ", "Description": "<b>Latitude: <\/b> 18.06939<br\/>  <b>Longitude: <\/b> -71.65964<br\/>  <b>Detection Time: <\/b> 2022-10-08 18:39 UTC<br\/>  <b>Sensor: <\/b> NOAA-20 VIIRS<br\/> <b>Confidence: <\/b> High<br\/>  <b>Day\/Night: <\/b> Day<br\/> <b>Scan: <\/b> 0.4 km<br\/> <b>Track: <\/b> 0.6 km<br\/> <b>FRP: <\/b> 7.79 MW<br\/> <b>Brightness: <\/b> 367 K" }, "geometry": { "type": "Point", "coordinates": [ -71.65964, 18.06939, 0.0 ] } },
{ "type": "Feature", "properties": { "Name": "Fire Detection Centroid ", "Description": "<b>Latitude: <\/b> 18.06856<br\/>  <b>Longitude: <\/b> -71.65862<br\/>  <b>Detection Time: <\/b> 2022-10-08 18:39 UTC<br\/>  <b>Sensor: <\/b> NOAA-20 VIIRS<br\/> <b>Confidence: <\/b> High<br\/>  <b>Day\/Night: <\/b> Day<br\/> <b>Scan: <\/b> 0.4 km<br\/> <b>Track: <\/b> 0.6 km<br\/> <b>FRP: <\/b> 6.7 MW<br\/> <b>Brightness: <\/b> 367 K" }, "geometry": { "type": "Point", "coordinates": [ -71.65862, 18.06856, 0.0 ] } },
{ "type": "Feature", "properties": { "Name": "Fire Detection Centroid ", "Description": "<b>Latitude: <\/b> 46.04234<br\/>  <b>Longitude: <\/b> -73.14461<br\/>  <b>Detection Time: <\/b> 2022-10-08 17:06 UTC<br\/>  <b>Sensor: <\/b> NOAA-20 VIIRS<br\/> <b>Confidence: <\/b> Nominal<br\/>  <b>Day\/Night: <\/b> Day<br\/> <b>Scan: <\/b> 0.4 km<br\/> <b>Track: <\/b> 0.5 km<br\/> <b>FRP: <\/b> 4.81 MW<br\/> <b>Brightness: <\/b> 339 K" }, "geometry": { "type": "Point", "coordinates": [ -73.14461, 46.04234, 0.0 ] } },
{ "type": "Feature", "properties": { "Name": "Fire Detection Centroid ", "Description": "<b>Latitude: <\/b> 41.58852<br\/>  <b>Longitude: <\/b> -74.18088<br\/>  <b>Detection Time: <\/b> 2022-10-08 17:05 UTC<br\/>  <b>Sensor: <\/b> NOAA-20 VIIRS<br\/> <b>Confidence: <\/b> Nominal<br\/>  <b>Day\/Night: <\/b> Day<br\/> <b>Scan: <\/b> 0.33 km<br\/> <b>Track: <\/b> 0.55 km<br\/> <b>FRP: <\/b> 3.26 MW<br\/> <b>Brightness: <\/b> 340.64 K" }, "geometry": { "type": "Point", "coordinates": [ -74.18088, 41.58852, 0.0 ] } },
{ "type": "Feature", "properties": { "Name": "Fire Detection Centroid ", "Description": "<b>Latitude: <\/b> 18.92638<br\/>  <b>Longitude: <\/b> -70.35447<br\/>  <b>Detection Time: <\/b> 2022-10-08 16:58 UTC<br\/>  <b>Sensor: <\/b> NOAA-20 VIIRS<br\/> <b>Confidence: <\/b> Nominal<br\/>  <b>Day\/Night: <\/b> Day<br\/> <b>Scan: <\/b> 0.7 km<br\/> <b>Track: <\/b> 0.8 km<br\/> <b>FRP: <\/b> 7.98 MW<br\/> <b>Brightness: <\/b> 328.76 K" }, "geometry": { "type": "Point", "coordinates": [ -70.35447, 18.92638, 0.0 ] } },
{ "type": "Feature", "properties": { "Name": "Fire Detection Centroid ", "Description": "<b>Latitude: <\/b> 18.92726<br\/>  <b>Longitude: <\/b> -70.35255<br\/>  <b>Detection Time: <\/b> 2022-10-08 16:58 UTC<br\/>  <b>Sensor: <\/b> NOAA-20 VIIRS<br\/> <b>Confidence: <\/b> Nominal<br\/>  <b>Day\/Night: <\/b> Day<br\/> <b>Scan: <\/b> 0.71 km<br\/> <b>Track: <\/b> 0.75 km<br\/> <b>FRP: <\/b> 7.98 MW<br\/> <b>Brightness: <\/b> 328.76 K" }, "geometry": { "type": "Point", "coordinates": [ -70.35255, 18.92726, 0.0 ] } },
{ "type": "Feature", "properties": { "Name": "Fire Detection Centroid ", "Description": "<b>Latitude: <\/b> 18.21717<br\/>  <b>Longitude: <\/b> -70.45697<br\/>  <b>Detection Time: <\/b> 2022-10-08 16:58 UTC<br\/>  <b>Sensor: <\/b> NOAA-20 VIIRS<br\/> <b>Confidence: <\/b> Nominal<br\/>  <b>Day\/Night: <\/b> Day<br\/> <b>Scan: <\/b> 0.75 km<br\/> <b>Track: <\/b> 0.77 km<br\/> <b>FRP: <\/b> 3.72 MW<br\/> <b>Brightness: <\/b> 327.69 K" }, "geometry": { "type": "Point", "coordinates": [ -70.45697, 18.21717, 0.0 ] } }
]
}
