{
"type": "FeatureCollection",
"crs": { "type": "name", "properties": { "name": "urn:ogc:def:crs:OGC:1.3:CRS84" } },
"features": [
{ "type": "Feature", "properties": { "Name": "Fire Detection Centroid ", "Description": "<b>Latitude: <\/b> 45.96807<br\/>  <b>Longitude: <\/b> -65.22549<br\/>  <b>Detection Time: <\/b> 2023-03-12 16:59 UTC<br\/>  <b>Sensor: <\/b> NOAA-20 VIIRS<br\/> <b>Confidence: <\/b> Nominal<br\/>  <b>Day\/Night: <\/b> Day<br\/> <b>Scan: <\/b> 0.4 km<br\/> <b>Track: <\/b> 0.4 km<br\/> <b>FRP: <\/b> 9.48 MW<br\/> <b>Brightness: <\/b> 327.79 K" }, "geometry": { "type": "Point", "coordinates": [ -65.22549, 45.96807, 0.0 ] } }
]
}
