{
"type": "FeatureCollection",
"crs": { "type": "name", "properties": { "name": "urn:ogc:def:crs:OGC:1.3:CRS84" } },
"features": [
{ "type": "Feature", "properties": { "Name": "Fire Detection Centroid ", "Description": "<b>Latitude: <\/b> 46.33615<br\/>  <b>Longitude: <\/b> -123.79022<br\/>  <b>Detection Time: <\/b> 2023-11-26 11:21 UTC<br\/>  <b>Sensor: <\/b> NOAA-20 VIIRS<br\/> <b>Confidence: <\/b> Nominal<br\/>  <b>Day\/Night: <\/b> Night<br\/> <b>Scan: <\/b> 0.5 km<br\/> <b>Track: <\/b> 0.6 km<br\/> <b>FRP: <\/b> 1.62 MW<br\/> <b>Brightness: <\/b> 318.72 K" }, "geometry": { "type": "Point", "coordinates": [ -123.79022, 46.33615, 0.0 ] } },
{ "type": "Feature", "properties": { "Name": "Fire Detection Centroid ", "Description": "<b>Latitude: <\/b> 48.77783<br\/>  <b>Longitude: <\/b> -124.20885<br\/>  <b>Detection Time: <\/b> 2023-11-26 11:21 UTC<br\/>  <b>Sensor: <\/b> NOAA-20 VIIRS<br\/> <b>Confidence: <\/b> Nominal<br\/>  <b>Day\/Night: <\/b> Night<br\/> <b>Scan: <\/b> 0.4 km<br\/> <b>Track: <\/b> 0.6 km<br\/> <b>FRP: <\/b> 0.64 MW<br\/> <b>Brightness: <\/b> 301.24 K" }, "geometry": { "type": "Point", "coordinates": [ -124.20885, 48.77783, 0.0 ] } },
{ "type": "Feature", "properties": { "Name": "Fire Detection Centroid ", "Description": "<b>Latitude: <\/b> 47.57035<br\/>  <b>Longitude: <\/b> -122.37157<br\/>  <b>Detection Time: <\/b> 2023-11-26 11:21 UTC<br\/>  <b>Sensor: <\/b> NOAA-20 VIIRS<br\/> <b>Confidence: <\/b> Nominal<br\/>  <b>Day\/Night: <\/b> Night<br\/> <b>Scan: <\/b> 0.5 km<br\/> <b>Track: <\/b> 0.7 km<br\/> <b>FRP: <\/b> 1.41 MW<br\/> <b>Brightness: <\/b> 313.64 K" }, "geometry": { "type": "Point", "coordinates": [ -122.37157, 47.57035, 0.0 ] } },
{ "type": "Feature", "properties": { "Name": "Fire Detection Centroid ", "Description": "<b>Latitude: <\/b> 48.77783<br\/>  <b>Longitude: <\/b> -124.20885<br\/>  <b>Detection Time: <\/b> 2023-11-26 11:21 UTC<br\/>  <b>Sensor: <\/b> NOAA-20 VIIRS<br\/> <b>Confidence: <\/b> Nominal<br\/>  <b>Day\/Night: <\/b> Night<br\/> <b>Scan: <\/b> 0.4 km<br\/> <b>Track: <\/b> 0.6 km<br\/> <b>FRP: <\/b> 0.64 MW<br\/> <b>Brightness: <\/b> 301.24 K" }, "geometry": { "type": "Point", "coordinates": [ -124.20885, 48.77783, 0.0 ] } },
{ "type": "Feature", "properties": { "Name": "Fire Detection Centroid ", "Description": "<b>Latitude: <\/b> 46.33352<br\/>  <b>Longitude: <\/b> -123.79244<br\/>  <b>Detection Time: <\/b> 2023-11-26 11:21 UTC<br\/>  <b>Sensor: <\/b> NOAA-20 VIIRS<br\/> <b>Confidence: <\/b> Nominal<br\/>  <b>Day\/Night: <\/b> Night<br\/> <b>Scan: <\/b> 0.49 km<br\/> <b>Track: <\/b> 0.65 km<br\/> <b>FRP: <\/b> 1.75 MW<br\/> <b>Brightness: <\/b> 307.02 K" }, "geometry": { "type": "Point", "coordinates": [ -123.79244, 46.33352, 0.0 ] } },
{ "type": "Feature", "properties": { "Name": "Fire Detection Centroid ", "Description": "<b>Latitude: <\/b> 46.33583<br\/>  <b>Longitude: <\/b> -123.79297<br\/>  <b>Detection Time: <\/b> 2023-11-26 11:21 UTC<br\/>  <b>Sensor: <\/b> NOAA-20 VIIRS<br\/> <b>Confidence: <\/b> Nominal<br\/>  <b>Day\/Night: <\/b> Night<br\/> <b>Scan: <\/b> 0.49 km<br\/> <b>Track: <\/b> 0.65 km<br\/> <b>FRP: <\/b> 1.63 MW<br\/> <b>Brightness: <\/b> 318.72 K" }, "geometry": { "type": "Point", "coordinates": [ -123.79297, 46.33583, 0.0 ] } },
{ "type": "Feature", "properties": { "Name": "Fire Detection Centroid ", "Description": "<b>Latitude: <\/b> 46.33386<br\/>  <b>Longitude: <\/b> -123.78979<br\/>  <b>Detection Time: <\/b> 2023-11-26 11:21 UTC<br\/>  <b>Sensor: <\/b> NOAA-20 VIIRS<br\/> <b>Confidence: <\/b> Nominal<br\/>  <b>Day\/Night: <\/b> Night<br\/> <b>Scan: <\/b> 0.5 km<br\/> <b>Track: <\/b> 0.6 km<br\/> <b>FRP: <\/b> 1.75 MW<br\/> <b>Brightness: <\/b> 307.02 K" }, "geometry": { "type": "Point", "coordinates": [ -123.78979, 46.33386, 0.0 ] } },
{ "type": "Feature", "properties": { "Name": "Fire Detection Centroid ", "Description": "<b>Latitude: <\/b> 47.57029<br\/>  <b>Longitude: <\/b> -122.37508<br\/>  <b>Detection Time: <\/b> 2023-11-26 11:21 UTC<br\/>  <b>Sensor: <\/b> NOAA-20 VIIRS<br\/> <b>Confidence: <\/b> Nominal<br\/>  <b>Day\/Night: <\/b> Night<br\/> <b>Scan: <\/b> 0.51 km<br\/> <b>Track: <\/b> 0.66 km<br\/> <b>FRP: <\/b> 1.42 MW<br\/> <b>Brightness: <\/b> 313.64 K" }, "geometry": { "type": "Point", "coordinates": [ -122.37508, 47.57029, 0.0 ] } },
{ "type": "Feature", "properties": { "Name": "Fire Detection Centroid ", "Description": "<b>Latitude: <\/b> 48.77803<br\/>  <b>Longitude: <\/b> -124.2131<br\/>  <b>Detection Time: <\/b> 2023-11-26 11:19 UTC<br\/>  <b>Sensor: <\/b> NOAA-20 VIIRS<br\/> <b>Confidence: <\/b> Nominal<br\/>  <b>Day\/Night: <\/b> Night<br\/> <b>Scan: <\/b> 0.39 km<br\/> <b>Track: <\/b> 0.59 km<br\/> <b>FRP: <\/b> 0.65 MW<br\/> <b>Brightness: <\/b> 301.24 K" }, "geometry": { "type": "Point", "coordinates": [ -124.2131, 48.77803, 0.0 ] } }
]
}
