{
"type": "FeatureCollection",
"crs": { "type": "name", "properties": { "name": "urn:ogc:def:crs:OGC:1.3:CRS84" } },
"features": [
{ "type": "Feature", "properties": { "Name": "Fire Detection Centroid ", "Description": "<b>Latitude: <\/b> 45.13991<br\/>  <b>Longitude: <\/b> -64.43166<br\/>  <b>Detection Time: <\/b> 2022-11-20 16:59 UTC<br\/>  <b>Sensor: <\/b> NOAA-20 VIIRS<br\/> <b>Confidence: <\/b> Nominal<br\/>  <b>Day\/Night: <\/b> Day<br\/> <b>Scan: <\/b> 0.4 km<br\/> <b>Track: <\/b> 0.4 km<br\/> <b>FRP: <\/b> 3.75 MW<br\/> <b>Brightness: <\/b> 326.86 K" }, "geometry": { "type": "Point", "coordinates": [ -64.43166, 45.13991, 0.0 ] } }
]
}
