{
"type": "FeatureCollection",
"crs": { "type": "name", "properties": { "name": "urn:ogc:def:crs:OGC:1.3:CRS84" } },
"features": [
{ "type": "Feature", "properties": { "Name": "Fire Detection Centroid ", "Description": "<b>Latitude: <\/b> 40.5891<br\/>  <b>Longitude: <\/b> -74.21062<br\/>  <b>Detection Time: <\/b> 2024-01-02 06:26 UTC<br\/>  <b>Sensor: <\/b> NOAA-20 VIIRS<br\/> <b>Confidence: <\/b> Nominal<br\/>  <b>Day\/Night: <\/b> Night<br\/> <b>Scan: <\/b> 0.4 km<br\/> <b>Track: <\/b> 0.4 km<br\/> <b>FRP: <\/b> 0.67 MW<br\/> <b>Brightness: <\/b> 302.13 K" }, "geometry": { "type": "Point", "coordinates": [ -74.21062, 40.5891, 0.0 ] } },
{ "type": "Feature", "properties": { "Name": "Fire Detection Centroid ", "Description": "<b>Latitude: <\/b> 40.63617<br\/>  <b>Longitude: <\/b> -74.22391<br\/>  <b>Detection Time: <\/b> 2024-01-02 06:26 UTC<br\/>  <b>Sensor: <\/b> NOAA-20 VIIRS<br\/> <b>Confidence: <\/b> Nominal<br\/>  <b>Day\/Night: <\/b> Night<br\/> <b>Scan: <\/b> 0.4 km<br\/> <b>Track: <\/b> 0.4 km<br\/> <b>FRP: <\/b> 1.12 MW<br\/> <b>Brightness: <\/b> 296.02 K" }, "geometry": { "type": "Point", "coordinates": [ -74.22391, 40.63617, 0.0 ] } },
{ "type": "Feature", "properties": { "Name": "Fire Detection Centroid ", "Description": "<b>Latitude: <\/b> 46.04421<br\/>  <b>Longitude: <\/b> -73.14104<br\/>  <b>Detection Time: <\/b> 2024-01-02 06:24 UTC<br\/>  <b>Sensor: <\/b> NOAA-20 VIIRS<br\/> <b>Confidence: <\/b> Nominal<br\/>  <b>Day\/Night: <\/b> Night<br\/> <b>Scan: <\/b> 0.4 km<br\/> <b>Track: <\/b> 0.4 km<br\/> <b>FRP: <\/b> 0.58 MW<br\/> <b>Brightness: <\/b> 297.45 K" }, "geometry": { "type": "Point", "coordinates": [ -73.14104, 46.04421, 0.0 ] } }
]
}
