{
"type": "FeatureCollection",
"crs": { "type": "name", "properties": { "name": "urn:ogc:def:crs:OGC:1.3:CRS84" } },
"features": [
{ "type": "Feature", "properties": { "Name": "Fire Detection Centroid ", "Description": "<b>Latitude: <\/b> 49.09656<br\/>  <b>Longitude: <\/b> -123.01595<br\/>  <b>Detection Time: <\/b> 2023-05-13 11:17 UTC<br\/>  <b>Sensor: <\/b> NOAA-20 VIIRS<br\/> <b>Confidence: <\/b> Nominal<br\/>  <b>Day\/Night: <\/b> Night<br\/> <b>Scan: <\/b> 0.36 km<br\/> <b>Track: <\/b> 0.58 km<br\/> <b>FRP: <\/b> 0.44 MW<br\/> <b>Brightness: <\/b> 305.62 K" }, "geometry": { "type": "Point", "coordinates": [ -123.01595, 49.09656, 0.0 ] } },
{ "type": "Feature", "properties": { "Name": "Fire Detection Centroid ", "Description": "<b>Latitude: <\/b> 49.14552<br\/>  <b>Longitude: <\/b> -123.02288<br\/>  <b>Detection Time: <\/b> 2023-05-13 11:17 UTC<br\/>  <b>Sensor: <\/b> NOAA-20 VIIRS<br\/> <b>Confidence: <\/b> Nominal<br\/>  <b>Day\/Night: <\/b> Night<br\/> <b>Scan: <\/b> 0.36 km<br\/> <b>Track: <\/b> 0.58 km<br\/> <b>FRP: <\/b> 0.59 MW<br\/> <b>Brightness: <\/b> 296.77 K" }, "geometry": { "type": "Point", "coordinates": [ -123.02288, 49.14552, 0.0 ] } },
{ "type": "Feature", "properties": { "Name": "Fire Detection Centroid ", "Description": "<b>Latitude: <\/b> 49.14491<br\/>  <b>Longitude: <\/b> -123.02103<br\/>  <b>Detection Time: <\/b> 2023-05-13 11:17 UTC<br\/>  <b>Sensor: <\/b> NOAA-20 VIIRS<br\/> <b>Confidence: <\/b> Nominal<br\/>  <b>Day\/Night: <\/b> Night<br\/> <b>Scan: <\/b> 0.36 km<br\/> <b>Track: <\/b> 0.58 km<br\/> <b>FRP: <\/b> 0.84 MW<br\/> <b>Brightness: <\/b> 301.81 K" }, "geometry": { "type": "Point", "coordinates": [ -123.02103, 49.14491, 0.0 ] } },
{ "type": "Feature", "properties": { "Name": "Fire Detection Centroid ", "Description": "<b>Latitude: <\/b> 46.23653<br\/>  <b>Longitude: <\/b> -120.14512<br\/>  <b>Detection Time: <\/b> 2023-05-13 11:17 UTC<br\/>  <b>Sensor: <\/b> NOAA-20 VIIRS<br\/> <b>Confidence: <\/b> Nominal<br\/>  <b>Day\/Night: <\/b> Night<br\/> <b>Scan: <\/b> 0.6 km<br\/> <b>Track: <\/b> 0.71 km<br\/> <b>FRP: <\/b> 0.67 MW<br\/> <b>Brightness: <\/b> 299.17 K" }, "geometry": { "type": "Point", "coordinates": [ -120.14512, 46.23653, 0.0 ] } },
{ "type": "Feature", "properties": { "Name": "Fire Detection Centroid ", "Description": "<b>Latitude: <\/b> 46.238<br\/>  <b>Longitude: <\/b> -120.14538<br\/>  <b>Detection Time: <\/b> 2023-05-13 11:17 UTC<br\/>  <b>Sensor: <\/b> NOAA-20 VIIRS<br\/> <b>Confidence: <\/b> Nominal<br\/>  <b>Day\/Night: <\/b> Night<br\/> <b>Scan: <\/b> 0.6 km<br\/> <b>Track: <\/b> 0.71 km<br\/> <b>FRP: <\/b> 1.04 MW<br\/> <b>Brightness: <\/b> 298.31 K" }, "geometry": { "type": "Point", "coordinates": [ -120.14538, 46.238, 0.0 ] } },
{ "type": "Feature", "properties": { "Name": "Fire Detection Centroid ", "Description": "<b>Latitude: <\/b> 47.57389<br\/>  <b>Longitude: <\/b> -122.36819<br\/>  <b>Detection Time: <\/b> 2023-05-13 11:17 UTC<br\/>  <b>Sensor: <\/b> NOAA-20 VIIRS<br\/> <b>Confidence: <\/b> Nominal<br\/>  <b>Day\/Night: <\/b> Night<br\/> <b>Scan: <\/b> 0.43 km<br\/> <b>Track: <\/b> 0.62 km<br\/> <b>FRP: <\/b> 1.37 MW<br\/> <b>Brightness: <\/b> 315.73 K" }, "geometry": { "type": "Point", "coordinates": [ -122.36819, 47.57389, 0.0 ] } },
{ "type": "Feature", "properties": { "Name": "Fire Detection Centroid ", "Description": "<b>Latitude: <\/b> 48.47024<br\/>  <b>Longitude: <\/b> -122.55325<br\/>  <b>Detection Time: <\/b> 2023-05-13 11:17 UTC<br\/>  <b>Sensor: <\/b> NOAA-20 VIIRS<br\/> <b>Confidence: <\/b> Nominal<br\/>  <b>Day\/Night: <\/b> Night<br\/> <b>Scan: <\/b> 0.4 km<br\/> <b>Track: <\/b> 0.6 km<br\/> <b>FRP: <\/b> 0.63 MW<br\/> <b>Brightness: <\/b> 297.22 K" }, "geometry": { "type": "Point", "coordinates": [ -122.55325, 48.47024, 0.0 ] } },
{ "type": "Feature", "properties": { "Name": "Fire Detection Centroid ", "Description": "<b>Latitude: <\/b> 48.4718<br\/>  <b>Longitude: <\/b> -122.5583<br\/>  <b>Detection Time: <\/b> 2023-05-13 11:17 UTC<br\/>  <b>Sensor: <\/b> NOAA-20 VIIRS<br\/> <b>Confidence: <\/b> Nominal<br\/>  <b>Day\/Night: <\/b> Night<br\/> <b>Scan: <\/b> 0.4 km<br\/> <b>Track: <\/b> 0.6 km<br\/> <b>FRP: <\/b> 0.63 MW<br\/> <b>Brightness: <\/b> 297.84 K" }, "geometry": { "type": "Point", "coordinates": [ -122.5583, 48.4718, 0.0 ] } },
{ "type": "Feature", "properties": { "Name": "Fire Detection Centroid ", "Description": "<b>Latitude: <\/b> 49.12075<br\/>  <b>Longitude: <\/b> -116.23051<br\/>  <b>Detection Time: <\/b> 2023-05-13 11:15 UTC<br\/>  <b>Sensor: <\/b> NOAA-20 VIIRS<br\/> <b>Confidence: <\/b> Nominal<br\/>  <b>Day\/Night: <\/b> Night<br\/> <b>Scan: <\/b> 0.69 km<br\/> <b>Track: <\/b> 0.74 km<br\/> <b>FRP: <\/b> 0.9 MW<br\/> <b>Brightness: <\/b> 300.92 K" }, "geometry": { "type": "Point", "coordinates": [ -116.23051, 49.12075, 0.0 ] } }
]
}
