{
"type": "FeatureCollection",
"crs": { "type": "name", "properties": { "name": "urn:ogc:def:crs:OGC:1.3:CRS84" } },
"features": [
{ "type": "Feature", "properties": { "Name": "Fire Detection Centroid ", "Description": "<b>Latitude: <\/b> 49.61876<br\/>  <b>Longitude: <\/b> -126.31728<br\/>  <b>Detection Time: <\/b> 2023-09-08 22:31 UTC<br\/>  <b>Sensor: <\/b> NOAA-20 VIIRS<br\/> <b>Confidence: <\/b> Nominal<br\/>  <b>Day\/Night: <\/b> Day<br\/> <b>Scan: <\/b> 0.73 km<br\/> <b>Track: <\/b> 0.76 km<br\/> <b>FRP: <\/b> 7.86 MW<br\/> <b>Brightness: <\/b> 330.61 K" }, "geometry": { "type": "Point", "coordinates": [ -126.31728, 49.61876, 0.0 ] } },
{ "type": "Feature", "properties": { "Name": "Fire Detection Centroid ", "Description": "<b>Latitude: <\/b> 49.62204<br\/>  <b>Longitude: <\/b> -126.31766<br\/>  <b>Detection Time: <\/b> 2023-09-08 22:29 UTC<br\/>  <b>Sensor: <\/b> NOAA-20 VIIRS<br\/> <b>Confidence: <\/b> Nominal<br\/>  <b>Day\/Night: <\/b> Day<br\/> <b>Scan: <\/b> 0.73 km<br\/> <b>Track: <\/b> 0.76 km<br\/> <b>FRP: <\/b> 7.73 MW<br\/> <b>Brightness: <\/b> 333.4 K" }, "geometry": { "type": "Point", "coordinates": [ -126.31766, 49.62204, 0.0 ] } }
]
}
