{
"type": "FeatureCollection",
"crs": { "type": "name", "properties": { "name": "urn:ogc:def:crs:OGC:1.3:CRS84" } },
"features": [
{ "type": "Feature", "properties": { "Name": "Fire Detection Centroid ", "Description": "<b>Latitude: <\/b> 21.90575<br\/>  <b>Longitude: <\/b> -159.49092<br\/>  <b>Detection Time: <\/b> 2023-07-17 23:58 UTC<br\/>  <b>Sensor: <\/b> NOAA-20 VIIRS<br\/> <b>Confidence: <\/b> Nominal<br\/>  <b>Day\/Night: <\/b> Day<br\/> <b>Scan: <\/b> 0.42 km<br\/> <b>Track: <\/b> 0.38 km<br\/> <b>FRP: <\/b> 2.5 MW<br\/> <b>Brightness: <\/b> 337.31 K" }, "geometry": { "type": "Point", "coordinates": [ -159.49092, 21.90575, 0.0 ] } },
{ "type": "Feature", "properties": { "Name": "Fire Detection Centroid ", "Description": "<b>Latitude: <\/b> 21.99724<br\/>  <b>Longitude: <\/b> -159.76305<br\/>  <b>Detection Time: <\/b> 2023-07-17 23:58 UTC<br\/>  <b>Sensor: <\/b> NOAA-20 VIIRS<br\/> <b>Confidence: <\/b> Low<br\/>  <b>Day\/Night: <\/b> Day<br\/> <b>Scan: <\/b> 0.41 km<br\/> <b>Track: <\/b> 0.37 km<br\/> <b>FRP: <\/b> 2.67 MW<br\/> <b>Brightness: <\/b> 334.51 K" }, "geometry": { "type": "Point", "coordinates": [ -159.76305, 21.99724, 0.0 ] } },
{ "type": "Feature", "properties": { "Name": "Fire Detection Centroid ", "Description": "<b>Latitude: <\/b> 21.99438<br\/>  <b>Longitude: <\/b> -159.75851<br\/>  <b>Detection Time: <\/b> 2023-07-17 23:58 UTC<br\/>  <b>Sensor: <\/b> NOAA-20 VIIRS<br\/> <b>Confidence: <\/b> Nominal<br\/>  <b>Day\/Night: <\/b> Day<br\/> <b>Scan: <\/b> 0.41 km<br\/> <b>Track: <\/b> 0.37 km<br\/> <b>FRP: <\/b> 6.02 MW<br\/> <b>Brightness: <\/b> 342.96 K" }, "geometry": { "type": "Point", "coordinates": [ -159.75851, 21.99438, 0.0 ] } },
{ "type": "Feature", "properties": { "Name": "Fire Detection Centroid ", "Description": "<b>Latitude: <\/b> 21.99383<br\/>  <b>Longitude: <\/b> -159.76248<br\/>  <b>Detection Time: <\/b> 2023-07-17 23:58 UTC<br\/>  <b>Sensor: <\/b> NOAA-20 VIIRS<br\/> <b>Confidence: <\/b> Nominal<br\/>  <b>Day\/Night: <\/b> Day<br\/> <b>Scan: <\/b> 0.41 km<br\/> <b>Track: <\/b> 0.37 km<br\/> <b>FRP: <\/b> 2.33 MW<br\/> <b>Brightness: <\/b> 335.77 K" }, "geometry": { "type": "Point", "coordinates": [ -159.76248, 21.99383, 0.0 ] } }
]
}
