{
"type": "FeatureCollection",
"crs": { "type": "name", "properties": { "name": "urn:ogc:def:crs:OGC:1.3:CRS84" } },
"features": [
{ "type": "Feature", "properties": { "Name": "Fire Detection Centroid ", "Description": "<b>Latitude: <\/b> 18.92832<br\/>  <b>Longitude: <\/b> -70.35226<br\/>  <b>Detection Time: <\/b> 2022-11-25 16:58 UTC<br\/>  <b>Sensor: <\/b> NOAA-20 VIIRS<br\/> <b>Confidence: <\/b> Nominal<br\/>  <b>Day\/Night: <\/b> Day<br\/> <b>Scan: <\/b> 0.7 km<br\/> <b>Track: <\/b> 0.8 km<br\/> <b>FRP: <\/b> 12.16 MW<br\/> <b>Brightness: <\/b> 353.02 K" }, "geometry": { "type": "Point", "coordinates": [ -70.35226, 18.92832, 0.0 ] } },
{ "type": "Feature", "properties": { "Name": "Fire Detection Centroid ", "Description": "<b>Latitude: <\/b> 18.92731<br\/>  <b>Longitude: <\/b> -70.35226<br\/>  <b>Detection Time: <\/b> 2022-11-25 16:58 UTC<br\/>  <b>Sensor: <\/b> NOAA-20 VIIRS<br\/> <b>Confidence: <\/b> Nominal<br\/>  <b>Day\/Night: <\/b> Day<br\/> <b>Scan: <\/b> 0.7 km<br\/> <b>Track: <\/b> 0.8 km<br\/> <b>FRP: <\/b> 13.62 MW<br\/> <b>Brightness: <\/b> 356.1 K" }, "geometry": { "type": "Point", "coordinates": [ -70.35226, 18.92731, 0.0 ] } }
]
}
