{
"type": "FeatureCollection",
"crs": { "type": "name", "properties": { "name": "urn:ogc:def:crs:OGC:1.3:CRS84" } },
"features": [
{ "type": "Feature", "properties": { "Name": "Fire Detection Centroid ", "Description": "<b>Latitude: <\/b> 46.04431<br\/>  <b>Longitude: <\/b> -73.14194<br\/>  <b>Detection Time: <\/b> 2023-01-28 07:20 UTC<br\/>  <b>Sensor: <\/b> NOAA-20 VIIRS<br\/> <b>Confidence: <\/b> Nominal<br\/>  <b>Day\/Night: <\/b> Night<br\/> <b>Scan: <\/b> 0.6 km<br\/> <b>Track: <\/b> 0.4 km<br\/> <b>FRP: <\/b> 4.44 MW<br\/> <b>Brightness: <\/b> 322.8 K" }, "geometry": { "type": "Point", "coordinates": [ -73.14194, 46.04431, 0.0 ] } },
{ "type": "Feature", "properties": { "Name": "Fire Detection Centroid ", "Description": "<b>Latitude: <\/b> 48.18762<br\/>  <b>Longitude: <\/b> -64.92045<br\/>  <b>Detection Time: <\/b> 2023-01-28 07:19 UTC<br\/>  <b>Sensor: <\/b> NOAA-20 VIIRS<br\/> <b>Confidence: <\/b> Nominal<br\/>  <b>Day\/Night: <\/b> Night<br\/> <b>Scan: <\/b> 0.4 km<br\/> <b>Track: <\/b> 0.6 km<br\/> <b>FRP: <\/b> 0.79 MW<br\/> <b>Brightness: <\/b> 296.62 K" }, "geometry": { "type": "Point", "coordinates": [ -64.92045, 48.18762, 0.0 ] } }
]
}
