{
"type": "FeatureCollection",
"crs": { "type": "name", "properties": { "name": "urn:ogc:def:crs:OGC:1.3:CRS84" } },
"features": [
{ "type": "Feature", "properties": { "Name": "Fire Detection Centroid ", "Description": "<b>Latitude: <\/b> 19.40495<br\/>  <b>Longitude: <\/b> -155.28177<br\/>  <b>Detection Time: <\/b> 2022-09-30 22:54 UTC<br\/>  <b>Sensor: <\/b> NOAA-20 VIIRS<br\/> <b>Confidence: <\/b> High<br\/>  <b>Day\/Night: <\/b> Day<br\/> <b>Scan: <\/b> 0.39 km<br\/> <b>Track: <\/b> 0.59 km<br\/> <b>FRP: <\/b> 53.84 MW<br\/> <b>Brightness: <\/b> 367 K" }, "geometry": { "type": "Point", "coordinates": [ -155.28177, 19.40495, 0.0 ] } },
{ "type": "Feature", "properties": { "Name": "Fire Detection Centroid ", "Description": "<b>Latitude: <\/b> 19.40419<br\/>  <b>Longitude: <\/b> -155.28542<br\/>  <b>Detection Time: <\/b> 2022-09-30 22:54 UTC<br\/>  <b>Sensor: <\/b> NOAA-20 VIIRS<br\/> <b>Confidence: <\/b> Nominal<br\/>  <b>Day\/Night: <\/b> Day<br\/> <b>Scan: <\/b> 0.39 km<br\/> <b>Track: <\/b> 0.6 km<br\/> <b>FRP: <\/b> 53.84 MW<br\/> <b>Brightness: <\/b> 329.36 K" }, "geometry": { "type": "Point", "coordinates": [ -155.28542, 19.40419, 0.0 ] } },
{ "type": "Feature", "properties": { "Name": "Fire Detection Centroid ", "Description": "<b>Latitude: <\/b> 19.41184<br\/>  <b>Longitude: <\/b> -155.27573<br\/>  <b>Detection Time: <\/b> 2022-09-30 22:54 UTC<br\/>  <b>Sensor: <\/b> NOAA-20 VIIRS<br\/> <b>Confidence: <\/b> Nominal<br\/>  <b>Day\/Night: <\/b> Day<br\/> <b>Scan: <\/b> 0.39 km<br\/> <b>Track: <\/b> 0.59 km<br\/> <b>FRP: <\/b> 9.96 MW<br\/> <b>Brightness: <\/b> 336.01 K" }, "geometry": { "type": "Point", "coordinates": [ -155.27573, 19.41184, 0.0 ] } },
{ "type": "Feature", "properties": { "Name": "Fire Detection Centroid ", "Description": "<b>Latitude: <\/b> 19.40572<br\/>  <b>Longitude: <\/b> -155.27817<br\/>  <b>Detection Time: <\/b> 2022-09-30 22:54 UTC<br\/>  <b>Sensor: <\/b> NOAA-20 VIIRS<br\/> <b>Confidence: <\/b> High<br\/>  <b>Day\/Night: <\/b> Day<br\/> <b>Scan: <\/b> 0.39 km<br\/> <b>Track: <\/b> 0.59 km<br\/> <b>FRP: <\/b> 58.27 MW<br\/> <b>Brightness: <\/b> 367 K" }, "geometry": { "type": "Point", "coordinates": [ -155.27817, 19.40572, 0.0 ] } }
]
}
