{
"type": "FeatureCollection",
"crs": { "type": "name", "properties": { "name": "urn:ogc:def:crs:OGC:1.3:CRS84" } },
"features": [
{ "type": "Feature", "properties": { "Name": "Fire Detection Centroid ", "Description": "<b>Latitude: <\/b> 45.28052<br\/>  <b>Longitude: <\/b> -66.02486<br\/>  <b>Detection Time: <\/b> 2022-09-29 05:08 UTC<br\/>  <b>Sensor: <\/b> NOAA-20 VIIRS<br\/> <b>Confidence: <\/b> Nominal<br\/>  <b>Day\/Night: <\/b> Night<br\/> <b>Scan: <\/b> 0.7 km<br\/> <b>Track: <\/b> 0.8 km<br\/> <b>FRP: <\/b> 1.09 MW<br\/> <b>Brightness: <\/b> 296.53 K" }, "geometry": { "type": "Point", "coordinates": [ -66.02486, 45.28052, 0.0 ] } },
{ "type": "Feature", "properties": { "Name": "Fire Detection Centroid ", "Description": "<b>Latitude: <\/b> 45.28394<br\/>  <b>Longitude: <\/b> -66.01797<br\/>  <b>Detection Time: <\/b> 2022-09-29 05:08 UTC<br\/>  <b>Sensor: <\/b> NOAA-20 VIIRS<br\/> <b>Confidence: <\/b> Nominal<br\/>  <b>Day\/Night: <\/b> Night<br\/> <b>Scan: <\/b> 0.7 km<br\/> <b>Track: <\/b> 0.8 km<br\/> <b>FRP: <\/b> 1.64 MW<br\/> <b>Brightness: <\/b> 296.61 K" }, "geometry": { "type": "Point", "coordinates": [ -66.01797, 45.28394, 0.0 ] } }
]
}
