{
"type": "FeatureCollection",
"crs": { "type": "name", "properties": { "name": "urn:ogc:def:crs:OGC:1.3:CRS84" } },
"features": [
{ "type": "Feature", "properties": { "Name": "Fire Detection Centroid ", "Description": "<b>Latitude: <\/b> 41.57806<br\/>  <b>Longitude: <\/b> -122.34274<br\/>  <b>Detection Time: <\/b> 2023-04-22 11:10 UTC<br\/>  <b>Sensor: <\/b> NOAA-20 VIIRS<br\/> <b>Confidence: <\/b> Nominal<br\/>  <b>Day\/Night: <\/b> Night<br\/> <b>Scan: <\/b> 0.57 km<br\/> <b>Track: <\/b> 0.69 km<br\/> <b>FRP: <\/b> 1.7 MW<br\/> <b>Brightness: <\/b> 303.82 K" }, "geometry": { "type": "Point", "coordinates": [ -122.34274, 41.57806, 0.0 ] } }
]
}
