{
"type": "FeatureCollection",
"crs": { "type": "name", "properties": { "name": "urn:ogc:def:crs:OGC:1.3:CRS84" } },
"features": [
{ "type": "Feature", "properties": { "Name": "Fire Detection Centroid ", "Description": "<b>Latitude: <\/b> 19.40611<br\/>  <b>Longitude: <\/b> -155.28268<br\/>  <b>Detection Time: <\/b> 2023-12-28 11:29 UTC<br\/>  <b>Sensor: <\/b> NOAA-20 VIIRS<br\/> <b>Confidence: <\/b> Nominal<br\/>  <b>Day\/Night: <\/b> Night<br\/> <b>Scan: <\/b> 0.51 km<br\/> <b>Track: <\/b> 0.49 km<br\/> <b>FRP: <\/b> 4.86 MW<br\/> <b>Brightness: <\/b> 304.61 K" }, "geometry": { "type": "Point", "coordinates": [ -155.28268, 19.40611, 0.0 ] } },
{ "type": "Feature", "properties": { "Name": "Fire Detection Centroid ", "Description": "<b>Latitude: <\/b> 47.47105<br\/>  <b>Longitude: <\/b> -122.04983<br\/>  <b>Detection Time: <\/b> 2023-12-28 11:21 UTC<br\/>  <b>Sensor: <\/b> NOAA-20 VIIRS<br\/> <b>Confidence: <\/b> Nominal<br\/>  <b>Day\/Night: <\/b> Night<br\/> <b>Scan: <\/b> 0.53 km<br\/> <b>Track: <\/b> 0.67 km<br\/> <b>FRP: <\/b> 0.83 MW<br\/> <b>Brightness: <\/b> 295.28 K" }, "geometry": { "type": "Point", "coordinates": [ -122.04983, 47.47105, 0.0 ] } },
{ "type": "Feature", "properties": { "Name": "Fire Detection Centroid ", "Description": "<b>Latitude: <\/b> 47.47124<br\/>  <b>Longitude: <\/b> -122.0466<br\/>  <b>Detection Time: <\/b> 2023-12-28 11:21 UTC<br\/>  <b>Sensor: <\/b> NOAA-20 VIIRS<br\/> <b>Confidence: <\/b> Nominal<br\/>  <b>Day\/Night: <\/b> Night<br\/> <b>Scan: <\/b> 0.5 km<br\/> <b>Track: <\/b> 0.7 km<br\/> <b>FRP: <\/b> 0.82 MW<br\/> <b>Brightness: <\/b> 295.28 K" }, "geometry": { "type": "Point", "coordinates": [ -122.0466, 47.47124, 0.0 ] } }
]
}
