{
"type": "FeatureCollection",
"crs": { "type": "name", "properties": { "name": "urn:ogc:def:crs:OGC:1.3:CRS84" } },
"features": [
{ "type": "Feature", "properties": { "Name": "Fire Detection Centroid ", "Description": "<b>Latitude: <\/b> 49.57244<br\/>  <b>Longitude: <\/b> -123.94195<br\/>  <b>Detection Time: <\/b> 2023-02-23 22:24 UTC<br\/>  <b>Sensor: <\/b> NOAA-20 VIIRS<br\/> <b>Confidence: <\/b> Nominal<br\/>  <b>Day\/Night: <\/b> Day<br\/> <b>Scan: <\/b> 0.78 km<br\/> <b>Track: <\/b> 0.78 km<br\/> <b>FRP: <\/b> 14.36 MW<br\/> <b>Brightness: <\/b> 346.56 K" }, "geometry": { "type": "Point", "coordinates": [ -123.94195, 49.57244, 0.0 ] } },
{ "type": "Feature", "properties": { "Name": "Fire Detection Centroid ", "Description": "<b>Latitude: <\/b> 49.56518<br\/>  <b>Longitude: <\/b> -123.94116<br\/>  <b>Detection Time: <\/b> 2023-02-23 22:24 UTC<br\/>  <b>Sensor: <\/b> NOAA-20 VIIRS<br\/> <b>Confidence: <\/b> Nominal<br\/>  <b>Day\/Night: <\/b> Day<br\/> <b>Scan: <\/b> 0.78 km<br\/> <b>Track: <\/b> 0.78 km<br\/> <b>FRP: <\/b> 14.36 MW<br\/> <b>Brightness: <\/b> 353.88 K" }, "geometry": { "type": "Point", "coordinates": [ -123.94116, 49.56518, 0.0 ] } }
]
}
