{
"type": "FeatureCollection",
"crs": { "type": "name", "properties": { "name": "urn:ogc:def:crs:OGC:1.3:CRS84" } },
"features": [
{ "type": "Feature", "properties": { "Name": "Fire Detection Centroid ", "Description": "<b>Latitude: <\/b> 47.57143<br\/>  <b>Longitude: <\/b> -122.3693<br\/>  <b>Detection Time: <\/b> 2023-06-25 11:10 UTC<br\/>  <b>Sensor: <\/b> NOAA-20 VIIRS<br\/> <b>Confidence: <\/b> Nominal<br\/>  <b>Day\/Night: <\/b> Night<br\/> <b>Scan: <\/b> 0.37 km<br\/> <b>Track: <\/b> 0.58 km<br\/> <b>FRP: <\/b> 2.33 MW<br\/> <b>Brightness: <\/b> 323.77 K" }, "geometry": { "type": "Point", "coordinates": [ -122.3693, 47.57143, 0.0 ] } },
{ "type": "Feature", "properties": { "Name": "Fire Detection Centroid ", "Description": "<b>Latitude: <\/b> 47.56749<br\/>  <b>Longitude: <\/b> -122.34075<br\/>  <b>Detection Time: <\/b> 2023-06-25 11:10 UTC<br\/>  <b>Sensor: <\/b> NOAA-20 VIIRS<br\/> <b>Confidence: <\/b> Nominal<br\/>  <b>Day\/Night: <\/b> Night<br\/> <b>Scan: <\/b> 0.37 km<br\/> <b>Track: <\/b> 0.58 km<br\/> <b>FRP: <\/b> 0.64 MW<br\/> <b>Brightness: <\/b> 300.26 K" }, "geometry": { "type": "Point", "coordinates": [ -122.34075, 47.56749, 0.0 ] } },
{ "type": "Feature", "properties": { "Name": "Fire Detection Centroid ", "Description": "<b>Latitude: <\/b> 47.57104<br\/>  <b>Longitude: <\/b> -122.37247<br\/>  <b>Detection Time: <\/b> 2023-06-25 11:10 UTC<br\/>  <b>Sensor: <\/b> NOAA-20 VIIRS<br\/> <b>Confidence: <\/b> Nominal<br\/>  <b>Day\/Night: <\/b> Night<br\/> <b>Scan: <\/b> 0.37 km<br\/> <b>Track: <\/b> 0.58 km<br\/> <b>FRP: <\/b> 1.09 MW<br\/> <b>Brightness: <\/b> 309.09 K" }, "geometry": { "type": "Point", "coordinates": [ -122.37247, 47.57104, 0.0 ] } },
{ "type": "Feature", "properties": { "Name": "Fire Detection Centroid ", "Description": "<b>Latitude: <\/b> 47.56949<br\/>  <b>Longitude: <\/b> -122.36726<br\/>  <b>Detection Time: <\/b> 2023-06-25 11:10 UTC<br\/>  <b>Sensor: <\/b> NOAA-20 VIIRS<br\/> <b>Confidence: <\/b> Nominal<br\/>  <b>Day\/Night: <\/b> Night<br\/> <b>Scan: <\/b> 0.37 km<br\/> <b>Track: <\/b> 0.58 km<br\/> <b>FRP: <\/b> 1.09 MW<br\/> <b>Brightness: <\/b> 304.85 K" }, "geometry": { "type": "Point", "coordinates": [ -122.36726, 47.56949, 0.0 ] } },
{ "type": "Feature", "properties": { "Name": "Fire Detection Centroid ", "Description": "<b>Latitude: <\/b> 48.88528<br\/>  <b>Longitude: <\/b> -122.73537<br\/>  <b>Detection Time: <\/b> 2023-06-25 11:10 UTC<br\/>  <b>Sensor: <\/b> NOAA-20 VIIRS<br\/> <b>Confidence: <\/b> Nominal<br\/>  <b>Day\/Night: <\/b> Night<br\/> <b>Scan: <\/b> 0.33 km<br\/> <b>Track: <\/b> 0.55 km<br\/> <b>FRP: <\/b> 0.77 MW<br\/> <b>Brightness: <\/b> 296.24 K" }, "geometry": { "type": "Point", "coordinates": [ -122.73537, 48.88528, 0.0 ] } }
]
}
