{
"type": "FeatureCollection",
"crs": { "type": "name", "properties": { "name": "urn:ogc:def:crs:OGC:1.3:CRS84" } },
"features": [
{ "type": "Feature", "properties": { "Name": "Fire Detection Centroid ", "Description": "<b>Latitude: <\/b> 46.5184<br\/>  <b>Longitude: <\/b> -84.3967<br\/>  <b>Detection Time: <\/b> 2023-03-09 06:31 UTC<br\/>  <b>Sensor: <\/b> NOAA-20 VIIRS<br\/> <b>Confidence: <\/b> Nominal<br\/>  <b>Day\/Night: <\/b> Night<br\/> <b>Scan: <\/b> 0.6 km<br\/> <b>Track: <\/b> 0.7 km<br\/> <b>FRP: <\/b> 5.38 MW<br\/> <b>Brightness: <\/b> 331.07 K" }, "geometry": { "type": "Point", "coordinates": [ -84.3967, 46.5184, 0.0 ] } },
{ "type": "Feature", "properties": { "Name": "Fire Detection Centroid ", "Description": "<b>Latitude: <\/b> 45.07035<br\/>  <b>Longitude: <\/b> -83.40426<br\/>  <b>Detection Time: <\/b> 2023-03-09 06:31 UTC<br\/>  <b>Sensor: <\/b> NOAA-20 VIIRS<br\/> <b>Confidence: <\/b> Nominal<br\/>  <b>Day\/Night: <\/b> Night<br\/> <b>Scan: <\/b> 0.5 km<br\/> <b>Track: <\/b> 0.7 km<br\/> <b>FRP: <\/b> 2.94 MW<br\/> <b>Brightness: <\/b> 302.28 K" }, "geometry": { "type": "Point", "coordinates": [ -83.40426, 45.07035, 0.0 ] } },
{ "type": "Feature", "properties": { "Name": "Fire Detection Centroid ", "Description": "<b>Latitude: <\/b> 45.07157<br\/>  <b>Longitude: <\/b> -83.40636<br\/>  <b>Detection Time: <\/b> 2023-03-09 06:31 UTC<br\/>  <b>Sensor: <\/b> NOAA-20 VIIRS<br\/> <b>Confidence: <\/b> Nominal<br\/>  <b>Day\/Night: <\/b> Night<br\/> <b>Scan: <\/b> 0.5 km<br\/> <b>Track: <\/b> 0.7 km<br\/> <b>FRP: <\/b> 2.29 MW<br\/> <b>Brightness: <\/b> 317.59 K" }, "geometry": { "type": "Point", "coordinates": [ -83.40636, 45.07157, 0.0 ] } }
]
}
