{
"type": "FeatureCollection",
"crs": { "type": "name", "properties": { "name": "urn:ogc:def:crs:OGC:1.3:CRS84" } },
"features": [
{ "type": "Feature", "properties": { "Name": "Fire Detection Centroid ", "Description": "<b>Latitude: <\/b> 19.40852<br\/>  <b>Longitude: <\/b> -155.28337<br\/>  <b>Detection Time: <\/b> 2022-10-10 23:06 UTC<br\/>  <b>Sensor: <\/b> NOAA-20 VIIRS<br\/> <b>Confidence: <\/b> Nominal<br\/>  <b>Day\/Night: <\/b> Day<br\/> <b>Scan: <\/b> 0.5 km<br\/> <b>Track: <\/b> 0.5 km<br\/> <b>FRP: <\/b> 4.77 MW<br\/> <b>Brightness: <\/b> 332.13 K" }, "geometry": { "type": "Point", "coordinates": [ -155.28337, 19.40852, 0.0 ] } },
{ "type": "Feature", "properties": { "Name": "Fire Detection Centroid ", "Description": "<b>Latitude: <\/b> 19.40938<br\/>  <b>Longitude: <\/b> -155.27885<br\/>  <b>Detection Time: <\/b> 2022-10-10 23:06 UTC<br\/>  <b>Sensor: <\/b> NOAA-20 VIIRS<br\/> <b>Confidence: <\/b> Nominal<br\/>  <b>Day\/Night: <\/b> Day<br\/> <b>Scan: <\/b> 0.5 km<br\/> <b>Track: <\/b> 0.5 km<br\/> <b>FRP: <\/b> 4.77 MW<br\/> <b>Brightness: <\/b> 330.43 K" }, "geometry": { "type": "Point", "coordinates": [ -155.27885, 19.40938, 0.0 ] } },
{ "type": "Feature", "properties": { "Name": "Fire Detection Centroid ", "Description": "<b>Latitude: <\/b> 19.40327<br\/>  <b>Longitude: <\/b> -155.287<br\/>  <b>Detection Time: <\/b> 2022-10-10 23:06 UTC<br\/>  <b>Sensor: <\/b> NOAA-20 VIIRS<br\/> <b>Confidence: <\/b> Nominal<br\/>  <b>Day\/Night: <\/b> Day<br\/> <b>Scan: <\/b> 0.5 km<br\/> <b>Track: <\/b> 0.5 km<br\/> <b>FRP: <\/b> 44.66 MW<br\/> <b>Brightness: <\/b> 344.49 K" }, "geometry": { "type": "Point", "coordinates": [ -155.287, 19.40327, 0.0 ] } },
{ "type": "Feature", "properties": { "Name": "Fire Detection Centroid ", "Description": "<b>Latitude: <\/b> 19.40903<br\/>  <b>Longitude: <\/b> -155.28265<br\/>  <b>Detection Time: <\/b> 2022-10-10 23:05 UTC<br\/>  <b>Sensor: <\/b> NOAA-20 VIIRS<br\/> <b>Confidence: <\/b> Nominal<br\/>  <b>Day\/Night: <\/b> Day<br\/> <b>Scan: <\/b> 0.49 km<br\/> <b>Track: <\/b> 0.48 km<br\/> <b>FRP: <\/b> 4.78 MW<br\/> <b>Brightness: <\/b> 332.13 K" }, "geometry": { "type": "Point", "coordinates": [ -155.28265, 19.40903, 0.0 ] } },
{ "type": "Feature", "properties": { "Name": "Fire Detection Centroid ", "Description": "<b>Latitude: <\/b> 19.40377<br\/>  <b>Longitude: <\/b> -155.28632<br\/>  <b>Detection Time: <\/b> 2022-10-10 23:05 UTC<br\/>  <b>Sensor: <\/b> NOAA-20 VIIRS<br\/> <b>Confidence: <\/b> Nominal<br\/>  <b>Day\/Night: <\/b> Day<br\/> <b>Scan: <\/b> 0.49 km<br\/> <b>Track: <\/b> 0.48 km<br\/> <b>FRP: <\/b> 44.66 MW<br\/> <b>Brightness: <\/b> 344.49 K" }, "geometry": { "type": "Point", "coordinates": [ -155.28632, 19.40377, 0.0 ] } },
{ "type": "Feature", "properties": { "Name": "Fire Detection Centroid ", "Description": "<b>Latitude: <\/b> 19.40988<br\/>  <b>Longitude: <\/b> -155.27817<br\/>  <b>Detection Time: <\/b> 2022-10-10 23:05 UTC<br\/>  <b>Sensor: <\/b> NOAA-20 VIIRS<br\/> <b>Confidence: <\/b> Nominal<br\/>  <b>Day\/Night: <\/b> Day<br\/> <b>Scan: <\/b> 0.49 km<br\/> <b>Track: <\/b> 0.48 km<br\/> <b>FRP: <\/b> 4.78 MW<br\/> <b>Brightness: <\/b> 330.43 K" }, "geometry": { "type": "Point", "coordinates": [ -155.27817, 19.40988, 0.0 ] } }
]
}
