{
"type": "FeatureCollection",
"crs": { "type": "name", "properties": { "name": "urn:ogc:def:crs:OGC:1.3:CRS84" } },
"features": [
{ "type": "Feature", "properties": { "Name": "Fire Detection Centroid ", "Description": "<b>Latitude: <\/b> 18.31513<br\/>  <b>Longitude: <\/b> -64.88409<br\/>  <b>Detection Time: <\/b> 2023-09-20 05:42 UTC<br\/>  <b>Sensor: <\/b> NOAA-20 VIIRS<br\/> <b>Confidence: <\/b> Nominal<br\/>  <b>Day\/Night: <\/b> Night<br\/> <b>Scan: <\/b> 0.5 km<br\/> <b>Track: <\/b> 0.4 km<br\/> <b>FRP: <\/b> 3.51 MW<br\/> <b>Brightness: <\/b> 323.11 K" }, "geometry": { "type": "Point", "coordinates": [ -64.88409, 18.31513, 0.0 ] } },
{ "type": "Feature", "properties": { "Name": "Fire Detection Centroid ", "Description": "<b>Latitude: <\/b> 18.9294<br\/>  <b>Longitude: <\/b> -70.35696<br\/>  <b>Detection Time: <\/b> 2023-09-20 05:42 UTC<br\/>  <b>Sensor: <\/b> NOAA-20 VIIRS<br\/> <b>Confidence: <\/b> Nominal<br\/>  <b>Day\/Night: <\/b> Night<br\/> <b>Scan: <\/b> 0.3 km<br\/> <b>Track: <\/b> 0.6 km<br\/> <b>FRP: <\/b> 2.97 MW<br\/> <b>Brightness: <\/b> 305.87 K" }, "geometry": { "type": "Point", "coordinates": [ -70.35696, 18.9294, 0.0 ] } },
{ "type": "Feature", "properties": { "Name": "Fire Detection Centroid ", "Description": "<b>Latitude: <\/b> 18.92905<br\/>  <b>Longitude: <\/b> -70.35361<br\/>  <b>Detection Time: <\/b> 2023-09-20 05:42 UTC<br\/>  <b>Sensor: <\/b> NOAA-20 VIIRS<br\/> <b>Confidence: <\/b> Nominal<br\/>  <b>Day\/Night: <\/b> Night<br\/> <b>Scan: <\/b> 0.3 km<br\/> <b>Track: <\/b> 0.6 km<br\/> <b>FRP: <\/b> 2.97 MW<br\/> <b>Brightness: <\/b> 346.64 K" }, "geometry": { "type": "Point", "coordinates": [ -70.35361, 18.92905, 0.0 ] } }
]
}
