{
"type": "FeatureCollection",
"crs": { "type": "name", "properties": { "name": "urn:ogc:def:crs:OGC:1.3:CRS84" } },
"features": [
{ "type": "Feature", "properties": { "Name": "Fire Detection Centroid ", "Description": "<b>Latitude: <\/b> 40.70193<br\/>  <b>Longitude: <\/b> -73.81519<br\/>  <b>Detection Time: <\/b> 2024-03-30 16:42 UTC<br\/>  <b>Sensor: <\/b> NOAA-20 VIIRS<br\/> <b>Confidence: <\/b> Nominal<br\/>  <b>Day\/Night: <\/b> Day<br\/> <b>Scan: <\/b> 0.7 km<br\/> <b>Track: <\/b> 0.7 km<br\/> <b>FRP: <\/b> 1.63 MW<br\/> <b>Brightness: <\/b> 325.35 K" }, "geometry": { "type": "Point", "coordinates": [ -73.81519, 40.70193, 0.0 ] } },
{ "type": "Feature", "properties": { "Name": "Fire Detection Centroid ", "Description": "<b>Latitude: <\/b> 44.0938<br\/>  <b>Longitude: <\/b> -73.27939<br\/>  <b>Detection Time: <\/b> 2024-03-30 16:42 UTC<br\/>  <b>Sensor: <\/b> NOAA-20 VIIRS<br\/> <b>Confidence: <\/b> Nominal<br\/>  <b>Day\/Night: <\/b> Day<br\/> <b>Scan: <\/b> 0.5 km<br\/> <b>Track: <\/b> 0.7 km<br\/> <b>FRP: <\/b> 3.48 MW<br\/> <b>Brightness: <\/b> 328.1 K" }, "geometry": { "type": "Point", "coordinates": [ -73.27939, 44.0938, 0.0 ] } },
{ "type": "Feature", "properties": { "Name": "Fire Detection Centroid ", "Description": "<b>Latitude: <\/b> 44.38357<br\/>  <b>Longitude: <\/b> -71.45483<br\/>  <b>Detection Time: <\/b> 2024-03-30 16:42 UTC<br\/>  <b>Sensor: <\/b> NOAA-20 VIIRS<br\/> <b>Confidence: <\/b> Nominal<br\/>  <b>Day\/Night: <\/b> Day<br\/> <b>Scan: <\/b> 0.4 km<br\/> <b>Track: <\/b> 0.6 km<br\/> <b>FRP: <\/b> 2.56 MW<br\/> <b>Brightness: <\/b> 338.48 K" }, "geometry": { "type": "Point", "coordinates": [ -71.45483, 44.38357, 0.0 ] } },
{ "type": "Feature", "properties": { "Name": "Fire Detection Centroid ", "Description": "<b>Latitude: <\/b> 20.80577<br\/>  <b>Longitude: <\/b> -156.43031<br\/>  <b>Detection Time: <\/b> 2024-03-30 12:10 UTC<br\/>  <b>Sensor: <\/b> NOAA-20 VIIRS<br\/> <b>Confidence: <\/b> Nominal<br\/>  <b>Day\/Night: <\/b> Night<br\/> <b>Scan: <\/b> 0.4 km<br\/> <b>Track: <\/b> 0.4 km<br\/> <b>FRP: <\/b> 0.34 MW<br\/> <b>Brightness: <\/b> 300.53 K" }, "geometry": { "type": "Point", "coordinates": [ -156.43031, 20.80577, 0.0 ] } },
{ "type": "Feature", "properties": { "Name": "Fire Detection Centroid ", "Description": "<b>Latitude: <\/b> 20.86231<br\/>  <b>Longitude: <\/b> -156.41988<br\/>  <b>Detection Time: <\/b> 2024-03-30 12:10 UTC<br\/>  <b>Sensor: <\/b> NOAA-20 VIIRS<br\/> <b>Confidence: <\/b> Nominal<br\/>  <b>Day\/Night: <\/b> Night<br\/> <b>Scan: <\/b> 0.4 km<br\/> <b>Track: <\/b> 0.37 km<br\/> <b>FRP: <\/b> 0.35 MW<br\/> <b>Brightness: <\/b> 300.53 K" }, "geometry": { "type": "Point", "coordinates": [ -156.41988, 20.86231, 0.0 ] } }
]
}
