{
"type": "FeatureCollection",
"crs": { "type": "name", "properties": { "name": "urn:ogc:def:crs:OGC:1.3:CRS84" } },
"features": [
{ "type": "Feature", "properties": { "Name": "Fire Detection Centroid ", "Description": "<b>Latitude: <\/b> 21.33936<br\/>  <b>Longitude: <\/b> -158.0103<br\/>  <b>Detection Time: <\/b> 2023-10-17 23:32 UTC<br\/>  <b>Sensor: <\/b> NOAA-20 VIIRS<br\/> <b>Confidence: <\/b> Nominal<br\/>  <b>Day\/Night: <\/b> Day<br\/> <b>Scan: <\/b> 0.4 km<br\/> <b>Track: <\/b> 0.4 km<br\/> <b>FRP: <\/b> 2.38 MW<br\/> <b>Brightness: <\/b> 337.51 K" }, "geometry": { "type": "Point", "coordinates": [ -158.0103, 21.33936, 0.0 ] } },
{ "type": "Feature", "properties": { "Name": "Fire Detection Centroid ", "Description": "<b>Latitude: <\/b> 21.33516<br\/>  <b>Longitude: <\/b> -158.01382<br\/>  <b>Detection Time: <\/b> 2023-10-17 23:32 UTC<br\/>  <b>Sensor: <\/b> NOAA-20 VIIRS<br\/> <b>Confidence: <\/b> Nominal<br\/>  <b>Day\/Night: <\/b> Day<br\/> <b>Scan: <\/b> 0.4 km<br\/> <b>Track: <\/b> 0.4 km<br\/> <b>FRP: <\/b> 3.23 MW<br\/> <b>Brightness: <\/b> 340.11 K" }, "geometry": { "type": "Point", "coordinates": [ -158.01382, 21.33516, 0.0 ] } },
{ "type": "Feature", "properties": { "Name": "Fire Detection Centroid ", "Description": "<b>Latitude: <\/b> 21.3358<br\/>  <b>Longitude: <\/b> -158.01335<br\/>  <b>Detection Time: <\/b> 2023-10-17 23:31 UTC<br\/>  <b>Sensor: <\/b> NOAA-20 VIIRS<br\/> <b>Confidence: <\/b> Nominal<br\/>  <b>Day\/Night: <\/b> Day<br\/> <b>Scan: <\/b> 0.44 km<br\/> <b>Track: <\/b> 0.38 km<br\/> <b>FRP: <\/b> 3.24 MW<br\/> <b>Brightness: <\/b> 340.11 K" }, "geometry": { "type": "Point", "coordinates": [ -158.01335, 21.3358, 0.0 ] } },
{ "type": "Feature", "properties": { "Name": "Fire Detection Centroid ", "Description": "<b>Latitude: <\/b> 21.33929<br\/>  <b>Longitude: <\/b> -158.01402<br\/>  <b>Detection Time: <\/b> 2023-10-17 23:31 UTC<br\/>  <b>Sensor: <\/b> NOAA-20 VIIRS<br\/> <b>Confidence: <\/b> Low<br\/>  <b>Day\/Night: <\/b> Day<br\/> <b>Scan: <\/b> 0.44 km<br\/> <b>Track: <\/b> 0.38 km<br\/> <b>FRP: <\/b> 2.17 MW<br\/> <b>Brightness: <\/b> 331.78 K" }, "geometry": { "type": "Point", "coordinates": [ -158.01402, 21.33929, 0.0 ] } },
{ "type": "Feature", "properties": { "Name": "Fire Detection Centroid ", "Description": "<b>Latitude: <\/b> 19.40869<br\/>  <b>Longitude: <\/b> -155.28714<br\/>  <b>Detection Time: <\/b> 2023-10-17 23:31 UTC<br\/>  <b>Sensor: <\/b> NOAA-20 VIIRS<br\/> <b>Confidence: <\/b> Low<br\/>  <b>Day\/Night: <\/b> Day<br\/> <b>Scan: <\/b> 0.4 km<br\/> <b>Track: <\/b> 0.4 km<br\/> <b>FRP: <\/b> 12.85 MW<br\/> <b>Brightness: <\/b> 348.19 K" }, "geometry": { "type": "Point", "coordinates": [ -155.28714, 19.40869, 0.0 ] } },
{ "type": "Feature", "properties": { "Name": "Fire Detection Centroid ", "Description": "<b>Latitude: <\/b> 19.40918<br\/>  <b>Longitude: <\/b> -155.2867<br\/>  <b>Detection Time: <\/b> 2023-10-17 23:31 UTC<br\/>  <b>Sensor: <\/b> NOAA-20 VIIRS<br\/> <b>Confidence: <\/b> Low<br\/>  <b>Day\/Night: <\/b> Day<br\/> <b>Scan: <\/b> 0.39 km<br\/> <b>Track: <\/b> 0.36 km<br\/> <b>FRP: <\/b> 12.85 MW<br\/> <b>Brightness: <\/b> 348.19 K" }, "geometry": { "type": "Point", "coordinates": [ -155.2867, 19.40918, 0.0 ] } },
{ "type": "Feature", "properties": { "Name": "Fire Detection Centroid ", "Description": "<b>Latitude: <\/b> 21.33999<br\/>  <b>Longitude: <\/b> -158.00984<br\/>  <b>Detection Time: <\/b> 2023-10-17 23:31 UTC<br\/>  <b>Sensor: <\/b> NOAA-20 VIIRS<br\/> <b>Confidence: <\/b> Nominal<br\/>  <b>Day\/Night: <\/b> Day<br\/> <b>Scan: <\/b> 0.44 km<br\/> <b>Track: <\/b> 0.38 km<br\/> <b>FRP: <\/b> 2.39 MW<br\/> <b>Brightness: <\/b> 337.51 K" }, "geometry": { "type": "Point", "coordinates": [ -158.00984, 21.33999, 0.0 ] } }
]
}
