{
"type": "FeatureCollection",
"crs": { "type": "name", "properties": { "name": "urn:ogc:def:crs:OGC:1.3:CRS84" } },
"features": [
{ "type": "Feature", "properties": { "Name": "Fire Detection Centroid ", "Description": "<b>Latitude: <\/b> 19.59683<br\/>  <b>Longitude: <\/b> -155.50378<br\/>  <b>Detection Time: <\/b> 2023-07-08 12:17 UTC<br\/>  <b>Sensor: <\/b> NOAA-20 VIIRS<br\/> <b>Confidence: <\/b> Nominal<br\/>  <b>Day\/Night: <\/b> Night<br\/> <b>Scan: <\/b> 0.49 km<br\/> <b>Track: <\/b> 0.4 km<br\/> <b>FRP: <\/b> 2.32 MW<br\/> <b>Brightness: <\/b> 300.56 K" }, "geometry": { "type": "Point", "coordinates": [ -155.50378, 19.59683, 0.0 ] } }
]
}
