{
"type": "FeatureCollection",
"crs": { "type": "name", "properties": { "name": "urn:ogc:def:crs:OGC:1.3:CRS84" } },
"features": [
{ "type": "Feature", "properties": { "Name": "Fire Detection Centroid ", "Description": "<b>Latitude: <\/b> 48.88821<br\/>  <b>Longitude: <\/b> -122.73409<br\/>  <b>Detection Time: <\/b> 2023-05-17 11:40 UTC<br\/>  <b>Sensor: <\/b> NOAA-20 VIIRS<br\/> <b>Confidence: <\/b> Nominal<br\/>  <b>Day\/Night: <\/b> Night<br\/> <b>Scan: <\/b> 0.69 km<br\/> <b>Track: <\/b> 0.74 km<br\/> <b>FRP: <\/b> 1.57 MW<br\/> <b>Brightness: <\/b> 295.31 K" }, "geometry": { "type": "Point", "coordinates": [ -122.73409, 48.88821, 0.0 ] } },
{ "type": "Feature", "properties": { "Name": "Fire Detection Centroid ", "Description": "<b>Latitude: <\/b> 47.57281<br\/>  <b>Longitude: <\/b> -122.36777<br\/>  <b>Detection Time: <\/b> 2023-05-17 11:40 UTC<br\/>  <b>Sensor: <\/b> NOAA-20 VIIRS<br\/> <b>Confidence: <\/b> Nominal<br\/>  <b>Day\/Night: <\/b> Night<br\/> <b>Scan: <\/b> 0.79 km<br\/> <b>Track: <\/b> 0.78 km<br\/> <b>FRP: <\/b> 1.31 MW<br\/> <b>Brightness: <\/b> 300.2 K" }, "geometry": { "type": "Point", "coordinates": [ -122.36777, 47.57281, 0.0 ] } },
{ "type": "Feature", "properties": { "Name": "Fire Detection Centroid ", "Description": "<b>Latitude: <\/b> 48.88841<br\/>  <b>Longitude: <\/b> -122.74178<br\/>  <b>Detection Time: <\/b> 2023-05-17 11:40 UTC<br\/>  <b>Sensor: <\/b> NOAA-20 VIIRS<br\/> <b>Confidence: <\/b> Nominal<br\/>  <b>Day\/Night: <\/b> Night<br\/> <b>Scan: <\/b> 0.69 km<br\/> <b>Track: <\/b> 0.74 km<br\/> <b>FRP: <\/b> 1.09 MW<br\/> <b>Brightness: <\/b> 296.36 K" }, "geometry": { "type": "Point", "coordinates": [ -122.74178, 48.88841, 0.0 ] } }
]
}
