{
"type": "FeatureCollection",
"crs": { "type": "name", "properties": { "name": "urn:ogc:def:crs:OGC:1.3:CRS84" } },
"features": [
{ "type": "Feature", "properties": { "Name": "Fire Detection Centroid ", "Description": "<b>Latitude: <\/b> 19.41336<br\/>  <b>Longitude: <\/b> -155.27174<br\/>  <b>Detection Time: <\/b> 2023-10-02 12:02 UTC<br\/>  <b>Sensor: <\/b> NOAA-20 VIIRS<br\/> <b>Confidence: <\/b> Nominal<br\/>  <b>Day\/Night: <\/b> Night<br\/> <b>Scan: <\/b> 0.39 km<br\/> <b>Track: <\/b> 0.36 km<br\/> <b>FRP: <\/b> 1.41 MW<br\/> <b>Brightness: <\/b> 300.73 K" }, "geometry": { "type": "Point", "coordinates": [ -155.27174, 19.41336, 0.0 ] } },
{ "type": "Feature", "properties": { "Name": "Fire Detection Centroid ", "Description": "<b>Latitude: <\/b> 19.41516<br\/>  <b>Longitude: <\/b> -155.28279<br\/>  <b>Detection Time: <\/b> 2023-10-02 12:02 UTC<br\/>  <b>Sensor: <\/b> NOAA-20 VIIRS<br\/> <b>Confidence: <\/b> Nominal<br\/>  <b>Day\/Night: <\/b> Night<br\/> <b>Scan: <\/b> 0.39 km<br\/> <b>Track: <\/b> 0.36 km<br\/> <b>FRP: <\/b> 2.2 MW<br\/> <b>Brightness: <\/b> 313.69 K" }, "geometry": { "type": "Point", "coordinates": [ -155.28279, 19.41516, 0.0 ] } },
{ "type": "Feature", "properties": { "Name": "Fire Detection Centroid ", "Description": "<b>Latitude: <\/b> 19.41006<br\/>  <b>Longitude: <\/b> -155.27234<br\/>  <b>Detection Time: <\/b> 2023-10-02 12:02 UTC<br\/>  <b>Sensor: <\/b> NOAA-20 VIIRS<br\/> <b>Confidence: <\/b> Nominal<br\/>  <b>Day\/Night: <\/b> Night<br\/> <b>Scan: <\/b> 0.39 km<br\/> <b>Track: <\/b> 0.36 km<br\/> <b>FRP: <\/b> 1.51 MW<br\/> <b>Brightness: <\/b> 300.26 K" }, "geometry": { "type": "Point", "coordinates": [ -155.27234, 19.41006, 0.0 ] } }
]
}
