{
"type": "FeatureCollection",
"crs": { "type": "name", "properties": { "name": "urn:ogc:def:crs:OGC:1.3:CRS84" } },
"features": [
{ "type": "Feature", "properties": { "Name": "Fire Detection Centroid ", "Description": "<b>Latitude: <\/b> 19.40881<br\/>  <b>Longitude: <\/b> -155.2847<br\/>  <b>Detection Time: <\/b> 2022-11-05 23:19 UTC<br\/>  <b>Sensor: <\/b> NOAA-20 VIIRS<br\/> <b>Confidence: <\/b> Low<br\/>  <b>Day\/Night: <\/b> Day<br\/> <b>Scan: <\/b> 0.5 km<br\/> <b>Track: <\/b> 0.4 km<br\/> <b>FRP: <\/b> 59.08 MW<br\/> <b>Brightness: <\/b> 332.57 K" }, "geometry": { "type": "Point", "coordinates": [ -155.2847, 19.40881, 0.0 ] } },
{ "type": "Feature", "properties": { "Name": "Fire Detection Centroid ", "Description": "<b>Latitude: <\/b> 19.4044<br\/>  <b>Longitude: <\/b> -155.28853<br\/>  <b>Detection Time: <\/b> 2022-11-05 23:19 UTC<br\/>  <b>Sensor: <\/b> NOAA-20 VIIRS<br\/> <b>Confidence: <\/b> Low<br\/>  <b>Day\/Night: <\/b> Day<br\/> <b>Scan: <\/b> 0.5 km<br\/> <b>Track: <\/b> 0.4 km<br\/> <b>FRP: <\/b> 59.08 MW<br\/> <b>Brightness: <\/b> 329.12 K" }, "geometry": { "type": "Point", "coordinates": [ -155.28853, 19.4044, 0.0 ] } },
{ "type": "Feature", "properties": { "Name": "Fire Detection Centroid ", "Description": "<b>Latitude: <\/b> 19.40516<br\/>  <b>Longitude: <\/b> -155.28404<br\/>  <b>Detection Time: <\/b> 2022-11-05 23:19 UTC<br\/>  <b>Sensor: <\/b> NOAA-20 VIIRS<br\/> <b>Confidence: <\/b> Low<br\/>  <b>Day\/Night: <\/b> Day<br\/> <b>Scan: <\/b> 0.5 km<br\/> <b>Track: <\/b> 0.4 km<br\/> <b>FRP: <\/b> 59.08 MW<br\/> <b>Brightness: <\/b> 367 K" }, "geometry": { "type": "Point", "coordinates": [ -155.28404, 19.40516, 0.0 ] } },
{ "type": "Feature", "properties": { "Name": "Fire Detection Centroid ", "Description": "<b>Latitude: <\/b> 19.40928<br\/>  <b>Longitude: <\/b> -155.28418<br\/>  <b>Detection Time: <\/b> 2022-11-05 23:18 UTC<br\/>  <b>Sensor: <\/b> NOAA-20 VIIRS<br\/> <b>Confidence: <\/b> Low<br\/>  <b>Day\/Night: <\/b> Day<br\/> <b>Scan: <\/b> 0.48 km<br\/> <b>Track: <\/b> 0.4 km<br\/> <b>FRP: <\/b> 59.09 MW<br\/> <b>Brightness: <\/b> 332.57 K" }, "geometry": { "type": "Point", "coordinates": [ -155.28418, 19.40928, 0.0 ] } },
{ "type": "Feature", "properties": { "Name": "Fire Detection Centroid ", "Description": "<b>Latitude: <\/b> 19.40563<br\/>  <b>Longitude: <\/b> -155.28354<br\/>  <b>Detection Time: <\/b> 2022-11-05 23:18 UTC<br\/>  <b>Sensor: <\/b> NOAA-20 VIIRS<br\/> <b>Confidence: <\/b> Low<br\/>  <b>Day\/Night: <\/b> Day<br\/> <b>Scan: <\/b> 0.48 km<br\/> <b>Track: <\/b> 0.4 km<br\/> <b>FRP: <\/b> 59.09 MW<br\/> <b>Brightness: <\/b> 367 K" }, "geometry": { "type": "Point", "coordinates": [ -155.28354, 19.40563, 0.0 ] } },
{ "type": "Feature", "properties": { "Name": "Fire Detection Centroid ", "Description": "<b>Latitude: <\/b> 19.40487<br\/>  <b>Longitude: <\/b> -155.28806<br\/>  <b>Detection Time: <\/b> 2022-11-05 23:18 UTC<br\/>  <b>Sensor: <\/b> NOAA-20 VIIRS<br\/> <b>Confidence: <\/b> Low<br\/>  <b>Day\/Night: <\/b> Day<br\/> <b>Scan: <\/b> 0.48 km<br\/> <b>Track: <\/b> 0.4 km<br\/> <b>FRP: <\/b> 59.09 MW<br\/> <b>Brightness: <\/b> 329.12 K" }, "geometry": { "type": "Point", "coordinates": [ -155.28806, 19.40487, 0.0 ] } }
]
}
