{
"type": "FeatureCollection",
"crs": { "type": "name", "properties": { "name": "urn:ogc:def:crs:OGC:1.3:CRS84" } },
"features": [
{ "type": "Feature", "properties": { "Name": "Fire Detection Centroid ", "Description": "<b>Latitude: <\/b> 39.67313<br\/>  <b>Longitude: <\/b> -121.93326<br\/>  <b>Detection Time: <\/b> 2024-06-15 11:10 UTC<br\/>  <b>Sensor: <\/b> NOAA-20 VIIRS<br\/> <b>Confidence: <\/b> Nominal<br\/>  <b>Day\/Night: <\/b> Night<br\/> <b>Scan: <\/b> 0.69 km<br\/> <b>Track: <\/b> 0.74 km<br\/> <b>FRP: <\/b> 2.49 MW<br\/> <b>Brightness: <\/b> 307.22 K" }, "geometry": { "type": "Point", "coordinates": [ -121.93326, 39.67313, 0.0 ] } },
{ "type": "Feature", "properties": { "Name": "Fire Detection Centroid ", "Description": "<b>Latitude: <\/b> 39.66832<br\/>  <b>Longitude: <\/b> -121.92598<br\/>  <b>Detection Time: <\/b> 2024-06-15 11:10 UTC<br\/>  <b>Sensor: <\/b> NOAA-20 VIIRS<br\/> <b>Confidence: <\/b> Nominal<br\/>  <b>Day\/Night: <\/b> Night<br\/> <b>Scan: <\/b> 0.69 km<br\/> <b>Track: <\/b> 0.74 km<br\/> <b>FRP: <\/b> 3.3 MW<br\/> <b>Brightness: <\/b> 310.23 K" }, "geometry": { "type": "Point", "coordinates": [ -121.92598, 39.66832, 0.0 ] } },
{ "type": "Feature", "properties": { "Name": "Fire Detection Centroid ", "Description": "<b>Latitude: <\/b> 39.67073<br\/>  <b>Longitude: <\/b> -121.93345<br\/>  <b>Detection Time: <\/b> 2024-06-15 11:10 UTC<br\/>  <b>Sensor: <\/b> NOAA-20 VIIRS<br\/> <b>Confidence: <\/b> Nominal<br\/>  <b>Day\/Night: <\/b> Night<br\/> <b>Scan: <\/b> 0.69 km<br\/> <b>Track: <\/b> 0.74 km<br\/> <b>FRP: <\/b> 2.68 MW<br\/> <b>Brightness: <\/b> 310.57 K" }, "geometry": { "type": "Point", "coordinates": [ -121.93345, 39.67073, 0.0 ] } },
{ "type": "Feature", "properties": { "Name": "Fire Detection Centroid ", "Description": "<b>Latitude: <\/b> 39.67069<br\/>  <b>Longitude: <\/b> -121.92582<br\/>  <b>Detection Time: <\/b> 2024-06-15 11:10 UTC<br\/>  <b>Sensor: <\/b> NOAA-20 VIIRS<br\/> <b>Confidence: <\/b> Nominal<br\/>  <b>Day\/Night: <\/b> Night<br\/> <b>Scan: <\/b> 0.69 km<br\/> <b>Track: <\/b> 0.74 km<br\/> <b>FRP: <\/b> 2.49 MW<br\/> <b>Brightness: <\/b> 314.15 K" }, "geometry": { "type": "Point", "coordinates": [ -121.92582, 39.67069, 0.0 ] } }
]
}
