{
"type": "FeatureCollection",
"crs": { "type": "name", "properties": { "name": "urn:ogc:def:crs:OGC:1.3:CRS84" } },
"features": [
{ "type": "Feature", "properties": { "Name": "Fire Detection Centroid ", "Description": "<b>Latitude: <\/b> 44.85492<br\/>  <b>Longitude: <\/b> -75.41845<br\/>  <b>Detection Time: <\/b> 2023-08-31 16:36 UTC<br\/>  <b>Sensor: <\/b> NOAA-20 VIIRS<br\/> <b>Confidence: <\/b> Nominal<br\/>  <b>Day\/Night: <\/b> Day<br\/> <b>Scan: <\/b> 0.7 km<br\/> <b>Track: <\/b> 0.7 km<br\/> <b>FRP: <\/b> 4.22 MW<br\/> <b>Brightness: <\/b> 326.92 K" }, "geometry": { "type": "Point", "coordinates": [ -75.41845, 44.85492, 0.0 ] } },
{ "type": "Feature", "properties": { "Name": "Fire Detection Centroid ", "Description": "<b>Latitude: <\/b> 44.85085<br\/>  <b>Longitude: <\/b> -75.41464<br\/>  <b>Detection Time: <\/b> 2023-08-31 16:36 UTC<br\/>  <b>Sensor: <\/b> NOAA-20 VIIRS<br\/> <b>Confidence: <\/b> Nominal<br\/>  <b>Day\/Night: <\/b> Day<br\/> <b>Scan: <\/b> 0.7 km<br\/> <b>Track: <\/b> 0.7 km<br\/> <b>FRP: <\/b> 4.13 MW<br\/> <b>Brightness: <\/b> 328.18 K" }, "geometry": { "type": "Point", "coordinates": [ -75.41464, 44.85085, 0.0 ] } },
{ "type": "Feature", "properties": { "Name": "Fire Detection Centroid ", "Description": "<b>Latitude: <\/b> 19.59748<br\/>  <b>Longitude: <\/b> -155.50471<br\/>  <b>Detection Time: <\/b> 2023-08-31 12:02 UTC<br\/>  <b>Sensor: <\/b> NOAA-20 VIIRS<br\/> <b>Confidence: <\/b> Nominal<br\/>  <b>Day\/Night: <\/b> Night<br\/> <b>Scan: <\/b> 0.39 km<br\/> <b>Track: <\/b> 0.36 km<br\/> <b>FRP: <\/b> 1.56 MW<br\/> <b>Brightness: <\/b> 297.49 K" }, "geometry": { "type": "Point", "coordinates": [ -155.50471, 19.59748, 0.0 ] } }
]
}
