{
"type": "FeatureCollection",
"crs": { "type": "name", "properties": { "name": "urn:ogc:def:crs:OGC:1.3:CRS84" } },
"features": [
{ "type": "Feature", "properties": { "Name": "Fire Detection Centroid ", "Description": "<b>Latitude: <\/b> 19.40259<br\/>  <b>Longitude: <\/b> -155.2757<br\/>  <b>Detection Time: <\/b> 2022-08-20 00:22 UTC<br\/>  <b>Sensor: <\/b> NOAA-20 VIIRS<br\/> <b>Confidence: <\/b> Nominal<br\/>  <b>Day\/Night: <\/b> Day<br\/> <b>Scan: <\/b> 0.54 km<br\/> <b>Track: <\/b> 0.68 km<br\/> <b>FRP: <\/b> 9.45 MW<br\/> <b>Brightness: <\/b> 339.63 K" }, "geometry": { "type": "Point", "coordinates": [ -155.2757, 19.40259, 0.0 ] } },
{ "type": "Feature", "properties": { "Name": "Fire Detection Centroid ", "Description": "<b>Latitude: <\/b> 19.40214<br\/>  <b>Longitude: <\/b> -155.28088<br\/>  <b>Detection Time: <\/b> 2022-08-20 00:22 UTC<br\/>  <b>Sensor: <\/b> NOAA-20 VIIRS<br\/> <b>Confidence: <\/b> Nominal<br\/>  <b>Day\/Night: <\/b> Day<br\/> <b>Scan: <\/b> 0.54 km<br\/> <b>Track: <\/b> 0.68 km<br\/> <b>FRP: <\/b> 7.59 MW<br\/> <b>Brightness: <\/b> 345.6 K" }, "geometry": { "type": "Point", "coordinates": [ -155.28088, 19.40214, 0.0 ] } },
{ "type": "Feature", "properties": { "Name": "Fire Detection Centroid ", "Description": "<b>Latitude: <\/b> 19.40168<br\/>  <b>Longitude: <\/b> -155.28618<br\/>  <b>Detection Time: <\/b> 2022-08-20 00:22 UTC<br\/>  <b>Sensor: <\/b> NOAA-20 VIIRS<br\/> <b>Confidence: <\/b> Nominal<br\/>  <b>Day\/Night: <\/b> Day<br\/> <b>Scan: <\/b> 0.54 km<br\/> <b>Track: <\/b> 0.68 km<br\/> <b>FRP: <\/b> 7.59 MW<br\/> <b>Brightness: <\/b> 349.35 K" }, "geometry": { "type": "Point", "coordinates": [ -155.28618, 19.40168, 0.0 ] } },
{ "type": "Feature", "properties": { "Name": "Fire Detection Centroid ", "Description": "<b>Latitude: <\/b> 19.40885<br\/>  <b>Longitude: <\/b> -155.2762<br\/>  <b>Detection Time: <\/b> 2022-08-20 00:22 UTC<br\/>  <b>Sensor: <\/b> NOAA-20 VIIRS<br\/> <b>Confidence: <\/b> Nominal<br\/>  <b>Day\/Night: <\/b> Day<br\/> <b>Scan: <\/b> 0.54 km<br\/> <b>Track: <\/b> 0.68 km<br\/> <b>FRP: <\/b> 8.36 MW<br\/> <b>Brightness: <\/b> 330.79 K" }, "geometry": { "type": "Point", "coordinates": [ -155.2762, 19.40885, 0.0 ] } },
{ "type": "Feature", "properties": { "Name": "Fire Detection Centroid ", "Description": "<b>Latitude: <\/b> 21.5163<br\/>  <b>Longitude: <\/b> -158.20799<br\/>  <b>Detection Time: <\/b> 2022-08-20 00:22 UTC<br\/>  <b>Sensor: <\/b> NOAA-20 VIIRS<br\/> <b>Confidence: <\/b> Nominal<br\/>  <b>Day\/Night: <\/b> Day<br\/> <b>Scan: <\/b> 0.37 km<br\/> <b>Track: <\/b> 0.58 km<br\/> <b>FRP: <\/b> 3.53 MW<br\/> <b>Brightness: <\/b> 355.98 K" }, "geometry": { "type": "Point", "coordinates": [ -158.20799, 21.5163, 0.0 ] } },
{ "type": "Feature", "properties": { "Name": "Fire Detection Centroid ", "Description": "<b>Latitude: <\/b> 21.52149<br\/>  <b>Longitude: <\/b> -158.21005<br\/>  <b>Detection Time: <\/b> 2022-08-20 00:22 UTC<br\/>  <b>Sensor: <\/b> NOAA-20 VIIRS<br\/> <b>Confidence: <\/b> Nominal<br\/>  <b>Day\/Night: <\/b> Day<br\/> <b>Scan: <\/b> 0.37 km<br\/> <b>Track: <\/b> 0.58 km<br\/> <b>FRP: <\/b> 4.65 MW<br\/> <b>Brightness: <\/b> 333.49 K" }, "geometry": { "type": "Point", "coordinates": [ -158.21005, 21.52149, 0.0 ] } },
{ "type": "Feature", "properties": { "Name": "Fire Detection Centroid ", "Description": "<b>Latitude: <\/b> 21.51601<br\/>  <b>Longitude: <\/b> -158.21094<br\/>  <b>Detection Time: <\/b> 2022-08-20 00:22 UTC<br\/>  <b>Sensor: <\/b> NOAA-20 VIIRS<br\/> <b>Confidence: <\/b> Nominal<br\/>  <b>Day\/Night: <\/b> Day<br\/> <b>Scan: <\/b> 0.37 km<br\/> <b>Track: <\/b> 0.58 km<br\/> <b>FRP: <\/b> 3.53 MW<br\/> <b>Brightness: <\/b> 341.21 K" }, "geometry": { "type": "Point", "coordinates": [ -158.21094, 21.51601, 0.0 ] } }
]
}
