{
"type": "FeatureCollection",
"crs": { "type": "name", "properties": { "name": "urn:ogc:def:crs:OGC:1.3:CRS84" } },
"features": [
{ "type": "Feature", "properties": { "Name": "Fire Detection Centroid ", "Description": "<b>Latitude: <\/b> 39.64764<br\/>  <b>Longitude: <\/b> -75.49542<br\/>  <b>Detection Time: <\/b> 2023-03-18 16:46 UTC<br\/>  <b>Sensor: <\/b> NOAA-20 VIIRS<br\/> <b>Confidence: <\/b> Nominal<br\/>  <b>Day\/Night: <\/b> Day<br\/> <b>Scan: <\/b> 0.7 km<br\/> <b>Track: <\/b> 0.8 km<br\/> <b>FRP: <\/b> 9 MW<br\/> <b>Brightness: <\/b> 334.31 K" }, "geometry": { "type": "Point", "coordinates": [ -75.49542, 39.64764, 0.0 ] } },
{ "type": "Feature", "properties": { "Name": "Fire Detection Centroid ", "Description": "<b>Latitude: <\/b> 39.65023<br\/>  <b>Longitude: <\/b> -75.48749<br\/>  <b>Detection Time: <\/b> 2023-03-18 16:46 UTC<br\/>  <b>Sensor: <\/b> NOAA-20 VIIRS<br\/> <b>Confidence: <\/b> Nominal<br\/>  <b>Day\/Night: <\/b> Day<br\/> <b>Scan: <\/b> 0.7 km<br\/> <b>Track: <\/b> 0.8 km<br\/> <b>FRP: <\/b> 9 MW<br\/> <b>Brightness: <\/b> 351.65 K" }, "geometry": { "type": "Point", "coordinates": [ -75.48749, 39.65023, 0.0 ] } },
{ "type": "Feature", "properties": { "Name": "Fire Detection Centroid ", "Description": "<b>Latitude: <\/b> 39.65462<br\/>  <b>Longitude: <\/b> -75.49589<br\/>  <b>Detection Time: <\/b> 2023-03-18 16:46 UTC<br\/>  <b>Sensor: <\/b> NOAA-20 VIIRS<br\/> <b>Confidence: <\/b> Nominal<br\/>  <b>Day\/Night: <\/b> Day<br\/> <b>Scan: <\/b> 0.7 km<br\/> <b>Track: <\/b> 0.8 km<br\/> <b>FRP: <\/b> 14.36 MW<br\/> <b>Brightness: <\/b> 356.21 K" }, "geometry": { "type": "Point", "coordinates": [ -75.49589, 39.65462, 0.0 ] } },
{ "type": "Feature", "properties": { "Name": "Fire Detection Centroid ", "Description": "<b>Latitude: <\/b> 39.64812<br\/>  <b>Longitude: <\/b> -75.49228<br\/>  <b>Detection Time: <\/b> 2023-03-18 16:46 UTC<br\/>  <b>Sensor: <\/b> NOAA-20 VIIRS<br\/> <b>Confidence: <\/b> Nominal<br\/>  <b>Day\/Night: <\/b> Day<br\/> <b>Scan: <\/b> 0.7 km<br\/> <b>Track: <\/b> 0.8 km<br\/> <b>FRP: <\/b> 8.07 MW<br\/> <b>Brightness: <\/b> 339.77 K" }, "geometry": { "type": "Point", "coordinates": [ -75.49228, 39.64812, 0.0 ] } },
{ "type": "Feature", "properties": { "Name": "Fire Detection Centroid ", "Description": "<b>Latitude: <\/b> 39.65412<br\/>  <b>Longitude: <\/b> -75.49908<br\/>  <b>Detection Time: <\/b> 2023-03-18 16:46 UTC<br\/>  <b>Sensor: <\/b> NOAA-20 VIIRS<br\/> <b>Confidence: <\/b> Nominal<br\/>  <b>Day\/Night: <\/b> Day<br\/> <b>Scan: <\/b> 0.7 km<br\/> <b>Track: <\/b> 0.8 km<br\/> <b>FRP: <\/b> 9 MW<br\/> <b>Brightness: <\/b> 334.44 K" }, "geometry": { "type": "Point", "coordinates": [ -75.49908, 39.65412, 0.0 ] } },
{ "type": "Feature", "properties": { "Name": "Fire Detection Centroid ", "Description": "<b>Latitude: <\/b> 19.59464<br\/>  <b>Longitude: <\/b> -155.50497<br\/>  <b>Detection Time: <\/b> 2023-03-18 12:14 UTC<br\/>  <b>Sensor: <\/b> NOAA-20 VIIRS<br\/> <b>Confidence: <\/b> Nominal<br\/>  <b>Day\/Night: <\/b> Night<br\/> <b>Scan: <\/b> 0.48 km<br\/> <b>Track: <\/b> 0.4 km<br\/> <b>FRP: <\/b> 2.79 MW<br\/> <b>Brightness: <\/b> 298.16 K" }, "geometry": { "type": "Point", "coordinates": [ -155.50497, 19.59464, 0.0 ] } },
{ "type": "Feature", "properties": { "Name": "Fire Detection Centroid ", "Description": "<b>Latitude: <\/b> 19.59825<br\/>  <b>Longitude: <\/b> -155.50404<br\/>  <b>Detection Time: <\/b> 2023-03-18 12:14 UTC<br\/>  <b>Sensor: <\/b> NOAA-20 VIIRS<br\/> <b>Confidence: <\/b> Nominal<br\/>  <b>Day\/Night: <\/b> Night<br\/> <b>Scan: <\/b> 0.48 km<br\/> <b>Track: <\/b> 0.4 km<br\/> <b>FRP: <\/b> 1.41 MW<br\/> <b>Brightness: <\/b> 302.71 K" }, "geometry": { "type": "Point", "coordinates": [ -155.50404, 19.59825, 0.0 ] } },
{ "type": "Feature", "properties": { "Name": "Fire Detection Centroid ", "Description": "<b>Latitude: <\/b> 19.57662<br\/>  <b>Longitude: <\/b> -155.50963<br\/>  <b>Detection Time: <\/b> 2023-03-18 12:14 UTC<br\/>  <b>Sensor: <\/b> NOAA-20 VIIRS<br\/> <b>Confidence: <\/b> Nominal<br\/>  <b>Day\/Night: <\/b> Night<br\/> <b>Scan: <\/b> 0.48 km<br\/> <b>Track: <\/b> 0.4 km<br\/> <b>FRP: <\/b> 2.6 MW<br\/> <b>Brightness: <\/b> 296.56 K" }, "geometry": { "type": "Point", "coordinates": [ -155.50963, 19.57662, 0.0 ] } },
{ "type": "Feature", "properties": { "Name": "Fire Detection Centroid ", "Description": "<b>Latitude: <\/b> 19.60185<br\/>  <b>Longitude: <\/b> -155.50311<br\/>  <b>Detection Time: <\/b> 2023-03-18 12:14 UTC<br\/>  <b>Sensor: <\/b> NOAA-20 VIIRS<br\/> <b>Confidence: <\/b> Nominal<br\/>  <b>Day\/Night: <\/b> Night<br\/> <b>Scan: <\/b> 0.48 km<br\/> <b>Track: <\/b> 0.4 km<br\/> <b>FRP: <\/b> 1.41 MW<br\/> <b>Brightness: <\/b> 299.11 K" }, "geometry": { "type": "Point", "coordinates": [ -155.50311, 19.60185, 0.0 ] } }
]
}
