{
"type": "FeatureCollection",
"crs": { "type": "name", "properties": { "name": "urn:ogc:def:crs:OGC:1.3:CRS84" } },
"features": [
{ "type": "Feature", "properties": { "Name": "Fire Detection Centroid ", "Description": "<b>Latitude: <\/b> 20.83778<br\/>  <b>Longitude: <\/b> -156.4621<br\/>  <b>Detection Time: <\/b> 2024-04-20 23:20 UTC<br\/>  <b>Sensor: <\/b> NOAA-20 VIIRS<br\/> <b>Confidence: <\/b> Nominal<br\/>  <b>Day\/Night: <\/b> Day<br\/> <b>Scan: <\/b> 0.51 km<br\/> <b>Track: <\/b> 0.41 km<br\/> <b>FRP: <\/b> 8.65 MW<br\/> <b>Brightness: <\/b> 345.39 K" }, "geometry": { "type": "Point", "coordinates": [ -156.4621, 20.83778, 0.0 ] } }
]
}
