{
"type": "FeatureCollection",
"crs": { "type": "name", "properties": { "name": "urn:ogc:def:crs:OGC:1.3:CRS84" } },
"features": [
{ "type": "Feature", "properties": { "Name": "Fire Detection Centroid ", "Description": "<b>Latitude: <\/b> 18.39457<br\/>  <b>Longitude: <\/b> -71.72672<br\/>  <b>Detection Time: <\/b> 2024-01-26 05:42 UTC<br\/>  <b>Sensor: <\/b> NOAA-20 VIIRS<br\/> <b>Confidence: <\/b> Nominal<br\/>  <b>Day\/Night: <\/b> Night<br\/> <b>Scan: <\/b> 0.4 km<br\/> <b>Track: <\/b> 0.6 km<br\/> <b>FRP: <\/b> 1.37 MW<br\/> <b>Brightness: <\/b> 299.88 K" }, "geometry": { "type": "Point", "coordinates": [ -71.72672, 18.39457, 0.0 ] } },
{ "type": "Feature", "properties": { "Name": "Fire Detection Centroid ", "Description": "<b>Latitude: <\/b> 18.76528<br\/>  <b>Longitude: <\/b> -70.98623<br\/>  <b>Detection Time: <\/b> 2024-01-26 05:41 UTC<br\/>  <b>Sensor: <\/b> NOAA-20 VIIRS<br\/> <b>Confidence: <\/b> Nominal<br\/>  <b>Day\/Night: <\/b> Night<br\/> <b>Scan: <\/b> 0.4 km<br\/> <b>Track: <\/b> 0.6 km<br\/> <b>FRP: <\/b> 3.5 MW<br\/> <b>Brightness: <\/b> 337.73 K" }, "geometry": { "type": "Point", "coordinates": [ -70.98623, 18.76528, 0.0 ] } },
{ "type": "Feature", "properties": { "Name": "Fire Detection Centroid ", "Description": "<b>Latitude: <\/b> 20.37536<br\/>  <b>Longitude: <\/b> -75.43812<br\/>  <b>Detection Time: <\/b> 2024-01-26 05:41 UTC<br\/>  <b>Sensor: <\/b> NOAA-20 VIIRS<br\/> <b>Confidence: <\/b> Nominal<br\/>  <b>Day\/Night: <\/b> Night<br\/> <b>Scan: <\/b> 0.8 km<br\/> <b>Track: <\/b> 0.8 km<br\/> <b>FRP: <\/b> 2.81 MW<br\/> <b>Brightness: <\/b> 310.31 K" }, "geometry": { "type": "Point", "coordinates": [ -75.43812, 20.37536, 0.0 ] } },
{ "type": "Feature", "properties": { "Name": "Fire Detection Centroid ", "Description": "<b>Latitude: <\/b> 20.1742<br\/>  <b>Longitude: <\/b> -75.21255<br\/>  <b>Detection Time: <\/b> 2024-01-26 05:41 UTC<br\/>  <b>Sensor: <\/b> NOAA-20 VIIRS<br\/> <b>Confidence: <\/b> Nominal<br\/>  <b>Day\/Night: <\/b> Night<br\/> <b>Scan: <\/b> 0.8 km<br\/> <b>Track: <\/b> 0.8 km<br\/> <b>FRP: <\/b> 0.82 MW<br\/> <b>Brightness: <\/b> 301.78 K" }, "geometry": { "type": "Point", "coordinates": [ -75.21255, 20.1742, 0.0 ] } }
]
}
