{
"type": "FeatureCollection",
"crs": { "type": "name", "properties": { "name": "urn:ogc:def:crs:OGC:1.3:CRS84" } },
"features": [
{ "type": "Feature", "properties": { "Name": "Fire Detection Centroid ", "Description": "<b>Latitude: <\/b> 44.57321<br\/>  <b>Longitude: <\/b> -68.72501<br\/>  <b>Detection Time: <\/b> 2023-04-08 16:53 UTC<br\/>  <b>Sensor: <\/b> NOAA-20 VIIRS<br\/> <b>Confidence: <\/b> Nominal<br\/>  <b>Day\/Night: <\/b> Day<br\/> <b>Scan: <\/b> 0.4 km<br\/> <b>Track: <\/b> 0.5 km<br\/> <b>FRP: <\/b> 2.66 MW<br\/> <b>Brightness: <\/b> 325.21 K" }, "geometry": { "type": "Point", "coordinates": [ -68.72501, 44.57321, 0.0 ] } },
{ "type": "Feature", "properties": { "Name": "Fire Detection Centroid ", "Description": "<b>Latitude: <\/b> 44.15707<br\/>  <b>Longitude: <\/b> -69.17963<br\/>  <b>Detection Time: <\/b> 2023-04-08 16:53 UTC<br\/>  <b>Sensor: <\/b> NOAA-20 VIIRS<br\/> <b>Confidence: <\/b> Nominal<br\/>  <b>Day\/Night: <\/b> Day<br\/> <b>Scan: <\/b> 0.5 km<br\/> <b>Track: <\/b> 0.5 km<br\/> <b>FRP: <\/b> 5.19 MW<br\/> <b>Brightness: <\/b> 335.04 K" }, "geometry": { "type": "Point", "coordinates": [ -69.17963, 44.15707, 0.0 ] } },
{ "type": "Feature", "properties": { "Name": "Fire Detection Centroid ", "Description": "<b>Latitude: <\/b> 42.66724<br\/>  <b>Longitude: <\/b> -70.6608<br\/>  <b>Detection Time: <\/b> 2023-04-08 16:53 UTC<br\/>  <b>Sensor: <\/b> NOAA-20 VIIRS<br\/> <b>Confidence: <\/b> Nominal<br\/>  <b>Day\/Night: <\/b> Day<br\/> <b>Scan: <\/b> 0.6 km<br\/> <b>Track: <\/b> 0.5 km<br\/> <b>FRP: <\/b> 12.6 MW<br\/> <b>Brightness: <\/b> 338.57 K" }, "geometry": { "type": "Point", "coordinates": [ -70.6608, 42.66724, 0.0 ] } }
]
}
