{
"type": "FeatureCollection",
"crs": { "type": "name", "properties": { "name": "urn:ogc:def:crs:OGC:1.3:CRS84" } },
"features": [
{ "type": "Feature", "properties": { "Name": "Fire Detection Centroid ", "Description": "<b>Latitude: <\/b> 28.86645<br\/>  <b>Longitude: <\/b> -80.99403<br\/>  <b>Detection Time: <\/b> 2023-01-25 17:58 UTC<br\/>  <b>Sensor: <\/b> NOAA-20 VIIRS<br\/> <b>Confidence: <\/b> Nominal<br\/>  <b>Day\/Night: <\/b> Day<br\/> <b>Scan: <\/b> 0.5 km<br\/> <b>Track: <\/b> 0.5 km<br\/> <b>FRP: <\/b> 2.73 MW<br\/> <b>Brightness: <\/b> 331.61 K" }, "geometry": { "type": "Point", "coordinates": [ -80.99403, 28.86645, 0.0 ] } },
{ "type": "Feature", "properties": { "Name": "Fire Detection Centroid ", "Description": "<b>Latitude: <\/b> 24.66687<br\/>  <b>Longitude: <\/b> -78.06204<br\/>  <b>Detection Time: <\/b> 2023-01-25 17:57 UTC<br\/>  <b>Sensor: <\/b> NOAA-20 VIIRS<br\/> <b>Confidence: <\/b> Nominal<br\/>  <b>Day\/Night: <\/b> Day<br\/> <b>Scan: <\/b> 0.4 km<br\/> <b>Track: <\/b> 0.5 km<br\/> <b>FRP: <\/b> 5.08 MW<br\/> <b>Brightness: <\/b> 338.06 K" }, "geometry": { "type": "Point", "coordinates": [ -78.06204, 24.66687, 0.0 ] } },
{ "type": "Feature", "properties": { "Name": "Fire Detection Centroid ", "Description": "<b>Latitude: <\/b> 26.53395<br\/>  <b>Longitude: <\/b> -80.86002<br\/>  <b>Detection Time: <\/b> 2023-01-25 17:57 UTC<br\/>  <b>Sensor: <\/b> NOAA-20 VIIRS<br\/> <b>Confidence: <\/b> Nominal<br\/>  <b>Day\/Night: <\/b> Day<br\/> <b>Scan: <\/b> 0.6 km<br\/> <b>Track: <\/b> 0.5 km<br\/> <b>FRP: <\/b> 8.56 MW<br\/> <b>Brightness: <\/b> 352.05 K" }, "geometry": { "type": "Point", "coordinates": [ -80.86002, 26.53395, 0.0 ] } },
{ "type": "Feature", "properties": { "Name": "Fire Detection Centroid ", "Description": "<b>Latitude: <\/b> 26.53862<br\/>  <b>Longitude: <\/b> -80.86127<br\/>  <b>Detection Time: <\/b> 2023-01-25 17:57 UTC<br\/>  <b>Sensor: <\/b> NOAA-20 VIIRS<br\/> <b>Confidence: <\/b> Nominal<br\/>  <b>Day\/Night: <\/b> Day<br\/> <b>Scan: <\/b> 0.6 km<br\/> <b>Track: <\/b> 0.5 km<br\/> <b>FRP: <\/b> 20.66 MW<br\/> <b>Brightness: <\/b> 349.17 K" }, "geometry": { "type": "Point", "coordinates": [ -80.86127, 26.53862, 0.0 ] } },
{ "type": "Feature", "properties": { "Name": "Fire Detection Centroid ", "Description": "<b>Latitude: <\/b> 26.53742<br\/>  <b>Longitude: <\/b> -80.86686<br\/>  <b>Detection Time: <\/b> 2023-01-25 17:57 UTC<br\/>  <b>Sensor: <\/b> NOAA-20 VIIRS<br\/> <b>Confidence: <\/b> Nominal<br\/>  <b>Day\/Night: <\/b> Day<br\/> <b>Scan: <\/b> 0.6 km<br\/> <b>Track: <\/b> 0.5 km<br\/> <b>FRP: <\/b> 23.67 MW<br\/> <b>Brightness: <\/b> 353.88 K" }, "geometry": { "type": "Point", "coordinates": [ -80.86686, 26.53742, 0.0 ] } },
{ "type": "Feature", "properties": { "Name": "Fire Detection Centroid ", "Description": "<b>Latitude: <\/b> 26.454<br\/>  <b>Longitude: <\/b> -81.27753<br\/>  <b>Detection Time: <\/b> 2023-01-25 17:57 UTC<br\/>  <b>Sensor: <\/b> NOAA-20 VIIRS<br\/> <b>Confidence: <\/b> Nominal<br\/>  <b>Day\/Night: <\/b> Day<br\/> <b>Scan: <\/b> 0.6 km<br\/> <b>Track: <\/b> 0.5 km<br\/> <b>FRP: <\/b> 6.37 MW<br\/> <b>Brightness: <\/b> 339.5 K" }, "geometry": { "type": "Point", "coordinates": [ -81.27753, 26.454, 0.0 ] } },
{ "type": "Feature", "properties": { "Name": "Fire Detection Centroid ", "Description": "<b>Latitude: <\/b> 26.4588<br\/>  <b>Longitude: <\/b> -81.27882<br\/>  <b>Detection Time: <\/b> 2023-01-25 17:57 UTC<br\/>  <b>Sensor: <\/b> NOAA-20 VIIRS<br\/> <b>Confidence: <\/b> Nominal<br\/>  <b>Day\/Night: <\/b> Day<br\/> <b>Scan: <\/b> 0.6 km<br\/> <b>Track: <\/b> 0.5 km<br\/> <b>FRP: <\/b> 5.34 MW<br\/> <b>Brightness: <\/b> 337.15 K" }, "geometry": { "type": "Point", "coordinates": [ -81.27882, 26.4588, 0.0 ] } },
{ "type": "Feature", "properties": { "Name": "Fire Detection Centroid ", "Description": "<b>Latitude: <\/b> 27.04993<br\/>  <b>Longitude: <\/b> -80.45412<br\/>  <b>Detection Time: <\/b> 2023-01-25 17:57 UTC<br\/>  <b>Sensor: <\/b> NOAA-20 VIIRS<br\/> <b>Confidence: <\/b> Nominal<br\/>  <b>Day\/Night: <\/b> Day<br\/> <b>Scan: <\/b> 0.5 km<br\/> <b>Track: <\/b> 0.5 km<br\/> <b>FRP: <\/b> 25.93 MW<br\/> <b>Brightness: <\/b> 341.73 K" }, "geometry": { "type": "Point", "coordinates": [ -80.45412, 27.04993, 0.0 ] } },
{ "type": "Feature", "properties": { "Name": "Fire Detection Centroid ", "Description": "<b>Latitude: <\/b> 27.04542<br\/>  <b>Longitude: <\/b> -80.45293<br\/>  <b>Detection Time: <\/b> 2023-01-25 17:57 UTC<br\/>  <b>Sensor: <\/b> NOAA-20 VIIRS<br\/> <b>Confidence: <\/b> Nominal<br\/>  <b>Day\/Night: <\/b> Day<br\/> <b>Scan: <\/b> 0.5 km<br\/> <b>Track: <\/b> 0.5 km<br\/> <b>FRP: <\/b> 25.93 MW<br\/> <b>Brightness: <\/b> 346.63 K" }, "geometry": { "type": "Point", "coordinates": [ -80.45293, 27.04542, 0.0 ] } }
]
}
