{
"type": "FeatureCollection",
"crs": { "type": "name", "properties": { "name": "urn:ogc:def:crs:OGC:1.3:CRS84" } },
"features": [
{ "type": "Feature", "properties": { "Name": "Fire Detection Centroid ", "Description": "<b>Latitude: <\/b> 46.8476<br\/>  <b>Longitude: <\/b> -71.22038<br\/>  <b>Detection Time: <\/b> 2022-09-06 17:06 UTC<br\/>  <b>Sensor: <\/b> NOAA-20 VIIRS<br\/> <b>Confidence: <\/b> Nominal<br\/>  <b>Day\/Night: <\/b> Day<br\/> <b>Scan: <\/b> 0.5 km<br\/> <b>Track: <\/b> 0.4 km<br\/> <b>FRP: <\/b> 3.15 MW<br\/> <b>Brightness: <\/b> 332.73 K" }, "geometry": { "type": "Point", "coordinates": [ -71.22038, 46.8476, 0.0 ] } },
{ "type": "Feature", "properties": { "Name": "Fire Detection Centroid ", "Description": "<b>Latitude: <\/b> 43.26485<br\/>  <b>Longitude: <\/b> -79.8071<br\/>  <b>Detection Time: <\/b> 2022-09-06 17:06 UTC<br\/>  <b>Sensor: <\/b> NOAA-20 VIIRS<br\/> <b>Confidence: <\/b> Nominal<br\/>  <b>Day\/Night: <\/b> Day<br\/> <b>Scan: <\/b> 0.5 km<br\/> <b>Track: <\/b> 0.7 km<br\/> <b>FRP: <\/b> 6.19 MW<br\/> <b>Brightness: <\/b> 328.59 K" }, "geometry": { "type": "Point", "coordinates": [ -79.8071, 43.26485, 0.0 ] } },
{ "type": "Feature", "properties": { "Name": "Fire Detection Centroid ", "Description": "<b>Latitude: <\/b> 44.25471<br\/>  <b>Longitude: <\/b> -78.86809<br\/>  <b>Detection Time: <\/b> 2022-09-06 17:06 UTC<br\/>  <b>Sensor: <\/b> NOAA-20 VIIRS<br\/> <b>Confidence: <\/b> Nominal<br\/>  <b>Day\/Night: <\/b> Day<br\/> <b>Scan: <\/b> 0.5 km<br\/> <b>Track: <\/b> 0.6 km<br\/> <b>FRP: <\/b> 4.34 MW<br\/> <b>Brightness: <\/b> 339.16 K" }, "geometry": { "type": "Point", "coordinates": [ -78.86809, 44.25471, 0.0 ] } },
{ "type": "Feature", "properties": { "Name": "Fire Detection Centroid ", "Description": "<b>Latitude: <\/b> 46.04406<br\/>  <b>Longitude: <\/b> -73.14044<br\/>  <b>Detection Time: <\/b> 2022-09-06 17:06 UTC<br\/>  <b>Sensor: <\/b> NOAA-20 VIIRS<br\/> <b>Confidence: <\/b> Nominal<br\/>  <b>Day\/Night: <\/b> Day<br\/> <b>Scan: <\/b> 0.5 km<br\/> <b>Track: <\/b> 0.5 km<br\/> <b>FRP: <\/b> 4.06 MW<br\/> <b>Brightness: <\/b> 329.5 K" }, "geometry": { "type": "Point", "coordinates": [ -73.14044, 46.04406, 0.0 ] } },
{ "type": "Feature", "properties": { "Name": "Fire Detection Centroid ", "Description": "<b>Latitude: <\/b> 42.8043<br\/>  <b>Longitude: <\/b> -80.09766<br\/>  <b>Detection Time: <\/b> 2022-09-06 17:05 UTC<br\/>  <b>Sensor: <\/b> NOAA-20 VIIRS<br\/> <b>Confidence: <\/b> Nominal<br\/>  <b>Day\/Night: <\/b> Day<br\/> <b>Scan: <\/b> 0.6 km<br\/> <b>Track: <\/b> 0.7 km<br\/> <b>FRP: <\/b> 7.71 MW<br\/> <b>Brightness: <\/b> 331.99 K" }, "geometry": { "type": "Point", "coordinates": [ -80.09766, 42.8043, 0.0 ] } },
{ "type": "Feature", "properties": { "Name": "Fire Detection Centroid ", "Description": "<b>Latitude: <\/b> 18.92898<br\/>  <b>Longitude: <\/b> -70.35144<br\/>  <b>Detection Time: <\/b> 2022-09-06 16:58 UTC<br\/>  <b>Sensor: <\/b> NOAA-20 VIIRS<br\/> <b>Confidence: <\/b> High<br\/>  <b>Day\/Night: <\/b> Day<br\/> <b>Scan: <\/b> 0.7 km<br\/> <b>Track: <\/b> 0.8 km<br\/> <b>FRP: <\/b> 14.79 MW<br\/> <b>Brightness: <\/b> 367 K" }, "geometry": { "type": "Point", "coordinates": [ -70.35144, 18.92898, 0.0 ] } },
{ "type": "Feature", "properties": { "Name": "Fire Detection Centroid ", "Description": "<b>Latitude: <\/b> 18.92359<br\/>  <b>Longitude: <\/b> -70.34818<br\/>  <b>Detection Time: <\/b> 2022-09-06 16:58 UTC<br\/>  <b>Sensor: <\/b> NOAA-20 VIIRS<br\/> <b>Confidence: <\/b> Nominal<br\/>  <b>Day\/Night: <\/b> Day<br\/> <b>Scan: <\/b> 0.7 km<br\/> <b>Track: <\/b> 0.8 km<br\/> <b>FRP: <\/b> 10.35 MW<br\/> <b>Brightness: <\/b> 343.51 K" }, "geometry": { "type": "Point", "coordinates": [ -70.34818, 18.92359, 0.0 ] } },
{ "type": "Feature", "properties": { "Name": "Fire Detection Centroid ", "Description": "<b>Latitude: <\/b> 18.93002<br\/>  <b>Longitude: <\/b> -70.35131<br\/>  <b>Detection Time: <\/b> 2022-09-06 16:58 UTC<br\/>  <b>Sensor: <\/b> NOAA-20 VIIRS<br\/> <b>Confidence: <\/b> Nominal<br\/>  <b>Day\/Night: <\/b> Day<br\/> <b>Scan: <\/b> 0.7 km<br\/> <b>Track: <\/b> 0.8 km<br\/> <b>FRP: <\/b> 8.23 MW<br\/> <b>Brightness: <\/b> 330.97 K" }, "geometry": { "type": "Point", "coordinates": [ -70.35131, 18.93002, 0.0 ] } }
]
}
