{
"type": "FeatureCollection",
"crs": { "type": "name", "properties": { "name": "urn:ogc:def:crs:OGC:1.3:CRS84" } },
"features": [
{ "type": "Feature", "properties": { "Name": "Fire Detection Centroid ", "Description": "<b>Latitude: <\/b> 19.40527<br\/>  <b>Longitude: <\/b> -155.28023<br\/>  <b>Detection Time: <\/b> 2022-07-08 00:28 UTC<br\/>  <b>Sensor: <\/b> NOAA-20 VIIRS<br\/> <b>Confidence: <\/b> Nominal<br\/>  <b>Day\/Night: <\/b> Day<br\/> <b>Scan: <\/b> 0.7 km<br\/> <b>Track: <\/b> 0.75 km<br\/> <b>FRP: <\/b> 18.05 MW<br\/> <b>Brightness: <\/b> 330.66 K" }, "geometry": { "type": "Point", "coordinates": [ -155.28023, 19.40527, 0.0 ] } },
{ "type": "Feature", "properties": { "Name": "Fire Detection Centroid ", "Description": "<b>Latitude: <\/b> 19.40473<br\/>  <b>Longitude: <\/b> -155.28699<br\/>  <b>Detection Time: <\/b> 2022-07-08 00:28 UTC<br\/>  <b>Sensor: <\/b> NOAA-20 VIIRS<br\/> <b>Confidence: <\/b> High<br\/>  <b>Day\/Night: <\/b> Day<br\/> <b>Scan: <\/b> 0.7 km<br\/> <b>Track: <\/b> 0.75 km<br\/> <b>FRP: <\/b> 27.45 MW<br\/> <b>Brightness: <\/b> 367 K" }, "geometry": { "type": "Point", "coordinates": [ -155.28699, 19.40473, 0.0 ] } }
]
}
