{
"type": "FeatureCollection",
"crs": { "type": "name", "properties": { "name": "urn:ogc:def:crs:OGC:1.3:CRS84" } },
"features": [
{ "type": "Feature", "properties": { "Name": "Fire Detection Centroid ", "Description": "<b>Latitude: <\/b> 43.57611<br\/>  <b>Longitude: <\/b> -70.68153<br\/>  <b>Detection Time: <\/b> 2023-10-15 17:30 UTC<br\/>  <b>Sensor: <\/b> NOAA-20 VIIRS<br\/> <b>Confidence: <\/b> Nominal<br\/>  <b>Day\/Night: <\/b> Day<br\/> <b>Scan: <\/b> 0.4 km<br\/> <b>Track: <\/b> 0.4 km<br\/> <b>FRP: <\/b> 2.27 MW<br\/> <b>Brightness: <\/b> 340.92 K" }, "geometry": { "type": "Point", "coordinates": [ -70.68153, 43.57611, 0.0 ] } },
{ "type": "Feature", "properties": { "Name": "Fire Detection Centroid ", "Description": "<b>Latitude: <\/b> 18.366<br\/>  <b>Longitude: <\/b> -71.40944<br\/>  <b>Detection Time: <\/b> 2023-10-15 17:24 UTC<br\/>  <b>Sensor: <\/b> NOAA-20 VIIRS<br\/> <b>Confidence: <\/b> Nominal<br\/>  <b>Day\/Night: <\/b> Day<br\/> <b>Scan: <\/b> 0.3 km<br\/> <b>Track: <\/b> 0.6 km<br\/> <b>FRP: <\/b> 1.06 MW<br\/> <b>Brightness: <\/b> 334.48 K" }, "geometry": { "type": "Point", "coordinates": [ -71.40944, 18.366, 0.0 ] } },
{ "type": "Feature", "properties": { "Name": "Fire Detection Centroid ", "Description": "<b>Latitude: <\/b> 19.00622<br\/>  <b>Longitude: <\/b> -71.5049<br\/>  <b>Detection Time: <\/b> 2023-10-15 17:24 UTC<br\/>  <b>Sensor: <\/b> NOAA-20 VIIRS<br\/> <b>Confidence: <\/b> Nominal<br\/>  <b>Day\/Night: <\/b> Day<br\/> <b>Scan: <\/b> 0.3 km<br\/> <b>Track: <\/b> 0.6 km<br\/> <b>FRP: <\/b> 1.65 MW<br\/> <b>Brightness: <\/b> 331.44 K" }, "geometry": { "type": "Point", "coordinates": [ -71.5049, 19.00622, 0.0 ] } },
{ "type": "Feature", "properties": { "Name": "Fire Detection Centroid ", "Description": "<b>Latitude: <\/b> 19.26812<br\/>  <b>Longitude: <\/b> -69.90356<br\/>  <b>Detection Time: <\/b> 2023-10-15 17:24 UTC<br\/>  <b>Sensor: <\/b> NOAA-20 VIIRS<br\/> <b>Confidence: <\/b> Nominal<br\/>  <b>Day\/Night: <\/b> Day<br\/> <b>Scan: <\/b> 0.5 km<br\/> <b>Track: <\/b> 0.5 km<br\/> <b>FRP: <\/b> 3.82 MW<br\/> <b>Brightness: <\/b> 340.92 K" }, "geometry": { "type": "Point", "coordinates": [ -69.90356, 19.26812, 0.0 ] } },
{ "type": "Feature", "properties": { "Name": "Fire Detection Centroid ", "Description": "<b>Latitude: <\/b> 19.12926<br\/>  <b>Longitude: <\/b> -69.79224<br\/>  <b>Detection Time: <\/b> 2023-10-15 17:24 UTC<br\/>  <b>Sensor: <\/b> NOAA-20 VIIRS<br\/> <b>Confidence: <\/b> Nominal<br\/>  <b>Day\/Night: <\/b> Day<br\/> <b>Scan: <\/b> 0.5 km<br\/> <b>Track: <\/b> 0.5 km<br\/> <b>FRP: <\/b> 5.1 MW<br\/> <b>Brightness: <\/b> 332.97 K" }, "geometry": { "type": "Point", "coordinates": [ -69.79224, 19.12926, 0.0 ] } },
{ "type": "Feature", "properties": { "Name": "Fire Detection Centroid ", "Description": "<b>Latitude: <\/b> 18.92799<br\/>  <b>Longitude: <\/b> -70.35374<br\/>  <b>Detection Time: <\/b> 2023-10-15 17:24 UTC<br\/>  <b>Sensor: <\/b> NOAA-20 VIIRS<br\/> <b>Confidence: <\/b> Nominal<br\/>  <b>Day\/Night: <\/b> Day<br\/> <b>Scan: <\/b> 0.6 km<br\/> <b>Track: <\/b> 0.5 km<br\/> <b>FRP: <\/b> 11.87 MW<br\/> <b>Brightness: <\/b> 347.1 K" }, "geometry": { "type": "Point", "coordinates": [ -70.35374, 18.92799, 0.0 ] } },
{ "type": "Feature", "properties": { "Name": "Fire Detection Centroid ", "Description": "<b>Latitude: <\/b> 18.5088<br\/>  <b>Longitude: <\/b> -68.47369<br\/>  <b>Detection Time: <\/b> 2023-10-15 17:23 UTC<br\/>  <b>Sensor: <\/b> NOAA-20 VIIRS<br\/> <b>Confidence: <\/b> Nominal<br\/>  <b>Day\/Night: <\/b> Day<br\/> <b>Scan: <\/b> 0.4 km<br\/> <b>Track: <\/b> 0.5 km<br\/> <b>FRP: <\/b> 4.59 MW<br\/> <b>Brightness: <\/b> 334.19 K" }, "geometry": { "type": "Point", "coordinates": [ -68.47369, 18.5088, 0.0 ] } },
{ "type": "Feature", "properties": { "Name": "Fire Detection Centroid ", "Description": "<b>Latitude: <\/b> 18.38949<br\/>  <b>Longitude: <\/b> -68.57993<br\/>  <b>Detection Time: <\/b> 2023-10-15 17:23 UTC<br\/>  <b>Sensor: <\/b> NOAA-20 VIIRS<br\/> <b>Confidence: <\/b> Nominal<br\/>  <b>Day\/Night: <\/b> Day<br\/> <b>Scan: <\/b> 0.4 km<br\/> <b>Track: <\/b> 0.5 km<br\/> <b>FRP: <\/b> 2.69 MW<br\/> <b>Brightness: <\/b> 331.8 K" }, "geometry": { "type": "Point", "coordinates": [ -68.57993, 18.38949, 0.0 ] } }
]
}
