{
"type": "FeatureCollection",
"crs": { "type": "name", "properties": { "name": "urn:ogc:def:crs:OGC:1.3:CRS84" } },
"features": [
{ "type": "Feature", "properties": { "Name": "Fire Detection Centroid ", "Description": "<b>Latitude: <\/b> 19.20033<br\/>  <b>Longitude: <\/b> -70.2048<br\/>  <b>Detection Time: <\/b> 2023-10-21 05:59 UTC<br\/>  <b>Sensor: <\/b> NOAA-20 VIIRS<br\/> <b>Confidence: <\/b> Nominal<br\/>  <b>Day\/Night: <\/b> Night<br\/> <b>Scan: <\/b> 0.53 km<br\/> <b>Track: <\/b> 0.42 km<br\/> <b>FRP: <\/b> 0.48 MW<br\/> <b>Brightness: <\/b> 307.04 K" }, "geometry": { "type": "Point", "coordinates": [ -70.2048, 19.20033, 0.0 ] } },
{ "type": "Feature", "properties": { "Name": "Fire Detection Centroid ", "Description": "<b>Latitude: <\/b> 19.07234<br\/>  <b>Longitude: <\/b> -69.65598<br\/>  <b>Detection Time: <\/b> 2023-10-21 05:59 UTC<br\/>  <b>Sensor: <\/b> NOAA-20 VIIRS<br\/> <b>Confidence: <\/b> Nominal<br\/>  <b>Day\/Night: <\/b> Night<br\/> <b>Scan: <\/b> 0.49 km<br\/> <b>Track: <\/b> 0.41 km<br\/> <b>FRP: <\/b> 2.13 MW<br\/> <b>Brightness: <\/b> 317.63 K" }, "geometry": { "type": "Point", "coordinates": [ -69.65598, 19.07234, 0.0 ] } },
{ "type": "Feature", "properties": { "Name": "Fire Detection Centroid ", "Description": "<b>Latitude: <\/b> 18.93002<br\/>  <b>Longitude: <\/b> -70.35628<br\/>  <b>Detection Time: <\/b> 2023-10-21 05:59 UTC<br\/>  <b>Sensor: <\/b> NOAA-20 VIIRS<br\/> <b>Confidence: <\/b> Nominal<br\/>  <b>Day\/Night: <\/b> Night<br\/> <b>Scan: <\/b> 0.54 km<br\/> <b>Track: <\/b> 0.42 km<br\/> <b>FRP: <\/b> 8.21 MW<br\/> <b>Brightness: <\/b> 331.25 K" }, "geometry": { "type": "Point", "coordinates": [ -70.35628, 18.93002, 0.0 ] } },
{ "type": "Feature", "properties": { "Name": "Fire Detection Centroid ", "Description": "<b>Latitude: <\/b> 18.92935<br\/>  <b>Longitude: <\/b> -70.35112<br\/>  <b>Detection Time: <\/b> 2023-10-21 05:59 UTC<br\/>  <b>Sensor: <\/b> NOAA-20 VIIRS<br\/> <b>Confidence: <\/b> Nominal<br\/>  <b>Day\/Night: <\/b> Night<br\/> <b>Scan: <\/b> 0.54 km<br\/> <b>Track: <\/b> 0.42 km<br\/> <b>FRP: <\/b> 8.21 MW<br\/> <b>Brightness: <\/b> 314.07 K" }, "geometry": { "type": "Point", "coordinates": [ -70.35112, 18.92935, 0.0 ] } },
{ "type": "Feature", "properties": { "Name": "Fire Detection Centroid ", "Description": "<b>Latitude: <\/b> 18.92612<br\/>  <b>Longitude: <\/b> -70.35651<br\/>  <b>Detection Time: <\/b> 2023-10-21 05:59 UTC<br\/>  <b>Sensor: <\/b> NOAA-20 VIIRS<br\/> <b>Confidence: <\/b> Nominal<br\/>  <b>Day\/Night: <\/b> Night<br\/> <b>Scan: <\/b> 0.54 km<br\/> <b>Track: <\/b> 0.42 km<br\/> <b>FRP: <\/b> 8.21 MW<br\/> <b>Brightness: <\/b> 313.43 K" }, "geometry": { "type": "Point", "coordinates": [ -70.35651, 18.92612, 0.0 ] } },
{ "type": "Feature", "properties": { "Name": "Fire Detection Centroid ", "Description": "<b>Latitude: <\/b> 18.17263<br\/>  <b>Longitude: <\/b> -77.06746<br\/>  <b>Detection Time: <\/b> 2023-10-21 05:59 UTC<br\/>  <b>Sensor: <\/b> NOAA-20 VIIRS<br\/> <b>Confidence: <\/b> Nominal<br\/>  <b>Day\/Night: <\/b> Night<br\/> <b>Scan: <\/b> 0.47 km<br\/> <b>Track: <\/b> 0.64 km<br\/> <b>FRP: <\/b> 0.75 MW<br\/> <b>Brightness: <\/b> 300.7 K" }, "geometry": { "type": "Point", "coordinates": [ -77.06746, 18.17263, 0.0 ] } },
{ "type": "Feature", "properties": { "Name": "Fire Detection Centroid ", "Description": "<b>Latitude: <\/b> 19.20249<br\/>  <b>Longitude: <\/b> -70.20305<br\/>  <b>Detection Time: <\/b> 2023-10-21 05:59 UTC<br\/>  <b>Sensor: <\/b> NOAA-20 VIIRS<br\/> <b>Confidence: <\/b> Nominal<br\/>  <b>Day\/Night: <\/b> Night<br\/> <b>Scan: <\/b> 0.53 km<br\/> <b>Track: <\/b> 0.42 km<br\/> <b>FRP: <\/b> 0.98 MW<br\/> <b>Brightness: <\/b> 307.19 K" }, "geometry": { "type": "Point", "coordinates": [ -70.20305, 19.20249, 0.0 ] } }
]
}
