{
"type": "FeatureCollection",
"crs": { "type": "name", "properties": { "name": "urn:ogc:def:crs:OGC:1.3:CRS84" } },
"features": [
{ "type": "Feature", "properties": { "Name": "Fire Detection Centroid ", "Description": "<b>Latitude: <\/b> 40.15303<br\/>  <b>Longitude: <\/b> -74.76919<br\/>  <b>Detection Time: <\/b> 2023-02-06 06:13 UTC<br\/>  <b>Sensor: <\/b> NOAA-20 VIIRS<br\/> <b>Confidence: <\/b> Nominal<br\/>  <b>Day\/Night: <\/b> Night<br\/> <b>Scan: <\/b> 0.6 km<br\/> <b>Track: <\/b> 0.5 km<br\/> <b>FRP: <\/b> 1.29 MW<br\/> <b>Brightness: <\/b> 306.51 K" }, "geometry": { "type": "Point", "coordinates": [ -74.76919, 40.15303, 0.0 ] } },
{ "type": "Feature", "properties": { "Name": "Fire Detection Centroid ", "Description": "<b>Latitude: <\/b> 39.59056<br\/>  <b>Longitude: <\/b> -75.63422<br\/>  <b>Detection Time: <\/b> 2023-02-06 06:13 UTC<br\/>  <b>Sensor: <\/b> NOAA-20 VIIRS<br\/> <b>Confidence: <\/b> Nominal<br\/>  <b>Day\/Night: <\/b> Night<br\/> <b>Scan: <\/b> 0.3 km<br\/> <b>Track: <\/b> 0.6 km<br\/> <b>FRP: <\/b> 1.18 MW<br\/> <b>Brightness: <\/b> 296.92 K" }, "geometry": { "type": "Point", "coordinates": [ -75.63422, 39.59056, 0.0 ] } }
]
}
