{
"type": "FeatureCollection",
"crs": { "type": "name", "properties": { "name": "urn:ogc:def:crs:OGC:1.3:CRS84" } },
"features": [
{ "type": "Feature", "properties": { "Name": "Fire Detection Centroid ", "Description": "<b>Latitude: <\/b> 47.57076<br\/>  <b>Longitude: <\/b> -122.36925<br\/>  <b>Detection Time: <\/b> 2024-04-22 11:21 UTC<br\/>  <b>Sensor: <\/b> NOAA-20 VIIRS<br\/> <b>Confidence: <\/b> Nominal<br\/>  <b>Day\/Night: <\/b> Night<br\/> <b>Scan: <\/b> 0.53 km<br\/> <b>Track: <\/b> 0.67 km<br\/> <b>FRP: <\/b> 0.73 MW<br\/> <b>Brightness: <\/b> 301.5 K" }, "geometry": { "type": "Point", "coordinates": [ -122.36925, 47.57076, 0.0 ] } }
]
}
