{
"type": "FeatureCollection",
"crs": { "type": "name", "properties": { "name": "urn:ogc:def:crs:OGC:1.3:CRS84" } },
"features": [
{ "type": "Feature", "properties": { "Name": "Fire Detection Centroid ", "Description": "<b>Latitude: <\/b> 19.77018<br\/>  <b>Longitude: <\/b> -71.61544<br\/>  <b>Detection Time: <\/b> 2024-05-26 05:48 UTC<br\/>  <b>Sensor: <\/b> NOAA-20 VIIRS<br\/> <b>Confidence: <\/b> Nominal<br\/>  <b>Day\/Night: <\/b> Night<br\/> <b>Scan: <\/b> 0.33 km<br\/> <b>Track: <\/b> 0.56 km<br\/> <b>FRP: <\/b> 0.48 MW<br\/> <b>Brightness: <\/b> 308.97 K" }, "geometry": { "type": "Point", "coordinates": [ -71.61544, 19.77018, 0.0 ] } },
{ "type": "Feature", "properties": { "Name": "Fire Detection Centroid ", "Description": "<b>Latitude: <\/b> 44.4059<br\/>  <b>Longitude: <\/b> -64.50491<br\/>  <b>Detection Time: <\/b> 2024-05-26 05:42 UTC<br\/>  <b>Sensor: <\/b> NOAA-20 VIIRS<br\/> <b>Confidence: <\/b> Nominal<br\/>  <b>Day\/Night: <\/b> Night<br\/> <b>Scan: <\/b> 0.49 km<br\/> <b>Track: <\/b> 0.48 km<br\/> <b>FRP: <\/b> 2.29 MW<br\/> <b>Brightness: <\/b> 317.14 K" }, "geometry": { "type": "Point", "coordinates": [ -64.50491, 44.4059, 0.0 ] } },
{ "type": "Feature", "properties": { "Name": "Fire Detection Centroid ", "Description": "<b>Latitude: <\/b> 45.27885<br\/>  <b>Longitude: <\/b> -66.01083<br\/>  <b>Detection Time: <\/b> 2024-05-26 05:40 UTC<br\/>  <b>Sensor: <\/b> NOAA-20 VIIRS<br\/> <b>Confidence: <\/b> Nominal<br\/>  <b>Day\/Night: <\/b> Night<br\/> <b>Scan: <\/b> 0.59 km<br\/> <b>Track: <\/b> 0.53 km<br\/> <b>FRP: <\/b> 1.71 MW<br\/> <b>Brightness: <\/b> 297.02 K" }, "geometry": { "type": "Point", "coordinates": [ -66.01083, 45.27885, 0.0 ] } }
]
}
