{
"type": "FeatureCollection",
"crs": { "type": "name", "properties": { "name": "urn:ogc:def:crs:OGC:1.3:CRS84" } },
"features": [
{ "type": "Feature", "properties": { "Name": "Fire Detection Centroid ", "Description": "<b>Latitude: <\/b> 45.77599<br\/>  <b>Longitude: <\/b> -73.21295<br\/>  <b>Detection Time: <\/b> 2024-03-09 16:54 UTC<br\/>  <b>Sensor: <\/b> NOAA-20 VIIRS<br\/> <b>Confidence: <\/b> Nominal<br\/>  <b>Day\/Night: <\/b> Day<br\/> <b>Scan: <\/b> 0.3 km<br\/> <b>Track: <\/b> 0.5 km<br\/> <b>FRP: <\/b> 3.03 MW<br\/> <b>Brightness: <\/b> 327.85 K" }, "geometry": { "type": "Point", "coordinates": [ -73.21295, 45.77599, 0.0 ] } }
]
}
