{
"type": "FeatureCollection",
"crs": { "type": "name", "properties": { "name": "urn:ogc:def:crs:OGC:1.3:CRS84" } },
"features": [
{ "type": "Feature", "properties": { "Name": "Fire Detection Centroid ", "Description": "<b>Latitude: <\/b> 46.71861<br\/>  <b>Longitude: <\/b> -64.35232<br\/>  <b>Detection Time: <\/b> 2022-09-09 16:09 UTC<br\/>  <b>Sensor: <\/b> NOAA-20 VIIRS<br\/> <b>Confidence: <\/b> Nominal<br\/>  <b>Day\/Night: <\/b> Day<br\/> <b>Scan: <\/b> 0.4 km<br\/> <b>Track: <\/b> 0.6 km<br\/> <b>FRP: <\/b> 2.57 MW<br\/> <b>Brightness: <\/b> 325.13 K" }, "geometry": { "type": "Point", "coordinates": [ -64.35232, 46.71861, 0.0 ] } }
]
}
