{
"type": "FeatureCollection",
"crs": { "type": "name", "properties": { "name": "urn:ogc:def:crs:OGC:1.3:CRS84" } },
"features": [
{ "type": "Feature", "properties": { "Name": "Fire Detection Centroid ", "Description": "<b>Latitude: <\/b> 38.02706<br\/>  <b>Longitude: <\/b> -122.16426<br\/>  <b>Detection Time: <\/b> 2024-04-28 11:12 UTC<br\/>  <b>Sensor: <\/b> NOAA-20 VIIRS<br\/> <b>Confidence: <\/b> Nominal<br\/>  <b>Day\/Night: <\/b> Night<br\/> <b>Scan: <\/b> 0.8 km<br\/> <b>Track: <\/b> 0.8 km<br\/> <b>FRP: <\/b> 1.05 MW<br\/> <b>Brightness: <\/b> 295.1 K" }, "geometry": { "type": "Point", "coordinates": [ -122.16426, 38.02706, 0.0 ] } },
{ "type": "Feature", "properties": { "Name": "Fire Detection Centroid ", "Description": "<b>Latitude: <\/b> 38.07285<br\/>  <b>Longitude: <\/b> -122.14076<br\/>  <b>Detection Time: <\/b> 2024-04-28 11:10 UTC<br\/>  <b>Sensor: <\/b> NOAA-20 VIIRS<br\/> <b>Confidence: <\/b> Nominal<br\/>  <b>Day\/Night: <\/b> Night<br\/> <b>Scan: <\/b> 0.78 km<br\/> <b>Track: <\/b> 0.78 km<br\/> <b>FRP: <\/b> 1.09 MW<br\/> <b>Brightness: <\/b> 295.1 K" }, "geometry": { "type": "Point", "coordinates": [ -122.14076, 38.07285, 0.0 ] } }
]
}
