{
"type": "FeatureCollection",
"crs": { "type": "name", "properties": { "name": "urn:ogc:def:crs:OGC:1.3:CRS84" } },
"features": [
{ "type": "Feature", "properties": { "Name": "Fire Detection Centroid ", "Description": "<b>Latitude: <\/b> 19.42204<br\/>  <b>Longitude: <\/b> -155.26503<br\/>  <b>Detection Time: <\/b> 2023-09-13 00:28 UTC<br\/>  <b>Sensor: <\/b> NOAA-20 VIIRS<br\/> <b>Confidence: <\/b> Nominal<br\/>  <b>Day\/Night: <\/b> Day<br\/> <b>Scan: <\/b> 0.71 km<br\/> <b>Track: <\/b> 0.75 km<br\/> <b>FRP: <\/b> 23.57 MW<br\/> <b>Brightness: <\/b> 331.56 K" }, "geometry": { "type": "Point", "coordinates": [ -155.26503, 19.42204, 0.0 ] } },
{ "type": "Feature", "properties": { "Name": "Fire Detection Centroid ", "Description": "<b>Latitude: <\/b> 19.40865<br\/>  <b>Longitude: <\/b> -155.25755<br\/>  <b>Detection Time: <\/b> 2023-09-13 00:28 UTC<br\/>  <b>Sensor: <\/b> NOAA-20 VIIRS<br\/> <b>Confidence: <\/b> Nominal<br\/>  <b>Day\/Night: <\/b> Day<br\/> <b>Scan: <\/b> 0.71 km<br\/> <b>Track: <\/b> 0.75 km<br\/> <b>FRP: <\/b> 30.57 MW<br\/> <b>Brightness: <\/b> 354.79 K" }, "geometry": { "type": "Point", "coordinates": [ -155.25755, 19.40865, 0.0 ] } },
{ "type": "Feature", "properties": { "Name": "Fire Detection Centroid ", "Description": "<b>Latitude: <\/b> 19.40815<br\/>  <b>Longitude: <\/b> -155.2639<br\/>  <b>Detection Time: <\/b> 2023-09-13 00:28 UTC<br\/>  <b>Sensor: <\/b> NOAA-20 VIIRS<br\/> <b>Confidence: <\/b> Low<br\/>  <b>Day\/Night: <\/b> Day<br\/> <b>Scan: <\/b> 0.71 km<br\/> <b>Track: <\/b> 0.75 km<br\/> <b>FRP: <\/b> 30.57 MW<br\/> <b>Brightness: <\/b> 356.28 K" }, "geometry": { "type": "Point", "coordinates": [ -155.2639, 19.40815, 0.0 ] } },
{ "type": "Feature", "properties": { "Name": "Fire Detection Centroid ", "Description": "<b>Latitude: <\/b> 19.40763<br\/>  <b>Longitude: <\/b> -155.27055<br\/>  <b>Detection Time: <\/b> 2023-09-13 00:28 UTC<br\/>  <b>Sensor: <\/b> NOAA-20 VIIRS<br\/> <b>Confidence: <\/b> Low<br\/>  <b>Day\/Night: <\/b> Day<br\/> <b>Scan: <\/b> 0.71 km<br\/> <b>Track: <\/b> 0.75 km<br\/> <b>FRP: <\/b> 33.23 MW<br\/> <b>Brightness: <\/b> 356.2 K" }, "geometry": { "type": "Point", "coordinates": [ -155.27055, 19.40763, 0.0 ] } },
{ "type": "Feature", "properties": { "Name": "Fire Detection Centroid ", "Description": "<b>Latitude: <\/b> 19.41458<br\/>  <b>Longitude: <\/b> -155.27101<br\/>  <b>Detection Time: <\/b> 2023-09-13 00:28 UTC<br\/>  <b>Sensor: <\/b> NOAA-20 VIIRS<br\/> <b>Confidence: <\/b> Nominal<br\/>  <b>Day\/Night: <\/b> Day<br\/> <b>Scan: <\/b> 0.71 km<br\/> <b>Track: <\/b> 0.75 km<br\/> <b>FRP: <\/b> 18.12 MW<br\/> <b>Brightness: <\/b> 346.06 K" }, "geometry": { "type": "Point", "coordinates": [ -155.27101, 19.41458, 0.0 ] } },
{ "type": "Feature", "properties": { "Name": "Fire Detection Centroid ", "Description": "<b>Latitude: <\/b> 19.41403<br\/>  <b>Longitude: <\/b> -155.27798<br\/>  <b>Detection Time: <\/b> 2023-09-13 00:28 UTC<br\/>  <b>Sensor: <\/b> NOAA-20 VIIRS<br\/> <b>Confidence: <\/b> Nominal<br\/>  <b>Day\/Night: <\/b> Day<br\/> <b>Scan: <\/b> 0.71 km<br\/> <b>Track: <\/b> 0.75 km<br\/> <b>FRP: <\/b> 18.12 MW<br\/> <b>Brightness: <\/b> 350.02 K" }, "geometry": { "type": "Point", "coordinates": [ -155.27798, 19.41403, 0.0 ] } }
]
}
