{
"type": "FeatureCollection",
"crs": { "type": "name", "properties": { "name": "urn:ogc:def:crs:OGC:1.3:CRS84" } },
"features": [
{ "type": "Feature", "properties": { "Name": "Fire Detection Centroid ", "Description": "<b>Latitude: <\/b> 21.40047<br\/>  <b>Longitude: <\/b> -158.0679<br\/>  <b>Detection Time: <\/b> 2024-02-17 23:26 UTC<br\/>  <b>Sensor: <\/b> NOAA-20 VIIRS<br\/> <b>Confidence: <\/b> Nominal<br\/>  <b>Day\/Night: <\/b> Day<br\/> <b>Scan: <\/b> 0.5 km<br\/> <b>Track: <\/b> 0.4 km<br\/> <b>FRP: <\/b> 2.98 MW<br\/> <b>Brightness: <\/b> 340.3 K" }, "geometry": { "type": "Point", "coordinates": [ -158.0679, 21.40047, 0.0 ] } },
{ "type": "Feature", "properties": { "Name": "Fire Detection Centroid ", "Description": "<b>Latitude: <\/b> 21.37468<br\/>  <b>Longitude: <\/b> -158.06287<br\/>  <b>Detection Time: <\/b> 2024-02-17 23:26 UTC<br\/>  <b>Sensor: <\/b> NOAA-20 VIIRS<br\/> <b>Confidence: <\/b> Nominal<br\/>  <b>Day\/Night: <\/b> Day<br\/> <b>Scan: <\/b> 0.52 km<br\/> <b>Track: <\/b> 0.42 km<br\/> <b>FRP: <\/b> 2.99 MW<br\/> <b>Brightness: <\/b> 340.3 K" }, "geometry": { "type": "Point", "coordinates": [ -158.06287, 21.37468, 0.0 ] } }
]
}
