{
"type": "FeatureCollection",
"crs": { "type": "name", "properties": { "name": "urn:ogc:def:crs:OGC:1.3:CRS84" } },
"features": [
{ "type": "Feature", "properties": { "Name": "Fire Detection Centroid ", "Description": "<b>Latitude: <\/b> 33.0164<br\/>  <b>Longitude: <\/b> -79.88341<br\/>  <b>Detection Time: <\/b> 2022-12-31 06:09 UTC<br\/>  <b>Sensor: <\/b> NOAA-20 VIIRS<br\/> <b>Confidence: <\/b> Nominal<br\/>  <b>Day\/Night: <\/b> Night<br\/> <b>Scan: <\/b> 0.6 km<br\/> <b>Track: <\/b> 0.7 km<br\/> <b>FRP: <\/b> 1.66 MW<br\/> <b>Brightness: <\/b> 298.7 K" }, "geometry": { "type": "Point", "coordinates": [ -79.88341, 33.0164, 0.0 ] } },
{ "type": "Feature", "properties": { "Name": "Fire Detection Centroid ", "Description": "<b>Latitude: <\/b> 33.01666<br\/>  <b>Longitude: <\/b> -79.89021<br\/>  <b>Detection Time: <\/b> 2022-12-31 06:09 UTC<br\/>  <b>Sensor: <\/b> NOAA-20 VIIRS<br\/> <b>Confidence: <\/b> Nominal<br\/>  <b>Day\/Night: <\/b> Night<br\/> <b>Scan: <\/b> 0.6 km<br\/> <b>Track: <\/b> 0.7 km<br\/> <b>FRP: <\/b> 1.66 MW<br\/> <b>Brightness: <\/b> 311.61 K" }, "geometry": { "type": "Point", "coordinates": [ -79.89021, 33.01666, 0.0 ] } },
{ "type": "Feature", "properties": { "Name": "Fire Detection Centroid ", "Description": "<b>Latitude: <\/b> 37.8245<br\/>  <b>Longitude: <\/b> -77.76809<br\/>  <b>Detection Time: <\/b> 2022-12-31 06:07 UTC<br\/>  <b>Sensor: <\/b> NOAA-20 VIIRS<br\/> <b>Confidence: <\/b> Nominal<br\/>  <b>Day\/Night: <\/b> Night<br\/> <b>Scan: <\/b> 0.5 km<br\/> <b>Track: <\/b> 0.7 km<br\/> <b>FRP: <\/b> 0.81 MW<br\/> <b>Brightness: <\/b> 296.48 K" }, "geometry": { "type": "Point", "coordinates": [ -77.76809, 37.8245, 0.0 ] } },
{ "type": "Feature", "properties": { "Name": "Fire Detection Centroid ", "Description": "<b>Latitude: <\/b> 37.42392<br\/>  <b>Longitude: <\/b> -77.42855<br\/>  <b>Detection Time: <\/b> 2022-12-31 06:07 UTC<br\/>  <b>Sensor: <\/b> NOAA-20 VIIRS<br\/> <b>Confidence: <\/b> Nominal<br\/>  <b>Day\/Night: <\/b> Night<br\/> <b>Scan: <\/b> 0.5 km<br\/> <b>Track: <\/b> 0.6 km<br\/> <b>FRP: <\/b> 1.42 MW<br\/> <b>Brightness: <\/b> 296.02 K" }, "geometry": { "type": "Point", "coordinates": [ -77.42855, 37.42392, 0.0 ] } },
{ "type": "Feature", "properties": { "Name": "Fire Detection Centroid ", "Description": "<b>Latitude: <\/b> 45.28112<br\/>  <b>Longitude: <\/b> -66.01951<br\/>  <b>Detection Time: <\/b> 2022-12-31 06:05 UTC<br\/>  <b>Sensor: <\/b> NOAA-20 VIIRS<br\/> <b>Confidence: <\/b> Nominal<br\/>  <b>Day\/Night: <\/b> Night<br\/> <b>Scan: <\/b> 0.5 km<br\/> <b>Track: <\/b> 0.4 km<br\/> <b>FRP: <\/b> 1.93 MW<br\/> <b>Brightness: <\/b> 302.01 K" }, "geometry": { "type": "Point", "coordinates": [ -66.01951, 45.28112, 0.0 ] } }
]
}
