{
"type": "FeatureCollection",
"crs": { "type": "name", "properties": { "name": "urn:ogc:def:crs:OGC:1.3:CRS84" } },
"features": [
{ "type": "Feature", "properties": { "Name": "Fire Detection Centroid ", "Description": "<b>Latitude: <\/b> 18.82128<br\/>  <b>Longitude: <\/b> -68.6064<br\/>  <b>Detection Time: <\/b> 2024-02-01 05:29 UTC<br\/>  <b>Sensor: <\/b> NOAA-20 VIIRS<br\/> <b>Confidence: <\/b> Nominal<br\/>  <b>Day\/Night: <\/b> Night<br\/> <b>Scan: <\/b> 0.4 km<br\/> <b>Track: <\/b> 0.6 km<br\/> <b>FRP: <\/b> 0.72 MW<br\/> <b>Brightness: <\/b> 302.73 K" }, "geometry": { "type": "Point", "coordinates": [ -68.6064, 18.82128, 0.0 ] } },
{ "type": "Feature", "properties": { "Name": "Fire Detection Centroid ", "Description": "<b>Latitude: <\/b> 19.12312<br\/>  <b>Longitude: <\/b> -72.1869<br\/>  <b>Detection Time: <\/b> 2024-02-01 05:29 UTC<br\/>  <b>Sensor: <\/b> NOAA-20 VIIRS<br\/> <b>Confidence: <\/b> Nominal<br\/>  <b>Day\/Night: <\/b> Night<br\/> <b>Scan: <\/b> 0.8 km<br\/> <b>Track: <\/b> 0.8 km<br\/> <b>FRP: <\/b> 4.59 MW<br\/> <b>Brightness: <\/b> 311.36 K" }, "geometry": { "type": "Point", "coordinates": [ -72.1869, 19.12312, 0.0 ] } },
{ "type": "Feature", "properties": { "Name": "Fire Detection Centroid ", "Description": "<b>Latitude: <\/b> 18.92015<br\/>  <b>Longitude: <\/b> -72.21154<br\/>  <b>Detection Time: <\/b> 2024-02-01 05:29 UTC<br\/>  <b>Sensor: <\/b> NOAA-20 VIIRS<br\/> <b>Confidence: <\/b> Nominal<br\/>  <b>Day\/Night: <\/b> Night<br\/> <b>Scan: <\/b> 0.8 km<br\/> <b>Track: <\/b> 0.8 km<br\/> <b>FRP: <\/b> 4.47 MW<br\/> <b>Brightness: <\/b> 306.65 K" }, "geometry": { "type": "Point", "coordinates": [ -72.21154, 18.92015, 0.0 ] } }
]
}
