{
"type": "FeatureCollection",
"crs": { "type": "name", "properties": { "name": "urn:ogc:def:crs:OGC:1.3:CRS84" } },
"features": [
{ "type": "Feature", "properties": { "Name": "Fire Detection Centroid ", "Description": "<b>Latitude: <\/b> 45.28495<br\/>  <b>Longitude: <\/b> -66.01276<br\/>  <b>Detection Time: <\/b> 2022-09-17 05:34 UTC<br\/>  <b>Sensor: <\/b> NOAA-20 VIIRS<br\/> <b>Confidence: <\/b> Nominal<br\/>  <b>Day\/Night: <\/b> Night<br\/> <b>Scan: <\/b> 0.4 km<br\/> <b>Track: <\/b> 0.6 km<br\/> <b>FRP: <\/b> 1.57 MW<br\/> <b>Brightness: <\/b> 313.02 K" }, "geometry": { "type": "Point", "coordinates": [ -66.01276, 45.28495, 0.0 ] } },
{ "type": "Feature", "properties": { "Name": "Fire Detection Centroid ", "Description": "<b>Latitude: <\/b> 45.28841<br\/>  <b>Longitude: <\/b> -66.01102<br\/>  <b>Detection Time: <\/b> 2022-09-17 05:34 UTC<br\/>  <b>Sensor: <\/b> NOAA-20 VIIRS<br\/> <b>Confidence: <\/b> Nominal<br\/>  <b>Day\/Night: <\/b> Night<br\/> <b>Scan: <\/b> 0.4 km<br\/> <b>Track: <\/b> 0.6 km<br\/> <b>FRP: <\/b> 0.61 MW<br\/> <b>Brightness: <\/b> 306.11 K" }, "geometry": { "type": "Point", "coordinates": [ -66.01102, 45.28841, 0.0 ] } }
]
}
