{
"type": "FeatureCollection",
"crs": { "type": "name", "properties": { "name": "urn:ogc:def:crs:OGC:1.3:CRS84" } },
"features": [
{ "type": "Feature", "properties": { "Name": "Fire Detection Centroid ", "Description": "<b>Latitude: <\/b> 20.83408<br\/>  <b>Longitude: <\/b> -156.47894<br\/>  <b>Detection Time: <\/b> 2023-09-07 22:42 UTC<br\/>  <b>Sensor: <\/b> NOAA-20 VIIRS<br\/> <b>Confidence: <\/b> Nominal<br\/>  <b>Day\/Night: <\/b> Day<br\/> <b>Scan: <\/b> 0.69 km<br\/> <b>Track: <\/b> 0.74 km<br\/> <b>FRP: <\/b> 11.28 MW<br\/> <b>Brightness: <\/b> 326.14 K" }, "geometry": { "type": "Point", "coordinates": [ -156.47894, 20.83408, 0.0 ] } },
{ "type": "Feature", "properties": { "Name": "Fire Detection Centroid ", "Description": "<b>Latitude: <\/b> 20.84227<br\/>  <b>Longitude: <\/b> -156.47429<br\/>  <b>Detection Time: <\/b> 2023-09-07 22:42 UTC<br\/>  <b>Sensor: <\/b> NOAA-20 VIIRS<br\/> <b>Confidence: <\/b> Nominal<br\/>  <b>Day\/Night: <\/b> Day<br\/> <b>Scan: <\/b> 0.69 km<br\/> <b>Track: <\/b> 0.74 km<br\/> <b>FRP: <\/b> 4.21 MW<br\/> <b>Brightness: <\/b> 333.07 K" }, "geometry": { "type": "Point", "coordinates": [ -156.47429, 20.84227, 0.0 ] } }
]
}
