{
"type": "FeatureCollection",
"crs": { "type": "name", "properties": { "name": "urn:ogc:def:crs:OGC:1.3:CRS84" } },
"features": [
{ "type": "Feature", "properties": { "Name": "Fire Detection Centroid ", "Description": "<b>Latitude: <\/b> 39.64617<br\/>  <b>Longitude: <\/b> -122.05529<br\/>  <b>Detection Time: <\/b> 2024-03-08 22:14 UTC<br\/>  <b>Sensor: <\/b> NOAA-20 VIIRS<br\/> <b>Confidence: <\/b> Nominal<br\/>  <b>Day\/Night: <\/b> Day<br\/> <b>Scan: <\/b> 0.77 km<br\/> <b>Track: <\/b> 0.77 km<br\/> <b>FRP: <\/b> 3.35 MW<br\/> <b>Brightness: <\/b> 326.15 K" }, "geometry": { "type": "Point", "coordinates": [ -122.05529, 39.64617, 0.0 ] } },
{ "type": "Feature", "properties": { "Name": "Fire Detection Centroid ", "Description": "<b>Latitude: <\/b> 39.1749<br\/>  <b>Longitude: <\/b> -122.29848<br\/>  <b>Detection Time: <\/b> 2024-03-08 22:14 UTC<br\/>  <b>Sensor: <\/b> NOAA-20 VIIRS<br\/> <b>Confidence: <\/b> Nominal<br\/>  <b>Day\/Night: <\/b> Day<br\/> <b>Scan: <\/b> 0.74 km<br\/> <b>Track: <\/b> 0.76 km<br\/> <b>FRP: <\/b> 8.02 MW<br\/> <b>Brightness: <\/b> 325.85 K" }, "geometry": { "type": "Point", "coordinates": [ -122.29848, 39.1749, 0.0 ] } },
{ "type": "Feature", "properties": { "Name": "Fire Detection Centroid ", "Description": "<b>Latitude: <\/b> 38.92445<br\/>  <b>Longitude: <\/b> -122.06953<br\/>  <b>Detection Time: <\/b> 2024-03-08 22:14 UTC<br\/>  <b>Sensor: <\/b> NOAA-20 VIIRS<br\/> <b>Confidence: <\/b> Nominal<br\/>  <b>Day\/Night: <\/b> Day<br\/> <b>Scan: <\/b> 0.76 km<br\/> <b>Track: <\/b> 0.77 km<br\/> <b>FRP: <\/b> 4.07 MW<br\/> <b>Brightness: <\/b> 331.9 K" }, "geometry": { "type": "Point", "coordinates": [ -122.06953, 38.92445, 0.0 ] } },
{ "type": "Feature", "properties": { "Name": "Fire Detection Centroid ", "Description": "<b>Latitude: <\/b> 38.77426<br\/>  <b>Longitude: <\/b> -122.07219<br\/>  <b>Detection Time: <\/b> 2024-03-08 22:14 UTC<br\/>  <b>Sensor: <\/b> NOAA-20 VIIRS<br\/> <b>Confidence: <\/b> Nominal<br\/>  <b>Day\/Night: <\/b> Day<br\/> <b>Scan: <\/b> 0.8 km<br\/> <b>Track: <\/b> 0.8 km<br\/> <b>FRP: <\/b> 4.06 MW<br\/> <b>Brightness: <\/b> 331.9 K" }, "geometry": { "type": "Point", "coordinates": [ -122.07219, 38.77426, 0.0 ] } }
]
}
