{
"type": "FeatureCollection",
"crs": { "type": "name", "properties": { "name": "urn:ogc:def:crs:OGC:1.3:CRS84" } },
"features": [
{ "type": "Feature", "properties": { "Name": "Fire Detection Centroid ", "Description": "<b>Latitude: <\/b> 45.77301<br\/>  <b>Longitude: <\/b> -64.47935<br\/>  <b>Detection Time: <\/b> 2023-04-03 16:47 UTC<br\/>  <b>Sensor: <\/b> NOAA-20 VIIRS<br\/> <b>Confidence: <\/b> Nominal<br\/>  <b>Day\/Night: <\/b> Day<br\/> <b>Scan: <\/b> 0.5 km<br\/> <b>Track: <\/b> 0.4 km<br\/> <b>FRP: <\/b> 2.71 MW<br\/> <b>Brightness: <\/b> 328.92 K" }, "geometry": { "type": "Point", "coordinates": [ -64.47935, 45.77301, 0.0 ] } },
{ "type": "Feature", "properties": { "Name": "Fire Detection Centroid ", "Description": "<b>Latitude: <\/b> 40.93617<br\/>  <b>Longitude: <\/b> -72.79079<br\/>  <b>Detection Time: <\/b> 2023-04-03 16:46 UTC<br\/>  <b>Sensor: <\/b> NOAA-20 VIIRS<br\/> <b>Confidence: <\/b> Nominal<br\/>  <b>Day\/Night: <\/b> Day<br\/> <b>Scan: <\/b> 0.5 km<br\/> <b>Track: <\/b> 0.7 km<br\/> <b>FRP: <\/b> 2.72 MW<br\/> <b>Brightness: <\/b> 328.91 K" }, "geometry": { "type": "Point", "coordinates": [ -72.79079, 40.93617, 0.0 ] } }
]
}
