{
"type": "FeatureCollection",
"crs": { "type": "name", "properties": { "name": "urn:ogc:def:crs:OGC:1.3:CRS84" } },
"features": [
{ "type": "Feature", "properties": { "Name": "Fire Detection Centroid ", "Description": "<b>Latitude: <\/b> 19.40748<br\/>  <b>Longitude: <\/b> -155.27705<br\/>  <b>Detection Time: <\/b> 2022-08-05 23:44 UTC<br\/>  <b>Sensor: <\/b> NOAA-20 VIIRS<br\/> <b>Confidence: <\/b> Nominal<br\/>  <b>Day\/Night: <\/b> Day<br\/> <b>Scan: <\/b> 0.43 km<br\/> <b>Track: <\/b> 0.38 km<br\/> <b>FRP: <\/b> 5.7 MW<br\/> <b>Brightness: <\/b> 337.15 K" }, "geometry": { "type": "Point", "coordinates": [ -155.27705, 19.40748, 0.0 ] } },
{ "type": "Feature", "properties": { "Name": "Fire Detection Centroid ", "Description": "<b>Latitude: <\/b> 19.39938<br\/>  <b>Longitude: <\/b> -155.28419<br\/>  <b>Detection Time: <\/b> 2022-08-05 23:44 UTC<br\/>  <b>Sensor: <\/b> NOAA-20 VIIRS<br\/> <b>Confidence: <\/b> Nominal<br\/>  <b>Day\/Night: <\/b> Day<br\/> <b>Scan: <\/b> 0.43 km<br\/> <b>Track: <\/b> 0.38 km<br\/> <b>FRP: <\/b> 7.34 MW<br\/> <b>Brightness: <\/b> 331.89 K" }, "geometry": { "type": "Point", "coordinates": [ -155.28419, 19.39938, 0.0 ] } },
{ "type": "Feature", "properties": { "Name": "Fire Detection Centroid ", "Description": "<b>Latitude: <\/b> 19.3992<br\/>  <b>Longitude: <\/b> -155.28427<br\/>  <b>Detection Time: <\/b> 2022-08-05 23:44 UTC<br\/>  <b>Sensor: <\/b> NOAA-20 VIIRS<br\/> <b>Confidence: <\/b> Nominal<br\/>  <b>Day\/Night: <\/b> Day<br\/> <b>Scan: <\/b> 0.4 km<br\/> <b>Track: <\/b> 0.4 km<br\/> <b>FRP: <\/b> 7.34 MW<br\/> <b>Brightness: <\/b> 331.89 K" }, "geometry": { "type": "Point", "coordinates": [ -155.28427, 19.3992, 0.0 ] } },
{ "type": "Feature", "properties": { "Name": "Fire Detection Centroid ", "Description": "<b>Latitude: <\/b> 19.40325<br\/>  <b>Longitude: <\/b> -155.28067<br\/>  <b>Detection Time: <\/b> 2022-08-05 23:44 UTC<br\/>  <b>Sensor: <\/b> NOAA-20 VIIRS<br\/> <b>Confidence: <\/b> Nominal<br\/>  <b>Day\/Night: <\/b> Day<br\/> <b>Scan: <\/b> 0.4 km<br\/> <b>Track: <\/b> 0.4 km<br\/> <b>FRP: <\/b> 5.7 MW<br\/> <b>Brightness: <\/b> 335.01 K" }, "geometry": { "type": "Point", "coordinates": [ -155.28067, 19.40325, 0.0 ] } },
{ "type": "Feature", "properties": { "Name": "Fire Detection Centroid ", "Description": "<b>Latitude: <\/b> 19.40343<br\/>  <b>Longitude: <\/b> -155.28062<br\/>  <b>Detection Time: <\/b> 2022-08-05 23:44 UTC<br\/>  <b>Sensor: <\/b> NOAA-20 VIIRS<br\/> <b>Confidence: <\/b> Nominal<br\/>  <b>Day\/Night: <\/b> Day<br\/> <b>Scan: <\/b> 0.43 km<br\/> <b>Track: <\/b> 0.38 km<br\/> <b>FRP: <\/b> 5.7 MW<br\/> <b>Brightness: <\/b> 335.01 K" }, "geometry": { "type": "Point", "coordinates": [ -155.28062, 19.40343, 0.0 ] } },
{ "type": "Feature", "properties": { "Name": "Fire Detection Centroid ", "Description": "<b>Latitude: <\/b> 19.4073<br\/>  <b>Longitude: <\/b> -155.27711<br\/>  <b>Detection Time: <\/b> 2022-08-05 23:44 UTC<br\/>  <b>Sensor: <\/b> NOAA-20 VIIRS<br\/> <b>Confidence: <\/b> Nominal<br\/>  <b>Day\/Night: <\/b> Day<br\/> <b>Scan: <\/b> 0.4 km<br\/> <b>Track: <\/b> 0.4 km<br\/> <b>FRP: <\/b> 5.7 MW<br\/> <b>Brightness: <\/b> 337.15 K" }, "geometry": { "type": "Point", "coordinates": [ -155.27711, 19.4073, 0.0 ] } }
]
}
