{
"type": "FeatureCollection",
"crs": { "type": "name", "properties": { "name": "urn:ogc:def:crs:OGC:1.3:CRS84" } },
"features": [
{ "type": "Feature", "properties": { "Name": "Fire Detection Centroid ", "Description": "<b>Latitude: <\/b> 40.63583<br\/>  <b>Longitude: <\/b> -74.22369<br\/>  <b>Detection Time: <\/b> 2022-10-29 05:48 UTC<br\/>  <b>Sensor: <\/b> NOAA-20 VIIRS<br\/> <b>Confidence: <\/b> Nominal<br\/>  <b>Day\/Night: <\/b> Night<br\/> <b>Scan: <\/b> 0.6 km<br\/> <b>Track: <\/b> 0.7 km<br\/> <b>FRP: <\/b> 1.72 MW<br\/> <b>Brightness: <\/b> 295.02 K" }, "geometry": { "type": "Point", "coordinates": [ -74.22369, 40.63583, 0.0 ] } },
{ "type": "Feature", "properties": { "Name": "Fire Detection Centroid ", "Description": "<b>Latitude: <\/b> 40.63757<br\/>  <b>Longitude: <\/b> -74.22382<br\/>  <b>Detection Time: <\/b> 2022-10-29 05:48 UTC<br\/>  <b>Sensor: <\/b> NOAA-20 VIIRS<br\/> <b>Confidence: <\/b> Nominal<br\/>  <b>Day\/Night: <\/b> Night<br\/> <b>Scan: <\/b> 0.6 km<br\/> <b>Track: <\/b> 0.7 km<br\/> <b>FRP: <\/b> 1.23 MW<br\/> <b>Brightness: <\/b> 296.7 K" }, "geometry": { "type": "Point", "coordinates": [ -74.22382, 40.63757, 0.0 ] } },
{ "type": "Feature", "properties": { "Name": "Fire Detection Centroid ", "Description": "<b>Latitude: <\/b> 40.63583<br\/>  <b>Longitude: <\/b> -74.22369<br\/>  <b>Detection Time: <\/b> 2022-10-29 05:48 UTC<br\/>  <b>Sensor: <\/b> NOAA-20 VIIRS<br\/> <b>Confidence: <\/b> Nominal<br\/>  <b>Day\/Night: <\/b> Night<br\/> <b>Scan: <\/b> 0.6 km<br\/> <b>Track: <\/b> 0.7 km<br\/> <b>FRP: <\/b> 1.72 MW<br\/> <b>Brightness: <\/b> 295.02 K" }, "geometry": { "type": "Point", "coordinates": [ -74.22369, 40.63583, 0.0 ] } },
{ "type": "Feature", "properties": { "Name": "Fire Detection Centroid ", "Description": "<b>Latitude: <\/b> 45.8413<br\/>  <b>Longitude: <\/b> -73.25618<br\/>  <b>Detection Time: <\/b> 2022-10-29 05:46 UTC<br\/>  <b>Sensor: <\/b> NOAA-20 VIIRS<br\/> <b>Confidence: <\/b> Nominal<br\/>  <b>Day\/Night: <\/b> Night<br\/> <b>Scan: <\/b> 0.6 km<br\/> <b>Track: <\/b> 0.7 km<br\/> <b>FRP: <\/b> 1.86 MW<br\/> <b>Brightness: <\/b> 299.66 K" }, "geometry": { "type": "Point", "coordinates": [ -73.25618, 45.8413, 0.0 ] } },
{ "type": "Feature", "properties": { "Name": "Fire Detection Centroid ", "Description": "<b>Latitude: <\/b> 45.84071<br\/>  <b>Longitude: <\/b> -73.25606<br\/>  <b>Detection Time: <\/b> 2022-10-29 05:46 UTC<br\/>  <b>Sensor: <\/b> NOAA-20 VIIRS<br\/> <b>Confidence: <\/b> Nominal<br\/>  <b>Day\/Night: <\/b> Night<br\/> <b>Scan: <\/b> 0.6 km<br\/> <b>Track: <\/b> 0.7 km<br\/> <b>FRP: <\/b> 1.46 MW<br\/> <b>Brightness: <\/b> 298.45 K" }, "geometry": { "type": "Point", "coordinates": [ -73.25606, 45.84071, 0.0 ] } }
]
}
