{
"type": "FeatureCollection",
"crs": { "type": "name", "properties": { "name": "urn:ogc:def:crs:OGC:1.3:CRS84" } },
"features": [
{ "type": "Feature", "properties": { "Name": "Fire Detection Centroid ", "Description": "<b>Latitude: <\/b> 19.6039<br\/>  <b>Longitude: <\/b> -155.5043<br\/>  <b>Detection Time: <\/b> 2023-03-31 11:30 UTC<br\/>  <b>Sensor: <\/b> NOAA-20 VIIRS<br\/> <b>Confidence: <\/b> Nominal<br\/>  <b>Day\/Night: <\/b> Night<br\/> <b>Scan: <\/b> 0.53 km<br\/> <b>Track: <\/b> 0.5 km<br\/> <b>FRP: <\/b> 2.66 MW<br\/> <b>Brightness: <\/b> 297.5 K" }, "geometry": { "type": "Point", "coordinates": [ -155.5043, 19.6039, 0.0 ] } },
{ "type": "Feature", "properties": { "Name": "Fire Detection Centroid ", "Description": "<b>Latitude: <\/b> 19.59924<br\/>  <b>Longitude: <\/b> -155.50439<br\/>  <b>Detection Time: <\/b> 2023-03-31 11:30 UTC<br\/>  <b>Sensor: <\/b> NOAA-20 VIIRS<br\/> <b>Confidence: <\/b> Nominal<br\/>  <b>Day\/Night: <\/b> Night<br\/> <b>Scan: <\/b> 0.53 km<br\/> <b>Track: <\/b> 0.5 km<br\/> <b>FRP: <\/b> 2.75 MW<br\/> <b>Brightness: <\/b> 298.63 K" }, "geometry": { "type": "Point", "coordinates": [ -155.50439, 19.59924, 0.0 ] } }
]
}
