{
"type": "FeatureCollection",
"crs": { "type": "name", "properties": { "name": "urn:ogc:def:crs:OGC:1.3:CRS84" } },
"features": [
{ "type": "Feature", "properties": { "Name": "Fire Detection Centroid ", "Description": "<b>Latitude: <\/b> 40.41265<br\/>  <b>Longitude: <\/b> -79.86372<br\/>  <b>Detection Time: <\/b> 2024-01-31 17:05 UTC<br\/>  <b>Sensor: <\/b> NOAA-20 VIIRS<br\/> <b>Confidence: <\/b> Nominal<br\/>  <b>Day\/Night: <\/b> Day<br\/> <b>Scan: <\/b> 0.7 km<br\/> <b>Track: <\/b> 0.7 km<br\/> <b>FRP: <\/b> 4.93 MW<br\/> <b>Brightness: <\/b> 337.42 K" }, "geometry": { "type": "Point", "coordinates": [ -79.86372, 40.41265, 0.0 ] } }
]
}
