{
"type": "FeatureCollection",
"crs": { "type": "name", "properties": { "name": "urn:ogc:def:crs:OGC:1.3:CRS84" } },
"features": [
{ "type": "Feature", "properties": { "Name": "Fire Detection Centroid ", "Description": "<b>Latitude: <\/b> 43.62295<br\/>  <b>Longitude: <\/b> -105.41003<br\/>  <b>Detection Time: <\/b> 2023-05-06 10:06 UTC<br\/>  <b>Sensor: <\/b> NOAA-20 VIIRS<br\/> <b>Confidence: <\/b> Nominal<br\/>  <b>Day\/Night: <\/b> Night<br\/> <b>Scan: <\/b> 0.6 km<br\/> <b>Track: <\/b> 0.7 km<br\/> <b>FRP: <\/b> 2.25 MW<br\/> <b>Brightness: <\/b> 301.35 K" }, "geometry": { "type": "Point", "coordinates": [ -105.41003, 43.62295, 0.0 ] } },
{ "type": "Feature", "properties": { "Name": "Fire Detection Centroid ", "Description": "<b>Latitude: <\/b> 49.31585<br\/>  <b>Longitude: <\/b> -102.6326<br\/>  <b>Detection Time: <\/b> 2023-05-06 10:05 UTC<br\/>  <b>Sensor: <\/b> NOAA-20 VIIRS<br\/> <b>Confidence: <\/b> Nominal<br\/>  <b>Day\/Night: <\/b> Night<br\/> <b>Scan: <\/b> 0.5 km<br\/> <b>Track: <\/b> 0.6 km<br\/> <b>FRP: <\/b> 2.81 MW<br\/> <b>Brightness: <\/b> 319.23 K" }, "geometry": { "type": "Point", "coordinates": [ -102.6326, 49.31585, 0.0 ] } },
{ "type": "Feature", "properties": { "Name": "Fire Detection Centroid ", "Description": "<b>Latitude: <\/b> 48.06606<br\/>  <b>Longitude: <\/b> -103.39467<br\/>  <b>Detection Time: <\/b> 2023-05-06 10:05 UTC<br\/>  <b>Sensor: <\/b> NOAA-20 VIIRS<br\/> <b>Confidence: <\/b> Nominal<br\/>  <b>Day\/Night: <\/b> Night<br\/> <b>Scan: <\/b> 0.5 km<br\/> <b>Track: <\/b> 0.6 km<br\/> <b>FRP: <\/b> 1.43 MW<br\/> <b>Brightness: <\/b> 305.4 K" }, "geometry": { "type": "Point", "coordinates": [ -103.39467, 48.06606, 0.0 ] } },
{ "type": "Feature", "properties": { "Name": "Fire Detection Centroid ", "Description": "<b>Latitude: <\/b> 47.59052<br\/>  <b>Longitude: <\/b> -103.02299<br\/>  <b>Detection Time: <\/b> 2023-05-06 10:05 UTC<br\/>  <b>Sensor: <\/b> NOAA-20 VIIRS<br\/> <b>Confidence: <\/b> Nominal<br\/>  <b>Day\/Night: <\/b> Night<br\/> <b>Scan: <\/b> 0.5 km<br\/> <b>Track: <\/b> 0.7 km<br\/> <b>FRP: <\/b> 0.69 MW<br\/> <b>Brightness: <\/b> 301.27 K" }, "geometry": { "type": "Point", "coordinates": [ -103.02299, 47.59052, 0.0 ] } },
{ "type": "Feature", "properties": { "Name": "Fire Detection Centroid ", "Description": "<b>Latitude: <\/b> 47.58999<br\/>  <b>Longitude: <\/b> -103.02479<br\/>  <b>Detection Time: <\/b> 2023-05-06 10:05 UTC<br\/>  <b>Sensor: <\/b> NOAA-20 VIIRS<br\/> <b>Confidence: <\/b> Nominal<br\/>  <b>Day\/Night: <\/b> Night<br\/> <b>Scan: <\/b> 0.5 km<br\/> <b>Track: <\/b> 0.7 km<br\/> <b>FRP: <\/b> 0.77 MW<br\/> <b>Brightness: <\/b> 298.03 K" }, "geometry": { "type": "Point", "coordinates": [ -103.02479, 47.58999, 0.0 ] } }
]
}
