{
"type": "FeatureCollection",
"crs": { "type": "name", "properties": { "name": "urn:ogc:def:crs:OGC:1.3:CRS84" } },
"features": [
{ "type": "Feature", "properties": { "Name": "Fire Detection Centroid ", "Description": "<b>Latitude: <\/b> 18.56862<br\/>  <b>Longitude: <\/b> -69.35773<br\/>  <b>Detection Time: <\/b> 2024-03-15 05:23 UTC<br\/>  <b>Sensor: <\/b> NOAA-20 VIIRS<br\/> <b>Confidence: <\/b> Nominal<br\/>  <b>Day\/Night: <\/b> Night<br\/> <b>Scan: <\/b> 0.6 km<br\/> <b>Track: <\/b> 0.7 km<br\/> <b>FRP: <\/b> 2.73 MW<br\/> <b>Brightness: <\/b> 313.56 K" }, "geometry": { "type": "Point", "coordinates": [ -69.35773, 18.56862, 0.0 ] } },
{ "type": "Feature", "properties": { "Name": "Fire Detection Centroid ", "Description": "<b>Latitude: <\/b> 18.35298<br\/>  <b>Longitude: <\/b> -65.87563<br\/>  <b>Detection Time: <\/b> 2024-03-15 05:23 UTC<br\/>  <b>Sensor: <\/b> NOAA-20 VIIRS<br\/> <b>Confidence: <\/b> Nominal<br\/>  <b>Day\/Night: <\/b> Night<br\/> <b>Scan: <\/b> 0.4 km<br\/> <b>Track: <\/b> 0.6 km<br\/> <b>FRP: <\/b> 1.6 MW<br\/> <b>Brightness: <\/b> 316.45 K" }, "geometry": { "type": "Point", "coordinates": [ -65.87563, 18.35298, 0.0 ] } },
{ "type": "Feature", "properties": { "Name": "Fire Detection Centroid ", "Description": "<b>Latitude: <\/b> 19.05732<br\/>  <b>Longitude: <\/b> -70.61077<br\/>  <b>Detection Time: <\/b> 2024-03-15 05:22 UTC<br\/>  <b>Sensor: <\/b> NOAA-20 VIIRS<br\/> <b>Confidence: <\/b> Nominal<br\/>  <b>Day\/Night: <\/b> Night<br\/> <b>Scan: <\/b> 0.8 km<br\/> <b>Track: <\/b> 0.8 km<br\/> <b>FRP: <\/b> 2.15 MW<br\/> <b>Brightness: <\/b> 301.7 K" }, "geometry": { "type": "Point", "coordinates": [ -70.61077, 19.05732, 0.0 ] } },
{ "type": "Feature", "properties": { "Name": "Fire Detection Centroid ", "Description": "<b>Latitude: <\/b> 19.26951<br\/>  <b>Longitude: <\/b> -70.61129<br\/>  <b>Detection Time: <\/b> 2024-03-15 05:22 UTC<br\/>  <b>Sensor: <\/b> NOAA-20 VIIRS<br\/> <b>Confidence: <\/b> Nominal<br\/>  <b>Day\/Night: <\/b> Night<br\/> <b>Scan: <\/b> 0.8 km<br\/> <b>Track: <\/b> 0.8 km<br\/> <b>FRP: <\/b> 1.78 MW<br\/> <b>Brightness: <\/b> 295.96 K" }, "geometry": { "type": "Point", "coordinates": [ -70.61129, 19.26951, 0.0 ] } }
]
}
