{
"type": "FeatureCollection",
"crs": { "type": "name", "properties": { "name": "urn:ogc:def:crs:OGC:1.3:CRS84" } },
"features": [
{ "type": "Feature", "properties": { "Name": "Fire Detection Centroid ", "Description": "<b>Latitude: <\/b> 19.40008<br\/>  <b>Longitude: <\/b> -155.28859<br\/>  <b>Detection Time: <\/b> 2023-06-26 00:09 UTC<br\/>  <b>Sensor: <\/b> NOAA-20 VIIRS<br\/> <b>Confidence: <\/b> Nominal<br\/>  <b>Day\/Night: <\/b> Day<br\/> <b>Scan: <\/b> 0.34 km<br\/> <b>Track: <\/b> 0.56 km<br\/> <b>FRP: <\/b> 5.37 MW<br\/> <b>Brightness: <\/b> 343.57 K" }, "geometry": { "type": "Point", "coordinates": [ -155.28859, 19.40008, 0.0 ] } },
{ "type": "Feature", "properties": { "Name": "Fire Detection Centroid ", "Description": "<b>Latitude: <\/b> 19.4076<br\/>  <b>Longitude: <\/b> -155.28802<br\/>  <b>Detection Time: <\/b> 2023-06-26 00:09 UTC<br\/>  <b>Sensor: <\/b> NOAA-20 VIIRS<br\/> <b>Confidence: <\/b> Low<br\/>  <b>Day\/Night: <\/b> Day<br\/> <b>Scan: <\/b> 0.34 km<br\/> <b>Track: <\/b> 0.56 km<br\/> <b>FRP: <\/b> 11.64 MW<br\/> <b>Brightness: <\/b> 367 K" }, "geometry": { "type": "Point", "coordinates": [ -155.28802, 19.4076, 0.0 ] } },
{ "type": "Feature", "properties": { "Name": "Fire Detection Centroid ", "Description": "<b>Latitude: <\/b> 19.40794<br\/>  <b>Longitude: <\/b> -155.28465<br\/>  <b>Detection Time: <\/b> 2023-06-26 00:09 UTC<br\/>  <b>Sensor: <\/b> NOAA-20 VIIRS<br\/> <b>Confidence: <\/b> Low<br\/>  <b>Day\/Night: <\/b> Day<br\/> <b>Scan: <\/b> 0.34 km<br\/> <b>Track: <\/b> 0.56 km<br\/> <b>FRP: <\/b> 11.63 MW<br\/> <b>Brightness: <\/b> 367 K" }, "geometry": { "type": "Point", "coordinates": [ -155.28465, 19.40794, 0.0 ] } },
{ "type": "Feature", "properties": { "Name": "Fire Detection Centroid ", "Description": "<b>Latitude: <\/b> 19.40828<br\/>  <b>Longitude: <\/b> -155.28133<br\/>  <b>Detection Time: <\/b> 2023-06-26 00:09 UTC<br\/>  <b>Sensor: <\/b> NOAA-20 VIIRS<br\/> <b>Confidence: <\/b> Low<br\/>  <b>Day\/Night: <\/b> Day<br\/> <b>Scan: <\/b> 0.34 km<br\/> <b>Track: <\/b> 0.56 km<br\/> <b>FRP: <\/b> 11.63 MW<br\/> <b>Brightness: <\/b> 353.21 K" }, "geometry": { "type": "Point", "coordinates": [ -155.28133, 19.40828, 0.0 ] } },
{ "type": "Feature", "properties": { "Name": "Fire Detection Centroid ", "Description": "<b>Latitude: <\/b> 19.40212<br\/>  <b>Longitude: <\/b> -155.29071<br\/>  <b>Detection Time: <\/b> 2023-06-26 00:09 UTC<br\/>  <b>Sensor: <\/b> NOAA-20 VIIRS<br\/> <b>Confidence: <\/b> Low<br\/>  <b>Day\/Night: <\/b> Day<br\/> <b>Scan: <\/b> 0.34 km<br\/> <b>Track: <\/b> 0.56 km<br\/> <b>FRP: <\/b> 8.8 MW<br\/> <b>Brightness: <\/b> 351.69 K" }, "geometry": { "type": "Point", "coordinates": [ -155.29071, 19.40212, 0.0 ] } },
{ "type": "Feature", "properties": { "Name": "Fire Detection Centroid ", "Description": "<b>Latitude: <\/b> 19.4028<br\/>  <b>Longitude: <\/b> -155.28398<br\/>  <b>Detection Time: <\/b> 2023-06-26 00:09 UTC<br\/>  <b>Sensor: <\/b> NOAA-20 VIIRS<br\/> <b>Confidence: <\/b> Nominal<br\/>  <b>Day\/Night: <\/b> Day<br\/> <b>Scan: <\/b> 0.34 km<br\/> <b>Track: <\/b> 0.56 km<br\/> <b>FRP: <\/b> 14.41 MW<br\/> <b>Brightness: <\/b> 355.02 K" }, "geometry": { "type": "Point", "coordinates": [ -155.28398, 19.4028, 0.0 ] } },
{ "type": "Feature", "properties": { "Name": "Fire Detection Centroid ", "Description": "<b>Latitude: <\/b> 19.40246<br\/>  <b>Longitude: <\/b> -155.28731<br\/>  <b>Detection Time: <\/b> 2023-06-26 00:09 UTC<br\/>  <b>Sensor: <\/b> NOAA-20 VIIRS<br\/> <b>Confidence: <\/b> High<br\/>  <b>Day\/Night: <\/b> Day<br\/> <b>Scan: <\/b> 0.34 km<br\/> <b>Track: <\/b> 0.56 km<br\/> <b>FRP: <\/b> 8.8 MW<br\/> <b>Brightness: <\/b> 367 K" }, "geometry": { "type": "Point", "coordinates": [ -155.28731, 19.40246, 0.0 ] } },
{ "type": "Feature", "properties": { "Name": "Fire Detection Centroid ", "Description": "<b>Latitude: <\/b> 19.40045<br\/>  <b>Longitude: <\/b> -155.28525<br\/>  <b>Detection Time: <\/b> 2023-06-26 00:09 UTC<br\/>  <b>Sensor: <\/b> NOAA-20 VIIRS<br\/> <b>Confidence: <\/b> Low<br\/>  <b>Day\/Night: <\/b> Day<br\/> <b>Scan: <\/b> 0.34 km<br\/> <b>Track: <\/b> 0.56 km<br\/> <b>FRP: <\/b> 5.37 MW<br\/> <b>Brightness: <\/b> 345.15 K" }, "geometry": { "type": "Point", "coordinates": [ -155.28525, 19.40045, 0.0 ] } }
]
}
