{
"type": "FeatureCollection",
"crs": { "type": "name", "properties": { "name": "urn:ogc:def:crs:OGC:1.3:CRS84" } },
"features": [
{ "type": "Feature", "properties": { "Name": "Fire Detection Centroid ", "Description": "<b>Latitude: <\/b> 18.92979<br\/>  <b>Longitude: <\/b> -70.35693<br\/>  <b>Detection Time: <\/b> 2023-10-22 05:42 UTC<br\/>  <b>Sensor: <\/b> NOAA-20 VIIRS<br\/> <b>Confidence: <\/b> Nominal<br\/>  <b>Day\/Night: <\/b> Night<br\/> <b>Scan: <\/b> 0.36 km<br\/> <b>Track: <\/b> 0.57 km<br\/> <b>FRP: <\/b> 5.37 MW<br\/> <b>Brightness: <\/b> 349.94 K" }, "geometry": { "type": "Point", "coordinates": [ -70.35693, 18.92979, 0.0 ] } },
{ "type": "Feature", "properties": { "Name": "Fire Detection Centroid ", "Description": "<b>Latitude: <\/b> 18.92942<br\/>  <b>Longitude: <\/b> -70.35349<br\/>  <b>Detection Time: <\/b> 2023-10-22 05:42 UTC<br\/>  <b>Sensor: <\/b> NOAA-20 VIIRS<br\/> <b>Confidence: <\/b> Nominal<br\/>  <b>Day\/Night: <\/b> Night<br\/> <b>Scan: <\/b> 0.36 km<br\/> <b>Track: <\/b> 0.57 km<br\/> <b>FRP: <\/b> 5.37 MW<br\/> <b>Brightness: <\/b> 331.41 K" }, "geometry": { "type": "Point", "coordinates": [ -70.35349, 18.92942, 0.0 ] } }
]
}
