{
"type": "FeatureCollection",
"crs": { "type": "name", "properties": { "name": "urn:ogc:def:crs:OGC:1.3:CRS84" } },
"features": [
{ "type": "Feature", "properties": { "Name": "Fire Detection Centroid ", "Description": "<b>Latitude: <\/b> 20.87601<br\/>  <b>Longitude: <\/b> -156.63084<br\/>  <b>Detection Time: <\/b> 2022-11-09 00:05 UTC<br\/>  <b>Sensor: <\/b> NOAA-20 VIIRS<br\/> <b>Confidence: <\/b> Nominal<br\/>  <b>Day\/Night: <\/b> Day<br\/> <b>Scan: <\/b> 0.46 km<br\/> <b>Track: <\/b> 0.47 km<br\/> <b>FRP: <\/b> 20.01 MW<br\/> <b>Brightness: <\/b> 353.27 K" }, "geometry": { "type": "Point", "coordinates": [ -156.63084, 20.87601, 0.0 ] } },
{ "type": "Feature", "properties": { "Name": "Fire Detection Centroid ", "Description": "<b>Latitude: <\/b> 20.88453<br\/>  <b>Longitude: <\/b> -156.6329<br\/>  <b>Detection Time: <\/b> 2022-11-09 00:05 UTC<br\/>  <b>Sensor: <\/b> NOAA-20 VIIRS<br\/> <b>Confidence: <\/b> Nominal<br\/>  <b>Day\/Night: <\/b> Day<br\/> <b>Scan: <\/b> 0.46 km<br\/> <b>Track: <\/b> 0.47 km<br\/> <b>FRP: <\/b> 65.06 MW<br\/> <b>Brightness: <\/b> 355.1 K" }, "geometry": { "type": "Point", "coordinates": [ -156.6329, 20.88453, 0.0 ] } },
{ "type": "Feature", "properties": { "Name": "Fire Detection Centroid ", "Description": "<b>Latitude: <\/b> 20.87801<br\/>  <b>Longitude: <\/b> -156.63048<br\/>  <b>Detection Time: <\/b> 2022-11-09 00:05 UTC<br\/>  <b>Sensor: <\/b> NOAA-20 VIIRS<br\/> <b>Confidence: <\/b> Nominal<br\/>  <b>Day\/Night: <\/b> Day<br\/> <b>Scan: <\/b> 0.46 km<br\/> <b>Track: <\/b> 0.47 km<br\/> <b>FRP: <\/b> 53.18 MW<br\/> <b>Brightness: <\/b> 352.77 K" }, "geometry": { "type": "Point", "coordinates": [ -156.63048, 20.87801, 0.0 ] } },
{ "type": "Feature", "properties": { "Name": "Fire Detection Centroid ", "Description": "<b>Latitude: <\/b> 20.88228<br\/>  <b>Longitude: <\/b> -156.63153<br\/>  <b>Detection Time: <\/b> 2022-11-09 00:05 UTC<br\/>  <b>Sensor: <\/b> NOAA-20 VIIRS<br\/> <b>Confidence: <\/b> Nominal<br\/>  <b>Day\/Night: <\/b> Day<br\/> <b>Scan: <\/b> 0.46 km<br\/> <b>Track: <\/b> 0.47 km<br\/> <b>FRP: <\/b> 63.67 MW<br\/> <b>Brightness: <\/b> 356.1 K" }, "geometry": { "type": "Point", "coordinates": [ -156.63153, 20.88228, 0.0 ] } },
{ "type": "Feature", "properties": { "Name": "Fire Detection Centroid ", "Description": "<b>Latitude: <\/b> 20.88184<br\/>  <b>Longitude: <\/b> -156.63542<br\/>  <b>Detection Time: <\/b> 2022-11-09 00:05 UTC<br\/>  <b>Sensor: <\/b> NOAA-20 VIIRS<br\/> <b>Confidence: <\/b> Nominal<br\/>  <b>Day\/Night: <\/b> Day<br\/> <b>Scan: <\/b> 0.46 km<br\/> <b>Track: <\/b> 0.47 km<br\/> <b>FRP: <\/b> 63.67 MW<br\/> <b>Brightness: <\/b> 341.21 K" }, "geometry": { "type": "Point", "coordinates": [ -156.63542, 20.88184, 0.0 ] } },
{ "type": "Feature", "properties": { "Name": "Fire Detection Centroid ", "Description": "<b>Latitude: <\/b> 20.8803<br\/>  <b>Longitude: <\/b> -156.63165<br\/>  <b>Detection Time: <\/b> 2022-11-09 00:05 UTC<br\/>  <b>Sensor: <\/b> NOAA-20 VIIRS<br\/> <b>Confidence: <\/b> Nominal<br\/>  <b>Day\/Night: <\/b> Day<br\/> <b>Scan: <\/b> 0.46 km<br\/> <b>Track: <\/b> 0.47 km<br\/> <b>FRP: <\/b> 65.06 MW<br\/> <b>Brightness: <\/b> 355.07 K" }, "geometry": { "type": "Point", "coordinates": [ -156.63165, 20.8803, 0.0 ] } },
{ "type": "Feature", "properties": { "Name": "Fire Detection Centroid ", "Description": "<b>Latitude: <\/b> 19.40715<br\/>  <b>Longitude: <\/b> -155.283<br\/>  <b>Detection Time: <\/b> 2022-11-09 00:02 UTC<br\/>  <b>Sensor: <\/b> NOAA-20 VIIRS<br\/> <b>Confidence: <\/b> Low<br\/>  <b>Day\/Night: <\/b> Day<br\/> <b>Scan: <\/b> 0.53 km<br\/> <b>Track: <\/b> 0.5 km<br\/> <b>FRP: <\/b> 27.13 MW<br\/> <b>Brightness: <\/b> 336.07 K" }, "geometry": { "type": "Point", "coordinates": [ -155.283, 19.40715, 0.0 ] } },
{ "type": "Feature", "properties": { "Name": "Fire Detection Centroid ", "Description": "<b>Latitude: <\/b> 19.40655<br\/>  <b>Longitude: <\/b> -155.28821<br\/>  <b>Detection Time: <\/b> 2022-11-09 00:02 UTC<br\/>  <b>Sensor: <\/b> NOAA-20 VIIRS<br\/> <b>Confidence: <\/b> Nominal<br\/>  <b>Day\/Night: <\/b> Day<br\/> <b>Scan: <\/b> 0.53 km<br\/> <b>Track: <\/b> 0.5 km<br\/> <b>FRP: <\/b> 27.13 MW<br\/> <b>Brightness: <\/b> 346.11 K" }, "geometry": { "type": "Point", "coordinates": [ -155.28821, 19.40655, 0.0 ] } },
{ "type": "Feature", "properties": { "Name": "Fire Detection Centroid ", "Description": "<b>Latitude: <\/b> 19.40193<br\/>  <b>Longitude: <\/b> -155.28757<br\/>  <b>Detection Time: <\/b> 2022-11-09 00:02 UTC<br\/>  <b>Sensor: <\/b> NOAA-20 VIIRS<br\/> <b>Confidence: <\/b> Nominal<br\/>  <b>Day\/Night: <\/b> Day<br\/> <b>Scan: <\/b> 0.53 km<br\/> <b>Track: <\/b> 0.5 km<br\/> <b>FRP: <\/b> 27.13 MW<br\/> <b>Brightness: <\/b> 347.39 K" }, "geometry": { "type": "Point", "coordinates": [ -155.28757, 19.40193, 0.0 ] } }
]
}
