{
"type": "FeatureCollection",
"crs": { "type": "name", "properties": { "name": "urn:ogc:def:crs:OGC:1.3:CRS84" } },
"features": [
{ "type": "Feature", "properties": { "Name": "Fire Detection Centroid ", "Description": "<b>Latitude: <\/b> 19.4159<br\/>  <b>Longitude: <\/b> -155.28108<br\/>  <b>Detection Time: <\/b> 2022-09-14 11:42 UTC<br\/>  <b>Sensor: <\/b> NOAA-20 VIIRS<br\/> <b>Confidence: <\/b> Nominal<br\/>  <b>Day\/Night: <\/b> Night<br\/> <b>Scan: <\/b> 0.49 km<br\/> <b>Track: <\/b> 0.41 km<br\/> <b>FRP: <\/b> 1.74 MW<br\/> <b>Brightness: <\/b> 308.51 K" }, "geometry": { "type": "Point", "coordinates": [ -155.28108, 19.4159, 0.0 ] } },
{ "type": "Feature", "properties": { "Name": "Fire Detection Centroid ", "Description": "<b>Latitude: <\/b> 19.40415<br\/>  <b>Longitude: <\/b> -155.2782<br\/>  <b>Detection Time: <\/b> 2022-09-14 11:42 UTC<br\/>  <b>Sensor: <\/b> NOAA-20 VIIRS<br\/> <b>Confidence: <\/b> Nominal<br\/>  <b>Day\/Night: <\/b> Night<br\/> <b>Scan: <\/b> 0.49 km<br\/> <b>Track: <\/b> 0.41 km<br\/> <b>FRP: <\/b> 92.58 MW<br\/> <b>Brightness: <\/b> 324.03 K" }, "geometry": { "type": "Point", "coordinates": [ -155.2782, 19.40415, 0.0 ] } },
{ "type": "Feature", "properties": { "Name": "Fire Detection Centroid ", "Description": "<b>Latitude: <\/b> 19.40541<br\/>  <b>Longitude: <\/b> -155.28752<br\/>  <b>Detection Time: <\/b> 2022-09-14 11:42 UTC<br\/>  <b>Sensor: <\/b> NOAA-20 VIIRS<br\/> <b>Confidence: <\/b> Nominal<br\/>  <b>Day\/Night: <\/b> Night<br\/> <b>Scan: <\/b> 0.49 km<br\/> <b>Track: <\/b> 0.41 km<br\/> <b>FRP: <\/b> 110.03 MW<br\/> <b>Brightness: <\/b> 337.99 K" }, "geometry": { "type": "Point", "coordinates": [ -155.28752, 19.40541, 0.0 ] } },
{ "type": "Feature", "properties": { "Name": "Fire Detection Centroid ", "Description": "<b>Latitude: <\/b> 19.40786<br\/>  <b>Longitude: <\/b> -155.27765<br\/>  <b>Detection Time: <\/b> 2022-09-14 11:42 UTC<br\/>  <b>Sensor: <\/b> NOAA-20 VIIRS<br\/> <b>Confidence: <\/b> Nominal<br\/>  <b>Day\/Night: <\/b> Night<br\/> <b>Scan: <\/b> 0.49 km<br\/> <b>Track: <\/b> 0.41 km<br\/> <b>FRP: <\/b> 6.22 MW<br\/> <b>Brightness: <\/b> 318.96 K" }, "geometry": { "type": "Point", "coordinates": [ -155.27765, 19.40786, 0.0 ] } },
{ "type": "Feature", "properties": { "Name": "Fire Detection Centroid ", "Description": "<b>Latitude: <\/b> 19.40849<br\/>  <b>Longitude: <\/b> -155.28229<br\/>  <b>Detection Time: <\/b> 2022-09-14 11:42 UTC<br\/>  <b>Sensor: <\/b> NOAA-20 VIIRS<br\/> <b>Confidence: <\/b> Nominal<br\/>  <b>Day\/Night: <\/b> Night<br\/> <b>Scan: <\/b> 0.49 km<br\/> <b>Track: <\/b> 0.41 km<br\/> <b>FRP: <\/b> 6.22 MW<br\/> <b>Brightness: <\/b> 325.15 K" }, "geometry": { "type": "Point", "coordinates": [ -155.28229, 19.40849, 0.0 ] } },
{ "type": "Feature", "properties": { "Name": "Fire Detection Centroid ", "Description": "<b>Latitude: <\/b> 19.40911<br\/>  <b>Longitude: <\/b> -155.2869<br\/>  <b>Detection Time: <\/b> 2022-09-14 11:42 UTC<br\/>  <b>Sensor: <\/b> NOAA-20 VIIRS<br\/> <b>Confidence: <\/b> Nominal<br\/>  <b>Day\/Night: <\/b> Night<br\/> <b>Scan: <\/b> 0.49 km<br\/> <b>Track: <\/b> 0.41 km<br\/> <b>FRP: <\/b> 6.3 MW<br\/> <b>Brightness: <\/b> 342.4 K" }, "geometry": { "type": "Point", "coordinates": [ -155.2869, 19.40911, 0.0 ] } },
{ "type": "Feature", "properties": { "Name": "Fire Detection Centroid ", "Description": "<b>Latitude: <\/b> 19.41157<br\/>  <b>Longitude: <\/b> -155.27707<br\/>  <b>Detection Time: <\/b> 2022-09-14 11:42 UTC<br\/>  <b>Sensor: <\/b> NOAA-20 VIIRS<br\/> <b>Confidence: <\/b> Nominal<br\/>  <b>Day\/Night: <\/b> Night<br\/> <b>Scan: <\/b> 0.49 km<br\/> <b>Track: <\/b> 0.41 km<br\/> <b>FRP: <\/b> 6.22 MW<br\/> <b>Brightness: <\/b> 314.63 K" }, "geometry": { "type": "Point", "coordinates": [ -155.27707, 19.41157, 0.0 ] } },
{ "type": "Feature", "properties": { "Name": "Fire Detection Centroid ", "Description": "<b>Latitude: <\/b> 19.41281<br\/>  <b>Longitude: <\/b> -155.28625<br\/>  <b>Detection Time: <\/b> 2022-09-14 11:42 UTC<br\/>  <b>Sensor: <\/b> NOAA-20 VIIRS<br\/> <b>Confidence: <\/b> Nominal<br\/>  <b>Day\/Night: <\/b> Night<br\/> <b>Scan: <\/b> 0.49 km<br\/> <b>Track: <\/b> 0.41 km<br\/> <b>FRP: <\/b> 6.3 MW<br\/> <b>Brightness: <\/b> 308.98 K" }, "geometry": { "type": "Point", "coordinates": [ -155.28625, 19.41281, 0.0 ] } },
{ "type": "Feature", "properties": { "Name": "Fire Detection Centroid ", "Description": "<b>Latitude: <\/b> 19.41219<br\/>  <b>Longitude: <\/b> -155.28169<br\/>  <b>Detection Time: <\/b> 2022-09-14 11:42 UTC<br\/>  <b>Sensor: <\/b> NOAA-20 VIIRS<br\/> <b>Confidence: <\/b> Nominal<br\/>  <b>Day\/Night: <\/b> Night<br\/> <b>Scan: <\/b> 0.49 km<br\/> <b>Track: <\/b> 0.41 km<br\/> <b>FRP: <\/b> 6.22 MW<br\/> <b>Brightness: <\/b> 342.42 K" }, "geometry": { "type": "Point", "coordinates": [ -155.28169, 19.41219, 0.0 ] } }
]
}
