{
"type": "FeatureCollection",
"crs": { "type": "name", "properties": { "name": "urn:ogc:def:crs:OGC:1.3:CRS84" } },
"features": [
{ "type": "Feature", "properties": { "Name": "Fire Detection Centroid ", "Description": "<b>Latitude: <\/b> 49.15947<br\/>  <b>Longitude: <\/b> -123.00605<br\/>  <b>Detection Time: <\/b> 2023-05-29 11:17 UTC<br\/>  <b>Sensor: <\/b> NOAA-20 VIIRS<br\/> <b>Confidence: <\/b> Nominal<br\/>  <b>Day\/Night: <\/b> Night<br\/> <b>Scan: <\/b> 0.36 km<br\/> <b>Track: <\/b> 0.57 km<br\/> <b>FRP: <\/b> 0.62 MW<br\/> <b>Brightness: <\/b> 300.58 K" }, "geometry": { "type": "Point", "coordinates": [ -123.00605, 49.15947, 0.0 ] } },
{ "type": "Feature", "properties": { "Name": "Fire Detection Centroid ", "Description": "<b>Latitude: <\/b> 49.09802<br\/>  <b>Longitude: <\/b> -123.01569<br\/>  <b>Detection Time: <\/b> 2023-05-29 11:17 UTC<br\/>  <b>Sensor: <\/b> NOAA-20 VIIRS<br\/> <b>Confidence: <\/b> Nominal<br\/>  <b>Day\/Night: <\/b> Night<br\/> <b>Scan: <\/b> 0.36 km<br\/> <b>Track: <\/b> 0.58 km<br\/> <b>FRP: <\/b> 0.67 MW<br\/> <b>Brightness: <\/b> 305.86 K" }, "geometry": { "type": "Point", "coordinates": [ -123.01569, 49.09802, 0.0 ] } },
{ "type": "Feature", "properties": { "Name": "Fire Detection Centroid ", "Description": "<b>Latitude: <\/b> 48.8858<br\/>  <b>Longitude: <\/b> -122.73322<br\/>  <b>Detection Time: <\/b> 2023-05-29 11:17 UTC<br\/>  <b>Sensor: <\/b> NOAA-20 VIIRS<br\/> <b>Confidence: <\/b> Nominal<br\/>  <b>Day\/Night: <\/b> Night<br\/> <b>Scan: <\/b> 0.38 km<br\/> <b>Track: <\/b> 0.59 km<br\/> <b>FRP: <\/b> 0.89 MW<br\/> <b>Brightness: <\/b> 295.61 K" }, "geometry": { "type": "Point", "coordinates": [ -122.73322, 48.8858, 0.0 ] } },
{ "type": "Feature", "properties": { "Name": "Fire Detection Centroid ", "Description": "<b>Latitude: <\/b> 43.9332<br\/>  <b>Longitude: <\/b> -123.51376<br\/>  <b>Detection Time: <\/b> 2023-05-29 11:17 UTC<br\/>  <b>Sensor: <\/b> NOAA-20 VIIRS<br\/> <b>Confidence: <\/b> Nominal<br\/>  <b>Day\/Night: <\/b> Night<br\/> <b>Scan: <\/b> 0.5 km<br\/> <b>Track: <\/b> 0.66 km<br\/> <b>FRP: <\/b> 1.03 MW<br\/> <b>Brightness: <\/b> 298.2 K" }, "geometry": { "type": "Point", "coordinates": [ -123.51376, 43.9332, 0.0 ] } }
]
}
