{
"type": "FeatureCollection",
"crs": { "type": "name", "properties": { "name": "urn:ogc:def:crs:OGC:1.3:CRS84" } },
"features": [
{ "type": "Feature", "properties": { "Name": "Fire Detection Centroid ", "Description": "<b>Latitude: <\/b> 42.7938<br\/>  <b>Longitude: <\/b> -80.09703<br\/>  <b>Detection Time: <\/b> 2024-05-04 17:19 UTC<br\/>  <b>Sensor: <\/b> NOAA-20 VIIRS<br\/> <b>Confidence: <\/b> Nominal<br\/>  <b>Day\/Night: <\/b> Day<br\/> <b>Scan: <\/b> 0.4 km<br\/> <b>Track: <\/b> 0.6 km<br\/> <b>FRP: <\/b> 5.97 MW<br\/> <b>Brightness: <\/b> 343.35 K" }, "geometry": { "type": "Point", "coordinates": [ -80.09703, 42.7938, 0.0 ] } },
{ "type": "Feature", "properties": { "Name": "Fire Detection Centroid ", "Description": "<b>Latitude: <\/b> 19.49775<br\/>  <b>Longitude: <\/b> -72.74268<br\/>  <b>Detection Time: <\/b> 2024-05-04 17:13 UTC<br\/>  <b>Sensor: <\/b> NOAA-20 VIIRS<br\/> <b>Confidence: <\/b> Nominal<br\/>  <b>Day\/Night: <\/b> Day<br\/> <b>Scan: <\/b> 0.6 km<br\/> <b>Track: <\/b> 0.7 km<br\/> <b>FRP: <\/b> 4.34 MW<br\/> <b>Brightness: <\/b> 335.29 K" }, "geometry": { "type": "Point", "coordinates": [ -72.74268, 19.49775, 0.0 ] } },
{ "type": "Feature", "properties": { "Name": "Fire Detection Centroid ", "Description": "<b>Latitude: <\/b> 19.14743<br\/>  <b>Longitude: <\/b> -72.14553<br\/>  <b>Detection Time: <\/b> 2024-05-04 17:13 UTC<br\/>  <b>Sensor: <\/b> NOAA-20 VIIRS<br\/> <b>Confidence: <\/b> Nominal<br\/>  <b>Day\/Night: <\/b> Day<br\/> <b>Scan: <\/b> 0.6 km<br\/> <b>Track: <\/b> 0.7 km<br\/> <b>FRP: <\/b> 5.29 MW<br\/> <b>Brightness: <\/b> 331.28 K" }, "geometry": { "type": "Point", "coordinates": [ -72.14553, 19.14743, 0.0 ] } },
{ "type": "Feature", "properties": { "Name": "Fire Detection Centroid ", "Description": "<b>Latitude: <\/b> 18.4789<br\/>  <b>Longitude: <\/b> -70.21471<br\/>  <b>Detection Time: <\/b> 2024-05-04 17:12 UTC<br\/>  <b>Sensor: <\/b> NOAA-20 VIIRS<br\/> <b>Confidence: <\/b> Nominal<br\/>  <b>Day\/Night: <\/b> Day<br\/> <b>Scan: <\/b> 0.4 km<br\/> <b>Track: <\/b> 0.6 km<br\/> <b>FRP: <\/b> 5.11 MW<br\/> <b>Brightness: <\/b> 338.52 K" }, "geometry": { "type": "Point", "coordinates": [ -70.21471, 18.4789, 0.0 ] } },
{ "type": "Feature", "properties": { "Name": "Fire Detection Centroid ", "Description": "<b>Latitude: <\/b> 18.71619<br\/>  <b>Longitude: <\/b> -69.49073<br\/>  <b>Detection Time: <\/b> 2024-05-04 17:12 UTC<br\/>  <b>Sensor: <\/b> NOAA-20 VIIRS<br\/> <b>Confidence: <\/b> Nominal<br\/>  <b>Day\/Night: <\/b> Day<br\/> <b>Scan: <\/b> 0.4 km<br\/> <b>Track: <\/b> 0.6 km<br\/> <b>FRP: <\/b> 4.24 MW<br\/> <b>Brightness: <\/b> 330.51 K" }, "geometry": { "type": "Point", "coordinates": [ -69.49073, 18.71619, 0.0 ] } }
]
}
