{
"type": "FeatureCollection",
"crs": { "type": "name", "properties": { "name": "urn:ogc:def:crs:OGC:1.3:CRS84" } },
"features": [
{ "type": "Feature", "properties": { "Name": "Fire Detection Centroid ", "Description": "<b>Latitude: <\/b> 43.26452<br\/>  <b>Longitude: <\/b> -79.80492<br\/>  <b>Detection Time: <\/b> 2023-08-19 17:01 UTC<br\/>  <b>Sensor: <\/b> NOAA-20 VIIRS<br\/> <b>Confidence: <\/b> Nominal<br\/>  <b>Day\/Night: <\/b> Day<br\/> <b>Scan: <\/b> 0.6 km<br\/> <b>Track: <\/b> 0.7 km<br\/> <b>FRP: <\/b> 7.69 MW<br\/> <b>Brightness: <\/b> 331.06 K" }, "geometry": { "type": "Point", "coordinates": [ -79.80492, 43.26452, 0.0 ] } },
{ "type": "Feature", "properties": { "Name": "Fire Detection Centroid ", "Description": "<b>Latitude: <\/b> 43.71873<br\/>  <b>Longitude: <\/b> -69.7254<br\/>  <b>Detection Time: <\/b> 2023-08-19 17:00 UTC<br\/>  <b>Sensor: <\/b> NOAA-20 VIIRS<br\/> <b>Confidence: <\/b> Nominal<br\/>  <b>Day\/Night: <\/b> Day<br\/> <b>Scan: <\/b> 0.4 km<br\/> <b>Track: <\/b> 0.5 km<br\/> <b>FRP: <\/b> 4.67 MW<br\/> <b>Brightness: <\/b> 336.75 K" }, "geometry": { "type": "Point", "coordinates": [ -69.7254, 43.71873, 0.0 ] } },
{ "type": "Feature", "properties": { "Name": "Fire Detection Centroid ", "Description": "<b>Latitude: <\/b> 43.71745<br\/>  <b>Longitude: <\/b> -69.72263<br\/>  <b>Detection Time: <\/b> 2023-08-19 17:00 UTC<br\/>  <b>Sensor: <\/b> NOAA-20 VIIRS<br\/> <b>Confidence: <\/b> Nominal<br\/>  <b>Day\/Night: <\/b> Day<br\/> <b>Scan: <\/b> 0.4 km<br\/> <b>Track: <\/b> 0.5 km<br\/> <b>FRP: <\/b> 3.06 MW<br\/> <b>Brightness: <\/b> 334.94 K" }, "geometry": { "type": "Point", "coordinates": [ -69.72263, 43.71745, 0.0 ] } },
{ "type": "Feature", "properties": { "Name": "Fire Detection Centroid ", "Description": "<b>Latitude: <\/b> 42.80302<br\/>  <b>Longitude: <\/b> -80.09734<br\/>  <b>Detection Time: <\/b> 2023-08-19 17:00 UTC<br\/>  <b>Sensor: <\/b> NOAA-20 VIIRS<br\/> <b>Confidence: <\/b> Nominal<br\/>  <b>Day\/Night: <\/b> Day<br\/> <b>Scan: <\/b> 0.7 km<br\/> <b>Track: <\/b> 0.7 km<br\/> <b>FRP: <\/b> 13.48 MW<br\/> <b>Brightness: <\/b> 340.85 K" }, "geometry": { "type": "Point", "coordinates": [ -80.09734, 42.80302, 0.0 ] } },
{ "type": "Feature", "properties": { "Name": "Fire Detection Centroid ", "Description": "<b>Latitude: <\/b> 40.88898<br\/>  <b>Longitude: <\/b> -77.70805<br\/>  <b>Detection Time: <\/b> 2023-08-19 17:00 UTC<br\/>  <b>Sensor: <\/b> NOAA-20 VIIRS<br\/> <b>Confidence: <\/b> Nominal<br\/>  <b>Day\/Night: <\/b> Day<br\/> <b>Scan: <\/b> 0.6 km<br\/> <b>Track: <\/b> 0.7 km<br\/> <b>FRP: <\/b> 5.13 MW<br\/> <b>Brightness: <\/b> 328.46 K" }, "geometry": { "type": "Point", "coordinates": [ -77.70805, 40.88898, 0.0 ] } },
{ "type": "Feature", "properties": { "Name": "Fire Detection Centroid ", "Description": "<b>Latitude: <\/b> 35.13234<br\/>  <b>Longitude: <\/b> -76.5883<br\/>  <b>Detection Time: <\/b> 2023-08-19 16:58 UTC<br\/>  <b>Sensor: <\/b> NOAA-20 VIIRS<br\/> <b>Confidence: <\/b> Nominal<br\/>  <b>Day\/Night: <\/b> Day<br\/> <b>Scan: <\/b> 0.8 km<br\/> <b>Track: <\/b> 0.8 km<br\/> <b>FRP: <\/b> 5.31 MW<br\/> <b>Brightness: <\/b> 328.54 K" }, "geometry": { "type": "Point", "coordinates": [ -76.5883, 35.13234, 0.0 ] } },
{ "type": "Feature", "properties": { "Name": "Fire Detection Centroid ", "Description": "<b>Latitude: <\/b> 35.02226<br\/>  <b>Longitude: <\/b> -76.46675<br\/>  <b>Detection Time: <\/b> 2023-08-19 16:58 UTC<br\/>  <b>Sensor: <\/b> NOAA-20 VIIRS<br\/> <b>Confidence: <\/b> Nominal<br\/>  <b>Day\/Night: <\/b> Day<br\/> <b>Scan: <\/b> 0.8 km<br\/> <b>Track: <\/b> 0.8 km<br\/> <b>FRP: <\/b> 5.04 MW<br\/> <b>Brightness: <\/b> 326.69 K" }, "geometry": { "type": "Point", "coordinates": [ -76.46675, 35.02226, 0.0 ] } }
]
}
