{
"type": "FeatureCollection",
"crs": { "type": "name", "properties": { "name": "urn:ogc:def:crs:OGC:1.3:CRS84" } },
"features": [
{ "type": "Feature", "properties": { "Name": "Fire Detection Centroid ", "Description": "<b>Latitude: <\/b> 19.59248<br\/>  <b>Longitude: <\/b> -70.89454<br\/>  <b>Detection Time: <\/b> 2024-01-15 16:58 UTC<br\/>  <b>Sensor: <\/b> NOAA-20 VIIRS<br\/> <b>Confidence: <\/b> Nominal<br\/>  <b>Day\/Night: <\/b> Day<br\/> <b>Scan: <\/b> 0.75 km<br\/> <b>Track: <\/b> 0.77 km<br\/> <b>FRP: <\/b> 3.41 MW<br\/> <b>Brightness: <\/b> 327.05 K" }, "geometry": { "type": "Point", "coordinates": [ -70.89454, 19.59248, 0.0 ] } },
{ "type": "Feature", "properties": { "Name": "Fire Detection Centroid ", "Description": "<b>Latitude: <\/b> 19.59399<br\/>  <b>Longitude: <\/b> -70.89382<br\/>  <b>Detection Time: <\/b> 2024-01-15 16:58 UTC<br\/>  <b>Sensor: <\/b> NOAA-20 VIIRS<br\/> <b>Confidence: <\/b> Nominal<br\/>  <b>Day\/Night: <\/b> Day<br\/> <b>Scan: <\/b> 0.75 km<br\/> <b>Track: <\/b> 0.77 km<br\/> <b>FRP: <\/b> 3.05 MW<br\/> <b>Brightness: <\/b> 326.82 K" }, "geometry": { "type": "Point", "coordinates": [ -70.89382, 19.59399, 0.0 ] } }
]
}
