{
"type": "FeatureCollection",
"crs": { "type": "name", "properties": { "name": "urn:ogc:def:crs:OGC:1.3:CRS84" } },
"features": [
{ "type": "Feature", "properties": { "Name": "Fire Detection Centroid ", "Description": "<b>Latitude: <\/b> 18.79106<br\/>  <b>Longitude: <\/b> -72.37218<br\/>  <b>Detection Time: <\/b> 2024-01-25 17:11 UTC<br\/>  <b>Sensor: <\/b> NOAA-20 VIIRS<br\/> <b>Confidence: <\/b> Nominal<br\/>  <b>Day\/Night: <\/b> Day<br\/> <b>Scan: <\/b> 0.6 km<br\/> <b>Track: <\/b> 0.7 km<br\/> <b>FRP: <\/b> 7.12 MW<br\/> <b>Brightness: <\/b> 341.2 K" }, "geometry": { "type": "Point", "coordinates": [ -72.37218, 18.79106, 0.0 ] } },
{ "type": "Feature", "properties": { "Name": "Fire Detection Centroid ", "Description": "<b>Latitude: <\/b> 18.99439<br\/>  <b>Longitude: <\/b> -72.42809<br\/>  <b>Detection Time: <\/b> 2024-01-25 17:11 UTC<br\/>  <b>Sensor: <\/b> NOAA-20 VIIRS<br\/> <b>Confidence: <\/b> Nominal<br\/>  <b>Day\/Night: <\/b> Day<br\/> <b>Scan: <\/b> 0.6 km<br\/> <b>Track: <\/b> 0.7 km<br\/> <b>FRP: <\/b> 7.19 MW<br\/> <b>Brightness: <\/b> 342.95 K" }, "geometry": { "type": "Point", "coordinates": [ -72.42809, 18.99439, 0.0 ] } },
{ "type": "Feature", "properties": { "Name": "Fire Detection Centroid ", "Description": "<b>Latitude: <\/b> 19.36558<br\/>  <b>Longitude: <\/b> -72.25777<br\/>  <b>Detection Time: <\/b> 2024-01-25 17:11 UTC<br\/>  <b>Sensor: <\/b> NOAA-20 VIIRS<br\/> <b>Confidence: <\/b> Nominal<br\/>  <b>Day\/Night: <\/b> Day<br\/> <b>Scan: <\/b> 0.6 km<br\/> <b>Track: <\/b> 0.7 km<br\/> <b>FRP: <\/b> 6.52 MW<br\/> <b>Brightness: <\/b> 334.01 K" }, "geometry": { "type": "Point", "coordinates": [ -72.25777, 19.36558, 0.0 ] } },
{ "type": "Feature", "properties": { "Name": "Fire Detection Centroid ", "Description": "<b>Latitude: <\/b> 18.73905<br\/>  <b>Longitude: <\/b> -70.99487<br\/>  <b>Detection Time: <\/b> 2024-01-25 17:11 UTC<br\/>  <b>Sensor: <\/b> NOAA-20 VIIRS<br\/> <b>Confidence: <\/b> High<br\/>  <b>Day\/Night: <\/b> Day<br\/> <b>Scan: <\/b> 0.5 km<br\/> <b>Track: <\/b> 0.7 km<br\/> <b>FRP: <\/b> 9.01 MW<br\/> <b>Brightness: <\/b> 367 K" }, "geometry": { "type": "Point", "coordinates": [ -70.99487, 18.73905, 0.0 ] } },
{ "type": "Feature", "properties": { "Name": "Fire Detection Centroid ", "Description": "<b>Latitude: <\/b> 19.44754<br\/>  <b>Longitude: <\/b> -71.72163<br\/>  <b>Detection Time: <\/b> 2024-01-25 17:11 UTC<br\/>  <b>Sensor: <\/b> NOAA-20 VIIRS<br\/> <b>Confidence: <\/b> Nominal<br\/>  <b>Day\/Night: <\/b> Day<br\/> <b>Scan: <\/b> 0.5 km<br\/> <b>Track: <\/b> 0.7 km<br\/> <b>FRP: <\/b> 3.23 MW<br\/> <b>Brightness: <\/b> 330.15 K" }, "geometry": { "type": "Point", "coordinates": [ -71.72163, 19.44754, 0.0 ] } },
{ "type": "Feature", "properties": { "Name": "Fire Detection Centroid ", "Description": "<b>Latitude: <\/b> 19.46055<br\/>  <b>Longitude: <\/b> -154.94135<br\/>  <b>Detection Time: <\/b> 2024-01-25 12:46 UTC<br\/>  <b>Sensor: <\/b> NOAA-20 VIIRS<br\/> <b>Confidence: <\/b> Nominal<br\/>  <b>Day\/Night: <\/b> Night<br\/> <b>Scan: <\/b> 0.55 km<br\/> <b>Track: <\/b> 0.68 km<br\/> <b>FRP: <\/b> 1.2 MW<br\/> <b>Brightness: <\/b> 298.42 K" }, "geometry": { "type": "Point", "coordinates": [ -154.94135, 19.46055, 0.0 ] } },
{ "type": "Feature", "properties": { "Name": "Fire Detection Centroid ", "Description": "<b>Latitude: <\/b> 19.43082<br\/>  <b>Longitude: <\/b> -154.94696<br\/>  <b>Detection Time: <\/b> 2024-01-25 12:45 UTC<br\/>  <b>Sensor: <\/b> NOAA-20 VIIRS<br\/> <b>Confidence: <\/b> Nominal<br\/>  <b>Day\/Night: <\/b> Night<br\/> <b>Scan: <\/b> 0.5 km<br\/> <b>Track: <\/b> 0.7 km<br\/> <b>FRP: <\/b> 1.2 MW<br\/> <b>Brightness: <\/b> 298.42 K" }, "geometry": { "type": "Point", "coordinates": [ -154.94696, 19.43082, 0.0 ] } }
]
}
