{
"type": "FeatureCollection",
"crs": { "type": "name", "properties": { "name": "urn:ogc:def:crs:OGC:1.3:CRS84" } },
"features": [
{ "type": "Feature", "properties": { "Name": "Fire Detection Centroid ", "Description": "<b>Latitude: <\/b> 19.40611<br\/>  <b>Longitude: <\/b> -155.28268<br\/>  <b>Detection Time: <\/b> 2023-12-28 11:29 UTC<br\/>  <b>Sensor: <\/b> NOAA-20 VIIRS<br\/> <b>Confidence: <\/b> Nominal<br\/>  <b>Day\/Night: <\/b> Night<br\/> <b>Scan: <\/b> 0.51 km<br\/> <b>Track: <\/b> 0.49 km<br\/> <b>FRP: <\/b> 4.86 MW<br\/> <b>Brightness: <\/b> 304.61 K" }, "geometry": { "type": "Point", "coordinates": [ -155.28268, 19.40611, 0.0 ] } }
]
}
