{
"type": "FeatureCollection",
"crs": { "type": "name", "properties": { "name": "urn:ogc:def:crs:OGC:1.3:CRS84" } },
"features": [
{ "type": "Feature", "properties": { "Name": "Fire Detection Centroid ", "Description": "<b>Latitude: <\/b> 18.53023<br\/>  <b>Longitude: <\/b> -71.27145<br\/>  <b>Detection Time: <\/b> 2024-02-05 05:54 UTC<br\/>  <b>Sensor: <\/b> NOAA-20 VIIRS<br\/> <b>Confidence: <\/b> Nominal<br\/>  <b>Day\/Night: <\/b> Night<br\/> <b>Scan: <\/b> 0.5 km<br\/> <b>Track: <\/b> 0.5 km<br\/> <b>FRP: <\/b> 2.31 MW<br\/> <b>Brightness: <\/b> 326.72 K" }, "geometry": { "type": "Point", "coordinates": [ -71.27145, 18.53023, 0.0 ] } },
{ "type": "Feature", "properties": { "Name": "Fire Detection Centroid ", "Description": "<b>Latitude: <\/b> 18.79394<br\/>  <b>Longitude: <\/b> -71.95325<br\/>  <b>Detection Time: <\/b> 2024-02-05 05:54 UTC<br\/>  <b>Sensor: <\/b> NOAA-20 VIIRS<br\/> <b>Confidence: <\/b> Nominal<br\/>  <b>Day\/Night: <\/b> Night<br\/> <b>Scan: <\/b> 0.6 km<br\/> <b>Track: <\/b> 0.5 km<br\/> <b>FRP: <\/b> 0.59 MW<br\/> <b>Brightness: <\/b> 304.38 K" }, "geometry": { "type": "Point", "coordinates": [ -71.95325, 18.79394, 0.0 ] } },
{ "type": "Feature", "properties": { "Name": "Fire Detection Centroid ", "Description": "<b>Latitude: <\/b> 18.86928<br\/>  <b>Longitude: <\/b> -71.68398<br\/>  <b>Detection Time: <\/b> 2024-02-05 05:54 UTC<br\/>  <b>Sensor: <\/b> NOAA-20 VIIRS<br\/> <b>Confidence: <\/b> Nominal<br\/>  <b>Day\/Night: <\/b> Night<br\/> <b>Scan: <\/b> 0.5 km<br\/> <b>Track: <\/b> 0.5 km<br\/> <b>FRP: <\/b> 3.12 MW<br\/> <b>Brightness: <\/b> 331.36 K" }, "geometry": { "type": "Point", "coordinates": [ -71.68398, 18.86928, 0.0 ] } },
{ "type": "Feature", "properties": { "Name": "Fire Detection Centroid ", "Description": "<b>Latitude: <\/b> 19.23534<br\/>  <b>Longitude: <\/b> -72.02637<br\/>  <b>Detection Time: <\/b> 2024-02-05 05:54 UTC<br\/>  <b>Sensor: <\/b> NOAA-20 VIIRS<br\/> <b>Confidence: <\/b> Nominal<br\/>  <b>Day\/Night: <\/b> Night<br\/> <b>Scan: <\/b> 0.6 km<br\/> <b>Track: <\/b> 0.5 km<br\/> <b>FRP: <\/b> 1.34 MW<br\/> <b>Brightness: <\/b> 300.89 K" }, "geometry": { "type": "Point", "coordinates": [ -72.02637, 19.23534, 0.0 ] } },
{ "type": "Feature", "properties": { "Name": "Fire Detection Centroid ", "Description": "<b>Latitude: <\/b> 19.2381<br\/>  <b>Longitude: <\/b> -72.53316<br\/>  <b>Detection Time: <\/b> 2024-02-05 05:54 UTC<br\/>  <b>Sensor: <\/b> NOAA-20 VIIRS<br\/> <b>Confidence: <\/b> Nominal<br\/>  <b>Day\/Night: <\/b> Night<br\/> <b>Scan: <\/b> 0.6 km<br\/> <b>Track: <\/b> 0.5 km<br\/> <b>FRP: <\/b> 0.73 MW<br\/> <b>Brightness: <\/b> 301.23 K" }, "geometry": { "type": "Point", "coordinates": [ -72.53316, 19.2381, 0.0 ] } },
{ "type": "Feature", "properties": { "Name": "Fire Detection Centroid ", "Description": "<b>Latitude: <\/b> 18.31727<br\/>  <b>Longitude: <\/b> -71.3039<br\/>  <b>Detection Time: <\/b> 2024-02-05 05:54 UTC<br\/>  <b>Sensor: <\/b> NOAA-20 VIIRS<br\/> <b>Confidence: <\/b> Nominal<br\/>  <b>Day\/Night: <\/b> Night<br\/> <b>Scan: <\/b> 0.5 km<br\/> <b>Track: <\/b> 0.5 km<br\/> <b>FRP: <\/b> 3.05 MW<br\/> <b>Brightness: <\/b> 327.55 K" }, "geometry": { "type": "Point", "coordinates": [ -71.3039, 18.31727, 0.0 ] } },
{ "type": "Feature", "properties": { "Name": "Fire Detection Centroid ", "Description": "<b>Latitude: <\/b> 18.449<br\/>  <b>Longitude: <\/b> -72.33607<br\/>  <b>Detection Time: <\/b> 2024-02-05 05:54 UTC<br\/>  <b>Sensor: <\/b> NOAA-20 VIIRS<br\/> <b>Confidence: <\/b> Nominal<br\/>  <b>Day\/Night: <\/b> Night<br\/> <b>Scan: <\/b> 0.6 km<br\/> <b>Track: <\/b> 0.5 km<br\/> <b>FRP: <\/b> 1.64 MW<br\/> <b>Brightness: <\/b> 309.08 K" }, "geometry": { "type": "Point", "coordinates": [ -72.33607, 18.449, 0.0 ] } },
{ "type": "Feature", "properties": { "Name": "Fire Detection Centroid ", "Description": "<b>Latitude: <\/b> 17.90118<br\/>  <b>Longitude: <\/b> -66.4471<br\/>  <b>Detection Time: <\/b> 2024-02-05 05:54 UTC<br\/>  <b>Sensor: <\/b> NOAA-20 VIIRS<br\/> <b>Confidence: <\/b> Nominal<br\/>  <b>Day\/Night: <\/b> Night<br\/> <b>Scan: <\/b> 0.4 km<br\/> <b>Track: <\/b> 0.4 km<br\/> <b>FRP: <\/b> 2.47 MW<br\/> <b>Brightness: <\/b> 316.6 K" }, "geometry": { "type": "Point", "coordinates": [ -66.4471, 17.90118, 0.0 ] } }
]
}
