{
"type": "FeatureCollection",
"crs": { "type": "name", "properties": { "name": "urn:ogc:def:crs:OGC:1.3:CRS84" } },
"features": [
{ "type": "Feature", "properties": { "Name": "Fire Detection Centroid ", "Description": "<b>Latitude: <\/b> 19.59976<br\/>  <b>Longitude: <\/b> -155.50375<br\/>  <b>Detection Time: <\/b> 2023-04-23 12:40 UTC<br\/>  <b>Sensor: <\/b> NOAA-20 VIIRS<br\/> <b>Confidence: <\/b> Nominal<br\/>  <b>Day\/Night: <\/b> Night<br\/> <b>Scan: <\/b> 0.4 km<br\/> <b>Track: <\/b> 0.6 km<br\/> <b>FRP: <\/b> 2 MW<br\/> <b>Brightness: <\/b> 296.44 K" }, "geometry": { "type": "Point", "coordinates": [ -155.50375, 19.59976, 0.0 ] } },
{ "type": "Feature", "properties": { "Name": "Fire Detection Centroid ", "Description": "<b>Latitude: <\/b> 42.14735<br\/>  <b>Longitude: <\/b> -121.31246<br\/>  <b>Detection Time: <\/b> 2023-04-23 10:51 UTC<br\/>  <b>Sensor: <\/b> NOAA-20 VIIRS<br\/> <b>Confidence: <\/b> Nominal<br\/>  <b>Day\/Night: <\/b> Night<br\/> <b>Scan: <\/b> 0.37 km<br\/> <b>Track: <\/b> 0.58 km<br\/> <b>FRP: <\/b> 0.71 MW<br\/> <b>Brightness: <\/b> 295.54 K" }, "geometry": { "type": "Point", "coordinates": [ -121.31246, 42.14735, 0.0 ] } },
{ "type": "Feature", "properties": { "Name": "Fire Detection Centroid ", "Description": "<b>Latitude: <\/b> 37.4574<br\/>  <b>Longitude: <\/b> -121.93042<br\/>  <b>Detection Time: <\/b> 2023-04-23 10:51 UTC<br\/>  <b>Sensor: <\/b> NOAA-20 VIIRS<br\/> <b>Confidence: <\/b> Nominal<br\/>  <b>Day\/Night: <\/b> Night<br\/> <b>Scan: <\/b> 0.46 km<br\/> <b>Track: <\/b> 0.63 km<br\/> <b>FRP: <\/b> 0.86 MW<br\/> <b>Brightness: <\/b> 295.31 K" }, "geometry": { "type": "Point", "coordinates": [ -121.93042, 37.4574, 0.0 ] } },
{ "type": "Feature", "properties": { "Name": "Fire Detection Centroid ", "Description": "<b>Latitude: <\/b> 37.95119<br\/>  <b>Longitude: <\/b> -122.40113<br\/>  <b>Detection Time: <\/b> 2023-04-23 10:51 UTC<br\/>  <b>Sensor: <\/b> NOAA-20 VIIRS<br\/> <b>Confidence: <\/b> Nominal<br\/>  <b>Day\/Night: <\/b> Night<br\/> <b>Scan: <\/b> 0.42 km<br\/> <b>Track: <\/b> 0.61 km<br\/> <b>FRP: <\/b> 0.88 MW<br\/> <b>Brightness: <\/b> 299.63 K" }, "geometry": { "type": "Point", "coordinates": [ -122.40113, 37.95119, 0.0 ] } },
{ "type": "Feature", "properties": { "Name": "Fire Detection Centroid ", "Description": "<b>Latitude: <\/b> 38.07404<br\/>  <b>Longitude: <\/b> -122.14021<br\/>  <b>Detection Time: <\/b> 2023-04-23 10:51 UTC<br\/>  <b>Sensor: <\/b> NOAA-20 VIIRS<br\/> <b>Confidence: <\/b> Nominal<br\/>  <b>Day\/Night: <\/b> Night<br\/> <b>Scan: <\/b> 0.43 km<br\/> <b>Track: <\/b> 0.62 km<br\/> <b>FRP: <\/b> 1.19 MW<br\/> <b>Brightness: <\/b> 299.24 K" }, "geometry": { "type": "Point", "coordinates": [ -122.14021, 38.07404, 0.0 ] } }
]
}
