{
"type": "FeatureCollection",
"crs": { "type": "name", "properties": { "name": "urn:ogc:def:crs:OGC:1.3:CRS84" } },
"features": [
{ "type": "Feature", "properties": { "Name": "Fire Detection Centroid ", "Description": "<b>Latitude: <\/b> 39.44082<br\/>  <b>Longitude: <\/b> -76.13978<br\/>  <b>Detection Time: <\/b> 2024-01-05 16:52 UTC<br\/>  <b>Sensor: <\/b> NOAA-20 VIIRS<br\/> <b>Confidence: <\/b> Nominal<br\/>  <b>Day\/Night: <\/b> Day<br\/> <b>Scan: <\/b> 0.7 km<br\/> <b>Track: <\/b> 0.7 km<br\/> <b>FRP: <\/b> 13.78 MW<br\/> <b>Brightness: <\/b> 340.95 K" }, "geometry": { "type": "Point", "coordinates": [ -76.13978, 39.44082, 0.0 ] } },
{ "type": "Feature", "properties": { "Name": "Fire Detection Centroid ", "Description": "<b>Latitude: <\/b> 39.44193<br\/>  <b>Longitude: <\/b> -76.14699<br\/>  <b>Detection Time: <\/b> 2024-01-05 16:52 UTC<br\/>  <b>Sensor: <\/b> NOAA-20 VIIRS<br\/> <b>Confidence: <\/b> Nominal<br\/>  <b>Day\/Night: <\/b> Day<br\/> <b>Scan: <\/b> 0.7 km<br\/> <b>Track: <\/b> 0.7 km<br\/> <b>FRP: <\/b> 7.99 MW<br\/> <b>Brightness: <\/b> 339.2 K" }, "geometry": { "type": "Point", "coordinates": [ -76.14699, 39.44193, 0.0 ] } },
{ "type": "Feature", "properties": { "Name": "Fire Detection Centroid ", "Description": "<b>Latitude: <\/b> 39.43845<br\/>  <b>Longitude: <\/b> -76.14715<br\/>  <b>Detection Time: <\/b> 2024-01-05 16:52 UTC<br\/>  <b>Sensor: <\/b> NOAA-20 VIIRS<br\/> <b>Confidence: <\/b> Low<br\/>  <b>Day\/Night: <\/b> Day<br\/> <b>Scan: <\/b> 0.7 km<br\/> <b>Track: <\/b> 0.7 km<br\/> <b>FRP: <\/b> 13.78 MW<br\/> <b>Brightness: <\/b> 355.96 K" }, "geometry": { "type": "Point", "coordinates": [ -76.14715, 39.43845, 0.0 ] } },
{ "type": "Feature", "properties": { "Name": "Fire Detection Centroid ", "Description": "<b>Latitude: <\/b> 39.43612<br\/>  <b>Longitude: <\/b> -76.15443<br\/>  <b>Detection Time: <\/b> 2024-01-05 16:52 UTC<br\/>  <b>Sensor: <\/b> NOAA-20 VIIRS<br\/> <b>Confidence: <\/b> Nominal<br\/>  <b>Day\/Night: <\/b> Day<br\/> <b>Scan: <\/b> 0.7 km<br\/> <b>Track: <\/b> 0.7 km<br\/> <b>FRP: <\/b> 19.59 MW<br\/> <b>Brightness: <\/b> 353.92 K" }, "geometry": { "type": "Point", "coordinates": [ -76.15443, 39.43612, 0.0 ] } }
]
}
