{
"type": "FeatureCollection",
"crs": { "type": "name", "properties": { "name": "urn:ogc:def:crs:OGC:1.3:CRS84" } },
"features": [
{ "type": "Feature", "properties": { "Name": "Fire Detection Centroid ", "Description": "<b>Latitude: <\/b> 18.92873<br\/>  <b>Longitude: <\/b> -70.34983<br\/>  <b>Detection Time: <\/b> 2022-10-02 06:00 UTC<br\/>  <b>Sensor: <\/b> NOAA-20 VIIRS<br\/> <b>Confidence: <\/b> Nominal<br\/>  <b>Day\/Night: <\/b> Night<br\/> <b>Scan: <\/b> 0.5 km<br\/> <b>Track: <\/b> 0.4 km<br\/> <b>FRP: <\/b> 12.51 MW<br\/> <b>Brightness: <\/b> 305.34 K" }, "geometry": { "type": "Point", "coordinates": [ -70.34983, 18.92873, 0.0 ] } },
{ "type": "Feature", "properties": { "Name": "Fire Detection Centroid ", "Description": "<b>Latitude: <\/b> 18.92554<br\/>  <b>Longitude: <\/b> -70.35526<br\/>  <b>Detection Time: <\/b> 2022-10-02 06:00 UTC<br\/>  <b>Sensor: <\/b> NOAA-20 VIIRS<br\/> <b>Confidence: <\/b> Nominal<br\/>  <b>Day\/Night: <\/b> Night<br\/> <b>Scan: <\/b> 0.5 km<br\/> <b>Track: <\/b> 0.4 km<br\/> <b>FRP: <\/b> 1.51 MW<br\/> <b>Brightness: <\/b> 299.7 K" }, "geometry": { "type": "Point", "coordinates": [ -70.35526, 18.92554, 0.0 ] } },
{ "type": "Feature", "properties": { "Name": "Fire Detection Centroid ", "Description": "<b>Latitude: <\/b> 18.92942<br\/>  <b>Longitude: <\/b> -70.35503<br\/>  <b>Detection Time: <\/b> 2022-10-02 06:00 UTC<br\/>  <b>Sensor: <\/b> NOAA-20 VIIRS<br\/> <b>Confidence: <\/b> Nominal<br\/>  <b>Day\/Night: <\/b> Night<br\/> <b>Scan: <\/b> 0.5 km<br\/> <b>Track: <\/b> 0.4 km<br\/> <b>FRP: <\/b> 12.51 MW<br\/> <b>Brightness: <\/b> 341.26 K" }, "geometry": { "type": "Point", "coordinates": [ -70.35503, 18.92942, 0.0 ] } },
{ "type": "Feature", "properties": { "Name": "Fire Detection Centroid ", "Description": "<b>Latitude: <\/b> 37.56015<br\/>  <b>Longitude: <\/b> -75.78231<br\/>  <b>Detection Time: <\/b> 2022-10-02 05:55 UTC<br\/>  <b>Sensor: <\/b> NOAA-20 VIIRS<br\/> <b>Confidence: <\/b> Nominal<br\/>  <b>Day\/Night: <\/b> Night<br\/> <b>Scan: <\/b> 0.6 km<br\/> <b>Track: <\/b> 0.7 km<br\/> <b>FRP: <\/b> 0.92 MW<br\/> <b>Brightness: <\/b> 296.34 K" }, "geometry": { "type": "Point", "coordinates": [ -75.78231, 37.56015, 0.0 ] } },
{ "type": "Feature", "properties": { "Name": "Fire Detection Centroid ", "Description": "<b>Latitude: <\/b> 37.5605<br\/>  <b>Longitude: <\/b> -75.79014<br\/>  <b>Detection Time: <\/b> 2022-10-02 05:55 UTC<br\/>  <b>Sensor: <\/b> NOAA-20 VIIRS<br\/> <b>Confidence: <\/b> Nominal<br\/>  <b>Day\/Night: <\/b> Night<br\/> <b>Scan: <\/b> 0.6 km<br\/> <b>Track: <\/b> 0.7 km<br\/> <b>FRP: <\/b> 0.8 MW<br\/> <b>Brightness: <\/b> 295.74 K" }, "geometry": { "type": "Point", "coordinates": [ -75.79014, 37.5605, 0.0 ] } },
{ "type": "Feature", "properties": { "Name": "Fire Detection Centroid ", "Description": "<b>Latitude: <\/b> 37.56033<br\/>  <b>Longitude: <\/b> -75.7834<br\/>  <b>Detection Time: <\/b> 2022-10-02 05:55 UTC<br\/>  <b>Sensor: <\/b> NOAA-20 VIIRS<br\/> <b>Confidence: <\/b> Nominal<br\/>  <b>Day\/Night: <\/b> Night<br\/> <b>Scan: <\/b> 0.6 km<br\/> <b>Track: <\/b> 0.7 km<br\/> <b>FRP: <\/b> 0.8 MW<br\/> <b>Brightness: <\/b> 298.57 K" }, "geometry": { "type": "Point", "coordinates": [ -75.7834, 37.56033, 0.0 ] } },
{ "type": "Feature", "properties": { "Name": "Fire Detection Centroid ", "Description": "<b>Latitude: <\/b> 37.56036<br\/>  <b>Longitude: <\/b> -75.78902<br\/>  <b>Detection Time: <\/b> 2022-10-02 05:55 UTC<br\/>  <b>Sensor: <\/b> NOAA-20 VIIRS<br\/> <b>Confidence: <\/b> Nominal<br\/>  <b>Day\/Night: <\/b> Night<br\/> <b>Scan: <\/b> 0.6 km<br\/> <b>Track: <\/b> 0.7 km<br\/> <b>FRP: <\/b> 0.85 MW<br\/> <b>Brightness: <\/b> 297.99 K" }, "geometry": { "type": "Point", "coordinates": [ -75.78902, 37.56036, 0.0 ] } },
{ "type": "Feature", "properties": { "Name": "Fire Detection Centroid ", "Description": "<b>Latitude: <\/b> 46.04626<br\/>  <b>Longitude: <\/b> -73.1417<br\/>  <b>Detection Time: <\/b> 2022-10-02 05:53 UTC<br\/>  <b>Sensor: <\/b> NOAA-20 VIIRS<br\/> <b>Confidence: <\/b> Nominal<br\/>  <b>Day\/Night: <\/b> Night<br\/> <b>Scan: <\/b> 0.5 km<br\/> <b>Track: <\/b> 0.6 km<br\/> <b>FRP: <\/b> 2.27 MW<br\/> <b>Brightness: <\/b> 296.67 K" }, "geometry": { "type": "Point", "coordinates": [ -73.1417, 46.04626, 0.0 ] } },
{ "type": "Feature", "properties": { "Name": "Fire Detection Centroid ", "Description": "<b>Latitude: <\/b> 48.18826<br\/>  <b>Longitude: <\/b> -64.92239<br\/>  <b>Detection Time: <\/b> 2022-10-02 05:52 UTC<br\/>  <b>Sensor: <\/b> NOAA-20 VIIRS<br\/> <b>Confidence: <\/b> Nominal<br\/>  <b>Day\/Night: <\/b> Night<br\/> <b>Scan: <\/b> 0.4 km<br\/> <b>Track: <\/b> 0.4 km<br\/> <b>FRP: <\/b> 1.18 MW<br\/> <b>Brightness: <\/b> 307.75 K" }, "geometry": { "type": "Point", "coordinates": [ -64.92239, 48.18826, 0.0 ] } }
]
}
