{
"type": "FeatureCollection",
"crs": { "type": "name", "properties": { "name": "urn:ogc:def:crs:OGC:1.3:CRS84" } },
"features": [
{ "type": "Feature", "properties": { "Name": "Fire Detection Centroid ", "Description": "<b>Latitude: <\/b> 40.86274<br\/>  <b>Longitude: <\/b> -75.20341<br\/>  <b>Detection Time: <\/b> 2023-09-15 16:53 UTC<br\/>  <b>Sensor: <\/b> NOAA-20 VIIRS<br\/> <b>Confidence: <\/b> Nominal<br\/>  <b>Day\/Night: <\/b> Day<br\/> <b>Scan: <\/b> 0.5 km<br\/> <b>Track: <\/b> 0.7 km<br\/> <b>FRP: <\/b> 6.67 MW<br\/> <b>Brightness: <\/b> 347.63 K" }, "geometry": { "type": "Point", "coordinates": [ -75.20341, 40.86274, 0.0 ] } }
]
}
