{
"type": "FeatureCollection",
"crs": { "type": "name", "properties": { "name": "urn:ogc:def:crs:OGC:1.3:CRS84" } },
"features": [
{ "type": "Feature", "properties": { "Name": "Fire Detection Centroid ", "Description": "<b>Latitude: <\/b> 44.43511<br\/>  <b>Longitude: <\/b> -78.88715<br\/>  <b>Detection Time: <\/b> 2022-11-04 17:00 UTC<br\/>  <b>Sensor: <\/b> NOAA-20 VIIRS<br\/> <b>Confidence: <\/b> Nominal<br\/>  <b>Day\/Night: <\/b> Day<br\/> <b>Scan: <\/b> 0.5 km<br\/> <b>Track: <\/b> 0.7 km<br\/> <b>FRP: <\/b> 4.3 MW<br\/> <b>Brightness: <\/b> 327.09 K" }, "geometry": { "type": "Point", "coordinates": [ -78.88715, 44.43511, 0.0 ] } },
{ "type": "Feature", "properties": { "Name": "Fire Detection Centroid ", "Description": "<b>Latitude: <\/b> 44.61239<br\/>  <b>Longitude: <\/b> -71.52448<br\/>  <b>Detection Time: <\/b> 2022-11-04 16:59 UTC<br\/>  <b>Sensor: <\/b> NOAA-20 VIIRS<br\/> <b>Confidence: <\/b> Nominal<br\/>  <b>Day\/Night: <\/b> Day<br\/> <b>Scan: <\/b> 0.5 km<br\/> <b>Track: <\/b> 0.5 km<br\/> <b>FRP: <\/b> 4.33 MW<br\/> <b>Brightness: <\/b> 327.59 K" }, "geometry": { "type": "Point", "coordinates": [ -71.52448, 44.61239, 0.0 ] } },
{ "type": "Feature", "properties": { "Name": "Fire Detection Centroid ", "Description": "<b>Latitude: <\/b> 40.88885<br\/>  <b>Longitude: <\/b> -77.70867<br\/>  <b>Detection Time: <\/b> 2022-11-04 16:59 UTC<br\/>  <b>Sensor: <\/b> NOAA-20 VIIRS<br\/> <b>Confidence: <\/b> Nominal<br\/>  <b>Day\/Night: <\/b> Day<br\/> <b>Scan: <\/b> 0.6 km<br\/> <b>Track: <\/b> 0.7 km<br\/> <b>FRP: <\/b> 4.83 MW<br\/> <b>Brightness: <\/b> 328.68 K" }, "geometry": { "type": "Point", "coordinates": [ -77.70867, 40.88885, 0.0 ] } },
{ "type": "Feature", "properties": { "Name": "Fire Detection Centroid ", "Description": "<b>Latitude: <\/b> 21.45518<br\/>  <b>Longitude: <\/b> -158.1512<br\/>  <b>Detection Time: <\/b> 2022-11-04 12:25 UTC<br\/>  <b>Sensor: <\/b> NOAA-20 VIIRS<br\/> <b>Confidence: <\/b> Nominal<br\/>  <b>Day\/Night: <\/b> Night<br\/> <b>Scan: <\/b> 0.49 km<br\/> <b>Track: <\/b> 0.4 km<br\/> <b>FRP: <\/b> 1.69 MW<br\/> <b>Brightness: <\/b> 318.92 K" }, "geometry": { "type": "Point", "coordinates": [ -158.1512, 21.45518, 0.0 ] } }
]
}
