{
"type": "FeatureCollection",
"crs": { "type": "name", "properties": { "name": "urn:ogc:def:crs:OGC:1.3:CRS84" } },
"features": [
{ "type": "Feature", "properties": { "Name": "Fire Detection Centroid ", "Description": "<b>Latitude: <\/b> 19.40284<br\/>  <b>Longitude: <\/b> -155.28026<br\/>  <b>Detection Time: <\/b> 2023-06-29 22:57 UTC<br\/>  <b>Sensor: <\/b> NOAA-20 VIIRS<br\/> <b>Confidence: <\/b> Low<br\/>  <b>Day\/Night: <\/b> Day<br\/> <b>Scan: <\/b> 0.39 km<br\/> <b>Track: <\/b> 0.59 km<br\/> <b>FRP: <\/b> 21.35 MW<br\/> <b>Brightness: <\/b> 341.27 K" }, "geometry": { "type": "Point", "coordinates": [ -155.28026, 19.40284, 0.0 ] } },
{ "type": "Feature", "properties": { "Name": "Fire Detection Centroid ", "Description": "<b>Latitude: <\/b> 19.40973<br\/>  <b>Longitude: <\/b> -155.27425<br\/>  <b>Detection Time: <\/b> 2023-06-29 22:57 UTC<br\/>  <b>Sensor: <\/b> NOAA-20 VIIRS<br\/> <b>Confidence: <\/b> Low<br\/>  <b>Day\/Night: <\/b> Day<br\/> <b>Scan: <\/b> 0.39 km<br\/> <b>Track: <\/b> 0.59 km<br\/> <b>FRP: <\/b> 22.12 MW<br\/> <b>Brightness: <\/b> 339.9 K" }, "geometry": { "type": "Point", "coordinates": [ -155.27425, 19.40973, 0.0 ] } }
]
}
