{
"type": "FeatureCollection",
"crs": { "type": "name", "properties": { "name": "urn:ogc:def:crs:OGC:1.3:CRS84" } },
"features": [
{ "type": "Feature", "properties": { "Name": "Fire Detection Centroid ", "Description": "<b>Latitude: <\/b> 19.59761<br\/>  <b>Longitude: <\/b> -155.50296<br\/>  <b>Detection Time: <\/b> 2023-05-12 11:45 UTC<br\/>  <b>Sensor: <\/b> NOAA-20 VIIRS<br\/> <b>Confidence: <\/b> Nominal<br\/>  <b>Day\/Night: <\/b> Night<br\/> <b>Scan: <\/b> 0.51 km<br\/> <b>Track: <\/b> 0.41 km<br\/> <b>FRP: <\/b> 2.49 MW<br\/> <b>Brightness: <\/b> 298.47 K" }, "geometry": { "type": "Point", "coordinates": [ -155.50296, 19.59761, 0.0 ] } },
{ "type": "Feature", "properties": { "Name": "Fire Detection Centroid ", "Description": "<b>Latitude: <\/b> 45.23192<br\/>  <b>Longitude: <\/b> -123.16145<br\/>  <b>Detection Time: <\/b> 2023-05-12 11:34 UTC<br\/>  <b>Sensor: <\/b> NOAA-20 VIIRS<br\/> <b>Confidence: <\/b> Nominal<br\/>  <b>Day\/Night: <\/b> Night<br\/> <b>Scan: <\/b> 0.77 km<br\/> <b>Track: <\/b> 0.77 km<br\/> <b>FRP: <\/b> 2 MW<br\/> <b>Brightness: <\/b> 304.15 K" }, "geometry": { "type": "Point", "coordinates": [ -123.16145, 45.23192, 0.0 ] } },
{ "type": "Feature", "properties": { "Name": "Fire Detection Centroid ", "Description": "<b>Latitude: <\/b> 47.56837<br\/>  <b>Longitude: <\/b> -122.34106<br\/>  <b>Detection Time: <\/b> 2023-05-12 11:34 UTC<br\/>  <b>Sensor: <\/b> NOAA-20 VIIRS<br\/> <b>Confidence: <\/b> Nominal<br\/>  <b>Day\/Night: <\/b> Night<br\/> <b>Scan: <\/b> 0.69 km<br\/> <b>Track: <\/b> 0.74 km<br\/> <b>FRP: <\/b> 1.14 MW<br\/> <b>Brightness: <\/b> 298.85 K" }, "geometry": { "type": "Point", "coordinates": [ -122.34106, 47.56837, 0.0 ] } }
]
}
