{
"type": "FeatureCollection",
"crs": { "type": "name", "properties": { "name": "urn:ogc:def:crs:OGC:1.3:CRS84" } },
"features": [
{ "type": "Feature", "properties": { "Name": "Fire Detection Centroid ", "Description": "<b>Latitude: <\/b> 45.68492<br\/>  <b>Longitude: <\/b> -121.92513<br\/>  <b>Detection Time: <\/b> 2023-02-24 22:03 UTC<br\/>  <b>Sensor: <\/b> NOAA-20 VIIRS<br\/> <b>Confidence: <\/b> Nominal<br\/>  <b>Day\/Night: <\/b> Day<br\/> <b>Scan: <\/b> 0.57 km<br\/> <b>Track: <\/b> 0.69 km<br\/> <b>FRP: <\/b> 6.14 MW<br\/> <b>Brightness: <\/b> 338.82 K" }, "geometry": { "type": "Point", "coordinates": [ -121.92513, 45.68492, 0.0 ] } },
{ "type": "Feature", "properties": { "Name": "Fire Detection Centroid ", "Description": "<b>Latitude: <\/b> 46.36934<br\/>  <b>Longitude: <\/b> -120.18137<br\/>  <b>Detection Time: <\/b> 2023-02-24 22:03 UTC<br\/>  <b>Sensor: <\/b> NOAA-20 VIIRS<br\/> <b>Confidence: <\/b> Nominal<br\/>  <b>Day\/Night: <\/b> Day<br\/> <b>Scan: <\/b> 0.69 km<br\/> <b>Track: <\/b> 0.75 km<br\/> <b>FRP: <\/b> 11.2 MW<br\/> <b>Brightness: <\/b> 356.14 K" }, "geometry": { "type": "Point", "coordinates": [ -120.18137, 46.36934, 0.0 ] } },
{ "type": "Feature", "properties": { "Name": "Fire Detection Centroid ", "Description": "<b>Latitude: <\/b> 45.68596<br\/>  <b>Longitude: <\/b> -121.92413<br\/>  <b>Detection Time: <\/b> 2023-02-24 22:03 UTC<br\/>  <b>Sensor: <\/b> NOAA-20 VIIRS<br\/> <b>Confidence: <\/b> Nominal<br\/>  <b>Day\/Night: <\/b> Day<br\/> <b>Scan: <\/b> 0.57 km<br\/> <b>Track: <\/b> 0.69 km<br\/> <b>FRP: <\/b> 4.6 MW<br\/> <b>Brightness: <\/b> 327.25 K" }, "geometry": { "type": "Point", "coordinates": [ -121.92413, 45.68596, 0.0 ] } },
{ "type": "Feature", "properties": { "Name": "Fire Detection Centroid ", "Description": "<b>Latitude: <\/b> 42.57672<br\/>  <b>Longitude: <\/b> -121.90215<br\/>  <b>Detection Time: <\/b> 2023-02-24 22:01 UTC<br\/>  <b>Sensor: <\/b> NOAA-20 VIIRS<br\/> <b>Confidence: <\/b> Nominal<br\/>  <b>Day\/Night: <\/b> Day<br\/> <b>Scan: <\/b> 0.55 km<br\/> <b>Track: <\/b> 0.68 km<br\/> <b>FRP: <\/b> 3.83 MW<br\/> <b>Brightness: <\/b> 326.53 K" }, "geometry": { "type": "Point", "coordinates": [ -121.90215, 42.57672, 0.0 ] } },
{ "type": "Feature", "properties": { "Name": "Fire Detection Centroid ", "Description": "<b>Latitude: <\/b> 42.27438<br\/>  <b>Longitude: <\/b> -122.95735<br\/>  <b>Detection Time: <\/b> 2023-02-24 22:01 UTC<br\/>  <b>Sensor: <\/b> NOAA-20 VIIRS<br\/> <b>Confidence: <\/b> Nominal<br\/>  <b>Day\/Night: <\/b> Day<br\/> <b>Scan: <\/b> 0.49 km<br\/> <b>Track: <\/b> 0.65 km<br\/> <b>FRP: <\/b> 3.25 MW<br\/> <b>Brightness: <\/b> 326.19 K" }, "geometry": { "type": "Point", "coordinates": [ -122.95735, 42.27438, 0.0 ] } }
]
}
