{
"type": "FeatureCollection",
"crs": { "type": "name", "properties": { "name": "urn:ogc:def:crs:OGC:1.3:CRS84" } },
"features": [
{ "type": "Feature", "properties": { "Name": "Fire Detection Centroid ", "Description": "<b>Latitude: <\/b> 18.59664<br\/>  <b>Longitude: <\/b> -69.61576<br\/>  <b>Detection Time: <\/b> 2023-12-30 05:48 UTC<br\/>  <b>Sensor: <\/b> NOAA-20 VIIRS<br\/> <b>Confidence: <\/b> Nominal<br\/>  <b>Day\/Night: <\/b> Night<br\/> <b>Scan: <\/b> 0.5 km<br\/> <b>Track: <\/b> 0.5 km<br\/> <b>FRP: <\/b> 2.14 MW<br\/> <b>Brightness: <\/b> 325.85 K" }, "geometry": { "type": "Point", "coordinates": [ -69.61576, 18.59664, 0.0 ] } },
{ "type": "Feature", "properties": { "Name": "Fire Detection Centroid ", "Description": "<b>Latitude: <\/b> 18.1309<br\/>  <b>Longitude: <\/b> -65.80783<br\/>  <b>Detection Time: <\/b> 2023-12-30 05:48 UTC<br\/>  <b>Sensor: <\/b> NOAA-20 VIIRS<br\/> <b>Confidence: <\/b> Nominal<br\/>  <b>Day\/Night: <\/b> Night<br\/> <b>Scan: <\/b> 0.4 km<br\/> <b>Track: <\/b> 0.4 km<br\/> <b>FRP: <\/b> 0.29 MW<br\/> <b>Brightness: <\/b> 302.28 K" }, "geometry": { "type": "Point", "coordinates": [ -65.80783, 18.1309, 0.0 ] } },
{ "type": "Feature", "properties": { "Name": "Fire Detection Centroid ", "Description": "<b>Latitude: <\/b> 18.66513<br\/>  <b>Longitude: <\/b> -69.25859<br\/>  <b>Detection Time: <\/b> 2023-12-30 05:48 UTC<br\/>  <b>Sensor: <\/b> NOAA-20 VIIRS<br\/> <b>Confidence: <\/b> Nominal<br\/>  <b>Day\/Night: <\/b> Night<br\/> <b>Scan: <\/b> 0.5 km<br\/> <b>Track: <\/b> 0.5 km<br\/> <b>FRP: <\/b> 1.39 MW<br\/> <b>Brightness: <\/b> 315.08 K" }, "geometry": { "type": "Point", "coordinates": [ -69.25859, 18.66513, 0.0 ] } }
]
}
