{
"type": "FeatureCollection",
"crs": { "type": "name", "properties": { "name": "urn:ogc:def:crs:OGC:1.3:CRS84" } },
"features": [
{ "type": "Feature", "properties": { "Name": "Fire Detection Centroid ", "Description": "<b>Latitude: <\/b> 49.35598<br\/>  <b>Longitude: <\/b> -125.08891<br\/>  <b>Detection Time: <\/b> 2023-03-30 21:27 UTC<br\/>  <b>Sensor: <\/b> NOAA-20 VIIRS<br\/> <b>Confidence: <\/b> Nominal<br\/>  <b>Day\/Night: <\/b> Day<br\/> <b>Scan: <\/b> 0.49 km<br\/> <b>Track: <\/b> 0.4 km<br\/> <b>FRP: <\/b> 3.15 MW<br\/> <b>Brightness: <\/b> 329.78 K" }, "geometry": { "type": "Point", "coordinates": [ -125.08891, 49.35598, 0.0 ] } },
{ "type": "Feature", "properties": { "Name": "Fire Detection Centroid ", "Description": "<b>Latitude: <\/b> 49.37282<br\/>  <b>Longitude: <\/b> -121.64395<br\/>  <b>Detection Time: <\/b> 2023-03-30 21:27 UTC<br\/>  <b>Sensor: <\/b> NOAA-20 VIIRS<br\/> <b>Confidence: <\/b> Nominal<br\/>  <b>Day\/Night: <\/b> Day<br\/> <b>Scan: <\/b> 0.45 km<br\/> <b>Track: <\/b> 0.47 km<br\/> <b>FRP: <\/b> 9.21 MW<br\/> <b>Brightness: <\/b> 339.53 K" }, "geometry": { "type": "Point", "coordinates": [ -121.64395, 49.37282, 0.0 ] } },
{ "type": "Feature", "properties": { "Name": "Fire Detection Centroid ", "Description": "<b>Latitude: <\/b> 49.52259<br\/>  <b>Longitude: <\/b> -119.50943<br\/>  <b>Detection Time: <\/b> 2023-03-30 21:27 UTC<br\/>  <b>Sensor: <\/b> NOAA-20 VIIRS<br\/> <b>Confidence: <\/b> Nominal<br\/>  <b>Day\/Night: <\/b> Day<br\/> <b>Scan: <\/b> 0.56 km<br\/> <b>Track: <\/b> 0.52 km<br\/> <b>FRP: <\/b> 11.71 MW<br\/> <b>Brightness: <\/b> 341.17 K" }, "geometry": { "type": "Point", "coordinates": [ -119.50943, 49.52259, 0.0 ] } },
{ "type": "Feature", "properties": { "Name": "Fire Detection Centroid ", "Description": "<b>Latitude: <\/b> 49.37467<br\/>  <b>Longitude: <\/b> -121.64082<br\/>  <b>Detection Time: <\/b> 2023-03-30 21:27 UTC<br\/>  <b>Sensor: <\/b> NOAA-20 VIIRS<br\/> <b>Confidence: <\/b> Nominal<br\/>  <b>Day\/Night: <\/b> Day<br\/> <b>Scan: <\/b> 0.45 km<br\/> <b>Track: <\/b> 0.47 km<br\/> <b>FRP: <\/b> 4.16 MW<br\/> <b>Brightness: <\/b> 338.13 K" }, "geometry": { "type": "Point", "coordinates": [ -121.64082, 49.37467, 0.0 ] } },
{ "type": "Feature", "properties": { "Name": "Fire Detection Centroid ", "Description": "<b>Latitude: <\/b> 49.52257<br\/>  <b>Longitude: <\/b> -119.50983<br\/>  <b>Detection Time: <\/b> 2023-03-30 21:27 UTC<br\/>  <b>Sensor: <\/b> NOAA-20 VIIRS<br\/> <b>Confidence: <\/b> Nominal<br\/>  <b>Day\/Night: <\/b> Day<br\/> <b>Scan: <\/b> 0.56 km<br\/> <b>Track: <\/b> 0.52 km<br\/> <b>FRP: <\/b> 14.11 MW<br\/> <b>Brightness: <\/b> 341.41 K" }, "geometry": { "type": "Point", "coordinates": [ -119.50983, 49.52257, 0.0 ] } }
]
}
