{
"type": "FeatureCollection",
"crs": { "type": "name", "properties": { "name": "urn:ogc:def:crs:OGC:1.3:CRS84" } },
"features": [
{ "type": "Feature", "properties": { "Name": "Fire Detection Centroid ", "Description": "<b>Latitude: <\/b> 38.07252<br\/>  <b>Longitude: <\/b> -122.14213<br\/>  <b>Detection Time: <\/b> 2024-02-06 10:34 UTC<br\/>  <b>Sensor: <\/b> NOAA-20 VIIRS<br\/> <b>Confidence: <\/b> Nominal<br\/>  <b>Day\/Night: <\/b> Night<br\/> <b>Scan: <\/b> 0.48 km<br\/> <b>Track: <\/b> 0.48 km<br\/> <b>FRP: <\/b> 0.93 MW<br\/> <b>Brightness: <\/b> 295.69 K" }, "geometry": { "type": "Point", "coordinates": [ -122.14213, 38.07252, 0.0 ] } },
{ "type": "Feature", "properties": { "Name": "Fire Detection Centroid ", "Description": "<b>Latitude: <\/b> 38.0155<br\/>  <b>Longitude: <\/b> -122.11681<br\/>  <b>Detection Time: <\/b> 2024-02-06 10:34 UTC<br\/>  <b>Sensor: <\/b> NOAA-20 VIIRS<br\/> <b>Confidence: <\/b> Nominal<br\/>  <b>Day\/Night: <\/b> Night<br\/> <b>Scan: <\/b> 0.49 km<br\/> <b>Track: <\/b> 0.48 km<br\/> <b>FRP: <\/b> 0.86 MW<br\/> <b>Brightness: <\/b> 295.01 K" }, "geometry": { "type": "Point", "coordinates": [ -122.11681, 38.0155, 0.0 ] } },
{ "type": "Feature", "properties": { "Name": "Fire Detection Centroid ", "Description": "<b>Latitude: <\/b> 38.0178<br\/>  <b>Longitude: <\/b> -122.1629<br\/>  <b>Detection Time: <\/b> 2024-02-06 10:33 UTC<br\/>  <b>Sensor: <\/b> NOAA-20 VIIRS<br\/> <b>Confidence: <\/b> Nominal<br\/>  <b>Day\/Night: <\/b> Night<br\/> <b>Scan: <\/b> 0.5 km<br\/> <b>Track: <\/b> 0.5 km<br\/> <b>FRP: <\/b> 0.95 MW<br\/> <b>Brightness: <\/b> 295.69 K" }, "geometry": { "type": "Point", "coordinates": [ -122.1629, 38.0178, 0.0 ] } },
{ "type": "Feature", "properties": { "Name": "Fire Detection Centroid ", "Description": "<b>Latitude: <\/b> 44.0797<br\/>  <b>Longitude: <\/b> -116.94338<br\/>  <b>Detection Time: <\/b> 2024-02-06 10:32 UTC<br\/>  <b>Sensor: <\/b> NOAA-20 VIIRS<br\/> <b>Confidence: <\/b> Nominal<br\/>  <b>Day\/Night: <\/b> Night<br\/> <b>Scan: <\/b> 0.62 km<br\/> <b>Track: <\/b> 0.54 km<br\/> <b>FRP: <\/b> 2.3 MW<br\/> <b>Brightness: <\/b> 297.81 K" }, "geometry": { "type": "Point", "coordinates": [ -116.94338, 44.0797, 0.0 ] } },
{ "type": "Feature", "properties": { "Name": "Fire Detection Centroid ", "Description": "<b>Latitude: <\/b> 44.04776<br\/>  <b>Longitude: <\/b> -116.95872<br\/>  <b>Detection Time: <\/b> 2024-02-06 10:31 UTC<br\/>  <b>Sensor: <\/b> NOAA-20 VIIRS<br\/> <b>Confidence: <\/b> Nominal<br\/>  <b>Day\/Night: <\/b> Night<br\/> <b>Scan: <\/b> 0.6 km<br\/> <b>Track: <\/b> 0.5 km<br\/> <b>FRP: <\/b> 2.29 MW<br\/> <b>Brightness: <\/b> 297.81 K" }, "geometry": { "type": "Point", "coordinates": [ -116.95872, 44.04776, 0.0 ] } },
{ "type": "Feature", "properties": { "Name": "Fire Detection Centroid ", "Description": "<b>Latitude: <\/b> 46.72327<br\/>  <b>Longitude: <\/b> -110.85435<br\/>  <b>Detection Time: <\/b> 2024-02-06 10:30 UTC<br\/>  <b>Sensor: <\/b> NOAA-20 VIIRS<br\/> <b>Confidence: <\/b> Nominal<br\/>  <b>Day\/Night: <\/b> Night<br\/> <b>Scan: <\/b> 0.5 km<br\/> <b>Track: <\/b> 0.6 km<br\/> <b>FRP: <\/b> 4.56 MW<br\/> <b>Brightness: <\/b> 320.67 K" }, "geometry": { "type": "Point", "coordinates": [ -110.85435, 46.72327, 0.0 ] } },
{ "type": "Feature", "properties": { "Name": "Fire Detection Centroid ", "Description": "<b>Latitude: <\/b> 46.62021<br\/>  <b>Longitude: <\/b> -110.92833<br\/>  <b>Detection Time: <\/b> 2024-02-06 10:30 UTC<br\/>  <b>Sensor: <\/b> NOAA-20 VIIRS<br\/> <b>Confidence: <\/b> Nominal<br\/>  <b>Day\/Night: <\/b> Night<br\/> <b>Scan: <\/b> 0.49 km<br\/> <b>Track: <\/b> 0.65 km<br\/> <b>FRP: <\/b> 4.56 MW<br\/> <b>Brightness: <\/b> 320.67 K" }, "geometry": { "type": "Point", "coordinates": [ -110.92833, 46.62021, 0.0 ] } }
]
}
