{
"type": "FeatureCollection",
"crs": { "type": "name", "properties": { "name": "urn:ogc:def:crs:OGC:1.3:CRS84" } },
"features": [
{ "type": "Feature", "properties": { "Name": "Fire Detection Centroid ", "Description": "<b>Latitude: <\/b> 19.40367<br\/>  <b>Longitude: <\/b> -155.28949<br\/>  <b>Detection Time: <\/b> 2023-08-15 12:02 UTC<br\/>  <b>Sensor: <\/b> NOAA-20 VIIRS<br\/> <b>Confidence: <\/b> Nominal<br\/>  <b>Day\/Night: <\/b> Night<br\/> <b>Scan: <\/b> 0.39 km<br\/> <b>Track: <\/b> 0.36 km<br\/> <b>FRP: <\/b> 2.55 MW<br\/> <b>Brightness: <\/b> 307.38 K" }, "geometry": { "type": "Point", "coordinates": [ -155.28949, 19.40367, 0.0 ] } },
{ "type": "Feature", "properties": { "Name": "Fire Detection Centroid ", "Description": "<b>Latitude: <\/b> 19.40577<br\/>  <b>Longitude: <\/b> -155.28151<br\/>  <b>Detection Time: <\/b> 2023-08-15 12:02 UTC<br\/>  <b>Sensor: <\/b> NOAA-20 VIIRS<br\/> <b>Confidence: <\/b> Nominal<br\/>  <b>Day\/Night: <\/b> Night<br\/> <b>Scan: <\/b> 0.39 km<br\/> <b>Track: <\/b> 0.36 km<br\/> <b>FRP: <\/b> 1.94 MW<br\/> <b>Brightness: <\/b> 311.2 K" }, "geometry": { "type": "Point", "coordinates": [ -155.28151, 19.40577, 0.0 ] } },
{ "type": "Feature", "properties": { "Name": "Fire Detection Centroid ", "Description": "<b>Latitude: <\/b> 19.40638<br\/>  <b>Longitude: <\/b> -155.28522<br\/>  <b>Detection Time: <\/b> 2023-08-15 12:02 UTC<br\/>  <b>Sensor: <\/b> NOAA-20 VIIRS<br\/> <b>Confidence: <\/b> Nominal<br\/>  <b>Day\/Night: <\/b> Night<br\/> <b>Scan: <\/b> 0.39 km<br\/> <b>Track: <\/b> 0.36 km<br\/> <b>FRP: <\/b> 2.24 MW<br\/> <b>Brightness: <\/b> 305.65 K" }, "geometry": { "type": "Point", "coordinates": [ -155.28522, 19.40638, 0.0 ] } },
{ "type": "Feature", "properties": { "Name": "Fire Detection Centroid ", "Description": "<b>Latitude: <\/b> 19.40698<br\/>  <b>Longitude: <\/b> -155.28891<br\/>  <b>Detection Time: <\/b> 2023-08-15 12:02 UTC<br\/>  <b>Sensor: <\/b> NOAA-20 VIIRS<br\/> <b>Confidence: <\/b> Nominal<br\/>  <b>Day\/Night: <\/b> Night<br\/> <b>Scan: <\/b> 0.39 km<br\/> <b>Track: <\/b> 0.36 km<br\/> <b>FRP: <\/b> 2.24 MW<br\/> <b>Brightness: <\/b> 305.34 K" }, "geometry": { "type": "Point", "coordinates": [ -155.28891, 19.40698, 0.0 ] } },
{ "type": "Feature", "properties": { "Name": "Fire Detection Centroid ", "Description": "<b>Latitude: <\/b> 19.40849<br\/>  <b>Longitude: <\/b> -155.27724<br\/>  <b>Detection Time: <\/b> 2023-08-15 12:02 UTC<br\/>  <b>Sensor: <\/b> NOAA-20 VIIRS<br\/> <b>Confidence: <\/b> Nominal<br\/>  <b>Day\/Night: <\/b> Night<br\/> <b>Scan: <\/b> 0.39 km<br\/> <b>Track: <\/b> 0.36 km<br\/> <b>FRP: <\/b> 1.94 MW<br\/> <b>Brightness: <\/b> 308.33 K" }, "geometry": { "type": "Point", "coordinates": [ -155.27724, 19.40849, 0.0 ] } },
{ "type": "Feature", "properties": { "Name": "Fire Detection Centroid ", "Description": "<b>Latitude: <\/b> 19.40909<br\/>  <b>Longitude: <\/b> -155.28093<br\/>  <b>Detection Time: <\/b> 2023-08-15 12:02 UTC<br\/>  <b>Sensor: <\/b> NOAA-20 VIIRS<br\/> <b>Confidence: <\/b> Nominal<br\/>  <b>Day\/Night: <\/b> Night<br\/> <b>Scan: <\/b> 0.39 km<br\/> <b>Track: <\/b> 0.36 km<br\/> <b>FRP: <\/b> 1.94 MW<br\/> <b>Brightness: <\/b> 311.69 K" }, "geometry": { "type": "Point", "coordinates": [ -155.28093, 19.40909, 0.0 ] } },
{ "type": "Feature", "properties": { "Name": "Fire Detection Centroid ", "Description": "<b>Latitude: <\/b> 19.4124<br\/>  <b>Longitude: <\/b> -155.28032<br\/>  <b>Detection Time: <\/b> 2023-08-15 12:02 UTC<br\/>  <b>Sensor: <\/b> NOAA-20 VIIRS<br\/> <b>Confidence: <\/b> Nominal<br\/>  <b>Day\/Night: <\/b> Night<br\/> <b>Scan: <\/b> 0.39 km<br\/> <b>Track: <\/b> 0.36 km<br\/> <b>FRP: <\/b> 2.9 MW<br\/> <b>Brightness: <\/b> 312.46 K" }, "geometry": { "type": "Point", "coordinates": [ -155.28032, 19.4124, 0.0 ] } },
{ "type": "Feature", "properties": { "Name": "Fire Detection Centroid ", "Description": "<b>Latitude: <\/b> 19.413<br\/>  <b>Longitude: <\/b> -155.28403<br\/>  <b>Detection Time: <\/b> 2023-08-15 12:02 UTC<br\/>  <b>Sensor: <\/b> NOAA-20 VIIRS<br\/> <b>Confidence: <\/b> Nominal<br\/>  <b>Day\/Night: <\/b> Night<br\/> <b>Scan: <\/b> 0.39 km<br\/> <b>Track: <\/b> 0.36 km<br\/> <b>FRP: <\/b> 2.01 MW<br\/> <b>Brightness: <\/b> 308.26 K" }, "geometry": { "type": "Point", "coordinates": [ -155.28403, 19.413, 0.0 ] } }
]
}
