{
"type": "FeatureCollection",
"crs": { "type": "name", "properties": { "name": "urn:ogc:def:crs:OGC:1.3:CRS84" } },
"features": [
{ "type": "Feature", "properties": { "Name": "Fire Detection Centroid ", "Description": "<b>Latitude: <\/b> 19.40684<br\/>  <b>Longitude: <\/b> -155.28119<br\/>  <b>Detection Time: <\/b> 2023-08-18 00:16 UTC<br\/>  <b>Sensor: <\/b> NOAA-20 VIIRS<br\/> <b>Confidence: <\/b> Nominal<br\/>  <b>Day\/Night: <\/b> Day<br\/> <b>Scan: <\/b> 0.44 km<br\/> <b>Track: <\/b> 0.62 km<br\/> <b>FRP: <\/b> 9.35 MW<br\/> <b>Brightness: <\/b> 333.22 K" }, "geometry": { "type": "Point", "coordinates": [ -155.28119, 19.40684, 0.0 ] } }
]
}
