{
"type": "FeatureCollection",
"crs": { "type": "name", "properties": { "name": "urn:ogc:def:crs:OGC:1.3:CRS84" } },
"features": [
{ "type": "Feature", "properties": { "Name": "Fire Detection Centroid ", "Description": "<b>Latitude: <\/b> 18.53454<br\/>  <b>Longitude: <\/b> -69.14866<br\/>  <b>Detection Time: <\/b> 2024-01-04 05:54 UTC<br\/>  <b>Sensor: <\/b> NOAA-20 VIIRS<br\/> <b>Confidence: <\/b> Nominal<br\/>  <b>Day\/Night: <\/b> Night<br\/> <b>Scan: <\/b> 0.6 km<br\/> <b>Track: <\/b> 0.4 km<br\/> <b>FRP: <\/b> 0.77 MW<br\/> <b>Brightness: <\/b> 300.31 K" }, "geometry": { "type": "Point", "coordinates": [ -69.14866, 18.53454, 0.0 ] } },
{ "type": "Feature", "properties": { "Name": "Fire Detection Centroid ", "Description": "<b>Latitude: <\/b> 18.00854<br\/>  <b>Longitude: <\/b> -66.65572<br\/>  <b>Detection Time: <\/b> 2024-01-04 05:54 UTC<br\/>  <b>Sensor: <\/b> NOAA-20 VIIRS<br\/> <b>Confidence: <\/b> Nominal<br\/>  <b>Day\/Night: <\/b> Night<br\/> <b>Scan: <\/b> 0.4 km<br\/> <b>Track: <\/b> 0.4 km<br\/> <b>FRP: <\/b> 0.42 MW<br\/> <b>Brightness: <\/b> 305.65 K" }, "geometry": { "type": "Point", "coordinates": [ -66.65572, 18.00854, 0.0 ] } }
]
}
