{
"type": "FeatureCollection",
"crs": { "type": "name", "properties": { "name": "urn:ogc:def:crs:OGC:1.3:CRS84" } },
"features": [
{ "type": "Feature", "properties": { "Name": "Fire Detection Centroid ", "Description": "<b>Latitude: <\/b> 48.85663<br\/>  <b>Longitude: <\/b> -72.26649<br\/>  <b>Detection Time: <\/b> 2024-06-03 06:30 UTC<br\/>  <b>Sensor: <\/b> NOAA-20 VIIRS<br\/> <b>Confidence: <\/b> Nominal<br\/>  <b>Day\/Night: <\/b> Night<br\/> <b>Scan: <\/b> 0.5 km<br\/> <b>Track: <\/b> 0.4 km<br\/> <b>FRP: <\/b> 1.12 MW<br\/> <b>Brightness: <\/b> 306.76 K" }, "geometry": { "type": "Point", "coordinates": [ -72.26649, 48.85663, 0.0 ] } },
{ "type": "Feature", "properties": { "Name": "Fire Detection Centroid ", "Description": "<b>Latitude: <\/b> 48.42672<br\/>  <b>Longitude: <\/b> -71.1761<br\/>  <b>Detection Time: <\/b> 2024-06-03 06:30 UTC<br\/>  <b>Sensor: <\/b> NOAA-20 VIIRS<br\/> <b>Confidence: <\/b> Nominal<br\/>  <b>Day\/Night: <\/b> Night<br\/> <b>Scan: <\/b> 0.5 km<br\/> <b>Track: <\/b> 0.4 km<br\/> <b>FRP: <\/b> 0.87 MW<br\/> <b>Brightness: <\/b> 295.01 K" }, "geometry": { "type": "Point", "coordinates": [ -71.1761, 48.42672, 0.0 ] } }
]
}
