{
"type": "FeatureCollection",
"crs": { "type": "name", "properties": { "name": "urn:ogc:def:crs:OGC:1.3:CRS84" } },
"features": [
{ "type": "Feature", "properties": { "Name": "Fire Detection Centroid ", "Description": "<b>Latitude: <\/b> 43.54219<br\/>  <b>Longitude: <\/b> -116.87341<br\/>  <b>Detection Time: <\/b> 2024-03-30 21:46 UTC<br\/>  <b>Sensor: <\/b> NOAA-20 VIIRS<br\/> <b>Confidence: <\/b> Nominal<br\/>  <b>Day\/Night: <\/b> Day<br\/> <b>Scan: <\/b> 0.61 km<br\/> <b>Track: <\/b> 0.71 km<br\/> <b>FRP: <\/b> 5.05 MW<br\/> <b>Brightness: <\/b> 349.8 K" }, "geometry": { "type": "Point", "coordinates": [ -116.87341, 43.54219, 0.0 ] } },
{ "type": "Feature", "properties": { "Name": "Fire Detection Centroid ", "Description": "<b>Latitude: <\/b> 42.14503<br\/>  <b>Longitude: <\/b> -121.23217<br\/>  <b>Detection Time: <\/b> 2024-03-30 21:46 UTC<br\/>  <b>Sensor: <\/b> NOAA-20 VIIRS<br\/> <b>Confidence: <\/b> Nominal<br\/>  <b>Day\/Night: <\/b> Day<br\/> <b>Scan: <\/b> 0.35 km<br\/> <b>Track: <\/b> 0.57 km<br\/> <b>FRP: <\/b> 3.84 MW<br\/> <b>Brightness: <\/b> 348.75 K" }, "geometry": { "type": "Point", "coordinates": [ -121.23217, 42.14503, 0.0 ] } },
{ "type": "Feature", "properties": { "Name": "Fire Detection Centroid ", "Description": "<b>Latitude: <\/b> 43.49707<br\/>  <b>Longitude: <\/b> -116.87605<br\/>  <b>Detection Time: <\/b> 2024-03-30 21:45 UTC<br\/>  <b>Sensor: <\/b> NOAA-20 VIIRS<br\/> <b>Confidence: <\/b> Nominal<br\/>  <b>Day\/Night: <\/b> Day<br\/> <b>Scan: <\/b> 0.6 km<br\/> <b>Track: <\/b> 0.7 km<br\/> <b>FRP: <\/b> 5.04 MW<br\/> <b>Brightness: <\/b> 349.8 K" }, "geometry": { "type": "Point", "coordinates": [ -116.87605, 43.49707, 0.0 ] } },
{ "type": "Feature", "properties": { "Name": "Fire Detection Centroid ", "Description": "<b>Latitude: <\/b> 42.1193<br\/>  <b>Longitude: <\/b> -121.23003<br\/>  <b>Detection Time: <\/b> 2024-03-30 21:45 UTC<br\/>  <b>Sensor: <\/b> NOAA-20 VIIRS<br\/> <b>Confidence: <\/b> Nominal<br\/>  <b>Day\/Night: <\/b> Day<br\/> <b>Scan: <\/b> 0.3 km<br\/> <b>Track: <\/b> 0.6 km<br\/> <b>FRP: <\/b> 4.06 MW<br\/> <b>Brightness: <\/b> 348.75 K" }, "geometry": { "type": "Point", "coordinates": [ -121.23003, 42.1193, 0.0 ] } },
{ "type": "Feature", "properties": { "Name": "Fire Detection Centroid ", "Description": "<b>Latitude: <\/b> 32.29438<br\/>  <b>Longitude: <\/b> -114.75996<br\/>  <b>Detection Time: <\/b> 2024-03-30 21:42 UTC<br\/>  <b>Sensor: <\/b> NOAA-20 VIIRS<br\/> <b>Confidence: <\/b> Nominal<br\/>  <b>Day\/Night: <\/b> Day<br\/> <b>Scan: <\/b> 0.7 km<br\/> <b>Track: <\/b> 0.7 km<br\/> <b>FRP: <\/b> 2.68 MW<br\/> <b>Brightness: <\/b> 330.36 K" }, "geometry": { "type": "Point", "coordinates": [ -114.75996, 32.29438, 0.0 ] } },
{ "type": "Feature", "properties": { "Name": "Fire Detection Centroid ", "Description": "<b>Latitude: <\/b> 32.39614<br\/>  <b>Longitude: <\/b> -114.76311<br\/>  <b>Detection Time: <\/b> 2024-03-30 21:42 UTC<br\/>  <b>Sensor: <\/b> NOAA-20 VIIRS<br\/> <b>Confidence: <\/b> Nominal<br\/>  <b>Day\/Night: <\/b> Day<br\/> <b>Scan: <\/b> 0.69 km<br\/> <b>Track: <\/b> 0.74 km<br\/> <b>FRP: <\/b> 2.69 MW<br\/> <b>Brightness: <\/b> 330.36 K" }, "geometry": { "type": "Point", "coordinates": [ -114.76311, 32.39614, 0.0 ] } }
]
}
