{
"type": "FeatureCollection",
"crs": { "type": "name", "properties": { "name": "urn:ogc:def:crs:OGC:1.3:CRS84" } },
"features": [
{ "type": "Feature", "properties": { "Name": "Fire Detection Centroid ", "Description": "<b>Latitude: <\/b> 32.58635<br\/>  <b>Longitude: <\/b> -114.5815<br\/>  <b>Detection Time: <\/b> 2022-12-23 21:40 UTC<br\/>  <b>Sensor: <\/b> NOAA-20 VIIRS<br\/> <b>Confidence: <\/b> Nominal<br\/>  <b>Day\/Night: <\/b> Day<br\/> <b>Scan: <\/b> 0.7 km<br\/> <b>Track: <\/b> 0.7 km<br\/> <b>FRP: <\/b> 4 MW<br\/> <b>Brightness: <\/b> 333.67 K" }, "geometry": { "type": "Point", "coordinates": [ -114.5815, 32.58635, 0.0 ] } },
{ "type": "Feature", "properties": { "Name": "Fire Detection Centroid ", "Description": "<b>Latitude: <\/b> 32.42668<br\/>  <b>Longitude: <\/b> -115.01256<br\/>  <b>Detection Time: <\/b> 2022-12-23 21:40 UTC<br\/>  <b>Sensor: <\/b> NOAA-20 VIIRS<br\/> <b>Confidence: <\/b> Nominal<br\/>  <b>Day\/Night: <\/b> Day<br\/> <b>Scan: <\/b> 0.6 km<br\/> <b>Track: <\/b> 0.7 km<br\/> <b>FRP: <\/b> 4.93 MW<br\/> <b>Brightness: <\/b> 333.35 K" }, "geometry": { "type": "Point", "coordinates": [ -115.01256, 32.42668, 0.0 ] } },
{ "type": "Feature", "properties": { "Name": "Fire Detection Centroid ", "Description": "<b>Latitude: <\/b> 32.58685<br\/>  <b>Longitude: <\/b> -114.57909<br\/>  <b>Detection Time: <\/b> 2022-12-23 21:40 UTC<br\/>  <b>Sensor: <\/b> NOAA-20 VIIRS<br\/> <b>Confidence: <\/b> Nominal<br\/>  <b>Day\/Night: <\/b> Day<br\/> <b>Scan: <\/b> 0.66 km<br\/> <b>Track: <\/b> 0.73 km<br\/> <b>FRP: <\/b> 4 MW<br\/> <b>Brightness: <\/b> 333.67 K" }, "geometry": { "type": "Point", "coordinates": [ -114.57909, 32.58685, 0.0 ] } },
{ "type": "Feature", "properties": { "Name": "Fire Detection Centroid ", "Description": "<b>Latitude: <\/b> 32.42668<br\/>  <b>Longitude: <\/b> -115.01256<br\/>  <b>Detection Time: <\/b> 2022-12-23 21:40 UTC<br\/>  <b>Sensor: <\/b> NOAA-20 VIIRS<br\/> <b>Confidence: <\/b> Nominal<br\/>  <b>Day\/Night: <\/b> Day<br\/> <b>Scan: <\/b> 0.6 km<br\/> <b>Track: <\/b> 0.7 km<br\/> <b>FRP: <\/b> 4.93 MW<br\/> <b>Brightness: <\/b> 333.35 K" }, "geometry": { "type": "Point", "coordinates": [ -115.01256, 32.42668, 0.0 ] } },
{ "type": "Feature", "properties": { "Name": "Fire Detection Centroid ", "Description": "<b>Latitude: <\/b> 32.42717<br\/>  <b>Longitude: <\/b> -115.01031<br\/>  <b>Detection Time: <\/b> 2022-12-23 21:40 UTC<br\/>  <b>Sensor: <\/b> NOAA-20 VIIRS<br\/> <b>Confidence: <\/b> Nominal<br\/>  <b>Day\/Night: <\/b> Day<br\/> <b>Scan: <\/b> 0.62 km<br\/> <b>Track: <\/b> 0.72 km<br\/> <b>FRP: <\/b> 4.94 MW<br\/> <b>Brightness: <\/b> 333.35 K" }, "geometry": { "type": "Point", "coordinates": [ -115.01031, 32.42717, 0.0 ] } }
]
}
