{
"type": "FeatureCollection",
"crs": { "type": "name", "properties": { "name": "urn:ogc:def:crs:OGC:1.3:CRS84" } },
"features": [
{ "type": "Feature", "properties": { "Name": "Fire Detection Centroid ", "Description": "<b>Latitude: <\/b> 18.44117<br\/>  <b>Longitude: <\/b> -71.25304<br\/>  <b>Detection Time: <\/b> 2023-05-05 05:30 UTC<br\/>  <b>Sensor: <\/b> NOAA-20 VIIRS<br\/> <b>Confidence: <\/b> Nominal<br\/>  <b>Day\/Night: <\/b> Night<br\/> <b>Scan: <\/b> 0.6 km<br\/> <b>Track: <\/b> 0.7 km<br\/> <b>FRP: <\/b> 2.61 MW<br\/> <b>Brightness: <\/b> 317.51 K" }, "geometry": { "type": "Point", "coordinates": [ -71.25304, 18.44117, 0.0 ] } },
{ "type": "Feature", "properties": { "Name": "Fire Detection Centroid ", "Description": "<b>Latitude: <\/b> 18.44461<br\/>  <b>Longitude: <\/b> -71.25226<br\/>  <b>Detection Time: <\/b> 2023-05-05 05:30 UTC<br\/>  <b>Sensor: <\/b> NOAA-20 VIIRS<br\/> <b>Confidence: <\/b> Nominal<br\/>  <b>Day\/Night: <\/b> Night<br\/> <b>Scan: <\/b> 0.6 km<br\/> <b>Track: <\/b> 0.7 km<br\/> <b>FRP: <\/b> 2.65 MW<br\/> <b>Brightness: <\/b> 314.15 K" }, "geometry": { "type": "Point", "coordinates": [ -71.25226, 18.44461, 0.0 ] } },
{ "type": "Feature", "properties": { "Name": "Fire Detection Centroid ", "Description": "<b>Latitude: <\/b> 18.98927<br\/>  <b>Longitude: <\/b> -69.54171<br\/>  <b>Detection Time: <\/b> 2023-05-05 05:29 UTC<br\/>  <b>Sensor: <\/b> NOAA-20 VIIRS<br\/> <b>Confidence: <\/b> Nominal<br\/>  <b>Day\/Night: <\/b> Night<br\/> <b>Scan: <\/b> 0.5 km<br\/> <b>Track: <\/b> 0.7 km<br\/> <b>FRP: <\/b> 0.78 MW<br\/> <b>Brightness: <\/b> 301.97 K" }, "geometry": { "type": "Point", "coordinates": [ -69.54171, 18.98927, 0.0 ] } },
{ "type": "Feature", "properties": { "Name": "Fire Detection Centroid ", "Description": "<b>Latitude: <\/b> 19.03604<br\/>  <b>Longitude: <\/b> -69.70809<br\/>  <b>Detection Time: <\/b> 2023-05-05 05:29 UTC<br\/>  <b>Sensor: <\/b> NOAA-20 VIIRS<br\/> <b>Confidence: <\/b> Nominal<br\/>  <b>Day\/Night: <\/b> Night<br\/> <b>Scan: <\/b> 0.5 km<br\/> <b>Track: <\/b> 0.7 km<br\/> <b>FRP: <\/b> 1.48 MW<br\/> <b>Brightness: <\/b> 306.52 K" }, "geometry": { "type": "Point", "coordinates": [ -69.70809, 19.03604, 0.0 ] } },
{ "type": "Feature", "properties": { "Name": "Fire Detection Centroid ", "Description": "<b>Latitude: <\/b> 19.0364<br\/>  <b>Longitude: <\/b> -69.71069<br\/>  <b>Detection Time: <\/b> 2023-05-05 05:29 UTC<br\/>  <b>Sensor: <\/b> NOAA-20 VIIRS<br\/> <b>Confidence: <\/b> Nominal<br\/>  <b>Day\/Night: <\/b> Night<br\/> <b>Scan: <\/b> 0.5 km<br\/> <b>Track: <\/b> 0.7 km<br\/> <b>FRP: <\/b> 1.77 MW<br\/> <b>Brightness: <\/b> 317.17 K" }, "geometry": { "type": "Point", "coordinates": [ -69.71069, 19.0364, 0.0 ] } },
{ "type": "Feature", "properties": { "Name": "Fire Detection Centroid ", "Description": "<b>Latitude: <\/b> 18.92764<br\/>  <b>Longitude: <\/b> -70.3541<br\/>  <b>Detection Time: <\/b> 2023-05-05 05:29 UTC<br\/>  <b>Sensor: <\/b> NOAA-20 VIIRS<br\/> <b>Confidence: <\/b> Nominal<br\/>  <b>Day\/Night: <\/b> Night<br\/> <b>Scan: <\/b> 0.6 km<br\/> <b>Track: <\/b> 0.7 km<br\/> <b>FRP: <\/b> 5.75 MW<br\/> <b>Brightness: <\/b> 343.62 K" }, "geometry": { "type": "Point", "coordinates": [ -70.3541, 18.92764, 0.0 ] } },
{ "type": "Feature", "properties": { "Name": "Fire Detection Centroid ", "Description": "<b>Latitude: <\/b> 19.03647<br\/>  <b>Longitude: <\/b> -69.71298<br\/>  <b>Detection Time: <\/b> 2023-05-05 05:29 UTC<br\/>  <b>Sensor: <\/b> NOAA-20 VIIRS<br\/> <b>Confidence: <\/b> Nominal<br\/>  <b>Day\/Night: <\/b> Night<br\/> <b>Scan: <\/b> 0.5 km<br\/> <b>Track: <\/b> 0.7 km<br\/> <b>FRP: <\/b> 1.38 MW<br\/> <b>Brightness: <\/b> 304.22 K" }, "geometry": { "type": "Point", "coordinates": [ -69.71298, 19.03647, 0.0 ] } }
]
}
