{
"type": "FeatureCollection",
"crs": { "type": "name", "properties": { "name": "urn:ogc:def:crs:OGC:1.3:CRS84" } },
"features": [
{ "type": "Feature", "properties": { "Name": "Fire Detection Centroid ", "Description": "<b>Latitude: <\/b> 39.19504<br\/>  <b>Longitude: <\/b> -121.05119<br\/>  <b>Detection Time: <\/b> 2024-01-04 10:52 UTC<br\/>  <b>Sensor: <\/b> NOAA-20 VIIRS<br\/> <b>Confidence: <\/b> Nominal<br\/>  <b>Day\/Night: <\/b> Night<br\/> <b>Scan: <\/b> 0.5 km<br\/> <b>Track: <\/b> 0.6 km<br\/> <b>FRP: <\/b> 1.25 MW<br\/> <b>Brightness: <\/b> 298.71 K" }, "geometry": { "type": "Point", "coordinates": [ -121.05119, 39.19504, 0.0 ] } },
{ "type": "Feature", "properties": { "Name": "Fire Detection Centroid ", "Description": "<b>Latitude: <\/b> 37.63449<br\/>  <b>Longitude: <\/b> -120.97496<br\/>  <b>Detection Time: <\/b> 2024-01-04 10:52 UTC<br\/>  <b>Sensor: <\/b> NOAA-20 VIIRS<br\/> <b>Confidence: <\/b> Nominal<br\/>  <b>Day\/Night: <\/b> Night<br\/> <b>Scan: <\/b> 0.5 km<br\/> <b>Track: <\/b> 0.7 km<br\/> <b>FRP: <\/b> 3.47 MW<br\/> <b>Brightness: <\/b> 313.23 K" }, "geometry": { "type": "Point", "coordinates": [ -120.97496, 37.63449, 0.0 ] } },
{ "type": "Feature", "properties": { "Name": "Fire Detection Centroid ", "Description": "<b>Latitude: <\/b> 37.63292<br\/>  <b>Longitude: <\/b> -120.96952<br\/>  <b>Detection Time: <\/b> 2024-01-04 10:52 UTC<br\/>  <b>Sensor: <\/b> NOAA-20 VIIRS<br\/> <b>Confidence: <\/b> Nominal<br\/>  <b>Day\/Night: <\/b> Night<br\/> <b>Scan: <\/b> 0.5 km<br\/> <b>Track: <\/b> 0.7 km<br\/> <b>FRP: <\/b> 3.47 MW<br\/> <b>Brightness: <\/b> 333.82 K" }, "geometry": { "type": "Point", "coordinates": [ -120.96952, 37.63292, 0.0 ] } },
{ "type": "Feature", "properties": { "Name": "Fire Detection Centroid ", "Description": "<b>Latitude: <\/b> 39.19381<br\/>  <b>Longitude: <\/b> -121.04692<br\/>  <b>Detection Time: <\/b> 2024-01-04 10:52 UTC<br\/>  <b>Sensor: <\/b> NOAA-20 VIIRS<br\/> <b>Confidence: <\/b> Nominal<br\/>  <b>Day\/Night: <\/b> Night<br\/> <b>Scan: <\/b> 0.5 km<br\/> <b>Track: <\/b> 0.6 km<br\/> <b>FRP: <\/b> 1.25 MW<br\/> <b>Brightness: <\/b> 309.04 K" }, "geometry": { "type": "Point", "coordinates": [ -121.04692, 39.19381, 0.0 ] } },
{ "type": "Feature", "properties": { "Name": "Fire Detection Centroid ", "Description": "<b>Latitude: <\/b> 37.63402<br\/>  <b>Longitude: <\/b> -120.97742<br\/>  <b>Detection Time: <\/b> 2024-01-04 10:51 UTC<br\/>  <b>Sensor: <\/b> NOAA-20 VIIRS<br\/> <b>Confidence: <\/b> Nominal<br\/>  <b>Day\/Night: <\/b> Night<br\/> <b>Scan: <\/b> 0.51 km<br\/> <b>Track: <\/b> 0.66 km<br\/> <b>FRP: <\/b> 3.48 MW<br\/> <b>Brightness: <\/b> 313.23 K" }, "geometry": { "type": "Point", "coordinates": [ -120.97742, 37.63402, 0.0 ] } },
{ "type": "Feature", "properties": { "Name": "Fire Detection Centroid ", "Description": "<b>Latitude: <\/b> 39.19447<br\/>  <b>Longitude: <\/b> -121.05315<br\/>  <b>Detection Time: <\/b> 2024-01-04 10:51 UTC<br\/>  <b>Sensor: <\/b> NOAA-20 VIIRS<br\/> <b>Confidence: <\/b> Nominal<br\/>  <b>Day\/Night: <\/b> Night<br\/> <b>Scan: <\/b> 0.45 km<br\/> <b>Track: <\/b> 0.63 km<br\/> <b>FRP: <\/b> 1.25 MW<br\/> <b>Brightness: <\/b> 298.71 K" }, "geometry": { "type": "Point", "coordinates": [ -121.05315, 39.19447, 0.0 ] } },
{ "type": "Feature", "properties": { "Name": "Fire Detection Centroid ", "Description": "<b>Latitude: <\/b> 39.19322<br\/>  <b>Longitude: <\/b> -121.04884<br\/>  <b>Detection Time: <\/b> 2024-01-04 10:51 UTC<br\/>  <b>Sensor: <\/b> NOAA-20 VIIRS<br\/> <b>Confidence: <\/b> Nominal<br\/>  <b>Day\/Night: <\/b> Night<br\/> <b>Scan: <\/b> 0.45 km<br\/> <b>Track: <\/b> 0.63 km<br\/> <b>FRP: <\/b> 1.25 MW<br\/> <b>Brightness: <\/b> 309.04 K" }, "geometry": { "type": "Point", "coordinates": [ -121.04884, 39.19322, 0.0 ] } },
{ "type": "Feature", "properties": { "Name": "Fire Detection Centroid ", "Description": "<b>Latitude: <\/b> 37.63245<br\/>  <b>Longitude: <\/b> -120.97201<br\/>  <b>Detection Time: <\/b> 2024-01-04 10:51 UTC<br\/>  <b>Sensor: <\/b> NOAA-20 VIIRS<br\/> <b>Confidence: <\/b> Nominal<br\/>  <b>Day\/Night: <\/b> Night<br\/> <b>Scan: <\/b> 0.51 km<br\/> <b>Track: <\/b> 0.66 km<br\/> <b>FRP: <\/b> 3.48 MW<br\/> <b>Brightness: <\/b> 333.82 K" }, "geometry": { "type": "Point", "coordinates": [ -120.97201, 37.63245, 0.0 ] } }
]
}
