{
"type": "FeatureCollection",
"crs": { "type": "name", "properties": { "name": "urn:ogc:def:crs:OGC:1.3:CRS84" } },
"features": [
{ "type": "Feature", "properties": { "Name": "Fire Detection Centroid ", "Description": "<b>Latitude: <\/b> 19.40829<br\/>  <b>Longitude: <\/b> -155.27318<br\/>  <b>Detection Time: <\/b> 2023-10-18 12:02 UTC<br\/>  <b>Sensor: <\/b> NOAA-20 VIIRS<br\/> <b>Confidence: <\/b> Nominal<br\/>  <b>Day\/Night: <\/b> Night<br\/> <b>Scan: <\/b> 0.39 km<br\/> <b>Track: <\/b> 0.36 km<br\/> <b>FRP: <\/b> 2.08 MW<br\/> <b>Brightness: <\/b> 309.46 K" }, "geometry": { "type": "Point", "coordinates": [ -155.27318, 19.40829, 0.0 ] } },
{ "type": "Feature", "properties": { "Name": "Fire Detection Centroid ", "Description": "<b>Latitude: <\/b> 19.40735<br\/>  <b>Longitude: <\/b> -155.28842<br\/>  <b>Detection Time: <\/b> 2023-10-18 12:02 UTC<br\/>  <b>Sensor: <\/b> NOAA-20 VIIRS<br\/> <b>Confidence: <\/b> Nominal<br\/>  <b>Day\/Night: <\/b> Night<br\/> <b>Scan: <\/b> 0.39 km<br\/> <b>Track: <\/b> 0.36 km<br\/> <b>FRP: <\/b> 1.89 MW<br\/> <b>Brightness: <\/b> 311.86 K" }, "geometry": { "type": "Point", "coordinates": [ -155.28842, 19.40735, 0.0 ] } },
{ "type": "Feature", "properties": { "Name": "Fire Detection Centroid ", "Description": "<b>Latitude: <\/b> 19.40676<br\/>  <b>Longitude: <\/b> -155.28476<br\/>  <b>Detection Time: <\/b> 2023-10-18 12:02 UTC<br\/>  <b>Sensor: <\/b> NOAA-20 VIIRS<br\/> <b>Confidence: <\/b> Nominal<br\/>  <b>Day\/Night: <\/b> Night<br\/> <b>Scan: <\/b> 0.39 km<br\/> <b>Track: <\/b> 0.36 km<br\/> <b>FRP: <\/b> 1.89 MW<br\/> <b>Brightness: <\/b> 302.49 K" }, "geometry": { "type": "Point", "coordinates": [ -155.28476, 19.40676, 0.0 ] } },
{ "type": "Feature", "properties": { "Name": "Fire Detection Centroid ", "Description": "<b>Latitude: <\/b> 19.41218<br\/>  <b>Longitude: <\/b> -155.27625<br\/>  <b>Detection Time: <\/b> 2023-10-18 12:02 UTC<br\/>  <b>Sensor: <\/b> NOAA-20 VIIRS<br\/> <b>Confidence: <\/b> Nominal<br\/>  <b>Day\/Night: <\/b> Night<br\/> <b>Scan: <\/b> 0.39 km<br\/> <b>Track: <\/b> 0.36 km<br\/> <b>FRP: <\/b> 3.55 MW<br\/> <b>Brightness: <\/b> 309.38 K" }, "geometry": { "type": "Point", "coordinates": [ -155.27625, 19.41218, 0.0 ] } },
{ "type": "Feature", "properties": { "Name": "Fire Detection Centroid ", "Description": "<b>Latitude: <\/b> 19.41159<br\/>  <b>Longitude: <\/b> -155.27258<br\/>  <b>Detection Time: <\/b> 2023-10-18 12:02 UTC<br\/>  <b>Sensor: <\/b> NOAA-20 VIIRS<br\/> <b>Confidence: <\/b> Nominal<br\/>  <b>Day\/Night: <\/b> Night<br\/> <b>Scan: <\/b> 0.39 km<br\/> <b>Track: <\/b> 0.36 km<br\/> <b>FRP: <\/b> 2.42 MW<br\/> <b>Brightness: <\/b> 305.41 K" }, "geometry": { "type": "Point", "coordinates": [ -155.27258, 19.41159, 0.0 ] } },
{ "type": "Feature", "properties": { "Name": "Fire Detection Centroid ", "Description": "<b>Latitude: <\/b> 19.40888<br\/>  <b>Longitude: <\/b> -155.27684<br\/>  <b>Detection Time: <\/b> 2023-10-18 12:02 UTC<br\/>  <b>Sensor: <\/b> NOAA-20 VIIRS<br\/> <b>Confidence: <\/b> Nominal<br\/>  <b>Day\/Night: <\/b> Night<br\/> <b>Scan: <\/b> 0.39 km<br\/> <b>Track: <\/b> 0.36 km<br\/> <b>FRP: <\/b> 3.79 MW<br\/> <b>Brightness: <\/b> 314.83 K" }, "geometry": { "type": "Point", "coordinates": [ -155.27684, 19.40888, 0.0 ] } }
]
}
