{
"type": "FeatureCollection",
"crs": { "type": "name", "properties": { "name": "urn:ogc:def:crs:OGC:1.3:CRS84" } },
"features": [
{ "type": "Feature", "properties": { "Name": "Fire Detection Centroid ", "Description": "<b>Latitude: <\/b> 19.40536<br\/>  <b>Longitude: <\/b> -155.28134<br\/>  <b>Detection Time: <\/b> 2024-05-01 12:04 UTC<br\/>  <b>Sensor: <\/b> NOAA-20 VIIRS<br\/> <b>Confidence: <\/b> Nominal<br\/>  <b>Day\/Night: <\/b> Night<br\/> <b>Scan: <\/b> 0.39 km<br\/> <b>Track: <\/b> 0.36 km<br\/> <b>FRP: <\/b> 2.87 MW<br\/> <b>Brightness: <\/b> 305.87 K" }, "geometry": { "type": "Point", "coordinates": [ -155.28134, 19.40536, 0.0 ] } },
{ "type": "Feature", "properties": { "Name": "Fire Detection Centroid ", "Description": "<b>Latitude: <\/b> 19.32897<br\/>  <b>Longitude: <\/b> -155.29483<br\/>  <b>Detection Time: <\/b> 2024-05-01 12:03 UTC<br\/>  <b>Sensor: <\/b> NOAA-20 VIIRS<br\/> <b>Confidence: <\/b> Nominal<br\/>  <b>Day\/Night: <\/b> Night<br\/> <b>Scan: <\/b> 0.4 km<br\/> <b>Track: <\/b> 0.4 km<br\/> <b>FRP: <\/b> 2.86 MW<br\/> <b>Brightness: <\/b> 305.87 K" }, "geometry": { "type": "Point", "coordinates": [ -155.29483, 19.32897, 0.0 ] } }
]
}
