{
"type": "FeatureCollection",
"crs": { "type": "name", "properties": { "name": "urn:ogc:def:crs:OGC:1.3:CRS84" } },
"features": [
{ "type": "Feature", "properties": { "Name": "Fire Detection Centroid ", "Description": "<b>Latitude: <\/b> 21.97489<br\/>  <b>Longitude: <\/b> -159.68265<br\/>  <b>Detection Time: <\/b> 2024-06-13 23:07 UTC<br\/>  <b>Sensor: <\/b> NOAA-20 VIIRS<br\/> <b>Confidence: <\/b> Nominal<br\/>  <b>Day\/Night: <\/b> Day<br\/> <b>Scan: <\/b> 0.4 km<br\/> <b>Track: <\/b> 0.6 km<br\/> <b>FRP: <\/b> 9.57 MW<br\/> <b>Brightness: <\/b> 354.55 K" }, "geometry": { "type": "Point", "coordinates": [ -159.68265, 21.97489, 0.0 ] } },
{ "type": "Feature", "properties": { "Name": "Fire Detection Centroid ", "Description": "<b>Latitude: <\/b> 21.97558<br\/>  <b>Longitude: <\/b> -159.68286<br\/>  <b>Detection Time: <\/b> 2024-06-13 23:07 UTC<br\/>  <b>Sensor: <\/b> NOAA-20 VIIRS<br\/> <b>Confidence: <\/b> High<br\/>  <b>Day\/Night: <\/b> Day<br\/> <b>Scan: <\/b> 0.4 km<br\/> <b>Track: <\/b> 0.6 km<br\/> <b>FRP: <\/b> 7.31 MW<br\/> <b>Brightness: <\/b> 367 K" }, "geometry": { "type": "Point", "coordinates": [ -159.68286, 21.97558, 0.0 ] } },
{ "type": "Feature", "properties": { "Name": "Fire Detection Centroid ", "Description": "<b>Latitude: <\/b> 21.97383<br\/>  <b>Longitude: <\/b> -159.68732<br\/>  <b>Detection Time: <\/b> 2024-06-13 23:07 UTC<br\/>  <b>Sensor: <\/b> NOAA-20 VIIRS<br\/> <b>Confidence: <\/b> Nominal<br\/>  <b>Day\/Night: <\/b> Day<br\/> <b>Scan: <\/b> 0.42 km<br\/> <b>Track: <\/b> 0.61 km<br\/> <b>FRP: <\/b> 5.63 MW<br\/> <b>Brightness: <\/b> 328.99 K" }, "geometry": { "type": "Point", "coordinates": [ -159.68732, 21.97383, 0.0 ] } },
{ "type": "Feature", "properties": { "Name": "Fire Detection Centroid ", "Description": "<b>Latitude: <\/b> 21.97488<br\/>  <b>Longitude: <\/b> -159.68266<br\/>  <b>Detection Time: <\/b> 2024-06-13 23:07 UTC<br\/>  <b>Sensor: <\/b> NOAA-20 VIIRS<br\/> <b>Confidence: <\/b> Nominal<br\/>  <b>Day\/Night: <\/b> Day<br\/> <b>Scan: <\/b> 0.41 km<br\/> <b>Track: <\/b> 0.61 km<br\/> <b>FRP: <\/b> 9.58 MW<br\/> <b>Brightness: <\/b> 354.55 K" }, "geometry": { "type": "Point", "coordinates": [ -159.68266, 21.97488, 0.0 ] } },
{ "type": "Feature", "properties": { "Name": "Fire Detection Centroid ", "Description": "<b>Latitude: <\/b> 21.97557<br\/>  <b>Longitude: <\/b> -159.68288<br\/>  <b>Detection Time: <\/b> 2024-06-13 23:07 UTC<br\/>  <b>Sensor: <\/b> NOAA-20 VIIRS<br\/> <b>Confidence: <\/b> High<br\/>  <b>Day\/Night: <\/b> Day<br\/> <b>Scan: <\/b> 0.42 km<br\/> <b>Track: <\/b> 0.61 km<br\/> <b>FRP: <\/b> 7.32 MW<br\/> <b>Brightness: <\/b> 367 K" }, "geometry": { "type": "Point", "coordinates": [ -159.68288, 21.97557, 0.0 ] } },
{ "type": "Feature", "properties": { "Name": "Fire Detection Centroid ", "Description": "<b>Latitude: <\/b> 21.97383<br\/>  <b>Longitude: <\/b> -159.6873<br\/>  <b>Detection Time: <\/b> 2024-06-13 23:07 UTC<br\/>  <b>Sensor: <\/b> NOAA-20 VIIRS<br\/> <b>Confidence: <\/b> Nominal<br\/>  <b>Day\/Night: <\/b> Day<br\/> <b>Scan: <\/b> 0.4 km<br\/> <b>Track: <\/b> 0.6 km<br\/> <b>FRP: <\/b> 5.63 MW<br\/> <b>Brightness: <\/b> 328.99 K" }, "geometry": { "type": "Point", "coordinates": [ -159.6873, 21.97383, 0.0 ] } }
]
}
