{
"type": "FeatureCollection",
"crs": { "type": "name", "properties": { "name": "urn:ogc:def:crs:OGC:1.3:CRS84" } },
"features": [
{ "type": "Feature", "properties": { "Name": "Fire Detection Centroid ", "Description": "<b>Latitude: <\/b> 20.01846<br\/>  <b>Longitude: <\/b> -155.77547<br\/>  <b>Detection Time: <\/b> 2024-01-14 00:22 UTC<br\/>  <b>Sensor: <\/b> NOAA-20 VIIRS<br\/> <b>Confidence: <\/b> Nominal<br\/>  <b>Day\/Night: <\/b> Day<br\/> <b>Scan: <\/b> 0.51 km<br\/> <b>Track: <\/b> 0.66 km<br\/> <b>FRP: <\/b> 4.14 MW<br\/> <b>Brightness: <\/b> 330.34 K" }, "geometry": { "type": "Point", "coordinates": [ -155.77547, 20.01846, 0.0 ] } }
]
}
