{
"type": "FeatureCollection",
"crs": { "type": "name", "properties": { "name": "urn:ogc:def:crs:OGC:1.3:CRS84" } },
"features": [
{ "type": "Feature", "properties": { "Name": "Fire Detection Centroid ", "Description": "<b>Latitude: <\/b> 19.40894<br\/>  <b>Longitude: <\/b> -155.28383<br\/>  <b>Detection Time: <\/b> 2022-10-20 23:20 UTC<br\/>  <b>Sensor: <\/b> NOAA-20 VIIRS<br\/> <b>Confidence: <\/b> Nominal<br\/>  <b>Day\/Night: <\/b> Day<br\/> <b>Scan: <\/b> 0.48 km<br\/> <b>Track: <\/b> 0.4 km<br\/> <b>FRP: <\/b> 5.01 MW<br\/> <b>Brightness: <\/b> 334.45 K" }, "geometry": { "type": "Point", "coordinates": [ -155.28383, 19.40894, 0.0 ] } },
{ "type": "Feature", "properties": { "Name": "Fire Detection Centroid ", "Description": "<b>Latitude: <\/b> 19.40529<br\/>  <b>Longitude: <\/b> -155.28317<br\/>  <b>Detection Time: <\/b> 2022-10-20 23:20 UTC<br\/>  <b>Sensor: <\/b> NOAA-20 VIIRS<br\/> <b>Confidence: <\/b> Nominal<br\/>  <b>Day\/Night: <\/b> Day<br\/> <b>Scan: <\/b> 0.48 km<br\/> <b>Track: <\/b> 0.4 km<br\/> <b>FRP: <\/b> 5.01 MW<br\/> <b>Brightness: <\/b> 349.86 K" }, "geometry": { "type": "Point", "coordinates": [ -155.28317, 19.40529, 0.0 ] } },
{ "type": "Feature", "properties": { "Name": "Fire Detection Centroid ", "Description": "<b>Latitude: <\/b> 19.40607<br\/>  <b>Longitude: <\/b> -155.27869<br\/>  <b>Detection Time: <\/b> 2022-10-20 23:20 UTC<br\/>  <b>Sensor: <\/b> NOAA-20 VIIRS<br\/> <b>Confidence: <\/b> Nominal<br\/>  <b>Day\/Night: <\/b> Day<br\/> <b>Scan: <\/b> 0.48 km<br\/> <b>Track: <\/b> 0.4 km<br\/> <b>FRP: <\/b> 5.01 MW<br\/> <b>Brightness: <\/b> 331.16 K" }, "geometry": { "type": "Point", "coordinates": [ -155.27869, 19.40607, 0.0 ] } },
{ "type": "Feature", "properties": { "Name": "Fire Detection Centroid ", "Description": "<b>Latitude: <\/b> 19.40166<br\/>  <b>Longitude: <\/b> -155.28247<br\/>  <b>Detection Time: <\/b> 2022-10-20 23:20 UTC<br\/>  <b>Sensor: <\/b> NOAA-20 VIIRS<br\/> <b>Confidence: <\/b> Nominal<br\/>  <b>Day\/Night: <\/b> Day<br\/> <b>Scan: <\/b> 0.48 km<br\/> <b>Track: <\/b> 0.4 km<br\/> <b>FRP: <\/b> 5.5 MW<br\/> <b>Brightness: <\/b> 330.89 K" }, "geometry": { "type": "Point", "coordinates": [ -155.28247, 19.40166, 0.0 ] } },
{ "type": "Feature", "properties": { "Name": "Fire Detection Centroid ", "Description": "<b>Latitude: <\/b> 19.40848<br\/>  <b>Longitude: <\/b> -155.28432<br\/>  <b>Detection Time: <\/b> 2022-10-20 23:19 UTC<br\/>  <b>Sensor: <\/b> NOAA-20 VIIRS<br\/> <b>Confidence: <\/b> Nominal<br\/>  <b>Day\/Night: <\/b> Day<br\/> <b>Scan: <\/b> 0.5 km<br\/> <b>Track: <\/b> 0.4 km<br\/> <b>FRP: <\/b> 5.01 MW<br\/> <b>Brightness: <\/b> 334.45 K" }, "geometry": { "type": "Point", "coordinates": [ -155.28432, 19.40848, 0.0 ] } },
{ "type": "Feature", "properties": { "Name": "Fire Detection Centroid ", "Description": "<b>Latitude: <\/b> 19.40121<br\/>  <b>Longitude: <\/b> -155.28294<br\/>  <b>Detection Time: <\/b> 2022-10-20 23:19 UTC<br\/>  <b>Sensor: <\/b> NOAA-20 VIIRS<br\/> <b>Confidence: <\/b> Nominal<br\/>  <b>Day\/Night: <\/b> Day<br\/> <b>Scan: <\/b> 0.5 km<br\/> <b>Track: <\/b> 0.4 km<br\/> <b>FRP: <\/b> 5.49 MW<br\/> <b>Brightness: <\/b> 330.89 K" }, "geometry": { "type": "Point", "coordinates": [ -155.28294, 19.40121, 0.0 ] } },
{ "type": "Feature", "properties": { "Name": "Fire Detection Centroid ", "Description": "<b>Latitude: <\/b> 19.40562<br\/>  <b>Longitude: <\/b> -155.27917<br\/>  <b>Detection Time: <\/b> 2022-10-20 23:19 UTC<br\/>  <b>Sensor: <\/b> NOAA-20 VIIRS<br\/> <b>Confidence: <\/b> Nominal<br\/>  <b>Day\/Night: <\/b> Day<br\/> <b>Scan: <\/b> 0.5 km<br\/> <b>Track: <\/b> 0.4 km<br\/> <b>FRP: <\/b> 5.01 MW<br\/> <b>Brightness: <\/b> 331.16 K" }, "geometry": { "type": "Point", "coordinates": [ -155.27917, 19.40562, 0.0 ] } },
{ "type": "Feature", "properties": { "Name": "Fire Detection Centroid ", "Description": "<b>Latitude: <\/b> 19.40483<br\/>  <b>Longitude: <\/b> -155.28366<br\/>  <b>Detection Time: <\/b> 2022-10-20 23:19 UTC<br\/>  <b>Sensor: <\/b> NOAA-20 VIIRS<br\/> <b>Confidence: <\/b> Nominal<br\/>  <b>Day\/Night: <\/b> Day<br\/> <b>Scan: <\/b> 0.5 km<br\/> <b>Track: <\/b> 0.4 km<br\/> <b>FRP: <\/b> 5.01 MW<br\/> <b>Brightness: <\/b> 349.86 K" }, "geometry": { "type": "Point", "coordinates": [ -155.28366, 19.40483, 0.0 ] } }
]
}
