{
"type": "FeatureCollection",
"crs": { "type": "name", "properties": { "name": "urn:ogc:def:crs:OGC:1.3:CRS84" } },
"features": [
{ "type": "Feature", "properties": { "Name": "Fire Detection Centroid ", "Description": "<b>Latitude: <\/b> 18.9262<br\/>  <b>Longitude: <\/b> -70.35831<br\/>  <b>Detection Time: <\/b> 2023-09-05 05:23 UTC<br\/>  <b>Sensor: <\/b> NOAA-20 VIIRS<br\/> <b>Confidence: <\/b> Nominal<br\/>  <b>Day\/Night: <\/b> Night<br\/> <b>Scan: <\/b> 0.7 km<br\/> <b>Track: <\/b> 0.8 km<br\/> <b>FRP: <\/b> 3.72 MW<br\/> <b>Brightness: <\/b> 314.1 K" }, "geometry": { "type": "Point", "coordinates": [ -70.35831, 18.9262, 0.0 ] } },
{ "type": "Feature", "properties": { "Name": "Fire Detection Centroid ", "Description": "<b>Latitude: <\/b> 18.9256<br\/>  <b>Longitude: <\/b> -70.3511<br\/>  <b>Detection Time: <\/b> 2023-09-05 05:23 UTC<br\/>  <b>Sensor: <\/b> NOAA-20 VIIRS<br\/> <b>Confidence: <\/b> Nominal<br\/>  <b>Day\/Night: <\/b> Night<br\/> <b>Scan: <\/b> 0.7 km<br\/> <b>Track: <\/b> 0.8 km<br\/> <b>FRP: <\/b> 3.82 MW<br\/> <b>Brightness: <\/b> 310.61 K" }, "geometry": { "type": "Point", "coordinates": [ -70.3511, 18.9256, 0.0 ] } }
]
}
