{
"type": "FeatureCollection",
"crs": { "type": "name", "properties": { "name": "urn:ogc:def:crs:OGC:1.3:CRS84" } },
"features": [
{ "type": "Feature", "properties": { "Name": "Fire Detection Centroid ", "Description": "<b>Latitude: <\/b> 47.56508<br\/>  <b>Longitude: <\/b> -122.34549<br\/>  <b>Detection Time: <\/b> 2024-02-03 11:27 UTC<br\/>  <b>Sensor: <\/b> NOAA-20 VIIRS<br\/> <b>Confidence: <\/b> Nominal<br\/>  <b>Day\/Night: <\/b> Night<br\/> <b>Scan: <\/b> 0.59 km<br\/> <b>Track: <\/b> 0.7 km<br\/> <b>FRP: <\/b> 0.84 MW<br\/> <b>Brightness: <\/b> 295.6 K" }, "geometry": { "type": "Point", "coordinates": [ -122.34549, 47.56508, 0.0 ] } }
]
}
