{
"type": "FeatureCollection",
"crs": { "type": "name", "properties": { "name": "urn:ogc:def:crs:OGC:1.3:CRS84" } },
"features": [
{ "type": "Feature", "properties": { "Name": "Fire Detection Centroid ", "Description": "<b>Latitude: <\/b> 18.90175<br\/>  <b>Longitude: <\/b> -72.39404<br\/>  <b>Detection Time: <\/b> 2024-02-27 05:42 UTC<br\/>  <b>Sensor: <\/b> NOAA-20 VIIRS<br\/> <b>Confidence: <\/b> Nominal<br\/>  <b>Day\/Night: <\/b> Night<br\/> <b>Scan: <\/b> 0.5 km<br\/> <b>Track: <\/b> 0.6 km<br\/> <b>FRP: <\/b> 0.96 MW<br\/> <b>Brightness: <\/b> 302.4 K" }, "geometry": { "type": "Point", "coordinates": [ -72.39404, 18.90175, 0.0 ] } },
{ "type": "Feature", "properties": { "Name": "Fire Detection Centroid ", "Description": "<b>Latitude: <\/b> 18.69895<br\/>  <b>Longitude: <\/b> -69.76458<br\/>  <b>Detection Time: <\/b> 2024-02-27 05:42 UTC<br\/>  <b>Sensor: <\/b> NOAA-20 VIIRS<br\/> <b>Confidence: <\/b> Nominal<br\/>  <b>Day\/Night: <\/b> Night<br\/> <b>Scan: <\/b> 0.3 km<br\/> <b>Track: <\/b> 0.5 km<br\/> <b>FRP: <\/b> 0.93 MW<br\/> <b>Brightness: <\/b> 309.02 K" }, "geometry": { "type": "Point", "coordinates": [ -69.76458, 18.69895, 0.0 ] } },
{ "type": "Feature", "properties": { "Name": "Fire Detection Centroid ", "Description": "<b>Latitude: <\/b> 18.90867<br\/>  <b>Longitude: <\/b> -72.40321<br\/>  <b>Detection Time: <\/b> 2024-02-27 05:42 UTC<br\/>  <b>Sensor: <\/b> NOAA-20 VIIRS<br\/> <b>Confidence: <\/b> Nominal<br\/>  <b>Day\/Night: <\/b> Night<br\/> <b>Scan: <\/b> 0.5 km<br\/> <b>Track: <\/b> 0.6 km<br\/> <b>FRP: <\/b> 1.57 MW<br\/> <b>Brightness: <\/b> 302.82 K" }, "geometry": { "type": "Point", "coordinates": [ -72.40321, 18.90867, 0.0 ] } },
{ "type": "Feature", "properties": { "Name": "Fire Detection Centroid ", "Description": "<b>Latitude: <\/b> 18.90964<br\/>  <b>Longitude: <\/b> -69.73402<br\/>  <b>Detection Time: <\/b> 2024-02-27 05:42 UTC<br\/>  <b>Sensor: <\/b> NOAA-20 VIIRS<br\/> <b>Confidence: <\/b> Nominal<br\/>  <b>Day\/Night: <\/b> Night<br\/> <b>Scan: <\/b> 0.3 km<br\/> <b>Track: <\/b> 0.5 km<br\/> <b>FRP: <\/b> 1.13 MW<br\/> <b>Brightness: <\/b> 314.19 K" }, "geometry": { "type": "Point", "coordinates": [ -69.73402, 18.90964, 0.0 ] } }
]
}
