{
"type": "FeatureCollection",
"crs": { "type": "name", "properties": { "name": "urn:ogc:def:crs:OGC:1.3:CRS84" } },
"features": [
{ "type": "Feature", "properties": { "Name": "Fire Detection Centroid ", "Description": "<b>Latitude: <\/b> 18.40951<br\/>  <b>Longitude: <\/b> -69.63317<br\/>  <b>Detection Time: <\/b> 2023-08-09 05:30 UTC<br\/>  <b>Sensor: <\/b> NOAA-20 VIIRS<br\/> <b>Confidence: <\/b> Nominal<br\/>  <b>Day\/Night: <\/b> Night<br\/> <b>Scan: <\/b> 0.5 km<br\/> <b>Track: <\/b> 0.7 km<br\/> <b>FRP: <\/b> 2.75 MW<br\/> <b>Brightness: <\/b> 309.46 K" }, "geometry": { "type": "Point", "coordinates": [ -69.63317, 18.40951, 0.0 ] } },
{ "type": "Feature", "properties": { "Name": "Fire Detection Centroid ", "Description": "<b>Latitude: <\/b> 18.40906<br\/>  <b>Longitude: <\/b> -69.62853<br\/>  <b>Detection Time: <\/b> 2023-08-09 05:30 UTC<br\/>  <b>Sensor: <\/b> NOAA-20 VIIRS<br\/> <b>Confidence: <\/b> Nominal<br\/>  <b>Day\/Night: <\/b> Night<br\/> <b>Scan: <\/b> 0.5 km<br\/> <b>Track: <\/b> 0.7 km<br\/> <b>FRP: <\/b> 2.75 MW<br\/> <b>Brightness: <\/b> 333.29 K" }, "geometry": { "type": "Point", "coordinates": [ -69.62853, 18.40906, 0.0 ] } }
]
}
