{
"type": "FeatureCollection",
"crs": { "type": "name", "properties": { "name": "urn:ogc:def:crs:OGC:1.3:CRS84" } },
"features": [
{ "type": "Feature", "properties": { "Name": "Fire Detection Centroid ", "Description": "<b>Latitude: <\/b> 45.40324<br\/>  <b>Longitude: <\/b> -64.19596<br\/>  <b>Detection Time: <\/b> 2023-12-16 16:28 UTC<br\/>  <b>Sensor: <\/b> NOAA-20 VIIRS<br\/> <b>Confidence: <\/b> Nominal<br\/>  <b>Day\/Night: <\/b> Day<br\/> <b>Scan: <\/b> 0.5 km<br\/> <b>Track: <\/b> 0.5 km<br\/> <b>FRP: <\/b> 9.19 MW<br\/> <b>Brightness: <\/b> 339.27 K" }, "geometry": { "type": "Point", "coordinates": [ -64.19596, 45.40324, 0.0 ] } },
{ "type": "Feature", "properties": { "Name": "Fire Detection Centroid ", "Description": "<b>Latitude: <\/b> 45.4049<br\/>  <b>Longitude: <\/b> -64.19509<br\/>  <b>Detection Time: <\/b> 2023-12-16 16:28 UTC<br\/>  <b>Sensor: <\/b> NOAA-20 VIIRS<br\/> <b>Confidence: <\/b> Nominal<br\/>  <b>Day\/Night: <\/b> Day<br\/> <b>Scan: <\/b> 0.5 km<br\/> <b>Track: <\/b> 0.5 km<br\/> <b>FRP: <\/b> 11.19 MW<br\/> <b>Brightness: <\/b> 350.38 K" }, "geometry": { "type": "Point", "coordinates": [ -64.19509, 45.4049, 0.0 ] } },
{ "type": "Feature", "properties": { "Name": "Fire Detection Centroid ", "Description": "<b>Latitude: <\/b> 19.40508<br\/>  <b>Longitude: <\/b> -155.28316<br\/>  <b>Detection Time: <\/b> 2023-12-16 11:55 UTC<br\/>  <b>Sensor: <\/b> NOAA-20 VIIRS<br\/> <b>Confidence: <\/b> Nominal<br\/>  <b>Day\/Night: <\/b> Night<br\/> <b>Scan: <\/b> 0.39 km<br\/> <b>Track: <\/b> 0.36 km<br\/> <b>FRP: <\/b> 3.62 MW<br\/> <b>Brightness: <\/b> 308.13 K" }, "geometry": { "type": "Point", "coordinates": [ -155.28316, 19.40508, 0.0 ] } }
]
}
