{
"type": "FeatureCollection",
"crs": { "type": "name", "properties": { "name": "urn:ogc:def:crs:OGC:1.3:CRS84" } },
"features": [
{ "type": "Feature", "properties": { "Name": "Fire Detection Centroid ", "Description": "<b>Latitude: <\/b> 19.40364<br\/>  <b>Longitude: <\/b> -155.28772<br\/>  <b>Detection Time: <\/b> 2023-12-30 12:33 UTC<br\/>  <b>Sensor: <\/b> NOAA-20 VIIRS<br\/> <b>Confidence: <\/b> Nominal<br\/>  <b>Day\/Night: <\/b> Night<br\/> <b>Scan: <\/b> 0.33 km<br\/> <b>Track: <\/b> 0.55 km<br\/> <b>FRP: <\/b> 2.2 MW<br\/> <b>Brightness: <\/b> 301.01 K" }, "geometry": { "type": "Point", "coordinates": [ -155.28772, 19.40364, 0.0 ] } }
]
}
