{
"type": "FeatureCollection",
"crs": { "type": "name", "properties": { "name": "urn:ogc:def:crs:OGC:1.3:CRS84" } },
"features": [
{ "type": "Feature", "properties": { "Name": "Fire Detection Centroid ", "Description": "<b>Latitude: <\/b> 19.60151<br\/>  <b>Longitude: <\/b> -71.0134<br\/>  <b>Detection Time: <\/b> 2023-12-18 06:13 UTC<br\/>  <b>Sensor: <\/b> NOAA-20 VIIRS<br\/> <b>Confidence: <\/b> Nominal<br\/>  <b>Day\/Night: <\/b> Night<br\/> <b>Scan: <\/b> 0.4 km<br\/> <b>Track: <\/b> 0.4 km<br\/> <b>FRP: <\/b> 1.55 MW<br\/> <b>Brightness: <\/b> 317.65 K" }, "geometry": { "type": "Point", "coordinates": [ -71.0134, 19.60151, 0.0 ] } },
{ "type": "Feature", "properties": { "Name": "Fire Detection Centroid ", "Description": "<b>Latitude: <\/b> 25.8617<br\/>  <b>Longitude: <\/b> -80.34646<br\/>  <b>Detection Time: <\/b> 2023-12-18 06:11 UTC<br\/>  <b>Sensor: <\/b> NOAA-20 VIIRS<br\/> <b>Confidence: <\/b> Nominal<br\/>  <b>Day\/Night: <\/b> Night<br\/> <b>Scan: <\/b> 0.6 km<br\/> <b>Track: <\/b> 0.7 km<br\/> <b>FRP: <\/b> 0.22 MW<br\/> <b>Brightness: <\/b> 297.45 K" }, "geometry": { "type": "Point", "coordinates": [ -80.34646, 25.8617, 0.0 ] } },
{ "type": "Feature", "properties": { "Name": "Fire Detection Centroid ", "Description": "<b>Latitude: <\/b> 26.28121<br\/>  <b>Longitude: <\/b> -80.15719<br\/>  <b>Detection Time: <\/b> 2023-12-18 06:11 UTC<br\/>  <b>Sensor: <\/b> NOAA-20 VIIRS<br\/> <b>Confidence: <\/b> Nominal<br\/>  <b>Day\/Night: <\/b> Night<br\/> <b>Scan: <\/b> 0.6 km<br\/> <b>Track: <\/b> 0.7 km<br\/> <b>FRP: <\/b> 0.41 MW<br\/> <b>Brightness: <\/b> 298.62 K" }, "geometry": { "type": "Point", "coordinates": [ -80.15719, 26.28121, 0.0 ] } },
{ "type": "Feature", "properties": { "Name": "Fire Detection Centroid ", "Description": "<b>Latitude: <\/b> 36.71566<br\/>  <b>Longitude: <\/b> -80.30579<br\/>  <b>Detection Time: <\/b> 2023-12-18 06:08 UTC<br\/>  <b>Sensor: <\/b> NOAA-20 VIIRS<br\/> <b>Confidence: <\/b> Nominal<br\/>  <b>Day\/Night: <\/b> Night<br\/> <b>Scan: <\/b> 0.7 km<br\/> <b>Track: <\/b> 0.7 km<br\/> <b>FRP: <\/b> 1.16 MW<br\/> <b>Brightness: <\/b> 298.29 K" }, "geometry": { "type": "Point", "coordinates": [ -80.30579, 36.71566, 0.0 ] } }
]
}
