{
"type": "FeatureCollection",
"crs": { "type": "name", "properties": { "name": "urn:ogc:def:crs:OGC:1.3:CRS84" } },
"features": [
{ "type": "Feature", "properties": { "Name": "Fire Detection Centroid ", "Description": "<b>Latitude: <\/b> 18.92624<br\/>  <b>Longitude: <\/b> -70.35572<br\/>  <b>Detection Time: <\/b> 2022-11-19 06:00 UTC<br\/>  <b>Sensor: <\/b> NOAA-20 VIIRS<br\/> <b>Confidence: <\/b> Nominal<br\/>  <b>Day\/Night: <\/b> Night<br\/> <b>Scan: <\/b> 0.5 km<br\/> <b>Track: <\/b> 0.4 km<br\/> <b>FRP: <\/b> 1.6 MW<br\/> <b>Brightness: <\/b> 310.72 K" }, "geometry": { "type": "Point", "coordinates": [ -70.35572, 18.92624, 0.0 ] } },
{ "type": "Feature", "properties": { "Name": "Fire Detection Centroid ", "Description": "<b>Latitude: <\/b> 18.93011<br\/>  <b>Longitude: <\/b> -70.35534<br\/>  <b>Detection Time: <\/b> 2022-11-19 06:00 UTC<br\/>  <b>Sensor: <\/b> NOAA-20 VIIRS<br\/> <b>Confidence: <\/b> Nominal<br\/>  <b>Day\/Night: <\/b> Night<br\/> <b>Scan: <\/b> 0.5 km<br\/> <b>Track: <\/b> 0.4 km<br\/> <b>FRP: <\/b> 18.13 MW<br\/> <b>Brightness: <\/b> 332.1 K" }, "geometry": { "type": "Point", "coordinates": [ -70.35534, 18.93011, 0.0 ] } },
{ "type": "Feature", "properties": { "Name": "Fire Detection Centroid ", "Description": "<b>Latitude: <\/b> 18.92942<br\/>  <b>Longitude: <\/b> -70.35011<br\/>  <b>Detection Time: <\/b> 2022-11-19 06:00 UTC<br\/>  <b>Sensor: <\/b> NOAA-20 VIIRS<br\/> <b>Confidence: <\/b> Nominal<br\/>  <b>Day\/Night: <\/b> Night<br\/> <b>Scan: <\/b> 0.5 km<br\/> <b>Track: <\/b> 0.4 km<br\/> <b>FRP: <\/b> 8.68 MW<br\/> <b>Brightness: <\/b> 308.73 K" }, "geometry": { "type": "Point", "coordinates": [ -70.35011, 18.92942, 0.0 ] } },
{ "type": "Feature", "properties": { "Name": "Fire Detection Centroid ", "Description": "<b>Latitude: <\/b> 20.67377<br\/>  <b>Longitude: <\/b> -74.9521<br\/>  <b>Detection Time: <\/b> 2022-11-19 05:59 UTC<br\/>  <b>Sensor: <\/b> NOAA-20 VIIRS<br\/> <b>Confidence: <\/b> Nominal<br\/>  <b>Day\/Night: <\/b> Night<br\/> <b>Scan: <\/b> 0.4 km<br\/> <b>Track: <\/b> 0.6 km<br\/> <b>FRP: <\/b> 5 MW<br\/> <b>Brightness: <\/b> 348.53 K" }, "geometry": { "type": "Point", "coordinates": [ -74.9521, 20.67377, 0.0 ] } },
{ "type": "Feature", "properties": { "Name": "Fire Detection Centroid ", "Description": "<b>Latitude: <\/b> 41.52549<br\/>  <b>Longitude: <\/b> -75.05315<br\/>  <b>Detection Time: <\/b> 2022-11-19 05:54 UTC<br\/>  <b>Sensor: <\/b> NOAA-20 VIIRS<br\/> <b>Confidence: <\/b> Nominal<br\/>  <b>Day\/Night: <\/b> Night<br\/> <b>Scan: <\/b> 0.6 km<br\/> <b>Track: <\/b> 0.7 km<br\/> <b>FRP: <\/b> 1.02 MW<br\/> <b>Brightness: <\/b> 303.83 K" }, "geometry": { "type": "Point", "coordinates": [ -75.05315, 41.52549, 0.0 ] } },
{ "type": "Feature", "properties": { "Name": "Fire Detection Centroid ", "Description": "<b>Latitude: <\/b> 40.15499<br\/>  <b>Longitude: <\/b> -74.77402<br\/>  <b>Detection Time: <\/b> 2022-11-19 05:54 UTC<br\/>  <b>Sensor: <\/b> NOAA-20 VIIRS<br\/> <b>Confidence: <\/b> Nominal<br\/>  <b>Day\/Night: <\/b> Night<br\/> <b>Scan: <\/b> 0.5 km<br\/> <b>Track: <\/b> 0.7 km<br\/> <b>FRP: <\/b> 0.74 MW<br\/> <b>Brightness: <\/b> 296.84 K" }, "geometry": { "type": "Point", "coordinates": [ -74.77402, 40.15499, 0.0 ] } },
{ "type": "Feature", "properties": { "Name": "Fire Detection Centroid ", "Description": "<b>Latitude: <\/b> 39.941<br\/>  <b>Longitude: <\/b> -76.81631<br\/>  <b>Detection Time: <\/b> 2022-11-19 05:54 UTC<br\/>  <b>Sensor: <\/b> NOAA-20 VIIRS<br\/> <b>Confidence: <\/b> Nominal<br\/>  <b>Day\/Night: <\/b> Night<br\/> <b>Scan: <\/b> 0.7 km<br\/> <b>Track: <\/b> 0.7 km<br\/> <b>FRP: <\/b> 1.91 MW<br\/> <b>Brightness: <\/b> 297.52 K" }, "geometry": { "type": "Point", "coordinates": [ -76.81631, 39.941, 0.0 ] } },
{ "type": "Feature", "properties": { "Name": "Fire Detection Centroid ", "Description": "<b>Latitude: <\/b> 39.94116<br\/>  <b>Longitude: <\/b> -76.8197<br\/>  <b>Detection Time: <\/b> 2022-11-19 05:54 UTC<br\/>  <b>Sensor: <\/b> NOAA-20 VIIRS<br\/> <b>Confidence: <\/b> Nominal<br\/>  <b>Day\/Night: <\/b> Night<br\/> <b>Scan: <\/b> 0.7 km<br\/> <b>Track: <\/b> 0.7 km<br\/> <b>FRP: <\/b> 1.51 MW<br\/> <b>Brightness: <\/b> 302.05 K" }, "geometry": { "type": "Point", "coordinates": [ -76.8197, 39.94116, 0.0 ] } },
{ "type": "Feature", "properties": { "Name": "Fire Detection Centroid ", "Description": "<b>Latitude: <\/b> 45.28194<br\/>  <b>Longitude: <\/b> -66.0183<br\/>  <b>Detection Time: <\/b> 2022-11-19 05:52 UTC<br\/>  <b>Sensor: <\/b> NOAA-20 VIIRS<br\/> <b>Confidence: <\/b> Nominal<br\/>  <b>Day\/Night: <\/b> Night<br\/> <b>Scan: <\/b> 0.4 km<br\/> <b>Track: <\/b> 0.5 km<br\/> <b>FRP: <\/b> 1.65 MW<br\/> <b>Brightness: <\/b> 300.78 K" }, "geometry": { "type": "Point", "coordinates": [ -66.0183, 45.28194, 0.0 ] } }
]
}
