{
"type": "FeatureCollection",
"crs": { "type": "name", "properties": { "name": "urn:ogc:def:crs:OGC:1.3:CRS84" } },
"features": [
{ "type": "Feature", "properties": { "Name": "Fire Detection Centroid ", "Description": "<b>Latitude: <\/b> 40.60865<br\/>  <b>Longitude: <\/b> -75.31812<br\/>  <b>Detection Time: <\/b> 2023-07-13 16:53 UTC<br\/>  <b>Sensor: <\/b> NOAA-20 VIIRS<br\/> <b>Confidence: <\/b> Low<br\/>  <b>Day\/Night: <\/b> Day<br\/> <b>Scan: <\/b> 0.6 km<br\/> <b>Track: <\/b> 0.7 km<br\/> <b>FRP: <\/b> 8.86 MW<br\/> <b>Brightness: <\/b> 326.12 K" }, "geometry": { "type": "Point", "coordinates": [ -75.31812, 40.60865, 0.0 ] } }
]
}
