{
"type": "FeatureCollection",
"crs": { "type": "name", "properties": { "name": "urn:ogc:def:crs:OGC:1.3:CRS84" } },
"features": [
{ "type": "Feature", "properties": { "Name": "Fire Detection Centroid ", "Description": "<b>Latitude: <\/b> 46.26592<br\/>  <b>Longitude: <\/b> -122.30708<br\/>  <b>Detection Time: <\/b> 2024-02-14 11:21 UTC<br\/>  <b>Sensor: <\/b> NOAA-20 VIIRS<br\/> <b>Confidence: <\/b> Nominal<br\/>  <b>Day\/Night: <\/b> Night<br\/> <b>Scan: <\/b> 0.6 km<br\/> <b>Track: <\/b> 0.7 km<br\/> <b>FRP: <\/b> 1.26 MW<br\/> <b>Brightness: <\/b> 312.6 K" }, "geometry": { "type": "Point", "coordinates": [ -122.30708, 46.26592, 0.0 ] } },
{ "type": "Feature", "properties": { "Name": "Fire Detection Centroid ", "Description": "<b>Latitude: <\/b> 46.07547<br\/>  <b>Longitude: <\/b> -122.4283<br\/>  <b>Detection Time: <\/b> 2024-02-14 11:21 UTC<br\/>  <b>Sensor: <\/b> NOAA-20 VIIRS<br\/> <b>Confidence: <\/b> Nominal<br\/>  <b>Day\/Night: <\/b> Night<br\/> <b>Scan: <\/b> 0.6 km<br\/> <b>Track: <\/b> 0.7 km<br\/> <b>FRP: <\/b> 2.79 MW<br\/> <b>Brightness: <\/b> 317.44 K" }, "geometry": { "type": "Point", "coordinates": [ -122.4283, 46.07547, 0.0 ] } },
{ "type": "Feature", "properties": { "Name": "Fire Detection Centroid ", "Description": "<b>Latitude: <\/b> 49.48055<br\/>  <b>Longitude: <\/b> -117.42519<br\/>  <b>Detection Time: <\/b> 2024-02-14 11:20 UTC<br\/>  <b>Sensor: <\/b> NOAA-20 VIIRS<br\/> <b>Confidence: <\/b> Nominal<br\/>  <b>Day\/Night: <\/b> Night<br\/> <b>Scan: <\/b> 0.7 km<br\/> <b>Track: <\/b> 0.7 km<br\/> <b>FRP: <\/b> 13.84 MW<br\/> <b>Brightness: <\/b> 336.04 K" }, "geometry": { "type": "Point", "coordinates": [ -117.42519, 49.48055, 0.0 ] } }
]
}
