{
"type": "FeatureCollection",
"crs": { "type": "name", "properties": { "name": "urn:ogc:def:crs:OGC:1.3:CRS84" } },
"features": [
{ "type": "Feature", "properties": { "Name": "Fire Detection Centroid ", "Description": "<b>Latitude: <\/b> 45.33911<br\/>  <b>Longitude: <\/b> -73.52338<br\/>  <b>Detection Time: <\/b> 2022-09-24 06:43 UTC<br\/>  <b>Sensor: <\/b> NOAA-20 VIIRS<br\/> <b>Confidence: <\/b> Nominal<br\/>  <b>Day\/Night: <\/b> Night<br\/> <b>Scan: <\/b> 0.4 km<br\/> <b>Track: <\/b> 0.4 km<br\/> <b>FRP: <\/b> 0.9 MW<br\/> <b>Brightness: <\/b> 299.68 K" }, "geometry": { "type": "Point", "coordinates": [ -73.52338, 45.33911, 0.0 ] } },
{ "type": "Feature", "properties": { "Name": "Fire Detection Centroid ", "Description": "<b>Latitude: <\/b> 46.04506<br\/>  <b>Longitude: <\/b> -73.14282<br\/>  <b>Detection Time: <\/b> 2022-09-24 06:43 UTC<br\/>  <b>Sensor: <\/b> NOAA-20 VIIRS<br\/> <b>Confidence: <\/b> Nominal<br\/>  <b>Day\/Night: <\/b> Night<br\/> <b>Scan: <\/b> 0.4 km<br\/> <b>Track: <\/b> 0.4 km<br\/> <b>FRP: <\/b> 2.34 MW<br\/> <b>Brightness: <\/b> 336.94 K" }, "geometry": { "type": "Point", "coordinates": [ -73.14282, 46.04506, 0.0 ] } },
{ "type": "Feature", "properties": { "Name": "Fire Detection Centroid ", "Description": "<b>Latitude: <\/b> 46.04169<br\/>  <b>Longitude: <\/b> -73.14375<br\/>  <b>Detection Time: <\/b> 2022-09-24 06:43 UTC<br\/>  <b>Sensor: <\/b> NOAA-20 VIIRS<br\/> <b>Confidence: <\/b> Nominal<br\/>  <b>Day\/Night: <\/b> Night<br\/> <b>Scan: <\/b> 0.4 km<br\/> <b>Track: <\/b> 0.4 km<br\/> <b>FRP: <\/b> 2.34 MW<br\/> <b>Brightness: <\/b> 305.13 K" }, "geometry": { "type": "Point", "coordinates": [ -73.14375, 46.04169, 0.0 ] } },
{ "type": "Feature", "properties": { "Name": "Fire Detection Centroid ", "Description": "<b>Latitude: <\/b> 46.04436<br\/>  <b>Longitude: <\/b> -73.13757<br\/>  <b>Detection Time: <\/b> 2022-09-24 06:43 UTC<br\/>  <b>Sensor: <\/b> NOAA-20 VIIRS<br\/> <b>Confidence: <\/b> Nominal<br\/>  <b>Day\/Night: <\/b> Night<br\/> <b>Scan: <\/b> 0.4 km<br\/> <b>Track: <\/b> 0.4 km<br\/> <b>FRP: <\/b> 1.05 MW<br\/> <b>Brightness: <\/b> 297.87 K" }, "geometry": { "type": "Point", "coordinates": [ -73.13757, 46.04436, 0.0 ] } },
{ "type": "Feature", "properties": { "Name": "Fire Detection Centroid ", "Description": "<b>Latitude: <\/b> 45.78125<br\/>  <b>Longitude: <\/b> -73.91356<br\/>  <b>Detection Time: <\/b> 2022-09-24 06:43 UTC<br\/>  <b>Sensor: <\/b> NOAA-20 VIIRS<br\/> <b>Confidence: <\/b> Nominal<br\/>  <b>Day\/Night: <\/b> Night<br\/> <b>Scan: <\/b> 0.4 km<br\/> <b>Track: <\/b> 0.4 km<br\/> <b>FRP: <\/b> 1.08 MW<br\/> <b>Brightness: <\/b> 303.36 K" }, "geometry": { "type": "Point", "coordinates": [ -73.91356, 45.78125, 0.0 ] } },
{ "type": "Feature", "properties": { "Name": "Fire Detection Centroid ", "Description": "<b>Latitude: <\/b> 45.83873<br\/>  <b>Longitude: <\/b> -73.25089<br\/>  <b>Detection Time: <\/b> 2022-09-24 06:43 UTC<br\/>  <b>Sensor: <\/b> NOAA-20 VIIRS<br\/> <b>Confidence: <\/b> Nominal<br\/>  <b>Day\/Night: <\/b> Night<br\/> <b>Scan: <\/b> 0.4 km<br\/> <b>Track: <\/b> 0.4 km<br\/> <b>FRP: <\/b> 2.31 MW<br\/> <b>Brightness: <\/b> 317.77 K" }, "geometry": { "type": "Point", "coordinates": [ -73.25089, 45.83873, 0.0 ] } }
]
}
