{
"type": "FeatureCollection",
"crs": { "type": "name", "properties": { "name": "urn:ogc:def:crs:OGC:1.3:CRS84" } },
"features": [
{ "type": "Feature", "properties": { "Name": "Fire Detection Centroid ", "Description": "<b>Latitude: </b> 18.92838<br/>  <b>Longitude: </b> -70.35272<br/>  <b>Detection Time: </b> 2022-06-17 06:07 UTC<br/>  <b>Sensor: </b> NOAA-20 VIIRS<br/> <b>Confidence: </b> Nominal<br/>  <b>Day/Night: </b> Night<br/> <b>Scan: </b> 0.4 km<br/> <b>Track: </b> 0.4 km<br/> <b>FRP: </b> 8.25 MW<br/> <b>Brightness: </b> 338.38 K" }, "geometry": { "type": "Point", "coordinates": [ -70.35272, 18.92838, 0.0 ] } },
{ "type": "Feature", "properties": { "Name": "Fire Detection Centroid ", "Description": "<b>Latitude: </b> 18.92898<br/>  <b>Longitude: </b> -70.35696<br/>  <b>Detection Time: </b> 2022-06-17 06:07 UTC<br/>  <b>Sensor: </b> NOAA-20 VIIRS<br/> <b>Confidence: </b> Nominal<br/>  <b>Day/Night: </b> Night<br/> <b>Scan: </b> 0.4 km<br/> <b>Track: </b> 0.4 km<br/> <b>FRP: </b> 1.08 MW<br/> <b>Brightness: </b> 295.59 K" }, "geometry": { "type": "Point", "coordinates": [ -70.35696, 18.92898, 0.0 ] } },
{ "type": "Feature", "properties": { "Name": "Fire Detection Centroid ", "Description": "<b>Latitude: </b> 18.92483<br/>  <b>Longitude: </b> -70.35314<br/>  <b>Detection Time: </b> 2022-06-17 06:07 UTC<br/>  <b>Sensor: </b> NOAA-20 VIIRS<br/> <b>Confidence: </b> Nominal<br/>  <b>Day/Night: </b> Night<br/> <b>Scan: </b> 0.4 km<br/> <b>Track: </b> 0.4 km<br/> <b>FRP: </b> 0.84 MW<br/> <b>Brightness: </b> 297.32 K" }, "geometry": { "type": "Point", "coordinates": [ -70.35314, 18.92483, 0.0 ] } },
{ "type": "Feature", "properties": { "Name": "Fire Detection Centroid ", "Description": "<b>Latitude: </b> 45.11421<br/>  <b>Longitude: </b> -73.01069<br/>  <b>Detection Time: </b> 2022-06-17 06:00 UTC<br/>  <b>Sensor: </b> NOAA-20 VIIRS<br/> <b>Confidence: </b> Nominal<br/>  <b>Day/Night: </b> Night<br/> <b>Scan: </b> 0.4 km<br/> <b>Track: </b> 0.6 km<br/> <b>FRP: </b> 0.69 MW<br/> <b>Brightness: </b> 303.13 K" }, "geometry": { "type": "Point", "coordinates": [ -73.01069, 45.11421, 0.0 ] } }
]
}
