{
"type": "FeatureCollection",
"crs": { "type": "name", "properties": { "name": "urn:ogc:def:crs:OGC:1.3:CRS84" } },
"features": [
{ "type": "Feature", "properties": { "Name": "Fire Detection Centroid ", "Description": "<b>Latitude: <\/b> 19.31898<br\/>  <b>Longitude: <\/b> -70.31767<br\/>  <b>Detection Time: <\/b> 2022-10-03 05:41 UTC<br\/>  <b>Sensor: <\/b> NOAA-20 VIIRS<br\/> <b>Confidence: <\/b> Nominal<br\/>  <b>Day\/Night: <\/b> Night<br\/> <b>Scan: <\/b> 0.3 km<br\/> <b>Track: <\/b> 0.6 km<br\/> <b>FRP: <\/b> 0.52 MW<br\/> <b>Brightness: <\/b> 301.04 K" }, "geometry": { "type": "Point", "coordinates": [ -70.31767, 19.31898, 0.0 ] } },
{ "type": "Feature", "properties": { "Name": "Fire Detection Centroid ", "Description": "<b>Latitude: <\/b> 45.28083<br\/>  <b>Longitude: <\/b> -66.01777<br\/>  <b>Detection Time: <\/b> 2022-10-03 05:34 UTC<br\/>  <b>Sensor: <\/b> NOAA-20 VIIRS<br\/> <b>Confidence: <\/b> Nominal<br\/>  <b>Day\/Night: <\/b> Night<br\/> <b>Scan: <\/b> 0.3 km<br\/> <b>Track: <\/b> 0.6 km<br\/> <b>FRP: <\/b> 0.8 MW<br\/> <b>Brightness: <\/b> 296.22 K" }, "geometry": { "type": "Point", "coordinates": [ -66.01777, 45.28083, 0.0 ] } },
{ "type": "Feature", "properties": { "Name": "Fire Detection Centroid ", "Description": "<b>Latitude: <\/b> 45.28102<br\/>  <b>Longitude: <\/b> -66.02238<br\/>  <b>Detection Time: <\/b> 2022-10-03 05:34 UTC<br\/>  <b>Sensor: <\/b> NOAA-20 VIIRS<br\/> <b>Confidence: <\/b> Nominal<br\/>  <b>Day\/Night: <\/b> Night<br\/> <b>Scan: <\/b> 0.3 km<br\/> <b>Track: <\/b> 0.6 km<br\/> <b>FRP: <\/b> 0.8 MW<br\/> <b>Brightness: <\/b> 302.68 K" }, "geometry": { "type": "Point", "coordinates": [ -66.02238, 45.28102, 0.0 ] } }
]
}
