{
"type": "FeatureCollection",
"crs": { "type": "name", "properties": { "name": "urn:ogc:def:crs:OGC:1.3:CRS84" } },
"features": [
{ "type": "Feature", "properties": { "Name": "Fire Detection Centroid ", "Description": "<b>Latitude: <\/b> 34.08305<br\/>  <b>Longitude: <\/b> -117.50032<br\/>  <b>Detection Time: <\/b> 2024-01-10 10:40 UTC<br\/>  <b>Sensor: <\/b> NOAA-20 VIIRS<br\/> <b>Confidence: <\/b> Nominal<br\/>  <b>Day\/Night: <\/b> Night<br\/> <b>Scan: <\/b> 0.7 km<br\/> <b>Track: <\/b> 0.7 km<br\/> <b>FRP: <\/b> 1.22 MW<br\/> <b>Brightness: <\/b> 299.72 K" }, "geometry": { "type": "Point", "coordinates": [ -117.50032, 34.08305, 0.0 ] } },
{ "type": "Feature", "properties": { "Name": "Fire Detection Centroid ", "Description": "<b>Latitude: <\/b> 37.9511<br\/>  <b>Longitude: <\/b> -122.39844<br\/>  <b>Detection Time: <\/b> 2024-01-10 10:40 UTC<br\/>  <b>Sensor: <\/b> NOAA-20 VIIRS<br\/> <b>Confidence: <\/b> Nominal<br\/>  <b>Day\/Night: <\/b> Night<br\/> <b>Scan: <\/b> 0.6 km<br\/> <b>Track: <\/b> 0.5 km<br\/> <b>FRP: <\/b> 1.59 MW<br\/> <b>Brightness: <\/b> 297.12 K" }, "geometry": { "type": "Point", "coordinates": [ -122.39844, 37.9511, 0.0 ] } },
{ "type": "Feature", "properties": { "Name": "Fire Detection Centroid ", "Description": "<b>Latitude: <\/b> 35.89772<br\/>  <b>Longitude: <\/b> -118.35448<br\/>  <b>Detection Time: <\/b> 2024-01-10 10:40 UTC<br\/>  <b>Sensor: <\/b> NOAA-20 VIIRS<br\/> <b>Confidence: <\/b> Nominal<br\/>  <b>Day\/Night: <\/b> Night<br\/> <b>Scan: <\/b> 0.5 km<br\/> <b>Track: <\/b> 0.7 km<br\/> <b>FRP: <\/b> 1.17 MW<br\/> <b>Brightness: <\/b> 298.12 K" }, "geometry": { "type": "Point", "coordinates": [ -118.35448, 35.89772, 0.0 ] } }
]
}
