{
"type": "FeatureCollection",
"crs": { "type": "name", "properties": { "name": "urn:ogc:def:crs:OGC:1.3:CRS84" } },
"features": [
{ "type": "Feature", "properties": { "Name": "Fire Detection Centroid ", "Description": "<b>Latitude: <\/b> 45.9004<br\/>  <b>Longitude: <\/b> -64.42195<br\/>  <b>Detection Time: <\/b> 2022-09-12 05:27 UTC<br\/>  <b>Sensor: <\/b> NOAA-20 VIIRS<br\/> <b>Confidence: <\/b> Nominal<br\/>  <b>Day\/Night: <\/b> Night<br\/> <b>Scan: <\/b> 0.4 km<br\/> <b>Track: <\/b> 0.6 km<br\/> <b>FRP: <\/b> 0.36 MW<br\/> <b>Brightness: <\/b> 296.33 K" }, "geometry": { "type": "Point", "coordinates": [ -64.42195, 45.9004, 0.0 ] } },
{ "type": "Feature", "properties": { "Name": "Fire Detection Centroid ", "Description": "<b>Latitude: <\/b> 48.18715<br\/>  <b>Longitude: <\/b> -64.92618<br\/>  <b>Detection Time: <\/b> 2022-09-12 05:26 UTC<br\/>  <b>Sensor: <\/b> NOAA-20 VIIRS<br\/> <b>Confidence: <\/b> Nominal<br\/>  <b>Day\/Night: <\/b> Night<br\/> <b>Scan: <\/b> 0.4 km<br\/> <b>Track: <\/b> 0.6 km<br\/> <b>FRP: <\/b> 0.78 MW<br\/> <b>Brightness: <\/b> 296.89 K" }, "geometry": { "type": "Point", "coordinates": [ -64.92618, 48.18715, 0.0 ] } },
{ "type": "Feature", "properties": { "Name": "Fire Detection Centroid ", "Description": "<b>Latitude: <\/b> 48.18699<br\/>  <b>Longitude: <\/b> -64.92062<br\/>  <b>Detection Time: <\/b> 2022-09-12 05:26 UTC<br\/>  <b>Sensor: <\/b> NOAA-20 VIIRS<br\/> <b>Confidence: <\/b> Nominal<br\/>  <b>Day\/Night: <\/b> Night<br\/> <b>Scan: <\/b> 0.4 km<br\/> <b>Track: <\/b> 0.6 km<br\/> <b>FRP: <\/b> 0.78 MW<br\/> <b>Brightness: <\/b> 301.7 K" }, "geometry": { "type": "Point", "coordinates": [ -64.92062, 48.18699, 0.0 ] } }
]
}
