{
"type": "FeatureCollection",
"crs": { "type": "name", "properties": { "name": "urn:ogc:def:crs:OGC:1.3:CRS84" } },
"features": [
{ "type": "Feature", "properties": { "Name": "Fire Detection Centroid ", "Description": "<b>Latitude: <\/b> 20.86321<br\/>  <b>Longitude: <\/b> -156.42078<br\/>  <b>Detection Time: <\/b> 2023-02-21 11:42 UTC<br\/>  <b>Sensor: <\/b> NOAA-20 VIIRS<br\/> <b>Confidence: <\/b> Nominal<br\/>  <b>Day\/Night: <\/b> Night<br\/> <b>Scan: <\/b> 0.4 km<br\/> <b>Track: <\/b> 0.44 km<br\/> <b>FRP: <\/b> 0.49 MW<br\/> <b>Brightness: <\/b> 299.02 K" }, "geometry": { "type": "Point", "coordinates": [ -156.42078, 20.86321, 0.0 ] } },
{ "type": "Feature", "properties": { "Name": "Fire Detection Centroid ", "Description": "<b>Latitude: <\/b> 45.23352<br\/>  <b>Longitude: <\/b> -123.16727<br\/>  <b>Detection Time: <\/b> 2023-02-21 11:34 UTC<br\/>  <b>Sensor: <\/b> NOAA-20 VIIRS<br\/> <b>Confidence: <\/b> Nominal<br\/>  <b>Day\/Night: <\/b> Night<br\/> <b>Scan: <\/b> 0.77 km<br\/> <b>Track: <\/b> 0.77 km<br\/> <b>FRP: <\/b> 1.29 MW<br\/> <b>Brightness: <\/b> 302.78 K" }, "geometry": { "type": "Point", "coordinates": [ -123.16727, 45.23352, 0.0 ] } },
{ "type": "Feature", "properties": { "Name": "Fire Detection Centroid ", "Description": "<b>Latitude: <\/b> 45.23248<br\/>  <b>Longitude: <\/b> -123.16944<br\/>  <b>Detection Time: <\/b> 2023-02-21 11:34 UTC<br\/>  <b>Sensor: <\/b> NOAA-20 VIIRS<br\/> <b>Confidence: <\/b> Nominal<br\/>  <b>Day\/Night: <\/b> Night<br\/> <b>Scan: <\/b> 0.76 km<br\/> <b>Track: <\/b> 0.77 km<br\/> <b>FRP: <\/b> 1.91 MW<br\/> <b>Brightness: <\/b> 301.53 K" }, "geometry": { "type": "Point", "coordinates": [ -123.16944, 45.23248, 0.0 ] } }
]
}
