{
"type": "FeatureCollection",
"crs": { "type": "name", "properties": { "name": "urn:ogc:def:crs:OGC:1.3:CRS84" } },
"features": [
{ "type": "Feature", "properties": { "Name": "Fire Detection Centroid ", "Description": "<b>Latitude: <\/b> 19.51961<br\/>  <b>Longitude: <\/b> -71.81521<br\/>  <b>Detection Time: <\/b> 2023-11-22 17:11 UTC<br\/>  <b>Sensor: <\/b> NOAA-20 VIIRS<br\/> <b>Confidence: <\/b> Nominal<br\/>  <b>Day\/Night: <\/b> Day<br\/> <b>Scan: <\/b> 0.5 km<br\/> <b>Track: <\/b> 0.7 km<br\/> <b>FRP: <\/b> 6.96 MW<br\/> <b>Brightness: <\/b> 344.25 K" }, "geometry": { "type": "Point", "coordinates": [ -71.81521, 19.51961, 0.0 ] } }
]
}
