{
"type": "FeatureCollection",
"crs": { "type": "name", "properties": { "name": "urn:ogc:def:crs:OGC:1.3:CRS84" } },
"features": [
{ "type": "Feature", "properties": { "Name": "Fire Detection Centroid ", "Description": "<b>Latitude: <\/b> 18.92808<br\/>  <b>Longitude: <\/b> -70.35485<br\/>  <b>Detection Time: <\/b> 2023-10-16 05:54 UTC<br\/>  <b>Sensor: <\/b> NOAA-20 VIIRS<br\/> <b>Confidence: <\/b> Nominal<br\/>  <b>Day\/Night: <\/b> Night<br\/> <b>Scan: <\/b> 0.4 km<br\/> <b>Track: <\/b> 0.5 km<br\/> <b>FRP: <\/b> 15.89 MW<br\/> <b>Brightness: <\/b> 340.92 K" }, "geometry": { "type": "Point", "coordinates": [ -70.35485, 18.92808, 0.0 ] } },
{ "type": "Feature", "properties": { "Name": "Fire Detection Centroid ", "Description": "<b>Latitude: <\/b> 18.92808<br\/>  <b>Longitude: <\/b> -70.35485<br\/>  <b>Detection Time: <\/b> 2023-10-16 05:54 UTC<br\/>  <b>Sensor: <\/b> NOAA-20 VIIRS<br\/> <b>Confidence: <\/b> Nominal<br\/>  <b>Day\/Night: <\/b> Night<br\/> <b>Scan: <\/b> 0.4 km<br\/> <b>Track: <\/b> 0.5 km<br\/> <b>FRP: <\/b> 15.89 MW<br\/> <b>Brightness: <\/b> 340.92 K" }, "geometry": { "type": "Point", "coordinates": [ -70.35485, 18.92808, 0.0 ] } },
{ "type": "Feature", "properties": { "Name": "Fire Detection Centroid ", "Description": "<b>Latitude: <\/b> 18.92861<br\/>  <b>Longitude: <\/b> -70.3531<br\/>  <b>Detection Time: <\/b> 2023-10-16 05:54 UTC<br\/>  <b>Sensor: <\/b> NOAA-20 VIIRS<br\/> <b>Confidence: <\/b> Nominal<br\/>  <b>Day\/Night: <\/b> Night<br\/> <b>Scan: <\/b> 0.4 km<br\/> <b>Track: <\/b> 0.5 km<br\/> <b>FRP: <\/b> 19.75 MW<br\/> <b>Brightness: <\/b> 350.28 K" }, "geometry": { "type": "Point", "coordinates": [ -70.3531, 18.92861, 0.0 ] } }
]
}
