{
"type": "FeatureCollection",
"crs": { "type": "name", "properties": { "name": "urn:ogc:def:crs:OGC:1.3:CRS84" } },
"features": [
{ "type": "Feature", "properties": { "Name": "Fire Detection Centroid ", "Description": "<b>Latitude: <\/b> 49.95855<br\/>  <b>Longitude: <\/b> -125.39663<br\/>  <b>Detection Time: <\/b> 2023-10-21 22:25 UTC<br\/>  <b>Sensor: <\/b> NOAA-20 VIIRS<br\/> <b>Confidence: <\/b> Nominal<br\/>  <b>Day\/Night: <\/b> Day<br\/> <b>Scan: <\/b> 0.67 km<br\/> <b>Track: <\/b> 0.73 km<br\/> <b>FRP: <\/b> 6.69 MW<br\/> <b>Brightness: <\/b> 331.52 K" }, "geometry": { "type": "Point", "coordinates": [ -125.39663, 49.95855, 0.0 ] } }
]
}
