{
"type": "FeatureCollection",
"crs": { "type": "name", "properties": { "name": "urn:ogc:def:crs:OGC:1.3:CRS84" } },
"features": [
{ "type": "Feature", "properties": { "Name": "Fire Detection Centroid ", "Description": "<b>Latitude: <\/b> 45.42802<br\/>  <b>Longitude: <\/b> -74.68727<br\/>  <b>Detection Time: <\/b> 2023-09-09 17:07 UTC<br\/>  <b>Sensor: <\/b> NOAA-20 VIIRS<br\/> <b>Confidence: <\/b> Nominal<br\/>  <b>Day\/Night: <\/b> Day<br\/> <b>Scan: <\/b> 0.5 km<br\/> <b>Track: <\/b> 0.5 km<br\/> <b>FRP: <\/b> 5.2 MW<br\/> <b>Brightness: <\/b> 338.86 K" }, "geometry": { "type": "Point", "coordinates": [ -74.68727, 45.42802, 0.0 ] } },
{ "type": "Feature", "properties": { "Name": "Fire Detection Centroid ", "Description": "<b>Latitude: <\/b> 18.79791<br\/>  <b>Longitude: <\/b> -70.22667<br\/>  <b>Detection Time: <\/b> 2023-09-09 16:59 UTC<br\/>  <b>Sensor: <\/b> NOAA-20 VIIRS<br\/> <b>Confidence: <\/b> Nominal<br\/>  <b>Day\/Night: <\/b> Day<br\/> <b>Scan: <\/b> 0.7 km<br\/> <b>Track: <\/b> 0.7 km<br\/> <b>FRP: <\/b> 15.46 MW<br\/> <b>Brightness: <\/b> 333.07 K" }, "geometry": { "type": "Point", "coordinates": [ -70.22667, 18.79791, 0.0 ] } },
{ "type": "Feature", "properties": { "Name": "Fire Detection Centroid ", "Description": "<b>Latitude: <\/b> 18.65317<br\/>  <b>Longitude: <\/b> -69.01911<br\/>  <b>Detection Time: <\/b> 2023-09-09 16:59 UTC<br\/>  <b>Sensor: <\/b> NOAA-20 VIIRS<br\/> <b>Confidence: <\/b> Nominal<br\/>  <b>Day\/Night: <\/b> Day<br\/> <b>Scan: <\/b> 0.6 km<br\/> <b>Track: <\/b> 0.7 km<br\/> <b>FRP: <\/b> 5.97 MW<br\/> <b>Brightness: <\/b> 329.76 K" }, "geometry": { "type": "Point", "coordinates": [ -69.01911, 18.65317, 0.0 ] } },
{ "type": "Feature", "properties": { "Name": "Fire Detection Centroid ", "Description": "<b>Latitude: <\/b> 18.7968<br\/>  <b>Longitude: <\/b> -70.23149<br\/>  <b>Detection Time: <\/b> 2023-09-09 16:59 UTC<br\/>  <b>Sensor: <\/b> NOAA-20 VIIRS<br\/> <b>Confidence: <\/b> Low<br\/>  <b>Day\/Night: <\/b> Day<br\/> <b>Scan: <\/b> 0.7 km<br\/> <b>Track: <\/b> 0.7 km<br\/> <b>FRP: <\/b> 19.01 MW<br\/> <b>Brightness: <\/b> 356.85 K" }, "geometry": { "type": "Point", "coordinates": [ -70.23149, 18.7968, 0.0 ] } },
{ "type": "Feature", "properties": { "Name": "Fire Detection Centroid ", "Description": "<b>Latitude: <\/b> 18.92244<br\/>  <b>Longitude: <\/b> -70.3486<br\/>  <b>Detection Time: <\/b> 2023-09-09 16:59 UTC<br\/>  <b>Sensor: <\/b> NOAA-20 VIIRS<br\/> <b>Confidence: <\/b> Nominal<br\/>  <b>Day\/Night: <\/b> Day<br\/> <b>Scan: <\/b> 0.7 km<br\/> <b>Track: <\/b> 0.7 km<br\/> <b>FRP: <\/b> 4.34 MW<br\/> <b>Brightness: <\/b> 327.26 K" }, "geometry": { "type": "Point", "coordinates": [ -70.3486, 18.92244, 0.0 ] } }
]
}
