{
"type": "FeatureCollection",
"crs": { "type": "name", "properties": { "name": "urn:ogc:def:crs:OGC:1.3:CRS84" } },
"features": [
{ "type": "Feature", "properties": { "Name": "Fire Detection Centroid ", "Description": "<b>Latitude: <\/b> 36.51099<br\/>  <b>Longitude: <\/b> -79.75842<br\/>  <b>Detection Time: <\/b> 2023-01-26 06:21 UTC<br\/>  <b>Sensor: <\/b> NOAA-20 VIIRS<br\/> <b>Confidence: <\/b> Nominal<br\/>  <b>Day\/Night: <\/b> Night<br\/> <b>Scan: <\/b> 0.4 km<br\/> <b>Track: <\/b> 0.6 km<br\/> <b>FRP: <\/b> 0.6 MW<br\/> <b>Brightness: <\/b> 296.74 K" }, "geometry": { "type": "Point", "coordinates": [ -79.75842, 36.51099, 0.0 ] } },
{ "type": "Feature", "properties": { "Name": "Fire Detection Centroid ", "Description": "<b>Latitude: <\/b> 36.51124<br\/>  <b>Longitude: <\/b> -79.76317<br\/>  <b>Detection Time: <\/b> 2023-01-26 06:21 UTC<br\/>  <b>Sensor: <\/b> NOAA-20 VIIRS<br\/> <b>Confidence: <\/b> Nominal<br\/>  <b>Day\/Night: <\/b> Night<br\/> <b>Scan: <\/b> 0.4 km<br\/> <b>Track: <\/b> 0.6 km<br\/> <b>FRP: <\/b> 0.6 MW<br\/> <b>Brightness: <\/b> 295.86 K" }, "geometry": { "type": "Point", "coordinates": [ -79.76317, 36.51124, 0.0 ] } },
{ "type": "Feature", "properties": { "Name": "Fire Detection Centroid ", "Description": "<b>Latitude: <\/b> 36.50554<br\/>  <b>Longitude: <\/b> -79.7637<br\/>  <b>Detection Time: <\/b> 2023-01-26 06:21 UTC<br\/>  <b>Sensor: <\/b> NOAA-20 VIIRS<br\/> <b>Confidence: <\/b> Nominal<br\/>  <b>Day\/Night: <\/b> Night<br\/> <b>Scan: <\/b> 0.4 km<br\/> <b>Track: <\/b> 0.6 km<br\/> <b>FRP: <\/b> 6.69 MW<br\/> <b>Brightness: <\/b> 324.68 K" }, "geometry": { "type": "Point", "coordinates": [ -79.7637, 36.50554, 0.0 ] } },
{ "type": "Feature", "properties": { "Name": "Fire Detection Centroid ", "Description": "<b>Latitude: <\/b> 33.87725<br\/>  <b>Longitude: <\/b> -79.42776<br\/>  <b>Detection Time: <\/b> 2023-01-26 06:21 UTC<br\/>  <b>Sensor: <\/b> NOAA-20 VIIRS<br\/> <b>Confidence: <\/b> Nominal<br\/>  <b>Day\/Night: <\/b> Night<br\/> <b>Scan: <\/b> 0.4 km<br\/> <b>Track: <\/b> 0.6 km<br\/> <b>FRP: <\/b> 0.82 MW<br\/> <b>Brightness: <\/b> 299.15 K" }, "geometry": { "type": "Point", "coordinates": [ -79.42776, 33.87725, 0.0 ] } },
{ "type": "Feature", "properties": { "Name": "Fire Detection Centroid ", "Description": "<b>Latitude: <\/b> 34.37625<br\/>  <b>Longitude: <\/b> -79.88737<br\/>  <b>Detection Time: <\/b> 2023-01-26 06:21 UTC<br\/>  <b>Sensor: <\/b> NOAA-20 VIIRS<br\/> <b>Confidence: <\/b> Nominal<br\/>  <b>Day\/Night: <\/b> Night<br\/> <b>Scan: <\/b> 0.4 km<br\/> <b>Track: <\/b> 0.6 km<br\/> <b>FRP: <\/b> 1.15 MW<br\/> <b>Brightness: <\/b> 298.66 K" }, "geometry": { "type": "Point", "coordinates": [ -79.88737, 34.37625, 0.0 ] } },
{ "type": "Feature", "properties": { "Name": "Fire Detection Centroid ", "Description": "<b>Latitude: <\/b> 34.3765<br\/>  <b>Longitude: <\/b> -79.89189<br\/>  <b>Detection Time: <\/b> 2023-01-26 06:21 UTC<br\/>  <b>Sensor: <\/b> NOAA-20 VIIRS<br\/> <b>Confidence: <\/b> Nominal<br\/>  <b>Day\/Night: <\/b> Night<br\/> <b>Scan: <\/b> 0.4 km<br\/> <b>Track: <\/b> 0.6 km<br\/> <b>FRP: <\/b> 0.55 MW<br\/> <b>Brightness: <\/b> 295.84 K" }, "geometry": { "type": "Point", "coordinates": [ -79.89189, 34.3765, 0.0 ] } },
{ "type": "Feature", "properties": { "Name": "Fire Detection Centroid ", "Description": "<b>Latitude: <\/b> 36.50529<br\/>  <b>Longitude: <\/b> -79.75896<br\/>  <b>Detection Time: <\/b> 2023-01-26 06:21 UTC<br\/>  <b>Sensor: <\/b> NOAA-20 VIIRS<br\/> <b>Confidence: <\/b> High<br\/>  <b>Day\/Night: <\/b> Night<br\/> <b>Scan: <\/b> 0.4 km<br\/> <b>Track: <\/b> 0.6 km<br\/> <b>FRP: <\/b> 6.69 MW<br\/> <b>Brightness: <\/b> 367 K" }, "geometry": { "type": "Point", "coordinates": [ -79.75896, 36.50529, 0.0 ] } },
{ "type": "Feature", "properties": { "Name": "Fire Detection Centroid ", "Description": "<b>Latitude: <\/b> 39.1718<br\/>  <b>Longitude: <\/b> -78.20401<br\/>  <b>Detection Time: <\/b> 2023-01-26 06:20 UTC<br\/>  <b>Sensor: <\/b> NOAA-20 VIIRS<br\/> <b>Confidence: <\/b> Nominal<br\/>  <b>Day\/Night: <\/b> Night<br\/> <b>Scan: <\/b> 0.4 km<br\/> <b>Track: <\/b> 0.6 km<br\/> <b>FRP: <\/b> 1.18 MW<br\/> <b>Brightness: <\/b> 306.49 K" }, "geometry": { "type": "Point", "coordinates": [ -78.20401, 39.1718, 0.0 ] } }
]
}
