{
"type": "FeatureCollection",
"crs": { "type": "name", "properties": { "name": "urn:ogc:def:crs:OGC:1.3:CRS84" } },
"features": [
{ "type": "Feature", "properties": { "Name": "Fire Detection Centroid ", "Description": "<b>Latitude: <\/b> 40.94456<br\/>  <b>Longitude: <\/b> -123.57818<br\/>  <b>Detection Time: <\/b> 2022-08-15 22:20 UTC<br\/>  <b>Sensor: <\/b> NOAA-20 VIIRS<br\/> <b>Confidence: <\/b> Nominal<br\/>  <b>Day\/Night: <\/b> Day<br\/> <b>Scan: <\/b> 0.78 km<br\/> <b>Track: <\/b> 0.78 km<br\/> <b>FRP: <\/b> 8.54 MW<br\/> <b>Brightness: <\/b> 335.88 K" }, "geometry": { "type": "Point", "coordinates": [ -123.57818, 40.94456, 0.0 ] } },
{ "type": "Feature", "properties": { "Name": "Fire Detection Centroid ", "Description": "<b>Latitude: <\/b> 40.94455<br\/>  <b>Longitude: <\/b> -123.57259<br\/>  <b>Detection Time: <\/b> 2022-08-15 22:20 UTC<br\/>  <b>Sensor: <\/b> NOAA-20 VIIRS<br\/> <b>Confidence: <\/b> Nominal<br\/>  <b>Day\/Night: <\/b> Day<br\/> <b>Scan: <\/b> 0.78 km<br\/> <b>Track: <\/b> 0.78 km<br\/> <b>FRP: <\/b> 9.43 MW<br\/> <b>Brightness: <\/b> 337.57 K" }, "geometry": { "type": "Point", "coordinates": [ -123.57259, 40.94455, 0.0 ] } },
{ "type": "Feature", "properties": { "Name": "Fire Detection Centroid ", "Description": "<b>Latitude: <\/b> 40.95184<br\/>  <b>Longitude: <\/b> -123.59737<br\/>  <b>Detection Time: <\/b> 2022-08-15 22:20 UTC<br\/>  <b>Sensor: <\/b> NOAA-20 VIIRS<br\/> <b>Confidence: <\/b> Nominal<br\/>  <b>Day\/Night: <\/b> Day<br\/> <b>Scan: <\/b> 0.78 km<br\/> <b>Track: <\/b> 0.78 km<br\/> <b>FRP: <\/b> 4.45 MW<br\/> <b>Brightness: <\/b> 325.1 K" }, "geometry": { "type": "Point", "coordinates": [ -123.59737, 40.95184, 0.0 ] } },
{ "type": "Feature", "properties": { "Name": "Fire Detection Centroid ", "Description": "<b>Latitude: <\/b> 40.94458<br\/>  <b>Longitude: <\/b> -123.5834<br\/>  <b>Detection Time: <\/b> 2022-08-15 22:20 UTC<br\/>  <b>Sensor: <\/b> NOAA-20 VIIRS<br\/> <b>Confidence: <\/b> Nominal<br\/>  <b>Day\/Night: <\/b> Day<br\/> <b>Scan: <\/b> 0.78 km<br\/> <b>Track: <\/b> 0.78 km<br\/> <b>FRP: <\/b> 8.54 MW<br\/> <b>Brightness: <\/b> 326.97 K" }, "geometry": { "type": "Point", "coordinates": [ -123.5834, 40.94458, 0.0 ] } },
{ "type": "Feature", "properties": { "Name": "Fire Detection Centroid ", "Description": "<b>Latitude: <\/b> 40.94452<br\/>  <b>Longitude: <\/b> -123.5638<br\/>  <b>Detection Time: <\/b> 2022-08-15 22:20 UTC<br\/>  <b>Sensor: <\/b> NOAA-20 VIIRS<br\/> <b>Confidence: <\/b> Nominal<br\/>  <b>Day\/Night: <\/b> Day<br\/> <b>Scan: <\/b> 0.78 km<br\/> <b>Track: <\/b> 0.78 km<br\/> <b>FRP: <\/b> 9.43 MW<br\/> <b>Brightness: <\/b> 327.96 K" }, "geometry": { "type": "Point", "coordinates": [ -123.5638, 40.94452, 0.0 ] } },
{ "type": "Feature", "properties": { "Name": "Fire Detection Centroid ", "Description": "<b>Latitude: <\/b> 40.92999<br\/>  <b>Longitude: <\/b> -123.54357<br\/>  <b>Detection Time: <\/b> 2022-08-15 22:20 UTC<br\/>  <b>Sensor: <\/b> NOAA-20 VIIRS<br\/> <b>Confidence: <\/b> Nominal<br\/>  <b>Day\/Night: <\/b> Day<br\/> <b>Scan: <\/b> 0.78 km<br\/> <b>Track: <\/b> 0.78 km<br\/> <b>FRP: <\/b> 7.35 MW<br\/> <b>Brightness: <\/b> 328.29 K" }, "geometry": { "type": "Point", "coordinates": [ -123.54357, 40.92999, 0.0 ] } },
{ "type": "Feature", "properties": { "Name": "Fire Detection Centroid ", "Description": "<b>Latitude: <\/b> 40.92826<br\/>  <b>Longitude: <\/b> -123.54599<br\/>  <b>Detection Time: <\/b> 2022-08-15 22:20 UTC<br\/>  <b>Sensor: <\/b> NOAA-20 VIIRS<br\/> <b>Confidence: <\/b> Nominal<br\/>  <b>Day\/Night: <\/b> Day<br\/> <b>Scan: <\/b> 0.78 km<br\/> <b>Track: <\/b> 0.78 km<br\/> <b>FRP: <\/b> 7.22 MW<br\/> <b>Brightness: <\/b> 325.47 K" }, "geometry": { "type": "Point", "coordinates": [ -123.54599, 40.92826, 0.0 ] } }
]
}
