{
"type": "FeatureCollection",
"crs": { "type": "name", "properties": { "name": "urn:ogc:def:crs:OGC:1.3:CRS84" } },
"features": [
{ "type": "Feature", "properties": { "Name": "Fire Detection Centroid ", "Description": "<b>Latitude: <\/b> 18.39583<br\/>  <b>Longitude: <\/b> -70.11311<br\/>  <b>Detection Time: <\/b> 2023-10-23 05:23 UTC<br\/>  <b>Sensor: <\/b> NOAA-20 VIIRS<br\/> <b>Confidence: <\/b> Nominal<br\/>  <b>Day\/Night: <\/b> Night<br\/> <b>Scan: <\/b> 0.7 km<br\/> <b>Track: <\/b> 0.75 km<br\/> <b>FRP: <\/b> 1.98 MW<br\/> <b>Brightness: <\/b> 299.29 K" }, "geometry": { "type": "Point", "coordinates": [ -70.11311, 18.39583, 0.0 ] } },
{ "type": "Feature", "properties": { "Name": "Fire Detection Centroid ", "Description": "<b>Latitude: <\/b> 18.93164<br\/>  <b>Longitude: <\/b> -70.35996<br\/>  <b>Detection Time: <\/b> 2023-10-23 05:23 UTC<br\/>  <b>Sensor: <\/b> NOAA-20 VIIRS<br\/> <b>Confidence: <\/b> Nominal<br\/>  <b>Day\/Night: <\/b> Night<br\/> <b>Scan: <\/b> 0.74 km<br\/> <b>Track: <\/b> 0.76 km<br\/> <b>FRP: <\/b> 2.23 MW<br\/> <b>Brightness: <\/b> 307.02 K" }, "geometry": { "type": "Point", "coordinates": [ -70.35996, 18.93164, 0.0 ] } }
]
}
