{
"type": "FeatureCollection",
"crs": { "type": "name", "properties": { "name": "urn:ogc:def:crs:OGC:1.3:CRS84" } },
"features": [
{ "type": "Feature", "properties": { "Name": "Fire Detection Centroid ", "Description": "<b>Latitude: <\/b> 45.28164<br\/>  <b>Longitude: <\/b> -66.02205<br\/>  <b>Detection Time: <\/b> 2023-11-13 05:21 UTC<br\/>  <b>Sensor: <\/b> NOAA-20 VIIRS<br\/> <b>Confidence: <\/b> Nominal<br\/>  <b>Day\/Night: <\/b> Night<br\/> <b>Scan: <\/b> 0.5 km<br\/> <b>Track: <\/b> 0.7 km<br\/> <b>FRP: <\/b> 1.36 MW<br\/> <b>Brightness: <\/b> 295.4 K" }, "geometry": { "type": "Point", "coordinates": [ -66.02205, 45.28164, 0.0 ] } },
{ "type": "Feature", "properties": { "Name": "Fire Detection Centroid ", "Description": "<b>Latitude: <\/b> 45.28303<br\/>  <b>Longitude: <\/b> -66.02071<br\/>  <b>Detection Time: <\/b> 2023-11-13 05:21 UTC<br\/>  <b>Sensor: <\/b> NOAA-20 VIIRS<br\/> <b>Confidence: <\/b> Nominal<br\/>  <b>Day\/Night: <\/b> Night<br\/> <b>Scan: <\/b> 0.5 km<br\/> <b>Track: <\/b> 0.7 km<br\/> <b>FRP: <\/b> 0.93 MW<br\/> <b>Brightness: <\/b> 297.65 K" }, "geometry": { "type": "Point", "coordinates": [ -66.02071, 45.28303, 0.0 ] } }
]
}
