{
"type": "FeatureCollection",
"crs": { "type": "name", "properties": { "name": "urn:ogc:def:crs:OGC:1.3:CRS84" } },
"features": [
{ "type": "Feature", "properties": { "Name": "Fire Detection Centroid ", "Description": "<b>Latitude: <\/b> 48.18849<br\/>  <b>Longitude: <\/b> -64.92059<br\/>  <b>Detection Time: <\/b> 2022-11-04 05:33 UTC<br\/>  <b>Sensor: <\/b> NOAA-20 VIIRS<br\/> <b>Confidence: <\/b> Nominal<br\/>  <b>Day\/Night: <\/b> Night<br\/> <b>Scan: <\/b> 0.3 km<br\/> <b>Track: <\/b> 0.6 km<br\/> <b>FRP: <\/b> 0.27 MW<br\/> <b>Brightness: <\/b> 298.58 K" }, "geometry": { "type": "Point", "coordinates": [ -64.92059, 48.18849, 0.0 ] } }
]
}
