{
"type": "FeatureCollection",
"crs": { "type": "name", "properties": { "name": "urn:ogc:def:crs:OGC:1.3:CRS84" } },
"features": [
{ "type": "Feature", "properties": { "Name": "Fire Detection Centroid ", "Description": "<b>Latitude: <\/b> 18.32546<br\/>  <b>Longitude: <\/b> -70.32216<br\/>  <b>Detection Time: <\/b> 2023-08-14 05:36 UTC<br\/>  <b>Sensor: <\/b> NOAA-20 VIIRS<br\/> <b>Confidence: <\/b> Nominal<br\/>  <b>Day\/Night: <\/b> Night<br\/> <b>Scan: <\/b> 0.4 km<br\/> <b>Track: <\/b> 0.6 km<br\/> <b>FRP: <\/b> 2.68 MW<br\/> <b>Brightness: <\/b> 319.01 K" }, "geometry": { "type": "Point", "coordinates": [ -70.32216, 18.32546, 0.0 ] } },
{ "type": "Feature", "properties": { "Name": "Fire Detection Centroid ", "Description": "<b>Latitude: <\/b> 18.92953<br\/>  <b>Longitude: <\/b> -70.35573<br\/>  <b>Detection Time: <\/b> 2023-08-14 05:36 UTC<br\/>  <b>Sensor: <\/b> NOAA-20 VIIRS<br\/> <b>Confidence: <\/b> Nominal<br\/>  <b>Day\/Night: <\/b> Night<br\/> <b>Scan: <\/b> 0.4 km<br\/> <b>Track: <\/b> 0.6 km<br\/> <b>FRP: <\/b> 0.63 MW<br\/> <b>Brightness: <\/b> 307.26 K" }, "geometry": { "type": "Point", "coordinates": [ -70.35573, 18.92953, 0.0 ] } },
{ "type": "Feature", "properties": { "Name": "Fire Detection Centroid ", "Description": "<b>Latitude: <\/b> 46.52129<br\/>  <b>Longitude: <\/b> -71.1396<br\/>  <b>Detection Time: <\/b> 2023-08-14 05:28 UTC<br\/>  <b>Sensor: <\/b> NOAA-20 VIIRS<br\/> <b>Confidence: <\/b> Nominal<br\/>  <b>Day\/Night: <\/b> Night<br\/> <b>Scan: <\/b> 0.8 km<br\/> <b>Track: <\/b> 0.8 km<br\/> <b>FRP: <\/b> 0.79 MW<br\/> <b>Brightness: <\/b> 298.41 K" }, "geometry": { "type": "Point", "coordinates": [ -71.1396, 46.52129, 0.0 ] } }
]
}
