{
"type": "FeatureCollection",
"crs": { "type": "name", "properties": { "name": "urn:ogc:def:crs:OGC:1.3:CRS84" } },
"features": [
{ "type": "Feature", "properties": { "Name": "Fire Detection Centroid ", "Description": "<b>Latitude: <\/b> 19.40392<br\/>  <b>Longitude: <\/b> -155.28091<br\/>  <b>Detection Time: <\/b> 2022-09-02 12:08 UTC<br\/>  <b>Sensor: <\/b> NOAA-20 VIIRS<br\/> <b>Confidence: <\/b> Nominal<br\/>  <b>Day\/Night: <\/b> Night<br\/> <b>Scan: <\/b> 0.43 km<br\/> <b>Track: <\/b> 0.38 km<br\/> <b>FRP: <\/b> 46.94 MW<br\/> <b>Brightness: <\/b> 314.94 K" }, "geometry": { "type": "Point", "coordinates": [ -155.28091, 19.40392, 0.0 ] } },
{ "type": "Feature", "properties": { "Name": "Fire Detection Centroid ", "Description": "<b>Latitude: <\/b> 19.41492<br\/>  <b>Longitude: <\/b> -155.28304<br\/>  <b>Detection Time: <\/b> 2022-09-02 12:08 UTC<br\/>  <b>Sensor: <\/b> NOAA-20 VIIRS<br\/> <b>Confidence: <\/b> Nominal<br\/>  <b>Day\/Night: <\/b> Night<br\/> <b>Scan: <\/b> 0.43 km<br\/> <b>Track: <\/b> 0.38 km<br\/> <b>FRP: <\/b> 6.2 MW<br\/> <b>Brightness: <\/b> 338.9 K" }, "geometry": { "type": "Point", "coordinates": [ -155.28304, 19.41492, 0.0 ] } },
{ "type": "Feature", "properties": { "Name": "Fire Detection Centroid ", "Description": "<b>Latitude: <\/b> 19.41217<br\/>  <b>Longitude: <\/b> -155.2877<br\/>  <b>Detection Time: <\/b> 2022-09-02 12:08 UTC<br\/>  <b>Sensor: <\/b> NOAA-20 VIIRS<br\/> <b>Confidence: <\/b> Nominal<br\/>  <b>Day\/Night: <\/b> Night<br\/> <b>Scan: <\/b> 0.43 km<br\/> <b>Track: <\/b> 0.38 km<br\/> <b>FRP: <\/b> 8.04 MW<br\/> <b>Brightness: <\/b> 343.3 K" }, "geometry": { "type": "Point", "coordinates": [ -155.2877, 19.41217, 0.0 ] } },
{ "type": "Feature", "properties": { "Name": "Fire Detection Centroid ", "Description": "<b>Latitude: <\/b> 19.41148<br\/>  <b>Longitude: <\/b> -155.28366<br\/>  <b>Detection Time: <\/b> 2022-09-02 12:08 UTC<br\/>  <b>Sensor: <\/b> NOAA-20 VIIRS<br\/> <b>Confidence: <\/b> Nominal<br\/>  <b>Day\/Night: <\/b> Night<br\/> <b>Scan: <\/b> 0.43 km<br\/> <b>Track: <\/b> 0.38 km<br\/> <b>FRP: <\/b> 6.2 MW<br\/> <b>Brightness: <\/b> 347.34 K" }, "geometry": { "type": "Point", "coordinates": [ -155.28366, 19.41148, 0.0 ] } },
{ "type": "Feature", "properties": { "Name": "Fire Detection Centroid ", "Description": "<b>Latitude: <\/b> 19.41079<br\/>  <b>Longitude: <\/b> -155.27962<br\/>  <b>Detection Time: <\/b> 2022-09-02 12:08 UTC<br\/>  <b>Sensor: <\/b> NOAA-20 VIIRS<br\/> <b>Confidence: <\/b> Nominal<br\/>  <b>Day\/Night: <\/b> Night<br\/> <b>Scan: <\/b> 0.43 km<br\/> <b>Track: <\/b> 0.38 km<br\/> <b>FRP: <\/b> 6.2 MW<br\/> <b>Brightness: <\/b> 332.7 K" }, "geometry": { "type": "Point", "coordinates": [ -155.27962, 19.41079, 0.0 ] } },
{ "type": "Feature", "properties": { "Name": "Fire Detection Centroid ", "Description": "<b>Latitude: <\/b> 19.40873<br\/>  <b>Longitude: <\/b> -155.28833<br\/>  <b>Detection Time: <\/b> 2022-09-02 12:08 UTC<br\/>  <b>Sensor: <\/b> NOAA-20 VIIRS<br\/> <b>Confidence: <\/b> Nominal<br\/>  <b>Day\/Night: <\/b> Night<br\/> <b>Scan: <\/b> 0.43 km<br\/> <b>Track: <\/b> 0.38 km<br\/> <b>FRP: <\/b> 57.85 MW<br\/> <b>Brightness: <\/b> 342.59 K" }, "geometry": { "type": "Point", "coordinates": [ -155.28833, 19.40873, 0.0 ] } },
{ "type": "Feature", "properties": { "Name": "Fire Detection Centroid ", "Description": "<b>Latitude: <\/b> 19.40735<br\/>  <b>Longitude: <\/b> -155.28026<br\/>  <b>Detection Time: <\/b> 2022-09-02 12:08 UTC<br\/>  <b>Sensor: <\/b> NOAA-20 VIIRS<br\/> <b>Confidence: <\/b> Nominal<br\/>  <b>Day\/Night: <\/b> Night<br\/> <b>Scan: <\/b> 0.43 km<br\/> <b>Track: <\/b> 0.38 km<br\/> <b>FRP: <\/b> 46.94 MW<br\/> <b>Brightness: <\/b> 319.36 K" }, "geometry": { "type": "Point", "coordinates": [ -155.28026, 19.40735, 0.0 ] } },
{ "type": "Feature", "properties": { "Name": "Fire Detection Centroid ", "Description": "<b>Latitude: <\/b> 19.40529<br\/>  <b>Longitude: <\/b> -155.28894<br\/>  <b>Detection Time: <\/b> 2022-09-02 12:08 UTC<br\/>  <b>Sensor: <\/b> NOAA-20 VIIRS<br\/> <b>Confidence: <\/b> Nominal<br\/>  <b>Day\/Night: <\/b> Night<br\/> <b>Scan: <\/b> 0.43 km<br\/> <b>Track: <\/b> 0.38 km<br\/> <b>FRP: <\/b> 57.85 MW<br\/> <b>Brightness: <\/b> 343.99 K" }, "geometry": { "type": "Point", "coordinates": [ -155.28894, 19.40529, 0.0 ] } },
{ "type": "Feature", "properties": { "Name": "Fire Detection Centroid ", "Description": "<b>Latitude: <\/b> 19.4046<br\/>  <b>Longitude: <\/b> -155.2849<br\/>  <b>Detection Time: <\/b> 2022-09-02 12:08 UTC<br\/>  <b>Sensor: <\/b> NOAA-20 VIIRS<br\/> <b>Confidence: <\/b> Nominal<br\/>  <b>Day\/Night: <\/b> Night<br\/> <b>Scan: <\/b> 0.43 km<br\/> <b>Track: <\/b> 0.38 km<br\/> <b>FRP: <\/b> 46.94 MW<br\/> <b>Brightness: <\/b> 327.51 K" }, "geometry": { "type": "Point", "coordinates": [ -155.2849, 19.4046, 0.0 ] } }
]
}
